{
  "title": "Accessibility",
  "content": "- ### OntologyBlock\n  id:: accessibility-ontology\n  collapsed:: true\n\t- ontology:: true\n\t- term-id:: mv-876717578844\n\t- preferred-term:: Accessibility\n\t- source-domain:: metaverse\n\t- status:: active\n\t- public-access:: true\n\t- definition:: A component of the metaverse ecosystem focusing on accessibility.\n\t- maturity:: mature\n\t- authority-score:: 0.85\n\t- owl:class:: mv:Accessibility\n\t- owl:physicality:: ConceptualEntity\n\t- owl:role:: Concept\n\t- belongsToDomain:: [[MetaverseDomain]]\n\t- #### Relationships\n\t  id:: accessibility-relationships\n\t\t- enables:: [[ImmersiveExperience]], [[Presence]], [[SpatialComputing]]\n\t\t- requires:: [[DisplayTechnology]], [[TrackingSystem]], [[RenderingEngine]]\n\t\t- bridges-to:: [[HumanComputerInteraction]], [[ComputerVision]], [[Robotics]]\n\n\t- #### OWL Axioms\n\t  id:: accessibility-owl-axioms\n\t  collapsed:: true\n\t\t- ```clojure\n\t\t  Declaration(Class(mv:Accessibility))\n\n\t\t  # Classification\n\t\t  SubClassOf(mv:Accessibility mv:ConceptualEntity)\n\t\t  SubClassOf(mv:Accessibility mv:Concept)\n\n\t\t  # Domain classification\n\t\t  SubClassOf(mv:Accessibility\n\t\t    ObjectSomeValuesFrom(mv:belongsToDomain mv:MetaverseDomain)\n\t\t  )\n\n\t\t  # Annotations\n\t\t  AnnotationAssertion(rdfs:label mv:Accessibility \"Accessibility\"@en)\n\t\t  AnnotationAssertion(rdfs:comment mv:Accessibility \"A component of the metaverse ecosystem focusing on accessibility.\"@en)\n\t\t  AnnotationAssertion(dcterms:identifier mv:Accessibility \"mv-876717578844\"^^xsd:string)\n\t\t  ```\n\npublic:: true\n\n- # Accessibility by Design\n\t- ## Introduction to Accessibility in Software Design\n\t\t- Accessibility is a fundamental aspect of software design, ensuring digital products are usable by the broadest range of individuals, regardless of their abilities. This primer examines the integration of accessibility considerations into the design process, focusing particularly on immersive technologies (Virtual Reality [VR], Augmented Reality [AR], and the Metaverse), while also addressing non-immersive software challenges. The goal is to provide a comprehensive framework for incorporating accessibility from the earliest stages of product development, thus mitigating costly retrofitting and promoting a more inclusive user experience. This is especially crucial in the context of AI, which has the potential to exacerbate existing accessibility gaps if not developed with inclusivity in mind.\n\t- ## Understanding the Scope of Accessibility\n\t\t- Accessibility in digital design encompasses a wide range of user needs, extending beyond traditional visual and auditory impairments to include cognitive, motor, and situational limitations. It is crucial to consider not only permanent disabilities but also temporary and situational impairments that may impact user interaction with digital products. For example, a user carrying shopping bags or holding a child may have limited mobility, affecting their ability to navigate a website or use a mobile app effectively.\n\t\t\t- ### Broader Challenges in Accessibility\n\t\t\t\t- * **Cognitive and Language Barriers:** Users with cognitive disabilities or non-native speakers may find complex language and instructions in software challenging. Simplified language and clear instructions are critical for enhancing accessibility.\n\t\t\t\t- * **Edge Case:** A user with dyslexia might benefit from using a font designed to reduce letter confusion, such as Dyslexie or OpenDyslexic. Similarly, real-time text-to-speech options can be invaluable for those with severe reading impairments. AI-powered tools, such as text-to-speech generators, can contribute to accessibility by providing more natural and accurate vocalizations.\n\t\t\t\t- * **Situational Impairments:** Temporary conditions, such as bright sunlight affecting screen visibility or a noisy environment hindering audio cues, must be considered in accessible design.\n\t\t\t\t- * **Edge Case:** Imagine a user attempting to interact with a mobile application in bright sunlight. High contrast modes or dark themes become essential for readability. Similarly, a parent with a sleeping child may need one-handed navigation and silent operation. AI can help adapt the interface to these situations, for example, by automatically detecting ambient light conditions and adjusting display settings accordingly.\n\t\t\t\t- * **Age-Related Impairments:** As the global population ages, designs must account for declining vision, hearing, and motor skills.\n\t\t\t\t- * **Edge Case:** An elderly user with reduced dexterity and vision may require larger touch targets on touchscreen devices and support for voice commands to interact effectively. AI can help by analysing user behaviour and adjusting the interface to optimize for ease of use, such as automatically increasing font sizes or simplifying navigation based on observed patterns.\n- ## Accessibility in Immersive Technologies\n\t- Immersive technologies such as VR, AR, and the Metaverse present unique challenges and opportunities for accessibility. The fully immersive nature of these environments can be both empowering and excluding, depending on how well accessibility is integrated.\n\t\t- ### Types of Accessibility Challenges in Immersive Environments\n\t\t  \n\t\t  1. **Visual Impairments:**\n\t\t    * Magnification tools, font enlargement, and colour inversion are crucial for users with visual impairments.\n\t\t    * Spatial audio and tactile feedback can serve as alternative modalities to convey visual information.\n\t\t    * **Edge Case:** A VR environment where users navigate through auditory cues rather than visual ones could be beneficial for visually impaired users. For instance, using echolocation or 3D audio mapping to provide context in a game or virtual tour. AI could play a role in generating dynamic auditory descriptions of the virtual environment based on the user's movement and interactions.\n\t\t  2. **Auditory Impairments:**\n\t\t    * Real-time sign language interpretation and closed captioning are critical for deaf or hard-of-hearing users.\n\t\t    * Open metadata standards are needed to support these features across platforms.\n\t\t    * **Edge Case:** Implementing haptic feedback in VR gloves to simulate sound vibrations or using visual sound indicators, like flashing lights that correspond to loud noises, can enhance the experience for hearing-impaired users. AI can be used to create real-time subtitles based on audio input and even translate sign language into text or audio. [Liopa](https://liopa.ai/) is a company that has developed AI that can decipher speech by analysing lip movements, providing a vital communication tool for patients who have lost their ability to speak.\n\t\t  3. **Physical Disabilities:**\n\t\t    * VR headsets and controllers must be designed to accommodate users with limited mobility or dexterity.\n\t\t    * Alternative input methods, such as eye-tracking or voice commands, can enhance accessibility for these users.\n\t\t    * **Edge Case:** Consider users with quadriplegia using a VR system that allows full navigation and interaction via eye-tracking combined with voice commands. The system could even include adaptive AI that learns the user's preferences and adjusts the interface accordingly. AI can be employed to develop intuitive and responsive eye-tracking interfaces, enabling users to interact with VR environments in a more natural and efficient way. Another example is [Project Gameface from Google](https://github.com/google/project-gameface), a hands-free virtual mouse that allows users to control a computer's cursor through head movements and facial gestures.\n\t\t  4. **Cognitive Disabilities:**\n\t\t    * Immersive environments should offer simplified navigation and clear, consistent instructions to support users with cognitive impairments.\n\t\t    * VR and AR applications can be tailored for vocational training or rehabilitation, using accessible interfaces that cater to specific cognitive needs.\n\t\t    * **Edge Case:** VR simulations designed for individuals with Autism Spectrum Disorder (ASD) can include adjustable levels of stimuli to prevent sensory overload. An example might be a calming VR environment that gradually introduces more complex social interactions as the user becomes comfortable. AI can help personalise the VR experience by adapting the level of stimulation, complexity of interactions, and pacing based on the individual's needs and preferences.\n- ### Case Studies and Research\n  \n  * **[XR Accessibility – Learning from the Past and Addressing Real User Needs for Inclusive Immersive Environments](https://doi.org/10.1007/978-3-030-58805-2_25):** This research explores how XR technologies can be made accessible to users with various disabilities, including blindness, stroke recovery, and intellectual disabilities. The study highlights the use of spatial sound for object location and interaction, as well as alternative symbolic representations for information accessibility.\n  * **[Inclusive Immersion: A Review of Efforts to Improve Accessibility in Virtual Reality, Augmented Reality, and the Metaverse](https://doi.org/10.1109/VRW55335.2023.00110):** This paper reviews current efforts to address accessibility in VR and AR, focusing on creating equitable access for diverse user needs. It also identifies ongoing challenges that require further research to ensure these technologies are inclusive.\n  * **[Accessibility in the Metaverse: Are We Prepared?](https://doi.org/10.5753/WAIHCWS.2022.234117):** This study discusses the significant challenges faced by people with disabilities in accessing the Metaverse. It emphasises that while efforts are being made, there is still a considerable distance to go before these environments are fully accessible.\n- ## Accessibility in Non-Immersive Software\n- While the focus has been on immersive technologies, non-immersive software also faces significant accessibility challenges. Ensuring that traditional software applications are accessible is critical to maintaining inclusivity in everyday digital interactions.\n\t- ### Common Accessibility Challenges in Non-Immersive Software\n\t\t- 1. **User Interface Design:**\n\t\t    * Ensuring that UI elements are perceivable and operable by users with various disabilities is fundamental. This includes considerations like colour contrast, font size, and the availability of keyboard navigation.\n\t\t    * **Edge Case:** A mobile banking app might include a high-contrast mode for users with low vision, alongside support for voice-controlled navigation to help users with motor impairments conduct transactions. AI can be integrated to personalize UI elements based on user preferences and needs, such as automatically adjusting font size, colour contrast, and navigation methods.\n\t\t  2. **Content Accessibility:**\n\t\t    * Text content should be simple and easy to understand, particularly for non-native speakers and users with cognitive disabilities. The use of plain language and intuitive icons can greatly enhance usability.\n\t\t    * **Edge Case:** A government website offering vital services could provide text-to-speech functionality, simple language summaries of complex legal documents, and symbols or infographics to assist users with varying levels of literacy. AI can be employed to generate text summaries of complex content, simplify language, and create alternative representations of information, such as visual diagrams or audio descriptions.\n\t\t  3. **Interactive Elements:**\n\t\t    * Buttons, forms, and other interactive elements must be accessible via multiple input methods, including keyboard, mouse, and voice commands.\n\t\t    * **Edge Case:** Consider a social media platform where users can fully engage through voice commands, allowing those with severe physical disabilities to post, comment, and interact without the need for traditional input devices. AI can enhance the accessibility of interactive elements by enabling users to interact with them using natural language, gestures, or other alternative methods.\n\t- ### Case Studies and Research\n\t\t- * **[Accessibility in Software Practice: A Practitioner’s Perspective](https://doi.org/10.1145/3424573):** This research paper identifies the challenges software practitioners face in integrating accessibility into design and development processes. It highlights the need for better documentation, specialized skills, and organisational support to address accessibility effectively.\n\t\t- * **[A Survey on Virtual Reality for Individuals with Autism Spectrum Disorder: Design Considerations](https://doi.org/10.1109/TLT.2018.2873070):** Although focused on VR, the principles of designing for individuals with Autism Spectrum Disorder (ASD) can be applied to non-immersive software. The paper discusses the importance of clear, consistent interfaces and the potential for tailored software experiences to meet diverse user needs.\n- ## Integrating Accessibility into the Design Process\n\t- To ensure digital products are accessible from the outset, it is essential to integrate accessibility considerations into every stage of the design and development process.\n\t\t- ### Shift-Left Approach\n\t\t- The shift-left approach involves addressing accessibility early in the design process rather than treating it as an afterthought. This strategy not only reduces the cost of retrofitting accessibility features but also improves the overall user experience.\n\t\t- 1. **Design Phase:**\n\t\t    * Use checklists and design systems to ensure accessibility is considered from the outset. This includes setting appropriate colour contrasts, designing for keyboard navigation, and considering alternative input methods.\n\t\t    * **Tools and Best Practices:**\n\t\t        * **Figma:** Utilize Figma’s built-in accessibility tools to ensure designs meet accessibility standards. Figma allows for the creation of accessible components and provides plugins for checking colour contrast and other accessibility features.\n\t\t        * **Web Content Accessibility Guidelines (WCAG):** Adherence to WCAG ensures that digital products meet global accessibility standards, covering a range of disabilities.\n\t\t- 2. **Development Phase:**\n\t\t    * Developers should be trained to implement accessibility features as part of the coding process. Reusable components that are pre-tested for accessibility can help streamline this integration.\n\t\t    * **Tools and Best Practices:**\n\t\t        * **ARIA (Accessible Rich Internet Applications):** Implement ARIA roles and properties to enhance accessibility for dynamic content and complex user interfaces.\n\t\t        * **Lighthouse Accessibility Audits:** Use Lighthouse or similar tools to perform automated accessibility audits during the development process.\n\t\t- 3. **Testing Phase:**\n\t\t    * Accessibility testing should be an integral part of quality assurance. Automated tools can help identify common issues, but real-world testing with users who have disabilities is essential for uncovering nuanced accessibility barriers.\n\t\t    * **Tools and Best Practices:**\n\t\t        * **Screen Readers (e.g., NVDA, JAWS):** Testing with screen readers ensures that visually impaired users can navigate and interact with your product effectively.\n\t\t        * **Manual Testing with Assistive Technologies:** Engage users who rely on assistive technologies to test your product, ensuring it meets their needs in real-world scenarios.\n- ### Organisational Support and Training\n- Creating accessible digital products requires organisational commitment. Training for designers, developers, and product managers on accessibility best practices is crucial. Regular workshops and feedback sessions can help teams stay updated on the latest accessibility trends and technologies.\n- * **Edge Case:** Establishing an Accessibility Champion within each team can help maintain focus on accessibility issues and ensure continuous improvement. This role would involve staying current with accessibility standards and advocating for inclusive design practices across the organisation.\n- ## Future of Accessibility in Design\n\t- The future of accessibility in both immersive and non-immersive software hinges on continuous innovation and research. As technologies evolve, so too must our approach to accessibility.\n\t\t- ### Emerging Trends\n\t\t- * **AI and Machine Learning:** AI has the potential to revolutionise accessibility by providing personalised experiences tailored to individual user needs. For example, AI can assist in real-time translation of sign language or generate alternative text descriptions for visual content. Projects like [ChatCaptioner](https://github.com/Vision-CAIR/ChatCaptioner) use a dialogue between two AI models to generate enriched image descriptions, while [Video-LLaMA](https://github.com/DAMO-NLP-SG/Video-LLaMA) empowers large language models to understand both video and audio content. The Visual Geometry Group (VGG) at the University of Oxford has also developed [AutoAD](httpss://www.robots.ox.ac.uk/~vgg/research/autoad/), a system for creating audio descriptions of movies in context.\n\t\t- * **Edge Case:** Consider an AI-driven virtual assistant that not only responds to voice commands but also detects when a user might be struggling and proactively offers assistance, such as simplifying a task or adjusting the user interface for better accessibility. AI can be trained to recognise specific user behaviours, such as frustration or difficulty, and adapt the system to provide more accessible options.\n\t\t- * **Inclusive Immersive Experiences:** As the Metaverse and other immersive environments continue to develop, there will be increasing demand for accessible experiences that cater to a diverse global audience. This includes creating new interaction patterns that are intuitive for all users, regardless of their abilities.\n\t\t- * **Edge Case:** Future immersive environments could use biometric data to dynamically adjust the level of sensory input, reducing stimuli for users prone to sensory overload or enhancing it for those who need more engagement. AI can be used to monitor user physiological responses and adapt the immersive environment to optimize for individual preferences and needs.\n- ### Challenges Ahead\n\t- While significant progress has been made, many challenges remain in making digital products truly accessible. Continued research, development, and collaboration between designers, developers, and users with disabilities are essential to overcoming these barriers and ensuring that digital experiences are inclusive for everyone.\n\t- * **Relevant Research:**\n\t    * **[White Paper: Recommendations for Immersive Accessibility Services](https://arxiv.org/abs/2010.04714):** This paper provides recommendations on integrating accessibility solutions with immersive media services, including subtitling, audio description, and sign language support for 360-degree video and spatial audio.\n\t- Accessibility by design is not just a best practice; it is a fundamental requirement for creating inclusive digital experiences. Whether designing for immersive technologies or traditional software, the principles of accessibility must be integrated into every stage of the design and development process. By doing so, we can create digital products that are not only compliant with accessibility standards but also provide a delightful and inclusive experience for all users.\n- ## Additional Resources\n  \n  * **[W3C Web Accessibility Initiative (WAI)](https://www.w3.org/WAI/):** A comprehensive resource for understanding and implementing web accessibility standards.\n  * **[Inclusive Design Principles](https://inclusivedesignprinciples.org/):** Practical guidelines for designing products that work for the widest possible audience.\n  * **[Accessible Technology Coalition](https://atcoalition.org/):** A resource hub for accessible technology tools and strategies.\n-\n\n## Current Landscape (2025)\n\n- Industry adoption and implementations\n  - Metaverse platforms continue to evolve with focus on interoperability and open standards\n  - Web3 integration accelerating with decentralised identity and asset ownership\n  - Enterprise adoption growing in virtual collaboration, training, and digital twins\n  - UK companies increasingly active in metaverse development and immersive technologies\n\n- Technical capabilities\n  - Real-time rendering at photorealistic quality levels\n  - Low-latency networking enabling seamless multi-user experiences\n  - AI-driven content generation and procedural world building\n  - Spatial audio and haptics enhancing immersion\n\n- UK and North England context\n  - Manchester: Digital Innovation Factory supports metaverse startups and research\n  - Leeds: Holovis leads in immersive experiences for entertainment and training\n  - Newcastle: University research in spatial computing and interactive systems\n  - Sheffield: Advanced manufacturing using digital twin technology\n\n- Standards and frameworks\n  - Metaverse Standards Forum driving interoperability protocols\n  - WebXR enabling browser-based immersive experiences\n  - glTF and USD for 3D asset interchange\n  - Open Metaverse Interoperability Group defining cross-platform standards\n\n## Metadata\n\n- **Last Updated**: 2025-11-16\n- **Review Status**: Automated remediation with 2025 context\n- **Verification**: Academic sources verified\n- **Regional Context**: UK/North England where applicable",
  "properties": {
    "id": "accessibility-owl-axioms",
    "collapsed": "true",
    "- ontology": "true",
    "- term-id": "mv-876717578844",
    "- preferred-term": "Accessibility",
    "- source-domain": "metaverse",
    "- status": "active",
    "- public-access": "true",
    "- definition": "A component of the metaverse ecosystem focusing on accessibility.",
    "- maturity": "mature",
    "- authority-score": "0.85",
    "- owl:class": "mv:Accessibility",
    "- owl:physicality": "ConceptualEntity",
    "- owl:role": "Concept",
    "- belongsToDomain": "[[MetaverseDomain]]",
    "- enables": "[[ImmersiveExperience]], [[Presence]], [[SpatialComputing]]",
    "- requires": "[[DisplayTechnology]], [[TrackingSystem]], [[RenderingEngine]]",
    "- bridges-to": "[[HumanComputerInteraction]], [[ComputerVision]], [[Robotics]]",
    "public": "true"
  },
  "backlinks": [
    "Patent",
    "BC 0115 minting",
    "Speech and voice",
    "Bitcoin As Money",
    "Telecollaboration and Telepresence"
  ],
  "wiki_links": [
    "TrackingSystem",
    "ImmersiveExperience",
    "ComputerVision",
    "RenderingEngine",
    "SpatialComputing",
    "Robotics",
    "HumanComputerInteraction",
    "MetaverseDomain",
    "DisplayTechnology",
    "Presence"
  ],
  "ontology": {
    "term_id": "mv-876717578844",
    "preferred_term": "Accessibility",
    "definition": "A component of the metaverse ecosystem focusing on accessibility.",
    "source_domain": "metaverse",
    "maturity_level": null,
    "authority_score": 0.85
  }
}