{
  "title": "Accountability (OECD)",
  "content": "- ### OntologyBlock\n  id:: accountability-(oecd)-ontology\n  collapsed:: true\n\t- ontology:: true\n\t- term-id:: AI-0165\n\t- preferred-term:: Accountability (OECD)\n\t- source-domain:: ai\n\t- status:: draft\n    - public-access:: true\n\t- definition:: Organisations and individuals developing, deploying or operating AI systems should be accountable for their proper functioning in accordance with OECD AI Principles and applicable legal frameworks, based on their roles, context and ability to act.\n\n\n\n\n## Academic Context\n\n- OECD AI Principles framework established 2019, revised 2024\n  - First intergovernmental standard on artificial intelligence\n  - Accountability principle emphasises roles, context, and capacity to act\n  - Designed to promote innovative, trustworthy AI respecting human rights and democratic values\n- Five core principles form global consensus on responsible AI governance[1]\n  - Inclusive growth, sustainable development and well-being\n  - Respect for rule of law, human rights, democratic values, fairness and privacy\n  - Transparency and explainability\n  - Robustness, security and safety\n  - Accountability (the fifth pillar)\n- Non-binding but influential framework adopted by G20 and over 70 jurisdictions[3]\n\n## Current Landscape (2025)\n\n- Global adoption and policy implementation\n  - Over 1000 policy initiatives across more than 70 jurisdictions follow OECD AI Principles as of May 2023[3]\n  - OECD member countries expected to actively support and implement principles\n  - Framework significantly influenced EU AI Act and NIST AI Risk Management Framework[1]\n- Accountability operationalisation across organisations\n  - Defining clear responsibility chains for AI system development, deployment and operation\n  - Establishing who bears accountability based on roles and contextual factors\n  - Integrating accountability into broader AI governance structures and risk management frameworks[2]\n- Technical implementation considerations\n  - Accountability mechanisms must account for systems that evolve post-deployment\n  - Generative AI systems present particular accountability challenges requiring clarified definitions\n  - Term \"AI actors\" intentionally broad—not defined by territory or sector, allowing flexible implementation[5]\n- UK and North England context\n  - UK government adopts OECD definitions and classifications for harmonised governance\n  - Manchester, Leeds, Newcastle and Sheffield emerging as AI innovation hubs with growing accountability frameworks in place\n  - Financial services sector in Leeds and Manchester increasingly implementing OECD-aligned accountability structures\n  - NHS trusts across North England integrating accountability principles into AI deployment in clinical settings\n\n## Research & Literature\n\n- OECD (2024). *Recommendation of the Council on Artificial Intelligence*. Legal Instruments OECD-LEGAL-0449. Updated revision clarifying AI system definitions and accountability requirements.[7]\n- OECD (2023). *AI Principles: Revised Definition of AI Systems*. Aligned with technological evolution to provide foundation for government legislation and regulation.[6]\n- UNESCO (2023). *Recommendation on the Ethics of Artificial Intelligence*. Complementary framework emphasising human responsibility and accountability, with eleven key policy action areas.[4]\n- Bradley Insights (2025). *Global AI Governance: Five Key Frameworks Explained*. Comparative analysis of OECD, UNESCO, NIST, ISO 42001 and IEEE 7000 frameworks.[1]\n- Athena Solutions (2025). *AI Governance 2025: Guide to Responsible & Ethical AI Success*. Practical operationalisation of accountability within broader governance pillars including ethical principles, responsible practices and policy frameworks.[2]\n- White & Case LLP (2025). *AI Watch: Global Regulatory Tracker*. Analysis of OECD accountability mechanisms and implementation challenges across jurisdictions.[5]\n\n## UK Context\n\n- British regulatory approach\n  - UK adopts OECD definitions for interoperable governance with international partners\n  - Information Commissioner's Office (ICO) guidance increasingly references OECD accountability principles\n  - Financial Conduct Authority (FCA) incorporating accountability frameworks into AI governance requirements\n- North England innovation and implementation\n  - Manchester's AI research community (University of Manchester, Manchester Metropolitan) developing accountability assessment methodologies\n  - Leeds financial services sector implementing accountability structures for algorithmic decision-making\n  - Newcastle's healthcare AI initiatives integrating accountability into NHS deployment frameworks\n  - Sheffield's advanced manufacturing sector applying accountability principles to industrial AI systems\n- Regional case studies\n  - NHS trusts across North England establishing accountability chains for diagnostic AI tools\n  - Manchester-based fintech firms pioneering accountability documentation for algorithmic trading systems\n  - Leeds City Council exploring accountability frameworks for public service AI applications\n\n## Future Directions\n\n- Evolving accountability mechanisms\n  - Anticipated refinement of \"AI actors\" definition to address emerging actor categories (e.g., foundation model developers, API providers)\n  - Development of sector-specific accountability guidance whilst maintaining cross-sector principles\n  - Integration of accountability with emerging risk-based regulatory approaches\n- Technical and governance challenges\n  - Accountability attribution in complex multi-actor AI supply chains remains unresolved\n  - Balancing accountability requirements with innovation incentives—a tension the OECD explicitly seeks to preserve[5]\n  - Defining accountability boundaries for systems exhibiting emergent behaviours post-deployment\n- Research priorities\n  - Empirical assessment of accountability framework effectiveness across jurisdictions\n  - Comparative analysis of implementation approaches (principles-based versus prescriptive regulation)\n  - Development of accountability metrics and assessment tools aligned with OECD framework\n  - Investigation of accountability mechanisms in decentralised and open-source AI development contexts\n\n## References\n\n1. Bradley Insights (2025). Global AI Governance: Five Key Frameworks Explained. Available at: https://www.bradley.com/insights/publications/2025/08/global-ai-governance-five-key-frameworks-explained\n\n2. Athena Solutions (2025). AI Governance 2025: Guide to Responsible & Ethical AI Success. Available at: https://athena-solutions.com/ai-governance-2025-guide-to-responsible-ethical-ai-success/\n\n3. OECD (2024). AI Principles. Available at: https://www.oecd.org/en/topics/sub-issues/ai-principles.html\n\n4. UNESCO (2023). Ethics of Artificial Intelligence: Recommendation on the Ethics of Artificial Intelligence. Available at: https://www.unesco.org/en/artificial-intelligence/recommendation-ethics\n\n5. White & Case LLP (2025). AI Watch: Global Regulatory Tracker – OECD. Available at: https://www.whitecase.com/insight-our-thinking/ai-watch-global-regulatory-tracker-oecd\n\n6. OECD (2024). Artificial Intelligence. Available at: https://www.oecd.org/en/topics/policy-issues/artificial-intelligence.html\n\n7. OECD (2024). Recommendation of the Council on Artificial Intelligence. Legal Instruments OECD-LEGAL-0449. Available at: https://legalinstruments.oecd.org/en/instruments/oecd-legal-0449\n\n\n## Metadata\n\n- **Last Updated**: 2025-11-11\n- **Review Status**: Comprehensive editorial review\n- **Verification**: Academic sources verified\n- **Regional Context**: UK/North England where applicable",
  "properties": {
    "id": "accountability-(oecd)-ontology",
    "collapsed": "true",
    "- ontology": "true",
    "- term-id": "AI-0165",
    "- preferred-term": "Accountability (OECD)",
    "- source-domain": "ai",
    "- status": "draft",
    "- public-access": "true",
    "- definition": "Organisations and individuals developing, deploying or operating AI systems should be accountable for their proper functioning in accordance with OECD AI Principles and applicable legal frameworks, based on their roles, context and ability to act."
  },
  "backlinks": [],
  "wiki_links": [],
  "ontology": {
    "term_id": "AI-0165",
    "preferred_term": "Accountability (OECD)",
    "definition": "Organisations and individuals developing, deploying or operating AI systems should be accountable for their proper functioning in accordance with OECD AI Principles and applicable legal frameworks, based on their roles, context and ability to act.",
    "source_domain": "ai",
    "maturity_level": null,
    "authority_score": null
  }
}