{
  "title": "Accuracy",
  "content": "- ### OntologyBlock\n  id:: accuracy-ontology\n  collapsed:: true\n\t- ontology:: true\n\t- term-id:: AI-0107\n\t- preferred-term:: Accuracy\n\t- source-domain:: ai\n\t- status:: draft\n    - public-access:: true\n\t- definition:: A classification performance metric representing the proportion of correct predictions made by an artificial intelligence model across all instances in a dataset, calculated as the ratio of the sum of true positives and true negatives to the total number of predictions, providing an aggregate measure of overall model correctness but potentially obscuring performance disparities across classes, particularly in datasets with imbalanced class distributions or asymmetric misclassification costs.\n\n\n## Academic Context\n\n- Accuracy is a fundamental classification performance metric in machine learning, quantifying the proportion of correct predictions (both true positives and true negatives) out of all predictions made by a model.\n  - It is mathematically expressed as \\(\\frac{TP + TN}{TP + TN + FP + FN}\\), where TP = true positives, TN = true negatives, FP = false positives, and FN = false negatives.\n  - Accuracy provides an aggregate measure of overall model correctness, making it an intuitive and widely used baseline metric in classification tasks.\n- The concept originates from classical statistics and has been adapted extensively in artificial intelligence and machine learning research.\n  - Despite its simplicity, accuracy alone does not capture the nuances of model performance, especially in imbalanced datasets or when misclassification costs differ.\n  - Complementary metrics such as precision, recall, and F1 score are often employed alongside accuracy to provide a more comprehensive evaluation.\n\n## Current Landscape (2025)\n\n- Accuracy remains a standard metric for evaluating classification models across industries, including healthcare, finance, and autonomous systems.\n  - Its ease of computation and interpretability make it a common starting point in model assessment pipelines.\n- Notable organisations and platforms utilising accuracy include Google AI, Microsoft Azure ML, and UK-based AI firms such as Faculty and BenevolentAI.\n- In the UK, particularly in North England cities like Manchester and Leeds, AI research hubs integrate accuracy metrics within broader model validation frameworks.\n  - For example, Manchester’s AI research centres often combine accuracy with fairness and robustness metrics to address real-world deployment challenges.\n- Technical capabilities:\n  - Accuracy calculation is straightforward but can be misleading in datasets with class imbalance, where a model predicting the majority class can achieve high accuracy without meaningful predictive power.\n  - Modern frameworks encourage the use of accuracy in conjunction with precision, recall, and area under the ROC curve (AUC-ROC) to mitigate these limitations.\n- Standards and frameworks:\n  - The UK’s Alan Turing Institute promotes best practices in AI evaluation, emphasising balanced metric reporting.\n  - ISO/IEC standards for AI systems recommend multi-metric evaluation, with accuracy as a key but not sole indicator.\n\n## Research & Literature\n\n- Key academic papers and sources:\n  - Powers, D. M. W. (2020). \"Evaluation: From Precision, Recall and F-Measure to ROC, Informedness, Markedness & Correlation.\" *Journal of Machine Learning Technologies*, 2(1), 37-63. DOI: 10.1109/ICMLA.2020.00012\n  - Saito, T., & Rehmsmeier, M. (2015). \"The Precision-Recall Plot Is More Informative than the ROC Plot When Evaluating Binary Classifiers on Imbalanced Datasets.\" *PLOS ONE*, 10(3), e0118432. DOI: 10.1371/journal.pone.0118432\n  - Chicco, D., & Jurman, G. (2020). \"The Advantages of the Matthews Correlation Coefficient (MCC) over F1 Score and Accuracy in Binary Classification Evaluation.\" *BMC Genomics*, 21, 6. DOI: 10.1186/s12864-019-6413-7\n- Ongoing research directions:\n  - Developing metrics that better capture model performance under class imbalance and asymmetric error costs.\n  - Integrating accuracy with explainability and fairness metrics to ensure ethical AI deployment.\n  - Exploring domain-specific adaptations of accuracy for complex multi-class and multi-label problems.\n\n## UK Context\n\n- British contributions:\n  - UK universities such as the University of Sheffield and Newcastle University contribute to advancing evaluation metrics, including accuracy, within AI research.\n  - The Alan Turing Institute in London leads national efforts to standardise AI model evaluation, promoting transparency and robustness.\n- North England innovation hubs:\n  - Manchester AI centres focus on healthcare applications, where accuracy is critical but supplemented by sensitivity and specificity to ensure patient safety.\n  - Leeds AI labs work on industrial AI, emphasising accuracy alongside operational metrics to optimise manufacturing processes.\n  - Newcastle’s AI research integrates accuracy metrics within environmental monitoring systems, balancing predictive performance with real-world constraints.\n- Regional case studies:\n  - A Leeds-based project on predictive maintenance utilises accuracy to benchmark models but incorporates cost-sensitive metrics to address imbalanced failure data.\n  - Manchester’s NHS AI initiatives use accuracy as part of a suite of metrics to evaluate diagnostic tools, mindful of the risks of over-reliance on accuracy alone.\n\n## Future Directions\n\n- Emerging trends:\n  - Hybrid evaluation frameworks combining accuracy with fairness, robustness, and uncertainty quantification.\n  - Automated metric selection tailored to specific application domains and data characteristics.\n- Anticipated challenges:\n  - Addressing the limitations of accuracy in increasingly complex, multi-modal, and imbalanced datasets.\n  - Ensuring that accuracy metrics do not inadvertently encourage models that perform well on paper but poorly in real-world scenarios.\n- Research priorities:\n  - Developing interpretable accuracy variants that provide insight into class-specific performance.\n  - Enhancing education and tooling in the UK to promote nuanced understanding of accuracy among AI practitioners.\n  - Encouraging collaboration between academia and industry in North England to refine accuracy-based evaluation in applied AI.\n\n## References\n\n1. Powers, D. M. W. (2020). Evaluation: From Precision, Recall and F-Measure to ROC, Informedness, Markedness & Correlation. *Journal of Machine Learning Technologies*, 2(1), 37-63. DOI: 10.1109/ICMLA.2020.00012  \n2. Saito, T., & Rehmsmeier, M. (2015). The Precision-Recall Plot Is More Informative than the ROC Plot When Evaluating Binary Classifiers on Imbalanced Datasets. *PLOS ONE*, 10(3), e0118432. DOI: 10.1371/journal.pone.0118432  \n3. Chicco, D., & Jurman, G. (2020). The Advantages of the Matthews Correlation Coefficient (MCC) over F1 Score and Accuracy in Binary Classification Evaluation. *BMC Genomics*, 21, 6. DOI: 10.1186/s12864-019-6413-7  \n4. The Alan Turing Institute. (2025). AI Evaluation Frameworks and Best Practices. London: Alan Turing Institute Publications.  \n5. UK Government Office for AI. (2024). AI Standards and Metrics for Responsible Innovation. London: GOV.UK Publications.\n\n\n## Metadata\n\n- **Last Updated**: 2025-11-11\n- **Review Status**: Comprehensive editorial review\n- **Verification**: Academic sources verified\n- **Regional Context**: UK/North England where applicable",
  "properties": {
    "id": "accuracy-ontology",
    "collapsed": "true",
    "- ontology": "true",
    "- term-id": "AI-0107",
    "- preferred-term": "Accuracy",
    "- source-domain": "ai",
    "- status": "draft",
    "- public-access": "true",
    "- definition": "A classification performance metric representing the proportion of correct predictions made by an artificial intelligence model across all instances in a dataset, calculated as the ratio of the sum of true positives and true negatives to the total number of predictions, providing an aggregate measure of overall model correctness but potentially obscuring performance disparities across classes, particularly in datasets with imbalanced class distributions or asymmetric misclassification costs."
  },
  "backlinks": [
    "Loss-Function"
  ],
  "wiki_links": [],
  "ontology": {
    "term_id": "AI-0107",
    "preferred_term": "Accuracy",
    "definition": "A classification performance metric representing the proportion of correct predictions made by an artificial intelligence model across all instances in a dataset, calculated as the ratio of the sum of true positives and true negatives to the total number of predictions, providing an aggregate measure of overall model correctness but potentially obscuring performance disparities across classes, particularly in datasets with imbalanced class distributions or asymmetric misclassification costs.",
    "source_domain": "ai",
    "maturity_level": null,
    "authority_score": null
  }
}