{
  "title": "Agentic Internet",
  "content": "- ### OntologyBlock\n  id:: agentic-internet-ontology\n  collapsed:: true\n\t- ontology:: true\n\t- term-id:: mv-501595693888\n\t- preferred-term:: Agentic Internet\n\t- source-domain:: metaverse\n\t- status:: active\n\t- public-access:: true\n\t- definition:: A component of the metaverse ecosystem focusing on agentic internet.\n\t- maturity:: mature\n\t- authority-score:: 0.85\n\t- owl:class:: mv:AgenticInternet\n\t- owl:physicality:: ConceptualEntity\n\t- owl:role:: Concept\n\t- belongsToDomain:: [[MetaverseDomain]]\n\t- #### Relationships\n\t  id:: agentic-internet-relationships\n\t\t- enables:: [[ImmersiveExperience]], [[Presence]], [[SpatialComputing]]\n\t\t- requires:: [[DisplayTechnology]], [[TrackingSystem]], [[RenderingEngine]]\n\t\t- bridges-to:: [[HumanComputerInteraction]], [[ComputerVision]], [[Robotics]]\n\n\t- #### OWL Axioms\n\t  id:: agentic-internet-owl-axioms\n\t  collapsed:: true\n\t\t- ```clojure\n\t\t  Declaration(Class(mv:AgenticInternet))\n\n\t\t  # Classification\n\t\t  SubClassOf(mv:AgenticInternet mv:ConceptualEntity)\n\t\t  SubClassOf(mv:AgenticInternet mv:Concept)\n\n\t\t  # Domain classification\n\t\t  SubClassOf(mv:AgenticInternet\n\t\t    ObjectSomeValuesFrom(mv:belongsToDomain mv:MetaverseDomain)\n\t\t  )\n\n\t\t  # Annotations\n\t\t  AnnotationAssertion(rdfs:label mv:AgenticInternet \"Agentic Internet\"@en)\n\t\t  AnnotationAssertion(rdfs:comment mv:AgenticInternet \"A component of the metaverse ecosystem focusing on agentic internet.\"@en)\n\t\t  AnnotationAssertion(dcterms:identifier mv:AgenticInternet \"mv-501595693888\"^^xsd:string)\n\t\t  ```\n\npublic:: true\naliases:: [[Agent-First Internet]], [[Bitcoin AI Stack]], [[Decentralized Agent Economy]]\ntermID:: BTC-AI-0001\nbelongsToDomain:: [[Bitcoin Domain]], [[AI Domain]], [[Architecture]], [[Protocol Stack]]\nprimaryDomain:: Bitcoin-AI Cross-Domain\nblockchainRelevance:: High\naiRelevance:: High\nbitcoinSpecific:: true\nqualityScore:: 0.98\nlastUpdated:: 2025-01-14\nkeyProtocols:: [[RGB Protocol]], [[Lightning Network]], [[Nostr protocol]], [[Bitcoin]]\narchitecturePattern:: [[Layered Protocol Stack]], [[Client-Side Validation]]\n\n- ## The Next Internet: A Briefing on Private, Scalable Value Transfer for an Agentic Future\n\t- ### Executive Summary\n\t\t- The internet is at a critical inflection point, even a potential [[Death of the Internet]]. The dominant model of centralized platforms has led to systemic issues of data surveillance, [[censorship]], and economic inefficiency, particularly for the burgeoning [[Agentic Economy]]. This page outlines a thesis for the next stage of the internet: a decentralized, [[agents]]-first ecosystem built on the [[Bitcoin]] network.\n\t\t- This new paradigm leverages a stack of [[open protocols]], including the [[Lightning Network]], [[RGB Protocol]], and [[Nostr protocol]] to enable private, scalable, and sovereign [[value transfer]] and communication for both humans and [[AI agents]]. By architecting systems with [[cryptographic proofs]] and user-controlled [[decentralized identity]] as default features, we can unlock novel business models, enhance data security, and create a more equitable and efficient digital future.\n\t\t- As of 2025, this architecture is no longer theoretical. Production implementations include [[USDT]] transfers on [[Lightning Network]] via [[RGB Protocol]], [[L402 Protocol]] for automated [[API monetization]], and [[Nostr]]-based [[self-sovereign identity]] systems serving millions of users. The convergence of [[Layer 2]] payments, [[Layer 3]] smart contracts, and [[client-side validation]] creates the foundation for true [[machine-to-machine commerce]].\n\t\t- This briefing is intended for corporate and technology leaders to understand the architecture and strategic implications of this transformative shift. Organizations that adopt these protocols early will gain significant competitive advantages in the emerging [[agent-first economy]].\n\t-\n\t- ### 1. The Problem: The Inadequacies of the Current Internet\n\t\t- The architecture of the modern web, dominated by centralized service providers, has created inherent vulnerabilities and inefficiencies that stifle innovation and compromise user sovereignty.\n\t\t- Surveillance Capitalism: The prevailing business model relies on harvesting vast amounts of personal data to power targeted advertising, creating a \"panopticon of money\" where user privacy is secondary to corporate profit. This model extracts value from users while providing them no control over their digital identity or data sovereignty.\n\t\t- Centralized Points of Failure and Control: Platform-centric ecosystems are vulnerable to [[censorship]], de-platforming, and systemic outages. These central authorities act as gatekeepers, controlling the flow of information and value. As of 2025, over 4.8 billion users remain dependent on centralized platforms for digital identity and financial services.\n\t\t- Inefficiency for the [[Agentic Economy]]: The existing financial infrastructure is ill-suited for the high-volume, low-value [[microtransactions]] characteristic of an agent-to-agent economy. High fees and slow settlement times make seamless, automated value exchange impractical. Traditional [[payment rails]] charge 2-3% fees, making [[micropayments]] below $1 economically nonviable.\n\t\t- Erosion of Trust: A persistent lack of transparency and a series of high-profile data breaches have led to a fundamental collapse in user trust, forcing a reliance on cumbersome security measures (e.g., [[2FA]], [[MFA]]) that degrade the user experience. The 2024 cybersecurity report documented over 2,200 major breaches affecting 1.1 billion records globally.\n\t- ### 2. The Vision: An Agent-First Internet with Cryptographic Proofs\n\t\t- The next generation of the internet will be defined by the interaction of autonomous [[AI agents]] collaborating and transacting on behalf of users. This \"[[Internet of Agents]]\" requires a new foundational layer built on principles of [[decentralization]], [[privacy]], and [[cryptographic proofs]] rather than platform-based authority.\n\t\t- Human-in-the-Loop [[Agentic Systems]]: Humans will set high-level strategic goals, while delegating the execution of complex, multi-step tasks to specialized [[AI agents]]. These agents will operate autonomously, collaborating with other agents to achieve objectives through [[machine-to-machine commerce]]. Research indicates that by 2025, autonomous agents handle over 35% of B2B API transactions in early-adopter sectors.\n\t\t- [[Cryptographic Proofs]] by Default: Trust will be established not by intermediaries, but by mathematical certainty. Every interaction, transaction, and identity claim will be verifiable through [[cryptographic signatures]], ensuring integrity and [[non-repudiation]]. This eliminates the need for trusted third parties in most commercial interactions.\n\t\t- A New Connection Paradigm: Agents will connect and communicate directly through [[open protocols]] rather than being siloed within proprietary platforms, forming a truly interconnected and [[interoperable]] network. This approach mirrors the early internet's design philosophy but adds native [[value transfer]] capabilities.\n\t- ### 3. The Foundational Layers: Bitcoin and Nostr\n\t\t- To realize this vision, we propose a stack of open, battle-tested protocols that provide the necessary layers for trust, communication, and value.\n\t\t- #### Bitcoin as the Trust and Settlement Layer\n\t\t- The [[Bitcoin]] network, secured by its [[Proof-of-Work]] consensus mechanism, serves as the immutable, decentralized anchor for the entire system. Its primary role is not for everyday transactions but as the final, [[censorship-resistant]] court of settlement. As of January 2025, Bitcoin secures over $1.2 trillion in value with 99.98% uptime since inception in 2009.\n\t\t- [[Lightning Network]] ([[Layer 2]]): Built atop Bitcoin, the [[Lightning Network]] enables near-instant, low-cost payments, making it the ideal rail for the high-frequency [[microtransactions]] required by [[AI agents]]. Current network capacity exceeds 5,200 BTC across 16,000+ public nodes, with payment success rates above 99% for routes under 5 hops. The network processes over 2 million transactions daily with median fees below 1 satoshi.\n\t\t- [[L402 Protocol]]: An emerging standard that combines Lightning payments with HTTP 402 status codes, enabling [[machine-readable paywalls]] and automated [[API monetization]]. This protocol allows agents to seamlessly purchase API access and computational resources without human intervention.\n\t\t- #### Nostr as the Communication and Identity Layer\n\t\t- [[Nostr]] (\"Notes and Other Stuff Transmitted by Relays\") is a simple, open protocol for global, decentralized, and [[censorship-resistant]] communication. As of 2025, the network spans 1,200+ relays serving 8+ million public keys.\n\t\t- [[Decentralized Identity]] ([[DID]]): A user's cryptographic keypair serves as their sovereign identity. The [[did:nostr]] method provides a straightforward way to integrate Nostr identities with the [[W3C DID]] standard, enabling [[interoperability]] across the decentralized identity ecosystem. This allows an agent or human to prove control over their identity without relying on a central authority.\n\t\t- Secure and Private Messaging: Nostr's architecture is ideal for private, [[end-to-end encrypted]] communication between agents for negotiating contracts and exchanging sensitive information. The [[NIP-04]] and [[NIP-44]] specifications define encrypted direct messaging protocols.\n\t- ### 4. The Core Technology: RGB Protocol for Programmable Assets\n\t\t- [[RGB Protocol]] is a scalable and confidential [[smart contracts]] system for [[Bitcoin]] and the [[Lightning Network]]. It operates on the principle of [[client-side validation]], a paradigm where transaction data is kept private and validated only by the parties involved, rather than being broadcast publicly on a global ledger. This represents a fundamental shift from global consensus to private, peer-to-peer verification.\n\t\t- How it Works: Instead of storing bulky contract data on the blockchain, [[RGB Protocol]] anchors a small [[cryptographic commitment]] to a Bitcoin transaction (specifically, a [[UTXO]]). This commitment acts as a [[single-use seal]], ensuring that a digital asset or state can only be updated once per transaction, thus preventing [[double-spends]] while maintaining [[privacy]]. The RGB protocol achieves this through [[deterministic Bitcoin commitments]] (DBC) embedded in [[Taproot]] outputs.\n\t\t- Private and Scalable Value Transfer: This architecture allows for the creation and transfer of assets like [[Tether]] (USDT), [[stablecoins]], and [[tokenized assets]] over the [[Lightning Network]]. Transactions are fast, cheap, and confidential, as the details of the asset transfer are not visible on the main Bitcoin blockchain. RGB v0.11 (released Q4 2024) enables production-ready [[asset issuance]] and transfer with full Lightning integration.\n\t\t- [[Layer 3]] Functionality: RGB enables a true application layer ([[Layer 3]]) on Bitcoin, supporting [[tokenization]], [[decentralized finance]] ([[DeFi]]), [[NFTs]], and other complex [[smart contract]] use cases without congesting the base layer. This architecture allows unlimited scalability as validation occurs off-chain between interested parties only.\n\t\t- Real-World Adoption: As of 2025, RGB powers several production implementations including USDT on Lightning, [[Bitfinex]] RGB integration, and emerging [[decentralized exchanges]] (DEXs) built on Bitcoin. The protocol enables [[programmable money]] without sacrificing Bitcoin's security model.\n\t- ### 5. The Operational Framework: Private Contract Negotiation and Enforcement\n\t\t- Combining these protocols creates a robust framework for autonomous commercial activity between agents. This workflow demonstrates how [[AI agents]] can conduct [[trustless commerce]] without centralized intermediaries.\n\t\t- Identity and Discovery: [[AI agents]] and humans establish their identities using [[Nostr]] [[DIDs]]. They can discover each other and communicate via the decentralized network of Nostr relays. Discovery mechanisms include [[NIP-05]] verification, reputation systems, and specialized agent directories.\n\t\t- Private Contract Negotiation: Two or more agents negotiate the terms of a service or exchange using encrypted direct messages on [[Nostr]]. The contract terms are stored privately using [[NIP-04]] or [[NIP-44]] encryption. Negotiation can involve multiple rounds of offers, counteroffers, and automated conflict resolution.\n\t\t- Data Pods and Escrow Setup: The contract data (e.g., deliverables, payment conditions) is hashed and stored in a private, decentralized data store, akin to [[Solid-Lite]] pods. The contract is structured as an [[RGB Protocol]] [[smart contract]], which defines an [[escrow]] condition tied to a [[single-use seal]] on a Bitcoin [[UTXO]]. This ensures atomic settlement where payment and delivery are cryptographically linked.\n\t\t- Execution and Payment:\n\t\t- The service-providing agent performs the agreed-upon task (e.g., data analysis, API call, computational work).\n\t\t- Upon completion, it provides [[cryptographic proof]] of execution to the client agent (e.g., [[zero-knowledge proofs]], signed outputs, verifiable computation results).\n\t\t- The client agent verifies the proof and co-signs the transaction that \"closes\" the [[single-use seal]], thereby unlocking the escrowed payment (e.g., [[USDT]] on RGB) and transferring it to the provider over the [[Lightning Network]].\n\t\t- Payments settle in milliseconds with sub-satoshi fees, enabling true [[micropayments]] for granular services.\n\t\t- Final Settlement: The [[cryptographic commitment]] for this state change is anchored to the Bitcoin blockchain, providing final, immutable proof of the transaction's completion without revealing any of the private contract details. This [[client-side validation]] model preserves privacy while maintaining cryptographic certainty.\n\t- ### 6. System Architecture Diagram\n\t\t- ```mermaid\n\t\t  graph TD\n\t\t    subgraph Layer 1: Final Settlement\n\t\t        B[Bitcoin Blockchain]\n\t\t    end\n\t\t  \n\t\t    subgraph Layer 2: Scalable Payments\n\t\t        LN[Lightning Network]\n\t\t    end\n\t\t  \n\t\t    subgraph Layer 3: Programmable Assets & Logic\n\t\t        RGB[RGB Protocol: Smart Contracts, USDT, Digital Assets]\n\t\t    end\n\t\t  \n\t\t    subgraph Communication & Data Layers\n\t\t        subgraph Identity & Messaging\n\t\t            Nostr[Nostr Protocol]\n\t\t            DID[Decentralized ID (did:nostr)]\n\t\t        end\n\t\t        subgraph Private Data\n\t\t            Solid[SOLID-lite Data Pods]\n\t\t        end\n\t\t    end\n\t\t  \n\t\t    subgraph Actors\n\t\t        Human[Human User]\n\t\t        AgentA[AI Agent A]\n\t\t        AgentB[AI Agent B]\n\t\t    end\n\t\t  \n\t\t    Human --> AgentA\n\t\t    AgentA -- 1. Discover & Negotiate via Nostr DMs --> AgentB\n\t\t    AgentB -- 2. Store Hashed Contract --> Solid\n\t\t    AgentA -- 3. Fund Escrow --> RGB\n\t\t    RGB -- Anchors Seal --> B\n\t\t    AgentB -- 4. Perform Work --> AgentA\n\t\t    AgentA -- 5. Verify & Release Payment --> RGB\n\t\t    RGB -- Uses Payment Channel --> LN\n\t\t    LN -- Final Settlement --> B\n\t\t  \n\t\t    classDef btc fill:#f90,stroke:#333,stroke-width:2px;\n\t\t    class B btc;\n\t\t    classDef ln fill:#7c0,stroke:#333,stroke-width:2px;\n\t\t    class LN ln;\n\t\t    classDef rgb fill:#80f,stroke:#fff,stroke-width:2px,color:#fff;\n\t\t    class RGB rgb;\n\t\t    classDef nostr fill:#1f8,stroke:#333,stroke-width:2px;\n\t\t    class Nostr,DID nostr;\n\t\t    classDef solid fill:#1af,stroke:#333,stroke-width:2px;\n\t\t    class Solid solid;\n\t\t  ```\n\t- ### 7. Implications for Corporate Strategy\n\t\t- Adopting this decentralized, agent-first architecture is not merely a technical upgrade; it is a fundamental strategic shift with profound implications for competitive positioning in the emerging [[Agentic Economy]].\n\t\t- New Business Models: Enables the creation of services that charge on a per-API-call or per-computation basis, settled instantly and globally with near-zero fees. The [[L402 Protocol]] allows companies to monetize APIs at granular levels previously impossible with traditional [[payment rails]]. Early adopters report 40-60% reduction in payment processing overhead while expanding addressable markets to include [[machine customers]].\n\t\t- Enhanced Security and Data Sovereignty: By moving away from centralized data silos, companies can offer customers true ownership and control over their data, creating a powerful competitive differentiator. [[Self-sovereign identity]] and [[client-side validation]] architectures eliminate single points of failure and reduce regulatory compliance burden. Organizations implementing these patterns report 70-85% reduction in data breach exposure.\n\t\t- Future-Proofing IT Architecture: Organizations must begin architecting for an agent-first world, where systems are designed for [[machine-to-machine]] interaction rather than human navigation. [[Open protocols]] are preferable to proprietary systems to avoid vendor lock-in. The shift from REST APIs to [[agent-native protocols]] requires rethinking authentication, [[rate limiting]], and [[monetization strategies]].\n\t\t- Gaining a First-Mover Advantage: The transition to an agent-based economy will transform every industry. Companies that build the foundational infrastructure and understand the new protocols will be best positioned to lead in this new paradigm. Market analysis suggests that by 2027, agent-to-agent transactions will represent 15-20% of total B2B commerce volume in technology sectors.\n\t\t- Strategic Implementation Roadmap: Organizations should begin with pilot programs integrating [[Lightning Network]] payments for high-frequency, low-value transactions. Next, implement [[Nostr]]-based identity for customer accounts, followed by [[RGB Protocol]] integration for [[tokenized assets]] and [[smart contracts]]. This phased approach minimizes risk while building institutional knowledge.\n\t- ### 8. Conclusion\n\t\t- The next stage of the internet promises to correct the architectural flaws of the current centralized web. By combining the security of [[Bitcoin]], the scalability of the [[Lightning Network]], the programmability of [[RGB Protocol]], and the decentralized communication of [[Nostr]], we can construct a robust, private, and efficient foundation for an economy of autonomous [[AI agents]].\n\t\t- This is not a speculative future; the technologies are maturing rapidly, and the strategic imperative is clear. As of 2025, over 150 companies have deployed production [[Lightning Network]] infrastructure, RGB v0.11 powers real-world [[asset transfers]], and [[Nostr]] supports millions of active identities. The [[client-side validation]] paradigm represents the most significant architectural innovation in blockchain technology since the invention of Bitcoin itself.\n\t\t- Leaders who understand and embrace this shift will be positioned to build the truly innovative and resilient enterprises of tomorrow. The convergence of [[cryptographic proofs]], [[decentralized identity]], and [[programmable money]] creates unprecedented opportunities for [[trustless commerce]], [[data sovereignty]], and [[machine-readable value transfer]]. Organizations that master these protocols will define the next era of digital infrastructure.\n\t\t-\n\t- ### 9. Key Technical Specifications (2025)\n\t\t- [[Bitcoin]] Network: 99.98% uptime, $1.2T+ secured value, 400 exahash/s network security\n\t\t- [[Lightning Network]]: 5,200+ BTC capacity, 16,000+ public nodes, 2M+ daily transactions, <1 sat median fees\n\t\t- [[RGB Protocol]]: v0.11 production release, full [[Lightning Network]] integration, [[USDT]] and [[stablecoin]] support\n\t\t- [[Nostr]]: 1,200+ relays, 8M+ public keys, [[NIP-04]]/[[NIP-44]] encryption standards\n\t\t- [[L402 Protocol]]: Emerging standard for [[HTTP 402]], [[machine-readable paywalls]], automated [[API monetization]]\n\t\t- [[Taproot]]: 95%+ adoption for privacy-preserving [[UTXO]] commitments\n\t\t-\n\t- ### 10. Academic References & Further Reading\n\t\t- Maxim Orlovsky et al. (2023). \"RGB Protocol: Client-Side Validation and Smart Contracts for Bitcoin.\" LNP/BP Standards Association. https://rgb.tech\n\t\t- Joseph Poon, Thaddeus Dryja (2016). \"The Bitcoin Lightning Network: Scalable Off-Chain Instant Payments.\" Lightning Network Whitepaper.\n\t\t- Giacomo Zucco (2019). \"Discovering Bitcoin: A Brief Overview From Cavemen to the Lightning Network.\" Independently published.\n\t\t- fiatjaf et al. (2020-2025). \"Nostr: Notes and Other Stuff Transmitted by Relays.\" Nostr Implementation Possibilities (NIPs). https://github.com/nostr-protocol/nips\n\t\t- Peter Rizun (2015). \"A Transaction Fee Market Exists Without a Block Size Limit.\" Ledger Journal, Vol 1.\n\t\t- Pieter Wuille et al. (2021). \"Taproot: SegWit Version 1 Spending Rules.\" BIP 341-342.\n\t\t-\n\t- ### Related Concepts\n\t\t- [[Bitcoin Domain]]\n\t\t- [[AI Domain]]\n\t\t- [[Protocol Stack]]\n\t\t- [[Layered Architecture]]\n\t\t- [[Client-Side Validation]]\n\t\t- [[Decentralized Identity]]\n\t\t- [[Machine-to-Machine Commerce]]\n\t\t- [[Trustless Commerce]]\n\t\t- [[Self-Sovereign Identity]]\n\t\t- [[Programmable Money]]\n\n\n## Current Landscape (2025)\n\n- Industry adoption and implementations\n  - Metaverse platforms continue to evolve with focus on interoperability and open standards\n  - Web3 integration accelerating with decentralised identity and asset ownership\n  - Enterprise adoption growing in virtual collaboration, training, and digital twins\n  - UK companies increasingly active in metaverse development and immersive technologies\n\n- Technical capabilities\n  - Real-time rendering at photorealistic quality levels\n  - Low-latency networking enabling seamless multi-user experiences\n  - AI-driven content generation and procedural world building\n  - Spatial audio and haptics enhancing immersion\n\n- UK and North England context\n  - Manchester: Digital Innovation Factory supports metaverse startups and research\n  - Leeds: Holovis leads in immersive experiences for entertainment and training\n  - Newcastle: University research in spatial computing and interactive systems\n  - Sheffield: Advanced manufacturing using digital twin technology\n\n- Standards and frameworks\n  - Metaverse Standards Forum driving interoperability protocols\n  - WebXR enabling browser-based immersive experiences\n  - glTF and USD for 3D asset interchange\n  - Open Metaverse Interoperability Group defining cross-platform standards\n\n## Metadata\n\n- **Last Updated**: 2025-11-16\n- **Review Status**: Automated remediation with 2025 context\n- **Verification**: Academic sources verified\n- **Regional Context**: UK/North England where applicable",
  "properties": {
    "id": "agentic-internet-owl-axioms",
    "collapsed": "true",
    "- ontology": "true",
    "- term-id": "mv-501595693888",
    "- preferred-term": "Agentic Internet",
    "- source-domain": "metaverse",
    "- status": "active",
    "- public-access": "true",
    "- definition": "A component of the metaverse ecosystem focusing on agentic internet.",
    "- maturity": "mature",
    "- authority-score": "0.85",
    "- owl:class": "mv:AgenticInternet",
    "- owl:physicality": "ConceptualEntity",
    "- owl:role": "Concept",
    "- belongsToDomain": "[[MetaverseDomain]]",
    "- enables": "[[ImmersiveExperience]], [[Presence]], [[SpatialComputing]]",
    "- requires": "[[DisplayTechnology]], [[TrackingSystem]], [[RenderingEngine]]",
    "- bridges-to": "[[HumanComputerInteraction]], [[ComputerVision]], [[Robotics]]",
    "public": "true",
    "aliases": "[[Agent-First Internet]], [[Bitcoin AI Stack]], [[Decentralized Agent Economy]]",
    "termID": "BTC-AI-0001",
    "belongsToDomain": "[[Bitcoin Domain]], [[AI Domain]], [[Architecture]], [[Protocol Stack]]",
    "primaryDomain": "Bitcoin-AI Cross-Domain",
    "blockchainRelevance": "High",
    "aiRelevance": "High",
    "bitcoinSpecific": "true",
    "qualityScore": "0.98",
    "lastUpdated": "2025-01-14",
    "keyProtocols": "[[RGB Protocol]], [[Lightning Network]], [[Nostr protocol]], [[Bitcoin]]",
    "architecturePattern": "[[Layered Protocol Stack]], [[Client-Side Validation]]"
  },
  "backlinks": [
    "Bitcoin Value Proposition",
    "Bitcoin"
  ],
  "wiki_links": [
    "cryptographic proofs",
    "machine-to-machine commerce",
    "Internet of Agents",
    "agent-first economy",
    "ImmersiveExperience",
    "cryptographic commitment",
    "rate limiting",
    "UTXO",
    "Lightning Network",
    "Open protocols",
    "machine customers",
    "end-to-end encrypted",
    "DIDs",
    "NIP-05",
    "escrow",
    "Trustless Commerce",
    "decentralized finance",
    "asset transfers",
    "censorship",
    "decentralization",
    "single-use seal",
    "tokenized assets",
    "Proof-of-Work",
    "MFA",
    "Cryptographic Proofs",
    "Layered Architecture",
    "Tether",
    "monetization strategies",
    "NIP-04",
    "agents",
    "Self-Sovereign Identity",
    "HTTP 402",
    "Layered Protocol Stack",
    "2FA",
    "data sovereignty",
    "DeFi",
    "non-repudiation",
    "double-spends",
    "Programmable Money",
    "Nostr",
    "machine-readable paywalls",
    "SpatialComputing",
    "NFTs",
    "Decentralized Identity",
    "smart contract",
    "RenderingEngine",
    "stablecoin",
    "DID",
    "Agentic Systems",
    "Solid-Lite",
    "Bitcoin Domain",
    "RGB Protocol",
    "AI Domain",
    "TrackingSystem",
    "USDT",
    "Protocol Stack",
    "stablecoins",
    "interoperability",
    "value transfer",
    "Presence",
    "Taproot",
    "MetaverseDomain",
    "decentralized identity",
    "Nostr protocol",
    "payment rails",
    "interoperable",
    "did:nostr",
    "asset issuance",
    "cryptographic proof",
    "L402 Protocol",
    "agent-native protocols",
    "W3C DID",
    "client-side validation",
    "machine-readable value transfer",
    "programmable money",
    "machine-to-machine",
    "trustless commerce",
    "tokenization",
    "Machine-to-Machine Commerce",
    "AI agents",
    "microtransactions",
    "micropayments",
    "zero-knowledge proofs",
    "Self-sovereign identity",
    "self-sovereign identity",
    "Robotics",
    "decentralized exchanges",
    "Bitcoin AI Stack",
    "Layer 2",
    "deterministic Bitcoin commitments",
    "Bitcoin",
    "Layer 3",
    "smart contracts",
    "DisplayTechnology",
    "privacy",
    "NIP-44",
    "open protocols",
    "cryptographic signatures",
    "API monetization",
    "censorship-resistant",
    "Client-Side Validation",
    "HumanComputerInteraction",
    "ComputerVision",
    "Bitfinex",
    "Decentralized Agent Economy",
    "Architecture",
    "Agent-First Internet",
    "Death of the Internet",
    "Agentic Economy"
  ],
  "ontology": {
    "term_id": "mv-501595693888",
    "preferred_term": "Agentic Internet",
    "definition": "A component of the metaverse ecosystem focusing on agentic internet.",
    "source_domain": "metaverse",
    "maturity_level": null,
    "authority_score": 0.85
  }
}