{
  "title": "Agentic Alliance",
  "content": "- ### OntologyBlock\n  id:: agentic-alliance-ontology\n  collapsed:: true\n\t- ontology:: true\n\t- term-id:: mv-585043035608\n\t- preferred-term:: Agentic Alliance\n\t- source-domain:: metaverse\n\t- status:: active\n\t- public-access:: true\n\t- definition:: A component of the metaverse ecosystem focusing on agentic alliance.\n\t- maturity:: mature\n\t- authority-score:: 0.85\n\t- owl:class:: mv:AgenticAlliance\n\t- owl:physicality:: VirtualEntity\n\t- owl:role:: Object\n\t- belongsToDomain:: [[MetaverseDomain]]\n\t- #### Relationships\n\t  id:: agentic-alliance-relationships\n\t\t- is-part-of:: [[VirtualWorld]], [[MetaversePlatform]]\n\t\t- requires:: [[DigitalIdentity]], [[AuthenticationService]]\n\t\t- enables:: [[SocialInteraction]], [[Presence]], [[UserRepresentation]]\n\t\t- has-property:: [[Appearance]], [[Customization]], [[Animation]]\n\n\t- #### OWL Axioms\n\t  id:: agentic-alliance-owl-axioms\n\t  collapsed:: true\n\t\t- ```clojure\n\t\t  Declaration(Class(mv:AgenticAlliance))\n\n\t\t  # Classification\n\t\t  SubClassOf(mv:AgenticAlliance mv:VirtualEntity)\n\t\t  SubClassOf(mv:AgenticAlliance mv:Object)\n\n\t\t  # Domain classification\n\t\t  SubClassOf(mv:AgenticAlliance\n\t\t    ObjectSomeValuesFrom(mv:belongsToDomain mv:MetaverseDomain)\n\t\t  )\n\n\t\t  # Annotations\n\t\t  AnnotationAssertion(rdfs:label mv:AgenticAlliance \"Agentic Alliance\"@en)\n\t\t  AnnotationAssertion(rdfs:comment mv:AgenticAlliance \"A component of the metaverse ecosystem focusing on agentic alliance.\"@en)\n\t\t  AnnotationAssertion(dcterms:identifier mv:AgenticAlliance \"mv-585043035608\"^^xsd:string)\n\t\t  ```\n\npublic:: true\n\n- [[Projects]] with [[Melvin Carvalho]] for [[Agents]] [[Distributed Identity]] [[Distributed Computing]] [[Nostr protocol]] [[Bitcoin]]\n\t- [Agentic Alliance - Advancing Agent Frameworks](https://agenticalliance.com/)\n\t- [agenticalliance/agenticalliance.com: Agentic Alliance](https://github.com/agenticalliance/agenticalliance.com)\n- # Initial chats with AI\n\t- ```\n\t  make me a mermaid diagram as code showing an open agentic framework which incorporates nostr relays, bitcoin lightning, synthetic stablecoin dollars, anthropic model context protocol for open data connectors, distributed git, the solid protocol and anything else you think necessary\n\t  ```\n\t- ## QWQ Framework Overview\n\t\t- [rawQWQchatAgenticAlliance.txt](../assets/rawQWQchatAgenticAlliance_1732964590389_0.txt)\n\t\t- The decentralized system revolves around **Agents** performing tasks and interacting with a variety of components for autonomy, decentralization, and interoperability.\n\t\t\t- #### **Key Components**\n\t\t- **Agents**: Perform tasks, make decisions, and interact with other entities.\n\t\t- **Nostr Relays**: Decentralized event handlers for communication (posts, messages, etc.).\n\t\t- **Bitcoin Lightning Network**: Enables fast, low-cost transactions.\n\t\t- **Synthetic Stablecoin System**: Manages stablecoin transactions and conversions.\n\t\t- **Anthropic Model Context Protocol**: Enhances AI context for tasks and decisions.\n\t\t- **Distributed Git Repositories**: Store and manage versioned digital assets.\n\t\t- **Solid Pods**: Decentralized, user-controlled data storage.\n\t\t- **Identity Management**: Verifies user and agent identities.\n\t\t- **API Gateways**: Provide standardized communication between components.\n\t\t- **Consensus Mechanisms**: Facilitate agreement among agents for tasks or data states.\n\t\t- **Logging System**: Ensures transparency and auditing of agent actions.\n\t\t- **Coordinator Agent** (optional): Orchestrates tasks while maintaining decentralization.\n\t\t  \n\t\t  ---\n\t\t- ### **Mermaid Diagrams**\n\t\t\t- #### **1. Overall Structure**\n\t\t\t  \n\t\t\t  ```mermaid\n\t\t\t  \n\t\t\t  graph TD;\n\t\t\t    A[Agents] -->|exchange requests| B[Nostr Relays];\n\t\t\t    A -->|make payments| C[Bitcoin Lightning Network];\n\t\t\t    A -->|manage stablecoins| D[Synthetic Stablecoin System];\n\t\t\t    A -->|enhance AI context| E[Anthropic Model Context Protocol];\n\t\t\t    A -->|store/code management| F[Distributed Git Repositories];\n\t\t\t    A -->|access user data| G[Solid Pods];\n\t\t\t    A -->|verify identities| H[Identity Management];\n\t\t\t    A -->|communicate via| I[API Gateways];\n\t\t\t    A -->|reach consensus| J[Consensus Mechanisms];\n\t\t\t    A -->|log activities| K[Logging System];\n\t\t\t    L[Coordinator Agent] -.-> A;\n\t\t\t  ```\n\t\t\t\t- **Dotted Arrows**: Optional relationships, like between **Agents** and a **Coordinator Agent**.\n\t\t\t\t- **Solid Connections**: Core interactions between components.\n\t\t\t\t  \n\t\t\t\t  ---\n\t\t- #### **2. Payment Transaction Sequence**\n\t\t\t- ```mermaid\n\t\t\t  \n\t\t\t  sequenceDiagram\n\t\t\t    participant Agent\n\t\t\t    participant SyntheticStablecoinSystem\n\t\t\t    participant BitcoinLightningNetwork\n\t\t\t    participant LoggingSystem\n\t\t\t  \n\t\t\t    Agent->>SyntheticStablecoinSystem: Check balance and convert if needed\n\t\t\t    SyntheticStablecoinSystem-->>Agent: Balance or conversion result\n\t\t\t  \n\t\t\t    alt Conversion Needed\n\t\t\t        Agent->>SyntheticStablecoinSystem: Execute conversion\n\t\t\t        SyntheticStablecoinSystem-->>Agent: Conversion confirmation\n\t\t\t    else No Conversion Needed\n\t\t\t        Agent->>BitcoinLightningNetwork: Initiate payment\n\t\t\t        BitcoinLightningNetwork-->>Agent: Payment receipt\n\t\t\t    end\n\t\t\t  \n\t\t\t    Agent->>LoggingSystem: Log transaction details\n\t\t\t  ```\n\t\t\t  \n\t\t\t  ---\n\t\t- #### **3. User Data Access Sequence**\n\t\t\t- ```mermaid\n\t\t\t  \n\t\t\t  sequenceDiagram\n\t\t\t    participant Agent\n\t\t\t    participant IdentityManagement\n\t\t\t    participant SolidPod\n\t\t\t    participant LoggingSystem\n\t\t\t  \n\t\t\t    Agent->>IdentityManagement: Authenticate request\n\t\t\t    IdentityManagement-->>Agent: Auth token or error\n\t\t\t  \n\t\t\t    alt Authenticated\n\t\t\t        Agent->>SolidPod: Request data with token\n\t\t\t        SolidPod-->>Agent: Data or permission denied\n\t\t\t    else Not Authenticated\n\t\t\t        Agent: Handle auth failure\n\t\t\t    end\n\t\t\t  \n\t\t\t    Agent->>LoggingSystem: Log access attempt\n\t\t\t  ```\n\t\t- #### **Key Implementation Notes**\n\t\t\t- **Error Handling**:\n\t\t\t\t- Ensure fallback mechanisms for failed payments or data access.\n\t\t\t\t- Use retry strategies for communication with external components.\n\t\t\t- **Privacy**:\n\t\t\t\t- Adhere strictly to user permissions with Solid Pods.\n\t\t\t- **Security**:\n\t\t\t\t- Use robust identity verification and cryptographic signatures for transactions.\n\t\t\t- **Scalability**:\n\t\t\t\t- Design APIs and logging systems to handle high throughput.\n\t\t- ## Claude\n\t\t\t- ```mermaid\n\t\t\t  %%{init: {'theme': 'base', 'themeVariables': { 'primaryColor': '#2563eb', 'primaryTextColor': '#ffffff', 'primaryBorderColor': '#1e40af', 'lineColor': '#3b82f6', 'secondaryColor': '#10b981', 'tertiaryColor': '#8b5cf6'}}}%%\n\t\t\t  \n\t\t\t  flowchart TB\n\t\t\t      %% Core Framework\n\t\t\t      A[Open Agentic Framework] --> B[Distributed Identity Layer]\n\t\t\t      A --> C[Decentralized Computation Network]\n\t\t\t      A --> D[Open Data Connectors]\n\t\t\t      A --> E[Economic Incentive Layer]\n\t\t\t  \n\t\t\t      %% Identity and Communication\n\t\t\t      B --> NostrRelays[Nostr Relay Network]\n\t\t\t      B --> SolidProtocol[Solid Protocol Identity]\n\t\t\t      \n\t\t\t      %% Computation and Agents\n\t\t\t      C --> DistributedGit[Distributed Git Compute Nodes]\n\t\t\t      C --> LightningNetwork[Bitcoin Lightning Compute Marketplace]\n\t\t\t      \n\t\t\t      %% Data Connectors\n\t\t\t      D --> AnthropicContext[Anthropic Model Context Protocol]\n\t\t\t      D --> OpenDataProtocols[Decentralized Data Schemas]\n\t\t\t      \n\t\t\t      %% Economic Layer\n\t\t\t      E --> SyntheticStablecoin[Synthetic Stablecoin Dollar Network]\n\t\t\t      E --> LightningPayments[Lightning Network Payments]\n\t\t\t      E --> ComputeMarketplace[Decentralized Compute Marketplace]\n\t\t\t  \n\t\t\t      %% Interconnections\n\t\t\t      NostrRelays <--> LightningNetwork\n\t\t\t      SyntheticStablecoin <--> LightningPayments\n\t\t\t      DistributedGit <--> ComputeMarketplace\n\t\t\t  \n\t\t\t      %% Additional Protocols and Layers\n\t\t\t      subgraph Protocols\n\t\t\t          WebSocketAPI[WebSocket API Layer]\n\t\t\t          P2PMessaging[Peer-to-Peer Messaging]\n\t\t\t          DecentralizedStorage[Decentralized Storage Protocols]\n\t\t\t      end\n\t\t\t  \n\t\t\t      %% Cross-Protocol Interactions\n\t\t\t      A --> Protocols\n\t\t\t      LightningNetwork --> WebSocketAPI\n\t\t\t      AnthropicContext --> DecentralizedStorage\n\t\t\t  \n\t\t\t      %% Governance and Standards\n\t\t\t      subgraph Governance\n\t\t\t          OpenStandards[Open Standards Body]\n\t\t\t          InteroperabilityProtocols[Interoperability Protocols]\n\t\t\t      end\n\t\t\t  \n\t\t\t      A --> Governance\n\t\t\t  \n\t\t\t      %% Additional Annotations\n\t\t\t      classDef core fill:#2563eb,color:#ffffff,stroke:#1e40af,stroke-width:2px;\n\t\t\t      classDef protocol fill:#10b981,color:#ffffff,stroke:#059669,stroke-width:2px;\n\t\t\t      classDef economic fill:#8b5cf6,color:#ffffff,stroke:#7c3aed,stroke-width:2px;\n\t\t\t  \n\t\t\t      class A,B,C,D,E core;\n\t\t\t      class NostrRelays,SolidProtocol,WebSocketAPI,P2PMessaging protocol;\n\t\t\t      class SyntheticStablecoin,LightningPayments,ComputeMarketplace economic;\n\t\t\t  ```\n\t\t\t- I've created a comprehensive Mermaid diagram that illustrates an open agentic framework incorporating the technologies you mentioned, along with some additional complementary protocols. Let me break down the key components:\n\t\t\t- ### Core Framework Layers:\n\t\t\t\t- Distributed Identity Layer\n\t\t\t\t- Decentralized Computation Network\n\t\t\t\t- Open Data Connectors\n\t\t\t\t- Economic Incentive Layer\n\t\t\t- ### Key Technologies Integrated:\n\t\t\t\t- Nostr Relays for decentralized communication\n\t\t\t\t- Bitcoin Lightning Network for compute marketplace and payments\n\t\t\t\t- Synthetic Stablecoin Dollar Network\n\t\t\t\t- Anthropic Model Context Protocol\n\t\t\t\t- Distributed Git\n\t\t\t\t- Solid Protocol for identity\n\t\t\t- ### Additional Protocols:\n\t\t\t\t- WebSocket API Layer\n\t\t\t\t- Peer-to-Peer Messaging\n\t\t\t\t- Decentralized Storage Protocols\n\t\t\t\t- Governance and Interoperability Protocols\n\t\t\t- The diagram shows how these different components interconnect, creating a robust, decentralized ecosystem for computational agents. The color-coded layers help visualize the different types of components:\n\t\t\t\t- Blue represents core framework layers\n\t\t\t\t- Green represents communication and protocol layers\n\t\t\t\t- Purple represents economic and incentive layers\n\t\t\t- The architecture is designed to be open, interoperable, and resistant to centralization, with multiple paths for data flow, computation, and economic exchange.\n\n## Current Landscape (2025)\n\n- Industry adoption and implementations\n  - Metaverse platforms continue to evolve with focus on interoperability and open standards\n  - Web3 integration accelerating with decentralised identity and asset ownership\n  - Enterprise adoption growing in virtual collaboration, training, and digital twins\n  - UK companies increasingly active in metaverse development and immersive technologies\n\n- Technical capabilities\n  - Real-time rendering at photorealistic quality levels\n  - Low-latency networking enabling seamless multi-user experiences\n  - AI-driven content generation and procedural world building\n  - Spatial audio and haptics enhancing immersion\n\n- UK and North England context\n  - Manchester: Digital Innovation Factory supports metaverse startups and research\n  - Leeds: Holovis leads in immersive experiences for entertainment and training\n  - Newcastle: University research in spatial computing and interactive systems\n  - Sheffield: Advanced manufacturing using digital twin technology\n\n- Standards and frameworks\n  - Metaverse Standards Forum driving interoperability protocols\n  - WebXR enabling browser-based immersive experiences\n  - glTF and USD for 3D asset interchange\n  - Open Metaverse Interoperability Group defining cross-platform standards\n\n## Metadata\n\n- **Last Updated**: 2025-11-16\n- **Review Status**: Automated remediation with 2025 context\n- **Verification**: Academic sources verified\n- **Regional Context**: UK/North England where applicable",
  "properties": {
    "id": "agentic-alliance-owl-axioms",
    "collapsed": "true",
    "- ontology": "true",
    "- term-id": "mv-585043035608",
    "- preferred-term": "Agentic Alliance",
    "- source-domain": "metaverse",
    "- status": "active",
    "- public-access": "true",
    "- definition": "A component of the metaverse ecosystem focusing on agentic alliance.",
    "- maturity": "mature",
    "- authority-score": "0.85",
    "- owl:class": "mv:AgenticAlliance",
    "- owl:physicality": "VirtualEntity",
    "- owl:role": "Object",
    "- belongsToDomain": "[[MetaverseDomain]]",
    "- is-part-of": "[[VirtualWorld]], [[MetaversePlatform]]",
    "- requires": "[[DigitalIdentity]], [[AuthenticationService]]",
    "- enables": "[[SocialInteraction]], [[Presence]], [[UserRepresentation]]",
    "- has-property": "[[Appearance]], [[Customization]], [[Animation]]",
    "public": "true"
  },
  "backlinks": [
    "BC-0030-digital-signature",
    "Project BroBots"
  ],
  "wiki_links": [
    "MetaversePlatform",
    "UserRepresentation",
    "MetaverseDomain",
    "DigitalIdentity",
    "Customization",
    "Animation",
    "Projects",
    "Distributed Computing",
    "Bitcoin",
    "Agents",
    "Appearance",
    "Presence",
    "VirtualWorld",
    "SocialInteraction",
    "Distributed Identity",
    "Melvin Carvalho",
    "AuthenticationService",
    "Nostr protocol"
  ],
  "ontology": {
    "term_id": "mv-585043035608",
    "preferred_term": "Agentic Alliance",
    "definition": "A component of the metaverse ecosystem focusing on agentic alliance.",
    "source_domain": "metaverse",
    "maturity_level": null,
    "authority_score": 0.85
  }
}