{
  "title": "AI Adoption",
  "content": "- ### OntologyBlock\n  id:: ai-adoption-ontology\n  collapsed:: true\n\t- ontology:: true\n\t- term-id:: mv-984519973317\n\t- preferred-term:: AI Adoption\n\t- source-domain:: metaverse\n\t- status:: active\n\t- public-access:: true\n\t- definition:: A component of the metaverse ecosystem focusing on ai adoption.\n\t- maturity:: mature\n\t- authority-score:: 0.85\n\t- owl:class:: mv:AiAdoption\n\t- owl:physicality:: ConceptualEntity\n\t- owl:role:: Concept\n\t- belongsToDomain:: [[MetaverseDomain]]\n\t- #### Relationships\n\t  id:: ai-adoption-relationships\n\t\t- enables:: [[ImmersiveExperience]], [[Presence]], [[SpatialComputing]]\n\t\t- requires:: [[DisplayTechnology]], [[TrackingSystem]], [[RenderingEngine]]\n\t\t- bridges-to:: [[HumanComputerInteraction]], [[ComputerVision]], [[Robotics]]\n\n\t- #### OWL Axioms\n\t  id:: ai-adoption-owl-axioms\n\t  collapsed:: true\n\t\t- ```clojure\n\t\t  Declaration(Class(mv:AiAdoption))\n\n\t\t  # Classification\n\t\t  SubClassOf(mv:AiAdoption mv:ConceptualEntity)\n\t\t  SubClassOf(mv:AiAdoption mv:Concept)\n\n\t\t  # Domain classification\n\t\t  SubClassOf(mv:AiAdoption\n\t\t    ObjectSomeValuesFrom(mv:belongsToDomain mv:MetaverseDomain)\n\t\t  )\n\n\t\t  # Annotations\n\t\t  AnnotationAssertion(rdfs:label mv:AiAdoption \"AI Adoption\"@en)\n\t\t  AnnotationAssertion(rdfs:comment mv:AiAdoption \"A component of the metaverse ecosystem focusing on ai adoption.\"@en)\n\t\t  AnnotationAssertion(dcterms:identifier mv:AiAdoption \"mv-984519973317\"^^xsd:string)\n\t\t  ```\n\n- [PsyArXiv Preprints | Quantifying Human-AI Synergy](https://osf.io/preprints/psyarxiv/vbkmt_v1)\n-\n- ## Adoption & Productivity\n- **90%** AI adoption among software development professionals (up 14% from last year)\n- **80%** of all developers surveyed report AI increased their productivity\n- **59%** say AI has positively improved their code quality\n- ## Trust Paradox\n- **30%** of developers trust AI only a little or not at all\n\t- 23% trust \"a little\"\n\t- 7% trust \"not at all\"\n- ## Usage Patterns\n- **Median start date**: April 2024 (spike in June/July 2024 with Claude 3.5 release)\n- **Median daily usage**: 2 hours\n- **Tool preference**:\n\t- 55% still using chatbots\n\t- 41% using IDEs like Cursor\n- ## Frequency of AI Use\n  \n  When encountering problems:\n- 39% sometimes\n- 26% almost half the time\n- 27% most of the time\n- 7% always\n- ## Task Applications\n- 71% writing new code\n- 66% modifying existing code\n- 64% writing documentation\n- 62% creating test cases\n- 62% explaining concepts\n- 61% analyzing data\n- 59% debugging\n- ## Individual Productivity Impact\n- 41% slightly increased\n- 31% moderately increased\n- 13% extremely increased\n- 9% no impact\n- 3% slightly decreased\n- ## Code Quality Impact\n- 31% slightly improved\n- 21% moderately improved\n- 7% extremely improved\n- 30% no impact\n- 7% slightly worsened\n- ## Organizational Findings\n  \n  **Key insight**: AI adoption linked to higher software delivery throughput but decreased delivery stability\n  \n  **Improvements seen in**:\n- Individual effectiveness\n- Organizational performance\n- Valuable work\n- Team performance\n  \n  **No change in**: Burnout levels\n- ## Team Archetypes\n  \n  Seven clusters identified, including:\n- **Legacy Bottleneck** (11% of respondents): Teams in reactive state with unstable systems, low product performance, high friction and burnout\n- ## Critical Organizational Challenge\n  \n  \"AI is an amplifier - it magnifies the strength of high-performing organizations and the dysfunction of struggling ones\"\n  \n  **Core finding**: Greatest returns come not from tools themselves but from:\n- Quality of internal platform\n- Clarity of workflows\n- Alignment of teams\n- Strategic focus on underlying organizational systems\n- ## DORA AI Capabilities Model\n  \n  Seven capabilities for amplifying AI benefits:\n- Clear and communicated AI stance\n- Healthy data ecosystems\n- AI-accessible internal data\n- Strong version control practices\n- Working in small batches\n- User-centric focus\n- Quality internal platforms\n- ## Methodology\n- Nearly 5,000 technology professionals surveyed globally\n- Hundreds of hours of qualitative data\n- Survey conducted July 2024\n\n## Current Landscape (2025)\n\n- Industry adoption and implementations\n  - Metaverse platforms continue to evolve with focus on interoperability and open standards\n  - Web3 integration accelerating with decentralised identity and asset ownership\n  - Enterprise adoption growing in virtual collaboration, training, and digital twins\n  - UK companies increasingly active in metaverse development and immersive technologies\n\n- Technical capabilities\n  - Real-time rendering at photorealistic quality levels\n  - Low-latency networking enabling seamless multi-user experiences\n  - AI-driven content generation and procedural world building\n  - Spatial audio and haptics enhancing immersion\n\n- UK and North England context\n  - Manchester: Digital Innovation Factory supports metaverse startups and research\n  - Leeds: Holovis leads in immersive experiences for entertainment and training\n  - Newcastle: University research in spatial computing and interactive systems\n  - Sheffield: Advanced manufacturing using digital twin technology\n\n- Standards and frameworks\n  - Metaverse Standards Forum driving interoperability protocols\n  - WebXR enabling browser-based immersive experiences\n  - glTF and USD for 3D asset interchange\n  - Open Metaverse Interoperability Group defining cross-platform standards\n\n## Metadata\n\n- **Last Updated**: 2025-11-16\n- **Review Status**: Automated remediation with 2025 context\n- **Verification**: Academic sources verified\n- **Regional Context**: UK/North England where applicable",
  "properties": {
    "id": "ai-adoption-owl-axioms",
    "collapsed": "true",
    "- ontology": "true",
    "- term-id": "mv-984519973317",
    "- preferred-term": "AI Adoption",
    "- source-domain": "metaverse",
    "- status": "active",
    "- public-access": "true",
    "- definition": "A component of the metaverse ecosystem focusing on ai adoption.",
    "- maturity": "mature",
    "- authority-score": "0.85",
    "- owl:class": "mv:AiAdoption",
    "- owl:physicality": "ConceptualEntity",
    "- owl:role": "Concept",
    "- belongsToDomain": "[[MetaverseDomain]]",
    "- enables": "[[ImmersiveExperience]], [[Presence]], [[SpatialComputing]]",
    "- requires": "[[DisplayTechnology]], [[TrackingSystem]], [[RenderingEngine]]",
    "- bridges-to": "[[HumanComputerInteraction]], [[ComputerVision]], [[Robotics]]"
  },
  "backlinks": [],
  "wiki_links": [
    "ComputerVision",
    "Presence",
    "MetaverseDomain",
    "TrackingSystem",
    "DisplayTechnology",
    "RenderingEngine",
    "ImmersiveExperience",
    "Robotics",
    "HumanComputerInteraction",
    "SpatialComputing"
  ],
  "ontology": {
    "term_id": "mv-984519973317",
    "preferred_term": "AI Adoption",
    "definition": "A component of the metaverse ecosystem focusing on ai adoption.",
    "source_domain": "metaverse",
    "maturity_level": null,
    "authority_score": 0.85
  }
}