{
  "title": "AI Companies",
  "content": "- ### OntologyBlock\n  id:: ai-companies-ontology\n  collapsed:: true\n\t- ontology:: true\n\t- term-id:: mv-164801311429\n\t- preferred-term:: AI Companies\n\t- source-domain:: metaverse\n\t- status:: active\n\t- public-access:: true\n\t- definition:: A component of the metaverse ecosystem focusing on ai companies.\n\t- maturity:: mature\n\t- authority-score:: 0.85\n\t- owl:class:: mv:AiCompanies\n\t- owl:physicality:: ConceptualEntity\n\t- owl:role:: Concept\n\t- belongsToDomain:: [[MetaverseDomain]]\n\t- #### Relationships\n\t  id:: ai-companies-relationships\n\t\t- enables:: [[ImmersiveExperience]], [[Presence]], [[SpatialComputing]]\n\t\t- requires:: [[DisplayTechnology]], [[TrackingSystem]], [[RenderingEngine]]\n\t\t- bridges-to:: [[HumanComputerInteraction]], [[ComputerVision]], [[Robotics]]\n\n\t- #### OWL Axioms\n\t  id:: ai-companies-owl-axioms\n\t  collapsed:: true\n\t\t- ```clojure\n\t\t  Declaration(Class(mv:AiCompanies))\n\n\t\t  # Classification\n\t\t  SubClassOf(mv:AiCompanies mv:ConceptualEntity)\n\t\t  SubClassOf(mv:AiCompanies mv:Concept)\n\n\t\t  # Domain classification\n\t\t  SubClassOf(mv:AiCompanies\n\t\t    ObjectSomeValuesFrom(mv:belongsToDomain mv:MetaverseDomain)\n\t\t  )\n\n\t\t  # Annotations\n\t\t  AnnotationAssertion(rdfs:label mv:AiCompanies \"AI Companies\"@en)\n\t\t  AnnotationAssertion(rdfs:comment mv:AiCompanies \"A component of the metaverse ecosystem focusing on ai companies.\"@en)\n\t\t  AnnotationAssertion(dcterms:identifier mv:AiCompanies \"mv-164801311429\"^^xsd:string)\n\t\t  ```\n\npublic:: true\n\n\t- **Majors**\n\t- There are several very strong [[Large language models]] Gemini, Claude, and ChatGPT, Llama, and Grok\n\t- [[Comparison of GPT4 and Gemini Ultra]]\n\t- [[OpenAI]]\n\t- OpenAI has been at the forefront of AI development, with significant advancements in 2024 and 2025.\n\t- ### Models\n\t\t- **[GPT-5](https://yourgpt.ai/gpt-5)**: Expected in summer 2025, with enhanced reasoning and reliability.\n\t\t- **Reasoning Models (o1, o3, o4-mini, o3-pro):** A new series of models designed for complex, analytical tasks.\n\t\t- **[Sora](https://openai.com/sora):** A text-to-video model that can generate high-resolution videos from text prompts.\n\t- ### Future Plans\n\t\t- **AGI and Agents:** OpenAI plans to launch Artificial General Intelligence (AGI) and Agents in 2025.\n\t\t- **Hardware:** The acquisition of [io](https://www.bleepingcomputer.com/news/technology/jony-ives-ai-hardware-startup-reportedly-in-talks-with-openai/) suggests a move into AI hardware.\n\t- ### Business and Infrastructure\n\t\t- **[The Stargate Project](https://en.wikipedia.org/wiki/Stargate_(supercomputer))**: A $500 billion joint venture to build an AI infrastructure system.\n\t\t- **[ChatGPT Gov](https://ai-supremacy.com/chatgpt-gov/):** A version of ChatGPT for U.S. government agencies.\n- \n- [[Comparison of GPT4 and Gemini Ultra]]\n- Google\n\t- Google has been aggressively advancing its AI capabilities in 2024 and 2025, with a focus on its Gemini models and deeper product integration.\n\t- ### Models\n\t\t- **[Gemini 2.0 and 2.5](https://blog.google/technology/ai/google-gemini-update-flash-pro-1-5-io-2024/)**: These models feature enhanced performance, multimodality, and larger context windows.\n\t\t- **[Veo, Imagen, and Lyria](https://blog.google/technology/ai/google-io-2024-new-generative-media-models-veo-imagen-3-lyria/)**: A suite of generative media models for creating video, images, and music.\n\t- ### Products and Services\n\t\t- **[AI Overviews in Search](https://blog.google/products/search/generative-ai-search-overviews/)**: AI-generated summaries at the top of search results.\n\t\t- **[Google AI Studio](https://aistudio.google.com/)**: A platform for building with Gemini models.\n\t\t- **[Jules](https://blog.google/technology/developers/google-io-2024-developer-news-updates/)**: An AI-powered coding assistant.\n\t\t- **[Gemini in Workspace](https://yourstory.com/2024/04/google-workspace-gets-new-ai-features-vids-app)**: Integration of Gemini into Gmail, Docs, Sheets, and other applications.\n\t- ### Future Plans\n\t\t- **[Project Astra](https://deepmind.google/technologies/gemini/project-astra/)**: A prototype for a universal AI assistant.\n\t\t- **[Android XR](https://yourstory.com/2024/04/google-workspace-gets-new-ai-features-vids-app)**: Gemini is coming to glasses and headsets.\n- Mistral\n\t- French company, and the only major player in Europe. [[Politics, Law, Privacy]] seem to be shaping around a bet on their success. They currently have 2 models which are unconstrained by guardrails and very high quality. They have a larger model accessible through API and their prices are very low.\n- Inflection\n\t- [Inflection](https://inflection.ai/)\n\t- Pi is the best of the \"conversational AI\" interfaces.\n- Waymo\n\t- Leading in autonomous driving technology, using AI to improve safety and efficiency.\n- IBM\n\t- Watson\n\t- A trailblazer in AI for business, offering solutions across various sectors.\n- Data Analysis\n\t- Utilizing AI to transform big data into actionable insights.\n\t- Natural Language Understanding\n\t- Enhancing machine's understanding of human language nuances.\n- Microsoft\n\t- Microsoft has been heavily focused on developing and integrating AI agents across its product ecosystem in 2024 and 2025.\n\t- ### Agents and Copilot\n\t\t- **[Copilot Actions](https://www.softwareone.com/en/blog/articles/2024/05/22/microsoft-build-2024-ai-agents-and-the-open-agentic-web)**: Allows users to automate routine tasks with simple prompts.\n\t\t- **[Azure AI Foundry Agent Service](https://www.microsoft.com/en-us/research/blog/the-open-agentic-web/)**: Provides tools for orchestrating multiple specialized agents.\n\t\t- **[Microsoft 365 Copilot](https://www.directionsonmicrosoft.com/blog/2024/05/22/microsoft-365-copilot-becoming-showcase-agents)**: The Copilot app is being revamped to become a showcase for agents, with a new image generator and deeper integration with Microsoft Search.\n\t- ### AI Integration\n\t\t- **[Azure AI](https://supersimple365.com/azure-ai-updates-from-microsoft-build-2024/)**: The Azure AI Foundry has been expanded to include over 1,900 models.\n\t\t- **[Dynamics 365](https://msdynamicsworld.com/story/new-microsoft-dynamics-365-and-power-platform-features-2024-release-wave-1-plan)**: AI-powered assistance in Sales, Customer Service, and Finance.\n\t\t- **[Microsoft 365](https://www.syskit.com/blog/microsoft-365-new-features-2024/)**: New AI-powered features in SharePoint, Outlook, and PowerPoint.\n\t- ### Research\n\t\t- **[Phi-3 and Phi-4](https://msdynamicsworld.com/story/new-microsoft-dynamics-365-and-power-platform-features-2024-release-wave-1-plan)**: Powerful language models compact enough to run on a smartphone.\n- Amazon\n\t- Amazon is making a significant push in AI with its new \"Nova\" models, a revamped \"Alexa Plus,\" and next-generation AI chips.\n\t- ### Models\n\t\t- **[Amazon Nova](https://aboutamazon.com/news/aws/amazon-nova-foundation-models)**: A new family of foundation models, including \"Micro,\" \"Lite,\" \"Pro,\" \"Premier,\" \"Canvas,\" and \"Reel.\"\n\t- ### Products and Services\n\t\t- **[Alexa Plus](https://www.newsweek.com/amazon-alexa-plus-generative-ai-subscription-1852840)**: A subscription-based, AI-powered version of Alexa, expected in early 2025.\n\t\t- **[Amazon Bedrock](https://aws.amazon.com/bedrock/)**: A fully managed service for building and scaling generative AI applications.\n\t- ### Hardware\n\t\t- **[Trainium3](https://siliconangle.com/2024/12/04/aws-unveils-next-generation-ai-chips-trainium3-graviton5/)**: Amazon's next-generation AI training chip, expected in late 2025.\n- Meta\n\t- Meta has made significant advancements in AI in 2024 and 2025, with a focus on new hardware, advanced AI models, and enhanced user experiences.\n\t- ### Hardware\n\t\t- **[Meta Quest 3S](https://www.linezero.com/blog/meta-connect-2024-new-headsets-ai-and-the-future-of-work)**: A more affordable mixed reality headset.\n\t\t- **[Orion](https://www.linezero.com/blog/meta-connect-2024-new-headsets-ai-and-the-future-of-work)**: Meta's first true augmented reality glasses.\n\t- ### Models\n\t\t- **[Llama 3.1, 3.2, and 4](https://yourstory.com/2025/02/meta-ai-llama-4-series-open-source-models)**: A series of powerful, open-source large language models.\n\t- ### Products and Services\n\t\t- **[Standalone Meta AI app](https://www.vktr.com/insights/meta-ai-app-launch-llama-4)**: A personalized and conversational AI assistant.\n\t\t- **AI-powered features:** AI-generated content, voice, photo editing, and translation are being integrated into Facebook, Instagram, WhatsApp, and Messenger.\n\t- ### Research\n\t\t- **[Open Molecules 2025](https://www.semafor.com/news/2025/05/21/meta-releases-huge-data-set-to-spur-ai-drug-discovery)**: A massive dataset of chemical simulations to train AI models for scientific research.\n- Tesla\n\t- Autopilot\n\t- Innovating with AI for advanced driver-assistance systems.\n\t- Self-Driving Cars\n\t- Pioneering autonomous vehicle technology with sophisticated AI algorithms.\n\t- Grok (LLM)\n\t\t- A witty and satirical AI chatbot that pulls in real-time information, Grok signifies Tesla's expansion into AI-driven communication.\n- NVIDIA\n\t- AI Hardware\n\t- Designing cutting-edge GPUs and systems to power AI computing.\n\t- GPUs\n\t- Accelerating AI with powerful graphics processing units.\n\t- Data Centers\n\t- Building AI-[[Infrastructure]] to support the increasing demands of machine learning workloads.\n\t- Autonomous Vehicles\n\t- Contributing to the AI ecosystem with technology for self-driving vehicles.\n\t- Salesforce\n\t- CRM with Predictive Analytics\n\t- Integrating AI to anticipate customer needs and enhance engagement.\n\t- Chatbots\n\t- Improving customer service with AI-powered chatbots.\n\t- Marketing Automation\n\t- Leveraging AI to automate and personalize marketing campaigns.\n- Adobe\n\t- Creative Software with AI\n\t- Infusing AI into creative software to augment the design process.\n\t- Photoshop\n\t\t- Using AI to streamline complex editing tasks with intuitive tools.\n\t- Illustrator\n\t\t- AI assists in creating vector graphics with precision and ease.\n- **Notable Minors**\n\t- Channel 1\n\t\t- AI News with translation of footage {{tweet https://twitter.com/channel1_ai/status/1734591810033373231}}\n-\n\n## Current Landscape (2025)\n\n- Industry adoption and implementations\n  - Metaverse platforms continue to evolve with focus on interoperability and open standards\n  - Web3 integration accelerating with decentralised identity and asset ownership\n  - Enterprise adoption growing in virtual collaboration, training, and digital twins\n  - UK companies increasingly active in metaverse development and immersive technologies\n\n- Technical capabilities\n  - Real-time rendering at photorealistic quality levels\n  - Low-latency networking enabling seamless multi-user experiences\n  - AI-driven content generation and procedural world building\n  - Spatial audio and haptics enhancing immersion\n\n- UK and North England context\n  - Manchester: Digital Innovation Factory supports metaverse startups and research\n  - Leeds: Holovis leads in immersive experiences for entertainment and training\n  - Newcastle: University research in spatial computing and interactive systems\n  - Sheffield: Advanced manufacturing using digital twin technology\n\n- Standards and frameworks\n  - Metaverse Standards Forum driving interoperability protocols\n  - WebXR enabling browser-based immersive experiences\n  - glTF and USD for 3D asset interchange\n  - Open Metaverse Interoperability Group defining cross-platform standards\n\n## Metadata\n\n- **Last Updated**: 2025-11-16\n- **Review Status**: Automated remediation with 2025 context\n- **Verification**: Academic sources verified\n- **Regional Context**: UK/North England where applicable",
  "properties": {
    "id": "ai-companies-owl-axioms",
    "collapsed": "true",
    "- ontology": "true",
    "- term-id": "mv-164801311429",
    "- preferred-term": "AI Companies",
    "- source-domain": "metaverse",
    "- status": "active",
    "- public-access": "true",
    "- definition": "A component of the metaverse ecosystem focusing on ai companies.",
    "- maturity": "mature",
    "- authority-score": "0.85",
    "- owl:class": "mv:AiCompanies",
    "- owl:physicality": "ConceptualEntity",
    "- owl:role": "Concept",
    "- belongsToDomain": "[[MetaverseDomain]]",
    "- enables": "[[ImmersiveExperience]], [[Presence]], [[SpatialComputing]]",
    "- requires": "[[DisplayTechnology]], [[TrackingSystem]], [[RenderingEngine]]",
    "- bridges-to": "[[HumanComputerInteraction]], [[ComputerVision]], [[Robotics]]",
    "public": "true"
  },
  "backlinks": [
    "Proprietary Large Language Models"
  ],
  "wiki_links": [
    "Politics, Law, Privacy",
    "MetaverseDomain",
    "RenderingEngine",
    "Robotics",
    "Infrastructure",
    "Presence",
    "Comparison of GPT4 and Gemini Ultra",
    "HumanComputerInteraction",
    "OpenAI",
    "SpatialComputing",
    "TrackingSystem",
    "Large language models",
    "ImmersiveExperience",
    "DisplayTechnology",
    "ComputerVision"
  ],
  "ontology": {
    "term_id": "mv-164801311429",
    "preferred_term": "AI Companies",
    "definition": "A component of the metaverse ecosystem focusing on ai companies.",
    "source_domain": "metaverse",
    "maturity_level": null,
    "authority_score": 0.85
  }
}