{
  "title": "AI diagram tools",
  "content": "- ### OntologyBlock\n  id:: ai-diagram-tools-ontology\n  collapsed:: true\n\t- ontology:: true\n\t- term-id:: mv-655036373419\n\t- preferred-term:: AI diagram tools\n\t- source-domain:: metaverse\n\t- status:: active\n\t- public-access:: true\n\t- definition:: A component of the metaverse ecosystem focusing on ai diagram tools.\n\t- maturity:: mature\n\t- authority-score:: 0.85\n\t- owl:class:: mv:AiDiagramTools\n\t- owl:physicality:: ConceptualEntity\n\t- owl:role:: Concept\n\t- belongsToDomain:: [[MetaverseDomain]]\n\t- #### Relationships\n\t  id:: ai-diagram-tools-relationships\n\t\t- enables:: [[ImmersiveExperience]], [[Presence]], [[SpatialComputing]]\n\t\t- requires:: [[DisplayTechnology]], [[TrackingSystem]], [[RenderingEngine]]\n\t\t- bridges-to:: [[HumanComputerInteraction]], [[ComputerVision]], [[Robotics]]\n\n\t- #### OWL Axioms\n\t  id:: ai-diagram-tools-owl-axioms\n\t  collapsed:: true\n\t\t- ```clojure\n\t\t  Declaration(Class(mv:AiDiagramTools))\n\n\t\t  # Classification\n\t\t  SubClassOf(mv:AiDiagramTools mv:ConceptualEntity)\n\t\t  SubClassOf(mv:AiDiagramTools mv:Concept)\n\n\t\t  # Domain classification\n\t\t  SubClassOf(mv:AiDiagramTools\n\t\t    ObjectSomeValuesFrom(mv:belongsToDomain mv:MetaverseDomain)\n\t\t  )\n\n\t\t  # Annotations\n\t\t  AnnotationAssertion(rdfs:label mv:AiDiagramTools \"AI diagram tools\"@en)\n\t\t  AnnotationAssertion(rdfs:comment mv:AiDiagramTools \"A component of the metaverse ecosystem focusing on ai diagram tools.\"@en)\n\t\t  AnnotationAssertion(dcterms:identifier mv:AiDiagramTools \"mv-655036373419\"^^xsd:string)\n\t\t  ```\n\n- Sure, I can help you with that! Here's an example of how you can create a mermaid diagram in code to plan a 2-month project scoping out a music app:\nid:: 65a7adf6-eabb-43de-9882-ef5e4bd0bb15\n  :LOGBOOK:\n  CLOCK: [2024-01-17 Wed 11:21:05]--[2024-01-17 Wed 11:21:08] =>  00:00:03\n  :END:\n  ```mermaid\n  graph LR\n  A(Analyze Requirements) --> B(Define Features)\n  B --> C(Design UI/UX)\n  C --> D(Develop Frontend)\n  D --> E(Develop Backend)\n  E --> F(Test and QA)\n  F --> G(Deploy to Production)\n  G --> H(Monitor and Optimize)\n  ```\n  This diagram represents the typical flow of tasks involved in the project scoping phase for a music app. Feel free to customize it according to the specific requirements of your project.\n  Is there anything specific you would like to add or modify in this diagram?\n  make a gantt chart\n- make me a mermaid diagram as code for a 6 month 2 person development epic to create an LLM based educational app\n\t- Sure! Here is a mermaid diagram as code for a 6 month 2 person development epic to create an LLM based educational app: ```mermaid graph TD A[Research and Planning] --> B[Design UI/UX] B --> C[Develop Backend] C --> D[Implement Features] D --> E[Test and Debug] E --> F[Refine and Optimize] F --> G[Deploy and Launch] ``` Please let me know if you have any additional information or if there's anything specific you would like to add to the diagram!\n-\n\n## Current Landscape (2025)\n\n- Industry adoption and implementations\n  - Metaverse platforms continue to evolve with focus on interoperability and open standards\n  - Web3 integration accelerating with decentralised identity and asset ownership\n  - Enterprise adoption growing in virtual collaboration, training, and digital twins\n  - UK companies increasingly active in metaverse development and immersive technologies\n\n- Technical capabilities\n  - Real-time rendering at photorealistic quality levels\n  - Low-latency networking enabling seamless multi-user experiences\n  - AI-driven content generation and procedural world building\n  - Spatial audio and haptics enhancing immersion\n\n- UK and North England context\n  - Manchester: Digital Innovation Factory supports metaverse startups and research\n  - Leeds: Holovis leads in immersive experiences for entertainment and training\n  - Newcastle: University research in spatial computing and interactive systems\n  - Sheffield: Advanced manufacturing using digital twin technology\n\n- Standards and frameworks\n  - Metaverse Standards Forum driving interoperability protocols\n  - WebXR enabling browser-based immersive experiences\n  - glTF and USD for 3D asset interchange\n  - Open Metaverse Interoperability Group defining cross-platform standards\n\n## Metadata\n\n- **Last Updated**: 2025-11-16\n- **Review Status**: Automated remediation with 2025 context\n- **Verification**: Academic sources verified\n- **Regional Context**: UK/North England where applicable",
  "properties": {
    "id": "65a7adf6-eabb-43de-9882-ef5e4bd0bb15",
    "collapsed": "true",
    "- ontology": "true",
    "- term-id": "mv-655036373419",
    "- preferred-term": "AI diagram tools",
    "- source-domain": "metaverse",
    "- status": "active",
    "- public-access": "true",
    "- definition": "A component of the metaverse ecosystem focusing on ai diagram tools.",
    "- maturity": "mature",
    "- authority-score": "0.85",
    "- owl:class": "mv:AiDiagramTools",
    "- owl:physicality": "ConceptualEntity",
    "- owl:role": "Concept",
    "- belongsToDomain": "[[MetaverseDomain]]",
    "- enables": "[[ImmersiveExperience]], [[Presence]], [[SpatialComputing]]",
    "- requires": "[[DisplayTechnology]], [[TrackingSystem]], [[RenderingEngine]]",
    "- bridges-to": "[[HumanComputerInteraction]], [[ComputerVision]], [[Robotics]]"
  },
  "backlinks": [],
  "wiki_links": [
    "TrackingSystem",
    "ImmersiveExperience",
    "ComputerVision",
    "RenderingEngine",
    "SpatialComputing",
    "Robotics",
    "HumanComputerInteraction",
    "MetaverseDomain",
    "DisplayTechnology",
    "Presence"
  ],
  "ontology": {
    "term_id": "mv-655036373419",
    "preferred_term": "AI diagram tools",
    "definition": "A component of the metaverse ecosystem focusing on ai diagram tools.",
    "source_domain": "metaverse",
    "maturity_level": null,
    "authority_score": 0.85
  }
}