{
  "title": "AI Governance Framework",
  "content": "- ### OntologyBlock\n  id:: ai-governance-framework-ontology\n  collapsed:: true\n\t- ontology:: true\n\t- term-id:: 20181\n\t- source-domain:: metaverse\n\t- status:: draft\n\t- public-access:: true\n\t- preferred-term:: AI Governance Framework\n\t- definition:: Set of policies and procedures ensuring responsible development and operation of AI components in the metaverse.\n\t- maturity:: mature\n\t- source:: [[ISO/IEC 42001]], [[OECD AI Principles]]\n\t- owl:class:: mv:AIGovernanceFramework\n\t- owl:physicality:: VirtualEntity\n\t- owl:role:: Object\n\t- owl:inferred-class:: mv:VirtualObject\n\t- owl:functional-syntax:: true\n\t- belongsToDomain:: [[TrustAndGovernanceDomain]]\n\t- implementedInLayer:: [[MiddlewareLayer]]\n\t- #### Relationships\n\t  id:: ai-governance-framework-relationships\n\t\t- has-part:: [[Ethical Framework]], [[Compliance Policy]], [[AI Risk Assessment]], [[Audit Mechanism]], [[AI Ethics Checklist]], [[Algorithmic Transparency Index]]\n\t\t- is-part-of:: [[Governance Model]]\n\t\t- requires:: [[Identity Management]], [[Access Control]], [[Data Governance]]\n\t\t- depends-on:: [[Policy Framework]], [[Regulatory Compliance]]\n\t\t- enables:: [[Responsible AI]], [[Ethical AI Operation]], [[AI Transparency]], [[AI Accountability]]\n\t- #### OWL Axioms\n\t  id:: ai-governance-framework-owl-axioms\n\t  collapsed:: true\n\t\t- ```clojure\n\t\t  Declaration(Class(mv:AIGovernanceFramework))\n\n\t\t  # Classification along two primary dimensions\n\t\t  SubClassOf(mv:AIGovernanceFramework mv:VirtualEntity)\n\t\t  SubClassOf(mv:AIGovernanceFramework mv:Object)\n\n\t\t  # Domain-specific constraints\n\t\t  SubClassOf(mv:AIGovernanceFramework\n\t\t    ObjectSomeValuesFrom(mv:hasPart mv:EthicalFramework)\n\t\t  )\n\n\t\t  SubClassOf(mv:AIGovernanceFramework\n\t\t    ObjectSomeValuesFrom(mv:hasPart mv:CompliancePolicy)\n\t\t  )\n\n\t\t  SubClassOf(mv:AIGovernanceFramework\n\t\t    ObjectSomeValuesFrom(mv:enables mv:ResponsibleAI)\n\t\t  )\n\n\t\t  # Domain classification\n\t\t  SubClassOf(mv:AIGovernanceFramework\n\t\t    ObjectSomeValuesFrom(mv:belongsToDomain mv:TrustAndGovernanceDomain)\n\t\t  )\n\n\t\t  # Layer classification\n\t\t  SubClassOf(mv:AIGovernanceFramework\n\t\t    ObjectSomeValuesFrom(mv:implementedInLayer mv:MiddlewareLayer)\n\t\t  )\n\n  # Property characteristics\n  TransitiveObjectProperty(dt:ispartof)\n\n  # Property characteristics\n  AsymmetricObjectProperty(dt:requires)\n\n  # Property characteristics\n  AsymmetricObjectProperty(dt:dependson)\n\n  # Property characteristics\n  AsymmetricObjectProperty(dt:enables)\n```\n- ## About AI Governance Framework\n  id:: ai-governance-framework-about\n\t- An AI Governance Framework establishes the comprehensive set of policies, procedures, and controls that ensure artificial intelligence systems in the metaverse are developed, deployed, and operated responsibly. It provides the structural foundation for ethical AI use, regulatory compliance, and accountability across virtual environments.\n\t- ### Key Characteristics\n\t  id:: ai-governance-framework-characteristics\n\t\t- **Policy-Driven**: Structured set of policies governing AI behavior and decision-making\n\t\t- **Compliance-Oriented**: Ensures adherence to international AI standards and regulations\n\t\t- **Risk-Based**: Incorporates systematic AI risk assessment and mitigation\n\t\t- **Auditable**: Provides mechanisms for transparency and accountability verification\n\t- ### Technical Components\n\t  id:: ai-governance-framework-components\n\t\t- [[Ethical Framework]] - Core principles guiding responsible AI conduct\n\t\t- [[Compliance Policy]] - Regulatory and standard adherence mechanisms\n\t\t- [[AI Risk Assessment]] - Systematic evaluation of AI system risks\n\t\t- [[Audit Mechanism]] - Verification and accountability processes\n\t\t- [[Bias Detection]] - Tools and procedures for identifying algorithmic bias\n\t\t- [[Explainability Requirements]] - Standards for AI decision transparency\n\t- ### Functional Capabilities\n\t  id:: ai-governance-framework-capabilities\n\t\t- **Ethical Compliance**: Ensures AI systems align with established ethical principles\n\t\t- **Regulatory Adherence**: Maintains compliance with international AI regulations\n\t\t- **Risk Management**: Systematically identifies, assesses, and mitigates AI risks\n\t\t- **Accountability Tracking**: Provides clear audit trails for AI decisions and actions\n\t\t- **Transparency Enforcement**: Requires explainability and interpretability in AI systems\n\t\t- **Bias Prevention**: Monitors and prevents discriminatory AI behavior\n\t- ### Use Cases\n\t  id:: ai-governance-framework-use-cases\n\t\t- AI-driven avatar behavior regulation in social metaverse platforms\n\t\t- Automated content moderation governance in virtual communities\n\t\t- AI marketplace recommendations with fairness and transparency requirements\n\t\t- Virtual world NPC behavior aligned with ethical guidelines\n\t\t- AI-powered accessibility features with privacy protection\n\t\t- Autonomous agent governance in multi-user virtual environments\n\t- ### Standards & References\n\t  id:: ai-governance-framework-standards\n\t\t- [[ISO/IEC 42001]] - AI Management System standard\n\t\t- [[OECD AI Principles]] - International AI governance principles\n\t\t- [[UNESCO AI Ethics]] - Global AI ethics recommendations\n\t\t- [[EU AI Act]] - European Union AI regulation framework\n\t\t- [[NIST AI Risk Management Framework]] - US AI risk management guidance\n\t- ### Related Concepts\n\t  id:: ai-governance-framework-related\n\t\t- [[Ethical Framework]] - Foundational ethical principles component\n\t\t- [[Governance Model]] - Broader governance structure parent concept\n\t\t- [[Data Governance]] - Related data management governance\n\t\t- [[Identity Management]] - Required for AI accountability\n\t\t- [[VirtualObject]] - Ontology classification as policy framework object\n\n\n\n### Relationships\n- is-subclass-of:: [[AIGovernance]]\n\n## Current Landscape (2025)\n\n- Industry adoption and implementations\n  - Metaverse platforms continue to evolve with focus on interoperability and open standards\n  - Web3 integration accelerating with decentralised identity and asset ownership\n  - Enterprise adoption growing in virtual collaboration, training, and digital twins\n  - UK companies increasingly active in metaverse development and immersive technologies\n\n- Technical capabilities\n  - Real-time rendering at photorealistic quality levels\n  - Low-latency networking enabling seamless multi-user experiences\n  - AI-driven content generation and procedural world building\n  - Spatial audio and haptics enhancing immersion\n\n- UK and North England context\n  - Manchester: Digital Innovation Factory supports metaverse startups and research\n  - Leeds: Holovis leads in immersive experiences for entertainment and training\n  - Newcastle: University research in spatial computing and interactive systems\n  - Sheffield: Advanced manufacturing using digital twin technology\n\n- Standards and frameworks\n  - Metaverse Standards Forum driving interoperability protocols\n  - WebXR enabling browser-based immersive experiences\n  - glTF and USD for 3D asset interchange\n  - Open Metaverse Interoperability Group defining cross-platform standards\n\n## Metadata\n\n- **Last Updated**: 2025-11-16\n- **Review Status**: Automated remediation with 2025 context\n- **Verification**: Academic sources verified\n- **Regional Context**: UK/North England where applicable",
  "properties": {
    "id": "ai-governance-framework-related",
    "collapsed": "true",
    "- ontology": "true",
    "- term-id": "20181",
    "- source-domain": "metaverse",
    "- status": "draft",
    "- public-access": "true",
    "- preferred-term": "AI Governance Framework",
    "- definition": "Set of policies and procedures ensuring responsible development and operation of AI components in the metaverse.",
    "- maturity": "mature",
    "- source": "[[ISO/IEC 42001]], [[OECD AI Principles]]",
    "- owl:class": "mv:AIGovernanceFramework",
    "- owl:physicality": "VirtualEntity",
    "- owl:role": "Object",
    "- owl:inferred-class": "mv:VirtualObject",
    "- owl:functional-syntax": "true",
    "- belongsToDomain": "[[TrustAndGovernanceDomain]]",
    "- implementedInLayer": "[[MiddlewareLayer]]",
    "- has-part": "[[Ethical Framework]], [[Compliance Policy]], [[AI Risk Assessment]], [[Audit Mechanism]], [[AI Ethics Checklist]], [[Algorithmic Transparency Index]]",
    "- is-part-of": "[[Governance Model]]",
    "- requires": "[[Identity Management]], [[Access Control]], [[Data Governance]]",
    "- depends-on": "[[Policy Framework]], [[Regulatory Compliance]]",
    "- enables": "[[Responsible AI]], [[Ethical AI Operation]], [[AI Transparency]], [[AI Accountability]]"
  },
  "backlinks": [],
  "wiki_links": [
    "Identity Management",
    "Responsible AI",
    "Bias Detection",
    "Governance Model",
    "MiddlewareLayer",
    "Explainability Requirements",
    "Algorithmic Transparency Index",
    "Data Governance",
    "TrustAndGovernanceDomain",
    "NIST AI Risk Management Framework",
    "VirtualObject",
    "AI Accountability",
    "Audit Mechanism",
    "EU AI Act",
    "Ethical AI Operation",
    "OECD AI Principles",
    "AI Ethics Checklist",
    "ISO/IEC 42001",
    "Regulatory Compliance",
    "AI Risk Assessment",
    "Compliance Policy",
    "Access Control",
    "AI Transparency",
    "Policy Framework",
    "Ethical Framework",
    "UNESCO AI Ethics",
    "AIGovernance"
  ],
  "ontology": {
    "term_id": "20181",
    "preferred_term": "AI Governance Framework",
    "definition": "Set of policies and procedures ensuring responsible development and operation of AI components in the metaverse.",
    "source_domain": "metaverse",
    "maturity_level": null,
    "authority_score": null
  }
}