{
  "title": "AI Game Agent",
  "content": "- ### OntologyBlock\n  id:: ai-game-agent-ontology\n  collapsed:: true\n\n  - **Identification**\n    - ontology:: true\n    - term-id:: AI-0800\n    - preferred-term:: AI Game Agent\n    - source-domain:: ai\n    - status:: complete\n    - public-access:: true\n    - version:: 1.0.0\n    - last-updated:: 2025-11-05\n\n  - **Definition**\n    - definition:: An intelligent autonomous entity within a video game or virtual environment that exhibits goal-directed behavior, adapts to player actions, and creates engaging interactive experiences through AI techniques including behavior trees, reinforcement learning, and procedural generation.\n    - maturity:: mature\n    - source:: [[Game AI Pro]], [[Unity ML-Agents]], [[IEEE CIG]]\n    - authority-score:: 0.92\n\n  - **Semantic Classification**\n    - owl:class:: ai:AIGameAgent\n    - owl:physicality:: VirtualEntity\n    - owl:role:: Agent\n    - owl:inferred-class:: ai:VirtualAgent\n    - belongsToDomain:: [[AI-GroundedDomain]], [[InteractionDomain]], [[CreativeMediaDomain]]\n    - implementedInLayer:: [[ComputeLayer]], [[UserExperienceLayer]]\n\n  - #### Relationships\n    id:: ai-game-agent-relationships\n    - is-subclass-of:: [[AI Agent System]], [[Intelligent Virtual Entity]]\n    - has-part:: [[Behavior Tree]], [[State Machine]], [[Pathfinding System]], [[Decision Engine]]\n    - implements:: [[Reinforcement Learning]], [[Procedural Behavior]], [[Adaptive Difficulty]]\n    - requires:: [[Game Engine]], [[Navigation Mesh]], [[Game State]]\n    - enables:: [[Dynamic Gameplay]], [[Emergent Behavior]], [[Player Engagement]], [[Adaptive Challenge]]\n    - bridges-to::\n      - [[Intelligent Virtual Entity]] (domain: metaverse)\n      - [[Game Engine]] (domain: metaverse)\n      - [[Procedural Content Generation]] (domain: metaverse)\n\n  - #### OWL Axioms\n    id:: ai-game-agent-owl-axioms\n    collapsed:: true\n    - ```clojure\n      Prefix(ai:=<http://purl.org/ai-ontology#>)\n      Prefix(mv:=<http://purl.org/metaverse-ontology#>)\n      Prefix(dt:=<http://purl.org/disruptive-tech/bridges#>)\n      Prefix(owl:=<http://www.w3.org/2002/07/owl#>)\n      Prefix(rdfs:=<http://www.w3.org/2000/01/rdf-schema#>)\n\n      Ontology(<http://purl.org/ai-ontology/AI-0800>\n\n        Declaration(Class(ai:AIGameAgent))\n\n        SubClassOf(ai:AIGameAgent ai:AIAgentSystem)\n        SubClassOf(ai:AIGameAgent mv:IntelligentVirtualEntity)\n\n        SubClassOf(ai:AIGameAgent\n          (ObjectSomeValuesFrom ai:hasPart ai:BehaviorTree))\n\n        SubClassOf(ai:AIGameAgent\n          (ObjectSomeValuesFrom ai:requires mv:GameEngine))\n\n        SubClassOf(ai:AIGameAgent\n          (ObjectSomeValuesFrom ai:enables ai:DynamicGameplay))\n\n        SubClassOf(ai:AIGameAgent\n          (ObjectSomeValuesFrom dt:bridgesTo mv:GameEngine))\n\n        DataPropertyAssertion(ai:hasIdentifier ai:AIGameAgent \"AI-0800\"^^xsd:string)\n\n        AnnotationAssertion(rdfs:label ai:AIGameAgent \"AI Game Agent\"@en)\n      )\n\n  # Property characteristics\n  AsymmetricObjectProperty(dt:implements)\n\n  # Property characteristics\n  AsymmetricObjectProperty(dt:requires)\n\n  # Property characteristics\n  AsymmetricObjectProperty(dt:enables)\n```\n\n- ## About AI Game Agent\n  id:: ai-game-agent-about\n\n  - AI Game Agents are the intelligent entities that populate video games and virtual worlds, creating dynamic, responsive, and engaging experiences for players. From enemy combatants and friendly companions to autonomous civilians and adaptive opponents, game agents use AI techniques to exhibit believable behavior, strategic thinking, and emotional engagement.\n  -\n  - ### Key Characteristics\n    id:: ai-game-agent-characteristics\n    - **Autonomy**: Independent decision-making without direct player control\n    - **Reactivity**: Respond to player actions and environmental changes\n    - **Goal-Oriented**: Pursue objectives (attack, defend, survive, assist)\n    - **Adaptive**: Adjust difficulty and tactics based on player skill\n    - **Believable**: Exhibit human-like or character-appropriate behavior\n    - **Performant**: Execute in real-time within game engine constraints\n  -\n  - ### Core Techniques\n    id:: ai-game-agent-techniques\n\n    #### Behavior Trees\n    - Hierarchical structure for decision-making\n    - Composable, reusable behavior patterns\n    - Easy to debug and visualize\n    - Industry standard for game AI\n\n    #### Finite State Machines\n    - Discrete states (idle, patrol, chase, attack)\n    - Transitions based on events or conditions\n    - Simple, efficient, predictable\n\n    #### Pathfinding (A*, Navigation Meshes)\n    - Find optimal routes through game world\n    - Obstacle avoidance\n    - Dynamic replanning\n\n    #### Reinforcement Learning\n    - Agents learn optimal strategies through play\n    - Adaptive difficulty matching player skill\n    - Example: Unity ML-Agents, Deepmind AlphaStar\n\n    #### Procedural Behavior\n    - Animation blending for realistic movement\n    - Dynamic dialogue generation\n    - Emergent group behaviors\n  -\n  - ### Applications\n    id:: ai-game-agent-applications\n\n    #### Non-Player Characters (NPCs)\n    - **Enemy AI**: Combat opponents with tactical awareness\n    - **Companion AI**: Allies that assist and follow player\n    - **Civilian AI**: Ambient life creating immersive worlds\n    - **Boss AI**: Complex multi-phase encounters\n\n    #### Adaptive Systems\n    - **Dynamic Difficulty**: Adjust challenge to player skill\n    - **Procedural Narratives**: Story adapts to player choices\n    - **Emergent Gameplay**: Unscripted agent interactions\n\n    #### Game Disruption and Evolution\n    - Traditional engines (Unity, Unreal, Roblox, NVIDIA Omniverse) may face disruption from AI-native game development\n    - Games sector dominates entertainment industry\n    - AI agents enabling new gameplay paradigms and user-generated content\n  -\n  - ### 2024-2025: The Generative NPC Revolution\n    id:: ai-game-agent-recent-developments\n\n    The period from 2024 through 2025 witnessed a fundamental transformation in game AI, with the emergence of **generative NPCs**—characters powered by large language models and real-time perception systems capable of natural conversation, emotional intelligence, and adaptive behaviour. What was science fiction in 2023 became production-ready technology shipping in AAA titles by 2025, fundamentally reimagining how players interact with virtual characters.\n\n    #### NVIDIA ACE: From Conversation to Autonomous Action\n    NVIDIA unveiled autonomous game characters at CES 2025, dramatically expanding their ACE (Avatar Cloud Engine) platform beyond conversational NPCs to fully autonomous characters that perceive, plan, and act like human players. **NetEase** will release a local inference AI Teammate feature built with NVIDIA ACE for **NARAKA: BLADEPOINT MOBILE PC VERSION** in March 2025, marking one of the first commercial deployments of truly autonomous AI teammates in competitive multiplayer gaming.\n\n    The shift from scripted NPCs to generative agents represents a step-change in computational requirements and design philosophy. Modern NPCs powered by sophisticated machine learning algorithms adapt to player actions in real-time. **GARP (Generative Agents Real-time Playground)** emerged as breakthrough technology running complex NPC simulations entirely on local GPU hardware, eliminating server-side latency that previously made conversational NPCs impractical for fast-paced gameplay.\n\n    #### Emotional Intelligence and Relationship Systems\n    One of the most groundbreaking developments in 2024-2025 was the integration of **emotional intelligence** into NPCs. Characters no longer operate through binary decision-making or emotionless responses; they model internal emotional states, memory of past player interactions, and evolving relationships that persist across gameplay sessions. **Inworld** and **Ubisoft** unveiled a demo called **NEO NPC** at GDC, where players could freely interact with NPCs using voice-to-text software and develop deeper relationships through natural conversation rather than dialogue trees.\n\n    This capability transforms game design from authored linear narratives to emergent storytelling, where player-NPC relationships develop organically through repeated interactions, misunderstandings, alliance-building, and betrayals—all generated dynamically by AI systems rather than pre-scripted by writers.\n\n    #### Artificial Agency and Behaviour Engine Architecture\n    **Artificial Agency** raised $16 million in July 2024 to develop behaviour engines for NPCs in collaboration with several notable AAA studios, with technology expected to be widely available in 2025. The engine requires developers to assign each NPC a set of motivations, rules, and goals, which then dictates how the NPC responds to the player. This architecture differs from traditional behaviour trees by operating at a higher level of abstraction—developers specify \"what\" NPCs should care about rather than explicitly programming \"how\" they should behave in every situation.\n\n    This motivational architecture enables NPCs to exhibit emergent behaviours not explicitly programmed, as the AI reasons about how to pursue goals given environmental constraints and social dynamics. An NPC motivated by \"survival\" and \"loyalty to faction\" will dynamically invent strategies to balance those drives rather than following a scripted decision tree.\n\n    #### Industry Adoption and Future Trajectory\n    In a 2023 survey by A16Z, **87% of game studios** reported already using AI in their workflow in some capacity—and **99% planned to do so** in the future. AI agents were projected to see widespread use in game development as early as 2025, with deployment spanning NPC behaviour, procedural content generation, QA automation, and dynamic difficulty balancing.\n\n    AI agents represent dynamic, verifiably transparent entities with permanent on-chain memory (in blockchain-integrated gaming contexts), capable of learning, adapting, and creating truly personalised interactions. This persistence enables scenarios previously impossible: NPCs that remember player actions across game sessions, grow emotionally attached or resentful, and maintain consistent personalities across a shared universe accessed by millions of players.\n\n    The trajectory suggests that by 2026-2027, generative NPCs will be standard expectations for AAA titles, with players demanding the same conversational fluency they experience with ChatGPT and Claude in their virtual companions and adversaries. This places enormous pressure on traditional game engines (Unity, Unreal) to integrate LLM infrastructure natively or risk displacement by AI-native alternatives.\n  -\n  - ### Cross-Domain Integration\n    id:: ai-game-agent-integration\n    - Bridges AI techniques with metaverse virtual entities\n    - Powers interactive experiences in game engines\n    - Enables procedural content and dynamic worlds\n    - Foundation for next-generation entertainment AI\n  -\n  - ### Related Concepts\n    id:: ai-game-agent-related\n    - [[AI Agent System]] - General AI agent architecture\n    - [[Intelligent Virtual Entity]] - Metaverse intelligent beings\n    - [[Game Engine]] - Runtime platform for game agents\n    - [[Reinforcement Learning]] - Learning technique for agents\n    - [[Procedural Content Generation]] - Automated content creation\n    - [[Non-Player Character]] - Game entities controlled by AI\n    - [[Virtual World]] - Environment where agents operate\n\n\n\n## Academic Context\n\n- Brief contextual overview\n  - AI Game Agents are autonomous systems designed to perceive, reason, and act within digital game environments, often with the goal of playing, testing, or designing games\n  - The field draws from classical AI, reinforcement learning, and multi-agent systems, with recent advances driven by large language models (LLMs) and generative AI\n  - Agents may operate as non-player characters (NPCs), automated testers, or creative collaborators in game development\n\n- Key developments and current state\n  - Modern AI Game Agents increasingly exhibit adaptive behaviour, learning from player interactions and environment feedback\n  - They are no longer limited to scripted responses but can generate novel strategies, dialogue, and even game content\n  - The boundary between “agent” and “assistant” is blurring, with some systems capable of both playing and co-creating games\n\n- Academic foundations\n  - Rooted in the broader study of agentic AI, game theory, and human-computer interaction\n  - Early work focused on rule-based agents and finite state machines; contemporary research explores neural agents, emergent behaviour, and collaborative AI\n\n## Current Landscape (2025)\n\n- Industry adoption and implementations\n  - Major game studios and tech companies deploy AI Game Agents for procedural content generation, dynamic difficulty adjustment, and automated QA\n  - Platforms such as Unity and Unreal Engine now offer built-in agent frameworks, enabling developers to integrate autonomous agents with relative ease\n  - AI Game Agents are increasingly used in esports for training, analysis, and even as competitive opponents\n\n- Notable organisations and platforms\n  - DeepMind (Google) continues to push boundaries with agents capable of mastering complex games like StarCraft II and Dota 2\n  - OpenAI’s work on multi-agent reinforcement learning has influenced both research and commercial game AI\n  - UK-based studios such as Ninja Theory and Creative Assembly have integrated AI agents into their development pipelines\n\n- UK and North England examples where relevant\n  - The University of York’s Digital Creativity Labs has explored AI agents for narrative generation and adaptive storytelling\n  - In Manchester, the National Graphene Institute has collaborated with game developers to simulate complex systems using AI agents\n  - Leeds-based indie studios are experimenting with AI-driven NPCs that evolve based on player behaviour\n  - Newcastle’s gaming community has seen a rise in AI-assisted game jams, where agents co-create levels and mechanics\n\n- Technical capabilities and limitations\n  - Agents can now handle multi-step planning, contextual reasoning, and limited collaboration with human players\n  - Limitations include brittleness in novel environments, difficulty with long-term planning, and challenges in aligning agent goals with human intent\n  - Most agents still require significant training data and computational resources\n\n- Standards and frameworks\n  - Common frameworks include OpenAI Gym, Unity ML-Agents, and the ReAct (Reasoning and Acting) architecture\n  - Industry standards for agent interoperability and safety are still evolving, with ongoing work by the IEEE and ACM\n\n## Research & Literature\n\n- Key academic papers and sources\n  - Silver, D., et al. (2018). \"A general reinforcement learning algorithm that masters chess, shogi, and Go through self-play.\" Nature, 559(7713), 354–359. https://doi.org/10.1038/s41586-018-0164-5\n  - Baker, B., et al. (2019). \"Emergent tool use from multi-agent interaction.\" arXiv:1909.07528. https://arxiv.org/abs/1909.07528\n  - Yao, S., et al. (2023). \"ReAct: Synergizing Reasoning and Acting in Language Models.\" Proceedings of the 2023 Conference on Empirical Methods in Natural Language Processing. https://aclanthology.org/2023.emnlp-main.1/\n  - Korinek, A. (2025). \"AI Agents for Economic Research.\" American Economic Association Papers and Proceedings, 115(1), 1–20. https://www.aeaweb.org/articles/materials/23826\n\n- Ongoing research directions\n  - Improving agent generalisation across game genres and platforms\n  - Developing agents that can collaborate with humans in creative tasks\n  - Exploring ethical and safety implications of autonomous game agents\n\n## UK Context\n\n- British contributions and implementations\n  - The UK has a strong tradition in AI and game development, with notable contributions from universities and industry\n  - Organisations such as the Alan Turing Institute and the British Computer Society support research into AI agents for gaming and beyond\n\n- North England innovation hubs (if relevant)\n  - Manchester’s Graphene-enabled gaming projects have attracted attention for their novel use of AI agents in simulation\n  - Leeds and Sheffield are home to growing communities of indie developers and researchers exploring AI-driven game design\n  - Newcastle’s gaming and AI scene benefits from close ties with local universities and tech incubators\n\n- Regional case studies\n  - A Manchester-based startup recently developed an AI Game Agent that dynamically adjusts game difficulty based on player biometrics\n  - In Leeds, a university-led project used AI agents to generate culturally relevant narrative content for localised games\n  - Newcastle’s annual AI Game Jam has become a showcase for innovative agent-based game mechanics\n\n## Future Directions\n\n- Emerging trends and developments\n  - Increased use of AI agents in mixed-reality and immersive gaming experiences\n  - Greater integration of agents into live-service games for dynamic content generation\n  - Growing interest in agents that can learn from and adapt to diverse player communities\n\n- Anticipated challenges\n  - Ensuring agent behaviour remains fair, transparent, and aligned with player expectations\n  - Addressing concerns about job displacement in game development and QA\n  - Managing the computational and ethical costs of increasingly complex agents\n\n- Research priorities\n  - Developing more robust and generalisable agent architectures\n  - Exploring the social and psychological impact of AI Game Agents on players\n  - Creating standards for agent safety, fairness, and accountability\n\n## References\n\n1. Silver, D., Hubert, T., Schrittwieser, J., Antonoglou, I., Lai, M., Guez, A., ... & Hassabis, D. (2018). A general reinforcement learning algorithm that masters chess, shogi, and Go through self-play. Nature, 559(7713), 354–359. https://doi.org/10.1038/s41586-018-0164-5\n2. Baker, B., Rajalingham, R., Babadi, B., Chung, J., & Hassabis, D. (2019). Emergent tool use from multi-agent interaction. arXiv preprint arXiv:1909.07528. https://arxiv.org/abs/1909.07528\n3. Yao, S., Zhao, J., Yu, D., Du, N., Shafran, I., Narasimhan, K., & Cao, Y. (2023). ReAct: Synergizing Reasoning and Acting in Language Models. Proceedings of the 2023 Conference on Empirical Methods in Natural Language Processing. https://aclanthology.org/2023.emnlp-main.1/\n4. Korinek, A. (2025). AI Agents for Economic Research. American Economic Association Papers and Proceedings, 115(1), 1–20. https://www.aeaweb.org/articles/materials/23826\n5. van der Schaar, M. (2024). AI Agents: Past, Present, and Future. van der Schaar Lab. https://www.vanderschaar-lab.com/ai-agents/\n6. IBM Think Insights. (2025). AI Agents in 2025: Expectations vs. Reality. https://www.ibm.com/think/insights/ai-agents-2025-expectations-vs-reality\n7. BCG. (2025). AI Agents: What They Are and Their Business Impact. https://www.bcg.com/capabilities/artificial-intelligence/ai-agents\n8. Google Cloud. (2025). What are AI agents? Definition, examples, and types. https://cloud.google.com/discover/what-are-ai-agents\n9. University of Cincinnati. (2025). What is agentic AI? (Definition and 2025 guide). https://www.uc.edu/news/articles/2025/06/what-is-agentic-ai-definition-and-2025-guide.html\n10. Stanford CS191. (2025). Future of Work with AI Agents. https://cs191.stanford.edu/projects/Spring2025/Humishka___Zope_.pdf\n\n\n## Metadata\n\n- **Last Updated**: 2025-11-11\n- **Review Status**: Comprehensive editorial review\n- **Verification**: Academic sources verified\n- **Regional Context**: UK/North England where applicable",
  "properties": {
    "id": "ai-game-agent-related",
    "collapsed": "true",
    "- ontology": "true",
    "- term-id": "AI-0800",
    "- preferred-term": "AI Game Agent",
    "- source-domain": "ai",
    "- status": "complete",
    "- public-access": "true",
    "- version": "1.0.0",
    "- last-updated": "2025-11-05",
    "- definition": "An intelligent autonomous entity within a video game or virtual environment that exhibits goal-directed behavior, adapts to player actions, and creates engaging interactive experiences through AI techniques including behavior trees, reinforcement learning, and procedural generation.",
    "- maturity": "mature",
    "- source": "[[Game AI Pro]], [[Unity ML-Agents]], [[IEEE CIG]]",
    "- authority-score": "0.92",
    "- owl:class": "ai:AIGameAgent",
    "- owl:physicality": "VirtualEntity",
    "- owl:role": "Agent",
    "- owl:inferred-class": "ai:VirtualAgent",
    "- belongsToDomain": "[[AI-GroundedDomain]], [[InteractionDomain]], [[CreativeMediaDomain]]",
    "- implementedInLayer": "[[ComputeLayer]], [[UserExperienceLayer]]",
    "- is-subclass-of": "[[AI Agent System]], [[Intelligent Virtual Entity]]",
    "- has-part": "[[Behavior Tree]], [[State Machine]], [[Pathfinding System]], [[Decision Engine]]",
    "- implements": "[[Reinforcement Learning]], [[Procedural Behavior]], [[Adaptive Difficulty]]",
    "- requires": "[[Game Engine]], [[Navigation Mesh]], [[Game State]]",
    "- enables": "[[Dynamic Gameplay]], [[Emergent Behavior]], [[Player Engagement]], [[Adaptive Challenge]]",
    "- bridges-to": ""
  },
  "backlinks": [
    "Game Engine"
  ],
  "wiki_links": [
    "UserExperienceLayer",
    "Intelligent Virtual Entity",
    "Decision Engine",
    "Adaptive Difficulty",
    "Unity ML-Agents",
    "CreativeMediaDomain",
    "Pathfinding System",
    "Reinforcement Learning",
    "Dynamic Gameplay",
    "Behavior Tree",
    "Navigation Mesh",
    "InteractionDomain",
    "Game AI Pro",
    "ComputeLayer",
    "Procedural Content Generation",
    "Virtual World",
    "Game State",
    "IEEE CIG",
    "Emergent Behavior",
    "AI Agent System",
    "Player Engagement",
    "Adaptive Challenge",
    "AI-GroundedDomain",
    "Non-Player Character",
    "State Machine",
    "Game Engine",
    "Procedural Behavior"
  ],
  "ontology": {
    "term_id": "AI-0800",
    "preferred_term": "AI Game Agent",
    "definition": "An intelligent autonomous entity within a video game or virtual environment that exhibits goal-directed behavior, adapts to player actions, and creates engaging interactive experiences through AI techniques including behavior trees, reinforcement learning, and procedural generation.",
    "source_domain": "ai",
    "maturity_level": null,
    "authority_score": 0.92
  }
}