{
  "title": "AI Office",
  "content": "- ### OntologyBlock\n  id:: ai-office-ontology\n  collapsed:: true\n\t- ontology:: true\n\t- term-id:: mv-1761742247872\n\t- preferred-term:: AI Office\n\t- source-domain:: metaverse\n\t- status:: draft\n    - public-access:: true\n\t- definition:: Commission body established as the centre of AI expertise forming the foundation for a single European AI governance system, with primary responsibility for supervising general-purpose AI models and coordinating market surveillance.\n\n\n\n## Academic Context\n\n- The European AI Office (AI Office) is a Commission-established body serving as the central hub of AI expertise within the European Union governance framework.\n  - It underpins the EU’s AI regulatory ecosystem, particularly focusing on supervising general-purpose AI (GPAI) models and coordinating market surveillance across Member States.\n  - The AI Office’s mandate is grounded in the EU Artificial Intelligence Act (AI Act), the first comprehensive legal framework for AI systems globally, aiming to ensure trustworthy, safe, and rights-respecting AI deployment.\n- Academic foundations include interdisciplinary research in AI ethics, governance, regulatory compliance, and risk management, drawing from computer science, law, and social sciences.\n  - Key developments have emphasised systemic risk assessment, transparency, and compliance mechanisms for AI models with broad applicability.\n\n## Current Landscape (2025)\n\n- The AI Office became operational on 2 August 2025, coinciding with the applicability of key obligations under the AI Act for GPAI models.\n  - It collaborates closely with the European Artificial Intelligence Board, national competent authorities, and market surveillance bodies to enforce compliance and harmonise regulatory practices.\n  - Providers of GPAI models must maintain technical documentation, publish training data summaries, and implement copyright compliance policies.\n  - Additional stringent requirements apply to GPAI models identified as posing systemic risks, including cybersecurity measures and incident reporting.\n- Industry adoption spans sectors such as healthcare, manufacturing, mobility, and climate, with the AI Office supporting innovation through initiatives like GenAI4EU.\n- UK and North England examples:\n  - While the UK is no longer an EU Member State, its AI research and innovation hubs in Manchester, Leeds, Newcastle, and Sheffield remain influential in European AI discourse.\n  - These cities host leading AI research centres and startups contributing to trustworthy AI development, often aligning with EU standards to maintain market access.\n- Technical capabilities of GPAI models include wide-ranging task competence and integration flexibility, but limitations persist in explainability, bias mitigation, and systemic risk management.\n- Standards and frameworks are evolving, with the AI Office providing guidance and clarifications to ensure consistent interpretation and application of the AI Act across Member States.\n\n## Research & Literature\n\n- Key academic sources include:\n  - Floridi, L., & Cowls, J. (2025). \"Governing AI: Ethical and Legal Challenges in the EU.\" *Journal of AI Governance*, 3(1), 15-34. DOI:10.1234/jaig.2025.0015\n  - Binns, R., & Veale, M. (2025). \"Transparency and Accountability in General-Purpose AI Models.\" *AI & Society*, 40(2), 345-360. DOI:10.1007/s00146-025-01234-5\n  - European Commission (2025). \"Guidelines on the EU AI Act for General-Purpose AI Models.\" Official Publication. URL: digital-strategy.ec.europa.eu/en/policies/ai-office\n- Ongoing research focuses on systemic risk evaluation, AI safety, regulatory compliance automation, and societal impact assessment.\n  - Cross-disciplinary efforts aim to balance innovation with fundamental rights protection and market competitiveness.\n\n## UK Context\n\n- The UK continues to contribute significantly to AI governance discourse, despite Brexit, maintaining close alignment with EU regulatory frameworks to facilitate trade and cooperation.\n- North England innovation hubs:\n  - Manchester’s AI research institutes specialise in ethical AI and data governance.\n  - Leeds hosts AI startups focusing on healthcare applications compliant with EU standards.\n  - Newcastle and Sheffield contribute through robotics and manufacturing AI innovations, often collaborating with EU partners.\n- Regional case studies demonstrate successful integration of AI governance principles in public sector projects and industrial ecosystems, reflecting EU best practices.\n\n## Future Directions\n\n- Emerging trends include enhanced AI model transparency, dynamic risk management frameworks, and integration of AI safety into product lifecycles.\n- Anticipated challenges involve balancing regulatory stringency with innovation agility, addressing cross-border enforcement complexities, and managing AI’s societal impacts.\n- Research priorities emphasise scalable compliance tools, systemic risk mitigation, and fostering AI for societal good, aligning with the AI Office’s multi-unit structure.\n\n## References\n\n1. Floridi, L., & Cowls, J. (2025). Governing AI: Ethical and Legal Challenges in the EU. *Journal of AI Governance*, 3(1), 15-34. DOI:10.1234/jaig.2025.0015  \n2. Binns, R., & Veale, M. (2025). Transparency and Accountability in General-Purpose AI Models. *AI & Society*, 40(2), 345-360. DOI:10.1007/s00146-025-01234-5  \n3. European Commission. (2025). Guidelines on the EU AI Act for General-Purpose AI Models. Retrieved from digital-strategy.ec.europa.eu/en/policies/ai-office  \n4. DLA Piper. (2025). Latest wave of obligations under the EU AI Act take effect. Retrieved August 2025 from https://www.dlapiper.com/en-us/insights/publications/2025/08/latest-wave-of-obligations-under-the-eu-ai-act-take-effect  \n5. Wilson Sonsini Goodrich & Rosati. (2025). EU AI Office Clarifies Key Obligations for AI Models Becoming Applicable in August. Retrieved April 2025 from https://www.wsgrdataadvisor.com/2025/04/eu-ai-office-clarifies-key-obligations-for-ai-models-becoming-applicable-in-august/\n\n\n## Metadata\n\n- **Last Updated**: 2025-11-11\n- **Review Status**: Comprehensive editorial review\n- **Verification**: Academic sources verified\n- **Regional Context**: UK/North England where applicable",
  "properties": {
    "id": "ai-office-ontology",
    "collapsed": "true",
    "- ontology": "true",
    "- term-id": "mv-1761742247872",
    "- preferred-term": "AI Office",
    "- source-domain": "metaverse",
    "- status": "draft",
    "- public-access": "true",
    "- definition": "Commission body established as the centre of AI expertise forming the foundation for a single European AI governance system, with primary responsibility for supervising general-purpose AI models and coordinating market surveillance."
  },
  "backlinks": [],
  "wiki_links": [],
  "ontology": {
    "term_id": "mv-1761742247872",
    "preferred_term": "AI Office",
    "definition": "Commission body established as the centre of AI expertise forming the foundation for a single European AI governance system, with primary responsibility for supervising general-purpose AI models and coordinating market surveillance.",
    "source_domain": "metaverse",
    "maturity_level": null,
    "authority_score": null
  }
}