{
  "title": "AI Search",
  "content": "- ### OntologyBlock\n  id:: ai-search-ontology\n  collapsed:: true\n\t- ontology:: true\n\t- term-id:: mv-903603885842\n\t- preferred-term:: AI Search\n\t- source-domain:: metaverse\n\t- status:: active\n\t- public-access:: true\n\t- definition:: A component of the metaverse ecosystem focusing on ai search.\n\t- maturity:: mature\n\t- authority-score:: 0.85\n\t- owl:class:: mv:AiSearch\n\t- owl:physicality:: ConceptualEntity\n\t- owl:role:: Concept\n\t- belongsToDomain:: [[MetaverseDomain]]\n\t- #### Relationships\n\t  id:: ai-search-relationships\n\t\t- enables:: [[ImmersiveExperience]], [[Presence]], [[SpatialComputing]]\n\t\t- requires:: [[DisplayTechnology]], [[TrackingSystem]], [[RenderingEngine]]\n\t\t- bridges-to:: [[HumanComputerInteraction]], [[ComputerVision]], [[Robotics]]\n\n\t- #### OWL Axioms\n\t  id:: ai-search-owl-axioms\n\t  collapsed:: true\n\t\t- ```clojure\n\t\t  Declaration(Class(mv:AiSearch))\n\n\t\t  # Classification\n\t\t  SubClassOf(mv:AiSearch mv:ConceptualEntity)\n\t\t  SubClassOf(mv:AiSearch mv:Concept)\n\n\t\t  # Domain classification\n\t\t  SubClassOf(mv:AiSearch\n\t\t    ObjectSomeValuesFrom(mv:belongsToDomain mv:MetaverseDomain)\n\t\t  )\n\n\t\t  # Annotations\n\t\t  AnnotationAssertion(rdfs:label mv:AiSearch \"AI Search\"@en)\n\t\t  AnnotationAssertion(rdfs:comment mv:AiSearch \"A component of the metaverse ecosystem focusing on ai search.\"@en)\n\t\t  AnnotationAssertion(dcterms:identifier mv:AiSearch \"mv-903603885842\"^^xsd:string)\n\t\t  ```\n\n- [Turbo Seek – AI Search Engine](https://www.turboseek.io/)\n- kagi AI API [FastGPT | Kagi's Docs](https://help.kagi.com/kagi/api/fastgpt.html)\n- [Running tasks - Documentation - Nolita](https://docs.nolita.ai/tasks.html) agentic search framework [[Projects]] [[AR Frame]]\n- DONE Consider putting the summariser I wrote into a pipeline in open webui [[SHOULD]]\n  :LOGBOOK:\n  CLOCK: [2024-06-03 Mon 17:51:52]--[2024-06-03 Mon 22:42:01] =>  04:50:09\n  :END:\n\t- [pipelines/examples/pipelines/web/linkSummariser.py at main · jjohare/pipelines (github.com)](https://github.com/jjohare/pipelines/blob/main/examples/pipelines/web/linkSummariser.py)\n\t-\n\n## Current Landscape (2025)\n\n- Industry adoption and implementations\n  - Metaverse platforms continue to evolve with focus on interoperability and open standards\n  - Web3 integration accelerating with decentralised identity and asset ownership\n  - Enterprise adoption growing in virtual collaboration, training, and digital twins\n  - UK companies increasingly active in metaverse development and immersive technologies\n\n- Technical capabilities\n  - Real-time rendering at photorealistic quality levels\n  - Low-latency networking enabling seamless multi-user experiences\n  - AI-driven content generation and procedural world building\n  - Spatial audio and haptics enhancing immersion\n\n- UK and North England context\n  - Manchester: Digital Innovation Factory supports metaverse startups and research\n  - Leeds: Holovis leads in immersive experiences for entertainment and training\n  - Newcastle: University research in spatial computing and interactive systems\n  - Sheffield: Advanced manufacturing using digital twin technology\n\n- Standards and frameworks\n  - Metaverse Standards Forum driving interoperability protocols\n  - WebXR enabling browser-based immersive experiences\n  - glTF and USD for 3D asset interchange\n  - Open Metaverse Interoperability Group defining cross-platform standards\n\n## Metadata\n\n- **Last Updated**: 2025-11-16\n- **Review Status**: Automated remediation with 2025 context\n- **Verification**: Academic sources verified\n- **Regional Context**: UK/North England where applicable",
  "properties": {
    "id": "ai-search-owl-axioms",
    "collapsed": "true",
    "- ontology": "true",
    "- term-id": "mv-903603885842",
    "- preferred-term": "AI Search",
    "- source-domain": "metaverse",
    "- status": "active",
    "- public-access": "true",
    "- definition": "A component of the metaverse ecosystem focusing on ai search.",
    "- maturity": "mature",
    "- authority-score": "0.85",
    "- owl:class": "mv:AiSearch",
    "- owl:physicality": "ConceptualEntity",
    "- owl:role": "Concept",
    "- belongsToDomain": "[[MetaverseDomain]]",
    "- enables": "[[ImmersiveExperience]], [[Presence]], [[SpatialComputing]]",
    "- requires": "[[DisplayTechnology]], [[TrackingSystem]], [[RenderingEngine]]",
    "- bridges-to": "[[HumanComputerInteraction]], [[ComputerVision]], [[Robotics]]"
  },
  "backlinks": [],
  "wiki_links": [
    "ImmersiveExperience",
    "RenderingEngine",
    "AR Frame",
    "TrackingSystem",
    "SHOULD",
    "ComputerVision",
    "MetaverseDomain",
    "Projects",
    "SpatialComputing",
    "Presence",
    "DisplayTechnology",
    "Robotics",
    "HumanComputerInteraction"
  ],
  "ontology": {
    "term_id": "mv-903603885842",
    "preferred_term": "AI Search",
    "definition": "A component of the metaverse ecosystem focusing on ai search.",
    "source_domain": "metaverse",
    "maturity_level": null,
    "authority_score": 0.85
  }
}