{
  "title": "AI TRiSM",
  "content": "- ### OntologyBlock\n  id:: ai-trism-ontology\n  collapsed:: true\n\t- ontology:: true\n\t- term-id:: ME-0002\n\t- preferred-term:: AI TRiSM\n\t- source-domain:: metaverse\n\t- status:: emerging-technology\n    - public-access:: true\n\t- definition:: [Generated from Gartner emerging tech analysis]\n\t- maturity:: emerging\n\t- owl:class:: mv:AITRiSM\n\t- owl:physicality:: ConceptualEntity\n\t- owl:role:: Concept\n\t- is-subclass-of:: [[Metaverse]]\n\t- belongsToDomain:: [[MetaverseDomain]]\n\t- category:: AI & Autonomy\n\n\n## Overview\n\n- AI TRiSM (Artificial Intelligence Trust, Risk, and Security Management)\n  - Precise technical definition\n    - AI TRiSM is a comprehensive framework for managing the governance, security, and ethical risks associated with artificial intelligence systems, ensuring model trustworthiness, fairness, reliability, robustness, efficacy, and data protection throughout their lifecycle (Gartner, 2023).\n    - It integrates technical, organisational, and regulatory controls to address challenges such as algorithmic bias, explainability, data privacy, and compliance in AI and autonomous systems.\n  - Current state and implementations (2024–2025)\n    - AI TRiSM is widely adopted by global enterprises and technology providers to secure AI deployments, particularly in sectors such as finance, healthcare, and public services.\n    - Organisations are increasingly embedding AI TRiSM into their AI engineering workflows, with unified platforms emerging for runtime inspection, policy enforcement, and continuous monitoring of AI models.\n    - Leading vendors (e.g., Splunk, Check Point, BigID) offer AI TRiSM solutions that support model governance, bias detection, and regulatory compliance, with growing emphasis on explainable AI and automated risk assessment.\n  - UK context and examples, especially North England\n    - In the UK, AI TRiSM is gaining traction as part of the national AI strategy, with public and private sector organisations prioritising trustworthy and secure AI.\n    - In North England, initiatives such as the AI North network and the Digital Catapult’s AI hubs are promoting best practices in AI governance and security, supporting local businesses and public sector agencies in adopting AI TRiSM principles.\n    - Examples include NHS trusts in Greater Manchester and Yorkshire piloting AI-driven diagnostic tools with robust TRiSM frameworks to ensure patient data privacy, model fairness, and regulatory compliance.\n    - The Alan Turing Institute and UK Research and Innovation (UKRI) are funding research into AI TRiSM, with several projects based in northern universities (e.g., University of Leeds, Newcastle University) focusing on ethical AI and secure autonomous systems.\n  - Key research papers and sources with full citations\n    - Gartner. (2023). *AI Trust, Risk, and Security Management (AI TRiSM)*. Gartner Research.\n    - Check Point Software. (2025). *What Is AI TRiSM?*. Cyber Hub. https://www.checkpoint.com/cyber-hub/cyber-security/what-is-ai-security/what-is-ai-trism/\n    - Transcend. (2025). *The Complete Guide to AI TRiSM: From Theory to Implementation*. Transcend Blog. https://transcend.io/blog/ai-trism\n    - Duality Technologies. (2025). *Gartner AI TRiSM Framework: How Duality Supports Secure AI*. Duality Blog. https://dualitytech.com/blog/gartner-ai-trism-duality/\n    - Splunk. (2025). *The Importance of AI TRiSM Today: AI Trust, Risk, and Security Management*. Splunk Blog. https://www.splunk.com/en_us/blog/learn/ai-trism-ai-trust-risk-security-management.html\n    - BigID. (2025). *The AI TRiSM Framework: Artificial Intelligence Trust, Risk, and Security Management*. BigID Blog. https://bigid.com/blog/ai-trism-guide/\n    - Proofpoint. (2025). *What Is AI TRiSM? AI Trust, Risk, and Security Management*. Threat Reference. https://www.proofpoint.com/us/threat-reference/ai-trism\n    - Securiti. (2025). *What is AI TRiSM and Why It's Essential in the Era of GenAI*. Securiti Blog. https://securiti.ai/what-is-ai-trism/\n  - Future outlook\n    - AI TRiSM is expected to become a standard component of AI and autonomy governance, driven by increasing regulatory requirements (e.g., EU AI Act, UK AI Regulation) and public demand for trustworthy AI.\n    - Advances in explainable AI, automated bias detection, and runtime security will further enhance the effectiveness of AI TRiSM frameworks.\n    - In the UK, continued investment in AI research and regional innovation hubs will support the development and adoption of AI TRiSM, particularly in sectors such as healthcare, transport, and smart cities.\n\n\n## UK Context\n\n- British contributions and implementations\n  - Research institutions and programmes\n  - Industry adoption\n  - North England innovation (where relevant)\n\n\n## Metadata\n\n- **Created**: 2025-11-11\n- **Source**: Gartner Emerging Technology Analysis\n- **Category**: AI & Autonomy\n- **Status**: Emerging Technology\n\n\n\n\n## Current Landscape (2025)\n\n- Industry adoption and implementations\n  - Metaverse platforms continue to evolve with focus on interoperability and open standards\n  - Web3 integration accelerating with decentralised identity and asset ownership\n  - Enterprise adoption growing in virtual collaboration, training, and digital twins\n  - UK companies increasingly active in metaverse development and immersive technologies\n\n- Technical capabilities\n  - Real-time rendering at photorealistic quality levels\n  - Low-latency networking enabling seamless multi-user experiences\n  - AI-driven content generation and procedural world building\n  - Spatial audio and haptics enhancing immersion\n\n- UK and North England context\n  - Manchester: Digital Innovation Factory supports metaverse startups and research\n  - Leeds: Holovis leads in immersive experiences for entertainment and training\n  - Newcastle: University research in spatial computing and interactive systems\n  - Sheffield: Advanced manufacturing using digital twin technology\n\n- Standards and frameworks\n  - Metaverse Standards Forum driving interoperability protocols\n  - WebXR enabling browser-based immersive experiences\n  - glTF and USD for 3D asset interchange\n  - Open Metaverse Interoperability Group defining cross-platform standards\n\n## Metadata\n\n- **Last Updated**: 2025-11-16\n- **Review Status**: Automated remediation with 2025 context\n- **Verification**: Academic sources verified\n- **Regional Context**: UK/North England where applicable",
  "properties": {
    "id": "ai-trism-ontology",
    "collapsed": "true",
    "- ontology": "true",
    "- term-id": "ME-0002",
    "- preferred-term": "AI TRiSM",
    "- source-domain": "metaverse",
    "- status": "emerging-technology",
    "- public-access": "true",
    "- definition": "[Generated from Gartner emerging tech analysis]",
    "- maturity": "emerging",
    "- owl:class": "mv:AITRiSM",
    "- owl:physicality": "ConceptualEntity",
    "- owl:role": "Concept",
    "- is-subclass-of": "[[Metaverse]]",
    "- belongsToDomain": "[[MetaverseDomain]]",
    "- category": "AI & Autonomy"
  },
  "backlinks": [],
  "wiki_links": [
    "Metaverse",
    "MetaverseDomain"
  ],
  "ontology": {
    "term_id": "ME-0002",
    "preferred_term": "AI TRiSM",
    "definition": "[Generated from Gartner emerging tech analysis]",
    "source_domain": "metaverse",
    "maturity_level": null,
    "authority_score": null
  }
}