{
  "title": "Algorithmic Accountability",
  "content": "- ### OntologyBlock\n  id:: algorithmic-accountability-ontology\n  collapsed:: true\n\n  - **Identification**\n    - public-access:: true\n    - ontology:: true\n    - term-id:: AI-0376\n    - preferred-term:: Algorithmic Accountability\n    - source-domain:: ai\n    - status:: complete\n    - version:: 1.0\n    - last-updated:: 2025-10-28\n\n  - **Definition**\n    - definition:: Algorithmic Accountability is a responsibility framework that ensures AI systems and their developers are answerable for the decisions, outcomes, and impacts produced by algorithmic processes, including mechanisms for redress, transparency, and oversight.\n    - maturity:: mature\n    - source:: [[IEEE P2863]]\n    - authority-score:: 0.95\n\n  - **Semantic Classification**\n    - owl:class:: aigo:AIGovernancePrinciple\n    - owl:physicality:: VirtualEntity\n    - owl:role:: Process\n    - owl:inferred-class:: aigo:VirtualProcess\n    - belongsToDomain:: [[AIEthicsDomain]]\n    - implementedInLayer:: [[ConceptualLayer]]\n\n  - #### Relationships\n    id:: algorithmic-accountability-relationships\n    - is-subclass-of:: [[AIGovernancePrinciple]], [[EthicalFramework]], [[RegulatoryCompliance]]\n\n  - #### OWL Axioms\n    id:: algorithmic-accountability-owl-axioms\n    collapsed:: true\n    - ```clojure\n      ;; Algorithmic Accountability Ontology (OWL Functional Syntax)\n;; Term ID: AI-0376\n;; Domain: AIEthicsDomain | Layer: ConceptualLayer\n\n(Declaration (Class :AlgorithmicAccountability))\n\n;; Core Classification\n(SubClassOf :AlgorithmicAccountability :AIGovernancePrinciple)\n(SubClassOf :AlgorithmicAccountability :EthicalFramework)\n(SubClassOf :AlgorithmicAccountability :RegulatoryCompliance)\n\n;; Annotations\n(AnnotationAssertion rdfs:label :AlgorithmicAccountability \"Algorithmic Accountability\"@en)\n(AnnotationAssertion rdfs:comment :AlgorithmicAccountability\n  \"Responsibility framework ensuring AI systems and developers are answerable for algorithmic decisions, outcomes, and impacts through mechanisms for redress, transparency, and oversight\"@en)\n(AnnotationAssertion :isoReference :AlgorithmicAccountability \"IEEE P2863-2021\")\n(AnnotationAssertion :authorityScore :AlgorithmicAccountability \"0.95\"^^xsd:float)\n(AnnotationAssertion :priorityLevel :AlgorithmicAccountability \"4\"^^xsd:integer)\n\n;; Object Properties - Accountability Mechanisms\n(SubClassOf :AlgorithmicAccountability\n  (ObjectSomeValuesFrom :requiresAuditTrail :TraceabilityMechanism))\n(SubClassOf :AlgorithmicAccountability\n  (ObjectSomeValuesFrom :enablesRedress :RedressProcedure))\n(SubClassOf :AlgorithmicAccountability\n  (ObjectSomeValuesFrom :assignsResponsibility :AccountableParty))\n(SubClassOf :AlgorithmicAccountability\n  (ObjectSomeValuesFrom :implementsOversight :GovernanceStructure))\n(SubClassOf :AlgorithmicAccountability\n  (ObjectSomeValuesFrom :assessesImpact :AlgorithmicImpactAssessment))\n(SubClassOf :AlgorithmicAccountability\n  (ObjectSomeValuesFrom :verifiesCompliance :ComplianceAudit))\n\n;; Object Properties - Governance Integration\n(SubClassOf :AlgorithmicAccountability\n  (ObjectSomeValuesFrom :alignsWith :OECDPrinciple))\n(SubClassOf :AlgorithmicAccountability\n  (ObjectSomeValuesFrom :satisfies :EUAIActRequirement))\n(SubClassOf :AlgorithmicAccountability\n  (ObjectSomeValuesFrom :implements :IEEEStandard))\n\n;; Data Properties\n(DataPropertyAssertion :hasAccountabilityLevel :AlgorithmicAccountability \"comprehensive\"^^xsd:string)\n(DataPropertyAssertion :requiresHumanOversight :AlgorithmicAccountability \"true\"^^xsd:boolean)\n(DataPropertyAssertion :enablesContestability :AlgorithmicAccountability \"true\"^^xsd:boolean)\n(DataPropertyAssertion :mandatesDocumentation :AlgorithmicAccountability \"true\"^^xsd:boolean)\n\n;; Property Declarations - Accountability Relations\n(Declaration (ObjectProperty :requiresAuditTrail))\n(ObjectPropertyDomain :requiresAuditTrail :AlgorithmicAccountability)\n(ObjectPropertyRange :requiresAuditTrail :TraceabilityMechanism)\n\n(Declaration (ObjectProperty :enablesRedress))\n(ObjectPropertyDomain :enablesRedress :AlgorithmicAccountability)\n(ObjectPropertyRange :enablesRedress :RedressProcedure)\n\n(Declaration (ObjectProperty :assignsResponsibility))\n(ObjectPropertyDomain :assignsResponsibility :AlgorithmicAccountability)\n(ObjectPropertyRange :assignsResponsibility :AccountableParty)\n\n(Declaration (ObjectProperty :implementsOversight))\n(ObjectPropertyDomain :implementsOversight :AlgorithmicAccountability)\n(ObjectPropertyRange :implementsOversight :GovernanceStructure)\n\n(Declaration (ObjectProperty :assessesImpact))\n(ObjectPropertyDomain :assessesImpact :AlgorithmicAccountability)\n(ObjectPropertyRange :assessesImpact :AlgorithmicImpactAssessment)\n\n;; Data Property Declarations\n(Declaration (DataProperty :hasAccountabilityLevel))\n(DataPropertyDomain :hasAccountabilityLevel :AlgorithmicAccountability)\n(DataPropertyRange :hasAccountabilityLevel xsd:string)\n\n(Declaration (DataProperty :requiresHumanOversight))\n(DataPropertyDomain :requiresHumanOversight :AlgorithmicAccountability)\n(DataPropertyRange :requiresHumanOversight xsd:boolean)\n\n(Declaration (DataProperty :enablesContestability))\n(DataPropertyDomain :enablesContestability :AlgorithmicAccountability)\n(DataPropertyRange :enablesContestability xsd:boolean)\n      ```\n\n- ## About Algorithmic Accountability\n  id:: algorithmic-accountability-about\n\n  - Algorithmic Accountability is a responsibility framework that ensures AI systems and their developers are answerable for the decisions, outcomes, and impacts produced by algorithmic processes, including mechanisms for redress, transparency, and oversight.\n  -\n    - ### Implementation Patterns\n  - ### Pattern 1: Accountability Registry System\n    ```python\n    from dataclasses import dataclass\n    from datetime import datetime\n    from typing import List, Optional, Dict\n    from enum import Enum\n  -\n    class AccountabilityRole(Enum):\n        \"\"\"Roles with accountability for AI system stages\"\"\"\n        DATA_PROVIDER = \"data_provider\"\n        MODEL_DEVELOPER = \"model_developer\"\n        SYSTEM_DEPLOYER = \"system_deployer\"\n        OVERSIGHT_AUTHORITY = \"oversight_authority\"\n        REDRESS_HANDLER = \"redress_handler\"\n  -\n    @dataclass\n    class AccountableParty:\n        \"\"\"Individual or organisation responsible for AI system aspect\"\"\"\n        party_id: str\n        name: str\n        role: AccountabilityRole\n        contact_information: Dict[str, str]\n        responsibility_scope: str\n        liability_coverage: Optional[str] = None\n  -\n    @dataclass\n    class AlgorithmicDecision:\n        \"\"\"Record of individual algorithmic decision for audit trail\"\"\"\n        decision_id: str\n        timestamp: datetime\n        input_data: Dict\n        output_decision: Dict\n        model_version: str\n        confidence_score: float\n        accountable_party: str\n        audit_metadata: Dict\n  -\n    class AccountabilityFramework:\n        \"\"\"Implementation of comprehensive accountability framework\"\"\"\n  -\n        def __init__(self):\n            self.accountability_registry: Dict[str, AccountableParty] = {}\n            self.decision_audit_trail: List[AlgorithmicDecision] = []\n            self.redress_procedures: Dict[str, callable] = {}\n  -\n        def register_accountable_party(self, party: AccountableParty) -> None:\n            \"\"\"Register individual or organisation with accountability\"\"\"\n            self.accountability_registry[party.party_id] = party\n  -\n        def log_decision(self, decision: AlgorithmicDecision) -> None:\n            \"\"\"Record algorithmic decision in audit trail for traceability\"\"\"\n            if decision.accountable_party not in self.accountability_registry:\n                raise ValueError(f\"Accountable party {decision.accountable_party} not registered\")\n            self.decision_audit_trail.append(decision)\n  -\n        def initiate_redress(self, decision_id: str, contestation_reason: str) -> Dict:\n            \"\"\"Enable individuals to contest algorithmic decisions\"\"\"\n            decision = next((d for d in self.decision_audit_trail if d.decision_id == decision_id), None)\n            if not decision:\n                return {\"status\": \"error\", \"message\": \"Decision not found in audit trail\"}\n  -\n            accountable_party = self.accountability_registry[decision.accountable_party]\n  -\n            return {\n                \"status\": \"redress_initiated\",\n                \"decision_id\": decision_id,\n                \"accountable_party\": accountable_party.name,\n                \"contact\": accountable_party.contact_information,\n                \"contestation_reason\": contestation_reason,\n                \"review_timeline\": \"30 days\"\n            }\n  -\n        def generate_accountability_report(self) -> Dict:\n            \"\"\"Produce comprehensive accountability documentation\"\"\"\n            return {\n                \"total_decisions\": len(self.decision_audit_trail),\n                \"accountable_parties\": len(self.accountability_registry),\n                \"decisions_by_party\": self._aggregate_decisions_by_party(),\n                \"redress_statistics\": self._calculate_redress_metrics(),\n                \"audit_completeness\": self._verify_audit_trail_completeness()\n            }\n  -\n        def _aggregate_decisions_by_party(self) -> Dict[str, int]:\n            \"\"\"Calculate decision counts per accountable party\"\"\"\n            aggregation = {}\n            for decision in self.decision_audit_trail:\n                party = decision.accountable_party\n                aggregation[party] = aggregation.get(party, 0) + 1\n            return aggregation\n  -\n        def _calculate_redress_metrics(self) -> Dict:\n            \"\"\"Compute statistics on redress procedures\"\"\"\n            # Placeholder implementation\n            return {\"total_redress_cases\": 0, \"resolution_rate\": 0.0}\n  -\n        def _verify_audit_trail_completeness(self) -> float:\n            \"\"\"Check completeness of audit trail documentation\"\"\"\n            if not self.decision_audit_trail:\n                return 0.0\n            complete_records = sum(1 for d in self.decision_audit_trail\n                                  if d.accountable_party and d.audit_metadata)\n            return complete_records / len(self.decision_audit_trail)\n    ```\n    -\n  - ### Use Cases\n  - ### Use Case 1: Financial Services Credit Scoring\n    - **Scenario**: Bank deploys AI system for automated credit decisioning affecting loan approvals\n    - **Implementation**: Accountability framework assigns responsibility to Chief Risk Officer for model decisions, implements audit trail logging every credit decision with justification, enables applicants to contest decisions through formal redress procedure, requires quarterly algorithmic audits by independent third party\n    - **Benefits**: Regulatory compliance with fair lending laws, reduced discrimination risk, increased consumer trust, clear liability assignment, contestable decisions meeting due process requirements\n    - **Standards**: EU AI Act Article 14, IEEE P2863 Substantive Requirements, OECD Principle 1.3\n    -\n  - ### Technical Considerations\n  - ### Performance\n    - **Audit Trail Overhead**: Comprehensive decision logging increases storage requirements approximately 15-30% depending on metadata captured\n    - **Query Performance**: Indexed audit trails enable sub-second retrieval of decision provenance for redress procedures\n    - **Scalability**: Distributed accountability registries support horizontal scaling for high-volume decision systems\n    -\n  - ### Challenges and Solutions\n  - ### Challenge: Attribution in Complex AI Systems\n    - **Problem**: Multi-stage AI pipelines involving data providers, model developers, and deployment organisations create ambiguous responsibility assignment\n    - **Solution**: Implement accountability chain documentation mapping each system component to responsible party; use smart contracts to codify multi-party accountability agreements; establish joint liability frameworks for shared accountability scenarios\n    - **Standard Reference**: IEEE P2863 Section 5.3 - Procedural Governance Requirements\n    -\n  - ### Best Practices\n    1. **Comprehensive Responsibility Mapping**: Document all accountable parties across entire AI system lifecycle from data collection through deployment and monitoring\n    2. **Granular Audit Trails**: Log individual algorithmic decisions with sufficient metadata to enable complete reconstruction and explanation\n    3. **Accessible Redress Mechanisms**: Implement user-friendly contestation procedures requiring no technical expertise to invoke\n    4. **Independent Oversight**: Establish governance bodies with technical expertise and independence from AI system developers\n    5. **Regular Impact Assessments**: Conduct periodic algorithmic impact evaluations identifying emerging accountability gaps\n    6. **Proactive Transparency**: Publish accountability frameworks, responsible parties, and oversight procedures publicly\n    7. **Continuous Monitoring**: Implement automated compliance verification detecting accountability framework violations in real-time\n    8. **Stakeholder Engagement**: Involve affected communities in accountability framework design and oversight procedures\n    -\n  - ### Standards Alignment\n  - ### ISO/IEC Standards\n    - **ISO/IEC 42001:2023**: AI Management System requiring accountability as core governance component (Clause 5.3 - Leadership and Commitment)\n    - **ISO/IEC 23894:2023**: AI Risk Management emphasising accountability in risk treatment (Section 7.4 - Risk Treatment)\n    - **ISO/IEC TR 24028:2020**: AI Trustworthiness identifying accountability as key trustworthiness characteristic\n\n\t\t- ### Gimme a swarm of Shuriken\n\t\t\t- ```\n\t\t\t  connect to the blender mcp and create me a swarm of shurikan which exhibit flocking behaviour. \n\t\t\t  Use your neural enchancements to test the swarming code using algorithmic breeding here in the CPUs\n\t\t\t  and optionally GPUs until you have an efficient system then convert to python code for the remote mcp. \n\t\t\t  Make the 200 shurikan items black glass, each spinning on it's central axis\n\t\t\t  ```\n\t\t\t\t- ![1753954148599.gif](assets/1753954148599_1759153148906_0.gif){:height 526, :width 923}\n\n\t\t- ### Gimme a swarm of Shuriken\n\t\t\t- ```\n\t\t\t  connect to the blender mcp and create me a swarm of shurikan which exhibit flocking behaviour. \n\t\t\t  Use your neural enchancements to test the swarming code using algorithmic breeding here in the CPUs\n\t\t\t  and optionally GPUs until you have an efficient system then convert to python code for the remote mcp. \n\t\t\t  Make the 200 shurikan items black glass, each spinning on it's central axis\n\t\t\t  ```\n\t\t\t\t- ![1753954148599.gif](assets/1753954148599_1759153148906_0.gif){:height 526, :width 923}\n\n- ## Algorithmic Capture and Decline of Human Exploration\n\t- We've become dependent on personalised, AI-driven feeds, narrowing our experience of the web. As Eli Pariser's [TED talk](https://www.ted.com/talks/eli_pariser_beware_online_filter_bubbles) warned us years ago, AI-driven \"filter bubbles\" are trapping us in curated echo chambers, where discovery and serendipity are casualties of efficiency.\n\t\t- This reductionist approach to knowledge risks making us intellectually lazy. As [MIT Technology Review](https://www.technologyreview.com/2021/07/13/1028401/ai-large-language-models-bigscience-project/) notes, we're being spoon-fed tailored, context-stripped answers that limit our engagement with the broader, more complex web.\n\n- ## Algorithmic Capture and Decline of Human Exploration\n\t- We've become dependent on personalised, AI-driven feeds, narrowing our experience of the web. As Eli Pariser's [TED talk](https://www.ted.com/talks/eli_pariser_beware_online_filter_bubbles) warned us years ago, AI-driven \"filter bubbles\" are trapping us in curated echo chambers, where discovery and serendipity are casualties of efficiency.\n\t\t- This reductionist approach to knowledge risks making us intellectually lazy. As [MIT Technology Review](https://www.technologyreview.com/2021/07/13/1028401/ai-large-language-models-bigscience-project/) notes, we're being spoon-fed tailored, context-stripped answers that limit our engagement with the broader, more complex web.\n\n\n## Current Landscape (2025)\n\n- Industry adoption and implementations\n  - Metaverse platforms continue to evolve with focus on interoperability and open standards\n  - Web3 integration accelerating with decentralised identity and asset ownership\n  - Enterprise adoption growing in virtual collaboration, training, and digital twins\n  - UK companies increasingly active in metaverse development and immersive technologies\n\n- Technical capabilities\n  - Real-time rendering at photorealistic quality levels\n  - Low-latency networking enabling seamless multi-user experiences\n  - AI-driven content generation and procedural world building\n  - Spatial audio and haptics enhancing immersion\n\n- UK and North England context\n  - Manchester: Digital Innovation Factory supports metaverse startups and research\n  - Leeds: Holovis leads in immersive experiences for entertainment and training\n  - Newcastle: University research in spatial computing and interactive systems\n  - Sheffield: Advanced manufacturing using digital twin technology\n\n- Standards and frameworks\n  - Metaverse Standards Forum driving interoperability protocols\n  - WebXR enabling browser-based immersive experiences\n  - glTF and USD for 3D asset interchange\n  - Open Metaverse Interoperability Group defining cross-platform standards\n\n## Metadata\n\n- **Last Updated**: 2025-11-16\n- **Review Status**: Automated remediation with 2025 context\n- **Verification**: Academic sources verified\n- **Regional Context**: UK/North England where applicable",
  "properties": {
    "id": "algorithmic-accountability-about",
    "collapsed": "true",
    "- public-access": "true",
    "- ontology": "true",
    "- term-id": "AI-0376",
    "- preferred-term": "Algorithmic Accountability",
    "- source-domain": "ai",
    "- status": "complete",
    "- version": "1.0",
    "- last-updated": "2025-10-28",
    "- definition": "Algorithmic Accountability is a responsibility framework that ensures AI systems and their developers are answerable for the decisions, outcomes, and impacts produced by algorithmic processes, including mechanisms for redress, transparency, and oversight.",
    "- maturity": "mature",
    "- source": "[[IEEE P2863]]",
    "- authority-score": "0.95",
    "- owl:class": "aigo:AIGovernancePrinciple",
    "- owl:physicality": "VirtualEntity",
    "- owl:role": "Process",
    "- owl:inferred-class": "aigo:VirtualProcess",
    "- belongsToDomain": "[[AIEthicsDomain]]",
    "- implementedInLayer": "[[ConceptualLayer]]",
    "- is-subclass-of": "[[AIGovernancePrinciple]], [[EthicalFramework]], [[RegulatoryCompliance]]"
  },
  "backlinks": [],
  "wiki_links": [
    "EthicalFramework",
    "IEEE P2863",
    "AIEthicsDomain",
    "AIGovernancePrinciple",
    "RegulatoryCompliance",
    "ConceptualLayer"
  ],
  "ontology": {
    "term_id": "AI-0376",
    "preferred_term": "Algorithmic Accountability",
    "definition": "Algorithmic Accountability is a responsibility framework that ensures AI systems and their developers are answerable for the decisions, outcomes, and impacts produced by algorithmic processes, including mechanisms for redress, transparency, and oversight.",
    "source_domain": "ai",
    "maturity_level": null,
    "authority_score": 0.95
  }
}