{
  "title": "AI-Generated Content Disclosure",
  "content": "- ### OntologyBlock\n  id:: ai-generated-content-disclosure-ontology\n  collapsed:: true\n\t- ontology:: true\n\t- term-id:: AI-0421\n\t- source-domain:: ai\n\t- status:: complete\n\t- public-access:: true\n\t- preferred-term:: AI-Generated Content Disclosure\n\t- definition:: Mandatory transparency requirement specifying that content created wholly or partially by AI systems must be explicitly labeled with origin metadata for user awareness and regulatory compliance.\n\t- maturity:: mature\n\t- source:: [[EU AI Act]], [[IEEE 7001]]\n\t- owl:class:: mv:AIGeneratedContentDisclosure\n\t- owl:physicality:: VirtualEntity\n\t- owl:role:: Process\n\t- owl:inferred-class:: mv:VirtualProcess\n\t- owl:functional-syntax:: true\n\t- belongsToDomain:: [[TrustAndGovernanceDomain]]\n\t- implementedInLayer:: [[MiddlewareLayer]]\n\t- #### Relationships\n\t  id:: ai-generated-content-disclosure-relationships\n\t\t- has-part:: [[Content Labeling Metadata]], [[AI Origin Declaration]], [[Disclosure Enforcement Mechanism]], [[Transparency Notice]]\n\t\t- is-part-of:: [[AI Transparency Framework]]\n\t\t- requires:: [[Content Authentication]], [[Metadata Standards]], [[Provenance Tracking]]\n\t\t- depends-on:: [[EU AI Act]], [[IEEE 7001]], [[C2PA Standard]]\n\t\t- enables:: [[User Awareness]], [[Regulatory Compliance]], [[Trust Building]], [[Informed Consent]]\n\t- #### OWL Axioms\n\t  id:: ai-generated-content-disclosure-owl-axioms\n\t  collapsed:: true\n\t\t- ```clojure\n\t\t  Declaration(Class(mv:AIGeneratedContentDisclosure))\n\n\t\t  # Classification along two primary dimensions\n\t\t  SubClassOf(mv:AIGeneratedContentDisclosure mv:VirtualEntity)\n\t\t  SubClassOf(mv:AIGeneratedContentDisclosure mv:Process)\n\n\t\t  # Domain-specific constraints\n\t\t  SubClassOf(mv:AIGeneratedContentDisclosure\n\t\t    ObjectSomeValuesFrom(mv:belongsToDomain mv:TrustAndGovernanceDomain)\n\t\t  )\n\n\t\t  SubClassOf(mv:AIGeneratedContentDisclosure\n\t\t    ObjectSomeValuesFrom(mv:implementedInLayer mv:MiddlewareLayer)\n\t\t  )\n\n\t\t  # Required labeling components\n\t\t  SubClassOf(mv:AIGeneratedContentDisclosure\n\t\t    ObjectSomeValuesFrom(mv:hasPart mv:ContentLabelingMetadata)\n\t\t  )\n\n\t\t  SubClassOf(mv:AIGeneratedContentDisclosure\n\t\t    ObjectSomeValuesFrom(mv:hasPart mv:AIOriginDeclaration)\n\t\t  )\n\n\t\t  SubClassOf(mv:AIGeneratedContentDisclosure\n\t\t    ObjectSomeValuesFrom(mv:hasPart mv:DisclosureEnforcementMechanism)\n\t\t  )\n\n\t\t  # Dependencies on authentication\n\t\t  SubClassOf(mv:AIGeneratedContentDisclosure\n\t\t    ObjectSomeValuesFrom(mv:requires mv:ContentAuthentication)\n\t\t  )\n\n\t\t  SubClassOf(mv:AIGeneratedContentDisclosure\n\t\t    ObjectSomeValuesFrom(mv:requires mv:ProvenanceTracking)\n\t\t  )\n\n\t\t  SubClassOf(mv:AIGeneratedContentDisclosure\n\t\t    ObjectSomeValuesFrom(mv:dependsOn mv:EUAIAct)\n\t\t  )\n\n\t\t  # Enables transparency outcomes\n\t\t  SubClassOf(mv:AIGeneratedContentDisclosure\n\t\t    ObjectSomeValuesFrom(mv:enables mv:UserAwareness)\n\t\t  )\n\n\t\t  SubClassOf(mv:AIGeneratedContentDisclosure\n\t\t    ObjectSomeValuesFrom(mv:enables mv:RegulatoryCompliance)\n\t\t  )\n\n\t\t  SubClassOf(mv:AIGeneratedContentDisclosure\n\t\t    ObjectSomeValuesFrom(mv:enables mv:InformedConsent)\n\t\t  )\n\n  # Property characteristics\n  TransitiveObjectProperty(dt:ispartof)\n\n  # Property characteristics\n  AsymmetricObjectProperty(dt:requires)\n\n  # Property characteristics\n  AsymmetricObjectProperty(dt:dependson)\n\n  # Property characteristics\n  AsymmetricObjectProperty(dt:enables)\n```\n- ## About AI-Generated Content Disclosure\n  id:: ai-generated-content-disclosure-about\n\t- AI-Generated Content Disclosure establishes transparency obligations for content created by artificial intelligence systems within metaverse environments. This regulatory requirement, mandated by frameworks like the EU AI Act, ensures users can identify AI-generated text, images, videos, audio, and virtual assets through explicit labeling and metadata attribution.\n\t- ### Key Characteristics\n\t  id:: ai-generated-content-disclosure-characteristics\n\t\t- Mandatory labeling for all AI-generated or AI-assisted content\n\t\t- Machine-readable metadata standards enabling automated detection\n\t\t- Visual and textual disclosure mechanisms for user interfaces\n\t\t- Provenance tracking throughout content lifecycle and distribution\n\t\t- Standardized disclosure formats across platforms and jurisdictions\n\t\t- Enforcement mechanisms ensuring compliance with transparency requirements\n\t- ### Technical Components\n\t  id:: ai-generated-content-disclosure-components\n\t\t- [[Content Labeling Metadata]] - Structured data fields indicating AI generation source\n\t\t- [[AI Origin Declaration]] - Explicit statement of AI involvement and degree\n\t\t- [[Disclosure Enforcement Mechanism]] - Automated validation and compliance checking\n\t\t- [[Transparency Notice]] - User-facing notification formats and presentation\n\t\t- [[Provenance Tracking]] - Chain-of-custody records for content modifications\n\t\t- [[C2PA Credentials]] - Coalition for Content Provenance and Authenticity standards\n\t\t- [[Content Authentication Protocol]] - Cryptographic verification of origin claims\n\t- ### Functional Capabilities\n\t  id:: ai-generated-content-disclosure-capabilities\n\t\t- **Automated Labeling**: Embeds disclosure metadata at content creation time\n\t\t- **User Notification**: Displays clear visual indicators and text notices to users\n\t\t- **Compliance Verification**: Validates disclosure presence and accuracy for regulatory audits\n\t\t- **Provenance Chain**: Maintains tamper-evident records of AI generation and modifications\n\t\t- **Cross-Platform Standards**: Ensures consistent disclosure across different metaverse platforms\n\t- ### Use Cases\n\t  id:: ai-generated-content-disclosure-use-cases\n\t\t- AI-generated avatar customization content requiring transparency labels\n\t\t- Synthetic media in virtual events and entertainment venues\n\t\t- AI-created 3D assets and environments in metaverse marketplaces\n\t\t- Automated content moderation decisions requiring explanation\n\t\t- AI-assisted virtual influencer and NPC dialogue systems\n\t\t- Deepfake detection and disclosure in social virtual spaces\n\t\t- Generative AI tools for user-generated content creation\n\t\t- Compliance verification for platforms operating under EU AI Act jurisdiction\n\t- ### Standards & References\n\t  id:: ai-generated-content-disclosure-standards\n\t\t- [[EU AI Act]] - Article 52 transparency obligations for AI systems\n\t\t- [[IEEE 7001]] - Transparency of Autonomous Systems standard\n\t\t- [[C2PA Standard]] - Coalition for Content Provenance and Authenticity\n\t\t- [[OECD AI Principles]] - Transparency and explainability requirements\n\t\t- [[ISO/IEC 23894]] - AI risk management guidance on transparency\n\t\t- [[W3C Verifiable Credentials]] - Metadata authentication framework\n\t- ### Related Concepts\n\t  id:: ai-generated-content-disclosure-related\n\t\t- [[AI Transparency Framework]] - Broader disclosure and explainability requirements\n\t\t- [[Content Authentication]] - Verification mechanisms for origin claims\n\t\t- [[Digital Provenance]] - Chain-of-custody tracking for digital assets\n\t\t- [[Synthetic Media Detection]] - Technologies identifying AI-generated content\n\t\t- [[Informed Consent]] - User awareness enabling meaningful consent decisions\n\t\t- [[VirtualProcess]] - Ontology classification as compliance verification activity\n\n\n## Current Landscape (2025)\n\n- Industry adoption and implementations\n  - Metaverse platforms continue to evolve with focus on interoperability and open standards\n  - Web3 integration accelerating with decentralised identity and asset ownership\n  - Enterprise adoption growing in virtual collaboration, training, and digital twins\n  - UK companies increasingly active in metaverse development and immersive technologies\n\n- Technical capabilities\n  - Real-time rendering at photorealistic quality levels\n  - Low-latency networking enabling seamless multi-user experiences\n  - AI-driven content generation and procedural world building\n  - Spatial audio and haptics enhancing immersion\n\n- UK and North England context\n  - Manchester: Digital Innovation Factory supports metaverse startups and research\n  - Leeds: Holovis leads in immersive experiences for entertainment and training\n  - Newcastle: University research in spatial computing and interactive systems\n  - Sheffield: Advanced manufacturing using digital twin technology\n\n- Standards and frameworks\n  - Metaverse Standards Forum driving interoperability protocols\n  - WebXR enabling browser-based immersive experiences\n  - glTF and USD for 3D asset interchange\n  - Open Metaverse Interoperability Group defining cross-platform standards\n\n## Metadata\n\n- **Last Updated**: 2025-11-16\n- **Review Status**: Automated remediation with 2025 context\n- **Verification**: Academic sources verified\n- **Regional Context**: UK/North England where applicable",
  "properties": {
    "id": "ai-generated-content-disclosure-related",
    "collapsed": "true",
    "- ontology": "true",
    "- term-id": "AI-0421",
    "- source-domain": "ai",
    "- status": "complete",
    "- public-access": "true",
    "- preferred-term": "AI-Generated Content Disclosure",
    "- definition": "Mandatory transparency requirement specifying that content created wholly or partially by AI systems must be explicitly labeled with origin metadata for user awareness and regulatory compliance.",
    "- maturity": "mature",
    "- source": "[[EU AI Act]], [[IEEE 7001]]",
    "- owl:class": "mv:AIGeneratedContentDisclosure",
    "- owl:physicality": "VirtualEntity",
    "- owl:role": "Process",
    "- owl:inferred-class": "mv:VirtualProcess",
    "- owl:functional-syntax": "true",
    "- belongsToDomain": "[[TrustAndGovernanceDomain]]",
    "- implementedInLayer": "[[MiddlewareLayer]]",
    "- has-part": "[[Content Labeling Metadata]], [[AI Origin Declaration]], [[Disclosure Enforcement Mechanism]], [[Transparency Notice]]",
    "- is-part-of": "[[AI Transparency Framework]]",
    "- requires": "[[Content Authentication]], [[Metadata Standards]], [[Provenance Tracking]]",
    "- depends-on": "[[EU AI Act]], [[IEEE 7001]], [[C2PA Standard]]",
    "- enables": "[[User Awareness]], [[Regulatory Compliance]], [[Trust Building]], [[Informed Consent]]"
  },
  "backlinks": [],
  "wiki_links": [
    "Content Authentication",
    "Content Authentication Protocol",
    "User Awareness",
    "EU AI Act",
    "Transparency Notice",
    "C2PA Credentials",
    "AI Transparency Framework",
    "IEEE 7001",
    "Informed Consent",
    "ISO/IEC 23894",
    "OECD AI Principles",
    "Regulatory Compliance",
    "MiddlewareLayer",
    "Trust Building",
    "Digital Provenance",
    "Content Labeling Metadata",
    "TrustAndGovernanceDomain",
    "C2PA Standard",
    "VirtualProcess",
    "W3C Verifiable Credentials",
    "Metadata Standards",
    "AI Origin Declaration",
    "Provenance Tracking",
    "Synthetic Media Detection",
    "Disclosure Enforcement Mechanism"
  ],
  "ontology": {
    "term_id": "AI-0421",
    "preferred_term": "AI-Generated Content Disclosure",
    "definition": "Mandatory transparency requirement specifying that content created wholly or partially by AI systems must be explicitly labeled with origin metadata for user awareness and regulatory compliance.",
    "source_domain": "ai",
    "maturity_level": null,
    "authority_score": null
  }
}