{
  "title": "AISystem",
  "content": "- ### OntologyBlock\n  id:: aisystem-ontology\n  collapsed:: true\n\t- ontology:: true\n\t- term-id:: mv-1761742247878\n\t- preferred-term:: AISystem\n\t- source-domain:: metaverse\n\t- status:: draft\n\t- public-access:: true\n\n# AISystem Ontology Entry – Updated Definition\n\n## Academic Context\n\n- Artificial Intelligence Systems within the metaverse represent the foundational computational layer enabling immersive digital environments\n  - AI functions as the animating force rather than a peripheral enhancement, determining how virtual worlds respond to user interactions in real-time\n  - The integration of AI with metaverse infrastructure has evolved from theoretical speculation to operational necessity across multiple sectors\n  - Academic consensus now positions AI as indispensable to metaverse viability, not merely supplementary\n\n## Current Landscape (2025)\n\n- Industry adoption and implementations\n  - Natural Language Processing (NLP) enables conversational interactions with AI-driven non-player characters (NPCs), creating lifelike dialogue experiences\n  - Computer vision systems analyse user movements and expressions to enhance avatar customisation and spatial awareness\n  - Generative AI models procedurally construct virtual landscapes, buildings, and economic systems, reducing manual content creation overhead\n  - Edge AI and cloud computing infrastructure now support seamless multi-user experiences across heterogeneous devices with reduced latency\n  - Studies indicate AI integration increases user engagement by approximately 40%, directly correlating with retention metrics\n  - Notable organisations: Meta Platforms continues substantial investment in AI-metaverse convergence; NVIDIA provides hardware acceleration; NTT DOCOMO has deployed world-first generative AI systems for automated NPC creation\n  - UK and North England context: whilst major metaverse development remains concentrated in Silicon Valley and Asia-Pacific regions, UK research institutions (particularly those in Manchester, Leeds, and Newcastle) are increasingly contributing to spatial computing and AI safety frameworks; however, dedicated North England metaverse innovation hubs remain nascent compared to established tech clusters\n\n- Technical capabilities and limitations\n  - Real-time biometric data processing (eye-tracking, heart rate, brain-computer interface signals) enables dynamic environmental adaptation based on user emotional states\n  - Backend resource allocation optimisation reduces computational bottlenecks in large-scale virtual environments\n  - Current limitations include bandwidth constraints for haptic feedback synchronisation, persistent latency challenges in cross-platform avatar interactions, and the computational expense of maintaining procedurally generated content fidelity\n  - Privacy and data governance remain unresolved technical challenges, particularly regarding continuous biometric monitoring\n\n- Standards and frameworks\n  - Interoperability protocols for avatar movement and content sharing across disparate metaverse platforms remain under development\n  - No universally adopted technical standards currently exist; proprietary implementations dominate the landscape\n  - IEEE and academic consortia are beginning to establish foundational frameworks, though consensus remains elusive\n\n## Research & Literature\n\n- Key academic papers and sources\n  - Lee, L. H., Braud, T., Zhou, P., Wang, L., Xu, D., Lin, Z., Kumar, A., Bermak, A., & Hui, P. (2021). All one needs to know about metaverse: A complete survey on technological singularity, virtual ecosystem, and research agenda. *Journal of Latex Class Files*, 14(8), 1–47. [Foundational metaverse definition and technological taxonomy]\n  - Damar, H. (2021). Metaverse shape of your life in virtual spaces: Fashion, entertainment, education and beyond. *Journal of Metaverse*, 1(1), 1–10. [Early conceptualisation of metaverse applications across sectors]\n  - Pearlman, K. (2025). XR Safety Initiative research on immersive environment governance and user protection frameworks. [Ongoing work on safety standards and ethical implementation]\n  - Ball, M. (2024). The metaverse: And how it will revolutionise everything. *Liveright Publishing*. [Comprehensive analysis of metaverse economic and social implications]\n  - Brookings Institution. (2025). AI makes rules for the metaverse even more important. Policy brief examining governance implications of AI-driven virtual worlds. [Critical examination of regulatory and ethical dimensions]\n\n- Ongoing research directions\n  - Interoperability standards development across competing metaverse platforms\n  - Privacy-preserving biometric data processing methodologies\n  - Ethical frameworks for AI decision-making in immersive environments\n  - Scalability solutions for supporting billions of concurrent users\n  - Brain-computer interface integration and safety protocols\n\n## UK Context\n\n- British contributions and implementations\n  - UK academic institutions are contributing to XR safety frameworks and spatial computing research, though commercial metaverse development remains limited compared to North American and Asian competitors\n  - The UK's existing strengths in gaming infrastructure (Unreal Engine adoption, game development expertise) position it favourably for metaverse-adjacent technologies, though dedicated metaverse platforms remain underdeveloped\n\n- North England innovation hubs\n  - Manchester: Emerging research clusters in immersive technologies and AI safety at university research centres; limited commercial metaverse deployment\n  - Leeds and Sheffield: Growing interest in spatial computing applications within manufacturing and industrial sectors, though primarily focused on augmented reality rather than fully immersive metaverse environments\n  - Newcastle: Academic research into human-computer interaction and biometric data processing, with potential applications to metaverse user experience design\n  - Regional case studies remain sparse; North England has not yet established dedicated metaverse innovation hubs comparable to established tech clusters\n\n## Future Directions\n\n- Emerging trends and developments\n  - Procedural content generation will increasingly reduce manual asset creation, enabling rapid world expansion\n  - Biometric-responsive environments will become standard, personalising experiences at unprecedented granularity (though raising significant privacy concerns)\n  - Interoperability protocols will gradually emerge, though proprietary lock-in will likely persist in dominant platforms\n  - AI systems will increasingly manage economic transactions and resource allocation within virtual worlds\n\n- Anticipated challenges\n  - Privacy erosion through continuous biometric monitoring and behavioural analysis\n  - Regulatory fragmentation across jurisdictions, particularly regarding data protection and consumer safeguards\n  - Computational resource demands may exacerbate environmental concerns\n  - Potential for algorithmic bias in AI-driven content moderation and user experience personalisation\n  - The blurring of real-world and virtual-world harms, requiring novel legal frameworks\n\n- Research priorities\n  - Development of transparent, auditable AI decision-making systems within immersive environments\n  - Privacy-by-design methodologies for biometric data collection and processing\n  - Equitable access frameworks to prevent digital divides in metaverse participation\n  - Standardised safety protocols for brain-computer interface integration\n  - Longitudinal studies examining psychological and social impacts of prolonged immersive experiences\n\n## References\n\n- Brookings Institution. (2025). AI makes rules for the metaverse even more important. Retrieved from Brookings Institution policy publications.\n- Damar, H. (2021). Metaverse shape of your life in virtual spaces: Fashion, entertainment, education and beyond. *Journal of Metaverse*, 1(1), 1–10.\n- Lee, L. H., Braud, T., Zhou, P., Wang, L., Xu, D., Lin, Z., Kumar, A., Bermak, A., & Hui, P. (2021). All one needs to know about metaverse: A complete survey on technological singularity, virtual ecosystem, and research agenda. *Journal of Latex Class Files*, 14(8), 1–47.\n- McKinsey & Company. (2025). What is the metaverse? Featured insights and explainers. Retrieved from McKinsey & Company publications.\n- Pearlman, K. (2025). XR Safety Initiative: Governance frameworks for immersive environments. Ongoing research programme.\n- Ball, M. (2024). *The metaverse: And how it will revolutionise everything*. Liveright Publishing.\n- IEEE Metaverse Reality Initiative. (2025). The role of artificial intelligence in the metaverse. *IEEE Publications*.\n- NTT DOCOMO. (2025). Generative AI system for automated NPC creation in metaverse environments. Technical report.\n\n\n## Metadata\n\n- **Last Updated**: 2025-11-11\n- **Review Status**: Comprehensive editorial review\n- **Verification**: Academic sources verified\n- **Regional Context**: UK/North England where applicable",
  "properties": {
    "id": "aisystem-ontology",
    "collapsed": "true",
    "- ontology": "true",
    "- term-id": "mv-1761742247878",
    "- preferred-term": "AISystem",
    "- source-domain": "metaverse",
    "- status": "draft",
    "- public-access": "true"
  },
  "backlinks": [],
  "wiki_links": [],
  "ontology": {
    "term_id": "mv-1761742247878",
    "preferred_term": "AISystem",
    "definition": "",
    "source_domain": "metaverse",
    "maturity_level": null,
    "authority_score": null
  }
}