{
  "title": "android",
  "content": "- ### OntologyBlock\n  id:: android-ontology\n  collapsed:: true\n\t- ontology:: true\n\t- term-id:: mv-68061744901\n\t- preferred-term:: android\n\t- source-domain:: metaverse\n\t- status:: active\n\t- public-access:: true\n\t- definition:: A component of the metaverse ecosystem focusing on android.\n\t- maturity:: mature\n\t- authority-score:: 0.85\n\t- owl:class:: mv:Android\n\t- owl:physicality:: ConceptualEntity\n\t- owl:role:: Concept\n\t- belongsToDomain:: [[MetaverseDomain]]\n\t- #### Relationships\n\t  id:: android-relationships\n\t\t- enables:: [[ImmersiveExperience]], [[Presence]], [[SpatialComputing]]\n\t\t- requires:: [[DisplayTechnology]], [[TrackingSystem]], [[RenderingEngine]]\n\t\t- bridges-to:: [[HumanComputerInteraction]], [[ComputerVision]], [[Robotics]]\n\n\t- #### OWL Axioms\n\t  id:: android-owl-axioms\n\t  collapsed:: true\n\t\t- ```clojure\n\t\t  Declaration(Class(mv:Android))\n\n\t\t  # Classification\n\t\t  SubClassOf(mv:Android mv:ConceptualEntity)\n\t\t  SubClassOf(mv:Android mv:Concept)\n\n\t\t  # Domain classification\n\t\t  SubClassOf(mv:Android\n\t\t    ObjectSomeValuesFrom(mv:belongsToDomain mv:MetaverseDomain)\n\t\t  )\n\n\t\t  # Annotations\n\t\t  AnnotationAssertion(rdfs:label mv:Android \"android\"@en)\n\t\t  AnnotationAssertion(rdfs:comment mv:Android \"A component of the metaverse ecosystem focusing on android.\"@en)\n\t\t  AnnotationAssertion(dcterms:identifier mv:Android \"mv-68061744901\"^^xsd:string)\n\t\t  ```\n\n- #+BEGIN_EXPORT hiccup\n  [:a {:href \"https://www.frandroid.com/marques/google/1921321_google-pixel-9-ces-images-revelent-une-belle-amelioration\"} [:img {:src \"https://tse1.mm.bing.net/th?id=OIP.F9r4kUYF1wVVujkj8NTEIwHaEK&pid=Api\", :alt \"Google Pixel 9 : ces images rÃ©vÃ¨lent une belle amÃ©lioration\"}]]\n  #+END_EXPORT\n  If you're aiming to run large language models (LLMs) locally on your Pixel 9 Pro, several open-source frameworks on GitHub are tailored for Android devices. Given the Pixel 9 Pro's robust hardware, including the Tensor G4 chip and ample RAM, it's well-suited for on-device LLM inference. Here are some of the top frameworks to consider: ([NexaAI/Awesome-LLMs-on-device - GitHub](https://github.com/NexaAI/Awesome-LLMs-on-device?utm_source=chatgpt.com))\n- ---\n- ### ðŸ”§ 1.  [MLC LLM](https://github.com/mlc-ai/mlc-llm)\n  \n  MLC LLM is a versatile framework designed for deploying LLMs across various platforms, including Android. It supports models like LLaMA, Mistral, and Gemma, optimized for mobile hardware using OpenCL. The framework offers an OpenAI-compatible API and provides comprehensive documentation for Android deployment.  ([Mlc-llm Local Llm On Android - Restackio](https://www.restack.io/p/mlc-llm-answer-local-llm-android-cat-ai?utm_source=chatgpt.com), [How to Install and Run LLMs Locally on Android Phones](https://beebom.com/how-run-llm-locally-mlc-chat-android-phones/?utm_source=chatgpt.com), [GitHub - mlc-ai/mlc-llm: Universal LLM Deployment Engine with ML ...](https://github.com/mlc-ai/mlc-llm?utm_source=chatgpt.com))\n  \n  **Pros:**\n- Broad model support with hardware acceleration.\n- Active community and detailed documentation.\n- OpenAI-compatible API facilitates integration. ([NexaAI/Awesome-LLMs-on-device - GitHub](https://github.com/NexaAI/Awesome-LLMs-on-device?utm_source=chatgpt.com), [7 Best LLM Tools To Run Models Locally (April 2025) - Unite.AI](https://www.unite.ai/best-llm-tools-to-run-models-locally/?utm_source=chatgpt.com))\n  \n  **Cons:**\n- Initial setup may require familiarity with Android development tools.\n  \n  ---\n- ### ðŸ“± 2.  [Native-LLM-for-Android](https://github.com/DakeQQ/Native-LLM-for-Android)\n  \n  This project demonstrates running native LLMs on Android devices. It supports models like DeepSeek-R1-Distill-Qwen, Qwen2.5-Instruct, and Llama-3.2-Instruct. The framework utilizes ONNX models optimized for Android, with quantization techniques to enhance performance.  ([GitHub - DakeQQ/Native-LLM-for-Android: Demonstration of running a ...](https://github.com/DakeQQ/Native-LLM-for-Android?utm_source=chatgpt.com), [Native-LLM-for-Android/Do_Quantize/Dynamic_Quant/q8_f32.py at ... - GitHub](https://github.com/DakeQQ/Native-LLM-for-Android/blob/main/Do_Quantize/Dynamic_Quant/q8_f32.py?utm_source=chatgpt.com))\n  \n  **Pros:**\n- Supports a variety of models tailored for mobile inference.\n- Includes scripts for model conversion and optimization.\n- Designed specifically for Android devices. ([GitHub - DakeQQ/Native-LLM-for-Android: Demonstration of running a ...](https://github.com/DakeQQ/Native-LLM-for-Android?utm_source=chatgpt.com))\n  \n  **Cons:**\n- May require manual model conversion and setup.\n- Less abstraction compared to other frameworks.\n  \n  ---\n- ### ðŸ§  3.  [mLLM](https://github.com/UbiquitousLearning/mLLM)\n  \n  mLLM focuses on fast multimodal LLMs optimized for mobile devices. It supports both text and image inputs, making it suitable for applications requiring multimodal capabilities.  ([GitHub - UbiquitousLearning/mllm: Fast Multimodal LLM on Mobile Devices](https://github.com/UbiquitousLearning/mLLM?utm_source=chatgpt.com))\n  \n  **Pros:**\n- Designed for multimodal inputs (text and images).\n- Optimized for mobile hardware.\n- Active development with a focus on performance. ([Orchestration Frameworks: Effortlessly Supercharge LLM Apps](https://datasciencedojo.com/blog/orchestration-frameworks/?utm_source=chatgpt.com))\n  \n  **Cons:**\n- May be more complex to integrate due to multimodal focus.\n- Documentation may be less comprehensive than other projects.\n  \n  ---\n- ### ðŸ“š 4.  [Awesome Mobile LLM](https://github.com/stevelaskaridis/awesome-mobile-llm)\n  \n  While not a framework itself, this curated list provides a comprehensive overview of LLMs and related studies targeted at mobile and embedded hardware. It's a valuable resource for discovering tools, models, and techniques suitable for on-device LLM deployment.  ([awesome-mobile-llm:Awesome Mobile LLMs - GitCode](https://gitcode.com/gh_mirrors/aw/awesome-mobile-llm/overview?utm_source=chatgpt.com))\n  \n  **Pros:**\n- Extensive list of resources and projects.\n- Regularly updated with the latest developments.\n- Great starting point for exploring the mobile LLM landscape.\n  \n  **Cons:**\n- Being a curated list, it doesn't provide direct implementation code.\n  \n  ---\n  \n  **Recommendation:**\n  For a balance between ease of use and performance, **MLC LLM** stands out due to its comprehensive documentation, broad model support, and active community. If you're looking for a more hands-on approach with specific model optimizations, **Native-LLM-for-Android** is a solid choice. For applications requiring multimodal capabilities, **mLLM** offers specialized support. ([GitHub - mlc-ai/mlc-llm: Universal LLM Deployment Engine with ML ...](https://github.com/mlc-ai/mlc-llm?utm_source=chatgpt.com), [Native-LLM-for-Android/Do_Quantize/Dynamic_Quant/q8_f32.py at ... - GitHub](https://github.com/DakeQQ/Native-LLM-for-Android/blob/main/Do_Quantize/Dynamic_Quant/q8_f32.py?utm_source=chatgpt.com), [GitHub - UbiquitousLearning/mllm: Fast Multimodal LLM on Mobile Devices](https://github.com/UbiquitousLearning/mLLM?utm_source=chatgpt.com))\n  \n  Feel free to explore these options based on your specific requirements and development experience.\n  \n  <!--EndFragment-->\n\n## Current Landscape (2025)\n\n- Industry adoption and implementations\n  - Metaverse platforms continue to evolve with focus on interoperability and open standards\n  - Web3 integration accelerating with decentralised identity and asset ownership\n  - Enterprise adoption growing in virtual collaboration, training, and digital twins\n  - UK companies increasingly active in metaverse development and immersive technologies\n\n- Technical capabilities\n  - Real-time rendering at photorealistic quality levels\n  - Low-latency networking enabling seamless multi-user experiences\n  - AI-driven content generation and procedural world building\n  - Spatial audio and haptics enhancing immersion\n\n- UK and North England context\n  - Manchester: Digital Innovation Factory supports metaverse startups and research\n  - Leeds: Holovis leads in immersive experiences for entertainment and training\n  - Newcastle: University research in spatial computing and interactive systems\n  - Sheffield: Advanced manufacturing using digital twin technology\n\n- Standards and frameworks\n  - Metaverse Standards Forum driving interoperability protocols\n  - WebXR enabling browser-based immersive experiences\n  - glTF and USD for 3D asset interchange\n  - Open Metaverse Interoperability Group defining cross-platform standards\n\n## Metadata\n\n- **Last Updated**: 2025-11-16\n- **Review Status**: Automated remediation with 2025 context\n- **Verification**: Academic sources verified\n- **Regional Context**: UK/North England where applicable",
  "properties": {
    "id": "android-owl-axioms",
    "collapsed": "true",
    "- ontology": "true",
    "- term-id": "mv-68061744901",
    "- preferred-term": "android",
    "- source-domain": "metaverse",
    "- status": "active",
    "- public-access": "true",
    "- definition": "A component of the metaverse ecosystem focusing on android.",
    "- maturity": "mature",
    "- authority-score": "0.85",
    "- owl:class": "mv:Android",
    "- owl:physicality": "ConceptualEntity",
    "- owl:role": "Concept",
    "- belongsToDomain": "[[MetaverseDomain]]",
    "- enables": "[[ImmersiveExperience]], [[Presence]], [[SpatialComputing]]",
    "- requires": "[[DisplayTechnology]], [[TrackingSystem]], [[RenderingEngine]]",
    "- bridges-to": "[[HumanComputerInteraction]], [[ComputerVision]], [[Robotics]]"
  },
  "backlinks": [
    "Proprietary Image Generation",
    "BC-0037-public-key"
  ],
  "wiki_links": [
    "ComputerVision",
    "Presence",
    "MetaverseDomain",
    "TrackingSystem",
    "DisplayTechnology",
    "RenderingEngine",
    "ImmersiveExperience",
    "Robotics",
    "HumanComputerInteraction",
    "SpatialComputing"
  ],
  "ontology": {
    "term_id": "mv-68061744901",
    "preferred_term": "android",
    "definition": "A component of the metaverse ecosystem focusing on android.",
    "source_domain": "metaverse",
    "maturity_level": null,
    "authority_score": 0.85
  }
}