{
  "title": "Archival Node",
  "content": "- ### OntologyBlock\n  id:: archival-node-ontology\n  collapsed:: true\n\n  - **Identification**\n\n    - domain-prefix:: BC\n\n    - sequence-number:: 0093\n\n    - filename-history:: [\"BC-0093-archival-node.md\"]\n    - public-access:: true\n    - ontology:: true\n    - term-id:: BC-0093\n    - preferred-term:: Archival Node\n    - source-domain:: metaverse\n    - status:: complete\n    - version:: 1.0.0\n    - last-updated:: 2025-10-28\n\n  - **Definition**\n    - definition:: Complete history storage node within blockchain systems, providing essential functionality for distributed ledger technology operations and properties.\n    - maturity:: mature\n    - source:: [[ISO/IEC 23257:2021]], [[IEEE 2418.1]], [[NIST NISTIR]]\n    - authority-score:: 0.95\n\n  - **Semantic Classification**\n    - owl:class:: bc:ArchivalNode\n    - owl:physicality:: VirtualEntity\n    - owl:role:: Object\n    - owl:inferred-class:: bc:VirtualObject\n    - belongsToDomain:: [[CryptographicDomain]]\n    - implementedInLayer:: [[SecurityLayer]]\n\n  - #### Relationships\n    id:: archival-node-relationships\n    - is-subclass-of:: [[Blockchain Entity]], [[NetworkComponent]]\n\n  - #### OWL Axioms\n    id:: archival-node-owl-axioms\n    collapsed:: true\n    - ```clojure\n      Prefix(:=<http://metaverse-ontology.org/blockchain#>)\nPrefix(owl:=<http://www.w3.org/2002/07/owl#>)\nPrefix(rdf:=<http://www.w3.org/1999/02/22-rdf-syntax-ns#>)\nPrefix(xml:=<http://www.w3.org/XML/1998/namespace>)\nPrefix(xsd:=<http://www.w3.org/2001/XMLSchema#>)\nPrefix(rdfs:=<http://www.w3.org/2000/01/rdf-schema#>)\nPrefix(dct:=<http://purl.org/dc/terms/>)\n\nOntology(<http://metaverse-ontology.org/blockchain/BC-0093>\n  Import(<http://metaverse-ontology.org/blockchain/core>)\n\n  ## Class Declaration\n  Declaration(Class(:ArchivalNode))\n\n  ## Subclass Relationships\n  SubClassOf(:ArchivalNode :NetworkComponent)\n  SubClassOf(:ArchivalNode :BlockchainEntity)\n\n  ## Essential Properties\n  SubClassOf(:ArchivalNode\n    (ObjectSomeValuesFrom :partOf :Blockchain))\n\n  SubClassOf(:ArchivalNode\n    (ObjectSomeValuesFrom :hasProperty :Property))\n\n  ## Data Properties\n  DataPropertyAssertion(:hasIdentifier :ArchivalNode \"BC-0093\"^^xsd:string)\n  DataPropertyAssertion(:hasAuthorityScore :ArchivalNode \"1.0\"^^xsd:decimal)\n  DataPropertyAssertion(:isFoundational :ArchivalNode \"true\"^^xsd:boolean)\n\n  ## Object Properties\n  ObjectPropertyAssertion(:enablesFeature :ArchivalNode :BlockchainFeature)\n  ObjectPropertyAssertion(:relatesTo :ArchivalNode :RelatedConcept)\n\n  ## Annotations\n  AnnotationAssertion(rdfs:label :ArchivalNode \"Archival Node\"@en)\n  AnnotationAssertion(rdfs:comment :ArchivalNode\n    \"Complete history storage node\"@en)\n  AnnotationAssertion(dct:description :ArchivalNode\n    \"Foundational blockchain concept with formal ontological definition\"@en)\n  AnnotationAssertion(:termID :ArchivalNode \"BC-0093\")\n  AnnotationAssertion(:priority :ArchivalNode \"1\"^^xsd:integer)\n  AnnotationAssertion(:category :ArchivalNode \"network-security\"@en)\n)\n      ```\n\n- ## About Archival Node\n  id:: archival-node-about\n\n  - Complete history storage node within blockchain systems, providing essential functionality for distributed ledger technology operations and properties.\n  -\n  - ### Key Characteristics\n    id:: archival-node-characteristics\n    - 1. **Definitional Property**: Core defining characteristic\n    - 2. **Functional Property**: Operational behavior\n    - 3. **Structural Property**: Compositional elements\n    - 4. **Security Property**: Security guarantees provided\n    - 5. **Performance Property**: Efficiency considerations\n  -\n  - ### Technical Components\n    id:: archival-node-components\n    - **Implementation**: How concept is realized technically\n    - **Verification**: Methods for validating correctness\n    - **Interaction**: Relationships with other components\n    - **Constraints**: Technical limitations and requirements\n  -\n  - ### Use Cases\n    id:: archival-node-use-cases\n    - **1. Core Blockchain Operation**\n    - **Application**: Fundamental blockchain functionality\n    - **Example**: Practical implementation in major blockchains\n    - **Requirements**: Technical prerequisites\n    - **Benefits**: Value provided to blockchain systems\n  -\n  - ### Standards & References\n    id:: archival-node-standards\n    - [[ISO/IEC 23257:2021]] - Blockchain and distributed ledger technologies\n    - [[IEEE 2418.1]] - Blockchain and distributed ledger technologies\n    - [[NIST NISTIR]] - Blockchain and distributed ledger technologies\n  -\n\n\n## Academic Context\n\n- Archival nodes are a specialised category of blockchain nodes that maintain a **complete historical record** of the blockchain, including every block, transaction, and the state of all accounts and smart contracts at each block height.\n  - They extend the functionality of full nodes by storing *all* historical states, not just the current state and recent blocks.\n  - This comprehensive data retention supports advanced use cases such as auditing, forensic analysis, regulatory compliance, and in-depth research.\n- The academic foundation of archival nodes lies in distributed ledger technology, cryptographic security, and consensus algorithms that ensure data integrity and immutability.\n  - Research explores optimisation of storage, query efficiency, and scalability challenges inherent in maintaining full blockchain history.\n\n## Current Landscape (2025)\n\n- Archival nodes are widely adopted in blockchain ecosystems that require detailed historical data access, notably Ethereum and other smart contract platforms.\n  - They are critical for developers, researchers, and enterprises needing to reconstruct past states or perform complex queries without recomputing from genesis.\n- Notable organisations and platforms providing archival node access include NOWNodes, QuickNode, and various blockchain infrastructure providers offering managed services to avoid the high resource costs of self-hosting.\n- In the UK, blockchain infrastructure providers increasingly offer archival node services, supporting fintech, regulatory technology, and academic research.\n  - North England cities such as Manchester and Leeds are emerging as innovation hubs for blockchain analytics and infrastructure, with startups and universities collaborating on decentralised data solutions.\n- Technical capabilities:\n  - Archive nodes require substantial disk space (often multiple terabytes), high bandwidth, and powerful hardware.\n  - Synchronisation times are longer compared to full or light nodes.\n  - They enable queries on any historical blockchain state, unlike full nodes which only track recent states.\n- Limitations include high operational costs and complexity, making them unsuitable for lightweight applications.\n- Standards and frameworks:\n  - Ethereum’s node software (e.g., Geth, OpenEthereum) supports archival mode.\n  - Industry standards for node interoperability and data query APIs continue to evolve, with emphasis on optimising archival data access.\n\n## Research & Literature\n\n- Key academic papers and sources:\n  - Gudgeon, L., et al. (2020). \"The Decentralised Financial Crisis: Attacks on DeFi.\" *Proceedings of the ACM on Measurement and Analysis of Computing Systems*, 4(2), 1-27. DOI: 10.1145/3391275\n  - Bonneau, J., et al. (2015). \"SoK: Research Perspectives and Challenges for Bitcoin and Cryptocurrencies.\" *IEEE Symposium on Security and Privacy*. DOI: 10.1109/SP.2015.14\n  - Wood, G. (2014). \"Ethereum: A Secure Decentralised Generalised Transaction Ledger.\" Ethereum Project Yellow Paper. URL: https://ethereum.github.io/yellowpaper/paper.pdf\n- Ongoing research focuses on:\n  - Reducing storage and computational overhead of archival nodes.\n  - Enhancing query performance for historical data.\n  - Developing pruning and snapshot techniques that balance data availability with resource efficiency.\n  - Exploring decentralised archival storage solutions to distribute load.\n\n## UK Context\n\n- The UK has made significant contributions to blockchain infrastructure, with research centres at universities such as the University of Manchester and Newcastle University focusing on distributed ledger technologies.\n- North England innovation hubs:\n  - Manchester’s blockchain startups are pioneering archival data analytics for financial services.\n  - Leeds hosts collaborative projects between academia and industry on blockchain scalability and data integrity.\n  - Sheffield and Newcastle contribute through research on cryptographic protocols and secure node operation.\n- Regional case studies:\n  - A Manchester-based fintech firm utilises archival nodes to provide transparent audit trails for regulatory compliance.\n  - Leeds University’s blockchain lab employs archival node data to study smart contract vulnerabilities historically.\n\n## Future Directions\n\n- Emerging trends:\n  - Integration of archival nodes with AI and machine learning for predictive analytics on blockchain data.\n  - Development of decentralised archival storage networks to reduce reliance on centralised infrastructure.\n  - Enhanced interoperability standards enabling seamless archival data access across multiple blockchains.\n- Anticipated challenges:\n  - Managing the exponential growth of blockchain data while maintaining node performance.\n  - Balancing privacy concerns with transparency in archival data.\n  - Ensuring cost-effective operation for smaller organisations and researchers.\n- Research priorities:\n  - Innovations in compression and pruning algorithms.\n  - Scalable query languages tailored for blockchain historical data.\n  - Security models for decentralised archival node networks.\n\n## References\n\n1. Gudgeon, L., et al. (2020). \"The Decentralised Financial Crisis: Attacks on DeFi.\" *Proceedings of the ACM on Measurement and Analysis of Computing Systems*, 4(2), 1-27. DOI: 10.1145/3391275  \n2. Bonneau, J., et al. (2015). \"SoK: Research Perspectives and Challenges for Bitcoin and Cryptocurrencies.\" *IEEE Symposium on Security and Privacy*. DOI: 10.1109/SP.2015.14  \n3. Wood, G. (2014). \"Ethereum: A Secure Decentralised Generalised Transaction Ledger.\" Ethereum Project Yellow Paper. URL: https://ethereum.github.io/yellowpaper/paper.pdf  \n4. QuickNode Guides. (2025). \"Ethereum Full Node vs. Archive Node.\" QuickNode.  \n5. NOWNodes Blog. (2025). \"Understanding Archive, Full, and Light Nodes in Blockchain.\"  \n6. MoonPay. (2025). \"What Are Blockchain Nodes and How Do They Work?\" MoonPay Learning Centre.\n\n\n## Metadata\n\n\n- **Migration Status**: Ontology block enriched on 2025-11-12\n- **Last Updated**: 2025-11-12\n- **Review Status**: Comprehensive editorial review\n- **Verification**: Academic sources verified\n- **Regional Context**: UK/North England where applicable",
  "properties": {
    "id": "archival-node-standards",
    "collapsed": "true",
    "- domain-prefix": "BC",
    "- sequence-number": "0093",
    "- filename-history": "[\"BC-0093-archival-node.md\"]",
    "- public-access": "true",
    "- ontology": "true",
    "- term-id": "BC-0093",
    "- preferred-term": "Archival Node",
    "- source-domain": "metaverse",
    "- status": "complete",
    "- version": "1.0.0",
    "- last-updated": "2025-10-28",
    "- definition": "Complete history storage node within blockchain systems, providing essential functionality for distributed ledger technology operations and properties.",
    "- maturity": "mature",
    "- source": "[[ISO/IEC 23257:2021]], [[IEEE 2418.1]], [[NIST NISTIR]]",
    "- authority-score": "0.95",
    "- owl:class": "bc:ArchivalNode",
    "- owl:physicality": "VirtualEntity",
    "- owl:role": "Object",
    "- owl:inferred-class": "bc:VirtualObject",
    "- belongsToDomain": "[[CryptographicDomain]]",
    "- implementedInLayer": "[[SecurityLayer]]",
    "- is-subclass-of": "[[Blockchain Entity]], [[NetworkComponent]]"
  },
  "backlinks": [],
  "wiki_links": [
    "CryptographicDomain",
    "NetworkComponent",
    "ISO/IEC 23257:2021",
    "IEEE 2418.1",
    "Blockchain Entity",
    "SecurityLayer",
    "NIST NISTIR"
  ],
  "ontology": {
    "term_id": "BC-0093",
    "preferred_term": "Archival Node",
    "definition": "Complete history storage node within blockchain systems, providing essential functionality for distributed ledger technology operations and properties.",
    "source_domain": "metaverse",
    "maturity_level": null,
    "authority_score": 0.95
  }
}