{
  "title": "Artificial General Intelligence",
  "content": "- ### OntologyBlock\n  id:: artificial-general-intelligence-ontology\n  collapsed:: true\n\t- ontology:: true\n\t- term-id:: mv-327352489782\n\t- preferred-term:: Artificial General Intelligence\n\t- source-domain:: metaverse\n\t- status:: active\n\t- public-access:: true\n\t- definition:: A component of the metaverse ecosystem focusing on artificial general intelligence.\n\t- maturity:: mature\n\t- authority-score:: 0.85\n\t- owl:class:: mv:ArtificialGeneralIntelligence\n\t- owl:physicality:: ConceptualEntity\n\t- owl:role:: Concept\n\t- belongsToDomain:: [[MetaverseDomain]]\n\t- #### Relationships\n\t  id:: artificial-general-intelligence-relationships\n\t\t- enables:: [[ImmersiveExperience]], [[Presence]], [[SpatialComputing]]\n\t\t- requires:: [[DisplayTechnology]], [[TrackingSystem]], [[RenderingEngine]]\n\t\t- bridges-to:: [[HumanComputerInteraction]], [[ComputerVision]], [[Robotics]]\n\n\t- #### OWL Axioms\n\t  id:: artificial-general-intelligence-owl-axioms\n\t  collapsed:: true\n\t\t- ```clojure\n\t\t  Declaration(Class(mv:ArtificialGeneralIntelligence))\n\n\t\t  # Classification\n\t\t  SubClassOf(mv:ArtificialGeneralIntelligence mv:ConceptualEntity)\n\t\t  SubClassOf(mv:ArtificialGeneralIntelligence mv:Concept)\n\n\t\t  # Domain classification\n\t\t  SubClassOf(mv:ArtificialGeneralIntelligence\n\t\t    ObjectSomeValuesFrom(mv:belongsToDomain mv:MetaverseDomain)\n\t\t  )\n\n\t\t  # Annotations\n\t\t  AnnotationAssertion(rdfs:label mv:ArtificialGeneralIntelligence \"Artificial General Intelligence\"@en)\n\t\t  AnnotationAssertion(rdfs:comment mv:ArtificialGeneralIntelligence \"A component of the metaverse ecosystem focusing on artificial general intelligence.\"@en)\n\t\t  AnnotationAssertion(dcterms:identifier mv:ArtificialGeneralIntelligence \"mv-327352489782\"^^xsd:string)\n\t\t  ```\n\n- **# **Economic Impact of AGI and Superintelligence – A Deepseek Analysis**\n-\n- [Opinion | The Government Knows A.G.I. is Coming - The New York Times](https://www.nytimes.com/2025/03/04/opinion/ezra-klein-podcast-ben-buchanan.html)\n-\n- ## **Introduction**\n-\n- Artificial General Intelligence (AGI) refers to AI systems with broad, human-level cognitive abilities across diverse tasks, as opposed to “narrow” AI limited to specific domains ([Artificial general intelligence - Wikipedia](https://en.wikipedia.org/wiki/Artificial_general_intelligence#:~:text=Artificial%20general%20intelligence%20,the%20definitions%20of%20%20162)) gence* denotes an intellect far surpassing human intelligence in virtually all fields. The advent o ([ead safety beneficence v2](https://standards.ieee.org/wp-content/uploads/import/documents/other/ead_safety_beneficence_v2.pdf#:~:text=tasks%2C%20and%20artificial%20superintelligence%20,systems%20do%20not%20yet%20achieve)) ecially superintelligent AI is expected to be a transformative event for economies and societies. This report examines how the concepts of AGI and superintelligence have evolved, and analyzes their potential economic impacts on labor, productivity, inequality, and growth. It also explores predictions and policy considerations, including timeline-based scenarios and international dynamics.\n- ## **1. Definition and Evolution of AGI and Superintelligence**\n-\n- **Early Conceptions (Turing and McCarthy).** Early AI pioneers implicitly aimed at general intelligence. In 1950, Alan Turing sidestepped the question “Can machines think?” by proposing an operational test – if a machine’s answers were indistinguishable from a human’s, it could be considered intelligent. Turing even predicted th ([Computing Machinery and Intelligence - Wikipedia](https://en.wikipedia.org/wiki/Computing_Machinery_and_Intelligence#:~:text=As%20Stevan%20Harnad%20notes%2C,causal%20system%20can%20generate%20them)) 2000, machines would likely be able to fool 30% of human interrogators in a five-minute text conversation – an early vision of human-level AI. A ([A Computer Has Reportedly Passed Turing Test For The First Time | IFLScience](https://www.iflscience.com/computer-has-reportedly-passed-turing-test-first-time-24709#:~:text=required,the%20course%20of%20five%20minutes)) later, John McCarthy and colleagues organized the 1956 Dartmouth Workshop, coining the term *artificial intelligence*. Their proposal articulated the ambitious conjecture that “every aspect of learning or any other feature of intelligence can in principle be so precisely described that a machine can be made to simulate it”. This optimism reflected a belief that human-lik ([A PROPOSAL FOR THE DARTMOUTH SUMMER RESEARCH PROJECT ON ARTIFICIAL INTELLIGENCE](https://www-formal.stanford.edu/jmc/history/dartmouth/dartmouth.html#:~:text=The%20study%20is%20to%20proceed,it%20together%20for%20a%20summer)) elligence was attainable in machines, even if early AI research soon found the problem more difficult than expected.\n-\n- **Emergence of AGI and Superintelligence Concepts.** Through subsequent decades, AI progressed mainly in narrow domains, but the idea of general AI persisted. Researchers began using the term **Artificial General Intelligence (AGI)** to distinguish human-level flexible intelligence from narrow AI. AGI is defined as AI that “matches or surpasses human cognitive capabilities across a wide range of cognitive tasks,” in contrast to narrow AI limited to specific tasks. It is often considered equivalent to *strong AI* or *human- ([Artificial general intelligence - Wikipedia](https://en.wikipedia.org/wiki/Artificial_general_intelligence#:~:text=Artificial%20general%20intelligence%20,the%20definitions%20of%20%20162)) tificial superintelligence (ASI)**, as popularized by philosopher Nick Bostrom, refers to an intellect *far* superior to the best human brains “in practically every field, including scientific creativity, general wisdom and social skills”. Bostrom’s 2014 book *Superintelligence* raised awareness of the potential ([ead safety beneficence v2](https://standards.ieee.org/wp-content/uploads/import/documents/other/ead_safety_beneficence_v2.pdf#:~:text=tasks%2C%20and%20artificial%20superintelligence%20,systems%20do%20not%20yet%20achieve)) such an entity. He famously wrote that “the first superintelligence will be the last invention that humanity needs to make,” indicating that once human-level AI emerges and improves itself beyond our abilities, it could autonomously drive all further technological progress. Futurist Ray Kurzweil has also been a key figure in shaping AGI discourse. In the ear ([Artificial general intelligence - Wikipedia](https://en.wikipedia.org/wiki/Artificial_general_intelligence#:~:text=13.%20,Are%20AI%27s%20Doomsday%20Scenarios%20Worth)) l predicted that by 2029 AI would pass the Turing test – essentially achieving human-level intelligence – and that this would lead to a technological *Singularity* around 2045, when superintelligent AI triggers runaway growth in technology and intelligence. Such predictions, while speculative, helped to frame AGI as a looming possibility. Recent AI scientis ([Ray Kurzweil is sticking to his long-held predictions: 2029 for AGI ...](https://www.reddit.com/r/singularity/comments/18m0dnf/ray_kurzweil_is_sticking_to_his_longheld/#:~:text=,achieved%20in%20the%20year%202045)) ([Human-like Computers By 2029? — Futures Platform](https://www.futuresplatform.com/blog/human-computers-2029#:~:text=In%202014%2C%20he%20predicted%20that,funny%2C%20loving%2C%20and%20so%20on)) well: for example, DeepMind co-founder Shane Legg defined intelligence as the ability to achieve goals in a wide range of environments, implying a very general capability, and his company’s explicit mission has been to create AGI. Meanwhile, voices like Turing Award winner Geoffrey Hinton hav ([ead safety beneficence v2](https://standards.ieee.org/wp-content/uploads/import/documents/other/ead_safety_beneficence_v2.pdf#:~:text=The%20concept%20of%20intelligence%20can,%E2%80%9D)) om skepticism to concern – Hinton remarked in 2023 that with the rapid progress of AI, he suspects machines *“will be more intelligent than us”*, possibly within 5–20 years. On the other hand, some experts like Melanie Mitchell maintain *“we are far from creating machines that can outthink us in general w ([Scenario Planning for an AGI Future-Anton Korinek](https://www.imf.org/en/Publications/fandd/issues/2023/12/Scenario-Planning-for-an-AGI-future-Anton-korinek#:~:text=Recent%20advances%20in%20artificial%20intelligence,of%205%20to%2020%20years)) ring continued doubt about imminent AGI. Thus, definitions have evolved from early broad conjectures (Turing, McCarthy) to more formal distinctions between narrow AI, AGI, and superintell ([Artificial general intelligence - Wikipedia](https://en.wikipedia.org/wiki/Artificial_general_intelligence#:~:text=15.%20%5E%20,Kurzweil%202005%2C%20p.%C2%A0260)) Legg), accompanied by growing focus on the implications of achieving these milestones.\n-\n- **Current Debates: Is AGI on the Horizon?** There is vigorous debate today about **how soon AGI might arrive**. Optimistic forecasts cite the accelerating advances in machine learning (e.g. large language models) as evidence that human-level AI may be achievable in a matter of years or decades. Notable AI figures have sounded alarms that AGI could be “sooner than many expect”. In one survey of AI experts, the median estimate for a 50% chance of achieving high-level machine intelligence was around 2040–2050, with a 90% likelihood by 2075 ([Artificial general intelligence - Wikipedia](https://en.wikipedia.org/wiki/Artificial_general_intelligence#:~:text=The%20timeline%20for%20achieving%20AGI,7)) vey indicated experts believe a transition to superintelligence could follow within <30 years after AGI’s arrival. Kurzweil’s timeline (2029 for human-level AI) li ([Future Progress in Artificial Intelligence: A Survey of Expert Opinion](https://nickbostrom.com/papers/survey.pdf#:~:text=median%20estimate%20of%20respondents%20was,They%20estimate)) ptimistic end, whereas many researchers caution it may take much longer – some say *perhaps* a century or more, or even never. ([Future Progress in Artificial Intelligence: A Survey of Expert Opinion](https://nickbostrom.com/papers/survey.pdf#:~:text=median%20estimate%20of%20respondents%20was,They%20estimate)) int out that current AI systems, while impressive, still lack the robust generality and common sense of human cognition. There have been historical false dawns (leading to “AI winters”) ([Artificial general intelligence - Wikipedia](https://en.wikipedia.org/wiki/Artificial_general_intelligence#:~:text=The%20timeline%20for%20achieving%20AGI,7)) caution in assuming recent progress will continue at the same exponential pace. Nevertheless, the last decade’s breakthroughs in de ([Artificial general intelligence - Wikipedia](https://en.wikipedia.org/wiki/Artificial_general_intelligence#:~:text=15.%20%5E%20,Kurzweil%202005%2C%20p.%C2%A0260)) shifted expert opinion toward believing AGI is *plausible* in the foreseeable future, even if opinions diverge on exact timing. This uncertainty has not stopped intense speculation – and concern. A minority of commentators even claim rudimentary forms of AGI are “already here” in today’s large models, though this is contentious. In summary, while defin ([Artificial general intelligence - Wikipedia](https://en.wikipedia.org/wiki/Artificial_general_intelligence#:~:text=The%20timeline%20for%20achieving%20AGI,7)) nd superintelligence have crystallized, the field remains divided on when (or if) we will cross the threshold into true AGI. The following sections assume that AGI will event ([Artificial general intelligence - Wikipedia](https://en.wikipedia.org/wiki/Artificial_general_intelligence#:~:text=The%20timeline%20for%20achieving%20AGI,7)) ed and consider its economic ramifications.\n- ## **2. Economic Impact Analysis**\n-\n- If and when AGI emerges – especially if followed by superintelligence – the economic effects would be profound. This section analyzes several key areas of impact: labor markets, automation and productivity, wealth distribution and inequality, and overall economic growth and innovation.\n- ### **2.1 Labor Markets**\n-\n- One of the most immediate concerns about AGI is its impact on **jobs and employment**. A sufficiently advanced AI with general problem-solving abilities could automate a vast range of tasks currently done by humans. This raises the prospect of significant job *displacement*. Studies of narrower AI and robotics already suggest large portions of jobs are at risk: for example, one widely-cited analysis estimated that 47% of U.S. occupations are susceptible to automation by mid-2030s. Similarly, a recent report by Goldman Sachs projected that as many as **300 million jobs** globally could be affected by AI automation in the coming decades. In advanced economies, that could translate to a substantial share of the workforce seeing their ([Growth trends for selected occupations considered at risk from automation : Monthly Labor Review: U.S. Bureau of Labor Statistics](https://www.bls.gov/opub/mlr/2022/article/growth-trends-for-selected-occupations-considered-at-risk-from-automation.htm#:~:text=argued%20strongly%20that%20the%20new,10)) or replaced.\n-\n- Historical precedent, however, shows that technology also *creates* new jobs and categories of work – often in ways that are hard to predict b ([U-B-AI: universal basic income and the future of work](https://basicincometoday.com/u-b-ai-universal-basic-income-and-the-future-of-work/#:~:text=Support%20for%20Hinton%E2%80%99s%20view%20comes,all%20jobs%2C%20with%20fields%20like)) industrial revolution, for instance, eventually generated more jobs than it destroyed, but only after a difficult transition. With AGI, the potential scope of automation is far broader, encompassing not just factory or routine office jobs but also complex cognitive and creative tasks. Optimists argue that freeing humans from mundane labor could *enable* new occupations (in AI supervision, creative industries, personalized services, etc.) that we can’t yet imagine. In the near term, even as AI displaces certain roles, it is expected to create others. A World Economic Forum analysis forecasted that by 2025, automation will displace about **85 million jobs** worldwide but also produce **97 million** new jobs, as economies adapt to “the future of work”. In theory, AGI could supercharge productivity so much that society could afford shorter working weeks and more creative pursuits for humans – a positive vision where labor shifts rather than simply vanishes.\n-\n- **Wages and Employment Structures.** As AI takes over tasks, the nature o ([Recession and Automation Changes Our Future of Work, But There are Jobs Coming, Report Says > Press releases | World Economic Forum](https://www.weforum.org/press/2020/10/recession-and-automation-changes-our-future-of-work-but-there-are-jobs-coming-report-says-52c5162fce/#:~:text=,jobs%20in%20next%20five%20years)) would likely change. There may be a greater emphasis on jobs requiring uniquely human traits (e.g. interpersonal skills, complex strategic oversight, or empathy) – at least until and unless AI masters those as well. In the interim, workers might increasingly work *alongside* AI tools, enhancing their productivity. However, if AGI can perform “all human work tasks” more efficiently, the economic value of human labor could decline substantially. One scenario analysis envisions that within 20 years of AGI’s advent, human labor would be largely *devalued* as machines can do essentially every job at lower cost. In such a scenario, market wages for many jobs could collapse, an ([Scenario Planning for an AGI Future-Anton Korinek](https://www.imf.org/en/Publications/fandd/issues/2023/12/Scenario-Planning-for-an-AGI-future-Anton-korinek#:~:text=,This%20would%20correspond%20to%20the)) l employment could give way either to mass unemployment or to humans focusing on niche areas that AI cannot (or is not allowed to) penetrate.\n-\n- Even short of that extreme, labor economists warn of possible **downward pressure on ([Scenario Planning for an AGI Future-Anton Korinek](https://www.imf.org/en/Publications/fandd/issues/2023/12/Scenario-Planning-for-an-AGI-future-Anton-korinek#:~:text=,This%20would%20correspond%20to%20the)) AI enables one person to do the work of ten, or if companies can run with far fewer employees, the demand for certain skills will drop. Lower demand tends to reduce wages for those skills, *unless* workers can upskill or transition to roles that remain in demand. There is concern about **technological unemployment** – people whose jobs become obsolete faster than they can retrain. Already, AI is beginning to automate both blue-collar and white-collar tasks: from manufacturing and driving to drafting reports and analyzing data. If a significant portion of the workforce finds itself displaced with *no* equally robust new sector absorbing them, unemployment could rise and labor force participation could fall. Some analysts note that even partial automation can lead to reduced hiring and suppressed wages. For instance, even if AI doesn’t fully replace a job, automating *parts* of that job reduces the need for as many workers, which “would likely reduce hiring and decrease wages” for those roles. This dynamic may contribute to labor market polarization – high-skilled tech-savvy workers might command *higher* wages, while middle-skill jobs are hollowed out and lower-skilled service jobs see stagnant or lower pay.\n-\n- **Job Creation vs. Destruction – Uncertainty:** Whether AGI will result in net job loss or gain ([AI may increase economic inequality - MINDFUL TECHNICS](https://mindfultechnics.com/ai-may-increase-economic-inequality/#:~:text=One%20immediate%20consequence%20of%20AI,their%20work%20becomes%20fully%20automated)) pen question. Some economists argue that like past technological leaps, AI will *complement* workers rather than replace them entirely, leading to higher productivity and *shifting* job categories. Others fear this time is different, because AGI could potentially do *any* human job. Notably, a scenario in which AGI arrives very rapidly (within 5 years, per one aggressive forecast) could catch the economy flat-footed, leading to a sharp, disruptive displacement before new jobs and training systems emerge. A more gradual emergence over decades would give society more time to adjust, perhaps cushioning the shock. In any case, policymakers are already discussing safety nets given the risks. **Mass technological unemployment** is no longer a fringe idea; even mainstream outlets and experts consider it a possibility if AI progresses ([Scenario Planning for an AGI Future-Anton Korinek](https://www.imf.org/en/Publications/fandd/issues/2023/12/Scenario-Planning-for-an-AGI-future-Anton-korinek#:~:text=Scenario%20III%20,be%20reached%20within%20five%20years)) n one revealing statistic, an OpenAI research paper estimated that current AI technologies (not even full AGI yet) could affect *47–56%* of all jobs in the economy in terms of automating significant portions of their tasks. If those numbers approach 80–100% in the AGI era, the traditional model of employment could be upended.\n-\n- **Universal Basic Income (UBI) and Other Policy Responses.** The prospect of widespread job displacement by AI has driven serious consideration of **universal basic income** – a policy of providing every citizen a regular livable stipe ([U-B-AI: universal basic income and the future of work](https://basicincometoday.com/u-b-ai-universal-basic-income-and-the-future-of-work/#:~:text=Support%20for%20Hinton%E2%80%99s%20view%20comes,and%20mathematics%20at%20high%20risk)) ngs attached. UBI is seen as a way to ensure people can meet their basic needs even if they cannot find work, and to share the economic gains of automation with the whole population. In the context of AI, even some technologists have endorsed UBI. For example, **Geoffrey Hinton**, a pioneer of deep learning, has argued that because AI will boost productivity and wealth but concentrate it, *“universal basic income [is] a good idea”* to redistribute the gains and prevent those who lose their jobs from suffering. He warned that without such redistribution, “most of the financial gains will go to the rich and not the people whose jobs get lost, and that’s going to be very bad for society”. UBI could provide a floor for those displaced, giving them time to retrain or engage in other pursuits. Other proposals include wage subsidies, public works programs, or a **n (**[**U-B-AI: universal basic income and the future of work**](https://basicincometoday.com/u-b-ai-universal-basic-income-and-the-future-of-work/#:~:text=Geoffrey%20Hinton%2C%20a%20prominent%20AI,%E2%80%9D)**) tax** that supplements incomes below a certain threshold (potentially funded by taxing AI-driven corporate profits). The underlying idea is to decouple livelihood from formal emp ([U-B-AI: universal basic income and the future of work](https://basicincometoday.com/u-b-ai-universal-basic-income-and-the-future-of-work/#:~:text=Geoffrey%20Hinton%2C%20a%20prominent%20AI,%E2%80%9D)) oyment becomes scarce.\n-\n- It’s worth noting that not everyone agrees UBI is the panacea – critics cite the high fiscal cost and worry it could disincentivize work or fail to address the loss of meaning many derive from employment. Nonetheless, as AI capabilities advance, **the policy discourse has shifted ([AI may increase economic inequality - MINDFUL TECHNICS](https://mindfultechnics.com/ai-may-increase-economic-inequality/#:~:text=Although%20AI%20may%20increase%20economic,gains%20or%20profits%20from%20automation)) e theoretical, like UBI, are being actively experimented (e.g. pilot programs in several countries) in anticipation of automation shocks. In summary, AGI could fundamentally alter labor markets – potentially rendering the human labor of millions economically obsolete, *or* augmenting human workers to be far more productive in new types of jobs. Preparing for the former scenario (with robust safety nets, education, and possibly a reimagining of how we define work and purpose) will be crucial, even as we hope that human ingenuity finds ways to coexist with the machines.\n- ### **2.2 Automation and Productivity**\n-\n- Advocates of AI often highlight that automation driven by advanced AI will lead to **massive productivity gains**. An AGI workforce, unconstrained by human limitations, could operate 24/7, perform tasks with superhuman speed and accuracy, and innovate new solutions – theoretically boosting economic *output* enormously. By taking over routine and even complex tasks, AGI could free human resources for other activities or allow the same output to be produced with far fewer inputs.\n-\n- Nearly every industry stands to be transformed by **AGI-driven automation**. In manufacturing, fully autonomous factories could drastically increase throughput. In services, AI agents could handle customer service, financial advising, legal analysis, and medical diagnostics more quickly and consistently than humans. In research and development, an AGI could rapidly iterate experiments or design new products. Such automation promises **increased efficiency** – lower costs per unit of output – and could raise the global economic growth rate. For instance, one analysis by PricewaterhouseCoopers estimated that AI (broadly defined) could add about **14% to global GDP by 2030**, equivalent to an extra **$15.7 trillion** in economic output. This is due to both productivity effects and the creation of new products and services powered by AI. Similarly, the International Monetary Fund notes that with proper diffusion, AI could “significantly accelerate economic growth” and help reverse slowing productivity trends. Recent studies on **generative AI** (a subset of AI often seen as a stepping stone to AGI) suggest these technologies ([Artificial Intelligence](https://www.trade.gov/artificial-intelligence#:~:text=,1)) he order of *trillions* of dollars per year to the economy once integrated, potentially raising labor productivity growth by between 0.5 and 3 percentage points annually. These figures imply a substantial boost compared to pre-AI productivity growth rates.\n-\n- The positive visio ([AI's Promise for the Global Economy](https://www.imf.org/en/Publications/fandd/issues/2024/09/AIs-promise-for-the-global-economy-Michael-Spence#:~:text=AI%27s%20Promise%20for%20the%20Global,and%20help%20productivity%20growth%20rebound)) I will function as a **General-Purpose Technology (GPT)** akin to past GPTs like the steam engine, electricity, or computers – but potentially even more impactful. GPTs have historically driven surges in productivity and spawned new industries. Generative AI and future AGI are expected to join this ca ([Economic potential of generative AI | McKinsey](https://www.mckinsey.com/capabilities/mckinsey-digital/our-insights/the-economic-potential-of-generative-ai-the-next-productivity-frontier#:~:text=Economic%20potential%20of%20generative%20AI,points%20annually%20to%20productivity%20growth)) rtantly, some researchers argue AI might diffuse faster than earlier GPTs because of its digital nature and wide applicability. Once an effective AGI algorithm is developed, it can be replicated and deployed globally via software, without the physical infrastructure rollouts needed for railroads or electricity. This could compress the time between invention and broad economic impact, leading to a more sudden productivity j ([The impact of generative AI as a general-purpose technology | MIT Sloan](https://mitsloan.mit.edu/ideas-made-to-matter/impact-generative-ai-a-general-purpose-technology#:~:text=The%20steam%20engine%2C%20the%20internal,invention%20to%20join%20that%20category)) us industrial revolutions.\n-\n- However, **productivity gains** do not automatically equate to widespread prosperity – it depends on ho ([The impact of generative AI as a general-purpose technology | MIT Sloan](https://mitsloan.mit.edu/ideas-made-to-matter/impact-generative-ai-a-general-purpose-technology#:~:text=In%20a%20recent%20report%20about,accessibility%20and%20ease%20of%20diffusion)) re distributed and whether they translate into broader economic benefits (a theme addressed in the next section on inequality). A potential downside of extreme automation is the scenario of “**jobless growth**,” where GDP and corporate profits climb but employment and wages stagnate or decline for a large segment of the population. In su ([The impact of generative AI as a general-purpose technology | MIT Sloan](https://mitsloan.mit.edu/ideas-made-to-matter/impact-generative-ai-a-general-purpose-technology#:~:text=The%20steam%20engine%2C%20the%20internal,invention%20to%20join%20that%20category)) egate productivity (output per worker) could skyrocket simply because many workers are sidelined. If human labor is only a tiny fraction of economic input in the AGI era, traditional productivity metrics might become less meaningful; we could see high output but also high inequality or unemployment.\n-\n- There is also the issue of the **productivity paradox** – historically, there have been lags between the advent of a major technology and its visible effect on productivity statistics (as seen with computers in the 1970s-1990s). We may currently be in the early phase of this with AI: lots of hype and investment, but modest aggregate productivity growth so far. Integrating AI effectively into business processes and reaping the full benefits often requires complementary innovations (organizational change, upskilling workers, new business models). With AGI, one can imagine even greater organizational challenges – companies and economies would need to reinvent how work is done to harness an AGI’s capabilities fully. In the long run, though, if a machine can do everything better and cheaper, it is hard to see productivity doing ([AI and the Productivity Paradox - Bruegel](https://www.bruegel.org/blog-post/ai-and-productivity-paradox#:~:text=AI%20and%20the%20Productivity%20Paradox,In%20other%20words)) explosively increase. Some economists like Robert Gordon or Daron Acemoglu caution that AI’s impact might still be incremental and not automatically solve deep structural productivity slowdowns. But others foresee an unprecedented leap in output.\n-\n- **Potential Downsides and Challenges:** While productivity and output could surge, some potential downsides include:\n- *Diminished returns to human capital:* If machines handle most tasks, investing in human education/skills might yield lower returns, potentially leading to underutilization of human potential.\n- *Transition costs:* In the short-to-medium term, firms that cannot afford or adapt to AI may go out of business ([How AI can boost productivity and jump start growth](https://privatebank.jpmorgan.com/nam/en/insights/markets-and-investing/ideas-and-insights/how-ai-can-boost-productivity-and-jump-start-growth#:~:text=MIT%20economics%20professor%20Daron%20Acemo%C4%9Flu,boost%20to%20GDP)) may experience periods of unemployment, hurting economic well-being despite higher productivity on aggregate.\n- *Concentration of productivity:* It’s possible that a few AGI-powered firms become ultra-productive “superstar” companies, while others lag, leading to monopolistic markets (this ties into inequality again). In such a scenario, overall productivity could rise, but many firms and regions could actually see negative effects if they cannot compete.\n- *Quality and externalities:* If AGI-driven automation is not well-aligned with human needs, productivity might rise in terms of quantity of output, but the quality or societal value of that output could suffer (for example, AI could flood the market with products or content that have negative side-effects or there could be environmental externalities of massive computing).\n-\n- In balance, **AGI has the potential to dramatically increase economic efficiency and output**, enabling a wealth of goods and services at lower cost. This could herald an era of abundance – *if* managed correctly. The major caveat is ensuring these gains lead to broadly shared improvement in living standards. Without thoughtful policies, the benefits might accrue mainly to owners of AI and capital, while displaced workers and communities see little benefit from the higher output. Hence the next section’s focus on distributional issues.\n- ### **2.3 Wealth Distribution and Inequality**\n-\n- The introduction of AGI could significantly reshape **wealth distribution**, with a high risk of exacerbating economic inequality. The reason is that AGI effectively acts as an extremely potent form of capital (a productive asset). Those who *own* the AGI – likely big tech companies or governments that develop it – could reap enormous profits, whereas those who rely on selling their labor may find its value greatly diminished. As one analysis put it, through “winner-take-all” effects, *innovators will be able to capture most of the wealth generated by AI technology*, becoming vastly wealthier than everyone else. In concrete terms, if a company develops a superintelligent AI that outperforms all competitors, it could monopolize entire industries (or create new ones) and accumulate unprecedented wealth. Meanwhile, competitors, including human workers whose skills are now redundant, would lose economic power.\n-\n- **Risk of Widening Inequality:** If left unchecked, AGI could lead to a scenario where *the rich get richer* – owners of AI and capital see skyrocketing returns – and *the rest* face stagnant in ([James Hadley.pdf](https://sites.rutgers.edu/nb-senior-exhibits/wp-content/uploads/sites/442/2020/08/James-Hadley-final-pdf.pdf#:~:text=which%20uses%20Casares%E2%80%99s%20division%20of,and%20lower%20costs%20of%20goods)) ([James Hadley.pdf](https://sites.rutgers.edu/nb-senior-exhibits/wp-content/uploads/sites/442/2020/08/James-Hadley-final-pdf.pdf#:~:text=see%20how%20this%20inequality%20will,them%20to%20be%20worse%20off)) e share of income going to labor (wages) versus capital (profits) might shift heavily in favor of capital. We’ve already observed a decline in labor’s share of income in many countries in recent decades, partly attributed to automation and globalization. AGI could accelerate that trend dramatically. As Nobel laureate Angus Deaton and others have noted, periods of increasing capital income tend to increase inequality. AI stands to significantly boost returns on capital (machines, algorithms, data), thus **income from capital** (dividends, capital gains) could surge for investors, while wage income could stagnate or fall for workers who are displaced. Without intervention, this could create a stratum of AI-tech oligarchs vs. a large underclass.\n-\n- Additionally, **winner-takes-all markets** mean that even among companies, the top AI firm could dominate. For example, if one AI model is slightly better than others, it might capture ([James Hadley.pdf](https://sites.rutgers.edu/nb-senior-exhibits/wp-content/uploads/sites/442/2020/08/James-Hadley-final-pdf.pdf#:~:text=The%20first%20section%20of%20this,Brynjolfsson)) of the market (“few businesses will pay for second-rate programs”). The result is further concentration of wealth in a few corporations and individuals. A commentary on AI inequality noted that this scenario “would not be a rising tide ([James Hadley.pdf](https://sites.rutgers.edu/nb-senior-exhibits/wp-content/uploads/sites/442/2020/08/James-Hadley-final-pdf.pdf#:~:text=The%20first%20section%20of%20this,Brynjolfsson)) ([James Hadley.pdf](https://sites.rutgers.edu/nb-senior-exhibits/wp-content/uploads/sites/442/2020/08/James-Hadley-final-pdf.pdf#:~:text=to%20an%20increase%20in%20inequality,reduce%20the%20income%20of%20part)) rather a tide that lifts a few yachts while many rafts run aground. This extreme inequality is not only a social justice issue; it could have macroeconomic consequences. If too much wealth concentrates at the top, aggregate demand could fall (because the wealthy spend a smaller proportion of their income), potentially leading to secular stagnation. It could ([AI may increase economic inequality - MINDFUL TECHNICS](https://mindfultechnics.com/ai-may-increase-economic-inequality/#:~:text=Another%20consequence%20of%20AI%20will,better%20one%20to%20outcompete%20them)) itical instability and public backlash against the technology.\n-\n- **Democratizing AI Benefits vs. Monopolization:** A key question is whether the benefits of AGI can be broadly shared or will be monopolized. Optimistically, one could imagine AGI as a *public utili ([AI may increase economic inequality - MINDFUL TECHNICS](https://mindfultechnics.com/ai-may-increase-economic-inequality/#:~:text=Another%20consequence%20of%20AI%20will,better%20one%20to%20outcompete%20them)) wledge and productivity used to everyone’s benefit (e.g. breakthroughs in medicine disseminated widely, AI services available to all at low cost). Open-source AI and public-sector AI development could help in this direction. However, the current trajectory shows heavy investment by a handful of Big Tech firms and great powers. The structure of the AI market *“will determine whether AI lives up to its promise or entrenches the power of a few dominant corporations”*. At present, giants like Google, Microsoft, Amazon, and a few others are pouring billions into advanced AI, using their massive data and computing advantages to maintain leadership. Without regulatory intervention, there is a real possibility that AGI could be controlled by a duopoly or oligopoly of firms (or states), who then capture virtually all the surplus value. This would manifest as enormous profits for those firms and their shareholders, and relatively little benefit trickling down.\n-\n- Economists and policy experts have begun discussing measures to **avoid AI-driven i ([It’s Not Too Late to Stop the Monopolization of AI - Inequality.org](https://inequality.org/article/its-not-too-late-to-stop-the-monopolization-of-ai/#:~:text=society%20solve%20complex%20problems%20and,already%20hold%20over%20our%20lives)) e idea from the effective altruism and AI ethics community is a *Windfall Clause*, where AI developers commit to share a significant portion of any extremely large profits with soc ([It’s Not Too Late to Stop the Monopolization of AI - Inequality.org](https://inequality.org/article/its-not-too-late-to-stop-the-monopolization-of-ai/#:~:text=While%20competition%20ostensibly%20exists%20in,Apple%2C%20Amazon%2C%20Nvidia%2C%20and%20Meta)) ssentially an agreement to distribute the “windfall” gains from AGI success, as a way to ensure the common good. The principle behind it aligns with what Bostrom called the “common good principle” – that advanced AI should be developed for the benefit of all humanity. In practical terms, this could mean something like a special tax or profit-sharing mechanism kicks in if an AI company’s profits exceed some astronomical threshold, with those funds redistributed (perhaps funding UBI, public services, etc.). While voluntary, this reflects growing recognition that *new governance tools* are need ([Cullen O'Keefe: The Windfall Clause — Sharing the Benefits of Advanced AI | Effective Altruism](https://www.effectivealtruism.org/articles/cullen-okeefe-the-windfall-clause-sharing-the-benefits-of-advanced-ai#:~:text=could%20work%20toward%20equitable%20distribution,the%20challenges%20to%20implementing%20it)) GI’s riches don’t just pool in a few bank accounts.\n-\n- **Global Inequality:** There is also an international dimension. If AGI is developed primarily in one country or a small set of countries, it might worsen the wealth gap between those and the rest of the world. Advanced econ ([Cullen O'Keefe: The Windfall Clause — Sharing the Benefits of Advanced AI | Effective Altruism](https://www.effectivealtruism.org/articles/cullen-okeefe-the-windfall-clause-sharing-the-benefits-of-advanced-ai#:~:text=lot%20of%20work%20ahead%20of,us)) ading tech sectors could see huge gains, while developing countries that rely on labor-intensive industries might suffer (their comparative advantage eroded by AI, and lacking the capital to implement AGI at scale). The IMF has raised concerns that AI could widen the gap between rich and poor countries by concentrating investment in advanced economies. For example, countries with large pools of cheap labor have traditionally attracted manufacturing; if robots and AI make cheap labor less important, capital might instead flow to countries with better tech infrastructure. This suggests a need for international solidarity – perhaps sharing AI technology or ensuring global access – otherwise AGI might deepen global economic divides.\n-\n- In summary, without checks and balances, AGI could lead to **extreme economic inequality** – both within societies and between them. Policies like progressive taxation (especially on capital and high AI-generated incomes), profit-sharing schemes ([How Artificial Intelligence Could Widen the Gap Between Rich and ...](https://www.imf.org/en/Blogs/Articles/2020/12/02/blog-how-artificial-intelligence-could-widen-the-gap-between-rich-and-poor-nations#:~:text=How%20Artificial%20Intelligence%20Could%20Widen,more%20investment%20to%20advanced%20economies)) nforcement to prevent monopoly, and universal social programs may be necessary to *balance* the scales. The goal would be to harness AGI’s immense productive capacity in a way that **raises the floor** of prosperity without just further lifting the ceiling. If done well, AGI could even be an equalizer – for instance, cheap AI services could be provided to all, and a societal dividend from AI productivity could fund education and healthcare universally. The choices we make in the early stages of AGI development will likely have lasting impacts on how equitably its benefits are spread.\n- ### **2.4 Economic Growth and Innovation**\n-\n- The arrival of AGI has been described as akin to a new industrial revolution – or even more, *a new epoch* for economic growth. By effectively injecting an abundance of cognitive labor (and potentially vastly superhuman intellect) into the economy, AGI could dramatically **accelerate economic growth** and spur unprecedented innovation.\n-\n- **Acceleration of GDP Growth:** Throughout modern history, global GDP growth has averaged a few percent per year, driven by factors like capital accumulation, labor force growth, and incremental technological progress. AGI could change this equation by acting as a powerful new factor of production and innovation. Some futurists and economists speculate that we could see a shift from the current relatively steady growth to a much higher growth trajectory. For instance, if an AGI can improve itself (the classic “intelligence explosion” scenario), it might rapidly invent new technologies, solve scientific problems, and optimize production processes, leading to a cascade of economic innovations. Bostrom’s notion that superintelligence might be humanity’s “last invention” hints at this: after that point, *the AI itself drives invention*, possibly at a pace far beyond human R&D. In theory, this could result in extremely high economic growth for a period, as breakthroughs in energy, materials, medicine, etc. arrive in quick succession thanks to superhuman research capabilities.\n-\n- Even without an explosive singularity, a more gradual AGI could significantly raise growth rates. One analysis by economists projected that AI (including potential AGI) could add multiple percentage points to annual GDP growth for decades. Another report by McKinsey Global Institute found that combining generative AI with other automation could potentially *double* the annual productivity growth rate in the coming years. To illustrate ([Artificial general intelligence - Wikipedia](https://en.wikipedia.org/wiki/Artificial_general_intelligence#:~:text=13.%20,Are%20AI%27s%20Doomsday%20Scenarios%20Worth)) lobal economy was about $80-90 trillion in size in the late 2010s; adding $13-15 trillion by 2030 due to AI (as PwC and others forecast) is like adding an economy the size of China’s output, solely from AI contributions. Now consider AGI, which could be far more transformative than the narrow AI underpinning those forecasts. Some have even considered models where the economy’s doubling time (traditionally on the order of 20–30 years) coul ([Economic potential of generative AI | McKinsey](https://www.mckinsey.com/capabilities/mckinsey-digital/our-insights/the-economic-potential-of-generative-ai-the-next-productivity-frontier#:~:text=Economic%20potential%20of%20generative%20AI,points%20annually%20to%20productivity%20growth)) years or less under AI-driven growth – in a speculative far-future scenario, perhaps an AI-run economy could reach a point of *hypergrowth*, though this enters unknown territory in eco ([Economic potential of generative AI | McKinsey](https://www.mckinsey.com/capabilities/mckinsey-digital/our-insights/the-economic-potential-of-generative-ai-the-next-productivity-frontier#:~:text=Economic%20potential%20of%20generative%20AI,points%20annually%20to%20productivity%20growth)) ng.\n-\n- **Innovation and New Industries:** AGI could not only accelerate growth in existing sectors but also lead to the emergence of entirely new industries and economic ([Artificial Intelligence](https://www.trade.gov/artificial-intelligence#:~:text=,1)) t as the advent of computing created industries (software, digital services, etc.) that were nonexistent before, AGI could enable sectors we can barely conceive of now. For example:\n- **AI-driven Scientific Research:** An AGI scientist could vastly expand the rate of discovery in pharmaceuticals, materials science, energy technology, and more. We might see rapid development of cures for diseases, new sustainable energy sources, and solutions to climate change – each of which can create new economic activity and markets (think of a multi-trillion-dollar industry around, say, fusion energy if unlocked by AI).\n- **Personalized AI services:** AGIs could serve as personal tutors, medical advisors, or even creative companions to billions of people, spawning industries around individualized education, healthcare, and entertainment that adapts to each person. This could increase human capital (smarter, healthier population) which feeds back into growth.\n- **Autonomous Systems:** Entire fleets of autonomous vehicles, drones, and robots supervised by AGI could revolutionize logistics, transportation, and infrastructure. Smart cities managed by AI might use resources ultra-efficiently, improving economic efficiency.\n- **Space and Exploration:** Superintelligent AI might dramatically lower the cost of space exploration or mining by devising new technologies, potentially opening up the space economy (mining asteroids, colonization) which currently is speculative but could become viable with advanced AI planning and problem-solving.\n-\n- Furthermore, AGI could change **market dynamics** by reducing certain scarcities. If AI can design and run factories with minimal human input, goods could become much cheaper (a deflationary effect in consumer prices). If AI can essentially duplicate expertise, access to expert knowledge (medical, legal, etc.) could become near-free via AI assistants. In a positive spin, this is *democratization* of goods and knowledge, potentially raising living standards globally. It echoes the concept of a *post-scarcity economy* where basic needs are met by automated systems and human work is less essential for survival. Of course, whether that utopia is realized depends on economic and political choices (who owns the machines, etc., as discussed).\n-\n- **Transformative AI and Economic Paradigm Shifts:** Some analysts use the term **“transformative AI”** to describe AI that causes changes on the scale of the agricultural or industrial revolution in terms of impact on society. AGI would certainly qualify. Past transformative technologies led to periods of adjustment but ultimately supported much larger populations at higher income levels (e.g., mechanized agriculture freed people to move to cities and enter new jobs, electricity enabled all modern industries). Similarly, AGI could eventually allow humans to focus on higher-level pursuits – perhaps more creative or strategic endeavors – while routine work is done by machines, and overall economic output surges. In the best case, this could mean **higher GDP per capita** for all and more availability of goods (imagine everything from transportation to utilities becomes very cheap as AI optimizes their producti ([Artificial general intelligence - Wikipedia](https://en.wikipedia.org/wiki/Artificial_general_intelligence#:~:text=Related%20concepts%20include%20artificial%20superintelligence,24)) s could see increased tax revenues from the growth (assuming taxation systems capture AI-created value), which could fund public investments or redistribution.\n-\n- However, **managing the transition** is key. An AGI-driven economy might behave in unfamiliar ways. If an AI can replicate itself or produce other AIs, the effective “labor force” could grow extremely fast without the usual demographic constraints. Traditional economic models may break down; for example, infinite or hyper-fast growth is not realistically sustainable due to physical resource limits and environmental constraints. That said, AGI might also help solve resource bottlenecks (through innovation). We could even eventually reach a point where GDP is a less relevant measure – if AI enables near-zero cost production of many goods, monetary metrics might undervalue the real improvements in well-being (as has been argued with digital goods already).\n-\n- In sum, the **potential for economic growth and innovation from AGI is enormous**. We could witness a period of flourishing technological creativity, new industries blossoming, and rapid growth that improves living standards – *if* managed for broad benefit. Some experts have warned that this period could also be destabilizing; growth that is too rapid can overshoot or cause bubbles, and societies might struggle to adapt culturally to very fast change. Nonetheless, the promise of AGI includes tackling problems long deemed intractable (from aging to climate to interstellar travel) which holds the allure of not just economic growth, but qualitative leaps in human progress.\n- ## **3. Predictions and Policy Considerations**\n-\n- Given the wide-ranging possibilities, it’s prudent to consider **multiple scenarios** for AGI’s economic impact and to devise policies that maximize benefits and mitigate harms. In this section, we outline different scenarios based on how soon AGI arrives, then discuss policy measures for a fair and stable economic transition, and finally consider international dynamics and the need for cooperation.\n- ### **3.1 Scenario Analysis: Varying AGI Timelines**\n-\n- **Short-Term Emergence (within ~5 years):** In a scenario where AGI or something close to it is developed in the very near future, the economic shock could be abrupt. An “aggressive” scenario described by one economist posits AGI with human-level capabilities in **five years**, meaning by the early 2030s it can perform essentially all tasks humans can. This would be an unprecedented disruption: many industries would be caught unprepared, job displacement would outpace the ability of labor markets to retrain or reallocate workers, and social safety nets might be overwhelmed. Wages in jobs from driving to accounting could rapidly collapse as AIs outcompete human labor. Productivity would spike, but mainly benefiting those controlling the AGI (e.g., a handful of firms). Inequality would likely skyrocket in the short run. Governments would face a scramble to respond – possibly having to implement emergency UBI or public employment programs to avoid chaos. On the positive side, such an AGI could also accelerate solutions to pressing problems (perhaps h ([Scenario Planning for an AGI Future-Anton Korinek](https://www.imf.org/en/Publications/fandd/issues/2023/12/Scenario-Planning-for-an-AGI-future-Anton-korinek#:~:text=match%20at%20L326%20Scenario%20III,be%20reached%20within%20five%20years)) p vaccines, climate mitigation tech, etc. very quickly). But the key feature of this scenario is **lack of time to adapt**: institutions (education, regulatory frameworks, economic policies) would lag behind the tech change. This raises the risk of economic depression for populations whose labor is suddenly redundant, even as the country’s GDP might be climbing thanks to AI-driven output. Internationally, a country that suddenly attains AGI could gain a swift competitive edge, potentially widening global inequalities or even leading to geopolitical tension (rivals might panic to respond or even consider extreme measures to catch up).\n-\n- **Medium-Term Emergence (20–30 years):** A more gradual scenario has AGI developing by, say, the 2040s or 2050s. This roughly aligns with many expert surveys (mid-century as a median estimate for AGI). In this **baseline scenario**, progress in AI is steady and AGI arrives after a couple more decades of incremental improvements. Here, the transition, while still disruptive, allows more time for mitigation. Over 20 years, AI would progressively take on more tasks, and we would likely see a continuous, though accelerating, automation of jobs. Workers and young people could respond by steering their careers toward areas still less automatable. Education systems might adjust curricula to emphasize skills complementary to AI. Governments could gradually roll out policies like retraining programs, adjustment assistance for affected industries, and perhaps phased implementations of partial basic income or expanded w ([Future Progress in Artificial Intelligence: A Survey of Expert Opinion](https://nickbostrom.com/papers/survey.pdf#:~:text=median%20estimate%20of%20respondents%20was,They%20estimate)) the time AGI is fully realized, the economy would already have many AI-human hybrid workflows and a policy infrastructure to support those displaced. In this scenario, **labor is slowly devalued** – by 2045 or so, an AGI might be able to handle all work, effectively capping the value of human labor – but because it happens over a generation, society can collectively reorganize. We might see a shift in the social contract: work could be less central to identity and income, with more people in creative or care roles supported by an AI-augmented economy. The medium-term scenario is still challenging (some cohorts of workers will be hit harder, and political will must exist to implement needed policies), but it is less chaotic than the short-term shock scenario. Economically, moderate unemployment could persist if technology outruns job creation, but hopefully mitigated by forward-looking policies.\n-\n- **Long-Term or Distant Emergence (>50 years or never):** In a scenario where AGI does *not* materialize until late in the ([Scenario Planning for an AGI Future-Anton Korinek](https://www.imf.org/en/Publications/fandd/issues/2023/12/Scenario-Planning-for-an-AGI-future-Anton-korinek#:~:text=,This%20would%20correspond%20to%20the)) or beyond (if at all), the economic impacts of AI would remain more incremental. Narrow AI and automation would continue to affect the economy, but humanity would have much more time to adapt. The changes might be comparable to other technological transitions in the past. Traditional economic growth would continue with AI contributing as one factor among many. In this world, concerns about immediate mass unemployment might be overblown; instead, AI might augment human workers and boost productivity in a manageable way. Policy could proceed in a more measured fashion – focusing on things like education in STEM and AI ethics – without the urgency of existential economic disruption. However, if we assume AGI eventually comes even after many decades, this scenario just delays the big adjustments. The advantage is that our institutions by then might be far more prepared (having learned from smaller-scale AI impacts over time). It also might allow international frameworks to develop – e.g. agreements on how to handle AI’s economic dividends – before a single AGI system forces the issue.\n-\n- In planning for the future, it is wise to **hedge against multiple scenarios**. A recent IMF report suggests using a “portfolio of approaches” given the uncertainty in AI timelines. We cannot know for sure if AGI will hit like a thunderbolt or a slow wave, so robust strategies should account for either. That means investing in short-term safety nets that could scale up quickly (in case of a shock), **and** long-term reforms to ensure broad benefit from AI (in case of a gradual integration).\n- ### **3.2 Policy Responses to Mitigate Risks and Distribute Benefits**\n-\n- To navigate the economic upheaval from AGI, a range of **policy measures** will be needed. These policies aim to mitigate the risks (mass unemployment, extreme inequality, instability) and ensure that the benefits of advanced AI are shared broadly and sustainably. Key policy areas include:\n- **Education and Workforce Training:** Preparing the workforce ([Scenario Planning for an AGI Future-Anton Korinek](https://www.imf.org/en/Publications/fandd/issues/2023/12/Scenario-Planning-for-an-AGI-future-Anton-korinek#:~:text=)) ic economy is essential. This means massive investment in education, from K-12 up to lifelong learning programs. As routine jobs vanish, humans will need to develop skills that are complementary to AI (creative thinking, complex social interaction, etc.). Governments could provide free or subsidized retraining programs for workers displaced by automation. The concept of “lifelong learning accounts” or continuous education stipends might become commonplace, allowing workers to re-skill periodically as needed. Emphasizing STEM education as well as interdisciplinary skills (since AGI will permeate all fields) is important. Even so, no amount of training can make a human competitive with a superintelligence in many cognitive tasks – so education policy must also prepare people for a world where their job might not be the main source of livelihood (fostering adaptability, creativity, and perhaps non-work facets of life).\n- **Social Safety Nets and Basic Income:** As discussed, one of the boldest ideas is **Universal Basic Income (UBI)** or similar guaranteed income schemes (negative income tax, unive ([AI may increase economic inequality - MINDFUL TECHNICS](https://mindfultechnics.com/ai-may-increase-economic-inequality/#:~:text=guaranteeing%20a%20minimum%20income%20for,gains%20or%20profits%20from%20automation)) vidends, etc.). If AGI renders a large portion of people unemployed or underemployed, direct income support may be necessary to prevent poverty and maintain consumer demand. Pilot UBI programs today are testing how people respond – early evidence suggests people generally continue to seek purpose even with basic needs met. Funding UBI at scale in an AGI economy could actually be feasible **if** AGI dramatically increases total wealth. Sam Altman of OpenAI has argued that AI will create so much wealth that it could enable payments on the order of $10k per year to every adult. This presupposes mechanisms (like high taxes on AI profits or equity stakes for the public in AI firms) to channel the windfall. Short of full UBI, governments may strengthen unemployment insurance, offer job transition stipends, or public employment guarantees (perhaps paying people to do socially valuable work that AI can’t easily do, such as community building, artistic endeavors, or caring professions). In policy debates, even **tech leaders** are increasingly endorsing some form of guaranteed income as a cushion for the AI transition. Still, careful design is needed to avoid creating disincentives or political backlash; some propose a gradual ramp-up of UBI as automation increases, rather than implementing it overnight.\n- **Taxation and Redistribution (*[*OpenAI's Altman: AI will make wealth to pay all adults $13,500 a year*](https://www.cnbc.com/2021/03/17/openais-altman-ai-will-make-wealth-to-pay-all-adults-13500-a-year.html#:~:text=OpenAI%27s%20Altman%3A%20AI%20will%20make,from%20its%20windfall%20as)*) (*[*FLI Podcast: Distributing the Benefits of AI via the Windfall Clause ...*](https://futureoflife.org/podcast/distributing-the-benefits-of-ai-via-the-windfall-clause-with-cullen-okeefe/#:~:text=FLI%20Podcast%3A%20Distributing%20the%20Benefits,that%20if%20they%20achieve)*) ms and counteract inequality, ****tax policy**** will need to evolve. If capital owners are the primary beneficiaries of AGI, more progressive taxation on capital gains, corporate profits, and very high incomes will be needed to redistribute wealth. There have been proposals for a “robot tax” – taxing companies for the use of robots or AI that replace human workers – as one way to fund support for displaced workers. For example, a fraction of the productivity gains from AI could be taxed and put into a fund for retraining or UBI. Another idea (*[*U-B-AI: universal basic income and the future of work*](https://basicincometoday.com/u-b-ai-universal-basic-income-and-the-future-of-work/#:~:text=Geoffrey%20Hinton%2C%20a%20prominent%20AI,%E2%80%9D)*) l Clause* mentioned earlier: if an AI firm achieves extraordinary profits (say, beyond a certain ROI), it would be obligated to share those – essentially an extreme progressive tax triggered by success. Traditional tax bases might also shift; with fewer people earning wages, governments might rely more on taxing consumption or capital. International tax coordination could be important too, to avoid races to the bottom as capital becomes even more mobile (e.g., an AGI company could reside anywhere virtually). Policymakers will likely need to modernize antitrust and intellectual property law as well: preventing monopolistic control of AGI (through stricter antitrust enforcement or even treating key algorithms as public utilities) may be considered to keep markets compe ([AI may increase economic inequality - MINDFUL TECHNICS](https://mindfultechnics.com/ai-may-increase-economic-inequality/#:~:text=Although%20AI%20may%20increase%20economic,gains%20or%20profits%20from%20automation)) handful of firms control all AGI services, they could extract rent indefinitely; breaking that control or regulating it (like utilities) might spread benefits to consumers via lower prices and wider access.\n- **Public Investment (**[**Cullen O'Keefe: The Windfall Clause — Sharing the Benefits of Advanced AI | Effective Altruism**](https://www.effectivealtruism.org/articles/cullen-okeefe-the-windfall-clause-sharing-the-benefits-of-advanced-ai#:~:text=In%20a%20phrase%2C%20the%20Windfall,close%20to%20reaching%2C%20extreme%20benefits)**) :** Another approach is for the public (government or consortiums) to take a more active role in developing and owning AGI technologies. This could involve direct government funding of AGI research with mandates about open results, or even nationalizing certain AI capabilities for public use. If, for instance, a government developed an AGI for climate modeling and drug discovery, the *intellectual property* and its dividends could be public domain, ensuring benefits aren’t locked behind patents. Some economists suggest models where citizens each have a stake in an “AI divide ([It’s Not Too Late to Stop the Monopolization of AI - Inequality.org](https://inequality.org/article/its-not-too-late-to-stop-the-monopolization-of-ai/#:~:text=society%20solve%20complex%20problems%20and,already%20hold%20over%20our%20lives)) y a share of the returns on national AI productivity. Such schemes would function like a sovereign wealth fund: e.g., tax revenue or equity from AI companies goes into a fund that pays out to citizens (similar to how Norway uses oil revenues). This aligns with the idea that the knowledge and advancements leading to AGI are a collective achievement (built on public-funded science, etc.), so the outcomes should serve the common good. We might also see public-private partnerships ensuring that AGI is directed toward socially beneficial projects that the private sector might underprovide (like fundamental research or public health efforts).\n- **Regulation and Ethical Governance:** To mitigate risks, governments will likely impose regulations on AGI deployment. This might include safety standards (to ensure AI systems behave as intended and do not cause catastrophic harm), auditing requirements (to monitor how companies use AGI, especially with respect to labor practices and market manipulation), and perhaps limits on certain uses (for instance, an outright ban on fully autonomous weapons has been discussed internationally). In the economic realm, regulations could protect workers’ rights in an AI workplace (for example, preventing AI from being used for excessiv ([Cullen O'Keefe: The Windfall Clause — Sharing the Benefits of Advanced AI | Effective Altruism](https://www.effectivealtruism.org/articles/cullen-okeefe-the-windfall-clause-sharing-the-benefits-of-advanced-ai#:~:text=lot%20of%20work%20ahead%20of,us)) e or unfair scheduling). **Labor laws** may need updating: concepts like what constitutes an “employee” or work hours could be challenged if AI agents do work – do we tax their output like labor or treat it purely as capital? New legal frameworks might classify AI systems in ways relevant to liability and taxation. Another idea is phased integration – requiring, say, that for a period AI acts in an *assistive* role rather than fully replacing humans in certain critical professions (to ensure oversight and a slower transition).\n- **Innovation Policy:** To encourage positive uses of AGI, governments can fund research into AI for social good (like AI for healthcare, education, environmental sustainability). Prizes or grants could be set up for AGI solutions to key challenges. Additionally, easing the transition for workers could involve policies to encourage job-sharing or reduced work weeks, leveraging AI productivity to give people more leisure without sacrificing output. If productivity doubles, perhaps people can work 20 hours instead of 40 for the same pay – that’s another way to distribute gains (in time rather than money). Such ideas were floated even in the early 20th century when automation was increasing, but AGI might finally make them realistic.\n-\n- In implementing these measures, **flexibility and adaptability** will be crucial. Policymakers should monitor AI’s effects closely (data on job displacement, wage changes, who is benefiting economically) and be ready to adjust course. For example, if it turns out UBI at a modest level isn’t enough, it might need to scale up; if inequality is still rising, taxes might need to become more progressive; if, conversely, innovation is being hampered by too heavy regulation, some recalibration might be needed to avoid stifling the golden goose. There is also a need for **global policy coordination**, which brings us to the international aspect.\n- ### **3.3 International Competition and Cooperation**\n-\n- AGI development is not occurring in a vacuum – nations and corporations are effectively in a **race** to achieve advanced AI, given the enormous economic and strategic advantages at stake. As Russian President Vladimir Putin remarked in 2017, *“Whoever leads in AI will rule the world.”*. This blunt statement captures the geopolitical significance attributed to AI superiority. A country or entity that first develops AGI could potentially leverage it for dominating global markets, boosting its military power, and even influencing other nations’ economies (via control of key AI services or breakthroughs). This dynamic is already evident in national AI strategies: for example, **China’s government has a strategic plan to be the world leader in AI by 2030**, investing tens of billions into AI research and startups. The United States, for its part, is heavily funding AI through military and academic channels, and the EU is crafting its own approach. We can expect the economic competition to intensify as AGI nears – nations may enact protectionist measures (like restricting export of AI chips or software) to maintain an edge or preve ([Putin Wants Russia to Win the Artificial Intelligence Race. Here's ...](https://www.themoscowtimes.com/2023/11/14/putin-wants-russia-to-win-the-artificial-intelligence-race-heres-why-it-wont-a83103#:~:text=%E2%80%9CWhoever%20leads%20in%20AI%20will,the%202017%20Russian%20school%20year)) m gaining parity.\n-\n- **Shift in Global Economic Power:** If AGI is achieved by one country first (say Country A), it could see a rapid surge in productivity and wealth, potentially outpacing other economies dramatically. This might resemble the impact the industrial revolution had – nations that industrialized early grew much faster than those that didn’t, leading to colonial era power imbalances. However, unlike coal and steel, AGI could diffuse more quickly if not guarded, because it’s mostly software. There’s a scenario where ([Who will lead in the age of artificial intelligence? - Brookings Institution](https://www.brookings.edu/articles/who-will-lead-in-the-age-of-artificial-intelligence/#:~:text=Who%20will%20lead%20in%20the,and%20acquisition%20deals%20since%202015)) GI nation tries to keep the knowledge secret, treating it like the ultimate comparative advantage. That could lead to other nations falling behind economically, or trying to **steal or replicate** the technology (espionage, reverse-engineering). Economic competition might then hinge on computing resources and talent – similar to an arms race. Some worry this could even spark conflict if one nation fears another getting a decisively superior AI (analogous to nuclear arms race logic, though the weapon here is economic and informational dominance). On the other hand, if AGI is internationally collaborative or open, it might be shared and help all economies grow (a more optimistic outcome).\n-\n- **Need for Cooperation and Global Governance:** Because AGI has world-altering potential, many argue that international cooperation is crucial to ensure it benefits humanity as a whole. This could take the form of treaties or agreements on AGI use – for example, agreements that no country will withhold life-saving AI innovations, or that they will share a portion of AI’s economic benefits with less-developed nations (perhaps via something like an AI global fund). An analogy is how global public goods like cures for diseases or climate change solutions are handled; AGI’s knowledge might be considered a global public good under some frameworks. There have been calls for a kind of *“IAEA for AI”* – a global agency to monitor and guide AI development (the IAEA oversees nuclear tech to prevent proliferation). Such an agency could coordinate safety standards and also mediate the economic implications, perhaps discouraging destructive economic competition (like using AI to undercut all labor standards, etc.). Of course, getting nations to agree is challenging – trust is needed, and verification.\n-\n- From a competition standpoint, **international trade and labor markets** will also shift. Countries with high-skilled tech workers might benefit more initially (as they create AI), but eventually, AGI might make human labor less central, so having natural resources or data might become key advantages instead. Data-rich nations (population size, surveillance, etc.) like China could hold advantages in training AI. Meanwhile, countries reliant on cheap labor exports (manufacturing hubs in Asia or garment industries in poorer countries) could see their comparative advantage erode as robots can produce goods anywhere at low cost. This could necessitate a development rethink – those countries might need support to diversify their economies. Perhaps global institutions (World Bank, IMF) would create programs to assist developing nations in the AI transition, similar to how they assist with climate adaptation funds.\n-\n- **Avoiding a Zero-Sum Mentality:** If every nation tries to maximize its own AI power without regard for others, we might see tariff wars over AI tech, or talent brain-drains that hurt smaller economies. Alternatively, nations could adopt a more cooperative stance: sharing research, jointly managing risks, and even sharing in gains. For example, if AGI dramatically expands global wealth, an agreement could be made to allocate a percentage of that increase to global challenges (poverty, health, climate) under UN auspices – effectively ensuring AI’s bounty contributes to the UN Sustainable Development Goals. While idealistic, such proposals echo earlier calls during technological revolutions to address global inequality.\n-\n- In terms of security, countries will need to consider that superintelligent AI in an adversary’s hands could be a threat. This might ironically encourage cooperation – much like nations cooperate on nuclear arms control, realizing that an unchecked arms race endangers all. The difference is AI can also hugely benefit economies, so there is strong incentive to push ahead. We may see **bilateral or multilateral agreements** to share certain critical AI research (to reduce the temptation for conflict) while competing in the marketplace under agreed rules.\n-\n- Finally, international bodies might promote norms or guidelines for ethical AI use in the economy (preventing exploitation, protecting privacy even as AI collects data, etc.). If one nation sets very lax rules to gain an edge (say, no data privacy so its AI can train better, or no worker protections so companies can automate freely), others might feel pressure to follow (the “race to the bottom” problem). Hence a coordinated approach – say through the OECD or G20 establishing baseline standards – could help maintain fair competition and uphold values.\n-\n- **Summing up international aspects:** AGI could realign global economic leadership depending on who attains it and how it is shared. There is both a risk of *intense rivalry* (even conflict) and an opportunity for *unprecedented cooperation*. The development of AGI might be a unifying challenge for humanity – much like climate change or a global pandemic, it is a phenomenon that ultimately affects everyone. Some experts believe that mitigating existential and economic risks from AGI *must* be a global priority requiring collective action. The extent to which nations rise to that challenge will influence whether AGI leads to a golden age of global prosperity or a more fractured world of haves and have-nots.\n- ## **Conclusion**\n-\n- Artificial General Intelligence and superintelligence promise to be *transformative economic forces*, on par with or exceeding past industrial revolutions in impact. They carry the potential for astonishing improvements in productivity, wealth creation, and innovation – possibly solving problems long thought intractable and enabling a world of abundance. At the same time, they pose severe challenges: the disruption of labor markets, the concentration of economic power, the need to overhaul social contracts, and geopolitical tensions over AI dominance.\n-\n- History has shown that technology’s benefits are not automatic; they depend on how society manages the transition. Thus, the adven ([Artificial general intelligence - Wikipedia](https://en.wikipedia.org/wiki/Artificial_general_intelligence#:~:text=13.%20,Are%20AI%27s%20Doomsday%20Scenarios%20Worth)) ([Artificial general intelligence - Wikipedia](https://en.wikipedia.org/wiki/Artificial_general_intelligence#:~:text=15.%20%5E%20,Kurzweil%202005%2C%20p.%C2%A0260)) nd political institutions profoundly. Proactive policies – from education and social safety nets to fair distribution mechanisms and international treaties – will be crucial in steering the outcome towards inclusive prosperity rather than social upheaval. As we stand possibly on the cusp of this new era (whether it arrives in a decade or many decades hence), the debates involving Turing’s theoretical queries, McCarthy’s early conjectures, Bostrom’s warnings, and Kurzweil’s predictions are moving from academia and futurism into the realm of concrete planning. The **economic impact of AGI** will not be a singular event but an ongoing process that society must continuously navigate. By learning from past technological transformations and staying adaptable, humanity can aim to leverage AGI as a tool to *elevate* human well-being globally, rather than undermine it. Ensuring that “the last invention” truly benefits *all*, and not just a few, may be one of the greatest collective responsibilities we have ever faced.\n-\n- **\n\n## Current Landscape (2025)\n\n- Industry adoption and implementations\n  - Metaverse platforms continue to evolve with focus on interoperability and open standards\n  - Web3 integration accelerating with decentralised identity and asset ownership\n  - Enterprise adoption growing in virtual collaboration, training, and digital twins\n  - UK companies increasingly active in metaverse development and immersive technologies\n\n- Technical capabilities\n  - Real-time rendering at photorealistic quality levels\n  - Low-latency networking enabling seamless multi-user experiences\n  - AI-driven content generation and procedural world building\n  - Spatial audio and haptics enhancing immersion\n\n- UK and North England context\n  - Manchester: Digital Innovation Factory supports metaverse startups and research\n  - Leeds: Holovis leads in immersive experiences for entertainment and training\n  - Newcastle: University research in spatial computing and interactive systems\n  - Sheffield: Advanced manufacturing using digital twin technology\n\n- Standards and frameworks\n  - Metaverse Standards Forum driving interoperability protocols\n  - WebXR enabling browser-based immersive experiences\n  - glTF and USD for 3D asset interchange\n  - Open Metaverse Interoperability Group defining cross-platform standards\n\n## Metadata\n\n- **Last Updated**: 2025-11-16\n- **Review Status**: Automated remediation with 2025 context\n- **Verification**: Academic sources verified\n- **Regional Context**: UK/North England where applicable",
  "properties": {
    "id": "artificial-general-intelligence-owl-axioms",
    "collapsed": "true",
    "- ontology": "true",
    "- term-id": "mv-327352489782",
    "- preferred-term": "Artificial General Intelligence",
    "- source-domain": "metaverse",
    "- status": "active",
    "- public-access": "true",
    "- definition": "A component of the metaverse ecosystem focusing on artificial general intelligence.",
    "- maturity": "mature",
    "- authority-score": "0.85",
    "- owl:class": "mv:ArtificialGeneralIntelligence",
    "- owl:physicality": "ConceptualEntity",
    "- owl:role": "Concept",
    "- belongsToDomain": "[[MetaverseDomain]]",
    "- enables": "[[ImmersiveExperience]], [[Presence]], [[SpatialComputing]]",
    "- requires": "[[DisplayTechnology]], [[TrackingSystem]], [[RenderingEngine]]",
    "- bridges-to": "[[HumanComputerInteraction]], [[ComputerVision]], [[Robotics]]"
  },
  "backlinks": [
    "Convergence",
    "AI Risks"
  ],
  "wiki_links": [
    "ComputerVision",
    "Presence",
    "MetaverseDomain",
    "TrackingSystem",
    "DisplayTechnology",
    "RenderingEngine",
    "ImmersiveExperience",
    "Robotics",
    "HumanComputerInteraction",
    "SpatialComputing"
  ],
  "ontology": {
    "term_id": "mv-327352489782",
    "preferred_term": "Artificial General Intelligence",
    "definition": "A component of the metaverse ecosystem focusing on artificial general intelligence.",
    "source_domain": "metaverse",
    "maturity_level": null,
    "authority_score": 0.85
  }
}