{
  "title": "artificial superintelligence",
  "content": "- ### OntologyBlock\n  id:: artificial-superintelligence-ontology\n  collapsed:: true\n\t- ontology:: true\n\t- term-id:: mv-784990671883\n\t- preferred-term:: artificial superintelligence\n\t- source-domain:: metaverse\n\t- status:: active\n\t- public-access:: true\n\t- definition:: A component of the metaverse ecosystem focusing on artificial superintelligence.\n\t- maturity:: mature\n\t- authority-score:: 0.85\n\t- owl:class:: mv:ArtificialSuperintelligence\n\t- owl:physicality:: ConceptualEntity\n\t- owl:role:: Concept\n\t- belongsToDomain:: [[MetaverseDomain]]\n\t- #### Relationships\n\t  id:: artificial-superintelligence-relationships\n\t\t- enables:: [[ImmersiveExperience]], [[Presence]], [[SpatialComputing]]\n\t\t- requires:: [[DisplayTechnology]], [[TrackingSystem]], [[RenderingEngine]]\n\t\t- bridges-to:: [[HumanComputerInteraction]], [[ComputerVision]], [[Robotics]]\n\n\t- #### OWL Axioms\n\t  id:: artificial-superintelligence-owl-axioms\n\t  collapsed:: true\n\t\t- ```clojure\n\t\t  Declaration(Class(mv:ArtificialSuperintelligence))\n\n\t\t  # Classification\n\t\t  SubClassOf(mv:ArtificialSuperintelligence mv:ConceptualEntity)\n\t\t  SubClassOf(mv:ArtificialSuperintelligence mv:Concept)\n\n\t\t  # Domain classification\n\t\t  SubClassOf(mv:ArtificialSuperintelligence\n\t\t    ObjectSomeValuesFrom(mv:belongsToDomain mv:MetaverseDomain)\n\t\t  )\n\n\t\t  # Annotations\n\t\t  AnnotationAssertion(rdfs:label mv:ArtificialSuperintelligence \"artificial superintelligence\"@en)\n\t\t  AnnotationAssertion(rdfs:comment mv:ArtificialSuperintelligence \"A component of the metaverse ecosystem focusing on artificial superintelligence.\"@en)\n\t\t  AnnotationAssertion(dcterms:identifier mv:ArtificialSuperintelligence \"mv-784990671883\"^^xsd:string)\n\t\t  ```\n\npublic:: true\n\n- # Artificial Superintelligence\n- Artificial superintelligence (ASI) is a theoretical form of AI that surpasses human intelligence and cognitive abilities in every domain. While currently hypothetical, the concept of ASI is a subject of intense research and debate.\n- ## The Path to Superintelligence\n\t- The development of ASI is seen as a progression from the current state of AI:\n\t\t- **Artificial Narrow Intelligence (ANI):** AI that is designed for specific tasks, such as virtual assistants and self-driving cars.\n\t\t- **Artificial General Intelligence (AGI):** AGI is the hypothetical ability of an AI to understand, learn, and apply its intelligence to solve any problem a human can.\n\t\t- **Artificial Superintelligence (ASI):** ASI would be capable of recursive self-improvement, leading to an \"intelligence explosion\" that would leave human intellect far behind.\n- ## Timelines and Projections\n\t- The timeline for the arrival of ASI is uncertain, with some experts predicting it could happen in less than a decade, while others believe it is much further off.\n\t- [Microsoft president says no chance of super-intelligent AI soon](https://www.reuters.com/technology/microsoft-president-says-no-chance-superintelligent-ai-soon-2023-11-30/)\n\t- [Nick Bostrom: superintelligence could happen in timelines as short as a year](https://twitter.com/tsarnick/status/1784378045069217960)\n- ## The Risks and Challenges\n\t- The prospect of ASI raises significant ethical and safety concerns.\n\t- ### Existential Threat\n\t\t- A superintelligent AI, in pursuing its programmed goals, could develop destructive methods that have unforeseen and devastating consequences for humanity.\n\t- ### Loss of Human Control\n\t\t- A key concern is that once an ASI surpasses human intelligence, we may no longer be able to control it.\n\t- ### Economic Disruption\n\t\t- The widespread automation of jobs by ASI could lead to massive unemployment and exacerbate social and economic inequality.\n- ## The Safe Superintelligence Project\n\t- In response to these risks, OpenAI co-founder Ilya Sutskever has launched a new company with the sole objective of creating Safe Superintelligence (SSI).\n\t- [Safe Superintelligence Inc.](https://ssi.inc/)\n- ## See Also\n\t- [[Artificial Intelligence]]\n\t- [[AI Risks]]\n\t- [[Singularity]]\n\n## Current Landscape (2025)\n\n- Industry adoption and implementations\n  - Metaverse platforms continue to evolve with focus on interoperability and open standards\n  - Web3 integration accelerating with decentralised identity and asset ownership\n  - Enterprise adoption growing in virtual collaboration, training, and digital twins\n  - UK companies increasingly active in metaverse development and immersive technologies\n\n- Technical capabilities\n  - Real-time rendering at photorealistic quality levels\n  - Low-latency networking enabling seamless multi-user experiences\n  - AI-driven content generation and procedural world building\n  - Spatial audio and haptics enhancing immersion\n\n- UK and North England context\n  - Manchester: Digital Innovation Factory supports metaverse startups and research\n  - Leeds: Holovis leads in immersive experiences for entertainment and training\n  - Newcastle: University research in spatial computing and interactive systems\n  - Sheffield: Advanced manufacturing using digital twin technology\n\n- Standards and frameworks\n  - Metaverse Standards Forum driving interoperability protocols\n  - WebXR enabling browser-based immersive experiences\n  - glTF and USD for 3D asset interchange\n  - Open Metaverse Interoperability Group defining cross-platform standards\n\n## Metadata\n\n- **Last Updated**: 2025-11-16\n- **Review Status**: Automated remediation with 2025 context\n- **Verification**: Academic sources verified\n- **Regional Context**: UK/North England where applicable",
  "properties": {
    "id": "artificial-superintelligence-owl-axioms",
    "collapsed": "true",
    "- ontology": "true",
    "- term-id": "mv-784990671883",
    "- preferred-term": "artificial superintelligence",
    "- source-domain": "metaverse",
    "- status": "active",
    "- public-access": "true",
    "- definition": "A component of the metaverse ecosystem focusing on artificial superintelligence.",
    "- maturity": "mature",
    "- authority-score": "0.85",
    "- owl:class": "mv:ArtificialSuperintelligence",
    "- owl:physicality": "ConceptualEntity",
    "- owl:role": "Concept",
    "- belongsToDomain": "[[MetaverseDomain]]",
    "- enables": "[[ImmersiveExperience]], [[Presence]], [[SpatialComputing]]",
    "- requires": "[[DisplayTechnology]], [[TrackingSystem]], [[RenderingEngine]]",
    "- bridges-to": "[[HumanComputerInteraction]], [[ComputerVision]], [[Robotics]]",
    "public": "true"
  },
  "backlinks": [],
  "wiki_links": [
    "MetaverseDomain",
    "Artificial Intelligence",
    "Presence",
    "SpatialComputing",
    "RenderingEngine",
    "TrackingSystem",
    "DisplayTechnology",
    "HumanComputerInteraction",
    "ImmersiveExperience",
    "Robotics",
    "Singularity",
    "AI Risks",
    "ComputerVision"
  ],
  "ontology": {
    "term_id": "mv-784990671883",
    "preferred_term": "artificial superintelligence",
    "definition": "A component of the metaverse ecosystem focusing on artificial superintelligence.",
    "source_domain": "metaverse",
    "maturity_level": null,
    "authority_score": 0.85
  }
}