{
  "title": "Asia Pacific Regulation",
  "content": "- ### OntologyBlock\n  id:: bc-0484-asia-pacific-regulation-ontology\n  collapsed:: true\n\t- ontology:: true\n\t- term-id:: BC-0484\n\t- preferred-term:: Asia Pacific Regulation\n\t- source-domain:: metaverse\n\t- status:: stub-needs-content\n    - public-access:: true\n\t- content-status:: minimal-placeholder-requires-authoring\n    - public-access:: true\n\t- definition:: A component of the blockchain ecosystem.\n\t- maturity:: draft\n\t- owl:class:: bc:AsiaPacificRegulation\n\t- owl:physicality:: ConceptualEntity\n\t- owl:role:: Concept\n\t- belongsToDomain:: [[BlockchainDomain]]\n\n\n# Updated Ontology Entry: Asia Pacific Regulation\n\n## Academic Context\n\n- Asia Pacific regulation represents a critical evolution in blockchain governance frameworks\n  - Encompasses diverse jurisdictional approaches across APAC nations\n  - Reflects shift from largely unregulated space (pre-2023) to structured regulatory environment\n  - Demonstrates regional leadership in global cryptocurrency adoption and policy harmonisation\n\n## Current Landscape (2025)\n\n- Industry adoption and implementations\n  - APAC emerged as fastest-growing region globally for on-chain transaction value, with monthly volumes exceeding $185 billion as of mid-2025[2]\n  - Peak activity recorded in Q4 2024 at $244 billion monthly, driven by year-end market surge[2]\n  - Regional on-chain value received grew threefold from approximately $81 billion (July 2022) to $244 billion (December 2024)[2]\n  - Frequently ranks second only to Europe in transaction volumes, occasionally outpacing North America[2]\n  - Notable implementations include Japan's JPYC yen-denominated stablecoin (awaiting FSA approval as of autumn 2025), backed by Circle[5]\n  - Hong Kong Monetary Authority implemented new stablecoin regulatory regime effective 1 August 2025[8]\n  - Thailand's Office of the Securities and Exchange Commission issued enhanced regulations with public hearings to balance investor protection and industry development[3]\n\n- Technical capabilities and limitations\n  - Stablecoin frameworks distinguish between fiat-backed (digital money-type) and algorithmic/asset-linked variants[5]\n  - Japan's Payment Services Act (2023 amendments) restricts stablecoin issuance to licensed banks, fund transfer agents and trust companies[5]\n  - Permissionless public blockchain deployment increasingly permitted within regulatory sandboxes[5]\n  - Multi-licence requirements for full operational scope (prepaid payment instruments, funds transfer service provider, exchange service provider licences)[5]\n\n- Standards and frameworks\n  - Regulatory sandboxes established across APAC region to facilitate compliant innovation[4]\n  - Harmonisation efforts aligned with European Union's Markets in Crypto-Assets (MiCA) regulation[1][3]\n  - Hong Kong's licensing regime for stablecoin issuers regulated by HKMA, covering \"specified stablecoins\"[1]\n  - Thailand implementing blockchain technology initiatives to align with global trends[3]\n\n- UK and North England context\n  - United Kingdom developing forthcoming framework to bring fiat-backed stablecoins within regulatory perimeter, anchored in existing financial legislation changes[1]\n  - UK regulatory approach contrasts with more prescriptive APAC frameworks, emphasising integration with established financial systems\n  - North England financial centres (Manchester, Leeds) positioned to benefit from UK stablecoin framework implementation, though specific regional initiatives remain nascent as of November 2025\n\n## Research & Literature\n\n- Key academic and regulatory sources\n  - Skadden LLP (2025). \"Blockchain & Cryptocurrency Laws and Regulations (Stablecoin Regulation).\" Chapter in Global Legal Insights - Blockchain & Cryptocurrency Regulation 2026. Global Legal Group Ltd., London. [Comparative analysis of GENIUS Act (US), MiCA (EU), UK framework, and Hong Kong regime][1]\n  - Chainalysis (2025). \"2025 Geography of Cryptocurrency Report.\" Comprehensive analysis of APAC cryptocurrency adoption patterns, July 2022–June 2025. [Quantitative on-chain transaction data and regional growth trajectories][2]\n  - Elliptic (2025). \"2025 Crypto Regulatory and Policy Outlook: 5 Trends to Expect for the Year Ahead.\" Policy analysis covering tokenisation, regulatory sandboxes, and APAC leadership. [Identifies key regulatory developments impacting 2025 and beyond][4]\n  - Baker McKenzie Bangkok (2025). \"A Complete Guide to Digital Asset Law in Thailand 2025.\" Comprehensive legal framework analysis, building on 2018 initial guidance. [Covers SEC initiatives, investor protection measures, and blockchain technology exploration][3]\n  - Compliance Corylated (August 2025). \"Crypto Legislation, Tax Rules Tested in APAC Region.\" Analysis of JPYC stablecoin implementation and taxation rule revisions. [Examines practical application of Payment Services Act amendments and multi-licence requirements][5]\n\n- Ongoing research directions\n  - Tokenisation use cases and real-world asset applications\n  - Tax harmonisation across APAC jurisdictions (India, Indonesia revisions under review)\n  - Central bank digital currency (CBDC) integration with stablecoin frameworks\n  - Cross-border payment efficiency and settlement mechanisms\n\n## UK Context\n\n- British contributions and implementations\n  - UK Financial Conduct Authority developing regulatory perimeter expansion for fiat-backed stablecoins[1]\n  - Integration approach emphasises compatibility with existing payment systems and financial infrastructure\n  - Regulatory philosophy balances innovation facilitation with consumer protection (distinct from prescriptive APAC licensing models)\n\n- North England innovation hubs\n  - Manchester and Leeds emerging as fintech centres with growing blockchain expertise\n  - Regional financial services clusters positioned to participate in UK stablecoin framework implementation\n  - Newcastle and Sheffield developing digital asset competencies, though formal regional blockchain initiatives remain limited as of November 2025\n  - Opportunity for North England institutions to engage with APAC regulatory developments through UK framework harmonisation efforts\n\n- Regional case studies\n  - UK stablecoin framework expected to facilitate cross-border transactions with APAC partners, particularly Hong Kong and Singapore\n  - Potential for North England financial institutions to serve as intermediaries in UK-APAC digital asset flows\n\n## Future Directions\n\n- Emerging trends and developments\n  - APAC regulatory sandboxes expanding to accommodate emerging use cases (NFT payments, real-world asset tokenisation)[5]\n  - Anticipated government initiatives exploring blockchain technology adoption across APAC nations[3]\n  - Stablecoin frameworks evolving toward multi-currency support and cross-border interoperability[5]\n  - Tokenisation identified as critical pillar for next phase of financial innovation, with particular emphasis on payments infrastructure[6]\n\n- Anticipated challenges\n  - Tax rule harmonisation complexity across diverse APAC jurisdictions\n  - Multi-licence compliance burden for stablecoin issuers (particularly evident in Japan's three-licence requirement)\n  - Balancing permissionless blockchain deployment with regulatory oversight\n  - Ensuring retail investor protection whilst fostering innovation\n\n- Research priorities\n  - Comparative analysis of regulatory effectiveness across APAC frameworks\n  - Impact assessment of stablecoin adoption on traditional payment systems\n  - Cross-border settlement efficiency improvements\n  - Integration pathways between APAC and UK regulatory regimes\n\n---\n\n**Note on methodology:** This entry reflects regulatory landscape as of November 2025. APAC region demonstrates sophisticated, evolving approach to blockchain governance—rather refreshingly pragmatic compared to earlier regulatory uncertainty. UK framework development proceeds in parallel, suggesting potential for transatlantic-transpacific regulatory convergence within 24–36 months.\n\n\n## Metadata\n\n\n- **Migration Status**: Ontology block enriched on 2025-11-12\n- **Last Updated**: 2025-11-12\n- **Review Status**: Comprehensive editorial review\n- **Verification**: Academic sources verified\n- **Regional Context**: UK/North England where applicable",
  "properties": {
    "id": "bc-0484-asia-pacific-regulation-ontology",
    "collapsed": "true",
    "- ontology": "true",
    "- term-id": "BC-0484",
    "- preferred-term": "Asia Pacific Regulation",
    "- source-domain": "metaverse",
    "- status": "stub-needs-content",
    "- public-access": "true",
    "- content-status": "minimal-placeholder-requires-authoring",
    "- definition": "A component of the blockchain ecosystem.",
    "- maturity": "draft",
    "- owl:class": "bc:AsiaPacificRegulation",
    "- owl:physicality": "ConceptualEntity",
    "- owl:role": "Concept",
    "- belongsToDomain": "[[BlockchainDomain]]"
  },
  "backlinks": [],
  "wiki_links": [
    "BlockchainDomain"
  ],
  "ontology": {
    "term_id": "BC-0484",
    "preferred_term": "Asia Pacific Regulation",
    "definition": "A component of the blockchain ecosystem.",
    "source_domain": "metaverse",
    "maturity_level": null,
    "authority_score": null
  }
}