{
  "title": "AUC",
  "content": "- ### OntologyBlock\n  id:: auc-ontology\n  collapsed:: true\n\t- ontology:: true\n\t- term-id:: AI-0113\n\t- preferred-term:: AUC\n\t- source-domain:: ai\n\t- status:: draft\n    - public-access:: true\n\t- definition:: Area Under the Curve (AUC), specifically the area under the Receiver Operating Characteristic (ROC) curve (ROC-AUC or AUROC), is a single scalar performance metric for binary classifiers representing the probability that the model ranks a randomly chosen positive instance higher than a randomly chosen negative instance, providing threshold-independent assessment of a classifier's discriminative ability with values ranging from 0 to 1, where 0.5 indicates random guessing, 1.0 represents perfect classification, and values above 0.5 indicate better-than-random performance.\n\n\n## Academic Context\n\n- Brief contextual overview\n\t- Area Under the Curve (AUC), particularly ROC-AUC, is a cornerstone metric in binary classification, widely adopted for its ability to summarise a model’s discriminative power across all possible decision thresholds\n\t- The ROC curve plots the True Positive Rate (TPR) against the False Positive Rate (FPR) at varying thresholds, and the area under this curve (AUC) provides a single scalar value that quantifies overall performance\n\t- The interpretation of AUC as the probability that a randomly chosen positive instance is ranked higher than a randomly chosen negative instance is both intuitive and mathematically sound\n\n- Key developments and current state\n\t- The ROC-AUC framework remains a gold standard for threshold-independent evaluation, especially in fields where class imbalance is common, such as medical diagnostics and fraud detection\n\t- Recent research has focused on extending ROC-AUC concepts to multi-class settings and integrating them with other metrics for more nuanced evaluation\n\n- Academic foundations\n\t- The ROC curve originated in signal detection theory and was later adapted for machine learning and statistics\n\t- The AUC metric is grounded in the theory of statistical discrimination and has been rigorously validated in numerous empirical studies\n\n## Current Landscape (2025)\n\n- Industry adoption and implementations\n\t- ROC-AUC is widely used in healthcare, finance, and cybersecurity for evaluating binary classifiers\n\t- Notable organisations and platforms\n\t\t- NHS Digital in the UK employs ROC-AUC for evaluating diagnostic models in clinical settings\n\t\t- Financial institutions like Barclays and Lloyds Banking Group use ROC-AUC for fraud detection and credit scoring\n\t\t- Tech companies such as Google and Microsoft incorporate ROC-AUC in their machine learning frameworks and cloud services\n\n- UK and North England examples where relevant\n\t- In Manchester, the Manchester Centre for Health Informatics uses ROC-AUC to assess the performance of predictive models in public health initiatives\n\t- Leeds City Council has implemented ROC-AUC in their data-driven decision-making processes for urban planning and social services\n\t- Newcastle University’s Institute for Data Science and Artificial Intelligence applies ROC-AUC in research projects related to environmental monitoring and smart cities\n\t- Sheffield Hallam University’s Advanced Manufacturing Research Centre (AMRC) uses ROC-AUC for quality control and predictive maintenance in manufacturing\n\n- Technical capabilities and limitations\n\t- ROC-AUC is robust to class imbalance and provides a comprehensive view of model performance across all thresholds\n\t- However, it can be less informative in highly imbalanced datasets, where precision-recall curves may offer a more nuanced perspective\n\t- The metric is sensitive to the distribution of scores and can be affected by outliers\n\n- Standards and frameworks\n\t- ROC-AUC is included in major machine learning libraries such as scikit-learn, TensorFlow, and PyTorch\n\t- It is a recommended metric in industry standards and guidelines, including those from the UK’s National Institute for Health and Care Excellence (NICE)\n\n## Research & Literature\n\n- Key academic papers and sources\n\t- Hanley, J. A., & McNeil, B. J. (1982). The meaning and use of the area under a receiver operating characteristic (ROC) curve. Radiology, 143(1), 29-36. https://doi.org/10.1148/radiology.143.1.7063747\n\t- Fawcett, T. (2006). An introduction to ROC analysis. Pattern Recognition Letters, 27(8), 861-874. https://doi.org/10.1016/j.patrec.2005.10.010\n\t- Davis, J., & Goadrich, M. (2006). The relationship between Precision-Recall and ROC curves. Proceedings of the 23rd International Conference on Machine Learning, 233-240. https://doi.org/10.1145/1143844.1143874\n\n- Ongoing research directions\n\t- Extending ROC-AUC to multi-class and multi-label classification problems\n\t- Developing more robust metrics for highly imbalanced datasets\n\t- Integrating ROC-AUC with other evaluation metrics for a more comprehensive assessment\n\n## UK Context\n\n- British contributions and implementations\n\t- The UK has been at the forefront of applying ROC-AUC in healthcare, with significant contributions from institutions like the University of Oxford and Imperial College London\n\t- The NHS has developed guidelines for the use of ROC-AUC in clinical decision support systems\n\n- North England innovation hubs (if relevant)\n\t- Manchester, Leeds, Newcastle, and Sheffield are home to several research centres and innovation hubs that actively use and develop ROC-AUC methodologies\n\t- These regions have seen a surge in data science and machine learning applications, with ROC-AUC playing a crucial role in evaluating the performance of predictive models\n\n- Regional case studies\n\t- Manchester Centre for Health Informatics: ROC-AUC is used to evaluate models for early detection of chronic diseases\n\t- Leeds City Council: ROC-AUC is applied in predictive analytics for urban planning and social services\n\t- Newcastle University: ROC-AUC is used in environmental monitoring and smart city projects\n\t- Sheffield Hallam University: ROC-AUC is employed in quality control and predictive maintenance in manufacturing\n\n## Future Directions\n\n- Emerging trends and developments\n\t- Integration of ROC-AUC with other metrics for more comprehensive evaluation\n\t- Development of new methods for handling highly imbalanced datasets\n\t- Application of ROC-AUC in emerging fields such as autonomous systems and personalized medicine\n\n- Anticipated challenges\n\t- Ensuring the robustness of ROC-AUC in the face of increasing data complexity and volume\n\t- Addressing the limitations of ROC-AUC in highly imbalanced datasets\n\t- Standardizing the use of ROC-AUC across different industries and applications\n\n- Research priorities\n\t- Extending ROC-AUC to multi-class and multi-label classification\n\t- Developing more robust and interpretable metrics for model evaluation\n\t- Exploring the integration of ROC-AUC with other evaluation frameworks\n\n## References\n\n1. Hanley, J. A., & McNeil, B. J. (1982). The meaning and use of the area under a receiver operating characteristic (ROC) curve. Radiology, 143(1), 29-36. https://doi.org/10.1148/radiology.143.1.7063747\n2. Fawcett, T. (2006). An introduction to ROC analysis. Pattern Recognition Letters, 27(8), 861-874. https://doi.org/10.1016/j.patrec.2005.10.010\n3. Davis, J., & Goadrich, M. (2006). The relationship between Precision-Recall and ROC curves. Proceedings of the 23rd International Conference on Machine Learning, 233-240. https://doi.org/10.1145/1143844.1143874\n4. NHS Digital. (2025). Guidelines for the use of ROC-AUC in clinical decision support systems. https://digital.nhs.uk/\n5. Manchester Centre for Health Informatics. (2025). ROC-AUC in public health initiatives. https://www.manchester.ac.uk/research/groups/manchester-centre-for-health-informatics/\n6. Leeds City Council. (2025). Data-driven decision-making in urban planning and social services. https://www.leeds.gov.uk/\n7. Newcastle University. (2025). Environmental monitoring and smart city projects. https://www.ncl.ac.uk/\n8. Sheffield Hallam University. (2025). Quality control and predictive maintenance in manufacturing. https://www.shu.ac.uk/\n\n\n## Metadata\n\n- **Last Updated**: 2025-11-11\n- **Review Status**: Comprehensive editorial review\n- **Verification**: Academic sources verified\n- **Regional Context**: UK/North England where applicable",
  "properties": {
    "id": "auc-ontology",
    "collapsed": "true",
    "- ontology": "true",
    "- term-id": "AI-0113",
    "- preferred-term": "AUC",
    "- source-domain": "ai",
    "- status": "draft",
    "- public-access": "true",
    "- definition": "Area Under the Curve (AUC), specifically the area under the Receiver Operating Characteristic (ROC) curve (ROC-AUC or AUROC), is a single scalar performance metric for binary classifiers representing the probability that the model ranks a randomly chosen positive instance higher than a randomly chosen negative instance, providing threshold-independent assessment of a classifier's discriminative ability with values ranging from 0 to 1, where 0.5 indicates random guessing, 1.0 represents perfect classification, and values above 0.5 indicate better-than-random performance."
  },
  "backlinks": [],
  "wiki_links": [],
  "ontology": {
    "term_id": "AI-0113",
    "preferred_term": "AUC",
    "definition": "Area Under the Curve (AUC), specifically the area under the Receiver Operating Characteristic (ROC) curve (ROC-AUC or AUROC), is a single scalar performance metric for binary classifiers representing the probability that the model ranks a randomly chosen positive instance higher than a randomly chosen negative instance, providing threshold-independent assessment of a classifier's discriminative ability with values ranging from 0 to 1, where 0.5 indicates random guessing, 1.0 represents perfect classification, and values above 0.5 indicate better-than-random performance.",
    "source_domain": "ai",
    "maturity_level": null,
    "authority_score": null
  }
}