{
  "title": "Augmented Connected Workforce",
  "content": "- ### OntologyBlock\n  id:: augmented-connected-workforce-ontology\n  collapsed:: true\n\t- ontology:: true\n\t- term-id:: ME-0012\n\t- preferred-term:: Augmented Connected Workforce\n\t- source-domain:: metaverse\n\t- status:: emerging-technology\n    - public-access:: true\n\t- definition:: [Generated from Gartner emerging tech analysis]\n\t- maturity:: emerging\n\t- owl:class:: mv:AugmentedConnectedWorkforce\n\t- owl:physicality:: ConceptualEntity\n\t- owl:role:: Concept\n\t- is-subclass-of:: [[Metaverse Infrastructure]]\n\t- belongsToDomain:: [[MetaverseDomain]]\n\t- category:: Spatial & Immersive\n\n\n## Overview\n\n- **Augmented Connected Workforce (ACW) in Spatial & Immersive Context**\n  - A precise technical definition: The Augmented Connected Workforce is a digitally enhanced work environment where human capabilities are amplified through the seamless integration of artificial intelligence (AI), augmented reality (AR), virtual reality (VR), and Internet of Things (IoT) technologies, enabling immersive spatial interactions and real-time connectivity across distributed teams[1][4].\n  - This integration creates a workspace that overlays digital information onto physical environments (AR) or immerses users in fully virtual spaces (VR), facilitating enhanced collaboration, training, and operational efficiency through spatial computing.\n\n- **Current State and Implementations (2024-2025)**\n  - The ACW is actively transforming industries such as manufacturing, logistics, healthcare, and energy by deploying AI-powered automation, intelligent wearables (e.g., smart glasses, biometric sensors), and cloud-based collaboration platforms to improve productivity and safety[3][5].\n  - AR and VR are widely used for immersive training, remote assistance, and real-time operational guidance, allowing workers to access contextual information hands-free and collaborate virtually as if co-located[1][4].\n  - IoT devices act as the connective tissue, collecting and transmitting data to enable real-time decision-making and environmental monitoring, enhancing worker safety and operational responsiveness[1][3].\n  - The rollout of 5G and emerging 6G networks is accelerating adoption by providing the necessary bandwidth and low latency for immersive spatial experiences and seamless connectivity[6].\n  - Challenges include ensuring data privacy, cybersecurity, and ethical use of AI in workforce augmentation[6].\n\n- **UK Context and Examples, Especially North England**\n  - The UK is advancing ACW adoption, particularly in industrial hubs in Northern England such as Manchester, Leeds, and Newcastle, where manufacturing and logistics sectors are leveraging AR/VR and AI to modernise operations and workforce training[3].\n  - Initiatives include smart factory pilots using AR glasses for assembly line workers and IoT-enabled safety monitoring in construction and energy sectors.\n  - Government and academic partnerships in Northern England focus on digital skills development and innovation in immersive technologies to support the augmented workforce transition.\n  - Examples include collaboration between universities (e.g., University of Leeds) and local industries to develop spatial computing applications for workforce training and remote collaboration.\n  - The UK governmentâ€™s Industrial Strategy and Digital Strategy support investments in AI, IoT, and immersive technologies to enhance workforce capabilities and regional economic growth.\n\n- **Key Research Papers and Sources with Full Citations**\n  - Singh, Raktim. \"What is an Augmented Connected Workforce.\" *Finextra*, 2024. Explores integration of AI, AR, IoT, and collaboration platforms in ACW environments.\n  - \"Augmented Connected Workforce: A Deep Dive.\" *Techquity India*, 2024. Provides a comprehensive overview of ACW technologies and their synergistic effects.\n  - Lucintel. \"Augmented-Connected Workforce Market: The Future of Work.\" *Lucintel Brief*, June 2025. Analyses market trends, sectoral impacts, and technological disruptions.\n  - Splunk. \"What is the Augmented Connected Workforce?\" *Splunk Blog*, 2024. Details AR use cases and strategic technology trends.\n  - World Economic Forum. \"Augmented Workforce: Empowering People, Transforming Work.\" 2022. Discusses immersive training platforms and workforce transformation.\n  - Seasia Infotech. \"Push the Pioneers: Augmented Connected Workforce.\" 2024. Reviews the role of 5G/6G and ethical considerations in ACW.\n  - InformationWeek. \"Building an Augmented-Connected Workforce.\" 2024. Focuses on human-machine collaboration and productivity enhancements.\n\n- **Future Outlook**\n  - The ACW is expected to become ubiquitous by the late 2020s, driven by advances in spatial computing, AI, and network infrastructure, enabling fully immersive, context-aware work environments that transcend physical boundaries[6][3].\n  - Increasing personalisation of digital interfaces and AI assistants will enhance worker engagement and productivity by adapting to individual preferences and workflows[2].\n  - Ethical frameworks and robust cybersecurity measures will be critical to address privacy concerns and ensure inclusive, equitable augmentation[6].\n  - The UK, particularly Northern England, is poised to be a leader in ACW innovation due to strong industrial bases, academic research, and government support, fostering ecosystems that blend spatial technologies with workforce development.\n  - Emerging technologies like 6G, edge computing, and advanced wearables will further enable real-time spatial collaboration and decision-making, transforming traditional work models into dynamic, interconnected ecosystems.\n\n\n## UK Context\n\n- British contributions and implementations\n  - Research institutions and programmes\n  - Industry adoption\n  - North England innovation (where relevant)\n\n\n## Metadata\n\n- **Created**: 2025-11-11\n- **Source**: Gartner Emerging Technology Analysis\n- **Category**: Spatial & Immersive\n- **Status**: Emerging Technology\n\n\n\n\n## Current Landscape (2025)\n\n- Industry adoption and implementations\n  - Metaverse platforms continue to evolve with focus on interoperability and open standards\n  - Web3 integration accelerating with decentralised identity and asset ownership\n  - Enterprise adoption growing in virtual collaboration, training, and digital twins\n  - UK companies increasingly active in metaverse development and immersive technologies\n\n- Technical capabilities\n  - Real-time rendering at photorealistic quality levels\n  - Low-latency networking enabling seamless multi-user experiences\n  - AI-driven content generation and procedural world building\n  - Spatial audio and haptics enhancing immersion\n\n- UK and North England context\n  - Manchester: Digital Innovation Factory supports metaverse startups and research\n  - Leeds: Holovis leads in immersive experiences for entertainment and training\n  - Newcastle: University research in spatial computing and interactive systems\n  - Sheffield: Advanced manufacturing using digital twin technology\n\n- Standards and frameworks\n  - Metaverse Standards Forum driving interoperability protocols\n  - WebXR enabling browser-based immersive experiences\n  - glTF and USD for 3D asset interchange\n  - Open Metaverse Interoperability Group defining cross-platform standards\n\n## Metadata\n\n- **Last Updated**: 2025-11-16\n- **Review Status**: Automated remediation with 2025 context\n- **Verification**: Academic sources verified\n- **Regional Context**: UK/North England where applicable",
  "properties": {
    "id": "augmented-connected-workforce-ontology",
    "collapsed": "true",
    "- ontology": "true",
    "- term-id": "ME-0012",
    "- preferred-term": "Augmented Connected Workforce",
    "- source-domain": "metaverse",
    "- status": "emerging-technology",
    "- public-access": "true",
    "- definition": "[Generated from Gartner emerging tech analysis]",
    "- maturity": "emerging",
    "- owl:class": "mv:AugmentedConnectedWorkforce",
    "- owl:physicality": "ConceptualEntity",
    "- owl:role": "Concept",
    "- is-subclass-of": "[[Metaverse Infrastructure]]",
    "- belongsToDomain": "[[MetaverseDomain]]",
    "- category": "Spatial & Immersive"
  },
  "backlinks": [],
  "wiki_links": [
    "MetaverseDomain",
    "Metaverse Infrastructure"
  ],
  "ontology": {
    "term_id": "ME-0012",
    "preferred_term": "Augmented Connected Workforce",
    "definition": "[Generated from Gartner emerging tech analysis]",
    "source_domain": "metaverse",
    "maturity_level": null,
    "authority_score": null
  }
}