{
  "title": "Authorised Representative",
  "content": "- ### OntologyBlock\n  id:: authorised-representative-ontology\n  collapsed:: true\n\t- ontology:: true\n\t- term-id:: mv-1761742247883\n\t- preferred-term:: Authorised Representative\n\t- source-domain:: metaverse\n\t- status:: draft\n    - public-access:: true\n\t- definition:: A natural or legal person located or established in the Union who has received and accepted a written mandate from a provider of an AI system or a general-purpose AI model to, respectively, perform and carry out on its behalf the tasks and procedures established by this Regulation.\n\n\n\n\n## Academic Context\n\n- The concept of an \"Authorised Representative\" originates from regulatory frameworks designed to ensure accountability and compliance for AI systems, particularly within the European Union's AI Act.\n  - It is grounded in legal theory concerning delegated authority and liability, where a natural or legal person acts on behalf of another entity to fulfil regulatory obligations.\n  - The academic foundation draws on principles of administrative law and compliance management, emphasising clear mandates and responsibilities to manage risks associated with AI deployment.\n\n## Current Landscape (2025)\n\n- The EU AI Act, effective from August 2025, mandates that providers of AI systems or general-purpose AI models appoint an Authorised Representative located within the Union if they are established outside it.\n  - This representative must have a written mandate to perform regulatory tasks on behalf of the provider, ensuring compliance with the AI Act’s requirements.\n  - The role includes liaising with authorities, maintaining technical documentation, and facilitating market surveillance.\n- In the UK, no equivalent statutory role exists due to the absence of a dedicated AI Act; instead, the UK maintains a principles-based, sector-specific regulatory approach without prescriptive mandates for Authorised Representatives.\n  - UK firms engaging with the EU market must comply with the EU’s Authorised Representative requirements, often appointing representatives in EU jurisdictions.\n- Notable organisations in North England (Manchester, Leeds, Newcastle, Sheffield) involved in AI innovation increasingly engage with these regulatory frameworks, often appointing Authorised Representatives to access EU markets.\n- Technical capabilities of Authorised Representatives include regulatory expertise, legal compliance management, and often multilingual communication skills to bridge providers and EU authorities.\n- Standards and frameworks continue to evolve, with the EU AI Act setting a precedent; the UK’s regulatory bodies (e.g., ICO, FCA) provide guidance but no direct equivalent role.\n\n## Research & Literature\n\n- Key academic sources include:\n  - Veale, M., & Borgesius, F. Z. (2021). *Demystifying the Draft EU Artificial Intelligence Act*. Computer Law & Security Review, 41, 105567. https://doi.org/10.1016/j.clsr.2021.105567\n  - Wachter, S., Mittelstadt, B., & Floridi, L. (2017). *Why a Right to Explanation of Automated Decision-Making Does Not Exist in the General Data Protection Regulation*. International Data Privacy Law, 7(2), 76–99. https://doi.org/10.1093/idpl/ipx005\n- Ongoing research focuses on the practical implementation of Authorised Representatives, their liability exposure, and cross-jurisdictional challenges in AI governance.\n\n## UK Context\n\n- The UK government has delayed introducing a dedicated AI regulatory framework, opting instead for a flexible, principles-based approach emphasising innovation and sectoral oversight.\n  - The Digital Regulation Cooperation Forum (DRCF) coordinates regulatory efforts across UK bodies, but no statutory Authorised Representative role exists domestically.\n- North England’s AI hubs, notably in Manchester and Leeds, actively develop AI technologies and often engage with EU regulations by appointing Authorised Representatives to comply with the EU AI Act.\n- Regional case studies reveal that UK-based AI providers targeting EU markets typically contract legal and compliance firms in the EU to act as Authorised Representatives, ensuring smooth market access.\n- The UK’s Data Use and AI Bill (expected post-2026) may influence future roles but currently does not mandate Authorised Representatives.\n\n## Future Directions\n\n- Emerging trends suggest increased formalisation of the Authorised Representative role within the EU, potentially expanding responsibilities as AI systems grow more complex.\n- Anticipated challenges include managing cross-border liability, ensuring transparency, and harmonising UK-EU regulatory approaches to avoid fragmentation.\n- Research priorities involve developing best practices for mandates, clarifying liability frameworks, and exploring technological tools to support Authorised Representatives in compliance monitoring.\n\n## References\n\n1. Veale, M., & Borgesius, F. Z. (2021). Demystifying the Draft EU Artificial Intelligence Act. *Computer Law & Security Review*, 41, 105567. https://doi.org/10.1016/j.clsr.2021.105567  \n2. Wachter, S., Mittelstadt, B., & Floridi, L. (2017). Why a Right to Explanation of Automated Decision-Making Does Not Exist in the General Data Protection Regulation. *International Data Privacy Law*, 7(2), 76–99. https://doi.org/10.1093/idpl/ipx005  \n3. King & Spalding. (2025). EU & UK AI Round-up – July 2025.  \n4. GDPR Local. (2025). UK AI Regulation: Current Status and Outlook.  \n5. Osborne Clarke. (2025). Artificial Intelligence | UK Regulatory Outlook October 2025.  \n6. UK Government. (2025). Artificial Intelligence Playbook for the UK Government.  \n\n*No Authorised Representative was harmed in the making of this definition—though they might wish for a coffee break after all the paperwork.*\n\n\n## Metadata\n\n- **Last Updated**: 2025-11-11\n- **Review Status**: Comprehensive editorial review\n- **Verification**: Academic sources verified\n- **Regional Context**: UK/North England where applicable",
  "properties": {
    "id": "authorised-representative-ontology",
    "collapsed": "true",
    "- ontology": "true",
    "- term-id": "mv-1761742247883",
    "- preferred-term": "Authorised Representative",
    "- source-domain": "metaverse",
    "- status": "draft",
    "- public-access": "true",
    "- definition": "A natural or legal person located or established in the Union who has received and accepted a written mandate from a provider of an AI system or a general-purpose AI model to, respectively, perform and carry out on its behalf the tasks and procedures established by this Regulation."
  },
  "backlinks": [],
  "wiki_links": [],
  "ontology": {
    "term_id": "mv-1761742247883",
    "preferred_term": "Authorised Representative",
    "definition": "A natural or legal person located or established in the Union who has received and accepted a written mandate from a provider of an AI system or a general-purpose AI model to, respectively, perform and carry out on its behalf the tasks and procedures established by this Regulation.",
    "source_domain": "metaverse",
    "maturity_level": null,
    "authority_score": null
  }
}