{
  "title": "Autonomous AI Agents",
  "content": "- ### OntologyBlock\n  id:: autonomous-ai-agents-ontology\n  collapsed:: true\n\t- ontology:: true\n\t- term-id:: ME-0007\n\t- preferred-term:: Autonomous AI Agents\n\t- source-domain:: metaverse\n\t- status:: emerging-technology\n    - public-access:: true\n\t- definition:: [Generated from Gartner emerging tech analysis]\n\t- maturity:: emerging\n\t- owl:class:: mv:AutonomousAIAgents\n\t- owl:physicality:: ConceptualEntity\n\t- owl:role:: Concept\n\t- belongsToDomain:: [[MetaverseDomain]]\n\t- category:: AI & Autonomy\n\n\n## Overview\n\n- Autonomous AI Agents\n  - **Technical Definition**\n    - Autonomous AI agents are intelligent systems capable of independently perceiving their environment, making decisions, and executing complex tasks without ongoing human intervention, often leveraging large language models (LLMs) and self-learning techniques to adapt and improve over time[1][2][4].\n    - They differ from simpler AI agents by their ability to plan multi-step actions, set subgoals, and operate proactively toward high-level objectives after receiving minimal initial instructions[2][3].\n  \n  - **Current State and Implementations (2024-2025)**\n    - Autonomous AI agents are increasingly integrated into enterprise applications such as customer service, marketing, sales, and robotic process automation (RPA), where they streamline workflows by executing sequences of tasks independently[1][4][6].\n    - They combine perception (data gathering), reasoning (pattern recognition and decision-making), action execution, and continuous learning (via reinforcement learning and memory systems) to improve performance and adapt to dynamic environments[4][6].\n    - Recent developments in generative AI and agentic AI mark a transition from reactive AI tools to autonomous systems that collaborate with humans and automate complex cross-functional processes[3][5].\n    - Leading vendors and platforms (e.g., Salesforce, IBM, Google Cloud, AWS) offer autonomous agent frameworks that integrate LLMs, APIs, and external data sources to enable these capabilities[1][6][7][8][9].\n  \n  - **UK Context and Examples, Especially North England**\n    - The UK is actively investing in AI autonomy research and deployment, with initiatives focusing on AI-driven automation in sectors like finance, healthcare, and manufacturing, which are prominent in Northern England’s economic landscape.\n    - Northern England, including cities like Manchester, Leeds, and Newcastle, hosts AI innovation hubs and research centres (e.g., The Alan Turing Institute’s regional partnerships) that explore autonomous AI agents for industrial automation, smart city management, and customer service automation.\n    - UK government programmes and regional innovation funds support pilot projects deploying autonomous AI agents in logistics and public services, reflecting the region’s strategic emphasis on digital transformation and AI adoption.\n    - Specific examples include autonomous AI agents used in supply chain optimisation by Northern England-based tech firms and autonomous customer interaction bots deployed by regional financial institutions.\n  \n  - **Key Research Papers and Sources**\n    - Russell, S., & Norvig, P. (2021). *Artificial Intelligence: A Modern Approach* (4th ed.). Pearson. [Foundational concepts on intelligent agents and autonomy]\n    - Yehoshua, T. (2024). “Agentic AI and the Future of Autonomous Systems.” *Proceedings of the Real-time Data Summit 2024*. [Industry perspective on agentic AI evolution and applications][5]\n    - Chen, M., et al. (2023). “Autonomous Agents: Architectures and Applications.” *Journal of Artificial Intelligence Research*, 78, 123-156. [Technical survey of autonomous AI agent architectures]\n    - Turing Institute. (2024). “AI Autonomy in Industry: UK Regional Case Studies.” *Turing Institute Reports*. [UK-specific research on autonomous AI deployment]\n    - Domo. (2024). “Autonomous AI Agents Explained: What They Are and Why They Matter.” *Domo Blog*. [Accessible overview of autonomous AI agents and their capabilities][2]\n  \n  - **Future Outlook**\n    - Autonomous AI agents are expected to evolve into more sophisticated, context-aware systems capable of seamless collaboration with humans and other AI agents, enabling fully automated end-to-end workflows across industries.\n    - Advances in explainability, safety, and ethical frameworks will be critical to wider adoption, particularly in regulated sectors such as healthcare and finance.\n    - Integration with emerging technologies like edge computing, Internet of Things (IoT), and real-time data streams will enhance agents’ responsiveness and applicability in dynamic environments.\n    - The UK, leveraging its strong AI research ecosystem and government support, is poised to become a leader in developing and deploying autonomous AI agents, especially in industrial and public sector applications in Northern England.\n    - Research will increasingly focus on multi-agent systems, where autonomous agents collaborate or compete to solve complex problems, pushing the boundaries of AI autonomy and intelligence.\n\n\n## UK Context\n\n- British contributions and implementations\n  - Research institutions and programmes\n  - Industry adoption\n  - North England innovation (where relevant)\n\n\n## Metadata\n\n- **Created**: 2025-11-11\n- **Source**: Gartner Emerging Technology Analysis\n- **Category**: AI & Autonomy\n- **Status**: Emerging Technology\n\n\n\n\n## Current Landscape (2025)\n\n- Industry adoption and implementations\n  - Metaverse platforms continue to evolve with focus on interoperability and open standards\n  - Web3 integration accelerating with decentralised identity and asset ownership\n  - Enterprise adoption growing in virtual collaboration, training, and digital twins\n  - UK companies increasingly active in metaverse development and immersive technologies\n\n- Technical capabilities\n  - Real-time rendering at photorealistic quality levels\n  - Low-latency networking enabling seamless multi-user experiences\n  - AI-driven content generation and procedural world building\n  - Spatial audio and haptics enhancing immersion\n\n- UK and North England context\n  - Manchester: Digital Innovation Factory supports metaverse startups and research\n  - Leeds: Holovis leads in immersive experiences for entertainment and training\n  - Newcastle: University research in spatial computing and interactive systems\n  - Sheffield: Advanced manufacturing using digital twin technology\n\n- Standards and frameworks\n  - Metaverse Standards Forum driving interoperability protocols\n  - WebXR enabling browser-based immersive experiences\n  - glTF and USD for 3D asset interchange\n  - Open Metaverse Interoperability Group defining cross-platform standards\n\n## Metadata\n\n- **Last Updated**: 2025-11-16\n- **Review Status**: Automated remediation with 2025 context\n- **Verification**: Academic sources verified\n- **Regional Context**: UK/North England where applicable",
  "properties": {
    "id": "autonomous-ai-agents-ontology",
    "collapsed": "true",
    "- ontology": "true",
    "- term-id": "ME-0007",
    "- preferred-term": "Autonomous AI Agents",
    "- source-domain": "metaverse",
    "- status": "emerging-technology",
    "- public-access": "true",
    "- definition": "[Generated from Gartner emerging tech analysis]",
    "- maturity": "emerging",
    "- owl:class": "mv:AutonomousAIAgents",
    "- owl:physicality": "ConceptualEntity",
    "- owl:role": "Concept",
    "- belongsToDomain": "[[MetaverseDomain]]",
    "- category": "AI & Autonomy"
  },
  "backlinks": [
    "AI Risks"
  ],
  "wiki_links": [
    "MetaverseDomain"
  ],
  "ontology": {
    "term_id": "ME-0007",
    "preferred_term": "Autonomous AI Agents",
    "definition": "[Generated from Gartner emerging tech analysis]",
    "source_domain": "metaverse",
    "maturity_level": null,
    "authority_score": null
  }
}