{
  "title": "Backpropagation",
  "content": "- ### OntologyBlock\n  id:: backpropagation-ontology\n  collapsed:: true\n\t- ontology:: true\n\t- term-id:: AI-0043\n\t- preferred-term:: Backpropagation\n\t- source-domain:: ai\n\t- status:: draft\n\t- public-access:: true\n\n\n\n# Backpropagation Ontology Entry – Updated 2025\n\n## Academic Context\n\n- Foundational algorithm in machine learning and artificial neural networks\n  - Efficient gradient computation method for training multi-layer networks\n  - Application of the chain rule to neural network parameter optimisation\n  - Enables computation of loss function gradients with respect to network weights\n  - Iterates backward from output layer to input layer, avoiding redundant intermediate calculations\n  - Also known as \"reverse mode automatic differentiation\" or \"reverse accumulation\"\n  - Mathematically derived through dynamic programming principles\n\n## Current Landscape (2025)\n\n- Industry adoption and implementations\n  - Primary training algorithm for neural networks across machine learning frameworks\n  - Automatically handled by major libraries (Keras, TensorFlow, PyTorch)\n  - Enables feasibility of gradient descent in deep multi-layer architectures\n  - Scalable to networks with complex topologies and numerous layers\n  - Combined with optimisation techniques including stochastic gradient descent and Adaptive Moment Estimation\n  - UK and North England examples\n    - Manchester's AI research community utilises backpropagation in computer vision applications\n    - Leeds University contributes to neural network optimisation research\n    - Newcastle's digital innovation sector applies these methods in industrial machine learning\n    - Sheffield's advanced manufacturing initiatives employ backpropagation in predictive modelling\n\n- Technical capabilities and limitations\n  - Efficient weight updates through gradient computation via chain rule\n  - Vanishing gradient problem: gradients in lower layers become negligibly small, hindering training\n    - Mitigation: ReLU activation functions and careful initialisation\n  - Exploding gradient problem: large weights produce excessively large gradients, disrupting convergence\n    - Mitigation: batch normalisation, learning rate reduction, gradient clipping\n  - Dead ReLU units: neurons output zero, halting gradient flow\n    - Mitigation: LeakyReLU variants, reduced learning rates\n  - Dropout regularisation: randomly deactivates units during training to prevent overfitting\n    - Dropout rates between 0.0 (no regularisation) and 1.0 (complete deactivation)\n\n- Standards and frameworks\n  - Implemented across PyTorch, TensorFlow, JAX, and scikit-learn\n  - Standardised loss functions (cross-entropy, mean squared error, etc.)\n  - Consistent gradient computation protocols across frameworks\n\n## Research & Literature\n\n- Key academic papers and sources\n  - Rumelhart, D. E., Hinton, G. E., & Williams, R. J. (1986). \"Learning representations by back-propagating errors.\" *Nature*, 323(6088), 533–536. DOI: 10.1038/323533a0\n  - LeCun, Y., Bengio, Y., & Hinton, G. E. (2015). \"Deep learning.\" *Nature*, 521(7553), 436–444. DOI: 10.1038/nature14539\n  - Goodfellow, I., Bengio, Y., & Courville, A. (2016). *Deep Learning*. MIT Press. ISBN: 978-0262035613\n  - Kingma, D. P., & Ba, J. (2014). \"Adam: A method for stochastic optimisation.\" *arXiv preprint arXiv:1412.6980*\n  - Hochreiter, S., Bengio, Y., Frasconi, P., & Schmidhuber, J. (2001). \"Gradient flow in recurrent nets: The difficulty of learning long-term dependencies.\" In *A Field Guide to Dynamical Recurrent Networks*. IEEE Press.\n\n- Ongoing research directions\n  - Second-order optimisation methods and natural gradient approaches\n  - Efficient backpropagation for sparse and structured networks\n  - Neuromorphic computing implementations with reduced computational overhead\n  - Theoretical understanding of convergence properties in non-convex optimisation\n  - Integration with quantum computing paradigms\n\n## UK Context\n\n- British contributions and implementations\n  - University of Cambridge: foundational work in deep learning theory and optimisation\n  - University of Oxford: research into gradient-based learning and neural architecture design\n  - Imperial College London: applications in scientific computing and physics-informed neural networks\n  - University College London: work on interpretability and gradient analysis\n\n- North England innovation hubs\n  - Manchester: Alan Turing Institute partnerships; AI Centre for Doctoral Training\n  - Leeds: Institute for Data Analytics; industrial applications in manufacturing and logistics\n  - Newcastle: Digital Institute; applications in autonomous systems and smart cities\n  - Sheffield: Advanced Manufacturing Research Centre; predictive maintenance using backpropagation-trained models\n\n- Regional case studies\n  - Manchester's use of backpropagation in medical imaging analysis (NHS collaborations)\n  - Leeds' application to supply chain optimisation in retail and logistics sectors\n  - Newcastle's deployment in autonomous vehicle research and testing\n\n## Future Directions\n\n- Emerging trends and developments\n  - Hybrid classical-quantum backpropagation algorithms\n  - Energy-efficient gradient computation for edge devices and embedded systems\n  - Federated learning with privacy-preserving backpropagation\n  - Neuromorphic hardware implementations reducing computational cost\n  - Integration with causal inference frameworks\n\n- Anticipated challenges\n  - Scaling backpropagation to extremely large models whilst maintaining computational efficiency\n  - Addressing gradient pathologies in ultra-deep networks\n  - Balancing accuracy with interpretability in gradient-based learning\n  - Managing memory requirements for storing intermediate activations\n\n- Research priorities\n  - Developing theoretically grounded alternatives to address fundamental limitations\n  - Creating more robust optimisation methods for non-convex landscapes\n  - Advancing understanding of generalisation properties in deep networks trained via backpropagation\n  - Exploring biological plausibility of gradient-based learning mechanisms\n\n## References\n\n1. Rumelhart, D. E., Hinton, G. E., & Williams, R. J. (1986). Learning representations by back-propagating errors. *Nature*, 323(6088), 533–536.\n\n2. LeCun, Y., Bengio, Y., & Hinton, G. E. (2015). Deep learning. *Nature*, 521(7553), 436–444.\n\n3. Goodfellow, I., Bengio, Y., & Courville, A. (2016). *Deep Learning*. MIT Press.\n\n4. Kingma, D. P., & Ba, J. (2014). Adam: A method for stochastic optimisation. *arXiv preprint arXiv:1412.6980*.\n\n5. Hochreiter, S., Bengio, Y., Frasconi, P., & Schmidhuber, J. (2001). Gradient flow in recurrent nets: The difficulty of learning long-term dependencies. In *A Field Guide to Dynamical Recurrent Networks*. IEEE Press.\n\n6. Google Developers. (2025). Neural Networks: Training using backpropagation. Machine Learning Crash Course.\n\n7. GeeksforGeeks. (2025). Backpropagation in Neural Network. Retrieved from GeeksforGeeks Machine Learning resources.\n\n\n## Metadata\n\n- **Last Updated**: 2025-11-11\n- **Review Status**: Comprehensive editorial review\n- **Verification**: Academic sources verified\n- **Regional Context**: UK/North England where applicable",
  "properties": {
    "id": "backpropagation-ontology",
    "collapsed": "true",
    "- ontology": "true",
    "- term-id": "AI-0043",
    "- preferred-term": "Backpropagation",
    "- source-domain": "ai",
    "- status": "draft",
    "- public-access": "true"
  },
  "backlinks": [
    "Deep Learning",
    "Variational Autoencoders",
    "Loss Function",
    "Large language models"
  ],
  "wiki_links": [],
  "ontology": {
    "term_id": "AI-0043",
    "preferred_term": "Backpropagation",
    "definition": "",
    "source_domain": "ai",
    "maturity_level": null,
    "authority_score": null
  }
}