{
  "title": "BART",
  "content": "- ### OntologyBlock\n  id:: bart-ontology\n  collapsed:: true\n\t- ontology:: true\n\t- term-id:: AI-0222\n\t- preferred-term:: BART\n\t- source-domain:: ai\n\t- status:: draft\n    - public-access:: true\n\t- definition:: Bidirectional and Auto-Regressive Transformers: a denoising autoencoder for pre-training sequence-to-sequence models, combining bidirectional encoding (like BERT) with autoregressive decoding (like GPT).\n\n\n\n# BART Ontology Entry - Updated Content\n\n## Academic Context\n\n- BART (Bidirectional and Auto-Regressive Transformers) represents a significant architectural innovation in natural language processing\n  - Developed by Meta AI Research and published in July 2020\n  - Combines bidirectional encoding mechanisms from BERT with autoregressive decoding from GPT\n  - Functions as a denoising autoencoder for sequence-to-sequence pre-training\n  - Comprises approximately 140 million parameters, exceeding both BERT (110 million) and GPT-1 (117 million) whilst demonstrating superior performance across multiple benchmarks\n  - The architecture elegantly sidesteps the \"which approach is better?\" debate by simply using bothâ€”a pragmatic solution that has proven remarkably effective\n\n## Current Landscape (2025)\n\n- Industry adoption and implementations\n  - BART serves as a foundational model for abstractive text generation tasks including summarisation, question-answering, and machine translation\n  - Multilingual variants (mBART) enable cross-lingual applications, particularly for low-resource language pairs\n  - Integration with Retrieval-Augmented Generation (RAG) systems demonstrates enhanced capability for grounded, contextually-informed responses\n  - Fine-tuned implementations achieve competitive performance metrics (85.84 F1 scores reported for question-answering tasks as of 2025)\n  - Compression techniques combining distillation and quantization enable deployment on resource-constrained devices, achieving model reduction to approximately 1/28th original size with minimal performance degradation\n  - UK and North England context: whilst specific regional implementations remain limited in published literature, the model's adoption within British academic institutions and technology sectors follows broader transformer model uptake patterns\n\n- Technical capabilities and limitations\n  - Particularly effective for text generation and comprehension tasks\n  - Matches RoBERTa performance on GLUE and SQuAD benchmarks\n  - Achieves state-of-the-art results on abstractive dialogue, question-answering, and summarisation tasks (gains up to 3.5 ROUGE)\n  - Provides 1.1 BLEU improvement over back-translation systems for machine translation with target-language pretraining alone\n  - Compression performance varies by task; aggressive quantisation (2-bit) introduces cumulative distillation errors, particularly problematic for complex tasks like machine translation\n  - Requires careful task-specific assessment when deploying compressed variants\n\n- Standards and frameworks\n  - Operates within standard Transformer-based neural machine translation architecture\n  - Pre-training employs arbitrary noising functions, with optimal performance achieved through sentence shuffling and span in-filling (replacing text spans with single mask tokens)\n  - Encoder-decoder architecture comprises three primary blocks: multi-head attention, addition and normalisation, and feed-forward layers\n\n## Research & Literature\n\n- Key academic papers and sources\n  - Lewis, M., Liu, Y., Goyal, N., Ghazvininejad, M., Mohamed, A., Levy, O., Stoyanov, V., & Zettlemoyer, L. (2020). \"BART: Denoising Sequence-to-Sequence Pre-training for Natural Language Generation, Translation, and Comprehension.\" *Proceedings of the 58th Annual Meeting of the Association for Computational Linguistics*. Meta AI Research. Available: https://ai.meta.com/research/publications/bart-denoising-sequence-to-sequence-pre-training-for-natural-language-generation-translation-and-comprehension/\n  - Hansun, S., et al. (2025). \"A Fine-Tuned BART Pre-trained Language Model for the Indonesian Question-Answering Task.\" *ETASR: Engineering, Technology & Applied Science Review*, 15(2). Received 4 December 2024; Accepted 19 January 2025.\n  - Kheraj, S. A. (2025). \"A Deep Technical Exploration of Retrieval-Augmented Generation (RAG) with Transformers, DPR, FAISS, and BART.\" *Towards AI*, May 2025.\n\n- Ongoing research directions\n  - Compression and efficiency optimisation for edge deployment\n  - Multilingual and cross-lingual capability enhancement\n  - Integration with retrieval systems for grounded generation\n  - Head pruning and sequence-level distillation techniques\n  - Latency reduction alongside memory footprint optimisation\n  - Domain-specific fine-tuning for specialised applications (e.g., mass spectra structure elucidation, as demonstrated by MS-BART)\n\n## UK Context\n\n- British contributions and implementations\n  - BART adoption within UK academic institutions follows broader transformer model integration patterns\n  - Limited published case studies specific to North England innovation hubs at present\n  - Potential applications within UK-based NLP research centres and technology sectors remain largely undocumented in accessible literature\n\n- Research priorities\n  - Evaluation of BART performance on British English language variants\n  - Investigation of multilingual BART for UK-relevant language pairs\n  - Assessment of compression techniques for deployment within UK institutional constraints\n\n## Future Directions\n\n- Emerging trends and developments\n  - Continued refinement of compression techniques balancing performance and resource efficiency\n  - Expansion of multilingual capabilities for underrepresented language pairs\n  - Enhanced integration with retrieval and knowledge systems for more reliable, grounded outputs\n  - Specialised domain adaptations (scientific, medical, legal applications)\n\n- Anticipated challenges\n  - Performance degradation under aggressive quantisation, particularly for complex generation tasks\n  - Cumulative errors in distillation-aware quantisation pipelines requiring careful calibration\n  - Scalability considerations for truly resource-constrained environments\n\n- Research priorities\n  - Systematic evaluation of compression trade-offs across diverse task categories\n  - Investigation of alternative noising strategies for improved pre-training efficiency\n  - Development of task-specific deployment guidelines for practitioners\n\n## References\n\n- Lewis, M., Liu, Y., Goyal, N., Ghazvininejad, M., Mohamed, A., Levy, O., Stoyanov, V., & Zettlemoyer, L. (2020). BART: Denoising Sequence-to-Sequence Pre-training for Natural Language Generation, Translation, and Comprehension. *Proceedings of the 58th Annual Meeting of the Association for Computational Linguistics*. Meta AI Research.\n\n- Hansun, S., et al. (2025). A Fine-Tuned BART Pre-trained Language Model for the Indonesian Question-Answering Task. *ETASR: Engineering, Technology & Applied Science Review*, 15(2), 19 January 2025.\n\n- Kheraj, S. A. (2025). A Deep Technical Exploration of Retrieval-Augmented Generation (RAG) with Transformers, DPR, FAISS, and BART. *Towards AI*, May 2025.\n\n- Amazon Science. (2025). Compressing BART Models for Resource-Constrained Operation. Amazon Web Services.\n\n- Dataloop. (2025). BART: Bidirectional and Auto-Regressive Transformers. Model Library Documentation, 29 May 2025.\n\n\n## Metadata\n\n- **Last Updated**: 2025-11-11\n- **Review Status**: Comprehensive editorial review\n- **Verification**: Academic sources verified\n- **Regional Context**: UK/North England where applicable",
  "properties": {
    "id": "bart-ontology",
    "collapsed": "true",
    "- ontology": "true",
    "- term-id": "AI-0222",
    "- preferred-term": "BART",
    "- source-domain": "ai",
    "- status": "draft",
    "- public-access": "true",
    "- definition": "Bidirectional and Auto-Regressive Transformers: a denoising autoencoder for pre-training sequence-to-sequence models, combining bidirectional encoding (like BERT) with autoregressive decoding (like GPT)."
  },
  "backlinks": [
    "Transformers",
    "Telecollaboration and Telepresence"
  ],
  "wiki_links": [],
  "ontology": {
    "term_id": "AI-0222",
    "preferred_term": "BART",
    "definition": "Bidirectional and Auto-Regressive Transformers: a denoising autoencoder for pre-training sequence-to-sequence models, combining bidirectional encoding (like BERT) with autoregressive decoding (like GPT).",
    "source_domain": "ai",
    "maturity_level": null,
    "authority_score": null
  }
}