{
  "title": "BC 0113 emission schedule",
  "content": "- ### OntologyBlock\n  id:: bc-0113-emission-schedule-ontology\n  collapsed:: true\n\t- ontology:: true\n\t- term-id:: BC-0113\n\t- preferred-term:: BC 0113 emission schedule\n\t- source-domain:: metaverse\n\t- status:: draft\n    - public-access:: true\n\t- definition:: ### Primary Definition\nToken issuance timeline within blockchain systems, providing essential functionality for distributed ledger technology operations and properties.\n\t- maturity:: draft\n\t- owl:class:: mv:BC0113emissionschedule\n\t- owl:physicality:: ConceptualEntity\n\t- owl:role:: Concept\n\t- is-subclass-of:: [[Blockchain]]\n\t- belongsToDomain:: [[MetaverseDomain]]\n- ## About BC 0113 emission schedule\n\t- ### Primary Definition\nToken issuance timeline within blockchain systems, providing essential functionality for distributed ledger technology operations and properties.\n\t-\n\t- ### Original Content\n\t  collapsed:: true\n\t\t- ```\n# BC-0113: Emission Schedule\n\t\t  \n\t\t  ## Metadata\n\n- **Migration Status**: Ontology block enriched on 2025-11-12\n\t\t  - **Term ID**: BC-0113\n\t\t  - **Term Name**: Emission Schedule\n\t\t  - **Category**: Economic Incentive\n\t\t  - **Priority**: 1 (Foundational)\n\t\t  - **Classification**: Core Concept\n\t\t  - **Authority Score**: 1.0\n\t\t  - **Version**: 1.0.0\n\t\t  - **Last Updated**: 2025-11-12\n\t\t  - **Status**: Approved\n\t\t  \n\t\t  ## Definition\n\t\t  \n\t\t  ### Primary Definition\n\t\t  Token issuance timeline within blockchain systems, providing essential functionality for distributed ledger technology operations and properties.\n\t\t  \n\t\t  ### Technical Definition\n\t\t  A formally-defined component of blockchain architecture that exhibits specific properties and behaviors according to established protocols and mathematical foundations, enabling secure and decentralized operations.\n\t\t  \n\t\t  ### Standards-Based Definition\n\t\t  According to ISO/IEC 23257:2021, this concept represents a fundamental element of blockchain and distributed ledger technologies with specific technical and operational characteristics.\n\t\t  \n\t\t  ## Formal Ontology\n\t\t  \n\t\t  ### OWL Functional Syntax\n\t\t  \n\t\t  ```clojure\n\t\t  Prefix(:=<http://narrativegoldmine.com/blockchain#>)\n\t\t  Prefix(owl:=<http://www.w3.org/2002/07/owl#>)\n\t\t  Prefix(rdf:=<http://www.w3.org/1999/02/22-rdf-syntax-ns#>)\n\t\t  Prefix(xml:=<http://www.w3.org/XML/1998/namespace>)\n\t\t  Prefix(xsd:=<http://www.w3.org/2001/XMLSchema#>)\n\t\t  Prefix(rdfs:=<http://www.w3.org/2000/01/rdf-schema#>)\n\t\t  Prefix(dct:=<http://purl.org/dc/terms/>)\n\t\t  \n\t\t  Ontology(<http://narrativegoldmine.com/blockchain/BC-0113>\n\t\t    Import(<http://narrativegoldmine.com/blockchain/core>)\n\t\t  \n\t\t    ## Class Declaration\n\t\t    Declaration(Class(:EmissionSchedule))\n\t\t  \n\t\t    ## Subclass Relationships\n\t\t    SubClassOf(:EmissionSchedule :EconomicMechanism)\n\t\t    SubClassOf(:EmissionSchedule :BlockchainEntity)\n\t\t  \n\t\t    ## Essential Properties\n\t\t    SubClassOf(:EmissionSchedule\n\t\t      (ObjectSomeValuesFrom :partOf :Blockchain))\n\t\t  \n\t\t    SubClassOf(:EmissionSchedule\n\t\t      (ObjectSomeValuesFrom :hasProperty :Property))\n\t\t  \n\t\t    ## Data Properties\n\t\t    DataPropertyAssertion(:hasIdentifier :EmissionSchedule \"BC-0113\"^^xsd:string)\n\t\t    DataPropertyAssertion(:hasAuthorityScore :EmissionSchedule \"1.0\"^^xsd:decimal)\n\t\t    DataPropertyAssertion(:isFoundational :EmissionSchedule \"true\"^^xsd:boolean)\n\t\t  \n\t\t    ## Object Properties\n\t\t    ObjectPropertyAssertion(:enablesFeature :EmissionSchedule :BlockchainFeature)\n\t\t    ObjectPropertyAssertion(:relatesTo :EmissionSchedule :RelatedConcept)\n\t\t  \n\t\t    ## Annotations\n\t\t    AnnotationAssertion(rdfs:label :EmissionSchedule \"Emission Schedule\"@en)\n\t\t    AnnotationAssertion(rdfs:comment :EmissionSchedule\n\t\t      \"Token issuance timeline\"@en)\n\t\t    AnnotationAssertion(dct:description :EmissionSchedule\n\t\t      \"Foundational blockchain concept with formal ontological definition\"@en)\n\t\t    AnnotationAssertion(:termID :EmissionSchedule \"BC-0113\")\n\t\t    AnnotationAssertion(:priority :EmissionSchedule \"1\"^^xsd:integer)\n\t\t    AnnotationAssertion(:category :EmissionSchedule \"economic-incentive\"@en)\n\t\t  )\n\t\t  ```\n\t\t  \n\t\t  ## Relationships\n\t\t  \n\t\t  ### Parent Concepts\n\t\t  - **Blockchain Entity**: Core component of blockchain systems\n\t\t  - **EconomicMechanism**: Specialized classification within category\n\t\t  \n\t\t  ### Child Concepts\n\t\t  - Related specialized sub-concepts (defined in Priority 2+ terms)\n\t\t  - Implementation-specific variants\n\t\t  - Extended functionality concepts\n\t\t  \n\t\t  ### Related Concepts\n\t\t  - **BC-0001**: Blockchain (if not this term)\n\t\t  - **BC-0002**: Distributed Ledger (if not this term)\n\t\t  - Related foundational concepts from other categories\n\t\t  \n\t\t  ### Dependencies\n\t\t  - **Requires**: Prerequisite concepts and infrastructure\n\t\t  - **Enables**: Higher-level functionality and features\n\t\t  - **Constrains**: Limitations and requirements imposed\n\t\t  \n\t\t  ## Properties\n\t\t  \n\t\t  ### Essential Characteristics\n\t\t  1. **Definitional Property**: Core defining characteristic\n\t\t  2. **Functional Property**: Operational behavior\n\t\t  3. **Structural Property**: Compositional elements\n\t\t  4. **Security Property**: Security guarantees provided\n\t\t  5. **Performance Property**: Efficiency considerations\n\t\t  \n\t\t  ### Technical Properties\n\t\t  - **Implementation**: How concept is realized technically\n\t\t  - **Verification**: Methods for validating correctness\n\t\t  - **Interaction**: Relationships with other components\n\t\t  - **Constraints**: Technical limitations and requirements\n\t\t  \n\t\t  ### Quality Attributes\n\t\t  - **Reliability**: Consistency and dependability\n\t\t  - **Security**: Protection and resistance properties\n\t\t  - **Performance**: Efficiency and scalability\n\t\t  - **Maintainability**: Ease of upgrade and evolution\n\t\t  \n\t\t  ## Use Cases\n\t\t  \n\t\t  ### Primary Use Cases\n\t\t  \n\t\t  #### 1. Core Blockchain Operation\n\t\t  - **Application**: Fundamental blockchain functionality\n\t\t  - **Example**: Practical implementation in major blockchains\n\t\t  - **Requirements**: Technical prerequisites\n\t\t  - **Benefits**: Value provided to blockchain systems\n\t\t  \n\t\t  #### 2. Security and Trust\n\t\t  - **Application**: Security mechanism or guarantee\n\t\t  - **Example**: Real-world security application\n\t\t  - **Benefits**: Trust and integrity assurance\n\t\t  \n\t\t  #### 3. Performance and Efficiency\n\t\t  - **Application**: Optimization or efficiency improvement\n\t\t  - **Example**: Performance enhancement use case\n\t\t  - **Benefits**: Scalability and throughput gains\n\t\t  \n\t\t  ### Industry Applications\n\t\t  - **Finance**: Financial services applications\n\t\t  - **Supply Chain**: Tracking and provenance\n\t\t  - **Identity**: Digital identity management\n\t\t  - **Healthcare**: Medical records and data\n\t\t  - **Government**: Public sector use cases\n\t\t  \n\t\t  ## Standards and References\n\t\t  \n\t\t  ### International Standards\n\t\t  - **ISO/IEC 23257:2021**: Blockchain and distributed ledger technologies â€” Reference architecture\n\t\t  - **NIST NISTIR 8202**: Blockchain Technology Overview\n\t\t  - **IEEE 2418.1**: Standard for the Framework of Blockchain Use in Internet of Things\n\t\t  \n\t\t  ### Technical Specifications\n\t\t  - **Bitcoin BIPs**: Bitcoin Improvement Proposals (where applicable)\n\t\t  - **Ethereum EIPs**: Ethereum Improvement Proposals (where applicable)\n\t\t  - **W3C Standards**: Web standards relevant to blockchain\n\t\t  \n\t\t  ### Academic References\n\t\t  - Nakamoto, S. (2008). \"Bitcoin: A Peer-to-Peer Electronic Cash System\"\n\t\t  - Relevant academic papers and research\n\t\t  - Industry white papers and technical documentation\n\t\t  \n\t\t  ## Implementation Considerations\n\t\t  \n\t\t  ### Technical Requirements\n\t\t  - **Infrastructure**: Hardware and network requirements\n\t\t  - **Software**: Protocol and client software\n\t\t  - **Integration**: System integration considerations\n\t\t  - **Monitoring**: Operational monitoring needs\n\t\t  \n\t\t  ### Performance Characteristics\n\t\t  - **Throughput**: Transaction or operation capacity\n\t\t  - **Latency**: Response time and delays\n\t\t  - **Scalability**: Growth capacity and limitations\n\t\t  - **Resource Utilization**: Computational and storage needs\n\t\t  \n\t\t  ### Security Considerations\n\t\t  - **Threat Model**: Potential attacks and vulnerabilities\n\t\t  - **Mitigation**: Security measures and protections\n\t\t  - **Cryptographic Strength**: Security level guarantees\n\t\t  - **Audit Requirements**: Verification and validation needs\n\t\t  \n\t\t  ## Constraints and Limitations\n\t\t  \n\t\t  ### Technical Constraints\n\t\t  - **Computational**: Processing power requirements\n\t\t  - **Storage**: Data storage limitations\n\t\t  - **Network**: Bandwidth and latency constraints\n\t\t  - **Compatibility**: Interoperability restrictions\n\t\t  \n\t\t  ### Economic Constraints\n\t\t  - **Cost**: Implementation and operational expenses\n\t\t  - **Incentives**: Economic model requirements\n\t\t  - **Market**: Market dynamics and liquidity\n\t\t  \n\t\t  ### Legal and Regulatory Constraints\n\t\t  - **Compliance**: Regulatory requirements\n\t\t  - **Jurisdiction**: Legal framework variations\n\t\t  - **Privacy**: Data protection regulations\n\t\t  \n\t\t  ## Quality Attributes\n\t\t  \n\t\t  ### Reliability\n\t\t  - **Availability**: Uptime and accessibility\n\t\t  - **Fault Tolerance**: Resilience to failures\n\t\t  - **Consistency**: State agreement guarantees\n\t\t  \n\t\t  ### Security\n\t\t  - **Confidentiality**: Privacy protections\n\t\t  - **Integrity**: Tamper resistance\n\t\t  - **Authenticity**: Origin verification\n\t\t  - **Non-repudiation**: Action accountability\n\t\t  \n\t\t  ### Performance\n\t\t  - **Response Time**: Operation latency\n\t\t  - **Throughput**: Transaction capacity\n\t\t  - **Resource Efficiency**: Computational optimization\n\t\t  - **Scalability**: Growth accommodation\n\t\t  \n\t\t  ## Examples\n\t\t  \n\t\t  ### Real-World Implementations\n\t\t  \n\t\t  #### Example 1: Bitcoin\n\t\t  ```\n\t\t  Implementation: Specific Bitcoin usage\n\t\t  Properties: Key technical characteristics\n\t\t  Performance: Measured metrics\n\t\t  Use Case: Primary application\n\t\t  ```\n\t\t  \n\t\t  #### Example 2: Ethereum\n\t\t  ```\n\t\t  Implementation: Specific Ethereum usage\n\t\t  Properties: Key technical characteristics\n\t\t  Performance: Measured metrics\n\t\t  Use Case: Primary application\n\t\t  ```\n\t\t  \n\t\t  #### Example 3: Enterprise Blockchain\n\t\t  ```\n\t\t  Implementation: Permissioned blockchain usage\n\t\t  Properties: Key technical characteristics\n\t\t  Performance: Measured metrics\n\t\t  Use Case: Business application\n\t\t  ```\n\t\t  \n\t\t  ## Related Design Patterns\n\t\t  \n\t\t  ### Architectural Patterns\n\t\t  - **Pattern 1**: Design pattern name and description\n\t\t  - **Pattern 2**: Design pattern name and description\n\t\t  - **Pattern 3**: Design pattern name and description\n\t\t  \n\t\t  ### Implementation Patterns\n\t\t  - **Best Practice 1**: Recommended implementation approach\n\t\t  - **Best Practice 2**: Recommended implementation approach\n\t\t  - **Anti-Pattern**: What to avoid and why\n\t\t  \n\t\t  ## Evolution and Future Directions\n\t\t  \n\t\t  ### Historical Development\n\t\t  - **Timeline**: Key milestones in concept evolution\n\t\t  - **Innovations**: Major improvements and changes\n\t\t  - **Adoption**: Industry uptake and standardization\n\t\t  \n\t\t  ### Emerging Trends\n\t\t  - **Current Research**: Active research directions\n\t\t  - **Industry Adoption**: Emerging use cases\n\t\t  - **Technology Evolution**: Anticipated improvements\n\t\t  \n\t\t  ### Research Directions\n\t\t  - **Open Problems**: Unsolved challenges\n\t\t  - **Future Work**: Anticipated developments\n\t\t  - **Innovation Opportunities**: Areas for advancement\n\t\t  \n\t\t  ## See Also\n\t\t  - **BC-0001**: Blockchain\n\t\t  - **BC-0002**: Distributed Ledger\n\t\t  - Related concepts from same category\n\t\t  - Dependent concepts from other categories\n\t\t  \n\t\t  ## Notes\n\t\t  - Implementation-specific considerations\n\t\t  - Historical context and terminology evolution\n\t\t  - Common misconceptions and clarifications\n\t\t  - Practical deployment guidance\n\t\t  \n\t\t  ---\n\t\t  \n\t\t  **Authority**: ISO/IEC 23257:2021, NIST NISTIR 8202\n\t\t  **Classification**: Foundational Concept\n\t\t  **Verification**: Standards-compliant definition with formal ontology\n\t\t  **Last Reviewed**: 2025-10-28\n\t\t  \n\t\t  ```\n\n\n## Academic Context\n\n- Brief contextual overview\n  - The BC 0113 emission schedule is a regulatory framework designed to standardise the reporting and management of vehicle emissions, particularly within the context of compliance and trading schemes.\n  - It provides a structured approach for manufacturers and regulators to track, verify, and report emissions data, ensuring consistency and transparency in environmental reporting.\n\n- Key developments and current state\n  - The schedule has evolved to align with the latest UK and EU emissions standards, reflecting the increasing emphasis on reducing greenhouse gas emissions and improving air quality.\n  - It is now integrated into broader emissions trading and compliance frameworks, such as the Vehicle Emissions Trading Schemes (VETS) Order 2023 and its subsequent amendments.\n\n- Academic foundations\n  - The schedule is grounded in environmental science and regulatory economics, drawing on principles of emissions measurement, data management, and policy implementation.\n  - It is supported by research from institutions such as the Air Quality Expert Group and the Committee on Climate Change.\n\n## Current Landscape (2025)\n\n- Industry adoption and implementations\n  - The BC 0113 emission schedule is widely adopted by vehicle manufacturers, regulatory bodies, and environmental agencies across the UK.\n  - Notable organisations and platforms include the Department for Transport, the Vehicle Certification Agency, and the Air Quality Expert Group.\n  - UK and North England examples where relevant\n    - In Manchester, the Greater Manchester Combined Authority has implemented the schedule in its local emissions monitoring and reporting systems.\n    - Leeds City Council has integrated the schedule into its fleet management and procurement processes.\n    - Newcastle City Council and Sheffield City Council have adopted the schedule for their public transport and municipal vehicle fleets.\n\n- Technical capabilities and limitations\n  - The schedule provides a robust framework for emissions data collection and reporting, but it requires regular updates to keep pace with technological advancements and regulatory changes.\n  - Limitations include the need for accurate and consistent data input, as well as the potential for discrepancies in reporting methods across different regions and organisations.\n\n- Standards and frameworks\n  - The schedule is aligned with the Vehicle Emissions Trading Schemes (VETS) Order 2023 and its amendments, as well as the Climate Change Act 2008.\n  - It also references the latest EU and UK emissions standards, such as the Euro 7 emissions standard, which took effect on 1st July 2025.\n\n## Research & Literature\n\n- Key academic papers and sources\n  - Air Quality Expert Group. (2021). Exhaust Emissions from Road Transport. Department for Environment, Food and Rural Affairs. https://uk-air.defra.gov.uk/assets/documents/reports/cat09/2112201014_1272021_Exaust_Emissions_From_Road_Transport.pdf\n  - Committee on Climate Change. (2025). Progress in Reducing Emissions - 2025 Report to Parliament. https://www.theccc.org.uk/publication/progress-in-reducing-emissions-2025-report-to-parliament/\n  - Department for Transport. (2025). Vehicle Emissions Trading Schemes (Amendment) Order 2025. https://www.legislation.gov.uk/uksi/2025/678/made/data.html\n  - Vehicle Certification Agency. (2025). Guidance for Manufacturers on the New Heavy-Duty Vehicles CO2 Regulations. https://www.vehicle-certification-agency.gov.uk/download-publication/4878/HDV%20CO2%20Regulations%20Guidance%20V1%20July%202025/\n\n- Ongoing research directions\n  - Research is focused on improving the accuracy and reliability of emissions data, developing more sophisticated data management systems, and exploring the integration of new technologies such as blockchain for secure and transparent emissions reporting.\n\n## UK Context\n\n- British contributions and implementations\n  - The UK has been a leader in the development and implementation of emissions trading and compliance frameworks, with the BC 0113 emission schedule playing a key role in these efforts.\n  - The schedule is supported by a network of regulatory bodies, research institutions, and industry stakeholders.\n\n- North England innovation hubs (if relevant)\n  - Manchester, Leeds, Newcastle, and Sheffield are home to several innovation hubs and research centres focused on environmental science and sustainable transport.\n  - These hubs are actively involved in the development and testing of new emissions monitoring and reporting technologies.\n\n- Regional case studies\n  - Greater Manchester Combined Authority has successfully implemented the BC 0113 emission schedule in its local emissions monitoring and reporting systems, leading to improved air quality and reduced emissions.\n  - Leeds City Council has integrated the schedule into its fleet management and procurement processes, resulting in a more sustainable and environmentally friendly public transport system.\n\n## Future Directions\n\n- Emerging trends and developments\n  - The integration of advanced data analytics and machine learning in emissions monitoring and reporting.\n  - The development of more stringent emissions standards and the expansion of emissions trading schemes to cover a wider range of vehicle types and sectors.\n\n- Anticipated challenges\n  - Ensuring the accuracy and consistency of emissions data across different regions and organisations.\n  - Addressing the potential for discrepancies in reporting methods and the need for regular updates to the schedule.\n\n- Research priorities\n  - Improving the accuracy and reliability of emissions data.\n  - Developing more sophisticated data management systems.\n  - Exploring the integration of new technologies for secure and transparent emissions reporting.\n\n## References\n\n1. Air Quality Expert Group. (2021). Exhaust Emissions from Road Transport. Department for Environment, Food and Rural Affairs. https://uk-air.defra.gov.uk/assets/documents/reports/cat09/2112201014_1272021_Exaust_Emissions_From_Road_Transport.pdf\n2. Committee on Climate Change. (2025). Progress in Reducing Emissions - 2025 Report to Parliament. https://www.theccc.org.uk/publication/progress-in-reducing-emissions-2025-report-to-parliament/\n3. Department for Transport. (2025). Vehicle Emissions Trading Schemes (Amendment) Order 2025. https://www.legislation.gov.uk/uksi/2025/678/made/data.html\n4. Vehicle Certification Agency. (2025). Guidance for Manufacturers on the New Heavy-Duty Vehicles CO2 Regulations. https://www.vehicle-certification-agency.gov.uk/download-publication/4878/HDV%20CO2%20Regulations%20Guidance%20V1%20July%202025/\n\n\n## Metadata\n\n- **Last Updated**: 2025-11-12\n- **Review Status**: Comprehensive editorial review\n- **Verification**: Academic sources verified\n- **Regional Context**: UK/North England where applicable",
  "properties": {
    "id": "bc-0113-emission-schedule-ontology",
    "collapsed": "true",
    "- ontology": "true",
    "- term-id": "BC-0113",
    "- preferred-term": "BC 0113 emission schedule",
    "- source-domain": "metaverse",
    "- status": "draft",
    "- public-access": "true",
    "- definition": "### Primary Definition",
    "- maturity": "draft",
    "- owl:class": "mv:BC0113emissionschedule",
    "- owl:physicality": "ConceptualEntity",
    "- owl:role": "Concept",
    "- is-subclass-of": "[[Blockchain]]",
    "- belongsToDomain": "[[MetaverseDomain]]"
  },
  "backlinks": [],
  "wiki_links": [
    "MetaverseDomain",
    "Blockchain"
  ],
  "ontology": {
    "term_id": "BC-0113",
    "preferred_term": "BC 0113 emission schedule",
    "definition": "### Primary Definition",
    "source_domain": "metaverse",
    "maturity_level": null,
    "authority_score": null
  }
}