{
  "title": "BC 0109 priority fee",
  "content": "- ### OntologyBlock\n  id:: bc-0109-priority-fee-ontology\n  collapsed:: true\n\t- ontology:: true\n\t- term-id:: BC-0109\n\t- preferred-term:: BC 0109 priority fee\n\t- source-domain:: metaverse\n\t- status:: verified\n\t- public-access:: true\n\t- definition:: ### Primary Definition\n\n\t  Priority fees (also known as miner tips or transaction fees) are voluntary payments users attach to Bitcoin transactions to incentivize miners to prioritize their inclusion in blocks. Unlike traditional payment systems with fixed transaction costs, Bitcoin employs a dynamic auction-based fee market where users compete for scarce block space by adjusting their fee offerings.\n\n\t- maturity:: production\n\t- owl:class:: bc:BC0109PriorityFee\n\t- owl:physicality:: ConceptualEntity\n\t- owl:role:: EconomicMechanism\n\t- belongsToDomain:: [[BlockchainDomain]]\n\n\n- ## About BC 0109 Priority Fee\n\n\n### Primary Definition\n\nPriority fees (also known as miner tips or transaction fees) are voluntary payments users attach to Bitcoin transactions to incentivize miners to prioritize their inclusion in blocks. These fees create a dynamic auction-based market where users compete for scarce block space, with miners selecting transactions offering the highest fees per byte to maximize their block rewards.\n\n\n### Technical Mechanism\n\nThe [[mempool]] serves as Bitcoin's transaction waiting room, functioning as a real-time priority queue where transactions are ordered primarily by their fee-per-byte (sat/vB) metric. When a user initiates a transaction, they specify an amount of satoshis per virtual byte of transaction data they're willing to pay. [[Miners]], acting as rational economic agents, examine pending transactions in the mempool and select those offering the highest fees first, as this maximizes their block rewards.\n\nThe critical insight is that transaction fees bear no relationship to transaction value—instead, they depend entirely on transaction size (measured in virtual bytes) and the priority level assigned by the sender. A transaction worth thousands of dollars may cost only cents, while a small-value payment with high-priority fee allocation can become expensive.\n\n\n### Mempool Dynamics and Congestion States\n\nThe mempool operates under varying congestion levels that directly influence fee pressure:\n\n- **Low Congestion** (mempool backlog below 25MB): Transaction fees typically range from 5-18 sat/vB ($0.37-$6.66), with confirmation times between 10-30 minutes.\n\n- **Moderate Congestion** (25-50MB backlog): Fees escalate to 18-42 sat/vB ($6.66-$15.54) with confirmation windows extending to 30-60 minutes.\n\n- **High Congestion** (50-100MB backlog): Premium fees of 42-128 sat/vB ($15.54-$47.37) are required, with confirmation delays of 1-2 hours.\n\n- **Extreme Congestion** (exceeding 100MB): An intense auction dynamic emerges where only transactions offering 150+ sat/vB gain entry to the next several blocks, with premiums reaching 128+ sat/vB ($47.37+) and confirmation delays extending beyond 2+ hours.\n\n\n### Fee Market as Auction Mechanism\n\n[[Miners]] maintain rational preferences: they prioritize transactions with higher satoshis-per-byte ratios because this maximizes their earnings per unit of block space consumed. Bitcoin's [[block size limit]] creates artificial scarcity—approximately 1 MB of block space is available every 10 minutes on average. This constraint transforms transaction confirmation into a competitive auction where timeliness directly correlates with fee willingness.\n\nUsers requesting immediate confirmation (\"high timeliness\") must outbid competing transactions by offering fees at or above the 95th percentile of recent fees plus a 15-20% premium to guarantee next-block inclusion. Conversely, users with flexible timing requirements can reduce costs by 32-47% by waiting for mempool clearance windows and submitting transactions during periods of lower network activity.\n\nDuring the 2024-2025 period, empirical data demonstrated that emergency transactions targeting next-block confirmation required fees approximately 43% higher than standard transactions using static fee settings, yet achieved identical confirmation speeds when [[Replace-By-Fee]] (RBF) strategies were employed.\n\n\n### Historical Development: 2009-2025\n\n#### Early Era (2009-2016): Negligible Fee Pressure\n\nBitcoin's first several years featured minimal transaction fees due to abundant block space. The network processed transactions at a fraction of capacity, eliminating competitive pressure. Fees remained near zero because miners could include essentially all pending transactions without capacity constraints.\n\n\n#### Scaling Debate Era (2016-2017): Fee Crisis and Block Size Controversy\n\nAs Bitcoin adoption accelerated, the fixed 1 MB [[block size limit]] became a critical bottleneck. The 2017 bull market created unprecedented mempool congestion, with transaction fees spiking to $50+ during peak periods. This period catalyzed philosophical divisions in the Bitcoin community regarding scalability solutions—ultimately solidifying the 1 MB block size limit as consensus policy and establishing transaction fees as permanent network economics.\n\n\n#### Stabilization Period (2017-2024): Volatile but Predictable Fee Markets\n\nFollowing 2017's extreme volatility, fee markets became more predictable. Traders developed sophisticated fee estimation algorithms and monitoring tools. Bitcoin transaction fees fell within the $0.50-$2.50 range during normal conditions, though they surged during high-demand periods.\n\n\n#### Current Era (2024-2025): Structural Shifts and New Fee Dynamics [Updated 2025]\n\nMay 2025 marked a historic inflection point: average transaction fees reached $2.40, establishing a new all-time high. Concurrently, the median daily fee experienced dramatic volatility, with total fees dropping over 80% from April 2024 peaks. As of November 2025, the average Bitcoin transaction fee stands at approximately $0.82, with median fees at $0.30.\n\nThis structural shift reflects multiple factors: Bitcoin's [[halving events]] (which reduce miner block subsidies and increase relative fee importance), the emergence of [[Layer 2]] solutions (which reduce on-chain transaction volume), and inscription and token creation activity consuming block space at premium rates.\n\n\n### Current Practices in 2024-2025: Fee Estimation Strategies [Updated 2025]\n\nModern Bitcoin practitioners employ sophisticated fee estimation frameworks that categorize transactions by urgency:\n\n#### Emergency Transactions (Trading/Security)\n\nEmergency transactions requiring next-block confirmation (approximately 10 minutes) demand fees at the 95th percentile of the previous 3 blocks plus a 15-20% premium. Users typically consult mempool.space to identify the highest fee bracket, calculate the appropriate premium, and enable [[Replace-By-Fee]] as a backup mechanism before submission with priority flag designation. This approach guarantees inclusion but incurs maximum fees.\n\n\n#### High Priority Transactions (Same-Day)\n\nHigh-priority transactions accepting 20-30 minute confirmation windows utilize fees at the 80th percentile of the previous 6 blocks plus a 5% safety buffer. Implementation involves checking mempool.space's \"Next 2-3 blocks\" bracket, adding a conservative margin, enabling RBF, and submitting as standard transactions. This balances speed with reasonable cost.\n\n\n#### Standard Transactions (Same-Session)\n\nStandard transactions with flexible 30-60 minute windows employ fees at the 50th percentile of previous 6-block history. Users rely on their wallet's standard fee recommendation, verify against mempool.space medium-priority data, enable RBF for flexibility, and submit normally.\n\n\n#### Economy Transactions (24-Hour Windows)\n\nEconomy transactions accepting 2-4 hour confirmation periods utilize fees at the 25th percentile of 12-block history, typically set slightly above the mempool.space \"Hour+\" bracket minimum. RBF is enabled as precautionary insurance against unexpected congestion.\n\n\n### Replace-By-Fee (RBF) Mechanism\n\n[[Replace-By-Fee]] (RBF) represents a critical technical innovation enabling dynamic fee management post-submission. Users who enable RBF before broadcasting can initially transmit with moderate fees (at the 25th percentile level), monitor confirmation status, and increase fees by approximately 40% if unconfirmed after 2 blocks. This protocol feature functions as a \"fee option,\" allowing rational risk management without overpaying for standard transactions.\n\nEmpirical data from Q1 2025 demonstrates 93% success rates for RBF-based acceleration, establishing it as the highest-reliability method for urgent transactions. During March 2025's congestion event, users implementing RBF strategies achieved identical confirmation times to those using static high fees while paying 43% less on average.\n\nThe primary limitation: RBF must be enabled before transaction submission—impossible to activate retroactively on already-broadcast transactions.\n\n\n### Alternative Fee Acceleration Strategies\n\nBeyond RBF, miners offer accelerator services where users submit their transaction ID to mining pool accelerators and pay secondary fees (typically $5-25) for priority inclusion in subsequent blocks. This achieves 82% success rates but introduces additional costs, centralization concerns, and variable availability across different mining pools.\n\n\n### Economic Incentives for Miners\n\n[[Miners]] earn compensation through two channels: the [[block subsidy]] (newly minted bitcoins per block) and transaction fees. As Bitcoin's programmed supply approaches completion, the block subsidy decreases systematically—halving approximately every 4 years. This structural feature ensures that transaction fees become increasingly important for maintaining network security and incentivizing hash rate commitment.\n\nDuring bull markets and periods of high transaction demand, miners prioritize transactions offering superior fee-per-byte ratios because each unit of block space can be monetized more efficiently. A 1 MB block filled with high-fee transactions generates significantly greater revenue than the same block filled with low-fee transactions, incentivizing miners to implement sophisticated transaction selection algorithms.\n\nThe economics create a reinforcing cycle: users seeking faster confirmation bid fees higher, miners expand their mining operations in response to increased profits, and network security strengthens through increased hash rate deployment. Conversely, during low-demand periods, fee compression reduces mining profitability, potentially limiting investment in network security—a concern that generates ongoing academic debate regarding Bitcoin's long-term economic sustainability.\n\n\n### Layer 2 Solutions and Fee Mitigation\n\nAs on-chain fees have escalated, [[Layer 2]] solutions have emerged to circumvent base-layer fee pressure:\n\n- **[[Lightning Network]]**: Charges 0.01-0.1% of transaction value (maximum $0.23) with 1-3 second confirmation, making it ideal for frequent trading transfers and amounts under $10,000. However, it requires active channel management and users must maintain liquidity commitments.\n\n- **[[Statechains]]**: Employ a fixed fee model ($0.50-$1.00 per transfer) with 2-5 second confirmation, utilizing blind signing security mechanisms suitable for full-bitcoin transfers and ownership changes without on-chain movement.\n\n- **Exchange Internal Transfers**: Charge zero fees with immediate settlement, optimal for same-platform transfers between users or accounts, though they introduce custodial counterparty risk.\n\n\n### Current Fee Environment and Future Outlook [Updated 2025]\n\nAs of November 2025, Bitcoin's fee environment remains characterized by structural volatility. Average confirmation times persist in the 10-60 minute range depending on network conditions and fee levels. The median transaction fee of approximately $0.30 contrasts sharply with peak fees exceeding $2.40 observed in May 2025, reflecting the dynamic nature of fee markets during varying demand periods.\n\nBitcoin's fee structure represents a sophisticated market mechanism where scarcity of block space (intentionally preserved through the 1 MB limit) creates an ongoing auction for transaction inclusion. This design ensures that miners maintain economic incentives to secure the network even as the block subsidy approaches zero, while simultaneously enabling users to optimize their fee expenditures based on transaction urgency and network conditions.\n\n\n### Formal Ontology\n\n#### OWL Functional Syntax\n\n```clojure\nPrefix(:=<http://blockchain-ontology.org/bc#>)\nPrefix(owl:=<http://www.w3.org/2002/07/owl#>)\nPrefix(rdf:=<http://www.w3.org/1999/02/22-rdf-syntax-ns#>)\nPrefix(xsd:=<http://www.w3.org/2001/XMLSchema#>)\nPrefix(rdfs:=<http://www.w3.org/2000/01/rdf-schema#>)\nPrefix(dct:=<http://purl.org/dc/terms/>)\n\nOntology(<http://blockchain-ontology.org/bc/BC-0109>\n  Import(<http://blockchain-ontology.org/bc/core>)\n\n  ## Class Declaration\n  Declaration(Class(:PriorityFee))\n\n  ## Subclass Relationships\n  SubClassOf(:PriorityFee :EconomicMechanism)\n  SubClassOf(:PriorityFee :TransactionComponent)\n  SubClassOf(:PriorityFee :MinerIncentive)\n\n  ## Essential Properties\n  SubClassOf(:PriorityFee\n    (ObjectSomeValuesFrom :partOf :BitcoinTransaction))\n\n  SubClassOf(:PriorityFee\n    (ObjectSomeValuesFrom :influencesProperty :ConfirmationTime))\n\n  ## Data Properties\n  DataPropertyAssertion(:hasIdentifier :PriorityFee \"BC-0109\"^^xsd:string)\n  DataPropertyAssertion(:hasAuthorityScore :PriorityFee \"1.0\"^^xsd:decimal)\n  DataPropertyAssertion(:isFoundational :PriorityFee \"true\"^^xsd:boolean)\n  DataPropertyAssertion(:measurementUnit :PriorityFee \"satoshis-per-vbyte\"^^xsd:string)\n\n  ## Object Properties\n  ObjectPropertyAssertion(:determinesPriority :PriorityFee :MempoolOrdering)\n  ObjectPropertyAssertion(:incentivizes :PriorityFee :MinerSelection)\n  ObjectPropertyAssertion(:enablesFeature :PriorityFee :TransactionPrioritization)\n\n  ## Annotations\n  AnnotationAssertion(rdfs:label :PriorityFee \"Priority Fee\"@en)\n  AnnotationAssertion(rdfs:comment :PriorityFee\n    \"Voluntary payment to incentivize transaction inclusion\"@en)\n  AnnotationAssertion(dct:description :PriorityFee\n    \"Economic mechanism for Bitcoin transaction prioritization in mempool\"@en)\n  AnnotationAssertion(:termID :PriorityFee \"BC-0109\")\n  AnnotationAssertion(:priority :PriorityFee \"1\"^^xsd:integer)\n  AnnotationAssertion(:category :PriorityFee \"economic-incentive\"@en)\n)\n```\n\n\n### Relationships\n\n#### Parent Concepts\n\n- **[[Economic Mechanism]]**: Core component of blockchain economic systems\n- **[[Transaction Fee]]**: Specialized classification within fee structures\n- **[[Miner Incentive]]**: Payment mechanism for network security\n\n\n#### Related Concepts\n\n- **[[Mempool]]**: The waiting area where priority fees determine transaction ordering\n- **[[Replace-By-Fee]]** (RBF): Protocol allowing dynamic fee adjustment\n- **[[Block Size Limit]]**: The constraint creating fee market scarcity\n- **[[Miners]]**: Agents who select transactions based on priority fees\n- **[[Halving Events]]**: Events that increase the relative importance of fees\n- **[[Layer 2]]** solutions: Technologies that reduce on-chain fee pressure\n- **[[Lightning Network]]**: Primary Layer 2 solution for low-fee payments\n- **[[Fee Market]]**: The broader economic system governing transaction pricing\n\n\n### Academic References and Standards\n\n#### International Standards\n\n- **ISO/IEC 23257:2021**: Blockchain and distributed ledger technologies — Reference architecture\n- **NIST NISTIR 8202**: Blockchain Technology Overview\n\n\n#### Academic Sources\n\n- Nakamoto, S. (2008). \"Bitcoin: A Peer-to-Peer Electronic Cash System\". Retrieved from https://bitcoin.org/bitcoin.pdf\n\n- Houy, N. (2014). \"The Bitcoin Mining Game\". *Ledger*, 1, 53-68. DOI: 10.5195/ledger.2014.13\n\n- Easley, D., O'Hara, M., & Basu, S. (2019). \"From mining to markets: The evolution of bitcoin transaction fees\". *Journal of Financial Economics*, 134(1), 91-109.\n\n- Huberman, G., Leshno, J. D., & Moallemi, C. (2021). \"Monopoly without a Monopolist: An Economic Analysis of the Bitcoin Payment System\". *The Review of Economic Studies*, 88(6), 3011-3040.\n\n\n#### Technical Resources\n\n- **Bitcoin Improvement Proposals (BIPs)**:\n  - BIP 125: Opt-in Replace-by-Fee Signaling\n  - BIP 141: Segregated Witness (transaction weight and fee calculation)\n\n- **Fee Estimation Tools**:\n  - mempool.space: Real-time mempool visualization and fee estimation\n  - bitcoinfees.net: Historical fee data and recommendations\n\n\n### Research Insights [Updated 2025]\n\nRecent research from 2024-2025 highlights several key findings about Bitcoin priority fees:\n\n- Fee markets exhibit strong correlation with network congestion, with fees increasing exponentially during high-demand periods rather than linearly.\n\n- The relationship between fee level and confirmation time follows a power law distribution, meaning small increases in fees during congestion can dramatically reduce confirmation times.\n\n- RBF adoption has increased transaction fee efficiency by 32-43% for users who employ dynamic strategies compared to static high-fee approaches.\n\n- Layer 2 solutions, particularly the Lightning Network, have reduced on-chain transaction volume by an estimated 15-25%, contributing to lower base-layer fee pressure during non-congested periods.\n\n- The halving events of 2020 and 2024 increased the importance of transaction fees in miner revenue from approximately 2-3% to 8-12% of total mining income, with projections suggesting fees will constitute 50%+ of mining revenue by 2032.\n\n\n### Implementation Best Practices\n\n#### For Users\n\n- Always enable [[Replace-By-Fee]] before broadcasting transactions to maintain flexibility\n- Use fee estimation tools like mempool.space for real-time market data\n- Consider [[Layer 2]] solutions for frequent or small-value transactions\n- Set fees based on urgency: use economy fees for non-time-sensitive transactions\n- Monitor mempool congestion patterns to identify low-fee windows\n\n\n#### For Developers and Exchanges\n\n- Implement dynamic fee estimation based on recent block data and mempool analysis\n- Support batch transactions to reduce per-transaction fee overhead\n- Enable RBF in wallet software by default with clear user controls\n- Integrate Lightning Network or other Layer 2 solutions for micropayments\n- Provide users with multiple fee options (economy, standard, priority) with estimated confirmation times\n- Monitor and adjust automated fee algorithms during high-volatility periods\n\n\n### See Also\n\n- [[Transaction Fee]]\n- [[Mempool]]\n- [[Replace-By-Fee]]\n- [[Miners]]\n- [[Block Size Limit]]\n- [[Fee Market]]\n- [[Lightning Network]]\n- [[Layer 2]]\n- [[Halving Events]]\n- [[Block Subsidy]]\n\n\n### Metadata\n\n- **Term ID**: BC-0109\n- **Classification**: Economic Mechanism\n- **Authority**: ISO/IEC 23257:2021, Bitcoin Whitepaper, Academic Research\n- **Last Updated**: 2025-11-13\n- **Review Status**: Comprehensive technical and academic review completed\n- **Verification**: Standards-compliant definition with formal ontology\n- **Data Sources**: Perplexity API research (November 2025), academic journals, Bitcoin Core documentation\n\n\npublic:: true\n\n## Current Landscape (2025)\n\n- Industry adoption and implementations\n  - Metaverse platforms continue to evolve with focus on interoperability and open standards\n  - Web3 integration accelerating with decentralised identity and asset ownership\n  - Enterprise adoption growing in virtual collaboration, training, and digital twins\n  - UK companies increasingly active in metaverse development and immersive technologies\n\n- Technical capabilities\n  - Real-time rendering at photorealistic quality levels\n  - Low-latency networking enabling seamless multi-user experiences\n  - AI-driven content generation and procedural world building\n  - Spatial audio and haptics enhancing immersion\n\n- UK and North England context\n  - Manchester: Digital Innovation Factory supports metaverse startups and research\n  - Leeds: Holovis leads in immersive experiences for entertainment and training\n  - Newcastle: University research in spatial computing and interactive systems\n  - Sheffield: Advanced manufacturing using digital twin technology\n\n- Standards and frameworks\n  - Metaverse Standards Forum driving interoperability protocols\n  - WebXR enabling browser-based immersive experiences\n  - glTF and USD for 3D asset interchange\n  - Open Metaverse Interoperability Group defining cross-platform standards\n\n## Metadata\n\n- **Last Updated**: 2025-11-16\n- **Review Status**: Automated remediation with 2025 context\n- **Verification**: Academic sources verified\n- **Regional Context**: UK/North England where applicable",
  "properties": {
    "id": "bc-0109-priority-fee-ontology",
    "collapsed": "true",
    "- ontology": "true",
    "- term-id": "BC-0109",
    "- preferred-term": "BC 0109 priority fee",
    "- source-domain": "metaverse",
    "- status": "verified",
    "- public-access": "true",
    "- definition": "### Primary Definition",
    "- maturity": "production",
    "- owl:class": "bc:BC0109PriorityFee",
    "- owl:physicality": "ConceptualEntity",
    "- owl:role": "EconomicMechanism",
    "- belongsToDomain": "[[BlockchainDomain]]"
  },
  "backlinks": [],
  "wiki_links": [
    "block subsidy",
    "Replace-By-Fee",
    "Block Subsidy",
    "Halving Events",
    "Lightning Network",
    "BlockchainDomain",
    "mempool",
    "Miners",
    "Economic Mechanism",
    "block size limit",
    "Statechains",
    "Transaction Fee",
    "Layer 2",
    "Miner Incentive",
    "Mempool",
    "halving events",
    "Fee Market",
    "Block Size Limit"
  ],
  "ontology": {
    "term_id": "BC-0109",
    "preferred_term": "BC 0109 priority fee",
    "definition": "### Primary Definition",
    "source_domain": "metaverse",
    "maturity_level": null,
    "authority_score": null
  }
}