{
  "title": "BC 0103 halving",
  "content": "- ### OntologyBlock\n  id:: bc-0103-halving-ontology\n  collapsed:: true\n- ontology:: true\n- term-id:: BC-0103\n- preferred-term:: BC 0103 halving\n- source-domain:: metaverse\n- status:: draft\n- public-access:: true\n- definition:: ### Primary Definition\nPeriodic reward reduction within blockchain systems, providing essential functionality for distributed ledger technology operations and properties.\n- maturity:: draft\n- owl:class:: mv:BC0103halving\n- owl:physicality:: ConceptualEntity\n- owl:role:: Concept\n- belongsToDomain:: [[MetaverseDomain]]\n\n\n- ## About BC 0103 halving\n\n- ### Primary Definition\nPeriodic reward reduction within blockchain systems, providing essential functionality for distributed ledger technology operations and properties.\n\n\n- ## Academic Context\n\n- [[Bitcoin halving]] is a pre-programmed event within the [[Bitcoin]] protocol that reduces the [[block reward]] miners receive by 50%, occurring approximately every four years or every 210,000 blocks. This mechanism enforces scarcity by limiting the total supply of Bitcoin to 21 million coins, a fundamental principle underpinning Bitcoin's value proposition as a [[store of value]].\n  - The halving acts as an anti-inflationary measure, gradually decreasing the rate at which new bitcoins enter circulation. This contrasts sharply with fiat currencies that typically lose value through inflation, as Bitcoin's [[monetary policy]] is algorithmic and transparent rather than controlled by central authorities.\n  - Academically, Bitcoin halving is studied within the fields of [[cryptoeconomics]], [[monetary theory]], and [[blockchain technology]], with emphasis on its impact on supply dynamics, [[miner incentives]], and market behavior. The mechanism represents a novel approach to controlling [[digital scarcity]] through programmatic enforcement.\n\n\n- ## The Bitcoin Whitepaper and Halving Mechanism\n\n- Satoshi Nakamoto's 2008 whitepaper \"Bitcoin: A Peer-to-Peer Electronic Cash System\" introduced a decentralized, peer-to-peer electronic cash system that operates without intermediaries, relying on cryptographic proof and consensus among network participants to ensure security and prevent [[double-spending]].\n  - The [[Proof of Work]] (PoW) mechanism requires [[miners]] to compete to solve computational puzzles, securing the network and validating transactions. The first to solve the puzzle adds a new block to the [[blockchain]] and receives a block reward, creating the economic incentive structure that sustains network security.\n  - The block reward system serves dual purposes: it incentivizes miners to contribute computational power and maintain network security, while simultaneously controlling the money supply through a predictable issuance schedule. Initially, block rewards are the primary incentive, but as rewards decrease through halving events, [[transaction fees]] are expected to become the main compensation for miners.\n  - Bitcoin's total supply is capped at 21 million coins, with the block reward halved every 210,000 blocks (approximately every four years). This halving mechanism slows the rate at which new bitcoins are created, reducing inflation and ensuring scarcity similar to precious metals like gold. When all 21 million bitcoins have been mined (estimated around 2140), miners will be compensated solely through transaction fees, as no new bitcoins will be created.\n\n\n- ## Historical Halving Events [Updated 2025]\n\n- ### First Halving (November 28, 2012)\n  - Block height: 210,000\n  - Block reward reduced from 50 BTC to 25 BTC\n  - Price at halving: approximately $12\n  - Price 365 days later: approximately $1,000 (8,233% increase)\n  - This first halving demonstrated the economic impact of supply reduction, with Bitcoin experiencing significant price appreciation in the following 12-18 months.\n\n- ### Second Halving (July 9, 2016)\n  - Block height: 420,000\n  - Block reward reduced from 25 BTC to 12.5 BTC\n  - Price at halving: approximately $650\n  - Price 365 days later: approximately $2,500 (284% increase)\n  - Peak of cycle (December 2017): approximately $19,000\n  - The second halving preceded the 2017 bull run, reinforcing the correlation between supply reduction and market cycles.\n\n- ### Third Halving (May 11, 2020)\n  - Block height: 630,000\n  - Block reward reduced from 12.5 BTC to 6.25 BTC\n  - Price at halving: approximately $8,700\n  - Price 365 days later: approximately $57,000 (555% increase)\n  - Peak of cycle (November 2021): approximately $69,000\n  - The third halving occurred during global monetary expansion and institutional adoption, contributing to unprecedented price levels.\n\n- ### Fourth Halving (April 19, 2024)\n  - Block height: 840,000\n  - Block reward reduced from 6.25 BTC to 3.125 BTC\n  - Price at halving: approximately $64,000\n  - The most recent halving reduced Bitcoin's annual inflation rate to approximately 0.85%, making it more scarce than gold on an annual production basis.\n  - As of November 2024, Bitcoin's price increased 41.2% to approximately $90,000 in the seven months following the halving, though this underperformed the gains seen at the same point in previous post-halving periods (53.3% in 2016, 122.5% in 2020).\n\n- ### Fifth Halving (Projected April 2028)\n  - Estimated block height: 1,050,000\n  - Block reward will reduce from 3.125 BTC to 1.5625 BTC\n  - Annual inflation rate will drop to approximately 0.4%\n  - By this point, over 19.7 million of the 21 million total bitcoins will have been mined (approximately 93.8% of total supply).\n\n\n- ## Halving Mechanism and Economic Impact\n\n- ### How Bitcoin Halving Works\n  - The halving is triggered automatically by the blockchain itself when 210,000 blocks have been mined, requiring no human intervention or governance decisions. It is embedded in Bitcoin's core protocol and cannot be changed without overwhelming network consensus.\n  - The process reduces miners' BTC rewards for transaction authentication by 50%, slowing down the rate at which new Bitcoin enters circulation. This creates a predictable, transparent monetary policy unlike fiat currencies controlled by central banks.\n  - The halving mechanism ensures controlled money supply and deflationary economics, with the final bitcoin estimated to be mined around the year 2140. After that point, miners will rely entirely on transaction fees for compensation.\n\n- ### Economic Impact and Supply Dynamics\n  - **Inflation Reduction**: Each halving decreases Bitcoin's inflation rate by reducing the rate of new BTC issuance. After the 2024 halving, Bitcoin's annual inflation rate fell to approximately 0.85%, lower than gold's estimated 1.5-2% annual supply growth.\n  - **Supply Shock**: Fewer bitcoins entering circulation daily creates scarcity pressure. If demand remains constant or increases while supply growth decreases, basic economic principles suggest upward price pressure.\n  - **Mining Economics**: Miners face reduced block reward incentives, requiring increased operational efficiency, lower energy costs, or higher Bitcoin prices to maintain profitability. This can lead to consolidation in the mining industry and increased focus on renewable energy sources.\n  - **Market Cycles**: Halvings have historically preceded bull markets and increased market attention, though the magnitude of price increases appears to be diminishing with each successive halving as the market matures and Bitcoin's market capitalization grows.\n\n- ### Price Performance and Market Cycles\n  - Historically, Bitcoin halvings have been followed by significant price increases within 12-18 months. The first halving in 2012 saw Bitcoin rise from around $12 to over $1,000. The second halving in 2016 preceded a peak at over $19,000 in December 2017. The third halving in 2020 preceded a major bull run to $69,000 in November 2021.\n  - The 2024 halving cycle shows Bitcoin increasing 5.72x from its cycle low, close to the 5.18x and 5.93x in previous cycles. If historical patterns continue, Bitcoin could potentially reach between $104,000 and $243,000 within 12-24 months post-halving, though past performance does not guarantee future results.\n  - Bitcoin's drawdown during the 2022 bear market was 76.9%, less severe than previous cycle lows (86.3% in 2018, 85.1% in 2015, 93.5% in 2011), suggesting market maturation with less extreme volatility.\n  - The launch of spot Bitcoin ETFs in the United States in January 2024 introduced institutional capital flows that may influence post-halving price dynamics differently than in previous cycles.\n\n\n- ## Current Landscape (2025)\n\n- ### Market Context\n  - The most recent [[Bitcoin halving]] occurred on April 19, 2024, reducing the mining reward from 6.25 to 3.125 bitcoins per block. This represents the fourth halving in Bitcoin's history and reduces the annual inflation rate to approximately 0.85%, making Bitcoin more scarce than gold on an annual production basis.\n  - The next halving is projected for approximately April 2028, when rewards will halve again to 1.5625 bitcoins per block. At that point, over 93% of all bitcoins that will ever exist will have been mined.\n  - Industry adoption remains robust, with major cryptocurrency exchanges such as [[Coinbase]], [[Binance]], and [[Kraken]] providing educational resources and trading services aligned with halving events. Institutional investors including [[BlackRock]], [[Fidelity]], and [[ARK Invest]] have launched Bitcoin ETF products, bringing traditional finance exposure to halving cycles.\n\n- ### Institutional and Technological Developments\n  - The 2024 approval of spot Bitcoin ETFs in the United States marked a watershed moment for institutional adoption, with over $50 billion in assets under management within the first year. This institutional interest has created new dynamics around halving events, as professional investors analyze supply reduction impacts.\n  - [[Mining]] operations have become increasingly sophisticated, with publicly traded mining companies optimizing for energy efficiency and renewable energy sources in anticipation of reduced block rewards. The shift toward sustainable mining practices has accelerated, particularly in regions with abundant renewable energy.\n  - Technical capabilities include secure, decentralized validation of transactions through the [[Proof of Work]] consensus mechanism, though halving events increase pressure on miners' profitability. This can potentially influence [[network security]] and decentralization, as smaller mining operations may struggle with reduced rewards.\n  - [[Layer 2]] solutions such as the [[Lightning Network]] have grown significantly, providing scaling capabilities that reduce reliance on base layer transaction fees while enabling new use cases for Bitcoin as a medium of exchange.\n\n- ### Regulatory and Standards Evolution\n  - Standards and frameworks around Bitcoin and blockchain technology continue to evolve, with regulatory bodies in the UK, EU, and United States focusing on consumer protection, market integrity, and anti-money laundering compliance.\n  - The UK's [[Financial Conduct Authority]] (FCA) has developed comprehensive guidance for cryptocurrency firms, while the European Union's [[Markets in Crypto-Assets]] (MiCA) regulation provides a unified regulatory framework. These developments create clearer operational guidelines for firms navigating post-halving market conditions.\n\n\n- ## UK and Northern England Context\n\n- ### UK Institutional and Academic Engagement\n  - The United Kingdom has seen increasing institutional interest in Bitcoin and blockchain technologies, with major financial institutions in London exploring Bitcoin as part of diversified investment portfolios. The approval of Bitcoin ETFs globally has influenced UK institutional approaches, even as the FCA maintains cautious regulatory oversight.\n  - UK universities including [[Imperial College London]], [[University of Cambridge]], [[University of Edinburgh]], and [[University College London]] are integrating blockchain and cryptocurrency studies into computer science, economics, and finance curricula. The [[Cambridge Centre for Alternative Finance]] publishes regular research on Bitcoin mining, energy consumption, and market dynamics.\n\n- ### Northern England Innovation Ecosystem\n  - Northern England cities such as [[Manchester]], [[Leeds]], [[Newcastle]], and [[Sheffield]] host blockchain accelerators, fintech incubators, and cryptocurrency meetup communities that contribute to innovation in crypto asset management and mining efficiency.\n  - Manchester's fintech corridor includes companies exploring blockchain applications in finance, supply chain, and digital identity. Leeds has emerging blockchain consultancies and development studios focused on enterprise blockchain solutions.\n  - Sheffield and Newcastle have emerging communities focused on sustainable blockchain practices, including university research into reducing the carbon footprint of mining operations and exploring renewable energy integration for cryptocurrency infrastructure.\n  - The northern innovation ecosystem benefits from lower operational costs compared to London, abundant renewable energy potential (particularly wind energy), and strong academic institutions collaborating with industry on blockchain research.\n\n\n- ## Research and Literature\n\n- ### Foundational Academic Papers\n  - **Nakamoto, S. (2008). \"Bitcoin: A Peer-to-Peer Electronic Cash System.\"**\n    - The original whitepaper introducing Bitcoin and its halving mechanism as a core component of monetary policy.\n    - Available at: https://bitcoin.org/bitcoin.pdf\n    - This seminal work introduced the concept of a decentralized, peer-to-peer electronic cash system with a capped supply enforced through halving events every 210,000 blocks.\n\n  - **Yermack, D. (2013). \"Is Bitcoin a Real Currency? An Economic Appraisal.\"**\n    - NIST Working Paper No. 19747. DOI: 10.3386/w19747\n\n  - **Baur, D. G., Hong, K., & Lee, A. D. (2018). \"Bitcoin: Medium of Exchange or Speculative Assets?\"**\n    - Journal of International Financial Markets, Institutions and Money, 54, 177-189. DOI: 10.1016/j.intfin.2017.12.004\n\n- ### Contemporary Research and Analysis\n  - More recent analyses focus on post-2024 halving market dynamics, including the impact of institutional adoption through ETFs, changes in miner economics, and evolving price volatility patterns.\n  - [[ARK Invest]] publishes quarterly Bitcoin research reports analyzing halving cycles, on-chain metrics, and market performance. Their \"Bitcoin Cycles, Entering 2025\" report examines historical patterns and projects potential price trajectories based on post-halving dynamics.\n  - Ongoing research from institutions like the [[Cambridge Centre for Alternative Finance]], [[Coin Metrics]], and [[Glassnode]] explores the long-term effects of halving on Bitcoin's price cycles, miner behavior, network security, and environmental impacts of mining.\n  - Academic focus areas include: (1) diminishing returns of successive halvings on price appreciation, (2) the transition from block rewards to transaction fees as the primary mining incentive, (3) impacts on mining centralization and network security, and (4) energy consumption patterns and sustainability of proof-of-work mining.\n\n\n- ## Future Directions and Emerging Trends\n\n- ### Technological and Economic Evolution\n  - Emerging trends include the integration of Bitcoin with traditional financial systems through [[ETFs]], [[custody solutions]], and [[institutional-grade infrastructure]]. Increased regulatory clarity across jurisdictions is creating more predictable operating environments for Bitcoin-related businesses.\n  - Advances in mining hardware efficiency, particularly through next-generation [[ASIC]] (Application-Specific Integrated Circuit) technology, are helping miners maintain profitability despite reduced block rewards. The shift toward renewable energy sources, including hydroelectric, solar, and wind power, addresses environmental concerns while reducing operational costs.\n  - The development of [[Layer 2]] scaling solutions like the [[Lightning Network]], [[RGB protocol]], and [[statechains]] expands Bitcoin's utility beyond simple value transfer, enabling micropayments, smart contracts, and improved privacy features.\n\n- ### Challenges and Research Priorities\n  - Anticipated challenges involve balancing miner incentives post-halving with network security requirements. As block rewards continue to diminish, transaction fees must increase sufficiently to maintain mining profitability and network hash rate. This transition represents a critical test of Bitcoin's long-term security model.\n  - Managing environmental concerns remains a priority, with research focusing on sustainable mining solutions, carbon-neutral or carbon-negative operations, and better integration with renewable energy grids. This is particularly relevant to UK and Northern England innovation ecosystems with abundant wind and emerging tidal energy resources.\n  - Addressing market volatility around halving events requires better understanding of behavioral economics, institutional capital flows, and the interplay between supply shocks and demand dynamics. The diminishing impact of successive halvings on price appreciation may reflect market maturation.\n  - Research priorities focus on: (1) improving scalability through layer 2 solutions while maintaining decentralization, (2) enhancing privacy features without compromising regulatory compliance, (3) developing sustainable mining solutions aligned with global climate goals, and (4) understanding the long-term economics of a transaction-fee-only mining incentive model.\n\n- ### Long-Term Outlook\n  - As Bitcoin approaches its maximum supply of 21 million coins (approximately 93.8% mined by 2028), the halving mechanism's impact on supply dynamics will gradually diminish. The final halving is expected around 2140, after which no new bitcoins will be created.\n  - The transition to a transaction-fee-only mining economy will test Bitcoin's security assumptions and economic sustainability. Successfully navigating this transition will require sufficient transaction volume and fee levels to maintain robust network security.\n  - One might say Bitcoin halving is the crypto world's way of keeping miners on their toes—or at least on their energy bills—while demonstrating that scarcity, when programmatically enforced, creates entirely new dynamics in digital asset economics.\n\n\n- ## References and Citations\n\n### Primary Sources\n\n1. **Nakamoto, S. (2008). \"Bitcoin: A Peer-to-Peer Electronic Cash System.\"**\n   - Available at: https://bitcoin.org/bitcoin.pdf\n   - **Context**: The original Bitcoin whitepaper introduced a decentralized, peer-to-peer electronic cash system with a capped supply of 21 million coins. The halving mechanism, occurring every 210,000 blocks, was designed to control money supply through predictable, transparent monetary policy. The block reward system incentivizes miners to secure the network while gradually reducing inflation through halving events. By around 2140, when all bitcoins are mined, miners will rely entirely on transaction fees.\n\n2. **Yermack, D. (2013). \"Is Bitcoin a Real Currency? An Economic Appraisal.\"**\n   - NBER Working Paper No. 19747. DOI: 10.3386/w19747\n\n3. **Baur, D. G., Hong, K., & Lee, A. D. (2018). \"Bitcoin: Medium of Exchange or Speculative Assets?\"**\n   - Journal of International Financial Markets, Institutions and Money, 54, 177-189. DOI: 10.1016/j.intfin.2017.12.004\n\n\n### Industry and Educational Resources\n\n4. **Guarda Academy (2025). \"What is Bitcoin Halving 2025?\"**\n   - Available at: https://guarda.com/academy/crypto/what-is-bitcoin-halving-2025/\n   - **Context**: Bitcoin halving is a pre-programmed event occurring approximately every 210,000 blocks (roughly 4 years) where mining rewards are cut in half. This mechanism acts as Bitcoin's intrinsic countermeasure against inflation, safeguarding the capped supply at 21 million coins. Historical halvings occurred in November 2012 (50→25 BTC), July 2016 (25→12.5 BTC), May 2020 (12.5→6.25 BTC), and April 2024 (6.25→3.125 BTC). The next halving around 2028 will reduce rewards to 1.5625 BTC. Halvings reduce inflation rate, create supply pressure, impact mining economics, and have historically preceded bull markets, though past performance doesn't guarantee future results.\n\n5. **Coinbase Learn (2024). \"What is Bitcoin halving?\"**\n   - Available at: https://www.coinbase.com/learn/crypto-basics/what-is-a-bitcoin-halving\n   - **Context**: Bitcoin halving is a programmed event in the protocol occurring every four years (every 210,000 blocks) where mining rewards are reduced by 50%. The halving mechanism controls the rate at which new bitcoins enter circulation, limiting inflation and ensuring Bitcoin remains deflationary over time. It is automatic, embedded in blockchain code, and cannot be changed without overwhelming network consensus. The initial block reward was 50 BTC in 2009; successive halvings have reduced it to the current 3.125 BTC (as of April 2024). Historically, halvings have preceded significant price increases (2012→2013, 2016→2017, 2020→2021) as reduced supply creation meets constant or increasing demand.\n\n6. **ARK Invest (2024). \"Bitcoin Cycles, Entering 2025.\"**\n   - Available at: https://www.ark-invest.com/articles/analyst-research/bitcoin-cycles-entering-2025\n   - **Context**: Bitcoin's price performance is historically shaped by four-year halving cycles where new bitcoin issuance is cut in half. The most recent halving occurred April 19, 2024, reducing block rewards from 6.25 to 3.125 BTC. As of November 2024, Bitcoin increased 41.2% to $90,446 in the seven months post-halving, underperforming previous cycles (53.3% and 122.5% at same points). Bitcoin's 2022 bear market drawdown of 76.9% was less severe than previous cycles (86.3% in 2018, 85.1% in 2015), suggesting market maturation. From cycle low, Bitcoin increased 5.72x, similar to 5.18x and 5.93x in previous cycles. If patterns continue, Bitcoin could potentially reach $104,000-$243,000 within 12-24 months post-halving, though past performance doesn't guarantee future results. Institutional adoption through ETFs and potential government strategic reserves may influence 2025 dynamics.\n\n\n- ## Metadata\n\n- **Last Updated**: 2025-11-13\n- **Review Status**: Comprehensive editorial review with Perplexity API expansions\n- **Verification**: Academic sources verified, all four historical halvings documented\n- **Regional Context**: UK/Northern England innovation ecosystem included\n- **Content Quality**: URLs expanded with citations, proper Logseq formatting applied\n- **Processing**: Agent 10, file 10 of 283 in knowledge graph cleanup\n\n\npublic:: true",
  "properties": {
    "id": "bc-0103-halving-ontology",
    "collapsed": "true",
    "- ontology": "true",
    "- term-id": "BC-0103",
    "- preferred-term": "BC 0103 halving",
    "- source-domain": "metaverse",
    "- status": "draft",
    "- public-access": "true",
    "- definition": "### Primary Definition",
    "- maturity": "draft",
    "- owl:class": "mv:BC0103halving",
    "- owl:physicality": "ConceptualEntity",
    "- owl:role": "Concept",
    "- belongsToDomain": "[[MetaverseDomain]]"
  },
  "backlinks": [],
  "wiki_links": [
    "Sheffield",
    "Cambridge Centre for Alternative Finance",
    "Financial Conduct Authority",
    "Coinbase",
    "Bitcoin halving",
    "University of Cambridge",
    "Proof of Work",
    "blockchain technology",
    "network security",
    "BlackRock",
    "Bitcoin",
    "monetary theory",
    "Leeds",
    "Fidelity",
    "monetary policy",
    "Manchester",
    "MetaverseDomain",
    "Lightning Network",
    "ARK Invest",
    "Glassnode",
    "University of Edinburgh",
    "Binance",
    "RGB protocol",
    "institutional-grade infrastructure",
    "custody solutions",
    "miner incentives",
    "ETFs",
    "University College London",
    "Newcastle",
    "statechains",
    "miners",
    "Layer 2",
    "double-spending",
    "digital scarcity",
    "Kraken",
    "Coin Metrics",
    "cryptoeconomics",
    "block reward",
    "store of value",
    "ASIC",
    "blockchain",
    "transaction fees",
    "Imperial College London",
    "Markets in Crypto-Assets",
    "Mining"
  ],
  "ontology": {
    "term_id": "BC-0103",
    "preferred_term": "BC 0103 halving",
    "definition": "### Primary Definition",
    "source_domain": "metaverse",
    "maturity_level": null,
    "authority_score": null
  }
}