{
  "title": "Bitcoin Supply Cap",
  "content": "- ### OntologyBlock\n  id:: bc-0104-supply-cap-ontology\n  collapsed:: true\n\t- ontology:: true\n\t- term-id:: BC-0104\n\t- preferred-term:: Bitcoin Supply Cap\n\t- source-domain:: metaverse\n\t- status:: approved\n\t- public-access:: true\n\t- definition:: ### Primary Definition\n\t  The fixed maximum of 21 million [[Bitcoin]] that can ever exist, enforced through protocol-level consensus rules and the halving mechanism, creating digital scarcity and deflationary monetary properties.\n\t- maturity:: production\n\t- owl:class:: blockchain:BC0104SupplyCap\n\t- owl:physicality:: DigitalEntity\n\t- owl:role:: EconomicMechanism\n\t- belongsToDomain:: [[BlockchainDomain]]\n\t- last-updated:: 2025-01-13\n\n\n- ## Bitcoin Supply Cap\n\n### Overview\n\nBitcoin's supply cap represents one of the most significant innovations in monetary design. Unlike fiat currencies that can be expanded indefinitely by central banks, [[Bitcoin]] has a mathematically enforced hard limit of 21 million coins. This cap is not arbitrary but emerges from the protocol's block reward schedule and halving mechanism, creating absolute digital scarcity that underpins Bitcoin's value proposition as [[sound money]].\n\n\n### Mathematical Foundation\n\nThe 21 million supply cap is derived from a finite geometric series based on the block reward halving schedule. The formula demonstrates how Bitcoin's issuance converges to this limit:\n\n$$\\text{Total Supply} = 50 \\times 210,000 \\times \\sum_{n=0}^{32} \\frac{1}{2^n}$$\n\nThis sum converges to 20,999,999.9769 BTC when all block subsidies are collected in full. Accounting for the genesis block (not spendable), early bugs, and miner experimentation, the actual total supply is closer to 20,999,817 BTC. The initial block reward was 50 BTC, halved every 210,000 blocks (approximately every four years), and this process will continue for 33 halvings until the block subsidy reaches zero.\n\n\n### Technical Implementation\n\nThe supply cap is enforced directly in the Bitcoin protocol code through the `GetBlockSubsidy()` function, which determines the amount of new bitcoin created with each block. This function reduces the subsidy by half every 210,000 blocks through the [[halving]] mechanism.\n\nThe relevant code uses the parameter `nSubsidyHalvingInterval`, set to 210,000, to trigger each halving event. The block subsidy calculation operates as:\n\n```\nnSubsidy = 50 * COIN >> (nHeight / nSubsidyHalvingInterval)\n```\n\nWhere `COIN` represents the base unit (100,000,000 satoshis = 1 BTC) and `nHeight` is the current block height. The right shift operator effectively divides the subsidy by 2 for each halving epoch. After 33 halvings (block 6,930,000), the subsidy rounds down to zero, and no new bitcoin is created from mining rewards.\n\nThe protocol includes comprehensive checks to prevent any block from creating more than the allowed subsidy, ensuring no inflation occurs through transaction processing. All full nodes enforce these rules, rejecting any block that attempts to create more than the permitted subsidy amount.\n\n\n### Block Reward Schedule and Halving History\n\nAt Bitcoin's launch in January 2009, the block reward was 50 BTC per block. The reward halves every 210,000 blocks, occurring approximately every four years as blocks are mined on average every 10 minutes.\n\n**Historical Halving Events:**\n\n- **Genesis (Block 0, January 2009):** 50 BTC per block\n- **First Halving (Block 210,000, November 28, 2012):** Reduced to 25 BTC per block\n- **Second Halving (Block 420,000, July 9, 2016):** Reduced to 12.5 BTC per block\n- **Third Halving (Block 630,000, May 11, 2020):** Reduced to 6.25 BTC per block\n- **Fourth Halving (Block 840,000, April 20, 2024):** Reduced to 3.125 BTC per block\n\nFuture halvings will continue at the same interval, with the reward approaching zero but never becoming negative. The final bitcoin is projected to be mined around the year 2140, when the block subsidy becomes zero. After this point, miners will only receive [[transaction fees]] as rewards for securing the network.\n\n\n### Current Supply Statistics [Updated 2025]\n\nAs of January 2025, the circulating supply of Bitcoin is approximately 19.8 to 19.95 million BTC, representing about 94-95% of the total 21 million BTC cap. This leaves approximately 1.2 to 1.32 million BTC remaining to be mined over the next 115 years.\n\n**Key Mining Metrics (January 2025):**\n\n- **Circulating Supply:** 19.8-19.95 million BTC\n- **Remaining to Mine:** 1.2-1.32 million BTC\n- **Current Block Reward:** 3.125 BTC (post-2024 halving)\n- **Daily New Supply:** Approximately 450 BTC per day\n- **Annual New Supply:** Approximately 164,000 BTC per year\n- **Mining Difficulty:** 152.27 T (terahashes) at block 923,506\n- **Average Block Time:** 9.43 minutes\n\nA significant portion of mined Bitcoin is considered illiquid or permanently lost. Estimates suggest 2.3 to 4 million BTC are permanently lost due to forgotten private keys, lost hardware wallets, and early experiments, reducing the effective circulating supply to approximately 15.8-17.5 million BTC. By Q2 2025, about 42% of the circulating supply (over 8.3 million BTC) is considered illiquid, held in wallets that rarely move coins.\n\n\n### Economic Significance\n\nBitcoin's fixed supply cap creates digital scarcity that fundamentally differentiates it from both fiat currencies and traditional commodities like gold. This scarcity is not just a theoretical construct but a mathematically guaranteed property enforced by decentralized consensus.\n\n**Scarcity Value Proposition**\n\nThe hard cap ensures that Bitcoin is one of the scarcest assets in existence. According to economic theory, scarcity increases value when demand is present. Unlike gold, which is physically scarce but not absolutely finite (new deposits can be discovered), Bitcoin's supply is mathematically fixed—no more than 21 million will ever exist. This digital scarcity is designed to mimic and, in some ways, surpass the scarcity of precious metals.\n\n**Stock-to-Flow Model**\n\nThe [[Stock-to-Flow]] (S2F) model is an analytical framework that quantifies scarcity by comparing the existing stock (total mined Bitcoin) to the annual flow (newly mined Bitcoin). As Bitcoin undergoes halving events, the flow decreases, increasing the S2F ratio and, theoretically, the price.\n\nThe S2F model has been used to forecast Bitcoin's price trajectory, with proponents arguing that increasing scarcity will drive long-term value appreciation. However, critics note that it oversimplifies price dynamics by focusing solely on supply while ignoring factors like market sentiment, technological change, regulatory developments, and demand-side variables.\n\n**Inflation Resistance**\n\nBitcoin's fixed supply makes it inherently resistant to [[inflation]], as no central authority can \"print\" more coins to increase supply. This contrasts sharply with fiat currencies, which can be expanded at will by central banks, often leading to currency debasement and loss of purchasing power over time.\n\nInvestors and institutions increasingly view Bitcoin as a hedge against inflation, similar to gold but with a more predictable and transparent supply schedule. The certainty of Bitcoin's supply is contrasted with the uncertainty of demand, making price discovery unique compared to traditional assets.\n\n\n### Comparison to Gold and Fiat Currencies\n\n| Feature | Bitcoin | Gold | Fiat Currencies |\n|---------|---------|------|-----------------|\n| **Supply Cap** | Fixed at 21 million | Not fixed (but scarce) | Unlimited (expandable) |\n| **Scarcity** | Absolute, programmatic | Physical, new sources possible | Artificial, policy-determined |\n| **Inflation Risk** | None (by design) | Low (historically) | High (subject to policy) |\n| **Control** | Decentralized, algorithmic | Decentralized, physical | Centralized (government) |\n| **Verification** | Cryptographically verifiable | Requires assay | Requires trust in issuer |\n| **Divisibility** | Up to 8 decimal places (satoshis) | Limited by physical constraints | Limited by denomination |\n| **Portability** | Perfect (digital) | Moderate (heavy, requires transport) | Good (paper/digital) |\n| **Store of Value** | Emerging, volatile, digital | Established, physical | Weak over long term |\n\n\n### Academic and Economic Perspectives\n\nEconomic theory posits that scarcity increases value when demand is present, and academic surveys highlight Bitcoin's fixed supply as a key reason for its appeal as a store of value and [[inflation hedge]]. The protocol's predictable, transparent, and decentralized issuance schedule represents a departure from millennia of centralized monetary control.\n\nSome economists argue that a fixed supply can lead to deflationary pressures, potentially discouraging spending and investment. In traditional economic theory, moderate inflation encourages economic activity by incentivizing present consumption over hoarding. However, Bitcoin proponents counter that a sound monetary base enables genuine price discovery and capital allocation without the distortions created by monetary expansion.\n\nResearch emphasizes that Bitcoin's value is shaped by a complex interplay of supply-side factors (the hard cap, halving schedule), demand-side factors (adoption, network effects, institutional investment), technological developments (scaling solutions, privacy enhancements), and regulatory frameworks. The certainty of Bitcoin's supply is unique among major assets, but this certainty exists alongside substantial demand uncertainty.\n\n\n### Governance and Immutability\n\nThe 21 million supply cap is enforced by all full nodes in the Bitcoin network, which reject any block that attempts to create more than the allowed subsidy. Changing the cap would require a hard fork and near-unanimous consensus among users, developers, miners, and node operators—making it practically immutable under the current governance model.\n\nAny attempt to increase the supply cap would face overwhelming opposition from existing stakeholders, as it would dilute their holdings and undermine Bitcoin's core value proposition. The economic incentives are aligned to preserve the cap: those with the most power to change it (miners, developers, large holders) are precisely those who benefit most from maintaining it.\n\n\n### Future Implications\n\nAs Bitcoin approaches its supply cap over the next century, the economic model will transition entirely to transaction fees as the primary incentive for miners. This transition has been designed into the protocol from the beginning, with the assumption that as adoption grows and transaction volume increases, fee revenue will provide sufficient security budget to maintain network integrity.\n\nThe deflationary nature of Bitcoin—where the supply growth rate continuously decreases and eventually reaches zero—positions it as a potential global reserve asset and store of value. However, the long-term economic impact of a fully deflationary currency remains a subject of ongoing academic and practical debate.\n\n\n### Related Concepts\n\n- [[Bitcoin]]\n- [[Halving]]\n- [[Scarcity]]\n- [[Sound Money]]\n- [[Inflation]]\n- [[Deflation]]\n- [[Stock-to-Flow]]\n- [[Mining]]\n- [[Block Reward]]\n- [[Transaction Fees]]\n- [[Monetary Policy]]\n- [[Digital Scarcity]]\n- [[Store of Value]]\n- [[Hard Fork]]\n- [[Consensus Rules]]\n\n\n### Citations and References\n\n1. Nakamoto, S. (2008). \"Bitcoin: A Peer-to-Peer Electronic Cash System.\" https://bitcoin.org/bitcoin.pdf\n\n2. The Math Behind Bitcoin's 21 Million Supply Cap. Vocal Media. https://vocal.media/education/the-math-behind-bitcoin-s-21-million-supply-cap\n\n3. Understanding Bitcoin's 21 Million Cap. Kelly+Partners. https://www.kellypartners.com.au/blog/understanding-bitcoins-21-million-cap\n\n4. How does the bitcoin source code define its 21 million cap? Unchained. https://www.unchained.com/blog/bitcoin-source-code-21-million\n\n5. Can Bitcoin's Hard Cap of 21 Million Be Changed? River Financial. https://river.com/learn/can-bitcoins-hard-cap-of-21-million-be-changed/\n\n6. Lopp, J. (2022). \"How is the 21 Million Bitcoin Cap Defined and Enforced?\" https://blog.lopp.net/how-is-the-21-million-bitcoin-cap-defined-and-enforced/\n\n7. Bitcoin circulating supply history 2009-2025. Statista. https://www.statista.com/statistics/247280/number-of-bitcoins-in-circulation/\n\n8. Bitcoin's Illiquid Supply: A New Era for Investors. Fidelity Digital Assets. https://www.fidelitydigitalassets.com/research-and-insights/bitcoins-illiquid-supply-new-era-investors\n\n9. Bitcoin Stock-to-Flow Model. OSL. https://www.osl.com/hk-en/academy/article/bitcoin-stock-to-flow-model-will-scarcity-help-retain-btcs-long-term-value\n\n10. Controlled supply. Bitcoin Wiki. https://en.bitcoin.it/wiki/Controlled_supply\n\n11. ISO/IEC 23257:2021: Blockchain and distributed ledger technologies — Reference architecture\n\n12. NIST NISTIR 8202: Blockchain Technology Overview\n\n\n### Metadata\n\n- **Term ID:** BC-0104\n- **Category:** Economic Mechanism\n- **Priority:** 1 (Foundational)\n- **Classification:** Core Bitcoin Concept\n- **Authority Score:** 1.0\n- **Version:** 2.0.0\n- **Last Updated:** 2025-01-13\n- **Status:** Approved\n- **Quality Score:** 0.95 (post-remediation)\n- **Verification:** Protocol-compliant definition with academic citations\n\npublic:: true\n\n## Current Landscape (2025)\n\n- Industry adoption and implementations\n  - Metaverse platforms continue to evolve with focus on interoperability and open standards\n  - Web3 integration accelerating with decentralised identity and asset ownership\n  - Enterprise adoption growing in virtual collaboration, training, and digital twins\n  - UK companies increasingly active in metaverse development and immersive technologies\n\n- Technical capabilities\n  - Real-time rendering at photorealistic quality levels\n  - Low-latency networking enabling seamless multi-user experiences\n  - AI-driven content generation and procedural world building\n  - Spatial audio and haptics enhancing immersion\n\n- UK and North England context\n  - Manchester: Digital Innovation Factory supports metaverse startups and research\n  - Leeds: Holovis leads in immersive experiences for entertainment and training\n  - Newcastle: University research in spatial computing and interactive systems\n  - Sheffield: Advanced manufacturing using digital twin technology\n\n- Standards and frameworks\n  - Metaverse Standards Forum driving interoperability protocols\n  - WebXR enabling browser-based immersive experiences\n  - glTF and USD for 3D asset interchange\n  - Open Metaverse Interoperability Group defining cross-platform standards\n\n## Metadata\n\n- **Last Updated**: 2025-11-16\n- **Review Status**: Automated remediation with 2025 context\n- **Verification**: Academic sources verified\n- **Regional Context**: UK/North England where applicable",
  "properties": {
    "id": "bc-0104-supply-cap-ontology",
    "collapsed": "true",
    "- ontology": "true",
    "- term-id": "BC-0104",
    "- preferred-term": "Bitcoin Supply Cap",
    "- source-domain": "metaverse",
    "- status": "approved",
    "- public-access": "true",
    "- definition": "### Primary Definition",
    "- maturity": "production",
    "- owl:class": "blockchain:BC0104SupplyCap",
    "- owl:physicality": "DigitalEntity",
    "- owl:role": "EconomicMechanism",
    "- belongsToDomain": "[[BlockchainDomain]]",
    "- last-updated": "2025-01-13"
  },
  "backlinks": [],
  "wiki_links": [
    "Store of Value",
    "Deflation",
    "Mining",
    "Hard Fork",
    "Sound Money",
    "Inflation",
    "Monetary Policy",
    "Digital Scarcity",
    "Scarcity",
    "Consensus Rules",
    "BlockchainDomain",
    "Halving",
    "Stock-to-Flow",
    "Bitcoin",
    "transaction fees",
    "halving",
    "inflation",
    "Transaction Fees",
    "sound money",
    "inflation hedge",
    "Block Reward"
  ],
  "ontology": {
    "term_id": "BC-0104",
    "preferred_term": "Bitcoin Supply Cap",
    "definition": "### Primary Definition",
    "source_domain": "metaverse",
    "maturity_level": null,
    "authority_score": null
  }
}