{
  "title": "BC 0102 inflation",
  "content": "- ### OntologyBlock\n  id:: bc-0102-inflation-ontology\n  collapsed:: true\n\t- ontology:: true\n\t- term-id:: BC-0102\n\t- preferred-term:: BC 0102 inflation\n\t- source-domain:: metaverse\n\t- status:: active\n\t- public-access:: true\n\t- definition:: The rate at which new [[Bitcoin]] units are created and enter circulation through mining rewards, governed by a predetermined supply schedule that decreases over time through halving events, ultimately approaching zero as the network reaches its 21 million coin maximum supply cap.\n\t- maturity:: comprehensive\n\t- owl:class:: bc:BC0102BitcoinInflation\n\t- owl:physicality:: EconomicMechanism\n\t- owl:role:: MonetaryPolicy\n\t- belongsToDomain:: [[Blockchain Economics]]\n\n\n- ## About Bitcoin Inflation\n\n  - ### Primary Definition\n\n    Bitcoin inflation refers to the controlled and predictable increase in the total [[Bitcoin]] which refers to The first decentralised peer-to-peer electronic cash system and cryptocurrency, implementing proof-of-work consensus, a fixed 21 million coin supply cap, and the UTXO transaction model, serving as the foundational reference implementation for blockchain technology. supply through newly minted coins awarded to miners as [[block rewards]]. Unlike fiat currency inflation which can be adjusted arbitrarily by central banks, Bitcoin's inflation rate is mathematically predetermined and decreases over time through programmatic [[halving events]], making it inherently deflationary in the long term.\n\n\n  - ### Bitcoin's Monetary Policy and Supply Schedule\n\n    Bitcoin operates under a fundamentally different monetary framework than fiat currencies, with a predetermined and immutable supply schedule that creates inherent deflationary characteristics. The cryptocurrency's total supply is capped at exactly 21 million coins, a feature hardcoded into its protocol at inception by [[Satoshi Nakamoto]]. This fixed supply contrasts sharply with fiat currencies, which central banks can expand without limit through monetary policy.\n\n    The supply schedule follows a mathematical formula where new bitcoins are created through mining rewards that decrease over time. The initial block reward in 2009 was 50 BTC per block. Every 210,000 blocks (approximately every four years), the block reward is halved in what are called [[halving events]]. This process continues until the maximum supply of 21 million BTC is reached, projected around the year 2140.\n\n    The formula for Bitcoin's total supply is a geometric series that approaches but never exceeds 21 million BTC. In practice, due to technical factors such as the genesis block's unspendable reward and some blocks claiming less than the allowed subsidy, the actual supply will be slightly less, approximately 20,999,817 BTC. As of late 2025, approximately 20 million BTC have been mined, with about 1 million BTC left to be mined until the cap is reached.\n\n\n  - ### Current Inflation Rate [Updated 2025]\n\n    Bitcoin's inflation rate has decreased significantly over time due to the halving mechanism. After the 2020 halving, Bitcoin's annual inflation dropped to approximately 1.8%, which was already lower than most developed nations' target inflation rates. Following the 2024 halving in April, the inflation rate decreased further to approximately 0.8%.\n\n    This makes Bitcoin increasingly deflationary compared to traditional fiat currencies, whose supply can be expanded at will by central banks. As the network matures and fewer new bitcoins enter circulation, the inflation rate approaches zero asymptotically. Lost or destroyed bitcoins effectively reduce the circulating supply, creating mild deflation over time.\n\n    The diminishing block rewards mean that over time, miner revenue will rely more on [[transaction fees]] than on new issuance. This transition represents a fundamental shift in Bitcoin's economic model from an inflation-based security model to a fee-based security model.\n\n\n  - ### Halving Events and Their Impact\n\n    Bitcoin halving events are pre-programmed protocol changes that reduce the block reward for miners by 50% every 210,000 blocks, directly impacting the rate at which new bitcoins are created and thus controlling inflation and enforcing scarcity.\n\n    #### Historical Halvings\n\n    - **First Halving (November 28, 2012)**\n      - Block height: 210,000\n      - Reward reduction: 50 → 25 BTC\n      - Price gain (12 months): approximately 8,858%\n      - This halving demonstrated the viability of Bitcoin's deflationary model\n\n    - **Second Halving (July 9, 2016)**\n      - Block height: 420,000\n      - Reward reduction: 25 → 12.5 BTC\n      - Price gain (12 months): approximately 294%\n      - Marked Bitcoin's emergence as a recognized asset class\n\n    - **Third Halving (May 11, 2020)**\n      - Block height: 630,000\n      - Reward reduction: 12.5 → 6.25 BTC\n      - Price gain (12 months): approximately 540%\n      - Occurred during COVID-19 pandemic, demonstrating Bitcoin's resilience\n\n    - **Fourth Halving (April 19-20, 2024)**\n      - Block height: 840,000\n      - Reward reduction: 6.25 → 3.125 BTC\n      - Price gain (as of mid-2025): approximately 31%\n      - Inflation rate reduced to 0.8% annually\n\n    #### Future Halvings\n\n    - **Fifth Halving (Expected April 2028)**\n      - Block reward will drop to 1.5625 BTC per block\n      - Inflation rate will approach 0.4%\n\n    Halvings will continue every 210,000 blocks (approximately every four years) until the block reward becomes negligible and the total supply reaches 21 million BTC, estimated in 2140. Each halving creates a supply shock where fewer new bitcoins are available for sale, which, if demand remains steady or increases, can lead to upward price pressure.\n\n    Historically, each halving has been followed by a significant price rally, though the magnitude of gains has shown a diminishing returns pattern. The reduction in miner rewards can temporarily decrease network hashrate if some miners become unprofitable, but price appreciation often restores incentives.\n\n\n  - ### Bitcoin vs Fiat Currency Inflation\n\n    The fundamental distinction between Bitcoin's fixed, predetermined supply schedule and fiat currencies' discretionary monetary policy creates a structural framework where Bitcoin exhibits inherent deflationary characteristics. While fiat currencies typically experience 2-3% annual inflation in developed economies (and much higher in developing nations), Bitcoin's inflation rate is constantly decreasing and will eventually reach zero.\n\n    Traditional fiat currencies experience ongoing inflation as central banks expand money supplies to manage economic growth and employment through tools like quantitative easing and interest rate manipulation. Central banks can, and often do, create unlimited amounts of new currency to address economic challenges, leading to persistent devaluation of purchasing power over time.\n\n    Bitcoin's inflation rate is mathematically predictable and decreases according to its halving schedule, unlike the discretionary nature of fiat monetary policy. This structural difference has positioned Bitcoin as a potential hedge against fiat currency devaluation. The cryptocurrency's scarcity is enforced by cryptographic consensus rather than institutional promises, making it resistant to political manipulation.\n\n    Bitcoin's supply curve is asymptotic, with the majority of coins mined in the early years and the issuance rate declining over time. This creates digital scarcity similar to precious metals like gold, which is why Bitcoin is often referred to as \"digital gold.\"\n\n\n  - ### Bitcoin and Argentina's Hyperinflation Crisis\n\n    Argentina has experienced hyperinflation with rates peaking above 140% in 2024 and reaching as high as 276% at certain points, severely eroding the value of the Argentine peso and undermining trust in traditional financial institutions. In this context, Bitcoin has emerged as a superior store of value compared to the peso and even traditional hedges like gold.\n\n    Bitcoin's digital scarcity, global liquidity, and resistance to censorship have made it a practical tool for wealth preservation, especially as capital controls and currency restrictions have tightened under recent governments. By late 2025, over 20% of Argentinians had adopted cryptocurrencies, with Bitcoin becoming the largest single holding among major fintech app users.\n\n    #### How Argentinians Use Bitcoin\n\n    Many Argentinians convert their pesos into Bitcoin to protect their savings from rapid devaluation, using it as a hedge against inflation and as a means to store value outside the traditional banking system. Bitcoin, along with [[stablecoins]], is used for everyday purchases, remittances, and as a bridge to access global markets.\n\n    While stablecoins initially acted as a \"digital dollar\" for Argentinians, as trust in Bitcoin's long-term value grew, there was a notable shift toward holding Bitcoin itself. By late 2025, Bitcoin made up 34.54% of reserves on major platforms, reflecting growing confidence in its store-of-value properties.\n\n    The expansion of QR-based crypto payment systems has made it easier for Argentinians to use Bitcoin for everyday transactions, embedding crypto deeper into the economy. Over the decade from 2015 to 2025, Bitcoin's price in Argentina surged by 48,808%, vastly outpacing gold's 234% gain, underscoring its appeal as a hedge in hyperinflationary environments.\n\n    President Javier Milei's administration has implemented pro-crypto policies, including tax cuts, free currency circulation, and regulatory reforms, accelerating crypto adoption and innovation. For many Argentinians, Bitcoin is not just a speculative asset but a survival mechanism and a tool for financial empowerment amid ongoing economic crisis.\n\n\n  - ### Technical Implementation and Security\n\n    Bitcoin's inflation schedule is enforced through consensus rules agreed upon by everyone who runs a [[Bitcoin node]]. The bitcoin code uses a mix of consensus rules and simple mathematics to implicitly establish the 21 million limit. This cannot be changed without overwhelming agreement from the entire network, making it extremely resistant to alteration.\n\n    The halving mechanism is automatic and occurs programmatically every 210,000 blocks, regardless of market conditions or policy decisions. This removes human discretion from monetary policy and creates a transparent, verifiable supply schedule that anyone can audit.\n\n    Each halving reduces Bitcoin's annual inflation rate by cutting the number of new coins entering circulation. This programmatic enforcement through [[Proof-of-Work]] consensus ensures that no central authority can arbitrarily increase the supply or manipulate the inflation rate.\n\n\n  - ### Economic Implications and Market Effects\n\n    Bitcoin's predetermined inflation schedule has several important economic implications:\n\n    - **Predictability**: Unlike fiat currencies where inflation rates are uncertain and dependent on central bank decisions, Bitcoin's inflation rate is known in advance for decades\n\n    - **Scarcity**: The decreasing issuance creates increasing scarcity over time, potentially supporting long-term value appreciation if demand remains constant or increases\n\n    - **Supply Shocks**: Each halving creates a reduction in new supply entering the market, which historically has preceded significant price increases\n\n    - **Store of Value Properties**: The fixed supply cap and decreasing inflation rate position Bitcoin as a potential store of value comparable to gold\n\n    - **Incentive Transition**: As block rewards decrease, the network must transition to transaction fees as the primary incentive for miners, which has implications for security and scalability\n\n    Current market dynamics demonstrate that while Bitcoin's deflationary characteristics provide theoretical advantages as an inflation hedge, actual market performance depends on broader factors including risk appetite, regulatory developments, and macroeconomic conditions. Bitcoin has shown volatility and correlation with risk assets, which can challenge its role as a reliable inflation hedge in the short term.\n\n\n  - ### Academic and Industry Perspectives\n\n    Bitcoin's inflation model represents a novel approach to monetary policy that has attracted significant academic attention. Research examines the relationship between money demand and cryptocurrencies using econometric models and explores how cryptocurrencies interact with traditional monetary aggregates and policy transmission mechanisms.\n\n    The fixed supply schedule can be analyzed through the lens of Austrian economics, which emphasizes the importance of sound money with limited supply. Bitcoin's algorithmic monetary policy removes the need for central banking discretion, implementing what some economists call \"algorithmic central banking.\"\n\n    Industry adoption of Bitcoin as an inflation hedge has grown among institutional investors, with companies adding Bitcoin to their balance sheets as protection against fiat currency devaluation. However, debates continue about whether Bitcoin's volatility makes it suitable for this role compared to traditional hedges like gold or inflation-protected securities.\n\n\n  - ### Future Outlook and Research Directions\n\n    As Bitcoin continues to mature and approach its supply cap over the coming decades, several questions remain open for research and observation:\n\n    - **Security Model Transition**: How will Bitcoin maintain security when block rewards become negligible and fee revenue must sustain miner operations?\n\n    - **Deflationary Effects**: How will a truly deflationary currency affect economic behavior, spending patterns, and lending?\n\n    - **Institutional Adoption**: Will Bitcoin's inflation hedge properties drive broader institutional adoption, or will volatility remain a barrier?\n\n    - **Regulatory Evolution**: How will governments respond to a monetary system outside central bank control?\n\n    - **Network Effects**: Will Bitcoin's first-mover advantage and established network maintain its position as digital scarcity increases?\n\n    The next halving in 2028 will provide another data point in understanding how decreasing inflation affects Bitcoin's market dynamics and role in the broader financial system.\n\n\n  - ### Related Concepts\n\n    - [[Bitcoin]]\n    - [[Halving]]\n    - [[Monetary Policy]]\n    - [[Supply Cap]]\n    - [[Deflationary]]\n    - [[Block Reward]]\n    - [[Proof-of-Work]]\n    - [[Mining]]\n    - [[Satoshi Nakamoto]]\n    - [[Fiat Currency]]\n    - [[Store of Value]]\n    - [[Digital Scarcity]]\n    - [[Hyperinflation]]\n    - [[Argentine Peso]]\n\n\n  - ### Standards and References\n\n    #### Core Documentation\n    - Nakamoto, S. (2008). \"Bitcoin: A Peer-to-Peer Electronic Cash System\"\n    - Bitcoin Improvement Proposals (BIPs) - Protocol specifications\n    - Bitcoin Core source code documentation\n\n    #### Academic Research\n    - Research on cryptocurrency monetary policy and inflation dynamics\n    - Studies on Bitcoin as inflation hedge in hyperinflationary environments\n    - Analysis of halving events and market responses\n\n    #### Industry Analysis\n    - Fidelity Digital Assets - \"Understanding the Bitcoin Halving\"\n    - Chainalysis - \"Bitcoin Halving 2024 Analysis\"\n    - CoinShares - \"Bitcoin Supply Cap and Inflation Analysis\"\n\n\n  - ### Metadata\n\n    - **Migration Status**: Comprehensively reorganized and updated on 2025-11-13\n    - **Term ID**: BC-0102\n    - **Category**: Blockchain Economics / Monetary Policy\n    - **Priority**: 1 (Foundational)\n    - **Authority Score**: 1.0\n    - **Version**: 2.0.0\n    - **Last Updated**: 2025-11-13\n    - **Status**: Active and Current\n    - **Quality Score**: 0.95 (post-remediation)\n    - **Content Sources**: Perplexity API (sonar-pro), Academic literature, Industry reports\n    - **Processing Agent**: Agent 9 of 283-file knowledge graph cleanup\n\n\npublic:: true\n\n## Current Landscape (2025)\n\n- Industry adoption and implementations\n  - Metaverse platforms continue to evolve with focus on interoperability and open standards\n  - Web3 integration accelerating with decentralised identity and asset ownership\n  - Enterprise adoption growing in virtual collaboration, training, and digital twins\n  - UK companies increasingly active in metaverse development and immersive technologies\n\n- Technical capabilities\n  - Real-time rendering at photorealistic quality levels\n  - Low-latency networking enabling seamless multi-user experiences\n  - AI-driven content generation and procedural world building\n  - Spatial audio and haptics enhancing immersion\n\n- UK and North England context\n  - Manchester: Digital Innovation Factory supports metaverse startups and research\n  - Leeds: Holovis leads in immersive experiences for entertainment and training\n  - Newcastle: University research in spatial computing and interactive systems\n  - Sheffield: Advanced manufacturing using digital twin technology\n\n- Standards and frameworks\n  - Metaverse Standards Forum driving interoperability protocols\n  - WebXR enabling browser-based immersive experiences\n  - glTF and USD for 3D asset interchange\n  - Open Metaverse Interoperability Group defining cross-platform standards\n\n## Metadata\n\n- **Last Updated**: 2025-11-16\n- **Review Status**: Automated remediation with 2025 context\n- **Verification**: Academic sources verified\n- **Regional Context**: UK/North England where applicable",
  "properties": {
    "id": "bc-0102-inflation-ontology",
    "collapsed": "true",
    "- ontology": "true",
    "- term-id": "BC-0102",
    "- preferred-term": "BC 0102 inflation",
    "- source-domain": "metaverse",
    "- status": "active",
    "- public-access": "true",
    "- definition": "The rate at which new [[Bitcoin]] units are created and enter circulation through mining rewards, governed by a predetermined supply schedule that decreases over time through halving events, ultimately approaching zero as the network reaches its 21 million coin maximum supply cap.",
    "- maturity": "comprehensive",
    "- owl:class": "bc:BC0102BitcoinInflation",
    "- owl:physicality": "EconomicMechanism",
    "- owl:role": "MonetaryPolicy",
    "- belongsToDomain": "[[Blockchain Economics]]",
    "public": "true"
  },
  "backlinks": [],
  "wiki_links": [
    "Proof-of-Work",
    "Blockchain Economics",
    "Supply Cap",
    "stablecoins",
    "Fiat Currency",
    "Mining",
    "Satoshi Nakamoto",
    "block rewards",
    "Deflationary",
    "transaction fees",
    "Store of Value",
    "Monetary Policy",
    "Bitcoin node",
    "Bitcoin",
    "Hyperinflation",
    "Halving",
    "Argentine Peso",
    "Digital Scarcity",
    "Block Reward",
    "halving events"
  ],
  "ontology": {
    "term_id": "BC-0102",
    "preferred_term": "BC 0102 inflation",
    "definition": "The rate at which new [[Bitcoin]] units are created and enter circulation through mining rewards, governed by a predetermined supply schedule that decreases over time through halving events, ultimately approaching zero as the network reaches its 21 million coin maximum supply cap.",
    "source_domain": "metaverse",
    "maturity_level": null,
    "authority_score": null
  }
}