{
  "title": "Travel Rule",
  "content": "- ### OntologyBlock\n  id:: bc-0477-travel-rule-ontology\n  collapsed:: true\n\t- ontology:: true\n\t- term-id:: BC-0477\n\t- preferred-term:: Travel Rule\n\t- source-domain:: blockchain\n\t- status:: stub-needs-content\n\t- public-access:: true\n\t- content-status:: minimal-placeholder-requires-authoring\n\t- public-access:: true\n\t- definition:: A component of the blockchain ecosystem.\n\t- maturity:: draft\n\t- owl:class:: bc:TravelRule\n\t- owl:physicality:: ConceptualEntity\n\t- owl:role:: Concept\n\t- belongsToDomain:: [[BlockchainDomain]]\n\n## OWL Formal Semantics\n\n```clojure\n;; OWL Functional Syntax\n\n(Declaration (Class :TravelRule))\n\n;; Annotations\n(AnnotationAssertion rdfs:label :TravelRule \"Travel Rule\"@en)\n(AnnotationAssertion rdfs:comment :TravelRule \"A component of the blockchain ecosystem.\"@en)\n\n;; Data Properties\n(AnnotationAssertion dcterms:identifier :TravelRule \"BC-0477\"^^xsd:string)\n```\n\n- ## About Travel Rule\n  id:: travel-rule-about\n\n  - The Travel Rule, formally known as FATF Recommendation 16, represents one of the most technically challenging regulatory requirements imposed on the cryptocurrency industry. Originally established for traditional financial institutions in 1996, the rule mandates that financial intermediaries transmit specific information about the originator and beneficiary of fund transfers to the next financial institution in the payment chain. In June 2019, the Financial Action Task Force (FATF) extended this requirement to Virtual Asset Service Providers (VASPs), requiring them to obtain, hold, and transmit originator and beneficiary information for virtual asset transfers exceeding specified thresholds—typically $1,000 or €1,000 equivalent.\n\n  - The application of the Travel Rule to cryptocurrency transactions creates fundamental technical and operational challenges. Traditional wire transfers occur through established banking networks with standardised messaging protocols (such as SWIFT) and centralised correspondent banking relationships. Cryptocurrency transfers, by contrast, occur peer-to-peer on decentralised networks where VASPs may have no prior relationship and no standard communication infrastructure. When a customer withdraws cryptocurrency from one exchange to deposit at another, the sending VASP must somehow communicate customer information to the receiving VASP before, during, or immediately after the blockchain transaction—without the blockchain itself providing any mechanism for such communication.\n\n  - Compliance with the Travel Rule has driven significant innovation in cryptocurrency compliance infrastructure, with multiple competing technical solutions emerging to facilitate VASP-to-VASP information exchange. These solutions must balance regulatory compliance with data protection requirements, operational efficiency, and cybersecurity concerns. The industry has developed standards including the InterVASP Messaging Standard (IVMS101), the Travel Rule Protocol (TRP), and various proprietary solutions. However, global implementation remains fragmented, with different jurisdictions adopting varying thresholds, enforcement timelines, and technical requirements. This regulatory patchwork creates compliance challenges for VASPs operating internationally and raises questions about financial privacy, data security, and the future viability of self-custodial cryptocurrency holdings.\n\n  - ### Regulatory Framework\n\n    - **FATF Recommendation 16**: The foundational requirement states that countries should ensure that VASPs obtain and transmit required originator and beneficiary information for virtual asset transfers. The FATF's June 2019 Interpretive Note to Recommendation 16 specifies that VASPs must obtain originator information (name, account number or unique transaction reference, and physical address or national identity number or customer identification number) and beneficiary information (name and account number). This information must be transmitted immediately and securely to the beneficiary VASP. The October 2021 FATF guidance provided additional clarity on implementation expectations, including risk-based approaches for phased implementation.\n\n    - **FinCEN Final Rule (United States)**: In October 2020, FinCEN proposed extending Bank Secrecy Act recordkeeping and travel rule requirements to cryptocurrency transactions, with a proposed $250 threshold. Following industry feedback, FinCEN withdrew this proposal and in 2023 issued final guidance implementing a $3,000 threshold for travel rule compliance—higher than the FATF-recommended $1,000. US VASPs must verify customer identity for transactions exceeding $3,000 and record this information, though the rule does not explicitly mandate real-time transmission to beneficiary institutions for blockchain transactions, creating some regulatory ambiguity.\n\n    - **EU Markets in Crypto-Assets Regulation (MiCA)**: MiCA, fully applicable from December 2024, implements the Travel Rule across EU member states with harmonised requirements. The Transfer of Funds Regulation, updated in 2023, extends travel rule obligations to crypto-asset transfers with no minimum threshold—meaning all transfers require information exchange. Controversially, the regulation also requires VASPs to collect beneficiary information for transfers to self-hosted wallets, creating significant privacy and enforcement concerns.\n\n    - **Singapore Payment Services Act**: The Monetary Authority of Singapore (MAS) implemented Travel Rule requirements in 2020, initially with a threshold of SGD 1,500 (approximately $1,100) for cross-border transfers. MAS has indicated that the threshold may be reduced to align with FATF recommendations. Singapore has been relatively progressive in accepting multiple technical solutions for Travel Rule compliance, including both centralised and decentralised information exchange protocols.\n\n    - **Japan Payment Services Act Amendment**: Japan's Financial Services Agency (FSA) implemented the Travel Rule in April 2023 with a threshold of ¥100,000 (approximately $750). Japanese VASPs must transmit originator and beneficiary information to counterparty VASPs, with specific requirements for notifications when counterparties cannot be identified. Japan has encouraged the adoption of the TRUST framework developed by industry participants.\n\n    - **Switzerland FINMA Guidelines**: The Swiss Financial Market Supervisory Authority (FINMA) requires Travel Rule compliance for virtual asset transfers exceeding CHF 1,000 (approximately $1,100). Switzerland recognises multiple technical solutions including the Travel Rule Information Sharing Alliance (TRISA), reflecting its principle-based regulatory approach.\n\n    - **UK Financial Conduct Authority**: While the UK has not yet implemented specific Travel Rule requirements, the FCA has indicated that crypto-asset businesses should prepare for such requirements as part of broader alignment with FATF standards. The Economic Crime Bill includes provisions that would enable Travel Rule implementation.\n\n  - ### Compliance Requirements\n\n    - **Originator Information**: VASPs must collect and verify the following information about customers initiating virtual asset transfers:\n      - Full legal name (as it appears on government-issued identification)\n      - Account number or unique transaction reference number\n      - Physical address (residential or business) OR national identity number OR customer identification number OR date and place of birth\n      - For legal entities: registered business name, registration number, and registered address\n\n    - **Beneficiary Information**: VASPs must obtain the following information about transfer recipients:\n      - Full legal name of the beneficiary\n      - Account number at the beneficiary VASP or unique transaction reference number\n      - Physical address OR national identity number OR customer identification number OR date and place of birth (depending on jurisdiction)\n\n    - **Information Transmission**: The originating VASP must transmit this information to the beneficiary VASP immediately and securely. \"Immediately\" is generally interpreted as concurrent with or immediately following the blockchain transaction. Transmission methods must ensure confidentiality, integrity, and availability of the data.\n\n    - **Screening Obligations**: VASPs must screen originators and beneficiaries against sanctions lists (OFAC SDN, EU sanctions, UN sanctions) before processing transactions. Transactions involving sanctioned parties must be blocked and reported to relevant authorities.\n\n    - **Record Keeping**: Both originating and beneficiary VASPs must maintain travel rule information for at least five years, readily accessible to regulators and law enforcement upon request. Records must link customer information to specific blockchain transactions through transaction hashes or other unique identifiers.\n\n    - **Threshold Determinations**: VASPs must aggregate multiple transactions to determine whether cumulative transfers exceed thresholds within specified time periods. Structuring—breaking large transactions into smaller amounts to avoid thresholds—is prohibited and constitutes a red flag for money laundering.\n\n    - **Self-Hosted Wallet Transfers**: Different jurisdictions apply varying requirements for transfers to or from self-hosted (non-custodial) wallets. The EU's approach requires VASPs to collect beneficiary information even for self-hosted wallet transfers exceeding €1,000, whilst the US currently applies less stringent requirements. This remains one of the most contentious aspects of Travel Rule implementation.\n\n  - ### Technical Solutions for Compliance\n\n    - **InterVASP Messaging Standard (IVMS101)**: Developed by the InterVASP Messaging Standard working group (now operating under the Global Digital Finance umbrella), IVMS101 defines a common data model for representing originator and beneficiary information in a standardised format. The standard addresses data field naming, structure, and validation rules, enabling interoperability between different travel rule solutions. IVMS101 has gained wide industry adoption as the underlying data standard, though it does not specify the transport mechanism for exchanging information.\n\n    - **Travel Rule Protocol (TRP)**: CipherTrace's Travel Rule Protocol provides an open-source solution for VASP-to-VASP information exchange. TRP uses a distributed architecture where VASPs operate their own nodes that communicate using HTTPS and the IVMS101 data standard. The protocol includes discovery mechanisms (finding which VASP controls a blockchain address), handshake protocols (establishing secure communication channels), and data exchange protocols (transmitting travel rule information). TRP emphasises data minimisation and privacy protection whilst meeting regulatory requirements.\n\n    - **Notabene**: A commercial Travel Rule solution that provides a SaaS platform for VASP information exchange. Notabene's SafeTransact product enables VASPs to identify counterparty institutions, exchange customer information securely, and maintain compliance records. The platform integrates with existing VASP systems through APIs and supports the IVMS101 standard. Notabene has gained significant market share, particularly among North American and European exchanges.\n\n    - **Sygna Bridge**: Developed by Coolbitx, Sygna Bridge uses blockchain-based identity verification to facilitate Travel Rule compliance. The protocol creates encrypted channels between VASPs for secure information exchange whilst leveraging blockchain technology for authentication and non-repudiation. Sygna Bridge has been adopted primarily in Asian markets.\n\n    - **Travel Rule Information Sharing Alliance (TRISA)**: An open-source, peer-to-peer solution that enables VASPs to exchange travel rule information directly without central intermediaries. TRISA uses a global directory service to identify VASPs, public key infrastructure for authentication, and encrypted communication channels for data exchange. The protocol emphasises data sovereignty and privacy protection, with VASPs maintaining control over their customer data.\n\n    - **Shyft Network**: A blockchain-based compliance network that provides Travel Rule compliance alongside other regulatory requirements. Shyft creates attestation tokens representing verified customer identities that can be shared between VASPs whilst preserving privacy. The network uses smart contracts to enforce compliance rules and maintain audit trails.\n\n    - **TRUST Framework**: Developed by Japanese VASP consortium including bitFlyer and Coincheck, the TRUST (Travel Rule Universal Solution Technology) framework provides a Japan-specific solution tailored to FSA requirements. The framework has been promoted by the Japan Virtual and Crypto Assets Exchange Association (JVCEA) as the preferred domestic solution.\n\n    - **Address Ownership Proof Protocol (AOPP)**: Enables users to prove ownership of self-hosted wallet addresses to VASPs, facilitating compliance with requirements for transfers to non-custodial wallets. However, AOPP has faced criticism from privacy advocates and some VASPs have discontinued support following community backlash.\n\n  - ### Real-World Compliance Implementations\n\n    - **Coinbase**: Implemented Travel Rule compliance using multiple solutions depending on jurisdiction and counterparty. For US transactions, Coinbase uses Notabene for VASP-to-VASP information exchange when withdrawing to external addresses. For transfers exceeding $3,000, customers must provide beneficiary information including name and address before processing withdrawals. Coinbase maintains a database of known VASP-controlled addresses to identify when Travel Rule obligations apply versus withdrawals to self-hosted wallets. The exchange has invested over $10 million in Travel Rule infrastructure and maintains compliance staff dedicated to VASP communications.\n\n    - **Kraken**: Adopted a multi-solution approach, integrating both Notabene and the Travel Rule Protocol to maximise counterparty coverage. Kraken requires customers withdrawing amounts exceeding applicable thresholds to provide beneficiary details and confirms whether destination addresses belong to VASPs requiring information exchange. Kraken has advocated for harmonised global standards and criticised jurisdictional variations that create compliance complexity. The exchange temporarily restricted services in certain jurisdictions where Travel Rule compliance requirements conflicted with operational capabilities.\n\n    - **Binance**: Following regulatory pressure, Binance implemented Travel Rule compliance globally using Notabene and proprietary systems. The exchange faces particular challenges due to its large international customer base and complex corporate structure spanning multiple jurisdictions. Binance has established jurisdiction-specific entities (Binance.US, Binance Australia, etc.) to manage localised compliance requirements. The $4.3 billion settlement with US authorities in 2023 included provisions requiring enhanced Travel Rule compliance and regular reporting to FinCEN.\n\n    - **Gemini**: As a New York-regulated trust company, Gemini implemented Travel Rule compliance early, using Notabene for VASP information exchange. Gemini applies conservative thresholds and requires beneficiary information for withdrawals exceeding $1,000 regardless of jurisdiction-specific requirements. The exchange maintains a comprehensive VASP directory and has established information-sharing relationships with over 100 counterparty institutions globally.\n\n    - **BitGo**: As a cryptocurrency custody provider serving institutional clients, BitGo implemented Travel Rule compliance through partnerships with Notabene and integration with client systems. BitGo's approach allows institutional clients to maintain control over customer data whilst facilitating required information exchange through BitGo's infrastructure. The company has developed API integrations enabling clients to automate Travel Rule compliance workflows.\n\n    - **Circle**: The issuer of USDC stablecoin implemented Travel Rule compliance for its Circle Account product, which enables individuals and businesses to hold and transfer cryptocurrency. Circle uses Notabene for VASP communications and requires customers to provide beneficiary information for large transfers. As both a VASP and stablecoin issuer, Circle faces dual compliance obligations under both Travel Rule and stablecoin-specific regulations.\n\n  - ### Enforcement Actions and Compliance Evolution\n\n    - **FinCEN Consent Order - Bittrex ($29.3 million, 2022)**: FinCEN imposed a $29.3 million penalty on cryptocurrency exchange Bittrex for violating the Bank Secrecy Act, including failures to implement adequate transaction monitoring and reporting systems. Whilst not exclusively focused on Travel Rule violations, the enforcement action highlighted expectations for comprehensive AML compliance including information gathering and transmission. Bittrex agreed to enhance compliance systems and retain an independent monitor.\n\n    - **New York DFS Consent Order - Robinhood Crypto ($30 million, 2022)**: The New York Department of Financial Services penalised Robinhood Crypto for AML and cybersecurity violations, including inadequate transaction monitoring systems that would support Travel Rule compliance. The consent order required implementation of enhanced AML systems capable of identifying and reporting suspicious transactions and facilitating information exchange with counterparty institutions.\n\n    - **Singapore MAS Enforcement**: The Monetary Authority of Singapore suspended several VASP licence applications and issued warnings to operating firms regarding Travel Rule non-compliance. Whilst not imposing formal penalties, MAS made clear that Travel Rule compliance is a prerequisite for maintaining payment services licences, effectively requiring implementation or market exit.\n\n    - **Swiss FINMA Supervisory Actions**: FINMA conducted supervisory reviews of Swiss VASPs' Travel Rule implementation, identifying deficiencies in beneficiary identification, information transmission protocols, and record keeping. Several firms received orders to remediate compliance systems or face potential licence revocation.\n\n    - **EU MiCA Preparation**: Ahead of MiCA's full application in December 2024, European regulators conducted assessments of VASP preparedness for enhanced Travel Rule requirements including zero-threshold implementation and self-hosted wallet provisions. Multiple VASPs indicated they would need to significantly enhance systems or potentially restrict services to meet the stringent requirements.\n\n  - ### Global Regulatory Landscape\n\n    - **United States**: FinCEN's $3,000 threshold for Travel Rule compliance applies to cryptocurrency transactions, with requirements to collect and verify originator and beneficiary information. However, the US has not mandated specific technical solutions, allowing VASPs flexibility in implementation. The patchwork of state money transmitter regulations adds complexity, with some states (notably New York under BitLicense requirements) imposing additional obligations. Proposed federal legislation seeks to clarify and harmonise cryptocurrency regulation including Travel Rule requirements.\n\n    - **European Union**: MiCA's zero-threshold approach represents the strictest Travel Rule implementation globally. All crypto-asset transfers require information exchange, and transfers exceeding €1,000 to self-hosted wallets require VASPs to verify beneficiary wallet ownership. The regulation creates significant compliance burdens and has prompted concerns about financial privacy and surveillance. Implementation across 27 member states with varying technical capabilities presents coordination challenges.\n\n    - **United Kingdom**: The UK has delayed Travel Rule implementation whilst developing its broader cryptoasset regulatory framework. The FCA has indicated that Travel Rule requirements will align with FATF standards (likely a £1,000 threshold) and expects VASPs to prepare systems accordingly. The Economic Crime Bill provides legal authority for implementation, with detailed rules expected to follow.\n\n    - **Asia-Pacific**: Significant variation exists across the region. Singapore (SGD 1,500 threshold), Japan (¥100,000 threshold), Hong Kong (HKD 8,000 threshold for licensed VASPs), and South Korea (KRW 1 million threshold) have implemented Travel Rule requirements with differing technical expectations. Regional coordination through organisations like the Asia/Pacific Group on Money Laundering aims to harmonise approaches, though significant differences remain.\n\n    - **Canada**: FINTRAC implemented Travel Rule requirements in June 2020 with a CAD 1,000 threshold. Canadian VASPs must record originator and beneficiary information and transmit it when transferring virtual assets to other VASPs. Canada has not mandated specific technical solutions, allowing market-driven approaches.\n\n    - **Australia**: AUSTRAC implemented Travel Rule requirements aligned with FATF recommendations, requiring VASPs to collect and transmit customer information for transactions exceeding AUD 1,000. Australia's principle-based approach allows VASPs to implement appropriate technical solutions based on their risk profiles and operational models.\n\n  - ### Compliance Challenges\n\n    - **VASP Identification**: Determining whether a blockchain address belongs to a VASP requiring Travel Rule information versus a self-hosted wallet remains technically challenging. No comprehensive global directory of VASP-controlled addresses exists, though various solutions maintain databases aggregating known addresses. Privacy-preserving cryptocurrencies and mixing services further complicate address attribution.\n\n    - **Interoperability**: Multiple competing Travel Rule solutions create network effects challenges. VASPs must either adopt multiple solutions to maximise counterparty coverage or risk being unable to exchange information with significant portions of the VASP ecosystem. The lack of mandatory standardisation has resulted in fragmentation, with different solutions predominating in different regions.\n\n    - **Data Protection Compliance**: Travel Rule requirements to transmit customer personal data conflict with data protection regulations including GDPR in Europe, PIPEDA in Canada, and state privacy laws in the US. Questions remain about legal bases for processing personal data, adequacy of data protection in cross-border transfers, and data minimisation principles. Some VASPs have implemented \"encryption-at-rest\" and \"zero-knowledge\" architectures to minimise data exposure.\n\n    - **Self-Hosted Wallet Challenges**: The EU's requirement to verify beneficiaries of self-hosted wallet transfers creates practical and philosophical challenges. VASPs cannot compel self-hosted wallet users to provide identity information, and blockchain transactions to such addresses can proceed without the receiving party's cooperation. Some VASPs have responded by restricting or prohibiting transfers to self-hosted wallets, raising concerns about financial freedom and self-custody rights.\n\n    - **DeFi Integration**: Decentralised exchanges and DeFi protocols operate without central operators who could implement Travel Rule compliance. As DeFi grows, an increasing proportion of cryptocurrency transactions occur outside the regulated VASP ecosystem. Regulators are exploring whether DeFi protocol developers, governance token holders, or liquidity providers should bear compliance obligations, though enforcement mechanisms remain unclear.\n\n    - **Layer-2 and Scaling Solutions**: Lightning Network channels, Polygon, Arbitrum, and other layer-2 solutions settle transactions off the main blockchain, creating challenges for Travel Rule compliance. Individual payment channel updates may not be recorded on-chain, making it difficult to apply threshold calculations and determine when information exchange is required. Some solutions are developing layer-2-specific compliance protocols.\n\n    - **Real-Time Implementation**: Blockchain transactions settle within minutes or seconds, requiring near-instantaneous information exchange between VASPs. Traditional correspondent banking can exchange SWIFT messages over hours or days. Building systems that reliably exchange, validate, and process Travel Rule information within transaction settlement windows creates technical and operational challenges, particularly for high-volume VASPs processing thousands of transactions hourly.\n\n    - **Customer Experience**: Travel Rule compliance introduces friction into withdrawal processes. Customers must provide additional information, wait for VASP-to-VASP communications to complete, and may face transaction rejections if counterparty VASPs cannot accept transmissions. This degrades user experience compared to traditional cryptocurrency's seamless global transfers.\n\n  - ### Best Practices\n\n    - **Multi-Solution Integration**: Adopt multiple Travel Rule solutions to maximise counterparty coverage. Leading VASPs typically integrate 2-3 different protocols (e.g., Notabene, TRP, and a regional solution) to ensure ability to communicate with the broadest range of counterparties.\n\n    - **Address Screening Automation**: Maintain comprehensive databases of known VASP addresses and integrate blockchain analytics tools to identify destination addresses before processing withdrawals. Automated screening reduces manual review requirements and improves customer experience by routing non-VASP transactions without unnecessary data collection.\n\n    - **Clear Customer Communication**: Provide transparent information to customers about Travel Rule requirements, why additional information is needed, how data will be protected, and potential delays in transaction processing. Clear communication reduces customer friction and support burdens.\n\n    - **Fallback Procedures**: Establish protocols for handling situations where counterparty VASPs cannot be contacted, do not respond to information requests, or use incompatible technical solutions. Options include rejecting transactions, obtaining customer attestations, or implementing risk-based approaches for lower-value transfers.\n\n    - **Data Minimisation**: Collect only required information and implement data retention policies compliant with both Travel Rule requirements (typically 5-year retention) and data protection laws (minimisation and deletion obligations). Encryption and access controls protect customer data from unauthorised access.\n\n    - **Regular Testing**: Conduct periodic testing of Travel Rule systems with counterparty VASPs to verify information exchange functionality. Test various scenarios including successful exchanges, timeout handling, and error conditions to ensure robust implementations.\n\n    - **Industry Participation**: Engage with industry working groups, standards organisations, and regulatory consultations to influence development of harmonised, workable Travel Rule requirements. Collaborative industry efforts can address technical challenges more effectively than individual VASP initiatives.\n\n  - ### Future Developments\n\n    - **Standards Convergence**: Ongoing efforts through organisations like Global Digital Finance and the Financial Action Task Force aim to harmonise Travel Rule technical standards and regulatory requirements across jurisdictions. Greater convergence would reduce compliance complexity and costs whilst improving effectiveness.\n\n    - **Decentralised Identity Integration**: Self-sovereign identity solutions could enable customers to maintain verifiable credentials in personal digital wallets, presenting proof of identity to VASPs without repeatedly providing personal information. W3C Decentralised Identifiers and Verifiable Credentials standards are evolving toward potential regulatory recognition.\n\n    - **Zero-Knowledge Compliance**: Cryptographic techniques including zero-knowledge proofs could theoretically enable VASPs to verify compliance with Travel Rule requirements (e.g., \"the beneficiary is not on sanctions lists\") without exchanging actual customer data. Research projects explore such privacy-preserving compliance architectures, though practical implementation and regulatory acceptance remain distant.\n\n    - **CBDC Integration**: Central Bank Digital Currencies may incorporate built-in compliance features including automatic Travel Rule data transmission or regulatory reporting. The architecture of CBDCs could either facilitate compliance through embedded features or create parallel payment systems with different regulatory requirements.\n\n    - **DeFi Compliance Solutions**: Emerging projects explore Travel Rule compliance for decentralised exchanges and DeFi protocols, potentially through optional compliance layers, identity attestation systems, or protocol-level compliance features. The viability and adoption of such solutions remains uncertain given DeFi's philosophical opposition to traditional financial intermediation.\n\n    - **Artificial Intelligence**: Machine learning could improve VASP identification, risk scoring, and anomaly detection whilst reducing false positives in Travel Rule workflows. AI-powered natural language processing might facilitate extraction of required information from various data formats, improving interoperability between systems.\n\n  - #\n\n## Current Landscape (2025)\n\n- Industry adoption and implementations\n  - Metaverse platforms continue to evolve with focus on interoperability and open standards\n  - Web3 integration accelerating with decentralised identity and asset ownership\n  - Enterprise adoption growing in virtual collaboration, training, and digital twins\n  - UK companies increasingly active in metaverse development and immersive technologies\n\n- Technical capabilities\n  - Real-time rendering at photorealistic quality levels\n  - Low-latency networking enabling seamless multi-user experiences\n  - AI-driven content generation and procedural world building\n  - Spatial audio and haptics enhancing immersion\n\n- UK and North England context\n  - Manchester: Digital Innovation Factory supports metaverse startups and research\n  - Leeds: Holovis leads in immersive experiences for entertainment and training\n  - Newcastle: University research in spatial computing and interactive systems\n  - Sheffield: Advanced manufacturing using digital twin technology\n\n- Standards and frameworks\n  - Metaverse Standards Forum driving interoperability protocols\n  - WebXR enabling browser-based immersive experiences\n  - glTF and USD for 3D asset interchange\n  - Open Metaverse Interoperability Group defining cross-platform standards\n\n## Metadata\n\n- **Last Updated**: 2025-11-16\n- **Review Status**: Automated remediation with 2025 context\n- **Verification**: Academic sources verified\n- **Regional Context**: UK/North England where applicable\n\n\n## References and Standards\n\n    - [[BC-0476-aml-kyc-compliance]] - Broader AML/KYC framework encompassing Travel Rule\n    - [[BC-0478-securities-regulation]] - Securities law interaction with Travel Rule for security tokens\n    - [[BC-0401-blockchain]] - Underlying technology creating compliance challenges\n    - [[BC-0455-blockchain-analytics]] - Tools for address identification and transaction tracing\n    - [[FATF]] - Financial Action Task Force Recommendation 16\n    - [[InterVASP Messaging Standard]] - IVMS101 data standard\n    - [[Virtual Asset Service Provider]] - Entities subject to Travel Rule\n    - [[FinCEN]] - US Travel Rule implementation and enforcement\n    - [[MiCA]] - EU Markets in Crypto-Assets Regulation\n    - [[Global Digital Finance]] - Industry standards development\n    - [[Self-Hosted Wallet]] - Non-custodial wallet compliance challenges",
  "properties": {
    "id": "bc-0477-travel-rule-ontology",
    "collapsed": "true",
    "- ontology": "true",
    "- term-id": "BC-0477",
    "- preferred-term": "Travel Rule",
    "- source-domain": "blockchain",
    "- status": "stub-needs-content",
    "- public-access": "true",
    "- content-status": "minimal-placeholder-requires-authoring",
    "- definition": "A component of the blockchain ecosystem.",
    "- maturity": "draft",
    "- owl:class": "bc:TravelRule",
    "- owl:physicality": "ConceptualEntity",
    "- owl:role": "Concept",
    "- belongsToDomain": "[[BlockchainDomain]]"
  },
  "backlinks": [
    "BC-0476-aml-kyc-compliance",
    "BC-0479-stablecoin-regulation",
    "BC-0478-securities-regulation",
    "BC-0480-cbdc-frameworks"
  ],
  "wiki_links": [
    "FinCEN",
    "BC-0455-blockchain-analytics",
    "Global Digital Finance",
    "BC-0478-securities-regulation",
    "MiCA",
    "BlockchainDomain",
    "BC-0476-aml-kyc-compliance",
    "Virtual Asset Service Provider",
    "FATF",
    "InterVASP Messaging Standard",
    "BC-0401-blockchain",
    "Self-Hosted Wallet"
  ],
  "ontology": {
    "term_id": "BC-0477",
    "preferred_term": "Travel Rule",
    "definition": "A component of the blockchain ecosystem.",
    "source_domain": "blockchain",
    "maturity_level": null,
    "authority_score": null
  }
}