{
  "title": "Output",
  "content": "- ### OntologyBlock\n  id:: output-ontology\n  collapsed:: true\n\n  - **Identification**\n    - public-access:: true\n    - ontology:: true\n    - term-id:: BC-0022\n    - preferred-term:: Output\n    - source-domain:: blockchain\n    - status:: complete\n    - version:: 1.0.0\n    - last-updated:: 2025-10-28\n\n  - **Definition**\n    - definition:: Transaction recipient destination within blockchain systems, providing essential functionality for distributed ledger technology operations and properties.\n    - maturity:: mature\n    - source:: [[ISO/IEC 23257:2021]], [[IEEE 2418.1]], [[NIST NISTIR]]\n    - authority-score:: 0.95\n\n  - **Semantic Classification**\n    - owl:class:: bc:Output\n    - owl:physicality:: VirtualEntity\n    - owl:role:: Object\n    - owl:inferred-class:: bc:VirtualObject\n    - belongsToDomain:: [[BlockchainDomain]]\n    - implementedInLayer:: [[ConceptualLayer]]\n\n  - #### Relationships\n    id:: output-relationships\n    - is-subclass-of:: [[Blockchain Entity]], [[DistributedDataStructure]]\n\n  - #### OWL Axioms\n    id:: output-owl-axioms\n    collapsed:: true\n    - ```clojure\n      Prefix(:=<http://metaverse-ontology.org/blockchain#>)\nPrefix(owl:=<http://www.w3.org/2002/07/owl#>)\nPrefix(rdf:=<http://www.w3.org/1999/02/22-rdf-syntax-ns#>)\nPrefix(xml:=<http://www.w3.org/XML/1998/namespace>)\nPrefix(xsd:=<http://www.w3.org/2001/XMLSchema#>)\nPrefix(rdfs:=<http://www.w3.org/2000/01/rdf-schema#>)\nPrefix(dct:=<http://purl.org/dc/terms/>)\n\nOntology(<http://metaverse-ontology.org/blockchain/BC-0022>\n  Import(<http://metaverse-ontology.org/blockchain/core>)\n\n  ## Class Declaration\n  Declaration(Class(:Output))\n\n  ## Subclass Relationships\n  SubClassOf(:Output :DistributedDataStructure)\n  SubClassOf(:Output :BlockchainEntity)\n\n  ## Essential Properties\n  SubClassOf(:Output\n    (ObjectSomeValuesFrom :partOf :Blockchain))\n\n  SubClassOf(:Output\n    (ObjectSomeValuesFrom :hasProperty :Property))\n\n  ## Data Properties\n  DataPropertyAssertion(:hasIdentifier :Output \"BC-0022\"^^xsd:string)\n  DataPropertyAssertion(:hasAuthorityScore :Output \"1.0\"^^xsd:decimal)\n  DataPropertyAssertion(:isFoundational :Output \"true\"^^xsd:boolean)\n\n  ## Object Properties\n  ObjectPropertyAssertion(:enablesFeature :Output :BlockchainFeature)\n  ObjectPropertyAssertion(:relatesTo :Output :RelatedConcept)\n\n  ## Annotations\n  AnnotationAssertion(rdfs:label :Output \"Output\"@en)\n  AnnotationAssertion(rdfs:comment :Output\n    \"Transaction recipient destination\"@en)\n  AnnotationAssertion(dct:description :Output\n    \"Foundational blockchain concept with formal ontological definition\"@en)\n  AnnotationAssertion(:termID :Output \"BC-0022\")\n  AnnotationAssertion(:priority :Output \"1\"^^xsd:integer)\n  AnnotationAssertion(:category :Output \"blockchain-fundamentals\"@en)\n)\n      ```",
  "properties": {
    "id": "output-owl-axioms",
    "collapsed": "true",
    "- public-access": "true",
    "- ontology": "true",
    "- term-id": "BC-0022",
    "- preferred-term": "Output",
    "- source-domain": "blockchain",
    "- status": "complete",
    "- version": "1.0.0",
    "- last-updated": "2025-10-28",
    "- definition": "Transaction recipient destination within blockchain systems, providing essential functionality for distributed ledger technology operations and properties.",
    "- maturity": "mature",
    "- source": "[[ISO/IEC 23257:2021]], [[IEEE 2418.1]], [[NIST NISTIR]]",
    "- authority-score": "0.95",
    "- owl:class": "bc:Output",
    "- owl:physicality": "VirtualEntity",
    "- owl:role": "Object",
    "- owl:inferred-class": "bc:VirtualObject",
    "- belongsToDomain": "[[BlockchainDomain]]",
    "- implementedInLayer": "[[ConceptualLayer]]",
    "- is-subclass-of": "[[Blockchain Entity]], [[DistributedDataStructure]]"
  },
  "backlinks": [],
  "wiki_links": [
    "NIST NISTIR",
    "ConceptualLayer",
    "BlockchainDomain",
    "DistributedDataStructure",
    "ISO/IEC 23257:2021",
    "IEEE 2418.1",
    "Blockchain Entity"
  ],
  "ontology": {
    "term_id": "BC-0022",
    "preferred_term": "Output",
    "definition": "Transaction recipient destination within blockchain systems, providing essential functionality for distributed ledger technology operations and properties.",
    "source_domain": "blockchain",
    "maturity_level": null,
    "authority_score": 0.95
  }
}