{
  "title": "Gas",
  "content": "- ### OntologyBlock\n  id:: gas-ontology\n  collapsed:: true\n\n  - **Identification**\n    - public-access:: true\n    - ontology:: true\n    - term-id:: BC-0100\n    - preferred-term:: Gas\n    - source-domain:: blockchain\n    - status:: complete\n    - version:: 1.0.0\n    - last-updated:: 2025-10-28\n\n  - **Definition**\n    - definition:: Transaction execution cost unit within blockchain systems, providing essential functionality for distributed ledger technology operations and properties.\n    - maturity:: mature\n    - source:: [[ISO/IEC 23257:2021]], [[IEEE 2418.1]], [[NIST NISTIR]]\n    - authority-score:: 0.90\n\n  - **Semantic Classification**\n    - owl:class:: bc:Gas\n    - owl:physicality:: VirtualEntity\n    - owl:role:: Object\n    - owl:inferred-class:: bc:VirtualObject\n    - belongsToDomain:: [[TokenEconomicsDomain]]\n\n  - #### OWL Restrictions\n    \n    \n\n  - #### Relationships\n    id:: relationships\n    - is-subclass-of:: [[Transaction Fee]]\n\n  - #### CrossDomainBridges\n    - bridges-to:: [[BlockchainEntity]] via is-subclass-of\n    - bridges-to:: [[Economicmechanism]] via is-subclass-of\n\n  -",
  "properties": {
    "id": "relationships",
    "collapsed": "true",
    "- public-access": "true",
    "- ontology": "true",
    "- term-id": "BC-0100",
    "- preferred-term": "Gas",
    "- source-domain": "blockchain",
    "- status": "complete",
    "- version": "1.0.0",
    "- last-updated": "2025-10-28",
    "- definition": "Transaction execution cost unit within blockchain systems, providing essential functionality for distributed ledger technology operations and properties.",
    "- maturity": "mature",
    "- source": "[[ISO/IEC 23257:2021]], [[IEEE 2418.1]], [[NIST NISTIR]]",
    "- authority-score": "0.90",
    "- owl:class": "bc:Gas",
    "- owl:physicality": "VirtualEntity",
    "- owl:role": "Object",
    "- owl:inferred-class": "bc:VirtualObject",
    "- belongsToDomain": "[[TokenEconomicsDomain]]",
    "- is-subclass-of": "[[Transaction Fee]]",
    "- bridges-to": "[[Economicmechanism]] via is-subclass-of"
  },
  "backlinks": [],
  "wiki_links": [
    "ISO/IEC 23257:2021",
    "IEEE 2418.1",
    "BlockchainEntity",
    "Economicmechanism",
    "NIST NISTIR",
    "Transaction Fee",
    "TokenEconomicsDomain"
  ],
  "ontology": {
    "term_id": "BC-0100",
    "preferred_term": "Gas",
    "definition": "Transaction execution cost unit within blockchain systems, providing essential functionality for distributed ledger technology operations and properties.",
    "source_domain": "blockchain",
    "maturity_level": null,
    "authority_score": 0.9
  }
}