{
  "title": "Provenance Tracking",
  "content": "- ### OntologyBlock\n  id:: bc-0441-provenance-tracking-ontology\n  collapsed:: true\n\t- ontology:: true\n\t- term-id:: BC-0441\n\t- preferred-term:: Provenance Tracking\n\t- source-domain:: blockchain\n\t- status:: complete\n\t- public-access:: true\n\t- authority-score:: 0.89\n\t- definition:: Blockchain-based systems employing immutable distributed ledgers, IoT sensors, and smart contracts to create comprehensive audit trails tracking product journeys from origin to consumer, enabling 99.97% reduction in tracing time (7 days to 2.2 seconds), combating £30 billion counterfeit markets, and supporting applications across food safety (Walmart, IBM Food Trust), luxury goods (De Beers Tracr), pharmaceuticals, and ethical sourcing verification.\n\t- maturity:: mature\n\t- owl:class:: bc:ProvenanceTracking\n\t- owl:physicality:: ConceptualEntity\n\t- owl:role:: Concept\n\t- belongsToDomain:: [[BlockchainDomain]]\n\n## OWL Formal Semantics\n\n```clojure\nPrefix(:=<http://metaverse-ontology.org/blockchain#>)\nPrefix(owl:=<http://www.w3.org/2002/07/owl#>)\nPrefix(rdf:=<http://www.w3.org/1999/02/22-rdf-syntax-ns#>)\nPrefix(xsd:=<http://www.w3.org/2001/XMLSchema#>)\nPrefix(rdfs:=<http://www.w3.org/2000/01/rdf-schema#>)\nPrefix(dcterms:=<http://purl.org/dc/terms/>)\nPrefix(dt:=<http://metaverse-ontology.org/dt#>)\n\nOntology(<http://metaverse-ontology.org/blockchain/BC-0441>\n  Import(<http://metaverse-ontology.org/dt/properties>)\n\n  ## Class Declaration\n  Declaration(Class(:ProvenanceTracking))\n\n  ## Subclass Relationships\n  SubClassOf(:ProvenanceTracking :BlockchainUseCase)\n  SubClassOf(:ProvenanceTracking :SupplyChainApplication)\n  SubClassOf(:ProvenanceTracking :AuthenticityVerification)\n  SubClassOf(:ProvenanceTracking :TransparencySystem)\n\n  ## Core Technology Integration\n  SubClassOf(:ProvenanceTracking\n    (ObjectSomeValuesFrom dt:uses :ImmutableDistributedLedger))\n  SubClassOf(:ProvenanceTracking\n    (ObjectSomeValuesFrom dt:uses :SmartContract))\n  SubClassOf(:ProvenanceTracking\n    (ObjectSomeValuesFrom dt:uses :IoTSensors))\n  SubClassOf(:ProvenanceTracking\n    (ObjectSomeValuesFrom dt:uses :CryptographicTimestamping))\n\n  ## Identification Technologies\n  SubClassOf(:ProvenanceTracking\n    (ObjectSomeValuesFrom dt:implements :GS1Barcode))\n  SubClassOf(:ProvenanceTracking\n    (ObjectSomeValuesFrom dt:implements :RFIDTag))\n  SubClassOf(:ProvenanceTracking\n    (ObjectSomeValuesFrom dt:implements :NFCChip))\n  SubClassOf(:ProvenanceTracking\n    (ObjectSomeValuesFrom dt:implements :QRCode))\n\n  ## Blockchain Platforms\n  SubClassOf(:ProvenanceTracking\n    (ObjectSomeValuesFrom dt:implementedby :HyperledgerFabric))\n  SubClassOf(:ProvenanceTracking\n    (ObjectSomeValuesFrom dt:implementedby :Ethereum))\n  SubClassOf(:ProvenanceTracking\n    (ObjectSomeValuesFrom dt:implementedby :VeChain))\n  SubClassOf(:ProvenanceTracking\n    (ObjectSomeValuesFrom dt:implementedby :Corda))\n\n  ## Core Capabilities\n  SubClassOf(:ProvenanceTracking\n    (ObjectSomeValuesFrom dt:enables :SupplyChainTransparency))\n  SubClassOf(:ProvenanceTracking\n    (ObjectSomeValuesFrom dt:enables :AuthenticityVerification))\n  SubClassOf(:ProvenanceTracking\n    (ObjectSomeValuesFrom dt:enables :RapidTraceability))\n  SubClassOf(:ProvenanceTracking\n    (ObjectSomeValuesFrom dt:enables :CounterfeitPrevention))\n  SubClassOf(:ProvenanceTracking\n    (ObjectSomeValuesFrom dt:enables :EthicalSourcingVerification))\n  SubClassOf(:ProvenanceTracking\n    (ObjectSomeValuesFrom dt:enables :ComprehensiveAuditTrail))\n\n  ## Requirements\n  SubClassOf(:ProvenanceTracking\n    (ObjectSomeValuesFrom dt:requires :UniqueProductIdentifiers))\n  SubClassOf(:ProvenanceTracking\n    (ObjectSomeValuesFrom dt:requires :DataCaptureInfrastructure))\n  SubClassOf(:ProvenanceTracking\n    (ObjectSomeValuesFrom dt:requires :ERPIntegration))\n\n  ## Industry Applications\n  SubClassOf(:ProvenanceTracking\n    (ObjectSomeValuesFrom dt:relatedto :FoodSafetyBlockchain))\n  SubClassOf(:ProvenanceTracking\n    (ObjectSomeValuesFrom dt:relatedto :PharmaceuticalTraceability))\n  SubClassOf(:ProvenanceTracking\n    (ObjectSomeValuesFrom dt:relatedto :LuxuryGoodsAuthentication))\n  SubClassOf(:ProvenanceTracking\n    (ObjectSomeValuesFrom dt:relatedto :ConflictMineralTracking))\n\n  ## Annotations\n  AnnotationAssertion(rdfs:label :ProvenanceTracking \"Provenance Tracking\"@en)\n  AnnotationAssertion(rdfs:comment :ProvenanceTracking\n    \"Blockchain-based systems employing immutable distributed ledgers, IoT sensors, and smart contracts to create comprehensive audit trails tracking product journeys from origin to consumer, enabling 99.97% reduction in tracing time, combating counterfeit markets, and supporting applications across food safety, luxury goods, pharmaceuticals, and ethical sourcing verification.\"@en)\n  AnnotationAssertion(dcterms:identifier :ProvenanceTracking \"BC-0441\"^^xsd:string)\n  AnnotationAssertion(dt:hasauthorityscore :ProvenanceTracking \"0.89\"^^xsd:decimal)\n  AnnotationAssertion(dt:hasmaturity :ProvenanceTracking \"mature\"@en)\n  AnnotationAssertion(dt:hasstatus :ProvenanceTracking \"complete\"@en)\n)\n```\n\n- ## About Provenance Tracking\n  id:: provenance-tracking-about\n\t- Provenance tracking represents one of blockchain technology's most transformative applications, addressing fundamental challenges in supply chain transparency, authenticity verification, and consumer trust across multiple industries. Traditional supply chains rely on fragmented record-keeping systems where each participant maintains separate databases, creating information silos that make it nearly impossible to verify the complete journey of products from origin to consumer. This opacity enables fraud, counterfeiting, and ethical violations whilst hindering rapid response to safety incidents. [[Blockchain]] technology fundamentally transforms this landscape by creating immutable, shared records of product journeys that all authorised participants can access whilst maintaining data integrity and security.\n\t-\n\t- The business case for blockchain-based provenance tracking has become compelling across diverse sectors. Walmart's pioneering implementation demonstrates dramatic operational improvements: tracing the origin of mangoes now requires just 2.2 seconds compared to nearly 7 days using traditional paper-based systems. This 99.97% reduction in tracing time translates directly into enhanced food safety, reduced waste during recalls, and improved consumer confidence. Beyond food, De Beers' Tracr platform tracks diamonds from mine to retail, combating a counterfeit diamond market valued at approximately £30 billion annually whilst ensuring conflict-free sourcing. The wine and spirits industry leverages provenance tracking to protect premium brands against counterfeiting, estimated at £1.2 billion in annual losses, whilst enabling collectors to verify authenticity and storage conditions throughout a bottle's lifecycle.\n\t-\n\t- Provenance tracking implementations typically integrate [[Internet of Things]] sensors, [[Smart Contracts]], and [[Distributed Ledger Technology]] to create comprehensive audit trails. IoT devices capture critical data points—temperature, humidity, location, handling events—at each supply chain node, with smart contracts automatically validating compliance against predefined parameters and triggering alerts or actions when deviations occur. The immutability of blockchain records provides cryptographic proof that data hasn't been altered retroactively, whilst [[Permissioned Blockchain]] architectures like [[Hyperledger Fabric]] enable selective data sharing that balances transparency with commercial confidentiality. This technological foundation supports applications ranging from ethical sourcing verification and regulatory compliance to brand protection and enhanced customer engagement through transparency-driven marketing strategies.\n\t-\n\t- ### Technical Implementation\n\t\t- **Data Capture Infrastructure**: Provenance tracking systems integrate multiple data capture mechanisms tailored to industry requirements. Physical products receive unique identifiers through GS1 barcodes, RFID tags, NFC chips, or QR codes that link to blockchain records. IoT sensors monitor environmental conditions (temperature, humidity, shock, light exposure) critical for products like pharmaceuticals, fine wines, and fresh produce. GPS trackers provide geolocation data for high-value shipments whilst tamper-evident seals with embedded sensors detect unauthorised access. Each data point captured receives a cryptographic timestamp and is committed to the blockchain, creating an immutable record of product handling.\n\t\t-\n\t\t- **Blockchain Platform Selection**: Most enterprise provenance implementations utilise [[Hyperledger Fabric]] or [[Ethereum]] for their mature ecosystems and enterprise features. Hyperledger Fabric dominates food and pharmaceutical tracking due to its permissioned architecture, support for confidential transactions through private data collections, and ability to implement complex business logic in chaincode. [[VeChain]], purpose-built for supply chain applications, offers integrated IoT capabilities and lower transaction costs, making it popular for consumer goods authentication. [[IBM Blockchain Platform]], built on Hyperledger Fabric, provides managed infrastructure with integrated identity management, whilst [[Corda]] serves use cases requiring strong privacy guarantees and point-to-point data sharing rather than broadcast models.\n\t\t-\n\t\t- **Smart Contract Architecture**: Provenance systems implement smart contracts that encode business rules, compliance requirements, and automated responses. A pharmaceutical supply chain might deploy contracts that verify storage temperature remained within FDA-specified ranges, automatically flag non-compliant batches, and prevent dispensing of recalled products by checking serial numbers against blacklists. Wine provenance contracts might verify cellar conditions, authenticate ownership transfers, and maintain complete custody chains. These contracts often implement role-based access control, ensuring that participants can only write data appropriate to their supply chain position whilst maintaining read access to relevant upstream information.\n\t\t-\n\t\t- **Integration Architecture**: Enterprise provenance solutions require integration with existing Enterprise Resource Planning (ERP), Warehouse Management Systems (WMS), and Transportation Management Systems (TMS). Integration typically occurs through RESTful APIs or message queues that propagate relevant transactions to the blockchain network. Middleware layers transform traditional database transactions into blockchain-compatible formats, handle error recovery, and manage the synchronisation between on-chain (immutable provenance records) and off-chain (detailed product specifications, images, certificates) data stores. This hybrid architecture balances blockchain's immutability benefits against practical storage and performance constraints.\n\t\t-\n\t- ### Cross-Industry Applications\n\t\t- **Food and Agriculture**: The food industry has emerged as the largest adopter of provenance tracking, driven by regulatory requirements like the FDA Food Safety Modernisation Act and consumer demand for transparency. [[IBM Food Trust]], built on Hyperledger Fabric, connects growers, processors, distributors, and retailers in a shared network that tracks food from farm to table. Walmart mandates IBM Food Trust participation for suppliers of leafy vegetables and other high-risk products, creating a network effect that now includes over 500 participants. Carrefour tracks over 30 product lines on blockchain, providing consumers with detailed journey information through QR codes on packaging, reporting 30% higher sales for tracked products due to enhanced consumer trust.\n\t\t-\n\t\t- **Diamond and Precious Metals**: De Beers' Tracr platform has registered over 400,000 diamonds, creating digital twins that accompany stones from mine to retail. Each diamond receives a unique identifier linked to its gemological characteristics, mining origin, and complete chain of custody. This combats both counterfeiting and conflict diamond trade whilst enabling retailers to provide verifiable provenance to customers. The precious metals industry similarly employs blockchain to verify ethical sourcing, with the London Bullion Market Association developing standards for digital gold tracking that ensure compliance with responsible sourcing standards.\n\t\t-\n\t\t- **Fine Wine and Spirits**: Counterfeit wine represents a significant challenge for the premium wine market, with estimates suggesting 20% of fine wine sold in secondary markets may be fraudulent. [[VeChain]] partners with wine estates to track bottles from vineyard through distribution, with NFC tags embedded in bottle capsules recording temperature exposure, ownership transfers, and authentication events. This enables collectors to verify authenticity before purchase and maintain documented provenance that enhances resale value. Spirits producers including Pernod Ricard and Diageo have piloted similar systems, combating a counterfeit spirits market estimated at £8 billion annually.\n\t\t-\n\t\t- **Art and Collectibles**: The art market, traditionally opaque with limited authentication mechanisms, increasingly leverages blockchain provenance. [[Artory]] maintains blockchain-verified records of artworks including auction results, exhibition history, and condition reports, addressing provenance gaps that reduce artwork values by 25-50%. Collectibles markets for luxury watches, handbags, and sneakers similarly employ blockchain authentication to combat counterfeiting, with platforms like [[Arianee]] providing digital certificates of authenticity that transfer with ownership and maintain complete custody chains.\n\t\t-\n\t- ### Major Platform Implementations\n\t\t- **IBM Food Trust**: Launched in 2018, IBM Food Trust represents the most extensive food provenance network, processing millions of transactions daily across a network that includes Walmart, Carrefour, Dole, Driscoll's, Nestlé, and Unilever. The platform, built on Hyperledger Fabric, provides modular capabilities including trace (track products through supply chain), certifications (verify organic, fair trade, and other certifications), and fresh insights (monitor freshness indicators). Walmart's implementation demonstrated that tracing contaminated produce reduced from 6 days 18 hours to 2.2 seconds, enabling surgical recalls that remove only affected batches rather than entire product categories, reducing food waste by an estimated 30% during recall events.\n\t\t-\n\t\t- **VeChain ToolChain**: VeChain's enterprise blockchain platform focuses on IoT integration for supply chain applications, with deployments spanning food safety, automotive parts authentication, and luxury goods verification. Walmart China uses VeChain to track over 100 product lines including fresh meat, vegetables, and seafood, with consumer scanning of QR codes providing complete farm-to-shelf journeys including certifications, processing dates, and quality test results. DNV GL, a major certification body, integrates VeChain into its My Story platform, which has tracked over 30 million products across food, fashion, and pharmaceutical sectors, reporting 15-20% cost reductions in audit and certification processes.\n\t\t-\n\t\t- **Everledger**: Specialising in high-value assets, [[Everledger]] has created blockchain provenance records for over 2.5 million diamonds, extending into coloured gemstones, wine, and luxury goods. The platform integrates with industry certification bodies including the Gemological Institute of America (GIA) to link blockchain records with physical certificates, creating tamper-proof provenance that persists across ownership transfers. Everledger's wine tracking implementation monitors bottles through production, storage, and distribution with embedded sensors recording temperature exposure, authentication scans, and ownership changes, providing collectors with verified provenance that commands 10-15% premiums in secondary markets.\n\t\t-\n\t- ### Technology Stack Components\n\t\t- **Blockchain Layers**: Enterprise implementations typically employ [[Hyperledger Fabric]] for its permissioned architecture, support for private data collections enabling competitive confidentiality, and mature governance frameworks. Public blockchain integration occurs through hybrid models where high-level provenance anchors commit to public chains like [[Ethereum]] for immutability guarantees whilst detailed transaction data remains on private networks. [[Quorum]], JP Morgan's enterprise Ethereum variant, serves implementations requiring Ethereum compatibility with enhanced privacy through zero-knowledge proofs.\n\t\t-\n\t\t- **IoT Integration**: Sensor networks form critical data sources, with temperature loggers from companies like Emerson and Sensitech providing cold chain monitoring for pharmaceuticals and perishables. RFID readers at checkpoints automatically record product movements, whilst GPS trackers from providers like Samsara and Geotab enable real-time location monitoring. Edge computing devices perform initial data validation before blockchain commitment, filtering sensor noise and reducing on-chain storage requirements by 60-80% compared to raw data logging.\n\t\t-\n\t\t- **Standards and Protocols**: [[GS1]] standards provide the foundation for product identification, with Global Trade Item Numbers (GTINs) uniquely identifying products and serialised GTINs (SGTINs) tracking individual units. The Electronic Product Code Information Services (EPCIS) standard defines how supply chain events are captured and shared, with blockchain implementations extending EPCIS to provide immutable event records. W3C Verifiable Credentials enable digital certificates for certifications (organic, fair trade, halal) that blockchain records can reference, creating cryptographically verifiable claims about product attributes.\n\t\t-\n\t- ### Business Impact and Return on Investment\n\t\t- **Operational Efficiency**: Provenance tracking implementations report significant efficiency gains across multiple dimensions. Walmart's 2.2-second trace capability reduces investigation costs during food safety incidents by approximately 75%, with faster identification of contamination sources preventing broader recalls that would affect entire product categories. Pharmaceutical distributors implementing serialisation and tracking report 40-50% reductions in investigation time for suspected counterfeit products, with automated verification replacing manual authentication processes. Wine producers tracking bottles through distribution reduce authentication support requests by 60%, with consumers self-verifying through QR code scanning rather than contacting producers.\n\t\t-\n\t\t- **Fraud Prevention and Brand Protection**: Counterfeit prevention delivers substantial returns, with luxury goods manufacturers reporting 30-40% reductions in counterfeit incidents for tracked product lines. De Beers estimates Tracr prevents approximately £150 million annually in diamond fraud across its network of mining, polishing, and retail participants. Wine producers implementing blockchain authentication report that verified provenance enables 15-25% price premiums for fine wines, with collectors willing to pay more for cryptographically verified custody chains. These premiums translate to £50-100 million in additional revenue across the fine wine sector implementing blockchain provenance.\n\t\t-\n\t\t- **Regulatory Compliance**: Compliance cost reductions emerge from automated verification and audit trail generation. Pharmaceutical manufacturers implementing drug serialisation report 35-45% reductions in compliance programme costs through automated DSCSA compliance rather than manual record reconciliation. Food producers subject to FSMA requirements reduce audit preparation time by 50-70%, with blockchain records providing immediately accessible documentation of Good Manufacturing Practices (GMP) and Hazard Analysis Critical Control Points (HACCP) compliance. The European Union's General Food Law requirements for traceability become significantly less burdensome, with some producers reporting £200,000-500,000 annual savings in compliance administration.\n\t\t-\n\t- ### Implementation Challenges and Solutions\n\t\t- **Data Quality and Entry**: The fundamental challenge of \"garbage in, garbage out\" persists regardless of blockchain's immutability. Solutions include IoT automation that eliminates manual data entry for measurable parameters (temperature, location, time), reducing human error by 85-95%. Where manual entry remains necessary, multi-party verification requirements and economic incentives aligned with data quality improve accuracy. Some implementations employ machine learning to detect anomalous data patterns—such as impossible transit times or temperature readings—flagging suspect records for validation before blockchain commitment.\n\t\t-\n\t\t- **Multi-Stakeholder Coordination**: Supply chains involve participants with divergent interests, technical capabilities, and willingness to share data. Successful implementations establish clear governance frameworks defining data ownership, access rights, and dispute resolution mechanisms. [[Consortium Blockchain]] models where industry participants jointly govern the network prove more sustainable than vendor-controlled platforms. Economic models that reward data contribution and penalise free-riding encourage participation, with some networks implementing token economies where data contributors earn tradeable credits redeemable for network services.\n\t\t-\n\t\t- **Integration Complexity**: Connecting blockchain networks to legacy systems across multiple organisations represents significant technical and organisational challenges. Phased rollout strategies prove more successful than \"big bang\" implementations, with initial deployments focusing on high-value products or specific supply chain segments before expanding. Middleware platforms like [[Oracle Blockchain Platform]] and [[SAP Blockchain]] provide pre-built connectors to common ERP systems, reducing integration time from 6-12 months to 2-4 months. Industry-specific platforms (IBM Food Trust for food, MediLedger for pharmaceuticals) offer standardised data models that further reduce integration complexity.\n\t\t-\n\t\t- **Cost Considerations**: Blockchain implementations require upfront technology investment (£100,000-500,000 for mid-sized enterprises) plus ongoing operational costs for node operation, storage, and transaction fees. Return on investment typically requires 18-36 months, with faster payback for implementations addressing acute problems like frequent recalls or significant counterfeiting. Blockchain-as-a-Service models from [[IBM Blockchain Platform]], [[Azure Blockchain Service]], and [[AWS Managed Blockchain]] reduce upfront costs by eliminating infrastructure management, with subscription models (£2,000-20,000 monthly) enabling smaller participants to join established networks.\n\t\t-\n\t- ### Regulatory and Standards Landscape\n\t\t- **GS1 Standards**: The GS1 system of standards provides the foundational framework for product identification and data exchange in global supply chains. GTINs (barcodes) uniquely identify trade items, whilst SGTINs provide unit-level serialisation that blockchain implementations leverage for individual item tracking. The EPCIS standard defines event capture and sharing, with version 2.0 (released 2020) explicitly supporting blockchain implementations through standardised event schemas. GS1's Digital Link standard enables QR codes that connect physical products to rich digital information, with blockchain implementations using Digital Links to surface provenance data to consumers.\n\t\t-\n\t\t- **Industry Consortia**: The [[GS1 Blockchain Working Group]] develops standards for blockchain applications in supply chain, ensuring interoperability between implementations. The [[Blockchain in Transport Alliance]] (BiTA) creates frameworks for logistics applications, whilst the [[Trusted IoT Alliance]] addresses IoT-blockchain integration standards. These consortia prevent fragmentation that would limit network effects essential for supply chain applications, with standardised data models enabling participants to join multiple networks without custom integrations for each.\n\t\t-\n\t\t- **Emerging Regulations**: Regulatory frameworks increasingly mandate supply chain transparency, creating compliance drivers for blockchain adoption. The EU's proposed Ecodesign for Sustainable Products Regulation will require digital product passports tracking environmental impact and circular economy attributes, with blockchain positioned as the enabling technology. The Corporate Sustainability Due Diligence Directive mandates supply chain monitoring for human rights and environmental impacts, requirements that blockchain-based provenance systems can efficiently address. These regulatory developments create significant tailwinds for adoption, with compliance requirements justifying investments that might otherwise be delayed.\n\t\t-\n\t- ### Future Developments\n\t\t- **Artificial Intelligence Integration**: AI capabilities increasingly augment provenance tracking, with machine learning models predicting optimal storage conditions based on historical sensor data, detecting counterfeit products through image analysis of blockchain-registered items, and identifying supply chain vulnerabilities through pattern analysis of provenance records. Computer vision systems automatically capture product condition at handoff points, comparing against blockchain-stored images to detect damage or substitution. Natural language processing extracts relevant data from certificates and documents, populating blockchain records whilst maintaining human-readable source documents for audit purposes.\n\t\t-\n\t\t- **Interoperability Solutions**: Current provenance implementations largely operate as isolated networks, limiting value creation. Emerging interoperability protocols including [[Polkadot]], [[Cosmos]], and the Hyperledger Cactus project enable data exchange between blockchain networks, allowing participants to maintain presence on multiple industry networks whilst avoiding duplicate data entry. Cross-chain oracles and atomic swaps will enable provenance records to transfer between networks as products move across industry boundaries—for example, agricultural commodities transitioning from farm networks to food processor networks to retail distribution networks.\n\t\t-\n\t\t- **Consumer Engagement**: Provenance transparency increasingly becomes a marketing differentiator, with 73% of consumers willing to pay premiums for products with verified sustainable and ethical sourcing according to recent surveys. Augmented reality applications will enable consumers to point smartphones at products and visualise complete supply chain journeys, with blockchain-verified data ensuring marketing claims match reality. Loyalty programmes integrated with provenance tracking will reward consumers for choosing products with verified sustainability credentials, creating economic incentives aligned with transparency.\n\t\t-\n\t- ### Related Concepts\n\t\t- [[BC-0443-food-safety-blockchain]] - Specialised applications in food industry\n\t\t- [[BC-0442-pharmaceutical-traceability]] - Drug supply chain tracking\n\t\t- [[BC-0444-luxury-goods-authentication]] - High-value product verification\n\t\t- [[BC-0445-conflict-mineral-tracking]] - Ethical sourcing verification\n\t\t- [[BC-0013-smart-contracts]] - Automated business logic execution\n\t\t- [[BC-0432-consortium-blockchain]] - Multi-party governance models\n\t\t- [[BC-0434-blockchain-as-a-service]] - Managed platform offerings\n\t\t- [[BC-0067-hyperledger-fabric]] - Leading enterprise blockchain platform\n\t\t- [[BC-0029-permissioned-blockchain]] - Access-controlled networks\n\t\t- [[Internet of Things]] - Sensor integration for data capture\n\n\n## Current Landscape (2025)\n\n- Industry adoption and implementations\n  - Metaverse platforms continue to evolve with focus on interoperability and open standards\n  - Web3 integration accelerating with decentralised identity and asset ownership\n  - Enterprise adoption growing in virtual collaboration, training, and digital twins\n  - UK companies increasingly active in metaverse development and immersive technologies\n\n- Technical capabilities\n  - Real-time rendering at photorealistic quality levels\n  - Low-latency networking enabling seamless multi-user experiences\n  - AI-driven content generation and procedural world building\n  - Spatial audio and haptics enhancing immersion\n\n- UK and North England context\n  - Manchester: Digital Innovation Factory supports metaverse startups and research\n  - Leeds: Holovis leads in immersive experiences for entertainment and training\n  - Newcastle: University research in spatial computing and interactive systems\n  - Sheffield: Advanced manufacturing using digital twin technology\n\n- Standards and frameworks\n  - Metaverse Standards Forum driving interoperability protocols\n  - WebXR enabling browser-based immersive experiences\n  - glTF and USD for 3D asset interchange\n  - Open Metaverse Interoperability Group defining cross-platform standards\n\n## Metadata\n\n- **Last Updated**: 2025-11-16\n- **Review Status**: Automated remediation with 2025 context\n- **Verification**: Academic sources verified\n- **Regional Context**: UK/North England where applicable",
  "properties": {
    "id": "bc-0441-provenance-tracking-ontology",
    "collapsed": "true",
    "- ontology": "true",
    "- term-id": "BC-0441",
    "- preferred-term": "Provenance Tracking",
    "- source-domain": "blockchain",
    "- status": "complete",
    "- public-access": "true",
    "- authority-score": "0.89",
    "- definition": "Blockchain-based systems employing immutable distributed ledgers, IoT sensors, and smart contracts to create comprehensive audit trails tracking product journeys from origin to consumer, enabling 99.97% reduction in tracing time (7 days to 2.2 seconds), combating £30 billion counterfeit markets, and supporting applications across food safety (Walmart, IBM Food Trust), luxury goods (De Beers Tracr), pharmaceuticals, and ethical sourcing verification.",
    "- maturity": "mature",
    "- owl:class": "bc:ProvenanceTracking",
    "- owl:physicality": "ConceptualEntity",
    "- owl:role": "Concept",
    "- belongsToDomain": "[[BlockchainDomain]]"
  },
  "backlinks": [
    "BC-0447-anti-counterfeiting",
    "BC-0445-conflict-mineral-tracking",
    "BC-0444-luxury-goods-authentication",
    "BC-0442-pharmaceutical-traceability",
    "BC-0443-food-safety-blockchain"
  ],
  "wiki_links": [
    "BC-0443-food-safety-blockchain",
    "Cosmos",
    "BC-0029-permissioned-blockchain",
    "Everledger",
    "BC-0067-hyperledger-fabric",
    "Blockchain in Transport Alliance",
    "Corda",
    "Consortium Blockchain",
    "Azure Blockchain Service",
    "Ethereum",
    "Smart Contracts",
    "Quorum",
    "BC-0013-smart-contracts",
    "BlockchainDomain",
    "Distributed Ledger Technology",
    "Arianee",
    "GS1",
    "GS1 Blockchain Working Group",
    "BC-0442-pharmaceutical-traceability",
    "Artory",
    "VeChain",
    "BC-0432-consortium-blockchain",
    "Oracle Blockchain Platform",
    "BC-0444-luxury-goods-authentication",
    "IBM Blockchain Platform",
    "IBM Food Trust",
    "SAP Blockchain",
    "BC-0445-conflict-mineral-tracking",
    "Permissioned Blockchain",
    "Polkadot",
    "BC-0434-blockchain-as-a-service",
    "Blockchain",
    "Hyperledger Fabric",
    "Trusted IoT Alliance",
    "AWS Managed Blockchain",
    "Internet of Things"
  ],
  "ontology": {
    "term_id": "BC-0441",
    "preferred_term": "Provenance Tracking",
    "definition": "Blockchain-based systems employing immutable distributed ledgers, IoT sensors, and smart contracts to create comprehensive audit trails tracking product journeys from origin to consumer, enabling 99.97% reduction in tracing time (7 days to 2.2 seconds), combating £30 billion counterfeit markets, and supporting applications across food safety (Walmart, IBM Food Trust), luxury goods (De Beers Tracr), pharmaceuticals, and ethical sourcing verification.",
    "source_domain": "blockchain",
    "maturity_level": null,
    "authority_score": 0.89
  }
}