{
  "title": "Public-Key Cryptography",
  "content": "- ### OntologyBlock\n  id:: public-key-cryptography-ontology\n  collapsed:: true\n\n  - **Identification**\n    - public-access:: true\n    - ontology:: true\n    - term-id:: BC-0031\n    - preferred-term:: Public-Key Cryptography\n    - source-domain:: blockchain\n    - status:: complete\n    - version:: 1.0.0\n    - last-updated:: 2025-10-28\n\n  - **Definition**\n    - definition:: Asymmetric encryption system within blockchain systems, providing essential functionality for distributed ledger technology operations and properties.\n    - maturity:: mature\n    - source:: [[ISO/IEC 23257:2021]], [[IEEE 2418.1]], [[NIST NISTIR]]\n    - authority-score:: 0.95\n\n  - **Semantic Classification**\n    - owl:class:: bc:Public-keyCryptography\n    - owl:physicality:: VirtualEntity\n    - owl:role:: Object\n    - owl:inferred-class:: bc:VirtualObject\n    - belongsToDomain:: [[CryptographicDomain]]\n    - implementedInLayer:: [[SecurityLayer]]\n\n  - #### Relationships\n    id:: public-key-cryptography-relationships\n    - is-subclass-of:: [[Blockchain Entity]], [[CryptographicPrimitive]]\n\n  - #### OWL Axioms\n    id:: public-key-cryptography-owl-axioms\n    collapsed:: true\n    - ```clojure\n      Prefix(:=<http://metaverse-ontology.org/blockchain#>)\nPrefix(owl:=<http://www.w3.org/2002/07/owl#>)\nPrefix(rdf:=<http://www.w3.org/1999/02/22-rdf-syntax-ns#>)\nPrefix(xml:=<http://www.w3.org/XML/1998/namespace>)\nPrefix(xsd:=<http://www.w3.org/2001/XMLSchema#>)\nPrefix(rdfs:=<http://www.w3.org/2000/01/rdf-schema#>)\nPrefix(dct:=<http://purl.org/dc/terms/>)\n\nOntology(<http://metaverse-ontology.org/blockchain/BC-0031>\n  Import(<http://metaverse-ontology.org/blockchain/core>)\n\n  ## Class Declaration\n  Declaration(Class(:Public-KeyCryptography))\n\n  ## Subclass Relationships\n  SubClassOf(:Public-KeyCryptography :CryptographicPrimitive)\n  SubClassOf(:Public-KeyCryptography :BlockchainEntity)\n\n  ## Essential Properties\n  SubClassOf(:Public-KeyCryptography\n    (ObjectSomeValuesFrom :partOf :Blockchain))\n\n  SubClassOf(:Public-KeyCryptography\n    (ObjectSomeValuesFrom :hasProperty :Property))\n\n  ## Data Properties\n  DataPropertyAssertion(:hasIdentifier :Public-KeyCryptography \"BC-0031\"^^xsd:string)\n  DataPropertyAssertion(:hasAuthorityScore :Public-KeyCryptography \"1.0\"^^xsd:decimal)\n  DataPropertyAssertion(:isFoundational :Public-KeyCryptography \"true\"^^xsd:boolean)\n\n  ## Object Properties\n  ObjectPropertyAssertion(:enablesFeature :Public-KeyCryptography :BlockchainFeature)\n  ObjectPropertyAssertion(:relatesTo :Public-KeyCryptography :RelatedConcept)\n\n  ## Annotations\n  AnnotationAssertion(rdfs:label :Public-KeyCryptography \"Public-Key Cryptography\"@en)\n  AnnotationAssertion(rdfs:comment :Public-KeyCryptography\n    \"Asymmetric encryption system\"@en)\n  AnnotationAssertion(dct:description :Public-KeyCryptography\n    \"Foundational blockchain concept with formal ontological definition\"@en)\n  AnnotationAssertion(:termID :Public-KeyCryptography \"BC-0031\")\n  AnnotationAssertion(:priority :Public-KeyCryptography \"1\"^^xsd:integer)\n  AnnotationAssertion(:category :Public-KeyCryptography \"cryptographic-foundations\"@en)\n)\n      ```\n\n- ## About Public-Key Cryptography\n  id:: public-key-cryptography-about\n\n  - Asymmetric encryption system within blockchain systems, providing essential functionality for distributed ledger technology operations and properties.\n  -\n  - ### Key Characteristics\n    id:: public-key-cryptography-characteristics\n    - 1. **Definitional Property**: Core defining characteristic\n    - 2. **Functional Property**: Operational behavior\n    - 3. **Structural Property**: Compositional elements\n    - 4. **Security Property**: Security guarantees provided\n    - 5. **Performance Property**: Efficiency considerations\n  -\n  - ### Technical Components\n    id:: public-key-cryptography-components\n    - **Implementation**: How concept is realized technically\n    - **Verification**: Methods for validating correctness\n    - **Interaction**: Relationships with other components\n    - **Constraints**: Technical limitations and requirements\n  -\n  - ### Use Cases\n    id:: public-key-cryptography-use-cases\n    - **1. Core Blockchain Operation**\n    - **Application**: Fundamental blockchain functionality\n    - **Example**: Practical implementation in major blockchains\n    - **Requirements**: Technical prerequisites\n    - **Benefits**: Value provided to blockchain systems\n  -\n  - ### Standards & References\n    id:: public-key-cryptography-standards\n    - [[ISO/IEC 23257:2021]] - Blockchain and distributed ledger technologies\n    - [[IEEE 2418.1]] - Blockchain and distributed ledger technologies\n    - [[NIST NISTIR]] - Blockchain and distributed ledger technologies\n  -",
  "properties": {
    "id": "public-key-cryptography-standards",
    "collapsed": "true",
    "- public-access": "true",
    "- ontology": "true",
    "- term-id": "BC-0031",
    "- preferred-term": "Public-Key Cryptography",
    "- source-domain": "blockchain",
    "- status": "complete",
    "- version": "1.0.0",
    "- last-updated": "2025-10-28",
    "- definition": "Asymmetric encryption system within blockchain systems, providing essential functionality for distributed ledger technology operations and properties.",
    "- maturity": "mature",
    "- source": "[[ISO/IEC 23257:2021]], [[IEEE 2418.1]], [[NIST NISTIR]]",
    "- authority-score": "0.95",
    "- owl:class": "bc:Public-keyCryptography",
    "- owl:physicality": "VirtualEntity",
    "- owl:role": "Object",
    "- owl:inferred-class": "bc:VirtualObject",
    "- belongsToDomain": "[[CryptographicDomain]]",
    "- implementedInLayer": "[[SecurityLayer]]",
    "- is-subclass-of": "[[Blockchain Entity]], [[CryptographicPrimitive]]"
  },
  "backlinks": [],
  "wiki_links": [
    "Blockchain Entity",
    "ISO/IEC 23257:2021",
    "CryptographicPrimitive",
    "NIST NISTIR",
    "SecurityLayer",
    "CryptographicDomain",
    "IEEE 2418.1"
  ],
  "ontology": {
    "term_id": "BC-0031",
    "preferred_term": "Public-Key Cryptography",
    "definition": "Asymmetric encryption system within blockchain systems, providing essential functionality for distributed ledger technology operations and properties.",
    "source_domain": "blockchain",
    "maturity_level": null,
    "authority_score": 0.95
  }
}