{
  "title": "R3 Corda",
  "content": "- ### OntologyBlock\n  id:: bc-0437-r3-corda-ontology\n  collapsed:: true\n\t- ontology:: true\n\t- term-id:: BC-0437\n\t- preferred-term:: R3 Corda\n\t- source-domain:: blockchain\n\t- status:: stub-needs-content\n\t- public-access:: true\n\t- content-status:: minimal-placeholder-requires-authoring\n\t- public-access:: true\n\t- definition:: A component of the blockchain ecosystem.\n\t- maturity:: draft\n\t- owl:class:: bc:R3Corda\n\t- owl:physicality:: ConceptualEntity\n\t- owl:role:: Concept\n\t- belongsToDomain:: [[BlockchainDomain]]\n\n## OWL Formal Semantics\n\n```clojure\n;; OWL Functional Syntax\n\n(Declaration (Class :R3Corda))\n\n;; Annotations\n(AnnotationAssertion rdfs:label :R3Corda \"R3 Corda\"@en)\n(AnnotationAssertion rdfs:comment :R3Corda \"A component of the blockchain ecosystem.\"@en)\n\n;; Data Properties\n(AnnotationAssertion dcterms:identifier :R3Corda \"BC-0437\"^^xsd:string)\n```\n\n- ## About R3 Corda\n  id:: r3-corda-about\n\n  - R3 Corda represents a fundamentally different approach to [[distributed ledger]] technology, purpose-built for the financial services industry rather than adapted from general-purpose blockchain architectures. Developed by R3, a consortium initially comprising over 200 financial institutions including Barclays, HSBC, Goldman Sachs, and UBS, Corda emerged from the recognition that traditional blockchain architectures, with their global state replication and proof-of-work [[consensus mechanisms]], were fundamentally unsuitable for regulated financial markets. Unlike public blockchains where all participants maintain complete ledger copies, Corda implements a \"need-to-know\" architecture wherein transaction data is shared only amongst parties with legitimate business need, addressing privacy requirements critical to financial institutions whilst maintaining the benefits of [[distributed ledger]] technology. The platform distinguishes itself through its explicit legal framework integration, modelling [[smart contracts]] as legally enforceable agreements between identified parties rather than anonymous code execution. Corda's architecture eliminates the concept of global state, instead representing the ledger as a graph of individual facts (states) with cryptographically assured lineage, enabling financial institutions to transact with strict privacy guarantees whilst maintaining consensus on transaction validity. The platform's notary services provide uniqueness consensus—preventing double-spending without requiring all nodes to see transaction details—achieving both privacy and correctness. Since its inception, Corda has established itself as the leading distributed ledger platform for regulated financial markets, processing over £10 billion in tokenised real-world assets and enabling applications from cross-border payments to securities settlement, insurance, and trade finance. The platform's design reflects deep understanding of financial market requirements, regulatory constraints, and the need for interoperability with existing financial infrastructure, positioning it uniquely as the distributed ledger technology most aligned with traditional financial services whilst offering transformative efficiency gains.\n\n  - ### Technical Architecture\n    - #### State Objects and UTXO Model\n      - Corda's architecture diverges fundamentally from account-based models employed by platforms like [[Ethereum]], instead implementing an **Unspent Transaction Output (UTXO) model** similar to [[Bitcoin]] but with significant enhancements. The ledger comprises **state objects** representing portions of real-world contracts or entire contracts, with each state containing arbitrary data describing agreements, ownership, obligations, or facts. States are **immutable**—once created, they cannot be modified, only consumed (marked as historic) and replaced by new states through transactions.\n      - This model provides several advantages for financial applications. First, transaction validation is **local**—only parties to a transaction need to validate it, rather than the entire network, enabling massive scalability and privacy. Second, the UTXO model provides clear **provenance tracking**, with each state's complete history traced through consumption chains, critical for regulatory compliance and audit. Third, the immutability ensures **non-repudiation**—parties cannot later claim transactions didn't occur, as the cryptographic chain of states provides irrefutable evidence.\n      - States carry **constraints** defining valid state transitions, implemented as contract code (not to be confused with smart contracts, which in Corda terminology refer to the entire agreement). When a transaction proposes consuming input states and creating output states, the associated contract code executes, verifying the transition satisfies all constraints. For example, a cash state might specify that the sum of output amounts must equal input amounts (conservation of value), whilst an equity state might require specific corporate actions to authorise ownership transfer.\n    - #### CorDapps: Corda Distributed Applications\n      - **CorDapps** (Corda Distributed Applications) encapsulate all components necessary for a particular business application on Corda. A CorDapp comprises **contract code** (defining valid state transitions), **state definitions** (data structures representing agreements), **flow logic** (orchestrating transaction creation, collection of signatures, and ledger updates), and **APIs** (enabling external systems to interact with the application). CorDapps are developed using **Java** or **Kotlin**, leveraging the mature JVM ecosystem's extensive libraries, tooling, and developer familiarity.\n      - The **flow framework** is central to CorDapp design, providing structured mechanisms for multi-party transaction coordination. Flows implement business processes: gathering required data, constructing transactions, collecting counterparty signatures, sending transactions to notaries for uniqueness consensus, and distributing finalised transactions to relevant parties. The framework handles communication, serialisation, exception handling, and flow checkpointing (enabling long-running flows to survive node restarts), abstracting complex distributed systems challenges from application developers.\n      - CorDapps deploy to Corda nodes like plugins, with nodes potentially running multiple CorDapps serving different business functions. This modularity enables financial institutions to participate in various networks (trade finance, securities settlement, syndicated loans) using a single Corda deployment, reducing operational complexity and costs. The CorDapp isolation model ensures different applications cannot interfere with each other, whilst shared states enable interoperability—for example, a cash CorDapp providing payment capabilities used by trade finance and securities CorDapps.\n    - #### Notary Services and Consensus\n      - Corda's approach to **consensus** differs radically from traditional blockchain consensus mechanisms. Rather than requiring all network participants to agree on transaction ordering and validity, Corda separates these concerns. **Validity consensus** is achieved through parties to a transaction (and their designated validators) verifying the transaction satisfies all contract constraints. **Uniqueness consensus**—ensuring input states haven't been consumed in other transactions—is achieved through **notary services**.\n      - A **notary** is a network service (potentially clustered for high availability) that signs transactions after verifying that the proposed input states haven't been previously consumed. Crucially, notaries need not see transaction contents—they operate on state references (cryptographic hashes), preserving transaction privacy whilst preventing double-spending. Corda supports multiple notary types: **validating notaries** that verify transaction validity in addition to uniqueness (requiring transaction details), **non-validating notaries** that only check uniqueness (preserving privacy), and **custom notary implementations** supporting specific consensus algorithms (Raft, Byzantine fault-tolerant algorithms).\n      - This architecture enables **horizontal scalability**—as the network grows, additional notaries can be deployed to handle increased transaction throughput, with transactions routed to appropriate notaries based on the states being consumed. Different business networks can employ different notaries with consensus algorithms suited to their trust assumptions, from simpler crash fault-tolerant algorithms for consortia with strong mutual trust to Byzantine fault-tolerant algorithms for environments requiring resilience against malicious participants.\n    - #### Point-to-Point Architecture\n      - Unlike blockchain platforms broadcasting transactions network-wide, Corda implements **point-to-point communication** wherein transaction data flows only to parties with legitimate need. When a transaction is constructed, it is shared with counterparties for signature collection, sent to the notary for uniqueness verification, and then distributed only to transaction participants. This architecture directly addresses financial services privacy requirements—competitors need not see each other's transaction details, regulatory information remains confidential to appropriate parties, and sensitive business terms aren't exposed network-wide.\n      - The point-to-point model provides **data minimisation**—parties receive only states relevant to them, reducing storage requirements and regulatory liability associated with possessing others' confidential data. When disputes arise or regulatory disclosure is required, the involved parties possess complete transaction histories with cryptographic proof of validity, whilst uninvolved parties have no access to irrelevant confidential information. This architecture aligns with privacy regulations like GDPR, which mandate minimising data exposure and enabling data subject rights—challenging in systems with global state replication.\n    - #### Network Map and Identity\n      - Corda networks employ a **network map service** maintaining a registry of network participants, their identities, and network parameters. Unlike permissionless blockchains with pseudonymous addresses, Corda requires **strong identity**, with participants possessing X.509 certificates issued by a certificate authority. This ensures all counterparties are known legal entities, critical for legal enforceability of agreements and regulatory compliance.\n      - The **Identity Service** enables privacy-preserving identity management, allowing nodes to generate confidential identities for specific transactions whilst maintaining linkage to their verified legal identity. This capability supports scenarios requiring transaction anonymity amongst broader network participants whilst enabling counterparties to verify they're transacting with licensed, regulated entities. The certificate hierarchy enables regulatory oversight—regulators can be granted visibility into all transactions involving specific participants without those participants losing privacy vis-à-vis their competitors.\n\n  - ### Key Features and Capabilities\n    - #### Legal Agreement Integration\n      - Corda's most distinctive feature is explicit integration of **legal prose** with smart contract code. CorDapps can include legal contract templates defining parties' legal rights and obligations, with the code enforcing these obligations through automated execution. This design recognises that financial agreements exist in legal frameworks—code cannot replace legal contracts but can automate their execution and enforcement. The platform supports **Ricardian contracts**—machine-readable, legally binding agreements combining legal prose with executable code.\n      - This integration addresses a critical limitation of smart contract platforms: code may execute reliably, but without legal grounding, parties may dispute whether the code accurately reflects their agreement or whether code execution constitutes legally binding performance. Corda's approach ensures the legal agreement and its automated execution are intrinsically linked, reducing ambiguity and supporting dispute resolution through traditional legal mechanisms when necessary.\n    - #### Privacy and Confidentiality\n      - Corda provides **multi-layered privacy**: transaction-level privacy (only participants see transaction details), state-level privacy (states shared only with relevant parties), and identity privacy (confidential identities for specific transactions). The point-to-point architecture ensures competitors transacting via the same network never see each other's business, whilst the notary uniqueness service prevents double-spending without exposing transaction contents.\n      - **Hierarchical disclosure** enables selective revelation of transaction details to regulators or auditors without broader network exposure. Parties can prove transaction validity to third parties by sharing the transaction and its input chain without revealing unrelated transactions. This capability supports regulatory reporting requirements whilst maintaining business confidentiality, addressing a fundamental tension in financial services blockchain adoption.\n    - #### Interoperability with Existing Systems\n      - Corda prioritises **integration** with existing financial infrastructure. The JVM-based architecture enables straightforward integration with enterprise Java applications, whilst extensive APIs support connectivity with databases, messaging systems, and legacy applications. CorDapps can interact with existing systems through standard integration patterns, enabling gradual migration rather than requiring disruptive replacement of functioning infrastructure.\n      - The platform supports **database integration**, allowing Corda vaults (the node's database storing states) to be queried using standard SQL, enabling existing business intelligence and reporting tools to analyse blockchain data without requiring blockchain-specific skills. This reduces adoption barriers, allowing financial institutions to leverage existing analytics infrastructure whilst benefiting from distributed ledger technology's transparency and automation.\n    - #### Time-Windowing and Scheduling\n      - Corda provides sophisticated **temporal capabilities** critical for financial instruments. Transactions can specify **time windows** during which they're valid, enabling precise coordination of time-sensitive operations like settlements that must occur during market hours. The platform supports **scheduled activities**—states can specify future times when particular flows should execute, enabling automated processing of events like bond coupon payments, loan instalments, or contract expirations.\n      - These capabilities reduce operational overhead for financial institutions, automating routine processes that traditionally required manual intervention. The distributed nature ensures automation occurs correctly even if individual nodes are unavailable, whilst the deterministic execution provides auditability and regulatory compliance.\n    - #### Attachments and Reference Data\n      - Corda supports **attachments**—arbitrary files (PDFs, spreadsheets, images) cryptographically linked to transactions. This enables supporting documentation (legal contracts, term sheets, prospectuses) to be distributed alongside transaction data, ensuring all parties possess identical document sets. The cryptographic linking prevents document tampering whilst maintaining clear audit trails.\n      - **Reference states** enable states to reference data without consuming it, supporting scenarios where multiple transactions need access to common reference information (exchange rates, pricing data, regulatory parameters). This capability reduces data duplication whilst ensuring all parties use consistent reference data, critical for financial calculations requiring precision and auditability.\n\n  - ### Industry Applications\n    - #### Cross-Border Payments and Settlement\n      - Multiple central banks and commercial banks employ Corda for **cross-border payment** initiatives. The **UK Regulated Liability Network (RLN)** project, involving Barclays, Citi, HSBC, Lloyds Banking Group, Mastercard, NatWest, Nationwide, Santander, Standard Chartered, Virgin Money, and Visa, utilises R3 technology to explore programmable payments and synchronised settlement. This initiative addresses inefficiencies in current cross-border payment systems, where transactions can take days and lack real-time visibility.\n      - The **Inthanon-LionRock** project between the Hong Kong Monetary Authority and Bank of Thailand demonstrated Corda's capability for central bank-to-central bank payments, achieving significant reductions in settlement time and cost compared to correspondent banking arrangements. The project established technical feasibility whilst identifying governance and operational considerations for multi-jurisdictional implementations, providing a blueprint for broader central bank adoption.\n    - #### Securities Settlement and Post-Trade Processing\n      - The **Depository Trust & Clearing Corporation (DTCC)**, the world's largest securities settlement organisation, selected R3 to develop its **Project Ion** platform, leveraging Corda to process bilateral equity transactions. The platform processes over 100,000 transactions daily, demonstrating Corda's capability to support institutional-scale operations with stringent performance, security, and regulatory requirements. DTCC's adoption provides significant validation of Corda's enterprise readiness and suitability for mission-critical financial infrastructure.\n      - **SIX Digital Exchange (SDX)**, the digital asset exchange operated by Switzerland's SIX Group, employs Corda for securities issuance, trading, and settlement. SDX represents one of the first fully regulated digital asset exchanges, supporting tokenised securities, cryptocurrencies, and other digital assets. The implementation demonstrates Corda's ability to support complex regulatory requirements whilst enabling new operating models for securities markets. Similarly, **Nasdaq** has integrated Corda into its Digital Asset Suite, enabling clients to issue and manage digital securities on distributed ledger infrastructure.\n    - #### Trade Finance and Letters of Credit\n      - Corda has seen extensive adoption in **trade finance**, where it addresses inefficiencies in letter of credit issuance, bill of lading management, and invoice financing. The platform enables digital representation of trade documents with cryptographic authenticity verification, reducing fraud whilst accelerating processing times from weeks to hours. Multiple banks have deployed Corda-based trade finance networks, enabling straight-through processing of transactions that traditionally required extensive manual document handling and verification.\n      - **Contour** (formerly Voltron), a Corda-based trade finance network, has onboarded major banks and corporations, processing real commercial transactions. The network demonstrates how distributed ledger technology can modernise trade finance, an industry sector still heavily reliant on paper documentation and manual processes, whilst maintaining legal compliance and addressing fraud concerns.\n    - #### Insurance and Reinsurance\n      - **B3i** (Blockchain Insurance Industry Initiative) developed a reinsurance solution on Corda, enabling insurance companies and reinsurers to exchange information and process claims more efficiently. The platform addresses inefficiencies in reinsurance markets, where complex contractual relationships and information asymmetries create operational overhead and delayed settlements. The Corda implementation enables automated data exchange, faster claim processing, and improved transparency whilst maintaining commercial confidentiality.\n      - **Insurwave**, involving Maersk, Microsoft, EY, and major marine insurers (MS Amlin, XL Catlin), built the world's first blockchain-based marine insurance platform on Corda. The system provides real-time visibility into insured assets (ships, cargo), automated risk assessment, and streamlined claims processing. By connecting insurers, brokers, and insureds on a shared platform, Insurwave reduces administrative costs whilst improving risk management and customer service.\n    - #### Syndicated Lending\n      - **Finastra** and **NatWest** developed a Corda-based platform for **syndicated lending**, addressing inefficiencies in loan syndication where multiple lenders participate in large corporate loans. Traditional syndication involves extensive manual coordination, document circulation, and reconciliation amongst participating banks. The Corda implementation automates much of this process, ensuring all participants maintain consistent views of loan terms, drawdown schedules, and repayment status whilst reducing operational risk and processing time.\n    - #### Tokenised Real-World Assets\n      - R3 reported in February 2025 that Corda hosts **over £10 billion in tokenised real-world assets** across live networks, with over 1 million transactions processed daily. This includes tokenised securities, bonds, commodities, and other financial instruments. The platform's emphasis on regulatory compliance, legal integration, and privacy makes it particularly suitable for asset tokenisation in regulated markets, where [[Ethereum]]-based platforms face challenges meeting financial services regulatory requirements.\n\n  - ### Standards and Governance\n    - #### R3 Governance and Consortium Model\n      - R3 operates as a **private company** backed by a consortium of financial institutions, technology companies, and investors. Unlike open-source projects governed by foundations ([[Hyperledger]] projects, for example), R3 maintains commercial control over Corda's development direction, though the platform itself is **open source** under the Apache 2.0 licence. This hybrid model provides financial sustainability through R3's commercial offerings (Corda Enterprise, support services, training) whilst enabling community participation and third-party innovation.\n      - The consortium model ensures Corda's roadmap reflects financial services industry requirements, with major banks and financial institutions influencing development priorities. This industry-driven approach contrasts with technology-first platforms that may develop features misaligned with financial market needs. However, it also means adoption outside financial services has been more limited, as the platform's design assumptions strongly reflect its target industry.\n    - #### Corda Open Source and Corda Enterprise\n      - R3 maintains two Corda distributions: **Corda Open Source** and **Corda Enterprise**. The open-source version provides core functionality suitable for development, testing, and smaller production deployments, enabling organisations to experiment with distributed ledger technology without licensing costs. Corda Enterprise adds enterprise-grade features: enhanced performance through database optimisation, high-availability configurations, advanced monitoring and management tools, disaster recovery capabilities, and commercial support with service level agreements.\n      - This dual-licensing model balances open innovation with sustainable business development. Financial institutions requiring mission-critical reliability, performance guarantees, and vendor support typically deploy Corda Enterprise, whilst CorDapp developers, researchers, and organisations exploring distributed ledger technology can utilise the open-source version. The compatibility between versions enables applications developed on open source to deploy on Enterprise with minimal modifications.\n    - #### Standards Alignment\n      - Corda aligns with various financial industry standards and regulatory frameworks. The platform's architecture supports compliance with **MiFID II** (Markets in Financial Instruments Directive), **GDPR** (General Data Protection Regulation), and other European financial regulations, whilst accommodating US regulatory requirements from the SEC, CFTC, and OCC. R3 actively participates in standards bodies including the **International Swaps and Derivatives Association (ISDA)**, the **Digital Dollar Project**, and various national blockchain and digital asset initiatives.\n      - The company contributes to **ISO technical committees** developing blockchain and distributed ledger technology standards, ensuring Corda's architecture and capabilities inform emerging international standards. This standards engagement positions Corda favourably as regulatory frameworks evolve and standardised approaches to digital assets emerge.\n\n  - ### Comparison with Alternatives\n    - #### R3 Corda vs Hyperledger Fabric\n      - [[Hyperledger Fabric]] and R3 Corda both target enterprise use cases but differ significantly in design philosophy and optimal applications. Fabric emphasises **modularity** and **cross-industry applicability**, supporting diverse consensus algorithms, multiple programming languages, and flexible network topologies. Its channel architecture enables complex privacy arrangements with fine-grained control over data sharing. Fabric excels in multi-organisation supply chains, consortia with diverse participants, and scenarios requiring pluggable components.\n      - Corda, conversely, optimises specifically for **financial services**, with architecture reflecting this focus. Its point-to-point communication provides stronger privacy than Fabric's channel-based approach for bilateral transactions, whilst its legal framework integration addresses financial services' regulatory requirements more directly. Fabric's chaincode (smart contracts) supports general-purpose logic in multiple languages, whilst Corda's contract code focuses on validating state transitions using JVM languages. Fabric requires more complex infrastructure setup (peers, orderers, certificate authorities, channels), whilst Corda's simpler node architecture reduces operational complexity for financial applications.\n      - **When to use Corda**: Financial instruments, regulated markets, scenarios requiring legal enforceability integration, bilateral privacy between competitors, applications modelling contracts and ownership.\n      - **When to use Fabric**: Multi-organisation supply chains, cross-industry consortia, scenarios requiring pluggable consensus, applications needing multiple programming languages, use cases prioritising flexibility over financial services optimisation.\n    - #### R3 Corda vs Quorum Blockchain\n      - [[Quorum Blockchain]], the enterprise Ethereum variant originally developed by JPMorgan Chase, shares Corda's financial services focus but takes a different architectural approach. Quorum provides **Ethereum compatibility**, enabling Solidity smart contracts and Ethereum tooling to be used in permissioned environments, offering continuity for organisations familiar with Ethereum. Its privacy mechanisms (Tessera private transaction manager) enable confidential transactions whilst maintaining Ethereum's account model and EVM execution environment.\n      - Corda's UTXO model provides clearer **asset provenance** and **regulatory auditability** than account-based models, advantages for applications tracking securities, commodities, or other regulated assets. Corda's notary services offer more flexible consensus than Quorum's adapted Ethereum consensus mechanisms, supporting multiple consensus algorithms optimised for different trust assumptions. Quorum's Ethereum compatibility provides access to a larger developer ecosystem and more extensive tooling, whilst Corda's purpose-built architecture better serves applications requiring legal integration and bilateral privacy.\n      - **When to use Corda**: Complex financial instruments, scenarios requiring legal contract integration, applications prioritising bilateral privacy, use cases demanding flexible consensus with privacy.\n      - **When to use Quorum**: Organisations wanting Ethereum compatibility, scenarios leveraging existing Solidity contracts, applications benefiting from Ethereum tooling, use cases requiring general-purpose smart contracts with privacy.\n    - #### R3 Corda vs Ethereum\n      - Public [[Ethereum]] and Corda serve fundamentally different purposes. Ethereum provides a **permissionless**, **censorship-resistant** platform for decentralised applications, with global state replication and proof-of-stake consensus. Its Turing-complete smart contract capabilities enable arbitrary application logic, whilst its large ecosystem provides extensive tooling, libraries, and developer resources. However, Ethereum's transparency, public accessibility, and pseudonymous transactions make it unsuitable for many financial services applications requiring confidentiality, known counterparties, and regulatory compliance.\n      - Corda addresses these limitations through **permissioned access**, **identity verification**, and **selective disclosure**, making it suitable for regulated financial markets. Its legal framework integration and focus on modelling agreements between identified parties align with financial services requirements in ways Ethereum's trustless, permissionless design cannot. However, Ethereum's larger ecosystem, more extensive documentation, and broader applicability provide advantages for decentralised applications not requiring Corda's financial services optimisations.\n      - **When to use Corda**: Regulated financial services, applications requiring known counterparties, scenarios demanding legal enforceability, use cases prioritising privacy between competitors.\n      - **When to use Ethereum**: Decentralised applications, scenarios requiring censorship resistance, applications benefiting from large ecosystem and tooling, use cases where transparency and permissionless access are desired.\n\n  - ### Implementation Considerations\n    - #### Technical Requirements\n      - Deploying Corda requires more substantial infrastructure than lightweight frameworks like [[Hyperledger Iroha]] but less complex multi-component architectures than [[Hyperledger Fabric]]. A typical production Corda node requires **4-8 CPU cores**, **16-32 GB RAM**, and **500 GB-2 TB storage** depending on transaction volume and state retention requirements. Enterprise deployments often include **high-availability configurations** with clustered nodes and database replication.\n      - The **notary service** requires dedicated infrastructure, with production deployments typically employing **highly available notary clusters** using Raft or BFT consensus. A minimal notary cluster comprises three nodes, though larger deployments may employ five or seven nodes for increased resilience. Each notary node requires specifications similar to regular nodes, with performance characteristics depending on expected transaction throughput.\n      - **Database infrastructure** is critical—Corda supports PostgreSQL, SQL Server, and Oracle databases, with enterprise deployments requiring database clustering, replication, and automated failover. The vault database stores all states relevant to the node, requiring careful capacity planning based on expected transaction volume and data retention policies. Network infrastructure must support TLS-encrypted communication between nodes, with appropriate firewall configuration and, for Internet-based networks, DDoS protection.\n      - **Development environments** can operate on modest hardware—laptops or development servers with 8 GB RAM and 4 cores suffice for CorDapp development and testing. Corda provides Docker containers and cloud templates simplifying environment setup, whilst the comprehensive SDK supports IntelliJ IDEA, Eclipse, and other JVM development environments.\n    - #### Costs and Investment\n      - Infrastructure costs for Corda deployments vary significantly based on deployment scale and whether open source or Enterprise editions are employed. A single-node Corda deployment for development or proof-of-concept can run on cloud infrastructure for **£200-£400 monthly**. Production deployments with high availability, clustered notaries, and enterprise databases typically cost **£5,000-£12,000 monthly** for infrastructure, depending on transaction volume, availability requirements, and whether dedicated or shared notary services are employed.\n      - **Corda Enterprise licensing** involves upfront and annual subscription costs. Whilst R3 doesn't publicly publish pricing, industry reports suggest Enterprise licences range from **£50,000-£200,000 annually per node** depending on transaction volume, support level, and negotiated terms. This positions Corda at the higher end of enterprise blockchain platform costs, reflecting its focus on mission-critical financial infrastructure. For organisations using Corda Open Source, these licensing costs are eliminated, though commercial support is unavailable.\n      - **Development costs** for CorDapps depend on application complexity and team experience. Simple applications (basic asset transfer, simple workflows) might require **3-6 months** with teams of 3-5 developers, costing **£150,000-£400,000** including architecture, development, testing, and deployment. Complex financial applications (sophisticated derivatives, multi-party workflows, regulatory reporting integration) can require **12-24 months** and **£1,000,000-£3,000,000+** investment, particularly when including business analysis, legal review, regulatory approval, and production deployment.\n      - **Operational costs** for enterprise Corda deployments include infrastructure management, security monitoring, database administration, network operations, and ongoing CorDapp maintenance. Organisations should budget **£150,000-£400,000 annually** for dedicated operational teams, or **£200,000-£600,000+ annually** for managed services from R3 or certified partners, depending on deployment scale and service level requirements.\n    - #### Deployment Timelines\n      - **Proof-of-concept** deployments demonstrating basic Corda capabilities and specific use case feasibility typically require **8-12 weeks**, including requirements gathering, CorDapp design, development, and demonstration. Financial institutions often conduct multiple proof-of-concept projects exploring different use cases before committing to production deployment.\n      - **Pilot deployments** with limited production traffic and controlled user groups typically require **6-9 months**, including detailed CorDapp development, integration with existing systems (identity providers, databases, core banking systems), security reviews, and operational procedure development. Financial services organisations must coordinate with compliance, risk, and legal teams, extending timelines compared to less regulated industries.\n      - **Full production deployments** supporting critical financial processes generally require **12-24 months** from project initiation to go-live, accounting for comprehensive requirements analysis, multi-party governance agreement, detailed architecture and design, development, extensive security and performance testing, regulatory review and approval (when required), operational team training, and phased rollout. Multi-organisation deployments (consortium networks) require additional time for governance framework development, legal agreements amongst participants, and coordinated deployment across institutions.\n\n  - ### Major Implementations\n    - #### DTCC Project Ion\n      - The **Depository Trust & Clearing Corporation**, processing the majority of US securities transactions, selected R3 to develop its **Project Ion** platform using Corda. The platform processes **over 100,000 bilateral equity transactions daily**, representing one of the largest production blockchain deployments globally. DTCC's adoption validates Corda's capability to support institutional-scale operations with mission-critical reliability requirements. The implementation demonstrates Corda's performance, security, and regulatory compliance capabilities in the world's largest securities market, providing a reference implementation for other clearinghouses and settlement systems considering distributed ledger technology adoption.\n    - #### UK Regulated Liability Network\n      - The **UK Regulated Liability Network (RLN)** project represents a collaboration between major UK banks (Barclays, HSBC, Lloyds Banking Group, NatWest, Nationwide, Santander, Standard Chartered, Virgin Money), payment networks (Mastercard, Visa), international banks (Citi), and the Bank of England, utilising R3 technology to explore programmable money and synchronised settlement. The initiative investigates how distributed ledger technology can enable new forms of money supporting programmable payments, conditional settlement, and delivery-versus-payment for digital assets. The project demonstrates central bank interest in distributed ledger technology whilst exploring how commercial bank money can interoperate with central bank digital currencies on shared infrastructure.\n    - #### SIX Digital Exchange\n      - **SIX Digital Exchange (SDX)**, operated by Switzerland's SIX Group (operator of the Swiss Stock Exchange), represents one of the first fully regulated digital asset exchanges globally. SDX utilises Corda for securities issuance, trading, settlement, and custody, providing end-to-end lifecycle management for tokenised securities. The platform supports both digital-native securities and tokenised representations of traditional securities, enabling new issuance models whilst maintaining compatibility with existing market infrastructure. Switzerland's supportive regulatory environment and SIX's established market position provide SDX with significant advantages, whilst the Corda implementation demonstrates the platform's suitability for regulated securities markets.\n    - #### Contour - Trade Finance Network\n      - **Contour** (formerly Voltron), a Corda-based trade finance network, has onboarded major global banks including HSBC, Standard Chartered, ING, Bangkok Bank, and BNP Paribas, along with corporate participants. The network digitises letters of credit and other trade finance instruments, reducing issuance time from 5-10 days to under 24 hours whilst reducing fraud risk through cryptographic document verification. Real commercial transactions, including multi-million-pound letters of credit, have been processed through the network, demonstrating production readiness and business value. The implementation showcases Corda's ability to modernise paper-intensive financial processes whilst maintaining legal validity and regulatory compliance.\n    - #### Insurwave - Marine Insurance Platform\n      - **Insurwave**, the world's first blockchain-based marine insurance platform, involves major participants including Maersk (the world's largest container shipping company), Microsoft, EY, and leading marine insurers MS Amlin and XL Catlin. The Corda-based platform provides real-time visibility into insured vessels and cargo, automated risk assessment, and streamlined claims processing. By connecting insurers, brokers, and insureds on a shared platform with consistent data, Insurwave reduces administrative overhead whilst improving risk management. The platform has achieved significant adoption in marine insurance, an industry sector worth tens of billions of pounds annually, demonstrating blockchain's applicability to complex, multi-party insurance scenarios.\n    - #### Inthanon-LionRock - Central Bank Cross-Border Payments\n      - The **Inthanon-LionRock** project between the Hong Kong Monetary Authority and Bank of Thailand demonstrated Corda's capability for **central bank-to-central bank cross-border payments**. The initiative explored multi-jurisdictional central bank digital currency implementation, achieving significant reductions in settlement time and cost compared to correspondent banking. Whilst not yet in production, the successful proof-of-concept establishes technical feasibility whilst identifying governance, operational, and policy considerations for broader implementation. The project positions Corda as infrastructure for future central bank digital currency networks enabling efficient cross-border settlement.\n\n  - ### Challenges and Limitations\n    - #### Limited Cross-Industry Adoption\n      - Corda's explicit optimisation for financial services, whilst a strength in that sector, limits adoption elsewhere. Industries with different requirements—supply chain management preferring channel-based privacy ([[Hyperledger Fabric]]), consumer applications requiring mobile optimisation ([[Hyperledger Iroha]]), or decentralised applications requiring permissionless access ([[Ethereum]])—often find Corda's architecture misaligned with their needs. The JVM-based platform, legal framework integration, and financial services terminology create adoption barriers for organisations outside finance.\n    - #### Complexity and Learning Curve\n      - Whilst simpler than some enterprise blockchain platforms, Corda presents a significant learning curve for developers unfamiliar with distributed ledger concepts, JVM development, or financial services domain knowledge. The platform's distinctive architecture (UTXO model, notaries, flows, state objects) requires conceptual shifts from traditional application development. Documentation, whilst extensive, assumes significant technical sophistication, and the smaller community compared to [[Ethereum]] means fewer tutorials, troubleshooting resources, and community support channels are available.\n    - #### Ecosystem Maturity\n      - Compared to [[Ethereum]]'s extensive tooling ecosystem, Corda has fewer third-party development tools, libraries, and integrations. Whilst R3 and the community provide essential tooling (SDKs, test frameworks, deployment tools), organisations may need to build custom integrations with enterprise systems, monitoring platforms, and analytics tools. The smaller developer community means fewer pre-built CorDapps and less reusable code, requiring more custom development than platforms with larger ecosystems.\n    - #### Cost and Commercial Model\n      - Corda Enterprise's licensing costs, whilst justified for mission-critical financial infrastructure, create barriers for smaller organisations, startups, and non-financial use cases with limited budgets. The commercial model contrasts with fully open-source platforms ([[Hyperledger Fabric]], [[Hyperledger Iroha]]) where all features are freely available. Whilst Corda Open Source exists, production financial institutions typically require Enterprise's enhanced performance, availability, and support, creating vendor dependency on R3.\n\n  - ### Future Directions\n    - #### Corda 5 and Next-Generation Architecture\n      - R3 is developing **Corda 5**, a major architectural evolution introducing modularity improvements, enhanced performance, and operational enhancements. The next-generation platform adopts a more microservices-oriented architecture, enabling organisations to deploy and scale components independently based on their requirements. Performance optimisations target increased transaction throughput and reduced latency, addressing scalability requirements for high-volume financial markets. Enhanced operational tooling simplifies deployment, monitoring, and management, reducing the operational expertise required for production deployments.\n    - #### Interoperability and Cross-Chain Integration\n      - R3 is investing in **interoperability** capabilities enabling Corda networks to interact with other blockchain platforms, legacy financial systems, and emerging digital asset infrastructure. This includes cross-chain asset transfers, shared identity schemes, and integration with central bank digital currency platforms. As financial institutions deploy multiple blockchain networks for different purposes, interoperability becomes critical, and Corda's roadmap reflects this requirement. The platform's legal framework and identity model position it favourably for compliance-preserving interoperability, where cross-chain transfers must maintain regulatory compliance and auditability.\n    - #### Central Bank Digital Currency Infrastructure\n      - Multiple central banks are exploring or piloting [[Central Bank Digital Currency]] implementations, and R3 is positioning Corda as infrastructure for these initiatives. The platform's privacy model (enabling central banks to maintain oversight whilst preserving commercial confidentiality), legal integration (ensuring digital currency has clear legal status), and proven scalability make it suitable for CBDC applications. The UK RLN project and various national CBDC experiments provide reference implementations, whilst R3's partnerships with central banks position it favourably as CBDC adoption accelerates.\n    - #### Tokenised Asset Expansion\n      - With over £10 billion in tokenised real-world assets already on Corda networks, R3 sees significant growth opportunity in asset tokenisation. This includes traditional securities (equities, bonds), alternative assets (real estate, commodities, fine art), and novel asset classes enabled by tokenisation (fractional ownership, programmable assets). Regulatory clarity in jurisdictions like Switzerland, Singapore, and the UK facilitates tokenisation, whilst Corda's compliance-focused architecture positions it as the platform of choice for regulated asset tokenisation. R3 is developing standardised CorDapps for common asset classes, reducing time-to-market for tokenisation projects.\n    - #### Enhanced Privacy and Confidential Computing\n      - Future Corda versions are exploring integration with **confidential computing** technologies (trusted execution environments, secure enclaves) to enable computation on encrypted data. This would allow notaries and validators to provide services without accessing plaintext data, further enhancing privacy whilst maintaining security guarantees. Integration with **zero-knowledge proof** systems could enable privacy-preserving regulatory compliance, where institutions prove regulatory compliance without revealing underlying transaction details—a capability with significant implications for financial privacy and regulatory reporting.\n\n  - #\n\n## Current Landscape (2025)\n\n- Industry adoption and implementations\n  - Metaverse platforms continue to evolve with focus on interoperability and open standards\n  - Web3 integration accelerating with decentralised identity and asset ownership\n  - Enterprise adoption growing in virtual collaboration, training, and digital twins\n  - UK companies increasingly active in metaverse development and immersive technologies\n\n- Technical capabilities\n  - Real-time rendering at photorealistic quality levels\n  - Low-latency networking enabling seamless multi-user experiences\n  - AI-driven content generation and procedural world building\n  - Spatial audio and haptics enhancing immersion\n\n- UK and North England context\n  - Manchester: Digital Innovation Factory supports metaverse startups and research\n  - Leeds: Holovis leads in immersive experiences for entertainment and training\n  - Newcastle: University research in spatial computing and interactive systems\n  - Sheffield: Advanced manufacturing using digital twin technology\n\n- Standards and frameworks\n  - Metaverse Standards Forum driving interoperability protocols\n  - WebXR enabling browser-based immersive experiences\n  - glTF and USD for 3D asset interchange\n  - Open Metaverse Interoperability Group defining cross-platform standards\n\n## Metadata\n\n- **Last Updated**: 2025-11-16\n- **Review Status**: Automated remediation with 2025 context\n- **Verification**: Academic sources verified\n- **Regional Context**: UK/North England where applicable\n\n\n## References and Further Reading\n    - [[Distributed Ledger]] - Underlying technology category\n    - [[Hyperledger Fabric]] - Alternative enterprise blockchain framework\n    - [[Quorum Blockchain]] - Enterprise Ethereum variant with financial services focus\n    - [[Ethereum]] - General-purpose smart contract platform\n    - [[Hyperledger Iroha]] - Mobile-optimised enterprise blockchain\n    - [[Smart Contracts]] - Programmable agreements and automated execution\n    - [[Byzantine Fault Tolerance]] - Consensus mechanism resilience property\n    - [[Consensus Mechanisms]] - Distributed agreement protocols\n    - [[Central Bank Digital Currency]] - Major application domain\n    - [[Bitcoin]] - Original blockchain platform using UTXO model\n    - [[Hyperledger Besu]] - Ethereum-compatible enterprise blockchain\n    - [[Solidity]] - Ethereum smart contract language\n    - [[Proof of Work]] - Alternative consensus mechanism\n    - [[Proof of Stake]] - Alternative consensus mechanism\n    - [[Enterprise Smart Contracts]] - Business logic in permissioned environments",
  "properties": {
    "id": "bc-0437-r3-corda-ontology",
    "collapsed": "true",
    "- ontology": "true",
    "- term-id": "BC-0437",
    "- preferred-term": "R3 Corda",
    "- source-domain": "blockchain",
    "- status": "stub-needs-content",
    "- public-access": "true",
    "- content-status": "minimal-placeholder-requires-authoring",
    "- definition": "A component of the blockchain ecosystem.",
    "- maturity": "draft",
    "- owl:class": "bc:R3Corda",
    "- owl:physicality": "ConceptualEntity",
    "- owl:role": "Concept",
    "- belongsToDomain": "[[BlockchainDomain]]"
  },
  "backlinks": [],
  "wiki_links": [
    "Hyperledger",
    "Proof of Work",
    "smart contracts",
    "Enterprise Smart Contracts",
    "Quorum Blockchain",
    "consensus mechanisms",
    "Hyperledger Besu",
    "Central Bank Digital Currency",
    "Bitcoin",
    "Hyperledger Iroha",
    "Consensus Mechanisms",
    "Hyperledger Fabric",
    "Smart Contracts",
    "BlockchainDomain",
    "Proof of Stake",
    "distributed ledger",
    "Solidity",
    "Distributed Ledger",
    "Ethereum",
    "Byzantine Fault Tolerance"
  ],
  "ontology": {
    "term_id": "BC-0437",
    "preferred_term": "R3 Corda",
    "definition": "A component of the blockchain ecosystem.",
    "source_domain": "blockchain",
    "maturity_level": null,
    "authority_score": null
  }
}