{
  "title": "Block",
  "content": "- ### OntologyBlock\n  id:: block-ontology\n  collapsed:: true\n\n  - **Identification**\n    - public-access:: true\n    - ontology:: true\n    - term-id:: BC-0003\n    - preferred-term:: Block\n    - source-domain:: blockchain\n    - status:: complete\n    - version:: 1.0.0\n    - last-updated:: 2025-10-28\n\n  - **Definition**\n    - definition:: Fundamental unit containing transactions within blockchain systems, providing essential functionality for distributed ledger technology operations and properties.\n    - maturity:: mature\n    - source:: [[ISO/IEC 23257:2021]], [[IEEE 2418.1]], [[NIST NISTIR]]\n    - authority-score:: 1.0\n\n  - **Semantic Classification**\n    - owl:class:: bc:Block\n    - owl:physicality:: VirtualEntity\n    - owl:role:: Object\n    - owl:inferred-class:: bc:VirtualObject\n    - belongsToDomain:: [[BlockchainDomain]]\n\n  - #### OWL Restrictions\n    \n    \n\n  - #### Relationships\n    id:: relationships\n    - is-subclass-of:: [[Blockchain]]\n\n  - #### CrossDomainBridges\n    - bridges-to:: [[Distributeddatastructure]] via is-subclass-of\n    - bridges-from:: [[Bitcoin]] via has-part\n\n  -",
  "properties": {
    "id": "relationships",
    "collapsed": "true",
    "- public-access": "true",
    "- ontology": "true",
    "- term-id": "BC-0003",
    "- preferred-term": "Block",
    "- source-domain": "blockchain",
    "- status": "complete",
    "- version": "1.0.0",
    "- last-updated": "2025-10-28",
    "- definition": "Fundamental unit containing transactions within blockchain systems, providing essential functionality for distributed ledger technology operations and properties.",
    "- maturity": "mature",
    "- source": "[[ISO/IEC 23257:2021]], [[IEEE 2418.1]], [[NIST NISTIR]]",
    "- authority-score": "1.0",
    "- owl:class": "bc:Block",
    "- owl:physicality": "VirtualEntity",
    "- owl:role": "Object",
    "- owl:inferred-class": "bc:VirtualObject",
    "- belongsToDomain": "[[BlockchainDomain]]",
    "- is-subclass-of": "[[Blockchain]]",
    "- bridges-to": "[[Distributeddatastructure]] via is-subclass-of",
    "- bridges-from": "[[Bitcoin]] via has-part"
  },
  "backlinks": [],
  "wiki_links": [
    "IEEE 2418.1",
    "Distributeddatastructure",
    "Blockchain",
    "NIST NISTIR",
    "Bitcoin",
    "ISO/IEC 23257:2021",
    "BlockchainDomain"
  ],
  "ontology": {
    "term_id": "BC-0003",
    "preferred_term": "Block",
    "definition": "Fundamental unit containing transactions within blockchain systems, providing essential functionality for distributed ledger technology operations and properties.",
    "source_domain": "blockchain",
    "maturity_level": null,
    "authority_score": 1.0
  }
}