{
  "title": "Longest Chain Rule",
  "content": "- ### OntologyBlock\n  id:: longest-chain-rule-ontology\n  collapsed:: true\n\n  - **Identification**\n    - public-access:: true\n    - ontology:: true\n    - term-id:: BC-0059\n    - preferred-term:: Longest Chain Rule\n    - source-domain:: blockchain\n    - status:: complete\n    - version:: 1.0.0\n    - last-updated:: 2025-10-28\n\n  - **Definition**\n    - definition:: Chain selection mechanism within blockchain systems, providing essential functionality for distributed ledger technology operations and properties.\n    - maturity:: mature\n    - source:: [[ISO/IEC 23257:2021]], [[IEEE 2418.1]], [[NIST NISTIR]]\n    - authority-score:: 0.95\n\n  - **Semantic Classification**\n    - owl:class:: bc:LongestChainRule\n    - owl:physicality:: VirtualEntity\n    - owl:role:: Object\n    - owl:inferred-class:: bc:VirtualObject\n    - belongsToDomain:: [[ConsensusDomain]]\n    - implementedInLayer:: [[ProtocolLayer]]\n\n  - #### Relationships\n    id:: longest-chain-rule-relationships\n    - is-subclass-of:: [[Blockchain Entity]], [[ConsensusProtocol]]\n\n  - #### OWL Axioms\n    id:: longest-chain-rule-owl-axioms\n    collapsed:: true\n    - ```clojure\n      Prefix(:=<http://metaverse-ontology.org/blockchain#>)\nPrefix(owl:=<http://www.w3.org/2002/07/owl#>)\nPrefix(rdf:=<http://www.w3.org/1999/02/22-rdf-syntax-ns#>)\nPrefix(xml:=<http://www.w3.org/XML/1998/namespace>)\nPrefix(xsd:=<http://www.w3.org/2001/XMLSchema#>)\nPrefix(rdfs:=<http://www.w3.org/2000/01/rdf-schema#>)\nPrefix(dct:=<http://purl.org/dc/terms/>)\n\nOntology(<http://metaverse-ontology.org/blockchain/BC-0059>\n  Import(<http://metaverse-ontology.org/blockchain/core>)\n\n  ## Class Declaration\n  Declaration(Class(:LongestChainRule))\n\n  ## Subclass Relationships\n  SubClassOf(:LongestChainRule :ConsensusProtocol)\n  SubClassOf(:LongestChainRule :BlockchainEntity)\n\n  ## Essential Properties\n  SubClassOf(:LongestChainRule\n    (ObjectSomeValuesFrom :partOf :Blockchain))\n\n  SubClassOf(:LongestChainRule\n    (ObjectSomeValuesFrom :hasProperty :Property))\n\n  ## Data Properties\n  DataPropertyAssertion(:hasIdentifier :LongestChainRule \"BC-0059\"^^xsd:string)\n  DataPropertyAssertion(:hasAuthorityScore :LongestChainRule \"1.0\"^^xsd:decimal)\n  DataPropertyAssertion(:isFoundational :LongestChainRule \"true\"^^xsd:boolean)\n\n  ## Object Properties\n  ObjectPropertyAssertion(:enablesFeature :LongestChainRule :BlockchainFeature)\n  ObjectPropertyAssertion(:relatesTo :LongestChainRule :RelatedConcept)\n\n  ## Annotations\n  AnnotationAssertion(rdfs:label :LongestChainRule \"Longest Chain Rule\"@en)\n  AnnotationAssertion(rdfs:comment :LongestChainRule\n    \"Chain selection mechanism\"@en)\n  AnnotationAssertion(dct:description :LongestChainRule\n    \"Foundational blockchain concept with formal ontological definition\"@en)\n  AnnotationAssertion(:termID :LongestChainRule \"BC-0059\")\n  AnnotationAssertion(:priority :LongestChainRule \"1\"^^xsd:integer)\n  AnnotationAssertion(:category :LongestChainRule \"consensus-fundamentals\"@en)\n)\n      ```\n\n- ## About Longest Chain Rule\n  id:: longest-chain-rule-about\n\n  - Chain selection mechanism within blockchain systems, providing essential functionality for distributed ledger technology operations and properties.\n  -\n  - ### Key Characteristics\n    id:: longest-chain-rule-characteristics\n    - 1. **Definitional Property**: Core defining characteristic\n    - 2. **Functional Property**: Operational behavior\n    - 3. **Structural Property**: Compositional elements\n    - 4. **Security Property**: Security guarantees provided\n    - 5. **Performance Property**: Efficiency considerations\n  -\n  - ### Technical Components\n    id:: longest-chain-rule-components\n    - **Implementation**: How concept is realized technically\n    - **Verification**: Methods for validating correctness\n    - **Interaction**: Relationships with other components\n    - **Constraints**: Technical limitations and requirements\n  -\n  - ### Use Cases\n    id:: longest-chain-rule-use-cases\n    - **1. Core Blockchain Operation**\n    - **Application**: Fundamental blockchain functionality\n    - **Example**: Practical implementation in major blockchains\n    - **Requirements**: Technical prerequisites\n    - **Benefits**: Value provided to blockchain systems\n  -\n  - ### Standards & References\n    id:: longest-chain-rule-standards\n    - [[ISO/IEC 23257:2021]] - Blockchain and distributed ledger technologies\n    - [[IEEE 2418.1]] - Blockchain and distributed ledger technologies\n    - [[NIST NISTIR]] - Blockchain and distributed ledger technologies\n  -",
  "properties": {
    "id": "longest-chain-rule-standards",
    "collapsed": "true",
    "- public-access": "true",
    "- ontology": "true",
    "- term-id": "BC-0059",
    "- preferred-term": "Longest Chain Rule",
    "- source-domain": "blockchain",
    "- status": "complete",
    "- version": "1.0.0",
    "- last-updated": "2025-10-28",
    "- definition": "Chain selection mechanism within blockchain systems, providing essential functionality for distributed ledger technology operations and properties.",
    "- maturity": "mature",
    "- source": "[[ISO/IEC 23257:2021]], [[IEEE 2418.1]], [[NIST NISTIR]]",
    "- authority-score": "0.95",
    "- owl:class": "bc:LongestChainRule",
    "- owl:physicality": "VirtualEntity",
    "- owl:role": "Object",
    "- owl:inferred-class": "bc:VirtualObject",
    "- belongsToDomain": "[[ConsensusDomain]]",
    "- implementedInLayer": "[[ProtocolLayer]]",
    "- is-subclass-of": "[[Blockchain Entity]], [[ConsensusProtocol]]"
  },
  "backlinks": [],
  "wiki_links": [
    "ConsensusDomain",
    "Blockchain Entity",
    "ISO/IEC 23257:2021",
    "NIST NISTIR",
    "ProtocolLayer",
    "IEEE 2418.1",
    "ConsensusProtocol"
  ],
  "ontology": {
    "term_id": "BC-0059",
    "preferred_term": "Longest Chain Rule",
    "definition": "Chain selection mechanism within blockchain systems, providing essential functionality for distributed ledger technology operations and properties.",
    "source_domain": "blockchain",
    "maturity_level": null,
    "authority_score": 0.95
  }
}