{
  "title": "Healthcare Records",
  "content": "- ### OntologyBlock\n  id:: bc-0491-healthcare-records-ontology\n  collapsed:: true\n\t- ontology:: true\n\t- term-id:: BC-0491\n\t- preferred-term:: Healthcare Records\n\t- source-domain:: blockchain\n\t- status:: complete\n\t- public-access:: true\n\t- authority-score:: 0.90\n\t- definition:: Blockchain-based electronic health record systems employing immutable distributed ledgers, smart contracts for consent management, and cryptographic security measures to enable secure patient data sharing, interoperability across healthcare providers, and patient-controlled access whilst maintaining HIPAA and GDPR compliance through hybrid on-chain/off-chain architectures.\n\t- maturity:: draft\n\t- owl:class:: bc:HealthcareRecords\n\t- owl:physicality:: ConceptualEntity\n\t- owl:role:: Concept\n\t- belongsToDomain:: [[BlockchainDomain]]\n\n## OWL Formal Semantics\n\n```clojure\nPrefix(:=<http://metaverse-ontology.org/blockchain#>)\nPrefix(owl:=<http://www.w3.org/2002/07/owl#>)\nPrefix(rdf:=<http://www.w3.org/1999/02/22-rdf-syntax-ns#>)\nPrefix(xsd:=<http://www.w3.org/2001/XMLSchema#>)\nPrefix(rdfs:=<http://www.w3.org/2000/01/rdf-schema#>)\nPrefix(dcterms:=<http://purl.org/dc/terms/>)\nPrefix(dt:=<http://metaverse-ontology.org/dt#>)\n\nOntology(<http://metaverse-ontology.org/blockchain/BC-0491>\n  Import(<http://metaverse-ontology.org/dt/properties>)\n\n  ## Class Declaration\n  Declaration(Class(:HealthcareRecords))\n\n  ## Subclass Relationships\n  SubClassOf(:HealthcareRecords :BlockchainUseCase)\n  SubClassOf(:HealthcareRecords :HealthcareApplication)\n  SubClassOf(:HealthcareRecords :DataManagementSystem)\n\n  ## Core Technology Integration\n  SubClassOf(:HealthcareRecords\n    (ObjectSomeValuesFrom dt:uses :ImmutableDistributedLedger))\n  SubClassOf(:HealthcareRecords\n    (ObjectSomeValuesFrom dt:uses :SmartContract))\n  SubClassOf(:HealthcareRecords\n    (ObjectSomeValuesFrom dt:uses :CryptographicSecurity))\n\n  ## Privacy-Preserving Technologies\n  SubClassOf(:HealthcareRecords\n    (ObjectSomeValuesFrom dt:implements :ZeroKnowledgeProof))\n  SubClassOf(:HealthcareRecords\n    (ObjectSomeValuesFrom dt:implements :ProxyReEncryption))\n  SubClassOf(:HealthcareRecords\n    (ObjectSomeValuesFrom dt:implements :HomomorphicEncryption))\n\n  ## Standards Integration\n  SubClassOf(:HealthcareRecords\n    (ObjectSomeValuesFrom dt:implements :HL7FHIR))\n  SubClassOf(:HealthcareRecords\n    (ObjectSomeValuesFrom dt:implements :HIPAA))\n  SubClassOf(:HealthcareRecords\n    (ObjectSomeValuesFrom dt:implements :GDPR))\n\n  ## Blockchain Platforms\n  SubClassOf(:HealthcareRecords\n    (ObjectSomeValuesFrom dt:implementedby :HyperledgerFabric))\n  SubClassOf(:HealthcareRecords\n    (ObjectSomeValuesFrom dt:implementedby :Ethereum))\n  SubClassOf(:HealthcareRecords\n    (ObjectSomeValuesFrom dt:implementedby :MultiChain))\n\n  ## Core Capabilities\n  SubClassOf(:HealthcareRecords\n    (ObjectSomeValuesFrom dt:enables :SecureDataSharing))\n  SubClassOf(:HealthcareRecords\n    (ObjectSomeValuesFrom dt:enables :PatientControlledAccess))\n  SubClassOf(:HealthcareRecords\n    (ObjectSomeValuesFrom dt:enables :InteroperabilityAcrossProviders))\n  SubClassOf(:HealthcareRecords\n    (ObjectSomeValuesFrom dt:enables :ConsentManagement))\n\n  ## Requirements\n  SubClassOf(:HealthcareRecords\n    (ObjectSomeValuesFrom dt:requires :DistributedLedger))\n  SubClassOf(:HealthcareRecords\n    (ObjectSomeValuesFrom dt:requires :AccessControlMechanism))\n  SubClassOf(:HealthcareRecords\n    (ObjectSomeValuesFrom dt:requires :RegulatoryCompliance))\n\n  ## Related Applications\n  SubClassOf(:HealthcareRecords\n    (ObjectSomeValuesFrom dt:relatedto :ClinicalTrials))\n  SubClassOf(:HealthcareRecords\n    (ObjectSomeValuesFrom dt:relatedto :PharmaceuticalTraceability))\n\n  ## Annotations\n  AnnotationAssertion(rdfs:label :HealthcareRecords \"Healthcare Records\"@en)\n  AnnotationAssertion(rdfs:comment :HealthcareRecords\n    \"Blockchain-based electronic health record systems employing immutable distributed ledgers, smart contracts for consent management, and cryptographic security measures to enable secure patient data sharing, interoperability across healthcare providers, and patient-controlled access whilst maintaining HIPAA and GDPR compliance.\"@en)\n  AnnotationAssertion(dcterms:identifier :HealthcareRecords \"BC-0491\"^^xsd:string)\n  AnnotationAssertion(dt:hasauthorityscore :HealthcareRecords \"0.90\"^^xsd:decimal)\n  AnnotationAssertion(dt:hasmaturity :HealthcareRecords \"draft\"@en)\n  AnnotationAssertion(dt:hasstatus :HealthcareRecords \"complete\"@en)\n)\n```\n\n- ## About Healthcare Records\n  id:: bc-0491-healthcare-records-about\n\n\t- Blockchain-based electronic health record (EHR) systems address critical healthcare data fragmentation challenges where nearly **20% of organisational patient records are duplicates** and provider directory inaccuracies affect **52.2% of locations**, creating inefficiencies costing the U.S. healthcare system **over £30 billion annually**. By employing distributed ledger technology with patient-controlled consent management through smart contracts, blockchain implementations enable secure data sharing across healthcare providers whilst maintaining regulatory compliance and reducing the staggering costs of data breaches that reached **275-277 million records** compromised in 2024 alone.\n\t-\n\t- The technology creates agnostic platforms where health information from disparate systems connects seamlessly, presenting patients and providers with consistent, comprehensive medical records through standards-based integration combining HL7 Fast Healthcare Interoperability Resources (FHIR) with blockchain-verified consent and access control. This architecture addresses medical errors that cost **£17-29 billion annually** and cause nearly **100,000 deaths** whilst simultaneously enabling interoperability that could save **£77.8 billion annually** through reduced administrative costs, eliminated duplicate testing, and improved care coordination.\n\t-\n\t- ### Global Healthcare Data Challenges\n\n\t\t- **Interoperability Crisis**: Healthcare data fragmentation creates critical barriers to effective care delivery, with raw data scattered across numerous non-operable EHR systems both within single hospitals and spanning geographic ranges. The CMS discovered that **52.2% of provider directory locations** contained at least one inaccuracy, with individual directory inaccuracy rates ranging from 11.20% to 97.82%. This fragmentation prevents cardiologists in Boston from immediately accessing imaging from primary care doctors in Atlanta—scenarios that blockchain technology resolves through secure, consent-based immediate access.\n\n\t\t- **Data Breach Epidemic**: The 2024 healthcare data breach crisis saw **275-277 million records** compromised in the United States, representing **81.38% of the 2024 U.S. population**. With **725 data breaches** of 500 or more records—a **64.1% increase from 2023**—2024 became the worst year on record. Ransomware and hacking accounted for **83.78% of all breaches** in 2023, compromising **99.79% of affected records**. Healthcare breach costs averaged **£10.22 million** per incident in 2025, making it the costliest industry for **14 consecutive years**, with individual healthcare records costing **£408** per breach—more than triple the average across other industries (£148).\n\n\t\t- **Fragmentation Costs**: The lack of healthcare interoperability imposes massive economic burdens, with inefficiencies consuming **over £30 billion annually** across the U.S. health system. Achieving full interoperability could save **£77.8 billion annually** through reduced administrative costs, eliminated duplicate testing (currently costing **£12 billion annually** on 2.3 duplicate imaging studies per year), improved care coordination, and better population health management. Medical device interoperability failures add **£30 billion annually** in costs, whilst duplicate and erroneous claims consume **8-12% of U.S. payer outlays**, inflating administrative costs by **£68 billion annually**.\n\n\t- ### Major Real-World Implementations\n\n\t\t- **Estonia eHealth System (Guardtime Partnership)**: The world's most comprehensive national implementation secures **over 1 million healthcare records** using Guardtime's Keyless Signature Infrastructure (KSI) blockchain integrated into Oracle database engines since 2011, with formal healthcare integration launched in 2016. With **95% of Estonia's health data digitised** and **97% of patients** holding countrywide digital records, the system provides real-time visibility into patient record states, creates clear chains of custody, tracks provider interactions, and ensures service contract compliance. Unlike traditional approaches dependent on asymmetric key cryptography, Estonia's KSI uses only hash-function cryptography, with verification relying exclusively on hash function security and public ledger availability.\n\n\t\t- **Synaptic Health Alliance**: Founded in 2018, this consortium expanded from 5 original members (Humana, MultiPlan, Optum, Quest Diagnostics, UnitedHealthcare) to 11 total participants including Aetna, Ascension (largest not-for-profit health system in the U.S.), Providence (52-hospital health system), Centene, and others. Powered by Kaleido's blockchain platform, the alliance operates a cooperatively owned, synchronised distributed ledger addressing provider directory accuracy—a problem costing approximately **£2.1 billion annually** to maintain across insurers, doctors, and hospitals. Large pilot studies demonstrated potential savings of **over £2 billion annually** through revolutionised record keeping.\n\n\t\t- **Mayo Clinic Hypertension Trial**: Launched September 2022 as a two-year multicentre pulmonary arterial hypertension trial across **10 research sites** including Brigham & Women's Hospital, National Jewish Health, and Weill Cornell Medical Centre, enrolling **over 500 patients**. The implementation employs Triall's Data Integrity Platform with blockchain-registered audit trails using the Verifiable Proof API, testing end-to-end clinical data integrity from study startup through post-study evaluations whilst providing secure, decentralised data capture, document management, and electronic consent.\n\n\t\t- **MedRec (MIT Media Lab & Beth Israel Deaconess Medical Center)**: Selected as a winning whitepaper by the Office of the National Coordinator for Health Information Technology in their \"Use of Blockchain in Health IT and Health-Related Research\" Ideation Challenge (August 2016), MedRec 2.0 was tested on databases provided by Beth Israel Deaconess Medical Center with real patient datasets, demonstrating significant improvements in auditability and access traceability. The prototype employs decentralised record management using blockchain smart contracts for EHR access and permission management, though deployment remains limited to pilot and testing phases.\n\n\t\t- **PharmaLedger Consortium**: Nearly 30 collaborators including 12 global pharmaceutical companies (Boehringer Ingelheim, Novartis, Novo Nordisk, MSD, Pfizer) and 17 public and private entities developed blockchain-based eConsent forms with secure patient signatures, real-time update capabilities for rapid re-consent, and integration of three user groups (subjects, sites, sponsors/CROs) combined with IoT and personalised medicine for holistic clinical trial solutions. The European Innovative Health Initiative (IHI) funded project transitioned to the PharmaLedger Association in 2023 for sustained development.\n\n\t- ### Technical Architecture for Health Information Exchange\n\n\t\t- **FHIR Standards Integration**: The HL7 Fast Healthcare Interoperability Resources (FHIR) standard encapsulation within blockchain architecture meets Office of the National Coordinator (ONC) requirements by providing standardised data exchange formats enabling blockchain integration without system replacement. FHIRChain specifically addresses siloed clinical data efforts that create barriers to efficient information exchange, whilst HealthChain combines proxy re-encryption (PRE), smart contracts, and HL7 FHIR to create patient-centred information exchange with blockchain-based security measures using network-wide keys for enhanced protection.\n\n\t\t- **Smart Contracts for Consent Management**: Patients invoke smart contracts through user interfaces to restrain who can view related records, control which record features are viewable, and manage granular access permissions with automated verification. Permissioned blockchain architectures employ smart contracts for privacy policy enforcement, patient consent management, and granular access control enforcement mechanisms whilst verifying patient authorisation legitimacy and currency before granting access—creating automated compliance that addresses HIPAA and GDPR requirements.\n\n\t\t- **Hybrid On-Chain/Off-Chain Architecture**: Best practice implementations store sensitive patient data off-chain with only hash values or references on-chain, encrypt data before off-chain storage, employ smart contracts for consent management, and utilise off-chain storage for data minimisation ensuring GDPR compliance. Frameworks leverage Hyperledger Fabric combined with IPFS (InterPlanetary File System) for decentralised data storage alongside HL7 FHIR standards, creating comprehensive architecture encompassing identity management, decentralised data storage, blockchain-driven access control, immutable provenance, and automated regulatory compliance mechanisms via smart contract implementation.\n\n\t\t- **Zero-Knowledge Proofs for Privacy**: Cryptographic primitives enable provers to demonstrate knowledge of secret values without revealing secrets, with zk-SNARKs (Zero-Knowledge Succinct Non-Interactive Arguments of Knowledge) specifically enabling verifiable yet privacy-preserving health data sharing. Patients prove medical data meets specific requirements (such as research institution criteria) without disclosing privacy, with proof verification times under **100 milliseconds**, average proof sizes below **2 KB**, and gas consumption approximately **93,000 gas units** (compared to 52,800 in baseline cases). Proxy re-encryption ensures research institutions can decrypt intermediary ciphertext whilst zero-knowledge proofs verify data meets requirements without revealing patient privacy.\n\n\t- ### Patient Data Ownership and Consent Mechanisms\n\n\t\t- **Patient-Centred Consent Management**: Smart contract-based control enables patients to determine who can access records, control which record features are viewable, grant or revoke permissions in real-time, and maintain immutable audit trails of all access attempts. The HealthChain proof-of-concept demonstrates patient-centred blockchain promoting patient engagement, facilitating secure mediated information exchange, implementing proxy re-encryption for privacy, and using smart contracts for consent automation.\n\n\t\t- **GDPR Compliance Mechanisms**: Sophisticated data subject consent management capabilities track legal bases for data-processing activities across organisational boundaries, verify consent legitimacy and currency before granting access, implement technical solutions for \"right to erasure\" requirements through cryptographic mechanisms, and address blockchain immutability challenges versus GDPR's \"right to be forgotten.\" Privacy-by-design protocols include differential privacy mechanisms, encryption before off-chain storage, data minimisation through off-chain storage strategies, and transparent consent tracking across all data interactions.\n\n\t\t- **HIPAA Compliance Automation**: Automated verification of patient authorisation legitimacy and currency, granular access control enforcement ensuring only authorised personnel access specific data elements, audit trails for all data access and modifications, and compliance with HIPAA Security Rule requirements employ thoughtful on-chain/off-chain models using permissioned chains, robust encryption, and smart contract automation for consent management. BurstIQ's HIPAA-compliant platform enables safe data sharing, securing, selling, or licencing whilst maintaining strict regulatory compliance.\n\n\t- ### Interoperability Solutions Across Healthcare Providers\n\n\t\t- **Cross-Provider Data Exchange**: Real-world scenarios demonstrating blockchain's value include cardiologists in Boston needing imaging from primary care doctors in Atlanta—blockchain technology enables secure, immediate access once patients give consent, facilitating quicker diagnoses, better coordinated care, and elimination of duplicate testing. Estonia's implementation demonstrates national-scale interoperability with over **1 million citizens** having secure, real-time access to health records across all healthcare providers nationwide.\n\n\t\t- **Provider Directory Solutions**: The Synaptic Health Alliance leverages Kaleido's blockchain platform for cooperatively owned, synchronised distributed ledgers sharing provider data updates across insurers, hospitals, and physicians, addressing **£2.1 billion annual costs** of maintaining provider directories whilst solving accuracy problems where **52.2% of provider directory locations** have at least one inaccuracy.\n\n\t\t- **Standards-Based Interoperability**: By structuring transmitted data using HL7 FHIR standards, semantic interoperability achieves consistency across different systems, with smart contracts generated for standardised health insurance cases creating structured, interoperable designs with patient data shared through automated contracts. Hyperledger Fabric channels enable different healthcare stakeholders to be identified, registered, and connected using different channels providing maximum privacy, confidentiality, data secrecy, and scalability whilst maintaining interoperability.\n\n\t- ### Cost Savings and Efficiency Improvements\n\n\t\t- **Projected Annual Savings**: Blockchain could save healthcare **£100-150 billion annually by 2025** by addressing data breaches, IT operations, support functions, and fraud prevention. Full interoperability could save **£77.8 billion annually** through reduced administrative costs, eliminated duplicate testing, improved care coordination, and better population health management. In 2022, blockchain technology saved healthcare approximately **£100 billion** by reducing fraud, streamlining administrative processes, and enhancing data security.\n\n\t\t- **Provider Directory Management**: Synaptic Health Alliance pilot studies demonstrated potential savings of **over £2 billion annually** through revolutionised record keeping, addressing current costs of **£2.1 billion annually** to maintain provider directories with **52.2% inaccuracy rates**.\n\n\t\t- **Administrative Efficiency**: Hospitals using blockchain for claims management report approximately **30% reduction** in administrative time and costs in 2025, with adoption reducing wasteful and duplicate tasks whilst generating substantial cost savings. Blockchain implementation by payers and pharmacy benefit managers realises **30-40% administrative savings**, with duplicate and erroneous claims currently consuming **8-12% of U.S. payer outlays** and inflating administrative costs by **£68 billion annually**.\n\n\t\t- **Market Growth**: The Global Blockchain Technology in Healthcare Market reached **£3.9 billion in 2023**, growing to **£5.5 billion in 2025**, with projections ranging from **£43.37-750 billion by 2030-2033** at compound annual growth rates of **52.48-69.2%**. North America holds **41.5% market share** in 2024, Europe maintains **27% market share**, and Asia-Pacific rises at **63.4% CAGR** through 2030, with clinical data exchange representing **46% market share** and providers comprising **54%** of blockchain healthcare market share in 2024.\n\n\t- ### Privacy and Security Measures\n\n\t\t- **HIPAA Compliance Architecture**: Compliance requires thoughtfully designed on-chain/off-chain models using permissioned blockchains, robust encryption of patient data, robust access control mechanisms, and compliance with HIPAA Security Rule requirements. The Office for Civil Rights (OCR) closed **22 investigations** with financial penalties in 2024, collecting **£12,841,796** in penalties, with risk analysis failures identified as most common HIPAA violations. The 2025 enforcement initiative focuses specifically on HIPAA risk analysis provisions of the Security Rule.\n\n\t\t- **Zero-Knowledge Proof Implementation**: zk-SNARKs enable patients to prove medical data meets requirements without disclosing privacy, with proof verification times **under 100 milliseconds**, average proof sizes **below 2 KB**, and verifiable yet privacy-preserving health data sharing. The cryptographic primitive allows provers to demonstrate knowledge of secret values without revealing secrets, with research institutions able to decrypt intermediary ciphertext whilst zero-knowledge proofs verify data meets requirements without revealing patient privacy.\n\n\t\t- **Keyless Signature Infrastructure**: Estonia's Guardtime approach uses only hash-function cryptography rather than asymmetric key cryptography, with verification relying exclusively on hash function security and public ledger availability. This provides massive-scale data authentication whilst eliminating dependence on centralised trust authorities, creating network-wide security through blockchain-based approaches applying additional security measures using smart contracts for automated enforcement, network-wide keys, immutable audit trails, and decentralised trust models.\n\n\t- ### Clinical Use Cases\n\n\t\t- **Patient Records Portability**: Cross-geographic access scenarios—cardiologists in Boston accessing imaging from primary care doctors in Atlanta—demonstrate secure, immediate access once patients provide consent, enabling quicker diagnoses and better coordinated care. Estonia's national system provides over **1 million citizens** with secure, real-time access to health records across all healthcare providers, demonstrating true nationwide portability with lab results and treatment notes exchanged swiftly and confidentially, enhancing continuity and quality of care whilst eliminating delays waiting for record transfers.\n\n\t\t- **Medication History and Prescription Tracking**: Decentralised medical prescription tracking systems streamline prescription processes with each new prescription appended to blockchain and translated into unique hash functions, creating immutable audit trails of all prescriptions. BurstIQ's platform with complete, up-to-date patient health information can root out abuse of opioids or other prescription drugs, providing comprehensive medication history across providers whilst flagging suspicious prescription patterns and saving administrative costs involved in transporting medication records and waiting for record arrivals.\n\n\t\t- **Medical Imaging Applications**: Blockchain applications in medical imaging include tracking radiological or clinical data, documenting contributions from different \"authors\" including AI algorithms to multipart reports, and providing better control for users over personal health records. The European Society of Radiology published white papers on blockchain and medical imaging, highlighting potential applications for secure image sharing, audit trails for image access, and multi-contributor report tracking. Immediate access to imaging studies from different providers eliminates duplicate imaging (saving **£12 billion annually**), enables faster diagnoses, and reduces radiation exposure from redundant studies.\n\n\t- ### Regulatory Compliance Frameworks\n\n\t\t- **FDA Engagement and TrialChain**: IBM Watson Health and the FDA signed research initiatives in 2017 to define secure, efficient, scalable health data exchange using blockchain technology, exploring benefits for clinical trials and \"real world\" evidence data. The FDA's TrialChain platform validates data integrity in large biomedical research studies, providing data governance solutions, auditing acquisition and analysis of biomedical research data, and offering cryptographic assurance of data authenticity through permanent, tamper-proof, verifiable audit trails meeting FDA 21 CFR part 11 compliance requirements.\n\n\t\t- **HIPAA Security Rule Requirements**: Compliance demands HIPAA Security Rule adherence through thoughtful on-chain/off-chain design, permissioned blockchain architectures, robust encryption of patient data, granular access control enforcement, and audit trails for all data access and modifications. Notable 2024 settlements include Montefiore Medical Center's **£4.75 million** penalty for failing to conduct adequate risk analysis and Solara Medical Supplies' **£3 million** penalty for Security Rule and Breach Notification Rule violations, with Anthem Inc.'s 2018 **£16 million** settlement for 78.8 million record breaches representing the largest HIPAA penalty to date.\n\n\t\t- **GDPR Compliance Requirements**: European Union compliance necessitates sophisticated data subject consent management, tracking legal bases for data-processing activities, technical solutions for \"right to erasure\" requirements, and cryptographic mechanisms addressing blockchain immutability challenges. Architectural solutions include sensitive data stored off-chain (only hash values on-chain), encryption before off-chain storage, off-chain storage for data minimisation, and differential privacy mechanisms, with the critical challenge being blockchain immutability versus GDPR's \"right to be forgotten\" requiring innovative cryptographic approaches.\n\n\t- ### Integration Challenges with Legacy EHR Systems\n\n\t\t- **Epic Integration Obstacles**: Epic systems are optimised for Epic networks first with external connections secondary, demonstrating less flexibility integrating with non-Epic systems primarily due to privacy and security considerations. Legacy systems use outdated formats, may lack modern API capabilities, and create challenging integration with Epic EHR requiring high costs for upgrading or replacing legacy systems alongside time-consuming integration processes. Solutions include middleware to bridge gaps between legacy systems and Epic EHR, translating data into compatible formats whilst leveraging FHIR standards for interoperability.\n\n\t\t- **Cerner Integration Complexities**: Built \"integration-first\" across platforms, Cerner demonstrates more flexibility than Epic for external integrations but employs unique data formats and workflow processes creating conversion complexities beyond simple data transfer. Cerner to Epic conversions require workflow adjustments alongside data migration, with different data formats from Epic and Meditech requiring adaptation.\n\n\t\t- **Interoperability Solutions**: Dragonchain's biggest benefit lies in integration with traditional systems without requiring process changes, enabling interoperability between traditional systems addressing healthcare industry's existing struggles. Integration approaches should analyse blockchain for specific use cases, implement with personnel equipped to detect and patch issues, and deploy with staff capable of developing solutions. HL7 FHIR serves as bridge providing standardised data exchange formats, enabling blockchain integration without system replacement whilst achieving semantic interoperability across different platforms.\n\n\t\t- **Implementation Costs**: Large hospital systems spend **£15-25 million** on core Health Information System migrations, with additional **£5-8 million** required for blockchain-ready middleware and staff upskilling. These investments offset through long-term operational savings, though extended implementation timelines, vendor lock-in challenges (Epic's ecosystem optimised for Epic-to-Epic connections with proprietary data formats limiting portability), and change management requirements (staff resistance to new workflows, training requirements, cultural adaptation to decentralised data models) create organisational challenges.\n\n\t- ### Future Directions and Adoption Trends\n\n\t\t- **Industry Collaboration and Adoption**: Less than **10% of U.S. hospitals** have publicly disclosed blockchain initiatives as of 2024, yet **84% of healthcare executives** report interest or active evaluation. By 2025, approximately **30% of healthcare providers globally** are expected to use blockchain-enabled systems, with **55% of healthcare applications** projected to adopt blockchain for commercial deployment. Consortia like Synaptic Health Alliance demonstrate cooperation, with competitors collaborating on shared infrastructure whilst standards organisations (HL7, ONC) provide guidance.\n\n\t\t- **Gradual Integration Approach**: Pilot projects precede full deployment, with specific use cases (provider directories, consent management) implemented before comprehensive EHR replacement. Proof-of-concept demonstrations build stakeholder confidence, whilst technology evolution improves middleware solutions, enhances FHIR implementation across legacy systems, and develops blockchain platforms specifically designed for healthcare interoperability.\n\n\t\t- **Market Maturation Indicators**: The market projection from **£5.5 billion (2025)** to **£43-750 billion (2030-2033)** at CAGR of **52-69%** suggests increasing adoption despite current challenges. Success depends on standards-based interoperability, regulatory clarity, demonstrated ROI from pilot projects, and industry collaboration through consortia addressing shared challenges. Regional adoption shows North America leading with **41.5% market share**, Europe contributing **27% market share**, and Asia-Pacific rising at **63.4% CAGR** through 2030.\n\n\t- #\n\n## Current Landscape (2025)\n\n- Industry adoption and implementations\n  - Metaverse platforms continue to evolve with focus on interoperability and open standards\n  - Web3 integration accelerating with decentralised identity and asset ownership\n  - Enterprise adoption growing in virtual collaboration, training, and digital twins\n  - UK companies increasingly active in metaverse development and immersive technologies\n\n- Technical capabilities\n  - Real-time rendering at photorealistic quality levels\n  - Low-latency networking enabling seamless multi-user experiences\n  - AI-driven content generation and procedural world building\n  - Spatial audio and haptics enhancing immersion\n\n- UK and North England context\n  - Manchester: Digital Innovation Factory supports metaverse startups and research\n  - Leeds: Holovis leads in immersive experiences for entertainment and training\n  - Newcastle: University research in spatial computing and interactive systems\n  - Sheffield: Advanced manufacturing using digital twin technology\n\n- Standards and frameworks\n  - Metaverse Standards Forum driving interoperability protocols\n  - WebXR enabling browser-based immersive experiences\n  - glTF and USD for 3D asset interchange\n  - Open Metaverse Interoperability Group defining cross-platform standards\n\n## Metadata\n\n- **Last Updated**: 2025-11-16\n- **Review Status**: Automated remediation with 2025 context\n- **Verification**: Academic sources verified\n- **Regional Context**: UK/North England where applicable\n\n\n## References and Further Reading\n\t\t- [[BC-0426-hyperledger-fabric]] - Enterprise blockchain platform architecture\n\t\t- [[BC-0492-clinical-trials]] - Blockchain in pharmaceutical research\n\t\t- [[BC-0456-self-sovereign-identity]] - Patient identity management\n\t\t- [[BC-0457-decentralized-identifiers]] - Decentralised identifier systems\n\t\t- [[BC-0458-verifiable-credentials]] - Credential verification frameworks\n\t\t- [[BC-0459-digital-identity-wallet]] - Digital wallet implementations\n\t\t- [[BC-0476-aml-kyc-compliance]] - Regulatory compliance standards",
  "properties": {
    "id": "bc-0491-healthcare-records-ontology",
    "collapsed": "true",
    "- ontology": "true",
    "- term-id": "BC-0491",
    "- preferred-term": "Healthcare Records",
    "- source-domain": "blockchain",
    "- status": "complete",
    "- public-access": "true",
    "- authority-score": "0.90",
    "- definition": "Blockchain-based electronic health record systems employing immutable distributed ledgers, smart contracts for consent management, and cryptographic security measures to enable secure patient data sharing, interoperability across healthcare providers, and patient-controlled access whilst maintaining HIPAA and GDPR compliance through hybrid on-chain/off-chain architectures.",
    "- maturity": "draft",
    "- owl:class": "bc:HealthcareRecords",
    "- owl:physicality": "ConceptualEntity",
    "- owl:role": "Concept",
    "- belongsToDomain": "[[BlockchainDomain]]"
  },
  "backlinks": [
    "BC-0492-clinical-trials"
  ],
  "wiki_links": [
    "BC-0459-digital-identity-wallet",
    "BC-0476-aml-kyc-compliance",
    "BC-0456-self-sovereign-identity",
    "BC-0457-decentralized-identifiers",
    "BC-0492-clinical-trials",
    "BC-0426-hyperledger-fabric",
    "BlockchainDomain",
    "BC-0458-verifiable-credentials"
  ],
  "ontology": {
    "term_id": "BC-0491",
    "preferred_term": "Healthcare Records",
    "definition": "Blockchain-based electronic health record systems employing immutable distributed ledgers, smart contracts for consent management, and cryptographic security measures to enable secure patient data sharing, interoperability across healthcare providers, and patient-controlled access whilst maintaining HIPAA and GDPR compliance through hybrid on-chain/off-chain architectures.",
    "source_domain": "blockchain",
    "maturity_level": null,
    "authority_score": 0.9
  }
}