{
  "title": "Selfish Mining",
  "content": "- ### OntologyBlock\n  id:: selfish-mining-ontology\n  collapsed:: true\n\n  - **Identification**\n    - public-access:: true\n    - ontology:: true\n    - term-id:: BC-0085\n    - preferred-term:: Selfish Mining\n    - source-domain:: blockchain\n    - status:: complete\n    - version:: 1.0.0\n    - last-updated:: 2025-10-28\n\n  - **Definition**\n    - definition:: Strategic block withholding within blockchain systems, providing essential functionality for distributed ledger technology operations and properties.\n    - maturity:: mature\n    - source:: [[ISO/IEC 23257:2021]], [[IEEE 2418.1]], [[NIST NISTIR]]\n    - authority-score:: 0.95\n\n  - **Semantic Classification**\n    - owl:class:: bc:SelfishMining\n    - owl:physicality:: VirtualEntity\n    - owl:role:: Object\n    - owl:inferred-class:: bc:VirtualObject\n    - belongsToDomain:: [[CryptographicDomain]]\n    - implementedInLayer:: [[SecurityLayer]]\n\n  - #### Relationships\n    id:: selfish-mining-relationships\n    - is-subclass-of:: [[Blockchain Entity]], [[NetworkComponent]]\n\n  - #### OWL Axioms\n    id:: selfish-mining-owl-axioms\n    collapsed:: true\n    - ```clojure\n      Prefix(:=<http://metaverse-ontology.org/blockchain#>)\nPrefix(owl:=<http://www.w3.org/2002/07/owl#>)\nPrefix(rdf:=<http://www.w3.org/1999/02/22-rdf-syntax-ns#>)\nPrefix(xml:=<http://www.w3.org/XML/1998/namespace>)\nPrefix(xsd:=<http://www.w3.org/2001/XMLSchema#>)\nPrefix(rdfs:=<http://www.w3.org/2000/01/rdf-schema#>)\nPrefix(dct:=<http://purl.org/dc/terms/>)\n\nOntology(<http://metaverse-ontology.org/blockchain/BC-0085>\n  Import(<http://metaverse-ontology.org/blockchain/core>)\n\n  ## Class Declaration\n  Declaration(Class(:SelfishMining))\n\n  ## Subclass Relationships\n  SubClassOf(:SelfishMining :NetworkComponent)\n  SubClassOf(:SelfishMining :BlockchainEntity)\n\n  ## Essential Properties\n  SubClassOf(:SelfishMining\n    (ObjectSomeValuesFrom :partOf :Blockchain))\n\n  SubClassOf(:SelfishMining\n    (ObjectSomeValuesFrom :hasProperty :Property))\n\n  ## Data Properties\n  DataPropertyAssertion(:hasIdentifier :SelfishMining \"BC-0085\"^^xsd:string)\n  DataPropertyAssertion(:hasAuthorityScore :SelfishMining \"1.0\"^^xsd:decimal)\n  DataPropertyAssertion(:isFoundational :SelfishMining \"true\"^^xsd:boolean)\n\n  ## Object Properties\n  ObjectPropertyAssertion(:enablesFeature :SelfishMining :BlockchainFeature)\n  ObjectPropertyAssertion(:relatesTo :SelfishMining :RelatedConcept)\n\n  ## Annotations\n  AnnotationAssertion(rdfs:label :SelfishMining \"Selfish Mining\"@en)\n  AnnotationAssertion(rdfs:comment :SelfishMining\n    \"Strategic block withholding\"@en)\n  AnnotationAssertion(dct:description :SelfishMining\n    \"Foundational blockchain concept with formal ontological definition\"@en)\n  AnnotationAssertion(:termID :SelfishMining \"BC-0085\")\n  AnnotationAssertion(:priority :SelfishMining \"1\"^^xsd:integer)\n  AnnotationAssertion(:category :SelfishMining \"network-security\"@en)\n)\n      ```",
  "properties": {
    "id": "selfish-mining-owl-axioms",
    "collapsed": "true",
    "- public-access": "true",
    "- ontology": "true",
    "- term-id": "BC-0085",
    "- preferred-term": "Selfish Mining",
    "- source-domain": "blockchain",
    "- status": "complete",
    "- version": "1.0.0",
    "- last-updated": "2025-10-28",
    "- definition": "Strategic block withholding within blockchain systems, providing essential functionality for distributed ledger technology operations and properties.",
    "- maturity": "mature",
    "- source": "[[ISO/IEC 23257:2021]], [[IEEE 2418.1]], [[NIST NISTIR]]",
    "- authority-score": "0.95",
    "- owl:class": "bc:SelfishMining",
    "- owl:physicality": "VirtualEntity",
    "- owl:role": "Object",
    "- owl:inferred-class": "bc:VirtualObject",
    "- belongsToDomain": "[[CryptographicDomain]]",
    "- implementedInLayer": "[[SecurityLayer]]",
    "- is-subclass-of": "[[Blockchain Entity]], [[NetworkComponent]]"
  },
  "backlinks": [],
  "wiki_links": [
    "NetworkComponent",
    "SecurityLayer",
    "CryptographicDomain",
    "Blockchain Entity",
    "IEEE 2418.1",
    "ISO/IEC 23257:2021",
    "NIST NISTIR"
  ],
  "ontology": {
    "term_id": "BC-0085",
    "preferred_term": "Selfish Mining",
    "definition": "Strategic block withholding within blockchain systems, providing essential functionality for distributed ledger technology operations and properties.",
    "source_domain": "blockchain",
    "maturity_level": null,
    "authority_score": 0.95
  }
}