{
  "title": "Blockchain Network",
  "content": "- ### OntologyBlock\n  id:: blockchain-network-ontology\n  collapsed:: true\n\n  - **Identification**\n    - public-access:: true\n    - ontology:: true\n    - term-id:: BC-0071\n    - preferred-term:: Blockchain Network\n    - source-domain:: blockchain\n    - status:: complete\n    - version:: 1.0.0\n    - last-updated:: 2025-10-28\n\n  - **Definition**\n    - definition:: Distributed node infrastructure within blockchain systems, providing essential functionality for distributed ledger technology operations and properties.\n    - maturity:: mature\n    - source:: [[ISO/IEC 23257:2021]], [[IEEE 2418.1]], [[NIST NISTIR]]\n    - authority-score:: 0.95\n\n  - **Semantic Classification**\n    - owl:class:: bc:BlockchainNetwork\n    - owl:physicality:: VirtualEntity\n    - owl:role:: Object\n    - owl:inferred-class:: bc:VirtualObject\n    - belongsToDomain:: [[CryptographicDomain]]\n    - implementedInLayer:: [[SecurityLayer]]\n\n  - #### Relationships\n    id:: blockchain-network-relationships\n    - is-subclass-of:: [[Blockchain Entity]], [[NetworkComponent]]\n\n  - #### OWL Axioms\n    id:: blockchain-network-owl-axioms\n    collapsed:: true\n    - ```clojure\n      Prefix(:=<http://metaverse-ontology.org/blockchain#>)\nPrefix(owl:=<http://www.w3.org/2002/07/owl#>)\nPrefix(rdf:=<http://www.w3.org/1999/02/22-rdf-syntax-ns#>)\nPrefix(xml:=<http://www.w3.org/XML/1998/namespace>)\nPrefix(xsd:=<http://www.w3.org/2001/XMLSchema#>)\nPrefix(rdfs:=<http://www.w3.org/2000/01/rdf-schema#>)\nPrefix(dct:=<http://purl.org/dc/terms/>)\n\nOntology(<http://metaverse-ontology.org/blockchain/BC-0071>\n  Import(<http://metaverse-ontology.org/blockchain/core>)\n\n  ## Class Declaration\n  Declaration(Class(:BlockchainNetwork))\n\n  ## Subclass Relationships\n  SubClassOf(:BlockchainNetwork :NetworkComponent)\n  SubClassOf(:BlockchainNetwork :BlockchainEntity)\n\n  ## Essential Properties\n  SubClassOf(:BlockchainNetwork\n    (ObjectSomeValuesFrom :partOf :Blockchain))\n\n  SubClassOf(:BlockchainNetwork\n    (ObjectSomeValuesFrom :hasProperty :Property))\n\n  ## Data Properties\n  DataPropertyAssertion(:hasIdentifier :BlockchainNetwork \"BC-0071\"^^xsd:string)\n  DataPropertyAssertion(:hasAuthorityScore :BlockchainNetwork \"1.0\"^^xsd:decimal)\n  DataPropertyAssertion(:isFoundational :BlockchainNetwork \"true\"^^xsd:boolean)\n\n  ## Object Properties\n  ObjectPropertyAssertion(:enablesFeature :BlockchainNetwork :BlockchainFeature)\n  ObjectPropertyAssertion(:relatesTo :BlockchainNetwork :RelatedConcept)\n\n  ## Annotations\n  AnnotationAssertion(rdfs:label :BlockchainNetwork \"Blockchain Network\"@en)\n  AnnotationAssertion(rdfs:comment :BlockchainNetwork\n    \"Distributed node infrastructure\"@en)\n  AnnotationAssertion(dct:description :BlockchainNetwork\n    \"Foundational blockchain concept with formal ontological definition\"@en)\n  AnnotationAssertion(:termID :BlockchainNetwork \"BC-0071\")\n  AnnotationAssertion(:priority :BlockchainNetwork \"1\"^^xsd:integer)\n  AnnotationAssertion(:category :BlockchainNetwork \"network-security\"@en)\n)\n      ```",
  "properties": {
    "id": "blockchain-network-owl-axioms",
    "collapsed": "true",
    "- public-access": "true",
    "- ontology": "true",
    "- term-id": "BC-0071",
    "- preferred-term": "Blockchain Network",
    "- source-domain": "blockchain",
    "- status": "complete",
    "- version": "1.0.0",
    "- last-updated": "2025-10-28",
    "- definition": "Distributed node infrastructure within blockchain systems, providing essential functionality for distributed ledger technology operations and properties.",
    "- maturity": "mature",
    "- source": "[[ISO/IEC 23257:2021]], [[IEEE 2418.1]], [[NIST NISTIR]]",
    "- authority-score": "0.95",
    "- owl:class": "bc:BlockchainNetwork",
    "- owl:physicality": "VirtualEntity",
    "- owl:role": "Object",
    "- owl:inferred-class": "bc:VirtualObject",
    "- belongsToDomain": "[[CryptographicDomain]]",
    "- implementedInLayer": "[[SecurityLayer]]",
    "- is-subclass-of": "[[Blockchain Entity]], [[NetworkComponent]]"
  },
  "backlinks": [],
  "wiki_links": [
    "SecurityLayer",
    "IEEE 2418.1",
    "Blockchain Entity",
    "CryptographicDomain",
    "ISO/IEC 23257:2021",
    "NIST NISTIR",
    "NetworkComponent"
  ],
  "ontology": {
    "term_id": "BC-0071",
    "preferred_term": "Blockchain Network",
    "definition": "Distributed node infrastructure within blockchain systems, providing essential functionality for distributed ledger technology operations and properties.",
    "source_domain": "blockchain",
    "maturity_level": null,
    "authority_score": 0.95
  }
}