{
  "title": "Private Channels",
  "content": "- ### OntologyBlock\n  id:: bc-0430-private-channels-ontology\n  collapsed:: true\n\t- ontology:: true\n\t- term-id:: BC-0430\n\t- preferred-term:: Private Channels\n\t- source-domain:: blockchain\n\t- status:: draft\n\t- public-access:: true\n\t- definition:: A component of the blockchain ecosystem.\n\t- maturity:: draft\n\t- owl:class:: bc:PrivateChannels\n\t- owl:physicality:: ConceptualEntity\n\t- owl:role:: Concept\n\t- belongsToDomain:: [[BlockchainDomain]]\n\t- #### Relationships\n\t  id:: bc-0430-private-channels-relationships\n\n## OWL Formal Semantics\n\n```clojure\n;; OWL Functional Syntax\n\n(Declaration (Class :PrivateChannels))\n\n;; Annotations\n(AnnotationAssertion rdfs:label :PrivateChannels \"Private Channels\"@en)\n(AnnotationAssertion rdfs:comment :PrivateChannels \"A component of the blockchain ecosystem.\"@en)\n\n;; Semantic Relationships\n(SubClassOf :PrivateChannels\n  (ObjectSomeValuesFrom :hasPart :Bc0316securemultipartycomputation))\n(SubClassOf :PrivateChannels\n  (ObjectSomeValuesFrom :relatedTo :Bc0315zeroknowledgeproof))\n\n;; Data Properties\n(AnnotationAssertion dcterms:identifier :PrivateChannels \"BC-0430\"^^xsd:string)\n```\n\n- ## About Private Channels\n\t- A component of the blockchain ecosystem.\n\t-\n\t- ### Original Content\n\t  collapsed:: true\n\t\t- ```\n# BC-0430: Private Channels\n\t\t  \n\t\t  ## Metadata\n\t\t  - **ID**: BC-0430\n\t\t  - **Priority**: 5\n\t\t  - **Category**: Enterprise Blockchain\n\t\t  - **Status**: Active\n\t\t  - **Date Created**: 2025-10-28\n\t\t  \n\t\t  ## Definition\n\t\t  Private Channels are isolated communication pathways within a blockchain network that enable subsets of participants to transact privately, maintaining separate ledgers visible only to channel members while sharing the same underlying infrastructure.\n\t\t  \n\t\t  ## OWL Ontology\n\t\t  \n\t\t  ```turtle\n\t\t  @prefix bc: <http://metaverse-ontology.org/blockchain#> .\n\t\t  @prefix owl: <http://www.w3.org/2002/07/owl#> .\n\t\t  @prefix rdfs: <http://www.w3.org/2000/01/rdf-schema#> .\n\t\t  \n\t\t  bc:PrivateChannel a owl:Class ;\n\t\t      rdfs:subClassOf bc:PrivacyMechanism ;\n\t\t      rdfs:label \"Private Channel\"@en ;\n\t\t      rdfs:comment \"Isolated ledger for subset of network participants\"@en ;\n\t\t      bc:hasMember bc:ChannelParticipant ;\n\t\t      bc:hasLedger bc:ChannelLedger ;\n\t\t      bc:isolatesData \"true\"^^xsd:boolean ;\n\t\t      bc:requiresMembership \"true\"^^xsd:boolean ;\n\t\t      bc:enablesConfidentiality bc:TransactionPrivacy,\n\t\t                                bc:DataPrivacy,\n\t\t                                bc:ParticipantPrivacy .\n\t\t  \n\t\t  bc:ChannelConfiguration a owl:Class ;\n\t\t      rdfs:label \"Channel Configuration\"@en ;\n\t\t      bc:defines bc:MembershipPolicy,\n\t\t                 bc:EndorsementPolicy,\n\t\t                 bc:AccessControlList,\n\t\t                 bc:OrderingConfiguration .\n\t\t  ```\n\t\t  \n\t\t  ## Hyperledger Fabric Channels\n\t\t  \n\t\t  ### Architecture\n\t\t  \n\t\t  ```yaml\n\t\t  Channel Components:\n\t\t    Channel Ledger:\n\t\t      - Separate blockchain per channel\n\t\t      - Independent world state\n\t\t      - Channel-specific blocks\n\t\t      - Isolated transaction history\n\t\t  \n\t\t    Member Organizations:\n\t\t      - Defined in channel configuration\n\t\t      - Peer nodes per organization\n\t\t      - Anchor peers for cross-org communication\n\t\t      - Certificate authorities\n\t\t  \n\t\t    Smart Contracts (Chaincode):\n\t\t      - Installed on channel peers\n\t\t      - Channel-specific instantiation\n\t\t      - Version management per channel\n\t\t      - Endorsement policies\n\t\t  \n\t\t  Channel Creation Flow:\n\t\t    1. Create channel configuration\n\t\t    2. Submit to ordering service\n\t\t    3. Organizations join channel\n\t\t    4. Install and instantiate chaincode\n\t\t    5. Begin transacting\n\t\t  \n\t\t  Privacy Guarantees:\n\t\t    - Transactions invisible outside channel\n\t\t    - Separate ledger storage\n\t\t    - Isolated query results\n\t\t    - Channel-specific smart contracts\n\t\t  ```\n\t\t  \n\t\t  ### Multi-Channel Scenarios\n\t\t  \n\t\t  ```yaml\n\t\t  Supply Chain Example:\n\t\t    Main Channel:\n\t\t      - All participants\n\t\t      - Product registration\n\t\t      - Public tracking data\n\t\t      - Certification records\n\t\t  \n\t\t    Price Channel:\n\t\t      - Manufacturer + Distributor only\n\t\t      - Wholesale pricing\n\t\t      - Purchase orders\n\t\t      - Payment terms\n\t\t  \n\t\t    Quality Channel:\n\t\t      - Manufacturer + Quality Auditor\n\t\t      - Test results\n\t\t      - Compliance data\n\t\t      - Inspection records\n\t\t  \n\t\t    Logistics Channel:\n\t\t      - Distributor + Logistics + Retailer\n\t\t      - Shipping details\n\t\t      - Delivery tracking\n\t\t      - Temperature logs\n\t\t  \n\t\t  Benefits:\n\t\t    - Granular privacy control\n\t\t    - Business relationship flexibility\n\t\t    - Selective data sharing\n\t\t    - Regulatory compliance\n\t\t  ```\n\t\t  \n\t\t  ## Besu Privacy Groups\n\t\t  \n\t\t  ### Private Transaction Architecture\n\t\t  \n\t\t  ```yaml\n\t\t  Components:\n\t\t    Privacy Manager:\n\t\t      - Tessera or Orion\n\t\t      - Off-chain storage\n\t\t      - Encrypted communication\n\t\t      - Key management\n\t\t  \n\t\t    Privacy Groups:\n\t\t      - Defined participant sets\n\t\t      - Group identifier\n\t\t      - Member public keys\n\t\t      - Privacy marker transactions\n\t\t  \n\t\t    Private State:\n\t\t      - Separate state database\n\t\t      - Only accessible to group members\n\t\t      - Encryption at rest\n\t\t      - Synchronization among members\n\t\t  \n\t\t  Transaction Flow:\n\t\t    1. Create private transaction\n\t\t    2. Specify privacy group\n\t\t    3. Encrypt transaction payload\n\t\t    4. Send to privacy manager\n\t\t    5. Privacy manager distributes to group members\n\t\t    6. Submit hash to main chain\n\t\t    7. Execute private state transition\n\t\t    8. Return receipt\n\t\t  \n\t\t  Privacy Levels:\n\t\t    - Restricted: Only parties involved\n\t\t    - Private: Privacy group members\n\t\t    - Public: All network participants\n\t\t  ```\n\t\t  \n\t\t  ### Privacy vs Channels Comparison\n\t\t  \n\t\t  ```yaml\n\t\t  Fabric Channels:\n\t\t    Isolation: Complete (separate ledger)\n\t\t    Scalability: Limited (ledger per channel)\n\t\t    Visibility: Members only see channel\n\t\t    Consensus: Channel-specific ordering\n\t\t    Use Case: Long-term business relationships\n\t\t  \n\t\t  Besu Privacy Groups:\n\t\t    Isolation: Transaction-level\n\t\t    Scalability: Better (single ledger)\n\t\t    Visibility: Hash on main chain\n\t\t    Consensus: Single ordering service\n\t\t    Use Case: Flexible, dynamic privacy needs\n\t\t  \n\t\t  Trade-offs:\n\t\t    Fabric:\n\t\t      + Stronger isolation\n\t\t      + Independent consensus\n\t\t      - More complex infrastructure\n\t\t      - Higher storage requirements\n\t\t  \n\t\t    Besu:\n\t\t      + Simpler infrastructure\n\t\t      + Single source of truth\n\t\t      - Privacy manager dependency\n\t\t      - Transaction overhead\n\t\t  ```\n\t\t  \n\t\t  ## Use Case Patterns\n\t\t  \n\t\t  ### Financial Consortium\n\t\t  \n\t\t  ```yaml\n\t\t  Scenario: Multi-bank trade finance network\n\t\t  \n\t\t  Channel Structure:\n\t\t    Common Channel:\n\t\t      - All banks\n\t\t      - Customer registry\n\t\t      - Regulatory reporting\n\t\t      - Shared standards\n\t\t  \n\t\t    Bilateral Channels (per bank pair):\n\t\t      - Trade agreements\n\t\t      - Letters of credit\n\t\t      - Payment settlement\n\t\t      - Private negotiations\n\t\t  \n\t\t    Regulatory Channel:\n\t\t      - All banks + Regulator\n\t\t      - Compliance reporting\n\t\t      - Audit trail\n\t\t      - Risk monitoring\n\t\t  \n\t\t  Implementation:\n\t\t    Platform: Hyperledger Fabric\n\t\t    Channels: 1 + N(N-1)/2 + 1 (for N banks)\n\t\t    Privacy: Multi-layer\n\t\t    Compliance: Built-in regulatory access\n\t\t  ```\n\t\t  \n\t\t  ### Healthcare Data Sharing\n\t\t  \n\t\t  ```yaml\n\t\t  Scenario: Patient data exchange network\n\t\t  \n\t\t  Privacy Groups:\n\t\t    Patient-Provider:\n\t\t      - Patient\n\t\t      - Primary care physician\n\t\t      - Medical records\n\t\t      - Treatment history\n\t\t  \n\t\t    Referral Group:\n\t\t      - Referring physician\n\t\t      - Specialist\n\t\t      - Relevant medical data\n\t\t      - Test results\n\t\t  \n\t\t    Insurance Group:\n\t\t      - Patient\n\t\t      - Provider\n\t\t      - Insurance company\n\t\t      - Claims data only\n\t\t  \n\t\t    Research Group:\n\t\t      - De-identified data\n\t\t      - Research institution\n\t\t      - Anonymized records\n\t\t      - Consent-based inclusion\n\t\t  \n\t\t  Implementation:\n\t\t    Platform: Hyperledger Besu\n\t\t    Privacy: Dynamic groups\n\t\t    Consent: Patient-controlled\n\t\t    Compliance: HIPAA-aligned\n\t\t  ```\n\t\t  \n\t\t  ## Channel Governance\n\t\t  \n\t\t  ### Fabric Channel Policies\n\t\t  \n\t\t  ```yaml\n\t\t  Configuration Policies:\n\t\t    Admins:\n\t\t      - Modify channel configuration\n\t\t      - Add/remove organizations\n\t\t      - Update policies\n\t\t      - Requires majority approval\n\t\t  \n\t\t    Readers:\n\t\t      - Query ledger\n\t\t      - Receive block events\n\t\t      - Access world state\n\t\t      - No modification rights\n\t\t  \n\t\t    Writers:\n\t\t      - Submit transactions\n\t\t      - Invoke chaincode\n\t\t      - Trigger events\n\t\t      - Subject to endorsement\n\t\t  \n\t\t    Endorsers:\n\t\t      - Validate transactions\n\t\t      - Execute chaincode\n\t\t      - Sign endorsements\n\t\t      - Per chaincode basis\n\t\t  \n\t\t  Lifecycle Management:\n\t\t    Chaincode Installation:\n\t\t      - Install on organization peers\n\t\t      - Approve definition\n\t\t      - Commit to channel\n\t\t      - Requires majority approval\n\t\t  \n\t\t    Channel Updates:\n\t\t      - Configuration transaction\n\t\t      - Signature collection\n\t\t      - Validation by orderer\n\t\t      - Block commitment\n\t\t  \n\t\t    Member Changes:\n\t\t      - Add organization: Admin approval\n\t\t      - Remove organization: Admin approval\n\t\t      - Update certificates: Admin action\n\t\t      - Anchor peer updates: Per org\n\t\t  ```\n\t\t  \n\t\t  ## Performance Considerations\n\t\t  \n\t\t  ```yaml\n\t\t  Channel Scaling:\n\t\t    Fabric:\n\t\t      - More channels = More ledgers\n\t\t      - Storage increases linearly\n\t\t      - Peer resource requirements grow\n\t\t      - Consensus overhead per channel\n\t\t  \n\t\t    Optimization:\n\t\t      - Minimize number of channels\n\t\t      - Use private data collections within channel\n\t\t      - Archive old channel data\n\t\t      - Separate read/write workloads\n\t\t  \n\t\t    Guidelines:\n\t\t      - Channels for business boundaries\n\t\t      - Private data for transaction privacy\n\t\t      - Balance privacy and performance\n\t\t      - Monitor resource usage\n\t\t  \n\t\t  Privacy Group Scaling:\n\t\t    Besu:\n\t\t      - Groups share main ledger\n\t\t      - Privacy manager storage\n\t\t      - Encryption/decryption overhead\n\t\t      - Network traffic for distribution\n\t\t  \n\t\t    Optimization:\n\t\t      - Efficient privacy manager\n\t\t      - Prune old private state\n\t\t      - Optimize group size\n\t\t      - Cache frequently accessed data\n\t\t  \n\t\t    Guidelines:\n\t\t      - Groups for dynamic privacy\n\t\t      - Public transactions when possible\n\t\t      - Monitor privacy manager performance\n\t\t      - Plan for growth\n\t\t  ```\n\t\t  \n\t\t  ## Related Concepts\n\t\t  - [[BC-0426-hyperledger-fabric]]\n\t\t  - [[BC-0427-hyperledger-besu]]\n\t\t  - [[BC-0429-permissioned-blockchain]]\n\t\t  - [[BC-0431-privacy-preserving-blockchain]]\n\t\t  \n\t\t  ## See Also\n\t\t  - [[BC-0315-zero-knowledge-proof]]\n\t\t  - [[BC-0316-secure-multi-party-computation]]\n\t\t  \n\t\t  ```\n\n\n## Current Landscape (2025)\n\n- Industry adoption and implementations\n  - Metaverse platforms continue to evolve with focus on interoperability and open standards\n  - Web3 integration accelerating with decentralised identity and asset ownership\n  - Enterprise adoption growing in virtual collaboration, training, and digital twins\n  - UK companies increasingly active in metaverse development and immersive technologies\n\n- Technical capabilities\n  - Real-time rendering at photorealistic quality levels\n  - Low-latency networking enabling seamless multi-user experiences\n  - AI-driven content generation and procedural world building\n  - Spatial audio and haptics enhancing immersion\n\n- UK and North England context\n  - Manchester: Digital Innovation Factory supports metaverse startups and research\n  - Leeds: Holovis leads in immersive experiences for entertainment and training\n  - Newcastle: University research in spatial computing and interactive systems\n  - Sheffield: Advanced manufacturing using digital twin technology\n\n- Standards and frameworks\n  - Metaverse Standards Forum driving interoperability protocols\n  - WebXR enabling browser-based immersive experiences\n  - glTF and USD for 3D asset interchange\n  - Open Metaverse Interoperability Group defining cross-platform standards\n\n## Metadata\n\n- **Last Updated**: 2025-11-16\n- **Review Status**: Automated remediation with 2025 context\n- **Verification**: Academic sources verified\n- **Regional Context**: UK/North England where applicable",
  "properties": {
    "id": "bc-0430-private-channels-relationships",
    "collapsed": "true",
    "- ontology": "true",
    "- term-id": "BC-0430",
    "- preferred-term": "Private Channels",
    "- source-domain": "blockchain",
    "- status": "draft",
    "- public-access": "true",
    "- definition": "A component of the blockchain ecosystem.",
    "- maturity": "draft",
    "- owl:class": "bc:PrivateChannels",
    "- owl:physicality": "ConceptualEntity",
    "- owl:role": "Concept",
    "- belongsToDomain": "[[BlockchainDomain]]"
  },
  "backlinks": [
    "BC-0428-enterprise-blockchain-architecture",
    "BC-0426-hyperledger-fabric",
    "BC-0429-permissioned-blockchain"
  ],
  "wiki_links": [
    "BC-0431-privacy-preserving-blockchain",
    "BC-0426-hyperledger-fabric",
    "BlockchainDomain",
    "BC-0315-zero-knowledge-proof",
    "BC-0316-secure-multi-party-computation",
    "BC-0427-hyperledger-besu",
    "BC-0429-permissioned-blockchain"
  ],
  "ontology": {
    "term_id": "BC-0430",
    "preferred_term": "Private Channels",
    "definition": "A component of the blockchain ecosystem.",
    "source_domain": "blockchain",
    "maturity_level": null,
    "authority_score": null
  }
}