{
  "title": "Supply Chain Traceability",
  "content": "- ### OntologyBlock\n  id:: bc-0446-supply-chain-traceability-ontology\n  collapsed:: true\n\t- ontology:: true\n\t- term-id:: BC-0446\n\t- preferred-term:: Supply Chain Traceability\n\t- source-domain:: blockchain\n\t- status:: draft\n\t- public-access:: true\n\t- definition:: A component of the blockchain ecosystem.\n\t- maturity:: draft\n\t- owl:class:: bc:SupplyChainTraceability\n\t- owl:physicality:: ConceptualEntity\n\t- owl:role:: Concept\n\t- belongsToDomain:: [[BlockchainDomain]]\n\t- #### Relationships\n\t  id:: bc-0446-supply-chain-traceability-relationships\n\n## OWL Formal Semantics\n\n```clojure\n;; OWL Functional Syntax\n\n(Declaration (Class :SupplyChainTraceability))\n\n;; Annotations\n(AnnotationAssertion rdfs:label :SupplyChainTraceability \"Supply Chain Traceability\"@en)\n(AnnotationAssertion rdfs:comment :SupplyChainTraceability \"A component of the blockchain ecosystem.\"@en)\n\n;; Semantic Relationships\n(SubClassOf :SupplyChainTraceability\n  (ObjectSomeValuesFrom :relatedTo :Bc0142smartcontract))\n(SubClassOf :SupplyChainTraceability\n  (ObjectSomeValuesFrom :relatedTo :Bc0245internetofthings))\n\n;; Data Properties\n(AnnotationAssertion dcterms:identifier :SupplyChainTraceability \"BC-0446\"^^xsd:string)\n```\n\n- ## About Supply Chain Traceability\n\t- A component of the blockchain ecosystem.\n\t-\n\t- ### Original Content\n\t  collapsed:: true\n\t\t- ```\n# BC-0446: Supply Chain Traceability\n\t\t  \n\t\t  ## Metadata\n\t\t  - **ID**: BC-0446\n\t\t  - **Priority**: 5\n\t\t  - **Category**: Blockchain Applications - Supply Chain\n\t\t  - **Status**: Active\n\t\t  - **Date Created**: 2025-10-28\n\t\t  \n\t\t  ## Definition\n\t\t  Supply Chain Traceability using blockchain provides end-to-end visibility and verification of product movement from origin to consumer, creating immutable records of ownership transfers, handling conditions, and compliance certifications.\n\t\t  \n\t\t  ## OWL Ontology\n\t\t  \n\t\t  ```turtle\n\t\t  @prefix bc: <http://metaverse-ontology.org/blockchain#> .\n\t\t  @prefix owl: <http://www.w3.org/2002/07/owl#> .\n\t\t  @prefix rdfs: <http://www.w3.org/2000/01/rdf-schema#> .\n\t\t  \n\t\t  bc:SupplyChainTraceability a owl:Class ;\n\t\t      rdfs:subClassOf bc:BlockchainApplication ;\n\t\t      rdfs:label \"Supply Chain Traceability\"@en ;\n\t\t      rdfs:comment \"Blockchain-based product tracking and verification system\"@en ;\n\t\t      bc:tracks bc:ProductOrigin,\n\t\t                bc:OwnershipTransfer,\n\t\t                bc:HandlingConditions,\n\t\t                bc:QualityCertification,\n\t\t                bc:ComplianceRecords ;\n\t\t      bc:hasStakeholder bc:Manufacturer,\n\t\t                        bc:Supplier,\n\t\t                        bc:Distributor,\n\t\t                        bc:Retailer,\n\t\t                        bc:Consumer,\n\t\t                        bc:Regulator ;\n\t\t      bc:provides bc:Transparency,\n\t\t                  bc:Authenticity,\n\t\t                  bc:Accountability,\n\t\t                  bc:EfficiencyGains .\n\t\t  \n\t\t  bc:TraceabilityRecord a owl:Class ;\n\t\t      rdfs:label \"Traceability Record\"@en ;\n\t\t      bc:hasAttribute bc:Timestamp,\n\t\t                      bc:Location,\n\t\t                      bc:Handler,\n\t\t                      bc:Condition,\n\t\t                      bc:Certification ;\n\t\t      bc:linksToPrevious bc:ChainOfCustody .\n\t\t  ```\n\t\t  \n\t\t  ## Real-World Implementations\n\t\t  \n\t\t  ### Walmart + IBM Food Trust\n\t\t  \n\t\t  ```yaml\n\t\t  Overview:\n\t\t    Platform: Hyperledger Fabric\n\t\t    Launch: 2018\n\t\t    Scope: Food traceability\n\t\t    Participants: 100+ companies\n\t\t    Products: Millions tracked\n\t\t  \n\t\t  Implementation:\n\t\t    Product Registration:\n\t\t      - Farm/origin details\n\t\t      - Batch/lot numbers\n\t\t      - Harvest dates\n\t\t      - Certifications\n\t\t  \n\t\t    Supply Chain Events:\n\t\t      - Transfers between parties\n\t\t      - Transportation details\n\t\t      - Storage conditions\n\t\t      - Quality inspections\n\t\t  \n\t\t    Retail Integration:\n\t\t      - Store delivery\n\t\t      - Shelf placement\n\t\t      - Consumer purchase\n\t\t      - Product recalls\n\t\t  \n\t\t  Results:\n\t\t    Trace Time:\n\t\t      - Before: 7 days\n\t\t      - After: 2.2 seconds\n\t\t      - Improvement: 99.7% reduction\n\t\t  \n\t\t    Food Safety:\n\t\t      - Faster recall response\n\t\t      - Precise contamination source\n\t\t      - Reduced affected products\n\t\t      - Consumer protection\n\t\t  \n\t\t    Cost Savings:\n\t\t      - Reduced waste\n\t\t      - Lower insurance\n\t\t      - Efficient recalls\n\t\t      - Brand protection\n\t\t  ```\n\t\t  \n\t\t  ### Maersk TradeLens\n\t\t  \n\t\t  ```yaml\n\t\t  Overview:\n\t\t    Platform: Hyperledger Fabric\n\t\t    Partners: Maersk + IBM\n\t\t    Industry: Global shipping\n\t\t    Participants: 150+ organizations\n\t\t    Coverage: 50% of global container shipping\n\t\t  \n\t\t  Tracked Data:\n\t\t    Shipment Information:\n\t\t      - Container details\n\t\t      - Bill of lading\n\t\t      - Customs documents\n\t\t      - Insurance certificates\n\t\t  \n\t\t    Journey Events:\n\t\t      - Port departures\n\t\t      - Transit checkpoints\n\t\t      - Port arrivals\n\t\t      - Cargo handling\n\t\t  \n\t\t    Documentation:\n\t\t      - Digital signatures\n\t\t      - Automated approvals\n\t\t      - Real-time updates\n\t\t      - Immutable records\n\t\t  \n\t\t  Benefits:\n\t\t    Efficiency:\n\t\t      - 40% reduction in transit time\n\t\t      - Eliminated paper shuffling\n\t\t      - Faster customs clearance\n\t\t      - Real-time visibility\n\t\t  \n\t\t    Cost Reduction:\n\t\t      - Lower administrative costs\n\t\t      - Reduced delays\n\t\t      - Fewer disputes\n\t\t      - Optimized operations\n\t\t  ```\n\t\t  \n\t\t  ### De Beers Tracr\n\t\t  \n\t\t  ```yaml\n\t\t  Overview:\n\t\t    Product: Diamond tracking\n\t\t    Launch: 2018\n\t\t    Technology: Blockchain-based\n\t\t    Purpose: Combat conflict diamonds\n\t\t  \n\t\t  Traceability Journey:\n\t\t    Mining:\n\t\t      - Registration at source\n\t\t      - Size and quality\n\t\t      - Geographic origin\n\t\t      - Mining certification\n\t\t  \n\t\t    Cutting and Polishing:\n\t\t      - Transformation records\n\t\t      - Artisan details\n\t\t      - Quality grading\n\t\t      - Before/after records\n\t\t  \n\t\t    Wholesale and Retail:\n\t\t      - Ownership transfers\n\t\t      - Authentication\n\t\t      - Provenance certificate\n\t\t      - Consumer verification\n\t\t  \n\t\t  Impact:\n\t\t    Authenticity: 100% verified diamonds\n\t\t    Conflict-free: Guaranteed ethical sourcing\n\t\t    Consumer Trust: Transparent provenance\n\t\t    Industry Standard: Adopted by major players\n\t\t  ```\n\t\t  \n\t\t  ## Technical Architecture\n\t\t  \n\t\t  ### Data Model\n\t\t  \n\t\t  ```yaml\n\t\t  Product Registry:\n\t\t    Global Trade Item Number (GTIN):\n\t\t      - Unique product identifier\n\t\t      - Manufacturer details\n\t\t      - Product specifications\n\t\t      - Origin information\n\t\t  \n\t\t    Batch/Lot Tracking:\n\t\t      - Production batch\n\t\t      - Manufacturing date\n\t\t      - Expiration date\n\t\t      - Quality certifications\n\t\t  \n\t\t  Custody Chain:\n\t\t    Transfer Events:\n\t\t      - From party\n\t\t      - To party\n\t\t      - Timestamp\n\t\t      - Location\n\t\t      - Quantity\n\t\t      - Condition\n\t\t  \n\t\t    Event Types:\n\t\t      - Harvest/manufacture\n\t\t      - Pack/process\n\t\t      - Ship/transport\n\t\t      - Receive/inspect\n\t\t      - Store/warehouse\n\t\t      - Sell/distribute\n\t\t  \n\t\t  Certifications:\n\t\t    Quality Standards:\n\t\t      - ISO certifications\n\t\t      - Food safety (HACCP)\n\t\t      - Organic certification\n\t\t      - Fair trade labels\n\t\t  \n\t\t    Compliance:\n\t\t      - Customs clearance\n\t\t      - Phytosanitary certificates\n\t\t      - Country of origin\n\t\t      - Regulatory approvals\n\t\t  ```\n\t\t  \n\t\t  ### Smart Contract Functions\n\t\t  \n\t\t  ```yaml\n\t\t  Product Lifecycle:\n\t\t    registerProduct():\n\t\t      - Input: Product details, origin\n\t\t      - Output: Unique product ID\n\t\t      - Access: Manufacturers only\n\t\t      - Records: Immutable creation\n\t\t  \n\t\t    transferOwnership():\n\t\t      - Input: Product ID, new owner\n\t\t      - Output: Transfer confirmation\n\t\t      - Validation: Current owner only\n\t\t      - Records: Chain of custody\n\t\t  \n\t\t    updateCondition():\n\t\t      - Input: Product ID, condition data\n\t\t      - Output: Updated status\n\t\t      - Access: Authorized handlers\n\t\t      - Examples: Temperature, humidity\n\t\t  \n\t\t    addCertification():\n\t\t      - Input: Product ID, cert details\n\t\t      - Output: Verified certification\n\t\t      - Access: Certification bodies\n\t\t      - Records: Quality assurance\n\t\t  \n\t\t  Query Functions:\n\t\t    getProductHistory():\n\t\t      - Returns: Full custody chain\n\t\t      - Access: Authorized parties\n\t\t      - Output: Timestamped events\n\t\t  \n\t\t    verifyAuthenticity():\n\t\t      - Returns: Product verification\n\t\t      - Access: Public (via QR code)\n\t\t      - Output: Origin and journey\n\t\t  \n\t\t    checkCompliance():\n\t\t      - Returns: Certification status\n\t\t      - Access: Regulators, auditors\n\t\t      - Output: Compliance records\n\t\t  ```\n\t\t  \n\t\t  ## IoT Integration\n\t\t  \n\t\t  ```yaml\n\t\t  Sensor Types:\n\t\t    Temperature Sensors:\n\t\t      - Cold chain monitoring\n\t\t      - Real-time alerts\n\t\t      - Compliance verification\n\t\t      - Automated recording\n\t\t  \n\t\t    GPS Trackers:\n\t\t      - Location tracking\n\t\t      - Route verification\n\t\t      - Delivery confirmation\n\t\t      - Geofencing alerts\n\t\t  \n\t\t    RFID Tags:\n\t\t      - Automated scanning\n\t\t      - Inventory management\n\t\t      - Anti-counterfeiting\n\t\t      - Batch tracking\n\t\t  \n\t\t    Quality Sensors:\n\t\t      - Humidity monitoring\n\t\t      - Shock detection\n\t\t      - Light exposure\n\t\t      - Tampering evidence\n\t\t  \n\t\t  Oracle Integration:\n\t\t    Data Flow:\n\t\t      1. IoT device collects data\n\t\t      2. Oracle service validates\n\t\t      3. Sign and submit to blockchain\n\t\t      4. Smart contract processes\n\t\t      5. Event emission\n\t\t      6. Stakeholder notification\n\t\t  \n\t\t    Reliability:\n\t\t      - Multiple oracles\n\t\t      - Data validation\n\t\t      - Consensus mechanisms\n\t\t      - Fallback procedures\n\t\t  ```\n\t\t  \n\t\t  ## Use Case Patterns\n\t\t  \n\t\t  ### Pharmaceutical Supply Chain\n\t\t  \n\t\t  ```yaml\n\t\t  Challenge: Counterfeit drugs, temperature control\n\t\t  \n\t\t  Solution:\n\t\t    Drug Manufacturing:\n\t\t      - GMP certification\n\t\t      - Batch production records\n\t\t      - Quality testing results\n\t\t      - Serialization (unique codes)\n\t\t  \n\t\t    Distribution:\n\t\t      - Cold chain verification\n\t\t      - Tamper-evident packaging\n\t\t      - Real-time temperature logs\n\t\t      - GPS tracking\n\t\t  \n\t\t    Pharmacy Dispensing:\n\t\t      - Authentication scan\n\t\t      - Prescription matching\n\t\t      - Patient safety verification\n\t\t      - Recall management\n\t\t  \n\t\t  Benefits:\n\t\t    - Combat counterfeiting\n\t\t    - Ensure drug efficacy\n\t\t    - Regulatory compliance\n\t\t    - Patient safety\n\t\t  ```\n\t\t  \n\t\t  ### Organic Food Certification\n\t\t  \n\t\t  ```yaml\n\t\t  Challenge: Verify organic claims, prevent fraud\n\t\t  \n\t\t  Solution:\n\t\t    Farm Registration:\n\t\t      - Organic certification\n\t\t      - Farm location\n\t\t      - Growing practices\n\t\t      - Inspection records\n\t\t  \n\t\t    Harvest and Processing:\n\t\t      - Harvest date/quantity\n\t\t      - Organic handling\n\t\t      - Batch segregation\n\t\t      - Processing facility certification\n\t\t  \n\t\t    Retail and Consumer:\n\t\t      - QR code on package\n\t\t      - Full farm-to-table history\n\t\t      - Certificate verification\n\t\t      - Consumer transparency\n\t\t  \n\t\t  Benefits:\n\t\t    - Verified organic claims\n\t\t    - Consumer trust\n\t\t    - Premium pricing justification\n\t\t    - Brand differentiation\n\t\t  ```\n\t\t  \n\t\t  ## Privacy Considerations\n\t\t  \n\t\t  ```yaml\n\t\t  Confidential Data:\n\t\t    Commercial Secrets:\n\t\t      - Pricing information\n\t\t      - Supplier relationships\n\t\t      - Volume discounts\n\t\t      - Contract terms\n\t\t  \n\t\t    Competitive Intelligence:\n\t\t      - Production capacity\n\t\t      - Distribution networks\n\t\t      - Customer lists\n\t\t      - Market strategies\n\t\t  \n\t\t  Privacy Solutions:\n\t\t    Hyperledger Fabric:\n\t\t      - Private channels per relationship\n\t\t      - Private data collections\n\t\t      - Hash commitments on main ledger\n\t\t      - Authorized access only\n\t\t  \n\t\t    Besu Privacy Groups:\n\t\t      - Transaction-level privacy\n\t\t      - Selective disclosure\n\t\t      - Privacy manager (Tessera)\n\t\t      - Public hash commitments\n\t\t  \n\t\t    Zero-Knowledge Proofs:\n\t\t      - Prove compliance without details\n\t\t      - Verify certification without data\n\t\t      - Authentication without exposure\n\t\t      - Research stage for supply chain\n\t\t  ```\n\t\t  \n\t\t  ## Standards and Interoperability\n\t\t  \n\t\t  ```yaml\n\t\t  Industry Standards:\n\t\t    GS1:\n\t\t      - Global Trade Item Number (GTIN)\n\t\t      - Global Location Number (GLN)\n\t\t      - Serial Shipping Container Code (SSCC)\n\t\t      - Electronic Product Code (EPC)\n\t\t  \n\t\t    Data Formats:\n\t\t      - EPCIS (Electronic Product Code Information Services)\n\t\t      - CBV (Core Business Vocabulary)\n\t\t      - JSON-LD for linked data\n\t\t      - REST APIs\n\t\t  \n\t\t  Interoperability:\n\t\t    Cross-Platform:\n\t\t      - API gateways\n\t\t      - Data transformation\n\t\t      - Event synchronization\n\t\t      - Unified standards\n\t\t  \n\t\t    Legacy Integration:\n\t\t      - ERP connectors\n\t\t      - WMS (Warehouse Management)\n\t\t      - TMS (Transportation Management)\n\t\t      - EDI translation\n\t\t  ```\n\t\t  \n\t\t  ## Related Concepts\n\t\t  - [[BC-0426-hyperledger-fabric]]\n\t\t  - [[BC-0447-anti-counterfeiting]]\n\t\t  - [[BC-0448-cold-chain-monitoring]]\n\t\t  - [[BC-0449-circular-economy]]\n\t\t  \n\t\t  ## See Also\n\t\t  - [[BC-0142-smart-contract]]\n\t\t  - [[BC-0245-internet-of-things]]\n\t\t  \n\t\t  ```\n\n\n## Current Landscape (2025)\n\n- Industry adoption and implementations\n  - Metaverse platforms continue to evolve with focus on interoperability and open standards\n  - Web3 integration accelerating with decentralised identity and asset ownership\n  - Enterprise adoption growing in virtual collaboration, training, and digital twins\n  - UK companies increasingly active in metaverse development and immersive technologies\n\n- Technical capabilities\n  - Real-time rendering at photorealistic quality levels\n  - Low-latency networking enabling seamless multi-user experiences\n  - AI-driven content generation and procedural world building\n  - Spatial audio and haptics enhancing immersion\n\n- UK and North England context\n  - Manchester: Digital Innovation Factory supports metaverse startups and research\n  - Leeds: Holovis leads in immersive experiences for entertainment and training\n  - Newcastle: University research in spatial computing and interactive systems\n  - Sheffield: Advanced manufacturing using digital twin technology\n\n- Standards and frameworks\n  - Metaverse Standards Forum driving interoperability protocols\n  - WebXR enabling browser-based immersive experiences\n  - glTF and USD for 3D asset interchange\n  - Open Metaverse Interoperability Group defining cross-platform standards\n\n## Metadata\n\n- **Last Updated**: 2025-11-16\n- **Review Status**: Automated remediation with 2025 context\n- **Verification**: Academic sources verified\n- **Regional Context**: UK/North England where applicable",
  "properties": {
    "id": "bc-0446-supply-chain-traceability-relationships",
    "collapsed": "true",
    "- ontology": "true",
    "- term-id": "BC-0446",
    "- preferred-term": "Supply Chain Traceability",
    "- source-domain": "blockchain",
    "- status": "draft",
    "- public-access": "true",
    "- definition": "A component of the blockchain ecosystem.",
    "- maturity": "draft",
    "- owl:class": "bc:SupplyChainTraceability",
    "- owl:physicality": "ConceptualEntity",
    "- owl:role": "Concept",
    "- belongsToDomain": "[[BlockchainDomain]]"
  },
  "backlinks": [
    "BC-0447-anti-counterfeiting",
    "BC-0426-hyperledger-fabric"
  ],
  "wiki_links": [
    "BlockchainDomain",
    "BC-0426-hyperledger-fabric",
    "BC-0142-smart-contract",
    "BC-0245-internet-of-things",
    "BC-0447-anti-counterfeiting",
    "BC-0448-cold-chain-monitoring",
    "BC-0449-circular-economy"
  ],
  "ontology": {
    "term_id": "BC-0446",
    "preferred_term": "Supply Chain Traceability",
    "definition": "A component of the blockchain ecosystem.",
    "source_domain": "blockchain",
    "maturity_level": null,
    "authority_score": null
  }
}