{
  "title": "Consensus Mechanism",
  "content": "- ### OntologyBlock\n  id:: consensus-mechanism-ontology\n  collapsed:: true\n\n  - **Identification**\n    - public-access:: true\n    - ontology:: true\n    - term-id:: BC-0051\n    - preferred-term:: Consensus Mechanism\n    - source-domain:: blockchain\n    - status:: complete\n    - version:: 1.0.0\n    - last-updated:: 2025-10-28\n\n  - **Definition**\n    - definition:: A consensus mechanism is a fault-tolerant protocol that enables distributed network nodes to agree on a single, consistent state of a distributed ledger despite the presence of faulty or malicious nodes, ensuring all valid transactions are recorded in the same order across all nodes without requiring a trusted central authority.\n    - maturity:: mature\n    - source:: [[ISO/IEC 23257:2021]], [[ITU-T Y.3051]], [[IEEE 2418.1]]\n    - authority-score:: 1.0\n\n  - **Semantic Classification**\n    - owl:class:: bc:ConsensusMechanism\n    - owl:physicality:: VirtualEntity\n    - owl:role:: Object\n    - owl:inferred-class:: bc:VirtualObject\n    - belongsToDomain:: [[ConsensusDomain]]\n    - implementedInLayer:: [[ProtocolLayer]]\n\n  - #### Relationships\n    id:: consensus-mechanism-relationships\n    - is-subclass-of:: [[Distributed Protocol]], [[Agreement Protocol]], [[Fault Tolerance System]]\n\n  - #### OWL Axioms\n    id:: consensus-mechanism-owl-axioms\n    collapsed:: true\n    - ```clojure\n      Prefix(:=<http://metaverse-ontology.org/blockchain#>)\nPrefix(owl:=<http://www.w3.org/2002/07/owl#>)\nPrefix(xsd:=<http://www.w3.org/2001/XMLSchema#>)\nPrefix(rdfs:=<http://www.w3.org/2000/01/rdf-schema#>)\n\nOntology(<http://metaverse-ontology.org/blockchain/BC-0051>\n\n  ## Class Declaration\n  Declaration(Class(:ConsensusMechanism))\n\n  ## Subclass Relationships\n  SubClassOf(:ConsensusMechanism :DistributedProtocol)\n  SubClassOf(:ConsensusMechanism :AgreementProtocol)\n  SubClassOf(:ConsensusMechanism :FaultToleranceSystem)\n\n  ## Essential Properties\n  SubClassOf(:ConsensusMechanism\n    (ObjectSomeValuesFrom :achieves :ConsensusState))\n\n  SubClassOf(:ConsensusMechanism\n    (ObjectSomeValuesFrom :tolerates :ByzantineFault))\n\n  SubClassOf(:ConsensusMechanism\n    (ObjectSomeValuesFrom :validates :Transaction))\n\n  SubClassOf(:ConsensusMechanism\n    (ObjectSomeValuesFrom :usedBy :Blockchain))\n\n  SubClassOf(:ConsensusMechanism\n    (DataSomeValuesFrom :hasSafetyProperty xsd:boolean))\n\n  SubClassOf(:ConsensusMechanism\n    (DataSomeValuesFrom :hasLivenessProperty xsd:boolean))\n\n  ## Consensus Properties\n  SubClassOf(:ConsensusMechanism\n    (ObjectExactCardinality 1 :hasValidationFunction :ValidationFunction))\n\n  SubClassOf(:ConsensusMechanism\n    (ObjectExactCardinality 1 :hasAgreementProtocol :AgreementProtocol))\n\n  ## Data Properties\n  DataPropertyAssertion(:faultToleranceThreshold :ConsensusMechanism xsd:decimal)\n  DataPropertyAssertion(:finalityTime :ConsensusMechanism xsd:duration)\n  DataPropertyAssertion(:throughput :ConsensusMechanism xsd:decimal)\n  DataPropertyAssertion(:energyEfficiency :ConsensusMechanism xsd:string)\n\n  ## Object Properties\n  ObjectPropertyAssertion(:implementedBy :ConsensusMechanism :Blockchain)\n  ObjectPropertyAssertion(:requires :ConsensusMechanism :NetworkCondition)\n  ObjectPropertyAssertion(:produces :ConsensusMechanism :ConsensusState)\n\n  ## Annotations\n  AnnotationAssertion(rdfs:label :ConsensusMechanism \"Consensus Mechanism\"@en)\n  AnnotationAssertion(rdfs:comment :ConsensusMechanism\n    \"Protocol enabling distributed nodes to agree on ledger state\"@en)\n  AnnotationAssertion(:termID :ConsensusMechanism \"BC-0051\")\n\n  ## Subclasses\n  Declaration(Class(:ProofOfWork))\n  SubClassOf(:ProofOfWork :ConsensusMechanism)\n\n  Declaration(Class(:ProofOfStake))\n  SubClassOf(:ProofOfStake :ConsensusMechanism)\n\n  Declaration(Class(:ByzantineFaultTolerance))\n  SubClassOf(:ByzantineFaultTolerance :ConsensusMechanism)\n\n  Declaration(Class(:ProofOfAuthority))\n  SubClassOf(:ProofOfAuthority :ConsensusMechanism)\n)\n      ```",
  "properties": {
    "id": "consensus-mechanism-owl-axioms",
    "collapsed": "true",
    "- public-access": "true",
    "- ontology": "true",
    "- term-id": "BC-0051",
    "- preferred-term": "Consensus Mechanism",
    "- source-domain": "blockchain",
    "- status": "complete",
    "- version": "1.0.0",
    "- last-updated": "2025-10-28",
    "- definition": "A consensus mechanism is a fault-tolerant protocol that enables distributed network nodes to agree on a single, consistent state of a distributed ledger despite the presence of faulty or malicious nodes, ensuring all valid transactions are recorded in the same order across all nodes without requiring a trusted central authority.",
    "- maturity": "mature",
    "- source": "[[ISO/IEC 23257:2021]], [[ITU-T Y.3051]], [[IEEE 2418.1]]",
    "- authority-score": "1.0",
    "- owl:class": "bc:ConsensusMechanism",
    "- owl:physicality": "VirtualEntity",
    "- owl:role": "Object",
    "- owl:inferred-class": "bc:VirtualObject",
    "- belongsToDomain": "[[ConsensusDomain]]",
    "- implementedInLayer": "[[ProtocolLayer]]",
    "- is-subclass-of": "[[Distributed Protocol]], [[Agreement Protocol]], [[Fault Tolerance System]]"
  },
  "backlinks": [],
  "wiki_links": [
    "ITU-T Y.3051",
    "Fault Tolerance System",
    "ProtocolLayer",
    "Distributed Protocol",
    "IEEE 2418.1",
    "Agreement Protocol",
    "ISO/IEC 23257:2021",
    "ConsensusDomain"
  ],
  "ontology": {
    "term_id": "BC-0051",
    "preferred_term": "Consensus Mechanism",
    "definition": "A consensus mechanism is a fault-tolerant protocol that enables distributed network nodes to agree on a single, consistent state of a distributed ledger despite the presence of faulty or malicious nodes, ensuring all valid transactions are recorded in the same order across all nodes without requiring a trusted central authority.",
    "source_domain": "blockchain",
    "maturity_level": null,
    "authority_score": 1.0
  }
}