{
  "title": "Zero-Knowledge Proof",
  "content": "- ### OntologyBlock\n  id:: zero-knowledge-proof-ontology\n  collapsed:: true\n\n  - **Identification**\n    - public-access:: true\n    - ontology:: true\n    - term-id:: BC-0033\n    - preferred-term:: Zero-Knowledge Proof\n    - source-domain:: blockchain\n    - status:: complete\n    - version:: 1.0.0\n    - last-updated:: 2025-10-28\n\n  - **Definition**\n    - definition:: Privacy-preserving verification within blockchain systems, providing essential functionality for distributed ledger technology operations and properties.\n    - maturity:: mature\n    - source:: [[ISO/IEC 23257:2021]], [[IEEE 2418.1]], [[NIST NISTIR]]\n    - authority-score:: 0.95\n\n  - **Semantic Classification**\n    - owl:class:: bc:Zero-knowledgeProof\n    - owl:physicality:: VirtualEntity\n    - owl:role:: Object\n    - owl:inferred-class:: bc:VirtualObject\n    - belongsToDomain:: [[CryptographicDomain]]\n    - implementedInLayer:: [[SecurityLayer]]\n\n  - #### Relationships\n    id:: zero-knowledge-proof-relationships\n    - is-subclass-of:: [[Blockchain Entity]], [[CryptographicPrimitive]]\n\n  - #### OWL Axioms\n    id:: zero-knowledge-proof-owl-axioms\n    collapsed:: true\n    - ```clojure\n      Prefix(:=<http://metaverse-ontology.org/blockchain#>)\nPrefix(owl:=<http://www.w3.org/2002/07/owl#>)\nPrefix(rdf:=<http://www.w3.org/1999/02/22-rdf-syntax-ns#>)\nPrefix(xml:=<http://www.w3.org/XML/1998/namespace>)\nPrefix(xsd:=<http://www.w3.org/2001/XMLSchema#>)\nPrefix(rdfs:=<http://www.w3.org/2000/01/rdf-schema#>)\nPrefix(dct:=<http://purl.org/dc/terms/>)\n\nOntology(<http://metaverse-ontology.org/blockchain/BC-0033>\n  Import(<http://metaverse-ontology.org/blockchain/core>)\n\n  ## Class Declaration\n  Declaration(Class(:Zero-KnowledgeProof))\n\n  ## Subclass Relationships\n  SubClassOf(:Zero-KnowledgeProof :CryptographicPrimitive)\n  SubClassOf(:Zero-KnowledgeProof :BlockchainEntity)\n\n  ## Essential Properties\n  SubClassOf(:Zero-KnowledgeProof\n    (ObjectSomeValuesFrom :partOf :Blockchain))\n\n  SubClassOf(:Zero-KnowledgeProof\n    (ObjectSomeValuesFrom :hasProperty :Property))\n\n  ## Data Properties\n  DataPropertyAssertion(:hasIdentifier :Zero-KnowledgeProof \"BC-0033\"^^xsd:string)\n  DataPropertyAssertion(:hasAuthorityScore :Zero-KnowledgeProof \"1.0\"^^xsd:decimal)\n  DataPropertyAssertion(:isFoundational :Zero-KnowledgeProof \"true\"^^xsd:boolean)\n\n  ## Object Properties\n  ObjectPropertyAssertion(:enablesFeature :Zero-KnowledgeProof :BlockchainFeature)\n  ObjectPropertyAssertion(:relatesTo :Zero-KnowledgeProof :RelatedConcept)\n\n  ## Annotations\n  AnnotationAssertion(rdfs:label :Zero-KnowledgeProof \"Zero-Knowledge Proof\"@en)\n  AnnotationAssertion(rdfs:comment :Zero-KnowledgeProof\n    \"Privacy-preserving verification\"@en)\n  AnnotationAssertion(dct:description :Zero-KnowledgeProof\n    \"Foundational blockchain concept with formal ontological definition\"@en)\n  AnnotationAssertion(:termID :Zero-KnowledgeProof \"BC-0033\")\n  AnnotationAssertion(:priority :Zero-KnowledgeProof \"1\"^^xsd:integer)\n  AnnotationAssertion(:category :Zero-KnowledgeProof \"cryptographic-foundations\"@en)\n)\n      ```",
  "properties": {
    "id": "zero-knowledge-proof-owl-axioms",
    "collapsed": "true",
    "- public-access": "true",
    "- ontology": "true",
    "- term-id": "BC-0033",
    "- preferred-term": "Zero-Knowledge Proof",
    "- source-domain": "blockchain",
    "- status": "complete",
    "- version": "1.0.0",
    "- last-updated": "2025-10-28",
    "- definition": "Privacy-preserving verification within blockchain systems, providing essential functionality for distributed ledger technology operations and properties.",
    "- maturity": "mature",
    "- source": "[[ISO/IEC 23257:2021]], [[IEEE 2418.1]], [[NIST NISTIR]]",
    "- authority-score": "0.95",
    "- owl:class": "bc:Zero-knowledgeProof",
    "- owl:physicality": "VirtualEntity",
    "- owl:role": "Object",
    "- owl:inferred-class": "bc:VirtualObject",
    "- belongsToDomain": "[[CryptographicDomain]]",
    "- implementedInLayer": "[[SecurityLayer]]",
    "- is-subclass-of": "[[Blockchain Entity]], [[CryptographicPrimitive]]"
  },
  "backlinks": [],
  "wiki_links": [
    "SecurityLayer",
    "IEEE 2418.1",
    "Blockchain Entity",
    "CryptographicDomain",
    "ISO/IEC 23257:2021",
    "CryptographicPrimitive",
    "NIST NISTIR"
  ],
  "ontology": {
    "term_id": "BC-0033",
    "preferred_term": "Zero-Knowledge Proof",
    "definition": "Privacy-preserving verification within blockchain systems, providing essential functionality for distributed ledger technology operations and properties.",
    "source_domain": "blockchain",
    "maturity_level": null,
    "authority_score": 0.95
  }
}