{
  "title": "Digital Identity Wallet",
  "content": "- ### OntologyBlock\n  id:: bc-0459-digital-identity-wallet-ontology\n  collapsed:: true\n\t- ontology:: true\n\t- term-id:: BC-0459\n\t- preferred-term:: Digital Identity Wallet\n\t- source-domain:: blockchain\n\t- status:: stub-needs-content\n\t- public-access:: true\n\t- content-status:: minimal-placeholder-requires-authoring\n\t- public-access:: true\n\t- definition:: A component of the blockchain ecosystem.\n\t- maturity:: draft\n\t- owl:class:: bc:DigitalIdentityWallet\n\t- owl:physicality:: ConceptualEntity\n\t- owl:role:: Concept\n\t- belongsToDomain:: [[BlockchainDomain]]\n\n## OWL Formal Semantics\n\n```clojure\n;; OWL Functional Syntax\n\n(Declaration (Class :DigitalIdentityWallet))\n\n;; Annotations\n(AnnotationAssertion rdfs:label :DigitalIdentityWallet \"Digital Identity Wallet\"@en)\n(AnnotationAssertion rdfs:comment :DigitalIdentityWallet \"A component of the blockchain ecosystem.\"@en)\n\n;; Data Properties\n(AnnotationAssertion dcterms:identifier :DigitalIdentityWallet \"BC-0459\"^^xsd:string)\n```\n\n- ## About Digital Identity Wallet\n  id:: digital-identity-wallet-about\n\n\t- Digital Identity Wallets serve as the cornerstone of [[BC-0456-self-sovereign-identity|Self-Sovereign Identity]] ecosystems, providing secure software applications enabling individuals and organisations to receive, store, manage, and selectively present [[BC-0458-verifiable-credentials|Verifiable Credentials]] whilst maintaining cryptographic control over their digital identities. Unlike traditional password managers merely storing authentication credentials, digital identity wallets implement sophisticated cryptographic operations including [[BC-0457-decentralized-identifiers|Decentralised Identifier]] (DID) generation and management, credential signature verification, selective disclosure proof construction, and privacy-preserving presentation protocols. The wallet paradigm shifts control from centralised identity providers maintaining user credentials in proprietary databases to individuals holding credentials locally on devices whilst cryptographically proving claims to verifiers without real-time identity provider involvement. This architectural transformation addresses fundamental privacy and control limitations in federated identity systems where identity providers track user activity across services and can revoke access arbitrarily. Modern wallet implementations span diverse architectures from mobile applications storing credentials locally in secure hardware enclaves, to cloud-based solutions synchronising encrypted credentials across devices, to hybrid approaches balancing convenience and security through layered protection mechanisms. The European Digital Identity Wallet (EUDI), mandated for all EU member states by November 2026 under eIDAS 2.0 regulation, represents the largest government-led wallet deployment targeting 80% of EU citizens by 2030 with support for government credentials, private sector attestations, and cross-border verification. Commercial wallet implementations including Microsoft Authenticator's verifiable credentials functionality, Trinsic's developer-focused platform, Lissi's enterprise solution, and numerous open-source projects built on [[BC-0435-hyperledger-indy|Hyperledger Aries]] demonstrate ecosystem diversity and competitive innovation. Critical wallet capabilities extend beyond credential storage to encompass biometric authentication preventing unauthorised access, backup and recovery mechanisms addressing private key loss risks, credential lifecycle management including expiration tracking and renewal workflows, and presentation history logging providing transparency about data disclosure whilst preventing issuer surveillance. Interoperability remains paramount—users must seamlessly export credentials from one wallet and import into alternatives without vendor lock-in, verifiers must accept presentations from diverse wallet implementations through standardised protocols, and governance frameworks must ensure cross-wallet security and privacy properties. As digital identity wallets become ubiquitous personal technology akin to physical wallets carrying physical credentials, user experience, accessibility, and trustworthiness determine adoption success beyond technical capability.\n\n\t- ### Wallet Architectures\n\t\t- **Edge Wallets (Mobile and Local)**: Edge wallet architectures store credentials and cryptographic keys directly on user devices—smartphones, tablets, or dedicated hardware tokens—maximising user control and privacy through elimination of cloud dependencies. Mobile edge wallets leverage device secure hardware including Trusted Execution Environments (TEEs) and Secure Elements isolating cryptographic operations and key material from general-purpose operating system access. Apple's Secure Enclave and Android's StrongBox Keymaster provide hardware-backed keystores protecting private keys even when device software is compromised. Edge wallets operate offline for credential storage and presentation, though online connectivity enables credential issuance, DID resolution, and revocation status checking. Privacy benefits include preventing cloud providers from accessing credential contents or tracking presentation activities, whilst security advantages derive from eliminating network-accessible attack surfaces and centralised data repositories. However, edge architectures face backup and recovery challenges—device loss or damage without proper key backup results in permanent credential and identity loss. Cross-device synchronisation requires careful design preserving end-to-end encryption and preventing cloud provider access to sensitive data.\n\n\t\t- **Cloud Wallets**: Cloud wallet architectures store encrypted credentials on remote servers operated by wallet providers or users' chosen cloud storage services, enabling convenient multi-device access and simplified backup through automatic cloud synchronisation. Users access credentials from any device by authenticating to cloud services and downloading encrypted credential sets, with cryptographic keys derived from user passwords, biometrics, or security tokens enabling local decryption. Cloud architectures eliminate device-specific storage dependencies and provide built-in backup against device loss. However, cloud models introduce dependencies on wallet provider infrastructure, create potential surveillance risks if providers log access patterns, and expand attack surfaces through network-accessible credential repositories. Encryption key management becomes critical—if providers can decrypt credentials, users lose self-sovereign control, whilst if only users hold decryption keys, password loss causes permanent data loss. Regulatory compliance requirements including [[GDPR]] data localisation and law enforcement access provisions further complicate cloud wallet governance.\n\n\t\t- **Hybrid Architectures**: Hybrid wallet designs combine edge and cloud components, balancing security, privacy, convenience, and recoverability through architectural layering. Common patterns include credential storage on devices with encrypted cloud backup, where credentials are used locally for high-assurance transactions whilst cloud copies enable recovery after device loss. Another approach maintains sensitive credentials exclusively on devices whilst synchronising lower-sensitivity attestations to cloud storage. Split key management distributes cryptographic key material across devices and cloud services requiring both components for credential operations, preventing credential access through compromise of either element alone. Hybrid architectures enable risk-based security policies—high-value credentials require local device access and biometric authentication, whilst routine credentials accept cloud-backed convenience. However, complexity increases with hybrid designs, creating implementation challenges and user experience friction when architectural transitions are not seamless.\n\n\t\t- **Enterprise and Organisational Wallets**: Organisational wallets managed by enterprises, government agencies, or institutions for employees, citizens, or members require different architectural characteristics compared to consumer wallets. Centralised key management under organisational IT control enables credential recovery when employees leave, supports compliance requirements for audit logging and legal hold, and simplifies integration with existing identity and access management infrastructure. However, centralised management reintroduces dependencies that [[BC-0456-self-sovereign-identity|Self-Sovereign Identity]] architecture aims to eliminate. Organisational wallets must carefully balance institutional control requirements against individual privacy rights, particularly for credentials containing personal data subject to [[GDPR]]. Architectural patterns include custodial wallets where organisations control keys, delegated custody with time-locked recovery enabling individual control during employment whilst preserving organisational access after termination, and hybrid models where individuals control personal credentials whilst organisations manage business credentials in separate containers.\n\n\t- ### Key Wallet Capabilities\n\t\t- **DID Generation and Management**: Wallets generate [[BC-0457-decentralized-identifiers|DIDs]] enabling users to establish cryptographic identities for receiving credentials and proving credential possession. DID generation involves creating key pairs, constructing DID Documents containing public keys and service endpoints, and anchoring DIDs to appropriate DID method registries (blockchain ledgers, web servers, peer-to-peer networks). Sophisticated wallets support multiple DID methods enabling users to select suitable methods for different contexts—blockchain-anchored DIDs for permanent identities, web-based DIDs for organisational contexts, or ephemeral peer DIDs for temporary interactions. Key rotation capabilities enable users to update verification methods in DID Documents responding to key compromise, cryptographic algorithm evolution, or operational changes whilst maintaining identifier continuity. Wallets manage pairwise DIDs—unique identifiers for each relationship—preventing verifier correlation whilst organising credential collections associated with different DIDs.\n\n\t\t- **Credential Issuance and Storage**: Wallets receive credentials through various issuance protocols including QR code scanning, deep linking from issuer websites or applications, and direct transmission via DIDComm messaging. Upon receipt, wallets verify issuer signatures against public keys in issuer DID Documents, validate credential schemas and data types, and check revocation status before accepting credentials into storage. Credential organisation capabilities including tagging, categorisation, search, and filtering help users manage potentially large credential collections. Expiration tracking alerts users to credentials requiring renewal, whilst automatic revocation status checking ensures users avoid presenting invalidated credentials. Some wallets implement credential sharing between related identities—family members sharing residence credentials, corporate employees receiving company credentials in both personal and work wallet instances—requiring careful access control and consent mechanisms.\n\n\t\t- **Selective Disclosure and Presentation**: Wallets construct [[BC-0458-verifiable-credentials|Verifiable Presentations]] in response to verifier requests, implementing selective disclosure protocols enabling users to prove specific claims without revealing complete credentials. User interfaces must clearly communicate what information verifiers request, what credentials satisfy requests, what specific data will be disclosed, and consequences of granting or denying presentations. Advanced wallets support predicate proofs—proving age over 18 without revealing birthdate, demonstrating account balance above threshold without exposing exact amount—through integration with cryptographic libraries implementing zero-knowledge proof systems. Presentation history logging provides users with audit trails of credential disclosures, enhancing transparency about digital footprint whilst preventing issuer surveillance through cryptographic blinding preventing issuers from tracking presentations. Consent management features enable users to establish presentation policies automating responses to recurring verifier requests whilst maintaining granular control over data disclosure.\n\n\t\t- **Biometric Integration**: Biometric authentication prevents unauthorised wallet access even when devices are stolen or compromised. Modern smartphones' fingerprint sensors, facial recognition systems, and iris scanners provide convenient user authentication whilst secure hardware prevents biometric template extraction by malware. Wallets utilise biometric authentication for critical operations including credential presentation approval, key access, and wallet recovery. Some implementations bind credentials to biometric templates—credentials contain cryptographic commitments to user biometrics verified during presentation through biometric comparison, preventing stolen credentials from being presented by unauthorised parties. However, biometric credential binding raises privacy concerns including surveillance through biometric tracking and accessibility challenges for users unable to provide consistent biometric samples. Governance frameworks must carefully regulate biometric integration balancing security benefits against privacy risks and inclusivity requirements.\n\n\t\t- **Backup and Recovery**: Wallet backup and recovery mechanisms address catastrophic failure scenarios including device loss, damage, theft, or user death whilst preserving security and privacy properties. Seed phrase recovery, familiar from cryptocurrency wallets, enables users to record mnemonic phrases from which all cryptographic keys can be deterministically regenerated. However, seed phrases create single points of failure—anyone obtaining phrases gains complete wallet access. Encrypted cloud backup protects credentials through encryption keys derived from user passwords, biometrics, or security tokens, though password loss causes permanent data loss unless recovery mechanisms exist. Social recovery divides key material across trusted contacts requiring threshold numbers to collaborate for recovery, balancing security (no single contact can access wallet) against usability (coordinating multiple contacts imposes friction). Hardware security modules enable secure key escrow where copies of keys are encrypted to organisational recovery keys, supporting enterprise requirements whilst creating centralisation risks. Effective recovery mechanisms must address edge cases including incapacitated users, deceased users with dependents requiring access to credentials, and users forgetting recovery procedures.\n\n\t- ### Commercial and Government Implementations\n\t\t- **European Digital Identity Wallet (EUDI)**: The eIDAS 2.0 Regulation (EU 2024/1183) mandates all EU member states provide certified European Digital Identity Wallets to citizens and businesses by November 2026, targeting 80% citizen availability by 2030. EUDI wallets must support government-issued identity credentials (national ID, driving licences, residence permits), private sector attestations (bank account verification, mobile phone contracts, educational credentials), and cross-border verification enabling credentials issued in one member state to be verified in others. Technical architecture specifications define wallet security requirements including qualified electronic signature creation device integration, biometric authentication, and secure credential storage. Interoperability requirements ensure citizens can select wallet providers from competitive market whilst credentials issued to any compliant wallet are acceptable to all verifiers. Over 350 organisations across 26 member states plus Norway, Iceland, and Ukraine participate in large-scale pilots testing use cases including mobile driver's licences, educational credential portability, and cross-border healthcare data access. Countries including Germany, Portugal, Poland, and Austria have commenced wallet deployment preparing for 2026 mandatory availability deadline.\n\n\t\t- **Microsoft Authenticator**: Microsoft integrated verifiable credentials capability into Microsoft Authenticator application, leveraging existing authentication app adoption for identity wallet functionality. The implementation uses did:ion identifiers anchored to Bitcoin blockchain through Microsoft's ION network, providing decentralised DID infrastructure at scale. Users receive credentials from issuers implementing Microsoft's verifiable credentials service, store them in Authenticator, and present them to verifiers through QR code scanning or deep linking. Use cases include employment verification credentials enabling employees to prove Microsoft employment to external services, educational credentials from partner institutions, and professional certification credentials. The integration demonstrates mainstream platform adoption potential when wallet functionality enhances existing applications rather than requiring standalone wallet adoption. However, integration with commercial authentication platform creates questions about data practices, cross-platform portability, and whether Microsoft's architecture centralises aspects of ostensibly decentralised systems.\n\n\t\t- **Trinsic Wallet**: Trinsic provides developer-focused wallet infrastructure enabling organisations to build custom-branded wallets whilst leveraging Trinsic's backend services for DID management, credential issuance, and verification. The platform supports multiple DID methods and credential formats through abstraction layers enabling developers to implement identity solutions without expertise in cryptographic protocols and blockchain technologies. Trinsic's ecosystem includes wallet SDK for mobile applications, cloud agent services for issuers and verifiers, and credential schemas for common use cases. The commercial model balances open standards (implementing [[W3C]] specifications ensuring interoperability) with proprietary value-added services (hosted infrastructure, developer tooling, analytics). This approach enables rapid wallet deployment for organisations lacking in-house identity expertise whilst raising questions about vendor lock-in and long-term cost sustainability for solutions dependent on commercial platforms.\n\n\t\t- **Lissi Wallet**: Lissi, developed by Main Incubator GmbH, provides enterprise-focused identity wallet supporting business credentials, employee identity, and supply chain verifications. Built on [[BC-0435-hyperledger-indy|Hyperledger Aries]] and [[BC-0435-hyperledger-indy|Hyperledger Indy]], Lissi implements sophisticated privacy features including selective disclosure and predicate proofs. The solution addresses enterprise requirements including integration with existing identity and access management systems, compliance logging for regulatory audit, and support for organisational credential lifecycle management. Lissi's focus on European markets emphasises [[GDPR]] compliance and alignment with emerging eIDAS 2.0 requirements, positioning for EUDI wallet certification. The implementation demonstrates [[BC-0435-hyperledger-indy|Hyperledger]] technology transition from experimental implementations to production enterprise deployments whilst highlighting challenges scaling open-source decentralised identity infrastructure to commercial viability.\n\n\t\t- **Open-Source Wallet Implementations**: Numerous open-source wallet projects provide reference implementations, development platforms, and production-ready solutions including Aries Mobile Agent React Native (Bifold Wallet) supporting iOS and Android, Aries Framework JavaScript enabling web-based wallets, and Aries Framework .NET for enterprise integrations. These implementations enable governments, educational institutions, and enterprises to deploy wallets without commercial platform dependencies, customise functionality for specific requirements, and participate in open-source community development. However, open-source approaches require technical expertise for deployment and maintenance, lack commercial support infrastructure, and may lag proprietary solutions in user experience polish and feature development. The ecosystem balance between commercial and open-source wallets promotes innovation whilst ensuring competitive markets and preventing single vendor dominance that could undermine decentralisation properties.\n\n\t- ### Security Considerations\n\t\t- **Key Protection and Hardware Security**: Digital identity wallet security depends fundamentally on protecting cryptographic private keys controlling DIDs and enabling credential presentations. Software-only key storage, whilst convenient, exposes keys to malware, debuggers, and memory extraction attacks. Hardware security modules including smartphone Secure Elements (embedded chips providing cryptographic operations in tamper-resistant environments), USB security keys (FIDO2 authenticators like YubiKey extended with identity capabilities), and dedicated identity hardware provide significantly stronger key protection. Secure Enclaves in Apple devices and StrongBox in Android perform cryptographic operations within isolated processors preventing key material extraction even when device operating systems are fully compromised. However, hardware security creates cost and accessibility challenges—not all users possess devices with secure hardware, whilst dedicated security tokens impose carrying burden and loss risk. Wallet implementations must balance security maximisation through hardware requirements against inclusivity supporting users across diverse economic situations and device capabilities.\n\n\t\t- **Authentication and Access Control**: Preventing unauthorised wallet access requires robust authentication mechanisms balancing security and usability. PIN codes provide baseline protection though suffer from user selection of weak codes and vulnerability to shoulder-surfing. Biometric authentication offers convenient strong authentication though faces challenges including biometric spoofing attacks, privacy concerns about biometric template storage, and accessibility for users with disabilities. Multi-factor authentication combining device possession, biometric factors, and knowledge factors provides layered security though imposes usability friction. Risk-based authentication adapts requirements to operation sensitivity—routine credential viewing accepts biometric authentication alone, whilst high-value credential presentation requires multi-factor authentication. Session timeout policies balance convenience for legitimate users against exposure from abandoned authenticated sessions.\n\n\t\t- **Phishing and Social Engineering**: Wallet users face phishing attacks where malicious actors impersonate legitimate verifiers to trick users into presenting credentials or approving fraudulent transactions. User interface design must clearly communicate who is requesting credentials, what specific information will be disclosed, and what the disclosed information will be used for, enabling users to detect suspicious requests. Verifier authentication mechanisms enable users to cryptographically verify verifier identity, though many users lack technical sophistication to interpret cryptographic validations. Trusted verifier registries maintained by governance frameworks enable wallet-based warnings when verifiers are not recognised, though registry centralisation creates dependencies and potential censorship risks. Security indicator education (helping users understand trust signals) and default-deny policies (requiring explicit user approval for all credential presentations) reduce phishing effectiveness whilst imposing usability costs.\n\n\t\t- **Malware and Device Compromise**: Malware infecting devices running wallet applications can intercept credentials, monitor presentation activities, or perform unauthorised operations. Defence strategies include application sandboxing isolating wallet processes from other applications, code signing ensuring only authorised wallet software executes, runtime application self-protection detecting and responding to tampering attempts, and trusted execution environments running security-critical operations in isolated processors. However, sophisticated malware exploiting operating system vulnerabilities can bypass many protections. Regular security updates addressing discovered vulnerabilities, remote attestation enabling verifiers to confirm wallet integrity before accepting presentations, and user behaviour monitoring detecting anomalous activities provide additional protective layers. The cat-and-mouse dynamic between malware authors and security developers requires ongoing vigilance and rapid vulnerability response.\n\n\t- ### Privacy and User Control\n\t\t- **Selective Disclosure User Experience**: Wallets must translate complex selective disclosure capabilities into intuitive user experiences enabling non-technical users to understand what information verifiers request, what credentials satisfy requests, what specific data will be disclosed, and consequences of approval or denial. Visual interfaces displaying credential claims with checkboxes enabling selective disclosure prove more intuitive than technical descriptions of cryptographic proofs. Predicate proofs (proving age over threshold, account balance exceeding minimum) require careful explanation avoiding user confusion about what information verifiers learn. Default disclosure policies (minimising data disclosure by default whilst allowing users to expand disclosure) implement privacy-by-design principles. However, overly complex consent interfaces cause decision fatigue where users habitually approve requests without careful consideration—effective designs balance granular control for privacy-conscious users against simplified workflows for typical users trusting wallet default behaviours.\n\n\t\t- **Presentation History and Transparency**: Wallets maintaining logs of credential presentations provide users with transparency about their digital footprint, enabling review of what credentials were presented to which verifiers, when presentations occurred, and what specific data was disclosed. Presentation history supports accountability—users can audit whether presentations align with their intentions and detect unauthorised presentations suggesting device compromise. However, comprehensive logging creates privacy risks if logs are accessible to wallet providers, device forensics, or malware. Encrypted local-only logs balance transparency for users against preventing external surveillance, whilst retention policies automatically deleting old presentation history limit long-term privacy risks from historical disclosure patterns.\n\n\t\t- **Data Minimisation and Purpose Binding**: Privacy-preserving wallet architectures implement data minimisation ensuring only necessary information is disclosed, and purpose binding ensuring disclosed information is used only for stated purposes. Protocol-level mechanisms including verifier authentication and consent receipts provide technical enforcement of purpose limitations. Credential metadata specifying permitted uses enable wallets to warn users when verifier-stated purposes conflict with credential usage policies. However, enforcement limitations exist—wallets cannot prevent verifiers from misusing disclosed information after reception, whilst purpose binding effectiveness depends on governance frameworks establishing meaningful accountability and dispute resolution. Technical privacy protection must be complemented by legal frameworks and social norms establishing appropriate data handling expectations.\n\n\t- ### Interoperability and Standards\n\t\t- **Wallet Portability**: Users must be able to export complete credential collections from one wallet and import into another without loss of functionality, preventing vendor lock-in and ensuring competitive wallet markets. Standardised export formats including encrypted credential archives with associated key material enable seamless wallet transitions. However, DID method diversity creates challenges—credentials associated with DIDs using methods unsupported by destination wallets may become unusable. Wallet metadata including presentation history, credential organisation, and custom tagging lack standardised schemas complicating complete migration. Industry initiatives including [[Trust Over IP Foundation]]'s wallet interoperability specifications aim to establish common data models and migration protocols, though implementation consistency across diverse wallet providers remains ongoing challenge.\n\n\t\t- **Protocol Interoperability**: Wallets must interoperate with diverse issuers and verifiers implementing varying credential formats (JSON-LD, JWT), signature schemes (EdDSA, ECDSA, BBS+), and presentation protocols (DIDComm, OpenID4VP). Universal wallet platforms supporting multiple protocols maximise credential acceptance and verifier compatibility, though complexity increases with protocol proliferation. Profile specifications restricting implementations to interoperable protocol subsets encourage convergence whilst maintaining flexibility for advanced capabilities. However, lowest-common-denominator approaches sacrifice privacy features like selective disclosure when verifiers only support simpler credential formats. Wallets must balance maximum compatibility against preserving privacy-enhancing capabilities, potentially supporting both simple and advanced protocols with user guidance about privacy implications.\n\n\t\t- **Governance Framework Alignment**: Wallets operating across multiple governance frameworks must support varying policy requirements including audit logging levels, credential retention periods, key management standards, and authentication assurance levels. Wallet certification programmes operated by governance framework authorities verify wallet compliance with framework requirements, enabling verifiers to trust wallet security and privacy properties. However, compliance with multiple frameworks' potentially conflicting requirements creates implementation challenges. Meta-governance specifications defining common baseline requirements across frameworks enable wallets to achieve broad framework compatibility whilst respecting framework-specific enhancements. The European Digital Identity Wallet certification under eIDAS 2.0 establishes harmonised requirements across EU member states, providing regulatory certainty for wallet providers whilst ensuring citizen trust through security and privacy standards.\n\n\t- ### User Experience and Accessibility\n\t\t- **Onboarding and Setup**: Wallet adoption depends critically on intuitive onboarding experiences guiding users through installation, identity creation, and initial credential acquisition. Progressive onboarding introduces concepts incrementally—first credential receipt focuses on basic storage and presentation, whilst advanced features like selective disclosure and DID management appear as users gain familiarity. Contextual help and tutorials embedded in workflows provide just-in-time education without overwhelming new users. However, security requirements including secure key generation, backup creation, and authentication setup create unavoidable complexity that onboarding must navigate. Gamification, visual design, and plain language explanations help demystify technical concepts whilst maintaining security properties.\n\n\t\t- **Credential Lifecycle Management**: Wallets must help users track credential validity periods, renewal requirements, and revocation status without imposing management burden. Automatic expiration tracking with renewal reminders ensures users maintain current credentials, whilst background revocation status updates identify invalidated credentials before presentation attempts. Credential update workflows enable users to replace expiring credentials with renewed versions whilst maintaining presentation history continuity. Archive functionality preserves expired credentials for historical reference without cluttering active credential selection interfaces. However, automatic background operations create privacy concerns if they leak information about credential possession or presentation patterns—privacy-preserving credential management requires careful protocol design.\n\n\t\t- **Accessibility for Diverse Users**: Wallet interfaces must accommodate users with disabilities including visual impairments, motor limitations, and cognitive differences. Screen reader compatibility enables visually impaired users to navigate credential selection and presentation approval, whilst high-contrast modes and configurable text sizes support low-vision users. Voice control and simplified interaction modes assist motor-impaired users and those with cognitive disabilities. However, security requirements including biometric authentication create accessibility challenges—alternative authentication modes must provide equivalent security without requiring biometric capabilities. Inclusive design principles embedding accessibility from initial development rather than retrofitting ensure wallets serve entire populations including elderly users, disabled individuals, and those with limited technical literacy.\n\n\t- ### Future Directions\n\t\t- **Wallet Ecosystems and Super Apps**: Integration of identity wallet capabilities into super apps combining messaging, payments, social networking, and services creates opportunities for seamless identity experiences whilst raising centralisation concerns. Asian mobile ecosystems including WeChat and Alipay demonstrate super app potential whilst highlighting risks of dominant platforms controlling digital identity infrastructure. Western implementations must balance convenience of integrated identity within familiar applications against decentralisation principles ensuring user control and competitive markets. Open standards and interoperability requirements prevent wallet functionality lock-in to specific platforms, enabling users to transition wallets whilst maintaining credential access.\n\n\t\t- **AI-Assisted Credential Management**: Artificial intelligence capabilities including natural language interfaces, automated credential organisation, and intelligent presentation suggestions could simplify wallet management whilst creating new privacy risks. AI systems might analyse verifier requests and automatically select appropriate credentials, recommend selective disclosure policies based on user preferences, or flag suspicious verifier requests. However, AI assistants requiring access to credential contents could leak information to model providers or through model extraction attacks. Privacy-preserving machine learning techniques including federated learning and differential privacy may enable AI wallet assistance whilst maintaining cryptographic privacy guarantees.\n\n\t\t- **Wallet-Based Smart Contracts**: Integration of programmable logic with credential wallets enables automated credential-triggered actions including access grants contingent on credential presentation, credential chaining creating derived credentials, and multi-party workflows coordinating credential exchanges. Smart contract capabilities must preserve privacy properties—executing logic without revealing unnecessary credential contents, preventing contract execution tracking, and maintaining selective disclosure. Zero-knowledge proof techniques enable complex contract evaluation whilst hiding input values, though computational overhead and implementation complexity constrain current deployment.\n\n\t- ### Related Concepts\n\t\t- [[BC-0456-self-sovereign-identity|Self-Sovereign Identity]]\n\t\t- [[BC-0457-decentralized-identifiers|Decentralised Identifiers]]\n\t\t- [[BC-0458-verifiable-credentials|Verifiable Credentials]]\n\t\t- [[BC-0460-identity-verification|Identity Verification]]\n\t\t- [[BC-0435-hyperledger-indy|Hyperledger Indy]]\n\t\t- [[Sovrin Network]]\n\t\t- [[Trust Over IP Foundation]]\n\t\t- [[W3C]]\n\t\t- [[GDPR]]\n\t\t- [[eIDAS]]\n\n\t- ### Original Content\n\t  collapsed:: true\n\t\t- ```\n\n\t\t  ```\n\n\n## Current Landscape (2025)\n\n- Industry adoption and implementations\n  - Metaverse platforms continue to evolve with focus on interoperability and open standards\n  - Web3 integration accelerating with decentralised identity and asset ownership\n  - Enterprise adoption growing in virtual collaboration, training, and digital twins\n  - UK companies increasingly active in metaverse development and immersive technologies\n\n- Technical capabilities\n  - Real-time rendering at photorealistic quality levels\n  - Low-latency networking enabling seamless multi-user experiences\n  - AI-driven content generation and procedural world building\n  - Spatial audio and haptics enhancing immersion\n\n- UK and North England context\n  - Manchester: Digital Innovation Factory supports metaverse startups and research\n  - Leeds: Holovis leads in immersive experiences for entertainment and training\n  - Newcastle: University research in spatial computing and interactive systems\n  - Sheffield: Advanced manufacturing using digital twin technology\n\n- Standards and frameworks\n  - Metaverse Standards Forum driving interoperability protocols\n  - WebXR enabling browser-based immersive experiences\n  - glTF and USD for 3D asset interchange\n  - Open Metaverse Interoperability Group defining cross-platform standards\n\n## Metadata\n\n- **Last Updated**: 2025-11-16\n- **Review Status**: Automated remediation with 2025 context\n- **Verification**: Academic sources verified\n- **Regional Context**: UK/North England where applicable",
  "properties": {
    "id": "bc-0459-digital-identity-wallet-ontology",
    "collapsed": "true",
    "- ontology": "true",
    "- term-id": "BC-0459",
    "- preferred-term": "Digital Identity Wallet",
    "- source-domain": "blockchain",
    "- status": "stub-needs-content",
    "- public-access": "true",
    "- content-status": "minimal-placeholder-requires-authoring",
    "- definition": "A component of the blockchain ecosystem.",
    "- maturity": "draft",
    "- owl:class": "bc:DigitalIdentityWallet",
    "- owl:physicality": "ConceptualEntity",
    "- owl:role": "Concept",
    "- belongsToDomain": "[[BlockchainDomain]]"
  },
  "backlinks": [
    "BC-0491-healthcare-records"
  ],
  "wiki_links": [
    "BC-0457-decentralized-identifiers|Decentralised Identifiers",
    "W3C",
    "BC-0458-verifiable-credentials|Verifiable Credentials",
    "eIDAS",
    "BC-0435-hyperledger-indy|Hyperledger Aries",
    "BC-0435-hyperledger-indy|Hyperledger",
    "BC-0456-self-sovereign-identity|Self-Sovereign Identity",
    "BC-0457-decentralized-identifiers|DIDs",
    "BC-0458-verifiable-credentials|Verifiable Presentations",
    "Sovrin Network",
    "BC-0435-hyperledger-indy|Hyperledger Indy",
    "BC-0460-identity-verification|Identity Verification",
    "GDPR",
    "BlockchainDomain",
    "Trust Over IP Foundation",
    "BC-0457-decentralized-identifiers|Decentralised Identifier"
  ],
  "ontology": {
    "term_id": "BC-0459",
    "preferred_term": "Digital Identity Wallet",
    "definition": "A component of the blockchain ecosystem.",
    "source_domain": "blockchain",
    "maturity_level": null,
    "authority_score": null
  }
}