{
  "title": "Difficulty Target",
  "content": "- ### OntologyBlock\n  id:: difficulty-target-ontology\n  collapsed:: true\n\n  - **Identification**\n    - public-access:: true\n    - ontology:: true\n    - term-id:: BC-0067\n    - preferred-term:: Difficulty Target\n    - source-domain:: blockchain\n    - status:: complete\n    - version:: 1.0.0\n    - last-updated:: 2025-10-28\n\n  - **Definition**\n    - definition:: Mining success threshold within blockchain systems, providing essential functionality for distributed ledger technology operations and properties.\n    - maturity:: mature\n    - source:: [[ISO/IEC 23257:2021]], [[IEEE 2418.1]], [[NIST NISTIR]]\n    - authority-score:: 0.95\n\n  - **Semantic Classification**\n    - owl:class:: bc:DifficultyTarget\n    - owl:physicality:: VirtualEntity\n    - owl:role:: Object\n    - owl:inferred-class:: bc:VirtualObject\n    - belongsToDomain:: [[ConsensusDomain]]\n    - implementedInLayer:: [[ProtocolLayer]]\n\n  - #### Relationships\n    id:: difficulty-target-relationships\n    - is-subclass-of:: [[Blockchain Entity]], [[ConsensusProtocol]]\n\n  - #### OWL Axioms\n    id:: difficulty-target-owl-axioms\n    collapsed:: true\n    - ```clojure\n      Prefix(:=<http://metaverse-ontology.org/blockchain#>)\nPrefix(owl:=<http://www.w3.org/2002/07/owl#>)\nPrefix(rdf:=<http://www.w3.org/1999/02/22-rdf-syntax-ns#>)\nPrefix(xml:=<http://www.w3.org/XML/1998/namespace>)\nPrefix(xsd:=<http://www.w3.org/2001/XMLSchema#>)\nPrefix(rdfs:=<http://www.w3.org/2000/01/rdf-schema#>)\nPrefix(dct:=<http://purl.org/dc/terms/>)\n\nOntology(<http://metaverse-ontology.org/blockchain/BC-0067>\n  Import(<http://metaverse-ontology.org/blockchain/core>)\n\n  ## Class Declaration\n  Declaration(Class(:DifficultyTarget))\n\n  ## Subclass Relationships\n  SubClassOf(:DifficultyTarget :ConsensusProtocol)\n  SubClassOf(:DifficultyTarget :BlockchainEntity)\n\n  ## Essential Properties\n  SubClassOf(:DifficultyTarget\n    (ObjectSomeValuesFrom :partOf :Blockchain))\n\n  SubClassOf(:DifficultyTarget\n    (ObjectSomeValuesFrom :hasProperty :Property))\n\n  ## Data Properties\n  DataPropertyAssertion(:hasIdentifier :DifficultyTarget \"BC-0067\"^^xsd:string)\n  DataPropertyAssertion(:hasAuthorityScore :DifficultyTarget \"1.0\"^^xsd:decimal)\n  DataPropertyAssertion(:isFoundational :DifficultyTarget \"true\"^^xsd:boolean)\n\n  ## Object Properties\n  ObjectPropertyAssertion(:enablesFeature :DifficultyTarget :BlockchainFeature)\n  ObjectPropertyAssertion(:relatesTo :DifficultyTarget :RelatedConcept)\n\n  ## Annotations\n  AnnotationAssertion(rdfs:label :DifficultyTarget \"Difficulty Target\"@en)\n  AnnotationAssertion(rdfs:comment :DifficultyTarget\n    \"Mining success threshold\"@en)\n  AnnotationAssertion(dct:description :DifficultyTarget\n    \"Foundational blockchain concept with formal ontological definition\"@en)\n  AnnotationAssertion(:termID :DifficultyTarget \"BC-0067\")\n  AnnotationAssertion(:priority :DifficultyTarget \"1\"^^xsd:integer)\n  AnnotationAssertion(:category :DifficultyTarget \"consensus-fundamentals\"@en)\n)\n      ```",
  "properties": {
    "id": "difficulty-target-owl-axioms",
    "collapsed": "true",
    "- public-access": "true",
    "- ontology": "true",
    "- term-id": "BC-0067",
    "- preferred-term": "Difficulty Target",
    "- source-domain": "blockchain",
    "- status": "complete",
    "- version": "1.0.0",
    "- last-updated": "2025-10-28",
    "- definition": "Mining success threshold within blockchain systems, providing essential functionality for distributed ledger technology operations and properties.",
    "- maturity": "mature",
    "- source": "[[ISO/IEC 23257:2021]], [[IEEE 2418.1]], [[NIST NISTIR]]",
    "- authority-score": "0.95",
    "- owl:class": "bc:DifficultyTarget",
    "- owl:physicality": "VirtualEntity",
    "- owl:role": "Object",
    "- owl:inferred-class": "bc:VirtualObject",
    "- belongsToDomain": "[[ConsensusDomain]]",
    "- implementedInLayer": "[[ProtocolLayer]]",
    "- is-subclass-of": "[[Blockchain Entity]], [[ConsensusProtocol]]"
  },
  "backlinks": [],
  "wiki_links": [
    "NIST NISTIR",
    "IEEE 2418.1",
    "ISO/IEC 23257:2021",
    "ConsensusDomain",
    "ConsensusProtocol",
    "Blockchain Entity",
    "ProtocolLayer"
  ],
  "ontology": {
    "term_id": "BC-0067",
    "preferred_term": "Difficulty Target",
    "definition": "Mining success threshold within blockchain systems, providing essential functionality for distributed ledger technology operations and properties.",
    "source_domain": "blockchain",
    "maturity_level": null,
    "authority_score": 0.95
  }
}