{
  "title": "Nonce",
  "content": "- ### OntologyBlock\n  id:: nonce-ontology\n  collapsed:: true\n\n  - **Identification**\n    - public-access:: true\n    - ontology:: true\n    - term-id:: BC-0034\n    - preferred-term:: Nonce\n    - source-domain:: blockchain\n    - status:: complete\n    - version:: 1.0.0\n    - last-updated:: 2025-10-28\n\n  - **Definition**\n    - definition:: Number used once for cryptographic operations within blockchain systems, providing essential functionality for distributed ledger technology operations and properties.\n    - maturity:: mature\n    - source:: [[ISO/IEC 23257:2021]], [[IEEE 2418.1]], [[NIST NISTIR]]\n    - authority-score:: 0.95\n\n  - **Semantic Classification**\n    - owl:class:: bc:Nonce\n    - owl:physicality:: VirtualEntity\n    - owl:role:: Object\n    - owl:inferred-class:: bc:VirtualObject\n    - belongsToDomain:: [[CryptographicDomain]]\n    - implementedInLayer:: [[SecurityLayer]]\n\n  - #### Relationships\n    id:: nonce-relationships\n    - is-subclass-of:: [[Blockchain Entity]], [[CryptographicPrimitive]]\n\n  - #### OWL Axioms\n    id:: nonce-owl-axioms\n    collapsed:: true\n    - ```clojure\n      Prefix(:=<http://metaverse-ontology.org/blockchain#>)\nPrefix(owl:=<http://www.w3.org/2002/07/owl#>)\nPrefix(rdf:=<http://www.w3.org/1999/02/22-rdf-syntax-ns#>)\nPrefix(xml:=<http://www.w3.org/XML/1998/namespace>)\nPrefix(xsd:=<http://www.w3.org/2001/XMLSchema#>)\nPrefix(rdfs:=<http://www.w3.org/2000/01/rdf-schema#>)\nPrefix(dct:=<http://purl.org/dc/terms/>)\n\nOntology(<http://metaverse-ontology.org/blockchain/BC-0034>\n  Import(<http://metaverse-ontology.org/blockchain/core>)\n\n  ## Class Declaration\n  Declaration(Class(:Nonce))\n\n  ## Subclass Relationships\n  SubClassOf(:Nonce :CryptographicPrimitive)\n  SubClassOf(:Nonce :BlockchainEntity)\n\n  ## Essential Properties\n  SubClassOf(:Nonce\n    (ObjectSomeValuesFrom :partOf :Blockchain))\n\n  SubClassOf(:Nonce\n    (ObjectSomeValuesFrom :hasProperty :Property))\n\n  ## Data Properties\n  DataPropertyAssertion(:hasIdentifier :Nonce \"BC-0034\"^^xsd:string)\n  DataPropertyAssertion(:hasAuthorityScore :Nonce \"1.0\"^^xsd:decimal)\n  DataPropertyAssertion(:isFoundational :Nonce \"true\"^^xsd:boolean)\n\n  ## Object Properties\n  ObjectPropertyAssertion(:enablesFeature :Nonce :BlockchainFeature)\n  ObjectPropertyAssertion(:relatesTo :Nonce :RelatedConcept)\n\n  ## Annotations\n  AnnotationAssertion(rdfs:label :Nonce \"Nonce\"@en)\n  AnnotationAssertion(rdfs:comment :Nonce\n    \"Number used once for cryptographic operations\"@en)\n  AnnotationAssertion(dct:description :Nonce\n    \"Foundational blockchain concept with formal ontological definition\"@en)\n  AnnotationAssertion(:termID :Nonce \"BC-0034\")\n  AnnotationAssertion(:priority :Nonce \"1\"^^xsd:integer)\n  AnnotationAssertion(:category :Nonce \"cryptographic-foundations\"@en)\n)\n      ```\n\n- ## About Nonce\n  id:: nonce-about\n\n  - Number used once for cryptographic operations within blockchain systems, providing essential functionality for distributed ledger technology operations and properties.\n  -\n  - ### Key Characteristics\n    id:: nonce-characteristics\n    - 1. **Definitional Property**: Core defining characteristic\n    - 2. **Functional Property**: Operational behavior\n    - 3. **Structural Property**: Compositional elements\n    - 4. **Security Property**: Security guarantees provided\n    - 5. **Performance Property**: Efficiency considerations\n  -\n  - ### Technical Components\n    id:: nonce-components\n    - **Implementation**: How concept is realized technically\n    - **Verification**: Methods for validating correctness\n    - **Interaction**: Relationships with other components\n    - **Constraints**: Technical limitations and requirements\n  -\n  - ### Use Cases\n    id:: nonce-use-cases\n    - **1. Core Blockchain Operation**\n    - **Application**: Fundamental blockchain functionality\n    - **Example**: Practical implementation in major blockchains\n    - **Requirements**: Technical prerequisites\n    - **Benefits**: Value provided to blockchain systems\n  -\n  - ### Standards & References\n    id:: nonce-standards\n    - [[ISO/IEC 23257:2021]] - Blockchain and distributed ledger technologies\n    - [[IEEE 2418.1]] - Blockchain and distributed ledger technologies\n    - [[NIST NISTIR]] - Blockchain and distributed ledger technologies\n  -\n\n- ## Rise of Bots Aligns With Dead Internet Theory\n\t- According to [Imperva](https://www.imperva.com/blog/bad-bot-report-2022-edition/), bots made up 47.4% of internet traffic in 2022. This proliferation aligns with the once-dismissed [Dead Internet Theory](https://en.wikipedia.org/wiki/Dead_Internet_theory), suggesting that the web is increasingly driven by AI, bots, and algorithms rather than real human interaction. This isn’t just theory—evidence of widespread bot activity has been reported on platforms like [Instagram](https://www.adweek.com/social-marketing/study-15-million-russian-instagram-influencers-followers-are-bots/) and [Twitter](https://finance.yahoo.com/news/cia-expert-says-80-twitter-222337217.html), where AI-driven manipulation of follower counts and traffic has become endemic.\n\n- ## Rise of Bots Aligns With Dead Internet Theory\n\t- According to [Imperva](https://www.imperva.com/blog/bad-bot-report-2022-edition/), bots made up 47.4% of internet traffic in 2022. This proliferation aligns with the once-dismissed [Dead Internet Theory](https://en.wikipedia.org/wiki/Dead_Internet_theory), suggesting that the web is increasingly driven by AI, bots, and algorithms rather than real human interaction. This isn’t just theory—evidence of widespread bot activity has been reported on platforms like [Instagram](https://www.adweek.com/social-marketing/study-15-million-russian-instagram-influencers-followers-are-bots/) and [Twitter](https://finance.yahoo.com/news/cia-expert-says-80-twitter-222337217.html), where AI-driven manipulation of follower counts and traffic has become endemic.",
  "properties": {
    "id": "nonce-standards",
    "collapsed": "true",
    "- public-access": "true",
    "- ontology": "true",
    "- term-id": "BC-0034",
    "- preferred-term": "Nonce",
    "- source-domain": "blockchain",
    "- status": "complete",
    "- version": "1.0.0",
    "- last-updated": "2025-10-28",
    "- definition": "Number used once for cryptographic operations within blockchain systems, providing essential functionality for distributed ledger technology operations and properties.",
    "- maturity": "mature",
    "- source": "[[ISO/IEC 23257:2021]], [[IEEE 2418.1]], [[NIST NISTIR]]",
    "- authority-score": "0.95",
    "- owl:class": "bc:Nonce",
    "- owl:physicality": "VirtualEntity",
    "- owl:role": "Object",
    "- owl:inferred-class": "bc:VirtualObject",
    "- belongsToDomain": "[[CryptographicDomain]]",
    "- implementedInLayer": "[[SecurityLayer]]",
    "- is-subclass-of": "[[Blockchain Entity]], [[CryptographicPrimitive]]"
  },
  "backlinks": [],
  "wiki_links": [
    "CryptographicDomain",
    "ISO/IEC 23257:2021",
    "IEEE 2418.1",
    "Blockchain Entity",
    "CryptographicPrimitive",
    "SecurityLayer",
    "NIST NISTIR"
  ],
  "ontology": {
    "term_id": "BC-0034",
    "preferred_term": "Nonce",
    "definition": "Number used once for cryptographic operations within blockchain systems, providing essential functionality for distributed ledger technology operations and properties.",
    "source_domain": "blockchain",
    "maturity_level": null,
    "authority_score": 0.95
  }
}