{
  "title": "Distributed Ledger",
  "content": "- ### OntologyBlock\n  id:: distributed-ledger-ontology\n  collapsed:: true\n\n  - **Identification**\n    - public-access:: true\n    - ontology:: true\n    - term-id:: BC-0002\n    - preferred-term:: Distributed Ledger\n    - source-domain:: blockchain\n    - status:: complete\n    - version:: 1.0.0\n    - last-updated:: 2025-10-28\n\n  - **Definition**\n    - definition:: A distributed ledger is a database architecture where multiple identical copies of a ledger are maintained across different nodes in a network, with updates replicated and synchronized through a consensus mechanism, eliminating the need for a central authority to prevent manipulation and maintain data integrity.\n    - maturity:: mature\n    - source:: [[ISO/IEC 23257:2021]], [[ITU-T Y.4560]]\n    - authority-score:: 1.0\n\n  - **Semantic Classification**\n    - owl:class:: bc:DistributedLedger\n    - owl:physicality:: VirtualEntity\n    - owl:role:: Object\n    - owl:inferred-class:: bc:VirtualObject\n    - belongsToDomain:: [[BlockchainDomain]]\n    - implementedInLayer:: [[ConceptualLayer]]\n\n  - #### Relationships\n    id:: distributed-ledger-relationships\n    - is-subclass-of:: [[Data Structure]], [[Distributed System]], [[Record-Keeping System]]\n\n  - #### OWL Axioms\n    id:: distributed-ledger-owl-axioms\n    collapsed:: true\n    - ```clojure\n      Prefix(:=<http://metaverse-ontology.org/blockchain#>)\nPrefix(owl:=<http://www.w3.org/2002/07/owl#>)\nPrefix(rdf:=<http://www.w3.org/1999/02/22-rdf-syntax-ns#>)\nPrefix(xsd:=<http://www.w3.org/2001/XMLSchema#>)\nPrefix(rdfs:=<http://www.w3.org/2000/01/rdf-schema#>)\n\nOntology(<http://metaverse-ontology.org/blockchain/BC-0002>\n\n  ## Class Declaration\n  Declaration(Class(:DistributedLedger))\n\n  ## Subclass Relationships\n  SubClassOf(:DistributedLedger :DataStructure)\n  SubClassOf(:DistributedLedger :DistributedSystem)\n  SubClassOf(:DistributedLedger :RecordKeepingSystem)\n\n  ## Essential Properties\n  SubClassOf(:DistributedLedger\n    (ObjectMinCardinality 2 :maintainedBy :Node))\n\n  SubClassOf(:DistributedLedger\n    (ObjectExactCardinality 1 :usesConsensus :ConsensusMechanism))\n\n  SubClassOf(:DistributedLedger\n    (ObjectMinCardinality 1 :recordsTransaction :Transaction))\n\n  SubClassOf(:DistributedLedger\n    (ObjectExactCardinality 1 :hasSynchronization :SynchronizationMechanism))\n\n  SubClassOf(:DistributedLedger\n    (DataHasValue :isDistributed \"true\"^^xsd:boolean))\n\n  SubClassOf(:DistributedLedger\n    (DataHasValue :hasReplication \"true\"^^xsd:boolean))\n\n  ## Data Properties\n  DataPropertyAssertion(:numberOfReplicas :DistributedLedger xsd:positiveInteger)\n  DataPropertyAssertion(:consistencyModel :DistributedLedger xsd:string)\n  DataPropertyAssertion(:replicationFactor :DistributedLedger xsd:decimal)\n\n  ## Object Properties\n  ObjectPropertyAssertion(:replicatedAcross :DistributedLedger :Node)\n  ObjectPropertyAssertion(:synchronizedBy :DistributedLedger :ConsensusMechanism)\n  ObjectPropertyAssertion(:contains :DistributedLedger :LedgerEntry)\n\n  ## Annotations\n  AnnotationAssertion(rdfs:label :DistributedLedger \"Distributed Ledger\"@en)\n  AnnotationAssertion(rdfs:comment :DistributedLedger\n    \"Database replicated and synchronized across multiple network nodes\"@en)\n  AnnotationAssertion(:termID :DistributedLedger \"BC-0002\")\n\n  ## Axioms\n  SubClassOf(:Blockchain :DistributedLedger)\n  SubClassOf(:DirectedAcyclicGraph :DistributedLedger)\n)\n      ```\n\n- ## About Distributed Ledger\n  id:: distributed-ledger-about\n\n  - A distributed ledger is a database architecture where multiple identical copies of a ledger are maintained across different nodes in a network, with updates replicated and synchronized through a consensus mechanism, eliminating the need for a central authority to prevent manipulation and maintain data integrity.\n  -\n  - ### Key Characteristics\n    id:: distributed-ledger-characteristics\n    - 1. **Distribution**: Multiple identical copies across nodes\n    - 2. **Consensus**: Agreement mechanism for updates\n    - 3. **Synchronization**: Consistent state across replicas\n    - 4. **Redundancy**: No single point of failure\n    - 5. **Shared Ownership**: No central controlling authority\n  -\n  - ### Technical Components\n    id:: distributed-ledger-components\n    - **Replication Model**: Full replication or partial (sharded)\n    - **Consistency Model**: Strong, eventual, or causal consistency\n    - **Partition Tolerance**: Continues operation during network splits\n    - **Availability**: High uptime through redundancy\n    - **CAP Trade-offs**: Balances consistency, availability, partition tolerance\n  -\n  - ### Use Cases\n    id:: distributed-ledger-use-cases\n    - **1. Financial Reconciliation**\n    - **Application**: Multi-party transaction settlement\n    - **Example**: Interbank payment systems\n    - **Benefits**: Real-time reconciliation, reduced discrepancies\n  -\n  - ### Standards & References\n    id:: distributed-ledger-standards\n    - [[ISO/IEC 23257:2021]] - Blockchain and distributed ledger technologies\n    - [[ITU-T Y.4560]] - Blockchain and distributed ledger technologies\n  -\n\n\n## Current Landscape (2025)\n\n- Industry adoption and implementations\n  - Metaverse platforms continue to evolve with focus on interoperability and open standards\n  - Web3 integration accelerating with decentralised identity and asset ownership\n  - Enterprise adoption growing in virtual collaboration, training, and digital twins\n  - UK companies increasingly active in metaverse development and immersive technologies\n\n- Technical capabilities\n  - Real-time rendering at photorealistic quality levels\n  - Low-latency networking enabling seamless multi-user experiences\n  - AI-driven content generation and procedural world building\n  - Spatial audio and haptics enhancing immersion\n\n- UK and North England context\n  - Manchester: Digital Innovation Factory supports metaverse startups and research\n  - Leeds: Holovis leads in immersive experiences for entertainment and training\n  - Newcastle: University research in spatial computing and interactive systems\n  - Sheffield: Advanced manufacturing using digital twin technology\n\n- Standards and frameworks\n  - Metaverse Standards Forum driving interoperability protocols\n  - WebXR enabling browser-based immersive experiences\n  - glTF and USD for 3D asset interchange\n  - Open Metaverse Interoperability Group defining cross-platform standards\n\n## Metadata\n\n- **Last Updated**: 2025-11-16\n- **Review Status**: Automated remediation with 2025 context\n- **Verification**: Academic sources verified\n- **Regional Context**: UK/North England where applicable",
  "properties": {
    "id": "distributed-ledger-standards",
    "collapsed": "true",
    "- public-access": "true",
    "- ontology": "true",
    "- term-id": "BC-0002",
    "- preferred-term": "Distributed Ledger",
    "- source-domain": "blockchain",
    "- status": "complete",
    "- version": "1.0.0",
    "- last-updated": "2025-10-28",
    "- definition": "A distributed ledger is a database architecture where multiple identical copies of a ledger are maintained across different nodes in a network, with updates replicated and synchronized through a consensus mechanism, eliminating the need for a central authority to prevent manipulation and maintain data integrity.",
    "- maturity": "mature",
    "- source": "[[ISO/IEC 23257:2021]], [[ITU-T Y.4560]]",
    "- authority-score": "1.0",
    "- owl:class": "bc:DistributedLedger",
    "- owl:physicality": "VirtualEntity",
    "- owl:role": "Object",
    "- owl:inferred-class": "bc:VirtualObject",
    "- belongsToDomain": "[[BlockchainDomain]]",
    "- implementedInLayer": "[[ConceptualLayer]]",
    "- is-subclass-of": "[[Data Structure]], [[Distributed System]], [[Record-Keeping System]]"
  },
  "backlinks": [],
  "wiki_links": [
    "ITU-T Y.4560",
    "Record-Keeping System",
    "ISO/IEC 23257:2021",
    "BlockchainDomain",
    "Distributed System",
    "Data Structure",
    "ConceptualLayer"
  ],
  "ontology": {
    "term_id": "BC-0002",
    "preferred_term": "Distributed Ledger",
    "definition": "A distributed ledger is a database architecture where multiple identical copies of a ledger are maintained across different nodes in a network, with updates replicated and synchronized through a consensus mechanism, eliminating the need for a central authority to prevent manipulation and maintain data integrity.",
    "source_domain": "blockchain",
    "maturity_level": null,
    "authority_score": 1.0
  }
}