{
  "title": "Block Height",
  "content": "- ### OntologyBlock\n  id:: block-height-ontology\n  collapsed:: true\n\n  - **Identification**\n    - public-access:: true\n    - ontology:: true\n    - term-id:: BC-0011\n    - preferred-term:: Block Height\n    - source-domain:: blockchain\n    - status:: complete\n    - version:: 1.0.0\n    - last-updated:: 2025-10-28\n\n  - **Definition**\n    - definition:: Number of blocks from genesis within blockchain systems, providing essential functionality for distributed ledger technology operations and properties.\n    - maturity:: mature\n    - source:: [[ISO/IEC 23257:2021]], [[IEEE 2418.1]], [[NIST NISTIR]]\n    - authority-score:: 0.95\n\n  - **Semantic Classification**\n    - owl:class:: bc:BlockHeight\n    - owl:physicality:: VirtualEntity\n    - owl:role:: Object\n    - owl:inferred-class:: bc:VirtualObject\n    - belongsToDomain:: [[BlockchainDomain]]\n\n  - #### OWL Restrictions\n    - is-subclass-of some Distributeddatastructure\n    - is-subclass-of some BlockchainEntity\n\n  - #### CrossDomainBridges\n    - bridges-to:: [[Distributeddatastructure]] via is-subclass-of\n\n  - #### OWL Restrictions\n    - is-subclass-of some Distributeddatastructure\n    - is-subclass-of some BlockchainEntity\n    - implementedInLayer:: [[ConceptualLayer]]\n\n  - #### Relationships\n    id:: block-height-relationships\n    - is-subclass-of:: [[Blockchain Entity]], [[DistributedDataStructure]]\n\n  - #### OWL Axioms\n    id:: block-height-owl-axioms\n    collapsed:: true\n    - ```clojure\n      Prefix(:=<http://metaverse-ontology.org/blockchain#>)\nPrefix(owl:=<http://www.w3.org/2002/07/owl#>)\nPrefix(rdf:=<http://www.w3.org/1999/02/22-rdf-syntax-ns#>)\nPrefix(xml:=<http://www.w3.org/XML/1998/namespace>)\nPrefix(xsd:=<http://www.w3.org/2001/XMLSchema#>)\nPrefix(rdfs:=<http://www.w3.org/2000/01/rdf-schema#>)\nPrefix(dct:=<http://purl.org/dc/terms/>)\n\nOntology(<http://metaverse-ontology.org/blockchain/BC-0011>\n  Import(<http://metaverse-ontology.org/blockchain/core>)\n\n  ## Class Declaration\n  Declaration(Class(:BlockHeight))\n\n  ## Subclass Relationships\n  SubClassOf(:BlockHeight :DistributedDataStructure)\n  SubClassOf(:BlockHeight :BlockchainEntity)\n\n  ## Essential Properties\n  SubClassOf(:BlockHeight\n    (ObjectSomeValuesFrom :partOf :Blockchain))\n\n  SubClassOf(:BlockHeight\n    (ObjectSomeValuesFrom :hasProperty :Property))\n\n  ## Data Properties\n  DataPropertyAssertion(:hasIdentifier :BlockHeight \"BC-0011\"^^xsd:string)\n  DataPropertyAssertion(:hasAuthorityScore :BlockHeight \"1.0\"^^xsd:decimal)\n  DataPropertyAssertion(:isFoundational :BlockHeight \"true\"^^xsd:boolean)\n\n  ## Object Properties\n  ObjectPropertyAssertion(:enablesFeature :BlockHeight :BlockchainFeature)\n  ObjectPropertyAssertion(:relatesTo :BlockHeight :RelatedConcept)\n\n  ## Annotations\n  AnnotationAssertion(rdfs:label :BlockHeight \"Block Height\"@en)\n  AnnotationAssertion(rdfs:comment :BlockHeight\n    \"Number of blocks from genesis\"@en)\n  AnnotationAssertion(dct:description :BlockHeight\n    \"Foundational blockchain concept with formal ontological definition\"@en)\n  AnnotationAssertion(:termID :BlockHeight \"BC-0011\")\n  AnnotationAssertion(:priority :BlockHeight \"1\"^^xsd:integer)\n  AnnotationAssertion(:category :BlockHeight \"blockchain-fundamentals\"@en)\n)\n      ```",
  "properties": {
    "id": "block-height-owl-axioms",
    "collapsed": "true",
    "- public-access": "true",
    "- ontology": "true",
    "- term-id": "BC-0011",
    "- preferred-term": "Block Height",
    "- source-domain": "blockchain",
    "- status": "complete",
    "- version": "1.0.0",
    "- last-updated": "2025-10-28",
    "- definition": "Number of blocks from genesis within blockchain systems, providing essential functionality for distributed ledger technology operations and properties.",
    "- maturity": "mature",
    "- source": "[[ISO/IEC 23257:2021]], [[IEEE 2418.1]], [[NIST NISTIR]]",
    "- authority-score": "0.95",
    "- owl:class": "bc:BlockHeight",
    "- owl:physicality": "VirtualEntity",
    "- owl:role": "Object",
    "- owl:inferred-class": "bc:VirtualObject",
    "- belongsToDomain": "[[BlockchainDomain]]",
    "- bridges-to": "[[Distributeddatastructure]] via is-subclass-of",
    "- implementedInLayer": "[[ConceptualLayer]]",
    "- is-subclass-of": "[[Blockchain Entity]], [[DistributedDataStructure]]"
  },
  "backlinks": [],
  "wiki_links": [
    "ConceptualLayer",
    "BlockchainDomain",
    "Blockchain Entity",
    "ISO/IEC 23257:2021",
    "DistributedDataStructure",
    "IEEE 2418.1",
    "NIST NISTIR",
    "Distributeddatastructure"
  ],
  "ontology": {
    "term_id": "BC-0011",
    "preferred_term": "Block Height",
    "definition": "Number of blocks from genesis within blockchain systems, providing essential functionality for distributed ledger technology operations and properties.",
    "source_domain": "blockchain",
    "maturity_level": null,
    "authority_score": 0.95
  }
}