{
  "title": "Governance Token",
  "content": "- ### OntologyBlock\n  id:: bc-0463-governance-token-ontology\n  collapsed:: true\n\t- ontology:: true\n\t- term-id:: BC-0463\n\t- preferred-term:: Governance Token\n\t- source-domain:: blockchain\n\t- status:: stub-needs-content\n\t- public-access:: true\n\t- content-status:: minimal-placeholder-requires-authoring\n\t- public-access:: true\n\t- definition:: A component of the blockchain ecosystem.\n\t- maturity:: draft\n\t- owl:class:: bc:GovernanceToken\n\t- owl:physicality:: ConceptualEntity\n\t- owl:role:: Concept\n\t- belongsToDomain:: [[BlockchainDomain]]\n\n## OWL Formal Semantics\n\n```clojure\n;; OWL Functional Syntax\n\n(Declaration (Class :GovernanceToken))\n\n;; Annotations\n(AnnotationAssertion rdfs:label :GovernanceToken \"Governance Token\"@en)\n(AnnotationAssertion rdfs:comment :GovernanceToken \"A component of the blockchain ecosystem.\"@en)\n\n;; Data Properties\n(AnnotationAssertion dcterms:identifier :GovernanceToken \"BC-0463\"^^xsd:string)\n```\n\n- ## About Governance Token\n  id:: governance-token-about\n\n  Governance tokens represent cryptographic assets that confer voting rights and protocol decision-making authority to holders, fundamentally reimagining corporate equity by unbundling economic ownership from governance participation, enabling [[BC-0461-decentralized-autonomous-organization|DAOs]] to distribute political power transparently through blockchain-based tokens rather than traditional shareholder structures mediated by brokers, custodians, and legal intermediaries. Unlike conventional corporate shares where voting rights are typically proportional to economic stake and exercised through intermediary-managed proxy systems with opacity around vote counting, governance tokens create **programmable governance** where voting power, delegation mechanisms, quorum requirements, and execution logic are encoded in auditable [[BC-0142-smart-contract|smart contracts]], enabling anyone to verify governance processes whilst simultaneously creating novel attack vectors (flash loan governance attacks, vote buying markets, whale plutocracy) and regulatory uncertainties (securities classification, taxation, fiduciary duties). The explosion of governance token issuance through 2020-2025—catalyzed by [[Compound]]'s pioneering COMP distribution in June 2020—distributed over $100 billion in governance token value across thousands of protocols, with major tokens like UNI ([[Uniswap]]), MKR ([[MakerDAO]]), AAVE ([[Aave]]), CRV ([[Curve]]), and ENS achieving multi-billion-dollar market capitalizations and facilitating decentralised governance of protocols managing $25+ billion in total value locked. This period simultaneously demonstrated governance tokens' capacity to coordinate global communities around protocol development and exposed persistent challenges: extreme wealth concentration (top 1% of holders typically controlling 70-85% of voting power), voter apathy (5-15% typical participation rates), securities law ambiguity (SEC enforcement actions against numerous token issuers), and the fundamental tension between decentralisation ideals and governance efficiency requiring expert participation.\n\n  ### Technical Architecture and Token Standards\n\n  Governance tokens extend standard fungible token specifications (ERC-20 on Ethereum) with additional functionality enabling voting, delegation, and historical balance tracking:\n\n  **ERC-20 Base Standard:**\n\n  The foundational fungible token standard on Ethereum implementing:\n  - `balanceOf(address)`: Query token balance for address\n  - `transfer(address, uint256)`: Transfer tokens between addresses\n  - `approve(address, uint256)`: Authorize third-party spending\n  - `transferFrom(address, address, uint256)`: Execute approved transfers\n\n  **ERC-20Votes Extension (OpenZeppelin):**\n\n  Governance tokens typically implement `ERC20Votes`, adding:\n\n  - **Historical balance snapshots**: `getPastVotes(address account, uint256 blockNumber)` queries voting power at specific block, preventing flash loan manipulation where attackers borrow tokens, vote, and return within single transaction. When proposal is created, the Governor contract records current block number, and voting power is calculated from balances at that block rather than current balances.\n\n  - **Vote delegation**: `delegate(address delegatee)` enables token holders to assign voting power to another address without transferring economic ownership. Delegation is transitive—if Alice delegates to Bob, and Bob delegates to Carol, Carol receives Alice's voting power. This separation of economic stake from governance participation enables liquid democracy where passive holders delegate to active community members, professional delegates, or protocol experts.\n\n  - **Checkpointing mechanism**: Internal mappings track balance changes at block numbers, enabling efficient historical lookups without scanning entire blockchain history. Each transfer/delegation triggers checkpoint update, recording new balance at current block.\n\n  - **Nonce tracking**: Supports EIP-712 typed signatures for gasless delegation via meta-transactions (user signs delegation message off-chain, third party submits on-chain paying gas fees).\n\n  **Example Implementation (Simplified):**\n\n  ```solidity\n  contract GovernanceToken is ERC20Votes {\n      constructor() ERC20(\"Protocol Token\", \"TOKEN\") ERC20Permit(\"TOKEN\") {\n          _mint(msg.sender, 1_000_000_000 * 10**18); // 1B tokens\n      }\n\n      function _afterTokenTransfer(address from, address to, uint256 amount)\n          internal override(ERC20Votes)\n      {\n          super._afterTokenTransfer(from, to, amount);\n          // Updates checkpoints automatically\n      }\n  }\n  ```\n\n  **Vote-Escrowed Tokens (veToken Model):**\n\n  Pioneered by [[Curve Finance]] with veCRV, this model requires **locking** tokens for extended periods to receive voting power:\n\n  - **Lock mechanism**: Users lock governance tokens for duration (e.g., 1 week to 4 years), receiving non-transferable vote-escrowed tokens (veCRV, veBAL, etc.)\n\n  - **Voting power formula**: `veTokens = Locked Amount × (Lock Time Remaining / Max Lock Time)`\n    - 1,000 CRV locked 4 years = 1,000 veCRV initially\n    - 1,000 CRV locked 1 year = 250 veCRV initially\n    - veCRV balance decays linearly as lock expiration approaches\n\n  - **Benefits**: Creates long-term alignment (cannot immediately exit after extractive votes), concentrates governance amongst committed participants, provides additional utility (veCRV earns trading fees, determines liquidity gauge allocations)\n\n  - **Liquidity cost**: Locked tokens cannot be sold during market downturns, creating significant opportunity cost and reducing token liquidity\n\n  ### Token Distribution Strategies\n\n  Governance token distribution profoundly influences decentralisation, regulatory classification, and community alignment. Major distribution models from 2020-2025:\n\n  **Liquidity Mining / Yield Farming (Compound Model):**\n\n  [[Compound]]'s June 2020 COMP distribution catalyzed the \"DeFi Summer,\" becoming the template for governance token launches:\n\n  - **Mechanism**: Distribute tokens proportional to protocol usage (lending, borrowing, liquidity provision). Compound allocated **~2,880 COMP daily** (42.3% of total supply over 4 years) to users proportional to interest paid/earned.\n\n  - **Benefits**: Distributes governance to active users rather than passive investors, creates organic user acquisition (users farm tokens whilst using protocol), aligns governance with protocol participants.\n\n  - **Drawbacks**: Favors large capital deployers (\"whales\" with millions in capital earn disproportionate tokens), creates mercenary behaviour (users farm tokens without long-term commitment, immediately selling), potential securities law issues (distributing tokens to users as compensation for protocol usage).\n\n  **Retroactive Airdrops (Uniswap Model):**\n\n  [[Uniswap]]'s September 2020 UNI airdrop (400 UNI to anyone who used protocol before September 1, 2020) distributed **~15% of total supply** to early users:\n\n  - **Mechanism**: Snapshot historical protocol users, distribute tokens based on past activity (trading volume, liquidity provision, transaction count).\n\n  - **Benefits**: Rewards early adopters who took risk using protocol before token existed, creates instant global community, avoids mercenary farming behaviour.\n\n  - **Drawbacks**: Sybil attacks (users create hundreds of addresses to farm airdrop), airdrop hunters who used protocol once solely to qualify for potential token, securities law concerns (retroactive compensation for past usage), rewarding past behaviour rather than future alignment.\n\n  **Fair Launch (No Premine):**\n\n  Some protocols distributed 100% of tokens through public mechanisms without team/investor allocation:\n\n  - **Examples**: Yearn Finance (YFI), Olympus DAO (OHM initially)\n\n  - **Mechanism**: Tokens distributed entirely through staking, liquidity provision, or community contribution—no presale, no team allocation, no venture capital.\n\n  - **Benefits**: Maximum decentralisation, no insider ownership, credible neutrality, avoids securities classification (no \"efforts of others\" if no founding team retains tokens).\n\n  - **Drawbacks**: Developers lack financial incentive to maintain protocol long-term, creates coordination challenges without funded foundation, realistically captured by sophisticated actors who farm from launch.\n\n  **Venture-Backed Model with Vesting:**\n\n  Traditional web3 model allocating tokens to team, investors, advisors with multi-year vesting:\n\n  - **Example allocation** (typical):\n    - Community/Treasury: 40-60%\n    - Team: 15-25% (4-year vest, 1-year cliff)\n    - Investors: 15-25% (2-4 year vest)\n    - Advisors: 1-5% (2-4 year vest)\n\n  - **Benefits**: Funds development before protocol generates revenue, aligns team for long-term through vesting, provides governance leadership during early phase.\n\n  - **Drawbacks**: Creates centralized ownership (VCs control large positions), team tokens unlock creating selling pressure, securities law compliance requirements, less credible decentralisation.\n\n  ### Real-World Governance Token Implementations\n\n  **UNI (Uniswap Governance Token):**\n\n  Launched September 2020 to govern the world's largest decentralised exchange:\n\n  - **Total Supply**: 1 billion UNI\n  - **Distribution**:\n    - Community treasury: 43% (430M UNI)\n    - Historical users airdrop: 15% (150M UNI, including 400 UNI to each past user)\n    - Team: 21.5% (4-year vest)\n    - Investors: 17.8% (4-year vest)\n    - Advisors: 0.7%\n\n  - **Governance Rights**: Protocol fee switch, treasury spending, liquidity mining programs, cross-chain deployments, upgrades\n\n  - **Market Metrics (2024)**:\n    - Market cap: ~$4.2B ($7.50/UNI)\n    - Treasury value: ~$3.2B (430M UNI)\n    - Circulating supply: ~570M (~57%)\n    - Top 10 holders: ~40% of supply\n    - Daily trading volume: $150-300M\n\n  - **Governance Thresholds**:\n    - Proposal creation: 2.5M UNI (0.25% supply, ~$19M)\n    - Quorum: 40M UNI (4% supply)\n    - Voting period: 7 days\n    - Typical participation: 5-10% of circulating supply\n\n  **COMP (Compound Governance Token):**\n\n  Pioneered the DeFi governance model in June 2020:\n\n  - **Total Supply**: 10 million COMP\n  - **Distribution**:\n    - Liquidity mining: 42.3% (distributed over 4 years to users)\n    - Shareholders (team/investors): 25% (4-year vest)\n    - Founder/team: 22.3% (4-year vest)\n    - Future team: 7.8%\n    - Community: 2.6%\n\n  - **Governance Rights**: Interest rate models, collateral factors, reserve factors, asset listings, COMP distribution rates, protocol upgrades\n\n  - **Market Metrics (2024)**:\n    - Market cap: ~$930M ($93/COMP)\n    - Circulating supply: ~7.3M (~73%)\n    - Top 10 holders: ~42% of supply\n    - Treasury value (protocol reserves): ~$450M\n\n  - **Governance Thresholds**:\n    - Proposal creation: 400K COMP (4% supply, ~$37M)\n    - Quorum: 400K COMP (4%)\n    - Voting period: 7 days\n    - Timelock: 2 days\n\n  - **Innovation**: Pioneered governance mining, influencing entire DeFi industry. First to implement Governor Bravo contract (became industry standard).\n\n  **MKR (MakerDAO Governance Token):**\n\n  The original DeFi governance token (launched 2014, formal governance 2017):\n\n  - **Total Supply**: ~977,000 MKR (supply fluctuates: MKR burned from fees when DAI demand exceeds supply, minted/auctioned when system is undercollateralized)\n\n  - **Distribution**: No formal token sale; distributed to early contributors, sold in various private sales 2015-2018, now primarily trades on open market\n\n  - **Governance Rights**: DAI stability fee, debt ceilings, collateral onboarding, DAI Savings Rate (DSR), oracle price feeds, emergency shutdown\n\n  - **Market Metrics (2024)**:\n    - Market cap: ~$1.3B ($1,330/MKR)\n    - Circulating supply: ~977K MKR\n    - Top 50 holders: ~80% of supply (extremely concentrated)\n    - Daily volume: $20-60M\n\n  - **Unique Mechanics**:\n    - **Continuous approval voting**: No quorum; executive vote with most MKR support is active until overtaken by new proposal\n    - **Emergency shutdown**: 50K MKR can trigger shutdown, halting protocol\n    - **Dual governance**: Governance polls (non-binding sentiment) + Executive votes (binding execution)\n    - **Value capture**: MKR burned when system is profitable (reduces supply), minted when undercollateralized (increases supply/dilutes holders)\n\n  **CRV (Curve DAO Token):**\n\n  Pioneered vote-escrow tokenomics influencing dozens of subsequent protocols:\n\n  - **Total Supply**: 3.03 billion CRV (inflating over 300 years, majority distributed in first decade)\n\n  - **Distribution**:\n    - Liquidity providers: 62% (distributed over time via liquidity mining)\n    - Shareholders (team/investors): 30% (vested over 2-4 years)\n    - Community reserve: 5%\n    - Employees: 3%\n\n  - **Governance Rights**: Liquidity gauge weights (which pools receive CRV emissions), parameter changes, fee structures, new pool deployments\n\n  - **Market Metrics (2024)**:\n    - Market cap: ~$450M ($0.33/CRV)\n    - Circulating supply: ~1.6B (~53%)\n    - Total veCRV: ~450M (from ~580M locked CRV)\n    - Daily volume: $50-150M\n\n  - **veCRV Mechanism**:\n    - Lock CRV for 1 week to 4 years → receive veCRV\n    - veCRV = CRV × (lock time / 4 years)\n    - veCRV is non-transferable, decays linearly until lock expiration\n    - veCRV earns 50% of trading fees\n    - veCRV determines liquidity gauge weights (which pools receive emissions)\n\n  - **Curve Wars**: Protocols accumulated massive veCRV positions to direct emissions to their pools, with Convex Finance controlling >50% of all veCRV at peak, creating meta-governance layer.\n\n  **AAVE (Aave Protocol Governance Token):**\n\n  Governs the leading decentralised lending protocol ($10B+ TVL at peak):\n\n  - **Total Supply**: 16 million AAVE\n\n  - **Distribution**: AAVE migrated from LEND token in 2020 (100 LEND = 1 AAVE), combining governance with protocol safety module staking\n\n  - **Governance Rights**: Interest rate parameters, collateral factors, asset listings, protocol fees, liquidity mining incentives, treasury spending\n\n  - **Dual-Token Model**:\n    - **AAVE**: Governance + staking in Safety Module (earns fees, acts as insurance capital)\n    - **stkAAVE**: Staked AAVE (voting power + fee earning + slashing risk if protocol suffers deficit)\n\n  - **Market Metrics (2024)**:\n    - Market cap: ~$2.4B ($155/AAVE)\n    - Circulating supply: ~15M (~93%)\n    - Staked in Safety Module: ~2.8M AAVE (~18%)\n    - Top 10 holders: ~38% of supply\n\n  - **Governance Thresholds**:\n    - Proposition power (create proposal): 80K AAVE\n    - Voting power (pass proposal): 320K AAVE quorum\n    - Voting period: ~10 days\n    - Timelock: 1-7 days depending on proposal risk level\n\n  **ENS (Ethereum Name Service Token):**\n\n  November 2021 airdrop creating governance for Ethereum's naming system:\n\n  - **Total Supply**: 100 million ENS\n\n  - **Distribution**:\n    - Airdrop to .eth holders: 25% (weighted by registration time, expiration date, account age)\n    - Community treasury: 25%\n    - Core contributors: 25% (4-year vest)\n    - Launch contributors: 25% (4-year vest)\n\n  - **Governance Rights**: .eth pricing, registrar controller upgrades, treasury management, service provider selection, protocol parameters, ecosystem funding\n\n  - **Unique Features**:\n    - **ENS Constitution**: Explicitly enumerated rights and governance limitations (e.g., cannot seize names, must preserve name ownership, requires supermajority for constitutional amendments)\n    - **Steward system**: Elected working group leaders with limited authority over specific domains\n    - **Retroactive airdrop**: Distributed to existing users rather than prospective users, creating instant engaged community\n\n  - **Market Metrics (2024)**:\n    - Market cap: ~$450M ($16/ENS)\n    - Circulating supply: ~28M (~28%, low due to 4-year vesting)\n    - Delegated supply: ~18M ENS (~64% of circulating)\n    - Active delegates: ~400\n    - Top 100 delegates: ~70% of delegated voting power\n\n  ### Token Economics and Value Accrual\n\n  Governance tokens face fundamental questions around value capture and economic sustainability:\n\n  **Value Accrual Mechanisms:**\n\n  1. **Fee sharing**: Token holders receive protocol revenue (e.g., Curve veCRV earns 50% of trading fees, Aave stkAAVE earns protocol fees)\n\n  2. **Buyback and burn**: Protocol uses revenue to buy tokens from market and destroy them, reducing supply (MakerDAO burns MKR when profitable)\n\n  3. **Staking yields**: Tokens staked for governance earn additional yield (Aave Safety Module earns ~7% APY in AAVE, plus trading fee share)\n\n  4. **Liquidity mining incentives**: Protocols distribute tokens to liquidity providers, creating buy pressure from LPs seeking emissions\n\n  5. **Governance power premium**: Large holders (institutions, protocols, DAOs) pay premium for governance influence (e.g., protocols buying CRV/CVX to control Curve gauge votes)\n\n  **Value Capture Challenges:**\n\n  Many governance tokens provide **governance rights without cash flow rights**, creating tension with securities classification whilst questioning economic value:\n\n  - **UNI**: Governance-only token (no fee sharing as of 2025). Value derives from potential future fee switch, treasury access, and governance power. Critics argue UNI is \"worthless\" without cash flows; supporters argue governance over $3B+ treasury and world's largest DEX is valuable.\n\n  - **COMP**: Initially governance-only; Compound III added revenue sharing to COMP stakers in 2023, creating value accrual beyond governance power.\n\n  - **Pure governance premium**: Institutional actors pay premiums for governance influence even without direct cash flows—a16z, Paradigm, and other VCs accumulated massive governance token positions primarily for protocol influence rather than fee income.\n\n  ### Securities Law Classification and Regulatory Challenges\n\n  Governance tokens occupy legally ambiguous territory between utility tokens, securities, and commodities:\n\n  **Howey Test Analysis (U.S. Securities Law):**\n\n  The **Howey Test** determines securities classification through four prongs:\n  1. **Investment of money**: ✓ Users purchase/receive tokens\n  2. **Common enterprise**: ✓ Token holders collectively govern shared protocol\n  3. **Expectation of profits**: ? Depends on token design (fee-sharing tokens likely yes, pure governance potentially no)\n  4. **Derived from efforts of others**: ? If token holders actively govern, potentially no; if passive investors relying on founding team, yes\n\n  **SEC Enforcement Actions (2020-2025):**\n\n  The SEC brought enforcement actions against numerous token projects, creating regulatory uncertainty:\n\n  - **Ripple (XRP)**: SEC sued Ripple Labs in 2020, arguing XRP is unregistered security. 2023 court ruling: XRP sales to institutional investors were securities, but programmatic sales (exchanges) were not—creating split precedent.\n\n  - **Telegram (TON)**: SEC halted Telegram's token offering in 2020, forcing project shutdown and investor refunds.\n\n  - **Uniswap Wells Notice (2024)**: SEC notified Uniswap Labs of potential enforcement, creating uncertainty around UNI governance token status and protocol operations.\n\n  - **Numerous DeFi protocols**: SEC issued subpoenas, Wells Notices, and informal guidance discouraging governance token launches without legal clarity.\n\n  **Regulatory Mitigation Strategies:**\n\n  Projects adopted various approaches to reduce securities law risk:\n\n  1. **Progressive decentralization** (Coinbase framework): Launch with centralized team, gradually transfer control to token holders over time, eventually dissolving founding entity. Argument: Initial token distribution may be securities offering, but mature decentralized protocol with diffuse governance is not security.\n\n  2. **Pure governance tokens**: Avoid fee sharing, revenue rights, or profit expectations—tokens provide only governance power. Argument: Fails Howey prong 3 (expectation of profits). Challenge: Why would tokens have value without cash flows?\n\n  3. **Non-profit foundation structures**: Establish Swiss foundations, Marshall Islands non-profits, or Wyoming DAO LLCs to provide legal personality whilst avoiding profit-driven securities classification.\n\n  4. **Airdrops instead of sales**: Distribute tokens freely to users rather than selling for capital. Argument: No \"investment of money\" prong. Challenge: SEC may still view as compensation for past usage.\n\n  5. **Geographic restrictions**: Block U.S. users from token distributions, governance participation, or protocol access. Creates fragmented global ecosystem.\n\n  ### Game Theory, Incentive Alignment, and Mechanism Design\n\n  Governance token design confronts fundamental game theory challenges:\n\n  **Voter Apathy and Free-Riding:**\n\n  Rational token holders face misaligned incentives: high costs to participate (gas fees, research time, cognitive load) for negligible individual influence (one vote amongst millions). Rational actors free-ride on others' governance efforts.\n\n  **Statistical Evidence (2024):**\n  - MakerDAO: 8-12% average participation\n  - Uniswap: 5-10% participation\n  - Compound: 8-15% participation\n  - Aave: 6-12% participation\n  - ENS: 3-8% participation (highly variable)\n\n  **Plutocratic Concentration:**\n\n  Token-weighted voting creates **wealth-equals-power** dynamics:\n\n  - **Uniswap**: Top 10 holders control ~40% (a16z, Paradigm, team)\n  - **MakerDAO**: Top 50 holders control ~80%\n  - **Compound**: Top 10 holders control ~42%\n  - **Curve**: Top holders + Convex control ~60% veCRV\n\n  This concentration enables unilateral decision-making by whales, undermining democratic ideals whilst potentially improving decisiveness and informed participation.\n\n  **Mechanism Design Solutions:**\n\n  1. **Quadratic voting**: Cost = votes², making large vote counts prohibitively expensive, reducing whale influence (implemented by Gitcoin Grants, trialed by various DAOs)\n\n  2. **Conviction voting**: Voting power accumulates over time based on staking duration, rewarding long-term commitment (1Hive, Gardens)\n\n  3. **Vote escrow (veCRV model)**: Require token locking for voting power, aligning governance with protocol success (Curve, Balancer, Frax, Yearn v3)\n\n  4. **Delegation incentives**: Compensate professional delegates for active participation (Uniswap Treasury Delegation Program: $113M UNI to 12 delegates; Optimism Collective: 90 paid delegates)\n\n  5. **Reputation-weighted voting**: Non-transferable reputation earned through contribution, resistant to plutocracy but requires sybil resistance (DAOstack, Aragon)\n\n  6. **Futarchy**: Prediction markets determine governance outcomes based on expected impact (proposed, minimal real-world implementation)\n\n  ### Best Practices for Governance Token Design\n\n  Based on 2020-2025 ecosystem experience:\n\n  1. **Use battle-tested token standards**: ERC20Votes (OpenZeppelin) provides audited checkpointing, delegation, and historical snapshots.\n\n  2. **Implement delegation mechanisms**: Separate economic ownership from governance participation, enabling liquid democracy.\n\n  3. **Design sustainable tokenomics**: Consider long-term value accrual (fee sharing, buybacks, staking yields) beyond speculative appreciation.\n\n  4. **Plan distribution carefully**: Balance decentralization (wide distribution) with sustainability (team/treasury funding). Fair launches maximize decentralization; venture-backed models fund development.\n\n  5. **Progressive decentralization**: Launch with \"training wheels\" (multi-sig, admin keys), gradually transfer control as community matures.\n\n  6. **Consider legal structure**: Evaluate DAO LLC, foundation, or non-profit wrappers for legal personality and limited liability.\n\n  7. **Enable gasless voting**: Support meta-transactions, off-chain signaling (Snapshot), or Layer 2 deployment to reduce participation barriers.\n\n  8. **Align long-term incentives**: Vote-escrow models, vesting schedules, and time-weighted voting create skin-in-the-game alignment.\n\n  9. **Transparent distribution**: Publish token allocation, vesting schedules, and unlock timelines to enable informed participation.\n\n  10. **Constitutional governance limits**: Explicit rights enumeration (ENS Constitution model) prevents governance overreach and protects minority stakeholders.\n\n  ### Future Developments\n\n  **Cross-Chain Governance Tokens**: As protocols deploy multi-chain, governance tokens will need cross-chain voting, delegation, and execution capabilities via LayerZero, Wormhole, Axelar bridges.\n\n  **AI-Augmented Token Design**: Machine learning models will optimize tokenomics parameters (emission rates, distribution curves, vesting schedules) based on simulated governance outcomes and historical data.\n\n  **Regulatory Clarity**: Clearer frameworks distinguishing pure governance tokens from securities will emerge through 2025-2027, potentially via SEC guidance, congressional legislation, or court precedents.\n\n  **Non-Fungible Governance**: Exploration of NFT-based governance (Optimism Citizens' House, Nouns DAO) where governance power is non-transferable or based on contribution rather than capital.\n\n  **Liquid Democracy Maturation**: More sophisticated delegation markets, reputation systems, and delegate accountability mechanisms will emerge as governance professionalization continues.\n\n  #\n\n## Current Landscape (2025)\n\n- Industry adoption and implementations\n  - Metaverse platforms continue to evolve with focus on interoperability and open standards\n  - Web3 integration accelerating with decentralised identity and asset ownership\n  - Enterprise adoption growing in virtual collaboration, training, and digital twins\n  - UK companies increasingly active in metaverse development and immersive technologies\n\n- Technical capabilities\n  - Real-time rendering at photorealistic quality levels\n  - Low-latency networking enabling seamless multi-user experiences\n  - AI-driven content generation and procedural world building\n  - Spatial audio and haptics enhancing immersion\n\n- UK and North England context\n  - Manchester: Digital Innovation Factory supports metaverse startups and research\n  - Leeds: Holovis leads in immersive experiences for entertainment and training\n  - Newcastle: University research in spatial computing and interactive systems\n  - Sheffield: Advanced manufacturing using digital twin technology\n\n- Standards and frameworks\n  - Metaverse Standards Forum driving interoperability protocols\n  - WebXR enabling browser-based immersive experiences\n  - glTF and USD for 3D asset interchange\n  - Open Metaverse Interoperability Group defining cross-platform standards\n\n## Metadata\n\n- **Last Updated**: 2025-11-16\n- **Review Status**: Automated remediation with 2025 context\n- **Verification**: Academic sources verified\n- **Regional Context**: UK/North England where applicable\n\n\n## References and Case Studies\n\n  - [[BC-0461-decentralized-autonomous-organization]]\n  - [[BC-0462-on-chain-voting]] which refers to A component of the blockchain ecosystem.\n  - [[BC-0465-proposal-system]] which refers to A component of the blockchain ecosystem.\n  - [[BC-0464-treasury-management]] which refers to A component of the blockchain ecosystem.\n  - [[BC-0142-smart-contract]]\n  - [[Uniswap UNI Token]]\n  - [[Compound COMP Distribution]]\n  - [[MakerDAO MKR Tokenomics]]\n  - [[Curve veCRV Model]]\n  - [[Aave Safety Module]]\n  - [[ENS Constitution]]\n  - [[OpenZeppelin ERC20Votes]]\n\n  ### Original Content\n    collapsed:: true\n\t- ```\n\n\t  ```",
  "properties": {
    "id": "bc-0463-governance-token-ontology",
    "collapsed": "true",
    "- ontology": "true",
    "- term-id": "BC-0463",
    "- preferred-term": "Governance Token",
    "- source-domain": "blockchain",
    "- status": "stub-needs-content",
    "- public-access": "true",
    "- content-status": "minimal-placeholder-requires-authoring",
    "- definition": "A component of the blockchain ecosystem.",
    "- maturity": "draft",
    "- owl:class": "bc:GovernanceToken",
    "- owl:physicality": "ConceptualEntity",
    "- owl:role": "Concept",
    "- belongsToDomain": "[[BlockchainDomain]]"
  },
  "backlinks": [
    "BC-0493-real-estate-tokenization",
    "BC-0465-proposal-system",
    "BC-0462-on-chain-voting",
    "BC-0464-treasury-management",
    "BC-0495-voting-systems"
  ],
  "wiki_links": [
    "BC-0142-smart-contract|smart contracts",
    "Curve veCRV Model",
    "Curve Finance",
    "Aave Safety Module",
    "BC-0461-decentralized-autonomous-organization",
    "BC-0142-smart-contract",
    "MakerDAO MKR Tokenomics",
    "Aave",
    "MakerDAO",
    "BlockchainDomain",
    "BC-0464-treasury-management",
    "Compound",
    "Uniswap UNI Token",
    "BC-0461-decentralized-autonomous-organization|DAOs",
    "OpenZeppelin ERC20Votes",
    "Uniswap",
    "Curve",
    "BC-0462-on-chain-voting",
    "ENS Constitution",
    "Compound COMP Distribution",
    "BC-0465-proposal-system"
  ],
  "ontology": {
    "term_id": "BC-0463",
    "preferred_term": "Governance Token",
    "definition": "A component of the blockchain ecosystem.",
    "source_domain": "blockchain",
    "maturity_level": null,
    "authority_score": null
  }
}