{
  "title": "Enterprise Token Standards",
  "content": "- ### OntologyBlock\n  id:: bc-0433-enterprise-token-standards-ontology\n  collapsed:: true\n\t- ontology:: true\n\t- term-id:: BC-0433\n\t- preferred-term:: Enterprise Token Standards\n\t- source-domain:: blockchain\n\t- status:: stub-needs-content\n\t- public-access:: true\n\t- content-status:: minimal-placeholder-requires-authoring\n\t- public-access:: true\n\t- definition:: A component of the blockchain ecosystem.\n\t- maturity:: draft\n\t- owl:class:: bc:EnterpriseTokenStandards\n\t- owl:physicality:: ConceptualEntity\n\t- owl:role:: Concept\n\t- belongsToDomain:: [[BlockchainDomain]]\n\n## OWL Formal Semantics\n\n```clojure\n;; OWL Functional Syntax\n\n(Declaration (Class :EnterpriseTokenStandards))\n\n;; Annotations\n(AnnotationAssertion rdfs:label :EnterpriseTokenStandards \"Enterprise Token Standards\"@en)\n(AnnotationAssertion rdfs:comment :EnterpriseTokenStandards \"A component of the blockchain ecosystem.\"@en)\n\n;; Data Properties\n(AnnotationAssertion dcterms:identifier :EnterpriseTokenStandards \"BC-0433\"^^xsd:string)\n```\n\n- ## About Enterprise Token Standards\n  id:: enterprise-token-standards-about\n\n  - Enterprise token standards represent specialised blockchain protocols designed to enable compliant tokenisation of regulated financial assets including securities, real estate, private equity, and debt instruments whilst embedding regulatory requirements directly into smart contract code. Unlike general-purpose token standards such as [[ERC-20]] for fungible tokens or [[ERC-721]] for non-fungible tokens, enterprise token standards incorporate sophisticated compliance mechanisms including transfer restrictions, identity verification, investor accreditation checks, regulatory reporting, and document management capabilities essential for representing real-world assets on blockchain infrastructure. These standards address fundamental challenges in traditional securities markets including settlement delays, intermediary costs, market fragmentation, and limited liquidity for alternative assets by creating programmable, divisible, and globally accessible digital representations of ownership whilst maintaining compliance with securities regulations such as the [[Securities Act 1933]], [[Regulation D]], [[Regulation S]], and international frameworks including [[MiFID II]] and [[Prospectus Regulation]]. The two predominant enterprise token standards are [[ERC-1400]] developed by [[Polymath]], [[Harbor]], and [[Securitize]] as a library of interoperable standards for security tokens, and [[ERC-3643]] (formerly T-REX) developed by [[Tokeny]] and officially accepted as an Ethereum Request for Comment, providing on-chain identity verification and automated compliance enforcement. These standards enable tokenisation of previously illiquid assets, fractional ownership of high-value assets, automated compliance and dividend distribution, programmable securities with embedded rights and restrictions, and 24/7 global trading infrastructure whilst ensuring adherence to complex regulatory frameworks varying by jurisdiction and asset class.\n\n  - ### Technical Architecture\n    - Enterprise token standard architectures build upon fungible token foundations like [[ERC-20]] whilst adding layers for compliance, identity management, transfer restrictions, and regulatory integration. The architecture separates concerns between token representation (ownership records), identity verification (investor eligibility), compliance rules (transfer restrictions), and operational functions (issuance, redemption, forced transfers). [[ERC-1400]] implements a modular architecture through a suite of sub-standards including [[ERC-1410]] for partially fungible tokens enabling tranches or share classes, [[ERC-1594]] defining core security token standard with transfer validity checks, [[ERC-1643]] for document management linking legal agreements to tokens, and [[ERC-1644]] enabling controller operations for regulatory intervention. [[ERC-3643]] takes a different architectural approach embedding identity verification directly in the standard through an [[Identity Registry]] smart contract that whitelists eligible investors and stores [[Claims]] verifying investor attributes like accreditation status, jurisdiction, and identity verification level.\n    - Key components:\n      - [[Transfer Restriction Modules]] - Smart contract logic encoding regulatory requirements as executable code, checking conditions before allowing token transfers including investor accreditation verification, holding period enforcement, maximum investor count limits per [[Regulation D]], and jurisdiction-based restrictions implementing [[KYC]]/[[AML]] requirements\n      - [[Identity Registry and Claims]] - On-chain or hybrid identity systems storing cryptographic proofs of investor eligibility, implementing [[ERC-725]] identity standards or [[Self-Sovereign Identity]] approaches with [[Verifiable Credentials]] attesting to investor qualifications without revealing unnecessary personal information\n      - [[Partition and Tranche Management]] - Mechanisms enabling different classes of tokens with varying rights, restrictions, or redemption priorities within single token contract, essential for representing complex securities like preferred shares, convertible notes, or multi-tranche structured products\n      - [[Document Management]] - On-chain references to legal documents defining token rights and obligations, typically using [[IPFS]] hashes or [[Arweave]] permanent storage references linking to offering memoranda, subscription agreements, and constitutional documents\n      - [[Controller and Forced Transfer Capabilities]] - Privileged operations enabling issuers or regulators to intervene in token ownership for legitimate purposes including court orders, regulatory seizure, correcting erroneous transfers, or implementing corporate actions like mergers\n      - [[Compliance Oracle Integration]] - External data feeds providing real-time regulatory information, accredited investor verification from services like [[Parallel Markets]] or [[Tokensoft]], and [[Sanctions Screening]] against [[OFAC]] lists and [[Politically Exposed Persons]] databases\n\n  - ### Key Features and Capabilities\n    - **Automated Regulatory Compliance**: Enterprise token standards encode complex securities regulations as smart contract logic that automatically enforces compliance before executing transfers. [[ERC-3643]] implements a validator system automatically checking sender and receiver eligibility before every transfer based on rules defined by issuer, preventing non-compliant transactions at protocol level rather than relying on post-transaction enforcement. This includes verifying investor accreditation status, enforcing [[Regulation D]] investor limits (maximum 2,000 holders for Rule 506(c)), checking jurisdictional restrictions implementing [[Regulation S]] requirements for offshore offerings, and maintaining holding periods for restricted securities. The automation reduces compliance costs, eliminates manual verification processes, and provides real-time regulatory assurance impossible in traditional securities infrastructure.\n    - **Flexible Partition and Share Class Representation**: [[ERC-1410]] within the ERC-1400 suite implements partially fungible tokens enabling single token contract to represent multiple share classes or tranches with different rights, restrictions, or economic terms. This architectural approach allows representing complex capital structures including Class A voting shares, Class B non-voting shares, preferred shares with liquidation preferences, and restricted versus unrestricted share classes whilst maintaining consolidated ownership records. Financial instruments like collateralised debt obligations with senior, mezzanine, and equity tranches can be accurately modelled with appropriate waterfall payment distribution programmed in smart contract logic.\n    - **Integrated Document Management and Legal Certainty**: [[ERC-1643]] provides standardised document management capabilities linking tokens to legal documents defining rights, restrictions, and obligations. Issuers publish cryptographic hashes of offering documents, subscription agreements, shareholder agreements, and amendments to blockchain, creating immutable audit trail of document versions. This integration of legal prose with executable code addresses [[Ricardian Contract]] concepts where human-readable legal agreements are cryptographically bound to smart contract implementations. Investors and regulators can verify they have authentic current versions of governing documents, whilst dispute resolution benefits from irrefutable record of terms in effect at transaction time.\n    - **Programmable Corporate Actions and Automation**: Enterprise tokens enable automation of shareholder processes including dividend distributions, stock splits, rights offerings, and voting. Smart contracts can execute pro-rata dividend payments in cryptocurrency or stablecoins instantaneously to all token holders, eliminating intermediary delays and reducing payment agent costs. Voting rights can be implemented through [[Governance Tokens]] mechanisms where vote weight automatically reflects shareholding, with proposals and voting on-chain providing transparent corporate governance. Complex corporate actions like mergers, spin-offs, or conversions can be programmed as smart contract logic executing automatically when conditions are met.\n\n  - ### Industry Applications\n    - **Real Estate Tokenisation**: Enterprise token standards enable fractional ownership of commercial and residential real estate, transforming traditionally illiquid property investments into tradable digital securities. Platforms like [[Tokeny]], [[Polymath]], and [[Securitize]] have facilitated tokenisation of properties worth hundreds of millions, enabling investors to purchase fractions of buildings with minimum investments as low as £1,000 versus traditional minimums of £100,000+ for commercial real estate funds. [[St. Regis Aspen Resort]] tokenisation issued $18 million in security tokens representing ownership in luxury resort property, with automated rental income distribution to token holders and secondary trading providing liquidity previously unavailable in real estate investments.\n      - Implementation details: Real estate special purpose vehicles issue security tokens under [[Regulation D]] or [[Regulation A+]], with [[ERC-3643]] or [[ERC-1400]] tokens representing beneficial ownership in the entity holding property title. Smart contracts distribute rental income quarterly based on ownership percentage, whilst transfer restrictions ensure only accredited investors acquire tokens and jurisdictional limits comply with offering exemptions. Property management agreements and lease documents are referenced via [[ERC-1643]] document management.\n      - Benefits achieved: Fractional ownership enabling portfolio diversification, liquidity through secondary trading on alternative trading systems, automated income distribution reducing administrative costs, global investor access expanding capital sources, transparent ownership records reducing title insurance costs\n      - [[Real Estate Investment Trusts]] (REITs), [[Alternative Trading Systems]], [[Regulation A+]] offerings\n    - **Private Equity and Venture Capital Tokenisation**: Private equity funds and venture capital investments traditionally suffer from extreme illiquidity with 7-10 year lock-up periods and limited secondary market options. Enterprise token standards enable fund interests to be represented as digital securities with compliant secondary trading, whilst portfolio companies can tokenise equity for more efficient fundraising and cap table management. [[SPiCE VC]] launched first tokenised venture capital fund, whilst platforms like [[Carta]] and [[Caplight]] implement enterprise token standards for private company equity.\n      - Implementation details: Fund general partners issue tokens representing limited partner interests under [[Regulation D]] Rule 506(c), with [[ERC-1400]] partitions representing different share classes (GP interest, LP Class A, LP Class B with different fee structures). Smart contracts enforce transfer restrictions including minimum holding periods, accredited investor verification, and rights of first refusal. Portfolio company investments are represented through linked tokens or [[NFTs]] representing SAFEs, convertible notes, or preferred shares.\n      - Benefits achieved: Earlier liquidity for LP investors through compliant secondary trading, reduced fund administration costs through automated capital call and distribution processes, improved transparency with on-chain reporting of NAV and portfolio valuations, fractional LP interests lowering investment minimums, programmable waterfall distributions enforcing carry and hurdle rates\n      - [[Simple Agreement for Future Equity]] (SAFE), [[Limited Partnership Agreements]], [[Delaware General Corporation Law]]\n    - **Tokenised Bonds and Debt Instruments**: Fixed income securities including corporate bonds, government bonds, and structured debt products benefit from enterprise token standards through faster settlement, fractional denominations, and automated coupon payments. [[Societe Generale]] issued €100 million covered bond as security token on [[Ethereum]], whilst [[Siemens]] issued €60 million digital bond demonstrating enterprise adoption. These implementations use enterprise token standards to enforce transfer restrictions, automate interest payments, and manage bondholder registries.\n      - Implementation details: Bond issuers deploy [[ERC-3643]] or [[ERC-1400]] tokens with payment schedules programmed in smart contracts, automatically distributing coupon payments in [[Stablecoins]] like [[USDC]] or [[DAI]] on payment dates to addresses holding tokens. Maturity and redemption logic automatically calculates principal repayment. Transfer restrictions ensure compliance with bond offering documents and regulatory requirements. [[Decentralised Oracles]] provide interest rate data for floating rate notes or inflation-linked bonds.\n      - Benefits achieved: T+0 settlement versus T+2 in traditional bond markets, automated coupon payments eliminating paying agent fees, fractional bonds expanding retail investor access, transparent pricing and ownership records, programmable bond covenants with automatic enforcement\n      - [[International Capital Market Association]] standards, [[Central Securities Depositories]], [[Bond Trustees]]\n\n  - ### Standards and Governance\n    - **Standards**: The enterprise token ecosystem features competing standards with different architectural philosophies and adoption patterns. [[ERC-1400]] represents a library approach with multiple interoperable sub-standards addressing specific requirements, enabling issuers to implement only needed components for their use case. [[ERC-3643]] provides comprehensive integrated standard addressing identity, compliance, and token functionality in unified framework, currently the only enterprise token standard to achieve full [[Ethereum Improvement Proposal]] acceptance. [[CMTAT]] (Capital Markets and Technology Association Token) developed by Swiss organisations provides alternative focusing on Swiss regulatory requirements. The [[InterWork Alliance]] Token Taxonomy Framework creates platform-agnostic token definitions enabling interoperability across different blockchain implementations. Standardisation bodies including [[ISO/TC 307]] are developing international standards for digital assets, whilst securities regulators including [[SEC]], [[ESMA]], and [[FCA]] are establishing regulatory frameworks for security tokens affecting technical requirements.\n    - **Governance models**: Enterprise token standards governance varies between community-driven open standards and commercial platform-specific implementations. [[ERC-3643]] governance follows Ethereum Improvement Proposal process with community review, technical discussion, and acceptance by Ethereum core developers. [[Polymath]] governs [[ERC-1400]] development through foundation structure with participation from security token issuers, service providers, and technology partners. Platform providers like [[Tokeny]], [[Securitize]], and [[Harbor]] implement enterprise token standards in commercial products with proprietary extensions while contributing to open standards development. Industry consortia including [[Global Digital Finance]] and [[International Token Standardization Association]] work on governance frameworks, best practices, and cross-border interoperability.\n    - **Compliance**: Enterprise token standards must navigate complex, jurisdiction-specific securities regulations. United States securities law requires compliance with [[Securities Act 1933]] registration requirements or qualifying exemptions like [[Regulation D]] for private placements or [[Regulation A+]] for mini-IPOs. [[Regulation S]] governs offshore offerings outside US jurisdiction. European regulations including [[MiFID II]], [[Prospectus Regulation]], and national securities laws create different requirements. Smart contract implementation of compliance rules must be regularly updated reflecting regulatory changes, with upgrade mechanisms enabling issuers to modify transfer restrictions without disrupting token functionality. [[FATF]] Travel Rule requirements necessitate identity data exchange for transfers above specified thresholds. Tax reporting requirements including [[Form 1099]] in United States and [[Common Reporting Standard]] internationally require automated transaction reporting capabilities.\n\n  - ### Comparison with Alternatives\n    - Compared to [[ERC-20 Standard Token]]: Enterprise token standards sacrifice simplicity and universal interoperability of ERC-20 for regulatory compliance and governance capabilities essential for representing securities. ERC-20 tokens transfer permissionlessly without restrictions, making them suitable for utility tokens or cryptocurrencies but legally problematic for regulated securities. Enterprise standards add identity verification, transfer restrictions, and issuer controls making them compliant with securities law but incompatible with standard decentralised exchanges and DeFi protocols expecting permissionless transfers. Developer tooling and wallet support for ERC-20 far exceeds enterprise standards, requiring specialised infrastructure.\n    - Compared to [[Traditional Securities Infrastructure]]: Enterprise token standards provide T+0 settlement versus T+2 standard in traditional markets, programmable automation versus manual corporate actions, 24/7 global accessibility versus business hours regional markets, and fractional ownership versus whole share minimums. Traditional securities benefit from mature regulatory frameworks, deep liquidity, established custodians and broker-dealers, and universal investor familiarity. Enterprise tokens face regulatory uncertainty, fragmented liquidity across multiple platforms, custody complexity with private key management, and technology barriers for less sophisticated investors. Cost structures differ significantly with traditional securities incurring higher intermediary fees but lower technology implementation costs, whilst tokenised securities require substantial upfront development but minimal ongoing operational costs.\n    - When to use enterprise token standards: Choose enterprise token standards when tokenising regulated securities requiring compliance with securities law, when benefits of fractional ownership, programmable automation, or global accessibility justify technology investment, when target investor base includes retail participants unable to access traditional private securities, or when asset class traditionally suffers from illiquidity that secondary trading could address. Traditional securities infrastructure remains more appropriate for large institutional offerings, highly liquid public markets, or situations where regulatory uncertainty outweighs tokenisation benefits.\n\n  - ### Implementation Considerations\n    - **Technical requirements**: Implementing enterprise token standards requires blockchain development expertise, securities law knowledge, and operational infrastructure. Development teams need proficiency in [[Solidity]] smart contract programming, security audit capabilities for financial applications handling valuable assets, and understanding of [[ERC-1400]] or [[ERC-3643]] specifications. Infrastructure requirements include [[Ethereum]] node operation or [[Blockchain-as-a-Service]] provider relationships, [[Hardware Security Modules]] for key management, integration with identity verification providers implementing [[KYC]]/[[AML]] checks, and connections to compliance oracles providing accredited investor verification and sanctions screening. [[Multisignature]] wallet infrastructure protects issuer control keys, whilst disaster recovery procedures address private key loss or compromise scenarios.\n    - **Organisational readiness**: Organisations tokenising securities must establish governance frameworks addressing smart contract upgrades, handling of corporate actions, and investor relations for token holders. Legal teams require expertise in securities law across relevant jurisdictions, understanding of smart contract legal enforceability, and capability to draft offering documents incorporating blockchain-specific terms. Compliance functions must adapt to automated compliance enforcement whilst maintaining oversight and responding to regulatory inquiries. Investor relations teams need capabilities to support investors managing private keys, understanding wallet software, and navigating decentralised infrastructure unfamiliar to traditional securities investors.\n    - **Cost considerations**: Enterprise token implementation costs include smart contract development and security auditing (£75,000-£250,000), legal structuring and offering documents (£100,000-£500,000), platform fees for commercial providers like Tokeny or Securitize (£25,000-£100,000 annual), identity verification and compliance services (£10-£50 per investor), and blockchain transaction fees for issuance and transfers (variable by network congestion, typically £5-£50 per transaction on [[Ethereum]], significantly less on [[Polygon]] or other [[Layer 2]] solutions). Ongoing costs include smart contract maintenance, regulatory reporting, investor support, and platform fees. Break-even analysis typically favours tokenisation for offerings above £5 million where investor base benefits from fractional ownership or secondary liquidity justifies implementation costs.\n    - **Timeline**: Enterprise token projects require 6-18 months from concept to successful issuance. Timeline includes 2-3 months legal structuring and regulatory analysis determining appropriate offering exemption and jurisdictional requirements, 2-4 months smart contract development implementing chosen token standard with custom compliance rules and business logic, 1-2 months security auditing by specialised firms, 2-3 months identity verification infrastructure integration and investor onboarding platform development, 1-2 months marketing and investor acquisition, and 1-2 months regulatory review for offerings requiring pre-clearance like [[Regulation A+]]. Accelerated timelines of 3-6 months are achievable using commercial platforms with pre-built infrastructure, though legal and compliance timelines remain largely fixed.\n\n  - ### Major Implementations\n    - **Societe Generale Covered Bond (€100 million)**: Major European bank [[Societe Generale]] issued €100 million covered bond as security token on public [[Ethereum]] blockchain using enterprise token standard, marking significant institutional adoption. The implementation used [[OFH]] (Obligation de Financement de l'Habitat) structure, French covered bond framework providing enhanced credit protection through dual recourse to issuer and cover pool of residential mortgages. The bond was issued, subscribed, and settled on blockchain infrastructure, with [[Societe Generale]] acting as both issuer and sole investor demonstrating technical viability before broader market adoption.\n    - **tZERO Alternative Trading System**: [[tZERO]] operates SEC-registered Alternative Trading System providing compliant secondary trading for security tokens issued under [[Regulation D]] and [[Regulation A+]]. The platform implements [[ERC-1400]]-compatible tokens with transfer restrictions enforcing accredited investor verification, holding periods, and beneficial ownership limits. tZERO facilitated [[Exodus Movement]]'s $75 million [[Regulation A+]] offering, one of largest security token offerings enabling retail investor participation. The platform integrates with traditional broker-dealers for fiat on/off ramps whilst maintaining blockchain settlement for token trades.\n    - **Tokeny Luxembourg Real Estate Tokenisation**: [[Tokeny]] developed [[ERC-3643]] standard (formerly T-REX) and implemented numerous real estate tokenisations in European market. Notable implementation includes Luxembourg real estate fund tokenisation enabling fractional ownership with minimum investments of €100,000 versus traditional €5 million minimums. The platform provides end-to-end infrastructure including token issuance, identity verification integrating with European [[eIDAS]] digital identity framework, compliance rule enforcement, and investor portal. [[Tokeny]]'s implementation demonstrates enterprise token standards enabling regulatory compliance whilst improving accessibility and liquidity for traditionally illiquid asset classes.\n\n  - ### Challenges and Limitations\n    - Technical challenges include smart contract security vulnerabilities where bugs in compliance logic could enable unauthorised transfers or lock tokens preventing legitimate transactions. [[Upgradeability patterns]] for smart contracts create complexity balancing immutability desired for securities with necessity to update compliance rules reflecting regulatory changes. [[Gas fees]] on [[Ethereum]] mainnet can make micro-transactions economically infeasible, with dividend distribution to thousands of token holders potentially costing more in transaction fees than dividend amount. Integration complexity with existing securities infrastructure including [[DTCC]], custodians, and broker-dealers creates operational friction requiring bridge solutions between blockchain and traditional systems.\n    - Organisational challenges centre on investor education and user experience, where private key management and wallet software present significant barriers for retail investors accustomed to traditional brokerage accounts. [[Recovery mechanisms]] for lost private keys conflict with self-sovereign ownership principles, requiring issuers to implement emergency procedures whilst maintaining security. Regulatory uncertainty in many jurisdictions creates legal risk where token issuers may face changing compliance requirements after initial issuance. [[Tax treatment]] ambiguity for tokenised securities in various jurisdictions creates uncertainty for investors regarding capital gains treatment, dividend taxation, and reporting requirements.\n    - Scalability considerations include fragmented liquidity where security tokens trade on multiple incompatible platforms, preventing price discovery and limiting trading volumes. [[Network effects]] favour existing securities infrastructure with vastly larger investor bases, creating chicken-and-egg problem where issuers hesitate to tokenise without liquid secondary markets but liquidity requires critical mass of issuances. Regulatory frameworks designed for traditional securities create friction for blockchain-based systems, with requirements for intermediaries like transfer agents and broker-dealers reducing disintermediation benefits whilst adding costs.\n    - Security concerns include smart contract vulnerabilities enabling unauthorised token creation, transfer, or destruction with potentially catastrophic consequences for issuers and investors. [[Oracle manipulation]] where compliance checks rely on external data feeds creates attack vectors if price oracles or identity verification services are compromised. [[Front-running]] attacks on decentralised exchanges could exploit information asymmetries in token transfers. Regulatory seizure capabilities required by [[ERC-1644]] controller operations create centralisation risks if issuer keys are compromised or subject to coercion.\n\n  - ### Future Directions\n    - Emerging trends include convergence of enterprise token standards with [[Decentralized Finance]] protocols, enabling tokenised securities as collateral in lending markets, liquidity provision in automated market makers, and derivatives creation through protocols like [[Synthetix]]. [[Regulation S]] compliant tokens with time-based transfer restriction lifting could automatically integrate with DeFi protocols when restrictions expire, bridging traditional finance and decentralised finance ecosystems.\n    - Planned improvements focus on cross-chain interoperability enabling security tokens issued on one blockchain to trade on others through bridge protocols or unified settlement layers. [[Layer 2]] scaling solutions including [[Optimism]], [[Arbitrum]], and [[Polygon]] reduce transaction costs making micro-transactions economically viable for dividend distributions and secondary trades. [[Account abstraction]] through [[ERC-4337]] improves user experience enabling social recovery, gasless transactions, and batched operations without users managing private keys directly.\n    - Research areas include integration with [[Central Bank Digital Currencies]] for atomic delivery-versus-payment settlement eliminating settlement risk between security transfer and payment. [[Zero-knowledge proofs]] enable privacy-preserving compliance where investors prove eligibility without revealing identity or asset holdings to all participants. [[Decentralised Identity]] standards including [[W3C DID]] and [[Verifiable Credentials]] create portable investor credentials usable across multiple issuance platforms without repeated KYC processes. [[Artificial Intelligence]] applications include automated regulatory interpretation updating smart contract compliance rules reflecting new regulations, fraud detection identifying suspicious trading patterns, and valuation models for illiquid tokenised assets. [[Tokenised carbon credits]] and [[ESG]] data integration enable programmable securities enforcing sustainability requirements through smart contract logic.\n\n  - #\n\n## Current Landscape (2025)\n\n- Industry adoption and implementations\n  - Metaverse platforms continue to evolve with focus on interoperability and open standards\n  - Web3 integration accelerating with decentralised identity and asset ownership\n  - Enterprise adoption growing in virtual collaboration, training, and digital twins\n  - UK companies increasingly active in metaverse development and immersive technologies\n\n- Technical capabilities\n  - Real-time rendering at photorealistic quality levels\n  - Low-latency networking enabling seamless multi-user experiences\n  - AI-driven content generation and procedural world building\n  - Spatial audio and haptics enhancing immersion\n\n- UK and North England context\n  - Manchester: Digital Innovation Factory supports metaverse startups and research\n  - Leeds: Holovis leads in immersive experiences for entertainment and training\n  - Newcastle: University research in spatial computing and interactive systems\n  - Sheffield: Advanced manufacturing using digital twin technology\n\n- Standards and frameworks\n  - Metaverse Standards Forum driving interoperability protocols\n  - WebXR enabling browser-based immersive experiences\n  - glTF and USD for 3D asset interchange\n  - Open Metaverse Interoperability Group defining cross-platform standards\n\n## Metadata\n\n- **Last Updated**: 2025-11-16\n- **Review Status**: Automated remediation with 2025 context\n- **Verification**: Academic sources verified\n- **Regional Context**: UK/North England where applicable\n\n\n## References and Further Reading\n    - [[ERC-1400 Specification]] - Polymath's security token standard library technical documentation\n    - [[ERC-3643 Standard]] - Official Ethereum Improvement Proposal for enterprise tokens\n    - [[Security Token Handbook]] by Blockchance and Frankfurt School - Comprehensive guide to security token ecosystem\n    - [[Token Taxonomy Framework]] by InterWork Alliance - Platform-agnostic token specification framework\n    - [[SEC Framework for Investment Contract Analysis of Digital Assets]] - US regulatory guidance on token securities classification\n    - [[ESMA Advice on Initial Coin Offerings and Crypto-Assets]] - European regulatory perspective on token securities\n    - [[The Impact of Tokenization on Financial Markets]] by BIS - Central bank analysis of asset tokenisation\n    - [[Smart Contracts: Building Blocks for Digital Markets]] by Nick Szabo - Foundational concepts for programmable securities",
  "properties": {
    "id": "bc-0433-enterprise-token-standards-ontology",
    "collapsed": "true",
    "- ontology": "true",
    "- term-id": "BC-0433",
    "- preferred-term": "Enterprise Token Standards",
    "- source-domain": "blockchain",
    "- status": "stub-needs-content",
    "- public-access": "true",
    "- content-status": "minimal-placeholder-requires-authoring",
    "- definition": "A component of the blockchain ecosystem.",
    "- maturity": "draft",
    "- owl:class": "bc:EnterpriseTokenStandards",
    "- owl:physicality": "ConceptualEntity",
    "- owl:role": "Concept",
    "- belongsToDomain": "[[BlockchainDomain]]"
  },
  "backlinks": [],
  "wiki_links": [
    "Sanctions Screening",
    "ERC-20 Standard Token",
    "Solidity",
    "FATF",
    "Alternative Trading Systems",
    "ERC-721",
    "Gas fees",
    "Oracle manipulation",
    "Optimism",
    "ESMA Advice on Initial Coin Offerings and Crypto-Assets",
    "Hardware Security Modules",
    "ERC-4337",
    "Tokeny",
    "DAI",
    "Global Digital Finance",
    "Document Management",
    "Politically Exposed Persons",
    "W3C DID",
    "Claims",
    "Security Token Handbook",
    "ERC-1400 Specification",
    "Controller and Forced Transfer Capabilities",
    "Ricardian Contract",
    "Network effects",
    "USDC",
    "ERC-1594",
    "InterWork Alliance",
    "ERC-1400",
    "Ethereum Improvement Proposal",
    "ERC-1644",
    "International Capital Market Association",
    "SEC",
    "Partition and Tranche Management",
    "International Token Standardization Association",
    "SEC Framework for Investment Contract Analysis of Digital Assets",
    "ERC-725",
    "Traditional Securities Infrastructure",
    "ERC-3643 Standard",
    "Tokenised carbon credits",
    "ESMA",
    "St. Regis Aspen Resort",
    "The Impact of Tokenization on Financial Markets",
    "Layer 2",
    "Verifiable Credentials",
    "Caplight",
    "Regulation S",
    "Polygon",
    "ERC-20",
    "FCA",
    "Decentralised Oracles",
    "Regulation D",
    "OFH",
    "Front-running",
    "Central Bank Digital Currencies",
    "Arweave",
    "Prospectus Regulation",
    "eIDAS",
    "Regulation A+",
    "Limited Partnership Agreements",
    "Self-Sovereign Identity",
    "Token Taxonomy Framework",
    "Harbor",
    "Blockchain-as-a-Service",
    "Arbitrum",
    "Form 1099",
    "Recovery mechanisms",
    "ERC-3643",
    "ERC-1643",
    "Upgradeability patterns",
    "Tokensoft",
    "Multisignature",
    "Carta",
    "Artificial Intelligence",
    "ISO/TC 307",
    "Identity Registry",
    "Common Reporting Standard",
    "SPiCE VC",
    "AML",
    "ESG",
    "Tax treatment",
    "Synthetix",
    "Parallel Markets",
    "Stablecoins",
    "Delaware General Corporation Law",
    "Exodus Movement",
    "Identity Registry and Claims",
    "Decentralized Finance",
    "Decentralised Identity",
    "Securitize",
    "OFAC",
    "KYC",
    "Governance Tokens",
    "Central Securities Depositories",
    "MiFID II",
    "Simple Agreement for Future Equity",
    "BlockchainDomain",
    "IPFS",
    "ERC-1410",
    "Real Estate Investment Trusts",
    "Smart Contracts: Building Blocks for Digital Markets",
    "Securities Act 1933",
    "Societe Generale",
    "NFTs",
    "CMTAT",
    "Zero-knowledge proofs",
    "Bond Trustees",
    "Ethereum",
    "Polymath",
    "Transfer Restriction Modules",
    "DTCC",
    "Compliance Oracle Integration",
    "tZERO",
    "Account abstraction",
    "Siemens"
  ],
  "ontology": {
    "term_id": "BC-0433",
    "preferred_term": "Enterprise Token Standards",
    "definition": "A component of the blockchain ecosystem.",
    "source_domain": "blockchain",
    "maturity_level": null,
    "authority_score": null
  }
}