{
  "title": "Smart Contract",
  "content": "- ### OntologyBlock\n  id:: smart-contract-ontology\n  collapsed:: true\n\n  - **Identification**\n    - public-access:: true\n    - ontology:: true\n    - term-id:: BC-0009\n    - preferred-term:: Smart Contract\n    - source-domain:: blockchain\n    - status:: complete\n    - version:: 1.0.0\n    - last-updated:: 2025-10-28\n\n  - **Definition**\n    - definition:: Self-executing programmable code within blockchain systems, providing essential functionality for distributed ledger technology operations and properties.\n    - maturity:: mature\n    - source:: [[ISO/IEC 23257:2021]], [[IEEE 2418.1]], [[NIST NISTIR]]\n    - authority-score:: 0.95\n\n  - **Semantic Classification**\n    - owl:class:: bc:SmartContract\n    - owl:physicality:: VirtualEntity\n    - owl:role:: Object\n    - owl:inferred-class:: bc:VirtualObject\n    - belongsToDomain:: [[BlockchainDomain]]\n    - implementedInLayer:: [[ConceptualLayer]]\n\n  - #### Relationships\n    id:: smart-contract-relationships\n    - is-subclass-of:: [[Blockchain Entity]], [[DistributedDataStructure]]\n\n  - #### OWL Axioms\n    id:: smart-contract-owl-axioms\n    collapsed:: true\n    - ```clojure\n      Prefix(:=<http://metaverse-ontology.org/blockchain#>)\nPrefix(owl:=<http://www.w3.org/2002/07/owl#>)\nPrefix(rdf:=<http://www.w3.org/1999/02/22-rdf-syntax-ns#>)\nPrefix(xml:=<http://www.w3.org/XML/1998/namespace>)\nPrefix(xsd:=<http://www.w3.org/2001/XMLSchema#>)\nPrefix(rdfs:=<http://www.w3.org/2000/01/rdf-schema#>)\nPrefix(dct:=<http://purl.org/dc/terms/>)\n\nOntology(<http://metaverse-ontology.org/blockchain/BC-0009>\n  Import(<http://metaverse-ontology.org/blockchain/core>)\n\n  ## Class Declaration\n  Declaration(Class(:SmartContract))\n\n  ## Subclass Relationships\n  SubClassOf(:SmartContract :DistributedDataStructure)\n  SubClassOf(:SmartContract :BlockchainEntity)\n\n  ## Essential Properties\n  SubClassOf(:SmartContract\n    (ObjectSomeValuesFrom :partOf :Blockchain))\n\n  SubClassOf(:SmartContract\n    (ObjectSomeValuesFrom :hasProperty :Property))\n\n  ## Data Properties\n  DataPropertyAssertion(:hasIdentifier :SmartContract \"BC-0009\"^^xsd:string)\n  DataPropertyAssertion(:hasAuthorityScore :SmartContract \"1.0\"^^xsd:decimal)\n  DataPropertyAssertion(:isFoundational :SmartContract \"true\"^^xsd:boolean)\n\n  ## Object Properties\n  ObjectPropertyAssertion(:enablesFeature :SmartContract :BlockchainFeature)\n  ObjectPropertyAssertion(:relatesTo :SmartContract :RelatedConcept)\n\n  ## Annotations\n  AnnotationAssertion(rdfs:label :SmartContract \"Smart Contract\"@en)\n  AnnotationAssertion(rdfs:comment :SmartContract\n    \"Self-executing programmable code\"@en)\n  AnnotationAssertion(dct:description :SmartContract\n    \"Foundational blockchain concept with formal ontological definition\"@en)\n  AnnotationAssertion(:termID :SmartContract \"BC-0009\")\n  AnnotationAssertion(:priority :SmartContract \"1\"^^xsd:integer)\n  AnnotationAssertion(:category :SmartContract \"blockchain-fundamentals\"@en)\n)\n      ```\n\n- ## About Smart Contract\n  id:: smart-contract-about\n\n  - Self-executing programmable code within blockchain systems, providing essential functionality for distributed ledger technology operations and properties.\n  -\n  - ### Key Characteristics\n    id:: smart-contract-characteristics\n    - 1. **Definitional Property**: Core defining characteristic\n    - 2. **Functional Property**: Operational behavior\n    - 3. **Structural Property**: Compositional elements\n    - 4. **Security Property**: Security guarantees provided\n    - 5. **Performance Property**: Efficiency considerations\n  -\n  - ### Technical Components\n    id:: smart-contract-components\n    - **Implementation**: How concept is realized technically\n    - **Verification**: Methods for validating correctness\n    - **Interaction**: Relationships with other components\n    - **Constraints**: Technical limitations and requirements\n  -\n  - ### Use Cases\n    id:: smart-contract-use-cases\n    - **1. Core Blockchain Operation**\n    - **Application**: Fundamental blockchain functionality\n    - **Example**: Practical implementation in major blockchains\n    - **Requirements**: Technical prerequisites\n    - **Benefits**: Value provided to blockchain systems\n  -\n  - ### Standards & References\n    id:: smart-contract-standards\n    - [[ISO/IEC 23257:2021]] - Blockchain and distributed ledger technologies\n    - [[IEEE 2418.1]] - Blockchain and distributed ledger technologies\n    - [[NIST NISTIR]] - Blockchain and distributed ledger technologies\n  -\n\n\t- ### 4. The Core Technology: RGB Protocol for Programmable Assets\n\t\t- RGB is a scalable and confidential smart contract system for Bitcoin and the Lightning Network. It operates on the principle of **client-side validation**, a paradigm where transaction data is kept private and validated only by the parties involved, rather than being broadcast publicly on a global ledger.\n\t\t- *   **How it Works:** Instead of storing bulky contract data on the blockchain, RGB anchors a small cryptographic commitment to a Bitcoin transaction (specifically, a UTXO). This commitment acts as a **single-use seal**, ensuring that a digital asset or state can only be updated once per transaction, thus preventing double-spends while maintaining privacy.\n\t\t  *   **Private and Scalable Value Transfer:** This architecture allows for the creation and transfer of assets like Tether (USDT) and Satoshis over the Lightning Network. Transactions are fast, cheap, and confidential, as the details of the asset transfer are not visible on the main Bitcoin blockchain.\n\t\t  *   **Layer 3 Functionality:** RGB enables a true application layer (Layer 3) on Bitcoin, supporting tokenization, decentralized finance (DeFi), and other complex smart contract use cases without congesting the base layer.\n\n\t- ### Smart Contract Platforms\n\t\t- **[Stacks](https://www.stacks.co/)**: A smart contract platform that enables decentralized applications and smart contracts on Bitcoin.\n\t\t- **[Rootstock (RSK)](https://www.rsk.co/)**: A sidechain to Bitcoin that provides a platform for smart contracts that is highly compatible with Ethereum's Virtual Machine (EVM).\n\n\t- ### RGB\n\t\t- [RGB](https://www.rgb.tech/) is a smart contract system for Bitcoin and the Lightning Network that allows for the issuance and management of digital assets.\n\n\t\t\t- ##### Royalty Sales on Pre-owned Games\n\t\t\t\t- ; A predetermined proportion of any resale of a used game can automatedin perpetuity via smart contracts; once these are set by the publisher,future royalties of all sales can be paid directly to thepublishers/developers wallets (a digital account) without the need of athird party (traditionally a retail entity). Traditionally only theinitial first sale of a game would financially benefit thepublisher/developer/retailer, secondary and subsequent sales would onlyever financially benefit the purchaser, with many developers/publishersarguing this is hurting the wider industry through the loss ofsignificant income generated by the secondary and subsequent sales,sometimes over the course of decades. However the use of NFTâ€™s smartcontracts means that if a game is sold/resold through 10,000 collectors;a pre-determined royalty payment rate set by the publisher would stillguarantee the publisher (and or developer/retailer) takes a proportionof any future sales.\n\n\t- ### Amazfit Smart Ring\n\t\t- {{tweet https://twitter.com/AmazfitGlobal/status/1745524225589547012}}\n\n\t- ## BIS proposal\n\t\t- The BIS proposed the concept of a Unified Electronic Ledger, which wouldcombine Central Bank Digital Currencies, tokenized money, and assets ona single platform. This ledger would enable smart contract functionality similar to Ethereum on a global scale. The BIS emphasized the benefitsof integrating different types of money and assets on a unified ledger,such as reducing delays, uncertainties, and trade financing costs. They also highlighted the importance of policy harmonization across jurisdictions for the success of such a system.\n\n\t- ## Introduction\n\t\t- The RGB protocol stands as a cornerstone for building and managing smart contracts on blockchain networks, emphasizing privacy, security, and flexibility. This document delves into the intricate mechanics of RGB, covering state validation, contract schemas, and interfaces, alongside practical code examples.\n\n\t- ## Contract Schemas\n\t\t- A schema in RGB defines the structure and rules for a specific type of contract, acting as a blueprint for creating and managing contract instances.\n\n\t- ### Implementation\n\t\t- **Rust Example**: Contracts are typically defined using Rust, providing a robust framework for schema creation.\n\t\t- ```rust\n\t\t      struct ContractSchema {\n\t\t          global_types: Map<TypeIdentifier, TypeName>,\n\t\t          own_types: Map<TypeIdentifier, TypeName>,\n\t\t          // Additional fields defining operations and their structure...\n\t\t      }\n\t\t      ```\n\t\t- **Simplification**: Future iterations aim to simplify schema creation, making it more accessible to non-developers.\n\n\t- ## Interfaces\n\t\t- Interfaces play a crucial role in making smart contracts accessible and interactable, serving as a bridge between the contract logic and external applications, such as wallets.\n\n\t- ### Implementation and Binding\n\t\t- **Process**: Contract schemas implement specific interfaces, mapping state types and operations to the interface's requirements.\n\t\t- ```rust\n\t\t      impl Interface for MyContractSchema {\n\t\t          // Mapping schema types to interface definitions...\n\t\t      }\n\t\t      ```\n\n\t- ### Challenges\n\t\t- **Complexity**: The dual-layer validation and the depth of schema definitions can be daunting for new developers.\n\t\t- **Flexibility vs. Standardization**: Balancing the need for flexible contract logic with the benefits of standardized interfaces and operations.\n\n\t-\n\n\n## Current Landscape (2025)\n\n- Industry adoption and implementations\n  - Metaverse platforms continue to evolve with focus on interoperability and open standards\n  - Web3 integration accelerating with decentralised identity and asset ownership\n  - Enterprise adoption growing in virtual collaboration, training, and digital twins\n  - UK companies increasingly active in metaverse development and immersive technologies\n\n- Technical capabilities\n  - Real-time rendering at photorealistic quality levels\n  - Low-latency networking enabling seamless multi-user experiences\n  - AI-driven content generation and procedural world building\n  - Spatial audio and haptics enhancing immersion\n\n- UK and North England context\n  - Manchester: Digital Innovation Factory supports metaverse startups and research\n  - Leeds: Holovis leads in immersive experiences for entertainment and training\n  - Newcastle: University research in spatial computing and interactive systems\n  - Sheffield: Advanced manufacturing using digital twin technology\n\n- Standards and frameworks\n  - Metaverse Standards Forum driving interoperability protocols\n  - WebXR enabling browser-based immersive experiences\n  - glTF and USD for 3D asset interchange\n  - Open Metaverse Interoperability Group defining cross-platform standards\n\n## Metadata\n\n- **Last Updated**: 2025-11-16\n- **Review Status**: Automated remediation with 2025 context\n- **Verification**: Academic sources verified\n- **Regional Context**: UK/North England where applicable",
  "properties": {
    "id": "smart-contract-standards",
    "collapsed": "true",
    "- public-access": "true",
    "- ontology": "true",
    "- term-id": "BC-0009",
    "- preferred-term": "Smart Contract",
    "- source-domain": "blockchain",
    "- status": "complete",
    "- version": "1.0.0",
    "- last-updated": "2025-10-28",
    "- definition": "Self-executing programmable code within blockchain systems, providing essential functionality for distributed ledger technology operations and properties.",
    "- maturity": "mature",
    "- source": "[[ISO/IEC 23257:2021]], [[IEEE 2418.1]], [[NIST NISTIR]]",
    "- authority-score": "0.95",
    "- owl:class": "bc:SmartContract",
    "- owl:physicality": "VirtualEntity",
    "- owl:role": "Object",
    "- owl:inferred-class": "bc:VirtualObject",
    "- belongsToDomain": "[[BlockchainDomain]]",
    "- implementedInLayer": "[[ConceptualLayer]]",
    "- is-subclass-of": "[[Blockchain Entity]], [[DistributedDataStructure]]"
  },
  "backlinks": [],
  "wiki_links": [
    "BlockchainDomain",
    "ConceptualLayer",
    "Blockchain Entity",
    "ISO/IEC 23257:2021",
    "DistributedDataStructure",
    "NIST NISTIR",
    "IEEE 2418.1"
  ],
  "ontology": {
    "term_id": "BC-0009",
    "preferred_term": "Smart Contract",
    "definition": "Self-executing programmable code within blockchain systems, providing essential functionality for distributed ledger technology operations and properties.",
    "source_domain": "blockchain",
    "maturity_level": null,
    "authority_score": 0.95
  }
}