{
  "title": "Elliptic Curve Cryptography",
  "content": "- ### OntologyBlock\n  id:: elliptic-curve-cryptography-ontology\n  collapsed:: true\n\n  - **Identification**\n    - public-access:: true\n    - ontology:: true\n    - term-id:: BC-0032\n    - preferred-term:: Elliptic Curve Cryptography\n    - source-domain:: blockchain\n    - status:: complete\n    - version:: 1.0.0\n    - last-updated:: 2025-10-28\n\n  - **Definition**\n    - definition:: ECC-based public-key system within blockchain systems, providing essential functionality for distributed ledger technology operations and properties.\n    - maturity:: mature\n    - source:: [[ISO/IEC 23257:2021]], [[IEEE 2418.1]], [[NIST NISTIR]]\n    - authority-score:: 0.95\n\n  - **Semantic Classification**\n    - owl:class:: bc:EllipticCurveCryptography\n    - owl:physicality:: VirtualEntity\n    - owl:role:: Object\n    - owl:inferred-class:: bc:VirtualObject\n    - belongsToDomain:: [[CryptographicDomain]]\n    - implementedInLayer:: [[SecurityLayer]]\n\n  - #### Relationships\n    id:: elliptic-curve-cryptography-relationships\n    - is-subclass-of:: [[Blockchain Entity]], [[CryptographicPrimitive]]\n\n  - #### OWL Axioms\n    id:: elliptic-curve-cryptography-owl-axioms\n    collapsed:: true\n    - ```clojure\n      Prefix(:=<http://metaverse-ontology.org/blockchain#>)\nPrefix(owl:=<http://www.w3.org/2002/07/owl#>)\nPrefix(rdf:=<http://www.w3.org/1999/02/22-rdf-syntax-ns#>)\nPrefix(xml:=<http://www.w3.org/XML/1998/namespace>)\nPrefix(xsd:=<http://www.w3.org/2001/XMLSchema#>)\nPrefix(rdfs:=<http://www.w3.org/2000/01/rdf-schema#>)\nPrefix(dct:=<http://purl.org/dc/terms/>)\n\nOntology(<http://metaverse-ontology.org/blockchain/BC-0032>\n  Import(<http://metaverse-ontology.org/blockchain/core>)\n\n  ## Class Declaration\n  Declaration(Class(:EllipticCurveCryptography))\n\n  ## Subclass Relationships\n  SubClassOf(:EllipticCurveCryptography :CryptographicPrimitive)\n  SubClassOf(:EllipticCurveCryptography :BlockchainEntity)\n\n  ## Essential Properties\n  SubClassOf(:EllipticCurveCryptography\n    (ObjectSomeValuesFrom :partOf :Blockchain))\n\n  SubClassOf(:EllipticCurveCryptography\n    (ObjectSomeValuesFrom :hasProperty :Property))\n\n  ## Data Properties\n  DataPropertyAssertion(:hasIdentifier :EllipticCurveCryptography \"BC-0032\"^^xsd:string)\n  DataPropertyAssertion(:hasAuthorityScore :EllipticCurveCryptography \"1.0\"^^xsd:decimal)\n  DataPropertyAssertion(:isFoundational :EllipticCurveCryptography \"true\"^^xsd:boolean)\n\n  ## Object Properties\n  ObjectPropertyAssertion(:enablesFeature :EllipticCurveCryptography :BlockchainFeature)\n  ObjectPropertyAssertion(:relatesTo :EllipticCurveCryptography :RelatedConcept)\n\n  ## Annotations\n  AnnotationAssertion(rdfs:label :EllipticCurveCryptography \"Elliptic Curve Cryptography\"@en)\n  AnnotationAssertion(rdfs:comment :EllipticCurveCryptography\n    \"ECC-based public-key system\"@en)\n  AnnotationAssertion(dct:description :EllipticCurveCryptography\n    \"Foundational blockchain concept with formal ontological definition\"@en)\n  AnnotationAssertion(:termID :EllipticCurveCryptography \"BC-0032\")\n  AnnotationAssertion(:priority :EllipticCurveCryptography \"1\"^^xsd:integer)\n  AnnotationAssertion(:category :EllipticCurveCryptography \"cryptographic-foundations\"@en)\n)\n      ```",
  "properties": {
    "id": "elliptic-curve-cryptography-owl-axioms",
    "collapsed": "true",
    "- public-access": "true",
    "- ontology": "true",
    "- term-id": "BC-0032",
    "- preferred-term": "Elliptic Curve Cryptography",
    "- source-domain": "blockchain",
    "- status": "complete",
    "- version": "1.0.0",
    "- last-updated": "2025-10-28",
    "- definition": "ECC-based public-key system within blockchain systems, providing essential functionality for distributed ledger technology operations and properties.",
    "- maturity": "mature",
    "- source": "[[ISO/IEC 23257:2021]], [[IEEE 2418.1]], [[NIST NISTIR]]",
    "- authority-score": "0.95",
    "- owl:class": "bc:EllipticCurveCryptography",
    "- owl:physicality": "VirtualEntity",
    "- owl:role": "Object",
    "- owl:inferred-class": "bc:VirtualObject",
    "- belongsToDomain": "[[CryptographicDomain]]",
    "- implementedInLayer": "[[SecurityLayer]]",
    "- is-subclass-of": "[[Blockchain Entity]], [[CryptographicPrimitive]]"
  },
  "backlinks": [],
  "wiki_links": [
    "NIST NISTIR",
    "IEEE 2418.1",
    "CryptographicPrimitive",
    "ISO/IEC 23257:2021",
    "CryptographicDomain",
    "SecurityLayer",
    "Blockchain Entity"
  ],
  "ontology": {
    "term_id": "BC-0032",
    "preferred_term": "Elliptic Curve Cryptography",
    "definition": "ECC-based public-key system within blockchain systems, providing essential functionality for distributed ledger technology operations and properties.",
    "source_domain": "blockchain",
    "maturity_level": null,
    "authority_score": 0.95
  }
}