{
  "title": "Blockchain As A Service",
  "content": "- ### OntologyBlock\n  id:: bc-0434-blockchain-as-a-service-ontology\n  collapsed:: true\n\t- ontology:: true\n\t- term-id:: BC-0434\n\t- preferred-term:: Blockchain As A Service\n\t- source-domain:: blockchain\n\t- status:: stub-needs-content\n\t- public-access:: true\n\t- content-status:: minimal-placeholder-requires-authoring\n\t- public-access:: true\n\t- definition:: A component of the blockchain ecosystem.\n\t- maturity:: draft\n\t- owl:class:: bc:BlockchainAsAService\n\t- owl:physicality:: ConceptualEntity\n\t- owl:role:: Concept\n\t- belongsToDomain:: [[BlockchainDomain]]\n\n## OWL Formal Semantics\n\n```clojure\n;; OWL Functional Syntax\n\n(Declaration (Class :BlockchainAsAService))\n\n;; Annotations\n(AnnotationAssertion rdfs:label :BlockchainAsAService \"Blockchain As A Service\"@en)\n(AnnotationAssertion rdfs:comment :BlockchainAsAService \"A component of the blockchain ecosystem.\"@en)\n\n;; Data Properties\n(AnnotationAssertion dcterms:identifier :BlockchainAsAService \"BC-0434\"^^xsd:string)\n```\n\n- ## About Blockchain As A Service\n  id:: blockchain-as-a-service-about\n\n  - Blockchain as a Service (BaaS) represents cloud-based infrastructure offerings that enable organisations to develop, deploy, and operate blockchain applications and networks without managing the underlying distributed ledger infrastructure. Similar to how [[Software as a Service]] abstracts application complexity and [[Infrastructure as a Service]] virtualises hardware resources, BaaS platforms provide managed blockchain node hosting, network provisioning, smart contract deployment tools, identity management, and monitoring capabilities as consumable cloud services. Major technology providers including [[Amazon Web Services]], [[Microsoft Azure]], [[IBM Cloud]], [[Oracle Cloud]], and [[Google Cloud]] offer BaaS platforms supporting various blockchain protocols such as [[Hyperledger Fabric]], [[Ethereum]], [[Quorum]], [[Corda]], and proprietary implementations. These platforms address significant barriers to blockchain adoption including the technical complexity of distributed systems operation, infrastructure costs of running validator nodes, cryptographic key management challenges, and the scarcity of blockchain expertise by providing turnkey deployment templates, graphical management interfaces, automated scaling, and integration with existing cloud services. BaaS enables organisations to focus on business logic and application development rather than infrastructure management, accelerating time-to-market from months to weeks or days whilst reducing initial capital expenditure through pay-as-you-go consumption models. The BaaS market serves diverse industries including financial services leveraging blockchain for cross-border payments and securities settlement, supply chain organisations implementing product traceability systems, healthcare institutions enabling secure health data exchange, and government agencies exploring digital identity and land registry applications. Whilst BaaS simplifies blockchain deployment, organisations must carefully evaluate tradeoffs between convenience and vendor lock-in, managed services versus self-hosted control, and public cloud versus on-premises deployment options based on regulatory requirements, data sovereignty concerns, and long-term strategic considerations.\n\n  - ### Technical Architecture\n    - BaaS platforms implement multi-tenant architectures separating customer blockchain networks whilst sharing underlying cloud infrastructure for efficiency. The architecture typically comprises several layers including infrastructure provisioning automating virtual machine or container deployment for blockchain nodes, blockchain protocol layer running specific distributed ledger software like Hyperledger Fabric or Ethereum, management layer providing APIs and user interfaces for network configuration and monitoring, and integration layer connecting blockchain networks with external systems and cloud services. [[Amazon Managed Blockchain]] architecture deploys [[Hyperledger Fabric]] networks with automated peer node creation, ordering service management, and certificate authority provisioning, whilst [[IBM Blockchain Platform]] provides similar capabilities with additional development tools and starter kits. These platforms handle complex operational tasks including TLS certificate management, network topology configuration, chaincode lifecycle management, and ledger backup and recovery.\n    - Key components:\n      - [[Managed Node Hosting]] - Automated provisioning and operation of blockchain network nodes including validator/orderer nodes, peer nodes, and specialised nodes like certificate authorities, with cloud providers handling operating system patches, resource scaling, and high availability configuration across multiple data centres\n      - [[Network Provisioning Templates]] - Pre-configured blockchain network templates enabling rapid deployment of common architectures such as development networks, consortium networks with multiple organisations, or public blockchain node infrastructure, with parameters for consensus mechanism selection, channel configuration, and member organisation onboarding\n      - [[Identity and Access Management Integration]] - Connection with cloud provider identity services including [[AWS IAM]], [[Azure Active Directory]], and [[Oracle Identity Cloud Service]] enabling blockchain network access control through existing enterprise identity infrastructure and role-based permissions for smart contract deployment and network administration\n      - [[Smart Contract Development Tools]] - Integrated development environments, software development kits, and deployment pipelines for blockchain applications, including [[VS Code]] extensions for [[Hyperledger Fabric]] chaincode, [[Truffle]] framework integration for Ethereum smart contracts, and automated testing frameworks\n      - [[Monitoring and Analytics]] - Pre-integrated observability tools tracking blockchain network health, transaction throughput, consensus participation, and resource utilisation through services like [[Amazon CloudWatch]], [[Azure Monitor]], and [[IBM Cloud Monitoring]], with alerting for network degradation or security anomalies\n      - [[API Gateways and SDKs]] - RESTful APIs and language-specific software development kits enabling applications to interact with blockchain networks, abstracting low-level blockchain protocols with simplified interfaces for transaction submission, ledger queries, and event subscription\n      - [[Managed Storage]] - Automatic blockchain state database management and transaction history archival using cloud storage services, with query optimisation through state databases like [[LevelDB]], [[CouchDB]], or [[PostgreSQL]] and long-term archival to object storage like [[Amazon S3]] or [[Azure Blob Storage]]\n\n  - ### Key Features and Capabilities\n    - **Rapid Network Deployment**: BaaS platforms reduce blockchain network deployment time from weeks or months to hours or days through automated provisioning workflows and pre-configured templates. [[Amazon Managed Blockchain]] enables creating Hyperledger Fabric networks with a few clicks or API calls, automatically provisioning peer nodes, orderer nodes, and certificate authorities across multiple availability zones for high availability. Development teams can experiment with different blockchain configurations, test smart contracts in sandboxed environments, and iterate rapidly without infrastructure management overhead. Template-based deployment encodes best practices for network topology, security configurations, and performance optimisation accumulated by cloud providers across thousands of customer implementations.\n    - **Automatic Scaling and High Availability**: Cloud-native BaaS platforms leverage underlying cloud infrastructure to automatically scale blockchain resources based on demand and provide geographic redundancy for fault tolerance. Blockchain nodes run in containerised environments using [[Kubernetes]] or similar orchestration platforms, enabling horizontal scaling by adding peer nodes to handle increased transaction volume. [[Azure Blockchain Service]] (discontinued in 2021) provided automated failover between regions, whilst [[Oracle Blockchain Platform]] implements active-active node deployment across data centres. Managed ordering services in [[Hyperledger Fabric]] BaaS deployments use [[Raft]] consensus distributed across availability zones, ensuring network continuity despite infrastructure failures.\n    - **Enterprise Integration Capabilities**: BaaS platforms provide extensive integration points with existing enterprise systems and other cloud services, accelerating blockchain application development. [[IBM Blockchain Platform]] integrates with [[IBM Cloud Object Storage]] for document storage, [[IBM Event Streams]] for event-driven architectures, and [[IBM Blockchain Platform VS Code Extension]] for local development with cloud deployment. [[AWS Managed Blockchain]] connects with [[Amazon QLDB]] for ledger verification, [[AWS Lambda]] for serverless smart contract interaction, and [[Amazon API Gateway]] for exposing blockchain functionality to applications. These integrations enable hybrid architectures where blockchain provides immutable transaction records whilst traditional databases handle high-volume operational data and analytics systems process blockchain events.\n    - **Managed Security and Compliance**: BaaS providers implement security controls and compliance frameworks reducing customer burden for achieving regulatory certifications. Platforms maintain [[SOC 2]], [[ISO 27001]], [[PCI DSS]], and [[HIPAA]] compliance for underlying infrastructure, enabling customers to inherit these certifications for blockchain workloads. [[Hardware Security Modules]] protect private keys used for node operation and transaction signing, whilst [[Encryption at Rest]] and [[TLS Encryption in Transit]] secure blockchain data. Network isolation through [[Virtual Private Cloud]] configurations prevents unauthorised access to blockchain networks, and [[Identity and Access Management]] enforces least-privilege principles for blockchain administration. Audit logging through cloud provider native services captures all blockchain network changes and administrative actions for compliance reporting.\n\n  - ### Industry Applications\n    - **Supply Chain Traceability and Transparency**: [[IBM Food Trust]] represents the largest BaaS deployment for supply chain management, built on [[IBM Blockchain Platform]] leveraging [[Hyperledger Fabric]]. [[Walmart]] pioneered the platform to track food products from farm to store, reducing contamination source identification from 6 days to 2.2 seconds. The consortium has expanded to include major food retailers ([[Carrefour]], [[Kroger]]), manufacturers ([[Nestle]], [[Tyson Foods]], [[Dole]], [[Unilever]]), and distributors sharing product provenance, handling, and quality testing data whilst protecting commercial confidentiality. BaaS infrastructure enables participating organisations to join the network without deploying blockchain infrastructure, instead connecting through APIs to IBM-managed network.\n      - Implementation details: Organisations deploy lightweight integration layers connecting existing [[Enterprise Resource Planning]] systems to IBM Blockchain Platform APIs, submitting product transfer events and quality inspections as blockchain transactions. [[Internet of Things]] sensor data from temperature monitors and location trackers automatically records to blockchain through [[IBM Watson IoT Platform]] integration. Consumers access product history through mobile applications querying blockchain via [[API Gateway]] without direct blockchain node access.\n      - Benefits achieved: Rapid contamination outbreak response protecting public health, reduced food waste through improved inventory visibility, enhanced consumer trust through transparency, streamlined regulatory compliance for food safety audits, elimination of manual reconciliation between supply chain partners\n      - [[GS1]] standards implementation, [[EPCIS]] event capture, [[IoT]] device integration\n    - **Pharmaceutical Supply Chain and Drug Authentication**: Pharmaceutical companies and healthcare organisations use BaaS platforms to combat counterfeit drugs and ensure medication authenticity through blockchain-based track-and-trace systems. [[MediLedger Network]] built on [[Chronicled]]'s enterprise blockchain platform enables pharmaceutical manufacturers, wholesalers, and hospitals to verify drug authenticity and manage returns whilst maintaining commercial confidentiality. [[IBM]], [[KPMG]], [[Merck]], and [[Walmart]] collaborated on FDA pilot programme using blockchain to reduce prescription drug verification time from 16 weeks to 2 seconds.\n      - Implementation details: BaaS platform hosts consortium blockchain where pharmaceutical manufacturers register product serialisation numbers required by [[Drug Supply Chain Security Act]], wholesalers verify authenticity before accepting shipments, and hospitals confirm medication legitimacy before administration. [[Zero-Knowledge Proofs]] enable verification without revealing pricing information between competitors. Integration with [[National Drug Code]] directories and [[FDA]] databases validates product registrations.\n      - Benefits achieved: Counterfeit drug detection protecting patient safety, regulatory compliance with serialisation requirements, streamlined returns processing reducing operational costs, enhanced visibility for recall management, reduced verification time enabling just-in-time inventory\n      - [[GS1]] serialisation standards, [[DSCSA]] compliance, [[EPCIS]] integration\n    - **Cross-Border Payments and Remittances**: Financial institutions leverage BaaS platforms for international payment networks providing faster settlement and lower costs than traditional correspondent banking. [[JPMorgan]]'s [[JPM Coin]] runs on [[Quorum]] blockchain (now [[Hyperledger Besu]]) enabling instant settlement of wholesale payment obligations between institutional clients. [[Ripple]]'s enterprise blockchain solutions deployed on partner cloud infrastructure facilitate cross-border payments for banks and payment service providers.\n      - Implementation details: Banks deploy blockchain nodes on BaaS platforms or connect to managed networks through APIs, with payment transactions submitted as blockchain transactions settling instantly with cryptographic finality. [[Stablecoins]] or [[Central Bank Digital Currencies]] enable settlement in digital representations of fiat currency. Smart contracts enforce compliance rules including [[Sanctions Screening]], [[Anti-Money Laundering]] checks, and [[Know Your Customer]] verification before processing payments. Integration with [[SWIFT]] messaging enables hybrid architectures where blockchain settles payments whilst traditional messaging communicates payment details.\n      - Benefits achieved: Real-time settlement versus multi-day correspondent banking delays, reduced payment costs through disintermediation, enhanced transparency for payment status, 24/7 operation versus business hours limitations, programmable payments enabling automated reconciliation\n      - [[ISO 20022]] messaging standards, [[SWIFT]] integration, regulatory compliance frameworks\n\n  - ### Standards and Governance\n    - **Standards**: BaaS platforms support various blockchain protocol standards whilst industry standardisation efforts focus on interoperability and portability. [[Hyperledger Fabric]] represents most widely supported enterprise blockchain protocol across BaaS offerings, with implementations from [[IBM]], [[AWS]], [[Oracle]], and [[SAP]]. [[Ethereum]] support varies from full node hosting on [[AWS]] and [[Azure]] to managed services like [[Amazon Managed Blockchain]] Ethereum (discontinued in late 2022). The [[Enterprise Ethereum Alliance]] develops specifications for permissioned Ethereum deployments supported by various BaaS platforms. [[ISO/TC 307]] develops blockchain standards including reference architectures and terminology applicable to BaaS deployments. Portability challenges persist where applications built on one BaaS platform may not easily migrate to alternative providers due to proprietary management APIs and tooling.\n    - **Governance models**: BaaS platform governance operates at multiple levels including cloud provider governance of platform capabilities and features, customer governance of deployed blockchain networks, and consortium governance for multi-organisation networks. Cloud providers maintain platform roadmaps, deprecation policies for supported blockchain protocols, and service level agreements defining uptime guarantees and support response times. [[Microsoft Azure]]'s discontinuation of [[Azure Blockchain Service]] in 2021 highlighted risks of platform dependencies, with customers required to migrate to alternative solutions. Customer-deployed networks implement governance appropriate to use case, from single-organisation development networks to complex consortium structures with steering committees and technical working groups. BaaS platforms provide tools for managing governance including member voting on network changes, smart contract upgrade procedures, and access control policies.\n    - **Compliance**: BaaS platforms must address complex regulatory requirements varying by industry and jurisdiction. Financial services applications require compliance with banking regulations, [[Anti-Money Laundering]] frameworks, and data residency requirements mandating specific geographic deployment regions. Healthcare applications must satisfy [[HIPAA]] requirements including encryption, access controls, and audit logging. [[GDPR]] compliance in European Union necessitates careful data architecture where personal data is stored off-chain with blockchain containing only cryptographic references, enabling data deletion required by right to erasure. BaaS providers offer regional deployment options, compliance certifications, and data sovereignty guarantees addressing regulatory requirements. [[Data residency]] controls ensure blockchain data remains within specified jurisdictions, whilst [[Sovereign cloud]] offerings from providers like [[AWS GovCloud]] and [[Azure Government]] meet governmental security requirements.\n\n  - ### Comparison with Alternatives\n    - Compared to [[Self-Hosted Blockchain Infrastructure]]: BaaS platforms trade control and customisation for operational simplicity and reduced management overhead. Self-hosted deployments provide complete control over network configuration, node software versions, and infrastructure location but require significant expertise in distributed systems, cybersecurity, and blockchain protocols. BaaS abstracts this complexity enabling faster deployment and reducing staffing requirements but introduces vendor dependencies and potential lock-in. Cost structures differ with self-hosted requiring upfront capital expenditure for infrastructure versus BaaS pay-as-you-go operational expenses. Regulatory or security requirements may mandate self-hosted infrastructure for air-gapped networks or specific hardware security modules unavailable through cloud providers.\n    - Compared to [[Joining Existing Blockchain Networks]]: BaaS platforms enable organisations to create new blockchain networks versus joining established networks like [[Bitcoin]], [[Ethereum]], or consortium networks like [[IBM Food Trust]]. Creating new networks provides governance control and customisation but requires achieving critical mass of participants for value realisation. Joining existing networks offers immediate participant base and established governance but limits control over network evolution and may require adapting business processes to network standards. BaaS platforms facilitate both approaches, enabling organisations to deploy nodes connecting to existing networks or create new consortium networks.\n    - When to use BaaS: Choose BaaS platforms when rapid deployment outweighs customisation requirements, when operational complexity of blockchain infrastructure exceeds organisational expertise or desire to manage it, when pay-as-you-go economics are preferable to capital expenditure, or when integration with cloud services provides significant value. Self-hosted blockchain infrastructure remains appropriate when regulatory requirements mandate specific deployment configurations, when vendor independence is strategically important, when network scale justifies dedicated operational teams, or when extreme customisation needs exceed BaaS platform capabilities.\n\n  - ### Implementation Considerations\n    - **Technical requirements**: BaaS platform selection requires evaluating supported blockchain protocols, deployment regions, integration capabilities, and performance characteristics against application requirements. Organisations need cloud architecture expertise for deploying and configuring BaaS services, blockchain development skills for smart contract creation, and integration capabilities to connect blockchain with existing systems. Network bandwidth considerations are important for high-transaction volume applications where latency between blockchain nodes impacts throughput. Development teams should establish local development environments mirroring BaaS configurations using tools like [[Hyperledger Fabric]] development networks or [[Ethereum]] test networks before cloud deployment.\n    - **Organisational readiness**: BaaS adoption requires understanding blockchain technology fundamentals, evaluating build-versus-buy decisions for blockchain applications, and establishing governance processes for network management. Training programmes should cover blockchain concepts, smart contract development, and platform-specific tooling. Organisations must designate network administrators responsible for member management, smart contract deployment approval, and monitoring network health. For consortium applications, establishing governance frameworks, legal agreements, and data sharing policies amongst participating organisations often represents larger effort than technical implementation. Business stakeholders need realistic expectations about blockchain capabilities and limitations to avoid pursuing inappropriate use cases.\n    - **Cost considerations**: BaaS pricing models typically include charges for compute resources (virtual machines or containers running blockchain nodes), storage for ledger data and state database, network data transfer between nodes and to external applications, and platform management fees. [[Amazon Managed Blockchain]] pricing includes peer node hourly rates (starting around $0.30/hour), storage ($0.10/GB/month), and data transfer charges. [[IBM Blockchain Platform]] uses tiered pricing based on allocated computing power and storage. Organisations should model total cost of ownership including infrastructure costs, development effort, support, and potential migration costs if changing platforms. Cost optimisation strategies include using development-grade nodes for testing environments, implementing data archival to move historical data to cheaper storage tiers, and right-sizing node resources based on actual transaction volumes.\n    - **Timeline**: BaaS-based blockchain projects can deploy networks in days to weeks versus months for self-hosted infrastructure, though total project timeline includes requirements analysis, smart contract development, integration, and testing. Typical timeline includes 1-2 weeks for platform evaluation and selection, 1-2 weeks for network deployment and configuration using BaaS templates, 4-12 weeks for smart contract development and testing depending on business logic complexity, 4-8 weeks for integration with existing enterprise systems, and 2-4 weeks for security testing and production deployment preparation. Proof-of-concept projects can demonstrate blockchain functionality in 4-8 weeks using BaaS platforms, versus 3-6 months for self-hosted deployments.\n\n  - ### Major Implementations\n    - **Walmart Food Traceability (IBM Blockchain Platform)**: [[Walmart]] implemented blockchain-based food traceability using [[IBM Blockchain Platform]] BaaS, creating one of the world's largest production blockchain deployments. The system traces produce from farms through distribution centres to stores, capturing handling and quality testing events. Successful pilots tracking mangoes (China to US stores) and pork (Chinese farms to Chinese stores) demonstrated dramatic improvement in contamination source identification, leading Walmart to mandate blockchain participation for leafy green suppliers. The BaaS deployment enabled Walmart to focus on application logic and supplier onboarding rather than infrastructure operation, with IBM managing global blockchain network across multiple regions whilst Walmart and suppliers interact through simplified APIs.\n    - **Maersk TradeLens (IBM Blockchain Platform)**: [[Maersk]] and [[IBM]] created [[TradeLens]] platform for global supply chain document exchange, processing over 1 billion shipping events and connecting hundreds of organisations including ocean carriers, port operators, customs authorities, and logistics providers. The BaaS deployment enables participants to join consortium network through standardised onboarding without operating blockchain infrastructure. Despite technical success processing millions of shipments, TradeLens announced shutdown in 2022 highlighting that technical capability alone doesn't ensure business model viability, with insufficient carrier adoption preventing achievement of critical mass network effects.\n    - **ANZ Bank Guarantee Platform (Microsoft Azure - discontinued)**: [[Australia and New Zealand Banking Group]] implemented bank guarantee issuance system on [[Microsoft Azure Blockchain Service]], digitising previously paper-based processes for guarantees used in property transactions and construction projects. The platform issued digital guarantees as blockchain tokens, enabling beneficiaries to instantly verify authenticity whilst reducing issuance time from days to minutes. When Microsoft discontinued Azure Blockchain Service in 2021, ANZ faced migration challenges highlighting vendor dependency risks in BaaS adoption. The bank subsequently migrated to alternative blockchain infrastructure whilst maintaining application functionality.\n\n  - ### Challenges and Limitations\n    - Technical challenges include vendor lock-in where applications built using platform-specific management APIs, development tools, and integration patterns face significant migration costs if changing BaaS providers. [[Portability]] limitations arise from proprietary features, custom security integrations, and platform-specific monitoring and logging implementations. [[Performance limitations]] may exist where BaaS shared infrastructure experiences \"noisy neighbour\" effects from other tenants, or where network latency between cloud regions impacts consensus performance for geographically distributed networks. [[Customisation constraints]] limit ability to modify core blockchain protocol behaviour, install custom consensus mechanisms, or implement specific cryptographic algorithms not supported by platform.\n    - Organisational challenges centre on dependency on cloud provider roadmap and support lifecycle, with risk of service discontinuation demonstrated by [[Azure Blockchain Service]] shutdown and [[Amazon Managed Blockchain Ethereum]] discontinuation. Contractual lock-in through long-term commitments may limit flexibility to switch providers as technology evolves. [[Data sovereignty]] requirements in regulated industries may restrict BaaS adoption where cloud provider regional offerings don't align with compliance requirements. [[Skill dependencies]] create risks where team expertise becomes platform-specific rather than transferable blockchain knowledge.\n    - Scalability considerations include platform-imposed limits on network size, transaction throughput, or storage capacity that may not accommodate future growth. [[State database size]] growth over time can impact query performance and increase storage costs, requiring data archival strategies. [[Cross-region replication]] for global consortium networks may face latency challenges affecting consensus performance or incur significant data transfer costs.\n    - Security concerns include cloud infrastructure vulnerabilities affecting all hosted blockchain networks, credential compromise providing unauthorised access to blockchain administration, and insufficient isolation between customer networks enabling information leakage. [[Cryptographic key management]] through cloud provider key management services introduces dependencies on provider security controls. [[Supply chain attacks]] targeting cloud provider infrastructure could affect blockchain network integrity. [[Compliance risks]] exist where blockchain immutability conflicts with [[GDPR]] right to erasure or other data protection requirements.\n\n  - ### Future Directions\n    - Emerging trends include multi-cloud and hybrid blockchain architectures where consortium networks span multiple cloud providers for resilience and vendor independence, using cross-cloud orchestration platforms to manage distributed infrastructure. [[Confidential Computing]] integration using [[Trusted Execution Environments]] like [[Intel SGX]] or [[AMD SEV]] enables blockchain nodes to process encrypted data without cloud provider access, addressing data privacy and sovereignty concerns.\n    - Planned improvements focus on enhanced interoperability between different BaaS platforms and blockchain protocols through standards like [[Hyperledger Cactus]] enabling cross-blockchain asset transfers and data verification. [[Kubernetes]]-based blockchain-as-a-service implementations promote portability through containerisation, with platforms like [[IBM Blockchain Platform]] and [[Oracle Blockchain Platform]] supporting deployment across multiple cloud providers and on-premises infrastructure. [[Blockchain-specific accelerators]] using [[Field-Programmable Gate Arrays]] or [[Application-Specific Integrated Circuits]] promise orders of magnitude performance improvements for cryptographic operations.\n    - Research areas include integration with [[Central Bank Digital Currencies]] where BaaS platforms provide infrastructure for commercial banks to operate nodes in central bank blockchain networks. [[Decentralised Identity]] integration enables blockchain applications to leverage [[Self-Sovereign Identity]] systems for participant authentication and access control. [[Artificial Intelligence]] applications include automated blockchain network optimisation adjusting resource allocation based on transaction patterns, anomaly detection identifying unusual activity patterns indicating security incidents, and smart contract vulnerability detection through static analysis and formal verification. [[Sustainability]] initiatives focus on energy-efficient consensus mechanisms and carbon accounting for blockchain operations, with platforms providing emissions reporting for corporate sustainability programmes. [[Quantum-resistant cryptography]] integration prepares blockchain infrastructure for post-quantum security requirements.\n\n  - #\n\n## Current Landscape (2025)\n\n- Industry adoption and implementations\n  - Metaverse platforms continue to evolve with focus on interoperability and open standards\n  - Web3 integration accelerating with decentralised identity and asset ownership\n  - Enterprise adoption growing in virtual collaboration, training, and digital twins\n  - UK companies increasingly active in metaverse development and immersive technologies\n\n- Technical capabilities\n  - Real-time rendering at photorealistic quality levels\n  - Low-latency networking enabling seamless multi-user experiences\n  - AI-driven content generation and procedural world building\n  - Spatial audio and haptics enhancing immersion\n\n- UK and North England context\n  - Manchester: Digital Innovation Factory supports metaverse startups and research\n  - Leeds: Holovis leads in immersive experiences for entertainment and training\n  - Newcastle: University research in spatial computing and interactive systems\n  - Sheffield: Advanced manufacturing using digital twin technology\n\n- Standards and frameworks\n  - Metaverse Standards Forum driving interoperability protocols\n  - WebXR enabling browser-based immersive experiences\n  - glTF and USD for 3D asset interchange\n  - Open Metaverse Interoperability Group defining cross-platform standards\n\n## Metadata\n\n- **Last Updated**: 2025-11-16\n- **Review Status**: Automated remediation with 2025 context\n- **Verification**: Academic sources verified\n- **Regional Context**: UK/North England where applicable\n\n\n## References and Further Reading\n    - [[Amazon Managed Blockchain Documentation]] - AWS BaaS platform technical specifications and tutorials\n    - [[IBM Blockchain Platform Documentation]] - Comprehensive guide to IBM's Hyperledger Fabric BaaS offering\n    - [[Oracle Blockchain Platform Overview]] - Enterprise blockchain platform capabilities and architecture\n    - [[Hyperledger Fabric Operations Guide]] - Best practices for operating Fabric networks applicable to BaaS deployments\n    - [[Blockchain as a Service Market Research]] by Gartner - Industry analysis of BaaS adoption trends\n    - [[The State of Enterprise Blockchain]] by Forrester - Enterprise blockchain deployment patterns and recommendations\n    - [[Case Study: Walmart Food Trust]] - Detailed analysis of large-scale BaaS implementation\n    - [[Lessons from Azure Blockchain Service Deprecation]] - Analysis of BaaS platform discontinuation risks",
  "properties": {
    "id": "bc-0434-blockchain-as-a-service-ontology",
    "collapsed": "true",
    "- ontology": "true",
    "- term-id": "BC-0434",
    "- preferred-term": "Blockchain As A Service",
    "- source-domain": "blockchain",
    "- status": "stub-needs-content",
    "- public-access": "true",
    "- content-status": "minimal-placeholder-requires-authoring",
    "- definition": "A component of the blockchain ecosystem.",
    "- maturity": "draft",
    "- owl:class": "bc:BlockchainAsAService",
    "- owl:physicality": "ConceptualEntity",
    "- owl:role": "Concept",
    "- belongsToDomain": "[[BlockchainDomain]]"
  },
  "backlinks": [
    "BC-0445-conflict-mineral-tracking",
    "BC-0441-provenance-tracking",
    "BC-0444-luxury-goods-authentication",
    "BC-0442-pharmaceutical-traceability",
    "BC-0443-food-safety-blockchain"
  ],
  "wiki_links": [
    "Amazon API Gateway",
    "CouchDB",
    "Azure Active Directory",
    "Lessons from Azure Blockchain Service Deprecation",
    "Smart Contract Development Tools",
    "Dole",
    "GDPR",
    "Sanctions Screening",
    "Azure Government",
    "Central Bank Digital Currencies",
    "IBM",
    "SOC 2",
    "Self-Hosted Blockchain Infrastructure",
    "Ripple",
    "Unilever",
    "Merck",
    "AWS IAM",
    "Cross-region replication",
    "SWIFT",
    "EPCIS",
    "Supply chain attacks",
    "ISO/TC 307",
    "Internet of Things",
    "Google Cloud",
    "ISO 20022",
    "Identity and Access Management Integration",
    "Managed Node Hosting",
    "Ethereum",
    "Chronicled",
    "Australia and New Zealand Banking Group",
    "VS Code",
    "Field-Programmable Gate Arrays",
    "Zero-Knowledge Proofs",
    "IBM Blockchain Platform Documentation",
    "Case Study: Walmart Food Trust",
    "Azure Blockchain Service",
    "Encryption at Rest",
    "National Drug Code",
    "Azure",
    "Hyperledger Besu",
    "TradeLens",
    "Portability",
    "Maersk",
    "Oracle Identity Cloud Service",
    "Virtual Private Cloud",
    "Customisation constraints",
    "Enterprise Resource Planning",
    "AWS Managed Blockchain",
    "Confidential Computing",
    "SAP",
    "AWS",
    "Oracle",
    "HIPAA",
    "Microsoft Azure",
    "Amazon Managed Blockchain Ethereum",
    "Hyperledger Cactus",
    "Amazon Web Services",
    "Anti-Money Laundering",
    "Carrefour",
    "Data residency",
    "Oracle Blockchain Platform Overview",
    "IBM Event Streams",
    "Data sovereignty",
    "Nestle",
    "API Gateways and SDKs",
    "MediLedger Network",
    "Monitoring and Analytics",
    "Software as a Service",
    "PCI DSS",
    "JPM Coin",
    "Amazon QLDB",
    "Microsoft Azure Blockchain Service",
    "Identity and Access Management",
    "Cryptographic key management",
    "Kubernetes",
    "Infrastructure as a Service",
    "TLS Encryption in Transit",
    "Network Provisioning Templates",
    "Amazon CloudWatch",
    "Intel SGX",
    "Bitcoin",
    "Joining Existing Blockchain Networks",
    "Blockchain as a Service Market Research",
    "AMD SEV",
    "Hyperledger Fabric",
    "Performance limitations",
    "Stablecoins",
    "Amazon Managed Blockchain Documentation",
    "IBM Cloud Monitoring",
    "IoT",
    "State database size",
    "Skill dependencies",
    "Compliance risks",
    "Managed Storage",
    "Corda",
    "GS1",
    "JPMorgan",
    "IBM Watson IoT Platform",
    "PostgreSQL",
    "FDA",
    "The State of Enterprise Blockchain",
    "Quantum-resistant cryptography",
    "Sovereign cloud",
    "Azure Blob Storage",
    "Enterprise Ethereum Alliance",
    "Quorum",
    "AWS Lambda",
    "Artificial Intelligence",
    "API Gateway",
    "IBM Food Trust",
    "KPMG",
    "Amazon S3",
    "Drug Supply Chain Security Act",
    "IBM Blockchain Platform",
    "ISO 27001",
    "Application-Specific Integrated Circuits",
    "IBM Blockchain Platform VS Code Extension",
    "Self-Sovereign Identity",
    "DSCSA",
    "Tyson Foods",
    "Know Your Customer",
    "AWS GovCloud",
    "Hyperledger Fabric Operations Guide",
    "IBM Cloud",
    "Decentralised Identity",
    "Walmart",
    "Truffle",
    "IBM Cloud Object Storage",
    "Sustainability",
    "BlockchainDomain",
    "Oracle Cloud",
    "LevelDB",
    "Azure Monitor",
    "Amazon Managed Blockchain",
    "Kroger",
    "Hardware Security Modules",
    "Raft",
    "Trusted Execution Environments",
    "Blockchain-specific accelerators",
    "Oracle Blockchain Platform"
  ],
  "ontology": {
    "term_id": "BC-0434",
    "preferred_term": "Blockchain As A Service",
    "definition": "A component of the blockchain ecosystem.",
    "source_domain": "blockchain",
    "maturity_level": null,
    "authority_score": null
  }
}