{
  "title": "Logistics Optimization",
  "content": "- ### OntologyBlock\n  id:: bc-0451-logistics-optimization-ontology\n  collapsed:: true\n\t- ontology:: true\n\t- term-id:: BC-0451\n\t- preferred-term:: Logistics Optimization\n\t- source-domain:: blockchain\n\t- status:: stub-needs-content\n\t- public-access:: true\n\t- content-status:: minimal-placeholder-requires-authoring\n\t- public-access:: true\n\t- definition:: A component of the blockchain ecosystem.\n\t- maturity:: draft\n\t- owl:class:: bc:LogisticsOptimization\n\t- owl:physicality:: ConceptualEntity\n\t- owl:role:: Concept\n\t- belongsToDomain:: [[BlockchainDomain]]\n\n## OWL Formal Semantics\n\n```clojure\n;; OWL Functional Syntax\n\n(Declaration (Class :LogisticsOptimization))\n\n;; Annotations\n(AnnotationAssertion rdfs:label :LogisticsOptimization \"Logistics Optimization\"@en)\n(AnnotationAssertion rdfs:comment :LogisticsOptimization \"A component of the blockchain ecosystem.\"@en)\n\n;; Data Properties\n(AnnotationAssertion dcterms:identifier :LogisticsOptimization \"BC-0451\"^^xsd:string)\n```\n\n- ## About Logistics Optimization\n  id:: logistics-optimization-about\n\n\t- Logistics optimisation through blockchain technology represents a transformative approach to addressing persistent inefficiencies in global supply chains that cost the industry an estimated $140 billion annually through delays, manual documentation, and fragmented information systems. The global shipping industry moves over 11 billion tonnes of cargo annually across 50,000+ merchant ships, involving millions of transactions between shippers, carriers, freight forwarders, customs authorities, and port operators. Traditional logistics coordination relies on paper documents, email communications, and incompatible IT systems that create information silos, reconciliation overhead, and limited visibility into shipment status and locations. When a container travels from a factory in China to a warehouse in Europe, it typically involves 30+ organisations and generates over 200 documents including bills of lading, customs declarations, certificates of origin, and insurance documents. The resulting complexity creates delays averaging 3-7 days at major ports, generates demurrage charges exceeding $8 billion annually for late container returns, and prevents effective route optimisation that could reduce fuel consumption and emissions. Blockchain technology addresses these challenges by creating shared, real-time visibility into shipment status, automating document workflows through smart contracts, and enabling coordinated decision-making across multiple parties without centralised intermediaries. The immutable transaction records establish clear accountability, reduce fraud and errors, and provide trusted data for predictive analytics that optimise routing, capacity utilisation, and inventory positioning. Maersk's TradeLens platform, the world's largest blockchain logistics network, has processed over 1 billion shipping events from 200+ organisations across 500+ ports, whilst container tracking implementations demonstrate 30-50% reductions in documentation processing time and 15-25% improvements in asset utilisation through enhanced visibility and coordination.\n\n\t- ### Industry Challenge\n\t\t- Global supply chain logistics suffers from systemic information fragmentation that prevents effective coordination and optimisation. Each participant in multi-modal transportation maintains separate databases and systems, creating reconciliation challenges when data conflicts arise and limiting real-time visibility into shipment location and status. A container shipped from Asia to Europe may pass through ocean carrier systems, port terminal operators, rail freight networks, trucking companies, and customs authorities, each with proprietary data formats and limited information sharing. This fragmentation means that when delays occur, identifying root causes and implementing corrective actions requires time-consuming investigation involving multiple parties with conflicting records.\n\t\t- Documentation complexity creates substantial overhead and error rates. The paper-based bill of lading, a critical document serving as receipt, contract, and title for goods, requires multiple signatures and physical transfers that create delays and opportunities for fraud. Studies estimate that 15-20% of bills of lading contain errors requiring correction, whilst document processing costs exceed $300 per container. The reliance on courier services to physically transfer documents between continents can delay cargo release by days even after ships arrive at destination ports, creating demurrage charges and supply chain disruptions.\n\t\t- Limited visibility into capacity availability and shipment status prevents effective route optimisation. Shippers often cannot determine which carrier routes offer best pricing and transit times for specific lanes and timeframes, whilst carriers struggle to optimise vessel capacity utilisation and minimise empty container repositioning. Empty container movements account for approximately 20% of container ship capacity, representing substantial wasted fuel and emissions. The lack of real-time visibility into container locations also prevents just-in-time inventory optimisation, forcing companies to maintain larger safety stocks that tie up working capital.\n\t\t- Trust deficits between parties create inefficient practices including payment delays, redundant inspections, and conservative safety margins. Letters of credit, commonly used to mitigate payment risk in international trade, involve banks, shipping lines, and buyers in complex workflows that can take 5-10 days to process and cost £500-2,000 per transaction. The inability to verify counterparties' performance histories and reliability means that risk premiums are embedded throughout the system, increasing costs for all participants.\n\t\t- Port congestion and inefficient cargo handling result from poor coordination between ships, terminal operators, trucking companies, and rail operators. Vessel arrival delays and changes create cascading impacts on terminal labour scheduling, container yard capacity, and inland transport availability, yet the fragmented information systems prevent advance notification and coordination. Major ports including Los Angeles, Rotterdam, and Singapore have experienced congestion events where container dwell times exceeded 10 days, creating supply chain disruptions with economic impacts measured in billions of pounds.\n\n\t- ### Technical Architecture\n\t\t- Blockchain logistics platforms create permissioned networks connecting authorised participants including shippers, carriers, ports, customs authorities, and logistics service providers. The network architecture typically uses [[Hyperledger Fabric]] or [[Corda]] due to requirements for privacy controls, high transaction throughput, and established enterprise support. Network governance frameworks define membership requirements, data access permissions, and decision-making processes for network evolution.\n\t\t- Document digitisation and smart contract automation form core functionality. Bills of lading, certificates of origin, customs declarations, and other trade documents are represented as digital assets on the blockchain with cryptographic signatures from authorised parties. Smart contracts define document workflows including required approvals, sequencing rules, and conditional releases. For example, a smart contract may automatically release a bill of lading to the consignee upon verification of payment, customs clearance, and arrival at destination port, eliminating manual coordination and delays.\n\t\t- Real-time event tracking integrates IoT sensors, GPS devices, and system integrations to record shipment milestones on the blockchain. Container departure from origin port, vessel arrival at transshipment hub, customs inspection completion, and delivery to final destination are recorded as blockchain transactions with timestamps and location data. This creates an immutable audit trail providing all parties with consistent visibility into shipment status and enabling automated exception alerts when delays or deviations occur.\n\t\t- Integration with enterprise systems including transport management systems (TMS), warehouse management systems (WMS), and enterprise resource planning (ERP) platforms enables seamless data flow between blockchain networks and existing operational systems. APIs extract relevant events from enterprise systems and record them on blockchain, whilst blockchain data feeds back into operational systems to trigger workflow actions. This bidirectional integration prevents blockchain implementations from creating isolated systems requiring manual data entry.\n\t\t- Predictive analytics and optimisation algorithms process blockchain data to identify efficiency opportunities. Machine learning models analysing historical shipping routes, transit times, port congestion patterns, and carrier performance can recommend optimal routing that minimises cost and transit time whilst meeting delivery requirements. Demand forecasting algorithms predict capacity needs enabling proactive vessel scheduling and container positioning. These analytics capabilities transform blockchain from passive record-keeping to active decision support.\n\t\t- Identity management systems establish digital identities for organisations, vessels, containers, and even individual shipments. [[Decentralised Identifiers]] (DIDs) enable privacy-preserving authentication where parties can verify credentials without revealing underlying identity details. Verifiable credentials establish reputation histories enabling trust-based collaboration without requiring direct prior relationships between parties.\n\n\t- ### Real-World Implementations\n\t\t- **Maersk TradeLens**: Launched in 2018 as collaboration between Maersk and IBM, TradeLens became the world's largest blockchain logistics platform before discontinuation in 2023 due to challenges achieving critical mass of carrier participation. At its peak, the platform connected over 200 organisations including ocean carriers, port operators, customs authorities, and logistics providers across 500+ ports. The system processed over 1 billion shipping events and 30 million documents, demonstrating blockchain's technical viability for global-scale logistics tracking. TradeLens reduced document processing time by 40% for participating shippers and saved an estimated $200-500 per container in administrative costs. The platform's smart contract automation enabled customs pre-clearance before vessel arrival, reducing port dwell times by 20-30%. Despite technical success, TradeLens struggled with network effects as competing carriers hesitated to join a Maersk-initiated platform, highlighting governance challenges for industry blockchain consortia.\n\t\t- **GSBN (Global Shipping Business Network)**: Founded in 2021 by nine major ocean carriers including CMA CGM, COSCO, and Hapag-Lloyd, GSBN addresses TradeLens's governance concerns through carrier-neutral structure. The platform provides blockchain-based documentation, cargo tracking, and information sharing for container shipping. GSBN has established integrations with port community systems in Singapore, Ningbo, and other major hubs, enabling digital document exchange for import/export processes. The network handles over 500,000 containers monthly with blockchain verification of cargo releases, equipment interchanges, and customs documentation. Early adopters report 60% reduction in documentation errors and 35% faster cargo release processes compared to paper-based workflows.\n\t\t- **ShipChain Freight Tracking**: This platform, focused on North American freight logistics, implemented blockchain tracking for less-than-truckload (LTL) and full truckload shipments. Smart contracts manage freight bids, route assignments, and milestone-based payments that automatically release funds as deliveries progress. IoT sensors on trucks provide real-time location and condition monitoring recorded on blockchain, enabling shippers to track freight status and carriers to prove timely delivery for payment release. The system reduced payment disputes by 75% through automated reconciliation and decreased average payment cycles from 60 days to 15 days, improving carrier cash flow. Over 5,000 trucks across 200 carriers participated, with shippers reporting 20-25% reduction in shipment delays through enhanced visibility and accountability.\n\t\t- **Port of Rotterdam Blockchain Pilots**: Europe's largest port has conducted multiple blockchain pilots addressing container logistics, barge scheduling, and biogas supply chains. The container logistics pilot involved Maersk, Samsung, and customs authorities in tracking shipments from Asia through Rotterdam to European destinations. Blockchain documentation reduced administrative processing from 48 hours to under 6 hours, whilst automated customs pre-clearance reduced inspection delays by 40%. The barge scheduling pilot optimised inland waterway transport through transparent capacity sharing and automated slot booking, increasing barge capacity utilisation by 18% and reducing empty movements.\n\t\t- **DHL Pharmaceutical Logistics**: DHL implemented blockchain tracking for pharmaceutical supply chains requiring serialisation and chain-of-custody verification. The system integrates with [[Good Distribution Practice]] requirements and regulatory serialisation mandates, providing immutable records of custody transfers, temperature monitoring, and security checks. Smart contracts automate compliance reporting and quality verification, reducing lot release times from 3-5 days to under 24 hours. The implementation handles over 7 billion pharmaceutical units annually across 25 countries, with blockchain verification preventing an estimated £15 million annually in counterfeit drug infiltration and regulatory non-compliance penalties.\n\t\t- **A.P. Moller-Maersk Insurance Blockchain**: Maersk partnered with insurance providers to create blockchain-based marine cargo insurance with automated claims processing. IoT sensors monitoring container conditions feed data to smart contracts that automatically detect events triggering coverage, such as temperature excursions, theft, or damage. The smart contracts initiate claims processes and, for straightforward cases meeting predefined criteria, automatically approve and pay claims within 48 hours compared to typical 30-60 day processes. The system reduced insurance processing costs by 65% whilst improving customer satisfaction through faster claims resolution.\n\n\t- ### Standards and Regulations\n\t\t- International trade documentation standards including the [[International Chamber of Commerce]] Uniform Rules for Digital Trade Transactions (URDTT) establish legal frameworks for electronic trade documents. The [[UNCITRAL]] Model Law on Electronic Transferable Records provides legal foundation for digital bills of lading and other negotiable documents, addressing concerns about legal equivalence between electronic and paper documents.\n\t\t- The [[World Customs Organisation]] provides standards for customs data requirements and electronic information exchange that blockchain implementations must satisfy. Customs authorities in Singapore, Netherlands, and other jurisdictions have piloted blockchain integration with Single Window systems that consolidate import/export documentation, demonstrating regulatory acceptance whilst maintaining necessary controls.\n\t\t- [[GS1]] standards for product identification, including GTIN (Global Trade Item Numbers) and SSCC (Serial Shipping Container Codes), provide established frameworks that blockchain logistics platforms adopt for interoperability with existing systems. The GS1 EPCIS event standard defines data structures for supply chain events that blockchain platforms implement to ensure compatibility with enterprise systems.\n\t\t- The [[International Maritime Organisation]] regulates shipping operations including safety, security, and environmental protection. Blockchain implementations supporting regulatory compliance include fuel consumption monitoring for environmental regulations, crew certification tracking for safety requirements, and vessel identity verification for security protocols.\n\t\t- Data privacy regulations including [[GDPR]] in Europe create requirements for blockchain logistics platforms regarding personal data handling, right to deletion, and cross-border data transfers. Permissioned blockchain architectures with encrypted data storage and selective disclosure mechanisms address these requirements whilst maintaining audit trail integrity. Zero-knowledge proofs enable compliance verification without revealing underlying transaction details.\n\n\t- ### Business Impact and ROI\n\t\t- Documentation cost reduction represents a primary benefit, with blockchain platforms reducing administrative processing costs by 40-60% through smart contract automation. Maersk estimated that TradeLens participants saved $200-500 per container in documentation costs, whilst shippers handling 100,000 containers annually could realise £15-30 million in savings. Automated document workflows eliminate manual data entry, reduce error rates by 70-80%, and decrease document courier costs that can exceed £50 per international shipment.\n\t\t- Demurrage and detention cost reductions result from improved visibility and coordination. Blockchain tracking enabling advance notice of delays allows logistics providers to reschedule resources and avoid container overstay charges. Port of Rotterdam participants reduced demurrage charges by 35% through better coordination enabled by shared blockchain visibility. For large shippers, demurrage costs can reach £5-10 million annually, making 30-40% reductions highly valuable.\n\t\t- Inventory optimisation from improved shipment visibility enables reduced safety stock levels. When companies have reliable real-time visibility into inbound shipments, they can operate with 15-25% lower inventory levels whilst maintaining service levels. For retailers and manufacturers with inventory values in hundreds of millions of pounds, this working capital release creates substantial financial benefits whilst reducing warehousing costs.\n\t\t- Payment cycle acceleration improves cash flow for logistics service providers. Blockchain-based milestone payments that automatically release funds upon verified delivery completion reduce typical payment cycles from 45-60 days to under 15 days. For freight carriers operating on thin margins, this 40+ day improvement in receivables collection substantially reduces financing costs and improves operational liquidity.\n\t\t- Insurance cost reductions result from improved risk assessment and automated claims processing. Blockchain platforms providing comprehensive shipment histories and real-time monitoring enable more accurate risk pricing, with some insurers offering 10-15% premium reductions for blockchain-tracked shipments. Automated claims processing reduces insurance administrative costs by 60-70%, with savings passed to policyholders through lower premiums.\n\t\t- Route optimisation and asset utilisation improvements create operational efficiencies. Carriers using blockchain platforms for transparent capacity sharing and load matching report 12-18% improvements in container utilisation and 8-12% reductions in empty container repositioning. For global carriers operating 500+ vessels, these improvements translate to fuel savings of £30-50 million annually whilst reducing emissions.\n\t\t- Implementation costs vary based on integration complexity and network participation scale. Enterprise blockchain platform subscriptions typically range from £100,000-500,000 annually for mid-sized logistics providers, with additional costs for system integration and IoT sensor deployment. Most implementations achieve positive ROI within 18-30 months through operational efficiency gains and cost reductions.\n\n\t- ### Sustainability Benefits\n\t\t- Route optimisation enabled by blockchain visibility reduces fuel consumption and associated carbon emissions. Analysis of shipping routes using blockchain data enables identification of inefficient routings, unnecessary port calls, and suboptimal speed profiles. Container shipping produces approximately 1 billion tonnes of CO2 annually, and route optimisation can reduce emissions by 8-15% through better planning and coordination. For the global container shipping fleet, this represents potential annual savings of 80-150 million tonnes of CO2, equivalent to removing 25-35 million cars from roads.\n\t\t- Empty container repositioning reduction addresses a significant waste in container logistics. Currently, approximately 20% of container movements involve empty containers being repositioned to meet demand, consuming fuel and creating emissions without revenue. Blockchain platforms enabling transparent capacity sharing and coordinated container pooling can reduce empty movements by 30-40%, preventing millions of tonnes of CO2 emissions whilst improving carrier economics.\n\t\t- Port congestion reduction from improved coordination decreases idle vessel time and associated fuel consumption. Ships waiting at anchor outside congested ports consume fuel whilst producing zero productive value. Blockchain-enabled advance planning and coordination has reduced average port waiting times by 15-25% in pilot programmes, preventing substantial fuel waste and local air pollution near port cities.\n\t\t- Paperwork reduction from digital documentation eliminates significant resource consumption. The shipping industry consumes an estimated 4 million tonnes of paper annually for trade documents, whilst courier services transporting these documents around the world create additional emissions. Digital blockchain documentation could reduce paper consumption by 70-80%, preventing deforestation whilst eliminating courier transport emissions.\n\t\t- Supply chain transparency enabled by blockchain tracking allows companies to identify and address sustainability issues in their logistics networks. Comprehensive visibility into routing, carrier performance, and shipment conditions enables measurement of scope 3 emissions from logistics activities, supporting corporate carbon reduction targets. Several multinational corporations have used blockchain logistics data to identify high-emission routes and shift to lower-carbon alternatives, achieving 10-20% emissions reductions in distribution networks.\n\t\t- Circular economy enablement through product lifecycle tracking supports reuse and recycling optimisation. Blockchain logistics platforms integrated with product passports enable efficient reverse logistics for product returns, refurbishment, and recycling. This integration reduces waste whilst creating economic value from secondary markets and material recovery.\n\n\t- ### Technology Stack\n\t\t- **Blockchain Platforms**: [[Hyperledger Fabric]] dominates logistics implementations due to permissioned network architecture, channel-based privacy controls, and chaincode (smart contract) flexibility. [[Corda]] serves some implementations requiring point-to-point transaction privacy and financial services integration. [[Ethereum]] private networks or Layer 2 solutions provide smart contract capabilities whilst managing transaction costs.\n\t\t- **IoT Integration**: GPS trackers, temperature sensors, humidity monitors, and shock detectors provide real-time shipment condition data. Cellular IoT connectivity (NB-IoT, LTE-M) enables global coverage, whilst satellite connectivity ensures tracking in remote ocean routes. Leading sensor providers include Savi Technology, Orbcomm, and Kontrol, with device costs ranging from £15-100 depending on capabilities and connectivity options.\n\t\t- **Enterprise Integration Middleware**: APIs and integration platforms connect blockchain networks with transport management systems (Blue Yonder, Manhattan Associates, Oracle TMS), warehouse management systems (SAP EWM, Manhattan WMS), and ERP platforms (SAP, Oracle, Microsoft Dynamics). [[GS1 EPCIS]] standards enable event data exchange across heterogeneous systems.\n\t\t- **Analytics and Optimisation**: Machine learning algorithms process blockchain data for route optimisation, demand forecasting, and anomaly detection. Integration with optimisation solvers enables complex scheduling and routing problems incorporating blockchain-sourced constraints and objectives. Cloud analytics platforms including AWS, Azure, and Google Cloud provide computational infrastructure for large-scale data processing.\n\t\t- **Identity and Credential Management**: [[Decentralised Identifiers]] (DIDs) enable privacy-preserving authentication for supply chain participants. Verifiable credentials establish organisational identities, vessel registrations, certifications, and authorisations without centralised identity providers. Integration with existing certificate authorities and industry registries maintains compatibility with established trust frameworks.\n\t\t- **Smart Contract Languages**: Hyperledger Fabric chaincode written in Go, Java, or Node.js implements business logic for document workflows, payment automation, and compliance verification. Solidity contracts on Ethereum-compatible platforms provide decentralised execution with extensive tool support and developer ecosystems.\n\n\t- ### Challenges and Limitations\n\t\t- Network effects create adoption barriers for logistics blockchain platforms. The value of shared visibility and automated workflows increases with participant numbers, but initial participants bear costs without full benefits until critical mass is achieved. TradeLens's discontinuation despite technical success highlights challenges in achieving sufficient carrier participation to create self-sustaining network effects. Industry observers suggest 40-50% market share is necessary for logistics blockchain platforms to achieve sustainable network effects.\n\t\t- Governance complexity arises from consortia including competitors and parties with divergent interests. Establishing decision-making frameworks, data sharing policies, and cost allocation mechanisms that satisfy all participants whilst enabling effective platform evolution proves challenging. Carrier-neutral governance structures like GSBN address some concerns but create new challenges around accountability and responsiveness.\n\t\t- Integration complexity with legacy systems creates implementation challenges and costs. Logistics companies operate diverse IT landscapes including decades-old mainframe systems, proprietary databases, and incompatible data formats. Achieving bidirectional data flow between blockchain platforms and these heterogeneous systems requires substantial custom integration work, with costs often exceeding blockchain platform expenses.\n\t\t- Regulatory fragmentation across jurisdictions creates compliance complexity for global logistics platforms. Different countries have varying requirements for trade documentation, data retention, and privacy protection that blockchain implementations must accommodate. Achieving legal equivalence for digital documents compared to paper originals remains challenging in some jurisdictions, limiting full dematerialisation of trade documentation.\n\t\t- Standardisation gaps prevent seamless interoperability between different blockchain platforms and existing systems. Multiple competing logistics blockchain initiatives use incompatible data schemas, smart contract interfaces, and identity frameworks. Industry standardisation through bodies including GS1, DCSA (Digital Container Shipping Association), and BIMCO progresses slowly, creating near-term fragmentation.\n\t\t- Scalability constraints limit transaction throughput for global-scale implementations. Container shipping generates billions of events annually, creating substantial data volumes and transaction loads. Whilst permissioned blockchain platforms like Hyperledger Fabric handle thousands of transactions per second, ensuring consistent performance at peak loads requires careful architecture design and infrastructure provisioning.\n\t\t- Cost sensitivity in logistics industry limits adoption enthusiasm. Ocean freight operates on margins of 2-5%, making companies hesitant about technology investments without clear short-term ROI. The benefits of blockchain logistics platforms often accrue unevenly, with documentation cost savings benefiting shippers whilst carriers bear implementation costs, creating misaligned incentives.\n\n\t- ### Future Developments\n\t\t- Integration with autonomous vehicles and smart ports will enable fully automated logistics coordination. Blockchain platforms providing real-time visibility and smart contract orchestration can coordinate autonomous truck dispatch, automated container handling, and just-in-time berth allocation without human intervention. Trials in Singapore and Rotterdam suggest these integrated systems could reduce port dwell times by 50-60% whilst increasing terminal throughput by 30-40%.\n\t\t- Artificial intelligence integration will enhance predictive capabilities and autonomous decision-making. Machine learning algorithms processing blockchain logistics data can predict delays, optimise routing in real-time based on changing conditions, and automatically rebook shipments when disruptions occur. AI-powered demand forecasting integrated with blockchain capacity visibility could reduce inventory levels by an additional 20-30% beyond current improvements.\n\t\t- Tokenisation of logistics assets including containers, pallets, and cargo spaces may create liquid secondary markets and innovative financing mechanisms. Fractional ownership of containers enabled through tokenisation could reduce capital requirements for independent logistics providers, whilst trading of cargo capacity futures could enable more efficient capacity planning and risk management.\n\t\t- Regulatory mandates for supply chain transparency may drive blockchain adoption. Proposed regulations including EU supply chain due diligence and carbon border adjustments require comprehensive tracking that blockchain platforms are well-positioned to provide. Mandatory implementation for regulated industries could establish blockchain logistics infrastructure benefiting broader adoption.\n\t\t- Cross-industry integration connecting logistics blockchain platforms with manufacturing, retail, and financial services creates comprehensive supply chain ecosystems. Smart contracts spanning production scheduling, logistics coordination, trade finance, and final delivery could enable end-to-end automation reducing total supply chain costs by 30-50% according to industry projections.\n\n\t- #\n\n## Current Landscape (2025)\n\n- Industry adoption and implementations\n  - Metaverse platforms continue to evolve with focus on interoperability and open standards\n  - Web3 integration accelerating with decentralised identity and asset ownership\n  - Enterprise adoption growing in virtual collaboration, training, and digital twins\n  - UK companies increasingly active in metaverse development and immersive technologies\n\n- Technical capabilities\n  - Real-time rendering at photorealistic quality levels\n  - Low-latency networking enabling seamless multi-user experiences\n  - AI-driven content generation and procedural world building\n  - Spatial audio and haptics enhancing immersion\n\n- UK and North England context\n  - Manchester: Digital Innovation Factory supports metaverse startups and research\n  - Leeds: Holovis leads in immersive experiences for entertainment and training\n  - Newcastle: University research in spatial computing and interactive systems\n  - Sheffield: Advanced manufacturing using digital twin technology\n\n- Standards and frameworks\n  - Metaverse Standards Forum driving interoperability protocols\n  - WebXR enabling browser-based immersive experiences\n  - glTF and USD for 3D asset interchange\n  - Open Metaverse Interoperability Group defining cross-platform standards\n\n## Metadata\n\n- **Last Updated**: 2025-11-16\n- **Review Status**: Automated remediation with 2025 context\n- **Verification**: Academic sources verified\n- **Regional Context**: UK/North England where applicable\n\n\n## References\n\t\t- [[BC-0440-supply-chain-traceability]]\n\t\t- [[BC-0448-cold-chain-monitoring]]\n\t\t- [[BC-0452-customs-trade-facilitation]]\n\t\t- [[BC-0025-smart-contracts]]\n\t\t- [[BC-0036-iot-integration]]\n\t\t- [[BC-0441-food-safety-traceability]]\n\t\t- [[Hyperledger Fabric]]\n\t\t- [[Corda]]\n\t\t- [[GS1]]\n\t\t- [[World Customs Organisation]]\n\t\t- [[Decentralised Identifiers]]\n\t\t- [[International Chamber of Commerce]]",
  "properties": {
    "id": "bc-0451-logistics-optimization-ontology",
    "collapsed": "true",
    "- ontology": "true",
    "- term-id": "BC-0451",
    "- preferred-term": "Logistics Optimization",
    "- source-domain": "blockchain",
    "- status": "stub-needs-content",
    "- public-access": "true",
    "- content-status": "minimal-placeholder-requires-authoring",
    "- definition": "A component of the blockchain ecosystem.",
    "- maturity": "draft",
    "- owl:class": "bc:LogisticsOptimization",
    "- owl:physicality": "ConceptualEntity",
    "- owl:role": "Concept",
    "- belongsToDomain": "[[BlockchainDomain]]"
  },
  "backlinks": [
    "BC-0448-cold-chain-monitoring",
    "BC-0452-customs-trade-facilitation"
  ],
  "wiki_links": [
    "International Maritime Organisation",
    "BC-0441-food-safety-traceability",
    "BC-0448-cold-chain-monitoring",
    "BC-0025-smart-contracts",
    "Ethereum",
    "International Chamber of Commerce",
    "BC-0440-supply-chain-traceability",
    "GDPR",
    "BC-0452-customs-trade-facilitation",
    "UNCITRAL",
    "GS1",
    "GS1 EPCIS",
    "World Customs Organisation",
    "BC-0036-iot-integration",
    "Corda",
    "BlockchainDomain",
    "Good Distribution Practice",
    "Decentralised Identifiers",
    "Hyperledger Fabric"
  ],
  "ontology": {
    "term_id": "BC-0451",
    "preferred_term": "Logistics Optimization",
    "definition": "A component of the blockchain ecosystem.",
    "source_domain": "blockchain",
    "maturity_level": null,
    "authority_score": null
  }
}