{
  "title": "Anti Counterfeiting",
  "content": "- ### OntologyBlock\n  id:: bc-0447-anti-counterfeiting-ontology\n  collapsed:: true\n\t- ontology:: true\n\t- term-id:: BC-0447\n\t- preferred-term:: Anti Counterfeiting\n\t- source-domain:: blockchain\n\t- status:: complete\n\t- public-access:: true\n\t- authority-score:: 0.88\n\t- definition:: Blockchain-based systems employing cryptographic verification, immutable ledgers, and physical-digital integration technologies (NFC tags, QR codes, RFID) to authenticate products, prevent counterfeiting, and establish verifiable supply chain provenance across pharmaceuticals, luxury goods, electronics, and consumer products.\n\t- maturity:: draft\n\t- owl:class:: bc:AntiCounterfeiting\n\t- owl:physicality:: ConceptualEntity\n\t- owl:role:: Concept\n\t- belongsToDomain:: [[BlockchainDomain]]\n\n## OWL Formal Semantics\n\n```clojure\nPrefix(:=<http://metaverse-ontology.org/blockchain#>)\nPrefix(owl:=<http://www.w3.org/2002/07/owl#>)\nPrefix(rdf:=<http://www.w3.org/1999/02/22-rdf-syntax-ns#>)\nPrefix(xsd:=<http://www.w3.org/2001/XMLSchema#>)\nPrefix(rdfs:=<http://www.w3.org/2000/01/rdf-schema#>)\nPrefix(dcterms:=<http://purl.org/dc/terms/>)\nPrefix(dt:=<http://metaverse-ontology.org/dt#>)\n\nOntology(<http://metaverse-ontology.org/blockchain/BC-0447>\n  Import(<http://metaverse-ontology.org/dt/properties>)\n\n  ## Class Declaration\n  Declaration(Class(:AntiCounterfeiting))\n\n  ## Subclass Relationships\n  SubClassOf(:AntiCounterfeiting :SupplyChainApplication)\n  SubClassOf(:AntiCounterfeiting :ProductAuthentication)\n  SubClassOf(:AntiCounterfeiting :BlockchainUseCase)\n\n  ## Essential Properties - Technology Integration\n  SubClassOf(:AntiCounterfeiting\n    (ObjectSomeValuesFrom dt:uses :CryptographicVerification))\n  SubClassOf(:AntiCounterfeiting\n    (ObjectSomeValuesFrom dt:uses :ImmutableLedger))\n  SubClassOf(:AntiCounterfeiting\n    (ObjectSomeValuesFrom dt:uses :PhysicalDigitalIntegration))\n\n  ## Physical Authentication Technologies\n  SubClassOf(:AntiCounterfeiting\n    (ObjectSomeValuesFrom dt:implements :NFCTag))\n  SubClassOf(:AntiCounterfeiting\n    (ObjectSomeValuesFrom dt:implements :QRCode))\n  SubClassOf(:AntiCounterfeiting\n    (ObjectSomeValuesFrom dt:implements :RFIDChip))\n\n  ## Blockchain Platforms\n  SubClassOf(:AntiCounterfeiting\n    (ObjectSomeValuesFrom dt:implementedby :HyperledgerFabric))\n  SubClassOf(:AntiCounterfeiting\n    (ObjectSomeValuesFrom dt:implementedby :VeChain))\n  SubClassOf(:AntiCounterfeiting\n    (ObjectSomeValuesFrom dt:implementedby :Ethereum))\n\n  ## Core Capabilities\n  SubClassOf(:AntiCounterfeiting\n    (ObjectSomeValuesFrom dt:enables :ProductAuthentication))\n  SubClassOf(:AntiCounterfeiting\n    (ObjectSomeValuesFrom dt:enables :ProvenanceTracking))\n  SubClassOf(:AntiCounterfeiting\n    (ObjectSomeValuesFrom dt:enables :SupplyChainVerification))\n\n  ## Requirements\n  SubClassOf(:AntiCounterfeiting\n    (ObjectSomeValuesFrom dt:requires :DistributedLedger))\n  SubClassOf(:AntiCounterfeiting\n    (ObjectSomeValuesFrom dt:requires :CryptographicHashFunction))\n  SubClassOf(:AntiCounterfeiting\n    (ObjectSomeValuesFrom dt:requires :TamperProofRecording))\n\n  ## Industry Applications\n  SubClassOf(:AntiCounterfeiting\n    (ObjectSomeValuesFrom dt:relatedto :PharmaceuticalTraceability))\n  SubClassOf(:AntiCounterfeiting\n    (ObjectSomeValuesFrom dt:relatedto :LuxuryGoodsAuthentication))\n  SubClassOf(:AntiCounterfeiting\n    (ObjectSomeValuesFrom dt:relatedto :FoodSafetyBlockchain))\n\n  ## Annotations\n  AnnotationAssertion(rdfs:label :AntiCounterfeiting \"Anti Counterfeiting\"@en)\n  AnnotationAssertion(rdfs:comment :AntiCounterfeiting\n    \"Blockchain-based systems employing cryptographic verification, immutable ledgers, and physical-digital integration technologies to authenticate products and prevent counterfeiting across pharmaceuticals, luxury goods, electronics, and consumer products.\"@en)\n  AnnotationAssertion(dcterms:identifier :AntiCounterfeiting \"BC-0447\"^^xsd:string)\n  AnnotationAssertion(dt:hasauthorityscore :AntiCounterfeiting \"0.88\"^^xsd:decimal)\n  AnnotationAssertion(dt:hasmaturity :AntiCounterfeiting \"draft\"@en)\n  AnnotationAssertion(dt:hasstatus :AntiCounterfeiting \"complete\"@en)\n)\n```\n\n- ## About Anti Counterfeiting\n  id:: bc-0447-anti-counterfeiting-about\n\n\t- Blockchain-based anti-counterfeiting solutions address a £1.023 trillion global counterfeit trade crisis that affects every major industry from pharmaceuticals to luxury goods, electronics to food safety. By creating immutable digital twins of physical products through cryptographic verification and secure physical-digital integration technologies, blockchain systems provide unprecedented product authentication capabilities whilst simultaneously tracking complete supply chain provenance from manufacture to end consumer.\n\t-\n\t- The technology combines tamper-resistant physical authentication methods—including secure NFC (Near Field Communication) tags generating dynamic cryptographic keys, serialised QR codes, and RFID chips—with distributed ledger systems that create permanent, unfalsifiable records of product origins, ownership transfers, and verification checkpoints throughout global supply chains.\n\t-\n\t- ### Global Counterfeiting Crisis\n\n\t\t- **Economic Impact**: Global counterfeit trade reached **£1.023 trillion in 2023**, representing 3.3% of global trade, with projections indicating growth to **£1.79 trillion by 2030**. The total displaced economic activity exceeds **£1.1 trillion annually**, with **£174 billion** lost to tax revenues and up to **5.4 million jobs** affected worldwide.\n\n\t\t- **Industry-Specific Losses**: Luxury brands lose approximately **£100 billion annually** to counterfeits, whilst the pharmaceutical sector experiences **£10 billion** in direct sales losses within the EU alone. The counterfeit pharmaceutical market reaches **£200-432 billion globally**, causing an estimated **500,000 deaths annually** in sub-Saharan Africa from fake medicines. Semiconductor companies face **£7.5 billion** annual losses, with counterfeit chips comprising a **£75 billion market** integrated into **£169 billion** of electronic devices.\n\n\t\t- **Consumer Safety Impact**: The World Health Organisation estimates that **10.5% of medicines globally** are substandard or falsified, rising to **1 in 10 medicines** in low- and middle-income countries. Counterfeit antimalarial drugs alone cause **267,000 deaths** annually in Africa. Beyond pharmaceuticals, **30% of counterfeit goods** pose direct health, safety, or environmental risks according to EU Customs data.\n\n\t- ### Major Blockchain Implementations\n\n\t\t- **LVMH AURA Blockchain Consortium**: The luxury goods sector's most comprehensive implementation tracks **50+ million registered products** with **15 million digital tokens** issued across Louis Vuitton, Bulgari, Hublot, Parfums Christian Dior, Hennessy, Prada, and Cartier. Built with ConsenSys and Microsoft Azure, the platform provides unique authenticity certificates, digital product passports for consumer verification, and e-warranty systems preventing stolen watch resale. Hennessy's 2022 Chinese New Year collector's edition demonstrated consumer engagement through WeChat-based certificate delivery.\n\n\t\t- **Everledger Diamond Tracking**: Having secured **£30.4 million** in funding, Everledger tracks **millions of diamonds** through complete provenance history from origin through cutting and polishing to retail. Partnerships with Chow Tai Fook Jewellery Group provide digital grading reports for the T Mark brand with GIA certification, whilst the Fred Meyer Jewelers collaboration deploys the RockSolid collection across **100 stores**. The platform creates permanent, unalterable records of diamond grading reports and craftsmanship traits accessible via desktop and mobile applications.\n\n\t\t- **MediLedger Pharmaceutical Network**: Launched in 2017 for U.S. Drug Supply Chain Security Act compliance, MediLedger connects Pfizer, Bayer, McKesson, and Novartis in a blockchain-based verification system that reduced pharmaceutical verification from **up to 48 hours to real-time** responses. The network employs Hyperledger Fabric with zero-knowledge proofs, enabling product authentication whilst maintaining commercial confidentiality. Performance metrics demonstrate verification success rates of **98.9%** with average response times of **0.4 seconds**.\n\n\t\t- **VeChain Multi-Industry Platform**: VeChain's implementations span luxury goods (LVMH Givenchy bags), food safety (Walmart China pork certification uploads), wine authentication (Penfolds bottles with NFC tags following **14,000-50,000 bottle** counterfeit seizures), and automotive parts tracking (BMW PartChain across **10 suppliers**). The platform combines NFC chip technology with blockchain verification, providing consumers with tamper-proof product detail access via smartphone scanning.\n\n\t\t- **Walmart-IBM Food Trust**: Deployed on Hyperledger Fabric since 2016, the system traces **25+ products from 5 suppliers** with **100+ participating companies**. The implementation reduced food tracing time from **6 days 18 hours to 2.2 seconds**—a 99.97% reduction enabling surgical recall precision. During contamination incidents, the system identifies affected batches in seconds rather than days, reducing recalled product volumes by **70-80%** and saving **£30-50 million** in product write-offs and administrative costs.\n\n\t- ### Technical Architecture\n\n\t\t- **Physical-Digital Integration Technologies**:\n\t\t  - **NFC (Near Field Communication)**: Secure type-4 NFC tags generate unique cryptographic keys with every tap, employing AES 128 encryption and SHA-256 hashing of chip UIDs during manufacturing. The tags integrate with Hyperledger Fabric, creating dynamic authentication that prevents duplication through keys that change and cannot be reused. With **90% of smartphones** NFC-enabled since 2020, consumer verification requires only device proximity.\n\t\t  - **QR Codes**: Whilst widespread and smartphone-compatible, static QR codes face cloning vulnerabilities via high-resolution photocopiers. Blockchain implementations combine QR scanning with backend verification systems, checking product histories against immutable ledgers to detect copied codes.\n\t\t  - **RFID Technology**: Radio-frequency identification enables automated scanning for inventory management and batch tracking, creating seamless physical-to-digital integration without manual intervention. Applications span warehouse automation, retail checkout verification, and anti-theft systems.\n\n\t\t- **Blockchain Architecture Components**:\n\t\t  - **Digital Twins**: Each physical product receives a unique digital identity during manufacturing, creating an unclonable link through serialisation recorded on immutable blockchain ledgers. The digital twin maintains an unalterable log of origin, supply chain journey, and authenticity verification checkpoints.\n\t\t  - **Smart Contracts**: Self-executing contracts automate verification logic, ownership transfers, and compliance checking. Implementations enable automated royalty distribution from resales, proof of shared ownership, and complex multi-party authentication workflows without manual intervention.\n\t\t  - **Cryptographic Hash Functions**: SHA-256 creates unique product fingerprints from NFC chip UIDs, whilst Keccak-256 secures pharmaceutical batch certificates in MediLedger implementations. These hashes provide tamper-evident verification—any modification produces completely different hash values, immediately revealing tampering attempts.\n\n\t\t- **Enterprise Blockchain Platforms**: **Hyperledger Fabric** dominates pharmaceutical and food safety implementations (Walmart, MediLedger, FarmaTrust) through permissioned networks with privacy controls. **Ethereum** supports public verification for luxury goods and NFT-based authentication (Nike CryptoKicks). **VeChain** provides enterprise-focused infrastructure with public verification elements for consumer-facing authentication.\n\n\t- ### Industry Applications and Outcomes\n\n\t\t- **Pharmaceuticals**: Beyond MediLedger, Pfizer deploys blockchain across multiple initiatives including the Clinical Supply Blockchain Working Group's KitChain solution and participation in Europe's Innovative Medicines Initiative. Merck holds patents for blockchain-based counterfeit prevention whilst implementing SAP Pharma Blockchain POC for Gardasil vaccine tracing. Novartis combines blockchain with IoT sensors for counterfeit identification and temperature tracking compliance. BRUINchain (UCLA and LedgerDomain) provides FDA DSCSA compliance through Hyperledger-based 2D barcode scanning with expired product flagging and suspect product quarantine.\n\n\t\t- **Luxury Goods and Fashion**: Nike's CryptoKicks patent (December 2019) evolved into Web3 sneakers limited to **19,000 pairs** through RTFKT Studios acquisition, generating **~3,100 Ethereum (£8.72 million)** in trade volume plus **~2,500 Ethereum (£7.04 million)** from customisation Skin Vials. H&M Group's TextileGenesis platform traced **1.5 million garments** in 2021, targeting **200 million items (20% of material base)** by 2022 across man-made cellulose and recycled polyester fibres. COS subsidiary deployed VeChain's MyStory platform for **4,000+ sustainability products** with detailed supply chain data.\n\n\t\t- **Electronics and Semiconductors**: The **£75 billion** counterfeit chip market integrated into **£169 billion** of devices drives consortium responses including the Mobility Open Blockchain Initiative (auto and chipmakers) for automotive supply chain tracking. The CHIPS Act forces next-generation authentication development at scale, whilst NIST creates authentication protocols making counterfeit chip entry exponentially harder. Implementations combine blockchain-based certificate authorities tracking chip IDs, grades, and transaction times with manufacturing date specifications and test results.\n\n\t\t- **Food and Beverage**: Carrefour extends IBM Food Trust across **12,000 stores in 33 countries** for poultry, tomato, and honey tracking, planning expansion to all Carrefour brands through partnerships with Unilever and Nestlé. Penfolds' VeChain implementation addresses Chinese counterfeit alcohol markets where **30% of all alcohol and 70% of wine** are fake, following police seizures of **14,000-50,000 fake bottles** in single incidents. The NFC tag integration enables customer verification of tamper-proof product details.\n\n\t\t- **Tobacco Industry**: Philip Morris International's blockchain tax stamp tracking on cigarette boxes could save **up to £20 million** by reducing paperwork and fraud in an industry facing **£100 million annual** tax stamp fraud costs, with individual packet stamps worth **~£5.50** representing significant revenue protection opportunities.\n\n\t- ### Cost-Benefit Analysis\n\n\t\t- **Direct Cost Savings**: Major pharmaceutical companies report **£200 million annual** fraud loss reductions through blockchain authentication, with one company saving **£500,000 annually** in intellectual property enforcement costs. Supply chains implementing blockchain demonstrate **50% efficiency improvements** through faster transactions, reduced paperwork, and real-time tracking capabilities. Electronics companies deploying blockchain with IoT could reduce fraudulent sales by **60-80%**, whilst complaint rates decrease by **50%** in implementations.\n\n\t\t- **Return on Investment Indicators**: Companies investing strategically in blockchain report **25% average growth** in cost reduction and new revenue streams. The anti-counterfeiting packaging market's expansion from **£159.87 billion (2024)** to **£326.3 billion (2029)** signals strong ROI expectations, whilst authentication and brand protection markets grow from **£2.99 billion (2024)** to **£7.64 billion (2032)** at 12.8% compound annual growth rate.\n\n\t\t- **Implementation Costs and Barriers**: Lack of clear ROI remains the fundamental adoption barrier, with expensive hardware and software infrastructure requirements for information collection. Small and medium pharmaceutical enterprises face significant financial and operational burdens for DSCSA compliance, whilst fashion brands producing clothing cheaply and quickly find supplier onboarding costs prohibitive. Research indicates firms may occasionally prefer pricing mechanisms over blockchain even when adoption costs are extremely low, particularly when indirect sales through blockchain-enabled platforms reduce brand-name firm profits through double marginalisation effects.\n\n\t- ### Regulatory Frameworks\n\n\t\t- **European Union Falsified Medicines Directive (2011/62/EU)**: Adopted July 2011, the directive harmonises European measures fighting medicine falsifications through rigorous trade controls and patient protections, reducing counterfeits in legal EU supply chains to approximately **1%** whilst addressing **£10 billion annual** pharmaceutical losses.\n\n\t\t- **U.S. Drug Supply Chain Security Act (DSCSA)**: Final phase Serialised Item-Level Traceability began November 27, 2023, with full enforcement November 27, 2024. Requirements mandate chain-of-ownership data sharing to product origin, serialisation of all pharmaceuticals, interoperable systems between trading partners, and enhanced verification including wholesaler verification of returned prescriptions before resale. Blockchain, AI, and predictive analytics drive compliance technology adoption.\n\n\t\t- **CHIPS Act and Semiconductor Standards**: U.S. legislation forces next-generation anti-counterfeiting development at scale, with NIST creating authentication protocols exponentially increasing counterfeit chip entry difficulty through standardised verification frameworks applicable across the semiconductor industry.\n\n\t\t- **OECD and International Frameworks**: The Organisation for Economic Co-operation and Development provides recommendations on blockchain and distributed ledger technology policy responses, collaborating with EUIPO on joint reports addressing dangerous fakes posing health, safety, and environmental risks. The 2022 EUIPO-OECD report \"Dangerous Fakes\" specifically addresses counterfeit goods threatening consumer safety.\n\n\t- ### Industry Standards\n\n\t\t- **GS1 Standards**: The Global Trade Item Number (GTIN), Global Location Number (GLN), Serial Shipping Container Code (SSCC), and Electronic Product Code (EPC) provide standardised identification enabling blockchain network scaling. Electronic Product Code Information Services (EPCIS) and Core Business Vocabulary (CBV) ISO open standards structure data exchange, maintaining single shared versions of truth about supply chain events whilst increasing data integrity and trust. GS1 digital signatures combined with item and transaction serialisation create well-practised authentication methods across multiple verticals.\n\n\t\t- **ISO/IEC 20248**: Maintained by ISO/IEC Joint Technical Committee 1 and Standards Committee 31, this standard governs Automatic Identification and Data Capture (AIDC) technologies including barcode and RFID standards for manufacturing and logistics, with GS1 serving as active participant in standards development.\n\n\t\t- **Hyperledger and Ethereum Standards**: Hyperledger Fabric provides the most common enterprise blockchain platform under Linux Foundation governance, offering permissioned networks, enterprise scalability, and privacy controls for Walmart food tracking, BMW automotive parts, and pharmaceutical sector implementations. Ethereum's ERC standards support NFT-based authentication (Nike CryptoKicks) and smart contract automation for public verification and ownership transfer.\n\n\t- ### Challenges and Limitations\n\n\t\t- **Physical-Digital Gap Vulnerability**: The link between physical products and digital records remains the weakest authentication point, as counterfeiters could potentially copy serial numbers or tags. QR codes face easy copying vulnerabilities, whilst even sophisticated NFC tags may succumb to advanced attacks. The \"first-mile problem\" recognises that blockchain trustworthiness depends entirely on initial data entry accuracy—fraudulent data entered during manufacturing persists immutably throughout the supply chain.\n\n\t\t- **Lack of Clear ROI**: Many enterprises cannot demonstrate clear return on investment, making measurement difficult and creating long payback periods that may require years to materialise. Strategic business considerations reveal that double marginalisation through indirect blockchain platform sales can reduce brand-name firm profits, whilst lack of coordinated pricing may damage profitability regardless of technology capabilities.\n\n\t\t- **Scalability and Interoperability**: Large-scale supply chain networks strain blockchain processing capacity, with some systems unsuitable for high-volume operations. Platform fragmentation creates established data-sharing protocol gaps, whilst legacy system integration requires substantial time and expertise. Different blockchains cannot easily communicate, and the supply chain management ecosystem lacks standardised interoperability frameworks.\n\n\t\t- **Implementation Reality**: No major pharmaceutical companies have fully implemented blockchain programmes as of 2024, with many projects remaining in pilot stages. Fashion and apparel industry adoption pace remains fairly slow despite extensive discussion. Scaling from proof-of-concept to full production proves difficult, requiring network effects where value increases only when critical mass of participants join—demanding competitor collaboration and industry-wide standards agreement.\n\n\t- ### Future Developments\n\n\t\t- **AI and Blockchain Convergence**: iTRACE Technologies' 2024 major upgrade integrates artificial intelligence with blockchain connectivity, employing natural language processing to monitor online platforms and social media for suspicious listings whilst using image recognition for enhanced counterfeit detection accuracy. The transformative approach combines AI detection capabilities with blockchain verification permanence.\n\n\t\t- **Enhanced Physical Authentication**: Unclonable NFC chips advance beyond current AES 128 encryption to quantum-resistant cryptography, whilst chemical markers integrate with blockchain for multi-factor authentication. DNA tagging employs microscopic DNA markers linked to blockchain records, and nano-printing creates invisible authentication features verified via blockchain systems.\n\n\t\t- **Market Growth Projections**: Anti-counterfeiting tracing platforms grow from **£5 billion (2025)** at 15% compound annual growth rate through 2033, whilst authentication and brand protection markets expand from **£2.99 billion (2024)** to **£7.64 billion (2032)** at 12.8% CAGR. Consumer awareness increases, regulatory pressure intensifies, and technology advancement drives continuous improvements in blockchain, AI, RFID, and IoT efficacy and security.\n\n\t\t- **Ubiquitous Authentication Vision (2030+)**: Blockchain authentication becomes standard expectation for all consumer goods, with seamless interoperability across all supply chain systems through universal standards enabling worldwide product verification. AI-powered systems detect and block counterfeits in real-time, whilst some industries achieve near-complete counterfeit elimination through quantum-resistant blockchain systems protected against future quantum computing threats.\n\n\t- #\n\n## Current Landscape (2025)\n\n- Industry adoption and implementations\n  - Metaverse platforms continue to evolve with focus on interoperability and open standards\n  - Web3 integration accelerating with decentralised identity and asset ownership\n  - Enterprise adoption growing in virtual collaboration, training, and digital twins\n  - UK companies increasingly active in metaverse development and immersive technologies\n\n- Technical capabilities\n  - Real-time rendering at photorealistic quality levels\n  - Low-latency networking enabling seamless multi-user experiences\n  - AI-driven content generation and procedural world building\n  - Spatial audio and haptics enhancing immersion\n\n- UK and North England context\n  - Manchester: Digital Innovation Factory supports metaverse startups and research\n  - Leeds: Holovis leads in immersive experiences for entertainment and training\n  - Newcastle: University research in spatial computing and interactive systems\n  - Sheffield: Advanced manufacturing using digital twin technology\n\n- Standards and frameworks\n  - Metaverse Standards Forum driving interoperability protocols\n  - WebXR enabling browser-based immersive experiences\n  - glTF and USD for 3D asset interchange\n  - Open Metaverse Interoperability Group defining cross-platform standards\n\n## Metadata\n\n- **Last Updated**: 2025-11-16\n- **Review Status**: Automated remediation with 2025 context\n- **Verification**: Academic sources verified\n- **Regional Context**: UK/North England where applicable\n\n\n## References and Further Reading\n\t\t- [[BC-0426-hyperledger-fabric]] - Enterprise blockchain platform\n\t\t- [[BC-0432-consortium-blockchain]] - Multi-organisation implementations\n\t\t- [[BC-0441-provenance-tracking]] - Supply chain traceability\n\t\t- [[BC-0442-pharmaceutical-traceability]] - Medical supply chain tracking\n\t\t- [[BC-0444-luxury-goods-authentication]] - Luxury brand implementations\n\t\t- [[BC-0446-supply-chain-traceability]] - End-to-end tracking systems\n\t\t- [[BC-0476-aml-kyc-compliance]] - Regulatory compliance frameworks",
  "properties": {
    "id": "bc-0447-anti-counterfeiting-ontology",
    "collapsed": "true",
    "- ontology": "true",
    "- term-id": "BC-0447",
    "- preferred-term": "Anti Counterfeiting",
    "- source-domain": "blockchain",
    "- status": "complete",
    "- public-access": "true",
    "- authority-score": "0.88",
    "- definition": "Blockchain-based systems employing cryptographic verification, immutable ledgers, and physical-digital integration technologies (NFC tags, QR codes, RFID) to authenticate products, prevent counterfeiting, and establish verifiable supply chain provenance across pharmaceuticals, luxury goods, electronics, and consumer products.",
    "- maturity": "draft",
    "- owl:class": "bc:AntiCounterfeiting",
    "- owl:physicality": "ConceptualEntity",
    "- owl:role": "Concept",
    "- belongsToDomain": "[[BlockchainDomain]]"
  },
  "backlinks": [],
  "wiki_links": [
    "BC-0426-hyperledger-fabric",
    "BC-0432-consortium-blockchain",
    "BC-0446-supply-chain-traceability",
    "BC-0476-aml-kyc-compliance",
    "BC-0441-provenance-tracking",
    "BC-0442-pharmaceutical-traceability",
    "BC-0444-luxury-goods-authentication",
    "BlockchainDomain"
  ],
  "ontology": {
    "term_id": "BC-0447",
    "preferred_term": "Anti Counterfeiting",
    "definition": "Blockchain-based systems employing cryptographic verification, immutable ledgers, and physical-digital integration technologies (NFC tags, QR codes, RFID) to authenticate products, prevent counterfeiting, and establish verifiable supply chain provenance across pharmaceuticals, luxury goods, electronics, and consumer products.",
    "source_domain": "blockchain",
    "maturity_level": null,
    "authority_score": 0.88
  }
}