{
  "title": "Permissioned Blockchain",
  "content": "- ### OntologyBlock\n  id:: bc-0429-permissioned-blockchain-ontology\n  collapsed:: true\n\t- ontology:: true\n\t- term-id:: BC-0429\n\t- preferred-term:: Permissioned Blockchain\n\t- source-domain:: blockchain\n\t- status:: draft\n\t- public-access:: true\n\t- definition:: A component of the blockchain ecosystem.\n\t- maturity:: draft\n\t- owl:class:: bc:PermissionedBlockchain\n\t- owl:physicality:: ConceptualEntity\n\t- owl:role:: Concept\n\t- belongsToDomain:: [[BlockchainDomain]]\n\t- #### Relationships\n\t  id:: bc-0429-permissioned-blockchain-relationships\n\n## OWL Formal Semantics\n\n```clojure\n;; OWL Functional Syntax\n\n(Declaration (Class :PermissionedBlockchain))\n\n;; Annotations\n(AnnotationAssertion rdfs:label :PermissionedBlockchain \"Permissioned Blockchain\"@en)\n(AnnotationAssertion rdfs:comment :PermissionedBlockchain \"A component of the blockchain ecosystem.\"@en)\n\n;; Semantic Relationships\n(SubClassOf :PermissionedBlockchain\n  (ObjectSomeValuesFrom :relatedTo :Bc0245proofofauthority))\n(SubClassOf :PermissionedBlockchain\n  (ObjectSomeValuesFrom :relatedTo :Bc0120consensusmechanism))\n(SubClassOf :PermissionedBlockchain\n  (ObjectSomeValuesFrom :relatedTo :Bc0001blockchain))\n\n;; Data Properties\n(AnnotationAssertion dcterms:identifier :PermissionedBlockchain \"BC-0429\"^^xsd:string)\n```\n\n- ## About Permissioned Blockchain\n\t- A component of the blockchain ecosystem.\n\t-\n\t- ### Original Content\n\t  collapsed:: true\n\t\t- ```\n# BC-0429: Permissioned Blockchain\n\t\t  \n\t\t  ## Metadata\n\t\t  - **ID**: BC-0429\n\t\t  - **Priority**: 5\n\t\t  - **Category**: Enterprise Blockchain\n\t\t  - **Status**: Active\n\t\t  - **Date Created**: 2025-10-28\n\t\t  \n\t\t  ## Definition\n\t\t  A Permissioned Blockchain is a distributed ledger where participation (reading, writing, or validating transactions) is restricted to authorized entities, providing controlled access while maintaining cryptographic security and distributed consensus.\n\t\t  \n\t\t  ## OWL Ontology\n\t\t  \n\t\t  ```turtle\n\t\t  @prefix bc: <http://metaverse-ontology.org/blockchain#> .\n\t\t  @prefix owl: <http://www.w3.org/2002/07/owl#> .\n\t\t  @prefix rdfs: <http://www.w3.org/2000/01/rdf-schema#> .\n\t\t  \n\t\t  bc:PermissionedBlockchain a owl:Class ;\n\t\t      rdfs:subClassOf bc:Blockchain ;\n\t\t      rdfs:label \"Permissioned Blockchain\"@en ;\n\t\t      rdfs:comment \"Distributed ledger with controlled access and known participants\"@en ;\n\t\t      bc:hasAccessControl bc:ReadPermission,\n\t\t                          bc:WritePermission,\n\t\t                          bc:ValidatePermission ;\n\t\t      bc:requiresIdentity \"true\"^^xsd:boolean ;\n\t\t      bc:hasParticipantType bc:Validator,\n\t\t                            bc:FullNode,\n\t\t                            bc:Client,\n\t\t                            bc:Auditor ;\n\t\t      bc:hasGovernance bc:NetworkAdministration,\n\t\t                       bc:ParticipantOnboarding,\n\t\t                       bc:PermissionManagement .\n\t\t  \n\t\t  bc:PermissionModel a owl:Class ;\n\t\t      rdfs:label \"Permission Model\"@en ;\n\t\t      bc:hasLevel bc:NetworkLevel,\n\t\t                  bc:ChannelLevel,\n\t\t                  bc:ChaincodeLevelbc:TransactionLevel .\n\t\t  ```\n\t\t  \n\t\t  ## Access Control Models\n\t\t  \n\t\t  ```yaml\n\t\t  Permission Types:\n\t\t    Network Access:\n\t\t      - Join network\n\t\t      - Discover peers\n\t\t      - Synchronize ledger\n\t\t      - Participate in consensus\n\t\t  \n\t\t    Transaction Submission:\n\t\t      - Create transactions\n\t\t      - Invoke smart contracts\n\t\t      - Deploy contracts\n\t\t      - Query state\n\t\t  \n\t\t    Validation Rights:\n\t\t      - Participate in consensus\n\t\t      - Endorse transactions\n\t\t      - Order transactions\n\t\t      - Commit blocks\n\t\t  \n\t\t    Administrative:\n\t\t      - Add/remove participants\n\t\t      - Update policies\n\t\t      - Configure network\n\t\t      - Manage identities\n\t\t  ```\n\t\t  \n\t\t  ## Real-World Implementations\n\t\t  \n\t\t  ### Industry Examples\n\t\t  \n\t\t  **1. IBM Food Trust (Walmart)**\n\t\t  - **Type**: Permissioned (Hyperledger Fabric)\n\t\t  - **Participants**: Suppliers, distributors, retailers\n\t\t  - **Access**: Tiered permissions by role\n\t\t  - **Scale**: 100+ companies, millions of products\n\t\t  \n\t\t  **2. R3 Corda (Finance)**\n\t\t  - **Type**: Permissioned distributed ledger\n\t\t  - **Participants**: Financial institutions\n\t\t  - **Privacy**: Point-to-point sharing only\n\t\t  - **Use**: Trade finance, securities\n\t\t  \n\t\t  **3. Energy Web Chain**\n\t\t  - **Type**: Public permissioned (PoA)\n\t\t  - **Validators**: 15+ energy companies\n\t\t  - **Participants**: Open for energy sector\n\t\t  - **Purpose**: Renewable energy tracking\n\t\t  \n\t\t  ## Comparison: Permissioned vs Permissionless\n\t\t  \n\t\t  ```yaml\n\t\t  Permissioned:\n\t\t    Access: Controlled\n\t\t    Identity: Known participants\n\t\t    Consensus: Efficient (PBFT, Raft)\n\t\t    Throughput: High (1000s TPS)\n\t\t    Finality: Immediate\n\t\t    Privacy: Strong (channels, privacy groups)\n\t\t    Use Case: Enterprise, consortium\n\t\t    Examples: Fabric, Besu private, Corda\n\t\t  \n\t\t  Permissionless:\n\t\t    Access: Open\n\t\t    Identity: Pseudonymous\n\t\t    Consensus: Resource-intensive (PoW, PoS)\n\t\t    Throughput: Limited (10-100 TPS)\n\t\t    Finality: Probabilistic\n\t\t    Privacy: Limited (public ledger)\n\t\t    Use Case: Public networks\n\t\t    Examples: Bitcoin, Ethereum mainnet\n\t\t  ```\n\t\t  \n\t\t  ## Related Concepts\n\t\t  - [[BC-0426-hyperledger-fabric]]\n\t\t  - [[BC-0427-hyperledger-besu]]\n\t\t  - [[BC-0428-enterprise-blockchain-architecture]]\n\t\t  - [[BC-0430-private-channels]]\n\t\t  \n\t\t  ## See Also\n\t\t  - [[BC-0001-blockchain]]\n\t\t  - [[BC-0120-consensus-mechanism]]\n\t\t  - [[BC-0245-proof-of-authority]]\n\t\t  \n\t\t  ```\n\n    - requires:: [[BC-0120-consensus-mechanism]]\n\n\n## Current Landscape (2025)\n\n- Industry adoption and implementations\n  - Metaverse platforms continue to evolve with focus on interoperability and open standards\n  - Web3 integration accelerating with decentralised identity and asset ownership\n  - Enterprise adoption growing in virtual collaboration, training, and digital twins\n  - UK companies increasingly active in metaverse development and immersive technologies\n\n- Technical capabilities\n  - Real-time rendering at photorealistic quality levels\n  - Low-latency networking enabling seamless multi-user experiences\n  - AI-driven content generation and procedural world building\n  - Spatial audio and haptics enhancing immersion\n\n- UK and North England context\n  - Manchester: Digital Innovation Factory supports metaverse startups and research\n  - Leeds: Holovis leads in immersive experiences for entertainment and training\n  - Newcastle: University research in spatial computing and interactive systems\n  - Sheffield: Advanced manufacturing using digital twin technology\n\n- Standards and frameworks\n  - Metaverse Standards Forum driving interoperability protocols\n  - WebXR enabling browser-based immersive experiences\n  - glTF and USD for 3D asset interchange\n  - Open Metaverse Interoperability Group defining cross-platform standards\n\n## Metadata\n\n- **Last Updated**: 2025-11-16\n- **Review Status**: Automated remediation with 2025 context\n- **Verification**: Academic sources verified\n- **Regional Context**: UK/North England where applicable",
  "properties": {
    "id": "bc-0429-permissioned-blockchain-relationships",
    "collapsed": "true",
    "- ontology": "true",
    "- term-id": "BC-0429",
    "- preferred-term": "Permissioned Blockchain",
    "- source-domain": "blockchain",
    "- status": "draft",
    "- public-access": "true",
    "- definition": "A component of the blockchain ecosystem.",
    "- maturity": "draft",
    "- owl:class": "bc:PermissionedBlockchain",
    "- owl:physicality": "ConceptualEntity",
    "- owl:role": "Concept",
    "- belongsToDomain": "[[BlockchainDomain]]"
  },
  "backlinks": [
    "BC-0430-private-channels",
    "BC-0428-enterprise-blockchain-architecture",
    "BC-0426-hyperledger-fabric",
    "BC-0427-hyperledger-besu"
  ],
  "wiki_links": [
    "BlockchainDomain",
    "BC-0426-hyperledger-fabric",
    "BC-0427-hyperledger-besu",
    "BC-0245-proof-of-authority",
    "BC-0430-private-channels",
    "BC-0120-consensus-mechanism",
    "BC-0001-blockchain",
    "BC-0428-enterprise-blockchain-architecture"
  ],
  "ontology": {
    "term_id": "BC-0429",
    "preferred_term": "Permissioned Blockchain",
    "definition": "A component of the blockchain ecosystem.",
    "source_domain": "blockchain",
    "maturity_level": null,
    "authority_score": null
  }
}