{
  "title": "Archival Node",
  "content": "- ### OntologyBlock\n  id:: archival-node-ontology\n  collapsed:: true\n\n  - **Identification**\n    - public-access:: true\n    - ontology:: true\n    - term-id:: BC-0093\n    - preferred-term:: Archival Node\n    - source-domain:: blockchain\n    - status:: complete\n    - version:: 1.0.0\n    - last-updated:: 2025-10-28\n\n  - **Definition**\n    - definition:: Complete history storage node within blockchain systems, providing essential functionality for distributed ledger technology operations and properties.\n    - maturity:: mature\n    - source:: [[ISO/IEC 23257:2021]], [[IEEE 2418.1]], [[NIST NISTIR]]\n    - authority-score:: 0.95\n\n  - **Semantic Classification**\n    - owl:class:: bc:ArchivalNode\n    - owl:physicality:: VirtualEntity\n    - owl:role:: Object\n    - owl:inferred-class:: bc:VirtualObject\n    - belongsToDomain:: [[CryptographicDomain]]\n\n  - #### OWL Restrictions\n    \n    \n\n  - #### Relationships\n    id:: relationships\n    - is-subclass-of:: [[Node]]\n\n  - #### CrossDomainBridges\n    - bridges-to:: [[Networkcomponent]] via is-subclass-of\n\n  -",
  "properties": {
    "id": "relationships",
    "collapsed": "true",
    "- public-access": "true",
    "- ontology": "true",
    "- term-id": "BC-0093",
    "- preferred-term": "Archival Node",
    "- source-domain": "blockchain",
    "- status": "complete",
    "- version": "1.0.0",
    "- last-updated": "2025-10-28",
    "- definition": "Complete history storage node within blockchain systems, providing essential functionality for distributed ledger technology operations and properties.",
    "- maturity": "mature",
    "- source": "[[ISO/IEC 23257:2021]], [[IEEE 2418.1]], [[NIST NISTIR]]",
    "- authority-score": "0.95",
    "- owl:class": "bc:ArchivalNode",
    "- owl:physicality": "VirtualEntity",
    "- owl:role": "Object",
    "- owl:inferred-class": "bc:VirtualObject",
    "- belongsToDomain": "[[CryptographicDomain]]",
    "- is-subclass-of": "[[Node]]",
    "- bridges-to": "[[Networkcomponent]] via is-subclass-of"
  },
  "backlinks": [],
  "wiki_links": [
    "IEEE 2418.1",
    "ISO/IEC 23257:2021",
    "Networkcomponent",
    "CryptographicDomain",
    "NIST NISTIR",
    "Node"
  ],
  "ontology": {
    "term_id": "BC-0093",
    "preferred_term": "Archival Node",
    "definition": "Complete history storage node within blockchain systems, providing essential functionality for distributed ledger technology operations and properties.",
    "source_domain": "blockchain",
    "maturity_level": null,
    "authority_score": 0.95
  }
}