{
  "title": "Privacy Preserving Blockchain",
  "content": "- ### OntologyBlock\n  id:: bc-0431-privacy-preserving-blockchain-ontology\n  collapsed:: true\n\t- ontology:: true\n\t- term-id:: BC-0431\n\t- preferred-term:: Privacy Preserving Blockchain\n\t- source-domain:: blockchain\n\t- status:: stub-needs-content\n\t- public-access:: true\n\t- content-status:: minimal-placeholder-requires-authoring\n\t- public-access:: true\n\t- definition:: A component of the blockchain ecosystem.\n\t- maturity:: draft\n\t- owl:class:: bc:PrivacyPreservingBlockchain\n\t- owl:physicality:: ConceptualEntity\n\t- owl:role:: Concept\n\t- belongsToDomain:: [[BlockchainDomain]]\n\n## OWL Formal Semantics\n\n```clojure\n;; OWL Functional Syntax\n\n(Declaration (Class :PrivacyPreservingBlockchain))\n\n;; Annotations\n(AnnotationAssertion rdfs:label :PrivacyPreservingBlockchain \"Privacy Preserving Blockchain\"@en)\n(AnnotationAssertion rdfs:comment :PrivacyPreservingBlockchain \"A component of the blockchain ecosystem.\"@en)\n\n;; Data Properties\n(AnnotationAssertion dcterms:identifier :PrivacyPreservingBlockchain \"BC-0431\"^^xsd:string)\n```\n\n- ## About Privacy Preserving Blockchain\n  id:: privacy-preserving-blockchain-about\n\n  - Privacy-preserving blockchain represents a fundamental advancement in distributed ledger technology that addresses the inherent transparency challenges of traditional blockchain systems. Whilst conventional blockchains provide immutability and decentralisation through their open, public ledgers, this transparency can compromise sensitive information in enterprise, healthcare, and financial applications. Privacy-preserving blockchain technologies employ sophisticated cryptographic techniques to enable confidential transactions whilst maintaining the core benefits of blockchain: verifiability, immutability, and decentralisation. These systems utilise [[Zero-Knowledge Proofs]], [[Ring Signatures]], [[Stealth Addresses]], and [[Homomorphic Encryption]] to obscure transaction details including sender and receiver identities, transaction amounts, and smart contract states, whilst still allowing network participants to verify the validity of transactions. This capability is essential for regulatory compliance in sectors such as healthcare, where [[GDPR]] and [[HIPAA]] mandate data privacy, and in finance, where [[Anti-Money Laundering]] requirements must be balanced against commercial confidentiality.\n\n  - ### Technical Architecture\n    - Privacy-preserving blockchain architectures employ multiple layers of cryptographic protection to achieve confidentiality whilst maintaining verifiability. At the protocol level, these systems implement specialised consensus mechanisms that validate transactions without exposing their contents, utilising [[Zero-Knowledge Succinct Non-Interactive Arguments of Knowledge]] (zk-SNARKs) or [[Zero-Knowledge Scalable Transparent Arguments of Knowledge]] (zk-STARKs) to generate cryptographic proofs that transactions are valid without revealing transaction data. The architecture typically separates the public verification layer from the private transaction layer, enabling network nodes to confirm transaction validity through mathematical proofs whilst transaction details remain encrypted.\n    - Key components:\n      - [[Zero-Knowledge Proof Systems]] - Cryptographic protocols enabling one party to prove knowledge of specific information without revealing the information itself, including zk-SNARKs used in [[Zcash]] and zk-STARKs providing quantum-resistant properties\n      - [[Confidential Transactions]] - Cryptographic commitments that hide transaction amounts whilst enabling verification that inputs equal outputs, implemented through [[Pedersen Commitments]] and [[Range Proofs]]\n      - [[Ring Signatures]] and [[Stealth Addresses]] - Technologies employed by [[Monero]] that obscure sender identity through mixing with decoy signatures and create one-time recipient addresses to protect receiver privacy\n      - [[Homomorphic Encryption]] - Advanced encryption allowing computations on encrypted data without decryption, enabling [[Smart Contracts]] to execute on private data\n      - [[Secure Multi-Party Computation]] - Protocols enabling multiple parties to jointly compute functions over their inputs whilst keeping those inputs private, crucial for collaborative enterprise applications\n      - [[Attribute-Based Encryption]] - Fine-grained access control mechanisms that encrypt data based on attributes, enabling selective disclosure for regulatory compliance\n\n  - ### Key Features and Capabilities\n    - **Selective Disclosure**: Privacy-preserving blockchains enable granular control over information sharing, allowing entities to prove specific claims about data without revealing the underlying data itself. [[Zcash]] pioneered selective transparency, enabling users to choose between shielded (private) and transparent transactions, with the shielded pool now holding approximately 25-30% of circulating supply. This capability is essential for enterprise applications where different stakeholders require different levels of information access.\n    - **Regulatory Compliance with Privacy**: Advanced privacy-preserving schemes implement multi-level regulation through the utilisation of zero-knowledge proofs and [[Attribute-Based Encryption]], enabling blockchain systems to maintain privacy whilst satisfying regulatory requirements such as [[Know Your Customer]] (KYC) and [[Anti-Money Laundering]] (AML) obligations. These systems allow authorised regulators to audit transactions under specific conditions without compromising general user privacy.\n    - **Scalability through Privacy**: [[zk-Rollups]] represent a significant advancement in [[Layer 2]] scaling solutions, bundling multiple transactions into a single proof submitted to the main chain. This approach reduces congestion and enhances throughput, with platforms like [[zkSync]] and [[StarkNet]] processing thousands of transactions per second whilst maintaining privacy and security guarantees. The efficiency gains come from both the compression of transaction data and the reduction in on-chain computation required for verification.\n    - **Cross-Chain Privacy**: Emerging protocols enable privacy-preserving transactions across different blockchain networks, with platforms like [[Oasis Network]] and [[Secret Network]] providing bridges between distinct blockchains including [[Ethereum]], [[Binance Smart Chain]], and privacy-focused chains. This interoperability is crucial for enterprise adoption where organisations need to interact with multiple blockchain ecosystems.\n\n  - ### Industry Applications\n    - **Healthcare Data Management**: Privacy-preserving blockchain enables secure sharing of electronic health records whilst maintaining [[HIPAA]] compliance and patient confidentiality. Patients control their data through self-sovereign identity systems, granting healthcare providers temporary access to specific medical information using verifiable credentials and zero-knowledge proofs. [[NuCypher]] Key Management System facilitates patient-controlled electronic health records, enabling healthcare stakeholders to collaborate on treatment whilst preserving data confidentiality through proxy re-encryption.\n      - Implementation details: Healthcare consortia deploy permissioned privacy-preserving blockchains where patient records are encrypted with patient-controlled keys, and [[Multi-Party Computation]] enables medical research on aggregated data without exposing individual patient information\n      - Benefits achieved: Reduced data breaches, improved interoperability between healthcare providers, enabling precision medicine research whilst protecting patient privacy, and empowering patients with data ownership\n      - [[Hyperledger Fabric]] with [[Private Data Collections]], [[Zero-Knowledge Proof]] protocols, [[Verifiable Credentials]]\n    - **Financial Services and Confidential Transactions**: Financial institutions utilise privacy-preserving blockchain for confidential settlements, protecting commercially sensitive information about transaction volumes, trading strategies, and client relationships. [[Monero]] employs ring signatures, stealth addresses, and confidential transactions to make tracing nearly impossible, making it widely adopted for private transactions, though this has led to delisting from several major exchanges due to regulatory pressure.\n      - Implementation details: Banks use [[Confidential Assets]] protocols based on [[Elements Project]] technology, implementing [[Pedersen Commitments]] to hide transaction amounts whilst proving inputs equal outputs, and utilising [[Bulletproofs]] for efficient range proofs that prevent negative value exploits\n      - Benefits achieved: Protection of trading strategies, maintenance of commercial confidentiality in supply chain finance, compliance with data protection regulations whilst enabling audit trails for regulators\n      - [[R3 Corda]], [[JP Morgan Quorum]], [[Enterprise Ethereum Alliance]] privacy standards\n    - **Supply Chain with Commercial Privacy**: Enterprises require privacy in supply chains to protect pricing information, supplier relationships, and inventory levels whilst maintaining transparency for specific authorised parties. Privacy-preserving smart contracts enable multiple organisations to execute complex business logic on shared data without revealing proprietary information to competitors.\n      - Implementation details: [[Hyperledger Fabric]] channels with [[Private Data Collections]] enable consortium members to selectively share information, with zero-knowledge proofs validating compliance with agreements without exposing commercial terms\n      - Benefits achieved: Protection of competitive pricing strategies, secure collaboration between competitors in consortium networks, compliance with antitrust regulations by preventing information leakage\n      - [[Baseline Protocol]] on [[Ethereum]], [[Hyperledger Besu]] with privacy groups\n\n  - ### Standards and Governance\n    - **Standards**: The privacy-preserving blockchain ecosystem lacks comprehensive standardisation, though several initiatives are progressing. [[IEEE P2418.1]] addresses blockchain terminology and interoperability, whilst the [[Decentralized Identity Foundation]] develops standards for privacy-preserving identity systems. The [[Enterprise Ethereum Alliance]] has published specifications for enterprise privacy including the [[EEA Privacy and Confidentiality Specification]]. Academic institutions and standards bodies are working on formal specifications for zero-knowledge proof systems to enable interoperability.\n    - **Governance models**: Privacy-preserving blockchain governance varies significantly between public privacy coins and enterprise implementations. [[Zcash]] governance involves the Electric Coin Company, Zcash Foundation, and community members through the [[Zcash Improvement Proposal]] (ZIP) process. Enterprise privacy solutions like [[Hyperledger Fabric]] follow the [[Hyperledger]] governance model under the [[Linux Foundation]], with technical steering committees and working groups. Privacy-focused [[Decentralized Autonomous Organizations]] are emerging to govern protocol upgrades and treasury management.\n    - **Compliance**: Regulatory frameworks present significant challenges for privacy-preserving blockchain adoption. The [[European Union]]'s [[Markets in Crypto-Assets Regulation]] (MiCA) and the [[Financial Action Task Force]] (FATF) Travel Rule require identity disclosure for transactions above certain thresholds, necessitating hybrid approaches that preserve privacy whilst enabling regulatory compliance. Solutions include zero-knowledge proof-based compliance systems where authorised regulators can audit transactions without general public visibility, and selective disclosure mechanisms enabling entities to prove regulatory compliance without revealing all transaction details.\n\n  - ### Comparison with Alternatives\n    - Compared to [[Public Transparent Blockchain]]: Privacy-preserving blockchains sacrifice some auditability and transparency for confidentiality, with additional computational overhead for zero-knowledge proof generation and verification. Transparent blockchains like [[Bitcoin]] enable anyone to analyse transaction flows and network activity, which is unacceptable for enterprise applications but beneficial for public accountability. Privacy-preserving systems require more sophisticated cryptographic implementations, increasing development complexity and audit requirements.\n    - Compared to [[Permissioned Blockchain Without Privacy]]: Permissioned blockchains like basic [[Hyperledger Fabric]] deployments control access through identity management but don't inherently hide transaction data from network participants. Privacy-preserving blockchains add cryptographic confidentiality even amongst authorised participants, enabling competitors to collaborate in consortium networks without revealing proprietary information. The tradeoff involves increased computational costs and reduced transparency for consortium governance.\n    - When to use privacy-preserving blockchain: Choose privacy-preserving blockchain when handling personally identifiable information subject to [[GDPR]] or [[CCPA]], when commercial confidentiality is paramount in multi-party business networks, when regulatory compliance requires both transparency to authorities and confidentiality from the public, or when cross-organisational collaboration involves competitors who must protect proprietary information. Traditional transparent blockchains suffice for applications requiring public auditability, such as charity fund tracking or government procurement transparency.\n\n  - ### Implementation Considerations\n    - **Technical requirements**: Implementing privacy-preserving blockchain requires specialised cryptographic expertise, particularly in zero-knowledge proof system design and security analysis. Infrastructure demands are substantial, with zk-SNARK proof generation requiring significant computational resources, though verification remains efficient. Development teams need proficiency in specialised frameworks such as [[Circom]] for zk-SNARK circuits, [[Cairo]] for [[StarkNet]] development, or [[Noir]] for [[Aztec Protocol]]. Hardware security modules may be required for key ceremony processes in trusted setup procedures for zk-SNARKs.\n    - **Organisational readiness**: Organisations must establish clear data governance policies defining what information requires privacy protection and what must remain transparent for regulatory compliance. Legal teams need to understand the implications of cryptographic privacy for compliance obligations, whilst business stakeholders must accept the increased complexity and costs associated with privacy-preserving systems. Training programmes should cover privacy-preserving concepts, cryptographic assumptions, and operational procedures for key management and emergency recovery.\n    - **Cost considerations**: Privacy-preserving blockchain implementations incur higher costs than traditional distributed ledger systems. Initial development costs include specialised cryptographic expertise, security audits from firms experienced in zero-knowledge proof systems, and integration with existing identity and access management systems. Operational costs include increased computational resources for proof generation, ongoing security monitoring, and potential licensing fees for commercial privacy-preserving protocols. [[Zcash]] shielded transactions consume more computational resources than transparent transactions, whilst enterprise implementations require dedicated hardware for cryptographic operations.\n    - **Timeline**: Privacy-preserving blockchain projects typically require 12-24 months from conception to production deployment. The timeline includes 3-6 months for requirements analysis and privacy model design, 6-12 months for development and cryptographic implementation, 3-6 months for security auditing and penetration testing, and 3-6 months for pilot deployment and stakeholder onboarding. Proof-of-concept implementations can be demonstrated in 3-6 months using existing platforms like [[Zcash]], [[Monero]], or [[Hyperledger Fabric]] with privacy extensions.\n\n  - ### Major Implementations\n    - **Zcash**: The pioneering privacy-preserving cryptocurrency utilising zk-SNARKs to enable selective transparency, Zcash has surged over 700% since late 2024, overtaking [[Monero]] to become the top privacy coin by market capitalisation. The shielded pool's growth to 25-30% of circulating supply demonstrates increasing adoption of privacy features. Zcash's [[Halo 2]] upgrade eliminated the trusted setup requirement, addressing a significant security concern. The [[Electric Coin Company]] continues development with focus on scalability through recursive proof composition and improved user experience for shielded transactions.\n    - **Monero**: Built for complete anonymity, Monero employs ring signatures, stealth addresses, and confidential transactions making transaction tracing nearly impossible. Despite delisting from several major exchanges due to regulatory pressure, Monero remains a leader in privacy technology with robust features proven through years of real-world usage. The [[RandomX]] proof-of-work algorithm ensures ASIC resistance and decentralised mining. Recent developments include [[Triptych]] and [[Seraphis]] protocols promising improved privacy guarantees and performance.\n    - **Enterprise Ethereum Alliance Privacy Implementations**: Major financial institutions have implemented privacy-preserving smart contracts using [[Baseline Protocol]], which combines zero-knowledge proofs with [[IPFS]] and [[Ethereum]] to enable confidential business processes. [[EY OpsChain]] utilises zero-knowledge proofs for private transactions on [[Ethereum]], enabling enterprises to benefit from public blockchain security whilst maintaining transaction confidentiality. [[ConsenSys Quorum]] (formerly JP Morgan Quorum) implements privacy through private transaction managers and secure enclaves, with organisations like [[ING Bank]] and [[Societe Generale]] using it for confidential settlements.\n\n  - ### Challenges and Limitations\n    - Technical challenges include the computational intensity of zero-knowledge proof generation, with zk-SNARK proof creation requiring seconds to minutes for complex transactions, limiting throughput. [[Trusted Setup Ceremonies]] required for many zk-SNARK implementations create potential security vulnerabilities if participants collude, though newer systems like [[zk-STARKs]] and [[Halo]] eliminate this requirement. Quantum computing poses long-term threats to current cryptographic assumptions underlying privacy-preserving systems, necessitating research into post-quantum privacy protocols.\n    - Organisational challenges centre on the tension between privacy and regulatory compliance, with financial regulators increasingly demanding transaction transparency to combat money laundering and terrorist financing. The [[Financial Action Task Force]] Travel Rule requires virtual asset service providers to share originator and beneficiary information for transactions above thresholds, conflicting with privacy coin designs. Organisations must navigate complex legal landscapes where privacy-preserving technologies may be prohibited or restricted in certain jurisdictions.\n    - Scalability considerations remain significant, with privacy-preserving operations generally requiring more computational resources than transparent alternatives. [[zk-Rollups]] improve throughput but add latency from proof generation time. Network participants may require more powerful hardware to generate proofs, potentially centralising block production. State growth in privacy-preserving systems can exceed transparent blockchains due to accumulation of cryptographic commitments and proofs.\n    - Security concerns include implementation vulnerabilities in complex cryptographic code, with historical bugs in zero-knowledge proof implementations leading to potential counterfeiting attacks. The opacity of private transactions complicates detection of network anomalies or attacks. Privacy-preserving smart contracts face additional security challenges as traditional audit and testing tools cannot inspect private state, requiring specialised verification techniques and formal methods.\n\n  - ### Future Directions\n    - Emerging trends include the convergence of privacy-preserving blockchain with [[Artificial Intelligence]] and [[Federated Learning]], enabling collaborative machine learning on private blockchain data without exposing training datasets. [[Zero-Knowledge Machine Learning]] proofs allow verification of AI model inference without revealing model weights or input data, opening applications in healthcare diagnostics and financial fraud detection whilst preserving confidentiality.\n    - Planned improvements focus on performance optimisation, with research into [[Recursive SNARKs]] enabling unlimited proof composition for complex applications. [[Proof aggregation]] techniques allow batching multiple proofs into a single compact proof, dramatically improving verification efficiency for rollup systems. [[Hardware acceleration]] through [[Field-Programmable Gate Arrays]] (FPGAs) and [[Application-Specific Integrated Circuits]] (ASICs) promises orders of magnitude improvement in proof generation speed.\n    - Research areas include post-quantum privacy-preserving protocols resistant to attacks from quantum computers, with [[Lattice-Based Cryptography]] and [[Hash-Based Signatures]] as promising foundations. [[Fully Homomorphic Encryption]] practical implementations would enable arbitrary computation on encrypted blockchain data. [[Private Smart Contract]] platforms like [[Secret Network]] and [[Oasis Network]] are advancing capabilities for confidential computation over sensitive data. Integration of privacy-preserving blockchain with [[Decentralized Identity]] and [[Verifiable Credentials]] through standards like [[W3C DID]] and [[Verifiable Credentials]] enables privacy-preserving authentication and authorisation.\n\n  - #\n\n## Current Landscape (2025)\n\n- Industry adoption and implementations\n  - Metaverse platforms continue to evolve with focus on interoperability and open standards\n  - Web3 integration accelerating with decentralised identity and asset ownership\n  - Enterprise adoption growing in virtual collaboration, training, and digital twins\n  - UK companies increasingly active in metaverse development and immersive technologies\n\n- Technical capabilities\n  - Real-time rendering at photorealistic quality levels\n  - Low-latency networking enabling seamless multi-user experiences\n  - AI-driven content generation and procedural world building\n  - Spatial audio and haptics enhancing immersion\n\n- UK and North England context\n  - Manchester: Digital Innovation Factory supports metaverse startups and research\n  - Leeds: Holovis leads in immersive experiences for entertainment and training\n  - Newcastle: University research in spatial computing and interactive systems\n  - Sheffield: Advanced manufacturing using digital twin technology\n\n- Standards and frameworks\n  - Metaverse Standards Forum driving interoperability protocols\n  - WebXR enabling browser-based immersive experiences\n  - glTF and USD for 3D asset interchange\n  - Open Metaverse Interoperability Group defining cross-platform standards\n\n## Metadata\n\n- **Last Updated**: 2025-11-16\n- **Review Status**: Automated remediation with 2025 context\n- **Verification**: Academic sources verified\n- **Regional Context**: UK/North England where applicable\n\n\n## References and Further Reading\n    - [[Zcash Protocol Specification]] - Technical documentation of zk-SNARK implementation in cryptocurrency\n    - [[Why and How zk-SNARK Works]] by Maksym Petkus - Comprehensive mathematical explanation of zero-knowledge proofs\n    - [[SoK: Privacy-Preserving Transactions in Blockchains]] - Academic systematisation of knowledge on blockchain privacy techniques\n    - [[Hyperledger Fabric Private Data]] - Enterprise permissioned blockchain privacy implementation guide\n    - [[A Survey on the Applications of Zero-Knowledge Proofs]] - Comprehensive overview of ZKP applications beyond cryptocurrency\n    - [[NIST Post-Quantum Cryptography Standardization]] - Future-proofing privacy-preserving systems against quantum threats\n    - [[Enterprise Ethereum Alliance Privacy and Confidentiality Specification]] - Industry standards for enterprise blockchain privacy\n    - [[Financial Action Task Force Guidance on Virtual Assets]] - Regulatory framework affecting privacy-preserving blockchain compliance",
  "properties": {
    "id": "bc-0431-privacy-preserving-blockchain-ontology",
    "collapsed": "true",
    "- ontology": "true",
    "- term-id": "BC-0431",
    "- preferred-term": "Privacy Preserving Blockchain",
    "- source-domain": "blockchain",
    "- status": "stub-needs-content",
    "- public-access": "true",
    "- content-status": "minimal-placeholder-requires-authoring",
    "- definition": "A component of the blockchain ecosystem.",
    "- maturity": "draft",
    "- owl:class": "bc:PrivacyPreservingBlockchain",
    "- owl:physicality": "ConceptualEntity",
    "- owl:role": "Concept",
    "- belongsToDomain": "[[BlockchainDomain]]"
  },
  "backlinks": [],
  "wiki_links": [
    "Aztec Protocol",
    "RandomX",
    "Range Proofs",
    "Cairo",
    "zk-STARKs",
    "ConsenSys Quorum",
    "Secure Multi-Party Computation",
    "Bulletproofs",
    "Elements Project",
    "Monero",
    "Financial Action Task Force Guidance on Virtual Assets",
    "zkSync",
    "Federated Learning",
    "Hash-Based Signatures",
    "Ethereum",
    "Field-Programmable Gate Arrays",
    "Triptych",
    "R3 Corda",
    "Zero-Knowledge Proof Systems",
    "Fully Homomorphic Encryption",
    "European Union",
    "Enterprise Ethereum Alliance Privacy and Confidentiality Specification",
    "IPFS",
    "Baseline Protocol",
    "Lattice-Based Cryptography",
    "Halo 2",
    "Pedersen Commitments",
    "Societe Generale",
    "StarkNet",
    "HIPAA",
    "Hyperledger",
    "Private Smart Contract",
    "Hyperledger Fabric",
    "Hardware acceleration",
    "EEA Privacy and Confidentiality Specification",
    "Proof aggregation",
    "GDPR",
    "Zero-Knowledge Proofs",
    "Zero-Knowledge Succinct Non-Interactive Arguments of Knowledge",
    "Decentralized Autonomous Organizations",
    "Homomorphic Encryption",
    "Zcash Protocol Specification",
    "Confidential Transactions",
    "Linux Foundation",
    "Trusted Setup Ceremonies",
    "EY OpsChain",
    "Zcash",
    "Layer 2",
    "Confidential Assets",
    "Noir",
    "Private Data Collections",
    "Seraphis",
    "JP Morgan Quorum",
    "CCPA",
    "A Survey on the Applications of Zero-Knowledge Proofs",
    "Oasis Network",
    "Stealth Addresses",
    "Smart Contracts",
    "Bitcoin",
    "BlockchainDomain",
    "Why and How zk-SNARK Works",
    "W3C DID",
    "Public Transparent Blockchain",
    "NIST Post-Quantum Cryptography Standardization",
    "Zcash Improvement Proposal",
    "SoK: Privacy-Preserving Transactions in Blockchains",
    "ING Bank",
    "Financial Action Task Force",
    "Decentralized Identity",
    "Application-Specific Integrated Circuits",
    "Halo",
    "Ring Signatures",
    "Attribute-Based Encryption",
    "Circom",
    "Zero-Knowledge Proof",
    "Zero-Knowledge Scalable Transparent Arguments of Knowledge",
    "Decentralized Identity Foundation",
    "Hyperledger Fabric Private Data",
    "Markets in Crypto-Assets Regulation",
    "Verifiable Credentials",
    "Zero-Knowledge Machine Learning",
    "Artificial Intelligence",
    "Anti-Money Laundering",
    "Permissioned Blockchain Without Privacy",
    "Electric Coin Company",
    "Hyperledger Besu",
    "zk-Rollups",
    "Recursive SNARKs",
    "Know Your Customer",
    "NuCypher",
    "Binance Smart Chain",
    "Secret Network",
    "IEEE P2418.1",
    "Enterprise Ethereum Alliance",
    "Multi-Party Computation"
  ],
  "ontology": {
    "term_id": "BC-0431",
    "preferred_term": "Privacy Preserving Blockchain",
    "definition": "A component of the blockchain ecosystem.",
    "source_domain": "blockchain",
    "maturity_level": null,
    "authority_score": null
  }
}