{
  "title": "DAO Legal Structures",
  "content": "- ### OntologyBlock\n  id:: bc-0470-dao-legal-structures-ontology\n  collapsed:: true\n\t- ontology:: true\n\t- term-id:: BC-0470\n\t- preferred-term:: DAO Legal Structures\n\t- source-domain:: blockchain\n\t- status:: stub-needs-content\n\t- public-access:: true\n\t- content-status:: minimal-placeholder-requires-authoring\n\t- public-access:: true\n\t- definition:: A component of the blockchain ecosystem.\n\t- maturity:: draft\n\t- owl:class:: bc:DAOLegalStructures\n\t- owl:physicality:: ConceptualEntity\n\t- owl:role:: Concept\n\t- belongsToDomain:: [[BlockchainDomain]]\n\n## OWL Formal Semantics\n\n```clojure\n;; OWL Functional Syntax\n\n(Declaration (Class :DAOLegalStructures))\n\n;; Annotations\n(AnnotationAssertion rdfs:label :DAOLegalStructures \"DAO Legal Structures\"@en)\n(AnnotationAssertion rdfs:comment :DAOLegalStructures \"A component of the blockchain ecosystem.\"@en)\n\n;; Data Properties\n(AnnotationAssertion dcterms:identifier :DAOLegalStructures \"BC-0470\"^^xsd:string)\n```\n\n- ## About DAO Legal Structures\n  id:: dao-legal-structures-about\n\t-\n\t- The legal status of [[BC-0461-decentralized-autonomous-organization]] entities represents one of the most consequential governance challenges in the blockchain ecosystem. By default, DAOs operating without legal incorporation exist in a regulatory grey zone—they lack legal personality to own property, sign contracts, or shield members from liability, whilst potentially creating unintended general partnerships where every token holder faces joint and several liability for the organisation's debts and legal violations. This untenable situation has driven the emergence of specialised DAO legal structures across multiple jurisdictions, each offering different trade-offs between regulatory clarity, liability protection, tax treatment, and operational flexibility. Wyoming's groundbreaking Decentralised Autonomous Organisation LLC statute (2021) established the first US framework explicitly recognising DAOs as limited liability companies, providing legal personality whilst accommodating algorithmic governance. Vermont's Blockchain-Based Limited Liability Company (BBLLC, 2018) pioneered earlier but more general blockchain-friendly corporate law. Offshore jurisdictions—the Marshall Islands DAO LLC (2022), Cayman Islands Foundation Company, and Swiss Associations—offer international alternatives with varying degrees of regulatory oversight and anonymity.\n\t-\n\t- These legal wrappers serve critical functions: they create liability shields protecting token holders from personal exposure to DAO liabilities, establish legal capacity to own assets and enter contracts (enabling DAO treasuries to hold bank accounts, real estate, intellectual property), provide tax classification (avoiding uncertain \"general partnership\" treatment), and create jurisdictional anchor points for regulatory compliance. However, each structure imposes costs and constraints. Wyoming DAO LLCs require registered agents, annual filings, and publicly disclosed members (or algorithmic management declarations). Cayman Foundations demand substantial setup costs ($50,000-$100,000+) and ongoing compliance. Swiss Associations require Swiss resident board members and detailed articles of association. The choice of structure profoundly affects governance: some jurisdictions mandate fiduciary duties for directors/managers, creating legal obligations that may conflict with token voting outcomes. Tax treatment varies dramatically—Wyoming LLCs default to partnership taxation (pass-through to members), Cayman entities pay zero income tax but may trigger controlled foreign corporation rules for US members, Swiss associations are taxed as non-profits if structured correctly. Real-world adoption shows clear patterns: investor-focused DAOs (The LAO, Flamingo DAO) favour Delaware/Wyoming LLCs for US securities law familiarity; protocol DAOs with global communities prefer Cayman Foundations for tax efficiency; small communities use Swiss Associations for simplicity. The legal landscape continues evolving rapidly, with Utah, Tennessee, and other US states passing DAO statutes whilst the European Union's MiCA regulation creates continent-wide frameworks affecting DAO operations.\n\t-\n\t- ### Legal Frameworks by Jurisdiction\n\t  collapsed:: true\n\t\t- **Wyoming DAO LLC (United States)**:\n\t\t- Wyoming's SF0038, effective July 2021, amended the state's LLC statute to explicitly recognise DAOs as a new LLC category. Key provisions:\n\t\t- - **Legal personality**: DAO LLCs are distinct legal entities capable of owning property, entering contracts, and suing/being sued\n\t\t- - **Formation requirements**: Articles of Organisation must state entity is a DAO LLC, include registered agent address, and declare whether management is member-managed, algorithmically managed, or manager-managed\n\t\t- - **Algorithmic management**: DAOs may be \"algorithmically managed\" via smart contracts, removing requirement for human managers. The smart contract addresses must be disclosed in formation documents\n\t\t- - **Member rights**: Token holders are \"members\" with voting rights proportional to their holdings (unless articles specify otherwise). Members are shielded from personal liability for DAO obligations except for their own wrongful acts\n\t\t- - **Fiduciary duties**: If manager-managed, managers owe fiduciary duties of care and loyalty to the DAO. Algorithmically managed DAOs have no fiduciary duties (the code governs), but this creates uncertainty if bugs or exploits occur\n\t\t- - **Public disclosure**: Articles of Organisation are public record, including member names (unless algorithmically managed with only smart contract addresses listed)\n\t\t- - **Annual reporting**: $60 annual report fee, must maintain registered agent ($50-$200/year)\n\t\t- - **Tax treatment**: Defaults to partnership taxation (pass-through to members) unless S-corp or C-corp election made\n\t\t-\n\t\t- Advantages: US jurisdiction provides legal certainty for US-based members, established court system for dispute resolution, relatively low setup costs ($100 filing + registered agent). Disadvantages: Public disclosure requirements, pass-through taxation may create individual tax complexity, Wyoming courts have little DAO case law creating precedent uncertainty.\n\t\t-\n\t\t- **Vermont Blockchain-Based LLC (United States)**:\n\t\t- Vermont's Title 11, Chapter 25, Section 4173-4177 (effective 2018) allows LLCs to use blockchain for record-keeping and governance:\n\t\t- - **Blockchain governance**: LLCs may use distributed ledger technology for voting, record-keeping, and member management\n\t\t- - **Operating agreement supremacy**: Operating agreement may specify governance entirely via blockchain, overriding default LLC rules\n\t\t- - **Legal personality**: Full LLC limited liability protections apply\n\t\t- - **Flexibility**: More general than Wyoming statute—not DAO-specific, but accommodates blockchain-based governance within standard LLC framework\n\t\t-\n\t\t- Adoption has been limited compared to Wyoming—most DAOs seeking US incorporation now prefer Wyoming's explicit DAO recognition. Vermont BBLLCs typically cost $125 to form with similar ongoing compliance as Wyoming.\n\t\t-\n\t\t- **Marshall Islands DAO LLC (International)**:\n\t\t- The Marshall Islands amended its Non-Profit Entities Act in 2022 to create Decentralised Autonomous Organisations as recognised entities:\n\t\t- - **International jurisdiction**: Marshall Islands is a sovereign nation, making this a non-US option for global DAOs\n\t\t- - **Limited liability**: Members enjoy liability protection similar to US LLCs\n\t\t- - **Flexible governance**: Statute explicitly allows algorithmic governance and smart contract-based decision-making\n\t\t- - **Registration requirements**: Must appoint registered agent in Marshall Islands, file annual reports\n\t\t- - **Non-profit focus**: Designed primarily for non-profit DAOs (unclear if for-profit DAOs can use structure)\n\t\t- - **Tax treatment**: Marshall Islands has no income tax, but members may owe tax in their home jurisdictions\n\t\t-\n\t\t- Adoption remains limited—setup costs are higher than Wyoming ($2,000-$5,000+), and fewer DAOs have international tax planning needs justifying offshore incorporation.\n\t\t-\n\t\t- **Cayman Islands Foundation Company (International)**:\n\t\t- Cayman's Foundation Companies Act (effective 2017, amended 2020) enables hybrid entity combining company and foundation features:\n\t\t- - **No shareholders**: Unlike corporations, foundations have no shareholders—they're governed by bylaws and a board (the \"Council\")\n\t\t- - **Purpose-driven**: Foundations exist to pursue specific purposes defined in bylaws (charitable, commercial, or combination)\n\t\t- - **Asset protection**: Foundation owns assets separate from founders/controllers, protecting against personal creditors\n\t\t- - **Governance flexibility**: Council members can be natural persons or corporations, located anywhere. Decisions can incorporate token voting or algorithmic governance via bylaws\n\t\t- - **Tax treatment**: Zero corporate income tax in Cayman Islands. However, US members may face Controlled Foreign Corporation (CFC) rules requiring income attribution\n\t\t- - **Privacy**: Beneficial ownership information is not public, though registers are maintained for anti-money laundering compliance\n\t\t- - **Costs**: High barrier to entry—formation costs $30,000-$75,000, annual maintenance $20,000-$50,000 (legal, audit, registered office fees)\n\t\t-\n\t\t- Cayman Foundations are favoured by large protocol DAOs (Aave Arc, certain DeFi protocols) seeking tax efficiency and privacy whilst operating globally. The high costs limit accessibility to well-funded DAOs.\n\t\t-\n\t\t- **Swiss Association (Verein) (Europe)**:\n\t\t- Switzerland's Civil Code Article 60-79 provides for associations (Vereins):\n\t\t- - **Non-profit orientation**: Associations must pursue non-profit purposes (but can engage in economic activity if incidental to mission)\n\t\t- - **Legal personality**: Associations are separate legal entities upon registration\n\t\t- - **Minimal capital requirements**: No minimum capital required (unlike corporations)\n\t\t- - **Governance structure**: Must have General Assembly (members' meeting) and Executive Board (at least 1 person). Board members must be Swiss residents\n\t\t- - **Blockchain accommodation**: Swiss regulators (FINMA) have issued guidance accepting that association membership can be represented by tokens, and voting can occur on-chain\n\t\t- - **Tax treatment**: Non-profit associations exempt from income tax on mission-related activities. Must pay VAT if revenue exceeds CHF 100,000\n\t\t- - **Disclosure**: Association bylaws and board members are public, but member lists are private\n\t\t- - **Costs**: Formation costs CHF 500-2,000, ongoing costs CHF 2,000-5,000/year\n\t\t-\n\t\t- Swiss Associations are used by community-driven projects (Ethereum Foundation, historically), particularly those with open-source or public goods missions. The non-profit restriction limits applicability for commercial DAOs.\n\t\t-\n\t- ### Comparison of Key Legal Features\n\t  collapsed:: true\n\t\t- **Liability Protection**:\n\t\t- - **Wyoming DAO LLC**: Full limited liability for members, except for personal wrongful acts\n\t\t- - **Vermont BBLLC**: Standard LLC limited liability\n\t\t- - **Marshall Islands DAO LLC**: Limited liability for members\n\t\t- - **Cayman Foundation**: Assets separated from founders/controllers; no shareholders to hold liable\n\t\t- - **Swiss Association**: Members not personally liable for association debts (Article 75a)\n\t\t- All structures provide liability shields, but enforceability in cross-border disputes is untested.\n\t\t-\n\t\t- **Fiduciary Duties**:\n\t\t- - **Wyoming**: Manager-managed LLCs have fiduciary duties; algorithmically managed do not (uncertain treatment)\n\t\t- - **Vermont**: Standard LLC fiduciary duties apply unless operating agreement modifies\n\t\t- - **Marshall Islands**: Statute silent; likely default to general fiduciary principles\n\t\t- - **Cayman**: Council members owe fiduciary duties to the Foundation (to pursue stated purposes)\n\t\t- - **Swiss**: Executive Board owes duties of care and loyalty under Swiss corporate law\n\t\t- This creates tension: if token vote directs action that board/managers believe violates fiduciary duty, who prevails? Legal doctrine undeveloped.\n\t\t-\n\t\t- **Tax Treatment**:\n\t\t- - **Wyoming**: Default partnership pass-through taxation; can elect C-corp or S-corp\n\t\t- - **Vermont**: Standard LLC taxation (pass-through default)\n\t\t- - **Marshall Islands**: No Marshall Islands tax; members taxed in home jurisdictions\n\t\t- - **Cayman**: Zero corporate tax; potential CFC issues for US persons\n\t\t- - **Swiss**: Non-profit exemption if mission-focused; otherwise corporate tax (8-21% depending on canton)\n\t\t- For US persons, offshore structures create complexity (FBAR reporting, potential CFC income attribution). Non-US members often prefer Cayman/Marshall for tax efficiency.\n\t\t-\n\t\t- **Formation and Ongoing Costs**:\n\t\t- - **Wyoming**: $100 formation, $60/year + registered agent ($50-$200/year) ≈ **$150-$400/year**\n\t\t- - **Vermont**: $125 formation, $35/year + registered agent ≈ **$200-$400/year**\n\t\t- - **Marshall Islands**: $2,000-$5,000 formation, $1,500-$3,000/year ≈ **$3,500-$8,000/year**\n\t\t- - **Cayman**: $30,000-$75,000 formation, $20,000-$50,000/year ≈ **$50,000-$125,000/year**\n\t\t- - **Swiss**: CHF 1,000-3,000 formation (~$1,100-$3,300), CHF 2,000-5,000/year (~$2,200-$5,500/year)\n\t\t- Costs heavily influence structure choice—small DAOs use Wyoming/Vermont, well-funded protocols use Cayman.\n\t\t-\n\t\t- **Privacy and Disclosure**:\n\t\t- - **Wyoming**: Articles of Organisation public (includes member names unless algorithmically managed)\n\t\t- - **Vermont**: Standard LLC filings public\n\t\t- - **Marshall Islands**: Registration details public; member lists may be private\n\t\t- - **Cayman**: Beneficial ownership not public (maintained privately for AML compliance)\n\t\t- - **Swiss**: Bylaws and board public, member lists private\n\t\t- Cayman offers maximum privacy, Wyoming/Vermont are most transparent.\n\t\t-\n\t\t- **Regulatory Oversight**:\n\t\t- - **Wyoming**: Wyoming Secretary of State; minimal ongoing oversight\n\t\t- - **Vermont**: Vermont Secretary of State; minimal oversight\n\t\t- - **Marshall Islands**: Marshall Islands registrar; annual reporting required\n\t\t- - **Cayman**: Cayman Islands Monetary Authority (CIMA) for certain activities; annual filings\n\t\t- - **Swiss**: Cantonal authorities; potential FINMA oversight if financial services offered\n\t\t- Offshore jurisdictions have more robust regulatory frameworks (AML, KYC requirements).\n\t\t-\n\t- ### Securities Law Implications\n\t  collapsed:: true\n\t\t- **US Securities Law (Wyoming/Vermont structures)**:\n\t\t- DAOs issuing governance tokens face securities law risk regardless of structure. The Howey Test asks whether a token is an investment contract:\n\t\t- - **Investment of money**: Check—token purchasers invest ETH/USD\n\t\t- - **Common enterprise**: Check—DAO treasury and protocol create common enterprise\n\t\t- - **Expectation of profits**: If token marketed emphasising profit potential from team's efforts, likely security\n\t\t- - **Efforts of others**: If DAO is genuinely decentralised with algorithmic governance, arguably not \"efforts of others\"; if core team controls, likely security\n\t\t-\n\t\t- Wyoming DAO LLC formation doesn't exempt tokens from securities classification. If tokens are securities:\n\t\t- - Must register with SEC or qualify for exemption (Reg D, Reg A, Reg S, etc.)\n\t\t- - Ongoing reporting requirements (10-K, 10-Q if registered)\n\t\t- - State securities laws (Blue Sky) compliance\n\t\t- - Potential liability for unregistered offerings\n\t\t-\n\t\t- The LAO pioneered Reg D exemption approach: accredited investor verification, no public solicitation, Form D filing. This limits participation to wealthy investors (income >$200K or net worth >$1M), but provides regulatory compliance path.\n\t\t-\n\t\t- **Offshore Securities Considerations (Cayman/Marshall Islands)**:\n\t\t- Offshore incorporation doesn't avoid US securities law if tokens are offered to US persons. SEC asserts extraterritorial jurisdiction based on:\n\t\t- - Offers made to US persons (regardless of entity location)\n\t\t- - Substantial US effects (if protocol primarily serves US users)\n\t\t-\n\t\t- Cayman Foundations often use Reg S exemption (offshore offerings to non-US persons) combined with US accredited investor verification for any US participants. This requires robust geoblocking and KYC.\n\t\t-\n\t\t- Marshall Islands and Cayman are not on OECD blacklists, providing legitimacy. However, US tax authorities scrutinise offshore structures for potential tax evasion.\n\t\t-\n\t\t- **EU MiCA Regulation (affecting all DAOs serving EU users)**:\n\t\t- Markets in Crypto-Assets (MiCA), effective 2024, creates EU-wide framework:\n\t\t- - Governance tokens may be \"crypto-assets\" requiring whitepapers, disclosures, and authorisation\n\t\t- - \"Asset-referenced tokens\" (stablecoins) face stringent capital requirements\n\t\t- - Crypto asset service providers (exchanges, custodians) must be licensed\n\t\t- DAOs serving EU users must consider MiCA compliance regardless of incorporation jurisdiction. Swiss structures may have advantage (Switzerland has equivalence arrangements with EU).\n\t\t-\n\t- ### Tax Treatment Detailed Analysis\n\t  collapsed:: true\n\t\t- **Wyoming/Vermont DAO LLC Taxation**:\n\t\t- Default classification: **Partnership** (multi-member) or **disregarded entity** (single-member)\n\t\t- - **Partnership taxation**: DAO files Form 1065 (information return), issues K-1s to members reporting their share of income/losses. Members pay tax on their allocation regardless of distributions\n\t\t- - **Challenges**: Tracking all token holders for K-1 issuance is impractical for DAOs with thousands of members. Many DAOs don't issue K-1s, creating tax uncertainty for members\n\t\t- - **C-corp election**: DAO can elect C-corp taxation (Form 8832). DAO pays corporate income tax (21% federal), then dividends to members taxed again (double taxation). Avoids K-1 complexity but higher effective rate\n\t\t- - **S-corp election**: Theoretically possible but impractical—S-corps limited to 100 shareholders, all US persons, single class of stock. Incompatible with global DAOs\n\t\t-\n\t\t- **Unincorporated DAO Risk**: DAOs without legal structure may be deemed general partnerships, with same K-1 obligations but unlimited liability exposure. Wyoming LLC formation eliminates liability but doesn't solve K-1 complexity.\n\t\t-\n\t\t- **Cayman Foundation Taxation**:\n\t\t- - **Cayman Islands**: Zero corporate income tax, zero capital gains tax, zero withholding tax. Foundation pays no Cayman tax on worldwide income\n\t\t- - **US member tax**: US persons holding Cayman Foundation interests may face:\n\t\t-   - **Controlled Foreign Corporation (CFC) rules**: If US persons own >50% (by vote or value), Foundation may be CFC. US shareholders (>10% owners) must report pro-rata share of \"Subpart F income\" (passive income, some services income) on Form 5471 annually\n\t\t-   - **Passive Foreign Investment Company (PFIC) rules**: If Foundation derives >75% income from passive sources or >50% assets produce passive income, it's a PFIC. US shareholders face punitive taxation on gains/distributions unless Qualified Electing Fund (QEF) election made\n\t\t- - **Strategy**: Foundations structured to avoid CFC/PFIC classification (active business income, diverse shareholders) or make QEF elections to mitigate PFIC penalties\n\t\t-\n\t\t- **Swiss Association Taxation**:\n\t\t- - **Switzerland**: Non-profit associations exempt from income tax on mission-related revenue. Unrelated business income taxed at cantonal corporate rates (8-21%)\n\t\t- - **VAT**: Associations exceeding CHF 100,000 revenue must register for VAT (7.7% standard rate)\n\t\t- - **US member tax**: US persons must report foreign association membership if certain thresholds met (Form 8938, FBAR). Association income may be taxable to US members depending on classification (likely foreign corporation or trust)\n\t\t-\n\t\t- **Marshall Islands DAO LLC Taxation**:\n\t\t- - **Marshall Islands**: No income tax on domestic or foreign-source income\n\t\t- - **US member tax**: Likely treated as foreign corporation. Dividend distributions to US members taxed as ordinary income (no qualified dividend treatment). Potential CFC issues if US persons control >50%\n\t\t-\n\t\t- **Practical Reality**: Most DAO members don't receive K-1s or tax reporting from their DAOs. Tax compliance is poor, creating audit risk. Sophisticated DAOs with legal counsel provide tax documentation; most do not.\n\t\t-\n\t- ### Real-World DAO Legal Structures\n\t  collapsed:: true\n\t\t- **The LAO (Wyoming DAO LLC)**:\n\t\t- The LAO, launched in 2020, pioneered the investor DAO model using Delaware LLC (later some migrated to Wyoming). Structure:\n\t\t- - Members: 100+ accredited investors, verified via third-party KYC\n\t\t- - Governance: Token-weighted voting via Moloch DAO smart contracts\n\t\t- - Legal compliance: Reg D exemption (Rule 506(c)), Form D filed\n\t\t- - Investment thesis: DeFi protocol equity investments, token purchases\n\t\t- - Results: Invested in 30+ projects including Aave, SushiSwap, Stake DAO\n\t\t- - Tax treatment: Partnership taxation, members receive K-1s annually\n\t\t-\n\t\t- The LAO demonstrated that DAOs can operate within securities law via accredited investor restrictions, but limited accessibility (minimum $120K contribution historically).\n\t\t-\n\t\t- **Flamingo DAO (Delaware LLC)**:\n\t\t- NFT-focused investment DAO using Delaware LLC:\n\t\t- - Members: 100 accredited investors (ETH whales, crypto executives)\n\t\t- - Governance: LAO-like Moloch structure\n\t\t- - Assets: $10M+ in NFTs (CryptoPunks, Autoglyphs, Bored Apes)\n\t\t- - Legal structure: Delaware LLC for established case law, ease of member management\n\t\t- - K-1s issued to members; partnership taxation\n\t\t-\n\t\t- **Uniswap Labs (Delaware C-Corp) vs Uniswap DAO (unincorporated)**:\n\t\t- Separation between company and DAO:\n\t\t- - **Uniswap Labs**: Delaware C-corp that developed Uniswap protocol, employs core team, holds IP\n\t\t- - **Uniswap DAO**: Decentralised community of UNI token holders governing protocol parameters and treasury\n\t\t- - **Legal relationship**: DAO has no formal legal structure. Uniswap Labs operates independently but influenced by DAO governance signals via [[BC-0469-snapshot-voting]]\n\t\t- - **Liability concern**: UNI token holders potentially in general partnership (joint liability), though arguable they're merely token holders without partnership intent\n\t\t-\n\t\t- Many major DAOs use this separation: company develops, DAO governs. Legally messy but common.\n\t\t-\n\t\t- **Gnosis DAO (Gnosis AG + Gnosis DAO)**:\n\t\t- - **Gnosis AG**: Swiss corporation (AG = Aktiengesellschaft) holding IP and employing developers\n\t\t- - **Gnosis DAO**: GNO token holders governing treasury and product decisions\n\t\t- - Swiss corporate structure provides European legal clarity whilst DAO handles community governance\n\t\t-\n\t\t- **Aave Arc (Cayman Foundation)**:\n\t\t- Aave launched \"Aave Arc,\" an institutional DeFi pool, via Cayman Islands Foundation:\n\t\t- - Structure: Cayman Foundation holding Aave Arc smart contracts and treasury\n\t\t- - Purpose: Serve institutional clients requiring regulatory compliance (KYC/AML)\n\t\t- - Governance: AAVE token holders govern via on-chain voting\n\t\t- - Tax efficiency: Zero Cayman tax; institutions receive tax documentation\n\t\t-\n\t\t- **ENS DAO (Cayman Foundation)**:\n\t\t- Ethereum Name Service uses Cayman Foundation structure:\n\t\t- - Foundation owns ENS protocol IP and treasury\n\t\t- - ENS token holders govern via [[BC-0469-snapshot-voting]] and on-chain execution\n\t\t- - Non-profit mission (provide decentralised naming), but Foundation structure (not Swiss association) for flexibility\n\t\t- - Setup costs ~$100K; annual costs ~$50K (legal, audit, Cayman registered office)\n\t\t-\n\t- ### Operational Considerations\n\t  collapsed:: true\n\t\t- **Bank Account Access**:\n\t\t- One of the most practical challenges for DAOs is banking. Banks require legal entities with beneficial ownership disclosure:\n\t\t- - **Wyoming/Vermont LLCs**: Can open US bank accounts (though some banks refuse crypto businesses). Requires EIN, formation documents, member disclosure\n\t\t- - **Cayman Foundations**: Can open Cayman or international accounts, but face enhanced due diligence. Many DAOs use Circle/Coinbase institutional accounts instead of traditional banks\n\t\t- - **Swiss Associations**: Can open Swiss bank accounts; Swiss banks somewhat crypto-friendly (Hypothekarbank Lenzburg, Sygnum)\n\t\t- - **Unincorporated DAOs**: Cannot open bank accounts—no legal personality. Must rely on multi-sig wallets or have individual members hold accounts (creating liability and tax issues)\n\t\t-\n\t\t- In practice, many DAOs avoid traditional banking entirely, holding assets in multi-sig wallets ([[BC-0468-multi-sig-governance]]) and using stablecoins for operations.\n\t\t-\n\t\t- **Intellectual Property Ownership**:\n\t\t- Legal entities can own IP (trademarks, patents, copyrights); unincorporated DAOs cannot:\n\t\t- - **The LAO/Flamingo**: Delaware LLCs own any IP created by DAO-funded projects\n\t\t- - **ENS DAO**: Cayman Foundation owns \"ENS\" trademark and protocol IP\n\t\t- - **Uniswap**: Uniswap Labs (company) owns IP; grants license to protocol (raises concerns about control)\n\t\t-\n\t\t- IP ownership is critical for protocol forks and defense against trademark squatters.\n\t\t-\n\t\t- **Employment and Contributor Payments**:\n\t\t- DAOs pay contributors, creating employment/contractor classification issues:\n\t\t- - **Legal entity**: Can issue W-2s (employees) or 1099s (contractors) with proper tax withholding\n\t\t- - **Unincorporated DAO**: Payments from multi-sig create ambiguity—are recipients independent contractors? Employees? Tax reporting unclear\n\t\t- - **International contributors**: Most DAOs have global contributors, complicating payroll (varying tax treaties, withholding requirements)\n\t\t-\n\t\t- Many DAOs use intermediaries: OpCo pays contributors as contractors, DAO funds OpCo. Example: Gitcoin uses Gitcoin Holdings (company) for payroll, Gitcoin DAO funds via grants.\n\t\t-\n\t\t- **Regulatory Licensing**:\n\t\t- Some DAO activities require licenses:\n\t\t- - **Money transmission**: If DAO facilitates payments/transfers, may need state MTLs (US) or equivalent\n\t\t- - **Securities dealer/broker**: If DAO operates trading venue, SEC broker-dealer registration required\n\t\t- - **Investment adviser**: If DAO manages others' assets for fee, SEC IA registration potentially required\n\t\t-\n\t\t- Legal entities can obtain licenses; unincorporated DAOs cannot. This limits permissible activities.\n\t\t-\n\t- ### Advantages and Benefits of Legal Incorporation\n\t  collapsed:: true\n\t\t- **Limited Liability Protection**: Shields members from personal liability for DAO debts, lawsuits, and regulatory penalties. Critical for risk management—without incorporation, token holders potentially liable for all DAO obligations.\n\t\t-\n\t\t- **Legal Personality**: Enables DAO to own assets, enter contracts, open bank accounts, register IP, employ workers. Unincorporated DAOs must use individual proxies, creating centralization and liability risks.\n\t\t-\n\t\t- **Tax Clarity**: Incorporation establishes tax classification (partnership, corporation, foundation), enabling compliance and avoiding worst-case treatment (general partnership with K-1 obligations AND unlimited liability).\n\t\t-\n\t\t- **Regulatory Compliance Path**: Legal entity can register securities, obtain licenses, comply with AML/KYC, and engage with regulators. Unincorporated DAOs cannot negotiate regulatory treatment.\n\t\t-\n\t\t- **Legitimacy and Counterparty Confidence**: Enterprises and institutions prefer transacting with legal entities. Partnerships, grants, and integrations easier with recognized legal status.\n\t\t-\n\t\t- **Dispute Resolution Mechanism**: Legal entities can sue and be sued in known jurisdictions with established procedures. Unincorporated DAOs face uncertainty about where disputes are adjudicated.\n\t\t-\n\t- ### Limitations and Challenges of Legal Incorporation\n\t  collapsed:: true\n\t\t- **Costs**: Formation and ongoing compliance fees range from $400/year (Wyoming) to $100,000+/year (Cayman), limiting accessibility for smaller DAOs.\n\t\t-\n\t\t- **Disclosure Requirements**: Most jurisdictions require public disclosure of formation documents, registered agents, and sometimes members/managers. This conflicts with crypto's pseudonymity culture.\n\t\t-\n\t\t- **Jurisdictional Anchor**: Incorporating creates nexus in a jurisdiction, subjecting DAO to that locale's laws, courts, and regulators. Global DAOs may prefer remaining stateless.\n\t\t-\n\t\t- **Fiduciary Duty Conflicts**: Directors/managers of legal entities owe fiduciary duties that may conflict with token holder votes. If token vote directs illegal or harmful action, do directors comply (violating duty) or refuse (violating DAO principle)? Case law nonexistent.\n\t\t-\n\t\t- **Algorithmic Governance Uncertainty**: Wyoming allows \"algorithmically managed\" DAOs, but courts haven't addressed liability when smart contract bugs cause harm. Who is sued? The code? The deployers? The token holders?\n\t\t-\n\t\t- **Tax Complexity**: Offshore structures create CFC/PFIC issues for US members. Partnership structures create K-1 complexity. No structure is tax-simple for global membership.\n\t\t-\n\t\t- **Regulatory Scrutiny**: Incorporation makes DAO visible to regulators. Unincorporated DAOs operate in shadows (risky but less visible). Some DAOs avoid incorporation to stay \"under the radar.\"\n\t\t-\n\t\t- **Philosophical Compromise**: Legal incorporation contradicts blockchain ethos of decentralization and statelessness. Anarcho-crypto purists view it as capitulation to nation-states.\n\t\t-\n\t- ### Best Practices for DAO Legal Structuring\n\t  collapsed:: true\n\t\t- **Structure Selection Based on DAO Type**:\n\t\t- - **Investor DAOs** (The LAO, Flamingo): Wyoming/Delaware LLC for US securities law familiarity, accredited investor verification\n\t\t- - **Protocol DAOs with treasuries** (Uniswap, Aave): Cayman Foundation for tax efficiency, global member base\n\t\t- - **Public goods DAOs** (Gitcoin, Ethereum Foundation): Swiss Association for non-profit status, regulatory credibility\n\t\t- - **Small community DAOs**: Wyoming DAO LLC for low costs, simple formation\n\t\t- - **Privacy-focused DAOs**: Cayman Foundation for confidential beneficial ownership\n\t\t-\n\t\t- **Dual-Entity Structures**:\n\t\t- Many DAOs use hybrid: **Operating Company + DAO**\n\t\t- - OpCo (Delaware/Swiss Corp): Holds IP, employs core team, provides services\n\t\t- - DAO (Cayman Foundation/Unincorporated): Holds treasury, governs protocol, community-driven\n\t\t- - Benefits: OpCo handles operational/legal needs, DAO handles governance/community\n\t\t- - Example: Uniswap Labs (OpCo) + Uniswap DAO, Gnosis AG + Gnosis DAO\n\t\t-\n\t\t- **Wrapper Selection Checklist**:\n\t\t- - **Budget**: <$5K/year → Wyoming/Vermont; $5-50K/year → Swiss; >$50K/year → Cayman\n\t\t- - **Member composition**: Mostly US → Wyoming; Mostly non-US → Cayman/Swiss; Global → Cayman\n\t\t- - **Privacy needs**: High → Cayman; Low → Wyoming/Vermont\n\t\t- - **Regulatory exposure**: Securities offering → Delaware/Wyoming + Reg D; Payment services → Need licensing (requires entity); Low exposure → Unincorporated possible\n\t\t- - **IP ownership**: Yes → Must incorporate somewhere; No → Can stay unincorporated\n\t\t-\n\t\t- **Legal Counsel Requirements**:\n\t\t- - **Formation**: Engage lawyers specializing in DAOs (Paradigm Legal, a16z legal, OpenLaw, LeXpunK)\n\t\t- - **Ongoing**: Retain counsel for governance questions, regulatory updates, dispute resolution\n\t\t- - **Costs**: Formation legal $5K-50K depending on jurisdiction; ongoing $10K-100K/year\n\t\t-\n\t\t- **Governance Document Alignment**:\n\t\t- - **Operating Agreement/Bylaws** must align with on-chain governance. Specify:\n\t\t-   - Voting mechanisms (token-weighted, [[BC-0466-quadratic-voting]], [[BC-0469-snapshot-voting]])\n\t\t-   - Proposal processes (minimum quorum, approval thresholds)\n\t\t-   - Execution: Who translates on-chain votes to legal entity actions? (Multi-sig, designated managers)\n\t\t-   - Dispute resolution: What if on-chain vote conflicts with legal requirements?\n\t\t- - **Example**: Wyoming DAO LLC operating agreement might state \"Decisions made by majority token holder vote are binding on managers, except where illegal or violating fiduciary duties.\"\n\t\t-\n\t\t- **Tax Planning**:\n\t\t- - Engage tax counsel for structure selection (international tax, partnership taxation, CFC/PFIC analysis)\n\t\t- - Decide K-1 approach: Will you issue K-1s? (impractical for 1000+ members) Or elect C-corp? Or offshore?\n\t\t- - Document distribution policy: Regular distributions avoid phantom income issues (members taxed on income they don't receive)\n\t\t-\n\t- ### Future Legal Developments\n\t  collapsed:: true\n\t\t- **Additional US State Statutes**: Tennessee (2022) and Utah (2023) passed DAO LLC statutes similar to Wyoming. Expect more states to follow, creating jurisdictional competition and potentially fragmenting standards.\n\t\t-\n\t\t- **Federal DAO Legislation (US)**: Proposals for federal DAO recognition are discussed but face political headwinds. Would provide nationwide clarity but reduce state experimentation.\n\t\t-\n\t\t- **EU DAO Framework**: MiCA addresses crypto-assets but not DAOs specifically. Expect EU member states (likely Estonia, Malta, Portugal) to introduce DAO legal frameworks in 2024-2026.\n\t\t-\n\t\t- **Tax Safe Harbors**: IRS could issue guidance on DAO taxation, potentially creating safe harbors for K-1 issuance or allowing simplified reporting for widely-held DAOs. No indication this is imminent.\n\t\t-\n\t\t- **Case Law Development**: Lawsuits involving DAOs will create precedents on liability, fiduciary duties, and algorithmic governance. Juno DAO's 2022 vote to confiscate whale's tokens raised questions about property rights and DAO legal authority—future cases will clarify.\n\t\t-\n\t\t- **Algorithmic Legal Entities**: Future structures might embed legal compliance into smart contracts—automated tax withholding, regulatory reporting, dividend distributions. \"LexDAO\" and similar projects research programmable legal entities.\n\t\t-\n\t\t- **DAO-to-DAO Contracting**: As more DAOs incorporate, legal entity DAOs can contract with each other (partnerships, service agreements). This enables formal B2B relationships between protocols.\n\t\t-\n\t- #\n\n## Current Landscape (2025)\n\n- Industry adoption and implementations\n  - Metaverse platforms continue to evolve with focus on interoperability and open standards\n  - Web3 integration accelerating with decentralised identity and asset ownership\n  - Enterprise adoption growing in virtual collaboration, training, and digital twins\n  - UK companies increasingly active in metaverse development and immersive technologies\n\n- Technical capabilities\n  - Real-time rendering at photorealistic quality levels\n  - Low-latency networking enabling seamless multi-user experiences\n  - AI-driven content generation and procedural world building\n  - Spatial audio and haptics enhancing immersion\n\n- UK and North England context\n  - Manchester: Digital Innovation Factory supports metaverse startups and research\n  - Leeds: Holovis leads in immersive experiences for entertainment and training\n  - Newcastle: University research in spatial computing and interactive systems\n  - Sheffield: Advanced manufacturing using digital twin technology\n\n- Standards and frameworks\n  - Metaverse Standards Forum driving interoperability protocols\n  - WebXR enabling browser-based immersive experiences\n  - glTF and USD for 3D asset interchange\n  - Open Metaverse Interoperability Group defining cross-platform standards\n\n## Metadata\n\n- **Last Updated**: 2025-11-16\n- **Review Status**: Automated remediation with 2025 context\n- **Verification**: Academic sources verified\n- **Regional Context**: UK/North England where applicable\n\n\n## References and Research\n\t  collapsed:: true\n\t\t- **Statutes and Regulations**:\n\t\t- - Wyoming SF0038 (2021). \"Decentralized Autonomous Organizations Supplement.\" Wyoming Secretary of State.\n\t\t- - Vermont Title 11, Chapter 25 (2018). \"Blockchain-Based Limited Liability Companies.\" Vermont Legislature.\n\t\t- - Marshall Islands Non-Profit Entities Act (2022 Amendment). \"Decentralized Autonomous Organizations.\"\n\t\t- - Cayman Islands Foundation Companies Act (2017, amended 2020). Cayman Islands Government.\n\t\t- - Swiss Civil Code Articles 60-79. \"Associations.\" Swiss Confederation.\n\t\t-\n\t\t- **Legal Analysis and Guidance**:\n\t\t- - Miles Jennings, a16z Crypto. (2022). \"A Legal Framework for Decentralized Autonomous Organizations.\" a16z.com/crypto\n\t\t- - COALA (Coalition of Automated Legal Applications). (2021). \"Model Law for Decentralized Autonomous Organizations (DAOs).\"\n\t\t- - Paradigm Legal. (2021). \"The Wyoming DAO LLC: A Practitioner's Guide.\"\n\t\t- - OpenLaw. (2020). \"The LAO: A For-Profit, Limited Liability Autonomous Organization.\"\n\t\t-\n\t\t- **Tax Guidance**:\n\t\t- - Houman B. Shadab. (2022). \"Taxation of Decentralized Autonomous Organizations.\" *Ohio State Technology Law Journal*.\n\t\t- - IRS Notice 2014-21 (Bitcoin/Crypto Tax Treatment - applicable to DAO tokens)\n\t\t- - Abraham Sutherland, EY. (2021). \"Tax Considerations for DAOs.\" *Tax Notes*.\n\t\t-\n\t\t- **Case Studies**:\n\t\t- - The LAO. \"Legal Structure and Compliance Documentation.\" theLAO.io\n\t\t- - Flamingo DAO. \"Operating Agreement and Governance.\" flamingodao.xyz\n\t\t- - ENS DAO. \"ENS Foundation (Cayman) Structure.\" docs.ens.domains\n\t\t- - Gitcoin DAO. \"Governance and Legal Structure.\" gov.gitcoin.co\n\t\t-\n\t\t- **Related Topics**:\n\t\t- - [[BC-0461-decentralized-autonomous-organization]] - DAO fundamentals and governance\n\t\t- - [[BC-0462-on-chain-voting]] - Governance voting mechanisms\n\t\t- - [[BC-0466-quadratic-voting]] - Voting mechanism used in DAO governance\n\t\t- - [[BC-0468-multi-sig-governance]] - Execution mechanism for DAO legal entities\n\t\t- - [[BC-0469-snapshot-voting]] - Off-chain voting commonly used by legal DAOs\n\t\t- - [[Corporate Law]] - Traditional corporate structures and fiduciary duties\n\t\t- - [[Securities Regulation]] - Reg D, Howey Test, token securities classification\n\t\t- - [[Tax Treatment]] - Partnership taxation, CFC rules, PFIC\n\t\t-\n\t- ### Original Content\n\t  collapsed:: true\n\t\t- ```\n\n\t\t  ```",
  "properties": {
    "id": "bc-0470-dao-legal-structures-ontology",
    "collapsed": "true",
    "- ontology": "true",
    "- term-id": "BC-0470",
    "- preferred-term": "DAO Legal Structures",
    "- source-domain": "blockchain",
    "- status": "stub-needs-content",
    "- public-access": "true",
    "- content-status": "minimal-placeholder-requires-authoring",
    "- definition": "A component of the blockchain ecosystem.",
    "- maturity": "draft",
    "- owl:class": "bc:DAOLegalStructures",
    "- owl:physicality": "ConceptualEntity",
    "- owl:role": "Concept",
    "- belongsToDomain": "[[BlockchainDomain]]"
  },
  "backlinks": [
    "BC-0467-conviction-voting",
    "BC-0466-quadratic-voting",
    "BC-0469-snapshot-voting",
    "BC-0495-voting-systems",
    "BC-0468-multi-sig-governance"
  ],
  "wiki_links": [
    "BC-0469-snapshot-voting",
    "BlockchainDomain",
    "Tax Treatment",
    "BC-0462-on-chain-voting",
    "Corporate Law",
    "Securities Regulation",
    "BC-0468-multi-sig-governance",
    "BC-0461-decentralized-autonomous-organization",
    "BC-0466-quadratic-voting"
  ],
  "ontology": {
    "term_id": "BC-0470",
    "preferred_term": "DAO Legal Structures",
    "definition": "A component of the blockchain ecosystem.",
    "source_domain": "blockchain",
    "maturity_level": null,
    "authority_score": null
  }
}