{
  "title": "Asia Pacific Regulation",
  "content": "- ### OntologyBlock\n  id:: bc-0484-asia-pacific-regulation-ontology\n  collapsed:: true\n\t- ontology:: true\n\t- term-id:: BC-0484\n\t- preferred-term:: Asia Pacific Regulation\n\t- source-domain:: blockchain\n\t- status:: stub-needs-content\n\t- public-access:: true\n\t- content-status:: minimal-placeholder-requires-authoring\n\t- public-access:: true\n\t- definition:: A component of the blockchain ecosystem.\n\t- maturity:: draft\n\t- owl:class:: bc:AsiaPacificRegulation\n\t- owl:physicality:: ConceptualEntity\n\t- owl:role:: Concept\n\t- belongsToDomain:: [[BlockchainDomain]]\n\n## OWL Formal Semantics\n\n```clojure\n;; OWL Functional Syntax\n\n(Declaration (Class :AsiaPacificRegulation))\n\n;; Annotations\n(AnnotationAssertion rdfs:label :AsiaPacificRegulation \"Asia Pacific Regulation\"@en)\n(AnnotationAssertion rdfs:comment :AsiaPacificRegulation \"A component of the blockchain ecosystem.\"@en)\n\n;; Data Properties\n(AnnotationAssertion dcterms:identifier :AsiaPacificRegulation \"BC-0484\"^^xsd:string)\n```\n\n- ## About Asia Pacific Regulation\n  id:: asia-pacific-regulation-about\n\n\t- The Asia-Pacific region encompasses the most diverse and rapidly evolving [[Cryptocurrency]] regulatory landscape globally, ranging from highly sophisticated frameworks positioning jurisdictions as international crypto hubs to comprehensive bans prohibiting all cryptocurrency activity. This regulatory spectrum reflects the region's economic diversity, varying policy priorities, technological capabilities, and governance philosophies. Singapore, Japan, and Hong Kong have established comprehensive licensing regimes balancing innovation support with consumer protection and financial stability, implementing proactive regulatory frameworks influenced by [[FATF]] standards but adapted to local circumstances. These jurisdictions compete to attract cryptocurrency businesses through regulatory clarity, supportive infrastructure, and integration with traditional finance, positioning themselves as the \"crypto-friendly\" alternatives to restrictive approaches elsewhere. Australia follows a similar path through progressive regulation incorporating cryptocurrency businesses into existing financial services frameworks whilst developing bespoke requirements. South Korea oscillates between embracing technological innovation and imposing strict regulations following market crashes or fraud scandals, reflecting political tensions between pro-crypto forces and conservative regulators. India represents regulatory uncertainty, with contradictory signals from different government branches creating compliance challenges despite massive grassroots cryptocurrency adoption. China stands as the region's most restrictive jurisdiction, having implemented comprehensive bans on cryptocurrency trading, mining, and services following years of progressive tightening, viewing digital assets as threats to financial stability and capital controls. Southeast Asian nations including Thailand, Malaysia, Philippines, Vietnam, and Indonesia pursue varying approaches from licensing regimes to outright prohibitions, often influenced by domestic political considerations and economic development priorities. This fragmentation creates complex compliance landscapes for regional cryptocurrency businesses, requiring navigation of multiple regulatory frameworks with differing definitions, licensing requirements, and enforcement approaches. The region's importance to global cryptocurrency markets derives from substantial retail and institutional adoption, significant mining operations (historically concentrated in China before the ban), major exchanges headquartered in regional jurisdictions, and large developer communities building [[Blockchain]] applications. Asia-Pacific regulatory developments significantly influence global norms, with Singapore's framework inspiring other jurisdictions, Japan's licensing providing templates for comprehensive oversight, and China's restrictions demonstrating government capabilities to suppress cryptocurrency activity through comprehensive enforcement.\n\t-\n\t- ### Singapore\n\t\t- Singapore has established itself as the premier Asia-Pacific cryptocurrency hub through the **Payment Services Act 2019** (PSA), which took effect on 28 January 2020, creating comprehensive licensing for Digital Payment Token (DPT) services whilst maintaining flexible, innovation-friendly regulatory approaches. The **Monetary Authority of Singapore** (MAS), the country's integrated financial regulator and central bank, oversees cryptocurrency regulation through licensing, supervision, and enforcement. The PSA establishes two licensing tiers: a **Standard Payment Institution** licence for entities with annual transaction values up to SGD 5 million, and a **Major Payment Institution** licence for those exceeding this threshold. DPT services covered include: dealing in DPTs (buying, selling, exchanging digital payment tokens), facilitating exchange of DPTs (operating platforms for others to exchange), transfer of DPTs (transmitting DPTs on behalf of others), DPT custodian services (safeguarding or controlling DPTs on behalf of others), and providing digital payment token advisory services. The licensing framework requires entities to demonstrate adequate capital (SGD 100,000 to SGD 250,000 base capital depending on services, plus additional amounts based on operational expenditure), robust governance structures with fit and proper senior management, comprehensive risk management frameworks addressing technology, cyber, money laundering, and terrorist financing risks, AML/CFT compliance programmes implementing [[FATF]] standards including customer due diligence, transaction monitoring, and suspicious transaction reporting to the Suspicious Transaction Reporting Office (STRO), and business continuity arrangements ensuring operational resilience. As of 2024, MAS has received over 400 VASP licence applications since the PSA's implementation, approving approximately 20% whilst rejecting many for failing to demonstrate adequate anti-money laundering controls, sufficient capital, or appropriate governance. Major licensed entities include global exchanges like Coinbase, Crypto.com, and Independent Reserve, institutional service providers including Matrixport and Coinhako, and payment platforms integrating cryptocurrency capabilities. MAS has been notably selective, refusing licences to several high-profile applicants including Binance (withdrawn application in December 2021) and FTX-affiliated entities, demonstrating rigorous supervisory standards despite the jurisdiction's reputation for innovation-friendliness. Singapore implements comprehensive **AML/CFT requirements** aligned with FATF Recommendations, including enhanced customer due diligence for higher-risk customers, ongoing monitoring of business relationships, screening against sanctions lists including United Nations and domestic designations, and suspicious transaction reporting. The **Travel Rule** applies to transfers exceeding SGD 1,500, requiring transmission of originator and beneficiary information between VASPs. MAS has issued detailed guidelines on AML controls, technology risk management, outsourcing, and cyber hygiene through notices and circulars. Singapore prohibits certain activities including offering derivatives to retail customers without appropriate licences, marketing to retail customers without balanced risk disclosure, and providing services to sanctioned jurisdictions. The regulatory approach emphasises proportionality, with requirements scaled to entity size and risk profile, and innovation support through regulatory sandboxes enabling testing of novel business models under MAS supervision with temporary regulatory relief.\n\t\t-\n\t- ### Japan\n\t\t- Japan pioneered comprehensive cryptocurrency regulation following the catastrophic collapse of Mt. Gox in 2014, which lost approximately 850,000 [[Bitcoin]] worth hundreds of millions at the time, devastating Japanese retail investors who comprised significant portions of early cryptocurrency adopters. The **Payment Services Act** (PSA), amended in 2017 to explicitly address virtual currencies (further revised in 2020), established the framework requiring Cryptocurrency Exchange Service Providers (CESPs) to register with the **Financial Services Agency** (JFSA). The 2017 amendments, effective April 2017, represented the world's first comprehensive national licensing regime for cryptocurrency exchanges, providing legal recognition for virtual currencies as means of payment whilst imposing robust regulatory requirements. The regulatory framework requires exchanges to register with the JFSA, demonstrating adequate capital (minimum JPY 10 million base capital), segregation of customer assets from proprietary assets with external audits verifying separation, cybersecurity measures protecting against hacking and unauthorised access (particularly emphasised following multiple exchange hacks including Coincheck's JPY 58 billion loss in January 2018), AML/KYC procedures implementing customer identification and verification, and internal controls ensuring compliance with all obligations. The **Financial Instruments and Exchange Act** (FIEA) was amended in 2020 to address crypto-derivatives and security tokens, requiring separate licensing for entities offering margin trading, futures, options, or other derivatives on crypto-assets. The 2020 amendments replaced the term \"virtual currency\" with \"crypto-asset\" to avoid confusion with sovereign currencies, strengthened customer asset protection requirements mandating segregation and trust arrangements, introduced regulations for crypto-asset custody service providers previously unregulated, and enhanced advertising restrictions requiring balanced risk disclosure. The **Japan Virtual Currency Exchange Association** (JVCEA), established as the JFSA-certified self-regulatory organisation, develops industry standards, conducts compliance examinations, and provides guidance to members on operational practices. All registered exchanges must join JVCEA, subjecting them to self-regulatory rules complementing statutory requirements. As of 2024, approximately 30 Cryptocurrency Exchange Service Providers maintain JFSA registration, including major platforms like bitFlyer, Coincheck, GMO Coin, Liquid (acquired by FTX and subsequently restructured), and DMM Bitcoin. The approval process requires extensive documentation, interviews with management, and system inspections, taking 6-12 months typically. Japan prohibits anonymous cryptocurrencies, with JVCEA rules restricting or prohibiting trading of privacy-focused coins like [[Monero]], [[Zcash]], and [[Dash]] due to money laundering and terrorist financing concerns. Tax treatment classifies cryptocurrency gains as miscellaneous income subject to progressive taxation up to 55% (combining national and local taxes), significantly higher than capital gains treatment in many jurisdictions, potentially discouraging retail trading. Enforcement actions have included business improvement orders for exchanges with inadequate AML controls, suspension orders for those suffering security breaches without adequate remediation, and criminal prosecutions for unlicensed operations.\n\t\t-\n\t- ### Hong Kong\n\t\t- Hong Kong has evolved from a relatively permissive approach to comprehensive regulation through the **Securities and Futures Ordinance** (SFO) and new licensing regime for Virtual Asset Service Providers (VASPs) implemented by the **Securities and Futures Commission** (SFC). The regulatory journey began with the SFC's November 2018 statement establishing a conceptual framework for regulating crypto-asset platforms, followed by voluntary opt-in licensing for platforms trading security tokens. The mandatory VASP licensing regime commenced on **1 June 2023** through amendments to the Anti-Money Laundering and Counter-Terrorist Financing Ordinance (AMLO), requiring all centralized virtual asset exchanges operating in Hong Kong or actively marketing to Hong Kong investors to obtain licences from the SFC regardless of whether traded assets constitute securities. This marked a significant shift to comprehensive regulation covering all crypto-assets rather than only those qualifying as securities or futures contracts under existing definitions. The licensing requirements include minimum paid-up share capital of HKD 5 million, liquid capital of HKD 3 million or 12 months of operating expenses (whichever is higher), robust corporate governance with fit and proper responsible officers and executive directors, comprehensive risk management frameworks addressing custody, cybersecurity, conflicts of interest, market manipulation, and money laundering risks, insurance covering custody risks, AML/CFT compliance programmes implementing [[FATF]] standards including customer due diligence, transaction monitoring, and suspicious transaction reporting to the Joint Financial Intelligence Unit (JFIU), segregation of client assets from platform's proprietary assets with daily reconciliation, and appropriate use of client assets with restrictions on rehypothecation and lending. The framework extends to both professional (institutional) and retail investors, with enhanced protections for retail including token admission criteria ensuring traded assets meet minimum standards for liquidity, custody arrangements, and disclosure, knowledge assessment ensuring retail customers understand crypto-asset risks before trading, concentration limits preventing over-concentration in particular assets, and prohibition of derivatives trading by retail investors. Licensed VASPs must provide adequate disclosure about token characteristics, risks, fees, and platform operations through offering documents reviewed by the SFC. The licensing process requires applications with detailed business plans, compliance manuals, system descriptions, financial projections, and governance documents, with SFC review taking 6-12 months typically. As of 2024, the SFC has granted licences to several platforms including OSL Digital Securities, Hash Blockchain, and Victory Securities, whilst numerous applications remain under review. Major global exchanges including Binance have withdrawn from Hong Kong retail markets rather than seek licensing, reflecting the regime's stringency. The regulatory approach distinguishes virtual assets (crypto-assets not qualifying as securities or futures) from securities tokens (those falling within securities definitions under the SFO), with the latter subject to additional securities regulation including prospectus requirements for public offerings.\n\t\t-\n\t- ### South Korea\n\t\t- South Korea has implemented one of the region's most stringent cryptocurrency regulatory frameworks following periods of market euphoria, crashes, and fraud scandals creating political pressure for comprehensive oversight. The **Virtual Asset User Protection Act**, passed by the National Assembly in June 2023 and effective from July 2024, represents the culmination of years of regulatory development, establishing comprehensive requirements for Virtual Asset Service Providers (VASPs) including exchanges, wallet providers, and brokers. The legislation requires VASPs to register with the Financial Services Commission (FSC) and Financial Intelligence Unit (FIU), demonstrating compliance with technical requirements including information security management systems (ISMS) certification from the Korea Internet & Security Agency, real-name verified bank accounts for deposits and withdrawals in partnership with commercial banks, deposit insurance or reserve funds protecting customer assets equivalent to deposit volumes, segregation of customer and company assets with external audits, and prohibition of unfair trading practices including market manipulation, insider trading, and fraud. The **Financial Services Commission** (FSC) and **Financial Intelligence Unit** (FIU) under the Korea Financial Intelligence Unit provide regulatory oversight, with the FSC developing policy and the FIU handling AML/CTF registration and supervision. The requirement for real-name bank account partnerships has proven particularly challenging, with only four commercial banks (KB Kookmin Bank, Shinhan Bank, NH Nonghyup Bank, and KEB Hana Bank) providing services to registered VASPs after extensive due diligence. This banking requirement effectively limits the number of viable exchanges, with approximately 30 VASPs maintaining partnerships whilst hundreds of smaller operators were forced to close or operate without fiat on/off-ramps. Major registered exchanges include Upbit (South Korea's largest by volume), Bithumb, Coinone, Korbit, and Gopax. The **Travel Rule** implementation in March 2022 required VASPs to collect and transmit customer information for transactions exceeding KRW 1 million (approximately USD 750), creating interoperability challenges as different exchanges adopted incompatible technical solutions. The Virtual Asset User Protection Act introduces additional consumer protections including mandatory deposit insurance or reserve equivalent to customer deposits, strict custody requirements with cold wallet storage for majority of assets, prohibition of unfair trading practices with criminal penalties, and regular audits of reserve ratios and security systems. South Korea prohibits token issuance by VASPs themselves (exchanges cannot list their own tokens), restricts trading of privacy coins, and maintains enhanced monitoring for unusual transaction patterns. Tax treatment subjects virtual asset gains to 20% taxation on profits exceeding KRW 2.5 million annually (deferred from original 2022 implementation to 2025 following industry lobbying). Enforcement has been aggressive, with the FSC imposing business suspension orders on exchanges failing to meet requirements, criminal prosecution of operators engaging in market manipulation, and international cooperation pursuing fraudsters including Do Kwon of Terraform Labs.\n\t\t-\n\t- ### Australia\n\t\t- Australia has adopted an evolving regulatory approach incorporating cryptocurrency businesses into existing financial services frameworks whilst developing bespoke requirements addressing unique crypto-asset characteristics. The **Australian Transaction Reports and Analysis Centre** (AUSTRAC) regulates virtual currency exchanges as digital currency exchange providers (DCEs) under the Anti-Money Laundering and Counter-Terrorism Financing Act 2006 (AML/CTF Act). DCEs must register with AUSTRAC, implement AML/CTF programmes including customer identification and verification, transaction monitoring and reporting of suspicious matters and threshold transactions, maintaining records of customer identification and transactions for seven years, conducting regular risk assessments, and appointing compliance officers responsible for programme oversight. As of 2024, over 400 digital currency exchanges maintain AUSTRAC registration, including major platforms like CoinSpot, Swyftx, Independent Reserve, and international entrants including Coinbase. Registration requires DCEs to demonstrate compliance capabilities but does not involve capital requirements or detailed business approval processes, creating a relatively accessible entry point compared to jurisdictions with comprehensive licensing. However, the **Treasury** has consulted on enhanced regulatory frameworks including potential licensing requirements, custodian obligations, market integrity rules, and consumer protection standards. The 2023 Token Mapping consultation examined whether different crypto-assets require differentiated regulation, potentially distinguishing stablecoins, security tokens, and other categories with varying requirements. The **Australian Securities and Investments Commission** (ASIC) regulates crypto-assets qualifying as financial products under the Corporations Act 2001, requiring entities offering financial services in relation to these assets to obtain Australian Financial Services Licences (AFSL). ASIC has pursued enforcement actions against ICO issuers making misleading statements, platforms offering derivatives without appropriate licences, and entities providing financial advice without authorisation. The determination of whether particular crypto-assets constitute financial products involves analysis of whether they provide rights similar to shares, derivatives, or managed investment schemes, creating classification uncertainty for novel tokens. ASIC's regulatory guidance emphasises disclosure obligations for issuers, appropriate design and distribution obligations ensuring products reach appropriate customers, and prohibition of misleading or deceptive conduct in marketing. The **Reserve Bank of Australia** (RBA) studies cryptocurrency's implications for monetary policy and payment systems whilst developing central bank digital currency capabilities. The RBA has expressed concerns about stablecoin systemic risk if payment stablecoins achieve significant scale, potentially supporting regulation similar to payment systems or electronic money. Tax treatment by the **Australian Taxation Office** (ATO) classifies cryptocurrency as property subject to capital gains tax, with specific guidance on trading, mining, staking, airdrops, and DeFi taxation. The ATO has implemented data-matching programmes obtaining customer information from exchanges to identify taxpayers failing to report cryptocurrency transactions.\n\t\t-\n\t- ### India\n\t\t- India's cryptocurrency regulatory landscape is characterised by uncertainty, contradictory signals from different government branches, and tension between grassroots adoption and regulatory hostility. Despite being among the world's largest cryptocurrency markets by user numbers and transaction volumes, India lacks comprehensive regulatory frameworks, oscillating between proposals for outright bans and regulated legalisation. The **Reserve Bank of India** (RBI) imposed a banking ban in April 2018, prohibiting regulated financial institutions from providing services to cryptocurrency businesses, effectively cutting exchanges from the banking system. The ban devastated India's cryptocurrency industry, with exchanges forced to close or relocate, trading volumes collapsing, and jobs lost. The **Supreme Court of India** struck down the banking ban in March 2020 in Internet and Mobile Association of India v. Reserve Bank of India, finding the RBI lacked statutory authority for the prohibition and the measure was disproportionate. The ruling temporarily revived India's cryptocurrency industry, with exchanges resuming fiat on-ramps and trading volumes recovering. However, the government introduced the **Cryptocurrency and Regulation of Official Digital Currency Bill** in 2021, proposing to ban all private cryptocurrencies whilst creating a framework for an official digital currency. The bill's status remains unclear, with multiple Parliamentary sessions delaying consideration amid controversy about definitions (whether \"private\" meant non-governmental or privacy-focused), implementation approaches, and economic impacts. The **2022 Budget** introduced 30% taxation on cryptocurrency gains without offsetting losses, characterising virtual digital assets as separate from capital assets, plus 1% Tax Deducted at Source (TDS) on transactions exceeding INR 10,000 (approximately USD 120) creating compliance burdens and reducing liquidity. These tax provisions provided implicit recognition of cryptocurrency's legality despite absence of positive regulation, creating legal ambiguity. The high taxation rate and TDS requirement significantly impacted trading volumes on Indian exchanges, with many traders moving to offshore platforms or peer-to-peer transactions. The **Financial Intelligence Unit** (FIU) issued notices in 2024 requiring cryptocurrency exchanges operating in India to register as Virtual Asset Service Providers under the Prevention of Money Laundering Act (PMLA), implementing KYC requirements, maintaining transaction records, filing suspicious transaction reports, and adhering to other AML obligations. Major exchanges including Binance, Kucoin, and others received show-cause notices for operating without FIU registration, with some subsequently blocking Indian users whilst others pursued registration. As of late 2024, several exchanges have obtained FIU registration, demonstrating government willingness to regulate rather than ban despite earlier rhetoric. The enforcement approach has been aggressive toward foreign exchanges, with the Enforcement Directorate (ED) pursuing investigations into WazirX, Binance, and others for alleged FEMA (Foreign Exchange Management Act) violations, freezing assets and pursuing criminal charges. Despite regulatory hostility, Indian cryptocurrency adoption remains substantial, with significant peer-to-peer trading, DeFi participation, and grassroots investment. Industry advocates continue pushing for comprehensive regulation providing legal certainty whilst enabling innovation.\n\t\t-\n\t- ### China\n\t\t- China has implemented the world's most comprehensive cryptocurrency prohibition, evolving from early tolerance through progressively restrictive measures culminating in complete bans on trading, mining, and services. China's regulatory journey began with growing concern about capital flight, financial stability risks, fraud, and Communist Party control over finance. Initial restrictions in 2013 prohibited financial institutions from handling Bitcoin transactions whilst permitting individual ownership and trading on exchanges. The 2017 ICO boom prompted the **People's Bank of China** (PBOC) to ban Initial Coin Offerings in September 2017, declaring them illegal fundraising activities, followed by prohibition of cryptocurrency exchanges in China, forcing major platforms including BTCC, Huobi, and OKCoin to relocate overseas or shut down domestic fiat trading. Despite exchange bans, over-the-counter trading persisted, with exchanges operating from Hong Kong, Singapore, or other jurisdictions serving mainland Chinese customers through VPNs and offshore accounts. The mining industry, concentrated in regions with cheap hydroelectric or coal power (Sichuan, Inner Mongolia, Xinjiang), continued operating, with China controlling approximately 65-75% of global Bitcoin hashrate by 2021. Environmental concerns about coal-powered mining, financial stability risks from cryptocurrency volatility, and desire for complete control ahead of Digital Yuan (e-CNY) CBDC rollout prompted comprehensive action. In May 2021, the State Council Financial Stability and Development Committee declared cryptocurrency trading and mining illegal, directing local governments to shut down mining operations and financial institutions to prevent all cryptocurrency-related services. Provincial governments across Sichuan, Yunjiang, Inner Mongolia, and other regions issued shutdown orders, with electricity providers cutting power to mining facilities, resulting in the \"great mining migration\" as Chinese miners relocated operations to United States, Kazakhstan, Russia, and other jurisdictions, fundamentally reshaping global mining geography. The **September 2021 comprehensive ban** declared all cryptocurrency transactions illegal, prohibited overseas exchanges from providing services to mainland residents, banned cryptocurrency-related financial activities including trading, order matching, token issuance, and derivatives, made it illegal to provide marketing, payment, or technical support for cryptocurrency transactions, and directed internet service providers to block cryptocurrency exchange and service websites. The enforcement infrastructure implemented includes Great Firewall blocking of cryptocurrency exchange domains, banking system monitoring for cryptocurrency-related transactions with account freezing, criminal prosecution of individuals facilitating cryptocurrency trading or providing services, and cooperation with foreign authorities pursuing Chinese nationals operating overseas cryptocurrency businesses. Despite comprehensive prohibition, underground trading persists through peer-to-peer transactions, VPNs accessing overseas exchanges, and stablecoin-based trading bypassing traditional banking. The enforcement challenge demonstrates limitations even of China's extensive state capacity to completely eliminate decentralised activity. The motivation for prohibition includes capital control enforcement preventing capital flight through cryptocurrency channels, financial stability protection from speculative trading and fraud affecting retail investors, Communist Party control over finance maintaining dominance of state-controlled banking, Digital Yuan promotion eliminating private cryptocurrency competition, and environmental concerns about energy-intensive mining.\n\t\t-\n\t- ### Other Asia-Pacific Jurisdictions\n\t\t- **Thailand** regulates through the Securities and Exchange Commission (SEC Thailand) under the Emergency Decree on Digital Asset Businesses B.E. 2561 (2018), requiring digital asset exchanges, brokers, and dealers to obtain licences, implementing AML/KYC requirements, and distinguishing investment tokens (securities) from utility tokens. Seven exchanges have obtained licences including Bitkub, the dominant platform with over 5 million users. **Malaysia** approaches regulation through Bank Negara Malaysia (central bank) and the Securities Commission Malaysia, registering digital asset exchanges under AML/CFT frameworks whilst considering securities regulation for token offerings. Major exchanges include Luno, Tokenize, and MX Global. **Philippines** requires Virtual Asset Service Providers to register with the Bangko Sentral ng Pilipinas (central bank) under AML/CTF regulations, with approximately 20 entities obtaining registration. The SEC regulates token offerings qualifying as securities. **Vietnam** maintains ambiguous status with State Bank of Vietnam statements discouraging cryptocurrency whilst not explicitly prohibiting ownership, creating grey-zone operations. Grassroots adoption remains substantial despite regulatory uncertainty. **Indonesia** prohibits cryptocurrency as payment instruments whilst permitting trading as commodities regulated by the Commodity Futures Trading Regulatory Agency (BAPPEBTI), requiring exchanges to register and implement AML controls. **New Zealand** incorporates cryptocurrency businesses under AML/CFT requirements through the Department of Internal Affairs whilst taxation authorities treat cryptocurrency as property. The **Monetary Authority** studies comprehensive regulation. **Taiwan** regulates through AML/CFT frameworks via the Financial Supervisory Commission whilst developing comprehensive virtual asset frameworks. **Cambodia** has banned cryptocurrency trading since 2018, pursuing strict enforcement. **Pakistan** oscillates between prohibition and tolerance, with the State Bank of Pakistan prohibiting banking services for cryptocurrency whilst courts examine legality. The regional diversity reflects varying development priorities, regulatory capacity, capital control concerns, and technological adoption patterns.\n\t\t-\n\t- ### Comparative Analysis\n\t\t- The Asia-Pacific regulatory spectrum reveals several key patterns. **Innovation vs. Control**: Jurisdictions like Singapore, Hong Kong, and Japan prioritise innovation and competitiveness through clear frameworks attracting businesses, whilst China and Cambodia prioritise state control through prohibitions. **Retail Protection**: Japan and South Korea implement stringent consumer protection following major exchange hacks and fraud affecting retail investors, whilst lighter-touch jurisdictions emphasise industry development. **Capital Controls**: China's prohibition primarily serves capital control enforcement, preventing cryptocurrency-facilitated outflows, whilst Singapore's open capital account enables permissive approaches. **Regulatory Capacity**: Sophisticated regulators (MAS, JFSA, SFC) implement nuanced frameworks with risk-based supervision, whilst jurisdictions with limited capacity often choose prohibition over complex licensing. **Banking Integration**: Successful regulatory frameworks provide banking access for licensed entities (Singapore, Japan, Hong Kong), whilst banking exclusion (India pre-2020, South Korea's limited partnerships) creates operational challenges. **FATF Compliance**: Most jurisdictions implement FATF standards through travel rule requirements, AML/KYC obligations, and VASP registration, with varying thresholds and technical solutions. **Tax Treatment**: Approaches range from capital gains (Australia, Hong Kong no capital gains tax) to income taxation (Japan's progressive rates, India's 30% flat tax) to effective prohibition through punitive treatment, significantly affecting trading attractiveness. **Enforcement**: Varies from collaborative regulatory engagement (Singapore's consultative processes) to aggressive prosecution (South Korea's criminal cases, China's comprehensive enforcement). The competitive dynamics see jurisdictions vie for cryptocurrency business, with Singapore, Hong Kong, and Dubai (outside Asia-Pacific but competitive) offering clear frameworks, whilst restrictive approaches in major markets create opportunities for permissive jurisdictions to attract businesses and talent.\n\t\t-\n\t- ### Industry Impact\n\t\t- Asia-Pacific regulatory diversity profoundly shapes global cryptocurrency industry structure. Major exchanges including Binance, Huobi, OKX, and Bybit trace origins to the region, with many initially based in China before migrating to Hong Kong, Singapore, or fully offshore structures following Chinese restrictions. The licensing requirements in major jurisdictions have created industry consolidation, with well-capitalised entities obtaining multiple licences whilst smaller operators exit or merge. Singapore has emerged as the regional headquarters preference for global exchanges and institutional service providers, offering regulatory clarity, rule of law, and geographic positioning. Japan's rigorous licensing has created a domestic market dominated by regulated exchanges with limited international expansion, reflecting stringent requirements discouraging cross-border operations. South Korea's banking partnership requirements have entrenched incumbent exchanges with existing relationships, creating barriers for new entrants. The Chinese mining exodus fundamentally reshaped global hashrate distribution, with United States and Kazakhstan becoming major mining centres following Chinese shutdowns. Retail adoption patterns reflect regulatory approaches: Japan's regulated market has substantial retail trading through licensed exchanges, South Korea's large retail market operates on registered VASPs with regulatory protections, whilst India's uncertain framework drives peer-to-peer and offshore trading despite massive grassroots interest. The DeFi sector has concentrated in jurisdictions with unclear regulation or permissive approaches, with many teams avoiding restrictive markets including China, whilst seeking regulatory engagement in Singapore and Hong Kong. Stablecoin adoption in the region is dominated by USDT and USDC, with regulatory frameworks in Japan restricting certain stablecoins and other jurisdictions studying whether domestic stablecoin frameworks could support financial innovation whilst maintaining monetary control. The development community remains vibrant across the region despite regulatory restrictions, with significant blockchain protocol development, NFT creation, gaming applications, and DeFi innovation originating from teams in Singapore, Hong Kong, South Korea, and increasingly Vietnam and Indonesia.\n\t\t-\n\t- ### Challenges and Controversies\n\t\t- Asia-Pacific cryptocurrency regulation faces numerous challenges. The **jurisdictional arbitrage** problem sees businesses incorporating in permissive jurisdictions whilst serving customers in restrictive markets through VPNs, offshore accounts, and decentralised protocols, undermining regulatory effectiveness. The **innovation vs. control tension** creates debates about whether comprehensive regulation provides necessary protection or stifles innovation that could benefit economic development. Countries imposing restrictions risk driving innovation elsewhere whilst potentially failing to eliminate domestic cryptocurrency activity. The **enforcement capacity** limitations in developing countries mean sophisticated cryptocurrency operations can evade inadequate regulatory oversight, whilst users in restrictive markets continue accessing offshore services despite prohibitions. **Banking access** remains a challenge even in regulated markets, with traditional banks cautious about cryptocurrency clients due to reputational risk, compliance costs, and regulatory uncertainty, limiting licensed VASPs' operational capabilities. The **tax treatment uncertainty** affects trading attractiveness and compliance, with varying approaches creating opportunities for regulatory arbitrage but also legitimate confusion about obligations. **Privacy vs. transparency** debates centre on travel rule implementation, with technical challenges transmitting customer information between VASPs, privacy concerns about transaction surveillance, and questions about proportionality. **Cross-border coordination** limitations mean activities legal in one jurisdiction may violate laws in neighbouring countries, creating compliance complexity for regional businesses. The **retail protection question** asks whether stringent requirements (minimum capital, insurance, token listing restrictions) effectively protect consumers or merely consolidate industries whilst sophisticated fraud persists. **Stablecoin regulation** challenges include determining whether algorithmic stablecoins require different treatment than fiat-backed ones, addressing systemic risk from payment stablecoins without stifling innovation, and preventing stablecoins from undermining monetary sovereignty. The **China question** looms large: will comprehensive prohibition succeed in eliminating cryptocurrency activity, or will underground trading and offshore access persist, and what lessons do other jurisdictions draw from Chinese approach?\n\t\t-\n\t- ### Best Practices for Asia-Pacific Compliance\n\t\t- Cryptocurrency businesses operating across Asia-Pacific must develop sophisticated multi-jurisdictional compliance programmes. **Jurisdictional licensing** requires obtaining VASP licences in each operating market: Singapore MAS licence for Southeast Asian hub operations, Hong Kong SFC licence for Greater China access, Japan JFSA registration for Japanese market entry, South Korea FSC/FIU registration with banking partnerships, and Australia AUSTRAC registration for Australian operations. Each application requires substantial investment (often USD 500,000 to USD 2 million per jurisdiction for legal fees, compliance systems, and capital requirements). **AML/KYC infrastructure** must meet varying requirements across jurisdictions: robust customer identification and verification with document verification, biometric authentication, address confirmation, enhanced due diligence for PEPs and high-risk customers, transaction monitoring with jurisdiction-specific thresholds and suspicious activity detection, sanctions screening against multiple lists (UN, national, regional), and suspicious transaction reporting to respective FIUs with varying timeframes and formats. **Travel rule compliance** requires implementing information exchange capabilities with counterparty VASPs, managing varying thresholds (Singapore SGD 1,500, South Korea KRW 1 million, Japan no specified threshold), adopting interoperable technical solutions (TRISA, IVMS101), and maintaining records demonstrating compliance. **Token listing policies** should evaluate whether tokens qualify as securities under varying jurisdictional tests, avoid privacy coins prohibited in Japan and South Korea, implement delisting procedures if regulatory classification changes, and conduct ongoing reviews as regulatory guidance evolves. **Geographical controls** must implement blocking for prohibited jurisdictions (China, Cambodia), manage compliance for restricted markets with licensing requirements, and ensure marketing materials don't target jurisdictions where unlicensed. **Legal structures** require establishing local entities in each licensed jurisdiction with appropriate capitalisation, governance meeting fit and proper standards, and local compliance personnel understanding regulatory requirements. Engaging local legal counsel, compliance consultants, and regulatory advisers is essential given language barriers, cultural considerations, and regulatory nuances.\n\t\t-\n\t- ### Future Developments\n\t\t- Asia-Pacific cryptocurrency regulation faces several critical developments. **Singapore's evolving framework** will continue refining requirements based on implementation experience, potentially expanding retail protections, adjusting capital requirements, and developing stablecoin-specific regulations. The MAS may implement additional restrictions on retail leverage or derivatives following global regulatory trends. **Hong Kong's VASP regime** will mature as more applicants complete licensing, potentially attracting major exchanges if regulatory clarity continues and political stability persists following national security law implementation. Competition with Singapore for regional dominance will intensify. **Japan's potential liberalisation** may adjust stringent requirements discouraging international exchange entry, balancing consumer protection with industry competitiveness. The JFSA may reconsider privacy coin prohibitions and tax treatment to revitalise domestic trading. **South Korea's implementation** of the Virtual Asset User Protection Act will demonstrate whether comprehensive consumer protection frameworks achieve objectives without excessive compliance burdens, potentially providing templates for other jurisdictions. **India's regulatory resolution** remains critical, with comprehensive frameworks potentially legitimising the industry or outright bans forcing activity fully underground. The government's approach will significantly impact the region's largest potential market. **China's potential reversal** appears unlikely under current leadership but remains possible if economic circumstances change, CBDC rollout succeeds enabling controlled private cryptocurrency reintroduction, or global competitive pressures mount. **Australia's enhanced regulation** will likely introduce licensing requirements replacing registration, implement custody standards, and provide clearer frameworks for token classifications and stablecoins. **Regional coordination** through ASEAN, APEC, or bilateral agreements may promote greater harmonisation, reducing compliance fragmentation whilst respecting jurisdictional sovereignty. **CBDC rollouts** across the region (China's Digital Yuan, Japan's experiments, Singapore's Project Ubin, Hong Kong's e-HKD) will influence private cryptocurrency regulation, potentially providing state alternatives whilst informing approaches to stablecoin oversight.\n\t\t-\n\t- #\n\n## Current Landscape (2025)\n\n- Industry adoption and implementations\n  - Metaverse platforms continue to evolve with focus on interoperability and open standards\n  - Web3 integration accelerating with decentralised identity and asset ownership\n  - Enterprise adoption growing in virtual collaboration, training, and digital twins\n  - UK companies increasingly active in metaverse development and immersive technologies\n\n- Technical capabilities\n  - Real-time rendering at photorealistic quality levels\n  - Low-latency networking enabling seamless multi-user experiences\n  - AI-driven content generation and procedural world building\n  - Spatial audio and haptics enhancing immersion\n\n- UK and North England context\n  - Manchester: Digital Innovation Factory supports metaverse startups and research\n  - Leeds: Holovis leads in immersive experiences for entertainment and training\n  - Newcastle: University research in spatial computing and interactive systems\n  - Sheffield: Advanced manufacturing using digital twin technology\n\n- Standards and frameworks\n  - Metaverse Standards Forum driving interoperability protocols\n  - WebXR enabling browser-based immersive experiences\n  - glTF and USD for 3D asset interchange\n  - Open Metaverse Interoperability Group defining cross-platform standards\n\n## Metadata\n\n- **Last Updated**: 2025-11-16\n- **Review Status**: Automated remediation with 2025 context\n- **Verification**: Academic sources verified\n- **Regional Context**: UK/North England where applicable\n\n\n## References\n\t\t- [[Monetary Authority of Singapore]]\n\t\t- [[Japan FSA]]\n\t\t- [[Hong Kong SFC]]\n\t\t- [[BC-0481-fatf-recommendations]]\n\t\t- [[BC-0482-eu-mica-regulation]]\n\t\t- [[BC-0483-us-regulatory-framework]]\n\t\t- [[BC-0456-virtual-asset-service-providers]]\n\t\t- [[BC-0457-aml-kyc-compliance]]\n\t\t- [[Virtual Asset Service Provider]]\n\t\t- [[Payment Services Act]]\n\t\t- [[Cryptocurrency Exchange]]\n\t\t- [[Anti-Money Laundering]]\n\t\t- [[Know Your Customer]]\n\t\t- [[Travel Rule]]\n\t\t- [[Digital Currency]]\n\t\t- [[Central Bank Digital Currency]]\n\t\t-",
  "properties": {
    "id": "bc-0484-asia-pacific-regulation-ontology",
    "collapsed": "true",
    "- ontology": "true",
    "- term-id": "BC-0484",
    "- preferred-term": "Asia Pacific Regulation",
    "- source-domain": "blockchain",
    "- status": "stub-needs-content",
    "- public-access": "true",
    "- content-status": "minimal-placeholder-requires-authoring",
    "- definition": "A component of the blockchain ecosystem.",
    "- maturity": "draft",
    "- owl:class": "bc:AsiaPacificRegulation",
    "- owl:physicality": "ConceptualEntity",
    "- owl:role": "Concept",
    "- belongsToDomain": "[[BlockchainDomain]]"
  },
  "backlinks": [],
  "wiki_links": [
    "BC-0483-us-regulatory-framework",
    "BC-0482-eu-mica-regulation",
    "Monetary Authority of Singapore",
    "Zcash",
    "Hong Kong SFC",
    "Japan FSA",
    "Cryptocurrency Exchange",
    "Travel Rule",
    "Blockchain",
    "FATF",
    "Dash",
    "Know Your Customer",
    "BC-0481-fatf-recommendations",
    "Digital Currency",
    "BlockchainDomain",
    "Virtual Asset Service Provider",
    "Bitcoin",
    "BC-0456-virtual-asset-service-providers",
    "Anti-Money Laundering",
    "Payment Services Act",
    "BC-0457-aml-kyc-compliance",
    "Central Bank Digital Currency",
    "Monero",
    "Cryptocurrency"
  ],
  "ontology": {
    "term_id": "BC-0484",
    "preferred_term": "Asia Pacific Regulation",
    "definition": "A component of the blockchain ecosystem.",
    "source_domain": "blockchain",
    "maturity_level": null,
    "authority_score": null
  }
}