{
  "title": "Behavioral Modeling",
  "content": "- ### OntologyBlock\n  id:: behavioralmodeling-ontology\n  collapsed:: true\n\n  - **Identification**\n    - domain-prefix:: AI\n    - sequence-number:: 0847\n    - filename-history:: [\"AI-0847-behavioralmodeling.md\"]\n    - public-access:: true\n    - ontology:: true\n    - term-id:: AI-0847\n    - preferred-term:: Behavioral Modeling\n    - source-domain:: ai\n    - status:: complete\n    - version:: 1.0.0\n    - last-updated:: 2025-11-13\n\n  - **Definition**\n    - definition:: \n    - maturity:: established\n    - source:: Chimera Prime Research\n    - authority-score:: 0.95\n\n  - **Semantic Classification**\n    - owl:class:: ai:BehavioralModeling\n    - belongsToDomain:: [[Artificial Intelligence]]\n\n  - #### OWL Restrictions\n    \n\n  - #### CrossDomainBridges\n    - bridges-to:: [[MachineLearning]] via is-subclass-of\n\n  -",
  "properties": {
    "id": "behavioralmodeling-ontology",
    "collapsed": "true",
    "- domain-prefix": "AI",
    "- sequence-number": "0847",
    "- filename-history": "[\"AI-0847-behavioralmodeling.md\"]",
    "- public-access": "true",
    "- ontology": "true",
    "- term-id": "AI-0847",
    "- preferred-term": "Behavioral Modeling",
    "- source-domain": "ai",
    "- status": "complete",
    "- version": "1.0.0",
    "- last-updated": "2025-11-13",
    "- definition": "",
    "- maturity": "established",
    "- source": "Chimera Prime Research",
    "- authority-score": "0.95",
    "- owl:class": "ai:BehavioralModeling",
    "- belongsToDomain": "[[Artificial Intelligence]]",
    "- bridges-to": "[[MachineLearning]] via is-subclass-of"
  },
  "backlinks": [],
  "wiki_links": [
    "Artificial Intelligence",
    "MachineLearning"
  ],
  "ontology": {
    "term_id": "AI-0847",
    "preferred_term": "Behavioral Modeling",
    "definition": "",
    "source_domain": "ai",
    "maturity_level": null,
    "authority_score": 0.95
  }
}