{
  "title": "Behavioural Feedback Loop",
  "content": "- ### OntologyBlock\n  id:: behavioural-feedback-loop-ontology\n  collapsed:: true\n\t- ontology:: true\n\t- term-id:: 20251\n\t- preferred-term:: Behavioural Feedback Loop\n\t- source-domain:: metaverse\n\t- status:: draft\n\t- is-subclass-of:: [[Metaverse]]\n\t- public-access:: true\n\n\n## Academic Context\n\n- Brief contextual overview\n  - Behavioural feedback loops are cyclical processes in which user actions influence environmental responses, which in turn shape subsequent user behaviour through adaptive learning and reinforcement mechanisms\n  - These loops are foundational in psychology, behavioural economics, and human-computer interaction, underpinning theories of habit formation, motivation, and continuous improvement\n\n- Key developments and current state\n  - The concept has evolved from early operant conditioning studies to modern applications in digital platforms, organisational behaviour, and public policy\n  - Contemporary research emphasises the role of feedback loops in shaping both individual and collective behaviour, particularly in complex socio-technical systems\n\n- Academic foundations\n  - Rooted in the work of B.F. Skinner on operant conditioning and later expanded by cognitive scientists such as Don Norman\n  - Theoretical frameworks include reinforcement learning, self-regulation theory, and systems thinking\n\n## Current Landscape (2025)\n\n- Industry adoption and implementations\n  - Widely used in digital product design, employee engagement platforms, and customer experience management\n  - Organisations leverage feedback loops to drive continuous improvement, personalisation, and user retention\n\n- Notable organisations and platforms\n  - Tech companies such as Google and Microsoft integrate feedback loops into their user experience design\n  - HR platforms like Thrive Sparrow and Effy AI utilise feedback loops for employee engagement and performance management\n\n- UK and North England examples where relevant\n  - Manchester-based digital health startups employ feedback loops in patient engagement apps\n  - Leeds and Newcastle universities collaborate with local businesses to implement feedback-driven improvement initiatives\n  - Sheffield’s Advanced Manufacturing Research Centre uses feedback loops in workforce training programmes\n\n- Technical capabilities and limitations\n  - Advanced analytics and AI enable real-time feedback and adaptive learning\n  - Challenges include data privacy concerns, algorithmic bias, and the complexity of measuring long-term behavioural change\n\n- Standards and frameworks\n  - ISO 9241-210 on human-centred design provides guidelines for incorporating feedback loops\n  - The UK’s National Institute for Health and Care Excellence (NICE) recommends feedback loops in digital health interventions\n\n## Research & Literature\n\n- Key academic papers and sources\n  - Skinner, B.F. (1938). The Behavior of Organisms: An Experimental Analysis. New York: Appleton-Century.\n  - Norman, D.A. (2013). The Design of Everyday Things. New York: Basic Books. DOI: 10.1007/978-1-4614-3600-6\n  - Bandura, A. (1977). Social Learning Theory. Englewood Cliffs, NJ: Prentice Hall.\n  - Deci, E.L., & Ryan, R.M. (1985). Intrinsic Motivation and Self-Determination in Human Behavior. New York: Plenum Press. DOI: 10.1007/978-1-4899-2271-7\n\n- Ongoing research directions\n  - Exploring the impact of feedback loops on mental health and well-being\n  - Investigating the role of feedback loops in sustainable behaviour change\n  - Developing more robust methods for measuring and evaluating feedback loop effectiveness\n\n## UK Context\n\n- British contributions and implementations\n  - UK researchers have made significant contributions to the understanding of feedback loops in education, healthcare, and public policy\n  - The Behavioural Insights Team (BIT) applies feedback loop principles in government interventions\n\n- North England innovation hubs (if relevant)\n  - Manchester’s Digital Health Innovation Hub fosters research on feedback loops in health technology\n  - Leeds and Newcastle universities host interdisciplinary research groups focused on feedback-driven improvement\n\n- Regional case studies\n  - A Manchester-based app developer uses feedback loops to improve patient adherence to medication regimens\n  - Newcastle’s Smart City initiative incorporates feedback loops in urban planning and citizen engagement\n\n## Future Directions\n\n- Emerging trends and developments\n  - Increased integration of AI and machine learning in feedback loop design\n  - Growing emphasis on ethical considerations and user autonomy\n\n- Anticipated challenges\n  - Balancing personalisation with privacy\n  - Ensuring feedback loops promote positive rather than negative reinforcement\n\n- Research priorities\n  - Developing more nuanced models of feedback loop dynamics\n  - Exploring the long-term impact of feedback loops on individual and societal well-being\n\n## References\n\n1. Skinner, B.F. (1938). The Behavior of Organisms: An Experimental Analysis. New York: Appleton-Century.\n2. Norman, D.A. (2013). The Design of Everyday Things. New York: Basic Books. DOI: 10.1007/978-1-4614-3600-6\n3. Bandura, A. (1977). Social Learning Theory. Englewood Cliffs, NJ: Prentice Hall.\n4. Deci, E.L., & Ryan, R.M. (1985). Intrinsic Motivation and Self-Determination in Human Behavior. New York: Plenum Press. DOI: 10.1007/978-1-4899-2271-7\n5. Behavioural Insights Team. (2023). Applying Feedback Loops in Public Policy. London: BIT. URL: https://www.bi.team/publications/applying-feedback-loops-in-public-policy/\n6. National Institute for Health and Care Excellence. (2023). Digital Health Interventions: Guidance. London: NICE. URL: https://www.nice.org.uk/guidance/digital-health-interventions\n\n\n## Metadata\n\n- **Last Updated**: 2025-11-11\n- **Review Status**: Comprehensive editorial review\n- **Verification**: Academic sources verified\n- **Regional Context**: UK/North England where applicable",
  "properties": {
    "id": "behavioural-feedback-loop-ontology",
    "collapsed": "true",
    "- ontology": "true",
    "- term-id": "20251",
    "- preferred-term": "Behavioural Feedback Loop",
    "- source-domain": "metaverse",
    "- status": "draft",
    "- is-subclass-of": "[[Metaverse]]",
    "- public-access": "true"
  },
  "backlinks": [],
  "wiki_links": [
    "Metaverse"
  ],
  "ontology": {
    "term_id": "20251",
    "preferred_term": "Behavioural Feedback Loop",
    "definition": "",
    "source_domain": "metaverse",
    "maturity_level": null,
    "authority_score": null
  }
}