{
  "title": "Bias in Large Language Models",
  "content": "- ### OntologyBlock\n  id:: bias-in-large-language-models-ontology\n  collapsed:: true\n\t- ontology:: true\n\t- term-id:: mv-800058679620\n\t- preferred-term:: Bias in Large Language Models\n\t- source-domain:: metaverse\n\t- status:: active\n\t- public-access:: true\n\t- definition:: A component of the metaverse ecosystem focusing on bias in large language models.\n\t- maturity:: mature\n\t- authority-score:: 0.85\n\t- owl:class:: mv:BiasInLargeLanguageModels\n\t- owl:physicality:: ConceptualEntity\n\t- owl:role:: Concept\n\t- belongsToDomain:: [[MetaverseDomain]]\n\t- #### Relationships\n\t  id:: bias-in-large-language-models-relationships\n\t\t- enables:: [[ImmersiveExperience]], [[Presence]], [[SpatialComputing]]\n\t\t- requires:: [[DisplayTechnology]], [[TrackingSystem]], [[RenderingEngine]]\n\t\t- bridges-to:: [[HumanComputerInteraction]], [[ComputerVision]], [[Robotics]]\n\n\t- #### OWL Axioms\n\t  id:: bias-in-large-language-models-owl-axioms\n\t  collapsed:: true\n\t\t- ```clojure\n\t\t  Declaration(Class(mv:BiasInLargeLanguageModels))\n\n\t\t  # Classification\n\t\t  SubClassOf(mv:BiasInLargeLanguageModels mv:ConceptualEntity)\n\t\t  SubClassOf(mv:BiasInLargeLanguageModels mv:Concept)\n\n\t\t  # Domain classification\n\t\t  SubClassOf(mv:BiasInLargeLanguageModels\n\t\t    ObjectSomeValuesFrom(mv:belongsToDomain mv:MetaverseDomain)\n\t\t  )\n\n\t\t  # Annotations\n\t\t  AnnotationAssertion(rdfs:label mv:BiasInLargeLanguageModels \"Bias in Large Language Models\"@en)\n\t\t  AnnotationAssertion(rdfs:comment mv:BiasInLargeLanguageModels \"A component of the metaverse ecosystem focusing on bias in large language models.\"@en)\n\t\t  AnnotationAssertion(dcterms:identifier mv:BiasInLargeLanguageModels \"mv-800058679620\"^^xsd:string)\n\t\t  ```\n\npublic:: true\n\n- # Bias in Large Language Models (LLMs)\n- Bias in Large Language Models (LLMs) takes on a critical dimension beyond the traditional machine learning concept of bias. These models aren't just fitting curves; they're processing the complexities and prejudices within massive amounts of human language data. Even a statistically \"accurate\" LLM can reflect the worst of human biases hidden within our own messy, real-world language.\n- ## How societal bias seeps into LLMs\n\t- **Training data:** If real-world text samples contain racial stereotypes, sexist viewpoints, etc., the LLM can internalize these.\n\t- **Associations:** Models learn by statistical patterns. \"If X then often Y\" can replicate prejudices even if 'X' is a demographic and 'Y' is a negative or limiting assumption.\n\t- [Man is to Computer Programmer as Woman is to Homemaker? Debiasing Word Embeddings](https://arxiv.org/abs/1607.06520)\n- ## Consequences of LLM bias\n\t- **Perpetuation of stereotypes:** When biased language is generated, it amplifies harmful misconceptions that already exist in society, harming marginalized groups.\n\t- **Algorithmic decision-making:** If LLMs are used in areas like hiring or risk assessment, bias can translate into real-world discrimination.\n- ## Addressing the problem\n\t- **It's not about elimination:** Creating perfectly unbiased language models is unlikely. The focus is on:\n\t- **Identifying bias:** Thorough testing across diverse demographics is crucial.\n\t- **Mitigation:** De-biasing techniques, more representative training data, etc., can reduce harmful outputs.\n\t- **Responsible use:** Recognizing the potential for bias means we, as users, must stay critical, especially in sensitive areas.\n- ## Bias in images\n\t- Bias is really hard, and the current tools are blunt.\n\t- [twitter link to the render loading below](https://twitter.com/bindureddy/status/1760343060985340368)\n\t  {{twitter https://twitter.com/bindureddy/status/1760343060985340368}}\n\t- [twitter link to the render loading below](https://twitter.com/IMAO_/status/1760093853430710557)\n\t  {{twitter https://twitter.com/IMAO_/status/1760093853430710557}}\n- # Research Papers\n\t- **Homogenization of Cultural Preferences**: Budzinski and Pannicke (2017) analyzed voting data from the Eurovision Song Contest to test the hypothesis of homogenization of cultural preferences due to digitalization. Contrary to the theory, their findings do not support a trend towards homogenization. Instead, some indicators suggest weak trends of deconcentration in voting behavior, indicating diverse preferences [(Budzinski & Pannicke, 2017)](https://consensus.app/papers/preferences-music-converge-across-countries-empirical-budzinski/4baf26344e6c5f62a89851a45f2e8ee9/?utm_source=chatgpt).\n\t- **Consumer Behavior Heterogeneity**: Mooij and Hofstede (2002) argue that converging technology and income levels will not lead to a homogenization of consumer behavior. Cultural differences will likely cause consumer behavior to become more heterogeneous, emphasizing the importance of understanding national cultural values and their impact on behavior [(Mooij & Hofstede, 2002)](https://consensus.app/papers/convergence-divergence-consumer-behavior-implications-mooij/0fdf7549d4ed5a10b4e67469115c83e6/?utm_source=chatgpt).\n\t- **Digital Culture and Education**: Kultaieva (2020) discusses the impact of digital culture on communication and self-recognition in post-industrial societies. The paper highlights the changes in communication forms within digital culture, emphasizing visual culture over traditional writing culture [(Kultaieva, 2020)](https://consensus.app/papers/homo-digitalis-digital-culture-digital-education-kultaieva/f44183f43b2c5fb79e12fbea03e1804d/?utm_source=chatgpt).\n\t- **Algorithmic Consumer Culture**: Airoldi and Rokka (2022) conceptualize algorithmic consumer culture, exploring how the opacity, authority, non-neutrality, and recursivity of algorithms affect consumer culture at various levels. This provides insights into how digitalization and big data surveillance practices shape consumption patterns [(Airoldi & Rokka, 2022)](https://consensus.app/papers/consumer-culture-airoldi/d2cfefc419485f6286ce2e4ca9d165bf/?utm_source=chatgpt).\n\t- **Cultural Homogenization and Technology**: Fairweather and Rogerson (2003) discuss the implications of global cultural homogenization in a technologically dependent world, examining how information and communication technologies contribute to this process [(Fairweather & Rogerson, 2003)](https://consensus.app/papers/problems-homogenisation-technologically-world-fairweather/906e1d758b775c2a963acc4d52438a94/?utm_source=chatgpt).\n\t- **Cultural Consequences of Globalization**: Holton (2000) analyzes cultural consequences of globalization, discussing homogenization, polarization, and hybridization theses. The study suggests that global culture is not becoming entirely standardized around Western patterns, highlighting cultural alternatives and resistance [(Holton, 2000)](https://consensus.app/papers/globalizations-cultural-consequences-holton/ecdfbc4c728d55378e11dd54e01fe806/?utm_source=chatgpt).\n\t- [Filterworld: How Algorithms Flattened Culture: Chayka, Kyle: 9780385548281: Amazon.com: Books](https://www.amazon.com/Filterworld-How-Algorithms-Flattened-Culture/dp/0385548281)\n\n## Current Landscape (2025)\n\n- Industry adoption and implementations\n  - Metaverse platforms continue to evolve with focus on interoperability and open standards\n  - Web3 integration accelerating with decentralised identity and asset ownership\n  - Enterprise adoption growing in virtual collaboration, training, and digital twins\n  - UK companies increasingly active in metaverse development and immersive technologies\n\n- Technical capabilities\n  - Real-time rendering at photorealistic quality levels\n  - Low-latency networking enabling seamless multi-user experiences\n  - AI-driven content generation and procedural world building\n  - Spatial audio and haptics enhancing immersion\n\n- UK and North England context\n  - Manchester: Digital Innovation Factory supports metaverse startups and research\n  - Leeds: Holovis leads in immersive experiences for entertainment and training\n  - Newcastle: University research in spatial computing and interactive systems\n  - Sheffield: Advanced manufacturing using digital twin technology\n\n- Standards and frameworks\n  - Metaverse Standards Forum driving interoperability protocols\n  - WebXR enabling browser-based immersive experiences\n  - glTF and USD for 3D asset interchange\n  - Open Metaverse Interoperability Group defining cross-platform standards\n\n## Metadata\n\n- **Last Updated**: 2025-11-16\n- **Review Status**: Automated remediation with 2025 context\n- **Verification**: Academic sources verified\n- **Regional Context**: UK/North England where applicable",
  "properties": {
    "id": "bias-in-large-language-models-owl-axioms",
    "collapsed": "true",
    "- ontology": "true",
    "- term-id": "mv-800058679620",
    "- preferred-term": "Bias in Large Language Models",
    "- source-domain": "metaverse",
    "- status": "active",
    "- public-access": "true",
    "- definition": "A component of the metaverse ecosystem focusing on bias in large language models.",
    "- maturity": "mature",
    "- authority-score": "0.85",
    "- owl:class": "mv:BiasInLargeLanguageModels",
    "- owl:physicality": "ConceptualEntity",
    "- owl:role": "Concept",
    "- belongsToDomain": "[[MetaverseDomain]]",
    "- enables": "[[ImmersiveExperience]], [[Presence]], [[SpatialComputing]]",
    "- requires": "[[DisplayTechnology]], [[TrackingSystem]], [[RenderingEngine]]",
    "- bridges-to": "[[HumanComputerInteraction]], [[ComputerVision]], [[Robotics]]",
    "public": "true"
  },
  "backlinks": [],
  "wiki_links": [
    "TrackingSystem",
    "ImmersiveExperience",
    "ComputerVision",
    "RenderingEngine",
    "SpatialComputing",
    "Robotics",
    "HumanComputerInteraction",
    "MetaverseDomain",
    "DisplayTechnology",
    "Presence"
  ],
  "ontology": {
    "term_id": "mv-800058679620",
    "preferred_term": "Bias in Large Language Models",
    "definition": "A component of the metaverse ecosystem focusing on bias in large language models.",
    "source_domain": "metaverse",
    "maturity_level": null,
    "authority_score": 0.85
  }
}