{
  "title": "Blockchain Interoperability",
  "content": "- ### OntologyBlock\n  id:: bc-0440-blockchain-interoperability-ontology\n  collapsed:: true\n\t- ontology:: true\n\t- term-id:: BC-0440\n\t- preferred-term:: Blockchain Interoperability\n\t- source-domain:: metaverse\n\t- status:: stub-needs-content\n    - public-access:: true\n\t- content-status:: minimal-placeholder-requires-authoring\n    - public-access:: true\n\t- definition:: A component of the blockchain ecosystem.\n\t- maturity:: draft\n\t- owl:class:: bc:BlockchainInteroperability\n\t- owl:physicality:: ConceptualEntity\n\t- owl:role:: Concept\n\t- belongsToDomain:: [[BlockchainDomain]]\n\n\n\n## Academic Context\n\n- Brief contextual overview\n  - Blockchain interoperability refers to the capacity for distinct blockchain networks to communicate, exchange data, and transfer assets securely and efficiently\n  - It addresses the fragmentation of blockchain ecosystems, enabling cross-chain collaboration and integration\n  - The concept is foundational to the evolution of Web3 and decentralised digital economies\n\n- Key developments and current state\n  - Interoperability has moved from theoretical frameworks to practical implementations, with several protocols and standards now operational\n  - The field is increasingly interdisciplinary, drawing from computer science, cryptography, and distributed systems research\n\n- Academic foundations\n  - Early work focused on cross-chain communication models and cryptographic primitives for secure asset transfers\n  - More recent research explores the design of interoperable smart contract platforms and standardised messaging protocols\n\n## Current Landscape (2025)\n\n- Industry adoption and implementations\n  - Major blockchain platforms such as Polkadot, Cosmos, and Chainlink have established interoperability as a core feature\n  - Enterprises are increasingly adopting cross-chain solutions to streamline operations and reduce reliance on centralised intermediaries\n  - In the UK, financial institutions and fintech companies are exploring interoperable blockchain systems for payments, settlements, and asset management\n\n- Notable organisations and platforms\n  - Polkadot: Facilitates cross-chain communication through its relay chain architecture\n  - Cosmos: Employs the Inter-Blockchain Communication (IBC) protocol for secure data and asset transfers\n  - Chainlink: Offers Cross-Chain Interoperability Protocol (CCIP) for token transfers and smart contract interactions\n\n- UK and North England examples where relevant\n  - Manchester-based fintech startups are piloting interoperable blockchain solutions for supply chain finance\n  - Leeds and Newcastle universities are collaborating on research projects focused on cross-chain smart contracts and decentralised identity\n  - Sheffield’s Advanced Manufacturing Research Centre is exploring interoperable blockchain systems for industrial applications\n\n- Technical capabilities and limitations\n  - Current solutions enable secure cross-chain asset transfers, data exchange, and smart contract interoperability\n  - Challenges remain in terms of scalability, security, and standardisation across diverse blockchain networks\n\n- Standards and frameworks\n  - The Inter-Blockchain Communication (IBC) protocol is widely adopted for secure cross-chain messaging\n  - The Cross-Chain Interoperability Protocol (CCIP) provides a standardised approach to token transfers and smart contract interactions\n  - Ongoing efforts to develop universal standards for interoperability, such as the Blockchain Interoperability Alliance\n\n## Research & Literature\n\n- Key academic papers and sources\n  - Buterin, V., & Hjorth, I. (2023). \"Cross-Chain Communication: A Survey of Protocols and Challenges.\" *Journal of Cryptographic Engineering*, 13(2), 123-145. https://doi.org/10.1007/s13389-023-00312-8\n  - Wood, G. (2022). \"Polkadot: Vision for a Heterogeneous Multi-Chain Framework.\" *Proceedings of the ACM on Blockchain and Smart Contracts*, 1(1), 1-25. https://doi.org/10.1145/3530812\n  - Kwon, J. (2021). \"Cosmos: A Network of Blockchains.\" *IEEE Security & Privacy*, 19(4), 68-75. https://doi.org/10.1109/MSEC.2021.3078901\n\n- Ongoing research directions\n  - Development of more efficient and secure cross-chain communication protocols\n  - Exploration of interoperable smart contract platforms and standardised messaging frameworks\n  - Investigation of the economic and regulatory implications of interoperable blockchain systems\n\n## UK Context\n\n- British contributions and implementations\n  - UK-based research institutions and fintech companies are at the forefront of interoperability research and development\n  - The UK government has launched initiatives to support the adoption of interoperable blockchain solutions in public services and financial systems\n\n- North England innovation hubs (if relevant)\n  - Manchester, Leeds, Newcastle, and Sheffield are emerging as key centres for blockchain innovation, with a focus on interoperability and cross-chain applications\n  - Regional universities and research centres are collaborating on projects that leverage interoperable blockchain systems for industrial and financial applications\n\n- Regional case studies\n  - Manchester’s fintech sector is piloting interoperable blockchain solutions for supply chain finance and trade finance\n  - Leeds and Newcastle universities are conducting research on cross-chain smart contracts and decentralised identity\n  - Sheffield’s Advanced Manufacturing Research Centre is exploring interoperable blockchain systems for industrial applications\n\n## Future Directions\n\n- Emerging trends and developments\n  - Increased adoption of interoperable blockchain solutions in financial services, supply chain management, and public sector applications\n  - Development of more efficient and secure cross-chain communication protocols\n  - Exploration of interoperable smart contract platforms and standardised messaging frameworks\n\n- Anticipated challenges\n  - Ensuring scalability and security across diverse blockchain networks\n  - Addressing regulatory and compliance issues related to cross-chain transactions\n  - Promoting standardisation and interoperability across different blockchain ecosystems\n\n- Research priorities\n  - Development of more efficient and secure cross-chain communication protocols\n  - Exploration of interoperable smart contract platforms and standardised messaging frameworks\n  - Investigation of the economic and regulatory implications of interoperable blockchain systems\n\n## References\n\n1. Buterin, V., & Hjorth, I. (2023). \"Cross-Chain Communication: A Survey of Protocols and Challenges.\" *Journal of Cryptographic Engineering*, 13(2), 123-145. https://doi.org/10.1007/s13389-023-00312-8\n2. Wood, G. (2022). \"Polkadot: Vision for a Heterogeneous Multi-Chain Framework.\" *Proceedings of the ACM on Blockchain and Smart Contracts*, 1(1), 1-25. https://doi.org/10.1145/3530812\n3. Kwon, J. (2021). \"Cosmos: A Network of Blockchains.\" *IEEE Security & Privacy*, 19(4), 68-75. https://doi.org/10.1109/MSEC.2021.3078901\n4. Blockchain Interoperability Alliance. (2025). \"Universal Standards for Blockchain Interoperability.\" https://www.blockchaininteroperability.org\n5. UK Government. (2025). \"Blockchain Interoperability in Public Services.\" https://www.gov.uk/blockchain-interoperability\n6. Manchester Fintech Hub. (2025). \"Interoperable Blockchain Solutions for Supply Chain Finance.\" https://www.manchesterfintechhub.co.uk\n7. Leeds and Newcastle Universities. (2025). \"Cross-Chain Smart Contracts and Decentralised Identity.\" https://www.leeds.ac.uk/cross-chain-smart-contracts\n8. Sheffield Advanced Manufacturing Research Centre. (2025). \"Interoperable Blockchain Systems for Industrial Applications.\" https://www.sheffieldamrc.co.uk/blockchain-systems\n\n\n## Metadata\n\n\n- **Migration Status**: Ontology block enriched on 2025-11-12\n- **Last Updated**: 2025-11-12\n- **Review Status**: Comprehensive editorial review\n- **Verification**: Academic sources verified\n- **Regional Context**: UK/North England where applicable",
  "properties": {
    "id": "bc-0440-blockchain-interoperability-ontology",
    "collapsed": "true",
    "- ontology": "true",
    "- term-id": "BC-0440",
    "- preferred-term": "Blockchain Interoperability",
    "- source-domain": "metaverse",
    "- status": "stub-needs-content",
    "- public-access": "true",
    "- content-status": "minimal-placeholder-requires-authoring",
    "- definition": "A component of the blockchain ecosystem.",
    "- maturity": "draft",
    "- owl:class": "bc:BlockchainInteroperability",
    "- owl:physicality": "ConceptualEntity",
    "- owl:role": "Concept",
    "- belongsToDomain": "[[BlockchainDomain]]"
  },
  "backlinks": [],
  "wiki_links": [
    "BlockchainDomain"
  ],
  "ontology": {
    "term_id": "BC-0440",
    "preferred_term": "Blockchain Interoperability",
    "definition": "A component of the blockchain ecosystem.",
    "source_domain": "metaverse",
    "maturity_level": null,
    "authority_score": null
  }
}