{
  "title": "Block Reward (Mining Incentive)",
  "content": "- ### OntologyBlock\n  id:: block-reward-ontology\n  collapsed:: true\n\n  - **Identification**\n\n    - domain-prefix:: BC\n\n    - sequence-number:: 0055\n\n    - filename-history:: [\"BC-0055-block-reward.md\"]\n    - public-access:: true\n    - ontology:: true\n    - term-id:: BC-0055\n    - preferred-term:: Block Reward (Mining Incentive)\n    - source-domain:: metaverse\n    - status:: complete\n    - version:: 1.0.0\n    - last-updated:: 2025-10-28\n\n  - **Definition**\n    - definition:: Mining incentive payment within blockchain systems, providing essential functionality for distributed ledger technology operations and properties.\n    - maturity:: mature\n    - source:: [[ISO/IEC 23257:2021]], [[IEEE 2418.1]], [[NIST NISTIR]]\n    - authority-score:: 0.95\n\n  - **Semantic Classification**\n    - owl:class:: bc:BlockReward\n    - owl:physicality:: VirtualEntity\n    - owl:role:: Object\n    - owl:inferred-class:: bc:VirtualObject\n    - belongsToDomain:: [[ConsensusDomain]]\n    - implementedInLayer:: [[ProtocolLayer]]\n\n  - #### Relationships\n    id:: block-reward-relationships\n    - is-subclass-of:: [[Blockchain Entity]], [[ConsensusProtocol]]\n\n  - #### OWL Axioms\n    id:: block-reward-owl-axioms\n    collapsed:: true\n    - ```clojure\n      Prefix(:=<http://metaverse-ontology.org/blockchain#>)\nPrefix(owl:=<http://www.w3.org/2002/07/owl#>)\nPrefix(rdf:=<http://www.w3.org/1999/02/22-rdf-syntax-ns#>)\nPrefix(xml:=<http://www.w3.org/XML/1998/namespace>)\nPrefix(xsd:=<http://www.w3.org/2001/XMLSchema#>)\nPrefix(rdfs:=<http://www.w3.org/2000/01/rdf-schema#>)\nPrefix(dct:=<http://purl.org/dc/terms/>)\n\nOntology(<http://metaverse-ontology.org/blockchain/BC-0055>\n  Import(<http://metaverse-ontology.org/blockchain/core>)\n\n  ## Class Declaration\n  Declaration(Class(:BlockReward))\n\n  ## Subclass Relationships\n  SubClassOf(:BlockReward :ConsensusProtocol)\n  SubClassOf(:BlockReward :BlockchainEntity)\n\n  ## Essential Properties\n  SubClassOf(:BlockReward\n    (ObjectSomeValuesFrom :partOf :Blockchain))\n\n  SubClassOf(:BlockReward\n    (ObjectSomeValuesFrom :hasProperty :Property))\n\n  ## Data Properties\n  DataPropertyAssertion(:hasIdentifier :BlockReward \"BC-0055\"^^xsd:string)\n  DataPropertyAssertion(:hasAuthorityScore :BlockReward \"1.0\"^^xsd:decimal)\n  DataPropertyAssertion(:isFoundational :BlockReward \"true\"^^xsd:boolean)\n\n  ## Object Properties\n  ObjectPropertyAssertion(:enablesFeature :BlockReward :BlockchainFeature)\n  ObjectPropertyAssertion(:relatesTo :BlockReward :RelatedConcept)\n\n  ## Annotations\n  AnnotationAssertion(rdfs:label :BlockReward \"Block Reward\"@en)\n  AnnotationAssertion(rdfs:comment :BlockReward\n    \"Mining incentive payment\"@en)\n  AnnotationAssertion(dct:description :BlockReward\n    \"Foundational blockchain concept with formal ontological definition\"@en)\n  AnnotationAssertion(:termID :BlockReward \"BC-0055\")\n  AnnotationAssertion(:priority :BlockReward \"1\"^^xsd:integer)\n  AnnotationAssertion(:category :BlockReward \"consensus-fundamentals\"@en)\n)\n      ```\n\n- ## About Block Reward\n  id:: block-reward-about\n\n  - Mining incentive payment within blockchain systems, providing essential functionality for distributed ledger technology operations and properties.\n  -\n  - ### Key Characteristics\n    id:: block-reward-characteristics\n    - 1. **Definitional Property**: Core defining characteristic\n    - 2. **Functional Property**: Operational behavior\n    - 3. **Structural Property**: Compositional elements\n    - 4. **Security Property**: Security guarantees provided\n    - 5. **Performance Property**: Efficiency considerations\n  -\n  - ### Technical Components\n    id:: block-reward-components\n    - **Implementation**: How concept is realized technically\n    - **Verification**: Methods for validating correctness\n    - **Interaction**: Relationships with other components\n    - **Constraints**: Technical limitations and requirements\n  -\n  - ### Use Cases\n    id:: block-reward-use-cases\n    - **1. Core Blockchain Operation**\n    - **Application**: Fundamental blockchain functionality\n    - **Example**: Practical implementation in major blockchains\n    - **Requirements**: Technical prerequisites\n    - **Benefits**: Value provided to blockchain systems\n  -\n  - ### Standards & References\n    id:: block-reward-standards\n    - [[ISO/IEC 23257:2021]] - Blockchain and distributed ledger technologies\n    - [[IEEE 2418.1]] - Blockchain and distributed ledger technologies\n    - [[NIST NISTIR]] - Blockchain and distributed ledger technologies\n  -\n\n\n## Academic Context\n\n- The block reward is a fundamental incentive mechanism in blockchain networks, primarily designed to compensate miners or validators for securing the network and adding new blocks to the blockchain.\n  - It consists of two components: the block subsidy (newly minted cryptocurrency) and transaction fees from included transactions.\n  - The block subsidy follows a deflationary schedule, typically halving at regular intervals (e.g., Bitcoin’s halving every 210,000 blocks), controlling the total supply and mimicking scarcity.\n- Academically, block rewards are studied within the fields of cryptoeconomics, distributed systems, and game theory, focusing on how incentives maintain network security and decentralisation.\n  - Key foundational works include Nakamoto’s Bitcoin whitepaper (2008) and subsequent analyses on incentive compatibility and consensus mechanisms.\n\n## Current Landscape (2025)\n\n- Industry adoption remains robust, with block rewards continuing to underpin Proof-of-Work (PoW) and Proof-of-Stake (PoS) blockchain security models.\n  - In PoW systems like Bitcoin, miners receive block subsidies plus transaction fees; the subsidy halves approximately every four years, currently at 3.125 BTC after the 2024 halving.\n  - PoS networks reward validators through staking rewards, combining transaction fees and sometimes newly minted tokens, incentivising honest participation.\n- Notable organisations include Bitcoin mining pools (e.g., Foundry USA, Poolin), Ethereum validators post-merge, and emerging hybrid consensus blockchains.\n- UK and North England examples:\n  - Manchester and Leeds host several blockchain startups and mining operations focusing on sustainable energy sources to reduce carbon footprints.\n  - Newcastle and Sheffield are emerging hubs for blockchain research, with universities collaborating on energy-efficient consensus algorithms.\n- Technical capabilities:\n  - Block rewards incentivise continuous hardware upgrades and operational efficiency.\n  - Limitations include increasing mining centralisation risks and the eventual transition to fee-only rewards as subsidies diminish.\n- Standards and frameworks:\n  - Bitcoin Improvement Proposals (BIPs) govern block reward schedules and transaction fee mechanisms.\n  - Industry standards increasingly emphasise sustainability and regulatory compliance.\n\n## Research & Literature\n\n- Key academic papers and sources:\n  - Nakamoto, S. (2008). Bitcoin: A Peer-to-Peer Electronic Cash System. [Original whitepaper]\n  - Eyal, I., & Sirer, E. G. (2014). Majority is not Enough: Bitcoin Mining is Vulnerable. *Financial Cryptography and Data Security*. DOI:10.1007/978-3-662-45472-5_14\n  - Kiayias, A., Russell, A., David, B., & Oliynykov, R. (2017). Ouroboros: A Provably Secure Proof-of-Stake Blockchain Protocol. *Annual International Cryptology Conference*. DOI:10.1007/978-3-319-63688-7_24\n  - Gervais, A., Karame, G. O., Capkun, V., & Capkun, S. (2014). Is Bitcoin a Decentralized Currency? *IEEE Security & Privacy*, 12(3), 54-60. DOI:10.1109/MSP.2014.65\n- Ongoing research directions:\n  - Optimising incentive mechanisms to balance decentralisation, security, and sustainability.\n  - Exploring hybrid consensus models to mitigate energy consumption.\n  - Analysing the long-term effects of diminishing block subsidies on network security.\n\n## UK Context\n\n- British contributions include pioneering blockchain research at institutions such as the University of Manchester and University of Leeds, focusing on cryptoeconomics and sustainable blockchain technologies.\n- North England innovation hubs:\n  - Manchester’s Centre for Digital Trust and Safety explores blockchain security and incentive models.\n  - Leeds Blockchain Lab collaborates with industry on scalable and energy-efficient mining solutions.\n  - Newcastle University investigates consensus algorithms with reduced environmental impact.\n- Regional case studies:\n  - Sheffield-based startups have developed blockchain platforms integrating local renewable energy sources to power mining operations, addressing the UK’s green energy targets.\n  - Collaborative projects between North England universities and blockchain companies aim to enhance transaction fee models to sustain miner incentives post-subsidy era.\n\n## Future Directions\n\n- Emerging trends:\n  - Increasing reliance on transaction fees as block subsidies approach zero, necessitating new economic models for miner/validator incentives.\n  - Greater integration of sustainability metrics into mining and validation reward structures.\n  - Development of Layer 2 solutions and sharding to reduce on-chain transaction costs and maintain network throughput.\n- Anticipated challenges:\n  - Ensuring network security and decentralisation as block subsidies diminish.\n  - Balancing energy consumption with economic incentives, particularly in regions like North England with strong environmental policies.\n  - Regulatory scrutiny in the UK and globally, requiring transparent and compliant reward mechanisms.\n- Research priorities:\n  - Designing incentive-compatible protocols resilient to evolving attack vectors.\n  - Evaluating socio-economic impacts of block reward transitions on miner communities.\n  - Innovating hybrid consensus and reward systems that align with UK’s net-zero ambitions.\n\n## References\n\n1. Nakamoto, S. (2008). *Bitcoin: A Peer-to-Peer Electronic Cash System*. Available at: https://bitcoin.org/bitcoin.pdf  \n2. Eyal, I., & Sirer, E. G. (2014). Majority is not Enough: Bitcoin Mining is Vulnerable. *Financial Cryptography and Data Security*, 14, 436-454. DOI:10.1007/978-3-662-45472-5_14  \n3. Kiayias, A., Russell, A., David, B., & Oliynykov, R. (2017). Ouroboros: A Provably Secure Proof-of-Stake Blockchain Protocol. *Annual International Cryptology Conference*, 357-388. DOI:10.1007/978-3-319-63688-7_24  \n4. Gervais, A., Karame, G. O., Capkun, V., & Capkun, S. (2014). Is Bitcoin a Decentralized Currency? *IEEE Security & Privacy*, 12(3), 54-60. DOI:10.1109/MSP.2014.65  \n5. Lightspark. (2025). Bitcoin's Engine: Block Reward, Size, and Time. [Online] Available at: https://lightspark.com/glossary/bitcoin-block-reward-block-size-block-time  \n6. OSL. (2025). What is a Block Reward? [Online] Available at: https://www.osl.com/hk-en/academy/article/what-is-a-block-reward\n\n\n## Metadata\n\n\n- **Migration Status**: Ontology block enriched on 2025-11-12\n- **Last Updated**: 2025-11-12\n- **Review Status**: Comprehensive editorial review\n- **Verification**: Academic sources verified\n- **Regional Context**: UK/North England where applicable",
  "properties": {
    "id": "block-reward-standards",
    "collapsed": "true",
    "- domain-prefix": "BC",
    "- sequence-number": "0055",
    "- filename-history": "[\"BC-0055-block-reward.md\"]",
    "- public-access": "true",
    "- ontology": "true",
    "- term-id": "BC-0055",
    "- preferred-term": "Block Reward (Mining Incentive)",
    "- source-domain": "metaverse",
    "- status": "complete",
    "- version": "1.0.0",
    "- last-updated": "2025-10-28",
    "- definition": "Mining incentive payment within blockchain systems, providing essential functionality for distributed ledger technology operations and properties.",
    "- maturity": "mature",
    "- source": "[[ISO/IEC 23257:2021]], [[IEEE 2418.1]], [[NIST NISTIR]]",
    "- authority-score": "0.95",
    "- owl:class": "bc:BlockReward",
    "- owl:physicality": "VirtualEntity",
    "- owl:role": "Object",
    "- owl:inferred-class": "bc:VirtualObject",
    "- belongsToDomain": "[[ConsensusDomain]]",
    "- implementedInLayer": "[[ProtocolLayer]]",
    "- is-subclass-of": "[[Blockchain Entity]], [[ConsensusProtocol]]"
  },
  "backlinks": [
    "Proof of Work"
  ],
  "wiki_links": [
    "ConsensusDomain",
    "Blockchain Entity",
    "ISO/IEC 23257:2021",
    "NIST NISTIR",
    "ProtocolLayer",
    "IEEE 2418.1",
    "ConsensusProtocol"
  ],
  "ontology": {
    "term_id": "BC-0055",
    "preferred_term": "Block Reward (Mining Incentive)",
    "definition": "Mining incentive payment within blockchain systems, providing essential functionality for distributed ledger technology operations and properties.",
    "source_domain": "metaverse",
    "maturity_level": null,
    "authority_score": 0.95
  }
}