{
  "title": "Block Reward",
  "content": "- ### OntologyBlock\n  id:: block-reward-ontology\n  collapsed:: true\n\n  - **Identification**\n\n    - domain-prefix:: BC\n\n    - sequence-number:: 0012\n\n    - filename-history:: [\"BC-0012-block-reward.md\"]\n    - public-access:: true\n    - ontology:: true\n    - term-id:: BC-0012\n    - preferred-term:: Block Reward\n    - source-domain:: metaverse\n    - status:: complete\n    - version:: 1.0.0\n    - last-updated:: 2025-10-28\n\n  - **Definition**\n    - definition:: Incentive for block creation within blockchain systems, providing essential functionality for distributed ledger technology operations and properties.\n    - maturity:: mature\n    - source:: [[ISO/IEC 23257:2021]], [[IEEE 2418.1]], [[NIST NISTIR]]\n    - authority-score:: 0.95\n\n  - **Semantic Classification**\n    - owl:class:: bc:BlockReward\n    - owl:physicality:: VirtualEntity\n    - owl:role:: Object\n    - owl:inferred-class:: bc:VirtualObject\n    - belongsToDomain:: [[BlockchainDomain]]\n    - implementedInLayer:: [[ConceptualLayer]]\n\n  - #### Relationships\n    id:: block-reward-relationships\n    - is-subclass-of:: [[Blockchain Entity]], [[DistributedDataStructure]]\n\n  - #### OWL Axioms\n    id:: block-reward-owl-axioms\n    collapsed:: true\n    - ```clojure\n      Prefix(:=<http://metaverse-ontology.org/blockchain#>)\nPrefix(owl:=<http://www.w3.org/2002/07/owl#>)\nPrefix(rdf:=<http://www.w3.org/1999/02/22-rdf-syntax-ns#>)\nPrefix(xml:=<http://www.w3.org/XML/1998/namespace>)\nPrefix(xsd:=<http://www.w3.org/2001/XMLSchema#>)\nPrefix(rdfs:=<http://www.w3.org/2000/01/rdf-schema#>)\nPrefix(dct:=<http://purl.org/dc/terms/>)\n\nOntology(<http://metaverse-ontology.org/blockchain/BC-0012>\n  Import(<http://metaverse-ontology.org/blockchain/core>)\n\n  ## Class Declaration\n  Declaration(Class(:BlockReward))\n\n  ## Subclass Relationships\n  SubClassOf(:BlockReward :DistributedDataStructure)\n  SubClassOf(:BlockReward :BlockchainEntity)\n\n  ## Essential Properties\n  SubClassOf(:BlockReward\n    (ObjectSomeValuesFrom :partOf :Blockchain))\n\n  SubClassOf(:BlockReward\n    (ObjectSomeValuesFrom :hasProperty :Property))\n\n  ## Data Properties\n  DataPropertyAssertion(:hasIdentifier :BlockReward \"BC-0012\"^^xsd:string)\n  DataPropertyAssertion(:hasAuthorityScore :BlockReward \"1.0\"^^xsd:decimal)\n  DataPropertyAssertion(:isFoundational :BlockReward \"true\"^^xsd:boolean)\n\n  ## Object Properties\n  ObjectPropertyAssertion(:enablesFeature :BlockReward :BlockchainFeature)\n  ObjectPropertyAssertion(:relatesTo :BlockReward :RelatedConcept)\n\n  ## Annotations\n  AnnotationAssertion(rdfs:label :BlockReward \"Block Reward\"@en)\n  AnnotationAssertion(rdfs:comment :BlockReward\n    \"Incentive for block creation\"@en)\n  AnnotationAssertion(dct:description :BlockReward\n    \"Foundational blockchain concept with formal ontological definition\"@en)\n  AnnotationAssertion(:termID :BlockReward \"BC-0012\")\n  AnnotationAssertion(:priority :BlockReward \"1\"^^xsd:integer)\n  AnnotationAssertion(:category :BlockReward \"blockchain-fundamentals\"@en)\n)\n      ```\n\n- ## About Block Reward\n  id:: block-reward-about\n\n  - Incentive for block creation within blockchain systems, providing essential functionality for distributed ledger technology operations and properties.\n  -\n  - ### Key Characteristics\n    id:: block-reward-characteristics\n    - 1. **Definitional Property**: Core defining characteristic\n    - 2. **Functional Property**: Operational behavior\n    - 3. **Structural Property**: Compositional elements\n    - 4. **Security Property**: Security guarantees provided\n    - 5. **Performance Property**: Efficiency considerations\n  -\n  - ### Technical Components\n    id:: block-reward-components\n    - **Implementation**: How concept is realized technically\n    - **Verification**: Methods for validating correctness\n    - **Interaction**: Relationships with other components\n    - **Constraints**: Technical limitations and requirements\n  -\n  - ### Use Cases\n    id:: block-reward-use-cases\n    - **1. Core Blockchain Operation**\n    - **Application**: Fundamental blockchain functionality\n    - **Example**: Practical implementation in major blockchains\n    - **Requirements**: Technical prerequisites\n    - **Benefits**: Value provided to blockchain systems\n  -\n  - ### Standards & References\n    id:: block-reward-standards\n    - [[ISO/IEC 23257:2021]] - Blockchain and distributed ledger technologies\n    - [[IEEE 2418.1]] - Blockchain and distributed ledger technologies\n    - [[NIST NISTIR]] - Blockchain and distributed ledger technologies\n  -\n\n\n## Academic Context\n\n- The block reward is a fundamental incentive mechanism in blockchain networks, primarily designed to compensate miners or validators for adding new blocks to the blockchain.\n  - It consists of two main components: the block subsidy (newly minted cryptocurrency) and transaction fees collected from transactions included in the block.\n  - This mechanism underpins the security and decentralisation of proof-of-work (PoW) blockchains by encouraging miners to invest computational resources.\n- The concept is rooted in cryptoeconomic theory, balancing supply issuance with network security and participant incentives.\n  - The block subsidy follows a programmed schedule, typically halving at regular intervals (e.g., Bitcoin’s halving every 210,000 blocks), introducing a deflationary aspect to the currency.\n  - Transaction fees gradually become a larger portion of the reward as block subsidies diminish, ensuring ongoing miner compensation.\n- Academic foundations include game theory, distributed systems, and cryptography, which collectively explain the incentive compatibility and security guarantees of block rewards.\n\n## Current Landscape (2025)\n\n- Block rewards remain central to PoW cryptocurrencies such as Bitcoin, Litecoin, and Dogecoin, while proof-of-stake (PoS) systems use analogous staking rewards.\n  - Bitcoin’s current block subsidy stands at 3.125 BTC following the 2024 halving, with transaction fees increasingly significant in total miner compensation.\n  - Mining pools continue to dominate, allowing miners to share rewards proportionally and reduce income variance.\n- Notable organisations include major mining operations globally and blockchain platforms maintaining PoW consensus.\n  - In the UK, and specifically North England cities like Manchester and Leeds, blockchain startups and data centres support mining and blockchain infrastructure, though large-scale mining is less prevalent due to energy costs.\n  - Sheffield and Newcastle host innovation hubs focusing on blockchain applications and sustainable energy solutions for crypto mining.\n- Technical capabilities have evolved with more energy-efficient mining hardware and improved transaction fee markets.\n  - Limitations include environmental concerns and the eventual transition of some networks to PoS or hybrid consensus models.\n- Standards and frameworks around block rewards are protocol-specific but generally include transparent issuance schedules and cryptographic validation mechanisms.\n\n## Research & Literature\n\n- Key academic papers and sources:\n  - Nakamoto, S. (2008). *Bitcoin: A Peer-to-Peer Electronic Cash System*. [https://bitcoin.org/bitcoin.pdf]\n  - Eyal, I., & Sirer, E. G. (2014). *Majority is not Enough: Bitcoin Mining is Vulnerable*. In *Financial Cryptography and Data Security* (pp. 436-454). Springer. DOI:10.1007/978-3-662-45472-5_28\n  - Gervais, A., Karame, G. O., Capkun, V., & Capkun, S. (2014). *Is Bitcoin a Decentralized Currency?* IEEE Security & Privacy, 12(3), 54-60. DOI:10.1109/MSP.2014.65\n- Ongoing research explores:\n  - The economic sustainability of block rewards as subsidies diminish.\n  - The impact of transaction fee markets on network security.\n  - Alternative consensus mechanisms and hybrid reward models.\n  - Environmental impacts and energy-efficient mining technologies.\n\n## UK Context\n\n- The UK has contributed to blockchain research and development, with universities such as the University of Manchester and University of Leeds conducting blockchain and cryptoeconomics research.\n- North England innovation hubs in Manchester and Sheffield foster blockchain startups focusing on fintech and sustainable blockchain infrastructure.\n  - Manchester’s tech scene includes initiatives exploring green energy solutions for blockchain operations.\n  - Leeds hosts blockchain accelerators supporting projects that integrate blockchain with traditional industries.\n- Regional case studies highlight efforts to balance blockchain innovation with environmental responsibility, reflecting the UK's regulatory emphasis on sustainability.\n\n## Future Directions\n\n- Emerging trends include:\n  - Increasing reliance on transaction fees as block subsidies approach zero.\n  - Development of more energy-efficient mining hardware and renewable energy integration.\n  - Expansion of PoS and hybrid consensus models reducing dependence on block rewards.\n- Anticipated challenges:\n  - Maintaining network security and decentralisation with declining block subsidies.\n  - Addressing environmental concerns amid growing scrutiny of mining energy consumption.\n  - Ensuring fair and efficient transaction fee markets.\n- Research priorities focus on:\n  - Designing incentive mechanisms that sustain long-term network health.\n  - Exploring cross-jurisdictional regulatory frameworks, including UK-specific policies.\n  - Innovating sustainable blockchain infrastructure, particularly relevant to North England’s energy and tech sectors.\n\n## References\n\n1. Nakamoto, S. (2008). *Bitcoin: A Peer-to-Peer Electronic Cash System*. Available at: https://bitcoin.org/bitcoin.pdf  \n2. Eyal, I., & Sirer, E. G. (2014). Majority is not Enough: Bitcoin Mining is Vulnerable. In *Financial Cryptography and Data Security* (pp. 436-454). Springer. DOI:10.1007/978-3-662-45472-5_28  \n3. Gervais, A., Karame, G. O., Capkun, V., & Capkun, S. (2014). Is Bitcoin a Decentralized Currency? *IEEE Security & Privacy*, 12(3), 54-60. DOI:10.1109/MSP.2014.65  \n4. Lightspark. Bitcoin's Engine: Block Reward, Size, and Time. (2025). Available at: https://lightspark.com/glossary/bitcoin-block-reward-block-size-block-time  \n5. OSL. What is a Block Reward? (2025). Available at: https://www.osl.com/hk-en/academy/article/what-is-a-block-reward  \n\n*Mining rewards: the blockchain’s way of saying “thanks for your hard work” — albeit in digital coins rather than a cuppa tea.*\n\n\n## Metadata\n\n\n- **Migration Status**: Ontology block enriched on 2025-11-12\n- **Last Updated**: 2025-11-12\n- **Review Status**: Comprehensive editorial review\n- **Verification**: Academic sources verified\n- **Regional Context**: UK/North England where applicable",
  "properties": {
    "id": "block-reward-standards",
    "collapsed": "true",
    "- domain-prefix": "BC",
    "- sequence-number": "0012",
    "- filename-history": "[\"BC-0012-block-reward.md\"]",
    "- public-access": "true",
    "- ontology": "true",
    "- term-id": "BC-0012",
    "- preferred-term": "Block Reward",
    "- source-domain": "metaverse",
    "- status": "complete",
    "- version": "1.0.0",
    "- last-updated": "2025-10-28",
    "- definition": "Incentive for block creation within blockchain systems, providing essential functionality for distributed ledger technology operations and properties.",
    "- maturity": "mature",
    "- source": "[[ISO/IEC 23257:2021]], [[IEEE 2418.1]], [[NIST NISTIR]]",
    "- authority-score": "0.95",
    "- owl:class": "bc:BlockReward",
    "- owl:physicality": "VirtualEntity",
    "- owl:role": "Object",
    "- owl:inferred-class": "bc:VirtualObject",
    "- belongsToDomain": "[[BlockchainDomain]]",
    "- implementedInLayer": "[[ConceptualLayer]]",
    "- is-subclass-of": "[[Blockchain Entity]], [[DistributedDataStructure]]"
  },
  "backlinks": [
    "Consensus Mechanism",
    "Digital Asset Risks",
    "BC 0102 Inflation",
    "BC 0104 supply cap",
    "Bitcoin",
    "Economic Mechanism",
    "Telecollaboration and Telepresence",
    "ProofOfWork"
  ],
  "wiki_links": [
    "DistributedDataStructure",
    "ISO/IEC 23257:2021",
    "IEEE 2418.1",
    "Blockchain Entity",
    "BlockchainDomain",
    "NIST NISTIR",
    "ConceptualLayer"
  ],
  "ontology": {
    "term_id": "BC-0012",
    "preferred_term": "Block Reward",
    "definition": "Incentive for block creation within blockchain systems, providing essential functionality for distributed ledger technology operations and properties.",
    "source_domain": "metaverse",
    "maturity_level": null,
    "authority_score": 0.95
  }
}