{
  "title": "Block Size",
  "content": "- ### OntologyBlock\n  id:: block-size-ontology\n  collapsed:: true\n\n  - **Identification**\n\n    - domain-prefix:: BC\n\n    - sequence-number:: 0013\n\n    - filename-history:: [\"BC-0013-block-size.md\"]\n    - public-access:: true\n    - ontology:: true\n    - term-id:: BC-0013\n    - preferred-term:: Block Size\n    - source-domain:: blockchain\n    - status:: complete\n    - version:: 1.0.0\n    - last-updated:: 2025-10-28\n\n  - **Definition**\n    - definition:: Data capacity limit of a block within blockchain systems, providing essential functionality for distributed ledger technology operations and properties.\n    - maturity:: mature\n    - source:: [[ISO/IEC 23257:2021]], [[IEEE 2418.1]], [[NIST NISTIR]]\n    - authority-score:: 0.95\n\n  - **Semantic Classification**\n    - owl:class:: bc:BlockSize\n    - owl:physicality:: VirtualEntity\n    - owl:role:: Object\n    - owl:inferred-class:: bc:VirtualObject\n    - belongsToDomain:: [[BlockchainDomain]]\n    - implementedInLayer:: [[ConceptualLayer]]\n\n  - #### Relationships\n    id:: block-size-relationships\n    - is-subclass-of:: [[Blockchain Entity]], [[DistributedDataStructure]]\n\n  - #### OWL Axioms\n    id:: block-size-owl-axioms\n    collapsed:: true\n    - ```clojure\n      Prefix(:=<http://metaverse-ontology.org/blockchain#>)\nPrefix(owl:=<http://www.w3.org/2002/07/owl#>)\nPrefix(rdf:=<http://www.w3.org/1999/02/22-rdf-syntax-ns#>)\nPrefix(xml:=<http://www.w3.org/XML/1998/namespace>)\nPrefix(xsd:=<http://www.w3.org/2001/XMLSchema#>)\nPrefix(rdfs:=<http://www.w3.org/2000/01/rdf-schema#>)\nPrefix(dct:=<http://purl.org/dc/terms/>)\n\nOntology(<http://metaverse-ontology.org/blockchain/BC-0013>\n  Import(<http://metaverse-ontology.org/blockchain/core>)\n\n  ## Class Declaration\n  Declaration(Class(:BlockSize))\n\n  ## Subclass Relationships\n  SubClassOf(:BlockSize :DistributedDataStructure)\n  SubClassOf(:BlockSize :BlockchainEntity)\n\n  ## Essential Properties\n  SubClassOf(:BlockSize\n    (ObjectSomeValuesFrom :partOf :Blockchain))\n\n  SubClassOf(:BlockSize\n    (ObjectSomeValuesFrom :hasProperty :Property))\n\n  ## Data Properties\n  DataPropertyAssertion(:hasIdentifier :BlockSize \"BC-0013\"^^xsd:string)\n  DataPropertyAssertion(:hasAuthorityScore :BlockSize \"1.0\"^^xsd:decimal)\n  DataPropertyAssertion(:isFoundational :BlockSize \"true\"^^xsd:boolean)\n\n  ## Object Properties\n  ObjectPropertyAssertion(:enablesFeature :BlockSize :BlockchainFeature)\n  ObjectPropertyAssertion(:relatesTo :BlockSize :RelatedConcept)\n\n  ## Annotations\n  AnnotationAssertion(rdfs:label :BlockSize \"Block Size\"@en)\n  AnnotationAssertion(rdfs:comment :BlockSize\n    \"Data capacity limit of a block\"@en)\n  AnnotationAssertion(dct:description :BlockSize\n    \"Foundational blockchain concept with formal ontological definition\"@en)\n  AnnotationAssertion(:termID :BlockSize \"BC-0013\")\n  AnnotationAssertion(:priority :BlockSize \"1\"^^xsd:integer)\n  AnnotationAssertion(:category :BlockSize \"blockchain-fundamentals\"@en)\n)\n      ```\n\n- ## About Block Size\n  id:: block-size-about\n\n  - Data capacity limit of a block within blockchain systems, providing essential functionality for distributed ledger technology operations and properties.\n  -\n  - ### Key Characteristics\n    id:: block-size-characteristics\n    - 1. **Definitional Property**: Core defining characteristic\n    - 2. **Functional Property**: Operational behavior\n    - 3. **Structural Property**: Compositional elements\n    - 4. **Security Property**: Security guarantees provided\n    - 5. **Performance Property**: Efficiency considerations\n  -\n  - ### Technical Components\n    id:: block-size-components\n    - **Implementation**: How concept is realized technically\n    - **Verification**: Methods for validating correctness\n    - **Interaction**: Relationships with other components\n    - **Constraints**: Technical limitations and requirements\n  -\n  - ### Use Cases\n    id:: block-size-use-cases\n    - **1. Core Blockchain Operation**\n    - **Application**: Fundamental blockchain functionality\n    - **Example**: Practical implementation in major blockchains\n    - **Requirements**: Technical prerequisites\n    - **Benefits**: Value provided to blockchain systems\n  -\n  - ### Standards & References\n    id:: block-size-standards\n    - [[ISO/IEC 23257:2021]] - Blockchain and distributed ledger technologies\n    - [[IEEE 2418.1]] - Blockchain and distributed ledger technologies\n    - [[NIST NISTIR]] - Blockchain and distributed ledger technologies\n  -\n\n\t- ## Market Awareness\n\t\t- **Target Market**: Creative industry, specifically museums, exhibitions, and immersive experience centers\n\t\t- **Market Size**: Estimated to be worth upwards of £200 million\n\n\t- ## Market Awareness\n\t\t- **Target Market**: Creative industry, specifically museums, exhibitions, and immersive experience centers\n\t\t- **Market Size**: Estimated to be worth upwards of £200 million\n\n\n## Academic Context\n\n- Brief contextual overview\n\t- Block size refers to the maximum amount of transaction data that can be stored within a single block of a blockchain\n\t- It is a foundational parameter influencing throughput, decentralisation, and network security\n\t- The concept emerged with Bitcoin but is now a core consideration across all blockchain architectures\n\n- Key developments and current state\n\t- Early blockchains like Bitcoin used fixed block size limits, but modern protocols often employ dynamic or weight-based limits\n\t- The debate over optimal block size remains active, balancing scalability against decentralisation and security\n\n- Academic foundations\n\t- The block size limit is a direct consequence of the trade-off between transaction throughput and network resilience\n\t- Research in distributed systems and cryptography underpins the design choices seen in contemporary blockchains\n\n## Current Landscape (2025)\n\n- Industry adoption and implementations\n\t- Most major blockchains have moved beyond simple fixed block size limits\n\t- Bitcoin uses a block weight limit of 4 million weight units, allowing for a theoretical maximum block size of 4 MB, though practical sizes are typically around 2 MB\n\t- Ethereum employs a gas limit per block, dynamically adjusting the amount of computation and data that can be processed\n\t- Alternative blockchains such as Litecoin and Dogecoin have different block size and block time parameters to optimise for specific use cases\n\n- Notable organisations and platforms\n\t- Bitstamp, Coinbase, and Yellow Card provide educational resources and trading platforms that reflect current block size practices\n\t- Academic and industry collaborations in the UK, including the University of Manchester and Leeds Beckett University, contribute to blockchain research and development\n\n- UK and North England examples where relevant\n\t- The University of Manchester’s Blockchain Research Group explores scalability solutions, including block size optimisation\n\t- Leeds Beckett University’s Centre for Digital Innovation has projects focused on blockchain applications in supply chain and finance\n\t- Newcastle University’s School of Computing Science investigates the impact of block size on network performance and security\n\n- Technical capabilities and limitations\n\t- Larger block sizes can increase transaction throughput but may lead to stales and temporary chain splits\n\t- Smaller block sizes enhance network resilience but can result in slower transaction processing and higher fees\n\t- Dynamic block size limits and weight-based systems offer a middle ground, balancing scalability and security\n\n- Standards and frameworks\n\t- The Bitcoin Improvement Proposal (BIP) process governs changes to block size and other parameters\n\t- Ethereum’s EIP (Ethereum Improvement Proposal) process similarly manages gas limit and block size adjustments\n\t- Industry standards such as the Blockchain Interoperability Alliance promote best practices for block size and other technical parameters\n\n## Research & Literature\n\n- Key academic papers and sources\n\t- Nakamoto, S. (2008). Bitcoin: A Peer-to-Peer Electronic Cash System. *Cryptology ePrint Archive*. https://eprint.iacr.org/2008/424\n\t- Decker, C., & Wattenhofer, R. (2013). Information Propagation in the Bitcoin Network. *IEEE P2P 2013 Proceedings*. https://doi.org/10.1109/P2P.2013.6688704\n\t- Eyal, I., & Sirer, E. G. (2014). Majority is not Enough: Bitcoin Mining is Vulnerable. *Financial Cryptography and Data Security*. https://doi.org/10.1007/978-3-662-45472-5_28\n\t- Sompolinsky, Y., & Zohar, A. (2015). Secure High-Rate Transaction Processing in Bitcoin. *Financial Cryptography and Data Security*. https://doi.org/10.1007/978-3-662-47854-7_37\n\n- Ongoing research directions\n\t- Optimising block size for different blockchain use cases\n\t- Investigating the impact of block size on network performance and security\n\t- Exploring dynamic and adaptive block size limits\n\n## UK Context\n\n- British contributions and implementations\n\t- The UK has a vibrant blockchain research community, with significant contributions from universities and industry\n\t- The National Cyber Security Centre (NCSC) provides guidance on blockchain security, including block size considerations\n\n- North England innovation hubs (if relevant)\n\t- Manchester, Leeds, Newcastle, and Sheffield are home to several blockchain innovation hubs and research centres\n\t- These hubs collaborate on projects that explore the practical implications of block size and other blockchain parameters\n\n- Regional case studies\n\t- The University of Manchester’s Blockchain Research Group has conducted studies on the impact of block size on transaction throughput and network resilience\n\t- Leeds Beckett University’s Centre for Digital Innovation has developed blockchain solutions for supply chain management, optimising block size for efficiency\n\n## Future Directions\n\n- Emerging trends and developments\n\t- Continued exploration of dynamic and adaptive block size limits\n\t- Integration of machine learning and AI to optimise block size in real-time\n\t- Increased focus on interoperability and standardisation across different blockchain platforms\n\n- Anticipated challenges\n\t- Balancing scalability with decentralisation and security\n\t- Addressing the potential for stales and temporary chain splits with larger block sizes\n\t- Ensuring that block size changes do not compromise network integrity\n\n- Research priorities\n\t- Developing robust models for predicting the impact of block size changes\n\t- Investigating the long-term effects of different block size strategies on network performance\n\t- Exploring the role of block size in emerging blockchain applications such as DeFi and NFTs\n\n## References\n\n1. Nakamoto, S. (2008). Bitcoin: A Peer-to-Peer Electronic Cash System. *Cryptology ePrint Archive*. https://eprint.iacr.org/2008/424\n2. Decker, C., & Wattenhofer, R. (2013). Information Propagation in the Bitcoin Network. *IEEE P2P 2013 Proceedings*. https://doi.org/10.1109/P2P.2013.6688704\n3. Eyal, I., & Sirer, E. G. (2014). Majority is not Enough: Bitcoin Mining is Vulnerable. *Financial Cryptography and Data Security*. https://doi.org/10.1007/978-3-662-45472-5_28\n4. Sompolinsky, Y., & Zohar, A. (2015). Secure High-Rate Transaction Processing in Bitcoin. *Financial Cryptography and Data Security*. https://doi.org/10.1007/978-3-662-47854-7_37\n5. Bitstamp. (2025). What is block size? https://www.bitstamp.net/en-gb/learn/crypto-101/what-is-block-size/\n6. Bitcoin Magazine. (2025). What Is The Bitcoin Block Size Limit? https://bitcoinmagazine.com/guides/what-is-the-bitcoin-block-size-limit\n7. CoinMarketCap Academy. (2025). Block Size Definition. https://coinmarketcap.com/academy/glossary/block-size\n8. Yellow Card Academy. (2025). Block Size Limit. https://academy.yellowcard.io/glossary/block-size-limit/\n9. Wikipedia. (2025). Bitcoin scalability problem. https://en.wikipedia.org/wiki/Bitcoin_scalability_problem\n10. Coinbase. (2025). Bitcoin block reward, block size, block time: what's the difference? https://www.coinbase.com/learn/crypto-basics/bitcoin-block-reward-block-size-block-time-whats-the-difference\n\n\n## Metadata\n\n\n- **Migration Status**: Ontology block enriched on 2025-11-12\n- **Last Updated**: 2025-11-12\n- **Review Status**: Comprehensive editorial review\n- **Verification**: Academic sources verified\n- **Regional Context**: UK/North England where applicable",
  "properties": {
    "id": "block-size-standards",
    "collapsed": "true",
    "- domain-prefix": "BC",
    "- sequence-number": "0013",
    "- filename-history": "[\"BC-0013-block-size.md\"]",
    "- public-access": "true",
    "- ontology": "true",
    "- term-id": "BC-0013",
    "- preferred-term": "Block Size",
    "- source-domain": "blockchain",
    "- status": "complete",
    "- version": "1.0.0",
    "- last-updated": "2025-10-28",
    "- definition": "Data capacity limit of a block within blockchain systems, providing essential functionality for distributed ledger technology operations and properties.",
    "- maturity": "mature",
    "- source": "[[ISO/IEC 23257:2021]], [[IEEE 2418.1]], [[NIST NISTIR]]",
    "- authority-score": "0.95",
    "- owl:class": "bc:BlockSize",
    "- owl:physicality": "VirtualEntity",
    "- owl:role": "Object",
    "- owl:inferred-class": "bc:VirtualObject",
    "- belongsToDomain": "[[BlockchainDomain]]",
    "- implementedInLayer": "[[ConceptualLayer]]",
    "- is-subclass-of": "[[Blockchain Entity]], [[DistributedDataStructure]]"
  },
  "backlinks": [
    "Bitcoin Centralisation Risks",
    "Telecollaboration and Telepresence"
  ],
  "wiki_links": [
    "BlockchainDomain",
    "ConceptualLayer",
    "Blockchain Entity",
    "ISO/IEC 23257:2021",
    "DistributedDataStructure",
    "NIST NISTIR",
    "IEEE 2418.1"
  ],
  "ontology": {
    "term_id": "BC-0013",
    "preferred_term": "Block Size",
    "definition": "Data capacity limit of a block within blockchain systems, providing essential functionality for distributed ledger technology operations and properties.",
    "source_domain": "blockchain",
    "maturity_level": null,
    "authority_score": 0.95
  }
}