{
  "title": "Burning Mechanism",
  "content": "- ### OntologyBlock\n  id:: burningmechanism-ontology\n  collapsed:: true\n\n  - **Identification**\n    - domain-prefix:: BC\n    - sequence-number:: 0531\n    - filename-history:: [\"BC-0531-burningmechanism.md\"]\n    - public-access:: true\n    - ontology:: true\n    - term-id:: BC-0531\n    - preferred-term:: Burning Mechanism\n    - source-domain:: metaverse\n    - status:: complete\n    - version:: 1.0.0\n    - last-updated:: 2025-11-13\n\n  - **Definition**\n    - definition:: A process that permanently removes tokens from circulation by sending them to unspendable addresses or destroying them, reducing total supply.\n    - maturity:: established\n    - source:: Chimera Prime Research\n    - authority-score:: 0.95\n\n  - **Semantic Classification**\n    - owl:class:: bc:BurningMechanism\n    - belongsToDomain:: [[Blockchain]]\n\n  - #### Relationships\n    - is-subclass-of:: [[Tokenomics]]\n\n  - #### OWL Axioms\n    - ```clojure\n      ; Class Declaration\n      (Declaration (Class :BurningMechanism))\n      (SubClassOf :BurningMechanism :Tokenomics)\n      \n      ; Annotations\n      (AnnotationAssertion rdfs:label :BurningMechanism \"Burning Mechanism\"@en)\n      (AnnotationAssertion rdfs:comment :BurningMechanism\n        \"A process that permanently removes tokens from circulation by sending them to unspendable addresses or destroying them, reducing total supply.\"@en)\n      ```\n\n- ## About Burning Mechanism\n  A process that permanently removes tokens from circulation by sending them to unspendable addresses or destroying them, reducing total supply.\n\t\n\t### Implementation Across Blockchains\n\tThe permanent and irreversible removal of cryptocurrency tokens from circulation by sending them to provably unspendable addresses (burn addresses), reducing total supply and creating deflationary pressure. Implemented through diverse mechanisms including Ethereum's EIP-1559 base fee burning (over 2.5M ETH burned since August 2021), Binance's quarterly BNB burns based on trading volume and profits, Shiba Inu's community-driven burn portals, proof-of-burn consensus protocols, transaction fee burning in layer-1 blockchains, and smart contract-triggered automatic burns, the burning mechanism serves as a core deflationary tool for managing token economics, reducing inflation, and increasing scarcity to support long-term value appreciation.\n\t\n  \n  ### Examples\n  - EIP-1559 base fee burning, BNB quarterly burns, buyback-and-burn programs\n\n## Current Landscape (2025)\n\n- Industry adoption and implementations\n  - Metaverse platforms continue to evolve with focus on interoperability and open standards\n  - Web3 integration accelerating with decentralised identity and asset ownership\n  - Enterprise adoption growing in virtual collaboration, training, and digital twins\n  - UK companies increasingly active in metaverse development and immersive technologies\n\n- Technical capabilities\n  - Real-time rendering at photorealistic quality levels\n  - Low-latency networking enabling seamless multi-user experiences\n  - AI-driven content generation and procedural world building\n  - Spatial audio and haptics enhancing immersion\n\n- UK and North England context\n  - Manchester: Digital Innovation Factory supports metaverse startups and research\n  - Leeds: Holovis leads in immersive experiences for entertainment and training\n  - Newcastle: University research in spatial computing and interactive systems\n  - Sheffield: Advanced manufacturing using digital twin technology\n\n- Standards and frameworks\n  - Metaverse Standards Forum driving interoperability protocols\n  - WebXR enabling browser-based immersive experiences\n  - glTF and USD for 3D asset interchange\n  - Open Metaverse Interoperability Group defining cross-platform standards\n\n## Metadata\n\n- **Last Updated**: 2025-11-16\n- **Review Status**: Automated remediation with 2025 context\n- **Verification**: Academic sources verified\n- **Regional Context**: UK/North England where applicable",
  "properties": {
    "id": "burningmechanism-ontology",
    "collapsed": "true",
    "- domain-prefix": "BC",
    "- sequence-number": "0531",
    "- filename-history": "[\"BC-0531-burningmechanism.md\"]",
    "- public-access": "true",
    "- ontology": "true",
    "- term-id": "BC-0531",
    "- preferred-term": "Burning Mechanism",
    "- source-domain": "metaverse",
    "- status": "complete",
    "- version": "1.0.0",
    "- last-updated": "2025-11-13",
    "- definition": "A process that permanently removes tokens from circulation by sending them to unspendable addresses or destroying them, reducing total supply.",
    "- maturity": "established",
    "- source": "Chimera Prime Research",
    "- authority-score": "0.95",
    "- owl:class": "bc:BurningMechanism",
    "- belongsToDomain": "[[Blockchain]]",
    "- is-subclass-of": "[[Tokenomics]]"
  },
  "backlinks": [],
  "wiki_links": [
    "Blockchain",
    "Tokenomics"
  ],
  "ontology": {
    "term_id": "BC-0531",
    "preferred_term": "Burning Mechanism",
    "definition": "A process that permanently removes tokens from circulation by sending them to unspendable addresses or destroying them, reducing total supply.",
    "source_domain": "metaverse",
    "maturity_level": null,
    "authority_score": 0.95
  }
}