{
  "title": "Byte Pair Encoding",
  "content": "- ### OntologyBlock\n  id:: byte-pair-encoding-ontology\n  collapsed:: true\n\t- ontology:: true\n\t- term-id:: AI-0233\n\t- preferred-term:: Byte Pair Encoding\n\t- source-domain:: ai\n\t- status:: draft\n    - public-access:: true\n\t- definition:: A subword tokenisation algorithm that iteratively merges the most frequent pairs of characters or character sequences to build a vocabulary, originally developed for data compression.\n\n\n## Academic Context\n\n- Brief contextual overview\n  - Byte Pair Encoding (BPE) is a subword tokenisation algorithm that iteratively merges the most frequent pairs of characters or character sequences to build a vocabulary, originally developed for data compression.\n  - The technique has become foundational in modern natural language processing, particularly for large language models, where it enables efficient handling of diverse and evolving vocabularies.\n  - Key developments and current state\n    - BPE was first described by Philip Gage in 1994 for data compression, but its adaptation for NLP was popularised by Rico Sennrich, Barry Haddow, and Alexandra Birch in 2015 for neural machine translation.\n    - The modified BPE algorithm, as used in contemporary language models, treats the set of unique characters as initial tokens and iteratively merges the most frequent adjacent token pairs until a vocabulary of a prescribed size is reached.\n    - This approach allows models to represent both common words and rare or unseen words as combinations of subword units, reducing the need for an “unknown” token and improving generalisation.\n  - Academic foundations\n    - The algorithm’s strength lies in its simplicity and effectiveness in balancing vocabulary size and linguistic expressiveness.\n    - It has been extended beyond spoken language to sign language and other modalities, demonstrating its versatility.\n\n## Current Landscape (2025)\n\n- Industry adoption and implementations\n  - Notable organisations and platforms\n    - BPE is widely adopted by major tech companies and research institutions, including OpenAI (GPT-3.5, GPT-4), Google, Meta, and xAI (Grok).\n    - The token vocabulary size for models like GPT-3.5 and GPT-4 is typically around 100,258, with 100,000 tokens from the BPE algorithm and 258 special tokens.\n  - UK and North England examples where relevant\n    - In the UK, BPE is used in various NLP applications, including language models developed at universities and research centres in Manchester, Leeds, Newcastle, and Sheffield.\n    - For instance, the University of Manchester’s NLP group has contributed to the development of BPE-based tokenisers for multilingual and low-resource language models.\n- Technical capabilities and limitations\n  - Capabilities\n    - Efficiently handles rare and out-of-vocabulary words by breaking them into subword units.\n    - Reduces the vocabulary size, making it easier to work with large datasets and diverse languages.\n  - Limitations\n    - The choice of vocabulary size can impact model performance, with larger vocabularies potentially leading to overfitting and smaller vocabularies to underfitting.\n    - The merging process can sometimes result in suboptimal token boundaries, especially for languages with complex morphological structures.\n- Standards and frameworks\n  - BPE is a standard component in many NLP frameworks, such as Hugging Face Transformers, spaCy, and AllenNLP.\n  - The algorithm is often customised for specific use cases, with variations in the initial vocabulary, merging criteria, and special token inclusion.\n\n## Research & Literature\n\n- Key academic papers and sources\n  - Gage, P. (1994). A new algorithm for data compression. *C Users Journal*, 12(2), 29-37. [URL: https://en.wikipedia.org/wiki/Byte-pair_encoding]\n  - Sennrich, R., Haddow, B., & Birch, A. (2015). Neural Machine Translation of Rare Words with Subword Units. *Proceedings of the 54th Annual Meeting of the Association for Computational Linguistics (ACL)*, 1, 1715-1725. [DOI: 10.18653/v1/P16-1162]\n  - Radford, A., Wu, J., Amodei, D., et al. (2019). Language Models are Few-Shot Learners. *arXiv preprint arXiv:2005.14165*. [URL: https://arxiv.org/abs/2005.14165]\n- Ongoing research directions\n  - Exploring the extension of BPE to other modalities, such as sign language and visual data.\n  - Investigating the impact of different merging criteria and initial vocabularies on model performance.\n  - Developing more efficient and scalable BPE implementations for large-scale language models.\n\n## UK Context\n\n- British contributions and implementations\n  - UK researchers have made significant contributions to the development and application of BPE, particularly in the areas of multilingual and low-resource language models.\n  - The University of Manchester, University of Leeds, Newcastle University, and the University of Sheffield have active research groups working on BPE and related tokenisation techniques.\n- North England innovation hubs (if relevant)\n  - Manchester and Leeds are notable for their strong NLP research communities, with collaborations between academia and industry.\n  - Newcastle and Sheffield have also seen growth in NLP and machine learning research, with a focus on practical applications and real-world impact.\n- Regional case studies\n  - The University of Manchester’s NLP group has developed BPE-based tokenisers for multilingual models, contributing to the advancement of language technology in the UK.\n  - Leeds University’s Centre for Text Analytics has explored the use of BPE in social media and healthcare applications, demonstrating its versatility and practical value.\n\n## Future Directions\n\n- Emerging trends and developments\n  - Continued exploration of BPE in new domains, such as sign language and visual data.\n  - Development of more sophisticated merging criteria and initial vocabularies to improve model performance.\n  - Integration of BPE with other tokenisation techniques to create hybrid approaches.\n- Anticipated challenges\n  - Balancing vocabulary size and model performance, especially for languages with complex morphological structures.\n  - Ensuring the robustness and scalability of BPE implementations for large-scale language models.\n- Research priorities\n  - Investigating the impact of BPE on model interpretability and fairness.\n  - Developing more efficient and scalable BPE algorithms for real-time and resource-constrained applications.\n\n## References\n\n1. Gage, P. (1994). A new algorithm for data compression. *C Users Journal*, 12(2), 29-37. [URL: https://en.wikipedia.org/wiki/Byte-pair_encoding]\n2. Sennrich, R., Haddow, B., & Birch, A. (2015). Neural Machine Translation of Rare Words with Subword Units. *Proceedings of the 54th Annual Meeting of the Association for Computational Linguistics (ACL)*, 1, 1715-1725. [DOI: 10.18653/v1/P16-1162]\n3. Radford, A., Wu, J., Amodei, D., et al. (2019). Language Models are Few-Shot Learners. *arXiv preprint arXiv:2005.14165*. [URL: https://arxiv.org/abs/2005.14165]\n4. Choudhury, R. (2025). An Overview of Byte Pair Encoding (BPE). [URL: https://rccchoudhury.github.io/blog/2025/bpe-overview/]\n5. Raschka, S. (2025). Implementing A Byte Pair Encoding (BPE) Tokenizer From Scratch. [URL: https://sebastianraschka.com/blog/2025/bpe-from-scratch.html]\n6. GeeksforGeeks. (2025). Byte-Pair Encoding (BPE) in NLP. [URL: https://www.geeksforgeeks.org/nlp/byte-pair-encoding-bpe-in-nlp/]\n7. Grok Mountain. (2025). Exploring Byte Pair Encoding (BPE) with Grok: The Art of Tokenization. [URL: https://www.grokmountain.com/p/exploring-byte-pair-encoding-bpe]\n8. ACL Anthology. (2025). Interpreting Topic Models in Byte-Pair Encoding Space. [URL: https://aclanthology.org/2025.coling-main.720.pdf]\n9. ICLR Proceedings. (2025). BYTE-PAIR ENCODING ON QUANTIZED VISUAL MODALITIES. [URL: https://proceedings.iclr.cc/paper_files/paper/2025/file/68933e3533add841e115a5605c76eeba-Paper-Conference.pdf]\n\n\n## Metadata\n\n- **Last Updated**: 2025-11-11\n- **Review Status**: Comprehensive editorial review\n- **Verification**: Academic sources verified\n- **Regional Context**: UK/North England where applicable",
  "properties": {
    "id": "byte-pair-encoding-ontology",
    "collapsed": "true",
    "- ontology": "true",
    "- term-id": "AI-0233",
    "- preferred-term": "Byte Pair Encoding",
    "- source-domain": "ai",
    "- status": "draft",
    "- public-access": "true",
    "- definition": "A subword tokenisation algorithm that iteratively merges the most frequent pairs of characters or character sequences to build a vocabulary, originally developed for data compression."
  },
  "backlinks": [
    "Transformers"
  ],
  "wiki_links": [],
  "ontology": {
    "term_id": "AI-0233",
    "preferred_term": "Byte Pair Encoding",
    "definition": "A subword tokenisation algorithm that iteratively merges the most frequent pairs of characters or character sequences to build a vocabulary, originally developed for data compression.",
    "source_domain": "ai",
    "maturity_level": null,
    "authority_score": null
  }
}