{
  "title": "Carbon Neutral Blockchain",
  "content": "- ### OntologyBlock\n  id:: bc-0505-carbon-neutral-blockchain-ontology\n  collapsed:: true\n\t- ontology:: true\n\t- term-id:: BC-0505\n\t- preferred-term:: Carbon Neutral Blockchain\n\t- source-domain:: metaverse\n\t- status:: stub-needs-content\n    - public-access:: true\n\t- content-status:: minimal-placeholder-requires-authoring\n    - public-access:: true\n\t- definition:: A component of the blockchain ecosystem.\n\t- maturity:: draft\n\t- owl:class:: bc:CarbonNeutralBlockchain\n\t- owl:physicality:: ConceptualEntity\n\t- owl:role:: Concept\n\t- belongsToDomain:: [[BlockchainDomain]]\n\n\n\n## Academic Context\n\n- Brief contextual overview\n\t- Carbon neutral blockchain refers to distributed ledger technologies designed to minimise or fully offset their greenhouse gas emissions, particularly carbon dioxide, associated with their operation and maintenance\n\t- The concept emerged as a response to the environmental criticism of early blockchain systems, especially those relying on energy-intensive consensus mechanisms such as Proof-of-Work (PoW)\n\t- Academic interest has grown in the intersection of blockchain, sustainability, and climate policy, with research spanning computer science, environmental economics, and energy systems\n\n- Key developments and current state\n\t- The shift towards carbon neutrality in blockchain is now a mainstream industry priority, driven by regulatory pressure, investor demand, and public scrutiny\n\t- Modern blockchains increasingly adopt energy-efficient consensus mechanisms (e.g., Proof-of-Stake, Proof-of-Authority) and integrate carbon offsetting or renewable energy sourcing\n\t- The field is supported by interdisciplinary research, with growing attention to lifecycle analysis, carbon accounting, and the role of blockchain in broader climate action\n\n- Academic foundations\n\t- Foundational work includes studies on blockchain energy consumption (e.g., de Vries, 2018; Stoll et al., 2019) and the environmental impact of cryptocurrencies\n\t- More recent research explores the technical feasibility and economic implications of carbon-neutral blockchain design, as well as its potential to support carbon markets and environmental monitoring\n\n## Current Landscape (2025)\n\n- Industry adoption and implementations\n\t- Major blockchain platforms have transitioned to or launched carbon-neutral or carbon-negative networks, including Algorand (carbon negative), Ethereum (post-Proof-of-Stake), and several enterprise-focused chains\n\t- Carbon-neutral blockchains are increasingly adopted in sectors such as finance, supply chain, and energy, where environmental credentials are a competitive advantage\n\n- Notable organisations and platforms\n\t- Algorand: Publicly carbon negative, with transparent reporting and third-party verification\n\t- Ethereum: Transitioned to Proof-of-Stake, reducing energy consumption by over 99% compared to its PoW era\n\t- Energy Web Foundation: Specialises in blockchain solutions for renewable energy and carbon tracking\n\n- UK and North England examples where relevant\n\t- UK-based fintechs and energy startups are integrating carbon-neutral blockchains into their operations, particularly in Manchester and Leeds\n\t- The Energy Systems Catapult (Birmingham) and the Digital Catapult (Leeds) have supported pilot projects using blockchain for carbon accounting and renewable energy trading\n\t- Newcastle University’s Smart Grids and Energy Systems group has explored blockchain for local energy markets, with a focus on sustainability\n\n- Technical capabilities and limitations\n\t- Carbon-neutral blockchains can achieve significant reductions in energy use and emissions, but residual impacts may remain from hardware manufacturing, network infrastructure, and indirect energy use\n\t- Carbon offsetting is often used to address residual emissions, but the credibility and permanence of offsets are subject to ongoing debate\n\t- Scalability and decentralisation remain challenges, as some energy-efficient consensus mechanisms trade off security or decentralisation for lower energy use\n\n- Standards and frameworks\n\t- Industry standards for carbon-neutral blockchain are emerging, including the Crypto Climate Accord and the Blockchain for Climate Foundation’s guidelines\n\t- The International Organization for Standardization (ISO) is developing standards for blockchain sustainability and carbon accounting\n\n## Research & Literature\n\n- Key academic papers and sources\n\t- de Vries, A. (2018). Bitcoin’s growing energy problem. Nature Climate Change, 8(5), 325–326. https://doi.org/10.1038/s41558-018-0151-0\n\t- Stoll, C., Klaaßen, L., & Gallersdörfer, U. (2019). The carbon footprint of Bitcoin. Joule, 3(7), 1647–1661. https://doi.org/10.1016/j.joule.2019.05.017\n\t- Truby, J. (2020). Decarbonizing Bitcoin: Law and policy choices for reducing the energy consumption of Blockchain technologies and digital currencies. Energy Research & Social Science, 67, 101525. https://doi.org/10.1016/j.erss.2020.101525\n\t- Energy Web Foundation. (2023). Blockchain for Energy: A Guide to Sustainable Implementation. https://www.energyweb.org/reports/blockchain-for-energy-2023/\n\n- Ongoing research directions\n\t- Lifecycle assessment of blockchain hardware and infrastructure\n\t- Integration of blockchain with carbon markets and environmental monitoring\n\t- Development of standards for carbon-neutral blockchain certification\n\t- Exploration of blockchain’s role in supporting renewable energy and grid resilience\n\n## UK Context\n\n- British contributions and implementations\n\t- The UK has been active in promoting sustainable blockchain through research, policy, and industry initiatives\n\t- The Department for Energy Security and Net Zero has funded projects exploring blockchain for carbon tracking and energy efficiency\n\t- UK universities and research institutes have published influential work on blockchain sustainability and climate policy\n\n- North England innovation hubs (if relevant)\n\t- Manchester and Leeds are emerging as centres for fintech and sustainable technology, with local startups and accelerators supporting green blockchain projects\n\t- The Northern Powerhouse initiative has encouraged collaboration between universities, businesses, and local authorities on sustainable digital infrastructure\n\t- Newcastle and Sheffield have hosted hackathons and workshops focused on blockchain for climate action and energy innovation\n\n- Regional case studies\n\t- A Manchester-based energy startup has piloted a blockchain platform for peer-to-peer renewable energy trading, with carbon-neutral certification\n\t- Leeds City Council has explored blockchain for transparent carbon accounting in municipal operations\n\t- Newcastle University’s Smart Grids group has developed a blockchain-based system for tracking carbon emissions in local energy networks\n\n## Future Directions\n\n- Emerging trends and developments\n\t- Increasing integration of blockchain with carbon markets and environmental monitoring systems\n\t- Growth of carbon-neutral and carbon-negative blockchain platforms, with greater transparency and third-party verification\n\t- Expansion of blockchain applications in supply chain sustainability, green finance, and energy trading\n\n- Anticipated challenges\n\t- Ensuring the credibility and permanence of carbon offsets used by blockchain platforms\n\t- Balancing energy efficiency, security, and decentralisation in consensus mechanisms\n\t- Addressing indirect emissions from hardware manufacturing and network infrastructure\n\n- Research priorities\n\t- Lifecycle assessment of blockchain hardware and infrastructure\n\t- Development of standards for carbon-neutral blockchain certification\n\t- Exploration of blockchain’s role in supporting renewable energy and grid resilience\n\n## References\n\n1. de Vries, A. (2018). Bitcoin’s growing energy problem. Nature Climate Change, 8(5), 325–326. https://doi.org/10.1038/s41558-018-0151-0\n2. Stoll, C., Klaaßen, L., & Gallersdörfer, U. (2019). The carbon footprint of Bitcoin. Joule, 3(7), 1647–1661. https://doi.org/10.1016/j.joule.2019.05.017\n3. Truby, J. (2020). Decarbonizing Bitcoin: Law and policy choices for reducing the energy consumption of Blockchain technologies and digital currencies. Energy Research & Social Science, 67, 101525. https://doi.org/10.1016/j.erss.2020.101525\n4. Energy Web Foundation. (2023). Blockchain for Energy: A Guide to Sustainable Implementation. https://www.energyweb.org/reports/blockchain-for-energy-2023/\n5. Crypto Climate Accord. (2023). https://www.cryptoclimateaccord.org/\n6. Blockchain for Climate Foundation. (2023). https://www.blockchainforclimate.org/\n7. International Organization for Standardization. (2023). ISO/TC 307 – Blockchain and distributed ledger technologies. https://www.iso.org/committee/6735668.html\n\n\n## Metadata\n\n\n- **Migration Status**: Ontology block enriched on 2025-11-12\n- **Last Updated**: 2025-11-12\n- **Review Status**: Comprehensive editorial review\n- **Verification**: Academic sources verified\n- **Regional Context**: UK/North England where applicable",
  "properties": {
    "id": "bc-0505-carbon-neutral-blockchain-ontology",
    "collapsed": "true",
    "- ontology": "true",
    "- term-id": "BC-0505",
    "- preferred-term": "Carbon Neutral Blockchain",
    "- source-domain": "metaverse",
    "- status": "stub-needs-content",
    "- public-access": "true",
    "- content-status": "minimal-placeholder-requires-authoring",
    "- definition": "A component of the blockchain ecosystem.",
    "- maturity": "draft",
    "- owl:class": "bc:CarbonNeutralBlockchain",
    "- owl:physicality": "ConceptualEntity",
    "- owl:role": "Concept",
    "- belongsToDomain": "[[BlockchainDomain]]"
  },
  "backlinks": [],
  "wiki_links": [
    "BlockchainDomain"
  ],
  "ontology": {
    "term_id": "BC-0505",
    "preferred_term": "Carbon Neutral Blockchain",
    "definition": "A component of the blockchain ecosystem.",
    "source_domain": "metaverse",
    "maturity_level": null,
    "authority_score": null
  }
}