{
  "title": "Censorship Resistance",
  "content": "- ### OntologyBlock\n  id:: censorship-resistance-ontology\n  collapsed:: true\n\n  - **Identification**\n\n    - domain-prefix:: BC\n\n    - sequence-number:: 0086\n\n    - filename-history:: [\"BC-0086-censorship-resistance.md\"]\n    - public-access:: true\n    - ontology:: true\n    - term-id:: BC-0086\n    - preferred-term:: Censorship Resistance\n    - source-domain:: metaverse\n    - status:: complete\n    - version:: 1.0.0\n    - last-updated:: 2025-10-28\n\n  - **Definition**\n    - definition:: Transaction inclusion guarantee within blockchain systems, providing essential functionality for distributed ledger technology operations and properties.\n    - maturity:: mature\n    - source:: [[ISO/IEC 23257:2021]], [[IEEE 2418.1]], [[NIST NISTIR]]\n    - authority-score:: 0.95\n\n  - **Semantic Classification**\n    - owl:class:: bc:CensorshipResistance\n    - owl:physicality:: VirtualEntity\n    - owl:role:: Object\n    - owl:inferred-class:: bc:VirtualObject\n    - belongsToDomain:: [[CryptographicDomain]]\n    - implementedInLayer:: [[SecurityLayer]]\n\n  - #### Relationships\n    id:: censorship-resistance-relationships\n    - is-subclass-of:: [[Blockchain Entity]], [[NetworkComponent]]\n\n  - #### OWL Axioms\n    id:: censorship-resistance-owl-axioms\n    collapsed:: true\n    - ```clojure\n      Prefix(:=<http://metaverse-ontology.org/blockchain#>)\nPrefix(owl:=<http://www.w3.org/2002/07/owl#>)\nPrefix(rdf:=<http://www.w3.org/1999/02/22-rdf-syntax-ns#>)\nPrefix(xml:=<http://www.w3.org/XML/1998/namespace>)\nPrefix(xsd:=<http://www.w3.org/2001/XMLSchema#>)\nPrefix(rdfs:=<http://www.w3.org/2000/01/rdf-schema#>)\nPrefix(dct:=<http://purl.org/dc/terms/>)\n\nOntology(<http://metaverse-ontology.org/blockchain/BC-0086>\n  Import(<http://metaverse-ontology.org/blockchain/core>)\n\n  ## Class Declaration\n  Declaration(Class(:CensorshipResistance))\n\n  ## Subclass Relationships\n  SubClassOf(:CensorshipResistance :NetworkComponent)\n  SubClassOf(:CensorshipResistance :BlockchainEntity)\n\n  ## Essential Properties\n  SubClassOf(:CensorshipResistance\n    (ObjectSomeValuesFrom :partOf :Blockchain))\n\n  SubClassOf(:CensorshipResistance\n    (ObjectSomeValuesFrom :hasProperty :Property))\n\n  ## Data Properties\n  DataPropertyAssertion(:hasIdentifier :CensorshipResistance \"BC-0086\"^^xsd:string)\n  DataPropertyAssertion(:hasAuthorityScore :CensorshipResistance \"1.0\"^^xsd:decimal)\n  DataPropertyAssertion(:isFoundational :CensorshipResistance \"true\"^^xsd:boolean)\n\n  ## Object Properties\n  ObjectPropertyAssertion(:enablesFeature :CensorshipResistance :BlockchainFeature)\n  ObjectPropertyAssertion(:relatesTo :CensorshipResistance :RelatedConcept)\n\n  ## Annotations\n  AnnotationAssertion(rdfs:label :CensorshipResistance \"Censorship Resistance\"@en)\n  AnnotationAssertion(rdfs:comment :CensorshipResistance\n    \"Transaction inclusion guarantee\"@en)\n  AnnotationAssertion(dct:description :CensorshipResistance\n    \"Foundational blockchain concept with formal ontological definition\"@en)\n  AnnotationAssertion(:termID :CensorshipResistance \"BC-0086\")\n  AnnotationAssertion(:priority :CensorshipResistance \"1\"^^xsd:integer)\n  AnnotationAssertion(:category :CensorshipResistance \"network-security\"@en)\n)\n      ```\n\n- ## About Censorship Resistance\n  id:: censorship-resistance-about\n\n  - Transaction inclusion guarantee within blockchain systems, providing essential functionality for distributed ledger technology operations and properties.\n  -\n  - ### Key Characteristics\n    id:: censorship-resistance-characteristics\n    - 1. **Definitional Property**: Core defining characteristic\n    - 2. **Functional Property**: Operational behavior\n    - 3. **Structural Property**: Compositional elements\n    - 4. **Security Property**: Security guarantees provided\n    - 5. **Performance Property**: Efficiency considerations\n  -\n  - ### Technical Components\n    id:: censorship-resistance-components\n    - **Implementation**: How concept is realized technically\n    - **Verification**: Methods for validating correctness\n    - **Interaction**: Relationships with other components\n    - **Constraints**: Technical limitations and requirements\n  -\n  - ### Use Cases\n    id:: censorship-resistance-use-cases\n    - **1. Core Blockchain Operation**\n    - **Application**: Fundamental blockchain functionality\n    - **Example**: Practical implementation in major blockchains\n    - **Requirements**: Technical prerequisites\n    - **Benefits**: Value provided to blockchain systems\n  -\n  - ### Standards & References\n    id:: censorship-resistance-standards\n    - [[ISO/IEC 23257:2021]] - Blockchain and distributed ledger technologies\n    - [[IEEE 2418.1]] - Blockchain and distributed ledger technologies\n    - [[NIST NISTIR]] - Blockchain and distributed ledger technologies\n  -\n\n\t\t- #### Merits as a Quantifiable Measure of Contribution\n\t\t- Merits are a fundamental component of the NostrRocket project, serving as a quantifiable measure of individual contribution. They represent the proportion of work undertaken by each contributor and determine the distribution of revenue or rewards.\n\t\t-\n\t\t\t- Earning Merits:\n\t\t\t\t- Contributors identify problems needing solutions, often outlined in a public problem tracker.\n\t\t\t\t- Solutions are proposed, typically in the form of code contributions or other tangible outputs.\n\t\t\t\t- Upon completion, contributors submit a merit request outlining the problem solved and the proposed number of merits earned.\n\t\t\t\t- Existing merit holders review the request and vote to approve or reject it based on predefined rules and criteria.\n\t\t- Social Trust and Verification: Leverages social trust mechanisms and potentially proof-of-work systems to ensure data accuracy and reliability.\n\t\t- Community Ownership: The map is collectively owned and maintained by the user community.\n\t\t- Decentralised Governance: Decisions regarding the platform's development and direction are made through decentralised consensus mechanisms.\n\t\t- Transparency and Accountability: All interactions and contributions are recorded on the Nostr network.\n\t\t- Resilience and Censorship Resistance: The decentralised nature of the platform provides resistance to censorship and single points of failure.\n\n\t\t- #### Merits as a Quantifiable Measure of Contribution\n\t\t- Merits are a fundamental component of the NostrRocket project, serving as a quantifiable measure of individual contribution. They represent the proportion of work undertaken by each contributor and determine the distribution of revenue or rewards.\n\t\t-\n\t\t\t- Earning Merits:\n\t\t\t\t- Contributors identify problems needing solutions, often outlined in a public problem tracker.\n\t\t\t\t- Solutions are proposed, typically in the form of code contributions or other tangible outputs.\n\t\t\t\t- Upon completion, contributors submit a merit request outlining the problem solved and the proposed number of merits earned.\n\t\t- Decentralised Governance: Decisions regarding the platform's development and direction are made through decentralised consensus mechanisms.\n\t\t- Transparency and Accountability: All interactions and contributions are recorded on the Nostr network.\n\t\t- Resilience and Censorship Resistance: The decentralised nature of the platform provides resistance to censorship and single points of failure.\n\n\t\t- #### NostrRocket: A Practical Example of DAO Structures on Nostr\n\t\t\t- NostrRocket, a project built on Nostr, showcases the practical application of these principles. It facilitates decentralised, non-custodial coordination, allowing contributors to collaborate on creating and managing digital objects – including software, merchandise, or content – without centralised control.\n\t\t\t- The project's governance is maintained through a system of \"merits,\" which quantify and reward contributions based on predefined rules. Operating without servers or traditional centralisation, NostrRocket relies solely on Nostr relays. Contributors propose and approve merits based on their work, ensuring the project's direction and outcomes are shaped directly by those involved. This approach upholds decentralised governance principles and streamlines operations by eliminating the need for conventional accounting and oversight.\n\t\t- Merits are a fundamental component of the NostrRocket project, serving as a quantifiable measure of individual contribution. They represent the proportion of work undertaken by each contributor and determine the distribution of revenue or rewards.\n\t\t\t\t- Contributors identify problems needing solutions, often outlined in a public problem tracker.\n\t\t\t\t- Solutions are proposed, typically in the form of code contributions or other tangible outputs.\n\t\t- Resilience and Censorship Resistance: The decentralised nature of the platform provides resistance to censorship and single points of failure.\n\n\n## Academic Context\n\n- **Overview**  \n  Censorship resistance refers to the property of a system—particularly decentralised networks and blockchains—that prevents any single party or coalition from arbitrarily excluding participants or censoring transactions. It ensures open access and participation without interference or control by central authorities.\n\n- **Key Developments and Current State**  \n  The concept has evolved from early peer-to-peer systems to sophisticated blockchain protocols that guarantee transaction inclusion and data availability despite adversarial attempts at censorship. Recent research distinguishes between short-term censorship resistance (immediate transaction inclusion) and long-term guarantees, highlighting limitations in leader-based consensus protocols such as Bitcoin and Ethereum.\n\n- **Academic Foundations**  \n  Foundational work spans distributed systems, cryptography, and game theory, with formal proofs of censorship resistance properties emerging alongside consensus protocol designs. Notably, consensusless and DAG-based protocols have been proposed to improve efficiency and reduce central points of failure in censorship resistance[2].\n\n## Current Landscape (2025)\n\n- **Industry Adoption and Implementations**  \n  Public permissionless blockchains remain the primary exemplars of censorship resistance, enabling users worldwide to transact without gatekeepers[1]. Decentralised social networks and DeFi platforms increasingly incorporate censorship-resistant features to enhance user autonomy and privacy[4].\n\n- **Notable Organisations and Platforms**  \n  Ethereum and Bitcoin continue to lead, though newer protocols explore consensusless or DAG-based approaches to improve censorship resistance and throughput[2]. Decentralised social media projects, some leveraging blockchain, aim to counteract centralised platform censorship[4].\n\n- **UK and North England Examples**  \n  UK academic institutions such as Middlesex University (London) contribute to research on blockchain-based decentralised social networks enhancing censorship resistance and privacy[4]. While North England cities like Manchester, Leeds, Newcastle, and Sheffield are emerging hubs for blockchain innovation, specific high-profile censorship resistance projects remain nascent but growing, often linked to fintech and digital identity startups.\n\n- **Technical Capabilities and Limitations**  \n  Leader-based consensus protocols face inherent censorship risks due to transaction selection by block proposers. Consensusless and DAG-based protocols offer promising alternatives but face challenges in scalability and security trade-offs[2]. Censorship resistance is not absolute; network-level attacks and regulatory pressures can still impose constraints.\n\n- **Standards and Frameworks**  \n  Industry and academic efforts are ongoing to standardise censorship resistance metrics and protocols, with emphasis on transparency, auditability, and decentralisation thresholds. No universally accepted standard exists yet, but frameworks increasingly consider socio-technical factors alongside cryptographic guarantees.\n\n## Research & Literature\n\n- **Key Academic Papers and Sources**  \n  - Alpos, O., David, B., Kamarinakis, N., & Zindros, D. (2025). *Consensus Protocols for Censorship Resistance and Efficiency*. arXiv preprint arXiv:2504.03588. https://doi.org/10.48550/arXiv.2504.03588[2]  \n  - Thiha, M., Yetgin, H., Piras, L., & Al-Obeidallah, M. G. (2025). *Enhancing Privacy, Censorship Resistance, and User Engagement in a Blockchain-Based Social Network*. SCITEPRESS Digital Library. https://doi.org/10.5220/0013238500003824[4]  \n  - Liberty Street Economics (2025). *How Censorship Resistant Are Decentralized Systems?* Federal Reserve Bank of New York. [1]\n\n- **Ongoing Research Directions**  \n  Research focuses on improving short-term censorship resistance guarantees, exploring consensusless protocols, and integrating privacy with censorship resistance in decentralised social networks. The interplay between technical censorship resistance and regulatory or infrastructural censorship remains a critical area.\n\n## UK Context\n\n- **British Contributions and Implementations**  \n  UK researchers contribute to blockchain-based decentralised social networks prioritising censorship resistance and privacy[4]. The UK government and private sector show growing interest in decentralised technologies, though regulatory frameworks continue to evolve cautiously.\n\n- **North England Innovation Hubs**  \n  Cities such as Manchester, Leeds, Newcastle, and Sheffield foster fintech and blockchain startups exploring decentralised identity, payments, and data sovereignty, indirectly supporting censorship resistance principles. Academic-industry collaborations in these regions are increasing, though specific censorship resistance projects are still emerging.\n\n- **Regional Case Studies**  \n  Middlesex University’s blockchain social network project exemplifies UK academic efforts to address censorship and privacy challenges in digital communication[4]. Regional innovation clusters in North England are poised to contribute further as decentralised technology adoption expands.\n\n## Future Directions\n\n- **Emerging Trends and Developments**  \n  - Development of consensusless and DAG-based protocols to enhance censorship resistance and efficiency[2].  \n  - Integration of censorship resistance with privacy-preserving technologies in social networks and financial applications[4].  \n  - Increased focus on socio-technical frameworks addressing regulatory and infrastructural censorship.\n\n- **Anticipated Challenges**  \n  - Balancing censorship resistance with regulatory compliance, especially in jurisdictions with stringent content controls.  \n  - Mitigating network-level censorship and denial-of-service attacks.  \n  - Ensuring scalability without compromising censorship resistance guarantees.\n\n- **Research Priorities**  \n  - Formalising censorship resistance metrics and standards.  \n  - Exploring hybrid consensus models combining leader-based and consensusless approaches.  \n  - Investigating the impact of censorship resistance on user behaviour and platform governance.\n\n## References\n\n1. Liberty Street Economics. (2025). *How Censorship Resistant Are Decentralized Systems?* Federal Reserve Bank of New York. Retrieved February 2025, from https://libertystreeteconomics.newyorkfed.org/2025/02/how-censorship-resistant-are-decentralized-systems/\n\n2. Alpos, O., David, B., Kamarinakis, N., & Zindros, D. (2025). *Consensus Protocols for Censorship Resistance and Efficiency*. arXiv preprint arXiv:2504.03588. https://doi.org/10.48550/arXiv.2504.03588\n\n3. Thiha, M., Yetgin, H., Piras, L., & Al-Obeidallah, M. G. (2025). *Enhancing Privacy, Censorship Resistance, and User Engagement in a Blockchain-Based Social Network*. SCITEPRESS Digital Library. https://doi.org/10.5220/0013238500003824\n\n\n## Metadata\n\n\n- **Migration Status**: Ontology block enriched on 2025-11-12\n- **Last Updated**: 2025-11-12\n- **Review Status**: Comprehensive editorial review\n- **Verification**: Academic sources verified\n- **Regional Context**: UK/North England where applicable",
  "properties": {
    "id": "censorship-resistance-standards",
    "collapsed": "true",
    "- domain-prefix": "BC",
    "- sequence-number": "0086",
    "- filename-history": "[\"BC-0086-censorship-resistance.md\"]",
    "- public-access": "true",
    "- ontology": "true",
    "- term-id": "BC-0086",
    "- preferred-term": "Censorship Resistance",
    "- source-domain": "metaverse",
    "- status": "complete",
    "- version": "1.0.0",
    "- last-updated": "2025-10-28",
    "- definition": "Transaction inclusion guarantee within blockchain systems, providing essential functionality for distributed ledger technology operations and properties.",
    "- maturity": "mature",
    "- source": "[[ISO/IEC 23257:2021]], [[IEEE 2418.1]], [[NIST NISTIR]]",
    "- authority-score": "0.95",
    "- owl:class": "bc:CensorshipResistance",
    "- owl:physicality": "VirtualEntity",
    "- owl:role": "Object",
    "- owl:inferred-class": "bc:VirtualObject",
    "- belongsToDomain": "[[CryptographicDomain]]",
    "- implementedInLayer": "[[SecurityLayer]]",
    "- is-subclass-of": "[[Blockchain Entity]], [[NetworkComponent]]"
  },
  "backlinks": [
    "Bitcoin Centralisation Risks",
    "Cashu",
    "Bitcoin",
    "Human Rights",
    "ecash",
    "Proof Of Authority"
  ],
  "wiki_links": [
    "Blockchain Entity",
    "ISO/IEC 23257:2021",
    "NIST NISTIR",
    "SecurityLayer",
    "CryptographicDomain",
    "IEEE 2418.1",
    "NetworkComponent"
  ],
  "ontology": {
    "term_id": "BC-0086",
    "preferred_term": "Censorship Resistance",
    "definition": "Transaction inclusion guarantee within blockchain systems, providing essential functionality for distributed ledger technology operations and properties.",
    "source_domain": "metaverse",
    "maturity_level": null,
    "authority_score": 0.95
  }
}