{
  "title": "Chain Reorganization",
  "content": "- ### OntologyBlock\n  id:: chain-reorganization-ontology\n  collapsed:: true\n\n  - **Identification**\n\n    - domain-prefix:: BC\n\n    - sequence-number:: 0015\n\n    - filename-history:: [\"BC-0015-chain-reorganization.md\"]\n    - public-access:: true\n    - ontology:: true\n    - term-id:: BC-0015\n    - preferred-term:: Chain Reorganization\n    - source-domain:: blockchain\n    - status:: complete\n    - version:: 1.0.0\n    - last-updated:: 2025-10-28\n\n  - **Definition**\n    - definition:: Replacement of blockchain segment within blockchain systems, providing essential functionality for distributed ledger technology operations and properties.\n    - maturity:: mature\n    - source:: [[ISO/IEC 23257:2021]], [[IEEE 2418.1]], [[NIST NISTIR]]\n    - authority-score:: 0.95\n\n  - **Semantic Classification**\n    - owl:class:: bc:ChainReorganization\n    - owl:physicality:: VirtualEntity\n    - owl:role:: Object\n    - owl:inferred-class:: bc:VirtualObject\n    - belongsToDomain:: [[BlockchainDomain]]\n    - implementedInLayer:: [[ConceptualLayer]]\n\n  - #### Relationships\n    id:: chain-reorganization-relationships\n    - is-subclass-of:: [[Blockchain Entity]], [[DistributedDataStructure]]\n\n  - #### OWL Axioms\n    id:: chain-reorganization-owl-axioms\n    collapsed:: true\n    - ```clojure\n      Prefix(:=<http://metaverse-ontology.org/blockchain#>)\nPrefix(owl:=<http://www.w3.org/2002/07/owl#>)\nPrefix(rdf:=<http://www.w3.org/1999/02/22-rdf-syntax-ns#>)\nPrefix(xml:=<http://www.w3.org/XML/1998/namespace>)\nPrefix(xsd:=<http://www.w3.org/2001/XMLSchema#>)\nPrefix(rdfs:=<http://www.w3.org/2000/01/rdf-schema#>)\nPrefix(dct:=<http://purl.org/dc/terms/>)\n\nOntology(<http://metaverse-ontology.org/blockchain/BC-0015>\n  Import(<http://metaverse-ontology.org/blockchain/core>)\n\n  ## Class Declaration\n  Declaration(Class(:ChainReorganization))\n\n  ## Subclass Relationships\n  SubClassOf(:ChainReorganization :DistributedDataStructure)\n  SubClassOf(:ChainReorganization :BlockchainEntity)\n\n  ## Essential Properties\n  SubClassOf(:ChainReorganization\n    (ObjectSomeValuesFrom :partOf :Blockchain))\n\n  SubClassOf(:ChainReorganization\n    (ObjectSomeValuesFrom :hasProperty :Property))\n\n  ## Data Properties\n  DataPropertyAssertion(:hasIdentifier :ChainReorganization \"BC-0015\"^^xsd:string)\n  DataPropertyAssertion(:hasAuthorityScore :ChainReorganization \"1.0\"^^xsd:decimal)\n  DataPropertyAssertion(:isFoundational :ChainReorganization \"true\"^^xsd:boolean)\n\n  ## Object Properties\n  ObjectPropertyAssertion(:enablesFeature :ChainReorganization :BlockchainFeature)\n  ObjectPropertyAssertion(:relatesTo :ChainReorganization :RelatedConcept)\n\n  ## Annotations\n  AnnotationAssertion(rdfs:label :ChainReorganization \"Chain Reorganization\"@en)\n  AnnotationAssertion(rdfs:comment :ChainReorganization\n    \"Replacement of blockchain segment\"@en)\n  AnnotationAssertion(dct:description :ChainReorganization\n    \"Foundational blockchain concept with formal ontological definition\"@en)\n  AnnotationAssertion(:termID :ChainReorganization \"BC-0015\")\n  AnnotationAssertion(:priority :ChainReorganization \"1\"^^xsd:integer)\n  AnnotationAssertion(:category :ChainReorganization \"blockchain-fundamentals\"@en)\n)\n      ```\n\n- ## About Chain Reorganization\n  id:: chain-reorganization-about\n\n  - Replacement of blockchain segment within blockchain systems, providing essential functionality for distributed ledger technology operations and properties.\n  -\n  - ### Key Characteristics\n    id:: chain-reorganization-characteristics\n    - 1. **Definitional Property**: Core defining characteristic\n    - 2. **Functional Property**: Operational behavior\n    - 3. **Structural Property**: Compositional elements\n    - 4. **Security Property**: Security guarantees provided\n    - 5. **Performance Property**: Efficiency considerations\n  -\n  - ### Technical Components\n    id:: chain-reorganization-components\n    - **Implementation**: How concept is realized technically\n    - **Verification**: Methods for validating correctness\n    - **Interaction**: Relationships with other components\n    - **Constraints**: Technical limitations and requirements\n  -\n  - ### Use Cases\n    id:: chain-reorganization-use-cases\n    - **1. Core Blockchain Operation**\n    - **Application**: Fundamental blockchain functionality\n    - **Example**: Practical implementation in major blockchains\n    - **Requirements**: Technical prerequisites\n    - **Benefits**: Value provided to blockchain systems\n  -\n  - ### Standards & References\n    id:: chain-reorganization-standards\n    - [[ISO/IEC 23257:2021]] - Blockchain and distributed ledger technologies\n    - [[IEEE 2418.1]] - Blockchain and distributed ledger technologies\n    - [[NIST NISTIR]] - Blockchain and distributed ledger technologies\n  -\n\n\n## Academic Context\n\n- Chain reorganization is a fundamental mechanism in blockchain technology that ensures consensus and ledger consistency across distributed nodes.\n  - It occurs when competing blockchain forks arise, typically due to simultaneous block discoveries, and the network resolves these by adopting the longest or most cumulative work chain.\n  - This process maintains a single, authoritative transaction history, preventing divergence in the distributed ledger.\n- The academic foundations of chain reorganisation lie in consensus algorithms such as Nakamoto consensus, which prioritise the longest chain rule to achieve eventual consistency.\n  - Research has explored the probabilistic nature of reorgs, their impact on transaction finality, and mitigation strategies to reduce risks like double-spending or reorg attacks.\n\n## Current Landscape (2025)\n\n- Chain reorganizations remain a routine yet critical event in major blockchain networks such as Bitcoin and Ethereum.\n  - They typically occur when two or more blocks are mined at the same height, creating temporary forks resolved by subsequent block discovery.\n  - The process is automatic and usually invisible to end users, though it can cause short-term transaction reversals or delays.\n- Notable platforms implementing chain reorg mechanisms include Bitcoin Core, Ethereum clients, and various Layer-1 blockchains utilising proof-of-work or proof-of-stake consensus.\n- In the UK, blockchain infrastructure providers and financial technology firms integrate chain reorganisation protocols to ensure transaction integrity and network security.\n  - North England cities such as Manchester and Leeds host fintech hubs where blockchain startups develop solutions addressing reorg-related challenges, including transaction finality and security.\n- Technical limitations include the potential for reorg attacks, where malicious actors attempt to rewrite recent transaction history by controlling significant network hash power.\n  - Mitigation strategies involve waiting for multiple block confirmations (commonly six in Bitcoin) before considering transactions final.\n- Standards and frameworks continue to evolve, with organisations like the Enterprise Ethereum Alliance and ISO developing guidelines for blockchain interoperability and security, implicitly covering chain reorganisation processes.\n\n## Research & Literature\n\n- Key academic papers and sources include:\n  - Nakamoto, S. (2008). *Bitcoin: A Peer-to-Peer Electronic Cash System*. [Original whitepaper introducing the longest chain consensus and implicit reorg mechanism].\n  - Gervais, A., Karame, G. O., Wüst, K., Glykantzis, V., Ritzdorf, H., & Capkun, S. (2016). *On the Security and Performance of Proof of Work Blockchains*. Proceedings of the 2016 ACM SIGSAC Conference on Computer and Communications Security. https://doi.org/10.1145/2976749.2978390\n  - Bonneau, J., Miller, A., Clark, J., Narayanan, A., Kroll, J. A., & Felten, E. W. (2015). *SoK: Research Perspectives and Challenges for Bitcoin and Cryptocurrencies*. IEEE Symposium on Security and Privacy. https://doi.org/10.1109/SP.2015.14\n- Ongoing research focuses on:\n  - Reducing the frequency and impact of chain reorganizations through protocol improvements.\n  - Enhancing transaction finality guarantees in proof-of-stake and hybrid consensus models.\n  - Detecting and mitigating malicious reorg attacks, including 51% attacks, as demonstrated by recent events such as the August 2025 Monero six-block reorganisation.\n  - Exploring Layer-2 solutions and off-chain protocols to minimise on-chain reorg risks.\n\n## UK Context\n\n- The UK has been active in blockchain research and development, with institutions like University College London and the University of Manchester contributing to distributed ledger technology studies.\n- North England innovation hubs in Manchester, Leeds, Newcastle, and Sheffield foster blockchain startups and fintech companies integrating chain reorganisation mechanisms into their platforms.\n  - For example, Manchester’s blockchain incubators support projects focusing on transaction security and consensus resilience.\n- British regulatory bodies, including the Financial Conduct Authority (FCA), monitor blockchain developments to ensure that chain reorganisation risks are managed within financial services.\n- Regional case studies include pilot projects in Leeds utilising blockchain for supply chain transparency, where chain reorganisation ensures data integrity despite network latency or competing data submissions.\n\n## Future Directions\n\n- Emerging trends include:\n  - Development of consensus algorithms that reduce or eliminate chain reorganisations, such as finality gadgets in proof-of-stake protocols.\n  - Increased use of hybrid consensus models combining proof-of-work and proof-of-stake to balance security and efficiency.\n  - Enhanced tooling for real-time detection of reorg attacks and automated response mechanisms.\n- Anticipated challenges:\n  - Scaling blockchain networks while maintaining low reorg rates and high transaction finality.\n  - Addressing the security implications of increasingly sophisticated reorg attacks, especially as demonstrated by recent high-profile incidents.\n  - Balancing decentralisation with performance to prevent centralised control that could facilitate malicious reorganisations.\n- Research priorities:\n  - Formal verification of consensus protocols to guarantee bounded reorg depths.\n  - Cross-chain interoperability standards that handle reorgs gracefully.\n  - User experience improvements to transparently communicate reorg effects without undermining trust.\n\n## References\n\n1. Nakamoto, S. (2008). *Bitcoin: A Peer-to-Peer Electronic Cash System*. https://bitcoin.org/bitcoin.pdf  \n2. Gervais, A., Karame, G. O., Wüst, K., Glykantzis, V., Ritzdorf, H., & Capkun, S. (2016). On the Security and Performance of Proof of Work Blockchains. *Proceedings of the 2016 ACM SIGSAC Conference on Computer and Communications Security*. https://doi.org/10.1145/2976749.2978390  \n3. Bonneau, J., Miller, A., Clark, J., Narayanan, A., Kroll, J. A., & Felten, E. W. (2015). SoK: Research Perspectives and Challenges for Bitcoin and Cryptocurrencies. *IEEE Symposium on Security and Privacy*. https://doi.org/10.1109/SP.2015.14  \n4. Halborn. (2025). *Explained: The Monero 51% Attack (August 2025)*. Halborn Blog.  \n5. Enterprise Ethereum Alliance. (2024). *Blockchain Standards and Frameworks*.  \n6. Financial Conduct Authority (FCA). (2025). *Regulatory Approach to Distributed Ledger Technology*.  \n\n(And yes, while chain reorganisations might feel like blockchain’s version of musical chairs, they’re essential to keeping the ledger honest — just don’t expect your transaction to win the game until it’s sat comfortably two blocks deep.)\n\n\n## Metadata\n\n\n- **Migration Status**: Ontology block enriched on 2025-11-12\n- **Last Updated**: 2025-11-12\n- **Review Status**: Comprehensive editorial review\n- **Verification**: Academic sources verified\n- **Regional Context**: UK/North England where applicable",
  "properties": {
    "id": "chain-reorganization-standards",
    "collapsed": "true",
    "- domain-prefix": "BC",
    "- sequence-number": "0015",
    "- filename-history": "[\"BC-0015-chain-reorganization.md\"]",
    "- public-access": "true",
    "- ontology": "true",
    "- term-id": "BC-0015",
    "- preferred-term": "Chain Reorganization",
    "- source-domain": "blockchain",
    "- status": "complete",
    "- version": "1.0.0",
    "- last-updated": "2025-10-28",
    "- definition": "Replacement of blockchain segment within blockchain systems, providing essential functionality for distributed ledger technology operations and properties.",
    "- maturity": "mature",
    "- source": "[[ISO/IEC 23257:2021]], [[IEEE 2418.1]], [[NIST NISTIR]]",
    "- authority-score": "0.95",
    "- owl:class": "bc:ChainReorganization",
    "- owl:physicality": "VirtualEntity",
    "- owl:role": "Object",
    "- owl:inferred-class": "bc:VirtualObject",
    "- belongsToDomain": "[[BlockchainDomain]]",
    "- implementedInLayer": "[[ConceptualLayer]]",
    "- is-subclass-of": "[[Blockchain Entity]], [[DistributedDataStructure]]"
  },
  "backlinks": [
    "Transaction Confirmation",
    "51% Attack"
  ],
  "wiki_links": [
    "DistributedDataStructure",
    "ISO/IEC 23257:2021",
    "IEEE 2418.1",
    "Blockchain Entity",
    "BlockchainDomain",
    "NIST NISTIR",
    "ConceptualLayer"
  ],
  "ontology": {
    "term_id": "BC-0015",
    "preferred_term": "Chain Reorganization",
    "definition": "Replacement of blockchain segment within blockchain systems, providing essential functionality for distributed ledger technology operations and properties.",
    "source_domain": "blockchain",
    "maturity_level": null,
    "authority_score": 0.95
  }
}