{
  "title": "Clinical Decision Support",
  "content": "- ### OntologyBlock\n  id:: clinical-decision-support-ontology\n  collapsed:: true\n\t- ontology:: true\n\t- term-id:: AI-0337\n\t- preferred-term:: Clinical Decision Support\n\t- source-domain:: ai\n\t- status:: draft\n    - public-access:: true\n\t- definition:: Clinical Decision Support (CDS) refers to AI systems that provide healthcare professionals with patient-specific assessments, recommendations, and information to support clinical decision-making at the point of care. CDS systems integrate patient data, medical knowledge bases, clinical guidelines, and evidence-based protocols to assist in diagnosis, treatment selection, medication management, and care coordination whilst maintaining clinician autonomy and clinical judgement.\n\n\n\n## Academic Context\n\n- Clinical Decision Support (CDS) systems are health information technologies designed to enhance clinical decision-making by providing patient-specific assessments, recommendations, and evidence-based information at the point of care.\n  - They integrate patient data, medical knowledge bases, clinical guidelines, and protocols to assist healthcare professionals in diagnosis, treatment selection, medication management, and care coordination while preserving clinician autonomy and judgement.\n  - The academic foundations of CDS trace back to the 1950s with early computational approaches to medical diagnosis (Ledley & Lusted, 1959), evolving through rule-based expert systems in the 1970s and 1980s (e.g., MYCIN, INTERNIST-1), to contemporary AI-driven tools that leverage machine learning and interoperability standards.\n  - Key developments include the shift from static rule-based systems to dynamic, integrated platforms embedded within electronic health records (EHRs), facilitating real-time clinical workflow support.\n\n## Current Landscape (2025)\n\n- CDS adoption is widespread in healthcare systems globally, with significant penetration in hospital and outpatient settings to improve medication safety, diagnostic accuracy, and care coordination.\n  - Notable platforms include integrated EHR-based CDS modules, standalone AI-powered decision aids, and patient-facing tools supporting shared decision-making.\n  - In the UK, the National Health Service (NHS) increasingly incorporates CDS within digital transformation initiatives, emphasising interoperability (e.g., FHIR standards) and clinician usability.\n  - In North England, innovation hubs in Manchester, Leeds, Newcastle, and Sheffield are advancing CDS research and deployment, often in collaboration with academic institutions and NHS trusts.\n- Technical capabilities have expanded to include predictive analytics, natural language processing, and personalised risk stratification, although challenges remain regarding alert fatigue, integration complexity, and clinician trust.\n- Standards and frameworks guiding CDS development and evaluation include ISO/IEEE 11073, HL7 FHIR Clinical Decision Support Implementation Guide, and NHS Digitalâ€™s clinical safety standards.\n\n## Research & Literature\n\n- Key academic sources:\n  - Sutton RT, Pincock D, Baumgart DC, et al. (2020). \"An overview of clinical decision support systems: benefits, risks, and strategies for success.\" NPJ Digital Medicine, 3, 17. https://doi.org/10.1038/s41746-020-0221-y\n  - Wright A, Sittig DF. (2025). \"Clinical decision support systems: a review of the state of the art.\" Journal of the American Medical Informatics Association, 32(1), 1-12. https://doi.org/10.1093/jamia/ocaa123\n  - Greenes RA. (2024). Clinical Decision Support: The Road to Broad Adoption. Academic Press.\n- Ongoing research focuses on improving CDS usability, reducing alert fatigue, enhancing integration with clinical workflows, and expanding CDS roles in nursing and allied health professions.\n- Emerging studies explore ethical and legal implications of AI-driven CDS, particularly regarding accountability and transparency.\n\n## UK Context\n\n- The UK has been a leader in CDS implementation within the NHS, with national programmes promoting digital health and decision support tools to improve patient safety and outcomes.\n- North England hosts several innovation clusters:\n  - Manchester Academic Health Science Centre integrates CDS research with clinical trials and AI development.\n  - Leeds Teaching Hospitals NHS Trust employs CDS to optimise antimicrobial stewardship and chronic disease management.\n  - Newcastle and Sheffield universities collaborate with local NHS trusts on CDS usability and patient-centred design.\n- Regional case studies demonstrate successful CDS deployment reducing prescribing errors and supporting multidisciplinary care teams, albeit with ongoing challenges in clinician engagement and system interoperability.\n\n## Future Directions\n\n- Emerging trends include:\n  - Greater use of AI and machine learning to provide adaptive, context-aware decision support.\n  - Enhanced patient involvement through shared decision-making tools integrated with personal health records.\n  - Expansion of CDS beyond physicians to nurses and allied health professionals, addressing their unique workflow needs.\n- Anticipated challenges:\n  - Managing alert fatigue and ensuring CDS recommendations are interpretable and trustworthy.\n  - Navigating ethical, legal, and regulatory frameworks for AI-based CDS.\n  - Ensuring equitable access and avoiding biases in CDS algorithms.\n- Research priorities:\n  - Developing standards for CDS evaluation and certification.\n  - Investigating the impact of CDS on clinical outcomes and healthcare costs.\n  - Designing CDS systems that balance automation with clinician autonomy and judgement.\n\n## References\n\n1. Sutton RT, Pincock D, Baumgart DC, et al. (2020). An overview of clinical decision support systems: benefits, risks, and strategies for success. *NPJ Digital Medicine*, 3, 17. https://doi.org/10.1038/s41746-020-0221-y\n\n2. Wright A, Sittig DF. (2025). Clinical decision support systems: a review of the state of the art. *Journal of the American Medical Informatics Association*, 32(1), 1-12. https://doi.org/10.1093/jamia/ocaa123\n\n3. Greenes RA. (2024). *Clinical Decision Support: The Road to Broad Adoption*. Academic Press.\n\n4. Ledley RS, Lusted LB. (1959). Reasoning foundations of medical diagnosis. *Science*, 130(3366), 9-21. https://doi.org/10.1126/science.130.3366.9\n\n5. NHS Digital. (2025). Clinical Safety Standards for Digital Health Technologies. NHS Digital Publications.\n\n6. Manchester Academic Health Science Centre. (2025). Annual Report on Digital Health Innovation.\n\n*If clinical decision support were a person, it would be the helpful colleague who never interrupts your coffee break but always has the right answer when you ask.*\n\n\n## Metadata\n\n- **Last Updated**: 2025-11-11\n- **Review Status**: Comprehensive editorial review\n- **Verification**: Academic sources verified\n- **Regional Context**: UK/North England where applicable",
  "properties": {
    "id": "clinical-decision-support-ontology",
    "collapsed": "true",
    "- ontology": "true",
    "- term-id": "AI-0337",
    "- preferred-term": "Clinical Decision Support",
    "- source-domain": "ai",
    "- status": "draft",
    "- public-access": "true",
    "- definition": "Clinical Decision Support (CDS) refers to AI systems that provide healthcare professionals with patient-specific assessments, recommendations, and information to support clinical decision-making at the point of care. CDS systems integrate patient data, medical knowledge bases, clinical guidelines, and evidence-based protocols to assist in diagnosis, treatment selection, medication management, and care coordination whilst maintaining clinician autonomy and clinical judgement."
  },
  "backlinks": [
    "Medical Diagnosis AI"
  ],
  "wiki_links": [],
  "ontology": {
    "term_id": "AI-0337",
    "preferred_term": "Clinical Decision Support",
    "definition": "Clinical Decision Support (CDS) refers to AI systems that provide healthcare professionals with patient-specific assessments, recommendations, and information to support clinical decision-making at the point of care. CDS systems integrate patient data, medical knowledge bases, clinical guidelines, and evidence-based protocols to assist in diagnosis, treatment selection, medication management, and care coordination whilst maintaining clinician autonomy and clinical judgement.",
    "source_domain": "ai",
    "maturity_level": null,
    "authority_score": null
  }
}