{
  "title": "Cognitive Feedback Interface",
  "content": "- ### OntologyBlock\n  id:: cognitive-feedback-interface-ontology\n  collapsed:: true\n\t- ontology:: true\n\t- term-id:: 20252\n\t- source-domain:: metaverse\n\t- status:: draft\n\t- public-access:: true\n\n\n## Academic Context\n\n- Cognitive feedback interfaces are adaptive systems that dynamically tailor information presentation and interaction modes by assessing users' cognitive states, attention, and mental workload in real time.\n  - These systems build upon cognitive psychology, human-computer interaction (HCI), and neuroadaptive learning foundations.\n  - Key developments include integration of physiological monitoring (e.g., EEG, eye-tracking) and AI-driven analytics to personalise user experience and optimise cognitive load management.\n  - The academic foundation rests on cognitive load theory, cognitive task analysis, and adaptive feedback mechanisms that enhance learning and task performance.\n\n## Current Landscape (2025)\n\n- Industry adoption spans education, professional training, and user experience design, with adaptive feedback systems increasingly embedded in Learning Management Systems (LMS) and interactive platforms.\n  - Notable implementations include multi-modal interfaces combining gaze tracking and gesture control, which have demonstrated comparable or improved information retention and user satisfaction relative to traditional input methods.\n  - UK organisations, particularly in North England, such as research groups in Manchester and Leeds, contribute to advancing cognitive feedback technologies through collaborations between universities and tech companies.\n- Technical capabilities now include real-time cognitive state monitoring using neurophysiological sensors and AI algorithms that adjust interface complexity and feedback dynamically.\n- Limitations remain in sensor accuracy, user privacy concerns, and the challenge of balancing adaptivity without causing distraction or cognitive overload.\n- Standards and frameworks are emerging around ethical AI use, data privacy, and interoperability of cognitive feedback modules within broader digital ecosystems.\n\n## Research & Literature\n\n- Key academic papers:\n  - Luque De La Rosa, A., Vargas Serrano, A., & Gallardo Herrerías, C. (2025). *Challenging Cognitive Load Theory: The Role of Educational Neuroscience and AI in Adaptive Learning*. Brain Sciences, 15(2), 203. https://doi.org/10.3390/brainsci15020203\n  - Shenakht Journal of Psychology and Psychiatry (2024). *An Empirical Study of Adaptive Feedback to Enhance Cognitive Ability in Programming Learners*, 5(3), 66–80. https://doi.org/10.29252/shenakht.5.3.66\n  - Recent Nature publication (2025). *An Adaptive Feedback System for the Improvement of Learners*. Nature Scientific Reports. https://doi.org/10.1038/s41598-025-01429-w\n  - Research on multi-modal gaze and gesture interfaces demonstrating cognitive load effects and usability equivalence to traditional interfaces (arXiv, 2025).\n- Ongoing research focuses on improving sensor integration, refining AI models for cognitive state inference, and addressing ethical concerns such as data privacy and algorithmic bias.\n\n## UK Context\n\n- The UK has been active in cognitive feedback interface research, with notable contributions from universities in Manchester, Leeds, Newcastle, and Sheffield.\n  - Manchester’s Human Factors and Cognitive Engineering groups have developed neuroadaptive interfaces for industrial and educational applications.\n  - Leeds has pioneered AI-driven adaptive learning platforms integrating cognitive load monitoring.\n  - Newcastle and Sheffield host innovation hubs focusing on multimodal interaction technologies and user-centred design.\n- Regional case studies include pilot deployments of adaptive LMS modules in North England schools and professional training centres, demonstrating improved learner engagement and performance.\n- The UK’s regulatory environment emphasises ethical AI deployment and data protection, influencing design and implementation practices.\n\n## Future Directions\n\n- Emerging trends include:\n  - Greater integration of multimodal sensors (e.g., EEG, eye-tracking, gesture) for richer cognitive state assessment.\n  - Enhanced AI models capable of predicting cognitive fatigue and dynamically adjusting interface complexity preemptively.\n  - Expansion beyond education into healthcare, automotive, and workplace safety domains.\n- Anticipated challenges:\n  - Balancing adaptivity with user autonomy to avoid overdependence or frustration.\n  - Ensuring equitable access and mitigating biases in AI-driven feedback.\n  - Addressing privacy and ethical concerns in real-time cognitive monitoring.\n- Research priorities:\n  - Developing standardised protocols for cognitive state measurement and adaptive feedback.\n  - Longitudinal studies on cognitive feedback impact on learning and productivity.\n  - Cross-disciplinary collaboration between cognitive scientists, AI researchers, and UX designers.\n\n## References\n\n1. Luque De La Rosa, A., Vargas Serrano, A., & Gallardo Herrerías, C. (2025). Challenging Cognitive Load Theory: The Role of Educational Neuroscience and AI in Adaptive Learning. *Brain Sciences*, 15(2), 203. https://doi.org/10.3390/brainsci15020203  \n2. Shenakht Journal of Psychology and Psychiatry. (2024). An Empirical Study of Adaptive Feedback to Enhance Cognitive Ability in Programming Learners, 5(3), 66–80. https://doi.org/10.29252/shenakht.5.3.66  \n3. Nature Scientific Reports. (2025). An Adaptive Feedback System for the Improvement of Learners. https://doi.org/10.1038/s41598-025-01429-w  \n4. arXiv. (2025). How Multi-modal Interfaces and Cognitive Load Alter Information Retention and Usability. https://arxiv.org/html/2509.05898v1\n\n\n## Metadata\n\n- **Last Updated**: 2025-11-11\n- **Review Status**: Comprehensive editorial review\n- **Verification**: Academic sources verified\n- **Regional Context**: UK/North England where applicable",
  "properties": {
    "id": "cognitive-feedback-interface-ontology",
    "collapsed": "true",
    "- ontology": "true",
    "- term-id": "20252",
    "- source-domain": "metaverse",
    "- status": "draft",
    "- public-access": "true"
  },
  "backlinks": [],
  "wiki_links": [],
  "ontology": {
    "term_id": "20252",
    "preferred_term": "Cognitive Feedback Interface",
    "definition": "",
    "source_domain": "metaverse",
    "maturity_level": null,
    "authority_score": null
  }
}