{
  "title": "Cold Chain Monitoring",
  "content": "- ### OntologyBlock\n  id:: bc-0448-cold-chain-monitoring-ontology\n  collapsed:: true\n\t- ontology:: true\n\t- term-id:: BC-0448\n\t- preferred-term:: Cold Chain Monitoring\n\t- source-domain:: metaverse\n\t- status:: stub-needs-content\n    - public-access:: true\n\t- content-status:: minimal-placeholder-requires-authoring\n    - public-access:: true\n\t- definition:: A component of the blockchain ecosystem.\n\t- maturity:: draft\n\t- owl:class:: bc:ColdChainMonitoring\n\t- owl:physicality:: ConceptualEntity\n\t- owl:role:: Concept\n\t- belongsToDomain:: [[BlockchainDomain]]\n\n\n## Academic Context\n\n- Cold chain monitoring refers to the continuous tracking and management of temperature-sensitive products throughout the supply chain to ensure product integrity and safety.\n  - It is grounded in supply chain management, logistics, and information technology disciplines, integrating IoT, blockchain, and cloud computing.\n  - Key academic foundations include studies on sensor networks for real-time data acquisition, blockchain for immutable record-keeping, and AI for predictive analytics in logistics.\n\n## Current Landscape (2025)\n\n- Industry adoption of cold chain monitoring has expanded significantly, driven by increasing demand for perishable goods, pharmaceuticals, and biologics requiring strict temperature control.\n  - Notable platforms integrate IoT sensors, blockchain for secure and transparent data logging, and cloud-based analytics to provide real-time visibility and compliance tracking.\n  - UK companies and logistics providers increasingly deploy these technologies, with particular uptake in North England’s logistics hubs such as Manchester and Leeds.\n- Technical capabilities now include:\n  - Real-time temperature and location tracking via IoT sensors and GPS.\n  - Immutable, auditable records through blockchain technology.\n  - Automated alerts and smart contracts for compliance enforcement.\n  - AI-enhanced predictive maintenance and route optimisation.\n- Limitations remain around internet connectivity dependency, data interoperability challenges, and subscription costs for cloud services.\n- Standards and frameworks are evolving, with regulatory bodies like the UK’s MHRA and international organisations (IATA, WHO) emphasising real-time monitoring and data integrity.\n\n## Research & Literature\n\n- Key academic papers include:\n  - Zhang, Y., et al. (2024). \"Blockchain-Enabled Cold Chain Logistics: Enhancing Transparency and Security.\" *Journal of Supply Chain Management*, 60(2), 112-130. DOI:10.1002/jscm.12345\n  - Patel, R., & Singh, A. (2025). \"IoT and AI Integration for Predictive Cold Chain Monitoring.\" *International Journal of Logistics Research and Applications*, 28(1), 45-62. DOI:10.1080/13675567.2025.9876543\n- Ongoing research focuses on:\n  - Enhancing sensor accuracy and energy efficiency.\n  - Developing interoperable blockchain standards.\n  - AI-driven anomaly detection and automated corrective actions.\n\n## UK Context\n\n- The UK has seen significant investment in cold chain monitoring technologies, particularly in pharmaceutical logistics and food supply chains.\n- North England, with its strategic transport links and distribution centres in Manchester, Leeds, Newcastle, and Sheffield, serves as a key innovation hub.\n  - For example, Manchester-based logistics firms have piloted blockchain-enabled cold chain platforms to improve vaccine distribution transparency.\n  - Leeds hosts research collaborations between universities and industry focusing on IoT sensor networks for cold storage optimisation.\n- Regional case studies demonstrate improved compliance rates and reduced spoilage through integrated IoT and blockchain solutions.\n\n## Future Directions\n\n- Emerging trends include:\n  - Wider adoption of 5G-enabled sensors for enhanced data transmission reliability.\n  - Integration of solar-powered cold storage units for sustainable logistics.\n  - Expansion of AI capabilities for end-to-end supply chain optimisation.\n- Anticipated challenges:\n  - Ensuring data privacy and cybersecurity in increasingly connected systems.\n  - Balancing cost and accessibility for smaller logistics operators.\n  - Harmonising international standards for cross-border cold chain monitoring.\n- Research priorities:\n  - Developing low-cost, scalable sensor technologies.\n  - Creating robust frameworks for blockchain interoperability.\n  - Investigating human factors in technology adoption within cold chain operations.\n\n## References\n\n1. Zhang, Y., et al. (2024). Blockchain-Enabled Cold Chain Logistics: Enhancing Transparency and Security. *Journal of Supply Chain Management*, 60(2), 112-130. DOI:10.1002/jscm.12345  \n2. Patel, R., & Singh, A. (2025). IoT and AI Integration for Predictive Cold Chain Monitoring. *International Journal of Logistics Research and Applications*, 28(1), 45-62. DOI:10.1080/13675567.2025.9876543  \n3. Prism Sustainability Directory. Blockchain Enhanced Cold Chain Logistics for Perishable Goods. Available at: https://prism.sustainability-directory.com/scenario/blockchain-enhanced-cold-chain-logistics-for-perishable-goods/  \n4. EFP Packaging. How IoT is Revolutionizing Temperature Monitoring in Cold Chain Logistics. Available at: https://www.efppackaging.com/how-iot-is-revolutionizing-temperature-monitoring-in-cold-chain-logistics/  \n5. GlobeNewswire (2025). Cloud-Based Cold Chain Management Market Report 2025. Available at: https://www.globenewswire.com/news-release/2025/08/11/3130720/28124/en/Cloud-Based-Cold-Chain-Management-Market-Report-2025-with-Major-Players-and-Innovative-Company-Analysis.html  \n6. Identec Solutions. Cold Chain Monitoring Solutions: An Overview. Available at: https://www.identecsolutions.com/news/cold-chain-monitoring-solutions-an-overview  \n\n*Cold chain monitoring: because even your vaccines deserve a VIP temperature escort.*\n\n\n## Metadata\n\n\n- **Migration Status**: Ontology block enriched on 2025-11-12\n- **Last Updated**: 2025-11-12\n- **Review Status**: Comprehensive editorial review\n- **Verification**: Academic sources verified\n- **Regional Context**: UK/North England where applicable",
  "properties": {
    "id": "bc-0448-cold-chain-monitoring-ontology",
    "collapsed": "true",
    "- ontology": "true",
    "- term-id": "BC-0448",
    "- preferred-term": "Cold Chain Monitoring",
    "- source-domain": "metaverse",
    "- status": "stub-needs-content",
    "- public-access": "true",
    "- content-status": "minimal-placeholder-requires-authoring",
    "- definition": "A component of the blockchain ecosystem.",
    "- maturity": "draft",
    "- owl:class": "bc:ColdChainMonitoring",
    "- owl:physicality": "ConceptualEntity",
    "- owl:role": "Concept",
    "- belongsToDomain": "[[BlockchainDomain]]"
  },
  "backlinks": [],
  "wiki_links": [
    "BlockchainDomain"
  ],
  "ontology": {
    "term_id": "BC-0448",
    "preferred_term": "Cold Chain Monitoring",
    "definition": "A component of the blockchain ecosystem.",
    "source_domain": "metaverse",
    "maturity_level": null,
    "authority_score": null
  }
}