{
  "title": "Collision Resistance",
  "content": "- ### OntologyBlock\n  id:: collision-resistance-ontology\n  collapsed:: true\n\n  - **Identification**\n\n    - domain-prefix:: BC\n\n    - sequence-number:: 0048\n\n    - filename-history:: [\"BC-0048-collision-resistance.md\"]\n    - public-access:: true\n    - ontology:: true\n    - term-id:: BC-0048\n    - preferred-term:: Collision Resistance\n    - source-domain:: blockchain\n    - status:: complete\n    - version:: 1.0.0\n    - last-updated:: 2025-10-28\n\n  - **Definition**\n    - definition:: Hash function security property within blockchain systems, providing essential functionality for distributed ledger technology operations and properties.\n    - maturity:: mature\n    - source:: [[ISO/IEC 23257:2021]], [[IEEE 2418.1]], [[NIST NISTIR]]\n    - authority-score:: 0.95\n\n  - **Semantic Classification**\n    - owl:class:: bc:CollisionResistance\n    - owl:physicality:: VirtualEntity\n    - owl:role:: Object\n    - owl:inferred-class:: bc:VirtualObject\n    - belongsToDomain:: [[CryptographicDomain]]\n    - implementedInLayer:: [[SecurityLayer]]\n\n  - #### Relationships\n    id:: collision-resistance-relationships\n    - is-subclass-of:: [[Blockchain Entity]], [[CryptographicPrimitive]]\n\n  - #### OWL Axioms\n    id:: collision-resistance-owl-axioms\n    collapsed:: true\n    - ```clojure\n      Prefix(:=<http://metaverse-ontology.org/blockchain#>)\nPrefix(owl:=<http://www.w3.org/2002/07/owl#>)\nPrefix(rdf:=<http://www.w3.org/1999/02/22-rdf-syntax-ns#>)\nPrefix(xml:=<http://www.w3.org/XML/1998/namespace>)\nPrefix(xsd:=<http://www.w3.org/2001/XMLSchema#>)\nPrefix(rdfs:=<http://www.w3.org/2000/01/rdf-schema#>)\nPrefix(dct:=<http://purl.org/dc/terms/>)\n\nOntology(<http://metaverse-ontology.org/blockchain/BC-0048>\n  Import(<http://metaverse-ontology.org/blockchain/core>)\n\n  ## Class Declaration\n  Declaration(Class(:CollisionResistance))\n\n  ## Subclass Relationships\n  SubClassOf(:CollisionResistance :CryptographicPrimitive)\n  SubClassOf(:CollisionResistance :BlockchainEntity)\n\n  ## Essential Properties\n  SubClassOf(:CollisionResistance\n    (ObjectSomeValuesFrom :partOf :Blockchain))\n\n  SubClassOf(:CollisionResistance\n    (ObjectSomeValuesFrom :hasProperty :Property))\n\n  ## Data Properties\n  DataPropertyAssertion(:hasIdentifier :CollisionResistance \"BC-0048\"^^xsd:string)\n  DataPropertyAssertion(:hasAuthorityScore :CollisionResistance \"1.0\"^^xsd:decimal)\n  DataPropertyAssertion(:isFoundational :CollisionResistance \"true\"^^xsd:boolean)\n\n  ## Object Properties\n  ObjectPropertyAssertion(:enablesFeature :CollisionResistance :BlockchainFeature)\n  ObjectPropertyAssertion(:relatesTo :CollisionResistance :RelatedConcept)\n\n  ## Annotations\n  AnnotationAssertion(rdfs:label :CollisionResistance \"Collision Resistance\"@en)\n  AnnotationAssertion(rdfs:comment :CollisionResistance\n    \"Hash function security property\"@en)\n  AnnotationAssertion(dct:description :CollisionResistance\n    \"Foundational blockchain concept with formal ontological definition\"@en)\n  AnnotationAssertion(:termID :CollisionResistance \"BC-0048\")\n  AnnotationAssertion(:priority :CollisionResistance \"1\"^^xsd:integer)\n  AnnotationAssertion(:category :CollisionResistance \"cryptographic-foundations\"@en)\n)\n      ```\n\n- ## About Collision Resistance\n  id:: collision-resistance-about\n\n  - Hash function security property within blockchain systems, providing essential functionality for distributed ledger technology operations and properties.\n  -\n  - ### Key Characteristics\n    id:: collision-resistance-characteristics\n    - 1. **Definitional Property**: Core defining characteristic\n    - 2. **Functional Property**: Operational behavior\n    - 3. **Structural Property**: Compositional elements\n    - 4. **Security Property**: Security guarantees provided\n    - 5. **Performance Property**: Efficiency considerations\n  -\n  - ### Technical Components\n    id:: collision-resistance-components\n    - **Implementation**: How concept is realized technically\n    - **Verification**: Methods for validating correctness\n    - **Interaction**: Relationships with other components\n    - **Constraints**: Technical limitations and requirements\n  -\n  - ### Use Cases\n    id:: collision-resistance-use-cases\n    - **1. Core Blockchain Operation**\n    - **Application**: Fundamental blockchain functionality\n    - **Example**: Practical implementation in major blockchains\n    - **Requirements**: Technical prerequisites\n    - **Benefits**: Value provided to blockchain systems\n  -\n  - ### Standards & References\n    id:: collision-resistance-standards\n    - [[ISO/IEC 23257:2021]] - Blockchain and distributed ledger technologies\n    - [[IEEE 2418.1]] - Blockchain and distributed ledger technologies\n    - [[NIST NISTIR]] - Blockchain and distributed ledger technologies\n  -\n\n\n## Academic Context\n\n- Collision resistance is a fundamental property of cryptographic hash functions ensuring it is computationally infeasible to find two distinct inputs producing the same hash output.\n  - This property underpins data integrity, digital signatures, and blockchain security by preventing malicious data manipulation.\n  - The concept emerged from foundational cryptographic research in the 1980s, notably the Merkle-Damgård construction, which influenced hash algorithms like MD5, SHA-1, and SHA-2.\n  - Collision resistance is one of three core hash function security properties, alongside preimage and second preimage resistance.\n\n## Current Landscape (2025)\n\n- Collision resistance remains critical in industry, especially in financial technology, cybersecurity, and blockchain platforms.\n  - Organisations such as major UK banks and fintech firms in London and Manchester rely on collision-resistant hashes to secure transactions.\n  - Blockchain projects in Leeds and Newcastle increasingly adopt SHA-3 and other advanced hash functions to mitigate vulnerabilities found in older algorithms like MD5 and SHA-1.\n- Technical capabilities have improved with newer hash functions offering stronger collision resistance, though the \"birthday paradox\" still sets theoretical limits on collision resistance based on output size.\n- Standards such as NIST SP 800-107 Rev. 1 continue to guide secure hash function design and evaluation, emphasising collision resistance as a key criterion.\n\n## Research & Literature\n\n- Seminal papers and authoritative sources include:\n  - Merkle, R. C. (1989). \"A Certified Digital Signature.\" *Advances in Cryptology — CRYPTO '89 Proceedings*. DOI: 10.1007/3-540-46885-4_32\n  - Damgård, I. (1989). \"A Design Principle for Hash Functions.\" *Advances in Cryptology — CRYPTO '89 Proceedings*. DOI: 10.1007/3-540-46885-4_31\n  - Wang, X., Yin, Y. L., & Yu, H. (2005). \"Finding Collisions in the Full SHA-1.\" *Advances in Cryptology — CRYPTO 2005*. DOI: 10.1007/11535218_3\n  - National Institute of Standards and Technology (NIST). (2020). *NIST SP 800-107 Rev. 1: Recommendation for Applications Using Approved Hash Algorithms*. Available at NIST website.\n- Ongoing research focuses on developing hash functions resistant to quantum attacks and improving efficiency without compromising collision resistance.\n\n## UK Context\n\n- The UK has contributed significantly to cryptographic research, with institutions such as the University of Manchester and University of Leeds hosting leading cryptography groups.\n  - Manchester’s Centre for Doctoral Training in Cyber Security and Privacy explores hash function security and collision resistance.\n  - Leeds-based fintech startups integrate collision-resistant hashing in blockchain applications to enhance transaction security.\n- Regional innovation hubs in Newcastle and Sheffield support cybersecurity initiatives that leverage collision resistance for secure data systems.\n- UK government agencies advocate for adoption of collision-resistant algorithms in national cybersecurity frameworks.\n\n## Future Directions\n\n- Emerging trends include quantum-resistant hash functions and hybrid cryptographic schemes combining classical and post-quantum algorithms.\n- Anticipated challenges involve balancing collision resistance with computational efficiency and adapting standards to evolving threat landscapes.\n- Research priorities emphasise provable security models, real-world cryptanalysis, and practical deployment in resource-constrained environments.\n\n## References\n\n1. Merkle, R. C. (1989). A Certified Digital Signature. *Advances in Cryptology — CRYPTO '89 Proceedings*, 218–238. DOI: 10.1007/3-540-46885-4_32  \n2. Damgård, I. (1989). A Design Principle for Hash Functions. *Advances in Cryptology — CRYPTO '89 Proceedings*, 416–427. DOI: 10.1007/3-540-46885-4_31  \n3. Wang, X., Yin, Y. L., & Yu, H. (2005). Finding Collisions in the Full SHA-1. *Advances in Cryptology — CRYPTO 2005*, 17–36. DOI: 10.1007/11535218_3  \n4. National Institute of Standards and Technology (NIST). (2020). *Recommendation for Applications Using Approved Hash Algorithms (SP 800-107 Rev. 1)*. Available at: csrc.nist.gov  \n5. Diversification.com. Collision resistance: Meaning, Criticisms & Real-World Uses. Accessed 2025.  \n6. GeeksforGeeks. What is Strong and Weak Collision Resistance in Cryptography? Updated July 2025.  \n7. Wikipedia contributors. Collision resistance. Wikipedia, The Free Encyclopedia. Accessed November 2025.  \n\n*If hash collisions were a party, collision resistance would be the bouncer ensuring no two guests wear the same mask—because in cryptography, identical masks are a security faux pas.*\n\n\n## Metadata\n\n\n- **Migration Status**: Ontology block enriched on 2025-11-12\n- **Last Updated**: 2025-11-12\n- **Review Status**: Comprehensive editorial review\n- **Verification**: Academic sources verified\n- **Regional Context**: UK/North England where applicable",
  "properties": {
    "id": "collision-resistance-standards",
    "collapsed": "true",
    "- domain-prefix": "BC",
    "- sequence-number": "0048",
    "- filename-history": "[\"BC-0048-collision-resistance.md\"]",
    "- public-access": "true",
    "- ontology": "true",
    "- term-id": "BC-0048",
    "- preferred-term": "Collision Resistance",
    "- source-domain": "blockchain",
    "- status": "complete",
    "- version": "1.0.0",
    "- last-updated": "2025-10-28",
    "- definition": "Hash function security property within blockchain systems, providing essential functionality for distributed ledger technology operations and properties.",
    "- maturity": "mature",
    "- source": "[[ISO/IEC 23257:2021]], [[IEEE 2418.1]], [[NIST NISTIR]]",
    "- authority-score": "0.95",
    "- owl:class": "bc:CollisionResistance",
    "- owl:physicality": "VirtualEntity",
    "- owl:role": "Object",
    "- owl:inferred-class": "bc:VirtualObject",
    "- belongsToDomain": "[[CryptographicDomain]]",
    "- implementedInLayer": "[[SecurityLayer]]",
    "- is-subclass-of": "[[Blockchain Entity]], [[CryptographicPrimitive]]"
  },
  "backlinks": [
    "CryptographicDomain",
    "SHA-256"
  ],
  "wiki_links": [
    "Blockchain Entity",
    "ISO/IEC 23257:2021",
    "CryptographicPrimitive",
    "NIST NISTIR",
    "SecurityLayer",
    "CryptographicDomain",
    "IEEE 2418.1"
  ],
  "ontology": {
    "term_id": "BC-0048",
    "preferred_term": "Collision Resistance",
    "definition": "Hash function security property within blockchain systems, providing essential functionality for distributed ledger technology operations and properties.",
    "source_domain": "blockchain",
    "maturity_level": null,
    "authority_score": 0.95
  }
}