{
  "title": "Computer Use and Browser Agents",
  "content": "- ### OntologyBlock\n  id:: computer-use-and-browser-agents-ontology\n  collapsed:: true\n\t- ontology:: true\n\t- term-id:: mv-107965237343\n\t- preferred-term:: Computer Use and Browser Agents\n\t- source-domain:: metaverse\n\t- status:: active\n\t- public-access:: true\n\t- definition:: A component of the metaverse ecosystem focusing on computer use and browser agents.\n\t- maturity:: mature\n\t- authority-score:: 0.85\n\t- owl:class:: mv:ComputerUseAndBrowserAgents\n\t- owl:physicality:: ConceptualEntity\n\t- owl:role:: Concept\n\t- belongsToDomain:: [[MetaverseDomain]]\n\t- #### Relationships\n\t  id:: computer-use-and-browser-agents-relationships\n\t\t- enables:: [[ImmersiveExperience]], [[Presence]], [[SpatialComputing]]\n\t\t- requires:: [[DisplayTechnology]], [[TrackingSystem]], [[RenderingEngine]]\n\t\t- bridges-to:: [[HumanComputerInteraction]], [[ComputerVision]], [[Robotics]]\n\n\t- #### OWL Axioms\n\t  id:: computer-use-and-browser-agents-owl-axioms\n\t  collapsed:: true\n\t\t- ```clojure\n\t\t  Declaration(Class(mv:ComputerUseAndBrowserAgents))\n\n\t\t  # Classification\n\t\t  SubClassOf(mv:ComputerUseAndBrowserAgents mv:ConceptualEntity)\n\t\t  SubClassOf(mv:ComputerUseAndBrowserAgents mv:Concept)\n\n\t\t  # Domain classification\n\t\t  SubClassOf(mv:ComputerUseAndBrowserAgents\n\t\t    ObjectSomeValuesFrom(mv:belongsToDomain mv:MetaverseDomain)\n\t\t  )\n\n\t\t  # Annotations\n\t\t  AnnotationAssertion(rdfs:label mv:ComputerUseAndBrowserAgents \"Computer Use and Browser Agents\"@en)\n\t\t  AnnotationAssertion(rdfs:comment mv:ComputerUseAndBrowserAgents \"A component of the metaverse ecosystem focusing on computer use and browser agents.\"@en)\n\t\t  AnnotationAssertion(dcterms:identifier mv:ComputerUseAndBrowserAgents \"mv-107965237343\"^^xsd:string)\n\t\t  ```\n\n## Browser-Based Agents\nid:: 68aef10f-4c4a-4c65-a81b-be1ac28622e2\n\t- ### Expanding Agent Capabilities\n\t\t- Browser agents can interact with any web-based interface, dramatically expanding what AI systems can accomplish. They operate websites designed for humans rather than requiring specific API access.\n\t- ### Use Cases and Applications\n\t\t- Browser agents excel at:\n\t\t\t- Web scraping and data collection from sites without APIs\n\t\t\t- Testing web applications and user interfaces\n\t\t\t- Automated form filling and data entry\n\t\t\t- Research across multiple websites and databases\n\t\t\t- E-commerce and booking tasks\n\t- ### Technical Implementation\n\t\t- Modern browser agent frameworks:\n\t\t\t- Provide headless browser environments\n\t\t\t- Support real-time session monitoring\n\t\t\t- Handle authentication and session management\n\t\t\t- Offer both programmatic and visual feedback\n\t\t\t- Scale to multiple concurrent sessions\n\n## Current Landscape (2025)\n\n- Industry adoption and implementations\n  - Metaverse platforms continue to evolve with focus on interoperability and open standards\n  - Web3 integration accelerating with decentralised identity and asset ownership\n  - Enterprise adoption growing in virtual collaboration, training, and digital twins\n  - UK companies increasingly active in metaverse development and immersive technologies\n\n- Technical capabilities\n  - Real-time rendering at photorealistic quality levels\n  - Low-latency networking enabling seamless multi-user experiences\n  - AI-driven content generation and procedural world building\n  - Spatial audio and haptics enhancing immersion\n\n- UK and North England context\n  - Manchester: Digital Innovation Factory supports metaverse startups and research\n  - Leeds: Holovis leads in immersive experiences for entertainment and training\n  - Newcastle: University research in spatial computing and interactive systems\n  - Sheffield: Advanced manufacturing using digital twin technology\n\n- Standards and frameworks\n  - Metaverse Standards Forum driving interoperability protocols\n  - WebXR enabling browser-based immersive experiences\n  - glTF and USD for 3D asset interchange\n  - Open Metaverse Interoperability Group defining cross-platform standards\n\n## Metadata\n\n- **Last Updated**: 2025-11-16\n- **Review Status**: Automated remediation with 2025 context\n- **Verification**: Academic sources verified\n- **Regional Context**: UK/North England where applicable",
  "properties": {
    "id": "computer-use-and-browser-agents-owl-axioms",
    "collapsed": "true",
    "- ontology": "true",
    "- term-id": "mv-107965237343",
    "- preferred-term": "Computer Use and Browser Agents",
    "- source-domain": "metaverse",
    "- status": "active",
    "- public-access": "true",
    "- definition": "A component of the metaverse ecosystem focusing on computer use and browser agents.",
    "- maturity": "mature",
    "- authority-score": "0.85",
    "- owl:class": "mv:ComputerUseAndBrowserAgents",
    "- owl:physicality": "ConceptualEntity",
    "- owl:role": "Concept",
    "- belongsToDomain": "[[MetaverseDomain]]",
    "- enables": "[[ImmersiveExperience]], [[Presence]], [[SpatialComputing]]",
    "- requires": "[[DisplayTechnology]], [[TrackingSystem]], [[RenderingEngine]]",
    "- bridges-to": "[[HumanComputerInteraction]], [[ComputerVision]], [[Robotics]]"
  },
  "backlinks": [],
  "wiki_links": [
    "TrackingSystem",
    "ImmersiveExperience",
    "ComputerVision",
    "RenderingEngine",
    "SpatialComputing",
    "Robotics",
    "HumanComputerInteraction",
    "MetaverseDomain",
    "DisplayTechnology",
    "Presence"
  ],
  "ontology": {
    "term_id": "mv-107965237343",
    "preferred_term": "Computer Use and Browser Agents",
    "definition": "A component of the metaverse ecosystem focusing on computer use and browser agents.",
    "source_domain": "metaverse",
    "maturity_level": null,
    "authority_score": 0.85
  }
}