{
  "title": "Comparison of GPT4 and Gemini Ultra",
  "content": "- ### OntologyBlock\n  id:: comparison-of-gpt4-and-gemini-ultra-ontology\n  collapsed:: true\n\t- ontology:: true\n\t- term-id:: mv-138449659368\n\t- preferred-term:: Comparison of GPT4 and Gemini Ultra\n\t- source-domain:: metaverse\n\t- status:: active\n\t- public-access:: true\n\t- definition:: A component of the metaverse ecosystem focusing on comparison of gpt4 and gemini ultra.\n\t- maturity:: mature\n\t- authority-score:: 0.85\n\t- owl:class:: mv:ComparisonOfGpt4AndGeminiUltra\n\t- owl:physicality:: ConceptualEntity\n\t- owl:role:: Concept\n\t- belongsToDomain:: [[MetaverseDomain]]\n\t- #### Relationships\n\t  id:: comparison-of-gpt4-and-gemini-ultra-relationships\n\t\t- enables:: [[ImmersiveExperience]], [[Presence]], [[SpatialComputing]]\n\t\t- requires:: [[DisplayTechnology]], [[TrackingSystem]], [[RenderingEngine]]\n\t\t- bridges-to:: [[HumanComputerInteraction]], [[ComputerVision]], [[Robotics]]\n\n\t- #### OWL Axioms\n\t  id:: comparison-of-gpt4-and-gemini-ultra-owl-axioms\n\t  collapsed:: true\n\t\t- ```clojure\n\t\t  Declaration(Class(mv:ComparisonOfGpt4AndGeminiUltra))\n\n\t\t  # Classification\n\t\t  SubClassOf(mv:ComparisonOfGpt4AndGeminiUltra mv:ConceptualEntity)\n\t\t  SubClassOf(mv:ComparisonOfGpt4AndGeminiUltra mv:Concept)\n\n\t\t  # Domain classification\n\t\t  SubClassOf(mv:ComparisonOfGpt4AndGeminiUltra\n\t\t    ObjectSomeValuesFrom(mv:belongsToDomain mv:MetaverseDomain)\n\t\t  )\n\n\t\t  # Annotations\n\t\t  AnnotationAssertion(rdfs:label mv:ComparisonOfGpt4AndGeminiUltra \"Comparison of GPT4 and Gemini Ultra\"@en)\n\t\t  AnnotationAssertion(rdfs:comment mv:ComparisonOfGpt4AndGeminiUltra \"A component of the metaverse ecosystem focusing on comparison of gpt4 and gemini ultra.\"@en)\n\t\t  AnnotationAssertion(dcterms:identifier mv:ComparisonOfGpt4AndGeminiUltra \"mv-138449659368\"^^xsd:string)\n\t\t  ```\n\npublic:: true\n\n- #Public page\n\t - automatically published\n- This analysis aims to highlight the strengths, weaknesses, and unique features of each model in various scenarios, including basic inquiries, local search functionalities, trip planning, email composition, data analysis, language tasks, coding capabilities, AI ethics, and creative tasks.\n\t-\n\t- ### **Performance and Speed:**\n\t\t- **ChatGPT-4**: Speed varies; sometimes faster than Gemini Ultra.\n\t\t- **Gemini Ultra**: Also varies in speed; comparable to ChatGPT-4.\n\t- ### **Formatting and Presentation:**\n\t\t- **ChatGPT-4**: More verbose, standard text formatting.\n\t\t- **Gemini Ultra**: Utilizes bold text and larger fonts for clarity.\n\t- ### **Functionality:**\n\t\t- #### Basic Inquiries:\n\t\t- Both models perform similarly in explaining basic concepts and answering various questions.\n\t- #### Local Search:\n\t\t- **ChatGPT-4**: Provides links to sources, no map integration.\n\t\t- **Gemini Ultra**: Integrates with Google Maps, offering a more convenient visualization but limits the number of suggestions.\n\t- #### Trip Planning:\n\t\t- **ChatGPT-4**: Comprehensive, text-based information without embeds.\n\t\t- **Gemini Ultra**: Faster, with embeds for a more engaging presentation.\n\t- #### Email Composition:\n\t\t- **ChatGPT-4**: Generates detailed emails.\n\t\t- **Gemini Ultra**: More succinct; allows direct drafting in Gmail through export feature.\n\t- #### Data Analysis and Visualization:\n\t\t- **ChatGPT-4**: Can interpret and visualize data from uploaded files.\n\t\t- **Gemini Ultra**: Lacks direct upload and visualization capabilities for data files.\n\t- #### Language Tasks:\n\t\t- Both models handle translation and grammar correction competently.\n\t- #### Coding and Development:\n\t\t- **ChatGPT-4**: Strong coding assistance, including SQL queries and web development.\n\t\t- **Gemini Ultra**: Offers code generation with an export option to Replit, though sometimes less detailed than ChatGPT-4.\n\t- ### **Integration Capabilities:**\n\t\t- **ChatGPT-4**: Supports file uploads for direct data analysis.\n\t\t- **Gemini Ultra**: Offers export features for emails, Google Sheets, and Replit, enhancing workflow integration.\n\t- ### **Ethical Considerations and Safety:**\n\t\t- Both models demonstrate awareness of ethical guidelines, refusing to provide information on sensitive or harmful topics.\n\t- ### **Creative Tasks:**\n\t\t- **ChatGPT-4**: Generates creative content with detailed formatting.\n\t\t- **Gemini Ultra**: Offers succinct creative outputs and sometimes provides more engaging formatting options.\n\t- ### **Conclusion:**\n\t\t- Both ChatGPT-4 and Gemini Ultra have their unique strengths and areas for improvement. ChatGPT-4 excels in detailed explanations, data analysis capabilities, and coding assistance, making it highly versatile for technical tasks and creative writing. Gemini Ultra, on the other hand, showcases strong integration features, such as direct exports to Gmail, Google Sheets, and Replit, and provides a more user-friendly presentation with its formatting choices and map integrations.\n\n## Current Landscape (2025)\n\n- Industry adoption and implementations\n  - Metaverse platforms continue to evolve with focus on interoperability and open standards\n  - Web3 integration accelerating with decentralised identity and asset ownership\n  - Enterprise adoption growing in virtual collaboration, training, and digital twins\n  - UK companies increasingly active in metaverse development and immersive technologies\n\n- Technical capabilities\n  - Real-time rendering at photorealistic quality levels\n  - Low-latency networking enabling seamless multi-user experiences\n  - AI-driven content generation and procedural world building\n  - Spatial audio and haptics enhancing immersion\n\n- UK and North England context\n  - Manchester: Digital Innovation Factory supports metaverse startups and research\n  - Leeds: Holovis leads in immersive experiences for entertainment and training\n  - Newcastle: University research in spatial computing and interactive systems\n  - Sheffield: Advanced manufacturing using digital twin technology\n\n- Standards and frameworks\n  - Metaverse Standards Forum driving interoperability protocols\n  - WebXR enabling browser-based immersive experiences\n  - glTF and USD for 3D asset interchange\n  - Open Metaverse Interoperability Group defining cross-platform standards\n\n## Metadata\n\n- **Last Updated**: 2025-11-16\n- **Review Status**: Automated remediation with 2025 context\n- **Verification**: Academic sources verified\n- **Regional Context**: UK/North England where applicable",
  "properties": {
    "id": "comparison-of-gpt4-and-gemini-ultra-owl-axioms",
    "collapsed": "true",
    "- ontology": "true",
    "- term-id": "mv-138449659368",
    "- preferred-term": "Comparison of GPT4 and Gemini Ultra",
    "- source-domain": "metaverse",
    "- status": "active",
    "- public-access": "true",
    "- definition": "A component of the metaverse ecosystem focusing on comparison of gpt4 and gemini ultra.",
    "- maturity": "mature",
    "- authority-score": "0.85",
    "- owl:class": "mv:ComparisonOfGpt4AndGeminiUltra",
    "- owl:physicality": "ConceptualEntity",
    "- owl:role": "Concept",
    "- belongsToDomain": "[[MetaverseDomain]]",
    "- enables": "[[ImmersiveExperience]], [[Presence]], [[SpatialComputing]]",
    "- requires": "[[DisplayTechnology]], [[TrackingSystem]], [[RenderingEngine]]",
    "- bridges-to": "[[HumanComputerInteraction]], [[ComputerVision]], [[Robotics]]",
    "public": "true"
  },
  "backlinks": [
    "AI Companies"
  ],
  "wiki_links": [
    "TrackingSystem",
    "ImmersiveExperience",
    "ComputerVision",
    "RenderingEngine",
    "SpatialComputing",
    "Robotics",
    "HumanComputerInteraction",
    "MetaverseDomain",
    "DisplayTechnology",
    "Presence"
  ],
  "ontology": {
    "term_id": "mv-138449659368",
    "preferred_term": "Comparison of GPT4 and Gemini Ultra",
    "definition": "A component of the metaverse ecosystem focusing on comparison of gpt4 and gemini ultra.",
    "source_domain": "metaverse",
    "maturity_level": null,
    "authority_score": 0.85
  }
}