{
  "title": "Comparison of SDXL and Midjourney v6",
  "content": "- ### OntologyBlock\n  id:: comparison-of-sdxl-and-midjourney-v6-ontology\n  collapsed:: true\n\t- ontology:: true\n\t- term-id:: mv-144609090526\n\t- preferred-term:: Comparison of SDXL and Midjourney v6\n\t- source-domain:: metaverse\n\t- status:: active\n\t- public-access:: true\n\t- definition:: A component of the metaverse ecosystem focusing on comparison of sdxl and midjourney v6.\n\t- maturity:: mature\n\t- authority-score:: 0.85\n\t- owl:class:: mv:ComparisonOfSdxlAndMidjourneyV6\n\t- owl:physicality:: ConceptualEntity\n\t- owl:role:: Concept\n\t- belongsToDomain:: [[MetaverseDomain]]\n\t- #### Relationships\n\t  id:: comparison-of-sdxl-and-midjourney-v6-relationships\n\t\t- enables:: [[ImmersiveExperience]], [[Presence]], [[SpatialComputing]]\n\t\t- requires:: [[DisplayTechnology]], [[TrackingSystem]], [[RenderingEngine]]\n\t\t- bridges-to:: [[HumanComputerInteraction]], [[ComputerVision]], [[Robotics]]\n\n\t- #### OWL Axioms\n\t  id:: comparison-of-sdxl-and-midjourney-v6-owl-axioms\n\t  collapsed:: true\n\t\t- ```clojure\n\t\t  Declaration(Class(mv:ComparisonOfSdxlAndMidjourneyV6))\n\n\t\t  # Classification\n\t\t  SubClassOf(mv:ComparisonOfSdxlAndMidjourneyV6 mv:ConceptualEntity)\n\t\t  SubClassOf(mv:ComparisonOfSdxlAndMidjourneyV6 mv:Concept)\n\n\t\t  # Domain classification\n\t\t  SubClassOf(mv:ComparisonOfSdxlAndMidjourneyV6\n\t\t    ObjectSomeValuesFrom(mv:belongsToDomain mv:MetaverseDomain)\n\t\t  )\n\n\t\t  # Annotations\n\t\t  AnnotationAssertion(rdfs:label mv:ComparisonOfSdxlAndMidjourneyV6 \"Comparison of SDXL and Midjourney v6\"@en)\n\t\t  AnnotationAssertion(rdfs:comment mv:ComparisonOfSdxlAndMidjourneyV6 \"A component of the metaverse ecosystem focusing on comparison of sdxl and midjourney v6.\"@en)\n\t\t  AnnotationAssertion(dcterms:identifier mv:ComparisonOfSdxlAndMidjourneyV6 \"mv-144609090526\"^^xsd:string)\n\t\t  ```\n\npublic:: true\n\n- #Public page\n\t - automatically published\n- ![ubk23oi2c99c1.webp](../assets/ubk23oi2c99c1_1704039598306_0.webp){:height 341, :width 636}\n- ![on7mfoi2c99c1.webp](../assets/on7mfoi2c99c1_1704039674387_0.webp)\n- ![oucsvni2c99c1.webp](../assets/oucsvni2c99c1_1704039919084_0.webp)\n- ![qtok2ri2c99c1.webp](../assets/qtok2ri2c99c1_1704039927334_0.webp)\n- ![wpwpuni2c99c1.webp](../assets/wpwpuni2c99c1_1704039947390_0.webp)\n- ![vrjm6oi2c99c1.webp](../assets/vrjm6oi2c99c1_1704039961984_0.webp)\n- [(2) Midjourney V6.0 vs SDXL, exact same prompts, using Fooocus (details in a comment) : StableDiffusion (reddit.com)](https://www.reddit.com/r/StableDiffusion/comments/18tqyn4/midjourney_v60_vs_sdxl_exact_same_prompts_using/)\n\n## Current Landscape (2025)\n\n- Industry adoption and implementations\n  - Metaverse platforms continue to evolve with focus on interoperability and open standards\n  - Web3 integration accelerating with decentralised identity and asset ownership\n  - Enterprise adoption growing in virtual collaboration, training, and digital twins\n  - UK companies increasingly active in metaverse development and immersive technologies\n\n- Technical capabilities\n  - Real-time rendering at photorealistic quality levels\n  - Low-latency networking enabling seamless multi-user experiences\n  - AI-driven content generation and procedural world building\n  - Spatial audio and haptics enhancing immersion\n\n- UK and North England context\n  - Manchester: Digital Innovation Factory supports metaverse startups and research\n  - Leeds: Holovis leads in immersive experiences for entertainment and training\n  - Newcastle: University research in spatial computing and interactive systems\n  - Sheffield: Advanced manufacturing using digital twin technology\n\n- Standards and frameworks\n  - Metaverse Standards Forum driving interoperability protocols\n  - WebXR enabling browser-based immersive experiences\n  - glTF and USD for 3D asset interchange\n  - Open Metaverse Interoperability Group defining cross-platform standards\n\n## Metadata\n\n- **Last Updated**: 2025-11-16\n- **Review Status**: Automated remediation with 2025 context\n- **Verification**: Academic sources verified\n- **Regional Context**: UK/North England where applicable",
  "properties": {
    "id": "comparison-of-sdxl-and-midjourney-v6-owl-axioms",
    "collapsed": "true",
    "- ontology": "true",
    "- term-id": "mv-144609090526",
    "- preferred-term": "Comparison of SDXL and Midjourney v6",
    "- source-domain": "metaverse",
    "- status": "active",
    "- public-access": "true",
    "- definition": "A component of the metaverse ecosystem focusing on comparison of sdxl and midjourney v6.",
    "- maturity": "mature",
    "- authority-score": "0.85",
    "- owl:class": "mv:ComparisonOfSdxlAndMidjourneyV6",
    "- owl:physicality": "ConceptualEntity",
    "- owl:role": "Concept",
    "- belongsToDomain": "[[MetaverseDomain]]",
    "- enables": "[[ImmersiveExperience]], [[Presence]], [[SpatialComputing]]",
    "- requires": "[[DisplayTechnology]], [[TrackingSystem]], [[RenderingEngine]]",
    "- bridges-to": "[[HumanComputerInteraction]], [[ComputerVision]], [[Robotics]]",
    "public": "true"
  },
  "backlinks": [],
  "wiki_links": [
    "ComputerVision",
    "Presence",
    "MetaverseDomain",
    "TrackingSystem",
    "DisplayTechnology",
    "RenderingEngine",
    "ImmersiveExperience",
    "Robotics",
    "HumanComputerInteraction",
    "SpatialComputing"
  ],
  "ontology": {
    "term_id": "mv-144609090526",
    "preferred_term": "Comparison of SDXL and Midjourney v6",
    "definition": "A component of the metaverse ecosystem focusing on comparison of sdxl and midjourney v6.",
    "source_domain": "metaverse",
    "maturity_level": null,
    "authority_score": 0.85
  }
}