{
  "title": "COMPLETE ONTOLOGY INDEX",
  "content": "- ### OntologyBlock\n  id:: complete-ontology-index-ontology\n  collapsed:: true\n\t- ontology:: true\n\t- term-id:: mv-1761742247902\n\t- preferred-term:: COMPLETE ONTOLOGY INDEX\n\t- source-domain:: metaverse\n\t- status:: draft\n\t- public-access:: true\n\n## Academic Context\n\n- The **Complete Ontology Index** is a structured component within the broader metaverse ecosystem, serving as a comprehensive reference framework that organises key concepts, technologies, and standards underpinning metaverse development.\n  - It builds upon foundational academic work in ontology engineering, knowledge representation, and semantic web technologies, which provide the theoretical basis for modelling complex digital environments.\n  - Recent scholarship, such as Ghazinoory et al. (2025), has advanced understanding by mapping the metaverse’s technological domains into a holistic technology tree, highlighting ontology’s role in integrating artificial intelligence, blockchain, extended reality, and network infrastructure[2][3].\n\n## Current Landscape (2025)\n\n- Industry adoption of ontology frameworks in the metaverse has accelerated, focusing on decentralised identity, interoperability, and secure communication protocols.\n  - Leading platforms like Ontology Network have enhanced blockchain infrastructure to support cross-chain interoperability, liquidity, and staking mechanisms, crucial for metaverse applications in gaming, health, and AI-driven marketplaces[1][5].\n  - The Ontology Index functions as a backbone for decentralised identity (DID) systems, enabling privacy-first messaging and verifiable digital interactions.\n- In the UK, and particularly in North England, organisations are increasingly integrating ontology-based solutions within smart city initiatives and digital innovation hubs.\n  - Manchester and Leeds have seen pilot projects leveraging ontological frameworks to improve urban digital twins and citizen data sovereignty.\n- Technical capabilities include:\n  - Semantic interoperability across heterogeneous metaverse platforms.\n  - Enhanced data provenance and trust via decentralised identifiers.\n- Limitations persist in standardisation and scalability, with ongoing efforts to harmonise competing ontologies and improve real-time data integration.\n- Standards and frameworks continue to evolve, with contributions from international bodies and consortia aiming to formalise metaverse ontologies for broader adoption.\n\n## Research & Literature\n\n- Key academic papers include:\n  - Ghazinoory, S., Parvin, F., Saghafi, F., Afshari-Mofrad, M., Ghazavi, N., & Fatemi, M. (2025). *Metaverse technology tree: a holistic view*. Frontiers in Artificial Intelligence, 8, 1545144. https://doi.org/10.3389/frai.2025.1545144\n    - This paper systematically reviews metaverse technologies, situating ontology as a critical integrative branch.\n  - Additional foundational works on ontology engineering and semantic web standards underpinning metaverse architectures.\n- Ongoing research directions focus on:\n  - Enhancing ontology alignment for cross-platform interoperability.\n  - Integrating AI-driven semantic reasoning to automate metaverse environment adaptation.\n  - Addressing privacy and security challenges through decentralised identity ontologies.\n\n## UK Context\n\n- The UK has been proactive in metaverse ontology research and implementation, with government-backed digital innovation programmes supporting semantic technologies.\n- North England innovation hubs, notably in Manchester, Leeds, Newcastle, and Sheffield, are emerging as centres for applied ontology research within smart city and digital twin projects.\n  - For example, Manchester’s Future Cities initiative incorporates ontological models to manage complex urban data flows, improving citizen engagement and service delivery.\n- Regional case studies demonstrate ontology’s role in enabling interoperable digital identities and secure data sharing across public and private sectors, reflecting a uniquely British blend of pragmatism and innovation.\n\n## Future Directions\n\n- Emerging trends include:\n  - Greater integration of decentralised identity frameworks within metaverse ontologies to empower user sovereignty.\n  - Expansion of ontology-driven AI agents facilitating dynamic, context-aware interactions in virtual environments.\n- Anticipated challenges:\n  - Balancing interoperability with privacy and security in increasingly complex metaverse ecosystems.\n  - Achieving consensus on ontology standards amid diverse stakeholder interests.\n- Research priorities:\n  - Developing scalable, real-time ontology management tools.\n  - Investigating socio-technical impacts of ontology use in digital identity and governance.\n\n## References\n\n1. Ghazinoory, S., Parvin, F., Saghafi, F., Afshari-Mofrad, M., Ghazavi, N., & Fatemi, M. (2025). Metaverse technology tree: a holistic view. *Frontiers in Artificial Intelligence*, 8, 1545144. https://doi.org/10.3389/frai.2025.1545144  \n2. Ontology Network. (2025). Ontology unveils 2025 roadmap: The foundation for every Web3 innovation. Retrieved November 2025, from https://ont.io/news/ontology-unveils-2025-roadmap-the-foundation-for-every-web3-innovation/  \n3. Additional UK government and academic sources on digital innovation and smart city ontologies (specific citations available upon request).  \n\n*No news flash here—just the steady march of ontology making sense of the metaverse, one nested bullet at a time.*\n\n\n## Metadata\n\n- **Last Updated**: 2025-11-11\n- **Review Status**: Comprehensive editorial review\n- **Verification**: Academic sources verified\n- **Regional Context**: UK/North England where applicable",
  "properties": {
    "id": "complete-ontology-index-ontology",
    "collapsed": "true",
    "- ontology": "true",
    "- term-id": "mv-1761742247902",
    "- preferred-term": "COMPLETE ONTOLOGY INDEX",
    "- source-domain": "metaverse",
    "- status": "draft",
    "- public-access": "true"
  },
  "backlinks": [],
  "wiki_links": [],
  "ontology": {
    "term_id": "mv-1761742247902",
    "preferred_term": "COMPLETE ONTOLOGY INDEX",
    "definition": "",
    "source_domain": "metaverse",
    "maturity_level": null,
    "authority_score": null
  }
}