{
  "title": "ConsensusDomain",
  "content": "- ### OntologyBlock\n  id:: consensusdomain-ontology\n  collapsed:: true\n\t- ontology:: true\n\t- term-id:: mv-85355095357\n\t- preferred-term:: ConsensusDomain\n\t- source-domain:: metaverse\n\t- status:: active\n\t- public-access:: true\n\t- definition:: A component of the metaverse ecosystem focusing on consensusdomain.\n\t- maturity:: mature\n\t- authority-score:: 0.85\n\t- owl:class:: mv:Consensusdomain\n\t- owl:physicality:: ConceptualEntity\n\t- owl:role:: Concept\n\t- belongsToDomain:: [[MetaverseDomain]]\n\t- #### Relationships\n\t  id:: consensusdomain-relationships\n\t\t- enables:: [[ImmersiveExperience]], [[Presence]], [[SpatialComputing]]\n\t\t- requires:: [[DisplayTechnology]], [[TrackingSystem]], [[RenderingEngine]]\n\t\t- bridges-to:: [[HumanComputerInteraction]], [[ComputerVision]], [[Robotics]]\n\n\t- #### OWL Axioms\n\t  id:: consensusdomain-owl-axioms\n\t  collapsed:: true\n\t\t- ```clojure\n\t\t  Declaration(Class(mv:Consensusdomain))\n\n\t\t  # Classification\n\t\t  SubClassOf(mv:Consensusdomain mv:ConceptualEntity)\n\t\t  SubClassOf(mv:Consensusdomain mv:Concept)\n\n\t\t  # Domain classification\n\t\t  SubClassOf(mv:Consensusdomain\n\t\t    ObjectSomeValuesFrom(mv:belongsToDomain mv:MetaverseDomain)\n\t\t  )\n\n\t\t  # Annotations\n\t\t  AnnotationAssertion(rdfs:label mv:Consensusdomain \"ConsensusDomain\"@en)\n\t\t  AnnotationAssertion(rdfs:comment mv:Consensusdomain \"A component of the metaverse ecosystem focusing on consensusdomain.\"@en)\n\t\t  AnnotationAssertion(dcterms:identifier mv:Consensusdomain \"mv-85355095357\"^^xsd:string)\n\t\t  ```\n\n- ### MetaOntologyBlock\n  id:: consensus-domain-meta\n  collapsed:: true\n\n  - **Classification**\n    - meta-ontology:: true\n    - classification-type:: domain\n    - name:: ConsensusDomain\n    - scope:: Specialized sub-domain encompassing consensus mechanisms, distributed agreement protocols, fault tolerance, Byzantine agreement, and coordination mechanisms in blockchain and distributed systems\n    - version:: 1.0.0\n    - last-updated:: 2025-11-08\n\n  - **Definition**\n    - definition:: The ConsensusDomain represents a specialized sub-domain within blockchain technology that encompasses all consensus mechanisms, distributed agreement protocols, and coordination systems that enable decentralized networks to achieve consistent state without trusted central authorities. This domain includes foundational consensus concepts, Byzantine Fault Tolerance (BFT) protocols, Proof-of-Work (PoW) mechanisms, Proof-of-Stake (PoS) systems and variants (Delegated PoS, Liquid PoS, Bonded PoS), hybrid consensus mechanisms, finality concepts, fork choice rules, validator systems, mining mechanisms, staking protocols, slashing conditions, leader election algorithms, and consensus security analysis. These consensus mechanisms solve the fundamental distributed systems problem of achieving agreement in adversarial environments where some participants may be faulty, malicious, or offline. The domain addresses critical challenges including the Byzantine Generals Problem, double-spending prevention, finality guarantees, liveness (ensuring continuous progress), safety (preventing invalid state transitions), and scalability tradeoffs inherent in distributed agreement. Consensus mechanisms typically combine cryptographic security, game-theoretic incentive alignment, and distributed systems protocols to achieve reliable coordination without central coordination.\n    - purpose:: To provide systematic classification and understanding of how decentralized networks achieve agreement and maintain consistent state, enabling analysis of consensus security properties, performance characteristics, economic incentive structures, and suitability for different blockchain applications\n    - coverage:: This domain covers approximately 20 consensus-related concepts including fundamental consensus theory (Byzantine agreement, state machine replication, atomic broadcast), Proof-of-Work systems (mining, difficulty adjustment, hashrate, nakamoto consensus), Proof-of-Stake variants (validators, staking, slashing, unbonding periods), Byzantine Fault Tolerance protocols (PBFT, Tendermint, HotStuff), hybrid consensus mechanisms, finality concepts (probabilistic vs deterministic finality), and consensus security analysis (51% attacks, nothing-at-stake problem, long-range attacks)\n\n  - **Taxonomy**\n    - parent-classification:: [[BlockchainDomain]]\n    - peer-classifications:: [[CryptographicDomain]], [[TokenEconomicsDomain]]\n    - related-classifications:: [[ProtocolLayer]], [[EconomicLayer]]\n\n  - **Member Concepts**\n    - concept-count:: 20\n    - foundational-concepts:: [[BC-0040-consensus-mechanism]], [[BC-0041-proof-of-work]], [[BC-0042-proof-of-stake]], [[BC-0056-byzantine-fault-tolerance]], [[BC-0057-nakamoto-consensus]], [[BC-0058-finality]]\n    - pow-concepts:: [[BC-0041-proof-of-work]], [[Miner]], [[BC-0043-mining-difficulty]], [[BC-0044-hashrate]], [[BC-0045-difficulty-adjustment]], [[BC-0046-mining-pool]], [[BC-0047-block-reward]]\n    - pos-concepts:: [[BC-0042-proof-of-stake]], [[BC-0055-validator]], [[BC-0051-staking]], [[BC-0052-slashing]], [[BC-0053-delegated-proof-of-stake]], [[BC-0059-liquid-proof-of-stake]], [[BC-0060-bonded-proof-of-stake]]\n    - bft-concepts:: [[BC-0056-byzantine-fault-tolerance]], [[BC-0061-pbft]], [[BC-0062-tendermint]], [[BC-0063-hotstuff]], [[BC-0064-istanbul-bft]], [[BC-0065-practical-byzantine-fault-tolerance]]\n    - finality-concepts:: [[BC-0058-finality]], [[BC-0066-probabilistic-finality]], [[BC-0067-deterministic-finality]], [[BC-0068-economic-finality]], [[BC-0069-instant-finality]]\n    - security-concepts:: [[BC-0070-51-percent-attack]], [[BC-0071-nothing-at-stake]], [[BC-0072-long-range-attack]], [[BC-0073-selfish-mining]], [[BC-0074-eclipse-attack]]\n    - key-ontologies:: BC-0040 through BC-0074 comprising consensus mechanism fundamentals, Proof-of-Work mining and difficulty adjustment, Proof-of-Stake validation and staking, Byzantine Fault Tolerance protocols, finality concepts, fork choice rules, and consensus security vulnerabilities\n\n  - ## About ConsensusDomain\n    id:: consensus-domain-about\n    - The ConsensusDomain constitutes a specialized sub-domain within BlockchainDomain, addressing one of the most fundamental challenges in distributed systems: achieving agreement among multiple parties in the presence of failures, network delays, and potentially malicious actors. Consensus mechanisms are the \"heart\" of blockchain systems, determining how transactions are ordered, how blocks are produced, who has authority to propose state changes, and what security guarantees the system provides. This domain emerged from classical distributed systems research (Byzantine Generals Problem, state machine replication, atomic broadcast) but has been transformed by blockchain's unique requirements: operation in permissionless adversarial environments, economic security models where attackers are motivated by financial gain, and the need to coordinate thousands or millions of participants without central coordination.\n\n    - The domain is organized around major consensus paradigm families, each representing fundamentally different approaches to distributed agreement. **Proof-of-Work (PoW)** consensus, pioneered by Bitcoin, achieves agreement through computational puzzles: miners compete to find hash values meeting difficulty targets, and the longest chain of valid blocks represents the consensus state. PoW provides several elegant properties: anyone can participate (permissionless), Sybil resistance through computational cost (creating multiple identities doesn't provide additional influence), and probabilistic security guarantees (deeper blocks become exponentially harder to reverse). However, PoW suffers from significant energy consumption (Bitcoin network consumes power equivalent to a medium-sized country), limited throughput (Bitcoin processes ~7 transactions per second), and probabilistic finality (transactions are never absolutely final, only increasingly secure with depth). PoW concepts in this domain include miners, mining difficulty, hashrate, difficulty adjustment algorithms, mining pools, selfish mining attacks, and the nakamoto consensus security model.\n\n    - **Proof-of-Stake (PoS)** consensus achieves agreement through economic stake: validators lock cryptocurrency as collateral and are selected to propose blocks proportional to their stake. PoS dramatically reduces energy consumption (Ethereum's transition to PoS reduced energy usage by ~99.95%), enables higher throughput, and provides economic security through slashing (destroying stake of misbehaving validators). However, PoS introduces new challenges: the \"nothing-at-stake\" problem (validators have no cost to vote on multiple forks), long-range attacks (attackers might create alternative histories from genesis), and wealth concentration concerns (the rich get richer through staking rewards). Variants address these challenges differently: Delegated Proof-of-Stake (DPoS) enables token holders to vote for a limited number of validators (improving performance but potentially reducing decentralization), Liquid Proof-of-Stake allows delegation with flexible re-delegation, and Bonded Proof-of-Stake requires unbonding periods before stake can be withdrawn (preventing certain attacks but reducing liquidity). PoS concepts include validators, staking mechanisms, slashing conditions, validator selection, and epoch structures.\n\n    - **Byzantine Fault Tolerance (BFT)** protocols represent a third major family, derived from classical distributed systems research but adapted for blockchain. BFT consensus (including PBFT, Tendermint, HotStuff, Istanbul BFT) provides deterministic finality: once a block is finalized, it cannot be reverted even with majority control (unlike PoW where sufficiently deep blocks can theoretically be reversed with enough hashpower). BFT protocols typically operate in rounds with a designated leader proposing blocks and validators voting in multiple phases to ensure safety and liveness. These protocols guarantee safety (no conflicting blocks are finalized) as long as less than 1/3 of validators are Byzantine (malicious), and guarantee liveness (continuous progress) with additional network assumptions. BFT consensus provides fast finality (seconds rather than minutes or hours) and high throughput, but traditionally required known validator sets (permissioned operation). Modern blockchain-adapted BFT protocols combine BFT consensus with PoS validator selection to achieve both performance and permissionless operation.\n\n    - ### Scope and Boundaries\n      - **Included:** All consensus mechanisms, distributed agreement protocols, coordination mechanisms, fault tolerance systems, Byzantine agreement protocols, finality concepts, fork choice rules, validator systems, mining mechanisms, staking protocols, slashing conditions, and consensus security analysis specific to blockchain and distributed ledger systems.\n\n      - **Excluded:** Centralized coordination mechanisms (not relevant to decentralized systems), consensus in non-blockchain distributed databases (unless applicable to blockchain), voting systems in traditional governance (unless blockchain-based), and general distributed systems algorithms without blockchain application.\n\n      - **Boundary Clarifications:** Concepts must relate to achieving distributed agreement in blockchain or distributed ledger contexts. Proof-of-Work belongs here as a consensus mechanism. Hash functions used in PoW belong primarily to CryptographicDomain (they're cryptographic primitives) but are referenced by ConsensusDomain concepts. Economic incentives for consensus participation (block rewards, transaction fees, staking yields) may span both ConsensusDomain (as part of consensus mechanism design) and TokenEconomicsDomain (as economic mechanisms).\n\n    - ### Relationship to Other Classifications\n      - **Parent Domain - BlockchainDomain:** ConsensusDomain is a specialized sub-domain of BlockchainDomain, focusing specifically on distributed agreement mechanisms while the parent domain encompasses all aspects of blockchain technology. This hierarchical relationship recognizes that consensus is a critical but not sole component of blockchain systems, working in concert with cryptographic primitives (CryptographicDomain), economic incentives (TokenEconomicsDomain), network protocols, smart contract systems, and other blockchain components.\n\n      - **Peer Sub-Domains:** ConsensusDomain shares BlockchainDomain with CryptographicDomain and TokenEconomicsDomain. These three sub-domains are highly interdependent in blockchain systems: consensus mechanisms rely on cryptographic primitives (PoW uses hash functions, PoS uses digital signatures for validator attestations, BFT protocols use signature aggregation), and consensus mechanisms are secured through economic incentives (block rewards, staking yields, slashing penalties). Many blockchain concepts span multiple sub-domains; for example, \"Miner\" belongs to ConsensusDomain (miners participate in PoW consensus) but involves economic incentives (block rewards) from TokenEconomicsDomain.\n\n      - **Layer Relationships:** ConsensusDomain concepts are typically implemented in ProtocolLayer (consensus mechanisms are protocol-level implementations) but may also involve EconomicLayer (economic security), SecurityLayer (security properties), or ConceptualLayer (abstract consensus theory). This multi-layer implementation reflects the complexity of consensus systems that span theoretical foundations, protocol specifications, economic incentives, and security guarantees.\n\n    - ### Design Rationale\n      - **Consensus Centrality:** ConsensusDomain is organized as a distinct sub-domain because consensus mechanisms are arguably the defining innovation of blockchain technology. While cryptography and peer-to-peer networking existed before Bitcoin, nakamoto consensus (PoW with longest-chain rule) represented a breakthrough in achieving Byzantine agreement in permissionless adversarial environments. This fundamental importance justifies dedicated domain classification.\n\n      - **Paradigm-Based Organization:** The domain organizes concepts around major consensus paradigms (PoW, PoS, BFT) rather than specific implementations. This organization recognizes that consensus mechanisms within each paradigm share fundamental properties, tradeoffs, and security models, even as specific implementations differ. For example, various PoS systems (Ethereum's Casper, Cardano's Ouroboros, Algorand's Pure PoS) differ in details but share core PoS characteristics.\n\n      - **Security-Centric Perspective:** ConsensusDomain emphasizes security properties and attack vectors because consensus security is paramount to blockchain value. A blockchain with broken consensus loses its fundamental properties (immutability, censorship resistance, decentralization). The domain therefore includes not just consensus mechanisms but also attack types (51% attacks, nothing-at-stake, long-range attacks, selfish mining) and security analyses.\n\n      - **Evolution and Hybrids:** The domain structure accommodates both established consensus mechanisms (PoW, PoS) and emerging hybrid approaches that combine multiple paradigms. For example, some systems use PoW for Sybil resistance but BFT for finality, or combine PoW and PoS in different chain components. As consensus research advances, the domain can incorporate novel mechanisms while maintaining coherent organization.\n\n      - **Theory-Practice Integration:** ConsensusDomain includes both theoretical concepts (Byzantine agreement, state machine replication, finality definitions) and practical implementations (specific PoW algorithms, PoS validator selection mechanisms, BFT protocol variants). This integration serves both academics studying consensus theory and practitioners implementing consensus systems, recognizing that blockchain consensus requires both rigorous theoretical foundations and practical engineering.\n\n\n## Current Landscape (2025)\n\n- Industry adoption and implementations\n  - Metaverse platforms continue to evolve with focus on interoperability and open standards\n  - Web3 integration accelerating with decentralised identity and asset ownership\n  - Enterprise adoption growing in virtual collaboration, training, and digital twins\n  - UK companies increasingly active in metaverse development and immersive technologies\n\n- Technical capabilities\n  - Real-time rendering at photorealistic quality levels\n  - Low-latency networking enabling seamless multi-user experiences\n  - AI-driven content generation and procedural world building\n  - Spatial audio and haptics enhancing immersion\n\n- UK and North England context\n  - Manchester: Digital Innovation Factory supports metaverse startups and research\n  - Leeds: Holovis leads in immersive experiences for entertainment and training\n  - Newcastle: University research in spatial computing and interactive systems\n  - Sheffield: Advanced manufacturing using digital twin technology\n\n- Standards and frameworks\n  - Metaverse Standards Forum driving interoperability protocols\n  - WebXR enabling browser-based immersive experiences\n  - glTF and USD for 3D asset interchange\n  - Open Metaverse Interoperability Group defining cross-platform standards\n\n## Metadata\n\n- **Last Updated**: 2025-11-16\n- **Review Status**: Automated remediation with 2025 context\n- **Verification**: Academic sources verified\n- **Regional Context**: UK/North England where applicable",
  "properties": {
    "id": "consensus-domain-about",
    "collapsed": "true",
    "- ontology": "true",
    "- term-id": "mv-85355095357",
    "- preferred-term": "ConsensusDomain",
    "- source-domain": "metaverse",
    "- status": "active",
    "- public-access": "true",
    "- definition": "The ConsensusDomain represents a specialized sub-domain within blockchain technology that encompasses all consensus mechanisms, distributed agreement protocols, and coordination systems that enable decentralized networks to achieve consistent state without trusted central authorities. This domain includes foundational consensus concepts, Byzantine Fault Tolerance (BFT) protocols, Proof-of-Work (PoW) mechanisms, Proof-of-Stake (PoS) systems and variants (Delegated PoS, Liquid PoS, Bonded PoS), hybrid consensus mechanisms, finality concepts, fork choice rules, validator systems, mining mechanisms, staking protocols, slashing conditions, leader election algorithms, and consensus security analysis. These consensus mechanisms solve the fundamental distributed systems problem of achieving agreement in adversarial environments where some participants may be faulty, malicious, or offline. The domain addresses critical challenges including the Byzantine Generals Problem, double-spending prevention, finality guarantees, liveness (ensuring continuous progress), safety (preventing invalid state transitions), and scalability tradeoffs inherent in distributed agreement. Consensus mechanisms typically combine cryptographic security, game-theoretic incentive alignment, and distributed systems protocols to achieve reliable coordination without central coordination.",
    "- maturity": "mature",
    "- authority-score": "0.85",
    "- owl:class": "mv:Consensusdomain",
    "- owl:physicality": "ConceptualEntity",
    "- owl:role": "Concept",
    "- belongsToDomain": "[[MetaverseDomain]]",
    "- enables": "[[ImmersiveExperience]], [[Presence]], [[SpatialComputing]]",
    "- requires": "[[DisplayTechnology]], [[TrackingSystem]], [[RenderingEngine]]",
    "- bridges-to": "[[HumanComputerInteraction]], [[ComputerVision]], [[Robotics]]",
    "- meta-ontology": "true",
    "- classification-type": "domain",
    "- name": "ConsensusDomain",
    "- scope": "Specialized sub-domain encompassing consensus mechanisms, distributed agreement protocols, fault tolerance, Byzantine agreement, and coordination mechanisms in blockchain and distributed systems",
    "- version": "1.0.0",
    "- last-updated": "2025-11-08",
    "- purpose": "To provide systematic classification and understanding of how decentralized networks achieve agreement and maintain consistent state, enabling analysis of consensus security properties, performance characteristics, economic incentive structures, and suitability for different blockchain applications",
    "- coverage": "This domain covers approximately 20 consensus-related concepts including fundamental consensus theory (Byzantine agreement, state machine replication, atomic broadcast), Proof-of-Work systems (mining, difficulty adjustment, hashrate, nakamoto consensus), Proof-of-Stake variants (validators, staking, slashing, unbonding periods), Byzantine Fault Tolerance protocols (PBFT, Tendermint, HotStuff), hybrid consensus mechanisms, finality concepts (probabilistic vs deterministic finality), and consensus security analysis (51% attacks, nothing-at-stake problem, long-range attacks)",
    "- parent-classification": "[[BlockchainDomain]]",
    "- peer-classifications": "[[CryptographicDomain]], [[TokenEconomicsDomain]]",
    "- related-classifications": "[[ProtocolLayer]], [[EconomicLayer]]",
    "- concept-count": "20",
    "- foundational-concepts": "[[BC-0040-consensus-mechanism]], [[BC-0041-proof-of-work]], [[BC-0042-proof-of-stake]], [[BC-0056-byzantine-fault-tolerance]], [[BC-0057-nakamoto-consensus]], [[BC-0058-finality]]",
    "- pow-concepts": "[[BC-0041-proof-of-work]], [[Miner]], [[BC-0043-mining-difficulty]], [[BC-0044-hashrate]], [[BC-0045-difficulty-adjustment]], [[BC-0046-mining-pool]], [[BC-0047-block-reward]]",
    "- pos-concepts": "[[BC-0042-proof-of-stake]], [[BC-0055-validator]], [[BC-0051-staking]], [[BC-0052-slashing]], [[BC-0053-delegated-proof-of-stake]], [[BC-0059-liquid-proof-of-stake]], [[BC-0060-bonded-proof-of-stake]]",
    "- bft-concepts": "[[BC-0056-byzantine-fault-tolerance]], [[BC-0061-pbft]], [[BC-0062-tendermint]], [[BC-0063-hotstuff]], [[BC-0064-istanbul-bft]], [[BC-0065-practical-byzantine-fault-tolerance]]",
    "- finality-concepts": "[[BC-0058-finality]], [[BC-0066-probabilistic-finality]], [[BC-0067-deterministic-finality]], [[BC-0068-economic-finality]], [[BC-0069-instant-finality]]",
    "- security-concepts": "[[BC-0070-51-percent-attack]], [[BC-0071-nothing-at-stake]], [[BC-0072-long-range-attack]], [[BC-0073-selfish-mining]], [[BC-0074-eclipse-attack]]",
    "- key-ontologies": "BC-0040 through BC-0074 comprising consensus mechanism fundamentals, Proof-of-Work mining and difficulty adjustment, Proof-of-Stake validation and staking, Byzantine Fault Tolerance protocols, finality concepts, fork choice rules, and consensus security vulnerabilities"
  },
  "backlinks": [
    "BlockchainDomain",
    "BC-0068-coinbase-transaction",
    "BC-0056-difficulty-adjustment",
    "Consensus Rule",
    "BC-0062-block-propagation",
    "BC-0064-mining-pool",
    "BC-0060-fork-choice-rule",
    "Difficulty Adjustment",
    "BC-0070-halving",
    "BC-0067-difficulty-target",
    "BC-0058-consensus-rule",
    "BC-0061-nakamoto-consensus",
    "Halving",
    "BC-0059-longest-chain-rule",
    "Coinbase Transaction",
    "Mining Reward",
    "BC-0066-pool-share",
    "Difficulty Target",
    "Miner",
    "Network Synchronization",
    "BC-0051-consensus-mechanism",
    "BC-0055-block-reward",
    "CryptographicDomain",
    "BC-0052-proof-of-work",
    "Block Reward (Mining Incentive)",
    "Block Propagation",
    "Pool Share",
    "BC-0057-network-synchronization",
    "BC-0054-miner",
    "Mining Pool",
    "BC-0069-mining-reward",
    "TokenEconomicsDomain",
    "Solo Mining",
    "Longest Chain Rule",
    "BC-0053-mining",
    "ProofOfWork",
    "Network Hash Rate",
    "Mining",
    "BC-0063-network-hash-rate",
    "Fork Choice Rule",
    "Proof of Work",
    "Nakamoto Consensus",
    "BC-0065-solo-mining"
  ],
  "wiki_links": [
    "BC-0074-eclipse-attack",
    "BC-0044-hashrate",
    "Presence",
    "MetaverseDomain",
    "BC-0046-mining-pool",
    "BlockchainDomain",
    "ImmersiveExperience",
    "BC-0065-practical-byzantine-fault-tolerance",
    "BC-0052-slashing",
    "SpatialComputing",
    "BC-0062-tendermint",
    "BC-0042-proof-of-stake",
    "BC-0072-long-range-attack",
    "BC-0057-nakamoto-consensus",
    "BC-0073-selfish-mining",
    "BC-0070-51-percent-attack",
    "BC-0060-bonded-proof-of-stake",
    "ProtocolLayer",
    "DisplayTechnology",
    "RenderingEngine",
    "BC-0051-staking",
    "BC-0071-nothing-at-stake",
    "BC-0061-pbft",
    "BC-0067-deterministic-finality",
    "BC-0047-block-reward",
    "CryptographicDomain",
    "BC-0040-consensus-mechanism",
    "Miner",
    "BC-0056-byzantine-fault-tolerance",
    "BC-0058-finality",
    "BC-0055-validator",
    "HumanComputerInteraction",
    "BC-0043-mining-difficulty",
    "ComputerVision",
    "BC-0053-delegated-proof-of-stake",
    "BC-0068-economic-finality",
    "BC-0069-instant-finality",
    "BC-0064-istanbul-bft",
    "TrackingSystem",
    "BC-0045-difficulty-adjustment",
    "BC-0059-liquid-proof-of-stake",
    "BC-0041-proof-of-work",
    "Robotics",
    "TokenEconomicsDomain",
    "BC-0066-probabilistic-finality",
    "EconomicLayer",
    "BC-0063-hotstuff"
  ],
  "ontology": {
    "term_id": "mv-85355095357",
    "preferred_term": "ConsensusDomain",
    "definition": "A component of the metaverse ecosystem focusing on consensusdomain.",
    "source_domain": "metaverse",
    "maturity_level": null,
    "authority_score": 0.85
  }
}