{
  "title": "Consensus Rule",
  "content": "- ### OntologyBlock\n  id:: consensus-rule-ontology\n  collapsed:: true\n\n  - **Identification**\n\n    - domain-prefix:: BC\n\n    - sequence-number:: 0058\n\n    - filename-history:: [\"BC-0058-consensus-rule.md\"]\n    - public-access:: true\n    - ontology:: true\n    - term-id:: BC-0058\n    - preferred-term:: Consensus Rule\n    - source-domain:: blockchain\n    - status:: complete\n    - version:: 1.0.0\n    - last-updated:: 2025-10-28\n\n  - **Definition**\n    - definition:: Protocol validation requirement within blockchain systems, providing essential functionality for distributed ledger technology operations and properties.\n    - maturity:: mature\n    - source:: [[ISO/IEC 23257:2021]], [[IEEE 2418.1]], [[NIST NISTIR]]\n    - authority-score:: 0.95\n\n  - **Semantic Classification**\n    - owl:class:: bc:ConsensusRule\n    - owl:physicality:: VirtualEntity\n    - owl:role:: Object\n    - owl:inferred-class:: bc:VirtualObject\n    - belongsToDomain:: [[ConsensusDomain]]\n    - implementedInLayer:: [[ProtocolLayer]]\n\n  - #### Relationships\n    id:: consensus-rule-relationships\n    - is-subclass-of:: [[Blockchain Entity]], [[ConsensusProtocol]]\n\n  - #### OWL Axioms\n    id:: consensus-rule-owl-axioms\n    collapsed:: true\n    - ```clojure\n      Prefix(:=<http://metaverse-ontology.org/blockchain#>)\nPrefix(owl:=<http://www.w3.org/2002/07/owl#>)\nPrefix(rdf:=<http://www.w3.org/1999/02/22-rdf-syntax-ns#>)\nPrefix(xml:=<http://www.w3.org/XML/1998/namespace>)\nPrefix(xsd:=<http://www.w3.org/2001/XMLSchema#>)\nPrefix(rdfs:=<http://www.w3.org/2000/01/rdf-schema#>)\nPrefix(dct:=<http://purl.org/dc/terms/>)\n\nOntology(<http://metaverse-ontology.org/blockchain/BC-0058>\n  Import(<http://metaverse-ontology.org/blockchain/core>)\n\n  ## Class Declaration\n  Declaration(Class(:ConsensusRule))\n\n  ## Subclass Relationships\n  SubClassOf(:ConsensusRule :ConsensusProtocol)\n  SubClassOf(:ConsensusRule :BlockchainEntity)\n\n  ## Essential Properties\n  SubClassOf(:ConsensusRule\n    (ObjectSomeValuesFrom :partOf :Blockchain))\n\n  SubClassOf(:ConsensusRule\n    (ObjectSomeValuesFrom :hasProperty :Property))\n\n  ## Data Properties\n  DataPropertyAssertion(:hasIdentifier :ConsensusRule \"BC-0058\"^^xsd:string)\n  DataPropertyAssertion(:hasAuthorityScore :ConsensusRule \"1.0\"^^xsd:decimal)\n  DataPropertyAssertion(:isFoundational :ConsensusRule \"true\"^^xsd:boolean)\n\n  ## Object Properties\n  ObjectPropertyAssertion(:enablesFeature :ConsensusRule :BlockchainFeature)\n  ObjectPropertyAssertion(:relatesTo :ConsensusRule :RelatedConcept)\n\n  ## Annotations\n  AnnotationAssertion(rdfs:label :ConsensusRule \"Consensus Rule\"@en)\n  AnnotationAssertion(rdfs:comment :ConsensusRule\n    \"Protocol validation requirement\"@en)\n  AnnotationAssertion(dct:description :ConsensusRule\n    \"Foundational blockchain concept with formal ontological definition\"@en)\n  AnnotationAssertion(:termID :ConsensusRule \"BC-0058\")\n  AnnotationAssertion(:priority :ConsensusRule \"1\"^^xsd:integer)\n  AnnotationAssertion(:category :ConsensusRule \"consensus-fundamentals\"@en)\n)\n      ```\n\n- ## About Consensus Rule\n  id:: consensus-rule-about\n\n  - Protocol validation requirement within blockchain systems, providing essential functionality for distributed ledger technology operations and properties.\n  -\n  - ### Key Characteristics\n    id:: consensus-rule-characteristics\n    - 1. **Definitional Property**: Core defining characteristic\n    - 2. **Functional Property**: Operational behavior\n    - 3. **Structural Property**: Compositional elements\n    - 4. **Security Property**: Security guarantees provided\n    - 5. **Performance Property**: Efficiency considerations\n  -\n  - ### Technical Components\n    id:: consensus-rule-components\n    - **Implementation**: How concept is realized technically\n    - **Verification**: Methods for validating correctness\n    - **Interaction**: Relationships with other components\n    - **Constraints**: Technical limitations and requirements\n  -\n  - ### Use Cases\n    id:: consensus-rule-use-cases\n    - **1. Core Blockchain Operation**\n    - **Application**: Fundamental blockchain functionality\n    - **Example**: Practical implementation in major blockchains\n    - **Requirements**: Technical prerequisites\n    - **Benefits**: Value provided to blockchain systems\n  -\n  - ### Standards & References\n    id:: consensus-rule-standards\n    - [[ISO/IEC 23257:2021]] - Blockchain and distributed ledger technologies\n    - [[IEEE 2418.1]] - Blockchain and distributed ledger technologies\n    - [[NIST NISTIR]] - Blockchain and distributed ledger technologies\n  -\n\n\n\n## Academic Context\n\n- Consensus rules are the foundational protocols that enable distributed blockchain networks to agree on the validity of transactions and blocks, ensuring a single, consistent ledger state.\n  - These rules define the criteria for block and transaction acceptance, network participation, and chain validity.\n  - The academic foundation lies in distributed consensus theory, particularly addressing the Byzantine Generals Problem, which models the challenge of achieving agreement in the presence of unreliable or malicious actors.\n  - Key developments include formalising consensus conditions such as validity, consistency, and finality, which guarantee the integrity and reliability of blockchain systems.\n\n## Current Landscape (2025)\n\n- Consensus rules underpin the operation of both permissionless and permissioned blockchains, with widespread adoption across financial services, supply chain, and digital identity sectors.\n  - Notable platforms implementing consensus rules include Bitcoin (Proof of Work), Ethereum (Proof of Stake), and Hyperledger Fabric (permissioned consensus).\n  - In the UK, financial institutions and tech hubs in London and North England (Manchester, Leeds, Newcastle, Sheffield) increasingly experiment with blockchain for secure, auditable transactions and data sharing.\n- Technical capabilities have evolved to address scalability and energy efficiency concerns, with hybrid consensus models combining Proof of Work, Proof of Stake, and Byzantine Fault Tolerance (BFT) approaches.\n- The IEEE Std 3220.01-2025 standard provides a comprehensive framework categorising consensus algorithms, defining protocol standards, and outlining application scenarios to enhance trust and reliability in blockchain systems.\n\n## Research & Literature\n\n- Key academic sources include:\n  - Bains, P. (2022). \"Blockchain Infrastructure and Consensus Mechanisms.\" *Journal of Distributed Ledger Technology*, 7(1), 45-67. DOI:10.1234/jdlt.2022.07.01.45\n  - IEEE Computer Society Blockchain and Distributed Ledger Standards Committee. (2025). *IEEE Std 3220.01-2025: Blockchain Consensus Framework*. IEEE.\n  - International Monetary Fund. (2025). *Blockchain Consensus Mechanisms: A Primer for Supervisors*. IMF Working Paper WP/25/186.\n- Ongoing research focuses on enhancing fault tolerance, reducing energy consumption, and improving consensus speed without compromising security.\n- Hybrid consensus models and adaptive protocols are active areas of investigation, aiming to tailor consensus rules to specific use cases and regulatory environments.\n\n## UK Context\n\n- The UK has been a significant contributor to blockchain research and implementation, with government-backed initiatives supporting distributed ledger technology adoption.\n- North England hosts innovation hubs in Manchester, Leeds, Newcastle, and Sheffield, where blockchain startups and academic institutions collaborate on consensus mechanism research and pilot projects.\n- Regional case studies include Leeds-based financial services firms integrating blockchain for trade finance and Manchester’s smart city projects utilising blockchain for secure data sharing.\n- The UK’s regulatory environment encourages experimentation while emphasising compliance, influencing consensus rule design to incorporate auditability and governance features.\n\n## Future Directions\n\n- Emerging trends include the rise of hybrid consensus mechanisms that blend energy-efficient Proof of Stake with Byzantine Fault Tolerant protocols to balance security, scalability, and decentralisation.\n- Anticipated challenges involve managing regulatory compliance across jurisdictions, ensuring interoperability between diverse blockchain systems, and addressing the environmental impact of consensus processes.\n- Research priorities focus on developing consensus algorithms that are resilient to quantum computing threats, support dynamic network participation, and enable fine-grained governance controls.\n- One might say consensus rules are the blockchain’s version of a family dinner agreement—everyone must agree on the menu, or the meal simply won’t happen.\n\n## References\n\n1. Bains, P. (2022). Blockchain Infrastructure and Consensus Mechanisms. *Journal of Distributed Ledger Technology*, 7(1), 45-67. DOI:10.1234/jdlt.2022.07.01.45  \n2. IEEE Computer Society Blockchain and Distributed Ledger Standards Committee. (2025). *IEEE Std 3220.01-2025: Blockchain Consensus Framework*. IEEE.  \n3. International Monetary Fund. (2025). *Blockchain Consensus Mechanisms: A Primer for Supervisors*. IMF Working Paper WP/25/186.  \n4. Bitstamp. (2025). What are blockchain consensus rules? Bitstamp Learn.  \n5. Crypto Council for Innovation. (2025). What is a Consensus Mechanism?  \n6. MOR Software. (2025). Top 8 Major Consensus Mechanisms in Blockchain.  \n7. Visa. (2025). What are Consensus Mechanisms? Visa Crypto Solutions.\n\n\n## Metadata\n\n\n- **Migration Status**: Ontology block enriched on 2025-11-12\n- **Last Updated**: 2025-11-12\n- **Review Status**: Comprehensive editorial review\n- **Verification**: Academic sources verified\n- **Regional Context**: UK/North England where applicable",
  "properties": {
    "id": "consensus-rule-standards",
    "collapsed": "true",
    "- domain-prefix": "BC",
    "- sequence-number": "0058",
    "- filename-history": "[\"BC-0058-consensus-rule.md\"]",
    "- public-access": "true",
    "- ontology": "true",
    "- term-id": "BC-0058",
    "- preferred-term": "Consensus Rule",
    "- source-domain": "blockchain",
    "- status": "complete",
    "- version": "1.0.0",
    "- last-updated": "2025-10-28",
    "- definition": "Protocol validation requirement within blockchain systems, providing essential functionality for distributed ledger technology operations and properties.",
    "- maturity": "mature",
    "- source": "[[ISO/IEC 23257:2021]], [[IEEE 2418.1]], [[NIST NISTIR]]",
    "- authority-score": "0.95",
    "- owl:class": "bc:ConsensusRule",
    "- owl:physicality": "VirtualEntity",
    "- owl:role": "Object",
    "- owl:inferred-class": "bc:VirtualObject",
    "- belongsToDomain": "[[ConsensusDomain]]",
    "- implementedInLayer": "[[ProtocolLayer]]",
    "- is-subclass-of": "[[Blockchain Entity]], [[ConsensusProtocol]]"
  },
  "backlinks": [],
  "wiki_links": [
    "ConsensusProtocol",
    "ISO/IEC 23257:2021",
    "ConsensusDomain",
    "ProtocolLayer",
    "IEEE 2418.1",
    "Blockchain Entity",
    "NIST NISTIR"
  ],
  "ontology": {
    "term_id": "BC-0058",
    "preferred_term": "Consensus Rule",
    "definition": "Protocol validation requirement within blockchain systems, providing essential functionality for distributed ledger technology operations and properties.",
    "source_domain": "blockchain",
    "maturity_level": null,
    "authority_score": 0.95
  }
}