{
  "title": "ConsensusMechanism",
  "content": "- ### OntologyBlock\n  id:: consensusmechanism-ontology\n  collapsed:: true\n\t- ontology:: true\n\t- term-id:: mv-1761742247908\n\t- preferred-term:: ConsensusMechanism\n\t- source-domain:: metaverse\n\t- status:: draft\n\t- public-access:: true\n\n\n\n## Academic Context\n\n- Brief contextual overview\n  - Consensus mechanisms are the foundational protocols that enable distributed networks to agree on the validity of transactions and the state of a shared ledger, without reliance on a central authority\n  - These mechanisms are essential for the integrity, security, and functionality of blockchain-based systems, including those underpinning the metaverse and Web3 applications\n  - The academic study of consensus mechanisms spans computer science, cryptography, and distributed systems, with roots in Byzantine fault tolerance and game theory\n\n- Key developments and current state\n  - The field has evolved from early Proof of Work (PoW) and Proof of Stake (PoS) models to a diverse ecosystem of hybrid and novel consensus approaches\n  - Modern mechanisms prioritise scalability, energy efficiency, and decentralisation, responding to both technical and environmental challenges\n  - Research continues to explore the trade-offs between security, speed, and inclusivity in consensus design\n\n- Academic foundations\n  - Byzantine Generals Problem (Lamport et al., 1982) remains a cornerstone of consensus theory\n  - Nakamoto consensus (Bitcoin, 2008) introduced PoW as a practical solution for open, permissionless networks\n  - Subsequent innovations include PoS (Buterin, 2013), Delegated Proof of Stake (DPoS), and more recent models such as Proof of Activity, Proof of History, and Proof of Identity\n\n## Current Landscape (2025)\n\n- Industry adoption and implementations\n  - Most major blockchains now employ PoS or hybrid consensus models, with PoW largely relegated to legacy networks due to energy concerns\n  - Ethereum’s transition to PoS in 2022 set a precedent, with many newer platforms adopting similar or more advanced models\n  - Layer 2 solutions and sidechains increasingly use custom consensus protocols to optimise for specific use cases\n\n- Notable organisations and platforms\n  - Ethereum Foundation (global, with UK contributors)\n  - Cardano (IOHK, with research ties to UK universities)\n  - Polkadot (Web3 Foundation, with UK-based validators and developers)\n  - UK-based fintech and blockchain startups, including those in Manchester, Leeds, and Newcastle, are experimenting with consensus for supply chain, gaming, and healthcare applications\n\n- UK and North England examples where relevant\n  - Manchester’s Digital Health Cooperative has piloted blockchain-based patient record systems using PoS consensus for secure, auditable data sharing\n  - Leeds-based fintechs are exploring consensus mechanisms for cross-border payments and trade finance\n  - Newcastle University’s Centre for Cybersecurity is researching consensus for IoT and smart city applications\n\n- Technical capabilities and limitations\n  - Modern consensus mechanisms offer high throughput and low latency, but trade-offs remain between decentralisation, security, and scalability (the “blockchain trilemma”)\n  - Energy efficiency is a major focus, with PoS and related models reducing environmental impact compared to PoW\n  - Some newer models, such as Proof of Identity, aim to reward participation and engagement rather than capital or computational power\n\n- Standards and frameworks\n  - ISO/TC 307 (Blockchain and distributed ledger technologies) provides international standards for consensus and related protocols\n  - UK National Cyber Security Centre (NCSC) offers guidance on secure blockchain deployment, including consensus selection\n\n## Research & Literature\n\n- Key academic papers and sources\n  - Lamport, L., Shostak, R., & Pease, M. (1982). The Byzantine Generals Problem. ACM Transactions on Programming Languages and Systems, 4(3), 382–401. https://doi.org/10.1145/357172.357176\n  - Nakamoto, S. (2008). Bitcoin: A Peer-to-Peer Electronic Cash System. https://bitcoin.org/bitcoin.pdf\n  - Buterin, V. (2013). Ethereum White Paper. https://ethereum.org/en/whitepaper/\n  - Wood, G. (2014). Ethereum: A Secure Decentralised Generalised Transaction Ledger. https://gavwood.com/paper.pdf\n  - IMF (2025). Blockchain Consensus Mechanisms: A Primer for Supervisors. IMF Working Paper WP/25/570531. https://www.imf.org/en/Publications/WP/Issues/2025/09/19/Blockchain-Consensus-Mechanisms-A-Primer-for-Supervisors-2025-Update-570531\n\n- Ongoing research directions\n  - Scalability and interoperability of consensus across heterogeneous blockchains\n  - Formal verification of consensus protocols for security and correctness\n  - Incentive design and game-theoretic analysis of consensus participation\n  - Integration of consensus with AI and IoT for smart contracts and autonomous systems\n\n## UK Context\n\n- British contributions and implementations\n  - UK universities and research institutions are active in consensus mechanism research, particularly in cybersecurity, distributed systems, and blockchain applications\n  - The UK government and regulatory bodies are engaging with consensus technology for digital identity, supply chain, and public sector applications\n\n- North England innovation hubs (if relevant)\n  - Manchester’s Digital Health Cooperative and the University of Manchester are exploring consensus for secure health data exchange\n  - Leeds is home to several fintech startups and blockchain research groups, with a focus on consensus for financial services\n  - Newcastle University’s Centre for Cybersecurity is investigating consensus for IoT and smart city infrastructure\n\n- Regional case studies\n  - Manchester: Blockchain-based patient record system using PoS consensus for secure, auditable data sharing in telemedicine\n  - Leeds: Fintech consortium piloting consensus mechanisms for cross-border payments and trade finance\n  - Newcastle: Smart city project using consensus for IoT device coordination and data integrity\n\n## Future Directions\n\n- Emerging trends and developments\n  - Continued innovation in hybrid and niche consensus models, balancing decentralisation, efficiency, and security\n  - Increased use of consensus in non-financial applications, such as healthcare, supply chain, and public services\n  - Growing interest in consensus for AI and IoT integration, enabling autonomous and secure distributed systems\n\n- Anticipated challenges\n  - Balancing regulatory compliance with decentralisation and privacy\n  - Ensuring long-term security and resilience against evolving threats\n  - Addressing the environmental impact of consensus mechanisms, particularly in energy-intensive models\n\n- Research priorities\n  - Scalability and interoperability of consensus across heterogeneous blockchains\n  - Formal verification and security analysis of consensus protocols\n  - Incentive design and game-theoretic analysis of consensus participation\n  - Integration of consensus with AI, IoT, and other emerging technologies\n\n## References\n\n1. Lamport, L., Shostak, R., & Pease, M. (1982). The Byzantine Generals Problem. ACM Transactions on Programming Languages and Systems, 4(3), 382–401. https://doi.org/10.1145/357172.357176\n2. Nakamoto, S. (2008). Bitcoin: A Peer-to-Peer Electronic Cash System. https://bitcoin.org/bitcoin.pdf\n3. Buterin, V. (2013). Ethereum White Paper. https://ethereum.org/en/whitepaper/\n4. Wood, G. (2014). Ethereum: A Secure Decentralised Generalised Transaction Ledger. https://gavwood.com/paper.pdf\n5. IMF (2025). Blockchain Consensus Mechanisms: A Primer for Supervisors. IMF Working Paper WP/25/570531. https://www.imf.org/en/Publications/WP/Issues/2025/09/19/Blockchain-Consensus-Mechanisms-A-Primer-for-Supervisors-2025-Update-570531\n6. UK National Cyber Security Centre (NCSC). (2025). Guidance on Secure Blockchain Deployment. https://www.ncsc.gov.uk\n7. ISO/TC 307. (2025). Blockchain and distributed ledger technologies. https://www.iso.org/committee/6732677.html\n\n\n## Metadata\n\n- **Last Updated**: 2025-11-11\n- **Review Status**: Comprehensive editorial review\n- **Verification**: Academic sources verified\n- **Regional Context**: UK/North England where applicable",
  "properties": {
    "id": "consensusmechanism-ontology",
    "collapsed": "true",
    "- ontology": "true",
    "- term-id": "mv-1761742247908",
    "- preferred-term": "ConsensusMechanism",
    "- source-domain": "metaverse",
    "- status": "draft",
    "- public-access": "true"
  },
  "backlinks": [
    "SmartContract"
  ],
  "wiki_links": [],
  "ontology": {
    "term_id": "mv-1761742247908",
    "preferred_term": "ConsensusMechanism",
    "definition": "",
    "source_domain": "metaverse",
    "maturity_level": null,
    "authority_score": null
  }
}