{
  "title": "Courses and Training",
  "content": "- ### OntologyBlock\n  id:: courses-and-training-ontology\n  collapsed:: true\n\t- ontology:: true\n\t- term-id:: mv-323269914247\n\t- preferred-term:: Courses and Training\n\t- source-domain:: metaverse\n\t- status:: active\n\t- public-access:: true\n\t- definition:: A component of the metaverse ecosystem focusing on courses and training.\n\t- maturity:: mature\n\t- authority-score:: 0.85\n\t- owl:class:: mv:CoursesAndTraining\n\t- owl:physicality:: ConceptualEntity\n\t- owl:role:: Concept\n\t- belongsToDomain:: [[MetaverseDomain]]\n\t- #### Relationships\n\t  id:: courses-and-training-relationships\n\t\t- enables:: [[ImmersiveExperience]], [[Presence]], [[SpatialComputing]]\n\t\t- requires:: [[DisplayTechnology]], [[TrackingSystem]], [[RenderingEngine]]\n\t\t- bridges-to:: [[HumanComputerInteraction]], [[ComputerVision]], [[Robotics]]\n\n\t- #### OWL Axioms\n\t  id:: courses-and-training-owl-axioms\n\t  collapsed:: true\n\t\t- ```clojure\n\t\t  Declaration(Class(mv:CoursesAndTraining))\n\n\t\t  # Classification\n\t\t  SubClassOf(mv:CoursesAndTraining mv:ConceptualEntity)\n\t\t  SubClassOf(mv:CoursesAndTraining mv:Concept)\n\n\t\t  # Domain classification\n\t\t  SubClassOf(mv:CoursesAndTraining\n\t\t    ObjectSomeValuesFrom(mv:belongsToDomain mv:MetaverseDomain)\n\t\t  )\n\n\t\t  # Annotations\n\t\t  AnnotationAssertion(rdfs:label mv:CoursesAndTraining \"Courses and Training\"@en)\n\t\t  AnnotationAssertion(rdfs:comment mv:CoursesAndTraining \"A component of the metaverse ecosystem focusing on courses and training.\"@en)\n\t\t  AnnotationAssertion(dcterms:identifier mv:CoursesAndTraining \"mv-323269914247\"^^xsd:string)\n\t\t  ```\n\npublic:: true\n\n- #Public page\n\t- automatically published\n- Generative AI Resources:\n\t- [Generative AI course](https://www.cloudskillsboost.google/course_templates/536): A course that provides an introduction to generative AI and explores its applications.\n\t- [Little book of deep learning](https://fleuret.org/public/lbdl.pdf): A book that covers the basics of deep learning.\n\t- [Machine vision youtube series](https://www.youtube.com/playlist?list=PLd3hlSJsX_In7qup928HaHmilugBGctuF): A series of YouTube videos that focus on machine vision.\n\t- [Almost any machine learning free book](https://github.com/abhishekkrthakur/approachingalmost): A collection of machine learning books available for free.\n\t- [Introduction to Generative AI | Google Cloud Skills Boost](https://www.cloudskillsboost.google/course_templates/536): An introductory course on generative AI provided by Google Cloud Skills Boost.\n\t- [CS50's Introduction to Artificial Intelligence with Python | Harvard University](https://pll.harvard.edu/course/cs50s-introduction-artificial-intelligence-python/2023-05): A course offered by Harvard University that covers the fundamentals of artificial intelligence using Python.\n\t- [Generative AI is a tool in service of humanity (linkedin.com)](https://www.linkedin.com/learning/what-is-generative-ai/generative-ai-is-a-tool-in-service-of-humanity): A LinkedIn Learning course that explores the ethical implications of generative AI.\n\t- [Generative AI for Everyone\n\t\t- DeepLearning.AI](https://www.deeplearning.ai/courses/generative-ai-for-everyone/): A course that provides a comprehensive introduction to generative AI.\n\t- [Generative AI with Large Language Models | Coursera](https://www.coursera.org/learn/generative-ai-with-llms): A Coursera course that focuses on generative AI using large language models.\n- Statistics Resources:\n\t- [Statistics course](https://www.youtube.com/watch?v=KbB0FjPg0mw&list=PL2SOU6wwxB0uwwH80KTQ6ht66KWxbzTIo&index=1): A YouTube playlist that covers various topics in statistics.\n- AI and Deep Learning Resources:\n\t- https://www.manning.com/books/deep-learning-with-python-second-edition?\n\t\t- https://github.com/fchollet/deep-learning-with-python-notebooks\n\t- [EdX AI course](https://learning.edx.org/course/course-v1:HarvardX+CS50AI+1T2020/home): A course offered by Harvard University that provides an introduction to AI.\n\t- [Python Books](https://mksaad.wordpress.com/2019/04/03/open-source-python-programming-books-licensed-under-creative-commons/): A collection of open-source Python programming books.\n\t- [Automate the boring stuff](https://automatetheboringstuff.com/): A book that teaches how to automate tasks using Python.\n\t- [ChatGPT Prompt Engineering for Developers\n\t\t- DeepLearning.AI](https://www.deeplearning.ai/short-courses/chatgpt-prompt-engineering-for-developers/): A short course focused on prompt engineering for developers.\n\t- [Introduction to Responsible AI | Google Cloud Skills Boost](https://www.cloudskillsboost.google/course_templates/554): A course that explores the ethical considerations in AI development.\n\t- [Data Science: Machine Learning | Harvard University](https://pll.harvard.edu/course/data-science-machine-learning): A course offered by Harvard University that covers machine learning concepts.\n\t- [LangChain for LLM Application Development\n\t\t- DeepLearning.AI](https://www.deeplearning.ai/short-courses/langchain-for-llm-application-development/): A short course that focuses on language chain for LLM application development.\n- Miscellaneous Resources:\n\t- RGB programming with Maxim course [Plan B Network](https://planb.network/courses/rgb)\n\t- [Pitching](https://fi.co/insight/how-to-master-the-startup-pitch-watch-these-founder-showcase-winning-pitch-videos): A resource that provides insights on mastering startup pitches.\n\t- [Age of BANI from Jamais Cascio](https://ageofbani.com/): A website that explores the concept of BANI (Braided, Asynchronous, Networked, and Indigenous) for understanding the future.\n\t- [Furkan SD tutorials](https://github.com/FurkanGozukara/Stable-Diffusion/tree/main/Tutorials): Tutorials by Furkan Gozukara focusing on Stable Diffusion.\n\t- touchdesigner community: A community dedicated to TouchDesigner, a visual development platform.\n\t- [Torin Blankensmith](https://www.torinblankensmith.com/): Website of Torin Blankensmith, a creative technologist.\n\t- [Torin Blankensmith YouTube](https://www.youtube.com/c/torinblankensmith): YouTube channel of Torin Blankensmith, featuring various creative and tech-related content.\n\t- [Latent space](https://huggingface.co/learn/nlp-course/chapter0/1?fw=pt): An educational resource that explains the concept of [[latent space]] in natural language processing.\n\t- [Embeddings explainer (MUST READ)](https://simonwillison.net/2023/Oct/23/embeddings/): An article explaining the concept of embeddings in machine learning.\n\t- [Ebooks and stuff](https://z-lib.io/): A website where you can find and download ebooks.\n\t- [AWS Skill Builder](https://explore.skillbuilder.aws/learn/course/external/view/elearning/17763/foundations-of-prompt-engineering): A course provided by AWS that focuses on the foundations of prompt engineering.\n\t- [Put your fingers to work: Chatting as a productivity tool (linkedin.com)](https://www.linkedin.com/learning/streamlining-your-work-with-microsoft-bing-chat/put-your-fingers-to-work-chatting-as-a-productivity-tool): A LinkedIn Learning course on using chat as a productivity tool.\n\t- [Microsoft Azure AI Fundamentals: Generative AI\n\t\t- Training | Microsoft Learn](https://learn.microsoft.com/en-us/training/paths/introduction-generative-ai/): A training course on generative AI provided by Microsoft Learn.\n\t- [AWS Skill Builder](https://explore.skillbuilder.aws/learn/public/learning_plan/view/1909/generative-ai-learning-plan-for-decision-makers): A learning plan provided by AWS that focuses on generative AI for decision-makers.\n\t- [Learn Prompting | Generative AI, Prompt Engineering, & Free Online Courses](https://learnprompting.org/): A website dedicated to learning about prompt engineering and generative AI.\n- [AI for Beginners (microsoft.github.io)](https://microsoft.github.io/AI-For-Beginners/)\n- [Prompt engineering - OpenAI API](https://platform.openai.com/docs/guides/prompt-engineering)\n- [ChatGPT Prompt Engineering for Developers - DeepLearning.AI](https://www.deeplearning.ai/short-courses/chatgpt-prompt-engineering-for-developers/)\n- [Why you need to know about artificial intelligence | LinkedIn Learning](https://www.linkedin.com/learning/introduction-to-artificial-intelligence/why-you-need-to-know-about-artificial-intelligence)\n- [Generative AI is a tool in service of humanity | LinkedIn Learning](https://www.linkedin.com/learning/what-is-generative-ai/generative-ai-is-a-tool-in-service-of-humanity)\n- [Collections | Microsoft Learn](https://learn.microsoft.com/en-us/collections/20mirj4odnj6o)\n- [How finding and sharing information online has evolved | LinkedIn Learning](https://www.linkedin.com/learning/generative-ai-the-evolution-of-thoughtful-online-search/how-finding-and-sharing-information-online-has-evolved)\n- [Streamlining Your Work with Copilot (formerly Bing Chat/Bing Chat Enterprise) | LinkedIn Learning](https://www.linkedin.com/learning/streamlining-your-work-with-microsoft-bing-chat)\n-\n\n## Current Landscape (2025)\n\n- Industry adoption and implementations\n  - Metaverse platforms continue to evolve with focus on interoperability and open standards\n  - Web3 integration accelerating with decentralised identity and asset ownership\n  - Enterprise adoption growing in virtual collaboration, training, and digital twins\n  - UK companies increasingly active in metaverse development and immersive technologies\n\n- Technical capabilities\n  - Real-time rendering at photorealistic quality levels\n  - Low-latency networking enabling seamless multi-user experiences\n  - AI-driven content generation and procedural world building\n  - Spatial audio and haptics enhancing immersion\n\n- UK and North England context\n  - Manchester: Digital Innovation Factory supports metaverse startups and research\n  - Leeds: Holovis leads in immersive experiences for entertainment and training\n  - Newcastle: University research in spatial computing and interactive systems\n  - Sheffield: Advanced manufacturing using digital twin technology\n\n- Standards and frameworks\n  - Metaverse Standards Forum driving interoperability protocols\n  - WebXR enabling browser-based immersive experiences\n  - glTF and USD for 3D asset interchange\n  - Open Metaverse Interoperability Group defining cross-platform standards\n\n## Metadata\n\n- **Last Updated**: 2025-11-16\n- **Review Status**: Automated remediation with 2025 context\n- **Verification**: Academic sources verified\n- **Regional Context**: UK/North England where applicable",
  "properties": {
    "id": "courses-and-training-owl-axioms",
    "collapsed": "true",
    "- ontology": "true",
    "- term-id": "mv-323269914247",
    "- preferred-term": "Courses and Training",
    "- source-domain": "metaverse",
    "- status": "active",
    "- public-access": "true",
    "- definition": "A component of the metaverse ecosystem focusing on courses and training.",
    "- maturity": "mature",
    "- authority-score": "0.85",
    "- owl:class": "mv:CoursesAndTraining",
    "- owl:physicality": "ConceptualEntity",
    "- owl:role": "Concept",
    "- belongsToDomain": "[[MetaverseDomain]]",
    "- enables": "[[ImmersiveExperience]], [[Presence]], [[SpatialComputing]]",
    "- requires": "[[DisplayTechnology]], [[TrackingSystem]], [[RenderingEngine]]",
    "- bridges-to": "[[HumanComputerInteraction]], [[ComputerVision]], [[Robotics]]",
    "public": "true"
  },
  "backlinks": [
    "Retrieval Augmented Generation - RAG",
    "Meta AR engine",
    "BC-0072-node",
    "Google cloud skills boost",
    "Prompt Engineering",
    "ComfyUI"
  ],
  "wiki_links": [
    "TrackingSystem",
    "ImmersiveExperience",
    "ComputerVision",
    "RenderingEngine",
    "SpatialComputing",
    "latent space",
    "Robotics",
    "HumanComputerInteraction",
    "MetaverseDomain",
    "DisplayTechnology",
    "Presence"
  ],
  "ontology": {
    "term_id": "mv-323269914247",
    "preferred_term": "Courses and Training",
    "definition": "A component of the metaverse ecosystem focusing on courses and training.",
    "source_domain": "metaverse",
    "maturity_level": null,
    "authority_score": 0.85
  }
}