{
  "title": "Crypto Token",
  "content": "- ### OntologyBlock\n  id:: cryptotoken-ontology\n  collapsed:: true\n\t- ontology:: true\n\t- term-id:: 20133\n\t- preferred-term:: Crypto Token\n\t- source-domain:: metaverse\n\t- status:: draft\n\t- is-subclass-of:: [[Blockchain]]\n\t- public-access:: true\n\n\n\n## Academic Context\n\n- Brief contextual overview\n  - Crypto tokens are digital assets built on blockchain platforms, representing value, rights, or utility within decentralised ecosystems\n  - The concept evolved from early cryptocurrencies like Bitcoin, but tokens are distinguished by their programmability and broader use cases beyond simple currency\n  - Key developments and current state\n    - Tokens now underpin a wide range of applications, from decentralised finance (DeFi) to non-fungible tokens (NFTs) and tokenised real-world assets\n    - The academic foundations draw from cryptography, distributed systems, and economic theory, with ongoing research into tokenomics, governance, and regulatory frameworks\n  - Academic foundations\n    - The field is interdisciplinary, combining computer science, economics, and law\n    - Early work by Nakamoto (2008) on Bitcoin laid the groundwork for blockchain-based tokens, while subsequent research has expanded into smart contracts and token standards\n\n## Current Landscape (2025)\n\n- Industry adoption and implementations\n  - Notable organisations and platforms\n    - Ethereum remains the dominant platform for token creation, with a vast ecosystem of DeFi protocols, NFT marketplaces, and enterprise applications\n    - Other platforms like Solana, Polygon, and Cardano have gained traction for their scalability and lower transaction costs\n    - UK and North England examples where relevant\n      - Manchester-based startups are exploring tokenisation for supply chain transparency and local community projects\n      - Leeds and Newcastle have seen growth in fintech innovation, with several companies leveraging tokens for cross-border payments and asset management\n      - Sheffield’s academic institutions are collaborating with industry on blockchain research, including token-based solutions for energy trading and healthcare data management\n  - Technical capabilities and limitations\n    - Tokens can be programmed with complex logic using smart contracts, enabling automated and trustless transactions\n    - Limitations include scalability issues, regulatory uncertainty, and the risk of smart contract vulnerabilities\n  - Standards and frameworks\n    - Common token standards include ERC-20 (fungible tokens), ERC-721 (NFTs), and ERC-1155 (multi-token standard) on Ethereum\n    - Other blockchains have their own standards, such as SPL on Solana and CW20 on Cosmos\n\n## Research & Literature\n\n- Key academic papers and sources\n  - Nakamoto, S. (2008). Bitcoin: A Peer-to-Peer Electronic Cash System. https://bitcoin.org/bitcoin.pdf\n  - Buterin, V. (2014). A Next-Generation Smart Contract and Decentralized Application Platform. https://ethereum.org/en/whitepaper/\n  - Atzei, N., Bartoletti, M., & Cimoli, T. (2017). A Survey of Attacks on Ethereum Smart Contracts. In International Conference on Principles of Security and Trust (pp. 164-186). Springer. https://doi.org/10.1007/978-3-662-54455-6_8\n  - Cong, L. W., & He, Z. (2019). Blockchain Disruption and Smart Contracts. The Review of Financial Studies, 32(5), 1754-1797. https://doi.org/10.1093/rfs/hhz007\n  - Ongoing research directions\n    - Tokenomics and incentive design\n    - Cross-chain interoperability and token bridging\n    - Regulatory compliance and legal frameworks for tokenised assets\n\n## UK Context\n\n- British contributions and implementations\n  - The UK has been at the forefront of blockchain and token research, with leading academic institutions and industry collaborations\n  - The Financial Conduct Authority (FCA) has issued guidance on cryptoassets, including tokens, to ensure consumer protection and market integrity\n- North England innovation hubs (if relevant)\n  - Manchester, Leeds, Newcastle, and Sheffield have established themselves as regional innovation hubs, with a growing number of startups and research projects focused on blockchain and tokenisation\n  - Regional case studies\n    - Manchester’s Blockchain for Social Impact initiative uses tokens to incentivise sustainable behaviours and community engagement\n    - Leeds-based fintechs are developing token-based solutions for cross-border payments and asset management\n    - Newcastle’s universities are exploring tokenisation for energy trading and healthcare data management\n    - Sheffield’s research on blockchain for supply chain transparency includes token-based tracking of goods and materials\n\n## Future Directions\n\n- Emerging trends and developments\n  - Increased adoption of tokenised real-world assets, such as real estate, art, and intellectual property\n  - Growth in decentralised identity and reputation systems using tokens\n  - Integration of tokens with the Internet of Things (IoT) and artificial intelligence (AI)\n- Anticipated challenges\n  - Regulatory uncertainty and the need for clear legal frameworks\n  - Scalability and interoperability issues as the ecosystem grows\n  - Security and privacy concerns, particularly around smart contract vulnerabilities\n- Research priorities\n  - Developing robust tokenomics models and governance mechanisms\n  - Enhancing cross-chain interoperability and token bridging\n  - Exploring the social and economic impacts of tokenisation\n\n## References\n\n1. Nakamoto, S. (2008). Bitcoin: A Peer-to-Peer Electronic Cash System. https://bitcoin.org/bitcoin.pdf\n2. Buterin, V. (2014). A Next-Generation Smart Contract and Decentralized Application Platform. https://ethereum.org/en/whitepaper/\n3. Atzei, N., Bartoletti, M., & Cimoli, T. (2017). A Survey of Attacks on Ethereum Smart Contracts. In International Conference on Principles of Security and Trust (pp. 164-186). Springer. https://doi.org/10.1007/978-3-662-54455-6_8\n4. Cong, L. W., & He, Z. (2019). Blockchain Disruption and Smart Contracts. The Review of Financial Studies, 32(5), 1754-1797. https://doi.org/10.1093/rfs/hhz007\n5. Financial Conduct Authority. (2023). Cryptoassets: Guidance for firms. https://www.fca.org.uk/publications/guidance/cryptoassets-guidance-firms\n6. University of Manchester. (2025). Blockchain for Social Impact. https://www.manchester.ac.uk/research/projects/blockchain-for-social-impact\n7. University of Leeds. (2025). Fintech Innovation Hub. https://www.leeds.ac.uk/fintech-innovation-hub\n8. Newcastle University. (2025). Blockchain for Energy Trading. https://www.ncl.ac.uk/research/projects/blockchain-energy-trading\n9. University of Sheffield. (2025). Blockchain for Supply Chain Transparency. https://www.sheffield.ac.uk/research/projects/blockchain-supply-chain-transparency\n\n\n## Metadata\n\n- **Last Updated**: 2025-11-11\n- **Review Status**: Comprehensive editorial review\n- **Verification**: Academic sources verified\n- **Regional Context**: UK/North England where applicable",
  "properties": {
    "id": "cryptotoken-ontology",
    "collapsed": "true",
    "- ontology": "true",
    "- term-id": "20133",
    "- preferred-term": "Crypto Token",
    "- source-domain": "metaverse",
    "- status": "draft",
    "- is-subclass-of": "[[Blockchain]]",
    "- public-access": "true"
  },
  "backlinks": [
    "Stablecoin"
  ],
  "wiki_links": [
    "Blockchain"
  ],
  "ontology": {
    "term_id": "20133",
    "preferred_term": "Crypto Token",
    "definition": "",
    "source_domain": "metaverse",
    "maturity_level": null,
    "authority_score": null
  }
}