{
  "title": "Cryptography",
  "content": "- ### OntologyBlock\n  id:: cryptography-ontology\n  collapsed:: true\n\n  - **Identification**\n\n    - domain-prefix:: BC\n\n    - sequence-number:: 0026\n\n    - filename-history:: [\"BC-0026-cryptography.md\"]\n    - ontology:: true\n    - is-subclass-of:: [[BlockchainTechnology]]\n    - term-id:: BC-0026\n    - preferred-term:: Cryptography\n    - source-domain:: blockchain\n    - status:: complete\n    - public-access:: true\n    - version:: 1.0.0\n    - last-updated:: 2025-10-28\n\n  - **Definition**\n    - definition:: Cryptography is the mathematical science of securing information through techniques that transform data into unintelligible forms for unauthorized parties whilst enabling authorized parties to reverse the transformation, providing confidentiality, integrity, authentication, and non-repudiation in blockchain systems.\n    - maturity:: mature\n    - source:: [[ISO/IEC 18033]], [[NIST FIPS]], [[NIST SP]]\n    - authority-score:: 1.0\n\n  - **Semantic Classification**\n    - owl:class:: bc:Cryptography\n    - owl:physicality:: VirtualEntity\n    - owl:role:: Object\n    - owl:inferred-class:: bc:VirtualObject\n    - belongsToDomain:: [[CryptographicDomain]]\n\n  - #### OWL Restrictions\n    \n    \n    \n\n  - #### CrossDomainBridges\n    - bridges-to:: [[MathematicalScience]] via is-subclass-of\n    - bridges-to:: [[InformationProtection]] via is-subclass-of\n    - bridges-to:: [[SecurityTechnology]] via is-subclass-of\n    - bridges-from:: [[DistributedLedgerTechnologyDlt]] via depends-on\n\n  -",
  "properties": {
    "id": "cryptography-ontology",
    "collapsed": "true",
    "- domain-prefix": "BC",
    "- sequence-number": "0026",
    "- filename-history": "[\"BC-0026-cryptography.md\"]",
    "- ontology": "true",
    "- is-subclass-of": "[[BlockchainTechnology]]",
    "- term-id": "BC-0026",
    "- preferred-term": "Cryptography",
    "- source-domain": "blockchain",
    "- status": "complete",
    "- public-access": "true",
    "- version": "1.0.0",
    "- last-updated": "2025-10-28",
    "- definition": "Cryptography is the mathematical science of securing information through techniques that transform data into unintelligible forms for unauthorized parties whilst enabling authorized parties to reverse the transformation, providing confidentiality, integrity, authentication, and non-repudiation in blockchain systems.",
    "- maturity": "mature",
    "- source": "[[ISO/IEC 18033]], [[NIST FIPS]], [[NIST SP]]",
    "- authority-score": "1.0",
    "- owl:class": "bc:Cryptography",
    "- owl:physicality": "VirtualEntity",
    "- owl:role": "Object",
    "- owl:inferred-class": "bc:VirtualObject",
    "- belongsToDomain": "[[CryptographicDomain]]",
    "- bridges-to": "[[SecurityTechnology]] via is-subclass-of",
    "- bridges-from": "[[DistributedLedgerTechnologyDlt]] via depends-on"
  },
  "backlinks": [
    "BC-0030-digital-signature",
    "RGB and Client Side Validation",
    "BC-0050-cryptographic-commitment",
    "BC-0027-hash-function",
    "BC-0033-zero-knowledge-proof",
    "BC-0034-nonce",
    "BC-0049-salt",
    "BC-0031-public-key-cryptography",
    "SHA-256"
  ],
  "wiki_links": [
    "NIST SP",
    "BlockchainTechnology",
    "SecurityTechnology",
    "DistributedLedgerTechnologyDlt",
    "NIST FIPS",
    "ISO/IEC 18033",
    "CryptographicDomain",
    "MathematicalScience",
    "InformationProtection"
  ],
  "ontology": {
    "term_id": "BC-0026",
    "preferred_term": "Cryptography",
    "definition": "Cryptography is the mathematical science of securing information through techniques that transform data into unintelligible forms for unauthorized parties whilst enabling authorized parties to reverse the transformation, providing confidentiality, integrity, authentication, and non-repudiation in blockchain systems.",
    "source_domain": "blockchain",
    "maturity_level": null,
    "authority_score": 1.0
  }
}