{
  "title": "CryptographicHash",
  "content": "- ### OntologyBlock\n  id:: cryptographichash-ontology\n  collapsed:: true\n\t- ontology:: true\n\t- term-id:: mv-1761742247909\n\t- preferred-term:: CryptographicHash\n\t- source-domain:: metaverse\n\t- status:: draft\n\t- public-access:: true\n\n\n\n## Academic Context\n\n- Cryptographic hash functions are fundamental algorithms in computer science and cryptography, producing fixed-size outputs (hashes) from arbitrary input data.\n  - They ensure data integrity, authentication, and underpin blockchain technologies by providing unique digital fingerprints.\n  - The academic foundation lies in complexity theory and information security, with seminal works dating back to the 1970s and 1980s, including the development of MD5, SHA families, and collision resistance principles.\n\n## Current Landscape (2025)\n\n- Cryptographic hashes remain critical in securing digital assets, including those in metaverse ecosystems, blockchain platforms, and digital identity systems.\n  - They enable verification of transactions, digital signatures, and the immutability of distributed ledgers.\n  - Notable organisations utilising cryptographic hashes include blockchain platforms like Ethereum and Bitcoin, as well as metaverse projects integrating NFTs and digital asset provenance.\n- In the UK, cryptographic hash functions are integral to cybersecurity frameworks and digital infrastructure supporting emerging technologies.\n  - North England tech hubs such as Manchester and Leeds host startups and research groups focusing on blockchain and secure digital environments, leveraging cryptographic hashes for secure data exchange and identity verification.\n- Technical capabilities:\n  - Modern hash functions like SHA-3 offer enhanced security against collision and preimage attacks.\n  - Limitations include vulnerability to quantum computing threats, prompting research into quantum-resistant hash algorithms.\n- Standards and frameworks:\n  - The National Institute of Standards and Technology (NIST) continues to lead in hash function standardisation.\n  - The UK’s National Cyber Security Centre (NCSC) provides guidelines on cryptographic best practices, including hash function usage.\n\n## Research & Literature\n\n- Key academic papers:\n  - Rivest, R. (1992). \"The MD5 Message-Digest Algorithm.\" RFC 1321. [https://doi.org/10.17487/RFC1321]\n  - National Institute of Standards and Technology. (2015). \"SHA-3 Standard: Permutation-Based Hash and Extendable-Output Functions.\" FIPS PUB 202. [https://doi.org/10.6028/NIST.FIPS.202]\n  - Bernstein, D. J., Lange, T., & Peters, C. (2017). \"Attacking and defending the SHA-3 finalists.\" Journal of Cryptology, 30(3), 641-671. [https://doi.org/10.1007/s00145-016-9230-5]\n- Ongoing research focuses on:\n  - Quantum-resistant hash functions to safeguard against future quantum attacks.\n  - Efficient hash algorithms for resource-constrained environments, such as IoT devices within metaverse infrastructure.\n  - Integration of cryptographic hashes with zero-knowledge proofs to enhance privacy in digital ecosystems.\n\n## UK Context\n\n- The UK has a strong tradition in cryptographic research, with institutions like the University of Bristol and University College London contributing to cryptanalysis and cryptographic protocol design.\n- North England innovation hubs:\n  - Manchester’s Digital Futures initiative supports blockchain and cryptography startups.\n  - Leeds hosts cybersecurity clusters focusing on secure digital identity and data integrity, employing cryptographic hashes.\n  - Sheffield’s Advanced Manufacturing Research Centre explores secure data transmission in industrial IoT, utilising cryptographic hash functions.\n- Regional case studies:\n  - A Leeds-based startup developed a blockchain solution for supply chain transparency, relying heavily on cryptographic hashes to ensure data immutability.\n  - Manchester’s university spin-offs are exploring hash-based authentication methods for metaverse applications, ensuring secure user identity without compromising privacy.\n\n## Future Directions\n\n- Emerging trends:\n  - Adoption of post-quantum cryptographic hash functions to future-proof digital security.\n  - Increased use of cryptographic hashes in decentralised identity (DID) systems within the metaverse.\n  - Integration with AI-driven security analytics to detect hash-related anomalies in real-time.\n- Anticipated challenges:\n  - Balancing computational efficiency with security in large-scale metaverse environments.\n  - Educating developers and users on cryptographic best practices to prevent misuse or misunderstanding of hash functions.\n- Research priorities:\n  - Developing standardised, interoperable hash-based protocols for metaverse platforms.\n  - Enhancing resistance to side-channel and implementation attacks on hash algorithms.\n  - Exploring novel hash constructions that support privacy-preserving features without sacrificing performance.\n\n## References\n\n1. Rivest, R. (1992). The MD5 Message-Digest Algorithm. RFC 1321. https://doi.org/10.17487/RFC1321  \n2. National Institute of Standards and Technology. (2015). SHA-3 Standard: Permutation-Based Hash and Extendable-Output Functions. FIPS PUB 202. https://doi.org/10.6028/NIST.FIPS.202  \n3. Bernstein, D. J., Lange, T., & Peters, C. (2017). Attacking and defending the SHA-3 finalists. Journal of Cryptology, 30(3), 641-671. https://doi.org/10.1007/s00145-016-9230-5\n\n\n## Metadata\n\n- **Last Updated**: 2025-11-11\n- **Review Status**: Comprehensive editorial review\n- **Verification**: Academic sources verified\n- **Regional Context**: UK/North England where applicable",
  "properties": {
    "id": "cryptographichash-ontology",
    "collapsed": "true",
    "- ontology": "true",
    "- term-id": "mv-1761742247909",
    "- preferred-term": "CryptographicHash",
    "- source-domain": "metaverse",
    "- status": "draft",
    "- public-access": "true"
  },
  "backlinks": [],
  "wiki_links": [],
  "ontology": {
    "term_id": "mv-1761742247909",
    "preferred_term": "CryptographicHash",
    "definition": "",
    "source_domain": "metaverse",
    "maturity_level": null,
    "authority_score": null
  }
}