{
  "title": "Cryptocurrency",
  "content": "- ### OntologyBlock\n  id:: cryptocurrency-ontology\n  collapsed:: true\n\t- ontology:: true\n\t- term-id:: 20134\n\t- source-domain:: metaverse\n\t- status:: draft\n\t- public-access:: true\n\t- preferred-term:: Cryptocurrency\n\t- definition:: A digital currency secured by cryptographic algorithms, operating on a decentralized blockchain network without central authority, enabling peer-to-peer value transfer.\n\t- maturity:: mature\n\t- source:: [[Reed Smith]], [[ISO 24165]]\n\t- owl:class:: mv:Cryptocurrency\n\t- owl:physicality:: VirtualEntity\n\t- owl:role:: Object\n\t- owl:inferred-class:: mv:VirtualObject\n\t- owl:functional-syntax:: true\n\t- belongsToDomain:: [[VirtualEconomyDomain]], [[InfrastructureDomain]]\n\t- implementedInLayer:: [[Middleware Layer]]\n\t- #### Relationships\n\t  id:: cryptocurrency-relationships\n\t\t- is-enabled-by:: [[Distributed Ledger Technology (DLT)]]\n\t\t- is-dependency-of:: [[Play-to-Earn (P2E)]]\n\t\t- has-part:: [[Blockchain]], [[Consensus Mechanism]], [[Cryptographic Protocol]], [[Transaction System]]\n\t\t- is-part-of:: [[Digital Currency System]], [[Decentralized Network]], [[Money]]\n\t\t- requires:: [[Distributed Ledger]], [[Mining]] or [[Staking]], [[Wallet]]\n\t\t- depends-on:: [[Cryptographic Hash]], [[Digital Signature]], [[Peer-to-Peer Network]]\n\t\t- enables:: [[Decentralized Payment]], [[Value Storage]], [[Programmable Money]], [[Cross-Border Transfer]]\n\t- #### OWL Axioms\n\t  id:: cryptocurrency-owl-axioms\n\t  collapsed:: true\n\t\t- ```clojure\n\t\t  Declaration(Class(mv:Cryptocurrency))\n\n\t\t  # Classification along two primary dimensions\n\t\t  SubClassOf(mv:Cryptocurrency mv:VirtualEntity)\n\t\t  SubClassOf(mv:Cryptocurrency mv:Object)\n\n\t\t  # Cryptocurrency operates on blockchain\n\t\t  SubClassOf(mv:Cryptocurrency\n\t\t    ObjectSomeValuesFrom(mv:hasPart mv:Blockchain)\n\t\t  )\n\n\t\t  # Cryptocurrency requires consensus mechanism\n\t\t  SubClassOf(mv:Cryptocurrency\n\t\t    ObjectSomeValuesFrom(mv:requiresComponent mv:ConsensusMechanism)\n\t\t  )\n\n\t\t  # Cryptocurrency secured by cryptography\n\t\t  SubClassOf(mv:Cryptocurrency\n\t\t    ObjectSomeValuesFrom(mv:hasPart mv:CryptographicProtocol)\n\t\t  )\n\n\t\t  # Cryptocurrency enables decentralized payment\n\t\t  SubClassOf(mv:Cryptocurrency\n\t\t    ObjectSomeValuesFrom(mv:enables mv:DecentralizedPayment)\n\t\t  )\n\n\t\t  # Domain classification\n\t\t  SubClassOf(mv:Cryptocurrency\n\t\t    ObjectSomeValuesFrom(mv:belongsToDomain mv:VirtualEconomyDomain)\n\t\t  )\n\n\t\t  SubClassOf(mv:Cryptocurrency\n\t\t    ObjectSomeValuesFrom(mv:belongsToDomain mv:InfrastructureDomain)\n\t\t  )\n\n\t\t  # Layer classification\n\t\t  SubClassOf(mv:Cryptocurrency\n\t\t    ObjectSomeValuesFrom(mv:implementedInLayer mv:MiddlewareLayer)\n\t\t  )\n\n\t\t  # Cryptocurrency has unique symbol\n\t\t  SubClassOf(mv:Cryptocurrency\n\t\t    DataExactCardinality(1 mv:hasCurrencySymbol)\n\t\t  )\n\n\t\t  # Cryptocurrency types distinction\n\t\t  DisjointClasses(mv:NativeCryptocurrency mv:TokenBasedCryptocurrency)\n\n  # Property characteristics\n  AsymmetricObjectProperty(dt:isdependencyof)\n\n  # Property characteristics\n  TransitiveObjectProperty(dt:ispartof)\n\n  # Property characteristics\n  AsymmetricObjectProperty(dt:requires)\n\n  # Property characteristics\n  AsymmetricObjectProperty(dt:dependson)\n\n  # Property characteristics\n  AsymmetricObjectProperty(dt:enables)\n```\n- ## About Cryptocurrency\n  id:: cryptocurrency-about\n\t- Cryptocurrency represents a revolutionary digital currency paradigm secured by cryptographic algorithms and operating on decentralized blockchain networks. Unlike traditional fiat currencies controlled by central banks, cryptocurrencies rely on distributed consensus mechanisms and cryptographic verification to maintain their integrity and enable peer-to-peer value transfer without intermediaries. Bitcoin, launched in 2009, pioneered this technology, followed by thousands of alternative cryptocurrencies (altcoins) serving various purposes from medium of exchange to platform fuel for decentralized applications.\n\t- ### Key Characteristics\n\t  id:: cryptocurrency-characteristics\n\t\t- **Decentralization**: No central authority or single point of control or failure\n\t\t- **Cryptographic Security**: Protected by advanced cryptographic algorithms resistant to counterfeiting\n\t\t- **Transparency**: All transactions publicly recorded on immutable blockchain ledger\n\t\t- **Pseudonymity**: Addresses provide privacy while maintaining transaction traceability\n\t\t- **Scarcity**: Many cryptocurrencies have fixed or predictable supply schedules\n\t\t- **Borderless**: Operates globally without geographic restrictions or intermediaries\n\t\t- **Programmability**: Can encode complex rules for issuance, transfer, and governance\n\t\t- **Irreversibility**: Confirmed transactions cannot be reversed or altered\n\t\t- **Permissionless**: Anyone can participate without approval from authorities\n\t- ### Technical Components\n\t  id:: cryptocurrency-components\n\t\t- [[Blockchain]] - Distributed ledger recording all cryptocurrency transactions in sequential blocks\n\t\t- [[Consensus Mechanism]] - Algorithm (Proof of Work, Proof of Stake) ensuring network agreement on transaction validity\n\t\t- [[Cryptographic Hash Function]] - One-way mathematical function securing transaction data and block integrity\n\t\t- [[Digital Signature]] - Cryptographic proof of ownership and authorization for spending\n\t\t- [[Wallet]] - Software for storing private keys and managing cryptocurrency holdings\n\t\t- [[Mining]] or [[Staking]] - Process for validating transactions and creating new currency units\n\t\t- [[Peer-to-Peer Network]] - Distributed nodes communicating to propagate and validate transactions\n\t\t- [[Transaction Pool]] - Mempool of unconfirmed transactions waiting for block inclusion\n\t\t- [[Block Explorer]] - Interface for querying and visualizing blockchain data\n\t- ### Functional Capabilities\n\t  id:: cryptocurrency-capabilities\n\t\t- **Peer-to-Peer Payments**: Direct transfer of value between parties without intermediaries\n\t\t- **Store of Value**: Digital asset with scarcity properties for preserving wealth\n\t\t- **Medium of Exchange**: Currency for purchasing goods and services in accepting ecosystems\n\t\t- **Unit of Account**: Denominating prices and measuring value in digital economies\n\t\t- **Remittances**: Fast, low-cost international money transfers across borders\n\t\t- **Micropayments**: Enabling small-value transactions economically infeasible with traditional systems\n\t\t- **Programmable Transfers**: Conditional payments executed automatically based on smart contract logic\n\t\t- **Censorship Resistance**: Transactions cannot be blocked by authorities or intermediaries\n\t\t- **Financial Inclusion**: Banking services accessible to unbanked populations with internet access\n\t\t- **Hedge Against Inflation**: Fixed supply providing alternative to inflationary fiat currencies\n\t- ### Use Cases\n\t  id:: cryptocurrency-use-cases\n\t\t- **Digital Gold**: Bitcoin as store of value and inflation hedge comparable to gold\n\t\t- **Smart Contract Platform**: Ethereum (ETH) as fuel for decentralized applications and DeFi\n\t\t- **Cross-Border Payments**: Using XRP, Stellar (XLM), or Bitcoin for international remittances\n\t\t- **Metaverse Economies**: Native currencies for virtual worlds and gaming ecosystems\n\t\t- **Decentralized Finance**: Collateral, lending, and liquidity provision in DeFi protocols\n\t\t- **Privacy Transactions**: Monero (XMR), Zcash (ZEC) for anonymous value transfer\n\t\t- **Content Creator Payments**: Tipping and micropayments for digital content creators\n\t\t- **Merchant Payments**: Accepting cryptocurrency at point of sale for goods and services\n\t\t- **Fundraising**: Initial Coin Offerings (ICOs) and token sales for project funding\n\t\t- **Stablecoins**: Cryptocurrency pegged to fiat for stable value (USDC, USDT, DAI)\n\t\t- **Central Bank Digital Currencies**: Government-issued digital currencies based on blockchain technology\n\t- ### Standards & References\n\t  id:: cryptocurrency-standards\n\t\t- [[ISO 24165]] - International standard for digital token identification including cryptocurrencies\n\t\t- [[FATF VASP Guidelines]] - Financial Action Task Force guidance on Virtual Asset Service Providers\n\t\t- [[IMF CBDC Notes]] - International Monetary Fund research on Central Bank Digital Currencies\n\t\t- [[Bitcoin Whitepaper]] - Satoshi Nakamoto's foundational document defining cryptocurrency\n\t\t- [[Ethereum Yellowpaper]] - Formal specification of Ethereum blockchain and smart contracts\n\t\t- [[BIP (Bitcoin Improvement Proposals)]] - Technical standards for Bitcoin protocol enhancements\n\t\t- [[EIP (Ethereum Improvement Proposals)]] - Standards process for Ethereum network upgrades\n\t\t- [[MiCA (Markets in Crypto-Assets)]] - EU regulatory framework for cryptocurrency markets\n\t\t- [[SEC Guidance]] - US Securities and Exchange Commission guidance on crypto assets\n\t- ### Related Concepts\n\t  id:: cryptocurrency-related\n\t\t- [[Crypto Token]] - Tokens built on blockchain platforms vs. native cryptocurrencies\n\t\t- [[Blockchain]] - Underlying distributed ledger technology enabling cryptocurrencies\n\t\t- [[Digital Asset]] - Broader category including cryptocurrencies and other digital value\n\t\t- [[Stablecoin]] - Cryptocurrency designed to maintain stable value pegged to fiat\n\t\t- [[Central Bank Digital Currency]] - Government-issued digital currency using blockchain principles\n\t\t- [[DeFi]] - Decentralized financial services built on cryptocurrency infrastructure\n\t\t- [[Mining]] - Computational process for validating transactions and minting new cryptocurrency\n\t\t- [[Wallet]] - Interface for managing cryptocurrency holdings and keys\n\t\t- [[Exchange]] - Platform for trading cryptocurrencies for fiat or other crypto\n\t\t- [[VirtualObject]] - Ontology classification for digital objects in virtual environments\n\n\n## Current Landscape (2025)\n\n- Industry adoption and implementations\n  - Metaverse platforms continue to evolve with focus on interoperability and open standards\n  - Web3 integration accelerating with decentralised identity and asset ownership\n  - Enterprise adoption growing in virtual collaboration, training, and digital twins\n  - UK companies increasingly active in metaverse development and immersive technologies\n\n- Technical capabilities\n  - Real-time rendering at photorealistic quality levels\n  - Low-latency networking enabling seamless multi-user experiences\n  - AI-driven content generation and procedural world building\n  - Spatial audio and haptics enhancing immersion\n\n- UK and North England context\n  - Manchester: Digital Innovation Factory supports metaverse startups and research\n  - Leeds: Holovis leads in immersive experiences for entertainment and training\n  - Newcastle: University research in spatial computing and interactive systems\n  - Sheffield: Advanced manufacturing using digital twin technology\n\n- Standards and frameworks\n  - Metaverse Standards Forum driving interoperability protocols\n  - WebXR enabling browser-based immersive experiences\n  - glTF and USD for 3D asset interchange\n  - Open Metaverse Interoperability Group defining cross-platform standards\n\n## Metadata\n\n- **Last Updated**: 2025-11-16\n- **Review Status**: Automated remediation with 2025 context\n- **Verification**: Academic sources verified\n- **Regional Context**: UK/North England where applicable",
  "properties": {
    "id": "cryptocurrency-related",
    "collapsed": "true",
    "- ontology": "true",
    "- term-id": "20134",
    "- source-domain": "metaverse",
    "- status": "draft",
    "- public-access": "true",
    "- preferred-term": "Cryptocurrency",
    "- definition": "A digital currency secured by cryptographic algorithms, operating on a decentralized blockchain network without central authority, enabling peer-to-peer value transfer.",
    "- maturity": "mature",
    "- source": "[[Reed Smith]], [[ISO 24165]]",
    "- owl:class": "mv:Cryptocurrency",
    "- owl:physicality": "VirtualEntity",
    "- owl:role": "Object",
    "- owl:inferred-class": "mv:VirtualObject",
    "- owl:functional-syntax": "true",
    "- belongsToDomain": "[[VirtualEconomyDomain]], [[InfrastructureDomain]]",
    "- implementedInLayer": "[[Middleware Layer]]",
    "- is-enabled-by": "[[Distributed Ledger Technology (DLT)]]",
    "- is-dependency-of": "[[Play-to-Earn (P2E)]]",
    "- has-part": "[[Blockchain]], [[Consensus Mechanism]], [[Cryptographic Protocol]], [[Transaction System]]",
    "- is-part-of": "[[Digital Currency System]], [[Decentralized Network]], [[Money]]",
    "- requires": "[[Distributed Ledger]], [[Mining]] or [[Staking]], [[Wallet]]",
    "- depends-on": "[[Cryptographic Hash]], [[Digital Signature]], [[Peer-to-Peer Network]]",
    "- enables": "[[Decentralized Payment]], [[Value Storage]], [[Programmable Money]], [[Cross-Border Transfer]]"
  },
  "backlinks": [
    "Patent",
    "BC-0483-us-regulatory-framework",
    "Transaction Confirmation",
    "Digital Asset Risks",
    "AI Model Card",
    "Creator Royalty Token",
    "BC-0481-fatf-recommendations",
    "Carbon Credit Token",
    "BC-0484-asia-pacific-regulation",
    "Money",
    "Central Bank Digital Currency (CBDC)",
    "PrivateBlockchain",
    "Coin",
    "AI Agent System",
    "Bitcoin",
    "Bitcoin As Money",
    "SmartContract",
    "Digital Objects",
    "AI Governance Principle",
    "Value Transfer",
    "TokenEconomicsDomain",
    "Proof Of Authority",
    "Address",
    "Decentralized Finance"
  ],
  "wiki_links": [
    "Mining",
    "Cryptographic Hash",
    "Peer-to-Peer Network",
    "Digital Currency System",
    "Cross-Border Transfer",
    "Blockchain",
    "MiCA (Markets in Crypto-Assets)",
    "Bitcoin Whitepaper",
    "Ethereum Yellowpaper",
    "BIP (Bitcoin Improvement Proposals)",
    "Distributed Ledger Technology (DLT)",
    "VirtualEconomyDomain",
    "Transaction Pool",
    "Crypto Token",
    "VirtualObject",
    "Reed Smith",
    "Central Bank Digital Currency",
    "Programmable Money",
    "Staking",
    "Money",
    "Digital Asset",
    "Decentralized Network",
    "Decentralized Payment",
    "Exchange",
    "Value Storage",
    "Consensus Mechanism",
    "IMF CBDC Notes",
    "Middleware Layer",
    "ISO 24165",
    "Distributed Ledger",
    "Cryptographic Hash Function",
    "DeFi",
    "FATF VASP Guidelines",
    "InfrastructureDomain",
    "Stablecoin",
    "Cryptographic Protocol",
    "Play-to-Earn (P2E)",
    "EIP (Ethereum Improvement Proposals)",
    "Digital Signature",
    "Block Explorer",
    "SEC Guidance",
    "Transaction System",
    "Wallet"
  ],
  "ontology": {
    "term_id": "20134",
    "preferred_term": "Cryptocurrency",
    "definition": "A digital currency secured by cryptographic algorithms, operating on a decentralized blockchain network without central authority, enabling peer-to-peer value transfer.",
    "source_domain": "metaverse",
    "maturity_level": null,
    "authority_score": null
  }
}