{
  "title": "CutMix",
  "content": "- ### OntologyBlock\n  id:: cutmix-ontology\n  collapsed:: true\n\t- ontology:: true\n\t- term-id:: AI-0288\n\t- preferred-term:: CutMix\n\t- source-domain:: ai\n\t- status:: draft\n    - public-access:: true\n\t- definition:: A data augmentation technique that creates training examples by cutting and pasting patches between images, with labels mixed proportionally to the patch areas. CutMix improves model robustness and localisation ability by forcing attention to less discriminative regions.\n\n\n## Academic Context\n\n- Data augmentation fundamentals in machine learning\n  - Addresses the persistent challenge of limited training data availability\n  - Enhances model generalisation and robustness without requiring additional data collection\n  - Particularly valuable when datasets miss critical variations (low-light conditions, partial occlusion, varied viewing angles)[4]\n- CutMix as a sophisticated evolution of earlier techniques\n  - Builds upon simpler augmentation methods like Cutout and Mixup[7]\n  - Introduces label mixing as a form of soft labelling, enabling models to handle ambiguity more effectively[5]\n  - Represents a meaningful departure from single-image transformation approaches\n\n## Current Landscape (2025)\n\n- Core technical mechanism\n  - Randomly selects two images from the training dataset[5]\n  - Extracts a rectangular patch from a donor image using uniform or beta distribution sampling[5]\n  - Pastes the patch onto a target image at a randomly chosen location[5]\n  - Adjusts composite image labels as weighted combinations proportional to patch area relative to total image size[5]\n  - This weighted label approach introduces a layer of complexity that mimics real-world scenarios where object recognition requires handling mixed or ambiguous visual information\n- Demonstrated applications and extensions\n  - Graph-based implementations: G-CutMix extends CutMix principles to graph neural networks for bot detection in social media[1]\n    - Conducts CutMix operations between original and shuffled graphs prior to graph convolution[1]\n    - Strategically merges outputs with user representations from both graph variants[1]\n    - Consistently enhances performance across Graph Convolutional Networks, GraphSAGE, and Graph Attention Networks[1]\n  - Intra-class variants: Improved methods for generating synthetic traces in specialised domains[6]\n  - Noise-mixing approaches: Novel augmentation methods incorporating CutMix concepts into noise generation processes[2]\n- Technical capabilities and limitations\n  - Strengths: Improves model robustness, reduces overfitting, enhances localisation ability by forcing attention to less discriminative regions\n  - Considerations: Effectiveness varies across different neural network architectures; requires careful tuning of patch size and distribution parameters\n  - Domain specificity: Direct application to non-image data (graphs, sequences) requires thoughtful adaptation rather than straightforward transfer\n\n## Research & Literature\n\n- Foundational and recent work\n  - Li, Y., Shi, S., Guo, X., Zhou, C., & Hu, Q. (2025). G-CutMix: A CutMix-based graph data augmentation method for bot detection in social networks. *PLOS ONE*, 20(9). DOI: 10.1371/journal.pone.0331978[1]\n  - Comparative analysis of modern augmentation techniques including CutMix, Cutout, Mixup, and AugMix, with robustness benchmarking on CIFAR-10-C datasets[7]\n  - Novel noise-mixing approaches extending CutMix concepts (arXiv:2509.00378)[2]\n- Ongoing research directions\n  - Adaptation of CutMix to non-Euclidean data structures (graphs, point clouds)\n  - Investigation of optimal patch distribution parameters for domain-specific applications\n  - Integration with emerging architectures and training paradigms\n\n## UK Context\n\n- British computer vision research community engagement\n  - UK institutions actively contributing to data augmentation methodology development\n  - Growing adoption in medical imaging applications, where data scarcity remains particularly acute\n- North England considerations\n  - Manchester and Leeds host significant AI research clusters with active computer vision programmes\n  - Industrial applications in manufacturing quality control and autonomous systems development across the region\n  - Limited region-specific CutMix implementations documented; opportunity for localised case studies in industrial applications\n\n## Future Directions\n\n- Emerging trends\n  - Hybrid augmentation strategies combining CutMix with other techniques for enhanced robustness\n  - Adaptive patch selection mechanisms that learn optimal cutting strategies during training\n  - Extension to multimodal data (combining vision with text or audio)\n- Anticipated challenges\n  - Balancing computational overhead against performance gains\n  - Determining domain-appropriate label mixing strategies for specialised applications\n  - Maintaining interpretability when models train on heavily augmented datasets\n- Research priorities\n  - Systematic evaluation across diverse architectures and domains\n  - Development of principled guidelines for hyperparameter selection\n  - Investigation of CutMix effectiveness in few-shot and zero-shot learning scenarios\n\n\n## Metadata\n\n- **Last Updated**: 2025-11-11\n- **Review Status**: Comprehensive editorial review\n- **Verification**: Academic sources verified\n- **Regional Context**: UK/North England where applicable",
  "properties": {
    "id": "cutmix-ontology",
    "collapsed": "true",
    "- ontology": "true",
    "- term-id": "AI-0288",
    "- preferred-term": "CutMix",
    "- source-domain": "ai",
    "- status": "draft",
    "- public-access": "true",
    "- definition": "A data augmentation technique that creates training examples by cutting and pasting patches between images, with labels mixed proportionally to the patch areas. CutMix improves model robustness and localisation ability by forcing attention to less discriminative regions."
  },
  "backlinks": [],
  "wiki_links": [],
  "ontology": {
    "term_id": "AI-0288",
    "preferred_term": "CutMix",
    "definition": "A data augmentation technique that creates training examples by cutting and pasting patches between images, with labels mixed proportionally to the patch areas. CutMix improves model robustness and localisation ability by forcing attention to less discriminative regions.",
    "source_domain": "ai",
    "maturity_level": null,
    "authority_score": null
  }
}