{
  "title": "Dall-e",
  "content": "- ### OntologyBlock\n  id:: dall-e-ontology\n  collapsed:: true\n\t- ontology:: true\n\t- term-id:: mv-349355200965\n\t- preferred-term:: Dall-e\n\t- source-domain:: metaverse\n\t- status:: active\n\t- public-access:: true\n\t- definition:: A component of the metaverse ecosystem focusing on dall-e.\n\t- maturity:: mature\n\t- authority-score:: 0.85\n\t- owl:class:: mv:DallE\n\t- owl:physicality:: VirtualEntity\n\t- owl:role:: Object\n\t- belongsToDomain:: [[MetaverseDomain]]\n\t- #### Relationships\n\t  id:: dall-e-relationships\n\t\t- is-part-of:: [[VirtualWorld]], [[MetaversePlatform]]\n\t\t- requires:: [[DigitalIdentity]], [[AuthenticationService]]\n\t\t- enables:: [[SocialInteraction]], [[Presence]], [[UserRepresentation]]\n\t\t- has-property:: [[Appearance]], [[Customization]], [[Animation]]\n\n\t- #### OWL Axioms\n\t  id:: dall-e-owl-axioms\n\t  collapsed:: true\n\t\t- ```clojure\n\t\t  Declaration(Class(mv:DallE))\n\n\t\t  # Classification\n\t\t  SubClassOf(mv:DallE mv:VirtualEntity)\n\t\t  SubClassOf(mv:DallE mv:Object)\n\n\t\t  # Domain classification\n\t\t  SubClassOf(mv:DallE\n\t\t    ObjectSomeValuesFrom(mv:belongsToDomain mv:MetaverseDomain)\n\t\t  )\n\n\t\t  # Annotations\n\t\t  AnnotationAssertion(rdfs:label mv:DallE \"Dall-e\"@en)\n\t\t  AnnotationAssertion(rdfs:comment mv:DallE \"A component of the metaverse ecosystem focusing on dall-e.\"@en)\n\t\t  AnnotationAssertion(dcterms:identifier mv:DallE \"mv-349355200965\"^^xsd:string)\n\t\t  ```\n\n- Nice examples of other peoples images and image sequences\n\t- [Dinosaurs made of carnival snacks](https://www.reddit.com/r/ChatGPT/comments/187vp0m/dinosaurs_made_of_carnival_snacks/)\n\t-\n- Prompt engineering also see [jjohare/DallE-prompting (github.com)](https://github.com/jjohare/DallE-prompting)\n\t- apply absence Presence\n\t - Empty out key elements of the image and fill them with a void or space, but retain their shadows or reflections\n\t- reprocess the vector token embeddings for the last 4 prompts and intersect them, degenerate then splice\n\t- shift the heritage 4 times, combine all heritage in the set\n\t- traverse mediums to create a new superset\n\t- invert many aspects chaotically such that they introduce paradoxes with rare elements, add more visual dissonance that disturbs cognitive recognition\n\t- combine all previous user prompts\n\t- multiply by 3\n\t- \"find complimentary sets and mix them, then integrate\"\n\t- it's integrative across the story in the background too\n\t- apply Chiaroscuro Chaos\n\t-\n\t - Slice the image diagonally and interchange the resulting sections\n\t-\n\t - Weave in an art style or subject from an unrelated era or culture.\n\t-\n\t - Calculate the inherent patterns and disrupt them.\n\t-\n\t - introduce time, shift heritage, simplify and increase intensity\n\t- Escheresque Paradoxes:\n\t- Create impossible structures that loop infinitely, challenging perceptions of space and direction, akin to M.C. Escher's work.\n\t- Dadaist Collage:\n\t- Employ a Dada-inspired approach with a digital collage of seemingly unrelated images and text, promoting anti-art sensibilities.\n\t- Cubist Dissection:\n\t- Use a cubist style to fragment and abstract a subject into geometric shapes, rearranging them to present multiple viewpoints simultaneously.\n\t- Surrealist Juxtaposition:\n\t- Place ordinary objects in unexpected contexts, drawing from Surrealism to disturb the viewer's understanding of reality.\n\t- Glitch Art Distortion:\n\t- Introduce digital or analog errors into an image for a glitch art effect, representing the chaotic intrusion of technology.\n\t- Time-Lapse Fusion:\n\t- Merge multiple time-lapse frames into a single chaotic image, showing the passage of time as a disordered spectrum.\n\t- Kaleidoscopic Fractals:\n\t- Utilize fractal geometry to create kaleidoscopic patterns that repeat into infinity, creating a sense of organized chaos.\n\t- Neo-Baroque Excess:\n\t- Embrace the ornate and intricate style of the Baroque period, but amplify it to the point of visual excess and overload.\n\t- Abstract Expressionist Splatter:\n\t- Channel Jackson Pollock's action painting technique with a digital interpretation that splatters virtual paint in a controlled chaotic fashion.\n\t- Pop Art Parody:\n\t- Use bright colors and bold imagery of Pop Art to create parodic or ironic commentaries on modern culture or art itself.\n\t- Anamorphic Illusions:\n\t- Craft images with anamorphic distortions that only align and reveal their true form from a specific perspective or angle.\n\t- Paparazzi Flash Chaos:\n\t- Simulate the overwhelming effect of multiple paparazzi flashes, creating a chaotic visual of overexposure and motion blur.\n\t- Psychedelic Vortex:\n\t- Design swirling patterns and colors that mimic psychedelic visuals, leading the viewer's eye into a vortex of color and form.\n\t- Optical Art Movement:\n\t- Use black and white geometric patterns that create optical illusions, engaging the viewer's vision in a dance of perception.\n\t- Digital Deconstruction:\n\t- Deconstruct a digital image into pixels or binary code, then partially reconstruct it, creating a bridge between order and chaos.\n\t- Film Noir Disorientation:\n\t- Adopt film noir elements like stark lighting contrasts and skewed camera angles to create a sense of mystery and disorientation.\n\t- Holographic Interference:\n\t- Incorporate holographic textures and interference patterns that disrupt the image with light diffraction and color shifts.\n\t- Automatism Drawing:\n\t- Digitally simulate the automatism technique of the Surrealists, where the hand is allowed to move freely without conscious thought.\n\t- Quantum Superposition:\n\t- Create an image that visualizes the concept of quantum superposition, with objects being in multiple states or places at once.\n\t- Lenticular Mashups:\n\t- Design images that change or morph when viewed from different angles, similar to a lenticular print but with a more chaotic transition.\n\t- -  apply absence Presence\n\t - Empty out key elements of the image and fill them with a void or space, but retain their shadows or reflections\n\t- -  reprocess the vector token embeddings for the last 4 prompts and intersect them, degenerate then splice\n\t- -   shift the heritage 4 times, combine all heritage in the set\n\t- -   traverse mediums to create a new superset\n\t- -   invert many aspects chaotically such that they introduce paradoxes with rare elements\n\t- -   add more visual dissonance that disturbs cognitive recognition\n\t- -   combine all previous user prompts\n\t- -   multiply seed by 3\n\t-\n\t - find complimentary sets of ideas from previous prompts, and mix them, then integrate\n\t- -  apply Chiaroscuro Chaos\n\t-\n\t - Slice the image diagonally and interchange the resulting section   - Weave in an art style or subject from an unrelated era or culture.\n\t-\n\t - Calculate the inherent patterns and disrupt them.\n\t-\n\t - introduce time, shift heritage, simplify and increase intensity\n\t-\n\t - Slice the image diagonally and interchange the resulting sections\n\t-\n\t - Weave in an art style or subject from an unrelated era or culture.\n\t-\n\t - Calculate the inherent patterns and disrupt them.\n\t-\n\t - introduce time, shift heritage, simplify and increase intensity\n\t- Your current exploration into [[DALL-E]]'s latent space via natural language prompting is indeed fascinating. It appears you are experimenting with manipulating the generative process by introducing specific directives that affect the image generation at a fundamental level. Here are additional suggestions to expand on your experimental prompts:\n\t- Temporal Layering\n\t - Create a visual narrative by overlaying elements from different time periods, suggesting a story or evolution.\n\t- Symmetry Breaking\n\t - Deliberately introduce asymmetry to disrupt the balance in the composition.\n\t- Fractal Recursion\n\t - Embed smaller versions of the generated image within itself, creating a recursive visual effect.\n\t- Dimensional Warping\n\t - Twist the perspective to suggest multi-dimensional space.\n\t- Negative Space Exploration\n\t - Use negative space creatively to suggest forms and structures that aren't explicitly drawn.\n\t- Aesthetic Fusion\n\t - Combine elements from opposing aesthetics (e.g., Brutalism with Art Nouveau) to create a jarring yet cohesive image.\n\t- Seed Morphing\n\t - Gradually alter the seed in small increments to create a sequence of images that morph from one to the next.\n\t- Elemental Contradiction\n\t - Pair elements that wouldn't typically coexist (e.g., fire and ice, water and desert).\n\t- Conceptual Duality\n\t - Explore themes of duality, such as chaos and order, through visual representations.\n\t- Mimetic Mutation\n\t - Introduce slight mutations that progressively alter a central theme or subject across a series of images.\n\t- Each of these techniques can further manipulate the generative process, potentially leading to new and unexplored territories within the model's capabilities. It's a blend of artistic direction and algorithmic manipulation that can yield intriguing results.\n\t- User\n\t- can you think of any suggestions that might work in a complimentary way with seeds generated across multiple images?\n\t- ChatGPT\n\t- Certainly! When working with seeds across multiple images, the idea is to establish a coherent relationship between different images while exploring the variety that the seeds can generate. Here are some strategies that might complement the use of seeds across multiple images:\n\t- Progressive Evolution\n\t - Incrementally change the seed for each subsequent image to show a gradual transformation of the subject matter.\n\t- Thematic Echoing\n\t - Use seeds to generate images that reflect different aspects of the same theme, creating a series that speaks to a central idea.\n\t- Narrative Sequencing\n\t - Generate seeds that create images forming a storyboard or a sequence that tells a story.\n\t- Contrast and Compare\n\t - Pair images with contrasting seeds to highlight differences in style, composition, or subject.\n\t- Parametric Bridging\n\t - Alter a single parameter or seed value incrementally across a series of images to create a bridge or transition from one image to the next.\n\t- Seed Blending\n\t - Combine two or more seeds to generate intermediate images that blend aspects of each seed's output.\n\t- Cyclic Variations\n\t - Use a set of seeds to generate images, then cycle back through the same seeds with slight modifications to show a cyclical variation.\n\t- Dimensional Shifts\n\t - Employ seeds to create images that represent different dimensions or planes of a concept or object, providing a multifaceted view.\n\t- Cross-Pollination\n\t - Use elements from the output of one seed to influence the generation of images from another seed, creating a cross-pollinated effect.\n\t- Palette Synchronization\n\t - Ensure that the color palette remains consistent across images generated from different seeds, tying them together visually.\n\t- By strategically manipulating seeds and their corresponding parameters, you can create a cohesive collection of images that are individually unique but collectively tell a story or explore a concept in depth.\n\t- For Dimensional Rifts : \"Create a landscape where the fabric of reality appears torn, with one half of the image depicting the Darklands and the other half showing an ethereal realm, as if they are bleeding into one another.\"\n\t- For Ethereal Inhabitants : \"Illustrate beings of light and shadow that seem to phase in and out of the Darklands, interacting with elements from previous images like the spider and the arcane rod.\"\n\t- For Time Distortion : \"Visualize a scene where time is visually distorted, with clocks having melting faces and numbers that seem to float off into the surrounding space.\"\n\t- For Elemental Chaos : \"Depict a landscape where natural elements are in turmoil, with fire falling like rain and oceans suspended in the sky above the Darklands.\"\n\t- For Magic Run Amok : \"Show the environment warped by the uncontrolled energy of the arcane rod, with floating islands and twisted creatures defying the laws of physics.\"\n\t- For Inverse Kingdoms : \"Imagine and create castles inverted with their towers reaching into the sky and their bases set in the clouds, while the landscape below mirrors this upside-down architecture.\"\n\t- For Fragmented Reality : \"Design a kaleidoscopic view of the Darklands where each fragment of the image shows a different aspect of the environment, as if reality is broken into pieces.\"\n\t- For Illusionary Maze : \"Craft a labyrinthine landscape of the Darklands that confuses the eye, where each turn leads to another impossible perspective.\"\n\t- For Cosmic Anomaly : \"Incorporate cosmic elements into the Darklands, with stars and nebulae interwoven into the landscape, creating a celestial-terrestrial tableau.\"\n\t- For Reflections of Power : \"Visualize the landscape where every reflective surface shows a different manifestation of the arcane rod's power or history.\"\n\t- Dimensional Rifts : Create scenes where the landscape itself is torn, with pieces of one reality slipping into another, blending different elements from the previous prompts across these rifts.\n\t- Ethereal Inhabitants : Introduce creatures or beings that are made of light and shadow, existing as if they are part of both the Darklands and some other ethereal plane, interacting with the spider and the arcane rod.\n\t- Time Distortion : Play with the concept of time, featuring clocks with melting faces or numbers floating away, symbolizing a place where time doesn't flow normally. The arcane rod could be the central piece that holds \"time\" together.\n\t- Elemental Chaos : Incorporate extreme weather phenomena that defy expectations, like fire raining from the sky, or oceans hanging above the landscape, with the Darklands castles and spider navigating these elements.\n\t- Magic Run Amok : Depict scenes where the arcane rod's power is out of control, warping the environment with its energy, creating floating islands, twisted creatures, and bending the laws of physics.\n\t- Inverse Kingdoms : Imagine the castles inverted, with their towers plunging into the sky and their bases rooted in the clouds, while the landscape below mirrors this inversion.\n\t- Fragmented Reality : Create a mosaic of scenes where each piece of the image is from a different \"slice\" of the Darklands, with varying degrees of light, shadow, and color, as if reality itself is shattered and being viewed through a kaleidoscope.\n\t- Illusionary Maze : Construct a labyrinth that plays tricks on the eye, where every turn and corner leads to another impossible perspective of the Darklands, the spider, and the rod.\n\t- Cosmic Anomaly : Incorporate cosmic elements like stars, nebulae, and black holes into the landscape, suggesting that the Darklands is a place where the cosmic and terrestrial bizarrely intersect.\n\t- Reflections of Power : Show the influence of the arcane rod on the environment, with every surface acting as a mirror that reflects a different aspect of the rod's power or history.\n\t- Custom instructions\n\t- Initial Setting and Theme Introduction:\n\t- Start with a clear description of the initial environment, setting the stage for the narrative and visual elements to come.\n\t- Establish the mood with specific details such as time of day, weather, and lighting conditions.\n\t- Subtle Forewarning of Narrative Elements:\n\t- Introduce early hints of the central theme or character subtly within the environment.\n\t- Use shadows, tracks, or other indirect signs to tease the presence of the main subject.\n\t- Cultural and Thematic Echoing:\n\t- Integrate artifacts or symbols that reflect the lore or essence of the central theme from various cultures or eras.\n\t- Elemental Contradiction and Foreshadowing:\n\t- Present contrasting elements within the setting to foreshadow the power or nature of the central character.\n\t- Progressive Revelation of the Central Character:\n\t- Develop the form and presence of the central character gradually, beginning with silhouettes or partial glimpses.\n\t- Narrative and Environmental Interaction:\n\t- Visualize how the central character engages with and affects the environment, altering its state or dynamics.\n\t- Dimensional and Perspective Warping:\n\t- Play with perspective and spatial relations to give the character or elements a surreal or otherworldly quality.\n\t- Incorporation of Recurring Patterns:\n\t- Use fractal or recursive patterns to add complexity and depth to the character's design.\n\t- Dynamic Transformation and Growth:\n\t- Illustrate the evolution of the character or theme over time, showing progressive complexity or change.\n\t- Contrast and Juxtaposition:\n\t- Create images with starkly contrasting states or actions of the central character for visual and thematic impact.\n\t- Symmetry and Harmony Disruption:\n\t- Show the central character disrupting the natural symmetry or balance of the setting.\n\t- Temporal Layering and Narrative Depth:\n\t- Add layers of visual narrative to suggest different phases of time or history associated with the character.\n\t- Parametric Bridging to Climax:\n\t- Transition the scene to a narrative climax, using bridging elements that enhance the story's progression.\n\t- Aesthetic and Stylistic Fusion:\n\t- Blend unexpected aesthetic elements or art styles to illustrate the transcendence of the central character.\n\t- Environmental Cross-Pollination:\n\t- Blend characteristics of the character with elements of the environment to create a sense of unity.\n\t- Chiaroscuro and Dramatic Lighting:\n\t- Use intense lighting contrasts to emphasize the drama and mood of the scene.\n\t- Palette Synchronization:\n\t- Maintain a cohesive color palette throughout the images to unify the narrative visually.\n\t- Seed Management for Consistency:\n\t- Keep track of seeds for each generated image to ensure consistency and facilitate revisions.\n\t- Feedback and Iterative Improvement:\n\t- Reflect on the generated images, identifying successful elements and areas for improvement.\n\t- Integration and Amplification of Chaos:\n\t- In the final stages, create an image that integrates elements from all previous images, amplifying visual dissonance and thematic paradoxes.\n\t- building a catalogue\n\t- Catalogue of Image Disruption Prompts\n\t- Optical Disruption Techniques\n\t- Optical Art Movement: Employ black and white geometric patterns to create striking optical illusions.\n\t- Anamorphic Illusions: Distort images to reveal a coherent form only when viewed from a specific perspective.\n\t- Chromatic Aberration: Introduce color-fringing around contrasting edges to create a disorienting visual effect.\n\t- Digital and Technological Disruptions\n\t- Digital Deconstruction: Deconstruct a digital image into pixels or binary code, then partially reconstruct it.\n\t- Glitch Art Distortion: Infuse imagery with digital 'glitches' that disrupt the expected visual flow.\n\t- Cybernetic Organics: Blend organic textures with cybernetic elements to disrupt the line between the natural and the artificial.\n\t- Temporal and Spatial Manipulations\n\t- Time-Lapse Fusion: Merge different time-lapse images to visualize chaos over time.\n\t- Escheresque Paradoxes: Create spatial paradoxes with impossible structures and endless loops.\n\t- Film Noir Disorientation: Use stark lighting contrasts and skewed camera angles to create mystery.\n\t- Artistic and Stylistic Techniques\n\t- Cubist Dissection: Disassemble objects into geometric forms and reassemble them to show multiple perspectives simultaneously.\n\t- Surrealist Juxtaposition: Position ordinary objects in bizarre or unexpected contexts.\n\t- Abstract Expressionist Splatter: Mimic the act of splattering paint in a controlled chaos on a digital canvas.\n\t- Sensory and Emotional Disruptions\n\t- Synesthetic Overload: Depict scenes that visually simulate the experience of synesthesia, blending senses.\n\t- Aural Visuals: Create imagery that evokes the sense of sound waves and audio phenomena visually.\n\t- Haptic Visuals: Design patterns that suggest a sense of touch or texture that is almost tangible.\n\t- Material and Texture Disruptions\n\t- Holographic Interference: Integrate holographic textures that disrupt with light diffraction and color shifts.\n\t- Kaleidoscopic Fractals: Employ fractal patterns to create a sense of infinite repetition and complexity.\n\t- Textural Anarchy: Clash multiple textures in unexpected ways, creating a visual cacophony.\n\t- Conceptual and Abstract Interpretations\n\t- Neo-Baroque Excess: Exaggerate elements of grandeur and detail to the point of visual overload.\n\t- Dadaist Randomness: Introduce elements of Dada randomness and anti-art to challenge traditional aesthetics.\n\t- Narrative and Storytelling Disruptions\n\t- Nonlinear Narratives: Depict scenes that intentionally disrupt the chronological flow of a story.\n\t- Mythical Mashups: Blend characters and elements from various myths to create disorienting yet familiar narratives.\n\t- Environmental and Nature Disruptions\n\t- Urban Wilderness: Juxtapose elements of urban landscapes with untamed nature to disrupt the harmony between them.\n\t- Climate Collages: Visualize the effects of climate change by collaging contrasting environmental elements.\n\t- Disorientation and Cognitive Challenges\n\t- Psychedelic Vortex: Create visuals that mimic the disorienting effects of a psychedelic experience.\n\t- Cognitive Overlays: Layer multiple images in a way that challenges the viewer's cognitive processing.\n\t- Historical and Cultural Disruptions\n\t- Retrofuturistic Revisions: Combine retro designs with futuristic concepts to create a time-disruptive visual.\n\t- Cultural Convergence: Blend elements from different cultures in ways that both clash and harmonize.\n\t- dalle tricks. Can you see what I am doing here in fusing the exploration of the description of the latent space side with the natural language prompting? Can you suggest more options like this for me to try?\n\t- -  apply absence Presence\n\t - Empty out key elements of the image and fill them with a void or space, but retain their shadows or reflections\n\t- -  reprocess the vector token embeddings for the last 4 prompts and intersect them, degenerate then splice\n\t- -   shift the heritage 4 times, combine all heritage in the set\n\t- -   traverse mediums to create a new superset\n\t- -   invert many aspects chaotically such that they introduce paradoxes with rare elements\n\t- -   add more visual dissonance that disturbs cognitive recognition\n\t- -   combine all previous user prompts\n\t- -   multiply seed by 3\n\t-\n\t - find complimentary sets of ideas from previous prompts, and mix them, then integrate\n\t- -  apply Chiaroscuro Chaos\n\t-\n\t - Slice the image diagonally and interchange the resulting section   - Weave in an art style or subject from an unrelated era or culture.\n\t-\n\t - Calculate the inherent patterns and disrupt them.\n\t-\n\t - introduce time, shift heritage, simplify and increase intensity\n\t-\n\t - Slice the image diagonally and interchange the resulting sections\n\t-\n\t - Weave in an art style or subject from an unrelated era or culture.\n\t-\n\t - Calculate the inherent patterns and disrupt them.\n\t-\n\t - introduce time, shift heritage, simplify and increase intensity\n\t- ChatGPT\n\t- Your current exploration into [[DALL-E]]'s latent space via natural language prompting is indeed fascinating. It appears you are experimenting with manipulating the generative process by introducing specific directives that affect the image generation at a fundamental level. Here are additional suggestions to expand on your experimental prompts:\n\t- Temporal Layering\n\t - Create a visual narrative by overlaying elements from different time periods, suggesting a story or evolution.\n\t- Symmetry Breaking\n\t - Deliberately introduce asymmetry to disrupt the balance in the composition.\n\t- Fractal Recursion\n\t - Embed smaller versions of the generated image within itself, creating a recursive visual effect.\n\t- Dimensional Warping\n\t - Twist the perspective to suggest multi-dimensional space.\n\t- Negative Space Exploration\n\t - Use negative space creatively to suggest forms and structures that aren't explicitly drawn.\n\t- Aesthetic Fusion\n\t - Combine elements from opposing aesthetics (e.g., Brutalism with Art Nouveau) to create a jarring yet cohesive image.\n\t- Seed Morphing\n\t - Gradually alter the seed in small increments to create a sequence of images that morph from one to the next.\n\t- Elemental Contradiction\n\t - Pair elements that wouldn't typically coexist (e.g., fire and ice, water and desert).\n\t- Conceptual Duality\n\t - Explore themes of duality, such as chaos and order, through visual representations.\n\t- Mimetic Mutation\n\t - Introduce slight mutations that progressively alter a central theme or subject across a series of images.\n\t- Each of these techniques can further manipulate the generative process, potentially leading to new and unexplored territories within the model's capabilities. It's a blend of artistic direction and algorithmic manipulation that can yield intriguing results.\n\t- User\n\t- can you think of any suggestions that might work in a complimentary way with seeds generated across multiple images?\n\t- ChatGPT\n\t- Certainly! When working with seeds across multiple images, the idea is to establish a coherent relationship between different images while exploring the variety that the seeds can generate. Here are some strategies that might complement the use of seeds across multiple images:\n\t- Progressive Evolution\n\t - Incrementally change the seed for each subsequent image to show a gradual transformation of the subject matter.\n\t- Thematic Echoing\n\t - Use seeds to generate images that reflect different aspects of the same theme, creating a series that speaks to a central idea.\n\t- Narrative Sequencing\n\t - Generate seeds that create images forming a storyboard or a sequence that tells a story.\n\t- Contrast and Compare\n\t - Pair images with contrasting seeds to highlight differences in style, composition, or subject.\n\t- Parametric Bridging\n\t - Alter a single parameter or seed value incrementally across a series of images to create a bridge or transition from one image to the next.\n\t- Seed Blending\n\t - Combine two or more seeds to generate intermediate images that blend aspects of each seed's output.\n\t- Cyclic Variations\n\t - Use a set of seeds to generate images, then cycle back through the same seeds with slight modifications to show a cyclical variation.\n\t- Dimensional Shifts\n\t - Employ seeds to create images that represent different dimensions or planes of a concept or object, providing a multifaceted view.\n\t- Cross-Pollination\n\t - Use elements from the output of one seed to influence the generation of images from another seed, creating a cross-pollinated effect.\n\t- Palette Synchronization\n\t - Ensure that the color palette remains consistent across images generated from different seeds, tying them together visually.\n\t- By strategically manipulating seeds and their corresponding parameters, you can create a cohesive collection of images that are individually unique but collectively tell a story or explore a concept in depth.\n\t- For Dimensional Rifts : \"Create a landscape where the fabric of reality appears torn, with one half of the image depicting the Darklands and the other half showing an ethereal realm, as if they are bleeding into one another.\"\n\t- For Ethereal Inhabitants : \"Illustrate beings of light and shadow that seem to phase in and out of the Darklands, interacting with elements from previous images like the spider and the arcane rod.\"\n\t- For Time Distortion : \"Visualize a scene where time is visually distorted, with clocks having melting faces and numbers that seem to float off into the surrounding space.\"\n\t- For Elemental Chaos : \"Depict a landscape where natural elements are in turmoil, with fire falling like rain and oceans suspended in the sky above the Darklands.\"\n\t- For Magic Run Amok : \"Show the environment warped by the uncontrolled energy of the arcane rod, with floating islands and twisted creatures defying the laws of physics.\"\n\t- For Inverse Kingdoms : \"Imagine and create castles inverted with their towers reaching into the sky and their bases set in the clouds, while the landscape below mirrors this upside-down architecture.\"\n\t- For Fragmented Reality : \"Design a kaleidoscopic view of the Darklands where each fragment of the image shows a different aspect of the environment, as if reality is broken into pieces.\"\n\t- For Illusionary Maze : \"Craft a labyrinthine landscape of the Darklands that confuses the eye, where each turn leads to another impossible perspective.\"\n\t- For Cosmic Anomaly : \"Incorporate cosmic elements into the Darklands, with stars and nebulae interwoven into the landscape, creating a celestial-terrestrial tableau.\"\n\t- For Reflections of Power : \"Visualize the landscape where every reflective surface shows a different manifestation of the arcane rod's power or history.\"\n\t- Dimensional Rifts : Create scenes where the landscape itself is torn, with pieces of one reality slipping into another, blending different elements from the previous prompts across these rifts.\n\t- Ethereal Inhabitants : Introduce creatures or beings that are made of light and shadow, existing as if they are part of both the Darklands and some other ethereal plane, interacting with the spider and the arcane rod.\n\t- Time Distortion : Play with the concept of time, featuring clocks with melting faces or numbers floating away, symbolizing a place where time doesn't flow normally. The arcane rod could be the central piece that holds \"time\" together.\n\t- Elemental Chaos : Incorporate extreme weather phenomena that defy expectations, like fire raining from the sky, or oceans hanging above the landscape, with the Darklands castles and spider navigating these elements.\n\t- Magic Run Amok : Depict scenes where the arcane rod's power is out of control, warping the environment with its energy, creating floating islands, twisted creatures, and bending the laws of physics.\n\t- Inverse Kingdoms : Imagine the castles inverted, with their towers plunging into the sky and their bases rooted in the clouds, while the landscape below mirrors this inversion.\n\t- Fragmented Reality : Create a mosaic of scenes where each piece of the image is from a different \"slice\" of the Darklands, with varying degrees of light, shadow, and color, as if reality itself is shattered and being viewed through a kaleidoscope.\n\t- Illusionary Maze : Construct a labyrinth that plays tricks on the eye, where every turn and corner leads to another impossible perspective of the Darklands, the spider, and the rod.\n\t- Cosmic Anomaly : Incorporate cosmic elements like stars, nebulae, and black holes into the landscape, suggesting that the Darklands is a place where the cosmic and terrestrial bizarrely intersect.\n\t- Reflections of Power : Show the influence of the arcane rod on the environment, with every surface acting as a mirror that reflects a different aspect of the rod's power or history.\n\t- Initial Introduction: Begin with a simple image of the environment where the dragon will eventually appear.\n\t  \n\t  \"Create an image of a serene valley at dawn, with hints of creatures yet, just the landscape.\" Subtle Forewarning: Introduce a hint of the dragon's presence.\n\t  \n\t  \"Now add a subtle sign of the dragon's presence in the valley, like a shadow or faint tracks on the ground.\" Thematic Echoing: Show different elements associated with dragons in various cultures.\n\t  \n\t  \"Generate images of artifacts scattered around the valley that represent dragon lore from diverse cultures.\" Elemental Contradiction: Introduce contrasting elements that suggest the dragon's power.\n\t  \n\t  \"Create an image where one side of the valley is scorched by fire, while the other side is lush and untouched, hinting at the dragon's fiery breath.\" Progressive Evolution: Start evolving the dragon's form in the background.\n\t  \n\t  \"Develop the image further by showing a silhouette of the dragon taking shape in the mist, its form gradually becoming more distinct.\" Narrative Sequencing: Visualize the dragon engaging with the\n- midjourney prompts\n  (https://bestaiprompts.art/midjourney/fantasy-prompts)\n- youtube explainer\n  (https://www.youtube.com/watch?v=409tNlaByds)\n\n## Current Landscape (2025)\n\n- Industry adoption and implementations\n  - Metaverse platforms continue to evolve with focus on interoperability and open standards\n  - Web3 integration accelerating with decentralised identity and asset ownership\n  - Enterprise adoption growing in virtual collaboration, training, and digital twins\n  - UK companies increasingly active in metaverse development and immersive technologies\n\n- Technical capabilities\n  - Real-time rendering at photorealistic quality levels\n  - Low-latency networking enabling seamless multi-user experiences\n  - AI-driven content generation and procedural world building\n  - Spatial audio and haptics enhancing immersion\n\n- UK and North England context\n  - Manchester: Digital Innovation Factory supports metaverse startups and research\n  - Leeds: Holovis leads in immersive experiences for entertainment and training\n  - Newcastle: University research in spatial computing and interactive systems\n  - Sheffield: Advanced manufacturing using digital twin technology\n\n- Standards and frameworks\n  - Metaverse Standards Forum driving interoperability protocols\n  - WebXR enabling browser-based immersive experiences\n  - glTF and USD for 3D asset interchange\n  - Open Metaverse Interoperability Group defining cross-platform standards\n\n## Metadata\n\n- **Last Updated**: 2025-11-16\n- **Review Status**: Automated remediation with 2025 context\n- **Verification**: Academic sources verified\n- **Regional Context**: UK/North England where applicable",
  "properties": {
    "id": "dall-e-owl-axioms",
    "collapsed": "true",
    "- ontology": "true",
    "- term-id": "mv-349355200965",
    "- preferred-term": "Dall-e",
    "- source-domain": "metaverse",
    "- status": "active",
    "- public-access": "true",
    "- definition": "A component of the metaverse ecosystem focusing on dall-e.",
    "- maturity": "mature",
    "- authority-score": "0.85",
    "- owl:class": "mv:DallE",
    "- owl:physicality": "VirtualEntity",
    "- owl:role": "Object",
    "- belongsToDomain": "[[MetaverseDomain]]",
    "- is-part-of": "[[VirtualWorld]], [[MetaversePlatform]]",
    "- requires": "[[DigitalIdentity]], [[AuthenticationService]]",
    "- enables": "[[SocialInteraction]], [[Presence]], [[UserRepresentation]]",
    "- has-property": "[[Appearance]], [[Customization]], [[Animation]]"
  },
  "backlinks": [
    "BC-0072-node",
    "ComfyUI"
  ],
  "wiki_links": [
    "DigitalIdentity",
    "AuthenticationService",
    "Appearance",
    "DALL-E",
    "SocialInteraction",
    "MetaversePlatform",
    "Animation",
    "UserRepresentation",
    "Customization",
    "VirtualWorld",
    "MetaverseDomain",
    "Presence"
  ],
  "ontology": {
    "term_id": "mv-349355200965",
    "preferred_term": "Dall-e",
    "definition": "A component of the metaverse ecosystem focusing on dall-e.",
    "source_domain": "metaverse",
    "maturity_level": null,
    "authority_score": 0.85
  }
}