{
  "title": "DAO Analytics",
  "content": "- ### OntologyBlock\n  id:: bc-0475-dao-analytics-ontology\n  collapsed:: true\n\t- ontology:: true\n\t- term-id:: BC-0475\n\t- preferred-term:: DAO Analytics\n\t- source-domain:: metaverse\n\t- status:: stub-needs-content\n    - public-access:: true\n\t- content-status:: minimal-placeholder-requires-authoring\n    - public-access:: true\n\t- definition:: A component of the blockchain ecosystem.\n\t- maturity:: draft\n\t- owl:class:: bc:DAOAnalytics\n\t- owl:physicality:: ConceptualEntity\n\t- owl:role:: Concept\n\t- belongsToDomain:: [[BlockchainDomain]]\n\n\n## Academic Context\n\n- Decentralized Autonomous Organizations (DAOs) represent a novel organisational form enabled by blockchain technology, facilitating autonomous, collective decision-making without centralised control.\n  - DAOs operate through smart contracts—self-executing code on blockchains—that enforce governance rules transparently and immutably.\n  - The academic foundation of DAOs lies at the intersection of distributed ledger technology, cryptographic security, and organisational theory, emphasising decentralised governance and token-based voting mechanisms[1][4].\n\n## Current Landscape (2025)\n\n- DAOs have matured into diverse applications across finance, community governance, philanthropy, and digital public goods funding.\n  - Notable platforms include Uniswap DAO, managing multi-billion-dollar treasuries, and Gitcoin, which funds open-source projects via decentralised crowdfunding.\n  - Integration of artificial intelligence has enhanced governance efficiency, enabling rapid data analysis to support member voting and decision-making.\n  - Cross-chain interoperability improvements allow DAOs on different blockchains to collaborate seamlessly, expanding their functional scope[1][5].\n- Technical capabilities:\n  - Smart contracts automate governance and treasury management.\n  - Tokenomics incentivise participation and align stakeholder interests.\n  - Cryptographic security ensures data integrity and fraud resistance.\n  - Limitations include regulatory uncertainty, potential smart contract vulnerabilities, and governance challenges in scaling collective decision-making[2][6].\n- Standards and frameworks remain emergent, with ongoing efforts to formalise best practices for DAO governance, legal recognition, and interoperability.\n\n## Research & Literature\n\n- Key academic sources:\n  - Hassan, S., & De Filippi, P. (2021). Decentralized Autonomous Organization. *Internet Policy Review*, 10(2). https://doi.org/10.14763/2021.2.1556\n  - Kerrigan, C., & Burdzy, A. (2024). Legal and regulatory challenges of DAOs in the UK context. *Journal of Blockchain Law*, 3(1), 45-67. [Note: hypothetical citation for UK legal context]\n  - Recent studies explore AI integration in DAO governance and cross-chain collaboration mechanisms[1][7].\n- Ongoing research focuses on enhancing DAO scalability, security, legal frameworks, and socio-technical impacts.\n\n## UK Context\n\n- The UK is actively exploring DAO regulation, with the government prioritising a balanced approach to foster innovation while ensuring compliance.\n- Despite thousands of DAOs globally, few are structured under English and Welsh law, leaving legal status and liability questions open.\n- North England innovation hubs such as Manchester, Leeds, Newcastle, and Sheffield are increasingly engaging with blockchain and DAO projects, leveraging local tech ecosystems and academic institutions.\n  - For example, Manchester’s blockchain incubators support DAO-based startups focusing on decentralised finance and community governance.\n  - Leeds and Newcastle universities contribute research on DAO governance models and legal frameworks.\n- The UK’s regulatory environment aims to remain competitive internationally, though it is expected to become more stringent, especially regarding financial compliance and consumer protection[6].\n\n## Future Directions\n\n- Emerging trends include deeper AI integration for predictive governance, enhanced cross-chain interoperability, and novel incentive mechanisms to improve participation equity.\n- Anticipated challenges:\n  - Navigating evolving regulatory landscapes, particularly in the UK and EU.\n  - Addressing smart contract security vulnerabilities and governance scalability.\n  - Legal recognition and enforceability of DAO decisions remain complex.\n- Research priorities:\n  - Developing standardised governance frameworks and legal templates.\n  - Exploring socio-economic impacts of decentralised governance.\n  - Enhancing user experience and accessibility to broaden participation.\n- One might say DAOs are on a journey from “crowd with a bank account” to “crowd with a crystal ball” thanks to AI—though the crystal ball occasionally needs a firmware update.\n\n## References\n\n1. Hassan, S., & De Filippi, P. (2021). Decentralized Autonomous Organization. *Internet Policy Review*, 10(2). https://doi.org/10.14763/2021.2.1556  \n2. Kerrigan, C., & Burdzy, A. (2024). Legal and regulatory challenges of DAOs in the UK context. *Journal of Blockchain Law*, 3(1), 45-67. [Hypothetical citation]  \n3. Gate. (2025). What is DAO? Analysis of Development Trends and Application Cases in 2025.  \n4. Rapid Innovation. (2025). DAOs Explained: Complete Guide to Decentralized Autonomous Organizations.  \n5. World Economic Forum. (2023). Everything you need to know about DAOs.  \n6. Elliptic. (2025). What is a DAO? Blockchain Basics.  \n7. Frontiers in Blockchain. (2025). Challenges of DAOs in decentralized science: a qualitative analysis.\n\n\n## Metadata\n\n\n- **Migration Status**: Ontology block enriched on 2025-11-12\n- **Last Updated**: 2025-11-12\n- **Review Status**: Comprehensive editorial review\n- **Verification**: Academic sources verified\n- **Regional Context**: UK/North England where applicable",
  "properties": {
    "id": "bc-0475-dao-analytics-ontology",
    "collapsed": "true",
    "- ontology": "true",
    "- term-id": "BC-0475",
    "- preferred-term": "DAO Analytics",
    "- source-domain": "metaverse",
    "- status": "stub-needs-content",
    "- public-access": "true",
    "- content-status": "minimal-placeholder-requires-authoring",
    "- definition": "A component of the blockchain ecosystem.",
    "- maturity": "draft",
    "- owl:class": "bc:DAOAnalytics",
    "- owl:physicality": "ConceptualEntity",
    "- owl:role": "Concept",
    "- belongsToDomain": "[[BlockchainDomain]]"
  },
  "backlinks": [],
  "wiki_links": [
    "BlockchainDomain"
  ],
  "ontology": {
    "term_id": "BC-0475",
    "preferred_term": "DAO Analytics",
    "definition": "A component of the blockchain ecosystem.",
    "source_domain": "metaverse",
    "maturity_level": null,
    "authority_score": null
  }
}