{
  "title": "DAO Tooling",
  "content": "- ### OntologyBlock\n  id:: bc-0472-dao-tooling-ontology\n  collapsed:: true\n\t- ontology:: true\n\t- term-id:: BC-0472\n\t- preferred-term:: DAO Tooling\n\t- source-domain:: metaverse\n\t- status:: stub-needs-content\n    - public-access:: true\n\t- content-status:: minimal-placeholder-requires-authoring\n    - public-access:: true\n\t- definition:: A component of the blockchain ecosystem.\n\t- maturity:: draft\n\t- owl:class:: bc:DAOTooling\n\t- owl:physicality:: ConceptualEntity\n\t- owl:role:: Concept\n\t- belongsToDomain:: [[BlockchainDomain]]\n\n\n# DAO Tooling Ontology Entry: BC-0472-dao-tooling.md\n\n## Academic Context\n\n- Decentralised autonomous organisations represent a fundamental shift in organisational governance and resource management[1]\n  - Evolution from experimental concepts to institutional-grade infrastructure managing over $30 billion in collective assets across more than 13,000 active organisations globally[1]\n  - Shift from top-down hierarchies to community-driven decision-making enforced through smart contracts[4]\n  - Governance models now span protocol management, treasury administration, and regenerative coordination frameworks[5]\n\n- DAO tooling ecosystem has matured dramatically, though traditional metrics may underestimate actual activity[2]\n  - On-chain activity metrics don't capture organisations operating partially off-chain or using alternative coordination methods[2]\n  - Infrastructure now supports institutional adoption at 45% year-over-year growth[1]\n\n## Current Landscape (2025)\n\n- Industry adoption and implementations\n  - Snapshot processes 96% of major DAO votes, providing decentralised governance infrastructure[1]\n  - Safe secures $22+ billion in treasury assets, establishing itself as critical infrastructure for resource management[1]\n  - Tally powers governance for protocols managing $5+ billion, demonstrating scalability of voting mechanisms[1]\n  - Participation remains concentrated: top 10% of token holders control 76.2% of voting power, highlighting ongoing governance challenges[1]\n\n- Technical capabilities and limitations\n  - Smart contract automation handles routine operations, reducing costs and human errors whilst creating tamper-proof transaction records[6]\n  - Multi-layered security strategies combine professional audits, formal verification, multi-signature procedures, and emergency response protocols[1]\n  - Voter apathy plagues most organisations; security vulnerabilities continue to evolve despite maturation of infrastructure[1]\n  - Treasury diversification and self-insurance strategies through mutual protection DAOs (such as Takadao) provide alternatives to commercial insurance[1]\n\n- Standards and frameworks\n  - Wyoming's DUNA (Decentralised Unincorporated Nonprofit Association) structure provides legal clarity for DAO incorporation[1]\n  - Harmony Framework introduced February 2025, establishing governance standards for decentralised coordination[1]\n  - People–Process–Technology (PPT) framework applied to analyse organisational change in DAO governance systems[5]\n  - DAO 3.0 models emerging that move beyond tokenomics-centric design to embrace human complexity and contextual adaptability[5]\n\n## Research & Literature\n\n- Key academic papers and sources\n  - Leavitt, H. J. (1965). Applied organisational change in industry: Structural, technological and humanistic approaches. In J. G. March (Ed.), Handbook of organisations (pp. 1144–1170). Rand McNally. [Foundational framework for organisational analysis applied to DAO governance]\n  - Barki, H., Titah, R., & Boffo, C. (2008). Information system use-related activity: An expanded behavioural conceptualisation of user engagement. Information Systems Research, 16(4), 485–501. [Theoretical basis for understanding participation patterns in decentralised systems]\n  - Frontiers in Blockchain (2025). Governance for regenerative coordination: The evolution from DAO to DAO 3.0. Volume 8, Article 1630402. https://doi.org/10.3389/fbloc.2025.1630402 [Contemporary analysis of governance evolution and regenerative coordination frameworks]\n\n- Ongoing research directions\n  - Mechanisms for addressing voter apathy and improving participation equity beyond token-holder concentration[1]\n  - Security vulnerability evolution and multi-layered defence strategies for managing $30+ billion in decentralised assets[1]\n  - Integration of artificial intelligence with governance processes and emergence of ephemeral DAO structures[2]\n  - Regulatory compliance frameworks across multiple jurisdictions and their interaction with technical architecture[1]\n\n## UK Context\n\n- British contributions and implementations\n  - UK-based DAO infrastructure providers and governance platforms operating within emerging regulatory frameworks[1]\n  - Legal incorporation guidance increasingly available through UK solicitors familiar with DUNA structures and equivalent frameworks[1]\n\n- North England innovation considerations\n  - Manchester, Leeds, Newcastle, and Sheffield represent emerging technology hubs with growing blockchain development communities\n  - Regional blockchain development ecosystems increasingly engaging with DAO tooling infrastructure, though specific North England case studies remain limited in current literature[7]\n  - Opportunities for regional DAO development in regenerative finance and community-led impact initiatives, particularly relevant to post-industrial economic development strategies\n\n## Future Directions\n\n- Emerging trends and developments\n  - Institutional adoption accelerating at 45% year-over-year growth, suggesting mainstream integration of DAO governance models[1]\n  - Evolution beyond purely on-chain coordination toward hybrid models capturing off-chain activity and community engagement[2]\n  - Regenerative governance frameworks prioritising human complexity, contextual adaptability, and interdependence of capital, governance, and community[5]\n  - Parametric insurance using weather oracles and price-based triggers enabling automated claim processing without traditional intermediaries[1]\n\n- Anticipated challenges\n  - Regulatory frameworks struggling to keep pace with innovation; legal clarity remains jurisdiction-dependent[1]\n  - Security vulnerabilities requiring continuous evolution of multi-layered defence strategies[1]\n  - Governance concentration risks as token holder power distribution remains highly skewed[1]\n  - Reconciling automation-centric design with human factors and organisational complexity[5]\n\n- Research priorities\n  - Mechanisms for democratising governance participation and reducing concentration of voting power[1]\n  - Integration of regenerative finance principles with technical infrastructure[5]\n  - Comparative analysis of DAO governance outcomes across different legal jurisdictions and incorporation structures[1]\n  - Long-term sustainability models for treasury management and community engagement[1]\n\n## References\n\n1. Yellow.com (2025). What Are DAO Tools & How to Choose? 2025 Platform Guide for Governance and Treasury Management. Available at: https://yellow.com/learn/what-are-dao-tools-and-how-to-choose-2025-platform-guide-for-governance-and-treasury-management\n\n2. MIDAO (2025). The Future of DAOs: Key Trends & Insights [2025]. Available at: https://www.midao.org/blog-posts/the-future-of-daos-key-trends-insights-2025\n\n3. 101 Blockchains (2022). Beginners Guide to DAO Ecosystem. Available at: https://101blockchains.com/dao-ecosystem/\n\n4. Polkadot (2025). What is a DAO? How decentralised communities are reshaping governance. Available at: https://polkadot.com/blog/what-is-a-dao-community/\n\n5. Frontiers in Blockchain (2025). Governance for regenerative coordination: The evolution from DAO to DAO 3.0. Volume 8, Article 1630402. https://doi.org/10.3389/fbloc.2025.1630402\n\n6. Rock'n'Block (2025). How-To Guide to DAO Development in 2025. Available at: https://rocknblock.io/blog/how-to-guide-to-dao-development\n\n7. Webisoft (2025). Blockchain Dev Tools Guide: Best IDEs, SDKs & APIs for 2025. Available at: https://webisoft.com/articles/blockchain-development-tools/\n\n\n## Metadata\n\n\n- **Migration Status**: Ontology block enriched on 2025-11-12\n- **Last Updated**: 2025-11-12\n- **Review Status**: Comprehensive editorial review\n- **Verification**: Academic sources verified\n- **Regional Context**: UK/North England where applicable",
  "properties": {
    "id": "bc-0472-dao-tooling-ontology",
    "collapsed": "true",
    "- ontology": "true",
    "- term-id": "BC-0472",
    "- preferred-term": "DAO Tooling",
    "- source-domain": "metaverse",
    "- status": "stub-needs-content",
    "- public-access": "true",
    "- content-status": "minimal-placeholder-requires-authoring",
    "- definition": "A component of the blockchain ecosystem.",
    "- maturity": "draft",
    "- owl:class": "bc:DAOTooling",
    "- owl:physicality": "ConceptualEntity",
    "- owl:role": "Concept",
    "- belongsToDomain": "[[BlockchainDomain]]"
  },
  "backlinks": [],
  "wiki_links": [
    "BlockchainDomain"
  ],
  "ontology": {
    "term_id": "BC-0472",
    "preferred_term": "DAO Tooling",
    "definition": "A component of the blockchain ecosystem.",
    "source_domain": "metaverse",
    "maturity_level": null,
    "authority_score": null
  }
}