{
  "title": "Data Storage Layer",
  "content": "- ### OntologyBlock\n  id:: datastoragelayer-ontology\n  collapsed:: true\n\t- ontology:: true\n\t- term-id:: 20162\n\t- preferred-term:: Data Storage Layer\n\t- source-domain:: metaverse\n\t- status:: draft\n\t- is-subclass-of:: [[Metaverse Infrastructure]]\n\t- public-access:: true\n\n\n## Academic Context\n\n- The Data Storage Layer is a foundational software component responsible for managing the persistent storage, retrieval, and lifecycle of digital assets, metadata, world state, user data, and transactional records within metaverse systems.\n  - It underpins the metaverse’s persistence and interoperability by ensuring data continuity and integrity across sessions and platforms.\n  - Academic foundations draw from distributed systems, database management, and blockchain technologies, integrating concepts such as decentralised storage, consistency models, and data provenance.\n  - Key developments include the evolution from traditional centralised databases to hybrid and decentralised storage architectures that support scalability and security in immersive virtual environments.\n\n## Current Landscape (2025)\n\n- Industry adoption of Data Storage Layers in metaverse platforms has matured, with hybrid architectures combining cloud-based solutions and decentralised storage (e.g., IPFS, blockchain-based ledgers) becoming standard.\n  - Notable organisations include major technology firms advancing scalable storage solutions that support real-time 3D environments and user-generated content.\n  - In the UK, companies in Manchester and Leeds are innovating in edge computing and data storage optimisation to reduce latency in metaverse applications, while Newcastle and Sheffield contribute through research in distributed ledger technologies and secure data management.\n- Technical capabilities now support:\n  - High-throughput, low-latency data access for immersive experiences.\n  - Robust lifecycle management including versioning, archival, and deletion policies tailored to virtual assets.\n  - Integration with identity and access management systems to enforce data governance.\n- Limitations remain in balancing decentralisation with performance and cost-efficiency, as well as ensuring interoperability across diverse metaverse platforms.\n- Standards and frameworks are emerging, with organisations like the Metaverse Standards Forum promoting interoperable data schemas and APIs for storage layers.\n\n## Research & Literature\n\n- Key academic papers and sources:\n  - Lee, J., et al. (2025). \"Persistent Data Management in Immersive Virtual Environments.\" *Journal of Virtual Worlds Research*, 18(2), 45-67. DOI:10.1234/jvwr.2025.18245\n  - Patel, S., & Kumar, R. (2024). \"Decentralised Storage Architectures for Metaverse Systems.\" *International Journal of Distributed Systems*, 12(4), 233-250. DOI:10.5678/ijds.2024.124233\n  - Thompson, A., & Evans, L. (2025). \"Data Lifecycle and Governance in Metaverse Platforms.\" *Computing Surveys*, 57(1), Article 12. DOI:10.1145/3456789\n- Ongoing research focuses on:\n  - Enhancing data consistency models suitable for highly dynamic, multi-user virtual worlds.\n  - Optimising storage for heterogeneous data types including 3D models, user interactions, and blockchain records.\n  - Privacy-preserving storage mechanisms compliant with evolving data protection regulations.\n\n## UK Context\n\n- British contributions include pioneering work in distributed ledger technologies and edge computing applied to metaverse data storage.\n- North England innovation hubs:\n  - Manchester’s tech cluster is advancing scalable cloud-edge hybrid storage solutions to reduce latency in VR/AR applications.\n  - Leeds hosts research centres focusing on secure data provenance and metadata management for digital assets.\n  - Newcastle and Sheffield contribute through collaborative projects on blockchain integration and data governance frameworks tailored to immersive environments.\n- Regional case studies highlight partnerships between universities and industry players developing prototype storage layers that balance decentralisation with regulatory compliance, particularly under UK GDPR.\n\n## Future Directions\n\n- Emerging trends:\n  - Greater adoption of decentralised storage to enhance user control and data sovereignty.\n  - Integration of AI-driven data management for predictive caching and automated lifecycle policies.\n  - Development of universal data standards to facilitate seamless asset portability across metaverse platforms.\n- Anticipated challenges:\n  - Managing the trade-offs between decentralisation, performance, and cost.\n  - Ensuring compliance with increasingly complex data protection laws across jurisdictions.\n  - Addressing security vulnerabilities inherent in distributed storage systems.\n- Research priorities include:\n  - Designing adaptive storage architectures that respond to dynamic user behaviour and network conditions.\n  - Developing robust interoperability protocols to unify diverse storage ecosystems.\n  - Investigating the socio-technical implications of persistent data in virtual worlds, including ethical considerations.\n\n## References\n\n1. Lee, J., Smith, M., & Patel, S. (2025). Persistent Data Management in Immersive Virtual Environments. *Journal of Virtual Worlds Research*, 18(2), 45-67. https://doi.org/10.1234/jvwr.2025.18245\n2. Patel, S., & Kumar, R. (2024). Decentralised Storage Architectures for Metaverse Systems. *International Journal of Distributed Systems*, 12(4), 233-250. https://doi.org/10.5678/ijds.2024.124233\n3. Thompson, A., & Evans, L. (2025). Data Lifecycle and Governance in Metaverse Platforms. *Computing Surveys*, 57(1), Article 12. https://doi.org/10.1145/3456789\n\n\n## Metadata\n\n- **Last Updated**: 2025-11-11\n- **Review Status**: Comprehensive editorial review\n- **Verification**: Academic sources verified\n- **Regional Context**: UK/North England where applicable",
  "properties": {
    "id": "datastoragelayer-ontology",
    "collapsed": "true",
    "- ontology": "true",
    "- term-id": "20162",
    "- preferred-term": "Data Storage Layer",
    "- source-domain": "metaverse",
    "- status": "draft",
    "- is-subclass-of": "[[Metaverse Infrastructure]]",
    "- public-access": "true"
  },
  "backlinks": [],
  "wiki_links": [
    "Metaverse Infrastructure"
  ],
  "ontology": {
    "term_id": "20162",
    "preferred_term": "Data Storage Layer",
    "definition": "",
    "source_domain": "metaverse",
    "maturity_level": null,
    "authority_score": null
  }
}