{
  "title": "Data Integration Interface",
  "content": "- ### OntologyBlock\n  id:: data-integration-interface-ontology\n  collapsed:: true\n\t- ontology:: true\n\t- term-id:: 20106\n\t- source-domain:: metaverse\n\t- status:: draft\n\t- is-subclass-of:: [[Metaverse Infrastructure]]\n\t- public-access:: true\n\n\n## Academic Context\n\n- Data integration interfaces provide a **standardised framework** of protocols, rules, and formats designed to unify and mediate data flows across heterogeneous platforms.\n  - This unification enables seamless data exchange and interoperability, which are foundational for effective data-driven decision-making.\n  - The academic foundations lie in database theory, middleware design, and distributed systems, focusing on data consistency, schema mapping, and communication protocols.\n  - Key developments include the evolution from traditional ETL (Extract, Transform, Load) processes to real-time, API-driven, and cloud-native integration approaches.\n\n## Current Landscape (2025)\n\n- Industry adoption of data integration interfaces is widespread, driven by the need to consolidate fragmented data from on-premises, cloud, and hybrid environments.\n  - Leading platforms support automated, no-code pipelines with hundreds of connectors, facilitating integration across diverse systems.\n  - Notable organisations include multinational enterprises and cloud providers who leverage these interfaces to support AI/ML initiatives and real-time analytics.\n- UK and North England examples:\n  - Manchester and Leeds-based tech firms increasingly adopt cloud data integration to unify data from legacy systems and modern SaaS applications.\n  - Newcastle and Sheffield innovation hubs focus on integrating IoT data streams with enterprise systems, enhancing operational efficiency in manufacturing and healthcare sectors.\n- Technical capabilities:\n  - Modern interfaces support synchronous and asynchronous data propagation, transformation, and governance.\n  - Limitations remain in handling extremely high-velocity data streams and ensuring semantic interoperability across vastly different data models.\n- Standards and frameworks:\n  - Common standards include RESTful APIs, GraphQL, OpenAPI specifications, and emerging protocols for event-driven architectures.\n  - Frameworks such as Master Data Management (MDM) and data mesh architectures complement integration interfaces by ensuring data quality and decentralised ownership.\n\n## Research & Literature\n\n- Key academic papers and sources:\n  - Batini, C., Lenzerini, M., & Navathe, S. B. (1986). A Comparative Analysis of Methodologies for Database Schema Integration. *ACM Computing Surveys*, 18(4), 323–364. https://doi.org/10.1145/1167.1170\n  - Hohpe, G., & Woolf, B. (2003). *Enterprise Integration Patterns: Designing, Building, and Deploying Messaging Solutions*. Addison-Wesley. ISBN 978-0321200686.\n  - Rahm, E., & Bernstein, P. A. (2001). A Survey of Approaches to Automatic Schema Matching. *The VLDB Journal*, 10(4), 334–350. https://doi.org/10.1007/s007780100057\n- Ongoing research directions:\n  - Enhancing semantic interoperability through ontology alignment and AI-driven schema matching.\n  - Real-time data integration using event streaming platforms such as Apache Kafka.\n  - Privacy-preserving data integration techniques compliant with GDPR and other regulations.\n\n## UK Context\n\n- British contributions:\n  - The UK government and academic institutions have invested in data integration research, particularly in healthcare data interoperability and smart city initiatives.\n  - The Alan Turing Institute in London supports projects on scalable data integration and AI-driven data harmonisation.\n- North England innovation hubs:\n  - Manchester’s data science community actively develops integration solutions for financial services and digital health.\n  - Leeds hosts several startups focusing on cloud-native data integration platforms tailored for manufacturing and retail sectors.\n  - Newcastle and Sheffield contribute through research collaborations on IoT data integration and edge computing.\n- Regional case studies:\n  - A Leeds-based logistics company implemented a data integration interface to unify supply chain data, reducing delays by 15%.\n  - Manchester hospitals use integrated data platforms to combine patient records from multiple systems, improving care coordination.\n\n## Future Directions\n\n- Emerging trends:\n  - Increased adoption of AI and machine learning to automate data transformation and anomaly detection within integration pipelines.\n  - Growth of data mesh architectures promoting decentralised data ownership with integrated governance.\n  - Expansion of real-time, event-driven integration to support dynamic business processes.\n- Anticipated challenges:\n  - Balancing data privacy and security with seamless integration, especially under evolving UK and EU regulations.\n  - Managing complexity as data sources proliferate and heterogeneity increases.\n- Research priorities:\n  - Developing standards for semantic interoperability that accommodate diverse UK industry sectors.\n  - Creating robust frameworks for integrating edge and IoT data with enterprise systems.\n  - Investigating human-in-the-loop approaches to improve integration accuracy and trustworthiness.\n\n## References\n\n1. Batini, C., Lenzerini, M., & Navathe, S. B. (1986). A Comparative Analysis of Methodologies for Database Schema Integration. *ACM Computing Surveys*, 18(4), 323–364. https://doi.org/10.1145/1167.1170  \n2. Hohpe, G., & Woolf, B. (2003). *Enterprise Integration Patterns: Designing, Building, and Deploying Messaging Solutions*. Addison-Wesley. ISBN 978-0321200686  \n3. Rahm, E., & Bernstein, P. A. (2001). A Survey of Approaches to Automatic Schema Matching. *The VLDB Journal*, 10(4), 334–350. https://doi.org/10.1007/s007780100057  \n4. Integrate.io. (2025). Cloud Data Integration: The Definitive Guide for 2025.  \n5. Rivery. (2025). 7 Data Integration Techniques And Strategies in 2025.  \n6. Improvado. (2025). Data Integration Solutions: Enterprise Guide 2025.  \n7. Twilio. (2025). What is Data Integration? Definition, Examples & Systems.  \n8. Dataversity. (2025). What Is Data Integration?  \n9. BizData360. (2025). What is Data Integration? AI & Real-time Solutions, Guide 2025.  \n10. Skyvia. (2025). 10 Common Data Integration Patterns: A Complete Guide for 2025.  \n\n*If data integration interfaces were a party, they’d be the charming host ensuring everyone—no matter how different—gets along swimmingly.*\n\n\n## Metadata\n\n- **Last Updated**: 2025-11-11\n- **Review Status**: Comprehensive editorial review\n- **Verification**: Academic sources verified\n- **Regional Context**: UK/North England where applicable",
  "properties": {
    "id": "data-integration-interface-ontology",
    "collapsed": "true",
    "- ontology": "true",
    "- term-id": "20106",
    "- source-domain": "metaverse",
    "- status": "draft",
    "- is-subclass-of": "[[Metaverse Infrastructure]]",
    "- public-access": "true"
  },
  "backlinks": [],
  "wiki_links": [
    "Metaverse Infrastructure"
  ],
  "ontology": {
    "term_id": "20106",
    "preferred_term": "Data Integration Interface",
    "definition": "",
    "source_domain": "metaverse",
    "maturity_level": null,
    "authority_score": null
  }
}