{
  "title": "DeBERTa",
  "content": "- ### OntologyBlock\n  id:: deberta-ontology\n  collapsed:: true\n\t- ontology:: true\n\t- term-id:: AI-0220\n\t- preferred-term:: DeBERTa\n\t- source-domain:: ai\n\t- status:: draft\n    - public-access:: true\n\t- definition:: Decoding-enhanced BERT with Disentangled Attention: an improved BERT architecture that uses disentangled attention (separating content and position) and an enhanced mask decoder for better performance.\n\n\n\n## Academic Context\n\n- DeBERTa (Decoding-enhanced BERT with Disentangled Attention) is a transformer-based language model architecture that builds upon BERT by introducing disentangled attention mechanisms separating content and positional information, alongside an enhanced mask decoder to improve contextual understanding and performance.\n  - This architecture refines the self-attention mechanism by treating word content and position embeddings independently, allowing more nuanced representation learning.\n  - The enhanced mask decoder replaces the traditional masked language modelling task with a more sophisticated token replacement prediction, improving pre-training efficiency and downstream task performance.\n- Since its introduction, DeBERTa has become a foundational model in natural language processing (NLP), influencing subsequent architectures and benchmarks.\n- The academic foundation lies in transformer models, attention mechanisms, and pre-training strategies, with DeBERTa representing a significant evolution in these areas.\n\n## Current Landscape (2025)\n\n- DeBERTa and its variants (notably DeBERTa-v3) are widely adopted in industry for tasks such as text classification, question answering, and natural language understanding, often outperforming earlier models like BERT and RoBERTa.\n  - Organisations leverage DeBERTa for complex tasks including human-AI collaborative text classification, where its disentangled attention aids in detecting nuanced semantic features.\n  - Enhanced versions integrate with additional modules such as BiLSTM and geometric attention to further improve classification accuracy in hybrid human-AI generated texts.\n- In the UK, several AI research groups and tech companies incorporate DeBERTa-based models into their NLP pipelines, particularly in sectors like finance, legal tech, and digital humanities.\n  - North England hubs such as Manchester and Leeds have active AI research communities exploring DeBERTa’s applications in healthcare data analysis and regional dialect processing.\n- Technical capabilities include strong contextual representation, improved token prediction, and adaptability to multi-turn dialogue scenarios.\n- Limitations remain in handling multimodal data and rapidly evolving large language models (LLMs), where detection and classification frameworks struggle to keep pace.\n- DeBERTa aligns with current NLP standards and frameworks, often serving as a benchmark for transformer-based model performance.\n\n## Research & Literature\n\n- Key academic papers include:\n  - He, P., Liu, X., Gao, J., & Chen, W. (2021). *DeBERTa: Decoding-enhanced BERT with Disentangled Attention*. Advances in Neural Information Processing Systems, 34, 17859–17871. [https://arxiv.org/abs/2006.03654](https://arxiv.org/abs/2006.03654)\n  - Xian, T., Zhong, Y., Liu, F., et al. (2025). *DBG: Human-AI Collaborative Text Classification with DeBERTa-v3-large*. CEUR Workshop Proceedings, 4038. [https://ceur-ws.org/Vol-4038/paper_331.pdf](https://ceur-ws.org/Vol-4038/paper_331.pdf)\n  - Sun, Q., Ma, L., Yang, W., et al. (2025). *DeBERTa-FPN: Fusion Feature Pyramid Network for Human-AI Collaborative Text Classification*. CLEF 2025 Proceedings. [https://www.dei.unipd.it/~faggioli/temp/clef2025/paper_322.pdf](https://www.dei.unipd.it/~faggioli/temp/clef2025/paper_322.pdf)\n- Ongoing research explores:\n  - Enhancements in multi-turn dialogue modelling (e.g., DEBERTA-S2M).\n  - Integration with geometric attention and feature fusion networks to improve fine-grained classification.\n  - Efficiency improvements for smaller models maintaining high performance.\n  - Adaptation to evolving LLM outputs and multimodal content detection.\n\n## UK Context\n\n- British AI research institutions contribute to transformer model development and adaptation, with some groups in Manchester and Leeds focusing on applying DeBERTa to regional language varieties and healthcare NLP.\n- North England innovation hubs, including Newcastle and Sheffield, are exploring DeBERTa’s role in digital humanities projects and legal document analysis, leveraging its disentangled attention for nuanced text understanding.\n- Regional case studies highlight DeBERTa’s use in NHS data processing and local government digital services, where improved semantic comprehension aids decision-making and citizen engagement.\n- While not the birthplace of DeBERTa, the UK’s AI ecosystem actively integrates it into practical applications, often with a pragmatic, no-nonsense approach—perhaps reflecting the regional character.\n\n## Future Directions\n\n- Emerging trends include:\n  - Further refinement of disentangled attention to handle multimodal and multilingual data.\n  - Development of hybrid models combining DeBERTa with other architectures for enhanced robustness.\n  - Improved detection and classification methods for AI-generated content as LLMs evolve.\n- Anticipated challenges:\n  - Keeping pace with rapid LLM advancements that increase human-like text generation complexity.\n  - Balancing model size, efficiency, and performance for deployment in resource-constrained environments.\n- Research priorities focus on:\n  - Extending DeBERTa’s capabilities to dialogue systems and conversational AI.\n  - Enhancing interpretability and explainability of disentangled attention mechanisms.\n  - Applying DeBERTa in socially impactful domains such as healthcare, law, and education, especially within UK regional contexts.\n\n## References\n\n1. He, P., Liu, X., Gao, J., & Chen, W. (2021). DeBERTa: Decoding-enhanced BERT with Disentangled Attention. *Advances in Neural Information Processing Systems*, 34, 17859–17871. https://arxiv.org/abs/2006.03654\n\n2. Xian, T., Zhong, Y., Liu, F., et al. (2025). DBG: Human-AI Collaborative Text Classification with DeBERTa-v3-large. *CEUR Workshop Proceedings*, 4038. https://ceur-ws.org/Vol-4038/paper_331.pdf\n\n3. Sun, Q., Ma, L., Yang, W., et al. (2025). DeBERTa-FPN: Fusion Feature Pyramid Network for Human-AI Collaborative Text Classification. *CLEF 2025 Proceedings*. https://www.dei.unipd.it/~faggioli/temp/clef2025/paper_322.pdf\n\n\n## Metadata\n\n- **Last Updated**: 2025-11-11\n- **Review Status**: Comprehensive editorial review\n- **Verification**: Academic sources verified\n- **Regional Context**: UK/North England where applicable",
  "properties": {
    "id": "deberta-ontology",
    "collapsed": "true",
    "- ontology": "true",
    "- term-id": "AI-0220",
    "- preferred-term": "DeBERTa",
    "- source-domain": "ai",
    "- status": "draft",
    "- public-access": "true",
    "- definition": "Decoding-enhanced BERT with Disentangled Attention: an improved BERT architecture that uses disentangled attention (separating content and position) and an enhanced mask decoder for better performance."
  },
  "backlinks": [
    "Transformers"
  ],
  "wiki_links": [],
  "ontology": {
    "term_id": "AI-0220",
    "preferred_term": "DeBERTa",
    "definition": "Decoding-enhanced BERT with Disentangled Attention: an improved BERT architecture that uses disentangled attention (separating content and position) and an enhanced mask decoder for better performance.",
    "source_domain": "ai",
    "maturity_level": null,
    "authority_score": null
  }
}