{
  "title": "Decentralized Identifiers",
  "content": "- ### OntologyBlock\n  id:: bc-0457-decentralized-identifiers-ontology\n  collapsed:: true\n\t- ontology:: true\n\t- term-id:: BC-0457\n\t- preferred-term:: Decentralized Identifiers\n\t- source-domain:: metaverse\n\t- status:: stub-needs-content\n    - public-access:: true\n\t- content-status:: minimal-placeholder-requires-authoring\n    - public-access:: true\n\t- definition:: A component of the blockchain ecosystem.\n\t- maturity:: draft\n\t- owl:class:: bc:DecentralizedIdentifiers\n\t- owl:physicality:: ConceptualEntity\n\t- owl:role:: Concept\n\t- is-subclass-of:: [[Metaverse]]\n\t- belongsToDomain:: [[BlockchainDomain]]\n\t- #### CrossDomainBridges\n\t\t- bc:authenticates:: [[Avatar]]\n\t\t- bc:authenticates:: [[DigitalAvatar]]\n\n\n# Updated Ontology Entry: Decentralized Identifiers\n\n## Academic Context\n\n- Decentralized Identifiers (DIDs) represent a paradigm shift in digital identity management\n  - Defined by the World Wide Web Consortium (W3C) as verifiable, cryptographically-secured digital identifiers that operate independently of centralised authorities[1][7]\n  - Enable individuals and organisations to maintain control over identity credentials without reliance on third-party issuers or certificate authorities\n  - Distinguish themselves from traditional federated identifiers through architectural decoupling from centralised registries and identity providers\n  - Form a core component of the broader decentralised identity ecosystem, though extend beyond blockchain applications to distributed systems generally\n\n- Foundational principles and design philosophy\n  - Controllers of DIDs can prove ownership without requiring permission from external parties[1]\n  - Each DID associates with a DID document containing cryptographic material, verification methods, and service endpoints\n  - URIs that incorporate method identifiers and unique, method-specific identifiers (format: `did:method:uniqueID`)[1]\n  - Resolvable to DID documents through standardised resolution processes\n\n## Current Landscape (2025)\n\n- Industry adoption and technical implementations\n  - Multiple DID methods now operational across distributed ledgers (Ethereum, Dock, ION, XRP Ledger and others)[3][7]\n  - Interoperable across different systems and platforms, enabling single digital identities across multiple services[2]\n  - Integration with verifiable credentials (VCs) and digital identity wallets for comprehensive identity management[2][4]\n  - Creation process simplified: select method, generate keypair, write DID document, anchor on-chain, store in wallet[3]\n\n- Technical capabilities and current limitations\n  - Cryptographic techniques ensure tamper-proof, verifiable identity management[2]\n  - Eliminates single points of failure inherent in centralised identity systems\n  - Adoption challenges persist: regulatory uncertainty, user experience hurdles, and remaining interoperability gaps, though standards organisations are actively addressing these[4]\n  - Account lockouts and unauthorised data access become technically infeasible within properly implemented DID systems[3]\n\n- Standards and frameworks\n  - W3C Decentralized Identifiers (DIDs) v1.1 specification provides comprehensive technical framework[1]\n  - Specifies DID syntax, common data model, core properties, serialised representations, and DID operations\n  - DID URLs extend basic DID syntax to incorporate standard URI components (path, query, fragment) for locating specific resources within or external to DID documents[1]\n\n## Research & Literature\n\n- Primary standards and specifications\n  - World Wide Web Consortium (2025). *Decentralized Identifiers (DIDs) v1.1*. W3C Technical Report. Available at: https://www.w3.org/TR/did-1.1/[1]\n  - Defines syntax, data models, and resolution mechanisms for decentralised identifier systems\n\n- Academic and technical foundations\n  - Identity.com. *What Are Decentralized Identifiers (DIDs)?* Comprehensive technical overview addressing cryptographic security, interoperability, and DID controller roles[2]\n  - 1Kosmos. *What Is Decentralized Identity? A Complete Guide for Beginners*. Addresses blockchain foundations, verifiable credentials, and adoption challenges[4]\n  - Regula Forensics. *Decentralized Identity Explained: Definition, Components, Use Cases*. Explores applications across finance, government, and education sectors[6]\n\n- Ongoing research directions\n  - Regulatory frameworks and compliance mechanisms for decentralised identity systems\n  - User experience optimisation for non-technical users\n  - Cross-ledger interoperability standards\n  - Integration with emerging technologies (biometrics, spoofing detection)\n\n## UK Context\n\n- British engagement with decentralised identity standards\n  - W3C specifications developed through international collaboration, with UK-based organisations participating in standards development\n  - Financial services sector exploring DID implementations for regulatory compliance and customer verification\n\n- North England innovation considerations\n  - Manchester, Leeds, and Newcastle emerging as fintech and digital innovation hubs with growing interest in decentralised identity solutions\n  - Academic institutions in the region (University of Manchester, University of Leeds) conducting research into blockchain-based identity systems\n  - Regional financial services clusters exploring DIDs for Know Your Customer (KYC) and Anti-Money Laundering (AML) compliance\n\n- Practical applications in UK context\n  - Government digital identity initiatives increasingly considering decentralised approaches\n  - Financial institutions evaluating DIDs for customer onboarding and credential verification\n  - Educational institutions exploring portable digital credentials for student records and qualifications\n\n## Future Directions\n\n- Emerging trends and developments\n  - Maturation of regulatory frameworks governing decentralised identity systems across UK and EU jurisdictions\n  - Increased integration with artificial intelligence for identity verification and fraud detection\n  - Expansion of DID adoption beyond financial services into healthcare, education, and government sectors\n  - Development of privacy-preserving verification mechanisms that avoid centralised personal information repositories[4]\n\n- Anticipated challenges\n  - Balancing user accessibility with technical complexityâ€”particularly for populations with limited digital literacy or infrastructure\n  - Establishing interoperability standards across heterogeneous blockchain and distributed ledger systems\n  - Regulatory harmonisation between jurisdictions with differing data protection requirements\n  - Managing the transition from centralised to decentralised identity paradigms within existing institutional frameworks\n\n- Research priorities\n  - User experience design for decentralised identity systems\n  - Scalability solutions for high-volume identity verification\n  - Integration standards for verifiable credentials across sectors\n  - Governance models for decentralised identity ecosystems\n  - Resilience and recovery mechanisms for compromised cryptographic material\n\n## References\n\n[1] World Wide Web Consortium (2025). Decentralized Identifiers (DIDs) v1.1. W3C Technical Report. https://www.w3.org/TR/did-1.1/\n\n[2] Identity.com. What Are Decentralized Identifiers (DIDs)? https://www.identity.com/what-are-decentralized-identifiers-dids/\n\n[3] CoinSwitch. Decentralized Identifiers (DIDs): The Ultimate Guide 2025. https://coinswitch.co/switch/crypto/decentralized-identifiers-dids/\n\n[4] 1Kosmos. What Is Decentralized Identity? A Complete Guide for Beginners. https://www.1kosmos.com/identity-management/decentralized-identity-complete-guide/\n\n[5] Gate.io. What Is Decentralized Identity (DID)? Definition, Applications, and 2025 Trend Analysis. https://www.gate.com/tr/blog/11025/what-is-decentralized-identity-did-definition-applications-and-2025-trend-analysis\n\n[6] Regula Forensics. Decentralized Identity Explained: Definition, Components, Use Cases. https://regulaforensics.com/blog/what-is-decentralized-identity/\n\n[7] XRP Ledger. Decentralized Identifiers. https://xrpl.org/docs/concepts/decentralized-storage/decentralized-identifiers\n\n\n## Metadata\n\n\n- **Migration Status**: Ontology block enriched on 2025-11-12\n- **Last Updated**: 2025-11-12\n- **Review Status**: Comprehensive editorial review\n- **Verification**: Academic sources verified\n- **Regional Context**: UK/North England where applicable",
  "properties": {
    "id": "bc-0457-decentralized-identifiers-ontology",
    "collapsed": "true",
    "- ontology": "true",
    "- term-id": "BC-0457",
    "- preferred-term": "Decentralized Identifiers",
    "- source-domain": "metaverse",
    "- status": "stub-needs-content",
    "- public-access": "true",
    "- content-status": "minimal-placeholder-requires-authoring",
    "- definition": "A component of the blockchain ecosystem.",
    "- maturity": "draft",
    "- owl:class": "bc:DecentralizedIdentifiers",
    "- owl:physicality": "ConceptualEntity",
    "- owl:role": "Concept",
    "- is-subclass-of": "[[Metaverse]]",
    "- belongsToDomain": "[[BlockchainDomain]]",
    "- bc:authenticates": "[[DigitalAvatar]]"
  },
  "backlinks": [],
  "wiki_links": [
    "Avatar",
    "BlockchainDomain",
    "Metaverse",
    "DigitalAvatar"
  ],
  "ontology": {
    "term_id": "BC-0457",
    "preferred_term": "Decentralized Identifiers",
    "definition": "A component of the blockchain ecosystem.",
    "source_domain": "metaverse",
    "maturity_level": null,
    "authority_score": null
  }
}