{
  "title": "Decentralization",
  "content": "- ### OntologyBlock\n  id:: decentralization-ontology\n  collapsed:: true\n\n  - **Identification**\n\n    - domain-prefix:: BC\n\n    - sequence-number:: 0010\n\n    - filename-history:: [\"BC-0010-decentralization.md\"]\n    - public-access:: true\n    - ontology:: true\n    - is-subclass-of:: [[BlockchainTechnology]]\n    - term-id:: BC-0010\n    - preferred-term:: Decentralization\n    - source-domain:: blockchain\n    - status:: complete\n    - version:: 1.0.0\n    - last-updated:: 2025-10-28\n\n  - **Definition**\n    - definition:: Distribution of control across network within blockchain systems, providing essential functionality for distributed ledger technology operations and properties.\n    - maturity:: mature\n    - source:: [[ISO/IEC 23257:2021]], [[IEEE 2418.1]], [[NIST NISTIR]]\n    - authority-score:: 0.95\n\n  - **Semantic Classification**\n    - owl:class:: bc:Decentralization\n    - owl:physicality:: VirtualEntity\n    - owl:role:: Object\n    - owl:inferred-class:: bc:VirtualObject\n    - belongsToDomain:: [[BlockchainDomain]]\n\n  - #### OWL Restrictions\n    \n    \n\n  - #### CrossDomainBridges\n    - bridges-to:: [[Distributeddatastructure]] via is-subclass-of\n    - bridges-to:: [[BlockchainEntity]] via is-subclass-of\n    - bridges-from:: [[DistributedArchitecture]] via enables\n\n  -",
  "properties": {
    "id": "decentralization-ontology",
    "collapsed": "true",
    "- domain-prefix": "BC",
    "- sequence-number": "0010",
    "- filename-history": "[\"BC-0010-decentralization.md\"]",
    "- public-access": "true",
    "- ontology": "true",
    "- is-subclass-of": "[[BlockchainTechnology]]",
    "- term-id": "BC-0010",
    "- preferred-term": "Decentralization",
    "- source-domain": "blockchain",
    "- status": "complete",
    "- version": "1.0.0",
    "- last-updated": "2025-10-28",
    "- definition": "Distribution of control across network within blockchain systems, providing essential functionality for distributed ledger technology operations and properties.",
    "- maturity": "mature",
    "- source": "[[ISO/IEC 23257:2021]], [[IEEE 2418.1]], [[NIST NISTIR]]",
    "- authority-score": "0.95",
    "- owl:class": "bc:Decentralization",
    "- owl:physicality": "VirtualEntity",
    "- owl:role": "Object",
    "- owl:inferred-class": "bc:VirtualObject",
    "- belongsToDomain": "[[BlockchainDomain]]",
    "- bridges-to": "[[BlockchainEntity]] via is-subclass-of",
    "- bridges-from": "[[DistributedArchitecture]] via enables"
  },
  "backlinks": [
    "Blockchain Entity",
    "Digital Twin of the Customer"
  ],
  "wiki_links": [
    "Distributeddatastructure",
    "BlockchainTechnology",
    "IEEE 2418.1",
    "BlockchainEntity",
    "NIST NISTIR",
    "DistributedArchitecture",
    "ISO/IEC 23257:2021",
    "BlockchainDomain"
  ],
  "ontology": {
    "term_id": "BC-0010",
    "preferred_term": "Decentralization",
    "definition": "Distribution of control across network within blockchain systems, providing essential functionality for distributed ledger technology operations and properties.",
    "source_domain": "blockchain",
    "maturity_level": null,
    "authority_score": 0.95
  }
}