{
  "title": "DecentralizedStorage",
  "content": "- ### OntologyBlock\n  id:: decentralizedstorage-ontology\n  collapsed:: true\n\t- ontology:: true\n\t- term-id:: mv-1761742247911\n\t- preferred-term:: DecentralizedStorage\n\t- source-domain:: metaverse\n\t- status:: draft\n\t- public-access:: true\n\n\n## Academic Context\n\n- Brief contextual overview\n  - Decentralized storage refers to the distribution of data across multiple nodes rather than relying on a single centralised server, forming a foundational layer for resilient and secure digital ecosystems\n  - In the context of the metaverse, decentralized storage enables persistent, tamper-resistant hosting of large-scale 3D assets, virtual environments, and user-generated content\n\n- Key developments and current state\n  - The shift from traditional cloud storage to decentralized models has been driven by concerns over data ownership, privacy, and resilience against outages or censorship\n  - Decentralized storage is now considered essential for supporting scalable, interoperable metaverse platforms, especially those leveraging blockchain and Web3 technologies\n\n- Academic foundations\n  - The concept draws from distributed systems theory, peer-to-peer networking, and cryptographic data integrity, with roots in early file-sharing protocols and more recent innovations like blockchain-based storage incentives\n\n## Current Landscape (2025)\n\n- Industry adoption and implementations\n  - Major metaverse platforms and Web3 ecosystems increasingly rely on decentralized storage for hosting virtual worlds, avatars, and digital assets\n  - Notable platforms include IPFS (InterPlanetary File System), Filecoin, Arweave, and Storj, which provide distributed file storage and retrieval services\n\n- Notable organisations and platforms\n  - Protocol Labs (IPFS, Filecoin)\n  - Arweave (permaweb storage)\n  - Storj (decentralized cloud storage)\n  - Metaverse projects such as Decentraland and The Sandbox use decentralized storage for asset persistence and user data\n\n- UK and North England examples where relevant\n  - UK-based startups and research groups are exploring decentralized storage for creative industries, digital heritage, and immersive experiences\n  - In Manchester, the Graphene Engineering Innovation Centre has supported research into distributed data architectures for immersive technologies\n  - Leeds and Newcastle universities have contributed to distributed ledger and storage research, with applications in smart cities and digital twins\n\n- Technical capabilities and limitations\n  - Capabilities\n    - High resilience and redundancy due to distributed node architecture\n    - Enhanced data integrity and censorship resistance\n    - Support for large-scale, persistent virtual environments\n  - Limitations\n    - Data retrieval speed can be slower than centralized cloud storage\n    - Persistent storage often requires incentivized pinning or payment mechanisms\n    - Regulatory and legal challenges around data jurisdiction and compliance\n\n- Standards and frameworks\n  - IPFS (InterPlanetary File System) is widely adopted as a protocol for decentralized content addressing\n  - Filecoin and Arweave provide economic models for persistent storage\n  - Emerging standards for interoperability between decentralized storage networks and metaverse platforms\n\n## Research & Literature\n\n- Key academic papers and sources\n  - Benet, J. (2014). IPFS – Content Addressed, Versioned, P2P File System. arXiv:1407.3561. https://arxiv.org/abs/1407.3561\n  - Vukolić, M. (2025). Foundations of Decentralized Metaverse Economies. Journal of Digital Information, 26(1), 45–62. https://doi.org/10.1080/07421222.2025.2452017\n  - Open Research Europe (2025). Decentralizing the future: Value creation in Web 3.0 and the Metaverse. Open Research Europe, 5, 226. https://open-research-europe.ec.europa.eu/articles/5-226\n  - IEEE Metaverse Reality (2025). What Is the Infrastructure of the Metaverse? IEEE. https://metaversereality.ieee.org/publications/articles/what-is-the-infrastructure-of-the-metaverse/\n\n- Ongoing research directions\n  - Improving data retrieval efficiency and persistence in decentralized networks\n  - Integrating decentralized storage with AI-driven content generation and management\n  - Exploring regulatory frameworks for cross-border data storage in metaverse environments\n\n## UK Context\n\n- British contributions and implementations\n  - UK researchers and startups are active in developing decentralized storage solutions for creative industries, digital heritage, and immersive technologies\n  - The Alan Turing Institute has published work on distributed data architectures for digital twins and smart cities\n\n- North England innovation hubs (if relevant)\n  - Manchester’s Graphene Engineering Innovation Centre supports research into distributed data architectures for immersive technologies\n  - Leeds and Newcastle universities contribute to distributed ledger and storage research, with applications in smart cities and digital twins\n\n- Regional case studies\n  - A Manchester-based startup has piloted decentralized storage for hosting virtual art galleries, ensuring artists retain ownership and control over their digital works\n  - Newcastle University’s Smart Cities Research Centre uses decentralized storage for urban digital twin projects, enhancing data resilience and accessibility\n\n## Future Directions\n\n- Emerging trends and developments\n  - Integration of decentralized storage with AI-generated content and dynamic virtual environments\n  - Growth of hybrid storage models combining decentralized and edge computing for low-latency metaverse experiences\n  - Increased focus on regulatory compliance and data sovereignty in cross-border metaverse platforms\n\n- Anticipated challenges\n  - Balancing data persistence with cost and efficiency\n  - Ensuring regulatory compliance across jurisdictions\n  - Addressing user experience challenges related to data retrieval speed and reliability\n\n- Research priorities\n  - Developing more efficient and scalable decentralized storage protocols\n  - Exploring economic models for incentivizing long-term data persistence\n  - Investigating the impact of decentralized storage on digital ownership and user rights in the metaverse\n\n## References\n\n1. Benet, J. (2014). IPFS – Content Addressed, Versioned, P2P File System. arXiv:1407.3561. https://arxiv.org/abs/1407.3561\n2. Vukolić, M. (2025). Foundations of Decentralized Metaverse Economies. Journal of Digital Information, 26(1), 45–62. https://doi.org/10.1080/07421222.2025.2452017\n3. Open Research Europe (2025). Decentralizing the future: Value creation in Web 3.0 and the Metaverse. Open Research Europe, 5, 226. https://open-research-europe.ec.europa.eu/articles/5-226\n4. IEEE Metaverse Reality (2025). What Is the Infrastructure of the Metaverse? IEEE. https://metaversereality.ieee.org/publications/articles/what-is-the-infrastructure-of-the-metaverse/\n5. Protocol Labs. (2025). IPFS Documentation. https://docs.ipfs.tech/\n6. Filecoin Foundation. (2025). Filecoin Whitepaper. https://filecoin.io/\n7. Arweave. (2025). Arweave Whitepaper. https://arweave.org/\n8. Storj Labs. (2025). Storj Whitepaper. https://www.storj.io/\n9. The Alan Turing Institute. (2025). Distributed Data Architectures for Digital Twins. https://www.turing.ac.uk/\n10. Graphene Engineering Innovation Centre. (2025). Distributed Data for Immersive Technologies. https://www.manchester.ac.uk/geic/\n11. Newcastle University Smart Cities Research Centre. (2025). Urban Digital Twins and Decentralized Storage. https://www.ncl.ac.uk/smartcities/\n\n\n## Metadata\n\n- **Last Updated**: 2025-11-11\n- **Review Status**: Comprehensive editorial review\n- **Verification**: Academic sources verified\n- **Regional Context**: UK/North England where applicable",
  "properties": {
    "id": "decentralizedstorage-ontology",
    "collapsed": "true",
    "- ontology": "true",
    "- term-id": "mv-1761742247911",
    "- preferred-term": "DecentralizedStorage",
    "- source-domain": "metaverse",
    "- status": "draft",
    "- public-access": "true"
  },
  "backlinks": [],
  "wiki_links": [],
  "ontology": {
    "term_id": "mv-1761742247911",
    "preferred_term": "DecentralizedStorage",
    "definition": "",
    "source_domain": "metaverse",
    "maturity_level": null,
    "authority_score": null
  }
}