{
  "title": "Decoder",
  "content": "- ### OntologyBlock\n  id:: decoder-ontology\n  collapsed:: true\n\t- ontology:: true\n\t- term-id:: AI-0206\n\t- preferred-term:: Decoder\n\t- source-domain:: ai\n\t- status:: draft\n    - public-access:: true\n\t- definition:: The component in an encoder-decoder architecture that generates the output sequence autoregressively, using masked self-attention, cross-attention to encoder outputs, and feed-forward layers.\n\n\n## Academic Context\n\n- Brief contextual overview\n\t- The decoder is a core component of encoder-decoder neural network architectures, originally developed for sequence-to-sequence tasks such as machine translation and text generation\n\t- It operates by generating output sequences step-by-step, using information from both its own previous outputs and the encoded input representation\n\t- Key developments and current state\n\t\t- Modern decoders are most commonly found in Transformer-based models, which have largely superseded earlier recurrent architectures due to their parallelisability and scalability\n\t\t- The decoder’s autoregressive nature allows it to generate sequences token by token, making it suitable for tasks ranging from language modelling to image captioning\n\t- Academic foundations\n\t\t- The foundational concept of encoder-decoder networks was established in the early 2010s, with the Transformer architecture (Vaswani et al., 2017) marking a pivotal shift in the field\n\n## Current Landscape (2025)\n\n- Industry adoption and implementations\n\t- Transformer decoders are now standard in large language models (LLMs) such as GPT, Llama, and PaLM, powering applications from chatbots to code generation\n\t- Notable organisations and platforms\n\t\t- OpenAI, Google DeepMind, Meta, and Anthropic all deploy decoder-heavy architectures in their flagship models\n\t\t- UK and North England examples where relevant\n\t\t\t- The Alan Turing Institute in London and the AI research groups at the University of Manchester have developed and deployed decoder-based models for natural language processing and healthcare applications\n\t\t\t- In Leeds, the Leeds Institute for Data Analytics has explored decoder architectures for social science and policy modelling\n\t\t\t- Newcastle University’s School of Computing has contributed to research on efficient decoder implementations for edge devices\n\t- Technical capabilities and limitations\n\t\t- Decoders excel at generating coherent, contextually relevant sequences but can struggle with long-range dependencies and computational efficiency at scale\n\t\t- Recent advances in sparse attention and speculative decoding have begun to address some of these limitations\n\t- Standards and frameworks\n\t\t- PyTorch and TensorFlow remain the dominant frameworks for implementing decoder architectures\n\t\t- Hugging Face’s Transformers library provides accessible, pre-trained decoder models and tools for fine-tuning\n\n## Research & Literature\n\n- Key academic papers and sources\n\t- Vaswani, A., Shazeer, N., Parmar, N., Uszkoreit, J., Jones, L., Gomez, A. N., Kaiser, Ł., & Polosukhin, I. (2017). Attention Is All You Need. Advances in Neural Information Processing Systems, 30. https://proceedings.neurips.cc/paper/2017/hash/3f5ee243547dee91fbd053c1c4a845aa-Abstract.html\n\t- Brown, T. B., Mann, B., Ryder, N., Subbiah, M., Kaplan, J., Dhariwal, P., ... & Amodei, D. (2020). Language Models are Few-Shot Learners. Advances in Neural Information Processing Systems, 33. https://proceedings.neurips.cc/paper/2020/hash/1457c0d6bfcb4967418bfb8ac142f64a-Abstract.html\n\t- Heckelmann, P. (2025). Investigation of different LSTM-based encoder-decoder architectures for vehicle speed prediction. Scientific Reports, 15(1), 19592. https://doi.org/10.1038/s41598-025-19592-5\n- Ongoing research directions\n\t- Improving decoder efficiency through sparse attention and quantisation\n\t- Exploring non-autoregressive decoding for faster inference\n\t- Investigating the integration of multimodal inputs (e.g., text, image, audio) into decoder architectures\n\n## UK Context\n\n- British contributions and implementations\n\t- UK researchers have played a significant role in advancing decoder-based models, particularly in the areas of natural language processing and healthcare\n\t- The Alan Turing Institute and the University of Cambridge have published influential work on decoder architectures and their applications\n- North England innovation hubs (if relevant)\n\t- The University of Manchester’s Centre for Machine Learning and Data Science has developed decoder-based models for medical text analysis and patient record summarisation\n\t- Leeds Institute for Data Analytics has applied decoder architectures to social science and policy research, including crime prediction and urban planning\n\t- Newcastle University’s School of Computing has explored efficient decoder implementations for edge devices and IoT applications\n- Regional case studies\n\t- A recent project at the University of Sheffield used decoder-based models to generate synthetic patient data for training healthcare professionals, demonstrating the practical impact of these architectures in the North of England\n\n## Future Directions\n\n- Emerging trends and developments\n\t- Increased focus on energy-efficient and environmentally sustainable decoder architectures\n\t- Integration of multimodal inputs and outputs for more versatile applications\n\t- Development of non-autoregressive and parallel decoding methods to improve inference speed\n- Anticipated challenges\n\t- Balancing computational efficiency with model performance\n\t- Ensuring robustness and fairness in decoder-generated outputs\n\t- Addressing the environmental impact of large-scale decoder training\n- Research priorities\n\t- Improving decoder efficiency and scalability\n\t- Enhancing the interpretability and controllability of decoder-generated sequences\n\t- Exploring new applications in healthcare, education, and social sciences\n\n## References\n\n1. Vaswani, A., Shazeer, N., Parmar, N., Uszkoreit, J., Jones, L., Gomez, A. N., Kaiser, Ł., & Polosukhin, I. (2017). Attention Is All You Need. Advances in Neural Information Processing Systems, 30. https://proceedings.neurips.cc/paper/2017/hash/3f5ee243547dee91fbd053c1c4a845aa-Abstract.html\n2. Brown, T. B., Mann, B., Ryder, N., Subbiah, M., Kaplan, J., Dhariwal, P., ... & Amodei, D. (2020). Language Models are Few-Shot Learners. Advances in Neural Information Processing Systems, 33. https://proceedings.neurips.cc/paper/2020/hash/1457c0d6bfcb4967418bfb8ac142f64a-Abstract.html\n3. Heckelmann, P. (2025). Investigation of different LSTM-based encoder-decoder architectures for vehicle speed prediction. Scientific Reports, 15(1), 19592. https://doi.org/10.1038/s41598-025-19592-5\n\n\n## Metadata\n\n- **Last Updated**: 2025-11-11\n- **Review Status**: Comprehensive editorial review\n- **Verification**: Academic sources verified\n- **Regional Context**: UK/North England where applicable",
  "properties": {
    "id": "decoder-ontology",
    "collapsed": "true",
    "- ontology": "true",
    "- term-id": "AI-0206",
    "- preferred-term": "Decoder",
    "- source-domain": "ai",
    "- status": "draft",
    "- public-access": "true",
    "- definition": "The component in an encoder-decoder architecture that generates the output sequence autoregressively, using masked self-attention, cross-attention to encoder outputs, and feed-forward layers."
  },
  "backlinks": [
    "Variational Autoencoders"
  ],
  "wiki_links": [],
  "ontology": {
    "term_id": "AI-0206",
    "preferred_term": "Decoder",
    "definition": "The component in an encoder-decoder architecture that generates the output sequence autoregressively, using masked self-attention, cross-attention to encoder outputs, and feed-forward layers.",
    "source_domain": "ai",
    "maturity_level": null,
    "authority_score": null
  }
}