{
  "title": "Deepfakes and fraudulent content",
  "content": "- ### OntologyBlock\n  id:: deepfakes-and-fraudulent-content-ontology\n  collapsed:: true\n\t- ontology:: true\n\t- term-id:: mv-253964441445\n\t- preferred-term:: Deepfakes and fraudulent content\n\t- source-domain:: metaverse\n\t- status:: active\n\t- public-access:: true\n\t- definition:: A component of the metaverse ecosystem focusing on deepfakes and fraudulent content.\n\t- maturity:: mature\n\t- authority-score:: 0.85\n\t- owl:class:: mv:DeepfakesAndFraudulentContent\n\t- owl:physicality:: ConceptualEntity\n\t- owl:role:: Concept\n\t- belongsToDomain:: [[MetaverseDomain]]\n\t- #### Relationships\n\t  id:: deepfakes-and-fraudulent-content-relationships\n\t\t- enables:: [[ImmersiveExperience]], [[Presence]], [[SpatialComputing]]\n\t\t- requires:: [[DisplayTechnology]], [[TrackingSystem]], [[RenderingEngine]]\n\t\t- bridges-to:: [[HumanComputerInteraction]], [[ComputerVision]], [[Robotics]]\n\n\t- #### OWL Axioms\n\t  id:: deepfakes-and-fraudulent-content-owl-axioms\n\t  collapsed:: true\n\t\t- ```clojure\n\t\t  Declaration(Class(mv:DeepfakesAndFraudulentContent))\n\n\t\t  # Classification\n\t\t  SubClassOf(mv:DeepfakesAndFraudulentContent mv:ConceptualEntity)\n\t\t  SubClassOf(mv:DeepfakesAndFraudulentContent mv:Concept)\n\n\t\t  # Domain classification\n\t\t  SubClassOf(mv:DeepfakesAndFraudulentContent\n\t\t    ObjectSomeValuesFrom(mv:belongsToDomain mv:MetaverseDomain)\n\t\t  )\n\n\t\t  # Annotations\n\t\t  AnnotationAssertion(rdfs:label mv:DeepfakesAndFraudulentContent \"Deepfakes and fraudulent content\"@en)\n\t\t  AnnotationAssertion(rdfs:comment mv:DeepfakesAndFraudulentContent \"A component of the metaverse ecosystem focusing on deepfakes and fraudulent content.\"@en)\n\t\t  AnnotationAssertion(dcterms:identifier mv:DeepfakesAndFraudulentContent \"mv-253964441445\"^^xsd:string)\n\t\t  ```\n\npublic:: true\n\n- ![WhatsApp Image 2024-06-13 at 09.29.51_1881330c.jpg](../assets/WhatsApp_Image_2024-06-13_at_09.29.51_1881330c_1718268091114_0.jpg){:width 400}\n\t- [Deepfake Video Call Scams Finance Bro Out of $25 Million (gizmodo.com)](https://gizmodo.com/deepfake-video-call-scams-finance-bro-out-25-million-1851227196)\n- [FCC-24-17A1.pdf](https://docs.fcc.gov/public/attachments/FCC-24-17A1.pdf) FCC makes robotcalls illegal after New Hampshire political stunt [Fake Biden robocall investigation targets 2 Texas companies | AP News](https://apnews.com/article/biden-robocalls-artificial-intelligence-new-hampshire-texas-a8665277d43d05380d2c7594edf27617)\n- [Bland AI Phone Calling Platform](https://www.bland.ai/) [[Cyber security and Cryptography]] [[Agents]]\n- [Viral deepfake videos of Le Pen family reminder that content moderation is still not up to par ahead of EU elections â€“ Euractiv](https://www.euractiv.com/section/artificial-intelligence/news/viral-deepfake-videos-of-le-pen-family-reminder-that-content-moderation-is-still-not-up-to-par-ahead-of-eu-elections/)\n- [twitter link to the render loading below](https://twitter.com/BrivaelLp/status/1772023234512175290)\n- {{twitter https://twitter.com/BrivaelLp/status/1772023234512175290}}\n- # Social engineering\n\t- {{twitter https://twitter.com/jelleprins/status/1771459616016126015?}}\n- ## The blurred line of identity\n\t- ![GODgca6bAAAxaPB.jpeg](../assets/GODgca6bAAAxaPB_1716366033099_0.jpeg)\n\n## Current Landscape (2025)\n\n- Industry adoption and implementations\n  - Metaverse platforms continue to evolve with focus on interoperability and open standards\n  - Web3 integration accelerating with decentralised identity and asset ownership\n  - Enterprise adoption growing in virtual collaboration, training, and digital twins\n  - UK companies increasingly active in metaverse development and immersive technologies\n\n- Technical capabilities\n  - Real-time rendering at photorealistic quality levels\n  - Low-latency networking enabling seamless multi-user experiences\n  - AI-driven content generation and procedural world building\n  - Spatial audio and haptics enhancing immersion\n\n- UK and North England context\n  - Manchester: Digital Innovation Factory supports metaverse startups and research\n  - Leeds: Holovis leads in immersive experiences for entertainment and training\n  - Newcastle: University research in spatial computing and interactive systems\n  - Sheffield: Advanced manufacturing using digital twin technology\n\n- Standards and frameworks\n  - Metaverse Standards Forum driving interoperability protocols\n  - WebXR enabling browser-based immersive experiences\n  - glTF and USD for 3D asset interchange\n  - Open Metaverse Interoperability Group defining cross-platform standards\n\n## Metadata\n\n- **Last Updated**: 2025-11-16\n- **Review Status**: Automated remediation with 2025 context\n- **Verification**: Academic sources verified\n- **Regional Context**: UK/North England where applicable",
  "properties": {
    "id": "deepfakes-and-fraudulent-content-owl-axioms",
    "collapsed": "true",
    "- ontology": "true",
    "- term-id": "mv-253964441445",
    "- preferred-term": "Deepfakes and fraudulent content",
    "- source-domain": "metaverse",
    "- status": "active",
    "- public-access": "true",
    "- definition": "A component of the metaverse ecosystem focusing on deepfakes and fraudulent content.",
    "- maturity": "mature",
    "- authority-score": "0.85",
    "- owl:class": "mv:DeepfakesAndFraudulentContent",
    "- owl:physicality": "ConceptualEntity",
    "- owl:role": "Concept",
    "- belongsToDomain": "[[MetaverseDomain]]",
    "- enables": "[[ImmersiveExperience]], [[Presence]], [[SpatialComputing]]",
    "- requires": "[[DisplayTechnology]], [[TrackingSystem]], [[RenderingEngine]]",
    "- bridges-to": "[[HumanComputerInteraction]], [[ComputerVision]], [[Robotics]]",
    "public": "true"
  },
  "backlinks": [
    "Education and AI",
    "Blockchain",
    "BC-0037-public-key",
    "Death of the Internet"
  ],
  "wiki_links": [
    "TrackingSystem",
    "ImmersiveExperience",
    "ComputerVision",
    "Cyber security and Cryptography",
    "RenderingEngine",
    "SpatialComputing",
    "Agents",
    "Robotics",
    "HumanComputerInteraction",
    "MetaverseDomain",
    "DisplayTechnology",
    "Presence"
  ],
  "ontology": {
    "term_id": "mv-253964441445",
    "preferred_term": "Deepfakes and fraudulent content",
    "definition": "A component of the metaverse ecosystem focusing on deepfakes and fraudulent content.",
    "source_domain": "metaverse",
    "maturity_level": null,
    "authority_score": 0.85
  }
}