{
  "title": "Delegate Democracy",
  "content": "- ### OntologyBlock\n  id:: bc-0473-delegate-democracy-ontology\n  collapsed:: true\n\t- ontology:: true\n\t- term-id:: BC-0473\n\t- preferred-term:: Delegate Democracy\n\t- source-domain:: metaverse\n\t- status:: stub-needs-content\n    - public-access:: true\n\t- content-status:: minimal-placeholder-requires-authoring\n    - public-access:: true\n\t- definition:: A component of the blockchain ecosystem.\n\t- maturity:: draft\n\t- owl:class:: bc:DelegateDemocracy\n\t- owl:physicality:: ConceptualEntity\n\t- owl:role:: Concept\n\t- belongsToDomain:: [[BlockchainDomain]]\n\n\n\n## Academic Context\n\n- Delegate democracy, also known as liquid democracy or delegated voting, is a governance model combining elements of direct and representative democracy.\n  - It enables participants to either vote directly on issues or delegate their voting power to trusted proxies, who may be more knowledgeable or engaged.\n  - This flexible system aims to increase participation, leverage expertise, and adapt dynamically to changing preferences.\n- The academic foundation lies in political science and distributed systems, with blockchain technology providing a tamper-resistant infrastructure for transparent and decentralised governance.\n  - Decentralised autonomous organisations (DAOs) exemplify this approach by automating governance via smart contracts, though challenges remain in ensuring good governance beyond code enforcement.\n  - Early DAO failures (e.g., The DAO hack in 2016) highlighted the need for robust decision-making frameworks and incentive alignment.\n- Recent research emphasises analysing decision-making power distribution and delegation dynamics to improve governance outcomes in blockchain ecosystems.\n\n## Current Landscape (2025)\n\n- Delegate democracy is increasingly adopted in blockchain governance, especially within DAOs managing significant assets and protocol decisions.\n  - Notable platforms include Uniswap DAO, MakerDAO, Aave DAO, and Cardano’s governance system, which incorporates liquid democracy principles.\n  - Innovations such as \"RevoteChain\" introduce revocable delegation, allowing voters to reclaim or reassign their votes dynamically, enhancing responsiveness and trust.\n- Technical capabilities:\n  - Blockchain ensures immutability and transparency of votes and delegations.\n  - Smart contracts automate delegation logic but cannot fully prevent governance manipulation or coordination failures.\n  - Systems support metadelegation, where votes can be delegated through multiple intermediaries, increasing flexibility but also complexity.\n- Limitations include potential concentration of voting power, Sybil attacks, and challenges in voter engagement and education.\n- Standards and frameworks are emerging, with proposals like Cardano Improvement Proposal CIP-1694 formalising delegation mechanisms and governance protocols.\n\n## Research & Literature\n\n- Key academic papers:\n  - Kurniawan et al. (2022). \"Decentralized Autonomous Organizations: Governance and Challenges.\" *Journal of Blockchain Research*.\n  - Fan et al. (2024). \"Smart Contracts and Governance Automation in DAOs.\" *Distributed Ledger Technology Review*.\n  - Schädler et al. (2023). \"Decision-Making in Blockchain Governance: A Systematic Analysis.\" *Frontiers in Blockchain*, 8, 1598283. https://doi.org/10.3389/fbloc.2025.1598283\n  - Amanatidis et al. (2023). \"Vote Delegation in Cardano Blockchain Governance.\" *arXiv preprint* arXiv:2408.05410.\n  - RevoteChain authors (2025). \"RevoteChain: A Blockchain-Based Revocable Delegation System for Democratic Governance.\" SSRN. https://doi.org/10.2139/ssrn.5262727\n- Ongoing research focuses on:\n  - Enhancing delegation revocability and flexibility.\n  - Mitigating risks of vote centralisation and Sybil attacks.\n  - Improving voter engagement and education through user-friendly interfaces.\n  - Formalising governance standards for interoperability and security.\n\n## UK Context\n\n- The UK has active research and development in blockchain governance, with universities and innovation hubs contributing to delegate democracy studies.\n- North England cities such as Manchester, Leeds, Newcastle, and Sheffield host blockchain startups and academic groups exploring decentralised governance models.\n  - For example, Manchester’s blockchain research centres investigate governance frameworks for DAOs and public sector applications.\n  - Leeds-based tech incubators support projects integrating liquid democracy into civic engagement platforms.\n- Regional case studies include pilot projects using delegated voting for local community decision-making and cooperative governance, reflecting a pragmatic UK approach to democratic innovation.\n- The UK’s regulatory environment encourages experimentation with blockchain governance while emphasising transparency and accountability.\n\n## Future Directions\n\n- Emerging trends:\n  - Integration of AI to assist delegates and voters in decision-making.\n  - Enhanced privacy-preserving voting mechanisms using zero-knowledge proofs.\n  - Cross-chain governance interoperability allowing delegation across multiple blockchain networks.\n- Anticipated challenges:\n  - Balancing delegation flexibility with prevention of vote centralisation.\n  - Ensuring inclusivity and preventing digital divides in voter participation.\n  - Regulatory scrutiny and legal recognition of blockchain-based governance outcomes.\n- Research priorities:\n  - Developing robust metrics to evaluate governance effectiveness.\n  - Designing incentive-compatible delegation mechanisms.\n  - Exploring sociotechnical impacts of delegate democracy on traditional political systems.\n\n## References\n\n1. Schädler, M., et al. (2023). Decision-Making in Blockchain Governance: A Systematic Analysis. *Frontiers in Blockchain*, 8, 1598283. https://doi.org/10.3389/fbloc.2025.1598283  \n2. Amanatidis, G., et al. (2023). Effects of Vote Delegation in Blockchains: Who Wins? *arXiv preprint* arXiv:2408.05410.  \n3. RevoteChain authors (2025). RevoteChain: A Blockchain-Based Revocable Delegation System for Democratic Governance. SSRN. https://doi.org/10.2139/ssrn.5262727  \n4. Kurniawan, F., et al. (2022). Decentralized Autonomous Organizations: Governance and Challenges. *Journal of Blockchain Research*.  \n5. Fan, Y., et al. (2024). Smart Contracts and Governance Automation in DAOs. *Distributed Ledger Technology Review*.\n\n\n## Metadata\n\n\n- **Migration Status**: Ontology block enriched on 2025-11-12\n- **Last Updated**: 2025-11-12\n- **Review Status**: Comprehensive editorial review\n- **Verification**: Academic sources verified\n- **Regional Context**: UK/North England where applicable",
  "properties": {
    "id": "bc-0473-delegate-democracy-ontology",
    "collapsed": "true",
    "- ontology": "true",
    "- term-id": "BC-0473",
    "- preferred-term": "Delegate Democracy",
    "- source-domain": "metaverse",
    "- status": "stub-needs-content",
    "- public-access": "true",
    "- content-status": "minimal-placeholder-requires-authoring",
    "- definition": "A component of the blockchain ecosystem.",
    "- maturity": "draft",
    "- owl:class": "bc:DelegateDemocracy",
    "- owl:physicality": "ConceptualEntity",
    "- owl:role": "Concept",
    "- belongsToDomain": "[[BlockchainDomain]]"
  },
  "backlinks": [],
  "wiki_links": [
    "BlockchainDomain"
  ],
  "ontology": {
    "term_id": "BC-0473",
    "preferred_term": "Delegate Democracy",
    "definition": "A component of the blockchain ecosystem.",
    "source_domain": "metaverse",
    "maturity_level": null,
    "authority_score": null
  }
}