{
  "title": "Democratic Values",
  "content": "- ### OntologyBlock\n  id:: democratic-values-ontology\n  collapsed:: true\n\t- ontology:: true\n\t- term-id:: AI-0167\n\t- preferred-term:: Democratic Values\n\t- source-domain:: ai\n\t- status:: draft\n    - public-access:: true\n\t- definition:: Principles and practices of democratic governance including pluralism, participatory decision-making, transparent governance, electoral integrity, free formation of political will and protection of civic space, which AI systems should respect and strengthen rather than undermine.\n\n\n\n# Democratic Values – Updated Ontology Entry\n\n## Academic Context\n\n- Foundational principles underpinning democratic systems\n  - Democratic values constitute the normative bedrock upon which legitimate governance rests, encompassing equality, freedom, justice, and meaningful participation[5]\n  - These principles extend beyond electoral mechanics to encompass substantive commitments to human dignity, accountability, and collective self-determination\n  - The concept has evolved from classical liberal theory through contemporary deliberative democracy frameworks, now increasingly intersecting with technology governance and artificial intelligence ethics\n\n- Historical development and contemporary relevance\n  - Originally articulated through Enlightenment philosophy and codified in instruments such as the Universal Declaration of Human Rights\n  - Contemporary scholarship emphasises the fragility of democratic institutions, particularly in contexts of authoritarian resurgence and democratic backsliding observed over recent decades[2]\n  - The relationship between democratic values and institutional resilience has become increasingly salient as democracies face novel challenges from digital disinformation, erosion of civic space, and institutional capture\n\n## Current Landscape (2025)\n\n- Core democratic values framework\n  - Rule of law and judicial independence\n    - Foundational to democratic legitimacy; enables accountability mechanisms and protects minority rights\n    - Increasingly threatened by executive overreach and politicisation of judiciaries globally\n  - Electoral integrity and universal suffrage\n    - Periodic, genuine elections conducted by universal suffrage remain essential elements of democratic legitimacy[1]\n    - Contemporary challenges include voter suppression, gerrymandering, and foreign interference in electoral processes\n  - Freedom of expression and independent media\n    - Critical for informed citizenry and government accountability\n    - Facing unprecedented pressure from digital surveillance, algorithmic amplification of disinformation, and state censorship\n  - Transparency and open governance\n    - Essential for public trust and corruption prevention[10]\n    - Tension between transparency imperatives and legitimate privacy protections (e.g., beneficial ownership registers) requires careful calibration\n  - Civic participation and inclusion\n    - Democratic legitimacy requires meaningful opportunities for citizens to shape policies affecting their lives[10]\n    - Inclusion mechanisms must actively address systemic barriers and foster engagement across diverse communities\n\n- Corruption as democratic corrosive\n  - Corruption fundamentally undermines the principle of equal treatment, affording selective benefits to those circumventing rules rather than following them[10]\n  - Reinforcing democratic values provides essential mechanisms for corruption control; conversely, anticorruption campaigns risk weaponisation as tools for political repression if divorced from democratic safeguards[10]\n\n- UK and North England context\n  - British democratic institutions face contemporary pressures including parliamentary sovereignty questions, devolution tensions, and erosion of civic participation in post-industrial regions\n  - North England innovation hubs (Manchester, Leeds, Newcastle, Sheffield) increasingly engage with democratic technology and civic engagement initiatives, though systematic documentation remains limited\n  - Regional variations in democratic participation and institutional trust warrant closer examination, particularly in areas experiencing economic transition\n\n- AI systems and democratic values\n  - Artificial intelligence systems must be designed to respect and strengthen democratic values rather than undermine them\n  - Specific concerns include algorithmic amplification of disinformation, automated decision-making lacking transparency, and concentration of technological power in ways that erode civic agency\n\n## Research & Literature\n\n- Foundational frameworks\n  - Eisen, N., Feldman, M., & Harwood, R. (2025). *Democracy Playbook 2025: 7 Pillars to Defend Democracy in 2025 and Beyond*. Brookings Institution. [Identifies seven foundational pillars including protection of elections, rule of law, and corruption prevention][2]\n  - International IDEA. *State Democracy Framework: Principles and Mediating Values*. Provides comprehensive framework anchoring democracy assessment in clear principles and mediating values[9]\n\n- Democratic values and governance\n  - United Nations. *Global Issues: Democracy*. Emphasises freedom, human rights respect, and periodic genuine elections as essential democratic elements[1]\n  - World Bank Governance Programme. (2024). \"Democratic Values and Corruption.\" *World Bank Blogs*. Explores interconnections between democratic value reinforcement and corruption control mechanisms[10]\n\n- Civic participation and inclusion\n  - Fiveable. *Democratic Values (Curriculum Development)*. Defines democratic values as principles upholding democratic society—equality, freedom, justice, participation—emphasising individual rights, responsibilities, and collective decision-making[5]\n\n- Ongoing research directions\n  - Intersection of democratic values with digital governance and artificial intelligence ethics\n  - Regional variations in democratic resilience and institutional trust, particularly in post-industrial economies\n  - Mechanisms for strengthening civic participation whilst maintaining security and privacy protections\n  - Relationship between transparency imperatives and legitimate privacy rights in contemporary governance\n\n## UK Context\n\n- British democratic traditions and contemporary challenges\n  - Westminster parliamentary democracy represents one of the world's oldest continuous democratic systems, yet faces contemporary pressures including parliamentary sovereignty questions, devolution complexities, and erosion of civic participation\n  - Recent years have witnessed heightened concerns regarding judicial independence, media plurality, and electoral integrity\n\n- North England regional considerations\n  - Post-industrial regions in North England (Manchester, Leeds, Newcastle, Sheffield) demonstrate variable levels of civic engagement and institutional trust\n  - Emerging civic technology initiatives and democratic participation experiments warrant systematic documentation and evaluation\n  - Regional economic transition creates both challenges and opportunities for democratic renewal and community-led governance\n\n- British contributions to democratic values discourse\n  - UK institutions contribute significantly to global democratic governance frameworks, though domestic implementation faces persistent challenges\n  - Civil society organisations across North England increasingly engage with democratic resilience and civic participation initiatives\n\n## Future Directions\n\n- Emerging challenges and opportunities\n  - Digital governance and algorithmic accountability\n    - Ensuring AI systems respect democratic values requires robust transparency mechanisms, meaningful human oversight, and protection against automated decision-making that erodes civic agency\n    - Balancing innovation with democratic safeguards remains an unresolved tension\n  - Civic space and participation\n    - Shrinking civic space in many democracies necessitates renewed commitment to protecting freedom of association, expression, and assembly\n    - Digital platforms present both opportunities for democratic participation and risks of manipulation and surveillance\n  - Democratic resilience in contexts of authoritarian pressure\n    - Strengthening institutional safeguards against executive overreach and democratic backsliding\n    - Supporting civil society and independent media in hostile environments\n\n- Research priorities\n  - Mechanisms for integrating democratic values into AI system design and deployment\n  - Regional analysis of democratic resilience, particularly in post-industrial economies\n  - Relationship between transparency, privacy, and democratic accountability in digital governance\n  - Effectiveness of democratic values reinforcement in corruption prevention and institutional trust-building\n\n## References\n\n- Eisen, N., Feldman, M., & Harwood, R. (2025). *Democracy Playbook 2025: 7 Pillars to Defend Democracy in 2025 and Beyond*. Brookings Institution.[2]\n- Fiveable. *Democratic Values (Curriculum Development)*. Curriculum Development Key Terms.[5]\n- International IDEA. *State Democracy Framework: Principles and Mediating Values*. Available at: https://www.idea.int/data-tools/tools/state-democracy-assessments/state-democracy-framework/principles-and-mediating-values[9]\n- United Nations. *Global Issues: Democracy*. Available at: https://www.un.org/en/global-issues/democracy[1]\n- World Bank Governance Programme. (2024). \"Democratic Values and Corruption.\" *World Bank Blogs*. Available at: https://blogs.worldbank.org/en/governance/democratic-values-and-corruption[10]\n\n\n## Metadata\n\n- **Last Updated**: 2025-11-11\n- **Review Status**: Comprehensive editorial review\n- **Verification**: Academic sources verified\n- **Regional Context**: UK/North England where applicable",
  "properties": {
    "id": "democratic-values-ontology",
    "collapsed": "true",
    "- ontology": "true",
    "- term-id": "AI-0167",
    "- preferred-term": "Democratic Values",
    "- source-domain": "ai",
    "- status": "draft",
    "- public-access": "true",
    "- definition": "Principles and practices of democratic governance including pluralism, participatory decision-making, transparent governance, electoral integrity, free formation of political will and protection of civic space, which AI systems should respect and strengthen rather than undermine."
  },
  "backlinks": [
    "Human-Rights",
    "AI Governance Principle"
  ],
  "wiki_links": [],
  "ontology": {
    "term_id": "AI-0167",
    "preferred_term": "Democratic Values",
    "definition": "Principles and practices of democratic governance including pluralism, participatory decision-making, transparent governance, electoral integrity, free formation of political will and protection of civic space, which AI systems should respect and strengthen rather than undermine.",
    "source_domain": "ai",
    "maturity_level": null,
    "authority_score": null
  }
}