{
  "title": "Deployer",
  "content": "- ### OntologyBlock\n  id:: deployer-ontology\n  collapsed:: true\n\t- ontology:: true\n\t- term-id:: mv-1761742247914\n\t- preferred-term:: Deployer\n\t- source-domain:: metaverse\n\t- status:: draft\n    - public-access:: true\n\t- definition:: A natural or legal person, public authority, agency or other body using an AI system under its authority except where the AI system is used in the course of a personal non-professional activity.\n\n\n\n## Academic Context\n\n- The concept of a \"deployer\" in AI governance originates from regulatory frameworks such as the EU Artificial Intelligence Act (AI Act), which distinguishes deployers from providers based on their role in the AI lifecycle.\n  - Deployers are defined as natural or legal persons, public authorities, agencies, or other bodies that use an AI system under their authority, excluding personal, non-professional use.\n  - This distinction is critical for assigning regulatory obligations, ensuring accountability for AI use beyond development or marketing.\n- The academic foundation for this role stems from legal and ethical scholarship on AI accountability, risk management, and human-centric AI governance.\n  - Key discussions focus on how deployers influence AI system outcomes through operational use, thus bearing responsibility for compliance with safety, transparency, and fairness standards.\n\n## Current Landscape (2025)\n\n- Industry adoption of the deployer role is widespread, especially in sectors with high AI integration such as healthcare, finance, and public administration.\n  - Notable organisations include multinational corporations, healthcare providers, and government agencies that deploy AI systems for decision-making, operational efficiency, or service delivery.\n  - In the UK, and particularly in North England cities like Manchester, Leeds, Newcastle, and Sheffield, AI deployment is prominent in smart city initiatives, healthcare innovation, and manufacturing automation.\n- Technical capabilities of deployers vary widely; while some have sophisticated AI governance frameworks, others are still developing compliance mechanisms.\n  - Limitations include challenges in understanding AI system behaviour, managing risks of bias or discrimination, and ensuring ongoing monitoring post-deployment.\n- Standards and frameworks guiding deployers include the EU AI Act (applicable in the UK context through retained EU law and alignment efforts), ISO standards on AI governance, and sector-specific guidelines.\n  - The AI Act’s obligations for deployers include risk assessment, transparency, human oversight, and post-market monitoring, especially for high-risk AI systems.\n\n## Research & Literature\n\n- Key academic papers and sources:\n  - Veale, M., & Borgesius, F. Z. (2021). *Demystifying the Draft EU Artificial Intelligence Act: Towards Trustworthy AI Regulation*. Computer Law & Security Review, 41, 105567. https://doi.org/10.1016/j.clsr.2021.105567\n  - Floridi, L., & Cowls, J. (2019). *A Unified Framework of Five Principles for AI in Society*. Harvard Data Science Review, 1(1). https://doi.org/10.1162/99608f92.8cd550d1\n  - European Commission (2024). *Guidelines on the AI System Definition*. Publications Office of the European Union. https://digital-strategy.ec.europa.eu/en/library/commission-publishes-guidelines-ai-system-definition-facilitate-first-ai-acts-rules-application\n- Ongoing research focuses on refining deployer responsibilities, improving AI system transparency, and developing tools for real-time risk mitigation during deployment.\n\n## UK Context\n\n- The UK has adopted a pragmatic approach to AI governance, aligning with EU standards while fostering innovation through regulatory sandboxes and sector-specific initiatives.\n- North England is a vibrant hub for AI deployment, with Manchester’s AI Foundry, Leeds’ digital health clusters, Newcastle’s AI research centres, and Sheffield’s advanced manufacturing AI applications leading regional innovation.\n- Regional case studies include:\n  - Manchester’s deployment of AI in urban traffic management systems, balancing efficiency with privacy concerns.\n  - Leeds’ NHS trusts integrating AI for patient data analysis under strict ethical oversight.\n  - Newcastle’s public sector use of AI for social services eligibility assessments, highlighting challenges in fairness and transparency.\n  - Sheffield’s manufacturing firms deploying AI-driven quality control systems, illustrating practical deployer responsibilities in industrial contexts.\n\n## Future Directions\n\n- Emerging trends include increased emphasis on continuous monitoring of AI systems post-deployment, dynamic risk assessment, and enhanced human-in-the-loop mechanisms.\n- Anticipated challenges involve managing the complexity of AI ecosystems where deployers may not fully control AI system design, necessitating clearer liability frameworks.\n- Research priorities focus on developing standardised deployer audit methodologies, improving explainability tools for deployed AI, and fostering cross-sector collaboration for best practices.\n\n## References\n\n1. Veale, M., & Borgesius, F. Z. (2021). Demystifying the Draft EU Artificial Intelligence Act: Towards Trustworthy AI Regulation. *Computer Law & Security Review*, 41, 105567. https://doi.org/10.1016/j.clsr.2021.105567  \n2. Floridi, L., & Cowls, J. (2019). A Unified Framework of Five Principles for AI in Society. *Harvard Data Science Review*, 1(1). https://doi.org/10.1162/99608f92.8cd550d1  \n3. European Commission. (2024). *Guidelines on the AI System Definition*. Publications Office of the European Union. Retrieved from https://digital-strategy.ec.europa.eu/en/library/commission-publishes-guidelines-ai-system-definition-facilitate-first-ai-acts-rules-application  \n4. A&O Shearman. (2024). Zooming in on AI – #4: What is the interplay between “Deployers” and “Providers” in the EU AI Act? Retrieved from https://www.aoshearman.com/en/insights/ao-shearman-on-tech/zooming-in-on-ai-4-what-is-the-interplay-between-deployers-and-providers-in-the-eu-ai-act  \n5. Osborne Clarke. (2024). EU AI Act's 'deployers' definition has wide-ranging significance for life sciences. Retrieved from https://www.osborneclarke.com/insights/eu-ai-acts-deployers-definition-has-wide-ranging-significance-life-sciences-2\n\n\n## Metadata\n\n- **Last Updated**: 2025-11-11\n- **Review Status**: Comprehensive editorial review\n- **Verification**: Academic sources verified\n- **Regional Context**: UK/North England where applicable",
  "properties": {
    "id": "deployer-ontology",
    "collapsed": "true",
    "- ontology": "true",
    "- term-id": "mv-1761742247914",
    "- preferred-term": "Deployer",
    "- source-domain": "metaverse",
    "- status": "draft",
    "- public-access": "true",
    "- definition": "A natural or legal person, public authority, agency or other body using an AI system under its authority except where the AI system is used in the course of a personal non-professional activity."
  },
  "backlinks": [],
  "wiki_links": [],
  "ontology": {
    "term_id": "mv-1761742247914",
    "preferred_term": "Deployer",
    "definition": "A natural or legal person, public authority, agency or other body using an AI system under its authority except where the AI system is used in the course of a personal non-professional activity.",
    "source_domain": "metaverse",
    "maturity_level": null,
    "authority_score": null
  }
}