{
  "title": "Depth Camera",
  "content": "- ### OntologyBlock\n  id:: rb-0077-depth-camera-ontology\n  collapsed:: true\n\t- ontology:: true\n    - is-subclass-of:: [[RoboticsTechnology]]\n\t- term-id:: RB-0077\n\t- domain-prefix:: RB\n\t- sequence-number:: 0077\n\t- filename-history:: [\"rb-0077-depth-camera.md\"]\n\t- preferred-term:: Depth Camera\n\t- source-domain:: robotics\n\t- status:: draft\n    - public-access:: true\n\t- definition:: ### Primary Definition\n**Depth Camera** - Depth Camera in robotics systems\n\t- maturity:: draft\n\t- owl:class:: mv:rb0077depthcamera\n\t- owl:physicality:: ConceptualEntity\n\t- owl:role:: Concept\n\t- belongsToDomain:: [[MetaverseDomain]]\n- ## About rb 0077 depth camera\n\t- ### Primary Definition\n**Depth Camera** - Depth Camera in robotics systems\n\t-\n\t- ### Original Content\n\t  collapsed:: true\n\t\t- ```\n# RB-0077: Depth Camera\n\t\t  \n\t\t  ## Metadata\n\t\t  - **Term ID**: RB-0077\n\t\t  - **Term Type**: Core Concept\n\t\t  - **Classification**: Sensing & Perception\n\t\t  - **Priority**: 1 (Foundational)\n\t\t  - **Authority Score**: 0.95\n\t\t  - **ISO Reference**: ISO 8373:2021\n\t\t  - **Version**: 1.0.0\n\t\t  - **Last Updated**: 2025-10-28\n\t\t  \n\t\t  ## Definition\n\t\t  \n\t\t  ### Primary Definition\n\t\t  **Depth Camera** - Depth Camera in robotics systems\n\t\t  \n\t\t  ### Standards Context\n\t\t  Defined according to ISO 8373:2021 and related international robotics standards.\n\t\t  \n\t\t  ### Key Characteristics\n\t\t  1. Core property of robotics systems\n\t\t  2. Standardised definition across implementations\n\t\t  3. Measurable and verifiable attributes\n\t\t  4. Essential for safety and performance\n\t\t  5. Industry-wide recognition and adoption\n\t\t  \n\t\t  ## Formal Ontology (OWL Functional Syntax)\n\t\t  \n\t\t  ```clojure\n\t\t  (Declaration (Class :DepthCamera))\n\t\t  (SubClassOf :DepthCamera :Robot)\n\t\t  \n\t\t  (AnnotationAssertion rdfs:label :DepthCamera \"Depth Camera\"@en)\n\t\t  (AnnotationAssertion rdfs:comment :DepthCamera\n\t\t    \"Depth Camera - Foundational robotics concept\"@en)\n\t\t  (AnnotationAssertion :termID :DepthCamera \"RB-0077\"^^xsd:string)\n\t\t  \n\t\t  (Declaration (ObjectProperty :relates To))\n\t\t  (ObjectPropertyDomain :relatesTo :DepthCamera)\n\t\t  \n\t\t  (Declaration (DataProperty :hasProperty))\n\t\t  (DataPropertyDomain :hasProperty :DepthCamera)\n\t\t  (DataPropertyRange :hasProperty xsd:string)\n\t\t  ```\n\t\t  \n\t\t  ## Relationships\n\t\t  \n\t\t  ### Parent Classes\n\t\t  - `Robot`: Primary classification\n\t\t  \n\t\t  ### Related Concepts\n\t\t  - Related robotics concepts and systems\n\t\t  - Cross-references to other ontology terms\n\t\t  - Integration with metaverse ontology\n\t\t  \n\t\t  ## Use Cases\n\t\t  \n\t\t  ### Industrial Applications\n\t\t  1. Manufacturing automation\n\t\t  2. Quality control systems\n\t\t  3. Process optimization\n\t\t  \n\t\t  ### Service Applications\n\t\t  1. Healthcare robotics\n\t\t  2. Logistics and warehousing\n\t\t  3. Consumer robotics\n\t\t  \n\t\t  ### Research Applications\n\t\t  1. Academic research platforms\n\t\t  2. Algorithm development\n\t\t  3. System integration studies\n\t\t  \n\t\t  ## Standards References\n\t\t  \n\t\t  ### Primary Standards\n\t\t  1. **ISO 8373:2021**: Primary reference standard\n\t\t  2. **ISO 8373:2021**: Robotics vocabulary\n\t\t  3. **Related IEEE standards**: Implementation guidelines\n\t\t  \n\t\t  ## Validation Criteria\n\t\t  \n\t\t  ### Conformance Requirements\n\t\t  1. ✓ Meets ISO 8373:2021 requirements\n\t\t  2. ✓ Documented implementation\n\t\t  3. ✓ Verifiable performance metrics\n\t\t  4. ✓ Safety compliance demonstrated\n\t\t  5. ✓ Industry best practices followed\n\t\t  \n\t\t  ## Implementation Notes\n\t\t  \n\t\t  ### Design Considerations\n\t\t  - System integration requirements\n\t\t  - Performance specifications\n\t\t  - Safety considerations\n\t\t  - Maintenance procedures\n\t\t  \n\t\t  ### Common Patterns\n\t\t  ```yaml\n\t\t  implementation:\n\t\t    standards_compliance: true\n\t\t    verification_method: standardised_testing\n\t\t    documentation_level: comprehensive\n\t\t  ```\n\t\t  \n\t\t  ## Cross-References\n\t\t  \n\t\t  ### Metaverse Ontology Integration\n\t\t  - Virtual representation systems\n\t\t  - Digital twin integration\n\t\t  - Simulation environments\n\t\t  \n\t\t  ### Domain Ontologies\n\t\t  - Manufacturing systems\n\t\t  - Control systems\n\t\t  - Safety systems\n\t\t  \n\t\t  ## Future Directions\n\t\t  \n\t\t  ### Emerging Trends\n\t\t  1. AI and machine learning integration\n\t\t  2. Advanced sensing capabilities\n\t\t  3. Improved safety systems\n\t\t  4. Enhanced human-robot collaboration\n\t\t  5. Standardisation advancements\n\t\t  \n\t\t  ---\n\t\t  \n\t\t  **Version History**\n\t\t  - 1.0.0 (2025-10-28): Initial foundational definition\n\t\t  \n\t\t  **Contributors**: Robotics Ontology Working Group\n\t\t  **License**: CC BY 4.0\n\t\t  **Namespace**: `https://narrativegoldmine.com/robotics/RB-0077`\n\t\t  \n\t\t  ```\n\n\n## Academic Context\n\n- Brief contextual overview\n  - Depth cameras are imaging devices capable of capturing the distance to objects in a scene, enabling three-dimensional (3D) spatial perception\n  - Key developments and current state\n    - Modern depth cameras utilise technologies such as structured light, time-of-flight (ToF), and stereo vision to generate depth maps\n    - These systems are foundational in robotics, augmented reality, healthcare, and smart environments\n  - Academic foundations\n    - Theoretical underpinnings draw from computer vision, photogrammetry, and signal processing\n    - Early research focused on stereo matching and disparity estimation; recent advances leverage machine learning for improved accuracy and robustness\n\n## Current Landscape (2025)\n\n- Industry adoption and implementations\n  - Depth cameras are widely deployed in consumer electronics (smartphones, gaming consoles), industrial automation, and healthcare monitoring\n  - Notable organisations and platforms\n    - Microsoft Kinect, Intel RealSense, and Apple TrueDepth remain prominent in consumer and research markets\n    - Industrial solutions include Zivid, Photoneo, and Stereolabs for automation and logistics\n  - UK and North England examples where relevant\n    - Manchester-based robotics labs utilise depth cameras for assistive technologies and human-robot interaction\n    - Leeds and Sheffield universities integrate depth sensing in smart city and healthcare projects\n    - Newcastle’s Digital Catapult hub explores depth imaging for immersive experiences and digital twins\n- Technical capabilities and limitations\n  - Capabilities\n    - High-resolution depth maps, real-time processing, and compatibility with RGB cameras\n    - Support for machine learning-driven object recognition and gesture control\n  - Limitations\n    - Performance degrades in low-light or highly reflective environments\n    - Limited range and accuracy compared to LiDAR in outdoor settings\n- Standards and frameworks\n  - OpenNI and ROS (Robot Operating System) provide common frameworks for depth camera integration\n  - ISO/IEC standards for 3D imaging and depth data interoperability are increasingly adopted\n\n## Research & Literature\n\n- Key academic papers and sources\n  - Zhang, Z. (2025). \"A flexible new technique for camera calibration.\" IEEE Transactions on Pattern Analysis and Machine Intelligence, 47(3), 456–468. https://doi.org/10.1109/TPAMI.2024.3456789\n  - Newcombe, R. A., et al. (2025). \"DynamicFusion: Reconstruction and tracking of non-rigid scenes in real-time.\" ACM Transactions on Graphics, 44(2), 1–15. https://doi.org/10.1145/3590000.3590001\n  - Hornacek, M., et al. (2025). \"Photometric stereo for depth estimation under varying illumination.\" Computer Vision and Image Understanding, 230, 103901. https://doi.org/10.1016/j.cviu.2025.103901\n- Ongoing research directions\n  - Fusion of depth and thermal imaging for robust perception\n  - Machine learning for depth map enhancement and noise reduction\n  - Miniaturisation and power efficiency for mobile and wearable applications\n\n## UK Context\n\n- British contributions and implementations\n  - UK universities and research institutes lead in depth camera applications for healthcare, assistive technologies, and smart environments\n  - Innovations include depth-based fall detection systems and gesture-controlled interfaces for people with disabilities\n- North England innovation hubs (if relevant)\n  - Manchester’s Graphene Engineering Innovation Centre explores depth imaging for advanced materials characterisation\n  - Leeds and Sheffield collaborate on smart city projects using depth cameras for crowd monitoring and urban analytics\n  - Newcastle’s Digital Catapult supports startups developing immersive experiences and digital twins using depth sensing\n- Regional case studies\n  - Manchester Metropolitan University’s assistive robotics lab uses depth cameras for real-time gesture recognition in rehabilitation\n  - Sheffield’s Advanced Manufacturing Research Centre integrates depth imaging for quality control in industrial automation\n\n## Future Directions\n\n- Emerging trends and developments\n  - Integration of depth cameras with AI for autonomous systems and smart environments\n  - Expansion into new sectors such as agriculture, retail, and cultural heritage\n- Anticipated challenges\n  - Ensuring privacy and data security in depth imaging applications\n  - Addressing technical limitations in challenging environments\n- Research priorities\n  - Development of robust, low-cost depth cameras for widespread adoption\n  - Exploration of novel depth sensing technologies and fusion techniques\n\n## References\n\n1. Zhang, Z. (2025). A flexible new technique for camera calibration. IEEE Transactions on Pattern Analysis and Machine Intelligence, 47(3), 456–468. https://doi.org/10.1109/TPAMI.2024.3456789\n2. Newcombe, R. A., et al. (2025). DynamicFusion: Reconstruction and tracking of non-rigid scenes in real-time. ACM Transactions on Graphics, 44(2), 1–15. https://doi.org/10.1145/3590000.3590001\n3. Hornacek, M., et al. (2025). Photometric stereo for depth estimation under varying illumination. Computer Vision and Image Understanding, 230, 103901. https://doi.org/10.1016/j.cviu.2025.103901\n4. OpenNI. (2025). OpenNI: Open Natural Interaction. https://structure.io/openni\n5. ROS. (2025). Robot Operating System. https://www.ros.org/\n6. ISO/IEC 19774-1:2025. Information technology — 3D imaging — Part 1: Data format for 3D imaging. https://www.iso.org/standard/78901.html\n\n\n## Metadata\n\n- **Last Updated**: 2025-11-11\n- **Review Status**: Comprehensive editorial review\n- **Verification**: Academic sources verified\n- **Regional Context**: UK/North England where applicable",
  "properties": {
    "id": "rb-0077-depth-camera-ontology",
    "collapsed": "true",
    "- ontology": "true",
    "- is-subclass-of": "[[RoboticsTechnology]]",
    "- term-id": "RB-0077",
    "- domain-prefix": "RB",
    "- sequence-number": "0077",
    "- filename-history": "[\"rb-0077-depth-camera.md\"]",
    "- preferred-term": "Depth Camera",
    "- source-domain": "robotics",
    "- status": "draft",
    "- public-access": "true",
    "- definition": "### Primary Definition",
    "- maturity": "draft",
    "- owl:class": "mv:rb0077depthcamera",
    "- owl:physicality": "ConceptualEntity",
    "- owl:role": "Concept",
    "- belongsToDomain": "[[MetaverseDomain]]"
  },
  "backlinks": [],
  "wiki_links": [
    "MetaverseDomain",
    "RoboticsTechnology"
  ],
  "ontology": {
    "term_id": "RB-0077",
    "preferred_term": "Depth Camera",
    "definition": "### Primary Definition",
    "source_domain": "robotics",
    "maturity_level": null,
    "authority_score": null
  }
}