{
  "title": "Difficulty Adjustment",
  "content": "- ### OntologyBlock\n  id:: difficulty-adjustment-ontology\n  collapsed:: true\n\n  - **Identification**\n\n    - domain-prefix:: BC\n\n    - sequence-number:: 0056\n\n    - filename-history:: [\"BC-0056-difficulty-adjustment.md\"]\n    - public-access:: true\n    - ontology:: true\n    - term-id:: BC-0056\n    - preferred-term:: Difficulty Adjustment\n    - source-domain:: blockchain\n    - status:: complete\n    - version:: 1.0.0\n    - last-updated:: 2025-10-28\n\n  - **Definition**\n    - definition:: Mining difficulty recalibration within blockchain systems, providing essential functionality for distributed ledger technology operations and properties.\n    - maturity:: mature\n    - source:: [[ISO/IEC 23257:2021]], [[IEEE 2418.1]], [[NIST NISTIR]]\n    - authority-score:: 0.95\n\n  - **Semantic Classification**\n    - owl:class:: bc:DifficultyAdjustment\n    - owl:physicality:: VirtualEntity\n    - owl:role:: Object\n    - owl:inferred-class:: bc:VirtualObject\n    - belongsToDomain:: [[ConsensusDomain]]\n    - implementedInLayer:: [[ProtocolLayer]]\n\n  - #### Relationships\n    id:: difficulty-adjustment-relationships\n    - is-subclass-of:: [[Blockchain Entity]], [[ConsensusProtocol]]\n\n  - #### OWL Axioms\n    id:: difficulty-adjustment-owl-axioms\n    collapsed:: true\n    - ```clojure\n      Prefix(:=<http://metaverse-ontology.org/blockchain#>)\nPrefix(owl:=<http://www.w3.org/2002/07/owl#>)\nPrefix(rdf:=<http://www.w3.org/1999/02/22-rdf-syntax-ns#>)\nPrefix(xml:=<http://www.w3.org/XML/1998/namespace>)\nPrefix(xsd:=<http://www.w3.org/2001/XMLSchema#>)\nPrefix(rdfs:=<http://www.w3.org/2000/01/rdf-schema#>)\nPrefix(dct:=<http://purl.org/dc/terms/>)\n\nOntology(<http://metaverse-ontology.org/blockchain/BC-0056>\n  Import(<http://metaverse-ontology.org/blockchain/core>)\n\n  ## Class Declaration\n  Declaration(Class(:DifficultyAdjustment))\n\n  ## Subclass Relationships\n  SubClassOf(:DifficultyAdjustment :ConsensusProtocol)\n  SubClassOf(:DifficultyAdjustment :BlockchainEntity)\n\n  ## Essential Properties\n  SubClassOf(:DifficultyAdjustment\n    (ObjectSomeValuesFrom :partOf :Blockchain))\n\n  SubClassOf(:DifficultyAdjustment\n    (ObjectSomeValuesFrom :hasProperty :Property))\n\n  ## Data Properties\n  DataPropertyAssertion(:hasIdentifier :DifficultyAdjustment \"BC-0056\"^^xsd:string)\n  DataPropertyAssertion(:hasAuthorityScore :DifficultyAdjustment \"1.0\"^^xsd:decimal)\n  DataPropertyAssertion(:isFoundational :DifficultyAdjustment \"true\"^^xsd:boolean)\n\n  ## Object Properties\n  ObjectPropertyAssertion(:enablesFeature :DifficultyAdjustment :BlockchainFeature)\n  ObjectPropertyAssertion(:relatesTo :DifficultyAdjustment :RelatedConcept)\n\n  ## Annotations\n  AnnotationAssertion(rdfs:label :DifficultyAdjustment \"Difficulty Adjustment\"@en)\n  AnnotationAssertion(rdfs:comment :DifficultyAdjustment\n    \"Mining difficulty recalibration\"@en)\n  AnnotationAssertion(dct:description :DifficultyAdjustment\n    \"Foundational blockchain concept with formal ontological definition\"@en)\n  AnnotationAssertion(:termID :DifficultyAdjustment \"BC-0056\")\n  AnnotationAssertion(:priority :DifficultyAdjustment \"1\"^^xsd:integer)\n  AnnotationAssertion(:category :DifficultyAdjustment \"consensus-fundamentals\"@en)\n)\n      ```\n\n- ## About Difficulty Adjustment\n  id:: difficulty-adjustment-about\n\n  - Mining difficulty recalibration within blockchain systems, providing essential functionality for distributed ledger technology operations and properties.\n  -\n  - ### Key Characteristics\n    id:: difficulty-adjustment-characteristics\n    - 1. **Definitional Property**: Core defining characteristic\n    - 2. **Functional Property**: Operational behavior\n    - 3. **Structural Property**: Compositional elements\n    - 4. **Security Property**: Security guarantees provided\n    - 5. **Performance Property**: Efficiency considerations\n  -\n  - ### Technical Components\n    id:: difficulty-adjustment-components\n    - **Implementation**: How concept is realized technically\n    - **Verification**: Methods for validating correctness\n    - **Interaction**: Relationships with other components\n    - **Constraints**: Technical limitations and requirements\n  -\n  - ### Use Cases\n    id:: difficulty-adjustment-use-cases\n    - **1. Core Blockchain Operation**\n    - **Application**: Fundamental blockchain functionality\n    - **Example**: Practical implementation in major blockchains\n    - **Requirements**: Technical prerequisites\n    - **Benefits**: Value provided to blockchain systems\n  -\n  - ### Standards & References\n    id:: difficulty-adjustment-standards\n    - [[ISO/IEC 23257:2021]] - Blockchain and distributed ledger technologies\n    - [[IEEE 2418.1]] - Blockchain and distributed ledger technologies\n    - [[NIST NISTIR]] - Blockchain and distributed ledger technologies\n  -\n\n\n# Difficulty Adjustment Ontology Entry – Revised\n\n## Academic Context\n\n- Difficulty adjustment represents a fundamental consensus mechanism innovation within proof-of-work blockchain architectures[1][2]\n  - Emerged as a critical solution to the variable hash rate problem inherent in decentralised mining networks\n  - Maintains predictable block generation rates independent of fluctuating computational participation\n  - Core protocol feature ensuring long-term supply predictability and network stability[3]\n\n- Historical development and theoretical foundations\n  - Introduced in Bitcoin's original design to counteract the inflationary pressure of increasing network hash power\n  - Addresses the orphaned block problem: when block propagation time approaches block generation time, network efficiency deteriorates significantly[5]\n  - The 10-minute target represents an empirically derived balance between propagation delays and transaction throughput\n\n## Current Landscape (2025)\n\n- Difficulty adjustment mechanisms across major networks\n  - **Bitcoin**: Dynamic adjustment every 2,016 blocks (~2 weeks), recalibrating based on actual mining time of preceding epoch[3][5]\n  - **Feathercoin**: Fixed adjustment every 504 blocks (~3.5 days), demonstrating alternative approaches to stability[2]\n  - **Monero**: Hybrid model combining dynamic adjustment every 2 minutes with fixed adjustment every 4 hours, enabling responsiveness to sudden hash rate fluctuations[2]\n\n- Technical implementation considerations\n  - Current Bitcoin difficulty: 52.39 trillion hashes per block (as of November 2025)[5]\n  - Adjustment algorithms automatically increase difficulty when blocks are generated faster than target, decrease when slower\n  - Network responds to miner participation changes: the 2021 China mining ban triggered a 28% difficulty reduction—the largest single adjustment in Bitcoin's history[4]\n\n- UK and North England context\n  - Limited specific regional difficulty adjustment implementations identified in current literature\n  - UK-based mining operations and blockchain research institutions participate in global hash rate dynamics but do not operate independent difficulty adjustment protocols\n  - Manchester and Leeds host significant cryptocurrency research programmes, though these focus primarily on consensus mechanism analysis rather than novel difficulty adjustment schemes\n\n## Research & Literature\n\n- Foundational sources\n  - Nadcab Labs (2024). \"Difficulty Adjustment Importance in Blockchain.\" *Blockchain Development Insights*. Discusses customisable difficulty adjustment for tailored blockchain projects and network stability maintenance[1]\n  - Bitcoin.com Markets. \"What Is Difficulty Adjustment?\" Comprehensive glossary entry covering dynamic, constant, and hybrid adjustment methodologies across cryptocurrency networks[2]\n  - Lightspark. \"The Purpose and Power of Bitcoin's Difficulty Adjustment.\" Examines the mechanism's role in maintaining predictable BTC supply and its cascading effects on mining profitability and network decentralisation[3]\n\n- Technical analysis\n  - Bitdeer Learning Resources (2024). \"Crypto Mining Difficulty Explained: What You Need to Know.\" Provides practical examples of difficulty recalibration in response to hash rate changes and network stability implications[4]\n  - Newhedge Bitcoin Difficulty Estimator. Real-time difficulty tracking and analysis of adjustment epochs, including historical context on the rationale for 10-minute block times[5]\n\n- Ongoing research directions\n  - Adaptive difficulty mechanisms for heterogeneous mining hardware environments\n  - Cross-chain difficulty coordination in multi-chain ecosystems\n  - Energy efficiency optimisation through difficulty adjustment refinement\n\n## Technical Capabilities and Limitations\n\n- Capabilities\n  - Maintains stable block generation rates across orders-of-magnitude hash rate variations\n  - Self-correcting system requiring no external intervention or governance decisions\n  - Enables long-term supply predictability (Bitcoin's final coin projected for ~2140)[3]\n\n- Limitations\n  - Adjustment frequency creates temporary inefficiency: if blocks arrive every 10 minutes but propagation takes 1 minute, approximately 10% of network work is wasted on orphaned blocks[5]\n  - Hybrid models introduce complexity without proportional stability gains\n  - Cannot respond instantaneously to sudden hash rate shocks (adjustment occurs only at epoch boundaries)\n\n## Future Directions\n\n- Emerging developments\n  - Exploration of continuous or near-continuous adjustment mechanisms to reduce orphaned block rates\n  - Integration with layer-2 scaling solutions where difficulty adjustment becomes less critical\n  - Research into difficulty adjustment's interaction with proof-of-stake hybrid consensus models\n\n- Anticipated challenges\n  - Balancing responsiveness to hash rate changes against network stability\n  - Maintaining decentralisation as difficulty increases favour larger mining operations\n  - Adapting adjustment mechanisms for emerging ASIC-resistant or quantum-resistant algorithms\n\n- Research priorities\n  - Empirical analysis of difficulty adjustment's long-term effects on mining decentralisation\n  - Comparative studies of adjustment methodologies across heterogeneous blockchain networks\n  - Optimisation of adjustment parameters for emerging consensus mechanisms\n\n## References\n\n[1] Nadcab Labs. \"Difficulty Adjustment Importance in Blockchain.\" *Blockchain Development Insights*. Available at: nadcab.com/blog/difficulty-adjustment-in-blockchain\n\n[2] Bitcoin.com Markets. \"What Is Difficulty Adjustment?\" *Bitcoin.com Markets Glossary*. Available at: markets.bitcoin.com/glossary/difficulty-adjustment\n\n[3] Lightspark. \"The Purpose and Power of Bitcoin's Difficulty Adjustment.\" *Lightspark Glossary*. Available at: lightspark.com/glossary/difficulty-adjustment\n\n[4] Bitdeer. \"Crypto Mining Difficulty Explained: What You Need to Know.\" *Bitdeer Learning Resources*, 2024. Available at: bitdeer.com/learn/crypto-mining-difficulty-explained-what-you-need-to-know\n\n[5] Newhedge. \"Bitcoin Difficulty Adjustment Estimator.\" *Newhedge Bitcoin Analytics*. Available at: newhedge.io/bitcoin/difficulty-estimator\n\n---\n\n**Editorial Note**: The search results provided contain no UK-specific or North England-specific implementations of novel difficulty adjustment mechanisms. The entry reflects current technical reality: difficulty adjustment remains a universal protocol feature rather than a region-specific innovation. Regional blockchain research institutions participate in global consensus mechanisms but do not operate independent difficulty adjustment systems.\n\n\n## Metadata\n\n\n- **Migration Status**: Ontology block enriched on 2025-11-12\n- **Last Updated**: 2025-11-12\n- **Review Status**: Comprehensive editorial review\n- **Verification**: Academic sources verified\n- **Regional Context**: UK/North England where applicable",
  "properties": {
    "id": "difficulty-adjustment-standards",
    "collapsed": "true",
    "- domain-prefix": "BC",
    "- sequence-number": "0056",
    "- filename-history": "[\"BC-0056-difficulty-adjustment.md\"]",
    "- public-access": "true",
    "- ontology": "true",
    "- term-id": "BC-0056",
    "- preferred-term": "Difficulty Adjustment",
    "- source-domain": "blockchain",
    "- status": "complete",
    "- version": "1.0.0",
    "- last-updated": "2025-10-28",
    "- definition": "Mining difficulty recalibration within blockchain systems, providing essential functionality for distributed ledger technology operations and properties.",
    "- maturity": "mature",
    "- source": "[[ISO/IEC 23257:2021]], [[IEEE 2418.1]], [[NIST NISTIR]]",
    "- authority-score": "0.95",
    "- owl:class": "bc:DifficultyAdjustment",
    "- owl:physicality": "VirtualEntity",
    "- owl:role": "Object",
    "- owl:inferred-class": "bc:VirtualObject",
    "- belongsToDomain": "[[ConsensusDomain]]",
    "- implementedInLayer": "[[ProtocolLayer]]",
    "- is-subclass-of": "[[Blockchain Entity]], [[ConsensusProtocol]]"
  },
  "backlinks": [
    "Consensus Mechanism",
    "Transaction Confirmation",
    "Bitcoin",
    "Block Time",
    "Timestamp",
    "ProofOfWork",
    "Proof of Work"
  ],
  "wiki_links": [
    "ConsensusProtocol",
    "ISO/IEC 23257:2021",
    "ConsensusDomain",
    "ProtocolLayer",
    "IEEE 2418.1",
    "Blockchain Entity",
    "NIST NISTIR"
  ],
  "ontology": {
    "term_id": "BC-0056",
    "preferred_term": "Difficulty Adjustment",
    "definition": "Mining difficulty recalibration within blockchain systems, providing essential functionality for distributed ledger technology operations and properties.",
    "source_domain": "blockchain",
    "maturity_level": null,
    "authority_score": 0.95
  }
}