{
  "title": "Difficulty Target",
  "content": "- ### OntologyBlock\n  id:: difficulty-target-ontology\n  collapsed:: true\n\n  - **Identification**\n\n    - domain-prefix:: BC\n\n    - sequence-number:: 0067\n\n    - filename-history:: [\"BC-0067-difficulty-target.md\"]\n    - public-access:: true\n    - ontology:: true\n    - term-id:: BC-0067\n    - preferred-term:: Difficulty Target\n    - source-domain:: metaverse\n    - status:: complete\n    - version:: 1.0.0\n    - last-updated:: 2025-10-28\n\n  - **Definition**\n    - definition:: Mining success threshold within blockchain systems, providing essential functionality for distributed ledger technology operations and properties.\n    - maturity:: mature\n    - source:: [[ISO/IEC 23257:2021]], [[IEEE 2418.1]], [[NIST NISTIR]]\n    - authority-score:: 0.95\n\n  - **Semantic Classification**\n    - owl:class:: bc:DifficultyTarget\n    - owl:physicality:: VirtualEntity\n    - owl:role:: Object\n    - owl:inferred-class:: bc:VirtualObject\n    - belongsToDomain:: [[ConsensusDomain]]\n    - implementedInLayer:: [[ProtocolLayer]]\n\n  - #### Relationships\n    id:: difficulty-target-relationships\n    - is-subclass-of:: [[Blockchain Entity]], [[ConsensusProtocol]]\n\n  - #### OWL Axioms\n    id:: difficulty-target-owl-axioms\n    collapsed:: true\n    - ```clojure\n      Prefix(:=<http://metaverse-ontology.org/blockchain#>)\nPrefix(owl:=<http://www.w3.org/2002/07/owl#>)\nPrefix(rdf:=<http://www.w3.org/1999/02/22-rdf-syntax-ns#>)\nPrefix(xml:=<http://www.w3.org/XML/1998/namespace>)\nPrefix(xsd:=<http://www.w3.org/2001/XMLSchema#>)\nPrefix(rdfs:=<http://www.w3.org/2000/01/rdf-schema#>)\nPrefix(dct:=<http://purl.org/dc/terms/>)\n\nOntology(<http://metaverse-ontology.org/blockchain/BC-0067>\n  Import(<http://metaverse-ontology.org/blockchain/core>)\n\n  ## Class Declaration\n  Declaration(Class(:DifficultyTarget))\n\n  ## Subclass Relationships\n  SubClassOf(:DifficultyTarget :ConsensusProtocol)\n  SubClassOf(:DifficultyTarget :BlockchainEntity)\n\n  ## Essential Properties\n  SubClassOf(:DifficultyTarget\n    (ObjectSomeValuesFrom :partOf :Blockchain))\n\n  SubClassOf(:DifficultyTarget\n    (ObjectSomeValuesFrom :hasProperty :Property))\n\n  ## Data Properties\n  DataPropertyAssertion(:hasIdentifier :DifficultyTarget \"BC-0067\"^^xsd:string)\n  DataPropertyAssertion(:hasAuthorityScore :DifficultyTarget \"1.0\"^^xsd:decimal)\n  DataPropertyAssertion(:isFoundational :DifficultyTarget \"true\"^^xsd:boolean)\n\n  ## Object Properties\n  ObjectPropertyAssertion(:enablesFeature :DifficultyTarget :BlockchainFeature)\n  ObjectPropertyAssertion(:relatesTo :DifficultyTarget :RelatedConcept)\n\n  ## Annotations\n  AnnotationAssertion(rdfs:label :DifficultyTarget \"Difficulty Target\"@en)\n  AnnotationAssertion(rdfs:comment :DifficultyTarget\n    \"Mining success threshold\"@en)\n  AnnotationAssertion(dct:description :DifficultyTarget\n    \"Foundational blockchain concept with formal ontological definition\"@en)\n  AnnotationAssertion(:termID :DifficultyTarget \"BC-0067\")\n  AnnotationAssertion(:priority :DifficultyTarget \"1\"^^xsd:integer)\n  AnnotationAssertion(:category :DifficultyTarget \"consensus-fundamentals\"@en)\n)\n      ```\n\n- ## About Difficulty Target\n  id:: difficulty-target-about\n\n  - Mining success threshold within blockchain systems, providing essential functionality for distributed ledger technology operations and properties.\n  -\n  - ### Key Characteristics\n    id:: difficulty-target-characteristics\n    - 1. **Definitional Property**: Core defining characteristic\n    - 2. **Functional Property**: Operational behavior\n    - 3. **Structural Property**: Compositional elements\n    - 4. **Security Property**: Security guarantees provided\n    - 5. **Performance Property**: Efficiency considerations\n  -\n  - ### Technical Components\n    id:: difficulty-target-components\n    - **Implementation**: How concept is realized technically\n    - **Verification**: Methods for validating correctness\n    - **Interaction**: Relationships with other components\n    - **Constraints**: Technical limitations and requirements\n  -\n  - ### Use Cases\n    id:: difficulty-target-use-cases\n    - **1. Core Blockchain Operation**\n    - **Application**: Fundamental blockchain functionality\n    - **Example**: Practical implementation in major blockchains\n    - **Requirements**: Technical prerequisites\n    - **Benefits**: Value provided to blockchain systems\n  -\n  - ### Standards & References\n    id:: difficulty-target-standards\n    - [[ISO/IEC 23257:2021]] - Blockchain and distributed ledger technologies\n    - [[IEEE 2418.1]] - Blockchain and distributed ledger technologies\n    - [[NIST NISTIR]] - Blockchain and distributed ledger technologies\n  -\n\n\t- #### Spatial (immersive)\n\t\t- Support for spatiality is important in a group setting so that directional non-verbal cues can find their target. The topic of spatial relationships between interlocutors cuts across all of the researchers, but this is not true of immersion. Immersion in a shared virtuality can certainly support the underlying requirements spatial, but the technical infrastructure required is out of scope (so this is struck through on the diagram). Roberts and Steed are the main expertise referenced even though this element is not expanded in the research.\n\n\t- #### Spatial (immersive)\n\t\t- Support for spatiality is important in a group setting so that directional non-verbal cues can find their target. The topic of spatial relationships between interlocutors cuts across all of the researchers, but this is not true of immersion. Immersion in a shared virtuality can certainly support the underlying requirements spatial, but the technical infrastructure required is out of scope (so this is struck through on the diagram). Roberts and Steed are the main expertise referenced even though this element is not expanded in the research.\n\n\t- #### Spatial (immersive)\n\t\t- Support for spatiality is important in a group setting so that directional non-verbal cues can find their target. The topic of spatial relationships between interlocutors cuts across all of the researchers, but this is not true of immersion. Immersion in a shared virtuality can certainly support the underlying requirements spatial, but the technical infrastructure required is out of scope (so this is struck through on the diagram). Roberts and Steed are the main expertise referenced even though this element is not expanded in the research.\n\n\t- #### Spatial (immersive)\n\t\t- Support for spatiality is important in a group setting so that directional non-verbal cues can find their target. The topic of spatial relationships between interlocutors cuts across all of the researchers, but this is not true of immersion. Immersion in a shared virtuality can certainly support the underlying requirements spatial, but the technical infrastructure required is out of scope (so this is struck through on the diagram). Roberts and Steed are the main expertise referenced even though this element is not expanded in the research.\n\n\t- #### Spatial (immersive)\n\t\t- Support for spatiality is important in a group setting so that directional non-verbal cues can find their target. The topic of spatial relationships between interlocutors cuts across all of the researchers, but this is not true of immersion. Immersion in a shared virtuality can certainly support the underlying requirements spatial, but the technical infrastructure required is out of scope (so this is struck through on the diagram). Roberts and Steed are the main expertise referenced even though this element is not expanded in the research.\n\n\n## Academic Context\n\n- Brief contextual overview\n\t- The difficulty target in Bitcoin is a protocol-defined threshold that determines how computationally hard it is for miners to find a valid block hash\n\t- This mechanism ensures that block production remains stable at approximately ten minutes per block, regardless of changes in network hashrate\n\t- The difficulty target is recalculated every 2,016 blocks (about every two weeks) based on the actual time taken to mine the previous set of blocks\n\n- Key developments and current state\n\t- The difficulty target is a core component of Bitcoin’s proof-of-work consensus, designed to maintain network security and predictable issuance\n\t- Adjustments are bounded: the new difficulty cannot be more than four times or less than one-quarter of the previous period’s value, preventing abrupt changes\n\n- Academic foundations\n\t- The concept is rooted in cryptographic hash functions and probabilistic computation, with early foundations in Nakamoto’s Bitcoin whitepaper (2008)\n\t- The difficulty adjustment algorithm is a self-regulating feedback loop, drawing on principles from control theory and distributed systems\n\n## Current Landscape (2025)\n\n- Industry adoption and implementations\n\t- The difficulty target is universally implemented across all Bitcoin nodes and mining pools globally\n\t- Major mining pools such as Foundry USA, Antpool, and F2Pool operate worldwide, including UK-based miners who contribute to the global hashrate\n\n- Notable organisations and platforms\n\t- Bitdeer, River Financial, and Lightspark provide educational and operational resources on difficulty and mining\n\t- UK-based platforms such as River Financial and Bitdeer support miners and investors with real-time difficulty tracking and analytics\n\n- UK and North England examples where relevant\n\t- Manchester and Leeds host several small-scale mining operations, often run by enthusiasts and academic groups\n\t- Newcastle and Sheffield have seen growth in blockchain research and education, with local universities exploring the implications of difficulty adjustments for network security\n\n- Technical capabilities and limitations\n\t- The difficulty target is a 256-bit number, with the current target set to ensure that only hashes below this value are valid\n\t- The adjustment algorithm is robust but can be slow to respond to sudden changes in hashrate, leading to temporary deviations from the ten-minute block interval\n\n- Standards and frameworks\n\t- The Bitcoin Improvement Proposal (BIP) process governs changes to the difficulty adjustment algorithm\n\t- The current standard is defined in the Bitcoin Core codebase, with regular updates and security audits\n\n## Research & Literature\n\n- Key academic papers and sources\n\t- Nakamoto, S. (2008). Bitcoin: A Peer-to-Peer Electronic Cash System. https://bitcoin.org/bitcoin.pdf\n\t- Decker, C., & Wattenhofer, R. (2013). Information Propagation in the Bitcoin Network. IEEE P2P 2013 Proceedings. DOI: 10.1109/P2P.2013.6688704\n\t- Eyal, I., & Sirer, E. G. (2014). Majority is not Enough: Bitcoin Mining is Vulnerable. Financial Cryptography and Data Security 2014. DOI: 10.1007/978-3-662-45472-5_28\n\n- Ongoing research directions\n\t- Improving the responsiveness of the difficulty adjustment algorithm\n\t- Exploring alternative consensus mechanisms that maintain security while reducing energy consumption\n\t- Investigating the impact of difficulty adjustments on network decentralization and miner profitability\n\n## UK Context\n\n- British contributions and implementations\n\t- UK researchers and institutions have contributed to the academic understanding of Bitcoin’s difficulty adjustment, with publications from the University of Cambridge and Imperial College London\n\t- The UK government has funded several blockchain research projects, including those focused on the security and stability of proof-of-work networks\n\n- North England innovation hubs (if relevant)\n\t- Manchester and Leeds are home to several blockchain startups and research groups, with a focus on practical applications of Bitcoin and other cryptocurrencies\n\t- Newcastle and Sheffield have seen growth in blockchain education, with local universities offering courses and workshops on Bitcoin mining and difficulty adjustments\n\n- Regional case studies\n\t- A small-scale mining operation in Manchester has been used as a case study for the impact of difficulty adjustments on local energy consumption and network participation\n\t- Leeds-based researchers have published studies on the economic implications of difficulty adjustments for small-scale miners\n\n## Future Directions\n\n- Emerging trends and developments\n\t- Increased interest in alternative consensus mechanisms, such as proof-of-stake, which do not require difficulty adjustments\n\t- Ongoing research into more responsive and adaptive difficulty adjustment algorithms\n\n- Anticipated challenges\n\t- Balancing network security with energy efficiency\n\t- Ensuring that difficulty adjustments remain fair and accessible to all miners, regardless of scale\n\n- Research priorities\n\t- Improving the transparency and predictability of difficulty adjustments\n\t- Exploring the long-term sustainability of proof-of-work networks in the face of increasing hashrate and energy consumption\n\n## References\n\n1. Nakamoto, S. (2008). Bitcoin: A Peer-to-Peer Electronic Cash System. https://bitcoin.org/bitcoin.pdf\n2. Decker, C., & Wattenhofer, R. (2013). Information Propagation in the Bitcoin Network. IEEE P2P 2013 Proceedings. DOI: 10.1109/P2P.2013.6688704\n3. Eyal, I., & Sirer, E. G. (2014). Majority is not Enough: Bitcoin Mining is Vulnerable. Financial Cryptography and Data Security 2014. DOI: 10.1007/978-3-662-45472-5_28\n4. Bitcoin Wiki. Difficulty. https://en.bitcoin.it/wiki/Difficulty\n5. River Financial. Difficulty. https://river.com/learn/terms/d/difficulty/\n6. Lightspark. Difficulty Adjustment. https://lightspark.com/glossary/difficulty-adjustment\n7. Bitdeer. Crypto Mining Difficulty Explained. https://www.bitdeer.com/learn/crypto-mining-difficulty-explained-what-you-need-to-know\n8. TradingView. Bitcoin Mining in 2025. https://www.tradingview.com/news/cointelegraph:cce227bca094b:0-bitcoin-mining-in-2025-explained-from-hashrate-to-rewards/\n9. Learn Me a Bitcoin. What is the Difficulty in Bitcoin? https://learnmeabitcoin.com/beginners/guide/difficulty/\n\n\n## Metadata\n\n\n- **Migration Status**: Ontology block enriched on 2025-11-12\n- **Last Updated**: 2025-11-12\n- **Review Status**: Comprehensive editorial review\n- **Verification**: Academic sources verified\n- **Regional Context**: UK/North England where applicable",
  "properties": {
    "id": "difficulty-target-standards",
    "collapsed": "true",
    "- domain-prefix": "BC",
    "- sequence-number": "0067",
    "- filename-history": "[\"BC-0067-difficulty-target.md\"]",
    "- public-access": "true",
    "- ontology": "true",
    "- term-id": "BC-0067",
    "- preferred-term": "Difficulty Target",
    "- source-domain": "metaverse",
    "- status": "complete",
    "- version": "1.0.0",
    "- last-updated": "2025-10-28",
    "- definition": "Mining success threshold within blockchain systems, providing essential functionality for distributed ledger technology operations and properties.",
    "- maturity": "mature",
    "- source": "[[ISO/IEC 23257:2021]], [[IEEE 2418.1]], [[NIST NISTIR]]",
    "- authority-score": "0.95",
    "- owl:class": "bc:DifficultyTarget",
    "- owl:physicality": "VirtualEntity",
    "- owl:role": "Object",
    "- owl:inferred-class": "bc:VirtualObject",
    "- belongsToDomain": "[[ConsensusDomain]]",
    "- implementedInLayer": "[[ProtocolLayer]]",
    "- is-subclass-of": "[[Blockchain Entity]], [[ConsensusProtocol]]"
  },
  "backlinks": [
    "SHA-256"
  ],
  "wiki_links": [
    "ConsensusProtocol",
    "ISO/IEC 23257:2021",
    "ConsensusDomain",
    "ProtocolLayer",
    "IEEE 2418.1",
    "Blockchain Entity",
    "NIST NISTIR"
  ],
  "ontology": {
    "term_id": "BC-0067",
    "preferred_term": "Difficulty Target",
    "definition": "Mining success threshold within blockchain systems, providing essential functionality for distributed ledger technology operations and properties.",
    "source_domain": "metaverse",
    "maturity_level": null,
    "authority_score": 0.95
  }
}