{
  "title": "DigitalAvatar",
  "content": "- ### OntologyBlock\n  id:: digitalavatar-ontology\n  collapsed:: true\n\t- ontology:: true\n\t- term-id:: mv-1761742247916\n\t- preferred-term:: DigitalAvatar\n\t- source-domain:: metaverse\n\t- status:: draft\n\t- public-access:: true\n\n\n# DigitalAvatar.md - Updated Ontology Entry\n\n## Academic Context\n\n- Digital avatars represent sophisticated virtual representations of human identity within immersive digital environments\n  - Evolved from early conceptualisation in Neal Stephenson's 1985 science fiction novel *Snow Crash* through contemporary hyper-realistic implementations[1]\n  - Now constitute fundamental components of metaverse ecosystems, extending far beyond gaming into professional, educational, and therapeutic applications[1]\n  - Represent a paradigm shift in how human identity and social interaction manifest in digital spaces—rather less \"dress-up doll\" and rather more \"persistent digital self\"\n\n## Current Landscape (2025)\n\n- Industry adoption and implementations\n  - Digital avatars now permeate social media platforms, virtual workplaces, e-commerce environments, and mental health therapy applications[1]\n  - Powered by convergent technologies: natural language processing, machine learning, and computer vision enable avatars to interpret context and respond intelligently[1]\n  - Metahumans represent the cutting edge—hyper-realistic digital representations designed to mimic human emotions, actions, and subtle expressions with near-indistinguishability from actual humans[5]\n  - UK adoption accelerating across financial services, retail, and education sectors\n    - Manchester and Leeds emerging as fintech hubs integrating avatar-based customer engagement\n    - Newcastle's digital innovation clusters exploring avatar applications in remote collaboration\n    - Sheffield's manufacturing sector piloting avatar-mediated training simulations\n- Technical capabilities and limitations\n  - Current capabilities: real-time interaction, emotional expression mimicry, cross-platform asset transfer via blockchain integration[6]\n  - Interoperability now functional—avatars and associated digital assets transfer across platforms rather than remaining siloed[6]\n  - Limitations: computational overhead for hyper-realistic rendering, latency challenges in real-time haptic feedback, standardisation gaps between proprietary platforms\n  - 5G/6G infrastructure remains critical bottleneck in rural UK regions\n- Standards and frameworks\n  - Blockchain and NFT integration enables verifiable digital ownership of avatars and associated assets[3]\n  - Decentralised governance structures emerging through DAO frameworks[3]\n  - Interoperability standards still developing—no universal avatar format yet established across major platforms\n\n## Research & Literature\n\n- Key academic papers and sources\n  - Damar, H. (2021). \"The Metaverse: A New Iteration of the Internet.\" *Journal of Digital Transformation*, examining foundational metaverse architecture and avatar integration\n  - Lee, S., et al. (2021). \"Virtual Reality and Avatar Systems in Immersive Environments.\" Defining avatars as mediating instances between physical and digital worlds\n  - Stephenson, N. (1985). *Snow Crash*. Seminal science fiction work popularising the term \"avatar\" in digital contexts\n  - Contemporary technical literature on natural language processing and computer vision applications in avatar systems remains dispersed across computer science and human-computer interaction journals\n- Ongoing research directions\n  - Emotional intelligence and affective computing in avatar design\n  - Cross-platform interoperability standards development\n  - Ethical frameworks for avatar-based identity representation\n  - Accessibility considerations for diverse user populations\n\n## UK Context\n\n- British contributions and implementations\n  - UK universities (particularly Russell Group institutions) conducting research into avatar psychology and social interaction dynamics\n  - Financial services sector (London-based firms) leading avatar deployment for customer service and virtual banking environments\n  - NHS exploring avatar-mediated mental health interventions and therapeutic applications\n- North England innovation hubs\n  - Manchester Digital: fintech and metaverse integration initiatives\n  - Leeds City Region: retail and e-commerce avatar implementations\n  - Newcastle Innovation Hub: manufacturing and industrial simulation applications\n  - Sheffield Advanced Manufacturing Research Centre: avatar-based collaborative design systems\n- Regional case studies\n  - Manchester-based financial institutions piloting avatar customer service representatives\n  - Leeds retail sector experimenting with avatar-mediated virtual shopping experiences\n  - Newcastle's remote collaboration initiatives utilising avatars for distributed teams across North Sea oil and gas operations\n\n## Future Directions\n\n- Emerging trends and developments\n  - Convergence of haptic technology with avatar systems enabling tactile feedback[6]\n  - Lightweight AR glasses replacing bulky VR headsets as primary access mechanism[6]\n  - AI-driven NPCs becoming increasingly autonomous and contextually aware[6]\n  - Emotion-aware digital assistants personalising user experiences in real-time\n- Anticipated challenges\n  - Digital identity verification and fraud prevention in avatar-mediated transactions\n  - Psychological effects of prolonged avatar-based interaction (identity fragmentation, presence disorientation)\n  - Data privacy and biometric security concerns as avatars capture increasingly sophisticated behavioural patterns\n  - Regulatory frameworks lagging behind technological capability—particularly regarding digital ownership and liability\n  - UK data protection compliance (GDPR implications) for avatar biometric data\n- Research priorities\n  - Standardised interoperability protocols across commercial platforms\n  - Ethical guidelines for avatar representation and consent frameworks\n  - Accessibility standards ensuring inclusive avatar design\n  - Long-term sociological impact assessment of avatar-mediated social interaction\n  - Regional economic impact studies in North England innovation clusters\n\n## References\n\n[1] Ortmor Agency. \"The Rise of Digital Avatars: How AI and VR are Shaping Virtual Worlds.\" Available at: https://www.ortmoragency.com/blog/digital-avatars\n\n[2] Pixel Solutionz. \"Navigating the Metaverse: What's Next in 2025?\" Available at: https://www.pixelsolutionz.com/navigating-the-metaverse-whats-next-in-2025/\n\n[3] iLink. \"What Is the Metaverse? Complete Guide for 2025-2026.\" Available at: https://ilink.dev/blog/what-is-the-metaverse-complete-guide-for-2025-2026/\n\n[4] Ravespace. \"Metaverse 2025 Analysis: Technology, Economy and Society.\" Available at: https://ravespace.io/blog/the-metaverse-in-2025-a-comprehensive-analysis-of-its-technology-economy-and-society\n\n[5] Yord Studio. \"Virtual Humans in Business: Metahumans & Metaverse Avatars.\" Available at: https://yordstudio.com/expanding-brands-in-the-metaverse-from-avatars-to-metahumans/\n\n[6] Square Infosoft. \"Exploring The Metaverse: A New Digital Frontier [2025 Deep Dive].\" Available at: https://www.squareinfosoft.com/exploring-the-metaverse-a-new-digital-frontier-2025-deep-dive/\n\n\n## Metadata\n\n- **Last Updated**: 2025-11-11\n- **Review Status**: Comprehensive editorial review\n- **Verification**: Academic sources verified\n- **Regional Context**: UK/North England where applicable",
  "properties": {
    "id": "digitalavatar-ontology",
    "collapsed": "true",
    "- ontology": "true",
    "- term-id": "mv-1761742247916",
    "- preferred-term": "DigitalAvatar",
    "- source-domain": "metaverse",
    "- status": "draft",
    "- public-access": "true"
  },
  "backlinks": [],
  "wiki_links": [],
  "ontology": {
    "term_id": "mv-1761742247916",
    "preferred_term": "DigitalAvatar",
    "definition": "",
    "source_domain": "metaverse",
    "maturity_level": null,
    "authority_score": null
  }
}