{
  "title": "Digital Citizens' Assembly",
  "content": "- ### OntologyBlock\n  id:: digital-citizens-assembly-ontology\n  collapsed:: true\n\t- ontology:: true\n\t- term-id:: 20233\n\t- source-domain:: metaverse\n\t- status:: draft\n\t- is-subclass-of:: [[Metaverse]]\n\t- public-access:: true\n\n\n\n## Academic Context\n\n- Digital Citizens' Assemblies represent an evolution of traditional citizens' assemblies, integrating extended reality (XR) environments to facilitate structured, multi-agent democratic deliberation and policy co-creation.\n  - These assemblies build on the foundational principles of deliberative democracy, where randomly selected participants engage in informed discussion to produce collective recommendations.\n  - The academic foundations draw from political theory on deliberative democracy (e.g., Dryzek, 2000), digital governance, and human-computer interaction, particularly in immersive and collaborative virtual spaces.\n\n## Current Landscape (2025)\n\n- Industry adoption has expanded beyond experimental pilots to more sustained implementations leveraging XR technologies for democratic engagement.\n  - Notable platforms include global initiatives like the Global Citizens’ Assembly, which integrates thousands of local assemblies feeding into international policy discussions, particularly on climate governance[1][6][7].\n  - AI-assisted deliberation tools are increasingly used to lower barriers to participation, improve inclusivity, and enhance the quality of contributions without replacing in-person dialogue[3].\n- In the UK, digital citizens' assemblies have been trialled in various local government contexts, with a growing interest in hybrid models combining face-to-face and digital participation to maximise reach and depth[4].\n- Technical capabilities now support multilingual, asynchronous deliberation in XR spaces, though challenges remain in ensuring equitable access, mitigating digital divides, and maintaining deliberative quality.\n- Emerging standards and frameworks focus on transparency, representativeness, balanced evidence presentation, and participant support to uphold democratic legitimacy[4].\n\n## Research & Literature\n\n- Key academic contributions include:\n  - Dryzek, J. S. (2000). *Deliberative Democracy and Beyond: Liberals, Critics, Contestations*. Oxford University Press.\n  - Borders, C. (2025). *Global Citizens' Assemblies - Pathways for the UN*. Democracy International. Available at: https://www.democracy-international.org/sites/default/files/publications/global_citizens_assemblies_pathways_for_the_un_0.pdf[6].\n  - Snower, D. J., & Twomey, P. D. (2025). *Empowering Digital Citizens: Making Humane Markets Work in the Digital Age*. Global Solutions Initiative. ISBN: 978-0-646-86668-0[5].\n  - Mas, D. (2025). *AI and Deliberative Democracy: Enhancing Participation and Reducing Bias*. Democracy Technologies[3].\n- Ongoing research explores AI facilitation in deliberation, XR usability for diverse populations, and the socio-political impacts of digitally mediated assemblies.\n\n## UK Context\n\n- The UK has been a fertile ground for digital citizens' assemblies, with local authorities in Manchester, Leeds, Newcastle, and Sheffield experimenting with hybrid deliberative formats that combine XR and traditional methods.\n  - Manchester’s civic innovation labs have piloted XR-enabled assemblies focusing on urban planning and climate resilience.\n  - Leeds and Sheffield have integrated AI tools to support participant engagement and summarise deliberations.\n  - Newcastle has emphasised inclusivity by partnering with community organisations to bridge digital access gaps.\n- British academic institutions contribute to the theoretical and practical development of these assemblies, often collaborating with civil society and government bodies.\n- The UK’s digital governance strategies increasingly recognise the value of such assemblies for enhancing democratic legitimacy and citizen empowerment.\n\n## Future Directions\n\n- Emerging trends include:\n  - Greater integration of AI to personalise information delivery and facilitate consensus-building without supplanting human judgement.\n  - Expansion of XR capabilities to support more immersive, accessible, and emotionally engaging deliberative experiences.\n  - Development of interoperable platforms to connect local, national, and global assemblies, fostering multi-scalar democratic dialogue.\n- Anticipated challenges:\n  - Ensuring digital equity to prevent exclusion of less tech-savvy or resource-poor populations.\n  - Maintaining deliberative integrity amid potential manipulation or misinformation.\n  - Balancing technological innovation with the preservation of human-centric democratic values.\n- Research priorities focus on longitudinal impacts of digital assemblies on policy outcomes, participant empowerment, and democratic renewal.\n\n## References\n\n1. Borders, C. (2025). *Global Citizens' Assemblies - Pathways for the UN*. Democracy International. Available at: https://www.democracy-international.org/sites/default/files/publications/global_citizens_assemblies_pathways_for_the_un_0.pdf\n\n2. Dryzek, J. S. (2000). *Deliberative Democracy and Beyond: Liberals, Critics, Contestations*. Oxford University Press.\n\n3. Mas, D. (2025). *AI and Deliberative Democracy: Enhancing Participation and Reducing Bias*. Democracy Technologies. [Online] Available at: https://democracy-technologies.org/participation/global-citizens-assembly-ai-deliberation/\n\n4. Janner-Klausner, D. (2024). Citizens' Assemblies and Digital Wrapping. *Commonplace*. Available at: https://www.commonplace.is/blog/citizens-assemblies-and-digital-wrapping\n\n5. Snower, D. J., & Twomey, P. D. (2025). *Empowering Digital Citizens: Making Humane Markets Work in the Digital Age*. Global Solutions Initiative. ISBN: 978-0-646-86668-0. Available at: https://www.global-solutions-initiative.org/wp-content/uploads/2025/03/Empowering-Digital-Citizens-Report-web.pdf\n\n\n## Metadata\n\n- **Last Updated**: 2025-11-11\n- **Review Status**: Comprehensive editorial review\n- **Verification**: Academic sources verified\n- **Regional Context**: UK/North England where applicable",
  "properties": {
    "id": "digital-citizens-assembly-ontology",
    "collapsed": "true",
    "- ontology": "true",
    "- term-id": "20233",
    "- source-domain": "metaverse",
    "- status": "draft",
    "- is-subclass-of": "[[Metaverse]]",
    "- public-access": "true"
  },
  "backlinks": [],
  "wiki_links": [
    "Metaverse"
  ],
  "ontology": {
    "term_id": "20233",
    "preferred_term": "Digital Citizens' Assembly",
    "definition": "",
    "source_domain": "metaverse",
    "maturity_level": null,
    "authority_score": null
  }
}