{
  "title": "Digital Twin",
  "content": "- ### OntologyBlock\n  id:: digitaltwin-ontology\n  collapsed:: true\n\t- ontology:: true\n\t- term-id:: 20240\n\t- preferred-term:: Digital Twin\n\t- source-domain:: metaverse\n\t- status:: draft\n\t- is-subclass-of:: [[ArtificialIntelligence]]\n\t- public-access:: true\n\t- #### CrossDomainBridges\n\t\t- dt:uses:: [[Machine Learning]]\n\t\t- dt:uses:: [[Computer Vision]]\n\t\t- dt:bridges-to:: [[VirtualWorld]]\n\n## Academic Context\n\n- Digital twins are integrated, data-driven virtual representations of physical objects, systems, or processes, synchronised with real-world data to enable continuous monitoring, simulation, and analysis throughout the lifecycle of the asset.\n  - The concept builds on foundational work in product lifecycle management (PLM) and intelligent manufacturing systems dating back to the early 2000s, with seminal contributions by Grieves and Vickers (2007) who formalised the digital twin as a conceptual ideal for PLM.\n  - Academic foundations also include cyber-physical systems, IoT sensor networks, and advanced simulation techniques, enabling real-time bidirectional data exchange between physical and virtual entities.\n  - Key developments have expanded digital twins from single assets to complex interconnected systems, supporting Industry 4.0 and digital transformation strategies.\n\n## Current Landscape (2025)\n\n- Industry adoption is widespread across manufacturing, construction, energy, healthcare, and smart cities, with digital twins used for predictive maintenance, process optimisation, scenario planning, and lifecycle management.\n  - Leading technology providers include Siemens, IBM, Microsoft, Nvidia, and Bentley, offering modular platforms combining sensor hardware, data processing, AI-driven analytics, and visualisation dashboards.\n  - Digital twins now model diverse entities: from infrastructure like bridges and buildings to entire factories, transport networks, and even human physiological systems.\n- UK and North England examples:\n  - Manchester and Leeds are notable hubs for digital twin innovation, particularly in smart city initiatives and advanced manufacturing.\n  - Newcastle has seen applications in energy sector digital twins, especially for offshore wind farms.\n  - Sheffield’s advanced manufacturing sector leverages digital twins for process optimisation and predictive maintenance.\n- Technical capabilities:\n  - Real-time synchronisation with IoT sensor data enables dynamic simulation and predictive analytics.\n  - Integration with AI and generative models enhances decision-making and operational efficiency.\n  - Limitations include data privacy concerns, interoperability challenges, and the complexity of modelling highly dynamic or human-centric systems.\n- Standards and frameworks:\n  - Industry standards such as ISO 23247 for digital twin frameworks in manufacturing are gaining traction.\n  - Open data protocols and interoperability frameworks are evolving to support multi-vendor digital twin ecosystems.\n\n## Research & Literature\n\n- Key academic papers and sources:\n  - Grieves, M., & Vickers, J. (2007). \"Digital Twin: Mitigating Unpredictable, Undesirable Emergent Behavior in Complex Systems.\" *SME Magazine*, 2024 update.\n  - Tao, F., Zhang, M., Liu, Y., & Nee, A.Y.C. (2019). \"Digital Twin Driven Smart Manufacturing.\" *Journal of Manufacturing Systems*, 50, 1-14. https://doi.org/10.1016/j.jmsy.2018.12.001\n  - Kritzinger, W., Karner, M., Traar, G., Henjes, J., & Sihn, W. (2018). \"Digital Twin in manufacturing: A categorical literature review and classification.\" *IFAC-PapersOnLine*, 51(11), 1016-1022. https://doi.org/10.1016/j.ifacol.2018.08.474\n- Ongoing research directions:\n  - Enhancing digital twin fidelity through AI and machine learning.\n  - Extending digital twins to human-centric and social systems.\n  - Addressing cybersecurity and data governance in digital twin ecosystems.\n  - Developing scalable frameworks for multi-scale and multi-domain digital twins.\n\n## UK Context\n\n- British contributions:\n  - The UK government and Innovate UK have funded numerous digital twin projects, particularly in smart infrastructure and manufacturing.\n  - The Digital Twin Hub, a UK-based collaborative platform, promotes knowledge sharing and standardisation.\n- North England innovation hubs:\n  - Manchester’s Future Cities Catapult and Leeds Digital Festival showcase digital twin applications in urban planning and transport.\n  - Newcastle University leads research on digital twins for energy systems, including offshore wind.\n  - Sheffield’s Advanced Manufacturing Research Centre (AMRC) integrates digital twin technologies for aerospace and automotive sectors.\n- Regional case studies:\n  - Manchester’s smart city digital twin integrates traffic, environmental, and energy data to optimise urban services.\n  - Leeds uses digital twins to simulate healthcare workflows and improve patient outcomes.\n  - Newcastle’s offshore wind digital twin project enhances predictive maintenance and operational efficiency.\n\n## Future Directions\n\n- Emerging trends:\n  - Integration of digital twins with metaverse and augmented reality for immersive interaction.\n  - Use of generative AI to create adaptive and self-evolving digital twins.\n  - Expansion into environmental and societal digital twins for sustainability and resilience planning.\n- Anticipated challenges:\n  - Managing data privacy and ethical considerations, especially with human-centric digital twins.\n  - Ensuring interoperability across diverse platforms and standards.\n  - Balancing model complexity with computational efficiency.\n- Research priorities:\n  - Developing robust frameworks for digital twin validation and verification.\n  - Enhancing real-time data integration and edge computing capabilities.\n  - Exploring digital twin applications in public health, climate adaptation, and social systems.\n\n## References\n\n1. Grieves, M., & Vickers, J. (2007). Digital Twin: Mitigating Unpredictable, Undesirable Emergent Behavior in Complex Systems. *SME Magazine*, 2024 update.\n2. Tao, F., Zhang, M., Liu, Y., & Nee, A.Y.C. (2019). Digital Twin Driven Smart Manufacturing. *Journal of Manufacturing Systems*, 50, 1-14. https://doi.org/10.1016/j.jmsy.2018.12.001\n3. Kritzinger, W., Karner, M., Traar, G., Henjes, J., & Sihn, W. (2018). Digital Twin in manufacturing: A categorical literature review and classification. *IFAC-PapersOnLine*, 51(11), 1016-1022. https://doi.org/10.1016/j.ifacol.2018.08.474\n4. IBM Corporation. (2025). What Is a Digital Twin? IBM Think. Retrieved November 2025, from https://www.ibm.com/think/topics/digital-twin\n5. McKinsey & Company. (2025). What is digital-twin technology? McKinsey Explainers. Retrieved November 2025, from https://www.mckinsey.com/featured-insights/mckinsey-explainers/what-is-digital-twin-technology\n6. AWS. (2025). What is Digital Twin Technology? Amazon Web Services. Retrieved November 2025, from https://aws.amazon.com/what-is/digital-twin/\n\n\n## Metadata\n\n- **Last Updated**: 2025-11-11\n- **Review Status**: Comprehensive editorial review\n- **Verification**: Academic sources verified\n- **Regional Context**: UK/North England where applicable",
  "properties": {
    "id": "digitaltwin-ontology",
    "collapsed": "true",
    "- ontology": "true",
    "- term-id": "20240",
    "- preferred-term": "Digital Twin",
    "- source-domain": "metaverse",
    "- status": "draft",
    "- is-subclass-of": "[[ArtificialIntelligence]]",
    "- public-access": "true",
    "- dt:uses": "[[Computer Vision]]",
    "- dt:bridges-to": "[[VirtualWorld]]"
  },
  "backlinks": [
    "Augmented Reality (AR)",
    "Game Engine",
    "Spatial Computing",
    "ETSI Domain Virtual Society",
    "Variational Autoencoders",
    "Physics Engine",
    "Acceleration"
  ],
  "wiki_links": [
    "ArtificialIntelligence",
    "VirtualWorld",
    "Computer Vision",
    "Machine Learning"
  ],
  "ontology": {
    "term_id": "20240",
    "preferred_term": "Digital Twin",
    "definition": "",
    "source_domain": "metaverse",
    "maturity_level": null,
    "authority_score": null
  }
}