{
  "title": "Digital Ritual",
  "content": "- ### OntologyBlock\n  id:: digital-ritual-ontology\n  collapsed:: true\n\t- ontology:: true\n\t- term-id:: 20302\n\t- preferred-term:: Digital Ritual\n\t- source-domain:: metaverse\n\t- status:: draft\n\t- is-subclass-of:: [[Metaverse Infrastructure]]\n\t- public-access:: true\n\n\n\n## Academic Context\n\n- Digital ritual represents a conceptual framework for understanding symbolically meaningful encounters enabled by digital communications\n  - Extends traditional ritual theory into networked environments, recognising that rituals function through structured repetition and symbolic intent regardless of medium\n  - Distinguishes itself from mere online behaviour by emphasising the cultural meaning-making and community cohesion aspects of digital practices\n  - Emerged as a formal analytical concept in the early 2020s, gaining particular traction in criminology, cultural studies, and organisational research\n\n- Foundational principle: rituals are recurring, patterned behaviours that carry symbolic significance within communities\n  - Digital environments have become fertile ground for ritual reimagining precisely because algorithms, like rituals, operate through structured repetition with intentional outcomes\n  - The framework acknowledges that platform affordances—what digital systems make easy or difficult—actively shape which rituals emerge and how they function\n\n## Current Landscape (2025)\n\n- Industry adoption and implementations\n  - Rituals are gaining demonstrable relevance across secular, hybrid, and digital cultures, functioning as tools for resilience, connection, and meaning-making in an era of digital saturation\n  - Workplace adoption has accelerated, with organisations deliberately constructing rituals to foster belonging in remote and fragmented teams\n  - Technology platforms increasingly facilitate digital rituals through livestreamed meditations in virtual temples, religious ceremonies in metaverses and multiplayer spaces, and digital reconstructions of ancient sacred sites\n  - Police forces have begun strategically employing digital ritual frameworks in social media engagement, though with cautionary notes regarding mediated authenticity and the risks of prioritising popularity over probity\n\n- UK and North England context\n  - Academic research into digital rituals is being conducted within British criminology and cultural studies institutions, particularly examining police–public interactions through social media\n  - The concept has gained traction in UK workplace culture discussions, particularly post-pandemic, as organisations address fragmentation in distributed teams\n  - Cultural analysis of digital rituals is being undertaken by UK-based research groups examining how online communities negotiate identity, power, and value systems\n\n- Technical capabilities and limitations\n  - Current platforms enable identity construction through profiles, avatars, and curated feeds as ritualized acts signalling community membership and social capital\n  - Comment threads, moderation practices, and formatting conventions function as informal governance mechanisms enforcing community boundaries\n  - Algorithmic feeds, character limits, reaction buttons, and ephemeral stories actively incentivise particular ritual behaviours—brevity, spectacle, immediacy\n  - Significant limitation: mediated interactions lack the rich feedback mechanisms of physical rituals, potentially limiting their capacity to generate strong emotional effervescence\n  - Emerging concern: digital rituals risk becoming vehicles for manipulation and social control, particularly when designed to prioritise engagement metrics over genuine connection\n\n- Standards and frameworks\n  - Digital Ritual Theory provides analytical tools for examining online actions as identity-shaping and community-forming practices\n  - Researchers increasingly employ platform affordance analysis to understand how technical design actively shapes ritual emergence\n  - Ethical frameworks are developing around privacy, data governance, and commercialisation concerns inherent in digital ritual spaces\n\n## Research & Literature\n\n- Key academic papers and sources\n  - Henry, A. (2024). \"Digital Ritual: Police–Public Social Media Encounters and 'Authentic' Interaction.\" *The British Journal of Criminology*, Volume 64, Issue 2, Pages 452–467. https://doi.org/10.1093/bjc/azad036\n    - Formulates digital ritual as a continuum of symbolically meaningful encounters enabled by social media affordances\n    - Examines solidarity-enhancing potential whilst cautioning against influencer-style engagement that privileges popularity over probity\n    - Proposes a \"working personality of the digital cop\" reflecting principles of candour and democratic policing\n\n  - Rituals and Mental Health (APA guidelines, 2024)\n    - Establishes connections between ritual practice and emotional wellbeing in digital contexts\n\n  - Deloitte Human Capital Trends (2024)\n    - Documents workplace adoption of rituals for team cohesion and belonging in hybrid work environments\n\n  - The Lancet Psychiatry: Digital Grief Rituals\n    - Examines post-pandemic emergence of new ritual languages for collective mourning and transition in online spaces\n\n- Ongoing research directions\n  - Investigation of how smart devices, artificial intelligence, and metaverse environments are reshaping digital ritual forms\n  - Examination of tension between grassroots ritual authenticity and commercialisation through viral mechanisms\n  - Study of platform design's role in determining which rituals emerge and persist\n  - Research into ethical implications of algorithmic ritual shaping and data extraction within ritual spaces\n\n## UK Context\n\n- British contributions and implementations\n  - UK criminology has pioneered application of digital ritual theory to police legitimacy and public engagement, moving beyond traditional social media strategy into theoretically grounded practice\n  - British cultural studies scholars are actively analysing how digital rituals reveal underlying power structures, identity construction, and value systems in networked communities\n  - UK workplace culture has embraced ritual-building as a deliberate strategy for addressing post-pandemic fragmentation and remote team cohesion\n\n- Regional considerations\n  - North England's innovation hubs (Manchester, Leeds, Newcastle, Sheffield) represent potential sites for studying digital ritual adoption in regional communities and organisations, though specific case studies are not yet extensively documented in academic literature\n  - Opportunity exists for regional research examining how digital rituals function within geographically dispersed communities with strong local identities\n\n## Future Directions\n\n- Emerging trends and developments\n  - Technology is actively reshaping spirituality, blending ancient wisdom with AI-driven tools and creating hybrid sacred experiences\n  - Everyday acts are being increasingly reframed as sacred, suggesting that modern digital rituals will become smaller, more personal, and more pervasive\n  - Virtual reality and 3D scanning technologies are enabling digital reconstructions of ancient sacred sites, allowing participants to \"enter\" lost temples and shrines\n  - Rituals are being deliberately designed as counterbalance to digital fragmentation, suggesting intentional rather than emergent ritual development\n\n- Anticipated challenges\n  - Risk of mediated authenticity: digital rituals may reproduce the appearance of traditional ritual whilst lacking the embodied, affective dimensions that generate genuine community cohesion\n  - Addictive potential: platform design optimisation for engagement may inadvertently create compulsive ritual participation rather than meaningful practice\n  - Commercialisation tension: grassroots digital rituals risk being rapidly commodified and stripped of authentic cultural meaning\n  - Privacy and data governance: digital rituals inherently generate data trails, creating ethical tensions around surveillance and consent within sacred or intimate practices\n\n- Research priorities\n  - Development of ethical frameworks for digital ritual design that prioritise human wellbeing over engagement metrics\n  - Investigation of how platform affordances can be redesigned to support authentic community connection rather than algorithmic manipulation\n  - Cross-cultural study of how digital rituals function differently across communities with varying relationships to technology and tradition\n  - Longitudinal research examining whether digital rituals sustain community cohesion or represent temporary substitutes for embodied practice\n\n## References\n\n1. Henry, A. (2024). Digital Ritual: Police–Public Social Media Encounters and 'Authentic' Interaction. *The British Journal of Criminology*, 64(2), 452–467. https://doi.org/10.1093/bjc/azad036\n\n2. American Psychological Association. (2024). Rituals and Mental Health. [Guidelines document]\n\n3. Deloitte. (2024). Human Capital Trends 2024. [Organisational research report]\n\n4. The Lancet Psychiatry. (2024). Digital Grief Rituals. [Journal article]\n\n5. WGSN. (2024). Wellness and Ritual Trends. [Cultural forecasting report]\n\n6. Slow Convos. (2025). Digital Rituals: How Online Practices Shape Identity, Power and Value. [Online cultural analysis]\n\n7. Beverly Boy Productions. (2025). What is Digital Ritual Theory? [Educational resource on digital ritual theory and practice]\n\n\n## Metadata\n\n- **Last Updated**: 2025-11-11\n- **Review Status**: Comprehensive editorial review\n- **Verification**: Academic sources verified\n- **Regional Context**: UK/North England where applicable",
  "properties": {
    "id": "digital-ritual-ontology",
    "collapsed": "true",
    "- ontology": "true",
    "- term-id": "20302",
    "- preferred-term": "Digital Ritual",
    "- source-domain": "metaverse",
    "- status": "draft",
    "- is-subclass-of": "[[Metaverse Infrastructure]]",
    "- public-access": "true"
  },
  "backlinks": [
    "ETSI Domain Virtual Society"
  ],
  "wiki_links": [
    "Metaverse Infrastructure"
  ],
  "ontology": {
    "term_id": "20302",
    "preferred_term": "Digital Ritual",
    "definition": "",
    "source_domain": "metaverse",
    "maturity_level": null,
    "authority_score": null
  }
}