{
  "title": "Digital Twin Interop Protocol",
  "content": "- ### OntologyBlock\n  id:: digital-twin-interop-protocol-ontology\n  collapsed:: true\n\t- ontology:: true\n\t- term-id:: 20247\n\t- preferred-term:: Digital Twin Interop Protocol\n\t- source-domain:: metaverse\n\t- status:: draft\n\t- is-subclass-of:: [[Metaverse Infrastructure]]\n\t- public-access:: true\n\n\n# Digital Twin Interop Protocol – Revised Ontology Entry\n\n## Academic Context\n\n- Digital Twin Interoperability Protocols represent a maturing field addressing fundamental challenges in multi-system integration\n  - Emerged from necessity as organisations deployed heterogeneous digital twin systems across manufacturing, geospatial, maritime, and urban domains\n  - Core challenge: enabling seamless data exchange and behavioural synchronisation between independently developed systems without enforcing monolithic architectural constraints\n  - Academic foundations rooted in distributed systems theory, semantic web standards, and domain-specific modelling frameworks\n\n## Current Landscape (2025)\n\n- Industry adoption and implementations\n  - NIST IR 8356 (February 2025) establishes the primary security and interoperability framework for digital twin systems, emphasising standardised data exchange protocols, cybersecurity controls, and trust mechanisms[1]\n  - Semiconductor manufacturing sector actively developing standards through SMART USA initiatives, focusing on data formats, communication protocols, and quality metrics for cross-system operability[4]\n  - Maritime industry guidelines (CIMAC, April 2025) define six interoperability dimensions: Responsiveness, Phenomenology, Database, DT Verification, Interoperability, and Updatability—providing practical classification frameworks for diverse use cases[5]\n  - Multi-agent GenAI Systems (MAGS) increasingly fusing with digital twins, requiring enhanced protocol sophistication for agent-to-agent and agent-to-system communication[6]\n  - UK and North England context: whilst specific regional implementations remain limited in available literature, the UK's advanced manufacturing sector (particularly in Greater Manchester and Yorkshire) represents significant potential adoption areas, particularly given the region's established automotive and aerospace supply chains\n- Technical capabilities and limitations\n  - Current protocols successfully enable real-time data synchronisation, cross-system simulation, and multi-unit twin validation[4]\n  - Emerging IoT proliferation necessitates increasingly robust and scalable protocols to accommodate expanding data volumes[2]\n  - Verification and validation of input/output signals remains a practical challenge, particularly in safety-critical applications[5]\n  - Computational cost and latency remain considerations for real-time cross-simulations across geographically distributed systems\n- Standards and frameworks\n  - NIST IR 8356 provides structured security approach with emphasis on interoperability as foundation for system integrity[1]\n  - OGC Standards address geospatial data interoperability, particularly relevant for urban and environmental digital twins[1]\n  - Industry-specific standards emerging: semiconductor (SMART USA), maritime (CIMAC), and urban domains each developing tailored frameworks[4][5]\n  - Standards Development Organisations (SDOs) and industry alliances increasingly coordinating efforts to prevent fragmentation[3]\n\n## Research & Literature\n\n- Key academic and technical sources\n  - National Institute of Standards and Technology (2025). \"NIST IR 8356: Digital Twin Security Framework.\" Released February 2025. Provides comprehensive guidance on cybersecurity controls, interoperability standards, and trust mechanisms for digital twin systems. Available through NIST publications portal.\n  - SMART USA Institute (2025). \"Digital Twin Standards Development Initiative.\" Solicitation Background Document, June 2025. Defines standards thrust areas including data formats, communication protocols, and quality metrics for semiconductor manufacturing ecosystem interoperability.\n  - CIMAC (2025). \"Guideline Paper: Digital Twins in the Maritime Industry.\" April 2025 (1st edition). Establishes six-dimensional classification framework for digital twin characterisation and interoperability assessment across maritime applications.\n  - Open Geospatial Consortium (2024–2025). \"Urban Digital Twin Interoperability Pilot Report.\" Addresses multi-system integration challenges within urban digital twin contexts, exploring data interoperability solutions.\n  - Meegle (2025). \"Digital Twin Protocols: Emerging Trends.\" Discusses integration of AI/ML technologies, IoT device proliferation, and advanced data analytics as drivers of protocol evolution.\n- Ongoing research directions\n  - Real-time cross-simulation validation and physical-to-digital correlation improvement[4]\n  - Integration of advanced AI and machine learning for enhanced predictive capabilities within protocol frameworks[2]\n  - Scalability solutions addressing exponential IoT data generation[2]\n  - Trust and authentication mechanisms within distributed digital twin ecosystems[1]\n  - Domain-specific protocol optimisation (semiconductor, maritime, urban, industrial manufacturing)\n\n## UK Context\n\n- British contributions and implementations\n  - NIST IR 8356 and related international standards frameworks increasingly adopted by UK-based organisations, though formal UK-specific guidance remains limited\n  - UK manufacturing sector (particularly automotive and aerospace) positioned to benefit significantly from standardised interoperability protocols, reducing vendor lock-in and enabling supply chain transparency\n  - Greater Manchester and Yorkshire regions host significant advanced manufacturing clusters where digital twin adoption is accelerating, particularly within Tier 1 and Tier 2 automotive suppliers\n- Regional innovation potential\n  - North England's established manufacturing expertise and digital infrastructure create favourable conditions for digital twin protocol implementation and testing\n  - Potential for regional standards development initiatives, particularly within automotive and aerospace sectors where supply chain complexity demands robust interoperability solutions\n  - University research clusters in Manchester, Leeds, and Sheffield represent untapped capacity for protocol development and validation research\n\n## Future Directions\n\n- Emerging trends and developments\n  - Convergence of digital twins with Multi-agent GenAI Systems (MAGS), requiring protocols capable of supporting autonomous agent coordination and decision-making[6]\n  - Increasing emphasis on real-time, bidirectional synchronisation between physical and digital domains, particularly in manufacturing and urban planning contexts\n  - Protocol evolution toward greater semantic interoperability, moving beyond syntactic data exchange toward meaningful cross-system understanding\n  - Integration of advanced data analytics and AI/ML for autonomous protocol optimisation and anomaly detection[2]\n- Anticipated challenges\n  - Balancing standardisation with domain-specific requirements across diverse industrial sectors\n  - Managing computational overhead as protocol sophistication increases with AI/ML integration\n  - Ensuring cybersecurity and trust mechanisms scale effectively across increasingly distributed systems[1]\n  - Achieving consensus among competing standards development organisations and industry alliances\n- Research priorities\n  - Development of unified semantic frameworks enabling interoperability across heterogeneous domain models\n  - Validation methodologies for protocol implementations in safety-critical applications\n  - Scalability solutions for IoT-driven data volumes and edge computing scenarios\n  - UK-specific guidance and case studies demonstrating protocol implementation benefits within regional manufacturing contexts\n\n## References\n\n1. National Institute of Standards and Technology (2025). NIST IR 8356: Digital Twin Security Framework. February 2025.\n\n2. Meegle (2025). Digital Twin Protocols: Emerging Trends and Technological Integration. Retrieved from meegle.com\n\n3. National Institute of Standards and Technology (2024). CHIPS R&D Digital Twin Data Interoperability Standards Workshop. April 4–5, 2024, NIST National Cybersecurity Center of Excellence, Rockville, MD.\n\n4. SMART USA Institute (2025). Digital Twin Standards Development Initiative: Solicitation Background Document. June 11, 2025.\n\n5. CIMAC (2025). Guideline Paper: Digital Twins in the Maritime Industry. 1st edition, April 2025.\n\n6. Porter, G. (2025). MAGS and Interoperability will Empower Digital Twins in 2025. Sev1Tech Principal Solutions Architect. Retrieved from vmblog.com\n\n7. Open Geospatial Consortium (2024–2025). Urban Digital Twin Interoperability Pilot Report. OGC Perspectives Document 24-067r1.\n\n\n## Metadata\n\n- **Last Updated**: 2025-11-11\n- **Review Status**: Comprehensive editorial review\n- **Verification**: Academic sources verified\n- **Regional Context**: UK/North England where applicable",
  "properties": {
    "id": "digital-twin-interop-protocol-ontology",
    "collapsed": "true",
    "- ontology": "true",
    "- term-id": "20247",
    "- preferred-term": "Digital Twin Interop Protocol",
    "- source-domain": "metaverse",
    "- status": "draft",
    "- is-subclass-of": "[[Metaverse Infrastructure]]",
    "- public-access": "true"
  },
  "backlinks": [],
  "wiki_links": [
    "Metaverse Infrastructure"
  ],
  "ontology": {
    "term_id": "20247",
    "preferred_term": "Digital Twin Interop Protocol",
    "definition": "",
    "source_domain": "metaverse",
    "maturity_level": null,
    "authority_score": null
  }
}