{
  "title": "Digital Ontology Repository",
  "content": "- ### OntologyBlock\n  id:: digital-ontology-repository-ontology\n  collapsed:: true\n\t- ontology:: true\n\t- term-id:: 20127\n\t- source-domain:: metaverse\n\t- status:: draft\n\t- is-subclass-of:: [[Metaverse Infrastructure]]\n\t- public-access:: true\n\n\n\n## Academic Context\n\n- Brief contextual overview\n  - Digital Ontology Repositories (DORs) are foundational infrastructures for the storage, versioning, and management of formal ontologies and semantic models, supporting interoperability and shared understanding across domains, including the metaverse, digital twins, and enterprise data ecosystems\n  - The field has matured beyond simple catalogues, now supporting advanced features such as mapping visualisation, metadata filtering, and bulk downloads, with increasing emphasis on standards compliance and community-driven curation\n\n- Key developments and current state\n  - Repositories now routinely support interoperable mappings between ontologies, leveraging standards such as SSSOM (Semantic Similarity and Mapping Ontology Model) for mapping import and storage\n  - There is a growing trend towards open, community-driven repositories that prioritise hosting and serving mappings rather than creating or editing them, reflecting a shift towards collaborative, distributed knowledge management\n\n- Academic foundations\n  - The theoretical underpinnings of DORs draw from knowledge representation, semantic web technologies, and model-based systems engineering, with ontologies serving as the backbone for structured knowledge representation and integration\n\n## Current Landscape (2025)\n\n- Industry adoption and implementations\n  - Notable organisations and platforms\n    - BioPortal, a leading open community resource, provides extensive support for sharing, searching, and utilising biomedical ontologies, with a strong focus on interoperable mappings and standards compliance\n    - Palantir Ontology offers an operational layer for organisations, connecting digital assets to real-world counterparts and enabling robust semantic and kinetic elements for enterprise workflows\n    - Azure Digital Twins leverages DTDL-based industry ontologies to accelerate development of digital twin solutions, particularly in energy and infrastructure domains\n  - UK and North England examples where relevant\n    - The University of Manchester’s Digital Health Centre has adopted ontology-driven approaches for integrating clinical and research data, supporting cross-domain interoperability in healthcare\n    - Leeds-based digital innovation hubs are exploring ontology repositories for smart city applications, focusing on urban infrastructure and citizen services\n    - Newcastle University’s Institute for Data Science is developing ontology frameworks for environmental monitoring and sustainability, with a particular emphasis on regional data integration\n\n- Technical capabilities and limitations\n  - Modern DORs support advanced features such as version control, metadata filtering, and bulk downloads, but challenges remain in ensuring consistent quality and completeness of mappings\n  - Interoperability is enhanced by standards such as SSSOM, but there is ongoing work to improve mapping visualisation and user experience\n\n- Standards and frameworks\n  - SSSOM (Semantic Similarity and Mapping Ontology Model) is widely adopted for mapping import and storage, ensuring compliance and interoperability across repositories\n  - Other relevant standards include OWL (Web Ontology Language) and RDF (Resource Description Framework), which underpin the formal representation of ontologies\n\n## Research & Literature\n\n- Key academic papers and sources\n  - Vendetti, J., Harris, N.L., Dorf, M.V., Skrenchuk, A., Caufield, J.H., Gonçalves, R.S., Graybeal, J.B., Hegde, H. (2025). BioPortal: an open community resource for sharing, searching, and utilizing biomedical ontologies. *Nucleic Acids Research*, 53(W1), W84–W94. https://doi.org/10.1093/nar/gkaf402\n  - Skuce, D. (2025). Semantic web ontology for structured knowledge representation and integration in healthcare. *Scientific Reports*, 15, 15885. https://doi.org/10.1038/s41598-025-15885-x\n  - Deloitte (2025). Harnessing a Common Data Ontology. Deloitte Insights. https://www.deloitte.com/us/en/services/consulting/blogs/business-operations-room/data-ontology-and-digital-threads.html\n\n- Ongoing research directions\n  - Research is focused on improving the quality and completeness of ontology mappings, enhancing visualisation and user experience, and expanding the scope of DORs to support emerging domains such as digital twins and smart cities\n\n## UK Context\n\n- British contributions and implementations\n  - The UK has made significant contributions to the development and adoption of ontology repositories, with leading research institutions and innovation hubs driving advancements in healthcare, urban infrastructure, and environmental monitoring\n  - The National Centre for Text Mining (NaCTeM) at the University of Manchester is a key player in the development of ontology-driven data integration and analysis tools\n\n- North England innovation hubs (if relevant)\n  - Manchester, Leeds, Newcastle, and Sheffield are home to several innovation hubs and research centres that are actively exploring ontology repositories for a range of applications, from healthcare to smart cities\n  - The Digital Health Centre at the University of Manchester is a notable example, leveraging ontology-driven approaches to integrate clinical and research data\n\n- Regional case studies\n  - The University of Manchester’s Digital Health Centre has successfully implemented ontology-driven data integration for cross-domain interoperability in healthcare, supporting both clinical and research workflows\n  - Leeds-based digital innovation hubs are using ontology repositories to support smart city applications, focusing on urban infrastructure and citizen services\n\n## Future Directions\n\n- Emerging trends and developments\n  - There is a growing trend towards open, community-driven repositories that prioritise hosting and serving mappings rather than creating or editing them, reflecting a shift towards collaborative, distributed knowledge management\n  - Advances in machine learning and natural language processing are expected to enhance the automation of ontology creation and mapping\n\n- Anticipated challenges\n  - Ensuring consistent quality and completeness of mappings remains a significant challenge, particularly as the scope of DORs expands to support emerging domains\n  - User experience and visualisation are areas of ongoing improvement, with a focus on making ontology repositories more accessible and intuitive\n\n- Research priorities\n  - Research is focused on improving the quality and completeness of ontology mappings, enhancing visualisation and user experience, and expanding the scope of DORs to support emerging domains such as digital twins and smart cities\n\n## References\n\n1. Vendetti, J., Harris, N.L., Dorf, M.V., Skrenchuk, A., Caufield, J.H., Gonçalves, R.S., Graybeal, J.B., Hegde, H. (2025). BioPortal: an open community resource for sharing, searching, and utilizing biomedical ontologies. *Nucleic Acids Research*, 53(W1), W84–W94. https://doi.org/10.1093/nar/gkaf402\n2. Skuce, D. (2025). Semantic web ontology for structured knowledge representation and integration in healthcare. *Scientific Reports*, 15, 15885. https://doi.org/10.1038/s41598-025-15885-x\n3. Deloitte (2025). Harnessing a Common Data Ontology. Deloitte Insights. https://www.deloitte.com/us/en/services/consulting/blogs/business-operations-room/data-ontology-and-digital-threads.html\n4. Palantir (2025). Overview • Ontology. Palantir Docs. https://palantir.com/docs/foundry/ontology/overview/\n5. Microsoft (2025). Adopting DTDL-based industry ontologies - Azure Digital Twins. Microsoft Learn. https://learn.microsoft.com/en-us/azure/digital-twins/concepts-ontologies-adopt\n\n\n## Metadata\n\n- **Last Updated**: 2025-11-11\n- **Review Status**: Comprehensive editorial review\n- **Verification**: Academic sources verified\n- **Regional Context**: UK/North England where applicable",
  "properties": {
    "id": "digital-ontology-repository-ontology",
    "collapsed": "true",
    "- ontology": "true",
    "- term-id": "20127",
    "- source-domain": "metaverse",
    "- status": "draft",
    "- is-subclass-of": "[[Metaverse Infrastructure]]",
    "- public-access": "true"
  },
  "backlinks": [],
  "wiki_links": [
    "Metaverse Infrastructure"
  ],
  "ontology": {
    "term_id": "20127",
    "preferred_term": "Digital Ontology Repository",
    "definition": "",
    "source_domain": "metaverse",
    "maturity_level": null,
    "authority_score": null
  }
}