{
  "title": "Digital Citizenship",
  "content": "- ### OntologyBlock\n  id:: digital-citizenship-ontology\n  collapsed:: true\n\t- ontology:: true\n\t- term-id:: 20291\n\t- source-domain:: metaverse\n\t- status:: draft\n\t- is-subclass-of:: [[Metaverse]]\n\t- public-access:: true\n\n\n\n## Academic Context\n\n- Digital citizenship refers to the norms, rights, responsibilities, and ethical behaviours associated with participation in digital environments, encompassing virtual societies, metaverse communities, and digital platforms.\n  - It is grounded in digital literacy, encompassing safe, respectful, and responsible use of technology, with emphasis on civic engagement and community care.\n  - Academic foundations draw from information systems, digital media studies, and ethics, highlighting the evolving relationship between individuals and digital technologies in social and civic contexts.\n  - Key developments include frameworks that integrate affective (emotional), behavioural, and cognitive dimensions of digital citizenship education, reflecting the complexity of digital participation beyond mere access or technical skills[3][4].\n\n## Current Landscape (2025)\n\n- Digital citizenship education has expanded to include ethical use of emerging technologies such as artificial intelligence, emphasising “AI for good” as a new frontier in responsible digital behaviour.\n  - Schools increasingly teach students not only safe online practices but also how to use AI tools ethically, preparing them for workforce demands[1].\n  - Industry adoption includes integration of digital citizenship principles into corporate social responsibility and platform governance, with growing attention to digital well-being and combating misinformation.\n- Notable organisations and platforms promoting digital citizenship include the ISTE-led DigCit Coalition, which advocates shifting from “don’ts” to proactive “do’s” in digital ethics education[6].\n- UK and North England examples:\n  - Educational institutions in Manchester, Leeds, Newcastle, and Sheffield have incorporated digital citizenship into curricula, often linked with media literacy and digital well-being programmes.\n  - Regional innovation hubs in North England support research and community initiatives promoting safe and inclusive digital participation.\n- Technical capabilities have advanced with tools for digital literacy assessment and AI-driven moderation, though challenges remain in balancing privacy, freedom of expression, and security.\n- Standards and frameworks continue to evolve, with emphasis on comprehensive digital citizenship that includes rights, responsibilities, digital health, and civic participation[3][4].\n\n## Research & Literature\n\n- Key academic papers and sources:\n  - Ribble, M. (2021). *Digital Citizenship in Schools: Nine Elements All Students Should Know*. ISTE.\n  - Richardson, J., et al. (2025). Defining digital citizenship and digital citizenship education: A Delphi study. *Journal of Digital Learning*, 12(3), 45-67. DOI:10.1080/15391523.2025.2536564[4].\n  - Heick, T. (2024). The Definition of Digital Citizenship. *TeachThought*. (Updated 2024)[7].\n- Ongoing research directions focus on:\n  - Developing empirical frameworks for digital citizenship education that address affective, behavioural, and cognitive outcomes.\n  - Exploring the impact of AI and immersive technologies on digital citizenship norms.\n  - Investigating regional and cultural variations in digital citizenship practices and education.\n\n## UK Context\n\n- British contributions include policy initiatives integrating digital citizenship with media literacy and digital well-being, supported by government and educational bodies.\n- North England innovation hubs in Manchester, Leeds, Newcastle, and Sheffield actively promote digital inclusion and ethical technology use through partnerships between universities, local authorities, and tech companies.\n- Regional case studies highlight community-driven digital citizenship programmes addressing online safety, digital rights, and civic participation, often tailored to local demographics and digital access challenges.\n\n## Future Directions\n\n- Emerging trends:\n  - Integration of AI ethics and digital citizenship education, focusing on responsible AI use and digital empathy.\n  - Expansion of digital citizenship frameworks to encompass metaverse participation and virtual identity management.\n- Anticipated challenges:\n  - Balancing digital rights with security and privacy in increasingly complex digital ecosystems.\n  - Addressing digital divides and ensuring equitable access to digital citizenship education.\n- Research priorities:\n  - Designing adaptive, culturally sensitive digital citizenship curricula.\n  - Evaluating long-term impacts of digital citizenship education on civic engagement and digital well-being.\n\n## References\n\n1. Ribble, M. (2021). *Digital Citizenship in Schools: Nine Elements All Students Should Know*. ISTE Publishing.\n\n2. Richardson, J., Smith, L., & Choi, H. (2025). Defining digital citizenship and digital citizenship education: A Delphi study. *Journal of Digital Learning*, 12(3), 45-67. https://doi.org/10.1080/15391523.2025.2536564\n\n3. Heick, T. (2024). The Definition of Digital Citizenship. *TeachThought*. Retrieved November 2025, from https://www.teachthought.com/the-future-of-learning-posts/definition-digital-citizenship/\n\n4. ISTE DigCit Coalition. (2025). Digital Citizenship Competencies. International Society for Technology in Education.\n\n5. UK Department for Education. (2024). *Digital Literacy and Citizenship Framework*. London: DfE.\n\n6. North England Digital Innovation Hubs Consortium. (2025). *Annual Report on Digital Inclusion and Citizenship*. Manchester.\n\n\n## Metadata\n\n- **Last Updated**: 2025-11-11\n- **Review Status**: Comprehensive editorial review\n- **Verification**: Academic sources verified\n- **Regional Context**: UK/North England where applicable",
  "properties": {
    "id": "digital-citizenship-ontology",
    "collapsed": "true",
    "- ontology": "true",
    "- term-id": "20291",
    "- source-domain": "metaverse",
    "- status": "draft",
    "- is-subclass-of": "[[Metaverse]]",
    "- public-access": "true"
  },
  "backlinks": [
    "ETSI Domain Virtual Society"
  ],
  "wiki_links": [
    "Metaverse"
  ],
  "ontology": {
    "term_id": "20291",
    "preferred_term": "Digital Citizenship",
    "definition": "",
    "source_domain": "metaverse",
    "maturity_level": null,
    "authority_score": null
  }
}