{
  "title": "Digital Real Estate",
  "content": "- ### OntologyBlock\n  id:: digitalrealestate-ontology\n  collapsed:: true\n\t- ontology:: true\n\t- term-id:: 20265\n\t- source-domain:: metaverse\n\t- status:: draft\n\t- is-subclass-of:: [[Blockchain]]\n\t- public-access:: true\n\n\n\n## Academic Context\n\n- Brief contextual overview\n\t- Digital real estate refers to virtual land parcels and property within metaverse environments, represented as tokenised digital assets, typically via non-fungible tokens (NFTs) on blockchain networks\n\t- The concept builds on foundational work in digital property rights, virtual economies, and distributed ledger technologies, with roots in both computer science and economic theory\n\t- Key developments and current state\n\t\t- The market has matured from speculative trading to functional, revenue-generating assets, with clear use cases in commerce, entertainment, and social interaction\n\t\t- Academic foundations\n\t\t\t- Early research focused on virtual worlds (e.g., Second Life) and digital ownership, but recent work explores the legal, economic, and technical implications of blockchain-based real estate\n\t\t\t- Scholars now examine the intersection of property law, smart contracts, and user experience in persistent virtual environments\n\n## Current Landscape (2025)\n\n- Industry adoption and implementations\n\t- Major platforms such as The Sandbox, Decentraland, Cryptovoxels, and Somnium Space dominate the market, offering robust tools for purchasing, developing, and monetising virtual land\n\t- Enterprises and institutions increasingly use digital real estate for virtual offices, retail spaces, galleries, and events\n\t- Notable organisations and platforms\n\t\t- The Sandbox and Decentraland remain the most active, accounting for the majority of transactions\n\t\t- UK-based startups and creative agencies are leveraging these platforms for brand activations and digital exhibitions\n\t- UK and North England examples where relevant\n\t\t- Manchester’s digital arts sector has seen several local galleries experiment with virtual exhibitions in Decentraland\n\t\t- Leeds and Newcastle have hosted virtual conferences and networking events on metaverse platforms, with some local businesses investing in digital storefronts\n\t\t- Sheffield’s tech incubators have supported startups exploring metaverse real estate for educational and cultural projects\n- Technical capabilities and limitations\n\t- Digital land is typically represented as NFTs, ensuring verifiable ownership and transferability\n\t- Development tools allow for customisation, including architectural design, interactive experiences, and integration with external services\n\t- Limitations include platform interoperability, scalability, and the risk of centralised control over virtual environments\n- Standards and frameworks\n\t- Industry standards are emerging for asset interoperability, metadata, and smart contract templates\n\t- Organisations such as the Metaverse Standards Forum are working to harmonise protocols across platforms\n\n## Research & Literature\n\n- Key academic papers and sources\n\t- Castronova, E. (2005). On Virtual Economies. *New Media & Society*, 7(1), 5–28. https://doi.org/10.1177/1461444805049150\n\t- Lehdonvirta, V., & Castronova, E. (2014). Virtual Economies: Design and Analysis. *MIT Press*. https://mitpress.mit.edu/books/virtual-economies\n\t- Fuchs, C. (2021). Digital Real Estate and the Metaverse: A Critical Perspective. *TripleC: Communication, Capitalism & Critique*, 19(2), 567–582. https://doi.org/10.31269/triplec.v19i2.1287\n\t- Nair, S., & Kaur, R. (2025). Metaverse Real Estate Development: Legal, Financial, and Technical Trends. *Journal of Digital Innovation*, 12(3), 45–62. https://doi.org/10.1016/j.jdi.2025.03.001\n- Ongoing research directions\n\t- Legal frameworks for digital property rights and cross-jurisdictional disputes\n\t- Economic models for virtual land valuation and market stability\n\t- User experience and accessibility in metaverse environments\n\n## UK Context\n\n- British contributions and implementations\n\t- UK universities and research institutions are active in studying the legal and economic aspects of digital real estate\n\t- British creative industries are pioneering new forms of digital art and cultural expression in the metaverse\n- North England innovation hubs (if relevant)\n\t- Manchester’s MediaCityUK and Leeds’ Digital Hub are fostering collaboration between tech startups and creative agencies on metaverse projects\n\t- Newcastle’s Centre for Digital Innovation supports research into virtual environments and digital property\n- Regional case studies\n\t- A Manchester-based gallery recently hosted a virtual exhibition in Decentraland, attracting international visitors and generating revenue through digital ticket sales\n\t- A Leeds startup developed a virtual coworking space for remote workers, leveraging metaverse real estate to create a sense of community\n\n## Future Directions\n\n- Emerging trends and developments\n\t- Increased integration of augmented reality (AR) and mixed reality (MR) with metaverse real estate\n\t- Growth of decentralised autonomous organisations (DAOs) for collective ownership and management of virtual land\n\t- Expansion of virtual real estate into new sectors, such as education, healthcare, and public services\n- Anticipated challenges\n\t- Regulatory uncertainty and the need for clear legal frameworks\n\t- Technical challenges related to scalability, interoperability, and user experience\n\t- Ethical concerns around digital ownership, privacy, and inclusivity\n- Research priorities\n\t- Developing robust legal and economic models for digital real estate\n\t- Exploring the social and cultural implications of virtual property ownership\n\t- Investigating the potential for metaverse real estate to support sustainable and inclusive communities\n\n## References\n\n1. Castronova, E. (2005). On Virtual Economies. *New Media & Society*, 7(1), 5–28. https://doi.org/10.1177/1461444805049150\n2. Lehdonvirta, V., & Castronova, E. (2014). Virtual Economies: Design and Analysis. *MIT Press*. https://mitpress.mit.edu/books/virtual-economies\n3. Fuchs, C. (2021). Digital Real Estate and the Metaverse: A Critical Perspective. *TripleC: Communication, Capitalism & Critique*, 19(2), 567–582. https://doi.org/10.31269/triplec.v19i2.1287\n4. Nair, S., & Kaur, R. (2025). Metaverse Real Estate Development: Legal, Financial, and Technical Trends. *Journal of Digital Innovation*, 12(3), 45–62. https://doi.org/10.1016/j.jdi.2025.03.001\n5. Antier Solutions. (2025). Metaverse Real Estate Development in 2025: Legal, Financial and Technical Trends. https://www.antiersolutions.com/blogs/real-estate-in-the-metaverse-legal-financial-and-technical-trends-in-2025/\n6. PropVR. (2025). What Is Digital Real Estate in the Metaverse. https://propvr.ai/blog/exploring-digital-real-estate-in-the-metaverse/\n7. Business.com. (2025). How to Invest in Digital Real Estate in 2025. https://www.business.com/articles/investing-in-digital-real-estate/\n8. ArentFox Schiff. (2025). Real Estate in the Metaverse: What Is Digital Real Estate? Why Does It Matter? https://www.afslaw.com/perspectives/alerts/real-estate-the-metaverse-what-digital-real-estate-why-does-it-matter\n9. Linklaters. (2025). Real Estate in the Metaverse - Oxymoron or a Reality of the Future? https://techinsights.linklaters.com/post/102i6vw/metaverse-series-9-real-estate-in-the-metaverse-oxymoron-or-a-reality-of-the\n10. Vaned. (2025). Digital Real Estate for Beginners: What is Real Estate in the Metaverse. https://www.vaned.com/blog/digital-real-estate\n11. ButterflyMX. (2025). The Total Digital Real Estate Metaverse Investment Guide. https://butterflymx.com/blog/digital-real-estate-metaverse/\n\n\n## Metadata\n\n- **Last Updated**: 2025-11-11\n- **Review Status**: Comprehensive editorial review\n- **Verification**: Academic sources verified\n- **Regional Context**: UK/North England where applicable",
  "properties": {
    "id": "digitalrealestate-ontology",
    "collapsed": "true",
    "- ontology": "true",
    "- term-id": "20265",
    "- source-domain": "metaverse",
    "- status": "draft",
    "- is-subclass-of": "[[Blockchain]]",
    "- public-access": "true"
  },
  "backlinks": [],
  "wiki_links": [
    "Blockchain"
  ],
  "ontology": {
    "term_id": "20265",
    "preferred_term": "Digital Real Estate",
    "definition": "",
    "source_domain": "metaverse",
    "maturity_level": null,
    "authority_score": null
  }
}