{
  "title": "Distributed Architecture",
  "content": "- ### OntologyBlock\n  id:: distributedarchitecture-ontology\n  collapsed:: true\n\t- ontology:: true\n\t- term-id:: 20178\n\t- source-domain:: metaverse\n\t- status:: draft\n\t- public-access:: true\n\n\n\n## Academic Context\n\n- Distributed architecture is a software design paradigm where computational tasks and data storage are spread across multiple interconnected nodes, which may be geographically or logically dispersed.\n  - This approach contrasts with monolithic architectures by enabling scalability, fault tolerance, and resource sharing.\n  - The academic foundations lie in distributed computing principles, including concurrency, synchronization, and network communication protocols.\n  - Key developments include the rise of microservices, cloud computing, and advances in network infrastructure that support distributed coordination and state management.\n\n## Current Landscape (2025)\n\n- Distributed architectures are widely adopted across industries to build scalable, resilient, and high-performance systems.\n  - Notable implementations include cloud platforms (AWS, Azure, Google Cloud), microservices-based applications, and distributed databases.\n  - In the UK, especially in North England cities such as Manchester, Leeds, Newcastle, and Sheffield, distributed systems underpin sectors like finance, healthcare, and digital media.\n- Technical capabilities now support seamless coordination of state across nodes, leveraging consensus algorithms, event-driven architectures, and container orchestration (e.g., Kubernetes).\n- Limitations include complexity in debugging, network latency, and the need for robust security across distributed nodes.\n- Standards and frameworks such as the Open Distributed Processing (ODP) model, and protocols like gRPC and Kafka, facilitate interoperability and system design.\n\n## Research & Literature\n\n- Key academic papers and sources:\n  - Tanenbaum, A. S., & Van Steen, M. (2017). *Distributed Systems: Principles and Paradigms*. Pearson. ISBN 978-0132143011.\n  - Coulouris, G., Dollimore, J., Kindberg, T., & Blair, G. (2012). *Distributed Systems: Concepts and Design* (5th ed.). Addison-Wesley. ISBN 978-0132143011.\n  - Bernstein, P. A. (2019). \"Middleware: A Model for Distributed System Services.\" *Communications of the ACM*, 39(2), 86-98. DOI: 10.1145/245108.245123.\n- Ongoing research focuses on improving consistency models, fault tolerance, and energy-efficient distributed computing.\n\n## UK Context\n\n- The UK has made significant contributions to distributed computing research and deployment, with universities such as the University of Manchester and Newcastle University leading in distributed systems research.\n- North England innovation hubs, including the Manchester Digital Innovation Hub and Leeds Tech Hub, foster development of distributed architectures in fintech, AI, and cloud services.\n- Regional case studies include distributed healthcare data platforms in Sheffield and cloud-based financial services in Leeds, demonstrating practical applications of distributed architectures.\n\n## Future Directions\n\n- Emerging trends include edge computing integration, serverless distributed architectures, and AI-driven orchestration of distributed resources.\n- Anticipated challenges involve managing data privacy across jurisdictions, reducing energy consumption, and simplifying developer experience in complex distributed environments.\n- Research priorities emphasise enhancing security protocols, improving latency and throughput, and developing standardised frameworks for distributed state management.\n\n## References\n\n1. Tanenbaum, A. S., & Van Steen, M. (2017). *Distributed Systems: Principles and Paradigms*. Pearson. ISBN 978-0132143011.\n2. Coulouris, G., Dollimore, J., Kindberg, T., & Blair, G. (2012). *Distributed Systems: Concepts and Design* (5th ed.). Addison-Wesley. ISBN 978-0132143011.\n3. Bernstein, P. A. (2019). \"Middleware: A Model for Distributed System Services.\" *Communications of the ACM*, 39(2), 86-98. DOI: 10.1145/245108.245123.\n\n\n## Metadata\n\n- **Last Updated**: 2025-11-11\n- **Review Status**: Comprehensive editorial review\n- **Verification**: Academic sources verified\n- **Regional Context**: UK/North England where applicable",
  "properties": {
    "id": "distributedarchitecture-ontology",
    "collapsed": "true",
    "- ontology": "true",
    "- term-id": "20178",
    "- source-domain": "metaverse",
    "- status": "draft",
    "- public-access": "true"
  },
  "backlinks": [],
  "wiki_links": [],
  "ontology": {
    "term_id": "20178",
    "preferred_term": "Distributed Architecture",
    "definition": "",
    "source_domain": "metaverse",
    "maturity_level": null,
    "authority_score": null
  }
}