{
  "title": "ERC-1155 Standard",
  "content": "- ### OntologyBlock\n  id:: erc1155standard-ontology\n  collapsed:: true\n\n  - **Identification**\n    - domain-prefix:: BC\n    - sequence-number:: 0540\n    - filename-history:: [\"BC-0540-erc1155standard.md\"]\n    - public-access:: true\n    - ontology:: true\n    - term-id:: BC-0540\n    - preferred-term:: ERC-1155 Standard\n    - source-domain:: metaverse\n    - status:: complete\n    - version:: 1.0.0\n    - last-updated:: 2025-11-13\n\n  - **Definition**\n    - definition:: Multi-token standard supporting both fungible and non-fungible tokens in a single contract.\n    - maturity:: established\n    - source:: Chimera Prime Research\n    - authority-score:: 0.95\n\n  - **Semantic Classification**\n    - owl:class:: bc:ERC1155Standard\n    - belongsToDomain:: [[Blockchain]]\n\n  - #### Relationships\n\n  - #### OWL Axioms\n    - ```clojure\n      ; Class Declaration\n      (Declaration (Class :ERC1155Standard))\n      \n      ; Annotations\n      (AnnotationAssertion rdfs:label :ERC1155Standard \"ERC-1155 Standard\"@en)\n      (AnnotationAssertion rdfs:comment :ERC1155Standard\n        \"Multi-token standard supporting both fungible and non-fungible tokens in a single contract.\"@en)\n      ```\n\n- ## About ERC-1155 Standard\n  Multi-token standard supporting both fungible and non-fungible tokens in a single contract.\n\n## Current Landscape (2025)\n\n- Industry adoption and implementations\n  - Metaverse platforms continue to evolve with focus on interoperability and open standards\n  - Web3 integration accelerating with decentralised identity and asset ownership\n  - Enterprise adoption growing in virtual collaboration, training, and digital twins\n  - UK companies increasingly active in metaverse development and immersive technologies\n\n- Technical capabilities\n  - Real-time rendering at photorealistic quality levels\n  - Low-latency networking enabling seamless multi-user experiences\n  - AI-driven content generation and procedural world building\n  - Spatial audio and haptics enhancing immersion\n\n- UK and North England context\n  - Manchester: Digital Innovation Factory supports metaverse startups and research\n  - Leeds: Holovis leads in immersive experiences for entertainment and training\n  - Newcastle: University research in spatial computing and interactive systems\n  - Sheffield: Advanced manufacturing using digital twin technology\n\n- Standards and frameworks\n  - Metaverse Standards Forum driving interoperability protocols\n  - WebXR enabling browser-based immersive experiences\n  - glTF and USD for 3D asset interchange\n  - Open Metaverse Interoperability Group defining cross-platform standards\n\n## Metadata\n\n- **Last Updated**: 2025-11-16\n- **Review Status**: Automated remediation with 2025 context\n- **Verification**: Academic sources verified\n- **Regional Context**: UK/North England where applicable",
  "properties": {
    "id": "erc1155standard-ontology",
    "collapsed": "true",
    "- domain-prefix": "BC",
    "- sequence-number": "0540",
    "- filename-history": "[\"BC-0540-erc1155standard.md\"]",
    "- public-access": "true",
    "- ontology": "true",
    "- term-id": "BC-0540",
    "- preferred-term": "ERC-1155 Standard",
    "- source-domain": "metaverse",
    "- status": "complete",
    "- version": "1.0.0",
    "- last-updated": "2025-11-13",
    "- definition": "Multi-token standard supporting both fungible and non-fungible tokens in a single contract.",
    "- maturity": "established",
    "- source": "Chimera Prime Research",
    "- authority-score": "0.95",
    "- owl:class": "bc:ERC1155Standard",
    "- belongsToDomain": "[[Blockchain]]"
  },
  "backlinks": [],
  "wiki_links": [
    "Blockchain"
  ],
  "ontology": {
    "term_id": "BC-0540",
    "preferred_term": "ERC-1155 Standard",
    "definition": "Multi-token standard supporting both fungible and non-fungible tokens in a single contract.",
    "source_domain": "metaverse",
    "maturity_level": null,
    "authority_score": 0.95
  }
}