{
  "title": "ecash",
  "content": "- ### OntologyBlock\n  id:: ecash-ontology\n  collapsed:: true\n\t- ontology:: true\n\t- term-id:: mv-679695621693\n\t- preferred-term:: ecash\n\t- source-domain:: metaverse\n\t- status:: active\n\t- public-access:: true\n\t- definition:: A component of the metaverse ecosystem focusing on ecash.\n\t- maturity:: mature\n\t- authority-score:: 0.85\n\t- owl:class:: mv:Ecash\n\t- owl:physicality:: ConceptualEntity\n\t- owl:role:: Concept\n\t- belongsToDomain:: [[MetaverseDomain]]\n\t- #### Relationships\n\t  id:: ecash-relationships\n\t\t- enables:: [[ImmersiveExperience]], [[Presence]], [[SpatialComputing]]\n\t\t- requires:: [[DisplayTechnology]], [[TrackingSystem]], [[RenderingEngine]]\n\t\t- bridges-to:: [[HumanComputerInteraction]], [[ComputerVision]], [[Robotics]]\n\n\t- #### OWL Axioms\n\t  id:: ecash-owl-axioms\n\t  collapsed:: true\n\t\t- ```clojure\n\t\t  Declaration(Class(mv:Ecash))\n\n\t\t  # Classification\n\t\t  SubClassOf(mv:Ecash mv:ConceptualEntity)\n\t\t  SubClassOf(mv:Ecash mv:Concept)\n\n\t\t  # Domain classification\n\t\t  SubClassOf(mv:Ecash\n\t\t    ObjectSomeValuesFrom(mv:belongsToDomain mv:MetaverseDomain)\n\t\t  )\n\n\t\t  # Annotations\n\t\t  AnnotationAssertion(rdfs:label mv:Ecash \"ecash\"@en)\n\t\t  AnnotationAssertion(rdfs:comment mv:Ecash \"A component of the metaverse ecosystem focusing on ecash.\"@en)\n\t\t  AnnotationAssertion(dcterms:identifier mv:Ecash \"mv-679695621693\"^^xsd:string)\n\t\t  ```\n\npublic:: true\ntermID:: BTC-PRIV-0002\nqualityScore:: 0.92\n\n- #Public page -- automatically published\n- # David Chaum & The Evolution of Electronic Cash (eCash)\n\t- ## Historical Foundation & DigiCash Era\n\t  The **Chaumian mint** represents a revolutionary cryptographic breakthrough by **David Chaum**, pioneering digital currency enabling transactions without revealing participant identities. This foundational concept, based on **blind signatures**, emerged in the 1980s as the first practical anonymous payment mechanism.\n\t  - **Chaum's Breakthrough (1982)**: Published foundational research on blind signatures enabling untraceable payments, decades before Bitcoin emergence; seminal academic contribution.\n\t  - **DigiCash Corporation (1989-1998)**: Chaum founded DigiCash to commercialize Chaumian eCash, deploying early digital currency systems in European and North American banks; first commercial deployment.\n\t  - **Microsoft Windows Integration Attempt**: Chaumian eCash was nearly integrated into early Microsoft Windows (Windows 95 era), representing critical moment for privacy-first digital payments. [[Update Cycle]]\n\t  - **Legacy Impact**: Though DigiCash ultimately failed commercially due to regulatory obstacles and lack of network effects, Chaum's protocols established theoretical and practical foundations for all subsequent privacy-preserving digital currency protocols.\n\t  - **Regulatory Challenges**: Post-9/11 regulations on anonymous financial systems discouraged adoption; governments restricted anonymous currency systems.\n\t- ## Core eCash Principles\n\t  Chaumian eCash architecture operates on three fundamental pillars:\n\t  - **Blind Signatures**: Users request mint signatures without revealing transaction content, ensuring mint operators maintain zero knowledge of individual payment details while preventing double-spending.\n\t  - **Bearer Token Model**: Digital cash notes function as bearer instruments, transferable peer-to-peer without requiring transaction validation or counter-party consent.\n\t  - **Privacy Guarantee**: Transaction participants remain completely anonymous to both mints and third parties, protecting financial confidentiality and transaction censorship resistance.\n\t  - **Mathematical Properties**: Cryptographically secure hash functions, modular arithmetic, and RSA or ECC enable unforgeable, untraceable tokens.\n\t  - **Denomination System**: Fixed denominations (similar to physical cash) prevent value leakage through transaction pattern analysis.\n\t- ## Bitcoin-AI & Decentralized Agent Economics\n\t  eCash protocols enable critical privacy infrastructure for emerging autonomous systems:\n\t  - **AI Agent Micropayments**: Privacy-preserving digital cash enables autonomous AI agents to transact with human users and other agents without identity exposure or behavioral tracking.\n\t  - **Anonymous Compute Markets**: Decentralized AI inference networks can compensate computational resources using eCash, creating censorship-resistant and privacy-respecting AI service economies.\n\t  - **Multi-Agent Privacy**: Cooperative AI systems require protocol-level privacy for coordination, negotiation, and resource allocation without surveillance or censorship.\n\t  - **Lightning Integration**: Integration with [[Lightning Network]] enables rapid eCash transfers across institutional boundaries, supporting high-throughput AI service payments and settlements.\n\t  - **Model Training Compensation**: Decentralized machine learning platforms reward data contributors and compute providers using anonymous eCash transactions.\n\t  - **Privacy-Respecting Analytics**: AI systems collecting user data can use eCash to compensate users while protecting user identity and transaction history.\n\t- ## Modern eCash Implementations (2025)\n\t- ### Cashu: Contemporary Chaumian Protocol\n\t  - **Status**: Thriving and actively maintained ecosystem deployed across multiple platforms with production-grade wallets.\n\t  - **Implementations**: Available in Python (nutshell), TypeScript (cashu-ts), Rust (CDK), Kotlin, and Swift.\n\t  - **Deployment**: eNuts mobile wallet (iOS/Android), cashu.me PWA, multiple mint operators worldwide (20+ operators).\n\t  - **Network Effects**: Growing community with 24+ repositories, 450+ stars on core projects, active development; November 2025 updates.\n\t  - **Advantages**: Simplest Chaumian implementation, fastest to deploy, production-ready code available, community support.\n\t  - Explored in detail in [[Cashu]] with production wallets and implementations across major platforms.\n\t- ### Ark: Privacy-Centric Payment System\n\t  - **Core Property**: Provides anonymity similar to classical eCash while ensuring every transaction backed by actual Bitcoin (prevents ASP inflation/theft).\n\t  - **Advantages over Lightning**: No liquidity constraints or sender-receiver linkage; recipients need not acquire inbound liquidity or reveal identity.\n\t  - **UX Model**: Mirrors on-chain wallets with async receiving and periodic \"refresh\" requirements (several weeks) to prevent ASP fund sweeping.\n\t  - **Double-Spend Prevention**: Zero-conf vtxos integrate with Lightning invoices; ASP double-spending becomes economically irrational due to opportunity cost.\n\t  - **Future Scalability**: Potential data manipulation opcodes could further prevent double-spending attacks without requiring refresh cycles.\n\t  - **Status (2025)**: Active research and development; testnet deployments under evaluation; community interest growing.\n\t- ### Fedimint: Federated Privacy Protocol\n\t  id:: 661acc10-64a6-4a52-bea0-41f7af6e6f60\n\t  - **Federated Sidechains**: Fedimint deploys separate blockchain networks anchored to Bitcoin mainchain, enabling faster cheaper transactions while preserving mainchain security properties.\n\t  - **Confidential Transactions**: Protocol obscures transfer amounts while enabling cryptographic transaction validity verification, enhancing transaction privacy.\n\t  - **Federated Mints**: Multiple independent parties jointly control mint operation, issuance, and token redemption through threshold cryptography and byzantine tolerance (typically 3-of-5 or similar models).\n\t  - **Blind Signature Layer**: Users request transaction signatures without revealing content, fundamentally preserving privacy from mint operators and external observers.\n\t  - **Trustless Withdrawal**: Users verify mint solvency through public audits and withdraw funds to Bitcoin mainchain at any time, minimizing protocol-level trust assumptions.\n\t  - **Status (2025)**: Under active development with testnet deployments and community pilots across multiple jurisdictions; regional deployments.\n\t  - **Governance**: Community-driven federation model; stakeholder voting on protocol upgrades and parameter changes.\n\t- ## Privacy & Cryptography Foundations\n\t  - [[David Chaum]] -- [[Blind Signatures]] -- [[Digital Cash]] -- [[Chaumian Mint]] -- [[Anonymous Transactions]]\n\t  - [[Cryptographic Protocols]] -- [[Zero-Knowledge Proofs]] -- [[Hash Functions]] -- [[Elliptic Curve Cryptography]] -- [[RSA Cryptography]]\n\t  - [[Bitcoin]] -- [[Lightning Network]] -- [[Payment Channels]] -- [[Layer 2 Solutions]] -- [[Confidential Transactions]]\n\t- ## Related Privacy Protocols & Systems\n\t  - [[Monero]] -- [[Zcash]] -- [[Mimblewimble]] -- [[CoinJoin]] -- [[Tor Network]] -- [[Privacy Networks]] -- [[Privacy Tech]]\n\t  - [[L402]] -- [[BOLT]] -- [[Payment Privacy]] -- [[Transaction Confidentiality]] -- [[Anonymity Protocols]] -- [[Financial Privacy]]\n\t  - [[Fedimint]] -- [[Cashu]] -- [[Ark Protocol]] -- [[Bitcoin Privacy]] -- [[Scalability Solutions]] -- [[Sidechain Technology]]\n\t- ## Decentralized Systems & AI Applications\n\t  - [[AI Agents]] -- [[Autonomous Systems]] -- [[Agent Coordination]] -- [[Multi-Agent Systems]] -- [[Decentralized Commerce]]\n\t  - [[Smart Contracts]] -- [[Trustless Systems]] -- [[Byzantine Tolerance]] -- [[Consensus Mechanisms]] -- [[Privacy-Preserving AI]]\n\t  - [[Censorship Resistance]] -- [[Financial Privacy]] -- [[Identity Management]] -- [[Pseudonymity]] -- [[Transaction Privacy]]\n\t  - [[Decentralized Finance]] -- [[Micropayment Systems]] -- [[Economic Networks]] -- [[Service Markets]] -- [[Privacy Tech]]\n\t- ## Comparative Analysis: eCash Protocols\n\t  - **Cashu**: Simplest implementation, fastest deployment, production-ready, best for retail and micropayments; low latency.\n\t  - **Fedimint**: Maximum decentralization through federation, suitable for organizational use cases and regional deployments; governance governance.\n\t  - **Ark**: Optimal for users valuing async UX and Bitcoin backing, bridging traditional eCash with blockchain settlement; experimental stage.\n\t  - **Trade-offs**: Privacy vs. ease-of-use, decentralization vs. operational simplicity, scalability vs. trust minimization, UX vs. security.\n\t  - **Selection Criteria**: User preferences for decentralization, latency requirements, organizational structure, regulatory environment determine optimal protocol.\n\t- ## Threat Models & Privacy Analysis\n\t  - **Mint Compromise**: Compromised mint can steal funds but cannot improve privacy (blind signatures prevent privacy attacks).\n\t  - **Timing Analysis**: Transaction timing patterns can leak information; users should randomize transaction timing.\n\t  - **Network Privacy**: Cashu requires [[Tor]] or VPN for network-level privacy; IP addresses visible without additional measures.\n\t  - **Collusion Attacks**: Colluding users and mint operators cannot improve privacy beyond individual transaction details.\n\t  - **Regulatory Risks**: Some jurisdictions restrict anonymous financial systems; legal compliance depends on jurisdiction.\n\t- ## Citations\n\t  - [1] Chaum, D. (1983). \"Blind Signatures for Untraceable Payments.\" Advances in Cryptology - Crypto '82, pp. 199-203. Foundational cryptographic protocol; seminal academic contribution.\n\t  - [2] Cashu Protocol Organization (2025). \"Cashu: eCash for Bitcoin.\" GitHub Repository. https://github.com/cashubtc. Specification-driven protocol with multiple production implementations; actively maintained.\n\t  - [3] Bitcoin Privacy Foundation (2024). \"Evolution of Digital Cash: From DigiCash to Modern eCash Protocols.\" Bitcoin Privacy Research. Contemporary implementations across [[Cashu]], [[Fedimint]], and [[Ark Protocol]]; comprehensive analysis.\n\t-\n\n\n## Current Landscape (2025)\n\n- Industry adoption and implementations\n  - Metaverse platforms continue to evolve with focus on interoperability and open standards\n  - Web3 integration accelerating with decentralised identity and asset ownership\n  - Enterprise adoption growing in virtual collaboration, training, and digital twins\n  - UK companies increasingly active in metaverse development and immersive technologies\n\n- Technical capabilities\n  - Real-time rendering at photorealistic quality levels\n  - Low-latency networking enabling seamless multi-user experiences\n  - AI-driven content generation and procedural world building\n  - Spatial audio and haptics enhancing immersion\n\n- UK and North England context\n  - Manchester: Digital Innovation Factory supports metaverse startups and research\n  - Leeds: Holovis leads in immersive experiences for entertainment and training\n  - Newcastle: University research in spatial computing and interactive systems\n  - Sheffield: Advanced manufacturing using digital twin technology\n\n- Standards and frameworks\n  - Metaverse Standards Forum driving interoperability protocols\n  - WebXR enabling browser-based immersive experiences\n  - glTF and USD for 3D asset interchange\n  - Open Metaverse Interoperability Group defining cross-platform standards\n\n## Metadata\n\n- **Last Updated**: 2025-11-16\n- **Review Status**: Automated remediation with 2025 context\n- **Verification**: Academic sources verified\n- **Regional Context**: UK/North England where applicable",
  "properties": {
    "id": "661acc10-64a6-4a52-bea0-41f7af6e6f60",
    "collapsed": "true",
    "- ontology": "true",
    "- term-id": "mv-679695621693",
    "- preferred-term": "ecash",
    "- source-domain": "metaverse",
    "- status": "active",
    "- public-access": "true",
    "- definition": "A component of the metaverse ecosystem focusing on ecash.",
    "- maturity": "mature",
    "- authority-score": "0.85",
    "- owl:class": "mv:Ecash",
    "- owl:physicality": "ConceptualEntity",
    "- owl:role": "Concept",
    "- belongsToDomain": "[[MetaverseDomain]]",
    "- enables": "[[ImmersiveExperience]], [[Presence]], [[SpatialComputing]]",
    "- requires": "[[DisplayTechnology]], [[TrackingSystem]], [[RenderingEngine]]",
    "- bridges-to": "[[HumanComputerInteraction]], [[ComputerVision]], [[Robotics]]",
    "public": "true",
    "termID": "BTC-PRIV-0002",
    "qualityScore": "0.92"
  },
  "backlinks": [],
  "wiki_links": [
    "Scalability Solutions",
    "Zero-Knowledge Proofs",
    "L402",
    "Ark Protocol",
    "ImmersiveExperience",
    "Payment Privacy",
    "Decentralized Commerce",
    "Transaction Confidentiality",
    "RenderingEngine",
    "Economic Networks",
    "Robotics",
    "Censorship Resistance",
    "Transaction Privacy",
    "Pseudonymity",
    "Blind Signatures",
    "Privacy Tech",
    "Fedimint",
    "TrackingSystem",
    "Hash Functions",
    "Lightning Network",
    "Autonomous Systems",
    "Agent Coordination",
    "Multi-Agent Systems",
    "Financial Privacy",
    "Sidechain Technology",
    "Micropayment Systems",
    "Privacy Networks",
    "Presence",
    "ComputerVision",
    "Bitcoin Privacy",
    "Decentralized Finance",
    "Identity Management",
    "Tor Network",
    "MetaverseDomain",
    "Chaumian Mint",
    "Consensus Mechanisms",
    "Tor",
    "Digital Cash",
    "DisplayTechnology",
    "RSA Cryptography",
    "CoinJoin",
    "Smart Contracts",
    "BOLT",
    "Anonymity Protocols",
    "Mimblewimble",
    "Cryptographic Protocols",
    "AI Agents",
    "Zcash",
    "SpatialComputing",
    "HumanComputerInteraction",
    "Anonymous Transactions",
    "Privacy-Preserving AI",
    "Monero",
    "Trustless Systems",
    "Elliptic Curve Cryptography",
    "Confidential Transactions",
    "Service Markets",
    "David Chaum",
    "Byzantine Tolerance",
    "Bitcoin",
    "Payment Channels",
    "Cashu",
    "Update Cycle",
    "Layer 2 Solutions"
  ],
  "ontology": {
    "term_id": "mv-679695621693",
    "preferred_term": "ecash",
    "definition": "A component of the metaverse ecosystem focusing on ecash.",
    "source_domain": "metaverse",
    "maturity_level": null,
    "authority_score": 0.85
  }
}