{
  "title": "EconomicLayer",
  "content": "- ### OntologyBlock\n  id:: economiclayer-ontology\n  collapsed:: true\n\t- ontology:: true\n\t- term-id:: mv-16107575907\n\t- preferred-term:: EconomicLayer\n\t- source-domain:: metaverse\n\t- status:: active\n\t- public-access:: true\n\t- definition:: A component of the metaverse ecosystem focusing on economiclayer.\n\t- maturity:: mature\n\t- authority-score:: 0.85\n\t- owl:class:: mv:Economiclayer\n\t- owl:physicality:: ConceptualEntity\n\t- owl:role:: Concept\n\t- belongsToDomain:: [[MetaverseDomain]]\n\t- #### Relationships\n\t  id:: economiclayer-relationships\n\t\t- enables:: [[ImmersiveExperience]], [[Presence]], [[SpatialComputing]]\n\t\t- requires:: [[DisplayTechnology]], [[TrackingSystem]], [[RenderingEngine]]\n\t\t- bridges-to:: [[HumanComputerInteraction]], [[ComputerVision]], [[Robotics]]\n\n\t- #### OWL Axioms\n\t  id:: economiclayer-owl-axioms\n\t  collapsed:: true\n\t\t- ```clojure\n\t\t  Declaration(Class(mv:Economiclayer))\n\n\t\t  # Classification\n\t\t  SubClassOf(mv:Economiclayer mv:ConceptualEntity)\n\t\t  SubClassOf(mv:Economiclayer mv:Concept)\n\n\t\t  # Domain classification\n\t\t  SubClassOf(mv:Economiclayer\n\t\t    ObjectSomeValuesFrom(mv:belongsToDomain mv:MetaverseDomain)\n\t\t  )\n\n\t\t  # Annotations\n\t\t  AnnotationAssertion(rdfs:label mv:Economiclayer \"EconomicLayer\"@en)\n\t\t  AnnotationAssertion(rdfs:comment mv:Economiclayer \"A component of the metaverse ecosystem focusing on economiclayer.\"@en)\n\t\t  AnnotationAssertion(dcterms:identifier mv:Economiclayer \"mv-16107575907\"^^xsd:string)\n\t\t  ```\n\n- ### MetaOntologyBlock\n  id:: economic-layer-meta\n  collapsed:: true\n\n  - **Classification**\n    - meta-ontology:: true\n    - classification-type:: layer\n    - name:: EconomicLayer\n    - scope:: Economic mechanism implementations, incentive structures, market designs, resource allocation systems, and game-theoretic implementations in blockchain ecosystems\n    - version:: 1.0.0\n    - last-updated:: 2025-11-08\n\n  - **Definition**\n    - definition:: The EconomicLayer represents the abstraction level of implemented economic mechanisms, incentive structures, market designs, resource allocation systems, and game-theoretic implementations that govern economic behavior in blockchain and distributed systems. This layer encompasses concrete economic implementations including token emission schedules (Bitcoin's halving schedule, Ethereum's changing issuance policy), fee market implementations (EIP-1559's base fee adjustment mechanism, priority fee auctions), incentive mechanism implementations (mining reward distribution, staking yield calculations, validator reward formulas), penalty mechanisms (slashing implementations specifying exact penalty amounts and conditions), market mechanism implementations (automated market maker formulas, bonding curves, liquidity pool mechanics), resource pricing mechanisms (gas price mechanisms, storage rent, computation pricing), economic security implementations (cost-of-attack calculations, security budget allocations), and game-theoretic mechanism implementations (auction mechanisms, voting systems, coordination games). Unlike ConceptualLayer which addresses abstract economic principles and theories, EconomicLayer focuses on concrete economic mechanism implementations with specific parameters, formulas, and behaviors. Unlike ProtocolLayer which addresses protocol mechanics broadly, EconomicLayer emphasizes economic aspects: incentive compatibility, market efficiency, resource allocation, and economic security.\n    - purpose:: To provide classification for economic mechanism implementations, enabling systematic understanding of how blockchain systems implement economic models, align participant incentives, allocate resources efficiently, and achieve economic security through concrete mechanisms with specific parameters and behaviors\n    - coverage:: This layer covers approximately 7+ economic implementation concepts including fee market mechanisms (EIP-1559, gas auctions), reward distribution systems (block rewards, staking yields), penalty implementations (slashing mechanisms with specific parameters), market mechanisms (AMM implementations, bonding curves), resource pricing (gas pricing, storage economics), and economic security implementations (validator economics, security budgets)\n\n  - **Taxonomy**\n    - parent-classification:: LayerHierarchy\n    - peer-classifications:: [[ConceptualLayer]], [[SecurityLayer]], [[ProtocolLayer]], [[MiddlewareLayer]], [[ApplicationLayer]]\n    - abstraction-level:: implementation\n    - cross-cutting:: true\n\n  - **Member Concepts**\n    - concept-count:: 7\n    - fee-mechanisms:: [[EIP-1559]], [[Gas-price-auction]], [[Base-fee-adjustment]], [[Priority-fee-market]], [[Transaction-fee-mechanism]]\n    - reward-systems:: [[Block-reward-distribution]], [[Staking-yield-calculation]], [[Validator-reward-formula]], [[Mining-reward-schedule]]\n    - market-mechanisms:: [[Automated-market-maker-implementation]], [[Bonding-curve]], [[Liquidity-pool-mechanics]], [[Price-impact-calculation]]\n    - penalty-mechanisms:: [[Slashing-implementation]], [[Penalty-calculation]], [[Validator-punishment]], [[Economic-finality-mechanism]]\n    - resource-pricing:: [[Gas-pricing-mechanism]], [[Storage-rent]], [[Computation-pricing]], [[State-rent]]\n    - economic-security:: [[Validator-economics]], [[Security-budget]], [[Cost-of-attack-calculation]], [[Economic-attack-resistance]]\n    - key-ontologies:: Economic mechanism implementations from TokenEconomicsDomain, concrete market designs, implemented incentive structures, and resource allocation systems\n\n  - ## About EconomicLayer\n    id:: economic-layer-about\n    - The EconomicLayer represents a critical implementation-focused abstraction level that addresses how blockchain systems implement economic mechanisms to align incentives, allocate resources, and achieve security through game-theoretic designs. Economics is not merely a consideration in blockchain systems but a fundamental component of their operation and security: blockchains are secured not just by cryptography but by economic incentives making attacks unprofitable, resources are allocated not by central planning but by market mechanisms, and coordination is achieved not by authority but by aligning individual incentives with collective goals. This layer focuses on concrete economic implementations: specific formulas, parameters, mechanisms, and behaviors that govern economic aspects of blockchain systems. Unlike theoretical economic models (ConceptualLayer), EconomicLayer addresses how economic principles are realized through specific implementations that can be deployed, tested, and optimized.\n\n    - The layer encompasses several categories of economic implementations. **Fee market mechanisms** implement dynamic pricing for scarce blockchain resources (transaction inclusion, state storage, computation). Ethereum's EIP-1559 exemplifies a sophisticated fee market implementation: a base fee that adjusts based on block fullness (increasing 12.5% when blocks are full, decreasing 12.5% when blocks are empty), targeting 50% block utilization, with users paying the base fee (which is burned) plus an optional priority fee (which goes to miners/validators). This mechanism creates predictable fee markets (users know the base fee for next block), reduces fee volatility (smooth adjustment rather than auction volatility), and creates deflationary pressure (fee burning reduces token supply). Gas auctions represent an alternative fee market implementation: users bid for transaction inclusion, with highest bids included first, creating first-price or second-price auction dynamics. These fee market mechanisms must balance efficiency (transactions are included efficiently), fairness (mechanisms are not easily manipulated), and simplicity (users can understand and use mechanisms).\n\n    - **Reward distribution systems** implement incentive mechanisms for network participants. Bitcoin's mining reward schedule specifies an initial 50 BTC block reward, halving every 210,000 blocks (~4 years), creating predictable supply emission and eventual supply cap of 21 million BTC. As block rewards decline, transaction fees must increasingly secure the network, raising questions about long-term security sustainability. Proof-of-Stake reward systems distribute staking yields based on stake amount and validation participation, with typical annual yields ranging from 3-15% depending on network parameters. These yields must be high enough to incentivize staking (providing economic security through locked stake) but not so high as to create unsustainable inflation. Reward formulas often incorporate penalties for validator downtime or unavailability, creating incentives for reliable operation. These distribution systems must balance multiple objectives: incentivizing honest participation, maintaining sufficient economic security, controlling inflation, ensuring long-term sustainability, and distributing rewards fairly across participants.\n\n    - **Market mechanism implementations** enable decentralized exchange and liquidity provision. Automated Market Makers (AMMs) implement specific mathematical formulas defining exchange rates. The constant product formula (x * y = k) used by Uniswap V2 creates a pricing curve where price impact increases with trade size, discouraging large trades and creating arbitrage opportunities that maintain price accuracy. Constant sum formulas (x + y = k) create zero price impact but risk reserves depletion if prices diverge from initial ratio. Hybrid curves combine multiple formulas for different price ranges, optimizing for different use cases (stable swaps for stablecoins, constant product for volatile assets). Bonding curves specify token price as a function of supply, creating predictable pricing for continuous token sales. Liquidity pools collect trading fees for liquidity providers, with fees set to compensate for impermanent loss (opportunity cost of providing liquidity vs holding tokens). These market mechanisms implement game-theoretic designs where arbitrageurs maintain price accuracy, liquidity providers earn fees compensating for risks, and traders get predictable execution.\n\n    - ### Scope and Boundaries\n      - **Included:** Economic mechanism implementations, fee market mechanisms, reward distribution systems, penalty implementations, market mechanism implementations (AMMs, bonding curves), resource pricing mechanisms, economic security implementations, incentive mechanism implementations, and game-theoretic mechanism implementations with specific parameters and formulas.\n\n      - **Excluded:** Abstract economic theories without specific implementation (belong in ConceptualLayer), economic analysis of existing systems without implementation details (may be properties of specific systems rather than mechanisms), general economics not specific to blockchain (not relevant), and financial applications (belong in ApplicationLayer).\n\n      - **Boundary Clarifications:** EconomicLayer focuses on economic mechanism implementations with specific formulas, parameters, and behaviors. A concept belongs here if it implements an economic mechanism that governs incentives, allocates resources, or creates markets. For example, \"EIP-1559\" belongs in EconomicLayer as it implements a specific fee market mechanism with defined formulas and behaviors. \"Transaction Fee\" as an abstract concept belongs in ConceptualLayer or TokenEconomicsDomain, but specific fee calculation mechanisms belong in EconomicLayer. Many concepts may span EconomicLayer and other layers depending on the aspect emphasized.\n\n    - ### Relationship to Other Classifications\n      - **Relationship to ConceptualLayer:** ConceptualLayer addresses abstract economic principles and theoretical models (what incentive compatibility means, what market efficiency requires), while EconomicLayer addresses concrete economic mechanism implementations (how EIP-1559 implements fee markets, how staking yield is calculated). Many concepts have both conceptual understanding (ConceptualLayer, TokenEconomicsDomain) and economic implementations (EconomicLayer).\n\n      - **Relationship to ProtocolLayer:** There is overlap between EconomicLayer and ProtocolLayer. Economic mechanisms are often specified in protocols (consensus protocols specify reward distribution, transaction protocols specify fee payment). The distinction is emphasis: EconomicLayer emphasizes economic properties (incentive compatibility, efficiency, allocation), while ProtocolLayer emphasizes protocol mechanics (message flows, state transitions). Many concepts appropriately belong to both layers.\n\n      - **Relationship to TokenEconomicsDomain:** TokenEconomicsDomain is a domain classification organizing economic concepts by subject matter (token economics, incentive mechanisms), while EconomicLayer is a layer classification organizing concepts by abstraction level (implemented economic mechanisms). A concept can belong to TokenEconomicsDomain (subject matter) and EconomicLayer (implementation level) simultaneously. For example, \"Staking Yield Calculation\" belongs to TokenEconomicsDomain (it's about token economics) and EconomicLayer (it's an implemented mechanism).\n\n    - ### Design Rationale\n      - **Economics as Security:** EconomicLayer was designed as a distinct layer because economic mechanisms are fundamental to blockchain security. Many blockchains are secured primarily through economic incentives: the cost to attack (acquiring 51% hashpower or stake) exceeds the benefit (double-spending or censorship gains). This economic security requires careful mechanism design with specific parameters, justifying dedicated layer classification.\n\n      - **Implementation-Level Economics:** While TokenEconomicsDomain addresses economic concepts broadly and ConceptualLayer addresses abstract economic principles, EconomicLayer focuses on concrete implementations with specific formulas and parameters. This implementation focus serves mechanism designers, protocol developers, and economic researchers who must implement and optimize economic mechanisms in real systems.\n\n      - **Game-Theoretic Design:** Economic mechanisms in blockchain systems are game-theoretic: they define games where participants' strategies determine outcomes. EconomicLayer captures these game implementations including payoff structures (rewards and penalties), strategy spaces (participant actions), and equilibrium properties (incentive compatibility, Nash equilibria). This game-theoretic perspective reflects that blockchain economics must account for strategic behavior.\n\n      - **Measurable Economic Properties:** EconomicLayer emphasizes mechanisms with measurable economic properties that can be analyzed, simulated, and optimized. Fee market efficiency can be measured through price volatility and allocation efficiency. Incentive compatibility can be analyzed through game-theoretic models. Economic security can be quantified through cost-of-attack calculations. This measurability enables scientific analysis and evidence-based optimization.\n\n      - **Cross-Domain Economics:** EconomicLayer is cross-cutting, addressing economic implementations across domains. Consensus mechanisms (ConsensusDomain) incorporate economic incentives. Token systems (TokenEconomicsDomain) implement economic mechanisms. DeFi applications implement market mechanisms. This cross-domain nature reflects that economic considerations span all aspects of blockchain systems.\n\n\n## Current Landscape (2025)\n\n- Industry adoption and implementations\n  - Metaverse platforms continue to evolve with focus on interoperability and open standards\n  - Web3 integration accelerating with decentralised identity and asset ownership\n  - Enterprise adoption growing in virtual collaboration, training, and digital twins\n  - UK companies increasingly active in metaverse development and immersive technologies\n\n- Technical capabilities\n  - Real-time rendering at photorealistic quality levels\n  - Low-latency networking enabling seamless multi-user experiences\n  - AI-driven content generation and procedural world building\n  - Spatial audio and haptics enhancing immersion\n\n- UK and North England context\n  - Manchester: Digital Innovation Factory supports metaverse startups and research\n  - Leeds: Holovis leads in immersive experiences for entertainment and training\n  - Newcastle: University research in spatial computing and interactive systems\n  - Sheffield: Advanced manufacturing using digital twin technology\n\n- Standards and frameworks\n  - Metaverse Standards Forum driving interoperability protocols\n  - WebXR enabling browser-based immersive experiences\n  - glTF and USD for 3D asset interchange\n  - Open Metaverse Interoperability Group defining cross-platform standards\n\n## Metadata\n\n- **Last Updated**: 2025-11-16\n- **Review Status**: Automated remediation with 2025 context\n- **Verification**: Academic sources verified\n- **Regional Context**: UK/North England where applicable",
  "properties": {
    "id": "economic-layer-about",
    "collapsed": "true",
    "- ontology": "true",
    "- term-id": "mv-16107575907",
    "- preferred-term": "EconomicLayer",
    "- source-domain": "metaverse",
    "- status": "active",
    "- public-access": "true",
    "- definition": "The EconomicLayer represents the abstraction level of implemented economic mechanisms, incentive structures, market designs, resource allocation systems, and game-theoretic implementations that govern economic behavior in blockchain and distributed systems. This layer encompasses concrete economic implementations including token emission schedules (Bitcoin's halving schedule, Ethereum's changing issuance policy), fee market implementations (EIP-1559's base fee adjustment mechanism, priority fee auctions), incentive mechanism implementations (mining reward distribution, staking yield calculations, validator reward formulas), penalty mechanisms (slashing implementations specifying exact penalty amounts and conditions), market mechanism implementations (automated market maker formulas, bonding curves, liquidity pool mechanics), resource pricing mechanisms (gas price mechanisms, storage rent, computation pricing), economic security implementations (cost-of-attack calculations, security budget allocations), and game-theoretic mechanism implementations (auction mechanisms, voting systems, coordination games). Unlike ConceptualLayer which addresses abstract economic principles and theories, EconomicLayer focuses on concrete economic mechanism implementations with specific parameters, formulas, and behaviors. Unlike ProtocolLayer which addresses protocol mechanics broadly, EconomicLayer emphasizes economic aspects: incentive compatibility, market efficiency, resource allocation, and economic security.",
    "- maturity": "mature",
    "- authority-score": "0.85",
    "- owl:class": "mv:Economiclayer",
    "- owl:physicality": "ConceptualEntity",
    "- owl:role": "Concept",
    "- belongsToDomain": "[[MetaverseDomain]]",
    "- enables": "[[ImmersiveExperience]], [[Presence]], [[SpatialComputing]]",
    "- requires": "[[DisplayTechnology]], [[TrackingSystem]], [[RenderingEngine]]",
    "- bridges-to": "[[HumanComputerInteraction]], [[ComputerVision]], [[Robotics]]",
    "- meta-ontology": "true",
    "- classification-type": "layer",
    "- name": "EconomicLayer",
    "- scope": "Economic mechanism implementations, incentive structures, market designs, resource allocation systems, and game-theoretic implementations in blockchain ecosystems",
    "- version": "1.0.0",
    "- last-updated": "2025-11-08",
    "- purpose": "To provide classification for economic mechanism implementations, enabling systematic understanding of how blockchain systems implement economic models, align participant incentives, allocate resources efficiently, and achieve economic security through concrete mechanisms with specific parameters and behaviors",
    "- coverage": "This layer covers approximately 7+ economic implementation concepts including fee market mechanisms (EIP-1559, gas auctions), reward distribution systems (block rewards, staking yields), penalty implementations (slashing mechanisms with specific parameters), market mechanisms (AMM implementations, bonding curves), resource pricing (gas pricing, storage economics), and economic security implementations (validator economics, security budgets)",
    "- parent-classification": "LayerHierarchy",
    "- peer-classifications": "[[ConceptualLayer]], [[SecurityLayer]], [[ProtocolLayer]], [[MiddlewareLayer]], [[ApplicationLayer]]",
    "- abstraction-level": "implementation",
    "- cross-cutting": "true",
    "- concept-count": "7",
    "- fee-mechanisms": "[[EIP-1559]], [[Gas-price-auction]], [[Base-fee-adjustment]], [[Priority-fee-market]], [[Transaction-fee-mechanism]]",
    "- reward-systems": "[[Block-reward-distribution]], [[Staking-yield-calculation]], [[Validator-reward-formula]], [[Mining-reward-schedule]]",
    "- market-mechanisms": "[[Automated-market-maker-implementation]], [[Bonding-curve]], [[Liquidity-pool-mechanics]], [[Price-impact-calculation]]",
    "- penalty-mechanisms": "[[Slashing-implementation]], [[Penalty-calculation]], [[Validator-punishment]], [[Economic-finality-mechanism]]",
    "- resource-pricing": "[[Gas-pricing-mechanism]], [[Storage-rent]], [[Computation-pricing]], [[State-rent]]",
    "- economic-security": "[[Validator-economics]], [[Security-budget]], [[Cost-of-attack-calculation]], [[Economic-attack-resistance]]",
    "- key-ontologies": "Economic mechanism implementations from TokenEconomicsDomain, concrete market designs, implemented incentive structures, and resource allocation systems"
  },
  "backlinks": [
    "ConceptualLayer",
    "BC-0097-cryptocurrency",
    "Money",
    "ProtocolLayer",
    "Native Token",
    "Coin",
    "BC-0100-gas",
    "BC-0096-token",
    "Bitcoin",
    "MiddlewareLayer",
    "Gas",
    "BC-0099-native-token",
    "Value Transfer",
    "TokenEconomicsDomain",
    "BC-0098-coin",
    "ConsensusDomain"
  ],
  "wiki_links": [
    "Priority-fee-market",
    "Validator-economics",
    "MiddlewareLayer",
    "Presence",
    "Bonding-curve",
    "MetaverseDomain",
    "Price-impact-calculation",
    "Slashing-implementation",
    "Economic-finality-mechanism",
    "Staking-yield-calculation",
    "Security-budget",
    "ImmersiveExperience",
    "SpatialComputing",
    "Economic-attack-resistance",
    "Mining-reward-schedule",
    "ProtocolLayer",
    "DisplayTechnology",
    "RenderingEngine",
    "State-rent",
    "Validator-punishment",
    "SecurityLayer",
    "Gas-price-auction",
    "Automated-market-maker-implementation",
    "Validator-reward-formula",
    "Penalty-calculation",
    "Storage-rent",
    "Transaction-fee-mechanism",
    "EIP-1559",
    "Base-fee-adjustment",
    "HumanComputerInteraction",
    "ComputerVision",
    "Computation-pricing",
    "Liquidity-pool-mechanics",
    "TrackingSystem",
    "Robotics",
    "Cost-of-attack-calculation",
    "ApplicationLayer",
    "Block-reward-distribution",
    "Gas-pricing-mechanism",
    "ConceptualLayer"
  ],
  "ontology": {
    "term_id": "mv-16107575907",
    "preferred_term": "EconomicLayer",
    "definition": "A component of the metaverse ecosystem focusing on economiclayer.",
    "source_domain": "metaverse",
    "maturity_level": null,
    "authority_score": 0.85
  }
}