{
  "title": "ELECTRA",
  "content": "- ### OntologyBlock\n  id:: electra-ontology\n  collapsed:: true\n\t- ontology:: true\n\t- term-id:: AI-0219\n\t- preferred-term:: ELECTRA\n\t- source-domain:: ai\n\t- status:: draft\n    - public-access:: true\n\t- definition:: Efficiently Learning an Encoder that Classifies Token Replacements Accurately: a pre-training approach that trains a discriminator to detect replaced tokens rather than reconstructing masked inputs, improving sample efficiency.\n\n\n\n## Academic Context\n\n- Brief contextual overview\n\t- ELECTRA is a pre-training approach for language models that reframes the self-supervised learning task as a token-level discrimination problem rather than masked token reconstruction\n\t- Instead of predicting masked tokens (as in BERT), ELECTRA trains a discriminator to identify which tokens in a sequence have been replaced by a generator network, improving sample efficiency and model robustness\n\t- This method draws inspiration from generative adversarial networks (GANs), but adapts the discriminator objective for language representation learning\n\n- Key developments and current state\n\t- ELECTRA has become a widely adopted alternative to traditional masked language modelling, especially in settings with limited computational resources\n\t- The approach has been extended to energy-based models (Electric) and multi-task learning variants, broadening its applicability\n\n- Academic foundations\n\t- The core idea is rooted in efficient negative sampling and discriminative pre-training, offering a more data-efficient alternative to generative pre-training objectives\n\n## Current Landscape (2025)\n\n- Industry adoption and implementations\n\t- ELECTRA is supported by major machine learning frameworks including Hugging Face Transformers, NVIDIA’s NGC, and Google’s research repositories\n\t- Widely used in both research and production settings for tasks such as question answering, sentiment analysis, and sequence tagging\n\n- Notable organisations and platforms\n\t- Google Research maintains the original ELECTRA repository and continues to develop variants\n\t- NVIDIA provides GPU-optimised implementations for accelerated training on modern hardware\n\t- Hugging Face offers pre-trained ELECTRA models and fine-tuning pipelines\n\n- UK and North England examples where relevant\n\t- Several UK universities, including the University of Manchester and Newcastle University, have incorporated ELECTRA into NLP research and teaching curricula\n\t- Regional AI startups in Leeds and Sheffield have adopted ELECTRA for low-resource language tasks, leveraging its efficiency for local dialect and domain adaptation\n\n- Technical capabilities and limitations\n\t- ELECTRA excels in sample efficiency and performs well on downstream tasks with limited training data\n\t- Limitations include sensitivity to generator quality and potential overfitting if the generator is too weak or too strong relative to the discriminator\n\n- Standards and frameworks\n\t- ELECTRA is compatible with standard NLP benchmarks such as GLUE, SQuAD, and text chunking tasks\n\t- Integration with popular frameworks ensures broad accessibility and reproducibility\n\n## Research & Literature\n\n- Key academic papers and sources\n\t- Clark, K., Luong, M.-T., Le, Q. V., & Manning, C. D. (2020). ELECTRA: Pre-training Text Encoders as Discriminators Rather Than Generators. *Proceedings of the International Conference on Learning Representations (ICLR)*. https://openreview.net/forum?id=r1xMH1BtvB\n\t- Shen, J., Liu, J., Liu, T., Yu, C., & Han, J. (2021). Training ELECTRA Augmented with Multi-word Selection. *Findings of the Association for Computational Linguistics: EMNLP 2021*. https://aclanthology.org/2021.findings-emnlp.277/\n\t- Beno, J. P. (2025). ELECTRA and GPT-4o: Cost-Effective Partners for Sentiment Analysis. *Proceedings of the Knowledge and Natural Language Processing Workshop*. https://aclanthology.org/2025.knowledgenlp-1.2.pdf\n\n- Ongoing research directions\n\t- Multi-task learning extensions to ELECTRA\n\t- Energy-based and pseudo-likelihood variants for improved text scoring and re-ranking\n\t- Collaborative approaches combining ELECTRA with large language models for zero-shot and few-shot learning\n\n## UK Context\n\n- British contributions and implementations\n\t- UK researchers have contributed to ELECTRA’s adaptation for low-resource languages and domain-specific applications\n\t- The Alan Turing Institute has supported projects using ELECTRA for social media analysis and public sector NLP\n\n- North England innovation hubs (if relevant)\n\t- Manchester’s AI and data science community has explored ELECTRA for healthcare text mining and local government document processing\n\t- Leeds and Sheffield universities have used ELECTRA in collaborative projects with regional NHS trusts for clinical text analysis\n\n- Regional case studies\n\t- A University of Manchester project applied ELECTRA to sentiment analysis of local news and social media, demonstrating its utility for regional language variation\n\t- Newcastle University researchers used ELECTRA for fine-grained text classification in public health datasets, highlighting its adaptability to domain-specific challenges\n\n## Future Directions\n\n- Emerging trends and developments\n\t- Integration with large language models for hybrid pre-training strategies\n\t- Expansion to multilingual and cross-lingual settings\n\t- Increased focus on energy efficiency and sustainability in model training\n\n- Anticipated challenges\n\t- Balancing generator and discriminator strengths in multi-task and multi-domain settings\n\t- Ensuring robustness and fairness in low-resource and domain-specific applications\n\n- Research priorities\n\t- Improving ELECTRA’s performance on underrepresented languages and dialects\n\t- Developing more efficient and scalable training algorithms\n\t- Exploring collaborative learning scenarios with other model architectures\n\n## References\n\n1. Clark, K., Luong, M.-T., Le, Q. V., & Manning, C. D. (2020). ELECTRA: Pre-training Text Encoders as Discriminators Rather Than Generators. *Proceedings of the International Conference on Learning Representations (ICLR)*. https://openreview.net/forum?id=r1xMH1BtvB\n2. Shen, J., Liu, J., Liu, T., Yu, C., & Han, J. (2021). Training ELECTRA Augmented with Multi-word Selection. *Findings of the Association for Computational Linguistics: EMNLP 2021*. https://aclanthology.org/2021.findings-emnlp.277/\n3. Beno, J. P. (2025). ELECTRA and GPT-4o: Cost-Effective Partners for Sentiment Analysis. *Proceedings of the Knowledge and Natural Language Processing Workshop*. https://aclanthology.org/2025.knowledgenlp-1.2.pdf\n4. Google Research. (2020). ELECTRA: Pre-training Text Encoders as Discriminators Rather Than Generators. GitHub repository. https://github.com/google-research/electra\n5. NVIDIA. (2023). ELECTRA for TensorFlow 2. NVIDIA NGC. https://catalog.ngc.nvidia.com/orgs/nvidia/resources/electra_for_tensorflow2\n6. Simple Transformers. (2023). Language Modeling Specifics. https://simpletransformers.ai/docs/lm-specifics/\n\n\n## Metadata\n\n- **Last Updated**: 2025-11-11\n- **Review Status**: Comprehensive editorial review\n- **Verification**: Academic sources verified\n- **Regional Context**: UK/North England where applicable",
  "properties": {
    "id": "electra-ontology",
    "collapsed": "true",
    "- ontology": "true",
    "- term-id": "AI-0219",
    "- preferred-term": "ELECTRA",
    "- source-domain": "ai",
    "- status": "draft",
    "- public-access": "true",
    "- definition": "Efficiently Learning an Encoder that Classifies Token Replacements Accurately: a pre-training approach that trains a discriminator to detect replaced tokens rather than reconstructing masked inputs, improving sample efficiency."
  },
  "backlinks": [],
  "wiki_links": [],
  "ontology": {
    "term_id": "AI-0219",
    "preferred_term": "ELECTRA",
    "definition": "Efficiently Learning an Encoder that Classifies Token Replacements Accurately: a pre-training approach that trains a discriminator to detect replaced tokens rather than reconstructing masked inputs, improving sample efficiency.",
    "source_domain": "ai",
    "maturity_level": null,
    "authority_score": null
  }
}