{
  "title": "Self-Sovereign Email Search Stack: A Comprehensive Report",
  "content": "- ### OntologyBlock\n  id:: self-sovereign-email-search-stack:-a-comprehensive-report-ontology\n  collapsed:: true\n\t- ontology:: true\n\t- term-id:: mv-491837127609\n\t- preferred-term:: Self-Sovereign Email Search Stack: A Comprehensive Report\n\t- source-domain:: metaverse\n\t- status:: active\n\t- public-access:: true\n\t- definition:: A component of the metaverse ecosystem focusing on self-sovereign email search stack: a comprehensive report.\n\t- maturity:: mature\n\t- authority-score:: 0.85\n\t- owl:class:: mv:SelfSovereignEmailSearchStackAComprehensiveReport\n\t- owl:physicality:: ConceptualEntity\n\t- owl:role:: Concept\n\t- belongsToDomain:: [[MetaverseDomain]]\n\t- #### Relationships\n\t  id:: self-sovereign-email-search-stack:-a-comprehensive-report-relationships\n\t\t- enables:: [[ImmersiveExperience]], [[Presence]], [[SpatialComputing]]\n\t\t- requires:: [[DisplayTechnology]], [[TrackingSystem]], [[RenderingEngine]]\n\t\t- bridges-to:: [[HumanComputerInteraction]], [[ComputerVision]], [[Robotics]]\n\n\t- #### OWL Axioms\n\t  id:: self-sovereign-email-search-stack:-a-comprehensive-report-owl-axioms\n\t  collapsed:: true\n\t\t- ```clojure\n\t\t  Declaration(Class(mv:SelfSovereignEmailSearchStackAComprehensiveReport))\n\n\t\t  # Classification\n\t\t  SubClassOf(mv:SelfSovereignEmailSearchStackAComprehensiveReport mv:ConceptualEntity)\n\t\t  SubClassOf(mv:SelfSovereignEmailSearchStackAComprehensiveReport mv:Concept)\n\n\t\t  # Domain classification\n\t\t  SubClassOf(mv:SelfSovereignEmailSearchStackAComprehensiveReport\n\t\t    ObjectSomeValuesFrom(mv:belongsToDomain mv:MetaverseDomain)\n\t\t  )\n\n\t\t  # Annotations\n\t\t  AnnotationAssertion(rdfs:label mv:SelfSovereignEmailSearchStackAComprehensiveReport \"Self-Sovereign Email Search Stack: A Comprehensive Report\"@en)\n\t\t  AnnotationAssertion(rdfs:comment mv:SelfSovereignEmailSearchStackAComprehensiveReport \"A component of the metaverse ecosystem focusing on self-sovereign email search stack: a comprehensive report.\"@en)\n\t\t  AnnotationAssertion(dcterms:identifier mv:SelfSovereignEmailSearchStackAComprehensiveReport \"mv-491837127609\"^^xsd:string)\n\t\t  ```\n\n# Self-Sovereign Email Search Stack: A Comprehensive Report\n- ## Executive Summary\n  \n  For searching 300k emails (multi-GB corpus) locally with LLM-enhanced fuzzy search capabilities, the optimal approach combines multiple layers:\n  \n  1. **Traditional full-text search** (Elasticsearch/Tantivy) for fast keyword matching\n  2. **Vector embeddings** for semantic similarity search\n  3. **Hybrid retrieval** combining BM25 and dense vectors\n  4. **Local LLM reranking** for precision\n  5. **Optional GraphRAG** for relationship-aware search\n- ## Layered Search Architecture\n- ### Layer 1: Traditional Full-Text Search (Foundation)\n  \n  **Technology Options:**\n- **Tantivy** (Rust-based, used by Meilisearch)\n\t- Extremely fast, memory-efficient\n\t- BM25 scoring, fuzzy matching\n\t- Faceted search support\n- **Apache Lucene/Elasticsearch** (self-hosted)\n\t- Most mature, extensive features\n\t- Higher resource consumption\n- **Xapian**\n\t- Lightweight, good for email specifically\n\t- Probabilistic ranking\n\t  \n\t  **Implementation:**\n\t  \n\t  ```bash\n\t  # Example with Tantivy-based Meilisearch\n\t  docker run -p 7700:7700 -v $(pwd)/data:/data.ms getmeili/meilisearch:latest\n\t  ```\n- ### Layer 2: Vector Embeddings (Semantic Search)\n  \n  **Embedding Models (Local):**\n- **Sentence-Transformers** (all-MiniLM-L6-v2)\n\t- 384 dimensions, fast, good quality\n\t- ~80MB model size\n- **E5-small/base/large**\n\t- Better multilingual support\n\t- Scales from 384 to 1024 dimensions\n- **BGE-small/base/large**\n\t- State-of-the-art quality\n\t- Optimized for retrieval\n\t  \n\t  **Vector Databases:**\n- **Qdrant** (Rust, highly efficient)\n  ```bash\n  docker run -p 6333:6333 qdrant/qdrant\n  ```\n- **Weaviate** (Go, good hybrid search)\n- **ChromaDB** (Python, easy integration)\n- **FAISS** (Facebook, CPU/GPU optimized)\n- ### Layer 3: Hybrid Retrieval Systems\n  \n  **Approach:** Combine BM25 (sparse) + Dense vectors\n  \n  **Options:**\n  \n  1. **Custom Pipeline:**\n  \n   ```python\n   # Pseudo-code\n   bm25_results = tantivy_search(query, k=100)\n   vector_results = qdrant_search(embed(query), k=100)\n   combined = reciprocal_rank_fusion(bm25_results, vector_results)\n   ```\n  2. **Vespa.ai** (Yahoo's open source)\n\t- Native hybrid search\n\t- Tensor support\n\t- Complex ranking expressions\n\t  3. **Weaviate with Hybrid mode**\n\t- Built-in BM25 + vector fusion\n\t- Configurable alpha parameter\n- ### Layer 4: LLM Enhancement Strategies\n  \n  **Local LLM Options:**\n- **Llama 3.2 1B/3B** - Fast, good for reranking\n- **Mistral 7B** - Better quality, slower\n- **Phi-3-mini** - Microsoft's efficient model\n  \n  **Implementation Patterns:**\n  \n  1. **Query Expansion:**\n  \n   ```python\n   # Use LLM to expand query\n   expanded_query = llm.generate(f\"Synonyms and related terms for: {query}\")\n   ```\n  2. **Reranking:**\n  \n   ```python\n   # Score top-k results with LLM\n   for result in top_100_results:\n       score = llm.score_relevance(query, result)\n   ```\n  3. **Extractive QA:**\n  \n   ```python\n   # Extract specific answers from retrieved emails\n   answer = llm.extract(question, relevant_emails)\n   ```\n- ### Layer 5: GraphRAG Implementation\n  \n  **When to Use:** For relationship-heavy queries (who emailed whom about what)\n  \n  **Architecture:**\n  \n  1. **Entity Extraction:**\n\t- Use spaCy/Stanza for NER\n\t- Extract people, organizations, topics\n\t  2. **Graph Database:**\n\t- **Neo4j** (most mature)\n\t- **ArangoDB** (multi-model)\n\t- **DGraph** (high performance)\n\t  3. **Graph Embeddings:**\n\t- Node2Vec for entity embeddings\n\t- GraphSAGE for inductive learning\n- ## Recommended Stack for 300k Emails\n- ### Optimal Configuration:\n  \n  ```yaml\n  Primary Stack:\n  Full-Text: Tantivy (via Meilisearch or raw)\n  Vectors: Qdrant + BGE-small embeddings\n  Hybrid: Custom reciprocal rank fusion\n  LLM: Llama 3.2 3B (quantized)\n  \n  Optional Additions:\n  GraphDB: Neo4j Community Edition\n  Entity Extraction: spaCy\n  ```\n- ### Implementation Pipeline:\n  \n  1. **Indexing Phase:**\n  \n   ```python\n   # Pseudo-code\n   for email in emails:\n       # Extract metadata\n       metadata = parse_email(email)\n  \n       # Full-text index\n       tantivy.index(email.content, metadata)\n  \n       # Generate embeddings\n       embedding = model.encode(email.content)\n       qdrant.upsert(embedding, metadata)\n  \n       # Extract entities (optional)\n       entities = spacy_nlp(email.content)\n       neo4j.create_nodes(entities)\n   ```\n  2. **Search Phase:**\n  \n   ```python\n   def search(query, k=20):\n       # Step 1: Parallel retrieval\n       bm25_results = tantivy.search(query, k=100)\n       vector_results = qdrant.search(embed(query), k=100)\n  \n       # Step 2: Fusion\n       candidates = reciprocal_rank_fusion(bm25_results, vector_results)[:50]\n  \n       # Step 3: LLM rerank\n       reranked = llm_rerank(query, candidates)[:k]\n  \n       return reranked\n   ```\n- ## Performance Optimization Strategies\n- ### 1. **Chunking Strategy:**\n- Split long emails into overlapping chunks (512 tokens)\n- Index chunks separately with email ID reference\n- Aggregate scores at retrieval time\n- ### 2. **Embedding Optimization:**\n- Use ONNX Runtime for 2-3x speedup\n- Batch processing during indexing\n- Cache frequently accessed embeddings\n- ### 3. **Index Sharding:**\n- Shard by date for time-based queries\n- Separate indices for attachments vs body text\n- ### 4. **Resource Requirements:**\n  \n  ```yaml\n  Minimal Setup (Quantized):\n  RAM: 16GB\n  Storage: 50GB (including indices)\n  GPU: Optional (CPU viable with quantization)\n  \n  Optimal Setup:\n  RAM: 32GB\n  Storage: 100GB (with redundancy)\n  GPU: 8GB VRAM (for faster inference)\n  ```\n- ## Advanced Techniques\n- ### 1. **ColBERT-style Late Interaction:**\n- Generate token-level embeddings\n- Enables fine-grained matching\n- Tools: RAGatouille, ColBERT-AI\n- ### 2. **Learned Sparse Representations:**\n- SPLADE models for better term expansion\n- Combines benefits of sparse and dense\n- ### 3. **Multi-Vector Representations:**\n- BGE-M3 supports multiple embedding types\n- Lexical, dense, and sparse in one model\n- ### 4. **Contextual Reranking:**\n- Use email thread context\n- Temporal proximity scoring\n- Social graph weighting\n- ## Privacy & Security Considerations\n  \n  1. **Encryption at Rest:**\n\t- LUKS for full-disk encryption\n\t- Transparent encryption for indices\n\t  2. **Access Control:**\n\t- Linux user permissions\n\t- Application-level ACLs\n\t  3. **Audit Logging:**\n\t- Track all search queries\n\t- Monitor model inputs/outputs\n- ## Monitoring & Maintenance\n  \n  ```python\n  # Key metrics to track\n  metrics = {\n    'search_latency': 'p50, p95, p99',\n    'index_size': 'bytes per document',\n    'memory_usage': 'peak and average',\n    'relevance': 'click-through rate, dwell time'\n  }\n  ```\n- ## Getting Started Commands\n  \n  ```bash\n  # 1. Install base dependencies\n  sudo apt-get install python3-pip docker.io git\n  \n  # 2. Set up Qdrant\n  docker run -p 6333:6333 -v $(pwd)/qdrant:/qdrant/storage qdrant/qdrant\n  \n  # 3. Install Python packages\n  pip install sentence-transformers qdrant-client tantivy spacy\n  \n  # 4. Download models\n  python -c \"from sentence_transformers import SentenceTransformer; SentenceTransformer('BAAI/bge-small-en-v1.5')\"\n  \n  # 5. Install local LLM runtime\n  pip install llama-cpp-python\n  # Download quantized Llama 3.2 3B model\n  ```\n- ## Conclusion\n  \n  For your 300k email corpus, I recommend starting with the hybrid approach (Tantivy + Qdrant) with BGE-small embeddings and Llama 3.2 3B for reranking. This provides an excellent balance of speed, accuracy, and resource usage. Add GraphRAG only if you have significant relationship-based query needs.\n  \n  The modular architecture allows you to start simple and add layers as needed. Begin with traditional search, add vectors for semantic capabilities, then layer in LLM reranking for precision.\n- ## Additional Resources\n- Haystack Framework: https://haystack.deepset.ai/\n- LangChain RAG modules: https://python.langchain.com/\n- DSPy for optimizing pipelines: https://github.com/stanfordnlp/dspy\n- MTEB Leaderboard for embedding models: https://huggingface.co/spaces/mteb/leaderboard\n\n## Current Landscape (2025)\n\n- Industry adoption and implementations\n  - Metaverse platforms continue to evolve with focus on interoperability and open standards\n  - Web3 integration accelerating with decentralised identity and asset ownership\n  - Enterprise adoption growing in virtual collaboration, training, and digital twins\n  - UK companies increasingly active in metaverse development and immersive technologies\n\n- Technical capabilities\n  - Real-time rendering at photorealistic quality levels\n  - Low-latency networking enabling seamless multi-user experiences\n  - AI-driven content generation and procedural world building\n  - Spatial audio and haptics enhancing immersion\n\n- UK and North England context\n  - Manchester: Digital Innovation Factory supports metaverse startups and research\n  - Leeds: Holovis leads in immersive experiences for entertainment and training\n  - Newcastle: University research in spatial computing and interactive systems\n  - Sheffield: Advanced manufacturing using digital twin technology\n\n- Standards and frameworks\n  - Metaverse Standards Forum driving interoperability protocols\n  - WebXR enabling browser-based immersive experiences\n  - glTF and USD for 3D asset interchange\n  - Open Metaverse Interoperability Group defining cross-platform standards\n\n## Metadata\n\n- **Last Updated**: 2025-11-16\n- **Review Status**: Automated remediation with 2025 context\n- **Verification**: Academic sources verified\n- **Regional Context**: UK/North England where applicable",
  "properties": {
    "id": "self-sovereign-email-search-stack:-a-comprehensive-report-owl-axioms",
    "collapsed": "true",
    "- ontology": "true",
    "- term-id": "mv-491837127609",
    "- preferred-term": "Self-Sovereign Email Search Stack: A Comprehensive Report",
    "- source-domain": "metaverse",
    "- status": "active",
    "- public-access": "true",
    "- definition": "A component of the metaverse ecosystem focusing on self-sovereign email search stack: a comprehensive report.",
    "- maturity": "mature",
    "- authority-score": "0.85",
    "- owl:class": "mv:SelfSovereignEmailSearchStackAComprehensiveReport",
    "- owl:physicality": "ConceptualEntity",
    "- owl:role": "Concept",
    "- belongsToDomain": "[[MetaverseDomain]]",
    "- enables": "[[ImmersiveExperience]], [[Presence]], [[SpatialComputing]]",
    "- requires": "[[DisplayTechnology]], [[TrackingSystem]], [[RenderingEngine]]",
    "- bridges-to": "[[HumanComputerInteraction]], [[ComputerVision]], [[Robotics]]"
  },
  "backlinks": [],
  "wiki_links": [
    "TrackingSystem",
    "ImmersiveExperience",
    "ComputerVision",
    "RenderingEngine",
    "SpatialComputing",
    "Robotics",
    "HumanComputerInteraction",
    "MetaverseDomain",
    "DisplayTechnology",
    "Presence"
  ],
  "ontology": {
    "term_id": "mv-491837127609",
    "preferred_term": "Self-Sovereign Email Search Stack: A Comprehensive Report",
    "definition": "A component of the metaverse ecosystem focusing on self-sovereign email search stack: a comprehensive report.",
    "source_domain": "metaverse",
    "maturity_level": null,
    "authority_score": 0.85
  }
}