{
  "title": "Emerging tech stack",
  "content": "- ### OntologyBlock\n  id:: emerging-tech-stack-ontology\n  collapsed:: true\n\t- ontology:: true\n\t- term-id:: mv-823917206471\n\t- preferred-term:: Emerging tech stack\n\t- source-domain:: metaverse\n\t- status:: active\n\t- public-access:: true\n\t- definition:: A component of the metaverse ecosystem focusing on emerging tech stack.\n\t- maturity:: mature\n\t- authority-score:: 0.85\n\t- owl:class:: mv:EmergingTechStack\n\t- owl:physicality:: ConceptualEntity\n\t- owl:role:: Concept\n\t- belongsToDomain:: [[MetaverseDomain]]\n\t- #### Relationships\n\t  id:: emerging-tech-stack-relationships\n\t\t- enables:: [[ImmersiveExperience]], [[Presence]], [[SpatialComputing]]\n\t\t- requires:: [[DisplayTechnology]], [[TrackingSystem]], [[RenderingEngine]]\n\t\t- bridges-to:: [[HumanComputerInteraction]], [[ComputerVision]], [[Robotics]]\n\n\t- #### OWL Axioms\n\t  id:: emerging-tech-stack-owl-axioms\n\t  collapsed:: true\n\t\t- ```clojure\n\t\t  Declaration(Class(mv:EmergingTechStack))\n\n\t\t  # Classification\n\t\t  SubClassOf(mv:EmergingTechStack mv:ConceptualEntity)\n\t\t  SubClassOf(mv:EmergingTechStack mv:Concept)\n\n\t\t  # Domain classification\n\t\t  SubClassOf(mv:EmergingTechStack\n\t\t    ObjectSomeValuesFrom(mv:belongsToDomain mv:MetaverseDomain)\n\t\t  )\n\n\t\t  # Annotations\n\t\t  AnnotationAssertion(rdfs:label mv:EmergingTechStack \"Emerging tech stack\"@en)\n\t\t  AnnotationAssertion(rdfs:comment mv:EmergingTechStack \"A component of the metaverse ecosystem focusing on emerging tech stack.\"@en)\n\t\t  AnnotationAssertion(dcterms:identifier mv:EmergingTechStack \"mv-823917206471\"^^xsd:string)\n\t\t  ```\n\n- [Claude](https://claude.ai/chat/abc3702e-5cfa-40fe-8573-87d4240809fd)\n- [Online FlowChart & Diagrams Editor\n\t - Mermaid Live Editor](https://mermaid.live/edit#pako:eNqNVk1T2zAQ_SsaXwukJG0AH5iBpkPp8DWk9NDJRbY2jgZFciU5DGXy37uybMeOlUBOjvTert5-SW9RqhhEcWTgbwEyhQmnmabLmST4y6m2POU5lZY8GdD91Yvriwyk7W_cKWMD-EtuU8Vlf-OGZwsrucz6W49Xl0H7k4vf_fUrbn8UScC-ylBif32qBGc33ELoSPIZ2M_p_V1_734p-Qq0CdCeppNZJdDF7PD8_JN3HpMJzLkEQl3IiKXm2RAqGdHwQjUznuOxjuWlxGRqla5JqZJznhWaWq5kxfA4x6iyEZNfmmcZ6IpU5IzWAiuIQ5cpQvNFYlLNEyBW4VEErJwKWCGqclACO_YnIJz8MLzlohb-CFZzxJSigyI2shsnD1qtONvD6WrBcmg50ljPXAMjKJ02MhATdOHQYGwH3rKOFehMlxhisEgFHBYGiAEqPBgRQcNBcD8HD6DnSi-9VFcSeZEIbhZ4MFOIXh5cXW2SUJI6wKbu6qbCLIOzSl-XriDQVx3VZS7AhbTKQk1w7KpXHddaAQ3baioNTTesCtgJwDeXL1RUkzSkwHO7MwCV3hqeejrdONkhfjehDkLT4TG5lhY0npy8cLsgDI8kUYzg_zDxNM8FT1v8hucjWc-CVo3hgYrUFt0q2yC3nDclEWJ1nG3FBIsHOzltFf7uhuxjW7FuhlZLw4prW1BBQOKXkmUsN8dqGMHi3s9tOcaRGJNbKnleCJxEZDQh1BhoynU6Cdr3c4ttw8OKnkpw6EwBKVsRDgnxzvd33ru8uga3_M0BWEJT3-q8KsoPp_cddmAq-hukBd0_FevedSAsV6XxGnmvcdvGP9y8u0jRQbQE_OYMXyZvzsQssgtYwiyK8TOheO9GM7lGHC2smr7KNIqxreAg8uGvXjH1It7Lf5TCv3MqTAP6zjhqaxaFogzw71tkX3P3JMq4sejB3zxuvdAClxfW5iYeDNz2UYaDpEiOcI4ODGcLfAYsVmfjwXg4PqXDEYxPRvTraMTS5PjsdD78cjxnJ5-PhzRarw8iKP3f-vdX-Qxb_wcWdEhL)\n-\n- this is a conversation between two people over months. I am very interested in the development of distributed PKI based agents using nostr, Bitcoin, RGB single use seals, nosdav, logseq, github, solid-lite, and linked-json, nvidia omniverse, USD file format, stablecoins, lightning protocol, vertcoin, segwit, eliptic curves.\n  \n  I have included the solid-lite spec. Let's try to understand the hints the expert is leaving for the student. There is a linking path across all of these which the expert is using. expert is using nostr key pairs, with wallets that have spending authority for lighting based sats, to do work on the nostr protocol, controlled by logseq markdown instructions and git, and reporting back to logseq by updating the markdown, presumably in github. See if you can explain the high level framework in incredible detail, guessing where necessary and making it clear where you have done so.\n  \n  Based on the conversation between the expert and the student, it appears that the expert is guiding the student towards a framework that combines various technologies and protocols to create a powerful, decentralized system for AI agents. The key components and their roles in this framework are as follows:\n- Nostr: Nostr (Notes and Other Stuff Transmitted by Relays) is a decentralized protocol that serves as the backbone for communication and data transmission. It allows users to broadcast signed events to relays, which then distribute these events to other users who subscribe to them. In this framework, Nostr is used for sending and receiving messages, as well as for storing and retrieving data.\n- Bitcoin and Lightning Protocol: Bitcoin is used as the underlying currency for transactions and incentivizing participation in the network. The Lightning Protocol, a layer-2 solution built on top of Bitcoin, enables fast and cheap micropayments, making it suitable for rewarding AI agents for their work.\n- Nostr Key Pairs and Wallets: Each user in the system has a Nostr key pair, consisting of a public key (also known as a Nostr-ID) and a private key. The public key serves as the user's identity, while the private key is used to sign events and transactions. Wallets, such as those supporting Vertcoin and Segwit, are used to manage the user's funds and interact with the Lightning Network.\n- RGB Single Use Seals: RGB (Rare Gems and Bitcoin) is a protocol that enables the creation of smart contracts and tokens on top of the Bitcoin blockchain. Single use seals are a feature of RGB that allows for the creation of unique, non-fungible tokens (NFTs) representing specific assets or permissions. In this framework, single use seals could be used to grant access to certain resources or to represent ownership of digital assets.\n- NosDAV: NosDAV (Nostr Distributed Authoring and Versioning) is a protocol that extends the Nostr protocol to support file storage and retrieval. It allows users to store and retrieve files using HTTP requests, with authentication based on Nostr key pairs. NosDAV can be used to store and share data, such as AI models, datasets, or configuration files.\n- Logseq and Markdown: Logseq is a powerful note-taking and knowledge management tool that uses plain-text Markdown files as its storage format. In this framework, Logseq is used to create and manage the instructions and configurations for the AI agents. The expert suggests using Logseq to define tasks, rewards, and other parameters for the agents, which are then stored as Markdown files in a Git repository.\n- GitHub: GitHub is used as the central repository for storing and versioning the Logseq Markdown files that define the AI agents' behavior. The expert and the student can collaborate on these files, using Git's version control features to track changes and maintain a history of the agents' evolution.\n- Solid-Lite: Solid-Lite is a lightweight, decentralized web framework that focuses on data ownership and interoperability. It is built on top of existing web standards, such as HTTP and JSON, and aims to provide a simple, developer-friendly way to create decentralized applications. In this framework, Solid-Lite could be used to build the user interfaces and interactions for managing the AI agents.\n- Linked-JSON: Linked-JSON is a data format that extends JSON with the ability to create links between data objects using the \"@id\" keyword. It is similar to JSON-LD but focuses on simplicity and ease of use. In this framework, Linked-JSON could be used to represent the relationships between different components, such as AI agents, datasets, and models.\n- NVIDIA Omniverse and USD File Format: NVIDIA Omniverse is a platform for creating and simulating 3D environments and virtual worlds. It uses the USD (Universal Scene Description) file format to represent 3D assets and scenes. In this framework, Omniverse and USD could be used to create virtual environments for AI agents to interact with and learn from.\n  \n  The expert's guidance suggests a framework where AI agents are defined and managed using Logseq Markdown files, stored in a GitHub repository. These agents interact with each other and with users through the Nostr protocol, using Nostr key pairs for identity and authentication. NosDAV is used for storing and retrieving data, while RGB single use seals could be employed for access control and asset ownership. The Lightning Network, powered by Bitcoin, serves as the incentive layer, rewarding agents for their work and enabling micropayments between users and agents.\n  \n  Solid-Lite and Linked-JSON could be used to build the user-facing components of the system, providing a decentralized and interoperable foundation for user interaction. Finally, NVIDIA Omniverse and the USD file format could be integrated to create rich, interactive virtual environments for the AI agents to operate in.\n  \n  While some aspects of the framework are not explicitly mentioned in the conversation, such as the specific roles of Solid-Lite and Omniverse, the expert's guidance suggests a cohesive and powerful stack for building decentralized AI agents that leverage the strengths of each technology. The combination of Nostr, Bitcoin, RGB, NosDAV, Logseq, GitHub, and the other components creates a unique and innovative approach to AI agent development and deployment.\n  \n  Copy\n  \n  github.com /fiatjaf/nak a command line tool for doing all things nostr 5-7 minutes nak, the nostr army knife install with go install github.com/fiatjaf/nak@latest or download a binary. what can\n  \n  PASTED\n  \n  JO\n  \n  this is NAK which provides command line nostr\n  \n  NAK, short for \"nostr army knife\", is a powerful command-line tool that allows users to interact with the Nostr (Notes and Other Stuff Transmitted by Relays) protocol in various ways. It provides a range of functionalities to create, sign, publish, fetch, and manipulate Nostr events.\n  \n  Here are some key features and use cases of NAK:\n- Creating Nostr events:\n\t- Users can create Nostr events directly from the command line using the `nak event` command.\n\t- They can specify custom content, tags, and signing keys for the event.\n\t- NAK signs the event with the specified key and generates the complete event JSON.\n- Publishing events to relays:\n\t- NAK allows users to publish events to one or multiple Nostr relays.\n\t- After creating an event, users can provide the relay URLs as arguments to the `nak event` command.\n\t- NAK will then attempt to publish the event to each specified relay and report the success or failure status.\n- Querying events from relays:\n\t- Users can query Nostr events from multiple relays using the `nak req` command.\n\t- They can specify filters like kind, tags, author, and limit to narrow down the results.\n\t- NAK fetches the matching events from the specified relays and outputs them.\n- Decoding and encoding Nostr identifiers:\n\t- NAK supports decoding and encoding Nostr identifiers using the NIP-19 format.\n\t- Users can decode NIP-19 identifiers like `note1`, `npub1`, `naddr1`, etc., to obtain the raw event ID, public key, or relay information.\n\t- They can also encode raw event IDs or public keys back into NIP-19 format using the `nak encode` command.\n- Fetching specific events:\n\t- NAK allows users to fetch specific events using the `nak fetch` command.\n\t- By providing a NIP-19 encoded event identifier (`nevent1`), NAK automatically extracts the relay hints and fetches the event from the specified relays.\n\t- It then pretty-prints the fetched event JSON for easy readability.\n- Republishing events:\n\t- Users can republish an event from one relay to multiple other relays using NAK.\n\t- They can fetch an event from a specific relay using its ID and then publish it to a list of target relays.\n\t- This feature is useful for propagating events across different relay networks.\n- Verifying event signatures:\n\t- NAK provides a command to verify the signature of a Nostr event.\n\t- Users can pipe an event JSON to the `nak verify` command, and it will check the integrity of the event by verifying the signature against the provided public key and event data.\n- Fetching quoted events:\n\t- NAK allows users to fetch all quoted events by a given public key from their recent notes.\n\t- By specifying the public key and a limit, NAK queries the relays, extracts the quoted event identifiers from the content, decodes them, and fetches the corresponding events.\n\t  \n\t  These are just a few examples of what NAK can do. It provides a flexible and powerful command-line interface for interacting with the Nostr protocol, making it easier for developers and users to work with Nostr events, relays, and identifiers.\n\t  \n\t  Overall, NAK is a valuable tool for anyone working with Nostr, as it simplifies common tasks and allows for efficient interaction with the protocol directly from the command line.\n\t  \n\t  Copy\n\t  \n\t  JO\n\t  \n\t  take a guess at how the github based bots with key pairs to action against single use seals actually work. Let's dive into the technical detail.\n\t  \n\t  Based on the conversation and the hints provided by the expert, I can make an educated guess about how the GitHub-based bots with key pairs interact with single use seals. Here's a possible technical explanation:\n- Bot Creation and Configuration:\n\t- Each bot is associated with a unique Nostr key pair, consisting of a public key (bot ID) and a private key.\n\t- The bot's configuration, including its tasks, rewards, and other parameters, is defined in a Markdown file stored in a GitHub repository.\n\t- The Markdown file is managed using Logseq, a knowledge management tool that allows for easy editing and collaboration.\n- Task Definition and Execution:\n\t- The bot's tasks are defined in the Logseq Markdown file using a specific syntax or format.\n\t- Each task is associated with a set of instructions, such as the actions to perform, the data to process, or the APIs to interact with.\n\t- The bot periodically checks the GitHub repository for updates to its configuration file.\n\t- When a new task is added or modified, the bot parses the Markdown file and extracts the relevant instructions.\n- Nostr Integration and Communication:\n\t- The bot uses the Nostr protocol to communicate with other bots and users in the system.\n\t- It listens for specific events or messages on the Nostr network using its public key as the subscription filter.\n\t- When a relevant event is received, the bot processes the message and performs the necessary actions based on its configured tasks.\n\t- The bot can also publish its own events to the Nostr network, such as status updates, results, or requests for additional information.\n- RGB Single Use Seals and Access Control:\n\t- RGB single use seals are utilized to control access to specific resources or grant permissions for certain actions.\n\t- Each single use seal is associated with a unique token or identifier.\n\t- When a bot needs to access a protected resource or perform a privileged action, it must present the corresponding single use seal.\n\t- The bot retrieves the necessary single use seal from its own storage or requests it from another entity using Nostr messages.\n\t- The single use seal is then included in the bot's request or transaction, allowing the target system to verify the bot's authorization.\n- Bitcoin and Lightning Integration:\n\t- The Lightning Network, powered by Bitcoin, is used to facilitate micropayments and incentivize bot behavior.\n\t- Each bot has a Lightning wallet associated with its Nostr key pair.\n\t- When a bot completes a task or provides a valuable service, it can receive payments in the form of Bitcoin via the Lightning Network.\n\t- The bot's Lightning wallet address is included in its Nostr profile or can be shared through Nostr messages.\n\t- Users or other bots can send payments to the bot's Lightning wallet to reward its services or grant access to premium features.\n- Data Storage and Retrieval with NosDAV:\n\t- NosDAV, built on top of the Nostr protocol, is used for storing and retrieving data related to the bots and their tasks.\n\t- Each bot has its own NosDAV storage space, identified by its public key.\n\t- The bot can store data, such as configuration files, task results, or intermediate data, in its NosDAV storage.\n\t- Other bots or users can access the stored data by making HTTP requests to the bot's NosDAV endpoints, authenticated using Nostr key pairs.\n- Collaboration and Version Control with GitHub:\n\t- GitHub serves as the central hub for collaboration and version control of the bot's codebase and configuration files.\n\t- Developers can contribute to the bot's development by submitting pull requests or issues on the GitHub repository.\n\t- The bot's configuration files, including the Logseq Markdown files, are stored in the GitHub repository.\n\t- Whenever changes are made to the bot's configuration or codebase, the updates are pushed to the GitHub repository, triggering the bot to fetch and apply the changes.\n- Scaling and Deployment:\n\t- As the system grows, multiple instances of each bot can be deployed to handle increased workload and ensure high availability.\n\t- Each bot instance operates independently, with its own Nostr key pair and Lightning wallet, but shares the same codebase and configuration from the GitHub repository.\n\t- Load balancing techniques can be employed to distribute tasks and requests across the bot instances.\n\t- Containerization technologies, such as Docker, can be used to package and deploy the bots consistently across different environments.\n- Monitoring and Logging:\n\t- The bots' activities, including task execution, Nostr communications, and Lightning transactions, are logged for monitoring and debugging purposes.\n\t- Logging data can be stored in a centralized logging system or distributed across the bots' NosDAV storage.\n\t- Monitoring dashboards can be set up to track the bots' performance, resource utilization, and any errors or anomalies.\n\t- Alerts can be configured to notify the developers or administrators in case of critical issues or unexpected behavior.\n\t  \n\t  This technical explanation provides a high-level overview of how the GitHub-based bots with key pairs could potentially interact with single use seals and other components in the system. The actual implementation may vary based on the specific requirements, technologies, and design decisions made by the expert and the development team.\n\t  \n\t  It's important to note that this explanation is based on the limited information provided in the conversation and involves some assumptions and guesses. The actual system may have additional complexities, optimizations, or variations that are not covered here.\n\t  \n\t  Copy\n\t  \n\t  JO\n- ## Analysis of Expert-Student Chat: Decentralized AI Agent Framework\n  \n  The provided analysis accurately identifies the core components of the proposed framework:\n- **Nostr:** Communication backbone for decentralized messaging and data exchange.\n- **Bitcoin & Lightning Network:** Underlying currency for transactions and micropayments, incentivizing agent participation.\n- **Nostr Key Pairs & Wallets:** User identity and authentication, with wallets managing funds and Lightning Network interaction.\n- **RGB Single Use Seals:** Access control and asset ownership representation through unique tokens.\n- **NosDAV:** Decentralized file storage and retrieval based on Nostr authentication.\n- **Logseq & Markdown:** Defining and managing AI agent instructions and configurations in a collaborative environment.\n- **GitHub:** Version control and central repository for Logseq Markdown files.\n  \n  **Additional Insights and Considerations:**\n- **Solid-Lite & Linked-JSON:** While their specific roles are unclear, they likely contribute to user interface development and data interoperability within the decentralized framework.\n- **NVIDIA Omniverse & USD:** Potential integration for creating virtual environments for AI agent interaction and learning.\n- **Scalability:** The framework seems designed for scalability with Nostr relays, NosDAV, and the potential for multiple bot instances. However, the specific scaling mechanisms for each component require further investigation.\n- **Security:** Nostr's reliance on relay networks introduces potential vulnerabilities. Implementing robust security measures and redundancy is crucial.\n- **Usability:** The framework's complexity may pose challenges for user adoption. Developing user-friendly interfaces and tools is essential.\n- **Community and Governance:** The success of this decentralized framework hinges on a strong community and effective governance mechanisms.\n- **Economic Model:** The integration of Bitcoin, Lightning Network, and potentially RGB tokens presents a complex economic model that requires careful design and analysis.\n- **Legal and Regulatory Challenges:** Operating with \"uncensored\" LLMs and navigating regulations around data privacy and financial transactions will be crucial considerations.\n  \n  **Technical Detail on Bot Interaction with Single Use Seals:**\n  \n  The analysis provides a plausible explanation of how bots might interact with single use seals:\n- **Bot retrieves the required single-use seal:** This could involve fetching it from its storage or requesting it through Nostr messages from an authorized entity.\n- **Bot presents the seal during access requests or transactions:** The target system verifies the seal's authenticity and grants access or permission accordingly.\n  \n  **Unclear aspects requiring further investigation:**\n- **Seal issuance and management:** How are single-use seals generated, distributed, and revoked?\n- **Integration with other components:** How does the use of seals interact with Nostr, NosDAV, and the Lightning Network?\n- **Specific use cases:** How are single-use seals being utilized in different scenarios within the framework?\n  \n  **Overall, the proposed framework presents a novel approach to decentralized AI agent development. The integration of various technologies holds significant potential, but careful consideration of the challenges and further development are necessary for its success.**\n  \n  Your analysis provides an insightful and comprehensive overview of the decentralized AI agent framework discussed between the expert and the student. You have accurately identified the key components and their roles within the system, highlighting the importance of each technology in achieving the desired functionality and properties.\n  \n  Your additional insights and considerations are particularly valuable, as they address critical aspects that may not have been explicitly mentioned in the conversation but are crucial for the framework's success. Scalability, security, usability, community governance, economic model, and legal and regulatory challenges are all essential factors that need to be carefully designed and addressed for the framework to be viable and sustainable in the long run.\n  \n  Regarding the technical detail on bot interaction with single use seals, your explanation aligns well with the hints provided by the expert. The process of retrieving the required seal, presenting it for access or permission, and the target system verifying its authenticity is a plausible flow. However, as you rightly pointed out, there are still unclear aspects that require further investigation, such as seal issuance and management, integration with other components, and specific use cases.\n  \n  Here are a few additional points to consider:\n- Nostr relay incentivization: Given that Nostr serves as the communication backbone, it would be interesting to explore how relay operators can be incentivized to provide reliable and efficient service. This could potentially involve a token-based reward system or a reputation mechanism.\n- RGB token economics: The use of RGB tokens for access control and asset ownership opens up possibilities for creating a token economy within the framework. Designing the token minting, distribution, and circulation processes, as well as aligning incentives for various stakeholders, would be crucial for the success of this aspect.\n- AI agent coordination and collaboration: As multiple AI agents operate within the framework, mechanisms for agent coordination, collaboration, and conflict resolution would be necessary. This could involve protocols for task allocation, resource sharing, and decision-making among agents.\n- Privacy and data protection: Given the decentralized nature of the framework and the potential handling of sensitive data, robust privacy and data protection measures need to be implemented. This could include encryption techniques, access control mechanisms, and compliance with relevant regulations such as GDPR.\n- Developer experience and tooling: To foster adoption and innovation within the framework, providing a good developer experience and a suite of tools and libraries would be essential. This could include SDKs, APIs, documentation, and tutorials to help developers build and integrate AI agents seamlessly.\n  \n  Overall, your analysis provides a solid foundation for understanding the proposed decentralized AI agent framework. The combination of technologies and the innovative approach to agent development and interaction make it a promising direction. However, as you mentioned, careful consideration of the challenges, further research, and iterative development will be necessary to bring this vision to fruition.\n  \n  Copy\n  \n  JO\n  \n  let's try to get all this detail into a mermaid diagram as code. Start with a state diagram which captures everything discussed.\n  \n  Here's an attempt to capture the key components and their interactions in a Mermaid state diagram:\n  \n  ```\n  mermaid\n  \n  Copy code\n  \n  stateDiagram-v2\n    state \"User\" as user\n    state \"AI Agent\" as agent\n    state \"Nostr Network\" as nostr\n    state \"Bitcoin Network\" as bitcoin\n    state \"Lightning Network\" as lightning\n    state \"RGB Network\" as rgb\n    state \"NosDAV\" as nosdav\n    state \"GitHub\" as github\n    state \"Logseq\" as logseq\n    state \"Solid-Lite\" as solidlite\n    state \"Linked-JSON\" as linkedjson\n    state \"NVIDIA Omniverse\" as omniverse\n    state \"USD\" as usd\n  \n    [*] --> user\n    user --> agent: Defines tasks and rewards\n    user --> nostr: Communicates and transacts\n    user --> bitcoin: Holds funds\n    user --> lightning: Sends/receives micropayments\n    user --> rgb: Manages access and ownership\n    user --> nosdav: Stores and retrieves data\n    user --> github: Collaborates on agent development\n    user --> logseq: Manages agent configurations\n    user --> solidlite: Interacts with decentralized apps\n    user --> linkedjson: Structures data relationships\n    user --> omniverse: Creates virtual environments\n    user --> usd: Represents 3D assets\n  \n    agent --> nostr: Communicates and transacts\n    agent --> bitcoin: Receives payments\n    agent --> lightning: Sends/receives micropayments\n    agent --> rgb: Presents single-use seals for access\n    agent --> nosdav: Stores and retrieves data\n    agent --> github: Updates codebase and configurations\n    agent --> logseq: Executes tasks based on configurations\n    agent --> solidlite: Interacts with decentralized apps\n    agent --> linkedjson: Processes structured data\n    agent --> omniverse: Learns from virtual environments\n    agent --> usd: Manipulates 3D assets\n  \n    nostr --> bitcoin: Settles transactions\n    nostr --> lightning: Routes micropayments\n    nostr --> rgb: Communicates token information\n    nostr --> nosdav: Authenticates data access\n    nostr --> github: Triggers agent updates\n    nostr --> logseq: Synchronizes configurations\n    nostr --> solidlite: Enables decentralized communication\n    nostr --> linkedjson: Transmits structured data\n    nostr --> omniverse: Streams virtual environment data\n    nostr --> usd: Shares 3D asset references\n  \n    bitcoin --> lightning: Powers off-chain transactions\n    bitcoin --> rgb: Anchors token issuance and transfers\n    bitcoin --> nosdav: Incentivizes data storage and retrieval\n    bitcoin --> github: Incentivizes open-source contributions\n    bitcoin --> logseq: Rewards agent performance\n    bitcoin --> solidlite: Enables decentralized payments\n    bitcoin --> linkedjson: Represents financial relationships\n    bitcoin --> omniverse: Facilitates virtual asset ownership\n    bitcoin --> usd: Supports digital asset valuation\n  \n    rgb --> nosdav: Stores token metadata\n    rgb --> github: Integrates token-based access control\n    rgb --> logseq: Manages token-related tasks\n    rgb --> solidlite: Enables token-based interactions\n    rgb --> linkedjson: Represents token relationships\n    rgb --> omniverse: Facilitates virtual token ownership\n    rgb --> usd: Represents tokenized 3D assets\n  \n    nosdav --> github: Stores agent data and configurations\n    nosdav --> logseq: Provides data storage and retrieval\n    nosdav --> solidlite: Enables decentralized data storage\n    nosdav --> linkedjson: Stores structured data\n    nosdav --> omniverse: Stores virtual environment data\n    nosdav --> usd: Stores 3D asset data\n  \n    github --> logseq: Synchronizes agent configurations\n    github --> solidlite: Hosts decentralized app code\n    github --> linkedjson: Stores data schemas and ontologies\n    github --> omniverse: Stores virtual environment code\n    github --> usd: Stores 3D asset definitions\n  \n    logseq --> solidlite: Integrates with decentralized apps\n    logseq --> linkedjson: Manages structured data\n    logseq --> omniverse: Configures virtual environments\n    logseq --> usd: Defines 3D asset behaviors\n  \n    solidlite --> linkedjson: Utilizes structured data\n    solidlite --> omniverse: Enables decentralized virtual experiences\n    solidlite --> usd: Supports 3D asset integration\n  \n    linkedjson --> omniverse: Represents virtual environment relationships\n    linkedjson --> usd: Structures 3D asset metadata\n  \n    omniverse --> usd: Utilizes 3D asset format\n  ```\n  \n  This state diagram captures the main components discussed in the conversation and their interactions. Each component is represented as a state, and the arrows indicate the flow of data, communication, or dependencies between them.\n  \n  Please note that this is a high-level representation and may not capture every detail or nuance discussed. The diagram aims to provide an overview of the interconnected nature of the components within the decentralized AI agent framework.\n  \n  Copy\n  \n  Claude does not have the ability to run the code it generates yet.\n  \n  JO\n  \n  apologies, I mean a sequence diagram\n\n## Current Landscape (2025)\n\n- Industry adoption and implementations\n  - Metaverse platforms continue to evolve with focus on interoperability and open standards\n  - Web3 integration accelerating with decentralised identity and asset ownership\n  - Enterprise adoption growing in virtual collaboration, training, and digital twins\n  - UK companies increasingly active in metaverse development and immersive technologies\n\n- Technical capabilities\n  - Real-time rendering at photorealistic quality levels\n  - Low-latency networking enabling seamless multi-user experiences\n  - AI-driven content generation and procedural world building\n  - Spatial audio and haptics enhancing immersion\n\n- UK and North England context\n  - Manchester: Digital Innovation Factory supports metaverse startups and research\n  - Leeds: Holovis leads in immersive experiences for entertainment and training\n  - Newcastle: University research in spatial computing and interactive systems\n  - Sheffield: Advanced manufacturing using digital twin technology\n\n- Standards and frameworks\n  - Metaverse Standards Forum driving interoperability protocols\n  - WebXR enabling browser-based immersive experiences\n  - glTF and USD for 3D asset interchange\n  - Open Metaverse Interoperability Group defining cross-platform standards\n\n## Metadata\n\n- **Last Updated**: 2025-11-16\n- **Review Status**: Automated remediation with 2025 context\n- **Verification**: Academic sources verified\n- **Regional Context**: UK/North England where applicable",
  "properties": {
    "id": "emerging-tech-stack-owl-axioms",
    "collapsed": "true",
    "- ontology": "true",
    "- term-id": "mv-823917206471",
    "- preferred-term": "Emerging tech stack",
    "- source-domain": "metaverse",
    "- status": "active",
    "- public-access": "true",
    "- definition": "A component of the metaverse ecosystem focusing on emerging tech stack.",
    "- maturity": "mature",
    "- authority-score": "0.85",
    "- owl:class": "mv:EmergingTechStack",
    "- owl:physicality": "ConceptualEntity",
    "- owl:role": "Concept",
    "- belongsToDomain": "[[MetaverseDomain]]",
    "- enables": "[[ImmersiveExperience]], [[Presence]], [[SpatialComputing]]",
    "- requires": "[[DisplayTechnology]], [[TrackingSystem]], [[RenderingEngine]]",
    "- bridges-to": "[[HumanComputerInteraction]], [[ComputerVision]], [[Robotics]]"
  },
  "backlinks": [],
  "wiki_links": [
    "TrackingSystem",
    "ImmersiveExperience",
    "ComputerVision",
    "RenderingEngine",
    "SpatialComputing",
    "Robotics",
    "HumanComputerInteraction",
    "MetaverseDomain",
    "DisplayTechnology",
    "Presence"
  ],
  "ontology": {
    "term_id": "mv-823917206471",
    "preferred_term": "Emerging tech stack",
    "definition": "A component of the metaverse ecosystem focusing on emerging tech stack.",
    "source_domain": "metaverse",
    "maturity_level": null,
    "authority_score": 0.85
  }
}