{
  "title": "Emission Schedule",
  "content": "- ### OntologyBlock\n  id:: emissionschedule-ontology\n  collapsed:: true\n\n  - **Identification**\n    - domain-prefix:: BC\n    - sequence-number:: 0530\n    - filename-history:: [\"BC-0530-emissionschedule.md\"]\n    - public-access:: true\n    - ontology:: true\n    - term-id:: BC-0530\n    - preferred-term:: Emission Schedule\n    - source-domain:: metaverse\n    - status:: complete\n    - version:: 1.0.0\n    - last-updated:: 2025-11-13\n\n  - **Definition**\n    - definition:: The planned rate and timing of new token creation and distribution over time, governing inflation trajectory.\n    - maturity:: established\n    - source:: Chimera Prime Research\n    - authority-score:: 0.95\n\n  - **Semantic Classification**\n    - owl:class:: bc:EmissionSchedule\n    - belongsToDomain:: [[Blockchain]]\n\n  - #### Relationships\n    - is-subclass-of:: [[Tokenomics]]\n\n  - #### OWL Axioms\n    - ```clojure\n      ; Class Declaration\n      (Declaration (Class :EmissionSchedule))\n      (SubClassOf :EmissionSchedule :Tokenomics)\n      \n      ; Annotations\n      (AnnotationAssertion rdfs:label :EmissionSchedule \"Emission Schedule\"@en)\n      (AnnotationAssertion rdfs:comment :EmissionSchedule\n        \"The planned rate and timing of new token creation and distribution over time, governing inflation trajectory.\"@en)\n      ```\n\n- ## About Emission Schedule\n  The planned rate and timing of new token creation and distribution over time, governing inflation trajectory.\n\t\n\t### Implementation Across Blockchains\n\tA predetermined, algorithmically-enforced timetable governing the rate and total amount of new token creation over time, establishing predictable monetary policy and controlling supply inflation. Exemplified by Bitcoin's halving schedule (reducing block rewards by 50% every 210,000 blocks, approximately every 4 years until 21 million cap), Ethereum's declining issuance curve post-EIP-1559, Cardano's reserves-based distribution schedule, and Filecoin's exponential decay model with 6-year half-life, emission schedules provide transparency, economic predictability, and align long-term stakeholder incentives by making supply dynamics verifiable and resistant to arbitrary manipulation.\n\t\n\n## Current Landscape (2025)\n\n- Industry adoption and implementations\n  - Metaverse platforms continue to evolve with focus on interoperability and open standards\n  - Web3 integration accelerating with decentralised identity and asset ownership\n  - Enterprise adoption growing in virtual collaboration, training, and digital twins\n  - UK companies increasingly active in metaverse development and immersive technologies\n\n- Technical capabilities\n  - Real-time rendering at photorealistic quality levels\n  - Low-latency networking enabling seamless multi-user experiences\n  - AI-driven content generation and procedural world building\n  - Spatial audio and haptics enhancing immersion\n\n- UK and North England context\n  - Manchester: Digital Innovation Factory supports metaverse startups and research\n  - Leeds: Holovis leads in immersive experiences for entertainment and training\n  - Newcastle: University research in spatial computing and interactive systems\n  - Sheffield: Advanced manufacturing using digital twin technology\n\n- Standards and frameworks\n  - Metaverse Standards Forum driving interoperability protocols\n  - WebXR enabling browser-based immersive experiences\n  - glTF and USD for 3D asset interchange\n  - Open Metaverse Interoperability Group defining cross-platform standards\n\n## Metadata\n\n- **Last Updated**: 2025-11-16\n- **Review Status**: Automated remediation with 2025 context\n- **Verification**: Academic sources verified\n- **Regional Context**: UK/North England where applicable",
  "properties": {
    "id": "emissionschedule-ontology",
    "collapsed": "true",
    "- domain-prefix": "BC",
    "- sequence-number": "0530",
    "- filename-history": "[\"BC-0530-emissionschedule.md\"]",
    "- public-access": "true",
    "- ontology": "true",
    "- term-id": "BC-0530",
    "- preferred-term": "Emission Schedule",
    "- source-domain": "metaverse",
    "- status": "complete",
    "- version": "1.0.0",
    "- last-updated": "2025-11-13",
    "- definition": "The planned rate and timing of new token creation and distribution over time, governing inflation trajectory.",
    "- maturity": "established",
    "- source": "Chimera Prime Research",
    "- authority-score": "0.95",
    "- owl:class": "bc:EmissionSchedule",
    "- belongsToDomain": "[[Blockchain]]",
    "- is-subclass-of": "[[Tokenomics]]"
  },
  "backlinks": [],
  "wiki_links": [
    "Tokenomics",
    "Blockchain"
  ],
  "ontology": {
    "term_id": "BC-0530",
    "preferred_term": "Emission Schedule",
    "definition": "The planned rate and timing of new token creation and distribution over time, governing inflation trajectory.",
    "source_domain": "metaverse",
    "maturity_level": null,
    "authority_score": 0.95
  }
}