{
  "title": "Emotional Intelligence",
  "content": "- ### OntologyBlock\n  id:: emotionalintelligence-ontology\n  collapsed:: true\n\n  - **Identification**\n    - domain-prefix:: AI\n    - sequence-number:: 0870\n    - filename-history:: [\"AI-0870-emotionalintelligence.md\"]\n    - public-access:: true\n    - ontology:: true\n    - is-subclass-of:: [[ArtificialIntelligenceTechnology]]\n    - term-id:: AI-0870\n    - preferred-term:: Emotional Intelligence\n    - source-domain:: ai\n    - status:: complete\n    - version:: 1.0.0\n    - last-updated:: 2025-11-13\n\n  - **Definition**\n    - definition:: \n    - maturity:: established\n    - source:: Chimera Prime Research\n    - authority-score:: 0.95\n\n  - **Semantic Classification**\n    - owl:class:: ai:EmotionalIntelligence\n    - belongsToDomain:: [[Artificial Intelligence]]\n\n  - #### OWL Restrictions\n    \n\n  -",
  "properties": {
    "id": "emotionalintelligence-ontology",
    "collapsed": "true",
    "- domain-prefix": "AI",
    "- sequence-number": "0870",
    "- filename-history": "[\"AI-0870-emotionalintelligence.md\"]",
    "- public-access": "true",
    "- ontology": "true",
    "- is-subclass-of": "[[ArtificialIntelligenceTechnology]]",
    "- term-id": "AI-0870",
    "- preferred-term": "Emotional Intelligence",
    "- source-domain": "ai",
    "- status": "complete",
    "- version": "1.0.0",
    "- last-updated": "2025-11-13",
    "- definition": "",
    "- maturity": "established",
    "- source": "Chimera Prime Research",
    "- authority-score": "0.95",
    "- owl:class": "ai:EmotionalIntelligence",
    "- belongsToDomain": "[[Artificial Intelligence]]"
  },
  "backlinks": [],
  "wiki_links": [
    "Artificial Intelligence",
    "ArtificialIntelligenceTechnology"
  ],
  "ontology": {
    "term_id": "AI-0870",
    "preferred_term": "Emotional Intelligence",
    "definition": "",
    "source_domain": "ai",
    "maturity_level": null,
    "authority_score": 0.95
  }
}