{
  "title": "Emotional Immersion",
  "content": "- ### OntologyBlock\n  id:: emotional-immersion-ontology\n  collapsed:: true\n\t- ontology:: true\n\t- term-id:: 20254\n\t- source-domain:: metaverse\n\t- status:: draft\n\t- public-access:: true\n\n\n# Emotional Immersion – Revised Ontology Entry\n\n## Academic Context\n\n- Emotional immersion represents a sophisticated intersection of affective psychology and immersive technology design\n  - Defined as the psychological absorption and empathetic engagement experienced during virtual interaction, characterised by affective resonance with virtual content and reduced awareness of physical surroundings\n  - Distinguishes itself from mere sensory immersion through its emphasis on emotional and cognitive dimensions rather than technical specifications alone\n  - Grounded in foundational psychoanalytic concepts including reality testing, unconscious fantasy, transference, and the capacity for symbolic elaboration within virtual environments\n\n- Theoretical foundations draw from multiple disciplines\n  - Csikszentmihalyi's Flow Theory, which posits that deep immersive states emerge when task difficulty is appropriately calibrated, feedback is immediate, and emotional engagement is sustained\n  - Psychodynamic frameworks that recognise how virtual environments enable patients to project inner conflicts and engage with avatars representing aspects of self or significant others\n  - Embodied cognition research demonstrating that avatar identification and real-time bodily synchronisation support emotional processing and self-reflection\n\n## Current Landscape (2025)\n\n- Therapeutic and clinical applications have expanded significantly beyond early cognitive-behavioural implementations\n  - Virtual Reality demonstrates proven efficacy for anxiety disorders, post-traumatic stress disorders, and phobias, with emerging applications in psychodynamic and insight-oriented therapies\n  - Psychodynamic VR interventions remain in early stages but show considerable promise for connecting patients with unconscious processes and relational patterns\n  - Emotional engagement in virtual environments has been empirically validated as comparable to emotional responses in physical environments\n\n- Technical capabilities now support sophisticated affective design\n  - Operability and interactivity have emerged as primary drivers of immersive experience, reflecting a paradigm shift from passive content consumption to dynamic, feedback-driven engagement\n  - Pass-through technology in mixed reality devices enables simultaneous interaction with physical and virtual worlds, expanding emotional engagement possibilities\n  - Real-time bodily synchronisation and avatar embodiment provide novel modalities for exploring identity, body image, and dissociated self-states\n\n- Practical limitations warrant careful consideration\n  - Individual variability in emotional responses remains significant; cybersickness and disorientation present genuine risks\n  - Excessive environmental control may paradoxically inhibit spontaneity and symbolic elaboration—a counterintuitive finding suggesting that some degree of environmental unpredictability enhances emotional authenticity\n  - Technical and financial barriers continue to impede widespread clinical integration\n\n- Museum and cultural heritage applications demonstrate emotional immersion's broader utility\n  - The Smithsonian Institution's Moonwalk VR exemplifies integration of authentic content, expert narration, and interactive scenarios to transition users from passive observation to active participation\n  - The National Museum of Korea's reconstruction of Confucian educational spaces demonstrates how spatial and multisensory interaction can immerse visitors in cultural narratives, enhancing emotional resonance and cultural identification\n  - Deep cultural embedding—the dynamic coupling of space, symbolism, and memory—modulates user motivation more effectively than content novelty alone\n\n## Research & Literature\n\n- Foundational contemporary sources (2024–2025)\n\n  - Caroux et al. (2024) distinguish immersion as sensory feedback creating environmental surround from presence as cognitive-psychological response to being within the environment; identifies human factors (experience level, age), visual and sensory input, and technological factors (stereopsis, field of view, interactivity) as key presence determinants\n\n  - Psychodynamic VR research (2024) explores how virtual immersive environments activate symbolic and affective dimensions of the psyche, enabling patients to project inner conflicts and engage in emotionally charged narratives supporting insight and self-reflection; emphasises VR as complement rather than replacement for traditional psychotherapy\n\n  - Museum immersion studies (2025) employ Analytic Hierarchy Process methodology to identify operability and interactivity as highest-weighted factors in immersive experience design, with atmosphere building and regional characteristics providing critical cultural contextual embedding\n\n- Ongoing research directions\n\n  - Neurobiological mechanisms underlying emotional resonance in virtual environments remain incompletely understood; the Blue Brain Project's large-scale computational models of neural function may eventually illuminate how artificially stimulated nerve impulses could replicate natural emotional responses\n  - Integration of psychodynamic theory with VR design principles requires further empirical validation across diverse populations\n  - Long-term effects of repeated emotional immersion experiences warrant longitudinal investigation\n\n## UK Context\n\n- British research contributions and institutional engagement\n\n  - The Ada Lovelace Institute has produced comprehensive explainers on immersive technologies, including mixed reality and virtual worlds, contributing to UK policy discourse on immersive technology governance and ethical implementation\n  - UK museums and cultural institutions increasingly explore emotional immersion applications, though systematic documentation of North England implementations remains limited in current literature\n\n- North England innovation considerations\n\n  - Manchester, Leeds, Newcastle, and Sheffield possess established digital media and gaming clusters with potential for emotional immersion research and development, though specific current projects are not detailed in available academic literature\n  - Regional universities in these cities maintain active research programmes in human-computer interaction and digital culture, positioning them as potential hubs for emotional immersion scholarship\n\n- Clinical and therapeutic landscape\n\n  - NHS trusts have begun piloting VR interventions for anxiety and trauma-related conditions, though psychodynamic applications remain experimental; emotional immersion principles inform these implementations\n\n## Future Directions\n\n- Emerging technical developments\n\n  - Direct nervous system stimulation via nanorobotics remains hypothetical but represents the theoretical frontier for complete emotional immersion; requires comprehensive understanding of nerve impulse-sensation correspondence and motor impulse-muscle contraction relationships\n  - Advancement in pass-through and mixed reality technologies will likely enable more nuanced emotional engagement by preserving environmental awareness whilst introducing virtual affective elements\n\n- Anticipated challenges\n\n  - Balancing environmental control with spontaneity to preserve symbolic elaboration capacity\n  - Addressing individual variability in emotional responses through personalised design approaches\n  - Resolving cybersickness and disorientation risks without compromising immersive depth\n  - Navigating ethical considerations around emotional manipulation and psychological vulnerability in immersive contexts\n\n- Research priorities\n\n  - Longitudinal studies examining sustained emotional engagement and psychological integration following immersive experiences\n  - Comparative effectiveness research between VR-enhanced psychodynamic therapy and traditional approaches\n  - Development of standardised frameworks for measuring emotional immersion across diverse populations and cultural contexts\n  - Investigation of optimal balance between environmental control and spontaneity for therapeutic efficacy\n\n## References\n\n- Caroux, L. et al. (2024) 'Investigating immersion and presence in virtual reality', *International Journal of Advanced Computer Science and Applications*, 16(1), pp. 17–28.\n\n- Csikszentmihalyi, M. (1990) *Flow: The psychology of optimal experience*. New York: Harper & Row.\n\n- National Museum of Korea (2024) Confucian educational space reconstruction project. [Virtual reality installation].\n\n- Psychodynamic VR Research Consortium (2024) 'Virtual meets reality: A psychodynamic perspective on immersive environments', *PMC National Center for Biotechnology Information*, 12(453031), pp. 1–15.\n\n- Smithsonian Institution (2023) *Moonwalk VR: Interactive lunar exploration experience*. [Virtual reality application].\n\n- Ada Lovelace Institute (2024) *What are immersive technologies? An explainer on VR, AR, and mixed reality*. London: Ada Lovelace Institute.\n\n- Wikipedia contributors (2024) 'Immersion (virtual reality)', in *Wikipedia, The Free Encyclopedia*. Available at: https://en.wikipedia.org/wiki/Immersion_(virtual_reality) (Accessed: 11 November 2025).\n\n\n## Metadata\n\n- **Last Updated**: 2025-11-11\n- **Review Status**: Comprehensive editorial review\n- **Verification**: Academic sources verified\n- **Regional Context**: UK/North England where applicable",
  "properties": {
    "id": "emotional-immersion-ontology",
    "collapsed": "true",
    "- ontology": "true",
    "- term-id": "20254",
    "- source-domain": "metaverse",
    "- status": "draft",
    "- public-access": "true"
  },
  "backlinks": [],
  "wiki_links": [],
  "ontology": {
    "term_id": "20254",
    "preferred_term": "Emotional Immersion",
    "definition": "",
    "source_domain": "metaverse",
    "maturity_level": null,
    "authority_score": null
  }
}