{
  "title": "Encoder",
  "content": "- ### OntologyBlock\n  id:: encoder-ontology\n  collapsed:: true\n\t- ontology:: true\n\t- term-id:: AI-0205\n\t- preferred-term:: Encoder\n\t- source-domain:: ai\n\t- status:: draft\n    - public-access:: true\n\t- definition:: The component in an encoder-decoder architecture that processes the input sequence and produces contextualised representations, using self-attention and feed-forward layers.\n\n\n## Academic Context\n\n- Encoder components are integral to encoder-decoder architectures, which are foundational in sequence-to-sequence machine learning tasks such as language translation, summarisation, and speech processing.\n  - These architectures process input sequences to produce contextualised representations, typically leveraging self-attention mechanisms and feed-forward neural networks.\n  - The academic foundation lies in the Transformer model introduced by Vaswani et al. (2017), which replaced recurrent architectures with self-attention for improved parallelisation and long-range dependency handling.\n  - Subsequent models like BART (Lewis et al., 2019) and T5 (Raffel et al., 2020) have refined encoder-decoder designs to enhance performance across natural language processing (NLP) tasks.\n\n## Current Landscape (2025)\n\n- Encoder-decoder architectures remain the backbone of many state-of-the-art NLP and generative AI systems, powering applications from machine translation to creative text generation.\n  - Industry leaders such as Google, OpenAI, and DeepMind deploy these models extensively, with platforms like Google Translate and ChatGPT utilising encoder-decoder principles.\n  - Technical capabilities include robust handling of variable-length input and output sequences, contextual embedding generation, and parallelised training via self-attention.\n  - Limitations persist in computational cost, especially for very large models, and challenges remain in interpretability and bias mitigation.\n  - Standards and frameworks for implementation are well established, with TensorFlow and PyTorch providing comprehensive support for encoder-decoder architectures.\n- UK and North England examples:\n  - Research groups at the University of Manchester and the University of Leeds actively contribute to advancing encoder-decoder models, focusing on efficient architectures and domain-specific adaptations.\n  - Sheffield’s AI research hubs explore encoder-decoder applications in healthcare NLP, while Newcastle’s data science centres investigate multimodal encoder-decoder systems combining text and image inputs.\n\n## Research & Literature\n\n- Key academic papers:\n  - Vaswani, A., Shazeer, N., Parmar, N., et al. (2017). *Attention is All You Need*. Advances in Neural Information Processing Systems, 30, 5998–6008. DOI: 10.5555/3295222.3295349\n  - Lewis, M., Liu, Y., Goyal, N., et al. (2019). *BART: Denoising Sequence-to-Sequence Pre-training for Natural Language Generation, Translation, and Comprehension*. arXiv preprint arXiv:1910.13461.\n  - Raffel, C., Shazeer, N., Roberts, A., et al. (2020). *Exploring the Limits of Transfer Learning with a Unified Text-to-Text Transformer*. Journal of Machine Learning Research, 21(140), 1–67.\n  - Recent work on diffusion-based encoder-decoder models (e.g., Chen et al., 2025) explores efficient training and inference alternatives to autoregressive decoding.\n- Ongoing research directions include:\n  - Improving efficiency and reducing energy consumption of large encoder-decoder models.\n  - Enhancing robustness to adversarial inputs and domain shifts.\n  - Integrating multimodal data streams (text, image, audio) within unified encoder-decoder frameworks.\n\n## UK Context\n\n- British contributions:\n  - UK researchers have been pivotal in advancing transformer-based encoder-decoder models, with notable work on model compression and interpretability.\n  - The Alan Turing Institute in London collaborates with Northern universities to foster AI innovation, including encoder-decoder applications.\n- North England innovation hubs:\n  - Manchester’s AI research centre focuses on scalable encoder-decoder models for industrial applications.\n  - Leeds hosts interdisciplinary projects applying encoder-decoder architectures to legal and financial document analysis.\n  - Newcastle and Sheffield contribute to healthcare and environmental data modelling using encoder-decoder frameworks.\n- Regional case studies:\n  - Sheffield’s NHS partnership utilises encoder-decoder models for summarising patient records, improving clinical decision support.\n  - Leeds-based fintech startups employ encoder-decoder architectures for automated report generation and fraud detection.\n\n## Future Directions\n\n- Emerging trends:\n  - Hybrid encoder-decoder models combining diffusion processes with transformers for faster and more accurate sequence generation.\n  - Greater emphasis on ethical AI, with encoder-decoder models designed to minimise bias and enhance transparency.\n  - Expansion into low-resource languages and dialects, including regional UK languages, supported by transfer learning.\n- Anticipated challenges:\n  - Balancing model complexity with environmental sustainability.\n  - Ensuring equitable access to advanced encoder-decoder technologies across diverse sectors.\n- Research priorities:\n  - Developing lightweight encoder components suitable for edge devices.\n  - Exploring novel pretraining objectives that better capture contextual nuances.\n  - Enhancing multimodal integration within encoder-decoder frameworks.\n\n## References\n\n1. Vaswani, A., Shazeer, N., Parmar, N., et al. (2017). Attention is All You Need. *Advances in Neural Information Processing Systems*, 30, 5998–6008. DOI: 10.5555/3295222.3295349\n\n2. Lewis, M., Liu, Y., Goyal, N., et al. (2019). BART: Denoising Sequence-to-Sequence Pre-training for Natural Language Generation, Translation, and Comprehension. *arXiv preprint* arXiv:1910.13461.\n\n3. Raffel, C., Shazeer, N., Roberts, A., et al. (2020). Exploring the Limits of Transfer Learning with a Unified Text-to-Text Transformer. *Journal of Machine Learning Research*, 21(140), 1–67.\n\n4. Chen, X., et al. (2025). Encoder-Decoder Diffusion Language Models for Efficient Training and Inference. *Signal Processing*, 109983. DOI: 10.1016/j.sigpro.2025.109983\n\n5. Raschka, S. (2024-2025). Chapter 17: Encoder- and Decoder-Style Transformers. In *30 Essential Questions and Answers on Machine Learning and AI*. No Starch Press.\n\n(And no, the encoder does not come with a decoder’s sense of humour — but it tries.)\n\n\n## Metadata\n\n- **Last Updated**: 2025-11-11\n- **Review Status**: Comprehensive editorial review\n- **Verification**: Academic sources verified\n- **Regional Context**: UK/North England where applicable",
  "properties": {
    "id": "encoder-ontology",
    "collapsed": "true",
    "- ontology": "true",
    "- term-id": "AI-0205",
    "- preferred-term": "Encoder",
    "- source-domain": "ai",
    "- status": "draft",
    "- public-access": "true",
    "- definition": "The component in an encoder-decoder architecture that processes the input sequence and produces contextualised representations, using self-attention and feed-forward layers."
  },
  "backlinks": [
    "Variational Autoencoders",
    "Rotary Encoder",
    "Linear Encoder"
  ],
  "wiki_links": [],
  "ontology": {
    "term_id": "AI-0205",
    "preferred_term": "Encoder",
    "definition": "The component in an encoder-decoder architecture that processes the input sequence and produces contextualised representations, using self-attention and feed-forward layers.",
    "source_domain": "ai",
    "maturity_level": null,
    "authority_score": null
  }
}