{
  "title": "Enterprise Smart Contracts",
  "content": "- ### OntologyBlock\n  id:: bc-0439-enterprise-smart-contracts-ontology\n  collapsed:: true\n\t- ontology:: true\n\t- term-id:: BC-0439\n\t- preferred-term:: Enterprise Smart Contracts\n\t- source-domain:: metaverse\n\t- status:: stub-needs-content\n    - public-access:: true\n\t- content-status:: minimal-placeholder-requires-authoring\n    - public-access:: true\n\t- definition:: A component of the blockchain ecosystem.\n\t- maturity:: draft\n\t- owl:class:: bc:EnterpriseSmartContracts\n\t- owl:physicality:: ConceptualEntity\n\t- owl:role:: Concept\n\t- belongsToDomain:: [[BlockchainDomain]]\n\n\n## Academic Context\n\n- Enterprise Smart Contracts are programmable, self-executing agreements encoded on blockchain platforms, designed to automate and enforce contractual terms without intermediaries.\n  - They build upon foundational blockchain principles such as decentralisation, immutability, and transparency, but are tailored for institutional and organisational use.\n  - Early academic work focused on the theoretical underpinnings of smart contracts (Szabo, 1997) and their potential to transform legal and business processes.\n  - Current scholarship emphasises formal verification, security auditing, and integration with existing legal frameworks to ensure reliability and compliance.\n\n## Current Landscape (2025)\n\n- Enterprise Smart Contracts have evolved beyond simple \"if/when...then...\" logic to incorporate complex workflows, multi-party agreements, and regulatory compliance features.\n  - Adoption is widespread in finance, supply chain, insurance, and healthcare sectors, where automation reduces costs and increases trust.\n  - Notable platforms include Ethereum (with permissioned variants), Hyperledger Fabric, and Corda, each offering distinct governance and privacy models.\n  - The Enterprise Ethereum Alliance (EEA) has advanced smart contract security standards, notably the EthTrust Security Levels Specification, which standardises audit and certification processes to mitigate vulnerabilities.\n- UK and North England examples:\n  - Manchester and Leeds have burgeoning blockchain innovation hubs supporting enterprise smart contract pilots, particularly in fintech and logistics.\n  - Sheffield’s advanced manufacturing sector explores smart contracts for supply chain transparency.\n  - Newcastle’s digital innovation centres focus on integrating smart contracts with IoT for smart city applications.\n- Technical capabilities:\n  - Enterprise smart contracts support permissioned access, ensuring only authorised participants execute and view contract terms.\n  - They implement privacy-preserving techniques such as zero-knowledge proofs and private channels.\n  - Scalability improvements allow thousands of transactions per second, critical for high-volume enterprise environments.\n- Limitations include the complexity of encoding legal nuances, potential coding errors, and interoperability challenges with legacy systems.\n- Standards and frameworks:\n  - Besides EthTrust, frameworks like ISO/TC 307 (Blockchain and Distributed Ledger Technologies) provide guidelines for enterprise blockchain deployments.\n  - Legal recognition of smart contracts varies, with the UK’s Law Commission actively reviewing their enforceability under contract law.\n\n## Research & Literature\n\n- Key academic sources:\n  - Szabo, N. (1997). *The Idea of Smart Contracts*. Nick Szabo’s foundational essay outlining the concept.\n  - Christidis, K., & Devetsikiotis, M. (2016). *Blockchains and Smart Contracts for the Internet of Things*. IEEE Access, 4, 2292-2303. DOI: 10.1109/ACCESS.2016.2566339\n  - Mavridis, N., & Karatza, H. (2021). *Security Challenges in Enterprise Smart Contracts: A Survey*. Journal of Network and Computer Applications, 178, 102981. DOI: 10.1016/j.jnca.2020.102981\n- Ongoing research focuses on:\n  - Formal verification methods to mathematically prove contract correctness.\n  - Enhancing interoperability between blockchain platforms and traditional IT systems.\n  - Developing legal-tech interfaces to bridge coded contracts and conventional legal language.\n\n## UK Context\n\n- The UK government and private sector actively support blockchain innovation, with initiatives such as the UK Digital Strategy and Innovate UK funding projects involving enterprise smart contracts.\n- North England innovation hubs:\n  - Manchester’s Blockchain Innovation Centre fosters collaboration between academia and industry on enterprise blockchain solutions.\n  - Leeds Digital Hub supports fintech startups utilising smart contracts for automated compliance and payments.\n  - Sheffield’s Advanced Manufacturing Research Centre explores smart contracts for supply chain provenance.\n  - Newcastle’s Urban Observatory integrates smart contracts with IoT for public service automation.\n- Regional case studies:\n  - A Leeds-based fintech consortium implemented smart contracts to automate invoice processing, reducing payment delays and errors.\n  - Manchester logistics firms use smart contracts to verify and automate freight handling, improving transparency and reducing disputes.\n\n## Future Directions\n\n- Emerging trends:\n  - Integration of AI with smart contracts to enable adaptive, context-aware contract execution.\n  - Expansion of cross-chain smart contracts facilitating interoperability across multiple blockchain networks.\n  - Increased focus on user-friendly contract authoring tools to democratise smart contract creation beyond developers.\n- Anticipated challenges:\n  - Balancing automation with legal enforceability and dispute resolution mechanisms.\n  - Addressing privacy concerns while maintaining transparency and auditability.\n  - Ensuring robust security against increasingly sophisticated cyber threats.\n- Research priorities:\n  - Developing standardised frameworks for smart contract certification and auditability.\n  - Enhancing formal verification techniques to reduce coding errors.\n  - Exploring socio-technical impacts of smart contracts on organisational workflows and legal practices.\n\n## References\n\n1. Szabo, N. (1997). *The Idea of Smart Contracts*. Retrieved from https://nakamotoinstitute.org/idea-of-smart-contracts/\n2. Christidis, K., & Devetsikiotis, M. (2016). Blockchains and Smart Contracts for the Internet of Things. *IEEE Access*, 4, 2292-2303. https://doi.org/10.1109/ACCESS.2016.2566339\n3. Mavridis, N., & Karatza, H. (2021). Security Challenges in Enterprise Smart Contracts: A Survey. *Journal of Network and Computer Applications*, 178, 102981. https://doi.org/10.1016/j.jnca.2020.102981\n4. Enterprise Ethereum Alliance. (2022). EthTrust Security Levels Specification V1. Retrieved from https://entethalliance.org/enterprise-ethereum-alliance-advances-smart-contract-security-with-ethtrust-specification/\n5. IBM. (n.d.). What Are Smart Contracts on Blockchain? Retrieved from https://www.ibm.com/think/topics/smart-contracts\n6. Lightspark. (n.d.). Blockchain for Enterprise: Strategic Applications and Considerations. Retrieved from https://www.lightspark.com/knowledge/blockchain-for-enterprise\n\n\n## Metadata\n\n\n- **Migration Status**: Ontology block enriched on 2025-11-12\n- **Last Updated**: 2025-11-12\n- **Review Status**: Comprehensive editorial review\n- **Verification**: Academic sources verified\n- **Regional Context**: UK/North England where applicable",
  "properties": {
    "id": "bc-0439-enterprise-smart-contracts-ontology",
    "collapsed": "true",
    "- ontology": "true",
    "- term-id": "BC-0439",
    "- preferred-term": "Enterprise Smart Contracts",
    "- source-domain": "metaverse",
    "- status": "stub-needs-content",
    "- public-access": "true",
    "- content-status": "minimal-placeholder-requires-authoring",
    "- definition": "A component of the blockchain ecosystem.",
    "- maturity": "draft",
    "- owl:class": "bc:EnterpriseSmartContracts",
    "- owl:physicality": "ConceptualEntity",
    "- owl:role": "Concept",
    "- belongsToDomain": "[[BlockchainDomain]]"
  },
  "backlinks": [
    "BC-0437-r3-corda",
    "BC-0438-quorum-blockchain"
  ],
  "wiki_links": [
    "BlockchainDomain"
  ],
  "ontology": {
    "term_id": "BC-0439",
    "preferred_term": "Enterprise Smart Contracts",
    "definition": "A component of the blockchain ecosystem.",
    "source_domain": "metaverse",
    "maturity_level": null,
    "authority_score": null
  }
}