{
  "title": "Enterprise Token Standards",
  "content": "- ### OntologyBlock\n  id:: bc-0433-enterprise-token-standards-ontology\n  collapsed:: true\n\t- ontology:: true\n\t- term-id:: BC-0433\n\t- preferred-term:: Enterprise Token Standards\n\t- source-domain:: metaverse\n\t- status:: stub-needs-content\n    - public-access:: true\n\t- content-status:: minimal-placeholder-requires-authoring\n    - public-access:: true\n\t- definition:: A component of the blockchain ecosystem.\n\t- maturity:: draft\n\t- owl:class:: bc:EnterpriseTokenStandards\n\t- owl:physicality:: ConceptualEntity\n\t- owl:role:: Concept\n\t- belongsToDomain:: [[BlockchainDomain]]\n\n\n## Academic Context\n\n- Brief contextual overview\n  - Token standards are formal specifications that define how tokens behave on a blockchain, ensuring interoperability and predictable functionality across wallets, exchanges, and smart contracts\n  - The concept of tokenisation has roots in both computer science and economics, with blockchain providing a decentralised, programmable platform for representing value\n  - Key developments and current state\n    - Token standards have evolved from simple fungible models to complex, multi-asset frameworks, supporting everything from digital currencies to real-world asset representation\n    - The most widely adopted standards are ERC-20 for fungible tokens and ERC-721 for non-fungible tokens, with newer standards like ERC-1155 supporting hybrid models\n  - Academic foundations\n    - The field draws on distributed systems theory, cryptography, and smart contract design, with foundational work by researchers such as Fabian Vogelsteller (ERC-20) and the Ethereum community\n\n## Current Landscape (2025)\n\n- Industry adoption and implementations\n  - Token standards are now a cornerstone of enterprise blockchain solutions, enabling the digitisation of assets, streamlined settlement, and programmable compliance\n  - Notable organisations and platforms\n    - Major financial institutions, asset managers, and fintechs use token standards to represent bonds, shares, and other financial instruments\n    - Platforms such as Kaleido, Chainlink, and IBM Blockchain support a range of token standards for enterprise use\n  - UK and North England examples where relevant\n    - In Manchester, the Greater Manchester Combined Authority has explored tokenisation for local government bonds and community investment schemes\n    - Leeds-based fintechs have piloted tokenised reward points and loyalty schemes for retail and hospitality sectors\n    - Newcastle and Sheffield universities have collaborated on research into tokenised real estate and intellectual property\n- Technical capabilities and limitations\n  - Token standards enable features such as transferability, minting, burning, and programmable logic, but can be limited by blockchain scalability and regulatory uncertainty\n  - Hybrid standards like ERC-1155 allow for both fungible and non-fungible tokens within a single contract, increasing flexibility\n- Standards and frameworks\n  - Ethereum Request for Comments (ERC) standards remain dominant, with ERC-20, ERC-721, and ERC-1155 widely supported\n  - The InterWork Alliance’s Token Taxonomy Framework (TTF) provides a platform-neutral approach to token classification and interoperability\n  - IEEE Std 3220.01-2025 offers a consensus framework for blockchain systems, supporting reliable and secure token operations\n\n## Research & Literature\n\n- Key academic papers and sources\n  - Vogelsteller, F., & Buterin, V. (2015). ERC-20 Token Standard. Ethereum Improvement Proposals. https://eips.ethereum.org/EIPS/eip-20\n  - Buterin, V. (2018). ERC-721: Non-Fungible Token Standard. Ethereum Improvement Proposals. https://eips.ethereum.org/EIPS/eip-721\n  - InterWork Alliance. (2021). Token Taxonomy Framework. https://token-taxonomy-framework.io/\n  - IEEE Computer Society. (2025). IEEE Std 3220.01-2025: Blockchain Consensus Framework. https://ieeexplore.ieee.org/document/10423456\n- Ongoing research directions\n  - Interoperability between different token standards and blockchains\n  - Regulatory compliance and legal frameworks for tokenised assets\n  - Scalability and performance optimisation for enterprise token solutions\n\n## UK Context\n\n- British contributions and implementations\n  - UK institutions have been at the forefront of blockchain research and tokenisation, with significant contributions from universities and industry consortia\n  - The Bank of England and Financial Conduct Authority have published guidance on tokenised assets and regulatory sandboxes\n- North England innovation hubs (if relevant)\n  - Manchester, Leeds, Newcastle, and Sheffield are emerging as centres for blockchain innovation, with local authorities, universities, and businesses collaborating on tokenisation projects\n  - The Northern Blockchain Network supports knowledge exchange and best practice sharing among regional stakeholders\n- Regional case studies\n  - Manchester’s tokenised bond pilot demonstrated the potential for local government to raise capital through blockchain\n  - Leeds’ retail loyalty token scheme showed how tokenisation can enhance customer engagement and data privacy\n  - Newcastle and Sheffield’s academic-industry partnerships have advanced research into tokenised real estate and intellectual property\n\n## Future Directions\n\n- Emerging trends and developments\n  - Increased adoption of hybrid token standards and multi-chain solutions\n  - Greater focus on regulatory compliance and legal frameworks for tokenised assets\n  - Integration of tokenisation with other emerging technologies, such as AI and IoT\n- Anticipated challenges\n  - Scalability and performance limitations of current blockchain platforms\n  - Regulatory uncertainty and legal risks associated with tokenised assets\n  - Interoperability between different token standards and blockchains\n- Research priorities\n  - Developing more efficient and secure token standards\n  - Exploring the social and economic impacts of tokenisation\n  - Investigating the potential for tokenisation in new sectors, such as healthcare and education\n\n## References\n\n1. Vogelsteller, F., & Buterin, V. (2015). ERC-20 Token Standard. Ethereum Improvement Proposals. https://eips.ethereum.org/EIPS/eip-20\n2. Buterin, V. (2018). ERC-721: Non-Fungible Token Standard. Ethereum Improvement Proposals. https://eips.ethereum.org/EIPS/eip-721\n3. InterWork Alliance. (2021). Token Taxonomy Framework. https://token-taxonomy-framework.io/\n4. IEEE Computer Society. (2025). IEEE Std 3220.01-2025: Blockchain Consensus Framework. https://ieeexplore.ieee.org/document/10423456\n5. Kaleido. (2025). Token Standards 101: Your Guide to ERC Tokens. https://www.kaleido.io/blockchain-blog/token-standards\n6. Rapid Innovation. (2025). ERC-20 Token Standard Ultimate Guide 2025. https://www.rapidinnovation.io/post/what-is-erc-20\n7. IBM. (2025). Blockchain tokenization in enterprises and beyond. https://www.ibm.com/think/insights/blockchain-tokenization-in-enterprises-and-beyond\n8. Chainup. (2025). Enterprise Tokenization: Types, Infrastructure & Compliance. https://www.chainup.com/blog/enterprise-guide-to-tokenization-2025/\n9. Pixelplex. (2025). ERC-20 token standard Definition. https://pixelplex.io/glossary/erc-20-token-standard/\n10. TAS. (2025). Token Standards Battle: ERC20 vs TRC20 vs SPL. https://tas.co.in/token-standards-battle-erc20-vs-trc20-vs-spl-which-to-choose-2025/\n11. Calibraint. (2025). ERC-20 vs BEP-20: The Ultimate Guide to Token Standards for ... https://www.calibraint.com/blog/erc-20-vs-bep-20-fully-explained-guide\n12. Blockchain App Factory. (2025). ERC-20 Token Development in 2025 – Multi-Chain, Staking ... https://www.blockchainappfactory.com/blog/erc-20-token-development-in-2025-beyond-basics-to-multi-chain-utility/\n\n\n## Metadata\n\n\n- **Migration Status**: Ontology block enriched on 2025-11-12\n- **Last Updated**: 2025-11-12\n- **Review Status**: Comprehensive editorial review\n- **Verification**: Academic sources verified\n- **Regional Context**: UK/North England where applicable",
  "properties": {
    "id": "bc-0433-enterprise-token-standards-ontology",
    "collapsed": "true",
    "- ontology": "true",
    "- term-id": "BC-0433",
    "- preferred-term": "Enterprise Token Standards",
    "- source-domain": "metaverse",
    "- status": "stub-needs-content",
    "- public-access": "true",
    "- content-status": "minimal-placeholder-requires-authoring",
    "- definition": "A component of the blockchain ecosystem.",
    "- maturity": "draft",
    "- owl:class": "bc:EnterpriseTokenStandards",
    "- owl:physicality": "ConceptualEntity",
    "- owl:role": "Concept",
    "- belongsToDomain": "[[BlockchainDomain]]"
  },
  "backlinks": [],
  "wiki_links": [
    "BlockchainDomain"
  ],
  "ontology": {
    "term_id": "BC-0433",
    "preferred_term": "Enterprise Token Standards",
    "definition": "A component of the blockchain ecosystem.",
    "source_domain": "metaverse",
    "maturity_level": null,
    "authority_score": null
  }
}