{
  "title": "Epoch",
  "content": "- ### OntologyBlock\n  id:: epoch-ontology\n  collapsed:: true\n\t- ontology:: true\n\t- term-id:: AI-0049\n\t- preferred-term:: Epoch\n\t- source-domain:: ai\n\t- status:: draft\n\t- public-access:: true\n\n\n## Academic Context\n\n- An epoch is a fundamental unit of geological time, positioned between a period and an age, used to categorise significant intervals in Earth's history characterised by distinct climatic, biological, and geological changes.\n  - It serves as a critical framework for understanding Earth's evolutionary timeline and environmental shifts over millions of years.\n  - The concept also extends beyond geology into astronomy, where an epoch denotes a precise reference moment for celestial measurements, and into machine learning, where it describes a complete pass through a dataset during training.\n- The academic foundations of the term trace back to classical languages—New Latin *epocha* and Greek *epochē*—meaning a fixed or paused time, reflecting its role as a temporal marker.\n\n## Current Landscape (2025)\n\n- Epochs remain central to multiple disciplines:\n  - In geology, epochs continue to structure the geologic time scale, with recent refinements in stratigraphy and radiometric dating enhancing precision.\n  - Astronomy utilises epochs as reference points for celestial coordinate systems, with Julian and Julian-like epochs (e.g., J2000.0) standardised for consistency.\n  - In machine learning, the term ‘epoch’ is a key hyperparameter defining the number of full dataset iterations during model training, balancing learning and overfitting risks.\n- Notable organisations and platforms employing epoch concepts include geological survey institutions, astronomical observatories, and AI research centres.\n- Within the UK, especially in North England cities such as Manchester, Leeds, Newcastle, and Sheffield, universities and research institutes actively engage in geological and astronomical research utilising epoch frameworks.\n- Technical capabilities have advanced with improved dating technologies and computational models, though limitations persist in precisely correlating epochs across different regional stratigraphies and in managing overfitting in machine learning epochs.\n- Standards and frameworks are governed by international bodies such as the International Commission on Stratigraphy for geological epochs and the International Astronomical Union for astronomical epochs.\n\n## Research & Literature\n\n- Key academic sources include:\n  - Gradstein, F.M., Ogg, J.G., Schmitz, M., & Ogg, G. (2020). *The Geologic Time Scale 2020*. Elsevier. DOI: 10.1016/C2018-0-04619-6\n  - Lindegren, L., et al. (2018). \"Gaia Data Release 2: The celestial reference frame (Gaia-CRF2).\" *Astronomy & Astrophysics*, 616, A14. DOI: 10.1051/0004-6361/201832916\n  - Kern, M.L., Benson, L., Steinberg, L., & Steinberg, L. (2016). \"The EPOCH Measure of Adolescent Well-Being.\" *Psychological Assessment*, 28(5), 586–597. DOI: 10.1037/pas0000201\n- Ongoing research explores:\n  - Refinement of epoch boundaries in stratigraphy using novel isotopic and palaeontological data.\n  - Enhanced epoch referencing in astronomy for improved satellite navigation and space observation.\n  - Optimisation of epoch parameters in machine learning to improve model generalisation without overfitting.\n\n## UK Context\n\n- British contributions to epoch-related research are significant in both geological and astronomical fields, with institutions such as the University of Manchester and the University of Leeds leading in stratigraphic studies and celestial mechanics.\n- North England innovation hubs, including the Science and Technology Facilities Council (STFC) in Newcastle and Sheffield’s Advanced Manufacturing Research Centre, integrate epoch concepts in earth sciences and AI research.\n- Regional case studies include:\n  - Stratigraphic analyses of the Carboniferous and Permian epochs in the Pennines and Yorkshire Dales.\n  - Astronomical epoch applications in satellite tracking and space weather monitoring conducted by UK observatories.\n  - Machine learning epoch optimisation research in Sheffield’s AI labs, contributing to healthcare and industrial applications.\n\n## Future Directions\n\n- Emerging trends:\n  - Integration of multi-disciplinary epoch data to create more comprehensive Earth system models.\n  - Adoption of dynamic epoch referencing in astronomy to accommodate relativistic effects and improve precision.\n  - Development of adaptive epoch strategies in machine learning that adjust training cycles based on real-time performance metrics.\n- Anticipated challenges:\n  - Harmonising epoch definitions across global stratigraphic records amid regional geological variability.\n  - Maintaining standardisation in astronomical epochs as observational technologies evolve.\n  - Preventing overfitting and computational inefficiency in machine learning through better epoch management.\n- Research priorities:\n  - Cross-disciplinary collaboration to unify epoch concepts and applications.\n  - Enhancing public and academic understanding of epoch significance through education and outreach.\n  - Leveraging UK regional expertise to pioneer innovative epoch-related methodologies.\n\n## References\n\n1. Gradstein, F.M., Ogg, J.G., Schmitz, M., & Ogg, G. (2020). *The Geologic Time Scale 2020*. Elsevier. https://doi.org/10.1016/C2018-0-04619-6\n2. Lindegren, L., et al. (2018). \"Gaia Data Release 2: The celestial reference frame (Gaia-CRF2).\" *Astronomy & Astrophysics*, 616, A14. https://doi.org/10.1051/0004-6361/201832916\n3. Kern, M.L., Benson, L., Steinberg, L., & Steinberg, L. (2016). \"The EPOCH Measure of Adolescent Well-Being.\" *Psychological Assessment*, 28(5), 586–597. https://doi.org/10.1037/pas0000201\n4. International Commission on Stratigraphy. (2024). *International Chronostratigraphic Chart*. https://stratigraphy.org/chart\n5. International Astronomical Union. (2025). *Standards for Astronomical Reference Systems*. https://iau.org/public/themes/astronomy_standards/\n\n\n## Metadata\n\n- **Last Updated**: 2025-11-11\n- **Review Status**: Comprehensive editorial review\n- **Verification**: Academic sources verified\n- **Regional Context**: UK/North England where applicable",
  "properties": {
    "id": "epoch-ontology",
    "collapsed": "true",
    "- ontology": "true",
    "- term-id": "AI-0049",
    "- preferred-term": "Epoch",
    "- source-domain": "ai",
    "- status": "draft",
    "- public-access": "true"
  },
  "backlinks": [
    "Telecollaboration and Telepresence",
    "ProofOfStake"
  ],
  "wiki_links": [],
  "ontology": {
    "term_id": "AI-0049",
    "preferred_term": "Epoch",
    "definition": "",
    "source_domain": "ai",
    "maturity_level": null,
    "authority_score": null
  }
}