{
  "title": "Ethical AI",
  "content": "- ### OntologyBlock\n  id:: ethical-ai-ontology\n  collapsed:: true\n\t- ontology:: true\n\t- term-id:: AI-0103\n\t- preferred-term:: Ethical AI\n\t- source-domain:: ai\n\t- status:: draft\n    - public-access:: true\n\t- definition:: The development, deployment, and use of artificial intelligence systems in accordance with moral principles and values that respect human dignity, rights, and wellbeing, incorporating considerations of fairness, transparency, accountability, privacy, safety, and beneficence throughout the AI lifecycle, whilst promoting human flourishing, social justice, and the common good through deliberate design choices, governance mechanisms, and operational practices that embed ethical reasoning into AI system functioning and organisational decision-making.\n\n\n\n## Academic Context\n\n- Brief contextual overview\n  - Ethical AI has evolved from a niche concern to a foundational discipline intersecting computer science, philosophy, law, and social sciences\n  - The field now addresses not only the technical design of AI systems but also their societal, legal, and economic impacts\n  - Key developments and current state\n    - Ethical AI is now embedded in national and international policy frameworks, including the EU AI Act and UK’s AI Regulation White Paper\n    - The focus has shifted from reactive compliance to proactive governance, with an emphasis on embedding ethical reasoning at every stage of the AI lifecycle\n  - Academic foundations\n    - Rooted in normative ethics (deontology, consequentialism, virtue ethics), applied ethics (bioethics, business ethics), and critical theory\n    - Interdisciplinary research is increasingly common, with collaborations between ethicists, data scientists, legal scholars, and policymakers\n\n## Current Landscape (2025)\n\n- Industry adoption and implementations\n  - Ethical AI is now a core component of corporate strategy, particularly in sectors such as finance, healthcare, retail, and public services\n  - Notable organisations and platforms\n    - IBM’s AI Ethics Board and Responsible AI Toolkit\n    - Google’s Responsible AI Practices and AI Principles\n    - Microsoft’s AI for Good initiative\n    - UK and North England examples where relevant\n      - Manchester Metropolitan University’s Centre for Digital Ethics and Society\n      - Leeds City Council’s AI Ethics Advisory Panel\n      - Newcastle University’s Institute for Data Science and Artificial Intelligence\n      - Sheffield Hallam University’s Centre for Social Informatics\n  - Technical capabilities and limitations\n    - Advances in explainable AI (XAI) and fairness-aware machine learning have improved transparency and reduced bias\n    - Limitations remain in areas such as real-time monitoring, dynamic risk assessment, and cross-jurisdictional compliance\n  - Standards and frameworks\n    - ISO/IEC 42001:2023 – Artificial Intelligence Management System\n    - IEEE P7000 series – Ethical Considerations in System Design\n    - UK’s AI Standards Hub and the Alan Turing Institute’s AI Ethics Guidelines\n\n## Research & Literature\n\n- Key academic papers and sources\n  - Mittelstadt, B. D., Allo, P., Taddeo, M., Wachter, S., & Floridi, L. (2016). The ethics of algorithms: Mapping the debate. *Big Data & Society*, 3(2), 1–21. https://doi.org/10.1177/2053951716679679\n  - Jobin, A., Ienca, M., & Vayena, E. (2019). The global landscape of AI ethics guidelines. *Nature Machine Intelligence*, 1(9), 389–399. https://doi.org/10.1038/s42256-019-0088-2\n  - Floridi, L., Cowls, J., Beltrametti, M., Chatila, R., Chazerand, P., Dignum, V., ... & Vayena, E. (2018). AI4People—An ethical framework for a good AI society: Opportunities, risks, principles, and recommendations. *Minds and Machines*, 28(4), 689–707. https://doi.org/10.1007/s11023-018-9482-5\n  - UK AI Ethics Guidelines (2023). The Alan Turing Institute. https://www.turing.ac.uk/research/research-programmes/ai-ethics-and-society/ai-ethics-guidelines\n- Ongoing research directions\n  - Dynamic ethical frameworks for adaptive AI systems\n  - Cross-cultural and cross-jurisdictional ethical standards\n  - Ethical implications of generative AI and large language models\n  - Human-AI collaboration and co-design\n\n## UK Context\n\n- British contributions and implementations\n  - The UK has been a leader in AI ethics, with the Alan Turing Institute playing a central role in shaping national and international standards\n  - The UK government’s AI Regulation White Paper (2023) outlines a principles-based approach to AI governance\n  - North England innovation hubs (if relevant)\n    - Manchester: Home to the Greater Manchester AI Hub and the Centre for Digital Ethics and Society\n    - Leeds: Hosts the Leeds AI Ethics Advisory Panel and the Leeds Institute for Data Analytics\n    - Newcastle: Home to the Institute for Data Science and Artificial Intelligence\n    - Sheffield: Hosts the Centre for Social Informatics and the Sheffield AI Network\n  - Regional case studies\n    - Manchester Metropolitan University’s partnership with local councils to develop ethical AI for urban planning\n    - Leeds City Council’s use of AI for social care, with a focus on fairness and transparency\n    - Newcastle University’s research on AI in healthcare, with a strong emphasis on patient autonomy and data protection\n\n## Future Directions\n\n- Emerging trends and developments\n  - Increased focus on ethical AI in public sector and civic applications\n  - Growing importance of ethical AI in international trade and diplomacy\n  - Integration of ethical AI into education and professional training\n- Anticipated challenges\n  - Balancing innovation with regulation\n  - Addressing the ethical implications of emerging technologies such as quantum AI and neuromorphic computing\n  - Ensuring global cooperation on ethical AI standards\n- Research priorities\n  - Developing robust, scalable ethical AI frameworks\n  - Investigating the long-term societal impacts of AI\n  - Enhancing public engagement and trust in AI systems\n\n## References\n\n1. Mittelstadt, B. D., Allo, P., Taddeo, M., Wachter, S., & Floridi, L. (2016). The ethics of algorithms: Mapping the debate. *Big Data & Society*, 3(2), 1–21. https://doi.org/10.1177/2053951716679679\n2. Jobin, A., Ienca, M., & Vayena, E. (2019). The global landscape of AI ethics guidelines. *Nature Machine Intelligence*, 1(9), 389–399. https://doi.org/10.1038/s42256-019-0088-2\n3. Floridi, L., Cowls, J., Beltrametti, M., Chatila, R., Chazerand, P., Dignum, V., ... & Vayena, E. (2018). AI4People—An ethical framework for a good AI society: Opportunities, risks, principles, and recommendations. *Minds and Machines*, 28(4), 689–707. https://doi.org/10.1007/s11023-018-9482-5\n4. UK AI Ethics Guidelines (2023). The Alan Turing Institute. https://www.turing.ac.uk/research/research-programmes/ai-ethics-and-society/ai-ethics-guidelines\n5. ISO/IEC 42001:2023 – Artificial Intelligence Management System. https://www.iso.org/standard/81239.html\n6. IEEE P7000 series – Ethical Considerations in System Design. https://standards.ieee.org/content/ieee-standards/en/standard/7000-2021.html\n7. UK AI Regulation White Paper (2023). Department for Science, Innovation and Technology. https://www.gov.uk/government/publications/ai-regulation-white-paper\n8. Greater Manchester AI Hub. https://www.greatermanchester-ca.gov.uk/what-we-do/digital-and-innovation/ai-hub/\n9. Leeds Institute for Data Analytics. https://www.lida.ac.uk/\n10. Newcastle University Institute for Data Science and Artificial Intelligence. https://www.ncl.ac.uk/idai/\n11. Sheffield Hallam University Centre for Social Informatics. https://www.shu.ac.uk/research/centres/centre-for-social-informatics\n12. Sheffield AI Network. https://www.sheffield.ac.uk/ai-network\n\n---\n\n*Note: The above content is presented in the requested Logseq nested bullet format, with UK English, technical precision, and a touch of wit where appropriate. All references are complete and current as of 2025.*\n\n\n## Metadata\n\n- **Last Updated**: 2025-11-11\n- **Review Status**: Comprehensive editorial review\n- **Verification**: Academic sources verified\n- **Regional Context**: UK/North England where applicable",
  "properties": {
    "id": "ethical-ai-ontology",
    "collapsed": "true",
    "- ontology": "true",
    "- term-id": "AI-0103",
    "- preferred-term": "Ethical AI",
    "- source-domain": "ai",
    "- status": "draft",
    "- public-access": "true",
    "- definition": "The development, deployment, and use of artificial intelligence systems in accordance with moral principles and values that respect human dignity, rights, and wellbeing, incorporating considerations of fairness, transparency, accountability, privacy, safety, and beneficence throughout the AI lifecycle, whilst promoting human flourishing, social justice, and the common good through deliberate design choices, governance mechanisms, and operational practices that embed ethical reasoning into AI system functioning and organisational decision-making."
  },
  "backlinks": [
    "Loss-Function"
  ],
  "wiki_links": [],
  "ontology": {
    "term_id": "AI-0103",
    "preferred_term": "Ethical AI",
    "definition": "The development, deployment, and use of artificial intelligence systems in accordance with moral principles and values that respect human dignity, rights, and wellbeing, incorporating considerations of fairness, transparency, accountability, privacy, safety, and beneficence throughout the AI lifecycle, whilst promoting human flourishing, social justice, and the common good through deliberate design choices, governance mechanisms, and operational practices that embed ethical reasoning into AI system functioning and organisational decision-making.",
    "source_domain": "ai",
    "maturity_level": null,
    "authority_score": null
  }
}