{
  "title": "ETSI_Domain_Human_Interface___Governance",
  "content": "- ### OntologyBlock\n  id:: etsi_domain_human_interface___governance-ontology\n  collapsed:: true\n\t- ontology:: true\n\t- term-id:: mv-1761742247924\n\t- preferred-term:: ETSI_Domain_Human_Interface___Governance\n\t- source-domain:: metaverse\n\t- status:: draft\n\t- public-access:: true\n\n\n## Academic Context\n\n- The ETSI Domain Human Interface — Governance forms a critical component within the broader metaverse ecosystem, focusing on the governance aspects of human interfaces in virtual environments.\n  - It builds on foundational research in virtual worlds, augmented reality, and human-computer interaction, integrating governance frameworks to ensure ethical, interoperable, and user-centric design.\n  - Key developments include the articulation of standards and policy recommendations that address interoperability, data protection, and inclusive design within immersive digital spaces.\n  - Academic foundations draw from interdisciplinary fields such as computer science, digital ethics, and social informatics, emphasising the socio-technical challenges of virtual world governance.\n\n## Current Landscape (2025)\n\n- Industry adoption of governance frameworks for human interfaces in the metaverse is accelerating, with ETSI and other standards bodies actively developing interoperable standards.\n  - Notable organisations include ETSI’s Industry Specification Group on Augmented Reality Framework (ISG ARF), the ITU-T Focus Group on Metaverse (FG-MV), and the Metaverse Standards Forum, all contributing to governance and interoperability standards.\n  - UK and North England examples:\n    - Manchester and Leeds universities are engaged in research on ethical AI and user interface governance in virtual environments.\n    - Newcastle’s digital innovation hubs are piloting governance models for immersive experiences in public services.\n    - Sheffield’s tech clusters focus on accessibility and inclusivity standards for human interfaces in virtual worlds.\n- Technical capabilities have matured to support secure, interoperable human interfaces, but challenges remain in privacy protection, user identity governance, and cross-platform consistency.\n- Standards and frameworks currently emphasise:\n  - Ethical and inclusive design principles\n  - Data privacy and personally identifiable information (PII) protection\n  - Interoperability across devices and platforms\n  - Governance structures that balance innovation with user rights and societal impact\n\n## Research & Literature\n\n- Key academic papers and sources include:\n  - Runde, C. (2025). *ETSI Augmented Reality Framework (ARF): Virtual World Standards Recommendations Report*. ETSI. Available at Figshare. DOI: 10.6084/m9.figshare.30444941.v1\n  - ITU-T Focus Group on Metaverse (2024). *Metaverse Standards and Governance Frameworks*. International Telecommunication Union. URL: https://www.itu.int/en/ITU-T/focusgroups/mv/\n  - Metaverse Standards Forum (2025). *Towards Interoperable Anchoring for XR*. April 2025. URL: https://metaverse-standards.org/wp-content/uploads/2025-04-30-Special-SDO-Session-Towards-Interoperable-Anchoring.pdf\n- Ongoing research directions focus on:\n  - Enhancing interoperability of governance mechanisms across heterogeneous platforms\n  - Developing scalable privacy-preserving identity management\n  - Embedding ethical AI governance in human interface design\n  - Addressing regulatory challenges in cross-jurisdictional virtual environments\n\n## UK Context\n\n- The UK is a significant contributor to metaverse governance research and standardisation, with government-backed initiatives supporting ethical digital innovation.\n- North England innovation hubs:\n  - Manchester’s Digital Futures Institute leads projects on user-centric governance models for immersive technologies.\n  - Leeds Digital Hub collaborates with industry partners to pilot governance frameworks ensuring accessibility and data protection.\n  - Newcastle’s Centre for Digital Innovation explores regulatory compliance and governance in public sector metaverse applications.\n  - Sheffield’s Advanced Manufacturing Research Centre integrates human interface governance into industrial metaverse use cases.\n- Regional case studies demonstrate practical governance implementations balancing user experience with regulatory compliance, often with a dash of northern wit to keep things lively.\n\n## Future Directions\n\n- Emerging trends include:\n  - Greater emphasis on decentralised governance models leveraging blockchain and distributed ledgers\n  - Integration of AI-driven governance assistants to support real-time compliance and ethical decision-making\n  - Expansion of governance frameworks to cover emerging modalities such as brain-computer interfaces and haptic feedback systems\n- Anticipated challenges:\n  - Harmonising international governance standards with local legal frameworks, especially post-Brexit UK\n  - Ensuring inclusivity without stifling innovation or user freedom\n  - Managing the complexity of multi-stakeholder governance in rapidly evolving virtual environments\n- Research priorities:\n  - Developing robust, transparent governance mechanisms that are user-friendly and adaptable\n  - Investigating socio-technical impacts of governance decisions on diverse user populations\n  - Creating educational resources and best practices to support governance adoption across sectors\n\n## References\n\n1. Runde, C. (2025). *ETSI Augmented Reality Framework (ARF): Virtual World Standards Recommendations Report*. ETSI. Available at Figshare. DOI: 10.6084/m9.figshare.30444941.v1  \n2. ITU-T Focus Group on Metaverse (2024). *Metaverse Standards and Governance Frameworks*. International Telecommunication Union. URL: https://www.itu.int/en/ITU-T/focusgroups/mv/  \n3. Metaverse Standards Forum (2025). *Towards Interoperable Anchoring for XR*. April 2025. URL: https://metaverse-standards.org/wp-content/uploads/2025-04-30-Special-SDO-Session-Towards-Interoperable-Anchoring.pdf  \n4. ETSI Portal (2025). Work Item Reports on Virtual Worlds and Human Interface Governance. URL: https://portal.etsi.org/webapp/workprogram/Report_WorkItem.asp?WKI_ID=73721\n\n\n## Metadata\n\n- **Last Updated**: 2025-11-11\n- **Review Status**: Comprehensive editorial review\n- **Verification**: Academic sources verified\n- **Regional Context**: UK/North England where applicable",
  "properties": {
    "id": "etsi_domain_human_interface___governance-ontology",
    "collapsed": "true",
    "- ontology": "true",
    "- term-id": "mv-1761742247924",
    "- preferred-term": "ETSI_Domain_Human_Interface___Governance",
    "- source-domain": "metaverse",
    "- status": "draft",
    "- public-access": "true"
  },
  "backlinks": [],
  "wiki_links": [],
  "ontology": {
    "term_id": "mv-1761742247924",
    "preferred_term": "ETSI_Domain_Human_Interface___Governance",
    "definition": "",
    "source_domain": "metaverse",
    "maturity_level": null,
    "authority_score": null
  }
}