{
  "title": "ETSI Domain: Data Management + Ethics",
  "content": "- ### OntologyBlock\n  id:: etsi-domain-datamgmt-ethics-ontology\n  collapsed:: true\n\t- ontology:: true\n\t- term-id:: 20344\n\t- source-domain:: metaverse\n\t- status:: draft\n    - public-access:: true\n\t- preferred-term:: ETSI Domain: Data Management + Ethics\n\t- definition:: Crossover domain for ETSI metaverse categorization addressing ethical data handling, privacy-preserving storage, consent management, and responsible data governance.\n\t- maturity:: mature\n\t- source:: [[ETSI GR MEC 032]]\n\t- owl:class:: mv:ETSIDomain_DataMgmt_Ethics\n\t- owl:physicality:: VirtualEntity\n\t- owl:role:: Object\n\t- owl:inferred-class:: mv:VirtualObject\n\t- owl:functional-syntax:: true\n\t- belongsToDomain:: [[InfrastructureDomain]]\n\t- implementedInLayer:: [[ApplicationLayer]]\n\t- #### Relationships\n\t  id:: etsi-domain-datamgmt-ethics-relationships\n\t\t- is-subclass-of:: [[Metaverse]]\n\t\t- is-part-of:: [[ETSI Metaverse Domain Taxonomy]]\n\t\t- has-part:: [[Consent Management]], [[Privacy Controls]], [[Anonymization]], [[Audit Logging]]\n\t\t- requires:: [[Data Management]], [[Ethics & Law]]\n\t\t- enables:: [[Privacy-Preserving Analytics]], [[User Control]], [[Compliance Verification]]\n\t\t- depends-on:: [[GDPR]], [[Privacy Regulations]]\n\t- #### OWL Axioms\n\t  id:: etsi-domain-datamgmt-ethics-owl-axioms\n\t  collapsed:: true\n\t\t- ```clojure\n\t\t  Declaration(Class(mv:ETSIDomain_DataMgmt_Ethics))\n\n\t\t  # Classification along two primary dimensions\n\t\t  SubClassOf(mv:ETSIDomain_DataMgmt_Ethics mv:VirtualEntity)\n\t\t  SubClassOf(mv:ETSIDomain_DataMgmt_Ethics mv:Object)\n\n\t\t  # Domain classification\n\t\t  SubClassOf(mv:ETSIDomain_DataMgmt_Ethics\n\t\t    ObjectSomeValuesFrom(mv:belongsToDomain mv:InfrastructureDomain)\n\t\t  )\n\n\t\t  # Layer classification\n\t\t  SubClassOf(mv:ETSIDomain_DataMgmt_Ethics\n\t\t    ObjectSomeValuesFrom(mv:implementedInLayer mv:ApplicationLayer)\n\t\t  )\n\n\t\t  # Crossover domain dependencies\n\t\t  SubClassOf(mv:ETSIDomain_DataMgmt_Ethics\n\t\t    ObjectSomeValuesFrom(mv:requires mv:ETSIDomain_DataManagement)\n\t\t  )\n\t\t  SubClassOf(mv:ETSIDomain_DataMgmt_Ethics\n\t\t    ObjectSomeValuesFrom(mv:requires mv:ETSIDomain_EthicsLaw)\n\t\t  )\n\n\t\t  # Privacy enablement\n\t\t  SubClassOf(mv:ETSIDomain_DataMgmt_Ethics\n\t\t    ObjectSomeValuesFrom(mv:enables mv:PrivacyPreservingAnalytics)\n\t\t  )\n\n  # Property characteristics\n  TransitiveObjectProperty(dt:ispartof)\n\n  # Property characteristics\n  AsymmetricObjectProperty(dt:requires)\n\n  # Property characteristics\n  AsymmetricObjectProperty(dt:enables)\n\n  # Property characteristics\n  AsymmetricObjectProperty(dt:dependson)\n```",
  "properties": {
    "id": "etsi-domain-datamgmt-ethics-owl-axioms",
    "collapsed": "true",
    "- ontology": "true",
    "- term-id": "20344",
    "- source-domain": "metaverse",
    "- status": "draft",
    "- public-access": "true",
    "- preferred-term": "ETSI Domain: Data Management + Ethics",
    "- definition": "Crossover domain for ETSI metaverse categorization addressing ethical data handling, privacy-preserving storage, consent management, and responsible data governance.",
    "- maturity": "mature",
    "- source": "[[ETSI GR MEC 032]]",
    "- owl:class": "mv:ETSIDomain_DataMgmt_Ethics",
    "- owl:physicality": "VirtualEntity",
    "- owl:role": "Object",
    "- owl:inferred-class": "mv:VirtualObject",
    "- owl:functional-syntax": "true",
    "- belongsToDomain": "[[InfrastructureDomain]]",
    "- implementedInLayer": "[[ApplicationLayer]]",
    "- is-subclass-of": "[[Metaverse]]",
    "- is-part-of": "[[ETSI Metaverse Domain Taxonomy]]",
    "- has-part": "[[Consent Management]], [[Privacy Controls]], [[Anonymization]], [[Audit Logging]]",
    "- requires": "[[Data Management]], [[Ethics & Law]]",
    "- enables": "[[Privacy-Preserving Analytics]], [[User Control]], [[Compliance Verification]]",
    "- depends-on": "[[GDPR]], [[Privacy Regulations]]"
  },
  "backlinks": [],
  "wiki_links": [
    "Audit Logging",
    "Consent Management",
    "ETSI GR MEC 032",
    "ETSI Metaverse Domain Taxonomy",
    "User Control",
    "ApplicationLayer",
    "Metaverse",
    "Anonymization",
    "GDPR",
    "Privacy Regulations",
    "Privacy Controls",
    "Ethics & Law",
    "Privacy-Preserving Analytics",
    "InfrastructureDomain",
    "Compliance Verification",
    "Data Management"
  ],
  "ontology": {
    "term_id": "20344",
    "preferred_term": "ETSI Domain: Data Management + Ethics",
    "definition": "Crossover domain for ETSI metaverse categorization addressing ethical data handling, privacy-preserving storage, consent management, and responsible data governance.",
    "source_domain": "metaverse",
    "maturity_level": null,
    "authority_score": null
  }
}