{
  "title": "ETSI_Domain_Governance_Security",
  "content": "- ### OntologyBlock\n  id:: etsi_domain_governance_security-ontology\n  collapsed:: true\n\t- ontology:: true\n\t- term-id:: MV-0014\n\t- preferred-term:: ETSI_Domain_Governance_Security\n\t- source-domain:: metaverse\n\t- status:: draft\n    - public-access:: true\n\t- definition:: A component of the metaverse ecosystem.\n\t- maturity:: draft\n\t- owl:class:: mv:ETSI_Domain_Governance_Security\n\t- owl:physicality:: ConceptualEntity\n\t- owl:role:: Concept\n\t- is-subclass-of:: [[Metaverse]]\n\t- belongsToDomain:: [[MetaverseDomain]]\n\n## OWL Formal Semantics\n\n```clojure\n;; OWL Functional Syntax\n\n(Declaration (Class :Etsidomaingovernancesecurity))\n\n;; Annotations\n(AnnotationAssertion rdfs:label :Etsidomaingovernancesecurity \"ETSI_Domain_Governance_Security\"@en)\n(AnnotationAssertion rdfs:comment :Etsidomaingovernancesecurity \"A component of the metaverse ecosystem.\"@en)\n\n;; Data Properties\n(AnnotationAssertion dcterms:identifier :Etsidomaingovernancesecurity \"mv-1761742247919\"^^xsd:string)\n```",
  "properties": {
    "id": "etsi_domain_governance_security-ontology",
    "collapsed": "true",
    "- ontology": "true",
    "- term-id": "MV-0014",
    "- preferred-term": "ETSI_Domain_Governance_Security",
    "- source-domain": "metaverse",
    "- status": "draft",
    "- public-access": "true",
    "- definition": "A component of the metaverse ecosystem.",
    "- maturity": "draft",
    "- owl:class": "mv:ETSI_Domain_Governance_Security",
    "- owl:physicality": "ConceptualEntity",
    "- owl:role": "Concept",
    "- is-subclass-of": "[[Metaverse]]",
    "- belongsToDomain": "[[MetaverseDomain]]"
  },
  "backlinks": [],
  "wiki_links": [
    "Metaverse",
    "MetaverseDomain"
  ],
  "ontology": {
    "term_id": "MV-0014",
    "preferred_term": "ETSI_Domain_Governance_Security",
    "definition": "A component of the metaverse ecosystem.",
    "source_domain": "metaverse",
    "maturity_level": null,
    "authority_score": null
  }
}