{
  "title": "ETSI Domain AI",
  "content": "- ### OntologyBlock\n  id:: etsi-domain-ai-ontology\n  collapsed:: true\n\t- ontology:: true\n\t- term-id:: 20330\n\t- source-domain:: metaverse\n\t- status:: draft\n    - public-access:: true\n\t- preferred-term:: ETSI Domain AI\n\t- definition:: Domain marker concept for categorizing metaverse components related to artificial intelligence, machine learning, and computational intelligence capabilities.\n\t- maturity:: mature\n\t- source:: [[ETSI GS MEC]]\n\t- owl:class:: mv:ETSIDomainAI\n\t- owl:physicality:: VirtualEntity\n\t- owl:role:: Object\n\t- owl:inferred-class:: mv:VirtualObject\n\t- owl:functional-syntax:: true\n\t- belongsToDomain:: [[ComputationAndIntelligenceDomain]]\n\t- implementedInLayer:: [[ApplicationLayer]]\n\t- #### Relationships\n\t  id:: etsi-domain-ai-relationships\n\t\t- is-subclass-of:: [[ArtificialIntelligence]]\n\t\t- is-dependency-of:: [[ETSI_Domain_AI___Governance]], [[ETSI_Domain_AI___Data_Mgmt]], [[ETSI_Domain_AI___Human_Interface]], [[ETSI_Domain_AI___Creative_Media]]\n\t\t- is-part-of:: [[ETSI Domain Taxonomy]]\n\t\t- enables:: [[AI Service Classification]], [[Intelligence Layer Categorization]]\n\t\t- depends-on:: [[ComputationAndIntelligenceDomain]]\n\t\t- has-part:: [[ETSI Domain AI Creative Media]], [[ETSI Domain AI Data Mgmt]], [[ETSI Domain AI Governance]], [[ETSI Domain AI Human Interface]]\n\t- #### OWL Axioms\n\t  id:: etsi-domain-ai-owl-axioms\n\t  collapsed:: true\n\t\t- ```clojure\n\t\t  Declaration(Class(mv:ETSIDomainAI))\n\n\t\t  # Classification along two primary dimensions\n\t\t  SubClassOf(mv:ETSIDomainAI mv:VirtualEntity)\n\t\t  SubClassOf(mv:ETSIDomainAI mv:Object)\n\n\t\t  # Domain marker classification\n\t\t  SubClassOf(mv:ETSIDomainAI mv:DomainMarker)\n\t\t  SubClassOf(mv:ETSIDomainAI mv:TaxonomyNode)\n\n\t\t  # Domain classification\n\t\t  SubClassOf(mv:ETSIDomainAI\n\t\t    ObjectSomeValuesFrom(mv:belongsToDomain mv:ComputationAndIntelligenceDomain)\n\t\t  )\n\n\t\t  # Layer classification\n\t\t  SubClassOf(mv:ETSIDomainAI\n\t\t    ObjectSomeValuesFrom(mv:implementedInLayer mv:ApplicationLayer)\n\t\t  )\n\n\t\t  # Taxonomy relationships\n\t\t  SubClassOf(mv:ETSIDomainAI\n\t\t    ObjectSomeValuesFrom(mv:categorizes mv:AIComponent)\n\t\t  )\n\n  # Property characteristics\n  AsymmetricObjectProperty(dt:isdependencyof)\n\n  # Property characteristics\n  TransitiveObjectProperty(dt:ispartof)\n\n  # Property characteristics\n  AsymmetricObjectProperty(dt:enables)\n\n  # Property characteristics\n  AsymmetricObjectProperty(dt:dependson)\n```",
  "properties": {
    "id": "etsi-domain-ai-owl-axioms",
    "collapsed": "true",
    "- ontology": "true",
    "- term-id": "20330",
    "- source-domain": "metaverse",
    "- status": "draft",
    "- public-access": "true",
    "- preferred-term": "ETSI Domain AI",
    "- definition": "Domain marker concept for categorizing metaverse components related to artificial intelligence, machine learning, and computational intelligence capabilities.",
    "- maturity": "mature",
    "- source": "[[ETSI GS MEC]]",
    "- owl:class": "mv:ETSIDomainAI",
    "- owl:physicality": "VirtualEntity",
    "- owl:role": "Object",
    "- owl:inferred-class": "mv:VirtualObject",
    "- owl:functional-syntax": "true",
    "- belongsToDomain": "[[ComputationAndIntelligenceDomain]]",
    "- implementedInLayer": "[[ApplicationLayer]]",
    "- is-subclass-of": "[[ArtificialIntelligence]]",
    "- is-dependency-of": "[[ETSI_Domain_AI___Governance]], [[ETSI_Domain_AI___Data_Mgmt]], [[ETSI_Domain_AI___Human_Interface]], [[ETSI_Domain_AI___Creative_Media]]",
    "- is-part-of": "[[ETSI Domain Taxonomy]]",
    "- enables": "[[AI Service Classification]], [[Intelligence Layer Categorization]]",
    "- depends-on": "[[ComputationAndIntelligenceDomain]]",
    "- has-part": "[[ETSI Domain AI Creative Media]], [[ETSI Domain AI Data Mgmt]], [[ETSI Domain AI Governance]], [[ETSI Domain AI Human Interface]]"
  },
  "backlinks": [
    "ETSI_Domain_AI___Governance",
    "ETSI_Domain_AI___Data_Mgmt"
  ],
  "wiki_links": [
    "Intelligence Layer Categorization",
    "ArtificialIntelligence",
    "ComputationAndIntelligenceDomain",
    "ETSI_Domain_AI___Data_Mgmt",
    "ETSI Domain AI Human Interface",
    "AI Service Classification",
    "ETSI Domain AI Creative Media",
    "ETSI_Domain_AI___Human_Interface",
    "ETSI Domain AI Governance",
    "ETSI_Domain_AI___Creative_Media",
    "ETSI Domain Taxonomy",
    "ETSI_Domain_AI___Governance",
    "ETSI GS MEC",
    "ETSI Domain AI Data Mgmt",
    "ApplicationLayer"
  ],
  "ontology": {
    "term_id": "20330",
    "preferred_term": "ETSI Domain AI",
    "definition": "Domain marker concept for categorizing metaverse components related to artificial intelligence, machine learning, and computational intelligence capabilities.",
    "source_domain": "metaverse",
    "maturity_level": null,
    "authority_score": null
  }
}