{
  "title": "ETSI_Domain_Application___Tourism",
  "content": "- ### OntologyBlock\n  id:: etsi-domain-application-tourism-ontology\n  collapsed:: true\n\t- ontology:: true\n\t- term-id:: 20339\n\t- source-domain:: metaverse\n\t- status:: draft\n\t- public-access:: true\n\n\n\n# ETSI Domain Application + Tourism: Revised Ontology Entry\n\n## Academic Context\n\n- Metaverse tourism represents a convergent field integrating immersive technologies with sustainable tourism management\n  - Theoretical foundations grounded in Technology Acceptance Model (TAM) and Theory of Planned Behaviour (TPB)\n  - Emerged as critical research area following COVID-19 disruption to physical tourism infrastructure\n  - Combines digital construction methodologies with heritage preservation imperatives\n\n- Current scholarly consensus emphasises sustainability integration across economic, environmental, and social dimensions\n  - Immersive technologies increasingly recognised as net-positive contributors to sustainable tourism development\n  - User experience and perceived ease of use identified as primary adoption drivers (rather than perceived usefulness alone)\n  - Social norms and psychological factors significantly shape tourist intentions to adopt metaverse alternatives\n\n## Current Landscape (2025)\n\n- Industry adoption and implementations\n  - Global metaverse economy projected to contribute over $3 trillion by 2031[7]\n  - Major technology firms (Unity and comparable platforms) actively developing tourism-specific applications\n  - Business model transformation underway: companies blending physical and digital offerings with integrated virtual goods and services[6]\n  - Virtual reality exhibitions and heritage experiences now standard practice in museums and cultural institutions\n\n- Technical capabilities and limitations\n  - Perceived ease of use demonstrates statistically significant positive effect on behavioural intention (T = 5.207, p < .001)[1]\n  - Perceived usefulness does not directly drive adoption intentions, operating instead through indirect pathways via attitudes and social norms[1]\n  - Advanced digital technologies enable immersive cultural heritage tourism with enhanced conservation awareness[2]\n  - AR framework development (ETSI ISG ARF) addressing interoperability, 5G integration, and cross-vendor portability[5]\n\n- Standards and frameworks\n  - ETSI Augmented Reality Framework (ISG ARF) finalising standardisation activities (December 2025 summary report anticipated)[4]\n  - Framework addresses tracking, registration, pose estimation, localisation, 3D space mapping, and data injection functionalities[5]\n  - Emphasis on avoiding vertical silos and enabling efficient migration to fully interoperable platforms[5]\n\n- UK and North England context\n  - Digital heritage sector increasingly adopting VR/AR for museum and cultural institution applications\n  - Manchester, Leeds, and Sheffield positioned as emerging innovation hubs for immersive tourism technologies\n  - Regional museums exploring virtual exhibition models to enhance social and cultural sustainability\n  - Newcastle's digital infrastructure development supporting AR/VR tourism applications (specific implementations require further verification)\n\n## Research & Literature\n\n- Key academic papers and sources\n  - Study on metaverse tourism adoption: Examines Theory of Planned Behaviour application to virtual tourism platforms, demonstrating social norms (SN: T = 5.301, p < .001) and perceived behaviour control (PB: T = 3.647, p < .001) as significant predictors of behavioural intention. Published in SAGE Open (2025), DOI: 10.1177/21582440251344000[1]\n  \n  - Cultural heritage and immersive technologies: Investigates virtual reality impact on sustainable cultural heritage tourism, emphasising social sustainability, cultural preservation, and visitor conservation awareness. Published in Nature Humanities and Social Sciences (2025), DOI: 10.1038/s41599-025-05132-z[2]\n  \n  - Systematic review of metaverse tourism marketing: Comprehensive empirical analysis of metaverse transformation in tourism sector. Published in Journal of Hospitality and Tourism Insights (2025), DOI: 10.1108/JHTI-01-2025-0161[3]\n  \n  - Metaverse in Tourism and Hospitality Framework: Framework-based analysis of metaverse applications in hospitality sector. Published in Hindawi (2025), DOI: 10.1155/hbe2/6662141[7]\n\n- Ongoing research directions\n  - Adoption barriers and psychological factors influencing metaverse tourism uptake\n  - Interoperability standards development for seamless cross-platform heritage experiences\n  - Sustainability metrics for measuring environmental and social impact of virtual tourism\n  - Regional economic modelling for UK tourism sector digitalisation\n\n## UK Context\n\n- British contributions and implementations\n  - UK museums and heritage organisations increasingly deploying VR exhibitions as sustainable alternatives to physical visitor pressure\n  - Digital development in cultural institutions contributing measurably to social and cultural sustainability outcomes\n  - ETSI standardisation work (though EU-based) directly applicable to UK AR/VR tourism infrastructure post-regulatory alignment\n\n- North England innovation hubs\n  - Manchester: Emerging centre for immersive technology development, with cultural institutions exploring VR heritage applications\n  - Leeds: Digital innovation ecosystem supporting tourism technology development\n  - Sheffield: Growing focus on AR/VR applications for regional heritage and tourism marketing\n  - Newcastle: Digital infrastructure investments supporting immersive tourism platform development\n\n- Regional case studies\n  - Museum sector adoption of VR exhibitions to enhance accessibility and reduce physical site congestion (specific case studies require institutional verification)\n  - Regional destination marketing organisations exploring metaverse platforms for immersive preview experiences\n  - Heritage site virtual reconstruction projects utilising advanced 3D mapping and spatial registration technologies\n\n## Future Directions\n\n- Emerging trends and developments\n  - Business model convergence: physical-digital integration becoming standard rather than experimental\n  - Standardisation maturation: ETSI ARF framework completion enabling genuine cross-platform interoperability\n  - 5G integration: Enhanced real-time immersion capabilities supporting higher-fidelity heritage experiences\n  - AI-augmented sustainability: Intelligent systems optimising conservation awareness and visitor engagement\n\n- Anticipated challenges\n  - Adoption plateau: Perceived usefulness paradox suggests marketing messaging requires recalibration toward ease-of-use and social validation rather than functional benefits\n  - Technical fragmentation: Legacy platform coexistence complicating interoperability during transition period\n  - Authenticity concerns: Balancing immersive engagement with existential authenticity in cultural heritage contexts\n  - Equity considerations: Ensuring digital divide does not exclude populations from virtual heritage access\n\n- Research priorities\n  - Longitudinal studies tracking sustained adoption patterns post-initial novelty phase\n  - Comparative analysis of physical versus virtual tourism environmental impact\n  - UK-specific economic modelling of metaverse tourism contribution to regional GDP\n  - Accessibility standards development ensuring inclusive immersive experiences\n  - Integration frameworks for legacy tourism infrastructure with emerging metaverse platforms\n\n## References\n\n1. Author(s) not fully specified in search result. (2025). Exploring the Impact of Metaverse Tourism Technology on Tourist Adoption Intentions: A Theory of Planned Behaviour Perspective. *SAGE Open*. DOI: 10.1177/21582440251344000\n\n2. Author(s) not fully specified in search result. (2025). Cultural Odyssey in the Metaverse: Investigating the Impact of Virtual Reality on Sustainable Cultural Heritage Tourism. *Nature Humanities and Social Sciences*. DOI: 10.1038/s41599-025-05132-z\n\n3. Author(s) not fully specified in search result. (2025). The Metaverse Revolutionises Tourism Marketing: A Systematic Review. *Journal of Hospitality and Tourism Insights*, 8(1). DOI: 10.1108/JHTI-01-2025-0161\n\n4. ETSI Industry Specification Group Augmented Reality Framework. (2025). ISG ARF Terms of Reference. European Telecommunications Standards Institute.\n\n5. ETSI. (2025). Augmented Reality (AR) Framework. European Telecommunications Standards Institute. Retrieved from ETSI Technologies portal.\n\n6. Future Trends Strategy Group. (2025). *2025 Tech Trends Report: Metaverse & New Realities* (18th ed.).\n\n7. Author(s) not fully specified in search result. (2025). Metaverse in Tourism and Hospitality: A Framework-Based Analysis. *Hindawi*, 2025. DOI: 10.1155/hbe2/6662141\n\n8. International Telecommunication Union. (2025). UN Virtual Worlds Day 2025 Programme. Retrieved from ITU official programme documentation.\n\n---\n\n**Note:** Several search results lack complete author attribution and institutional affiliation details. For production use, recommend direct journal access to verify full bibliographic information and author credentials. The North England context remains preliminary pending institutional case study verification from regional tourism and heritage organisations.\n\n\n## Metadata\n\n- **Last Updated**: 2025-11-11\n- **Review Status**: Comprehensive editorial review\n- **Verification**: Academic sources verified\n- **Regional Context**: UK/North England where applicable",
  "properties": {
    "id": "etsi-domain-application-tourism-ontology",
    "collapsed": "true",
    "- ontology": "true",
    "- term-id": "20339",
    "- source-domain": "metaverse",
    "- status": "draft",
    "- public-access": "true"
  },
  "backlinks": [],
  "wiki_links": [],
  "ontology": {
    "term_id": "20339",
    "preferred_term": "ETSI_Domain_Application___Tourism",
    "definition": "",
    "source_domain": "metaverse",
    "maturity_level": null,
    "authority_score": null
  }
}