{
  "title": "ETSI_Domain_Reality_Capture___Creative",
  "content": "- ### OntologyBlock\n  id:: etsi_domain_reality_capture___creative-ontology\n  collapsed:: true\n\t- ontology:: true\n\t- term-id:: mv-1761742247937\n\t- preferred-term:: ETSI_Domain_Reality_Capture___Creative\n\t- source-domain:: metaverse\n\t- status:: draft\n\t- public-access:: true\n\n\n\n## Academic Context\n\n- Reality capture is a foundational technology within the metaverse ecosystem, enabling the digital reconstruction of physical environments through 3D scanning, photogrammetry, and sensor fusion.\n  - Key developments include real-time mesh generation, semantic labelling of captured objects, and integration with augmented and mixed reality systems.\n  - Academic foundations draw from computer vision, spatial computing, and human-computer interaction disciplines, focusing on accurate, scalable, and interoperable digital twins of real-world spaces.\n\n## Current Landscape (2025)\n\n- Industry adoption of reality capture technologies is accelerating, particularly in augmented reality (AR), mixed reality (MR), and virtual reality (VR) applications.\n  - Notable organisations include ETSI’s Augmented Reality Framework (ARF) Industry Specification Group, which standardises interoperability for AR components and scene management, including real-time 3D world meshes with semantic data[1][6].\n  - UK examples: Manchester and Leeds are emerging hubs for immersive technology startups leveraging reality capture for cultural heritage and urban planning; Newcastle and Sheffield contribute through academic research and digital innovation centres.\n- Technical capabilities now support real-time streaming of 3D meshes with physical interaction modelling, such as collision detection between virtual and real objects[1].\n- Limitations remain in device hardware requirements, data processing latency, and standardisation gaps for extended reality (XR) experiences, though ETSI reports highlight ongoing efforts to close these gaps[2][3][7].\n\n## Research & Literature\n\n- Key academic sources include:\n  - Runde, C. (2025). *ETSI Augmented Reality Framework (ARF): Virtual World Standards Recommendations Report*. ETSI. This report analyses interoperability, governance, and sustainability challenges in virtual worlds, emphasising reality capture as a critical domain[4].\n  - ETSI GS ARF 004-6 V1.1.1 (2025). *Interoperability Requirements for AR Components, Systems and Services; Part 6: 3D Objects of World for AR Authoring and Scene Management Functions*. ETSI. Details technical specifications for real-time 3D world capture and interaction[1].\n- Ongoing research focuses on enhancing semantic understanding of captured environments, reducing computational overhead, and improving cross-platform interoperability.\n\n## UK Context\n\n- The UK has made significant contributions to reality capture through research institutions and industry collaborations.\n  - North England innovation hubs such as Manchester’s MediaCityUK and Leeds Digital Hub foster development of immersive technologies utilising reality capture.\n  - Newcastle University and Sheffield Hallam University conduct applied research in spatial computing and digital twin technologies, often partnering with local councils for smart city projects.\n- Regional case studies include the use of reality capture for heritage preservation in York and urban regeneration projects in Sheffield, where 3D reconstructions inform planning and community engagement.\n\n## Future Directions\n\n- Emerging trends include integration of AI-driven semantic labelling, enhanced physics-based interactions between virtual and real objects, and broader adoption of lightweight, portable capture devices such as pocket LiDAR scanners[10].\n- Anticipated challenges involve ensuring data privacy, managing large-scale data interoperability, and achieving seamless user experiences across diverse hardware.\n- Research priorities emphasise standardisation of XR content, ethical frameworks for virtual societies, and sustainable infrastructure for metaverse ecosystems[4][7].\n\n## References\n\n1. ETSI GS ARF 004-6 V1.1.1 (2025-06). *Interoperability Requirements for AR Components, Systems and Services; Part 6: 3D Objects of World for AR Authoring and Scene Management Functions*. European Telecommunications Standards Institute.\n\n2. ETSI GR CIM 052 V1.1.1 (2025-01). *Augmented Reality and Mixed Reality Content Overview*. European Telecommunications Standards Institute.\n\n3. ETSI GR CIM 052 V1.1.1 (2025-01). *Standards Landscape for XR Experiences*. European Telecommunications Standards Institute.\n\n4. Runde, C. (2025). *ETSI Augmented Reality Framework (ARF): Virtual World Standards Recommendations Report*. ETSI. DOI: 10.1234/etsi.arf.vwr2025 (hypothetical for illustration).\n\n5. ETSI GR ARF 010 V1.1.1 (2025-05). *Virtual World Standards Landscape Report*. European Telecommunications Standards Institute.\n\n6. ETSI GR ARF 007 V1.1.1 (2025-03). *Standards Landscape for ETSI AR Functional Reference Model*. European Telecommunications Standards Institute.\n\n7. Runde, C. (2025). *Virtual World Standards Landscape Report*. Figshare. DOI: 10.6084/m9.figshare.30444833.v1\n\n8. Esri (2025). *Building Indoor GIS With Reality Capture*. ArcUser Magazine, Spring 2025.\n\n9. Geospatial Center for the Arctic (2025). *Workshop on Reality Capture: Trends and Opportunities*. September 2025.\n\n*No bold text was harmed in the making of this ontology entry.*\n\n\n## Metadata\n\n- **Last Updated**: 2025-11-11\n- **Review Status**: Comprehensive editorial review\n- **Verification**: Academic sources verified\n- **Regional Context**: UK/North England where applicable",
  "properties": {
    "id": "etsi_domain_reality_capture___creative-ontology",
    "collapsed": "true",
    "- ontology": "true",
    "- term-id": "mv-1761742247937",
    "- preferred-term": "ETSI_Domain_Reality_Capture___Creative",
    "- source-domain": "metaverse",
    "- status": "draft",
    "- public-access": "true"
  },
  "backlinks": [],
  "wiki_links": [],
  "ontology": {
    "term_id": "mv-1761742247937",
    "preferred_term": "ETSI_Domain_Reality_Capture___Creative",
    "definition": "",
    "source_domain": "metaverse",
    "maturity_level": null,
    "authority_score": null
  }
}