{
  "title": "ETSI_Domain_Human_Interface",
  "content": "- ### OntologyBlock\n  id:: etsi_domain_human_interface-ontology\n  collapsed:: true\n\t- ontology:: true\n\t- term-id:: MV-0017\n\t- preferred-term:: ETSI_Domain_Human_Interface\n\t- source-domain:: metaverse\n\t- status:: draft\n    - public-access:: true\n\t- definition:: A component of the metaverse ecosystem.\n\t- maturity:: draft\n\t- owl:class:: mv:ETSI_Domain_Human_Interface\n\t- owl:physicality:: ConceptualEntity\n\t- owl:role:: Concept\n\t- belongsToDomain:: [[MetaverseDomain]]\n\n## OWL Formal Semantics\n\n```clojure\n;; OWL Functional Syntax\n\n(Declaration (Class :Etsidomainhumaninterface))\n\n;; Annotations\n(AnnotationAssertion rdfs:label :Etsidomainhumaninterface \"ETSI_Domain_Human_Interface\"@en)\n(AnnotationAssertion rdfs:comment :Etsidomainhumaninterface \"A component of the metaverse ecosystem.\"@en)\n\n;; Data Properties\n(AnnotationAssertion dcterms:identifier :Etsidomainhumaninterface \"mv-1761742247920\"^^xsd:string)\n```",
  "properties": {
    "id": "etsi_domain_human_interface-ontology",
    "collapsed": "true",
    "- ontology": "true",
    "- term-id": "MV-0017",
    "- preferred-term": "ETSI_Domain_Human_Interface",
    "- source-domain": "metaverse",
    "- status": "draft",
    "- public-access": "true",
    "- definition": "A component of the metaverse ecosystem.",
    "- maturity": "draft",
    "- owl:class": "mv:ETSI_Domain_Human_Interface",
    "- owl:physicality": "ConceptualEntity",
    "- owl:role": "Concept",
    "- belongsToDomain": "[[MetaverseDomain]]"
  },
  "backlinks": [],
  "wiki_links": [
    "MetaverseDomain"
  ],
  "ontology": {
    "term_id": "MV-0017",
    "preferred_term": "ETSI_Domain_Human_Interface",
    "definition": "A component of the metaverse ecosystem.",
    "source_domain": "metaverse",
    "maturity_level": null,
    "authority_score": null
  }
}