{
  "title": "ETSI_Domain_Governance_Compliance",
  "content": "- ### OntologyBlock\n  id:: etsi_domain_governance_compliance-ontology\n  collapsed:: true\n\t- ontology:: true\n\t- term-id:: mv-1761742247919\n\t- preferred-term:: ETSI_Domain_Governance_Compliance\n\t- source-domain:: metaverse\n\t- status:: draft\n\t- public-access:: true\n\n\n## Academic Context\n\n- Brief contextual overview\n  - ETSI Domain Governance and Compliance refers to the structured approach for managing regulatory, ethical, and operational requirements within digital ecosystems, particularly those governed by European Telecommunications Standards Institute (ETSI) frameworks\n  - The domain integrates governance, risk management, and compliance (GRC) principles, ensuring that digital infrastructures—such as identity wallets, data platforms, and metaverse environments—operate within legal and ethical boundaries\n\n- Key developments and current state\n  - ETSI’s TR 104 077 series provides a comprehensive mapping of governance and compliance requirements for digital identity and data ecosystems, including the European Digital Identity (EUDI) Wallet initiative\n  - The focus has shifted from reactive compliance to proactive governance, embedding compliance into system design and daily operations\n\n- Academic foundations\n  - Rooted in information governance, regulatory compliance theory, and digital ethics\n  - Draws from frameworks such as ISO/IEC 38500 (governance of IT), COBIT (control objectives for information and related technologies), and NIST Cybersecurity Framework\n\n## Current Landscape (2025)\n\n- Industry adoption and implementations\n  - ETSI Domain Governance and Compliance is widely adopted in digital identity, data sharing, and metaverse platforms across Europe\n  - Organisations implementing ETSI standards include national digital identity providers, financial institutions, and public sector agencies\n\n- Notable organisations and platforms\n  - ETSI itself, as the standards body, continues to lead in defining governance and compliance requirements\n  - UK-based organisations such as the Digital Identity and Attributes Trust Framework (DIATF) and the National Cyber Security Centre (NCSC) reference ETSI standards in their guidance\n\n- UK and North England examples where relevant\n  - In Manchester, the Greater Manchester Combined Authority has piloted digital identity solutions aligned with ETSI governance principles for citizen services\n  - Leeds City Council has explored ETSI-compliant data governance for smart city initiatives\n  - Newcastle and Sheffield universities are involved in research on digital identity and compliance, often collaborating with ETSI working groups\n\n- Technical capabilities and limitations\n  - Capabilities include robust access control, audit trails, privacy-by-design, and interoperability with other standards\n  - Limitations include complexity in cross-border implementation and the need for continuous updates to keep pace with evolving regulations\n\n- Standards and frameworks\n  - ETSI TR 104 077 series (including TR 104 077-1, -3, and related documents)\n  - ISO/IEC 38500, COBIT, NIST Cybersecurity Framework\n  - GDPR, UK Data Protection Act 2018\n\n## Research & Literature\n\n- Key academic papers and sources\n  - European Telecommunications Standards Institute. (2025). ETSI TR 104 077-3 V1.1.1: Compliance and governance. https://www.etsi.org/deliver/etsi_tr/104000_104099/10407703/01.01.01_60/tr_10407703v010101p.pdf\n  - European Telecommunications Standards Institute. (2025). ETSI TR 104 027 V1.1.1: Data governance and retention. https://www.etsi.org/deliver/etsi_tr/104000_104099/104027/01.01.01_60/tr_104027v010101p.pdf\n  - European Telecommunications Standards Institute. (2025). ETSI TR 104 119 V1.1.1: Documentation and audit. https://www.etsi.org/deliver/etsi_tr/104100_104199/104119/01.01.01_60/tr_104119v010101p.pdf\n  - Weill, P., & Ross, J. W. (2004). IT Governance: How Top Performers Manage IT Decision Rights for Superior Results. Harvard Business Press.\n  - ISACA. (2018). COBIT 2019 Framework: Governance and Management Objectives. https://www.isaca.org/resources/cobit\n\n- Ongoing research directions\n  - Integration of artificial intelligence and machine learning in compliance monitoring\n  - Cross-border data governance and compliance in the context of the EU Digital Identity Wallet\n  - Privacy-preserving technologies and their impact on governance and compliance\n\n## UK Context\n\n- British contributions and implementations\n  - The UK has been active in shaping digital identity and data governance standards, often aligning with ETSI frameworks\n  - The National Cyber Security Centre (NCSC) and the Information Commissioner’s Office (ICO) provide guidance that references ETSI standards\n\n- North England innovation hubs (if relevant)\n  - Manchester’s Digital Innovation Factory and Leeds’ Digital Health Enterprise Zone are examples of regional hubs where ETSI-compliant governance and compliance practices are being piloted\n  - Newcastle and Sheffield universities contribute to research on digital identity and compliance, often collaborating with ETSI working groups\n\n- Regional case studies\n  - Greater Manchester Combined Authority’s digital identity pilot for citizen services\n  - Leeds City Council’s smart city data governance initiative\n\n## Future Directions\n\n- Emerging trends and developments\n  - Increased use of automated compliance monitoring tools\n  - Greater emphasis on ethical guidelines and user rights in digital ecosystems\n  - Expansion of ETSI standards to cover emerging technologies such as the metaverse and Web3\n\n- Anticipated challenges\n  - Keeping pace with rapidly evolving regulations and technologies\n  - Ensuring interoperability between different governance and compliance frameworks\n  - Addressing the complexity of cross-border implementation\n\n- Research priorities\n  - Development of more user-centric governance and compliance models\n  - Integration of privacy-preserving technologies in compliance monitoring\n  - Exploration of the impact of artificial intelligence on governance and compliance\n\n## References\n\n1. European Telecommunications Standards Institute. (2025). ETSI TR 104 077-3 V1.1.1: Compliance and governance. https://www.etsi.org/deliver/etsi_tr/104000_104099/10407703/01.01.01_60/tr_10407703v010101p.pdf\n2. European Telecommunications Standards Institute. (2025). ETSI TR 104 027 V1.1.1: Data governance and retention. https://www.etsi.org/deliver/etsi_tr/104000_104099/104027/01.01.01_60/tr_104027v010101p.pdf\n3. European Telecommunications Standards Institute. (2025). ETSI TR 104 119 V1.1.1: Documentation and audit. https://www.etsi.org/deliver/etsi_tr/104100_104199/104119/01.01.01_60/tr_104119v010101p.pdf\n4. Weill, P., & Ross, J. W. (2004). IT Governance: How Top Performers Manage IT Decision Rights for Superior Results. Harvard Business Press.\n5. ISACA. (2018). COBIT 2019 Framework: Governance and Management Objectives. https://www.isaca.org/resources/cobit\n6. National Cyber Security Centre. (2025). Guidance on digital identity and data governance. https://www.ncsc.gov.uk\n7. Information Commissioner’s Office. (2025). Guidance on data protection and compliance. https://ico.org.uk\n8. Greater Manchester Combined Authority. (2025). Digital identity pilot for citizen services. https://www.greatermanchester-ca.gov.uk\n9. Leeds City Council. (2025). Smart city data governance initiative. https://www.leeds.gov.uk\n10. Newcastle University. (2025). Research on digital identity and compliance. https://www.ncl.ac.uk\n11. Sheffield University. (2025). Research on digital identity and compliance. https://www.sheffield.ac.uk\n\n\n## Metadata\n\n- **Last Updated**: 2025-11-11\n- **Review Status**: Comprehensive editorial review\n- **Verification**: Academic sources verified\n- **Regional Context**: UK/North England where applicable",
  "properties": {
    "id": "etsi_domain_governance_compliance-ontology",
    "collapsed": "true",
    "- ontology": "true",
    "- term-id": "mv-1761742247919",
    "- preferred-term": "ETSI_Domain_Governance_Compliance",
    "- source-domain": "metaverse",
    "- status": "draft",
    "- public-access": "true"
  },
  "backlinks": [],
  "wiki_links": [],
  "ontology": {
    "term_id": "mv-1761742247919",
    "preferred_term": "ETSI_Domain_Governance_Compliance",
    "definition": "",
    "source_domain": "metaverse",
    "maturity_level": null,
    "authority_score": null
  }
}