{
  "title": "ETSI Domain: Governance & Ethics",
  "content": "- ### OntologyBlock\n  id:: etsi-domain-governance-ethics-ontology\n  collapsed:: true\n\t- ontology:: true\n\t- term-id:: 20349\n\t- source-domain:: metaverse\n\t- status:: draft\n    - public-access:: true\n\t- preferred-term:: ETSI Domain: Governance & Ethics\n\t- definition:: Crossover domain for ETSI metaverse categorization addressing ethical governance frameworks, responsible decision-making processes, and value-aligned organizational structures.\n\t- maturity:: mature\n\t- source:: [[ETSI GR MEC 032]]\n\t- owl:class:: mv:ETSIDomain_Governance_Ethics\n\t- owl:physicality:: VirtualEntity\n\t- owl:role:: Object\n\t- owl:inferred-class:: mv:VirtualObject\n\t- owl:functional-syntax:: true\n\t- belongsToDomain:: [[InfrastructureDomain]]\n\t- implementedInLayer:: [[ApplicationLayer]]\n\t- #### Relationships\n\t  id:: etsi-domain-governance-ethics-relationships\n\t\t- is-subclass-of:: [[Metaverse]]\n\t\t- is-part-of:: [[ETSI Metaverse Domain Taxonomy]]\n\t\t- has-part:: [[Ethics Committee]], [[Governance Board]], [[Value Framework]], [[Stakeholder Engagement]]\n\t\t- requires:: [[Governance]], [[Ethics & Law]]\n\t\t- enables:: [[Ethical Decision-Making]], [[Stakeholder Accountability]], [[Value Alignment]]\n\t\t- depends-on:: [[Ethical Principles]], [[Governance Models]]\n\t- #### OWL Axioms\n\t  id:: etsi-domain-governance-ethics-owl-axioms\n\t  collapsed:: true\n\t\t- ```clojure\n\t\t  Declaration(Class(mv:ETSIDomain_Governance_Ethics))\n\n\t\t  # Classification along two primary dimensions\n\t\t  SubClassOf(mv:ETSIDomain_Governance_Ethics mv:VirtualEntity)\n\t\t  SubClassOf(mv:ETSIDomain_Governance_Ethics mv:Object)\n\n\t\t  # Domain classification\n\t\t  SubClassOf(mv:ETSIDomain_Governance_Ethics\n\t\t    ObjectSomeValuesFrom(mv:belongsToDomain mv:InfrastructureDomain)\n\t\t  )\n\n\t\t  # Layer classification\n\t\t  SubClassOf(mv:ETSIDomain_Governance_Ethics\n\t\t    ObjectSomeValuesFrom(mv:implementedInLayer mv:ApplicationLayer)\n\t\t  )\n\n\t\t  # Crossover domain dependencies\n\t\t  SubClassOf(mv:ETSIDomain_Governance_Ethics\n\t\t    ObjectSomeValuesFrom(mv:requires mv:ETSIDomain_Governance)\n\t\t  )\n\t\t  SubClassOf(mv:ETSIDomain_Governance_Ethics\n\t\t    ObjectSomeValuesFrom(mv:requires mv:ETSIDomain_EthicsLaw)\n\t\t  )\n\n\t\t  # Ethical decision-making enablement\n\t\t  SubClassOf(mv:ETSIDomain_Governance_Ethics\n\t\t    ObjectSomeValuesFrom(mv:enables mv:EthicalDecisionMaking)\n\t\t  )\n\n  # Property characteristics\n  TransitiveObjectProperty(dt:ispartof)\n\n  # Property characteristics\n  AsymmetricObjectProperty(dt:requires)\n\n  # Property characteristics\n  AsymmetricObjectProperty(dt:enables)\n\n  # Property characteristics\n  AsymmetricObjectProperty(dt:dependson)\n```",
  "properties": {
    "id": "etsi-domain-governance-ethics-owl-axioms",
    "collapsed": "true",
    "- ontology": "true",
    "- term-id": "20349",
    "- source-domain": "metaverse",
    "- status": "draft",
    "- public-access": "true",
    "- preferred-term": "ETSI Domain: Governance & Ethics",
    "- definition": "Crossover domain for ETSI metaverse categorization addressing ethical governance frameworks, responsible decision-making processes, and value-aligned organizational structures.",
    "- maturity": "mature",
    "- source": "[[ETSI GR MEC 032]]",
    "- owl:class": "mv:ETSIDomain_Governance_Ethics",
    "- owl:physicality": "VirtualEntity",
    "- owl:role": "Object",
    "- owl:inferred-class": "mv:VirtualObject",
    "- owl:functional-syntax": "true",
    "- belongsToDomain": "[[InfrastructureDomain]]",
    "- implementedInLayer": "[[ApplicationLayer]]",
    "- is-subclass-of": "[[Metaverse]]",
    "- is-part-of": "[[ETSI Metaverse Domain Taxonomy]]",
    "- has-part": "[[Ethics Committee]], [[Governance Board]], [[Value Framework]], [[Stakeholder Engagement]]",
    "- requires": "[[Governance]], [[Ethics & Law]]",
    "- enables": "[[Ethical Decision-Making]], [[Stakeholder Accountability]], [[Value Alignment]]",
    "- depends-on": "[[Ethical Principles]], [[Governance Models]]"
  },
  "backlinks": [],
  "wiki_links": [
    "Ethical Decision-Making",
    "Stakeholder Engagement",
    "InfrastructureDomain",
    "ApplicationLayer",
    "Governance Board",
    "Governance Models",
    "Governance",
    "Stakeholder Accountability",
    "Ethics Committee",
    "Ethics & Law",
    "ETSI GR MEC 032",
    "Ethical Principles",
    "Metaverse",
    "Value Framework",
    "Value Alignment",
    "ETSI Metaverse Domain Taxonomy"
  ],
  "ontology": {
    "term_id": "20349",
    "preferred_term": "ETSI Domain: Governance & Ethics",
    "definition": "Crossover domain for ETSI metaverse categorization addressing ethical governance frameworks, responsible decision-making processes, and value-aligned organizational structures.",
    "source_domain": "metaverse",
    "maturity_level": null,
    "authority_score": null
  }
}