{
  "title": "ETSI Domain: Data Management + Creative Media",
  "content": "- ### OntologyBlock\n  id:: etsi-domain-datamgmt-creative-ontology\n  collapsed:: true\n\t- ontology:: true\n\t- term-id:: 20342\n\t- source-domain:: metaverse\n\t- status:: draft\n<<<<<<< HEAD\n=======\n    - public-access:: true\n>>>>>>> 691c6e7cfbf51bb03aef4b19e8bb7f7924266439\n\t- preferred-term:: ETSI Domain: Data Management + Creative Media\n\t- definition:: Crossover domain for ETSI metaverse categorization addressing data infrastructure supporting creative content workflows, asset management, and version control systems.\n\t- maturity:: mature\n\t- source:: [[ETSI GR MEC 032]]\n\t- owl:class:: mv:ETSIDomain_DataMgmt_Creative\n\t- owl:physicality:: VirtualEntity\n\t- owl:role:: Object\n\t- owl:inferred-class:: mv:VirtualObject\n\t- owl:functional-syntax:: true\n\t- belongsToDomain:: [[InfrastructureDomain]]\n\t- implementedInLayer:: [[ApplicationLayer]]\n\t- #### Relationships\n\t  id:: etsi-domain-datamgmt-creative-relationships\n\t\t- is-part-of:: [[ETSI Metaverse Domain Taxonomy]]\n\t\t- has-part:: [[Asset Database]], [[Version Control]], [[Content Pipeline]], [[Media Library]]\n\t\t- requires:: [[Data Management]], [[Creative Media]]\n\t\t- enables:: [[Asset Version Control]], [[Collaborative Authoring]], [[Content Distribution]]\n\t\t- depends-on:: [[Distributed Storage]], [[Metadata Management]]\n\t- #### OWL Axioms\n\t  id:: etsi-domain-datamgmt-creative-owl-axioms\n\t  collapsed:: true\n\t\t- ```clojure\n\t\t  Declaration(Class(mv:ETSIDomain_DataMgmt_Creative))\n\n\t\t  # Classification along two primary dimensions\n\t\t  SubClassOf(mv:ETSIDomain_DataMgmt_Creative mv:VirtualEntity)\n\t\t  SubClassOf(mv:ETSIDomain_DataMgmt_Creative mv:Object)\n\n\t\t  # Domain classification\n\t\t  SubClassOf(mv:ETSIDomain_DataMgmt_Creative\n\t\t    ObjectSomeValuesFrom(mv:belongsToDomain mv:InfrastructureDomain)\n\t\t  )\n\n\t\t  # Layer classification\n\t\t  SubClassOf(mv:ETSIDomain_DataMgmt_Creative\n\t\t    ObjectSomeValuesFrom(mv:implementedInLayer mv:ApplicationLayer)\n\t\t  )\n\n\t\t  # Crossover domain dependencies\n\t\t  SubClassOf(mv:ETSIDomain_DataMgmt_Creative\n\t\t    ObjectSomeValuesFrom(mv:requires mv:ETSIDomain_DataManagement)\n\t\t  )\n\t\t  SubClassOf(mv:ETSIDomain_DataMgmt_Creative\n\t\t    ObjectSomeValuesFrom(mv:requires mv:ETSIDomain_CreativeMedia)\n\t\t  )\n\n\t\t  # Asset version control enablement\n\t\t  SubClassOf(mv:ETSIDomain_DataMgmt_Creative\n\t\t    ObjectSomeValuesFrom(mv:enables mv:AssetVersionControl)\n\t\t  )\n\n  # Property characteristics\n  TransitiveObjectProperty(dt:ispartof)\n\n  # Property characteristics\n  AsymmetricObjectProperty(dt:requires)\n\n  # Property characteristics\n  AsymmetricObjectProperty(dt:enables)\n\n  # Property characteristics\n  AsymmetricObjectProperty(dt:dependson)\n```",
  "properties": {
    "id": "etsi-domain-datamgmt-creative-owl-axioms",
    "collapsed": "true",
    "- ontology": "true",
    "- term-id": "20342",
    "- source-domain": "metaverse",
    "- status": "draft",
    "- public-access": "true",
    "- preferred-term": "ETSI Domain: Data Management + Creative Media",
    "- definition": "Crossover domain for ETSI metaverse categorization addressing data infrastructure supporting creative content workflows, asset management, and version control systems.",
    "- maturity": "mature",
    "- source": "[[ETSI GR MEC 032]]",
    "- owl:class": "mv:ETSIDomain_DataMgmt_Creative",
    "- owl:physicality": "VirtualEntity",
    "- owl:role": "Object",
    "- owl:inferred-class": "mv:VirtualObject",
    "- owl:functional-syntax": "true",
    "- belongsToDomain": "[[InfrastructureDomain]]",
    "- implementedInLayer": "[[ApplicationLayer]]",
    "- is-part-of": "[[ETSI Metaverse Domain Taxonomy]]",
    "- has-part": "[[Asset Database]], [[Version Control]], [[Content Pipeline]], [[Media Library]]",
    "- requires": "[[Data Management]], [[Creative Media]]",
    "- enables": "[[Asset Version Control]], [[Collaborative Authoring]], [[Content Distribution]]",
    "- depends-on": "[[Distributed Storage]], [[Metadata Management]]"
  },
  "backlinks": [],
  "wiki_links": [
    "ETSI GR MEC 032",
    "Asset Version Control",
    "InfrastructureDomain",
    "Asset Database",
    "Media Library",
    "ApplicationLayer",
    "ETSI Metaverse Domain Taxonomy",
    "Content Pipeline",
    "Collaborative Authoring",
    "Creative Media",
    "Metadata Management",
    "Distributed Storage",
    "Data Management",
    "Content Distribution",
    "Version Control"
  ],
  "ontology": {
    "term_id": "20342",
    "preferred_term": "ETSI Domain: Data Management + Creative Media",
    "definition": "Crossover domain for ETSI metaverse categorization addressing data infrastructure supporting creative content workflows, asset management, and version control systems.",
    "source_domain": "metaverse",
    "maturity_level": null,
    "authority_score": null
  }
}