{
  "title": "ETSI Domain: Data Management",
  "content": "- ### OntologyBlock\n  id:: etsi-domain-data-management-ontology\n  collapsed:: true\n\t- ontology:: true\n\t- term-id:: 20341\n\t- source-domain:: metaverse\n\t- status:: draft\n    - public-access:: true\n\t- preferred-term:: ETSI Domain: Data Management\n\t- definition:: Domain marker for ETSI metaverse categorization covering data storage, processing, synchronization, and lifecycle management for distributed virtual environments.\n\t- maturity:: mature\n\t- source:: [[ETSI GR MEC 032]]\n\t- owl:class:: mv:ETSIDomain_DataManagement\n\t- owl:physicality:: VirtualEntity\n\t- owl:role:: Object\n\t- owl:inferred-class:: mv:VirtualObject\n\t- owl:functional-syntax:: true\n\t- belongsToDomain:: [[InfrastructureDomain]]\n\t- implementedInLayer:: [[ApplicationLayer]]\n\t- #### Relationships\n\t  id:: etsi-domain-data-management-relationships\n\t\t- is-subclass-of:: [[Metaverse Infrastructure]]\n\t\t- is-part-of:: [[ETSI Metaverse Domain Taxonomy]]\n\t\t- has-part:: [[Data Storage]], [[Data Processing]], [[Data Synchronization]], [[Data Lifecycle]]\n\t\t- requires:: [[Database Systems]], [[Caching Infrastructure]], [[Replication Mechanisms]]\n\t\t- enables:: [[State Persistence]], [[Cross-Platform Synchronization]], [[Data Analytics]]\n\t\t- depends-on:: [[Distributed Systems]], [[Consistency Protocols]]\n\t- #### OWL Axioms\n\t  id:: etsi-domain-data-management-owl-axioms\n\t  collapsed:: true\n\t\t- ```clojure\n\t\t  Declaration(Class(mv:ETSIDomain_DataManagement))\n\n\t\t  # Classification along two primary dimensions\n\t\t  SubClassOf(mv:ETSIDomain_DataManagement mv:VirtualEntity)\n\t\t  SubClassOf(mv:ETSIDomain_DataManagement mv:Object)\n\n\t\t  # Domain classification\n\t\t  SubClassOf(mv:ETSIDomain_DataManagement\n\t\t    ObjectSomeValuesFrom(mv:belongsToDomain mv:InfrastructureDomain)\n\t\t  )\n\n\t\t  # Layer classification\n\t\t  SubClassOf(mv:ETSIDomain_DataManagement\n\t\t    ObjectSomeValuesFrom(mv:implementedInLayer mv:ApplicationLayer)\n\t\t  )\n\n\t\t  # Domain taxonomy membership\n\t\t  SubClassOf(mv:ETSIDomain_DataManagement\n\t\t    ObjectSomeValuesFrom(mv:isPartOf mv:ETSIMetaverseDomainTaxonomy)\n\t\t  )\n\n\t\t  # Data infrastructure requirements\n\t\t  SubClassOf(mv:ETSIDomain_DataManagement\n\t\t    ObjectSomeValuesFrom(mv:requires mv:DatabaseSystems)\n\t\t  )\n\n\t\t  # State persistence enablement\n\t\t  SubClassOf(mv:ETSIDomain_DataManagement\n\t\t    ObjectSomeValuesFrom(mv:enables mv:StatePersistence)\n\t\t  )\n\n  # Property characteristics\n  TransitiveObjectProperty(dt:ispartof)\n\n  # Property characteristics\n  AsymmetricObjectProperty(dt:requires)\n\n  # Property characteristics\n  AsymmetricObjectProperty(dt:enables)\n\n  # Property characteristics\n  AsymmetricObjectProperty(dt:dependson)\n```",
  "properties": {
    "id": "etsi-domain-data-management-owl-axioms",
    "collapsed": "true",
    "- ontology": "true",
    "- term-id": "20341",
    "- source-domain": "metaverse",
    "- status": "draft",
    "- public-access": "true",
    "- preferred-term": "ETSI Domain: Data Management",
    "- definition": "Domain marker for ETSI metaverse categorization covering data storage, processing, synchronization, and lifecycle management for distributed virtual environments.",
    "- maturity": "mature",
    "- source": "[[ETSI GR MEC 032]]",
    "- owl:class": "mv:ETSIDomain_DataManagement",
    "- owl:physicality": "VirtualEntity",
    "- owl:role": "Object",
    "- owl:inferred-class": "mv:VirtualObject",
    "- owl:functional-syntax": "true",
    "- belongsToDomain": "[[InfrastructureDomain]]",
    "- implementedInLayer": "[[ApplicationLayer]]",
    "- is-subclass-of": "[[Metaverse Infrastructure]]",
    "- is-part-of": "[[ETSI Metaverse Domain Taxonomy]]",
    "- has-part": "[[Data Storage]], [[Data Processing]], [[Data Synchronization]], [[Data Lifecycle]]",
    "- requires": "[[Database Systems]], [[Caching Infrastructure]], [[Replication Mechanisms]]",
    "- enables": "[[State Persistence]], [[Cross-Platform Synchronization]], [[Data Analytics]]",
    "- depends-on": "[[Distributed Systems]], [[Consistency Protocols]]"
  },
  "backlinks": [],
  "wiki_links": [
    "Data Synchronization",
    "Replication Mechanisms",
    "Cross-Platform Synchronization",
    "Caching Infrastructure",
    "ETSI Metaverse Domain Taxonomy",
    "Data Processing",
    "Data Analytics",
    "Consistency Protocols",
    "Distributed Systems",
    "State Persistence",
    "Metaverse Infrastructure",
    "InfrastructureDomain",
    "Data Storage",
    "ETSI GR MEC 032",
    "Database Systems",
    "ApplicationLayer",
    "Data Lifecycle"
  ],
  "ontology": {
    "term_id": "20341",
    "preferred_term": "ETSI Domain: Data Management",
    "definition": "Domain marker for ETSI metaverse categorization covering data storage, processing, synchronization, and lifecycle management for distributed virtual environments.",
    "source_domain": "metaverse",
    "maturity_level": null,
    "authority_score": null
  }
}