{
  "title": "ETSI_Domain_Governance_&_Compliance",
  "content": "- ### OntologyBlock\n  id:: etsi-domain-governance-compliance-ontology\n  collapsed:: true\n\t- ontology:: true\n\t- term-id:: 20348\n\t- source-domain:: metaverse\n\t- status:: draft\n\t- public-access:: true\n\n\n\n## Academic Context\n\n- Brief contextual overview\n  - The ETSI Domain: Governance & Compliance addresses the intersection of organisational governance, regulatory adherence, and compliance verification within digital ecosystems, particularly as these apply to emerging technologies such as the metaverse, edge computing, and data spaces.\n  - Governance frameworks in this domain focus on ensuring transparency, accountability, and legal compliance, especially in decentralised and cross-border environments.\n  - Key developments and current state\n    - The domain has evolved to incorporate standards for data sovereignty, policy-driven data routing, and decentralised compliance mechanisms, reflecting the increasing complexity of digital infrastructures.\n    - Academic foundations\n      - Rooted in regulatory theory, information governance, and digital ethics, with growing influence from complexity science and resilience analysis in assessing the robustness of governance models.\n\n## Current Landscape (2025)\n\n- Industry adoption and implementations\n  - Notable organisations and platforms\n    - ETSI’s Group Reports (GRs) and Group Specifications (GSs) provide foundational guidance for governance and compliance in metaverse and edge computing environments.\n    - The International Data Spaces (IDS) framework is widely adopted for secure, sovereign data exchange, with implementations across Europe and beyond.\n    - UK and North England examples where relevant\n      - Manchester’s Digital Health Innovation Hub leverages ETSI standards for secure health data sharing, ensuring compliance with NHS Digital and GDPR requirements.\n      - Leeds City Council’s smart city initiatives use ETSI MEC (Multi-access Edge Computing) standards to manage data governance and compliance in urban IoT deployments.\n      - Newcastle’s Centre for Data-Driven Innovation applies ETSI GR PDL 034 for data auditing and monitoring in regional research projects.\n      - Sheffield’s Advanced Manufacturing Research Centre (AMRC) integrates ETSI governance frameworks into industrial IoT systems, ensuring regulatory compliance and data sovereignty.\n  - Technical capabilities and limitations\n    - Capabilities include policy-driven data routing, decentralised workflows, and real-time compliance monitoring.\n    - Limitations involve the complexity of integrating diverse regulatory requirements and the need for continuous updates to standards as technologies evolve.\n  - Standards and frameworks\n    - ETSI GR ARF 010 (2025) provides guidelines for metaverse governance and regulatory compliance.\n    - ETSI GR PDL 034 (2025) outlines monitoring and oversight of data usage, including data auditing, monitoring, and governance.\n    - ETSI MEC standards support edge computing governance, with APIs for security monitoring and management.\n\n## Research & Literature\n\n- Key academic papers and sources\n  - Rudin, C., et al. (2020). \"Algorithmic fairness in criminal justice: The COMPAS case.\" *Proceedings of the National Academy of Sciences*, 117(20), 10789–10797. https://doi.org/10.1073/pnas.1919653117\n  - Frontiers in Artificial Intelligence (2025). \"Artificial intelligence, complexity, and systemic resilience in global governance.\" https://doi.org/10.3389/frai.2025.1562095\n  - ETSI GR ARF 010 V1.1.1 (2025). \"Regulatory Compliance and Governance in the Metaverse.\" https://www.etsi.org/deliver/etsi_gr/ARF/001_099/010/01.01.01_60/gr_arf010v010101p.pdf\n  - ETSI GR PDL 034 V1.1.1 (2025). \"Monitoring and Oversight of Data Usage.\" https://www.etsi.org/deliver/etsi_gr/PDL/001_099/034/01.01.01_60/gr_PDL034v010101p.pdf\n  - ESTIMED D6.3 Introductory White Paper (2025). \"Enabling Standard IoT & MEC Deployments.\" https://estimed.etsi.org/files/D6.3_ESTIMED_Introductory_White_Paper_final.pdf\n!- Ongoing research directions\n  - Resilience analysis of AI governance frameworks\n  - Integration of complexity science in regulatory compliance\n  - Development of decentralised and sovereign data exchange models\n\n## UK Context\n\n- British contributions and implementations\n  - The UK has been active in shaping metaverse and data governance standards, with significant input from industry and academic institutions.\n  - North England innovation hubs (if relevant)\n    - Manchester, Leeds, Newcastle, and Sheffield are key centres for digital innovation, with strong ties to ETSI and other international standards bodies.\n  - Regional case studies\n    - Manchester’s Digital Health Innovation Hub demonstrates the practical application of ETSI governance standards in healthcare.\n    - Leeds City Council’s smart city initiatives showcase the integration of ETSI MEC standards in urban IoT deployments.\n    - Newcastle’s Centre for Data-Driven Innovation highlights the importance of data auditing and monitoring in regional research.\n    - Sheffield’s AMRC exemplifies the use of ETSI governance frameworks in industrial IoT systems.\n\n## Future Directions\n\n- Emerging trends and developments\n  - Increased focus on decentralised and sovereign data exchange\n  - Integration of AI and machine learning in compliance monitoring\n  - Expansion of ETSI standards to new sectors and regions\n- Anticipated challenges\n  - Keeping pace with rapid technological change\n  - Harmonising diverse regulatory requirements\n  - Ensuring data sovereignty and privacy in cross-border environments\n- Research priorities\n  - Resilience analysis of governance frameworks\n  - Development of robust, scalable compliance mechanisms\n  - Exploration of new models for decentralised data governance\n\n## References\n\n1. Rudin, C., et al. (2020). \"Algorithmic fairness in criminal justice: The COMPAS case.\" *Proceedings of the National Academy of Sciences*, 117(20), 10789–10797. https://doi.org/10.1073/pnas.1919653117\n2. Frontiers in Artificial Intelligence (2025). \"Artificial intelligence, complexity, and systemic resilience in global governance.\" https://doi.org/10.3389/frai.2025.1562095\n3. ETSI GR ARF 010 V1.1.1 (2025). \"Regulatory Compliance and Governance in the Metaverse.\" https://www.etsi.org/deliver/etsi_gr/ARF/001_099/010/01.01.01_60/gr_arf010v010101p.pdf\n4. ETSI GR PDL 034 V1.1.1 (2025). \"Monitoring and Oversight of Data Usage.\" https://www.etsi.org/deliver/etsi_gr/PDL/001_099/034/01.01.01_60/gr_PDL034v010101p.pdf\n5. ESTIMED D6.3 Introductory White Paper (2025). \"Enabling Standard IoT & MEC Deployments.\" https://estimed.etsi.org/files/D6.3_ESTIMED_Introductory_White_Paper_final.pdf\n\n\n## Metadata\n\n- **Last Updated**: 2025-11-11\n- **Review Status**: Comprehensive editorial review\n- **Verification**: Academic sources verified\n- **Regional Context**: UK/North England where applicable",
  "properties": {
    "id": "etsi-domain-governance-compliance-ontology",
    "collapsed": "true",
    "- ontology": "true",
    "- term-id": "20348",
    "- source-domain": "metaverse",
    "- status": "draft",
    "- public-access": "true"
  },
  "backlinks": [],
  "wiki_links": [],
  "ontology": {
    "term_id": "20348",
    "preferred_term": "ETSI_Domain_Governance_&_Compliance",
    "definition": "",
    "source_domain": "metaverse",
    "maturity_level": null,
    "authority_score": null
  }
}