{
  "title": "ETSI Domain Application + Industry",
  "content": "- ### OntologyBlock\n  id:: etsi-domain-application-industry-ontology\n  collapsed:: true\n\t- ontology:: true\n\t- term-id:: 20338\n\t- source-domain:: metaverse\n\t- status:: draft\n    - public-access:: true\n\t- preferred-term:: ETSI Domain Application + Industry\n\t- definition:: Cross-domain marker for metaverse application components focused on industrial applications including manufacturing simulations, industrial digital twins, predictive maintenance, remote operations, and industrial training systems.\n\t- maturity:: mature\n\t- source:: [[ETSI GS MEC]]\n\t- owl:class:: mv:ETSIDomainApplicationIndustry\n\t- owl:physicality:: VirtualEntity\n\t- owl:role:: Object\n\t- owl:inferred-class:: mv:VirtualObject\n\t- owl:functional-syntax:: true\n\t- belongsToDomain:: [[InfrastructureDomain]], [[VirtualEconomyDomain]]\n\t- implementedInLayer:: [[ApplicationLayer]]\n\t- #### Relationships\n\t  id:: etsi-domain-application-industry-relationships\n\t\t- is-subclass-of:: [[ArtificialIntelligence]]\n\t\t- is-part-of:: [[ETSI Domain Taxonomy]]\n\t\t- depends-on:: [[InfrastructureDomain]], [[VirtualEconomyDomain]]\n\t\t- enables:: [[Industrial Application Classification]], [[Manufacturing Platform Categorization]]\n\t\t- categorizes:: [[Industrial Digital Twin]], [[Manufacturing Simulation]], [[Predictive Maintenance]], [[Remote Operations]]\n\t- #### OWL Axioms\n\t  id:: etsi-domain-application-industry-owl-axioms\n\t  collapsed:: true\n\t\t- ```clojure\n\t\t  Declaration(Class(mv:ETSIDomainApplicationIndustry))\n\n\t\t  # Classification along two primary dimensions\n\t\t  SubClassOf(mv:ETSIDomainApplicationIndustry mv:VirtualEntity)\n\t\t  SubClassOf(mv:ETSIDomainApplicationIndustry mv:Object)\n\n\t\t  # Cross-domain marker classification\n\t\t  SubClassOf(mv:ETSIDomainApplicationIndustry mv:DomainMarker)\n\t\t  SubClassOf(mv:ETSIDomainApplicationIndustry mv:CrossDomainMarker)\n\n\t\t  # Multiple domain classification\n\t\t  SubClassOf(mv:ETSIDomainApplicationIndustry\n\t\t    ObjectSomeValuesFrom(mv:belongsToDomain mv:InfrastructureDomain)\n\t\t  )\n\t\t  SubClassOf(mv:ETSIDomainApplicationIndustry\n\t\t    ObjectSomeValuesFrom(mv:belongsToDomain mv:VirtualEconomyDomain)\n\t\t  )\n\n\t\t  # Layer classification\n\t\t  SubClassOf(mv:ETSIDomainApplicationIndustry\n\t\t    ObjectSomeValuesFrom(mv:implementedInLayer mv:ApplicationLayer)\n\t\t  )\n\n  # Property characteristics\n  TransitiveObjectProperty(dt:ispartof)\n\n  # Property characteristics\n  AsymmetricObjectProperty(dt:dependson)\n\n  # Property characteristics\n  AsymmetricObjectProperty(dt:enables)\n```",
  "properties": {
    "id": "etsi-domain-application-industry-owl-axioms",
    "collapsed": "true",
    "- ontology": "true",
    "- term-id": "20338",
    "- source-domain": "metaverse",
    "- status": "draft",
    "- public-access": "true",
    "- preferred-term": "ETSI Domain Application + Industry",
    "- definition": "Cross-domain marker for metaverse application components focused on industrial applications including manufacturing simulations, industrial digital twins, predictive maintenance, remote operations, and industrial training systems.",
    "- maturity": "mature",
    "- source": "[[ETSI GS MEC]]",
    "- owl:class": "mv:ETSIDomainApplicationIndustry",
    "- owl:physicality": "VirtualEntity",
    "- owl:role": "Object",
    "- owl:inferred-class": "mv:VirtualObject",
    "- owl:functional-syntax": "true",
    "- belongsToDomain": "[[InfrastructureDomain]], [[VirtualEconomyDomain]]",
    "- implementedInLayer": "[[ApplicationLayer]]",
    "- is-subclass-of": "[[ArtificialIntelligence]]",
    "- is-part-of": "[[ETSI Domain Taxonomy]]",
    "- depends-on": "[[InfrastructureDomain]], [[VirtualEconomyDomain]]",
    "- enables": "[[Industrial Application Classification]], [[Manufacturing Platform Categorization]]",
    "- categorizes": "[[Industrial Digital Twin]], [[Manufacturing Simulation]], [[Predictive Maintenance]], [[Remote Operations]]"
  },
  "backlinks": [],
  "wiki_links": [
    "InfrastructureDomain",
    "Manufacturing Platform Categorization",
    "Remote Operations",
    "Predictive Maintenance",
    "ETSI Domain Taxonomy",
    "ETSI GS MEC",
    "Industrial Application Classification",
    "Manufacturing Simulation",
    "VirtualEconomyDomain",
    "ArtificialIntelligence",
    "Industrial Digital Twin",
    "ApplicationLayer"
  ],
  "ontology": {
    "term_id": "20338",
    "preferred_term": "ETSI Domain Application + Industry",
    "definition": "Cross-domain marker for metaverse application components focused on industrial applications including manufacturing simulations, industrial digital twins, predictive maintenance, remote operations, and industrial training systems.",
    "source_domain": "metaverse",
    "maturity_level": null,
    "authority_score": null
  }
}