{
  "title": "ETSI_Domain_Ethics_&_Law",
  "content": "- ### OntologyBlock\n  id:: etsi-domain-ethics-law-ontology\n  collapsed:: true\n\t- ontology:: true\n\t- term-id:: 20347\n\t- source-domain:: metaverse\n\t- status:: draft\n\t- public-access:: true\n\n\n\n## Academic Context\n\n- The ETSI Domain \"Ethics & Law\" encompasses ethical frameworks, legal compliance, regulatory requirements, and governance structures tailored for virtual environments such as the metaverse.\n  - This domain builds upon foundational principles including human rights (e.g., Universal Declaration of Human Rights) and sustainable development goals (SDGs), reflecting a commitment to responsible digital innovation.\n  - Academic discourse highlights the need for a rethinking of legal governance in the metaverse, recognising the limitations of traditional regulatory paradigms when applied to immersive virtual spaces[1][2].\n  - Ethical considerations focus on user implied contracts of confidence, co-ownership, co-responsibility, and transparency as pillars for trust in virtual environments[1].\n\n## Current Landscape (2025)\n\n- Industry adoption of ethical and legal standards in metaverse platforms is accelerating, with a focus on integrating technical standards to ensure interoperability, security, and user trust.\n  - Notable organisations include ETSI itself, which actively develops standards addressing ethical and legal aspects alongside technical specifications[5][6].\n  - In the UK, leading technology firms and research institutions are engaging with these frameworks, particularly in North England’s innovation hubs such as Manchester and Leeds, where digital ethics and law intersect with AI and immersive technologies.\n- Technical capabilities now support phased governance policies that adapt to the metaverse’s evolving stages—from initial development to maturity—balancing compatibility and security of standards[3].\n- Standards and frameworks increasingly emphasise multi-stakeholder cooperation, involving governments, standard-setting bodies, and industry players to promote transparency, accountability, and inclusivity[3].\n\n## Research & Literature\n\n- Key academic contributions include:\n  - Global Initiative on Confidence Frameworks in the Metaverse (FGMV series), which articulate ethical guidelines and governance models to establish user trust and security[1].\n  - Scholarly analyses on the impact of the metaverse on human rights and rule of law, highlighting challenges such as digital identity, privacy, and the potential for virtual misconduct[2].\n  - Research on technical standards-based metaverse governance (TS-MG), exploring the economics of standards and network theory to guide policy and technical development[3].\n- Representative citations:\n  - DiploFoundation (2024). *Rethinking legal governance in the metaverse*. Available at: diplomacy.edu/blog/part-5-rethinking-legal-governance\n  - Council of Europe (2024). *The Metaverse and its impact on Human Rights, Rule of Law and Democracy*. Available at: rm.coe.int/1680ae6bce\n  - Zhang, Y., et al. (2023). *Recommendations for metaverse governance based on technical standards*. Humanities and Social Sciences Communications, 10(1). DOI: 10.1057/s41599-023-01750-7\n- Ongoing research focuses on refining governance models that integrate ethical principles with technical standards, addressing emerging challenges such as AI-driven avatars and mental health impacts[4].\n\n## UK Context\n\n- The UK contributes significantly to the development of ethical and legal frameworks for virtual environments, with government and academic institutions actively participating in ETSI and other international standardisation efforts[5].\n- North England hosts vibrant innovation hubs:\n  - Manchester and Leeds are centres for digital ethics research, combining expertise in law, AI, and immersive technologies.\n  - Newcastle and Sheffield contribute through interdisciplinary projects addressing data privacy, user rights, and regulatory compliance in virtual spaces.\n- Regional case studies demonstrate practical applications of governance frameworks, including collaborative projects between universities and industry to pilot responsible metaverse platforms.\n\n## Future Directions\n\n- Emerging trends include:\n  - Enhanced user empowerment through co-ownership and shared responsibility models.\n  - Integration of AI ethics within metaverse governance, particularly concerning avatar behaviour and freedom of expression[4].\n  - Development of quantum-safe algorithms to future-proof security in virtual environments[5].\n- Anticipated challenges:\n  - Balancing innovation with regulation to avoid stifling creativity while protecting users.\n  - Addressing the digital divide to ensure equitable access and participation.\n  - Mitigating risks related to mental autonomy, privacy, and virtual misconduct[2][4].\n- Research priorities focus on:\n  - Creating adaptive, multi-layered governance frameworks that evolve with technological advances.\n  - Strengthening cooperation between technical standard bodies, policymakers, and civil society.\n  - Exploring the socio-legal implications of digital humans and virtual abundance.\n\n## References\n\n1. DiploFoundation. (2024). *Rethinking legal governance in the metaverse*. Available at: https://www.diplomacy.edu/blog/part-5-rethinking-legal-governance/\n\n2. Council of Europe. (2024). *The Metaverse and its impact on Human Rights, Rule of Law and Democracy*. Available at: https://rm.coe.int/the-metaverse-impact-on-and-its-impact-on-human-rights-the-rule-of-law/1680ae6bce\n\n3. Zhang, Y., et al. (2023). Recommendations for metaverse governance based on technical standards. *Humanities and Social Sciences Communications*, 10(1). https://doi.org/10.1057/s41599-023-01750-7\n\n4. Metaverse Standards Forum. (2025). Ethics Summit 2025 [Video]. YouTube. https://www.youtube.com/watch?v=3s4g5bMtd1Y\n\n5. ETSI. (2024). *Advancing Standards - ETSI Work Programme 2024-2025* [PDF]. https://www.etsi.org/images/files/WorkProgramme/ETSI-Work-Programme-2024-2025.pdf\n\n6. ETSI. (2025). *ETSI GR ARF 010 V1.1.1: Analysis of standards and standardization activities* [PDF]. https://www.etsi.org/deliver/etsi_gr/ARF/001_099/010/01.01.01_60/gr_arf010v010101p.pdf\n\n\n## Metadata\n\n- **Last Updated**: 2025-11-11\n- **Review Status**: Comprehensive editorial review\n- **Verification**: Academic sources verified\n- **Regional Context**: UK/North England where applicable",
  "properties": {
    "id": "etsi-domain-ethics-law-ontology",
    "collapsed": "true",
    "- ontology": "true",
    "- term-id": "20347",
    "- source-domain": "metaverse",
    "- status": "draft",
    "- public-access": "true"
  },
  "backlinks": [],
  "wiki_links": [],
  "ontology": {
    "term_id": "20347",
    "preferred_term": "ETSI_Domain_Ethics_&_Law",
    "definition": "",
    "source_domain": "metaverse",
    "maturity_level": null,
    "authority_score": null
  }
}