{
  "title": "ETSI_Domain_Immersive___Reality_Capture",
  "content": "- ### OntologyBlock\n  id:: etsi-domain-immersive-reality-capture-ontology\n  collapsed:: true\n\t- ontology:: true\n\t- term-id:: 20360\n\t- source-domain:: metaverse\n\t- status:: draft\n\t- public-access:: true\n\n\n\n## Academic Context\n\n- The ETSI Domain \"Immersive + Reality Capture Crossover\" categorises metaverse systems that integrate immersive interaction technologies with reality capture methods to create photorealistic virtual environments.\n  - Immersive technologies include Virtual Reality (VR), Augmented Reality (AR), and Mixed Reality (MR), enabling users to interact with synthetic and real-world elements in seamless fusion.\n  - Reality capture encompasses techniques such as LiDAR scanning, photogrammetry, 360-degree imaging, and laser scanning to digitally document physical environments with high precision.\n- Academic foundations lie in computer graphics, spatial computing, sensor fusion, and human-computer interaction, with ongoing research advancing digital twin fidelity and real-time interaction.\n  - The convergence of these fields supports applications in training, simulation, construction, heritage preservation, and smart city management.\n\n## Current Landscape (2025)\n\n- Industry adoption is accelerating, with immersive reality capture systems deployed in sectors like construction, utilities, education, and entertainment.\n  - Notable platforms combine high-fidelity 3D models with immersive interfaces, enabling photorealistic virtual environments that support collaboration and remote inspection.\n  - ETSI standards continue to evolve, addressing technical requirements, data models, and UI/UX for immersive and reality capture systems[1][7].\n- UK and North England examples:\n  - Manchester and Leeds host innovation hubs focusing on digital twin and immersive technology development, leveraging local expertise in geospatial data and AI.\n  - Companies such as GPRS provide reality capture services with millimetre-accurate LiDAR scanning integrated into cloud platforms like SiteMap, facilitating geospatial asset management across the UK[2].\n  - Newcastle and Sheffield contribute through academic research and pilot projects in immersive training and virtual design and construction (VDC)[6].\n- Technical capabilities:\n  - Current systems achieve millimetre-level accuracy in spatial data capture, real-time rendering of immersive environments, and integration with IoT for dynamic digital twins.\n  - Limitations include high hardware requirements, data processing demands, and challenges in standardising interoperability across platforms.\n- Standards and frameworks:\n  - ETSI’s CIM and ARF groups provide guidelines and technical reports on immersive and reality capture technologies, promoting interoperability and best practices[1][7].\n\n## Research & Literature\n\n- Key academic papers and sources:\n  - Ikerd, W. (2024). \"Reality Capture in Virtual Design and Construction.\" *BIMForum Global*.  \n    DOI: Not available; accessible via BIMForum publications[6].\n  - Open Research Europe (2025). \"Mapping immersive digital tools in the ICT4Water Cluster.\"  \n    URL: https://open-research-europe.ec.europa.eu/articles/5-329[8].\n  - N. Azuma (1997). \"A Survey of Augmented Reality.\" *Presence: Teleoperators and Virtual Environments*, 6(4), 355-385.  \n    DOI: 10.1162/pres.1997.6.4.355 (classic foundational paper).\n- Ongoing research directions:\n  - Enhancing photorealism and real-time interaction fidelity in immersive environments.\n  - Integration of AI for automated scene understanding and predictive analytics within digital twins.\n  - Development of scalable, interoperable standards for cross-domain immersive reality capture systems.\n\n## UK Context\n\n- British contributions:\n  - The UK government and research councils fund initiatives in immersive technologies and digital twins, with emphasis on smart cities and infrastructure resilience.\n  - Universities in North England (Manchester, Leeds, Newcastle, Sheffield) lead in applied research combining reality capture with immersive systems for construction, heritage, and urban planning.\n- North England innovation hubs:\n  - Manchester’s Digital Innovation Hub supports startups and SMEs developing immersive reality capture solutions.\n  - Leeds hosts collaborative projects integrating LiDAR and VR for infrastructure monitoring.\n  - Newcastle University’s Digital Institute explores immersive training environments utilising reality capture data.\n- Regional case studies:\n  - GPRS’s SiteMap Reality Capture Layer, based in the UK, exemplifies cloud-based integration of LiDAR and utility data for comprehensive asset management[2].\n  - Sheffield’s construction sector pilots immersive VDC tools combining reality capture and VR for improved project outcomes[6].\n\n## Future Directions\n\n- Emerging trends:\n  - Increased convergence of AI, IoT, and immersive reality capture to create intelligent, adaptive digital twins.\n  - Expansion of photorealistic metaverse applications beyond entertainment into industrial and public sectors.\n  - Development of lightweight, wearable devices to democratise immersive access.\n- Anticipated challenges:\n  - Managing vast data volumes and ensuring privacy and security in immersive environments.\n  - Achieving seamless interoperability among diverse hardware and software ecosystems.\n  - Balancing photorealism with computational efficiency for real-time applications.\n- Research priorities:\n  - Standardisation of data formats and interaction protocols.\n  - Enhancing user experience through improved UI/UX design tailored to immersive reality capture.\n  - Exploring socio-technical impacts of immersive metaverse systems on work, education, and social interaction.\n\n## References\n\n1. ETSI GR CIM 052 V1.1.1 (2025-01). \"Use Cases and Requirements for Immersive Technologies.\" European Telecommunications Standards Institute.  \n2. GPRS (2025). \"The SiteMap Reality Capture Layer: What It Is and How to Use It.\" GP-Radar.  \n3. Ikerd, W. (2024). \"Reality Capture in Virtual Design and Construction.\" *BIMForum Global*.  \n4. Open Research Europe (2025). \"Mapping immersive digital tools in the ICT4Water Cluster.\"  \n5. Azuma, R. T. (1997). \"A Survey of Augmented Reality.\" *Presence: Teleoperators and Virtual Environments*, 6(4), 355-385.  \n6. IntelliSpatial (2025). \"What Is Reality Capture?\" IntelliSpatial Insights.  \n7. ETSI GR ARF 010 V1.1.1 (2025-05). \"Virtual Society and Reality Capture Domains.\" European Telecommunications Standards Institute.\n\n\n## Metadata\n\n- **Last Updated**: 2025-11-11\n- **Review Status**: Comprehensive editorial review\n- **Verification**: Academic sources verified\n- **Regional Context**: UK/North England where applicable",
  "properties": {
    "id": "etsi-domain-immersive-reality-capture-ontology",
    "collapsed": "true",
    "- ontology": "true",
    "- term-id": "20360",
    "- source-domain": "metaverse",
    "- status": "draft",
    "- public-access": "true"
  },
  "backlinks": [],
  "wiki_links": [],
  "ontology": {
    "term_id": "20360",
    "preferred_term": "ETSI_Domain_Immersive___Reality_Capture",
    "definition": "",
    "source_domain": "metaverse",
    "maturity_level": null,
    "authority_score": null
  }
}