{
  "title": "ETSI Domain: Creative Media",
  "content": "- ### OntologyBlock\n  id:: etsi-domain-creative-media-ontology\n  collapsed:: true\n\t- ontology:: true\n\t- term-id:: 20340\n\t- source-domain:: metaverse\n\t- status:: draft\n<<<<<<< HEAD\n=======\n    - public-access:: true\n>>>>>>> 691c6e7cfbf51bb03aef4b19e8bb7f7924266439\n\t- preferred-term:: ETSI Domain: Creative Media\n\t- definition:: Domain marker for ETSI metaverse categorization covering creative content production, 3D modeling, rendering, and multimedia authoring for virtual environments.\n\t- maturity:: mature\n\t- source:: [[ETSI GR MEC 032]]\n\t- owl:class:: mv:ETSIDomain_CreativeMedia\n\t- owl:physicality:: VirtualEntity\n\t- owl:role:: Object\n\t- owl:inferred-class:: mv:VirtualObject\n\t- owl:functional-syntax:: true\n\t- belongsToDomain:: [[InfrastructureDomain]]\n\t- implementedInLayer:: [[ApplicationLayer]]\n\t- #### Relationships\n\t  id:: etsi-domain-creative-media-relationships\n\t\t- is-part-of:: [[ETSI Metaverse Domain Taxonomy]]\n\t\t- has-part:: [[3D Content Creation]], [[Rendering Pipeline]], [[Asset Management]], [[Multimedia Authoring]]\n\t\t- requires:: [[Creative Tools]], [[Content Pipeline]]\n\t\t- enables:: [[Virtual World Building]], [[Avatar Customization]], [[Scene Design]]\n\t\t- depends-on:: [[Graphics Processing]], [[Asset Format Standards]]\n\t- #### OWL Axioms\n\t  id:: etsi-domain-creative-media-owl-axioms\n\t  collapsed:: true\n\t\t- ```clojure\n\t\t  Declaration(Class(mv:ETSIDomain_CreativeMedia))\n\n\t\t  # Classification along two primary dimensions\n\t\t  SubClassOf(mv:ETSIDomain_CreativeMedia mv:VirtualEntity)\n\t\t  SubClassOf(mv:ETSIDomain_CreativeMedia mv:Object)\n\n\t\t  # Domain classification\n\t\t  SubClassOf(mv:ETSIDomain_CreativeMedia\n\t\t    ObjectSomeValuesFrom(mv:belongsToDomain mv:InfrastructureDomain)\n\t\t  )\n\n\t\t  # Layer classification\n\t\t  SubClassOf(mv:ETSIDomain_CreativeMedia\n\t\t    ObjectSomeValuesFrom(mv:implementedInLayer mv:ApplicationLayer)\n\t\t  )\n\n\t\t  # Domain taxonomy membership\n\t\t  SubClassOf(mv:ETSIDomain_CreativeMedia\n\t\t    ObjectSomeValuesFrom(mv:isPartOf mv:ETSIMetaverseDomainTaxonomy)\n\t\t  )\n\n\t\t  # Content creation enablement\n\t\t  SubClassOf(mv:ETSIDomain_CreativeMedia\n\t\t    ObjectSomeValuesFrom(mv:enables mv:VirtualWorldBuilding)\n\t\t  )\n\n\t\t  # Creative tools dependency\n\t\t  SubClassOf(mv:ETSIDomain_CreativeMedia\n\t\t    ObjectSomeValuesFrom(mv:requires mv:CreativeTools)\n\t\t  )\n\n  # Property characteristics\n  TransitiveObjectProperty(dt:ispartof)\n\n  # Property characteristics\n  AsymmetricObjectProperty(dt:requires)\n\n  # Property characteristics\n  AsymmetricObjectProperty(dt:enables)\n\n  # Property characteristics\n  AsymmetricObjectProperty(dt:dependson)\n```",
  "properties": {
    "id": "etsi-domain-creative-media-owl-axioms",
    "collapsed": "true",
    "- ontology": "true",
    "- term-id": "20340",
    "- source-domain": "metaverse",
    "- status": "draft",
    "- public-access": "true",
    "- preferred-term": "ETSI Domain: Creative Media",
    "- definition": "Domain marker for ETSI metaverse categorization covering creative content production, 3D modeling, rendering, and multimedia authoring for virtual environments.",
    "- maturity": "mature",
    "- source": "[[ETSI GR MEC 032]]",
    "- owl:class": "mv:ETSIDomain_CreativeMedia",
    "- owl:physicality": "VirtualEntity",
    "- owl:role": "Object",
    "- owl:inferred-class": "mv:VirtualObject",
    "- owl:functional-syntax": "true",
    "- belongsToDomain": "[[InfrastructureDomain]]",
    "- implementedInLayer": "[[ApplicationLayer]]",
    "- is-part-of": "[[ETSI Metaverse Domain Taxonomy]]",
    "- has-part": "[[3D Content Creation]], [[Rendering Pipeline]], [[Asset Management]], [[Multimedia Authoring]]",
    "- requires": "[[Creative Tools]], [[Content Pipeline]]",
    "- enables": "[[Virtual World Building]], [[Avatar Customization]], [[Scene Design]]",
    "- depends-on": "[[Graphics Processing]], [[Asset Format Standards]]"
  },
  "backlinks": [],
  "wiki_links": [
    "ETSI GR MEC 032",
    "Asset Management",
    "InfrastructureDomain",
    "Graphics Processing",
    "Multimedia Authoring",
    "Virtual World Building",
    "ApplicationLayer",
    "ETSI Metaverse Domain Taxonomy",
    "Creative Tools",
    "Content Pipeline",
    "Asset Format Standards",
    "Avatar Customization",
    "Scene Design",
    "Rendering Pipeline",
    "3D Content Creation"
  ],
  "ontology": {
    "term_id": "20340",
    "preferred_term": "ETSI Domain: Creative Media",
    "definition": "Domain marker for ETSI metaverse categorization covering creative content production, 3D modeling, rendering, and multimedia authoring for virtual environments.",
    "source_domain": "metaverse",
    "maturity_level": null,
    "authority_score": null
  }
}