{
  "title": "ETSI Domain AI + Creative Media",
  "content": "- ### OntologyBlock\n  id:: etsi-domain-ai-creative-media-ontology\n  collapsed:: true\n\t- ontology:: true\n\t- term-id:: 20331\n\t- source-domain:: metaverse\n\t- status:: draft\n<<<<<<< HEAD\n=======\n    - public-access:: true\n>>>>>>> 691c6e7cfbf51bb03aef4b19e8bb7f7924266439\n\t- preferred-term:: ETSI Domain AI + Creative Media\n\t- definition:: Cross-domain marker for metaverse components that combine artificial intelligence capabilities with creative media applications such as generative content, procedural generation, and AI-assisted authoring.\n\t- maturity:: mature\n\t- source:: [[ETSI GS MEC]]\n\t- owl:class:: mv:ETSIDomainAICreativeMedia\n\t- owl:physicality:: VirtualEntity\n\t- owl:role:: Object\n\t- owl:inferred-class:: mv:VirtualObject\n\t- owl:functional-syntax:: true\n\t- belongsToDomain:: [[ComputationAndIntelligenceDomain]], [[CreativeMediaDomain]]\n\t- implementedInLayer:: [[ApplicationLayer]]\n\t- #### Relationships\n\t  id:: etsi-domain-ai-creative-media-relationships\n\t\t- is-part-of:: [[ETSI Domain Taxonomy]]\n\t\t- depends-on:: [[ETSI Domain AI]], [[CreativeMediaDomain]]\n\t\t- enables:: [[Generative Content Classification]], [[AI Art Categorization]]\n\t\t- categorizes:: [[Generative AI]], [[Procedural Content Generation]], [[AI Assisted Authoring]]\n\t- #### OWL Axioms\n\t  id:: etsi-domain-ai-creative-media-owl-axioms\n\t  collapsed:: true\n\t\t- ```clojure\n\t\t  Declaration(Class(mv:ETSIDomainAICreativeMedia))\n\n\t\t  # Classification along two primary dimensions\n\t\t  SubClassOf(mv:ETSIDomainAICreativeMedia mv:VirtualEntity)\n\t\t  SubClassOf(mv:ETSIDomainAICreativeMedia mv:Object)\n\n\t\t  # Cross-domain marker classification\n\t\t  SubClassOf(mv:ETSIDomainAICreativeMedia mv:DomainMarker)\n\t\t  SubClassOf(mv:ETSIDomainAICreativeMedia mv:CrossDomainMarker)\n\n\t\t  # Multiple domain classification\n\t\t  SubClassOf(mv:ETSIDomainAICreativeMedia\n\t\t    ObjectSomeValuesFrom(mv:belongsToDomain mv:ComputationAndIntelligenceDomain)\n\t\t  )\n\t\t  SubClassOf(mv:ETSIDomainAICreativeMedia\n\t\t    ObjectSomeValuesFrom(mv:belongsToDomain mv:CreativeMediaDomain)\n\t\t  )\n\n\t\t  # Layer classification\n\t\t  SubClassOf(mv:ETSIDomainAICreativeMedia\n\t\t    ObjectSomeValuesFrom(mv:implementedInLayer mv:ApplicationLayer)\n\t\t  )\n\n  # Property characteristics\n  TransitiveObjectProperty(dt:ispartof)\n\n  # Property characteristics\n  AsymmetricObjectProperty(dt:dependson)\n\n  # Property characteristics\n  AsymmetricObjectProperty(dt:enables)\n```",
  "properties": {
    "id": "etsi-domain-ai-creative-media-owl-axioms",
    "collapsed": "true",
    "- ontology": "true",
    "- term-id": "20331",
    "- source-domain": "metaverse",
    "- status": "draft",
    "- public-access": "true",
    "- preferred-term": "ETSI Domain AI + Creative Media",
    "- definition": "Cross-domain marker for metaverse components that combine artificial intelligence capabilities with creative media applications such as generative content, procedural generation, and AI-assisted authoring.",
    "- maturity": "mature",
    "- source": "[[ETSI GS MEC]]",
    "- owl:class": "mv:ETSIDomainAICreativeMedia",
    "- owl:physicality": "VirtualEntity",
    "- owl:role": "Object",
    "- owl:inferred-class": "mv:VirtualObject",
    "- owl:functional-syntax": "true",
    "- belongsToDomain": "[[ComputationAndIntelligenceDomain]], [[CreativeMediaDomain]]",
    "- implementedInLayer": "[[ApplicationLayer]]",
    "- is-part-of": "[[ETSI Domain Taxonomy]]",
    "- depends-on": "[[ETSI Domain AI]], [[CreativeMediaDomain]]",
    "- enables": "[[Generative Content Classification]], [[AI Art Categorization]]",
    "- categorizes": "[[Generative AI]], [[Procedural Content Generation]], [[AI Assisted Authoring]]"
  },
  "backlinks": [
    "ETSI_Domain_AI"
  ],
  "wiki_links": [
    "ETSI Domain AI",
    "ETSI GS MEC",
    "ETSI Domain Taxonomy",
    "AI Assisted Authoring",
    "Procedural Content Generation",
    "Generative Content Classification",
    "ApplicationLayer",
    "CreativeMediaDomain",
    "Generative AI",
    "ComputationAndIntelligenceDomain",
    "AI Art Categorization"
  ],
  "ontology": {
    "term_id": "20331",
    "preferred_term": "ETSI Domain AI + Creative Media",
    "definition": "Cross-domain marker for metaverse components that combine artificial intelligence capabilities with creative media applications such as generative content, procedural generation, and AI-assisted authoring.",
    "source_domain": "metaverse",
    "maturity_level": null,
    "authority_score": null
  }
}