{
  "title": "ETSI_Domain_Governance___Ethics",
  "content": "- ### OntologyBlock\n  id:: etsi_domain_governance___ethics-ontology\n  collapsed:: true\n\t- ontology:: true\n\t- term-id:: mv-1761742247921\n\t- preferred-term:: ETSI_Domain_Governance___Ethics\n\t- source-domain:: metaverse\n\t- status:: draft\n\t- public-access:: true\n\n\n# ETSI_Domain_Governance___Ethics.md\n\n## Academic Context\n\n- Metaverse governance represents an emerging field addressing the intersection of technical standards, ethical frameworks, and regulatory oversight\n  - The metaverse is conceptualised as an open-ended digital reality connecting multiple virtual worlds through interoperable technical infrastructure\n  - Governance challenges stem from the fragmented nature of current implementations, which operate as multiple disconnected systems rather than a unified ecosystem\n  - ETSI's role centres on developing standardised approaches to ensure security, compatibility, and ethical alignment across virtual world platforms\n\n## Current Landscape (2025)\n\n- Industry adoption and implementations\n  - Technical standards-based metaverse governance (TS-MG) now encompasses formulation, security, and compatibility frameworks across three developmental levels: technology (core layer), application, and interaction\n  - The Metaverse Standards Forum has established working groups including an Ethical Principles Working Group to drive transparency and accountability\n  - Major technology organisations are integrating ethics into design processes, including explainability requirements, interdisciplinary team structures, and continuous fairness measurement\n  - UK and North England context remains underdeveloped in current literature, though ETSI's European standardisation mandate creates potential for regional implementation through Manchester, Leeds, and Newcastle technology clusters\n- Technical capabilities and limitations\n  - Current systems struggle with legacy infrastructure integration, data quality issues, and cross-platform interoperability\n  - Privacy controls and user consent mechanisms are increasingly embedded in platform design, though enforcement remains inconsistent\n  - Artificial intelligence governance within metaverse contexts requires addressing bias mitigation, explainability, and human-in-the-loop decision-making\n- Standards and frameworks\n  - ETSI GR ARF 020 Virtual Worlds Recommendations Report (2025) addresses standardisation gaps across eight technological domains: Infrastructure, Data Management, Artificial Intelligence, Reality Capture, Human Interface Systems, Immersive Experiences, Virtual Society, and Virtual Economy\n  - IEEE Standards Association has published governance recommendations addressing legal resources, control mechanisms, and copyright frameworks for digital assets\n  - Phased governance approaches differentiate between initial, growth, and mature stages of metaverse development, with varying compatibility and security requirements\n\n## Research & Literature\n\n- Key academic papers and sources\n  - Runde, C. (2025). ETSI Augmented Reality Framework (ARF): Virtual World Standards Recommendations Report. ETSI GR ARF 020. Published 25 October 2025. Available at: figshare.com/articles/book/ETSI_Augmented_Reality_Framework_ARF_Virtual_World_Standards_Recommendations_Report/30444941\n  - Nature Human Behaviour (2023). \"Recommendations for metaverse governance based on technical standards.\" Study investigating theoretical frameworks and policy implications for technical standards-based metaverse governance (TS-MG). DOI: 10.1038/s41599-023-01750-7\n  - IEEE Standards Association (2022). Metaverse and its Governance. Report addressing fragmentation in technology standards, legal guidelines, and legacy system management across metaverse implementations\n  - ACM Digital Library (2024). \"Will the metaverse be out of control? Addressing the ethical and...\" Examining novel ethical challenges presented by metaverse development and knowledge gaps regarding potential societal effects\n- Ongoing research directions\n  - Interoperability standards development across heterogeneous virtual world platforms\n  - Legal and regulatory harmonisation, particularly regarding GDPR compliance and digital asset ownership\n  - Ethical framework implementation and measurement of fairness, trust, and societal impact\n  - Human-centred design principles and inclusive stakeholder engagement in standards development\n\n## UK Context\n\n- British contributions and implementations\n  - ETSI's European standardisation mandate provides framework for UK participation through post-Brexit technical cooperation mechanisms\n  - UK technology sector engagement with Metaverse Standards Forum working groups remains limited in publicly available documentation\n- North England innovation potential\n  - Manchester's established digital technology cluster and media production infrastructure position it as potential hub for virtual world development and standards implementation\n  - Leeds and Sheffield possess emerging strengths in data management and AI governance, relevant to metaverse infrastructure layers\n  - Newcastle's digital innovation initiatives could contribute to human interface systems and accessibility standards development\n  - Regional universities (Manchester Metropolitan, Leeds Beckett, Sheffield Hallam) represent underutilised resources for metaverse ethics and governance research\n\n## Future Directions\n\n- Emerging trends and developments\n  - Shift from fragmented, proprietary systems towards interoperable, standards-based architectures requiring genuine cooperation between governments, standard-setting organisations, and enterprises\n  - Integration of ethical principles into technical standards from inception rather than as post-hoc considerations (though implementation remains inconsistent)\n  - Expansion of governance frameworks to address user-created content moderation, digital rights management, and virtual economy regulation\n- Anticipated challenges\n  - Balancing innovation velocity with regulatory oversight—a tension that standards bodies must navigate without stifling development\n  - Achieving genuine interoperability whilst maintaining security and preventing monopolistic control of standards formulation\n  - Addressing the \"legacy system problem\": existing platforms and infrastructure that predate standardisation efforts\n  - Ensuring meaningful stakeholder participation beyond technology companies, particularly from civil society and affected communities\n- Research priorities\n  - Empirical assessment of ethical framework effectiveness in deployed systems\n  - Longitudinal studies on societal impacts of metaverse adoption across different demographic groups\n  - Development of enforcement mechanisms for standards compliance\n  - Investigation of regional variations in governance approaches and their efficacy\n\n## References\n\n1. Runde, C. (2025). ETSI Augmented Reality Framework (ARF): Virtual World Standards Recommendations Report. ETSI GR ARF 020. Available at: figshare.com/articles/book/ETSI_Augmented_Reality_Framework_ARF_Virtual_World_Standards_Recommendations_Report/30444941\n\n2. Nature Human Behaviour (2023). \"Recommendations for metaverse governance based on technical standards.\" DOI: 10.1038/s41599-023-01750-7\n\n3. IEEE Standards Association (2022). Metaverse and its Governance. Available at: standards.ieee.org/wp-content/uploads/2022/06/XR_Metaverse_Governance.pdf\n\n4. ETSI (2025). ETSI GR ARF 010 V1.1.1 Virtual Worlds Standards Landscape Report. Available at: etsi.org\n\n5. ETSI (2024–2025). ETSI Work Programme 2024–2025. Available at: etsi.org/images/files/WorkProgramme/ETSI-Work-Programme-2024-2025.pdf\n\n6. ACM Digital Library (2024). \"Will the metaverse be out of control? Addressing the ethical and...\" DOI: 10.1145/3674148\n\n\n## Metadata\n\n- **Last Updated**: 2025-11-11\n- **Review Status**: Comprehensive editorial review\n- **Verification**: Academic sources verified\n- **Regional Context**: UK/North England where applicable",
  "properties": {
    "id": "etsi_domain_governance___ethics-ontology",
    "collapsed": "true",
    "- ontology": "true",
    "- term-id": "mv-1761742247921",
    "- preferred-term": "ETSI_Domain_Governance___Ethics",
    "- source-domain": "metaverse",
    "- status": "draft",
    "- public-access": "true"
  },
  "backlinks": [],
  "wiki_links": [],
  "ontology": {
    "term_id": "mv-1761742247921",
    "preferred_term": "ETSI_Domain_Governance___Ethics",
    "definition": "",
    "source_domain": "metaverse",
    "maturity_level": null,
    "authority_score": null
  }
}