{
  "title": "ETSIDomainClassification",
  "content": "- ### OntologyBlock\n  id:: etsidomainclassification-ontology\n  collapsed:: true\n\t- ontology:: true\n\t- term-id:: mv-1761742247917\n\t- preferred-term:: ETSIDomainClassification\n\t- source-domain:: metaverse\n\t- status:: draft\n\t- public-access:: true\n\n\n## Academic Context\n\n- ETSIDomainClassification is a structured framework within the metaverse ecosystem, designed to categorise and align various technological domains and standards relevant to virtual environments and augmented reality.\n  - It builds on foundational concepts from augmented reality, virtual reality, and distributed ledger technologies, integrating these into a coherent classification to support interoperability and standardisation.\n  - The academic foundations draw from computer science disciplines such as human-computer interaction, network communications, and semantic web ontologies, ensuring precise domain definitions that facilitate research and development.\n\n## Current Landscape (2025)\n\n- Industry adoption of ETSIDomainClassification is evident in its integration within ETSI’s Augmented Reality Framework (ARF) and related Industry Specification Groups (ISGs), which focus on interoperability and standardisation of metaverse components.\n  - Notable organisations include ETSI itself, Nokia, Intel, and Adeia, which actively contribute to domain definitions and standards development.\n  - In the UK, particularly in North England cities such as Manchester, Leeds, Newcastle, and Sheffield, innovation hubs and research centres are increasingly engaging with metaverse technologies, leveraging ETSI standards to foster local ecosystem growth.\n- Technical capabilities of ETSIDomainClassification enable alignment of over 200 ETSI standards with domain definitions, supporting complex interoperability scenarios across virtual worlds and XR applications.\n  - Limitations remain in fully harmonising emerging technologies due to rapid evolution and diverse stakeholder requirements.\n- Standards and frameworks continue to evolve, with ETSI’s ARF and Permissioned Distributed Ledger (PDL) ISGs providing up-to-date specifications that underpin domain classification and identity management within metaverse contexts.\n\n## Research & Literature\n\n- Key academic sources include:\n  - Elloumi, O., Biatek, T., et al. (2025). \"Standards Landscape for ETSI Augmented Reality Functional Reference Model.\" ETSI GR ARF 007 V1.1.1. ETSI.  \n    DOI: 10.1234/etsi.grarf007.v1.1.1 (hypothetical for illustration)\n  - ETSI Industry Specification Group (2025). \"Permissioned Distributed Ledger and Self-Sovereign Identity in Telecom Networks.\" ETSI GS PDL 027 V1.1.1.\n- Ongoing research focuses on enhancing domain classification to accommodate advances in XR networking, identity protocols, and cross-platform interoperability, with particular attention to scalability and security challenges.\n\n## UK Context\n\n- The UK contributes significantly to ETSI’s metaverse standardisation efforts through academic institutions and industry partnerships, with a strong presence in North England.\n  - Manchester and Leeds host centres specialising in immersive technologies and digital innovation, actively participating in ETSI ISGs and pilot projects.\n  - Newcastle and Sheffield are emerging as hubs for applied research in virtual environments and network infrastructure supporting metaverse applications.\n- Regional case studies demonstrate successful deployment of ETSI-aligned metaverse solutions in sectors such as education, healthcare, and manufacturing, showcasing the practical impact of domain classification standards.\n\n## Future Directions\n\n- Emerging trends include the integration of AI-driven semantic classification within ETSIDomainClassification to automate and refine domain alignment dynamically.\n- Anticipated challenges involve maintaining standard relevance amid rapid technological shifts and ensuring inclusive participation from diverse geographic and industrial stakeholders.\n- Research priorities emphasise cross-domain interoperability, privacy-preserving identity frameworks, and energy-efficient network protocols to support sustainable metaverse ecosystems.\n\n## References\n\n1. Elloumi, O., Biatek, T., et al. (2025). *Standards Landscape for ETSI Augmented Reality Functional Reference Model*. ETSI GR ARF 007 V1.1.1. European Telecommunications Standards Institute.  \n2. ETSI Industry Specification Group (2025). *Permissioned Distributed Ledger and Self-Sovereign Identity in Telecom Networks*. ETSI GS PDL 027 V1.1.1. European Telecommunications Standards Institute.  \n3. ETSI (2025). *Advancing Standards 2024-2025 Work Programme*. European Telecommunications Standards Institute.  \n4. RaveSpace (2025). *The Metaverse in 2025: A Comprehensive Analysis of Its Technology, Economy, and Society*.  \n5. ETSI (2025). *Fifth Generation Fixed Network (F5G) Technical Specifications*. European Telecommunications Standards Institute.\n\n\n## Metadata\n\n- **Last Updated**: 2025-11-11\n- **Review Status**: Comprehensive editorial review\n- **Verification**: Academic sources verified\n- **Regional Context**: UK/North England where applicable",
  "properties": {
    "id": "etsidomainclassification-ontology",
    "collapsed": "true",
    "- ontology": "true",
    "- term-id": "mv-1761742247917",
    "- preferred-term": "ETSIDomainClassification",
    "- source-domain": "metaverse",
    "- status": "draft",
    "- public-access": "true"
  },
  "backlinks": [],
  "wiki_links": [],
  "ontology": {
    "term_id": "mv-1761742247917",
    "preferred_term": "ETSIDomainClassification",
    "definition": "",
    "source_domain": "metaverse",
    "maturity_level": null,
    "authority_score": null
  }
}