{
  "title": "Executing all code blocks in a page",
  "content": "- ### OntologyBlock\n  id:: executing-all-code-blocks-in-a-page-ontology\n  collapsed:: true\n\t- ontology:: true\n\t- term-id:: mv-81010755883\n\t- preferred-term:: Executing all code blocks in a page\n\t- source-domain:: metaverse\n\t- status:: active\n\t- public-access:: true\n\t- definition:: A component of the metaverse ecosystem focusing on executing all code blocks in a page.\n\t- maturity:: mature\n\t- authority-score:: 0.85\n\t- owl:class:: mv:ExecutingAllCodeBlocksInAPage\n\t- owl:physicality:: ConceptualEntity\n\t- owl:role:: Concept\n\t- belongsToDomain:: [[MetaverseDomain]]\n\t- #### Relationships\n\t  id:: executing-all-code-blocks-in-a-page-relationships\n\t\t- enables:: [[ImmersiveExperience]], [[Presence]], [[SpatialComputing]]\n\t\t- requires:: [[DisplayTechnology]], [[TrackingSystem]], [[RenderingEngine]]\n\t\t- bridges-to:: [[HumanComputerInteraction]], [[ComputerVision]], [[Robotics]]\n\n\t- #### OWL Axioms\n\t  id:: executing-all-code-blocks-in-a-page-owl-axioms\n\t  collapsed:: true\n\t\t- ```clojure\n\t\t  Declaration(Class(mv:ExecutingAllCodeBlocksInAPage))\n\n\t\t  # Classification\n\t\t  SubClassOf(mv:ExecutingAllCodeBlocksInAPage mv:ConceptualEntity)\n\t\t  SubClassOf(mv:ExecutingAllCodeBlocksInAPage mv:Concept)\n\n\t\t  # Domain classification\n\t\t  SubClassOf(mv:ExecutingAllCodeBlocksInAPage\n\t\t    ObjectSomeValuesFrom(mv:belongsToDomain mv:MetaverseDomain)\n\t\t  )\n\n\t\t  # Annotations\n\t\t  AnnotationAssertion(rdfs:label mv:ExecutingAllCodeBlocksInAPage \"Executing all code blocks in a page\"@en)\n\t\t  AnnotationAssertion(rdfs:comment mv:ExecutingAllCodeBlocksInAPage \"A component of the metaverse ecosystem focusing on executing all code blocks in a page.\"@en)\n\t\t  AnnotationAssertion(dcterms:identifier mv:ExecutingAllCodeBlocksInAPage \"mv-81010755883\"^^xsd:string)\n\t\t  ```\n\n- {{evalpage}}\n- ## Javascript code block execution\n\t- ```javascript\n\t  return Math.random(); //da\n\t  ```\n\t\t- {{evalparent}}\n- ## Python multiple code block execution with global variable passing between blocks\n\t- Note global variable var1 is passed successfully to all the following code blocks\n\t- ```python\n\t  from random import random\n\t  global var1\n\t  var1=\"VAR1\"\n\t  def hello():\n\t    return \"Hi \" + var1\n\t  hello()\n\t  ```\n\t\t- {{evalparent}}\n\t- ```python\n\t  # test if var1 still exists\n\t  global var1\n\t  def hello2():\n\t    if var1 == \"VAR1\":\n\t      return \"var1 has been passed successfully from the previous code block\"\n\t    else:\n\t      return \"var1 did not get passed from the previous code block\"\n\t  hello2()\n\t  ```\n\t\t- {{evalparent}}\n\t- ```python\n\t  import sys\n\t  def run():\n\t  \treturn sys.version\n\t  run()\n\t  ```\n\t\t- {{evalparent}}\n\t- ```python\n\t  # test if var1 still exists\n\t  global var1\n\t  def hello3():\n\t    if var1 == \"VAR1\":\n\t      return \"var1 has been passed successfully from the previous code block\"\n\t    else:\n\t      return \"var1 did not get passed from the previous code block\"\n\t  hello2()\n\t  ```\n\t\t- {{evalparent}}\n\n## Current Landscape (2025)\n\n- Industry adoption and implementations\n  - Metaverse platforms continue to evolve with focus on interoperability and open standards\n  - Web3 integration accelerating with decentralised identity and asset ownership\n  - Enterprise adoption growing in virtual collaboration, training, and digital twins\n  - UK companies increasingly active in metaverse development and immersive technologies\n\n- Technical capabilities\n  - Real-time rendering at photorealistic quality levels\n  - Low-latency networking enabling seamless multi-user experiences\n  - AI-driven content generation and procedural world building\n  - Spatial audio and haptics enhancing immersion\n\n- UK and North England context\n  - Manchester: Digital Innovation Factory supports metaverse startups and research\n  - Leeds: Holovis leads in immersive experiences for entertainment and training\n  - Newcastle: University research in spatial computing and interactive systems\n  - Sheffield: Advanced manufacturing using digital twin technology\n\n- Standards and frameworks\n  - Metaverse Standards Forum driving interoperability protocols\n  - WebXR enabling browser-based immersive experiences\n  - glTF and USD for 3D asset interchange\n  - Open Metaverse Interoperability Group defining cross-platform standards\n\n## Metadata\n\n- **Last Updated**: 2025-11-16\n- **Review Status**: Automated remediation with 2025 context\n- **Verification**: Academic sources verified\n- **Regional Context**: UK/North England where applicable",
  "properties": {
    "id": "executing-all-code-blocks-in-a-page-owl-axioms",
    "collapsed": "true",
    "- ontology": "true",
    "- term-id": "mv-81010755883",
    "- preferred-term": "Executing all code blocks in a page",
    "- source-domain": "metaverse",
    "- status": "active",
    "- public-access": "true",
    "- definition": "A component of the metaverse ecosystem focusing on executing all code blocks in a page.",
    "- maturity": "mature",
    "- authority-score": "0.85",
    "- owl:class": "mv:ExecutingAllCodeBlocksInAPage",
    "- owl:physicality": "ConceptualEntity",
    "- owl:role": "Concept",
    "- belongsToDomain": "[[MetaverseDomain]]",
    "- enables": "[[ImmersiveExperience]], [[Presence]], [[SpatialComputing]]",
    "- requires": "[[DisplayTechnology]], [[TrackingSystem]], [[RenderingEngine]]",
    "- bridges-to": "[[HumanComputerInteraction]], [[ComputerVision]], [[Robotics]]"
  },
  "backlinks": [],
  "wiki_links": [
    "TrackingSystem",
    "ImmersiveExperience",
    "ComputerVision",
    "RenderingEngine",
    "SpatialComputing",
    "Robotics",
    "HumanComputerInteraction",
    "MetaverseDomain",
    "DisplayTechnology",
    "Presence"
  ],
  "ontology": {
    "term_id": "mv-81010755883",
    "preferred_term": "Executing all code blocks in a page",
    "definition": "A component of the metaverse ecosystem focusing on executing all code blocks in a page.",
    "source_domain": "metaverse",
    "maturity_level": null,
    "authority_score": 0.85
  }
}