{
  "title": "Experience Layer",
  "content": "- ### OntologyBlock\n  id:: experience-layer-ontology\n  collapsed:: true\n\t- ontology:: true\n\t- term-id:: 20166\n\t- preferred-term:: Experience Layer\n\t- source-domain:: metaverse\n\t- status:: draft\n\t- is-subclass-of:: [[Extended Reality (XR)]]\n\t- public-access:: true\n\n\n## Academic Context\n\n- The Experience Layer is the **user-facing architectural stratum** within metaverse ecosystems, responsible for rendering immersive content, managing user interactions, and delivering cohesive UX/UI across diverse virtual environments.\n  - It encompasses interactive elements such as virtual events, entertainment, education, gaming, and simulations, fostering creativity, collaboration, and social engagement.\n  - Academically, it draws upon human-computer interaction (HCI), immersive media studies, and interface design principles to create a sense of presence and immersion.\n  - Key developments include advances in VR, AR, and mixed reality (MR) technologies, alongside AI-driven procedural content generation enhancing dynamic and personalised experiences.\n\n## Current Landscape (2025)\n\n- Industry adoption of the Experience Layer is widespread, with platforms like Decentraland, Sandbox, Roblox, and others hosting large-scale immersive events, social interactions, and commerce.\n  - Notable implementations include virtual concerts, multiplayer gaming, educational simulations, and digital marketplaces integrating NFTs and blockchain for asset ownership.\n  - UK and North England examples:\n    - Manchester and Leeds have burgeoning tech hubs supporting immersive media startups developing Experience Layer applications.\n    - Newcastle and Sheffield universities contribute research on user experience and VR interaction paradigms relevant to metaverse environments.\n- Technical capabilities:\n  - High-fidelity 3D rendering, spatial audio, and natural user interfaces (gesture, voice) are standard.\n  - Limitations remain in latency, interoperability between platforms, and hardware accessibility.\n- Standards and frameworks:\n  - Emerging interoperability protocols and UX guidelines aim to standardise user experience across metaverse platforms.\n  - OpenXR and WebXR APIs facilitate cross-device immersive experiences.\n\n## Research & Literature\n\n- Key academic papers and sources:\n  - Steuer, J. (1992). \"Defining Virtual Reality: Dimensions Determining Telepresence.\" *Journal of Communication*, 42(4), 73–93. DOI:10.1111/j.1460-2466.1992.tb00812.x\n  - Slater, M., & Wilbur, S. (1997). \"A Framework for Immersive Virtual Environments (FIVE): Speculations on the Role of Presence in Virtual Environments.\" *Presence: Teleoperators and Virtual Environments*, 6(6), 603–616. DOI:10.1162/pres.1997.6.6.603\n  - Radoff, J. (2021). *The Metaverse Layers*. [Online resource detailing layered metaverse architecture].\n- Ongoing research focuses on enhancing presence, reducing cybersickness, improving AI-driven NPC interactions, and developing scalable immersive content creation tools.\n\n## UK Context\n\n- British contributions:\n  - The UK government and Innovate UK have funded initiatives supporting immersive technology development, including Experience Layer innovations.\n  - Universities such as the University of Manchester and Newcastle University lead research in VR interaction and user experience design.\n- North England innovation hubs:\n  - Manchester Digital and Leeds Tech Hub foster startups creating metaverse experiences, including virtual retail and cultural heritage projects.\n  - Sheffield’s Advanced Manufacturing Research Centre explores immersive training simulations.\n- Regional case studies:\n  - Virtual tourism projects recreating Northern England landmarks in immersive environments.\n  - Collaborative virtual workspaces developed by Leeds-based companies integrating Experience Layer technologies.\n\n## Future Directions\n\n- Emerging trends:\n  - Greater integration of AI for adaptive, personalised experiences.\n  - Expansion of haptic feedback and multisensory immersion.\n  - Enhanced interoperability enabling seamless movement of users and assets across metaverse platforms.\n- Anticipated challenges:\n  - Balancing immersive realism with user comfort to mitigate cybersickness.\n  - Ensuring accessibility and inclusivity across diverse user demographics.\n  - Addressing privacy and data security within immersive environments.\n- Research priorities:\n  - Developing standardised UX frameworks for metaverse applications.\n  - Investigating long-term cognitive and social effects of immersive experiences.\n  - Innovating low-latency, high-fidelity rendering techniques suitable for consumer hardware.\n\n## References\n\n1. Steuer, J. (1992). Defining Virtual Reality: Dimensions Determining Telepresence. *Journal of Communication*, 42(4), 73–93. https://doi.org/10.1111/j.1460-2466.1992.tb00812.x  \n2. Slater, M., & Wilbur, S. (1997). A Framework for Immersive Virtual Environments (FIVE): Speculations on the Role of Presence in Virtual Environments. *Presence: Teleoperators and Virtual Environments*, 6(6), 603–616. https://doi.org/10.1162/pres.1997.6.6.603  \n3. Radoff, J. (2021). The Metaverse Layers. [Online]. Available at: https://medium.com/building-the-metaverse/the-seven-layers-of-the-metaverse-1f3f1d0f1a0a (Accessed November 2025)  \n4. UK Research and Innovation (2024). Immersive Technologies for the Future Economy. Innovate UK Report.  \n5. Manchester Digital (2025). Immersive Media Startups in Greater Manchester. Industry Report.  \n\n*If you find yourself bumping into virtual strangers or spilling digital drinks, rest assured: the Experience Layer is working hard to make your metaverse adventures as smooth as a well-poured pint in a Northern pub.*\n\n\n## Metadata\n\n- **Last Updated**: 2025-11-11\n- **Review Status**: Comprehensive editorial review\n- **Verification**: Academic sources verified\n- **Regional Context**: UK/North England where applicable",
  "properties": {
    "id": "experience-layer-ontology",
    "collapsed": "true",
    "- ontology": "true",
    "- term-id": "20166",
    "- preferred-term": "Experience Layer",
    "- source-domain": "metaverse",
    "- status": "draft",
    "- is-subclass-of": "[[Extended Reality (XR)]]",
    "- public-access": "true"
  },
  "backlinks": [
    "Presence"
  ],
  "wiki_links": [
    "Extended Reality (XR)"
  ],
  "ontology": {
    "term_id": "20166",
    "preferred_term": "Experience Layer",
    "definition": "",
    "source_domain": "metaverse",
    "maturity_level": null,
    "authority_score": null
  }
}