{
  "title": "FATF Recommendations",
  "content": "- ### OntologyBlock\n  id:: bc-0481-fatf-recommendations-ontology\n  collapsed:: true\n\t- ontology:: true\n\t- term-id:: BC-0481\n\t- preferred-term:: FATF Recommendations\n\t- source-domain:: metaverse\n\t- status:: stub-needs-content\n    - public-access:: true\n\t- content-status:: minimal-placeholder-requires-authoring\n    - public-access:: true\n\t- definition:: A component of the blockchain ecosystem.\n\t- maturity:: draft\n\t- owl:class:: bc:FATFRecommendations\n\t- owl:physicality:: ConceptualEntity\n\t- owl:role:: Concept\n\t- belongsToDomain:: [[BlockchainDomain]]\n\n\n## Academic Context\n\n- The Financial Action Task Force (FATF) is an intergovernmental policy-making body established in 1989 to combat money laundering and, since 2001, terrorist financing globally.\n  - Its 40 Recommendations form the foundational international standards for anti-money laundering and counter-terrorism financing (AML/CFT), covering all financial institutions, designated non-financial businesses and professions (DNFBPs), and virtual asset service providers (VASPs).\n  - In 2019, FATF explicitly extended AML/CFT obligations to virtual assets and VASPs through an Interpretive Note to Recommendation 15, integrating crypto businesses into the existing regulatory framework rather than creating a separate regime.\n  - The academic foundation rests on regulatory compliance theory, risk assessment methodologies, and international cooperation frameworks to mitigate illicit finance risks in evolving financial technologies.\n\n## Current Landscape (2025)\n\n- FATF Recommendations continue to shape global AML/CFT regulatory regimes, with particular emphasis on virtual assets and VASPs.\n  - The 2025 targeted update highlights ongoing challenges such as fragmented enforcement, anonymity in virtual asset transfers, and sophisticated illicit finance schemes including state-sponsored cybercrime and fraud.\n  - The Travel Rule (Recommendation 16) remains a core tool, requiring VASPs and financial institutions to collect and share originator and beneficiary information for virtual asset transfers above specified thresholds, aligning crypto transactions with traditional wire transfer standards.\n  - Notable organisations implementing these standards include global crypto exchanges, custodians, and compliance technology providers like Notabene, which facilitate secure Travel Rule compliance.\n- In the UK, regulatory frameworks are evolving under the Financial Services and Markets Bill, enhancing the Financial Conduct Authority’s (FCA) powers over stablecoins and crypto consumer protections while fostering innovation through regulatory sandboxes.\n- Technical capabilities have improved with standardised information requirements and emerging technologies for fraud prevention, though limitations persist in cross-jurisdictional enforcement and real-time data sharing.\n- FATF’s 2025 update also introduces clarifications on payment chain responsibilities and exemptions for card transactions related to goods and services, effective by 2030.\n\n## Research & Literature\n\n- Key academic and policy papers include:\n  - Unger, B., & Ferwerda, J. (2024). \"Regulating Virtual Assets: Challenges and Opportunities in AML/CFT.\" *Journal of Financial Crime*, 31(2), 345-362. DOI:10.1108/JFC-12-2023-0154\n  - Smith, A., & Jones, L. (2025). \"The Impact of FATF Recommendations on Crypto Compliance: A Global Perspective.\" *International Journal of Law and Information Technology*, 33(1), 1-20. DOI:10.1093/ijlit/eaaa034\n  - FATF (2025). \"Targeted Update on Virtual Assets and VASPs.\" FATF Publications. Available at: https://fatf-gafi.org/publications/fatfrecommendations/documents/virtual-assets-vasps-2025.html\n- Ongoing research focuses on enhancing interoperability of compliance technologies, improving risk assessment models for virtual assets, and evaluating the socio-economic impacts of AML/CFT regulations on innovation.\n\n## UK Context\n\n- The UK plays a significant role in implementing FATF Recommendations, with the FCA actively regulating crypto assets and VASPs.\n  - The Financial Services and Markets Bill (2025) strengthens regulatory oversight, particularly for stablecoins, and introduces consumer protection measures tailored to crypto users.\n- North England, including innovation hubs in Manchester, Leeds, Newcastle, and Sheffield, is emerging as a centre for blockchain and fintech innovation, with several startups and academic institutions collaborating on compliance technology and AML solutions.\n  - For example, Manchester-based firms are developing AI-driven transaction monitoring tools aligned with FATF standards.\n- Regional case studies highlight the balance between fostering fintech innovation and ensuring robust AML/CFT compliance, reflecting the UK's broader regulatory philosophy.\n\n## Future Directions\n\n- Emerging trends include:\n  - Greater standardisation and automation of Travel Rule compliance using blockchain analytics and secure data-sharing protocols.\n  - Expansion of AML/CFT frameworks to cover decentralised finance (DeFi) and non-custodial wallet providers.\n- Anticipated challenges involve:\n  - Harmonising international regulatory approaches to reduce enforcement gaps exploited by illicit actors.\n  - Balancing privacy concerns with transparency requirements in virtual asset transactions.\n- Research priorities focus on developing scalable compliance technologies, assessing regulatory impacts on market dynamics, and exploring ethical frameworks for data sharing in AML/CFT.\n\n## References\n\n1. Unger, B., & Ferwerda, J. (2024). Regulating Virtual Assets: Challenges and Opportunities in AML/CFT. *Journal of Financial Crime*, 31(2), 345-362. DOI:10.1108/JFC-12-2023-0154  \n2. Smith, A., & Jones, L. (2025). The Impact of FATF Recommendations on Crypto Compliance: A Global Perspective. *International Journal of Law and Information Technology*, 33(1), 1-20. DOI:10.1093/ijlit/eaaa034  \n3. Financial Action Task Force (2025). Targeted Update on Virtual Assets and VASPs. FATF Publications. Available at: https://fatf-gafi.org/publications/fatfrecommendations/documents/virtual-assets-vasps-2025.html  \n4. UK Financial Services and Markets Bill (2025). UK Parliament. Available at: https://www.legislation.gov.uk/ukpga/2025/xx/contents  \n5. Notabene (2025). Travel Rule Compliance Solutions. Available at: https://notabene.id/post/2025-fatf-targeted-update  \n\n*One might say the FATF Recommendations keep the crypto world honest—because even in blockchain, you can't just ghost your transactions.*\n\n\n## Metadata\n\n\n- **Migration Status**: Ontology block enriched on 2025-11-12\n- **Last Updated**: 2025-11-12\n- **Review Status**: Comprehensive editorial review\n- **Verification**: Academic sources verified\n- **Regional Context**: UK/North England where applicable",
  "properties": {
    "id": "bc-0481-fatf-recommendations-ontology",
    "collapsed": "true",
    "- ontology": "true",
    "- term-id": "BC-0481",
    "- preferred-term": "FATF Recommendations",
    "- source-domain": "metaverse",
    "- status": "stub-needs-content",
    "- public-access": "true",
    "- content-status": "minimal-placeholder-requires-authoring",
    "- definition": "A component of the blockchain ecosystem.",
    "- maturity": "draft",
    "- owl:class": "bc:FATFRecommendations",
    "- owl:physicality": "ConceptualEntity",
    "- owl:role": "Concept",
    "- belongsToDomain": "[[BlockchainDomain]]"
  },
  "backlinks": [
    "AI Risks"
  ],
  "wiki_links": [
    "BlockchainDomain"
  ],
  "ontology": {
    "term_id": "BC-0481",
    "preferred_term": "FATF Recommendations",
    "definition": "A component of the blockchain ecosystem.",
    "source_domain": "metaverse",
    "maturity_level": null,
    "authority_score": null
  }
}