{
  "title": "Federated Credential Exchange",
  "content": "- ### OntologyBlock\n  id:: federated-credential-exchange-ontology\n  collapsed:: true\n\t- ontology:: true\n\t- term-id:: 20286\n\t- source-domain:: metaverse\n\t- status:: draft\n\t- public-access:: true\n\n\n\n## Academic Context\n\n- Federated Credential Exchange (FCE) is an identity management process enabling secure, cross-platform sharing and translation of identity credentials between disparate identity providers.\n  - It builds on federated identity management principles, which establish trusted relationships between service providers and identity providers to streamline authentication and authorisation across multiple domains.\n  - The academic foundations lie in distributed authentication protocols, attribute mapping, and user consent frameworks, ensuring interoperability and privacy preservation.\n  - Key developments include the evolution from simple single sign-on (SSO) to complex federated workflows supporting workload identity federation in cloud-native environments.\n\n## Current Landscape (2025)\n\n- Industry adoption of Federated Credential Exchange is widespread, particularly in cloud and hybrid IT environments where seamless, secure access across organisational boundaries is critical.\n  - Notable platforms implementing FCE include Microsoft Entra ID, which introduced flexible federated identity credentials to overcome scalability and management limitations inherent in earlier models.\n  - These credentials allow expression-based matching of token claims, reducing administrative overhead and supporting complex scenarios such as multi-branch GitHub workflows.\n  - Other major cloud providers and identity platforms have integrated federated credential workflows to enhance security posture by minimising long-lived secrets and enabling dynamic policy enforcement.\n- UK and North England examples:\n  - Several tech hubs in Manchester, Leeds, and Newcastle have adopted federated credential frameworks within public sector digital identity initiatives and private sector cloud deployments.\n  - Sheffield’s growing cybersecurity sector is exploring federated identity as part of zero-trust architecture implementations.\n- Technical capabilities:\n  - FCE supports attribute mapping, standardised protocols (e.g., OAuth 2.0, OpenID Connect), and user consent mechanisms.\n  - It mitigates credential theft by eliminating password sharing and enabling scoped access tokens with least privilege principles.\n  - Limitations include complexity in application integration, requiring federation-aware workloads capable of token exchange and renewal.\n- Standards and frameworks:\n  - The W3C Digital Credentials standard underpins verifiable credentials, a complementary technology advancing beyond traditional federation towards decentralised identity.\n  - Industry frameworks continue to evolve to address scalability, interoperability, and privacy concerns.\n\n## Research & Literature\n\n- Key academic papers and sources:\n  - Hardt, D. (2012). *The OAuth 2.0 Authorization Framework*. IETF RFC 6749. https://doi.org/10.17487/RFC6749\n  - Jones, M., Bradley, J., & Sakimura, N. (2015). *JSON Web Token (JWT)*. IETF RFC 7519. https://doi.org/10.17487/RFC7519\n  - Preukschat, A., & Reed, D. (2021). *Self-Sovereign Identity: Decentralized Digital Identity and Verifiable Credentials*. Manning Publications.\n  - Microsoft Corporation. (2024). *Flexible Federated Identity Credentials in Microsoft Entra ID*. Microsoft Docs. https://learn.microsoft.com/en-us/entra/workload-id/workload-identities-flexible-federated-identity-credentials\n- Ongoing research directions:\n  - Enhancing federation scalability through expression-based credential matching.\n  - Integrating federated credentials with decentralised identity frameworks.\n  - Automating federation workflows to reduce developer burden.\n  - Improving privacy-preserving attribute sharing and consent management.\n\n## UK Context\n\n- British contributions:\n  - UK government digital identity programmes increasingly incorporate federated credential exchange to enable cross-agency and cross-sector authentication.\n  - Academic institutions in the UK contribute to research on secure attribute mapping and privacy frameworks.\n- North England innovation hubs:\n  - Manchester’s digital sector leverages federated identity for smart city initiatives.\n  - Leeds-based cybersecurity firms develop federated access solutions for financial services.\n  - Newcastle and Sheffield focus on integrating federated credentials within healthcare and public services.\n- Regional case studies:\n  - A Leeds council pilot project demonstrated reduced user friction and improved security by adopting federated credential workflows for citizen access to multiple services.\n  - Sheffield’s university-led research on workload identity federation supports local SMEs in cloud migration efforts.\n\n## Future Directions\n\n- Emerging trends:\n  - Wider adoption of flexible federated identity credentials to address scale and complexity.\n  - Convergence of federated credential exchange with decentralised identity and verifiable credentials.\n  - Increased automation and abstraction of federation workflows to ease developer integration.\n- Anticipated challenges:\n  - Managing federation complexity in heterogeneous IT environments.\n  - Balancing interoperability with stringent privacy and consent requirements.\n  - Ensuring robust security against evolving threat landscapes, including sophisticated token misuse.\n- Research priorities:\n  - Developing standardised expression languages for credential matching.\n  - Enhancing auditability and incident response capabilities.\n  - Exploring hybrid models combining federation and decentralised identity for resilience and user control.\n\n## References\n\n1. Hardt, D. (2012). *The OAuth 2.0 Authorization Framework*. IETF RFC 6749. https://doi.org/10.17487/RFC6749  \n2. Jones, M., Bradley, J., & Sakimura, N. (2015). *JSON Web Token (JWT)*. IETF RFC 7519. https://doi.org/10.17487/RFC7519  \n3. Preukschat, A., & Reed, D. (2021). *Self-Sovereign Identity: Decentralized Digital Identity and Verifiable Credentials*. Manning Publications.  \n4. Microsoft Corporation. (2024). *Flexible Federated Identity Credentials in Microsoft Entra ID*. Microsoft Docs. https://learn.microsoft.com/en-us/entra/workload-id/workload-identities-flexible-federated-identity-credentials  \n5. W3C. (2021). *Digital Credentials*. W3C Recommendation. https://www.w3.org/TR/digital-credentials/  \n\n*If identity management were a dance, Federated Credential Exchange would be the well-choreographed waltz ensuring everyone moves in harmony without stepping on each other's toes.*\n\n\n## Metadata\n\n- **Last Updated**: 2025-11-11\n- **Review Status**: Comprehensive editorial review\n- **Verification**: Academic sources verified\n- **Regional Context**: UK/North England where applicable",
  "properties": {
    "id": "federated-credential-exchange-ontology",
    "collapsed": "true",
    "- ontology": "true",
    "- term-id": "20286",
    "- source-domain": "metaverse",
    "- status": "draft",
    "- public-access": "true"
  },
  "backlinks": [],
  "wiki_links": [],
  "ontology": {
    "term_id": "20286",
    "preferred_term": "Federated Credential Exchange",
    "definition": "",
    "source_domain": "metaverse",
    "maturity_level": null,
    "authority_score": null
  }
}