{
  "title": "Feedforward Neural Network",
  "content": "- ### OntologyBlock\n  id:: feedforward-neural-network-ontology\n  collapsed:: true\n\t- ontology:: true\n\t- term-id:: AI-0031\n\t- preferred-term:: Feedforward Neural Network\n\t- source-domain:: ai\n\t- status:: draft\n\t- public-access:: true\n\n\n## Academic Context\n\n- Feedforward Neural Networks (FNNs) are a foundational type of artificial neural network characterised by unidirectional data flow from input to output layers without cycles or feedback loops.\n  - They consist of an input layer, one or more hidden layers, and an output layer, with each neuron in a layer fully connected to neurons in the subsequent layer.\n  - The network learns by adjusting connection weights through optimisation algorithms such as gradient descent, minimising a loss function that quantifies prediction errors.\n  - Activation functions like ReLU, sigmoid, or tanh introduce non-linearity, enabling the modelling of complex patterns beyond linear relationships.\n- Academically, FNNs underpin many developments in machine learning and deep learning, serving as the conceptual basis for more complex architectures like convolutional and recurrent neural networks.\n\n## Current Landscape (2025)\n\n- FNNs remain widely used for pattern recognition tasks including image and speech classification, credit scoring, and regression problems.\n  - Their simplicity and interpretability make them a preferred choice for baseline models and educational purposes.\n- Notable organisations employing FNNs include technology firms, financial institutions, and healthcare analytics companies.\n  - In the UK, several AI research centres and companies in Manchester, Leeds, Newcastle, and Sheffield integrate FNNs within broader AI solutions, particularly in sectors such as finance, healthcare, and manufacturing.\n- Technical capabilities:\n  - FNNs excel at modelling static data but are limited in handling sequential or temporal data due to their lack of feedback connections.\n  - They are computationally less intensive than recurrent or convolutional networks but may require careful tuning to avoid overfitting or underfitting.\n- Standards and frameworks supporting FNN development include TensorFlow, PyTorch, and ONNX, which facilitate model interoperability and deployment.\n\n## Research & Literature\n\n- Key academic papers:\n  - Rumelhart, D.E., Hinton, G.E., & Williams, R.J. (1986). Learning representations by back-propagating errors. *Nature*, 323(6088), 533–536. DOI:10.1038/323533a0\n  - Cybenko, G. (1989). Approximation by superpositions of a sigmoidal function. *Mathematics of Control, Signals and Systems*, 2(4), 303–314. DOI:10.1007/BF02551274\n  - Goodfellow, I., Bengio, Y., & Courville, A. (2016). *Deep Learning*. MIT Press. [Available online]\n- Ongoing research explores:\n  - Enhancing FNN architectures with novel activation functions and optimisation techniques.\n  - Hybrid models combining FNNs with convolutional or recurrent layers for improved performance.\n  - Explainability and robustness of FNNs in safety-critical applications.\n\n## UK Context\n\n- The UK has made significant contributions to neural network research, with institutions like the University of Manchester historically pivotal in AI development.\n- North England hosts innovation hubs in Manchester, Leeds, Newcastle, and Sheffield, where AI startups and academic groups apply FNNs in healthcare diagnostics, financial risk assessment, and industrial automation.\n- Regional case studies include:\n  - Manchester-based AI firms using FNNs for predictive maintenance in manufacturing.\n  - Leeds research groups developing FNN-based models for medical image analysis.\n  - Newcastle initiatives applying FNNs in environmental data modelling.\n\n## Future Directions\n\n- Emerging trends:\n  - Integration of FNNs within larger, multi-modal AI systems.\n  - Development of energy-efficient FNN models suitable for edge computing.\n  - Advances in automated machine learning (AutoML) to optimise FNN architectures without extensive human intervention.\n- Anticipated challenges:\n  - Balancing model complexity with interpretability.\n  - Ensuring fairness and mitigating bias in FNN-based decision systems.\n  - Scaling FNNs for increasingly large and complex datasets.\n- Research priorities focus on improving generalisation, robustness to adversarial inputs, and seamless integration with other AI paradigms.\n\n## References\n\n1. Rumelhart, D.E., Hinton, G.E., & Williams, R.J. (1986). Learning representations by back-propagating errors. *Nature*, 323(6088), 533–536. DOI:10.1038/323533a0  \n2. Cybenko, G. (1989). Approximation by superpositions of a sigmoidal function. *Mathematics of Control, Signals and Systems*, 2(4), 303–314. DOI:10.1007/BF02551274  \n3. Goodfellow, I., Bengio, Y., & Courville, A. (2016). *Deep Learning*. MIT Press.  \n4. Milvus. (2025). What is a feedforward neural network? Retrieved November 2025, from https://milvus.io/ai-quick-reference/what-is-a-feedforward-neural-network  \n5. GeeksforGeeks. (2025). Feedforward Neural Network. Retrieved July 2025, from https://www.geeksforgeeks.org/deep-learning/feedforward-neural-network/\n\n\n## Metadata\n\n- **Last Updated**: 2025-11-11\n- **Review Status**: Comprehensive editorial review\n- **Verification**: Academic sources verified\n- **Regional Context**: UK/North England where applicable",
  "properties": {
    "id": "feedforward-neural-network-ontology",
    "collapsed": "true",
    "- ontology": "true",
    "- term-id": "AI-0031",
    "- preferred-term": "Feedforward Neural Network",
    "- source-domain": "ai",
    "- status": "draft",
    "- public-access": "true"
  },
  "backlinks": [
    "Recurrent Neural Network"
  ],
  "wiki_links": [],
  "ontology": {
    "term_id": "AI-0031",
    "preferred_term": "Feedforward Neural Network",
    "definition": "",
    "source_domain": "ai",
    "maturity_level": null,
    "authority_score": null
  }
}