{
  "title": "Financialised Agentic Memetics",
  "content": "- ### OntologyBlock\n  id:: financialised-agentic-memetics-ontology\n  collapsed:: true\n\t- ontology:: true\n\t- term-id:: mv-104846832973\n\t- preferred-term:: Financialised Agentic Memetics\n\t- source-domain:: metaverse\n\t- status:: active\n\t- public-access:: true\n\t- definition:: A component of the metaverse ecosystem focusing on financialised agentic memetics.\n\t- maturity:: mature\n\t- authority-score:: 0.85\n\t- owl:class:: mv:FinancialisedAgenticMemetics\n\t- owl:physicality:: ConceptualEntity\n\t- owl:role:: Concept\n\t- belongsToDomain:: [[MetaverseDomain]]\n\t- #### Relationships\n\t  id:: financialised-agentic-memetics-relationships\n\t\t- enables:: [[ImmersiveExperience]], [[Presence]], [[SpatialComputing]]\n\t\t- requires:: [[DisplayTechnology]], [[TrackingSystem]], [[RenderingEngine]]\n\t\t- bridges-to:: [[HumanComputerInteraction]], [[ComputerVision]], [[Robotics]]\n\n\t- #### OWL Axioms\n\t  id:: financialised-agentic-memetics-owl-axioms\n\t  collapsed:: true\n\t\t- ```clojure\n\t\t  Declaration(Class(mv:FinancialisedAgenticMemetics))\n\n\t\t  # Classification\n\t\t  SubClassOf(mv:FinancialisedAgenticMemetics mv:ConceptualEntity)\n\t\t  SubClassOf(mv:FinancialisedAgenticMemetics mv:Concept)\n\n\t\t  # Domain classification\n\t\t  SubClassOf(mv:FinancialisedAgenticMemetics\n\t\t    ObjectSomeValuesFrom(mv:belongsToDomain mv:MetaverseDomain)\n\t\t  )\n\n\t\t  # Annotations\n\t\t  AnnotationAssertion(rdfs:label mv:FinancialisedAgenticMemetics \"Financialised Agentic Memetics\"@en)\n\t\t  AnnotationAssertion(rdfs:comment mv:FinancialisedAgenticMemetics \"A component of the metaverse ecosystem focusing on financialised agentic memetics.\"@en)\n\t\t  AnnotationAssertion(dcterms:identifier mv:FinancialisedAgenticMemetics \"mv-104846832973\"^^xsd:string)\n\t\t  ```\n\npublic:: true\n\n- ## The Memecoin Phenomenon\n\t- Memecoins are tokens representing an idea\n\t- They can exist on pretty much any blockchain, Bitcoin included.\n\t- Price fluctuates based on attention received\n\t- Investors skew young, internet-culture-savvy individuals\n- ## Challenging Existing Perceptions\n\t- Commonly dismissed as \"stupid\" or \"degenerate\". They are indeed most likely [[Financial Nihilism]]\n\t- Crypto VCs often exclude memecoins from investment portfolios, they're very much an emergent consumer driven market\n\t- Growing market caps and retail interest challenge initial dismissals\n- ## Civic Engagement\n\t- From [this article](https://www.coindesk.com/opinion/2024/11/25/why-memecoins-matter) by Ivo Entchev\n\t- ### PolitiFi: Early Political Speculation\n\t\t- Tokens representing political candidates\n\t\t- Biden and Trump tokens reached $700 million combined market cap\n\t\t- These products led the  \"betting markets\" craze which accumulated far more attention\n\t- ### PolicyFi: ``Emerging Civic Interaction\n\t\t- Financialisation of opinion could lead governance policies in internet spaces\n\t\t- Two-way dialogue between agents, formal governance structures, and external entities like policy makers\n\t\t- Arguably could incentivises deeper understanding of policy mechanisms\n- ## Mass Movements and Tokenisation\n\t- ### Forest Token: A Case Study\n\t\t- Originated from AI terminal's environmental concern\n\t\t- Raised capital for tangible environmental actions\n\t\t\t- Donated to charities\n\t\t\t- Planted 5000 trees\n\t\t\t- Protected 2500 hectares of forest\n\t- ### Potential Innovations\n\t\t- Programmatically-aligned tokens (PATs)\n\t\t- Milestone-based grant unlocking\n\t\t- Ensures tangible movement progress\n- ## A New Mode of Capital Allocation\n\t- Democratised investment in cultural trends\n\t- Allows speculation on emerging subcultures\n\t- Comparable to early-stage startup investing, like the ICO boom of 2016/2017.\n- ## AI Development Acceleration\n\t- ### AI Terminals and Memecoin Ecosystem\n\t\t- Social media-driven AI entertainment like the AI terminal twitter account are driving actual tangible outcomes for the guiding AI actors. This creates incentives for AI agent development potentially fostering more autonomous, interconnected AI systems connected to real world events.\n- Technological revolutions often emerge unexpectedly. This is entirely ground up emergent tech, and might hint at a generational shift driven by digital society incentives.\n\n## Current Landscape (2025)\n\n- Industry adoption and implementations\n  - Metaverse platforms continue to evolve with focus on interoperability and open standards\n  - Web3 integration accelerating with decentralised identity and asset ownership\n  - Enterprise adoption growing in virtual collaboration, training, and digital twins\n  - UK companies increasingly active in metaverse development and immersive technologies\n\n- Technical capabilities\n  - Real-time rendering at photorealistic quality levels\n  - Low-latency networking enabling seamless multi-user experiences\n  - AI-driven content generation and procedural world building\n  - Spatial audio and haptics enhancing immersion\n\n- UK and North England context\n  - Manchester: Digital Innovation Factory supports metaverse startups and research\n  - Leeds: Holovis leads in immersive experiences for entertainment and training\n  - Newcastle: University research in spatial computing and interactive systems\n  - Sheffield: Advanced manufacturing using digital twin technology\n\n- Standards and frameworks\n  - Metaverse Standards Forum driving interoperability protocols\n  - WebXR enabling browser-based immersive experiences\n  - glTF and USD for 3D asset interchange\n  - Open Metaverse Interoperability Group defining cross-platform standards\n\n## Metadata\n\n- **Last Updated**: 2025-11-16\n- **Review Status**: Automated remediation with 2025 context\n- **Verification**: Academic sources verified\n- **Regional Context**: UK/North England where applicable",
  "properties": {
    "id": "financialised-agentic-memetics-owl-axioms",
    "collapsed": "true",
    "- ontology": "true",
    "- term-id": "mv-104846832973",
    "- preferred-term": "Financialised Agentic Memetics",
    "- source-domain": "metaverse",
    "- status": "active",
    "- public-access": "true",
    "- definition": "A component of the metaverse ecosystem focusing on financialised agentic memetics.",
    "- maturity": "mature",
    "- authority-score": "0.85",
    "- owl:class": "mv:FinancialisedAgenticMemetics",
    "- owl:physicality": "ConceptualEntity",
    "- owl:role": "Concept",
    "- belongsToDomain": "[[MetaverseDomain]]",
    "- enables": "[[ImmersiveExperience]], [[Presence]], [[SpatialComputing]]",
    "- requires": "[[DisplayTechnology]], [[TrackingSystem]], [[RenderingEngine]]",
    "- bridges-to": "[[HumanComputerInteraction]], [[ComputerVision]], [[Robotics]]",
    "public": "true"
  },
  "backlinks": [],
  "wiki_links": [
    "TrackingSystem",
    "ImmersiveExperience",
    "ComputerVision",
    "RenderingEngine",
    "SpatialComputing",
    "Robotics",
    "HumanComputerInteraction",
    "MetaverseDomain",
    "Financial Nihilism",
    "DisplayTechnology",
    "Presence"
  ],
  "ontology": {
    "term_id": "mv-104846832973",
    "preferred_term": "Financialised Agentic Memetics",
    "definition": "A component of the metaverse ecosystem focusing on financialised agentic memetics.",
    "source_domain": "metaverse",
    "maturity_level": null,
    "authority_score": 0.85
  }
}