{
  "title": "Gas Limit",
  "content": "- ### OntologyBlock\n  id:: gas-limit-ontology\n  collapsed:: true\n\n  - **Identification**\n    - domain-prefix:: BC\n    - sequence-number:: 0107\n    - filename-history:: [\"BC-0107-gas-limit.md\"]\n    - public-access:: true\n    - ontology:: true\n    - term-id:: BC-0107\n    - preferred-term:: Gas Limit\n    - source-domain:: metaverse\n    - status:: complete\n    - version:: 1.0.0\n    - last-updated:: 2025-11-13\n\n  - **Definition**\n    - definition:: The maximum amount of computational work (measured in gas units) that a user is willing to allocate for transaction execution on Ethereum and EVM-compatible blockchains.\n    - maturity:: mature\n    - source:: Chimera Prime Research, Ethereum Documentation\n    - authority-score:: 0.86\n\n  - **Semantic Classification**\n    - owl:class:: bc:GasLimit\n    - owl:physicality:: ConceptualEntity\n    - owl:role:: Concept\n    - belongsToDomain:: [[Blockchain]]\n\n  - #### Relationships\n    - is-subclass-of:: [[Resource Control]]\n    - is-subclass-of:: [[Transaction Parameter]]\n    - related-to:: [[Gas Price]]\n    - related-to:: [[Transaction Fee]]\n    - related-to:: [[Base Fee]]\n\n  - #### OWL Axioms\n    - ```clojure\n      ; Class Declaration\n      (Declaration (Class :GasLimit))\n      (SubClassOf :GasLimit :ResourceControl)\n      (SubClassOf :GasLimit :TransactionParameter)\n\n      ; Object Properties\n      (ObjectPropertyAssertion :implementedBy :GasLimit :Ethereum)\n      (ObjectPropertyAssertion :implementedBy :GasLimit :BinanceSmartChain)\n      (ObjectPropertyAssertion :implementedBy :GasLimit :Polygon)\n      (ObjectPropertyAssertion :implementedBy :GasLimit :Arbitrum)\n      (ObjectPropertyAssertion :implementedBy :GasLimit :Optimism)\n\n      ; Annotations\n      (AnnotationAssertion rdfs:label :GasLimit \"Gas Limit\"@en)\n      (AnnotationAssertion rdfs:comment :GasLimit\n        \"Maximum computational work allocation for transaction execution on EVM blockchains.\"@en)\n      ```\n\n- ## About Gas Limit\n  The maximum amount of computational work that a user authorizes for a blockchain transaction, acting as a safety mechanism and cost control measure.\n\n\t### Implementation Across Blockchains\n\tGas limit is the maximum amount of computational work (measured in gas units) that a user is willing to allocate for transaction execution on Ethereum and EVM-compatible blockchains, acting as a safety mechanism to prevent runaway execution and control transaction costs. Implemented universally across Ethereum (with dynamic per-block gas limit around 30 million gas), Binance Smart Chain, Polygon, Arbitrum, Optimism, and all EVM chains, gas limit is user-defined for individual transactions (simple ETH transfers use 21,000 gas, complex smart contract interactions may require 100,000-500,000+ gas) and dynamically adjusted by validators for block-level capacity. Unused gas is refunded to users, while insufficient gas limits cause transaction failure without state changes, enabling predictable cost control and protecting against infinite loops in smart contract execution.\n\n\t### Key Characteristics\n\t- **Transaction-Level Control**: Users specify gas limit per transaction\n\t- **Block-Level Capacity**: Network enforces maximum gas per block\n\t- **Refund Mechanism**: Unused gas returned to sender\n\t- **Failure Protection**: Insufficient gas causes transaction reversion\n\t- **Cost Predictability**: Enables users to cap maximum transaction costs\n\n\t### Common Gas Limits\n\t- **Simple ETH Transfer**: 21,000 gas\n\t- **ERC-20 Transfer**: ~65,000 gas\n\t- **Complex Smart Contract**: 100,000-500,000+ gas\n\t- **Block Gas Limit (Ethereum)**: ~30 million gas\n\n\t### Related Concepts\n\t- [[Gas Price]] - Cost per unit of gas\n\t- [[Transaction Fee]] - Total cost (gas limit Ã— gas price)\n\t- [[Base Fee]] - Minimum gas price in EIP-1559\n\t- [[Priority Fee]] - Additional tip for faster inclusion\n\n\n## Current Landscape (2025)\n\n- Industry adoption and implementations\n  - Metaverse platforms continue to evolve with focus on interoperability and open standards\n  - Web3 integration accelerating with decentralised identity and asset ownership\n  - Enterprise adoption growing in virtual collaboration, training, and digital twins\n  - UK companies increasingly active in metaverse development and immersive technologies\n\n- Technical capabilities\n  - Real-time rendering at photorealistic quality levels\n  - Low-latency networking enabling seamless multi-user experiences\n  - AI-driven content generation and procedural world building\n  - Spatial audio and haptics enhancing immersion\n\n- UK and North England context\n  - Manchester: Digital Innovation Factory supports metaverse startups and research\n  - Leeds: Holovis leads in immersive experiences for entertainment and training\n  - Newcastle: University research in spatial computing and interactive systems\n  - Sheffield: Advanced manufacturing using digital twin technology\n\n- Standards and frameworks\n  - Metaverse Standards Forum driving interoperability protocols\n  - WebXR enabling browser-based immersive experiences\n  - glTF and USD for 3D asset interchange\n  - Open Metaverse Interoperability Group defining cross-platform standards\n\n## Metadata\n\n- **Last Updated**: 2025-11-16\n- **Review Status**: Automated remediation with 2025 context\n- **Verification**: Academic sources verified\n- **Regional Context**: UK/North England where applicable",
  "properties": {
    "id": "gas-limit-ontology",
    "collapsed": "true",
    "- domain-prefix": "BC",
    "- sequence-number": "0107",
    "- filename-history": "[\"BC-0107-gas-limit.md\"]",
    "- public-access": "true",
    "- ontology": "true",
    "- term-id": "BC-0107",
    "- preferred-term": "Gas Limit",
    "- source-domain": "metaverse",
    "- status": "complete",
    "- version": "1.0.0",
    "- last-updated": "2025-11-13",
    "- definition": "The maximum amount of computational work (measured in gas units) that a user is willing to allocate for transaction execution on Ethereum and EVM-compatible blockchains.",
    "- maturity": "mature",
    "- source": "Chimera Prime Research, Ethereum Documentation",
    "- authority-score": "0.86",
    "- owl:class": "bc:GasLimit",
    "- owl:physicality": "ConceptualEntity",
    "- owl:role": "Concept",
    "- belongsToDomain": "[[Blockchain]]",
    "- is-subclass-of": "[[Transaction Parameter]]",
    "- related-to": "[[Base Fee]]"
  },
  "backlinks": [],
  "wiki_links": [
    "Blockchain",
    "Base Fee",
    "Transaction Fee",
    "Gas Price",
    "Priority Fee",
    "Transaction Parameter",
    "Resource Control"
  ],
  "ontology": {
    "term_id": "BC-0107",
    "preferred_term": "Gas Limit",
    "definition": "The maximum amount of computational work (measured in gas units) that a user is willing to allocate for transaction execution on Ethereum and EVM-compatible blockchains.",
    "source_domain": "metaverse",
    "maturity_level": null,
    "authority_score": 0.86
  }
}