{
  "title": "General Purpose AI Model",
  "content": "- ### OntologyBlock\n  id:: general-purpose-ai-model-ontology\n  collapsed:: true\n\t- ontology:: true\n\t- term-id:: mv-1761742247928\n\t- preferred-term:: General Purpose AI Model\n\t- source-domain:: metaverse\n\t- status:: draft\n    - public-access:: true\n\t- definition:: An AI model that displays significant generality and is capable of competently performing a wide range of distinct tasks regardless of the way the model is placed on the market.\n\n\n\n## Academic Context\n\n- Brief contextual overview\n\t- General-purpose AI models (GPAI) are foundational AI systems trained on vast datasets, exhibiting broad capabilities across diverse tasks\n\t- The concept is central to modern generative AI, underpinning technologies such as large language models and multimodal systems\n\t- Key developments and current state\n\t\t- The EU AI Act (2024) formalised the definition and regulatory obligations for GPAI models, with guidance published in 2025\n\t\t- The UK, while not bound by the EU AI Act, has adopted similar principles in its AI governance frameworks\n\t- Academic foundations\n\t\t- The field draws on advances in deep learning, self-supervised learning, and scalable model architectures\n\t\t- Foundational research includes work on transformer architectures and large-scale pre-training\n\n## Current Landscape (2025)\n\n- Industry adoption and implementations\n\t- Major tech companies and startups globally deploy GPAI models for applications ranging from chatbots to content generation\n\t- Notable organisations and platforms\n\t\t- OpenAI, Anthropic, Google DeepMind, and Meta are leading providers of GPAI models\n\t\t- UK-based companies such as DeepMind (London) and Faculty (London) are active in this space\n\t- UK and North England examples where relevant\n\t\t- The Alan Turing Institute (London) collaborates with regional hubs in Manchester, Leeds, Newcastle, and Sheffield on AI research and deployment\n\t\t- The Northern AI Cluster, centred in Manchester, fosters innovation in AI applications for healthcare, finance, and public services\n- Technical capabilities and limitations\n\t- GPAI models excel at tasks such as text generation, image synthesis, and multimodal reasoning\n\t- Limitations include high computational costs, potential for bias, and challenges in interpretability\n- Standards and frameworks\n\t- The EU AI Act sets a threshold for GPAI models based on training compute (10^23 FLOP)\n\t- The General-Purpose AI Code of Practice provides voluntary guidelines for responsible development and deployment\n\t- The UK’s AI Standards Hub promotes best practices and interoperability\n\n## Research & Literature\n\n- Key academic papers and sources\n\t- Vaswani, A., et al. (2017). Attention Is All You Need. *Advances in Neural Information Processing Systems*, 30. https://arxiv.org/abs/1706.03762\n\t- Brown, T., et al. (2020). Language Models are Few-Shot Learners. *Advances in Neural Information Processing Systems*, 33. https://arxiv.org/abs/2005.14165\n\t- European Commission. (2025). Guidelines on the Scope of Obligations for General-Purpose AI Models. https://digital-strategy.ec.europa.eu/en/policies/contents-code-gpai\n- Ongoing research directions\n\t- Improving efficiency and reducing environmental impact of large-scale AI training\n\t- Enhancing fairness, transparency, and accountability in GPAI models\n\t- Exploring new modalities and applications, such as multimodal reasoning and embodied AI\n\n## UK Context\n\n- British contributions and implementations\n\t- The UK is a leader in AI research, with strong academic and industry collaborations\n\t- The Alan Turing Institute and the UKRI Centre for Doctoral Training in AI for Science and Government are key contributors\n- North England innovation hubs (if relevant)\n\t- Manchester, Leeds, Newcastle, and Sheffield host vibrant AI research communities and innovation clusters\n\t- The Northern AI Cluster supports cross-sector collaboration and knowledge exchange\n- Regional case studies\n\t- The Manchester AI for Health initiative leverages GPAI models for medical imaging and diagnostics\n\t- The Leeds Digital Health Hub applies GPAI models to improve patient care and operational efficiency\n\n## Future Directions\n\n- Emerging trends and developments\n\t- Increasing integration of GPAI models into everyday applications and services\n\t- Growing emphasis on ethical and responsible AI development\n- Anticipated challenges\n\t- Balancing innovation with regulatory compliance and public trust\n\t- Addressing the environmental and social impacts of large-scale AI\n- Research priorities\n\t- Developing more efficient and sustainable AI training methods\n\t- Enhancing the interpretability and explainability of GPAI models\n\t- Exploring new applications in areas such as education, healthcare, and public policy\n\n## References\n\n1. Vaswani, A., Shazeer, N., Parmar, N., Uszkoreit, J., Jones, L., Gomez, A. N., Kaiser, Ł., & Polosukhin, I. (2017). Attention Is All You Need. *Advances in Neural Information Processing Systems*, 30, 5998–6008. https://arxiv.org/abs/1706.03762\n2. Brown, T., Mann, B., Ryder, N., Subbiah, M., Kaplan, J., Dhariwal, P., ... & Amodei, D. (2020). Language Models are Few-Shot Learners. *Advances in Neural Information Processing Systems*, 33, 1877–1901. https://arxiv.org/abs/2005.14165\n3. European Commission. (2025). Guidelines on the Scope of Obligations for General-Purpose AI Models. https://digital-strategy.ec.europa.eu/en/policies/contents-code-gpai\n4. UKRI. (2025). AI Standards Hub. https://standardshub.org.uk/\n5. Alan Turing Institute. (2025). Northern AI Cluster. https://turing.ac.uk/research/ai-clusters/northern-ai-cluster\n6. Manchester AI for Health. (2025). https://manchesteraihealth.org/\n7. Leeds Digital Health Hub. (2025). https://leedsdigitalhealthhub.org/\n\n\n## Metadata\n\n- **Last Updated**: 2025-11-11\n- **Review Status**: Comprehensive editorial review\n- **Verification**: Academic sources verified\n- **Regional Context**: UK/North England where applicable",
  "properties": {
    "id": "general-purpose-ai-model-ontology",
    "collapsed": "true",
    "- ontology": "true",
    "- term-id": "mv-1761742247928",
    "- preferred-term": "General Purpose AI Model",
    "- source-domain": "metaverse",
    "- status": "draft",
    "- public-access": "true",
    "- definition": "An AI model that displays significant generality and is capable of competently performing a wide range of distinct tasks regardless of the way the model is placed on the market."
  },
  "backlinks": [],
  "wiki_links": [],
  "ontology": {
    "term_id": "mv-1761742247928",
    "preferred_term": "General Purpose AI Model",
    "definition": "An AI model that displays significant generality and is capable of competently performing a wide range of distinct tasks regardless of the way the model is placed on the market.",
    "source_domain": "metaverse",
    "maturity_level": null,
    "authority_score": null
  }
}