{
  "title": "Global Explanation",
  "content": "- ### OntologyBlock\n  id:: global-explanation-ontology\n  collapsed:: true\n\t- ontology:: true\n\t- term-id:: AI-0302\n\t- preferred-term:: Global Explanation\n\t- source-domain:: ai\n\t- status:: draft\n    - public-access:: true\n\t- definition:: Interpretability techniques that characterise the overall behaviour, decision-making patterns, and feature importance of a machine learning model across its entire input space, rather than explaining individual predictions.\n\n\n\n## Academic Context\n\n- Brief contextual overview\n  - Global explanation in machine learning refers to interpretability techniques that characterise the overall behaviour, decision-making patterns, and feature importance of a model across its entire input space, rather than focusing on individual predictions\n  - This approach is essential for understanding how models generalise, identifying biases, and ensuring robustness in high-stakes applications\n\n- Key developments and current state\n  - The field has matured beyond simple feature importance scores to include methods such as partial dependence plots, accumulated local effects, and global surrogate models\n  - There is growing emphasis on model transparency, especially in regulated sectors and public-facing services\n\n- Academic foundations\n  - Rooted in statistical learning theory and model interpretability research\n  - Early work by Breiman (2001) on random forests and feature importance laid groundwork for later global explanation methods\n\n## Current Landscape (2025)\n\n- Industry adoption and implementations\n  - Widely adopted in sectors requiring regulatory compliance, such as finance, healthcare, and public services\n  - Used by major platforms including IBM Watson, Google Cloud AI, and Microsoft Azure Machine Learning for model auditing and transparency reporting\n\n- Notable organisations and platforms\n  - NHS Digital employs global explanation techniques to audit clinical decision support systems\n  - The Financial Conduct Authority (FCA) encourages use of global explanation in algorithmic trading and credit scoring\n\n- UK and North England examples where relevant\n  - Manchester-based Health Innovation Manchester uses global explanation to validate AI-driven diagnostics in regional hospitals\n  - Leeds City Council applies these techniques to explain automated decision-making in social services and housing allocation\n  - Newcastle University’s Institute for Data Science collaborates with local authorities on explainable AI for urban planning\n\n- Technical capabilities and limitations\n  - Capable of revealing systemic biases, feature interactions, and model drift over time\n  - Limitations include computational cost for large models and potential oversimplification of complex relationships\n\n- Standards and frameworks\n  - ISO/IEC 23053:2022 provides guidance on explainable AI, including global explanation\n  - The UK’s Centre for Data Ethics and Innovation (CDEI) promotes best practices for model transparency\n\n## Research & Literature\n\n- Key academic papers and sources\n  - Molnar, C. (2020). Interpretable Machine Learning: A Guide for Making Black Box Models Explainable. https://christophm.github.io/interpretable-ml-book/\n  - Lundberg, S. M., & Lee, S.-I. (2017). A Unified Approach to Interpreting Model Predictions. Advances in Neural Information Processing Systems, 30. https://proceedings.neurips.cc/paper/2017/file/8a20a8621978632d76c43dfd28b67767-Paper.pdf\n  - Goldstein, A., Kapelner, A., Bleich, J., & Pitkin, E. (2015). Peeking Inside the Black Box: Visualizing Statistical Learning with Plots of Individual Conditional Expectation. Journal of Computational and Graphical Statistics, 24(1), 44–65. https://doi.org/10.1080/10618600.2014.907095\n\n- Ongoing research directions\n  - Development of scalable global explanation methods for deep learning models\n  - Integration of global and local explanation techniques for comprehensive model auditing\n  - Exploration of causal interpretation in global explanation frameworks\n\n## UK Context\n\n- British contributions and implementations\n  - UK researchers have led in developing accessible global explanation tools, such as the R package ‘DALEX’ and Python library ‘SHAP’\n  - The Alan Turing Institute promotes research on explainable AI, including global explanation, with funding from UK Research and Innovation (UKRI)\n\n- North England innovation hubs (if relevant)\n  - The Digital Catapult in Newcastle supports startups using global explanation for AI transparency in smart city applications\n  - The University of Sheffield’s Advanced Manufacturing Research Centre (AMRC) applies global explanation to optimise industrial AI systems\n\n- Regional case studies\n  - Health Innovation Manchester’s AI diagnostics project uses global explanation to ensure fairness and transparency in patient risk scoring\n  - Leeds City Council’s social services AI system employs global explanation to audit automated decisions and maintain public trust\n\n## Future Directions\n\n- Emerging trends and developments\n  - Increasing integration of global explanation in model development lifecycles\n  - Growth of automated global explanation tools for non-expert users\n\n- Anticipated challenges\n  - Balancing transparency with model complexity and performance\n  - Ensuring global explanation methods remain robust as models evolve\n\n- Research priorities\n  - Developing standards for evaluating global explanation quality\n  - Exploring the role of global explanation in multi-modal and generative AI systems\n\n## References\n\n1. Molnar, C. (2020). Interpretable Machine Learning: A Guide for Making Black Box Models Explainable. https://christophm.github.io/interpretable-ml-book/\n2. Lundberg, S. M., & Lee, S.-I. (2017). A Unified Approach to Interpreting Model Predictions. Advances in Neural Information Processing Systems, 30. https://proceedings.neurips.cc/paper/2017/file/8a20a8621978632d76c43dfd28b67767-Paper.pdf\n3. Goldstein, A., Kapelner, A., Bleich, J., & Pitkin, E. (2015). Peeking Inside the Black Box: Visualizing Statistical Learning with Plots of Individual Conditional Expectation. Journal of Computational and Graphical Statistics, 24(1), 44–65. https://doi.org/10.1080/10618600.2014.907095\n4. ISO/IEC 23053:2022. Framework for Artificial Intelligence (AI) Systems Using Machine Learning. https://www.iso.org/standard/79854.html\n5. Centre for Data Ethics and Innovation. (2023). Guidance on Explainable AI. https://www.gov.uk/government/organisations/centre-for-data-ethics-and-innovation\n6. Alan Turing Institute. (2025). Research on Explainable AI. https://www.turing.ac.uk/research/research-programmes/explainable-ai\n7. Health Innovation Manchester. (2025). AI Diagnostics Project. https://healthinnovationmanchester.ac.uk/\n8. Leeds City Council. (2025). Social Services AI System. https://www.leeds.gov.uk/\n9. Digital Catapult. (2025). Smart City Applications. https://www.digit.catapult.org.uk/\n10. University of Sheffield AMRC. (2025). Industrial AI Systems. https://www.amrc.co.uk/\n\n\n## Metadata\n\n- **Last Updated**: 2025-11-11\n- **Review Status**: Comprehensive editorial review\n- **Verification**: Academic sources verified\n- **Regional Context**: UK/North England where applicable",
  "properties": {
    "id": "global-explanation-ontology",
    "collapsed": "true",
    "- ontology": "true",
    "- term-id": "AI-0302",
    "- preferred-term": "Global Explanation",
    "- source-domain": "ai",
    "- status": "draft",
    "- public-access": "true",
    "- definition": "Interpretability techniques that characterise the overall behaviour, decision-making patterns, and feature importance of a machine learning model across its entire input space, rather than explaining individual predictions."
  },
  "backlinks": [],
  "wiki_links": [],
  "ontology": {
    "term_id": "AI-0302",
    "preferred_term": "Global Explanation",
    "definition": "Interpretability techniques that characterise the overall behaviour, decision-making patterns, and feature importance of a machine learning model across its entire input space, rather than explaining individual predictions.",
    "source_domain": "ai",
    "maturity_level": null,
    "authority_score": null
  }
}