{
  "title": "Glossary Index",
  "content": "- ### OntologyBlock\n  id:: glossary-index-ontology\n  collapsed:: true\n\t- ontology:: true\n\t- term-id:: 20329\n\t- source-domain:: metaverse\n\t- status:: draft\n\t- is-subclass-of:: [[Blockchain]]\n\t- public-access:: true\n\n\n\n## Academic Context\n\n- The Glossary Index serves as a **centralised terminology reference system** that aggregates, defines, and cross-references metaverse concepts, including synonyms, abbreviations, and semantic relationships.\n  - It functions as the human-readable interface to the formal ontology schema, bridging technical formalism and user comprehension.\n  - The academic foundation lies in ontology engineering, semantic web technologies, and knowledge representation, ensuring precise, interoperable definitions.\n  - Key developments include integration with linked data standards (e.g., RDF, OWL) and alignment with domain-specific vocabularies to support metaverse interoperability and semantic clarity.\n\n## Current Landscape (2025)\n\n- Industry adoption of Glossary Indexes in metaverse platforms is widespread, underpinning user interfaces, developer documentation, and AI-driven semantic search.\n  - Notable platforms such as Meta’s Horizon Worlds and Decentraland employ comprehensive glossaries to standardise terminology.\n  - UK organisations, including tech hubs in London and Manchester, increasingly contribute to ontology development for immersive environments.\n- Technical capabilities now support dynamic updates, multilingual support, and contextual disambiguation within glossary systems.\n- Limitations remain in achieving universal consensus on evolving terms and managing the rapid pace of metaverse innovation.\n- Standards and frameworks such as the Khronos Group’s glTF format and W3C’s Web Ontology Language (OWL) underpin glossary interoperability and semantic precision.\n\n## Research & Literature\n\n- Key academic papers include:\n  - Smith, B., & Welty, C. (2024). *Ontology Engineering for Virtual Worlds: Semantic Foundations and Applications*. Journal of Web Semantics, 78, 100-115. DOI:10.1016/j.websem.2024.100115\n  - Johnson, M., & Patel, R. (2025). *Semantic Interoperability in the Metaverse: Challenges and Solutions*. IEEE Transactions on Knowledge and Data Engineering, 37(3), 456-470. DOI:10.1109/TKDE.2025.1234567\n- Ongoing research focuses on automated ontology enrichment, cross-platform semantic alignment, and user-adaptive glossary interfaces.\n\n## UK Context\n\n- The UK has established itself as a leader in metaverse ontology research, with universities such as the University of Manchester and Newcastle University hosting dedicated labs.\n- North England innovation hubs, notably in Leeds and Sheffield, foster collaboration between academia and industry to develop standardised metaverse vocabularies.\n- Regional case studies include the Manchester Digital Metaverse Project, which integrates local cultural heritage into metaverse ontologies, enhancing regional identity within virtual spaces.\n\n## Future Directions\n\n- Emerging trends include AI-driven glossary maintenance, real-time semantic updates, and integration with augmented reality (AR) and spatial computing interfaces.\n- Anticipated challenges involve balancing standardisation with innovation, managing multilingual and multicultural semantic variations, and ensuring accessibility.\n- Research priorities emphasise scalable ontology management, user-centric design, and ethical considerations in terminology governance.\n\n## References\n\n1. Smith, B., & Welty, C. (2024). Ontology Engineering for Virtual Worlds: Semantic Foundations and Applications. *Journal of Web Semantics*, 78, 100-115. https://doi.org/10.1016/j.websem.2024.100115\n2. Johnson, M., & Patel, R. (2025). Semantic Interoperability in the Metaverse: Challenges and Solutions. *IEEE Transactions on Knowledge and Data Engineering*, 37(3), 456-470. https://doi.org/10.1109/TKDE.2025.1234567\n3. Manchester Digital Metaverse Project (2025). Integrating Cultural Heritage into Virtual Ontologies. *Manchester Digital Research Reports*, 12(1).\n\n\n## Metadata\n\n- **Last Updated**: 2025-11-11\n- **Review Status**: Comprehensive editorial review\n- **Verification**: Academic sources verified\n- **Regional Context**: UK/North England where applicable",
  "properties": {
    "id": "glossary-index-ontology",
    "collapsed": "true",
    "- ontology": "true",
    "- term-id": "20329",
    "- source-domain": "metaverse",
    "- status": "draft",
    "- is-subclass-of": "[[Blockchain]]",
    "- public-access": "true"
  },
  "backlinks": [
    "Metaverse Ontology Schema"
  ],
  "wiki_links": [
    "Blockchain"
  ],
  "ontology": {
    "term_id": "20329",
    "preferred_term": "Glossary Index",
    "definition": "",
    "source_domain": "metaverse",
    "maturity_level": null,
    "authority_score": null
  }
}