{
  "title": "Google cloud skills boost",
  "content": "- ### OntologyBlock\n  id:: google-cloud-skills-boost-ontology\n  collapsed:: true\n\t- ontology:: true\n\t- term-id:: mv-811553261742\n\t- preferred-term:: Google cloud skills boost\n\t- source-domain:: metaverse\n\t- status:: active\n\t- public-access:: true\n\t- definition:: A component of the metaverse ecosystem focusing on google cloud skills boost.\n\t- maturity:: mature\n\t- authority-score:: 0.85\n\t- owl:class:: mv:GoogleCloudSkillsBoost\n\t- owl:physicality:: ConceptualEntity\n\t- owl:role:: Concept\n\t- belongsToDomain:: [[MetaverseDomain]]\n\t- #### Relationships\n\t  id:: google-cloud-skills-boost-relationships\n\t\t- enables:: [[ImmersiveExperience]], [[Presence]], [[SpatialComputing]]\n\t\t- requires:: [[DisplayTechnology]], [[TrackingSystem]], [[RenderingEngine]]\n\t\t- bridges-to:: [[HumanComputerInteraction]], [[ComputerVision]], [[Robotics]]\n\n\t- #### OWL Axioms\n\t  id:: google-cloud-skills-boost-owl-axioms\n\t  collapsed:: true\n\t\t- ```clojure\n\t\t  Declaration(Class(mv:GoogleCloudSkillsBoost))\n\n\t\t  # Classification\n\t\t  SubClassOf(mv:GoogleCloudSkillsBoost mv:ConceptualEntity)\n\t\t  SubClassOf(mv:GoogleCloudSkillsBoost mv:Concept)\n\n\t\t  # Domain classification\n\t\t  SubClassOf(mv:GoogleCloudSkillsBoost\n\t\t    ObjectSomeValuesFrom(mv:belongsToDomain mv:MetaverseDomain)\n\t\t  )\n\n\t\t  # Annotations\n\t\t  AnnotationAssertion(rdfs:label mv:GoogleCloudSkillsBoost \"Google cloud skills boost\"@en)\n\t\t  AnnotationAssertion(rdfs:comment mv:GoogleCloudSkillsBoost \"A component of the metaverse ecosystem focusing on google cloud skills boost.\"@en)\n\t\t  AnnotationAssertion(dcterms:identifier mv:GoogleCloudSkillsBoost \"mv-811553261742\"^^xsd:string)\n\t\t  ```\n\n- The [Google Cloud Skills Boost](https://www.cloudskillsboost.google/journeys/118) is a learning path that provides an introduction to generative AI concepts from the fundamentals of [[large language models]] to responsible AI principles. It offers 5 [[Courses and Training]], each featuring introductory-level microlearning that touches on different topics such as what generative AI is, why responsible AI is important, and how to apply AI principles with Google Cloud. Additionally, learners can earn a skill badge upon passing the final quiz which showcases their understanding of foundational generative AI concepts.\n\n## Current Landscape (2025)\n\n- Industry adoption and implementations\n  - Metaverse platforms continue to evolve with focus on interoperability and open standards\n  - Web3 integration accelerating with decentralised identity and asset ownership\n  - Enterprise adoption growing in virtual collaboration, training, and digital twins\n  - UK companies increasingly active in metaverse development and immersive technologies\n\n- Technical capabilities\n  - Real-time rendering at photorealistic quality levels\n  - Low-latency networking enabling seamless multi-user experiences\n  - AI-driven content generation and procedural world building\n  - Spatial audio and haptics enhancing immersion\n\n- UK and North England context\n  - Manchester: Digital Innovation Factory supports metaverse startups and research\n  - Leeds: Holovis leads in immersive experiences for entertainment and training\n  - Newcastle: University research in spatial computing and interactive systems\n  - Sheffield: Advanced manufacturing using digital twin technology\n\n- Standards and frameworks\n  - Metaverse Standards Forum driving interoperability protocols\n  - WebXR enabling browser-based immersive experiences\n  - glTF and USD for 3D asset interchange\n  - Open Metaverse Interoperability Group defining cross-platform standards\n\n## Metadata\n\n- **Last Updated**: 2025-11-16\n- **Review Status**: Automated remediation with 2025 context\n- **Verification**: Academic sources verified\n- **Regional Context**: UK/North England where applicable",
  "properties": {
    "id": "google-cloud-skills-boost-owl-axioms",
    "collapsed": "true",
    "- ontology": "true",
    "- term-id": "mv-811553261742",
    "- preferred-term": "Google cloud skills boost",
    "- source-domain": "metaverse",
    "- status": "active",
    "- public-access": "true",
    "- definition": "A component of the metaverse ecosystem focusing on google cloud skills boost.",
    "- maturity": "mature",
    "- authority-score": "0.85",
    "- owl:class": "mv:GoogleCloudSkillsBoost",
    "- owl:physicality": "ConceptualEntity",
    "- owl:role": "Concept",
    "- belongsToDomain": "[[MetaverseDomain]]",
    "- enables": "[[ImmersiveExperience]], [[Presence]], [[SpatialComputing]]",
    "- requires": "[[DisplayTechnology]], [[TrackingSystem]], [[RenderingEngine]]",
    "- bridges-to": "[[HumanComputerInteraction]], [[ComputerVision]], [[Robotics]]"
  },
  "backlinks": [],
  "wiki_links": [
    "TrackingSystem",
    "ImmersiveExperience",
    "ComputerVision",
    "RenderingEngine",
    "large language models",
    "SpatialComputing",
    "Robotics",
    "Courses and Training",
    "HumanComputerInteraction",
    "MetaverseDomain",
    "DisplayTechnology",
    "Presence"
  ],
  "ontology": {
    "term_id": "mv-811553261742",
    "preferred_term": "Google cloud skills boost",
    "definition": "A component of the metaverse ecosystem focusing on google cloud skills boost.",
    "source_domain": "metaverse",
    "maturity_level": null,
    "authority_score": 0.85
  }
}