{
  "title": "Google",
  "content": "- ### OntologyBlock\n  id:: google-ontology\n  collapsed:: true\n\t- ontology:: true\n\t- term-id:: mv-712933215552\n\t- preferred-term:: Google\n\t- source-domain:: metaverse\n\t- status:: active\n\t- public-access:: true\n\t- definition:: A component of the metaverse ecosystem focusing on google.\n\t- maturity:: mature\n\t- authority-score:: 0.85\n\t- owl:class:: mv:Google\n\t- owl:physicality:: ConceptualEntity\n\t- owl:role:: Concept\n\t- belongsToDomain:: [[MetaverseDomain]]\n\t- #### Relationships\n\t  id:: google-relationships\n\t\t- enables:: [[ImmersiveExperience]], [[Presence]], [[SpatialComputing]]\n\t\t- requires:: [[DisplayTechnology]], [[TrackingSystem]], [[RenderingEngine]]\n\t\t- bridges-to:: [[HumanComputerInteraction]], [[ComputerVision]], [[Robotics]]\n\n\t- #### OWL Axioms\n\t  id:: google-owl-axioms\n\t  collapsed:: true\n\t\t- ```clojure\n\t\t  Declaration(Class(mv:Google))\n\n\t\t  # Classification\n\t\t  SubClassOf(mv:Google mv:ConceptualEntity)\n\t\t  SubClassOf(mv:Google mv:Concept)\n\n\t\t  # Domain classification\n\t\t  SubClassOf(mv:Google\n\t\t    ObjectSomeValuesFrom(mv:belongsToDomain mv:MetaverseDomain)\n\t\t  )\n\n\t\t  # Annotations\n\t\t  AnnotationAssertion(rdfs:label mv:Google \"Google\"@en)\n\t\t  AnnotationAssertion(rdfs:comment mv:Google \"A component of the metaverse ecosystem focusing on google.\"@en)\n\t\t  AnnotationAssertion(dcterms:identifier mv:Google \"mv-712933215552\"^^xsd:string)\n\t\t  ```\n\n- Their priorities for the year are  [Googleâ€™s goals for 2024 include improving Bard, helpful Pixel products, and cost savings (androidpolice.com)](https://www.androidpolice.com/googles-goals-for-2024/)\n\t- Deliver the worldâ€™s most advanced, safe, and responsible Al.\n\t- Improve knowledge, learning, creativity, and productivity.\n\t- Build the most helpful personal computing platforms and devices.\n\t- Enable organizations and developers to innovate on Google Cloud.\n\t- Provide the worldâ€™s most trusted products and platforms.\n\t- Build a Google thatâ€™s extraordinary for Googlers and the world.\n\t- Improve company velocity, efficiency, and productivity, and deliver durable cost savings.\n- They have partnered with Huggingface to deploy open models in Google cloud, and leverage their hardware [blog/gcp-partnership.md at main Â· huggingface/blog (github.com)](https://github.com/huggingface/blog/blob/main/gcp-partnership.md)\n- Google Genie makes interactive worlds\n\t- [ðŸ§ž Genie: Generative Interactive Environments (google.com)](https://sites.google.com/view/genie-2024/)\n\t- ![media.gif](../assets/media_1708968841318_0.gif)\n\n## Current Landscape (2025)\n\n- Industry adoption and implementations\n  - Metaverse platforms continue to evolve with focus on interoperability and open standards\n  - Web3 integration accelerating with decentralised identity and asset ownership\n  - Enterprise adoption growing in virtual collaboration, training, and digital twins\n  - UK companies increasingly active in metaverse development and immersive technologies\n\n- Technical capabilities\n  - Real-time rendering at photorealistic quality levels\n  - Low-latency networking enabling seamless multi-user experiences\n  - AI-driven content generation and procedural world building\n  - Spatial audio and haptics enhancing immersion\n\n- UK and North England context\n  - Manchester: Digital Innovation Factory supports metaverse startups and research\n  - Leeds: Holovis leads in immersive experiences for entertainment and training\n  - Newcastle: University research in spatial computing and interactive systems\n  - Sheffield: Advanced manufacturing using digital twin technology\n\n- Standards and frameworks\n  - Metaverse Standards Forum driving interoperability protocols\n  - WebXR enabling browser-based immersive experiences\n  - glTF and USD for 3D asset interchange\n  - Open Metaverse Interoperability Group defining cross-platform standards\n\n## Metadata\n\n- **Last Updated**: 2025-11-16\n- **Review Status**: Automated remediation with 2025 context\n- **Verification**: Academic sources verified\n- **Regional Context**: UK/North England where applicable",
  "properties": {
    "id": "google-owl-axioms",
    "collapsed": "true",
    "- ontology": "true",
    "- term-id": "mv-712933215552",
    "- preferred-term": "Google",
    "- source-domain": "metaverse",
    "- status": "active",
    "- public-access": "true",
    "- definition": "A component of the metaverse ecosystem focusing on google.",
    "- maturity": "mature",
    "- authority-score": "0.85",
    "- owl:class": "mv:Google",
    "- owl:physicality": "ConceptualEntity",
    "- owl:role": "Concept",
    "- belongsToDomain": "[[MetaverseDomain]]",
    "- enables": "[[ImmersiveExperience]], [[Presence]], [[SpatialComputing]]",
    "- requires": "[[DisplayTechnology]], [[TrackingSystem]], [[RenderingEngine]]",
    "- bridges-to": "[[HumanComputerInteraction]], [[ComputerVision]], [[Robotics]]"
  },
  "backlinks": [
    "x402 and l402 payment protocols",
    "BC-0072-node",
    "AI-Augmented Software Engineering",
    "BC-0435-hyperledger-indy",
    "Agentic Mycelia",
    "rb-0022-robot-dynamics",
    "ComfyUI",
    "Death of the Internet",
    "AI Risks",
    "Micropayments",
    "Anthropic Claude"
  ],
  "wiki_links": [
    "TrackingSystem",
    "ImmersiveExperience",
    "ComputerVision",
    "RenderingEngine",
    "SpatialComputing",
    "Robotics",
    "HumanComputerInteraction",
    "MetaverseDomain",
    "DisplayTechnology",
    "Presence"
  ],
  "ontology": {
    "term_id": "mv-712933215552",
    "preferred_term": "Google",
    "definition": "A component of the metaverse ecosystem focusing on google.",
    "source_domain": "metaverse",
    "maturity_level": null,
    "authority_score": 0.85
  }
}