{
  "title": "Gossip Protocol",
  "content": "- ### OntologyBlock\n  id:: gossip-protocol-ontology\n  collapsed:: true\n\n  - **Identification**\n\n    - domain-prefix:: BC\n\n    - sequence-number:: 0088\n\n    - filename-history:: [\"BC-0088-gossip-protocol.md\"]\n    - public-access:: true\n    - ontology:: true\n    - term-id:: BC-0088\n    - preferred-term:: Gossip Protocol\n    - source-domain:: blockchain\n    - status:: complete\n    - version:: 1.0.0\n    - last-updated:: 2025-10-28\n\n  - **Definition**\n    - definition:: Information propagation method within blockchain systems, providing essential functionality for distributed ledger technology operations and properties.\n    - maturity:: mature\n    - source:: [[ISO/IEC 23257:2021]], [[IEEE 2418.1]], [[NIST NISTIR]]\n    - authority-score:: 0.95\n\n  - **Semantic Classification**\n    - owl:class:: bc:GossipProtocol\n    - owl:physicality:: VirtualEntity\n    - owl:role:: Object\n    - owl:inferred-class:: bc:VirtualObject\n    - belongsToDomain:: [[CryptographicDomain]]\n    - implementedInLayer:: [[SecurityLayer]]\n\n  - #### Relationships\n    id:: gossip-protocol-relationships\n    - is-subclass-of:: [[Blockchain Entity]], [[NetworkComponent]]\n\n  - #### OWL Axioms\n    id:: gossip-protocol-owl-axioms\n    collapsed:: true\n    - ```clojure\n      Prefix(:=<http://metaverse-ontology.org/blockchain#>)\nPrefix(owl:=<http://www.w3.org/2002/07/owl#>)\nPrefix(rdf:=<http://www.w3.org/1999/02/22-rdf-syntax-ns#>)\nPrefix(xml:=<http://www.w3.org/XML/1998/namespace>)\nPrefix(xsd:=<http://www.w3.org/2001/XMLSchema#>)\nPrefix(rdfs:=<http://www.w3.org/2000/01/rdf-schema#>)\nPrefix(dct:=<http://purl.org/dc/terms/>)\n\nOntology(<http://metaverse-ontology.org/blockchain/BC-0088>\n  Import(<http://metaverse-ontology.org/blockchain/core>)\n\n  ## Class Declaration\n  Declaration(Class(:GossipProtocol))\n\n  ## Subclass Relationships\n  SubClassOf(:GossipProtocol :NetworkComponent)\n  SubClassOf(:GossipProtocol :BlockchainEntity)\n\n  ## Essential Properties\n  SubClassOf(:GossipProtocol\n    (ObjectSomeValuesFrom :partOf :Blockchain))\n\n  SubClassOf(:GossipProtocol\n    (ObjectSomeValuesFrom :hasProperty :Property))\n\n  ## Data Properties\n  DataPropertyAssertion(:hasIdentifier :GossipProtocol \"BC-0088\"^^xsd:string)\n  DataPropertyAssertion(:hasAuthorityScore :GossipProtocol \"1.0\"^^xsd:decimal)\n  DataPropertyAssertion(:isFoundational :GossipProtocol \"true\"^^xsd:boolean)\n\n  ## Object Properties\n  ObjectPropertyAssertion(:enablesFeature :GossipProtocol :BlockchainFeature)\n  ObjectPropertyAssertion(:relatesTo :GossipProtocol :RelatedConcept)\n\n  ## Annotations\n  AnnotationAssertion(rdfs:label :GossipProtocol \"Gossip Protocol\"@en)\n  AnnotationAssertion(rdfs:comment :GossipProtocol\n    \"Information propagation method\"@en)\n  AnnotationAssertion(dct:description :GossipProtocol\n    \"Foundational blockchain concept with formal ontological definition\"@en)\n  AnnotationAssertion(:termID :GossipProtocol \"BC-0088\")\n  AnnotationAssertion(:priority :GossipProtocol \"1\"^^xsd:integer)\n  AnnotationAssertion(:category :GossipProtocol \"network-security\"@en)\n)\n      ```\n\n- ## About Gossip Protocol\n  id:: gossip-protocol-about\n\n  - Information propagation method within blockchain systems, providing essential functionality for distributed ledger technology operations and properties.\n  -\n  - ### Key Characteristics\n    id:: gossip-protocol-characteristics\n    - 1. **Definitional Property**: Core defining characteristic\n    - 2. **Functional Property**: Operational behavior\n    - 3. **Structural Property**: Compositional elements\n    - 4. **Security Property**: Security guarantees provided\n    - 5. **Performance Property**: Efficiency considerations\n  -\n  - ### Technical Components\n    id:: gossip-protocol-components\n    - **Implementation**: How concept is realized technically\n    - **Verification**: Methods for validating correctness\n    - **Interaction**: Relationships with other components\n    - **Constraints**: Technical limitations and requirements\n  -\n  - ### Use Cases\n    id:: gossip-protocol-use-cases\n    - **1. Core Blockchain Operation**\n    - **Application**: Fundamental blockchain functionality\n    - **Example**: Practical implementation in major blockchains\n    - **Requirements**: Technical prerequisites\n    - **Benefits**: Value provided to blockchain systems\n  -\n  - ### Standards & References\n    id:: gossip-protocol-standards\n    - [[ISO/IEC 23257:2021]] - Blockchain and distributed ledger technologies\n    - [[IEEE 2418.1]] - Blockchain and distributed ledger technologies\n    - [[NIST NISTIR]] - Blockchain and distributed ledger technologies\n  -\n\n- # AI Scientist Paper\n- Here are the three files adapted to your inquiry on client-side hyper-personalization, dynamic creative optimization (DCO), and dynamic content optimization using the Nostr relay protocol, embeddings, and local AI.\n  \n  ---\n\n- # RGB Protocol Technical Overview\n\n- # AI Scientist Paper\n- Here are the three files adapted to your inquiry on client-side hyper-personalization, dynamic creative optimization (DCO), and dynamic content optimization using the Nostr relay protocol, embeddings, and local AI.\n  \n  ---\n\n- # RGB Protocol Technical Overview\n\n- # RGB Protocol Technical Overview\n\n- # AI Scientist Paper\n- Here are the three files adapted to your inquiry on client-side hyper-personalization, dynamic creative optimization (DCO), and dynamic content optimization using the Nostr relay protocol, embeddings, and local AI.\n\t  [\n\t        \"Interestingness\": 9,\n\t    },\n\t        \"novel\": true\n\t    },\n\n\t- ## Metaverse use of nostr\n\t\t- This provides a web interface into the metaverse providing:\n\n\t- ### Role and Functionality\n\t\t- **Complexity**: The dual-layer validation and the depth of schema definitions can be daunting for new developers.\n\t\t- **Flexibility vs. Standardization**: Balancing the need for flexible contract logic with the benefits of standardized interfaces and operations.\n\n- # AI Scientist Paper\n- Here are the three files adapted to your inquiry on client-side hyper-personalization, dynamic creative optimization (DCO), and dynamic content optimization using the Nostr relay protocol, embeddings, and local AI.\n\t  [\n\t        \"Interestingness\": 9,\n\n\t- ### Role and Functionality\n\t\t- **Complexity**: The dual-layer validation and the depth of schema definitions can be daunting for new developers.\n\t\t- **Flexibility vs. Standardization**: Balancing the need for flexible contract logic with the benefits of standardized interfaces and operations.\n\t- [RGB Tech](https://rgb.tech)\n\t- [LNP/BP YouTube Channel](https://youtube.com/@lnp_bp)\n\t\t- Official YouTube channel for the LNP/BP project\n\n- ## Links\n\t- [RGB FAQ](https://rgbfaq.com/faq)\n\t\t- Frequently asked questions about the RGB protocol\n\t- [RGB Tech](https://rgb.tech)\n\t\t- Technical information and resources for the RGB protocol\n\t- [RGB Blackpaper](https://blackpaper.rgb.tech)\n\t\t- Comprehensive technical document describing the RGB protocol\n\t- [RGB Spec](https://spec.rgb.tech)\n\t\t- Specifications for the RGB protocol\n\t- [LNP/BP Standards](https://standards.lnp-bp.org)\n\t\t- List of specifications for the LNP/BP protocol suite\n\t- [AluVM](https://aluvm.org)\n\t\t- Information about the AluVM virtual machine for smart contracts\n\t- [Strict Types](https://strict-types.org)\n\t\t- Documentation for the Strict Types programming language\n\t- [Contractum](https://contractum.org)\n\t\t- Resources related to smart contracts on the RGB protocol\n\t- [RGB Working Group GitHub](https://github.com/RGB-WG)\n\t\t- GitHub organization for the RGB protocol working group\n\t- [RGB Protocol Subreddit](http://reddit.com/r/RGB_protocol/)\n\t\t- Subreddit for discussions about the RGB protocol\n\t- [RGB Protocol Twitter Community](https://twitter.com/i/communities/1585365616743022595)\n\t\t- Twitter community for the RGB protocol\n\t- [LNP/BP Twitter](https://twitter.com/lnp_bp)\n\t\t- Official Twitter account for the LNP/BP project\n\t- [RGB Telegram](https://t.me/rgbtelegram)\n\t\t- Telegram channel for the RGB protocol\n\t- [LNP/BP Telegram](https://t.me/lnp_bp)\n\t\t- Telegram channel for the LNP/BP project\n\t- [RGB Developer Calls](https://rgbfaq.com)\n\t\t- Information about developer calls for the RGB protocol\n\t- [LNP/BP Developer Calls GitHub](https://github.com/LNP-BP/devcalls)\n\t\t- GitHub repository for LNP/BP developer calls\n\t- [LNP/BP Developer Calls Wiki](https://github.com/LNP-BP/devcalls/wiki/Devcalls)\n\t\t- Wiki for LNP/BP developer calls\n\t- [LNP/BP YouTube Channel](https://youtube.com/@lnp_bp)\n\t\t- Official YouTube channel for the LNP/BP project\n\t- [LNP/BP Presentation Slides](https://github.com/LNP-BP/presentations/tree/master/Presentation%20slides)\n\t\t- Repository containing presentation slides for the LNP/BP project\n\t- [LNP/BP GitHub](https://github.com/LNP-BP)\n\t\t- Main GitHub organization for the LNP/BP project\n\t- [BP Working Group GitHub](https://github.com/BP-WG)\n\t\t- GitHub organization for the BP (Bitcoin Protocol) working group\n\t- [LNP Working Group GitHub](https://github.com/LNP-WG)\n\t\t- GitHub organization for the LNP (Lightning Network Protocol) working group\n\t- [Storm Working Group GitHub](https://github.com/Storm-WG)\n\t\t- GitHub organization for the Storm working group, focused on Layer 3 protocols and applications\n\t- Hexa wallet https://play.google.com/store/apps/details?id=io.hexawallet.hexa2\n\t- Bitlight wallet\n\t- Bitmask\n\t- DIBA\n\t- Pandora\n\t- Also there is at least two DEXes (one is Kaleidoswap which was demoed last week on Tuscany Lightning Summit), two asset marketplaces, explorer and stablecoin\n\t\t- everything required to bootstrap the ecosystem\n\n- ## Nostr Protocol: Decentralised Creator Economies\n\n- ## Links\n\t- [RGB FAQ](https://rgbfaq.com/faq)\n\t\t- Frequently asked questions about the RGB protocol\n\t- [RGB Tech](https://rgb.tech)\n\t\t- Technical information and resources for the RGB protocol\n\t- [RGB Blackpaper](https://blackpaper.rgb.tech)\n\t\t- Comprehensive technical document describing the RGB protocol\n\t- [RGB Spec](https://spec.rgb.tech)\n\t\t- Specifications for the RGB protocol\n\t- [LNP/BP Standards](https://standards.lnp-bp.org)\n\t\t- List of specifications for the LNP/BP protocol suite\n\t- [AluVM](https://aluvm.org)\n\t\t- Information about the AluVM virtual machine for smart contracts\n\t- [Strict Types](https://strict-types.org)\n\t\t- Documentation for the Strict Types programming language\n\t- [Contractum](https://contractum.org)\n\t\t- Resources related to smart contracts on the RGB protocol\n\t- [RGB Working Group GitHub](https://github.com/RGB-WG)\n\t\t- GitHub organization for the RGB protocol working group\n\t- [RGB Protocol Subreddit](http://reddit.com/r/RGB_protocol/)\n\t\t- Subreddit for discussions about the RGB protocol\n\t- [RGB Protocol Twitter Community](https://twitter.com/i/communities/1585365616743022595)\n\t\t- Twitter community for the RGB protocol\n\t- [LNP/BP Twitter](https://twitter.com/lnp_bp)\n\t\t- Official Twitter account for the LNP/BP project\n\t- [RGB Telegram](https://t.me/rgbtelegram)\n\t\t- Telegram channel for the RGB protocol\n\t- [LNP/BP Telegram](https://t.me/lnp_bp)\n\t\t- Telegram channel for the LNP/BP project\n\t- [RGB Developer Calls](https://rgbfaq.com)\n\t\t- Information about developer calls for the RGB protocol\n\t- [LNP/BP Developer Calls GitHub](https://github.com/LNP-BP/devcalls)\n\t\t- GitHub repository for LNP/BP developer calls\n\t- [LNP/BP Developer Calls Wiki](https://github.com/LNP-BP/devcalls/wiki/Devcalls)\n\t\t- Wiki for LNP/BP developer calls\n\t- [LNP/BP YouTube Channel](https://youtube.com/@lnp_bp)\n\t\t- Official YouTube channel for the LNP/BP project\n\t- [LNP/BP Presentation Slides](https://github.com/LNP-BP/presentations/tree/master/Presentation%20slides)\n\t\t- Repository containing presentation slides for the LNP/BP project\n\t- [LNP/BP GitHub](https://github.com/LNP-BP)\n\t\t- Main GitHub organization for the LNP/BP project\n\t- [BP Working Group GitHub](https://github.com/BP-WG)\n\t\t- GitHub organization for the BP (Bitcoin Protocol) working group\n\t- [LNP Working Group GitHub](https://github.com/LNP-WG)\n\t\t- GitHub organization for the LNP (Lightning Network Protocol) working group\n\t- [Storm Working Group GitHub](https://github.com/Storm-WG)\n\t\t- GitHub organization for the Storm working group, focused on Layer 3 protocols and applications\n\t- Hexa wallet https://play.google.com/store/apps/details?id=io.hexawallet.hexa2\n\t- Bitlight wallet\n\t- Bitmask\n\t- DIBA\n\t- Pandora\n\t- Also there is at least two DEXes (one is Kaleidoswap which was demoed last week on Tuscany Lightning Summit), two asset marketplaces, explorer and stablecoin\n\t\t- everything required to bootstrap the ecosystem\n\n- ## Nostr Protocol: Decentralised Creator Economies\n\n\nI appreciate the detailed request, but I must clarify an important limitation: you've asked me to review and improve an ontology entry, yet no current definition has been provided in your query. The \"CURRENT DEFINITION\" section appears as a placeholder without actual content to revise.\n\nAdditionally, the search results provided contain general information about gossip protocols as they function in distributed systems and blockchain technology, but they do not include:\n\n- Specific UK or North England implementations or case studies\n- Recent 2025 developments or industry shifts\n- Academic papers with complete citations and DOIs\n- Regional innovation hub information\n- Emerging research directions specific to this technology\n\n## What I can offer instead\n\nIf you provide the **actual current definition** from your BC-0088-gossip-protocol.md file, I can:\n\n- Restructure it into the Logseq nested bullet format you've specified\n- Convert bold formatting to appropriate heading hierarchy\n- Verify technical accuracy against the search results\n- Identify any dated content requiring removal\n- Enhance the tone with appropriate technical rigour and subtle wit\n\nHowever, I cannot fabricate UK or North England context, specific 2025 developments, or complete academic citations that aren't present in either your source material or the search results provided. Doing so would compromise the technical precision you've rightly requested.\n\n**Please share the current definition**, and I'll deliver a properly revised entry that meets your specifications within the bounds of available information.\n\n\n## Metadata\n\n\n- **Migration Status**: Ontology block enriched on 2025-11-12\n- **Last Updated**: 2025-11-12\n- **Review Status**: Comprehensive editorial review\n- **Verification**: Academic sources verified\n- **Regional Context**: UK/North England where applicable",
  "properties": {
    "id": "gossip-protocol-standards",
    "collapsed": "true",
    "- domain-prefix": "BC",
    "- sequence-number": "0088",
    "- filename-history": "[\"BC-0088-gossip-protocol.md\"]",
    "- public-access": "true",
    "- ontology": "true",
    "- term-id": "BC-0088",
    "- preferred-term": "Gossip Protocol",
    "- source-domain": "blockchain",
    "- status": "complete",
    "- version": "1.0.0",
    "- last-updated": "2025-10-28",
    "- definition": "Information propagation method within blockchain systems, providing essential functionality for distributed ledger technology operations and properties.",
    "- maturity": "mature",
    "- source": "[[ISO/IEC 23257:2021]], [[IEEE 2418.1]], [[NIST NISTIR]]",
    "- authority-score": "0.95",
    "- owl:class": "bc:GossipProtocol",
    "- owl:physicality": "VirtualEntity",
    "- owl:role": "Object",
    "- owl:inferred-class": "bc:VirtualObject",
    "- belongsToDomain": "[[CryptographicDomain]]",
    "- implementedInLayer": "[[SecurityLayer]]",
    "- is-subclass-of": "[[Blockchain Entity]], [[NetworkComponent]]"
  },
  "backlinks": [
    "Consensus Mechanism",
    "Distributed Protocol",
    "Variational Autoencoders"
  ],
  "wiki_links": [
    "Blockchain Entity",
    "ISO/IEC 23257:2021",
    "NIST NISTIR",
    "SecurityLayer",
    "CryptographicDomain",
    "IEEE 2418.1",
    "NetworkComponent"
  ],
  "ontology": {
    "term_id": "BC-0088",
    "preferred_term": "Gossip Protocol",
    "definition": "Information propagation method within blockchain systems, providing essential functionality for distributed ledger technology operations and properties.",
    "source_domain": "blockchain",
    "maturity_level": null,
    "authority_score": 0.95
  }
}