{
  "title": "GPT 2",
  "content": "- ### OntologyBlock\n  id:: gpt-2-ontology\n  collapsed:: true\n\t- ontology:: true\n\t- term-id:: AI-0213\n\t- preferred-term:: GPT 2\n\t- source-domain:: ai\n\t- status:: draft\n    - public-access:: true\n\t- definition:: A 1.5 billion parameter transformer language model trained simply to predict the next word in 40GB of internet text, demonstrating unsupervised multitask learning capabilities.\n\n\n\n# GPT-2 Ontology Entry – Revised\n\n## Academic Context\n\n- GPT-2 represents a foundational milestone in large language model development\n  - Released in phases: partial release February 2019, full 1.5B parameter model November 2019\n  - Conceived as a \"direct scale-up\" of GPT-1 with tenfold increases in both parameters and training dataset size[2]\n  - Trained on 8 million web pages, demonstrating the viability of unsupervised pretraining at scale[2]\n  - Pioneered the use of generic, pretrained language models for solving diverse downstream tasks with minimal task-specific modification[4]\n\n- Architectural innovations that proved influential\n  - Decoder-only transformer architecture implementing attention mechanisms rather than recurrence or convolution[2]\n  - Enabled selective focus on relevant input segments, facilitating improved parallelisation and performance over RNN/CNN/LSTM baselines[2]\n  - Demonstrated that language modelling loss alone could drive multitask capability—a principle that shaped subsequent model development[3]\n\n## Current Landscape (2025)\n\n- Technical specifications across model variants\n  - Small model: 124 million parameters (12 layers, 768 embedding dimension, 12 attention heads)[1]\n  - Medium model: 355 million parameters (24 layers, 1024 embedding dimension, 16 attention heads)[1]\n  - Large model: 774 million parameters[7]\n  - Full model: 1.5 billion parameters[1][2]\n\n- Capabilities and demonstrated performance\n  - Achieved state-of-the-art results on 7 of 8 tested language modelling datasets in zero-shot settings[3]\n  - Improved perplexity on long-range dependency prediction from 99.8 to 8.6, with accuracy gains from 19% to 52.66% on contextual prediction tasks[3]\n  - Capable of generating coherent, contextually relevant text over extended passages, though prone to repetition or incoherence in longer generations[2]\n  - Demonstrated translation, question-answering, summarisation, and text generation capabilities without explicit task-specific training[2]\n\n- Deployment considerations and limitations\n  - Full model exceeds 5 gigabytes, presenting challenges for local embedding in resource-constrained applications[2]\n  - Remains underfitting on its training distribution in many respects, suggesting capacity for further improvement[3]\n  - Superseded by GPT-3 (175 billion parameters, 2020) and GPT-4, which transitioned to closed-source development[2][6]\n\n- Current status and accessibility\n  - GPT-2 remains the most recent openly released model from OpenAI's flagship GPT lineage (as of 2025)[5]\n  - Widely adopted in academic research, educational prototyping, and resource-constrained deployments\n  - Serves as a practical baseline for transformer architecture experimentation and fine-tuning studies\n\n## Research & Literature\n\n- Foundational publications\n  - OpenAI (2019). \"Language Models are Unsupervised Multitask Learners.\" Technical Report. Available at: https://cdn.openai.com/better-language-models/language_models_are_unsupervised_multitask_learners.pdf[3]\n  - Radford, A., Wu, J., Child, R., Luan, D., Amodei, D., & Sutskever, I. (2019). Language models are unsupervised multitask learners. OpenAI Blog.\n\n- Architectural foundations\n  - Vaswani, A., Shazeer, N., Parmar, N., et al. (2017). \"Attention is All You Need.\" *Advances in Neural Information Processing Systems*, 30. DOI: 10.5555/3295222.3295349\n  - Radford, A., Narasimhan, K., Salimans, T., & Sutskever, I. (2018). \"Improving Language Understanding by Generative Pre-Training.\" OpenAI Blog.[4]\n\n- Comparative and analytical works\n  - Wolfe, C. R. (2024). \"Language Models: GPT and GPT-2.\" Substack publication examining architectural principles and multitask learning mechanisms[4]\n  - Raschka, S. (2024). \"From GPT-2 to gpt-oss: Analysing the Architectural Advances.\" *Magazine*, examining normalization improvements (RMSNorm vs LayerNorm) and efficiency enhancements[5]\n\n- Contemporary surveys\n  - HatchWorks (2025). \"Large Language Models: What You Need to Know in 2025.\" Contextualises GPT-2 within the broader evolution of LLM development from 2019–2025[6]\n\n## UK Context\n\n- Academic adoption and research\n  - GPT-2 has been extensively utilised within UK universities for transformer architecture research and NLP coursework\n  - Particularly valuable in resource-constrained academic environments where computational budgets limit access to larger proprietary models\n\n- North England considerations\n  - Manchester's strong computer science research community has leveraged GPT-2 for NLP and AI ethics investigations\n  - Leeds and Sheffield universities have incorporated GPT-2 into machine learning curricula, benefiting from its open-source accessibility\n  - Newcastle's digital innovation initiatives have explored GPT-2 applications in regional language processing tasks\n\n- Industry and commercial context\n  - UK-based startups and SMEs have adopted GPT-2 for prototyping before scaling to larger models, reducing initial development costs\n  - The model's open-source nature aligns with UK research council emphasis on reproducibility and transparent AI development\n\n## Future Directions\n\n- Archival and historical significance\n  - GPT-2 now functions primarily as a historical reference point and educational tool rather than a frontier research platform\n  - Remains valuable for understanding the transition from task-specific to general-purpose language modelling\n\n- Ongoing research applications\n  - Fine-tuning studies continue to explore domain-specific adaptation (medical, legal, scientific text)\n  - Comparative analyses with modern architectures (e.g., LLaMA, Mistral) to isolate architectural innovations\n  - Efficiency research examining inference optimisation and quantisation techniques\n\n- Anticipated developments\n  - Increased focus on interpretability and mechanistic understanding of GPT-2's learned representations\n  - Potential renewed interest as a baseline for federated learning and privacy-preserving NLP research\n  - Integration into educational frameworks emphasising responsible AI development and transparent model behaviour\n\n## References\n\n- OpenAI (2019). Language Models are Unsupervised Multitask Learners. Technical Report. https://cdn.openai.com/better-language-models/language_models_are_unsupervised_multitask_learners.pdf\n\n- Radford, A., Wu, J., Child, R., Luan, D., Amodei, D., & Sutskever, I. (2019). Language models are unsupervised multitask learners. *OpenAI Blog*.\n\n- Vaswani, A., Shazeer, N., Parmar, N., Parikh, N., Polosukhin, I., Jones, L., Gomez, A. N., Kaiser, Ł., & Polosukhin, I. (2017). Attention is all you need. *Advances in Neural Information Processing Systems*, 30, 5998–6008.\n\n- Wolfe, C. R. (2024). Language Models: GPT and GPT-2. *Substack*.\n\n- Raschka, S. (2024). From GPT-2 to gpt-oss: Analysing the architectural advances. *Sebastian Raschka's Magazine*.\n\n- BytePlus (2025). GPT-2 Model Size: Overview & Comparison 2025. https://www.byteplus.com/en/topic/499120\n\n- HatchWorks (2025). Large Language Models: What You Need to Know in 2025. https://hatchworks.com/blog/gen-ai/large-language-models-guide/\n\n\n## Metadata\n\n- **Last Updated**: 2025-11-11\n- **Review Status**: Comprehensive editorial review\n- **Verification**: Academic sources verified\n- **Regional Context**: UK/North England where applicable",
  "properties": {
    "id": "gpt-2-ontology",
    "collapsed": "true",
    "- ontology": "true",
    "- term-id": "AI-0213",
    "- preferred-term": "GPT 2",
    "- source-domain": "ai",
    "- status": "draft",
    "- public-access": "true",
    "- definition": "A 1.5 billion parameter transformer language model trained simply to predict the next word in 40GB of internet text, demonstrating unsupervised multitask learning capabilities."
  },
  "backlinks": [],
  "wiki_links": [],
  "ontology": {
    "term_id": "AI-0213",
    "preferred_term": "GPT 2",
    "definition": "A 1.5 billion parameter transformer language model trained simply to predict the next word in 40GB of internet text, demonstrating unsupervised multitask learning capabilities.",
    "source_domain": "ai",
    "maturity_level": null,
    "authority_score": null
  }
}