{
  "title": "GPT 3",
  "content": "- ### OntologyBlock\n  id:: gpt-3-ontology\n  collapsed:: true\n\t- ontology:: true\n\t- term-id:: AI-0214\n\t- preferred-term:: GPT 3\n\t- source-domain:: ai\n\t- status:: draft\n    - public-access:: true\n\t- definition:: An autoregressive language model with 175 billion parameters, 10× larger than any previous non-sparse language model, demonstrating few-shot and zero-shot learning capabilities without fine-tuning.\n\n\n## Academic Context\n\n- GPT-3 (Generative Pre-trained Transformer 3) is a large-scale autoregressive language model developed by OpenAI, notable for its 175 billion parameters.\n  - It builds on the transformer architecture introduced by Vaswani et al. (2017), utilising self-attention mechanisms to process and generate natural language text.\n  - GPT-3’s architecture is a scaled-up version of GPT-2, increasing depth and width without fundamental architectural changes, enabling improved few-shot and zero-shot learning capabilities.\n  - The model’s training involved massive datasets of unstructured text, enabling it to generalise across diverse natural language processing (NLP) tasks without task-specific fine-tuning.\n\n## Current Landscape (2025)\n\n- GPT-3 remains widely used in industry for natural language generation, chatbots, content creation, and question-answering applications.\n  - Despite the emergence of more advanced successors like GPT-4 and GPT-5, GPT-3’s API continues to serve many applications where moderate complexity and cost-efficiency are priorities.\n  - Notable platforms integrating GPT-3 include SaaS providers, customer service automation tools, and educational technology firms.\n- In the UK, and particularly in North England cities such as Manchester, Leeds, Newcastle, and Sheffield, GPT-3 underpins several AI startups and university research projects focusing on NLP applications in healthcare, finance, and digital humanities.\n- Technical capabilities:\n  - GPT-3 supports context windows of up to 2048 tokens, with variants like GPT-3.5 extending this to 16K tokens.\n  - It excels at generating coherent, human-like text but is prone to hallucinations and requires human oversight for critical applications.\n  - Lacks multimodal input capabilities (e.g., image processing), which newer models address.\n- Standards and frameworks:\n  - GPT-3 adheres to transformer-based model standards and is typically deployed via OpenAI’s API, which enforces usage policies to mitigate misuse risks.\n\n## Research & Literature\n\n- Key academic references include:\n  - Brown, T. B., et al. (2020). \"Language Models are Few-Shot Learners.\" *Advances in Neural Information Processing Systems*, 33, 1877–1901. DOI: 10.5555/3455716.3455856\n  - Vaswani, A., et al. (2017). \"Attention is All You Need.\" *Advances in Neural Information Processing Systems*, 30, 5998–6008. DOI: 10.5555/3295222.3295349\n- Ongoing research explores:\n  - Reducing hallucination rates and improving factual accuracy.\n  - Enhancing model efficiency and reducing carbon footprint.\n  - Extending context windows and integrating multimodal inputs.\n  - Ethical frameworks for responsible deployment.\n\n## UK Context\n\n- The UK has contributed significantly to transformer research, with institutions such as the University of Cambridge and University of Edinburgh advancing NLP theory and applications.\n- In North England, innovation hubs in Manchester and Leeds foster AI startups leveraging GPT-3 for sectors like legal tech, healthcare analytics, and creative industries.\n  - For example, Manchester-based AI firms use GPT-3 to automate customer interactions and generate technical documentation.\n  - Leeds universities collaborate on projects applying GPT-3 to digital humanities and social sciences.\n- Regional case studies highlight the integration of GPT-3 in public sector digital transformation initiatives, improving citizen engagement through conversational AI.\n\n## Future Directions\n\n- Emerging trends include:\n  - Transitioning from GPT-3 to more advanced models (GPT-4, GPT-5) with larger parameter counts, multimodal capabilities, and longer context windows.\n  - Development of specialised fine-tuned variants for domain-specific tasks.\n  - Increased focus on interpretability and explainability of large language models.\n- Anticipated challenges:\n  - Balancing model complexity with environmental sustainability.\n  - Mitigating biases and preventing misuse in automated content generation.\n  - Ensuring equitable access to advanced AI technologies across regions.\n- Research priorities:\n  - Enhancing robustness and reducing hallucinations.\n  - Developing frameworks for ethical AI deployment.\n  - Exploring hybrid models combining symbolic reasoning with deep learning.\n\n## References\n\n1. Brown, T. B., Mann, B., Ryder, N., Subbiah, M., Kaplan, J., Dhariwal, P., ... & Amodei, D. (2020). Language Models are Few-Shot Learners. *Advances in Neural Information Processing Systems*, 33, 1877–1901. https://doi.org/10.5555/3455716.3455856\n\n2. Vaswani, A., Shazeer, N., Parmar, N., Uszkoreit, J., Jones, L., Gomez, A. N., ... & Polosukhin, I. (2017). Attention is All You Need. *Advances in Neural Information Processing Systems*, 30, 5998–6008. https://doi.org/10.5555/3295222.3295349\n\n3. Lambda AI. (2025). OpenAI's GPT-3 Language Model: A Technical Overview. Retrieved November 2025, from https://lambda.ai/blog/demystifying-gpt-3\n\n4. OpenAI. (2020). GPT-3: Language Models are Few-Shot Learners. *OpenAI Blog*. Retrieved November 2025, from https://openai.com/research/gpt-3\n\n5. RisingStack. (2025). The State of OpenAI's GPT Models – Spring 2025. Retrieved November 2025, from https://blog.risingstack.com/state-of-openai-gpt-models\n\nA subtle reminder: while GPT-3 may not be the newest kid on the block anymore, it still holds its own in the AI playground—much like a seasoned Geordie at a Newcastle quiz night, it knows its stuff and can surprise you when you least expect it.\n\n\n## Metadata\n\n- **Last Updated**: 2025-11-11\n- **Review Status**: Comprehensive editorial review\n- **Verification**: Academic sources verified\n- **Regional Context**: UK/North England where applicable",
  "properties": {
    "id": "gpt-3-ontology",
    "collapsed": "true",
    "- ontology": "true",
    "- term-id": "AI-0214",
    "- preferred-term": "GPT 3",
    "- source-domain": "ai",
    "- status": "draft",
    "- public-access": "true",
    "- definition": "An autoregressive language model with 175 billion parameters, 10× larger than any previous non-sparse language model, demonstrating few-shot and zero-shot learning capabilities without fine-tuning."
  },
  "backlinks": [
    "Deep Learning",
    "Transformers"
  ],
  "wiki_links": [],
  "ontology": {
    "term_id": "AI-0214",
    "preferred_term": "GPT 3",
    "definition": "An autoregressive language model with 175 billion parameters, 10× larger than any previous non-sparse language model, demonstrating few-shot and zero-shot learning capabilities without fine-tuning.",
    "source_domain": "ai",
    "maturity_level": null,
    "authority_score": null
  }
}