{
  "title": "Gradient Clipping",
  "content": "- ### OntologyBlock\n  id:: gradient-clipping-ontology\n  collapsed:: true\n\t- ontology:: true\n\t- term-id:: AI-0294\n\t- preferred-term:: Gradient Clipping\n\t- source-domain:: ai\n\t- status:: draft\n    - public-access:: true\n\t- definition:: A technique that limits the magnitude of gradients during backpropagation to prevent exploding gradients and training instability. Gradient clipping rescales gradients when their norm exceeds a threshold, enabling stable training of deep networks, especially recurrent architectures.\n\n\n## Academic Context\n\n- Gradient clipping represents a foundational stabilisation technique in deep learning optimisation\n  - Emerged as a critical solution to the exploding gradient problem in deep and recurrent architectures\n  - Addresses numerical instability during backpropagation by constraining gradient magnitude\n  - Particularly essential for training recurrent neural networks (RNNs) and transformer-based models where gradient flow becomes problematic[1][2]\n  - Functions as both a fail-safe mechanism and a central controller of update magnitude, tightly coupled with learning rate dynamics[3]\n\n## Current Landscape (2025)\n\n- Industry adoption and implementations\n  - Widely integrated into major deep learning frameworks (PyTorch, TensorFlow, JAX)\n  - Standard practice in production training pipelines for large-scale models\n  - Particularly prevalent in natural language processing and computer vision applications\n  - UK-based AI research institutions (University of Oxford, University of Cambridge, Imperial College London) routinely employ gradient clipping in transformer training\n  - North England research clusters at University of Manchester and University of Leeds actively incorporate clipping strategies in their machine learning research programmes\n\n- Technical capabilities and limitations\n  - Traditional clipping applies hard thresholding with fixed thresholds, lacking layer-wise variance awareness[3]\n  - Introduces non-differentiable discontinuities that can complicate optimisation dynamics[3]\n  - Computational overhead includes norm calculation and conditional checks at each gradient update[2]\n  - Recent advances propose smoother, functional alternatives that preserve gradient direction whilst controlling magnitude[3]\n  - Two primary methodologies: clipping by value (element-wise thresholding) and clipping by norm (vector-level rescaling)[5]\n\n- Standards and frameworks\n  - Clipping threshold selection remains largely empirical, typically ranging from 1.0 to 10.0 depending on architecture\n  - Interacts synergistically with learning rate warmup schedules, forming an implicit update magnitude scheduler[3]\n  - Increasingly recognised as requiring adaptive, layer-specific tuning rather than uniform application[3]\n\n## Research & Literature\n\n- Key academic papers and sources\n  - Wang et al. (2025) – Observations on gradient clipping's role as a central controller in large-scale training\n  - Koloskova et al. (2023) – Learning rate dynamics and gradient clipping interactions\n  - Zhao et al. (2022) – Duality between warmup and clipping in controlling update magnitude\n  - Chen et al. (2020) – Limitations of traditional fixed-threshold clipping approaches\n  - Li et al. (2024b) – Non-differentiable discontinuities in conventional clipping formulations\n  - Mai and Johansson (2021) – Statistical grounding for gradient shaping alternatives\n  - Recent preprint (arXiv:2510.01578v1) – \"Gradient Shaping Beyond Clipping: A Functional Perspective\" proposing SPAMP framework for unified gradient norm shaping with per-layer statistical tracking and power-based modulation[3]\n\n- Ongoing research directions\n  - Development of smooth, differentiable gradient shaping operators that generalise beyond fixed-threshold clipping\n  - Adaptive, layer-wise approaches that account for distributional structure of gradients\n  - Integration of statistical tracking mechanisms for improved convergence speed and robustness\n  - Investigation of gradient clipping's interaction with modern optimisation algorithms (AdamW, LAMB, etc.)\n\n## UK Context\n\n- British contributions and implementations\n  - DeepMind (London-based) extensively utilises gradient clipping in large-scale model training\n  - University of Edinburgh's machine learning group conducts research on adaptive gradient control mechanisms\n  - Imperial College London's Department of Computing integrates clipping strategies in transformer research\n\n- North England innovation hubs\n  - University of Manchester's Department of Computer Science actively researches neural network optimisation, including gradient stabilisation techniques\n  - University of Leeds' School of Computing maintains research programmes on deep learning training dynamics\n  - Sheffield's Advanced Manufacturing Research Centre (AMRC) applies gradient clipping in industrial machine learning applications\n\n## Future Directions\n\n- Emerging trends and developments\n  - Shift from fixed-threshold clipping towards adaptive, functional approaches that respond to layer-wise and temporal gradient statistics\n  - Integration of gradient shaping with modern training paradigms (distributed training, mixed-precision computation)\n  - Development of theoretically grounded alternatives that maintain differentiability throughout the optimisation process[3]\n  - Potential convergence with other stabilisation techniques (batch normalisation, layer normalisation) for synergistic effects\n\n- Anticipated challenges\n  - Balancing computational overhead against stability gains, particularly in resource-constrained environments\n  - Determining optimal clipping thresholds remains largely heuristic despite theoretical advances\n  - Interaction with emerging optimisation methods requires continued empirical and theoretical investigation\n\n- Research priorities\n  - Formal theoretical analysis of gradient clipping's effect on convergence guarantees\n  - Development of principled, data-driven threshold selection methods\n  - Investigation of clipping's role in preventing catastrophic forgetting in continual learning scenarios\n  - Exploration of gradient shaping's applicability to federated and decentralised training\n\n## References\n\n[1] Product Teacher (2025). Understanding Gradient Clipping. Available at: productteacher.com/quick-product-tips/gradient-clipping-for-product-teams\n\n[2] Deepgram (2025). Gradient Clipping. AI Glossary. Available at: deepgram.com/ai-glossary/gradient-clipping\n\n[3] ArXiv (2025). Gradient Shaping Beyond Clipping: A Functional Perspective. arXiv:2510.01578v1. Available at: arxiv.org/html/2510.01578v1\n\n[4] Engati (2025). Gradient Clipping. Glossary. Available at: engati.com/glossary/gradient-clipping\n\n[5] GeeksforGeeks (2025). Understanding Gradient Clipping. Available at: geeksforgeeks.org/deep-learning/understanding-gradient-clipping/\n\n\n## Metadata\n\n- **Last Updated**: 2025-11-11\n- **Review Status**: Comprehensive editorial review\n- **Verification**: Academic sources verified\n- **Regional Context**: UK/North England where applicable",
  "properties": {
    "id": "gradient-clipping-ontology",
    "collapsed": "true",
    "- ontology": "true",
    "- term-id": "AI-0294",
    "- preferred-term": "Gradient Clipping",
    "- source-domain": "ai",
    "- status": "draft",
    "- public-access": "true",
    "- definition": "A technique that limits the magnitude of gradients during backpropagation to prevent exploding gradients and training instability. Gradient clipping rescales gradients when their norm exceeds a threshold, enabling stable training of deep networks, especially recurrent architectures."
  },
  "backlinks": [
    "Recurrent Neural Network",
    "Variational Autoencoders"
  ],
  "wiki_links": [],
  "ontology": {
    "term_id": "AI-0294",
    "preferred_term": "Gradient Clipping",
    "definition": "A technique that limits the magnitude of gradients during backpropagation to prevent exploding gradients and training instability. Gradient clipping rescales gradients when their norm exceeds a threshold, enabling stable training of deep networks, especially recurrent architectures.",
    "source_domain": "ai",
    "maturity_level": null,
    "authority_score": null
  }
}