{
  "title": "Hand Tracking",
  "content": "- ### OntologyBlock\n  id:: handtracking-ontology\n  collapsed:: true\n\n  - **Identification**\n    - domain-prefix:: AI\n    - sequence-number:: 0852\n    - filename-history:: [\"AI-0852-handtracking.md\"]\n    - public-access:: true\n    - ontology:: true\n    - is-subclass-of:: [[ArtificialIntelligenceTechnology]]\n    - term-id:: AI-0852\n    - preferred-term:: Hand Tracking\n    - source-domain:: ai\n    - status:: complete\n    - version:: 1.0.0\n    - last-updated:: 2025-11-13\n\n  - **Definition**\n    - definition:: \n    - maturity:: established\n    - source:: Chimera Prime Research\n    - authority-score:: 0.95\n\n  - **Semantic Classification**\n    - owl:class:: ai:HandTracking\n    - belongsToDomain:: [[Artificial Intelligence]]\n\n  - #### OWL Restrictions\n    \n\n  - #### CrossDomainBridges\n    - bridges-from:: [[MixedRealityMr]] via requires\n\n  -",
  "properties": {
    "id": "handtracking-ontology",
    "collapsed": "true",
    "- domain-prefix": "AI",
    "- sequence-number": "0852",
    "- filename-history": "[\"AI-0852-handtracking.md\"]",
    "- public-access": "true",
    "- ontology": "true",
    "- is-subclass-of": "[[ArtificialIntelligenceTechnology]]",
    "- term-id": "AI-0852",
    "- preferred-term": "Hand Tracking",
    "- source-domain": "ai",
    "- status": "complete",
    "- version": "1.0.0",
    "- last-updated": "2025-11-13",
    "- definition": "",
    "- maturity": "established",
    "- source": "Chimera Prime Research",
    "- authority-score": "0.95",
    "- owl:class": "ai:HandTracking",
    "- belongsToDomain": "[[Artificial Intelligence]]",
    "- bridges-from": "[[MixedRealityMr]] via requires"
  },
  "backlinks": [],
  "wiki_links": [
    "ArtificialIntelligenceTechnology",
    "MixedRealityMr",
    "Artificial Intelligence"
  ],
  "ontology": {
    "term_id": "AI-0852",
    "preferred_term": "Hand Tracking",
    "definition": "",
    "source_domain": "ai",
    "maturity_level": null,
    "authority_score": 0.95
  }
}