{
  "title": "Haptics",
  "content": "- ### OntologyBlock\n  id:: haptics-ontology\n  collapsed:: true\n\t- ontology:: true\n\t- term-id:: 20153\n\t- source-domain:: metaverse\n\t- status:: draft\n\t- public-access:: true\n\n\n\n# Haptics Ontology Entry – Revised Definition and Context\n\n## Academic Context\n\n- Haptics technology encompasses systems and devices that recreate the sense of touch through applied forces, vibrations and motions[4]\n  - Extends beyond simple vibration to simulate pressure, skin stretch, sliding and twisting sensations[6]\n  - Integrates with artificial intelligence and converges with AR/VR and biometric technologies[1]\n  - Grounded in understanding how the brain processes simultaneous tactile cues for refined device development[2]\n\n## Current Landscape (2025)\n\n### Industry Adoption and Market Position\n\n- Global haptics market projected to reach USD 14.7 billion by 2035, growing from USD 3.90 billion in 2024 at a CAGR of 14.19%[4]\n  - Haptic devices market specifically surged from USD 5.91 billion in 2024 to USD 7.08 billion in 2025, with anticipated growth to USD 14.39 billion by 2029 at 19.4% CAGR[5]\n  - Primary growth drivers include demand for immersive experiences, miniaturisation advances and power efficiency improvements[1]\n- Key application sectors expanding rapidly\n  - Consumer electronics and gaming interfaces\n  - Virtual and augmented reality environments, enhancing immersion for users to \"feel\" digital objects[2]\n  - Automotive interfaces and safety systems[5]\n  - Healthcare applications including motor skill training, post-stroke rehabilitation and prosthetic limb feedback[2]\n  - Remote robotics and teleoperation, enabling precise tactile feedback for delicate tasks such as robotic surgery[2]\n  - Assistive technology for individuals with visual or hearing impairments, translating sensory information into tactile signals[2]\n\n### Technical Capabilities and Current Limitations\n\n- Advanced multisensory haptic devices now integrate vibration, skin stretch, pressure and temperature feedback[2]\n  - Recent innovations include compact, lightweight wireless devices applying force in multiple directions, operable via Bluetooth connectivity[6]\n  - Devices can combine sensations and operate at variable speeds to simulate nuanced, realistic touch[6]\n- Acknowledged limitations requiring further refinement\n  - Response time optimisation remains necessary[2]\n  - Durability and energy efficiency improvements needed for widespread adoption[2]\n  - Understanding of how the brain processes simultaneous haptic cues still developing[2]\n  - Balance required between technological sophistication, user comfort and practical usability[2]\n\n### Standards and Frameworks\n\n- Emerging technologies include electromagnetic actuators, piezoelectric systems, electroactive polymers, surface haptics and mid-air feedback solutions[3]\n- Integration of 5G technology into haptic applications anticipated[5]\n- Flexible actuator technology and adaptive feedback through artificial intelligence represent key development areas[5]\n\n## Research & Literature\n\n- Northwestern University (2025) – Wearable multisensory haptic technology research\n  - Demonstrated compact wireless devices generating sophisticated tactile sensations beyond simple vibration[6]\n  - Published in *Science* journal; led by John A. Rogers, PhD\n  - Highlights potential for virtual experiences, accessibility applications and remote healthcare\n\n- Rice University (2025) – Multisensory haptic device review\n  - Comprehensive analysis of wearable haptic technology applications across medical rehabilitation, prosthetics and human-machine interaction[2]\n  - Identifies critical research priorities in perception and device refinement\n\n- Archive Market Research (2025) – Haptics Technology Market Analysis\n  - Comprehensive market study covering 2019–2033 period with 11.3% CAGR[1]\n  - Documents technological advancements in miniaturisation and algorithm sophistication\n\n- Spherical Insights & Consulting (2025) – Global Haptic Technology Market Report\n  - Detailed market projections and company analysis covering 2024–2035 forecast period[4]\n\n- The Business Research Company (2025) – Haptic Devices Global Market Report\n  - Market size analysis and trend forecasting through 2034, emphasising wearable device adoption and healthcare digitalisation[5]\n\n## UK Context\n\n- British research institutions contributing to haptic technology advancement, though specific North England innovation hubs require further verification\n- UK healthcare sector increasingly exploring haptic applications for rehabilitation and remote surgical procedures\n- Automotive sector integration aligns with UK manufacturing interests in advanced driver interfaces\n\n## Future Directions\n\n### Emerging Trends\n\n- Multisensory haptic integration expanding beyond vibration to encompass full tactile spectrum[2]\n- Artificial intelligence-driven adaptive feedback systems enabling personalised haptic responses[5]\n- Touchless interface development addressing post-pandemic interaction preferences[5]\n- Industrial automation applications expanding through haptic-enabled remote control systems[5]\n\n### Anticipated Challenges\n\n- Balancing technological sophistication with user comfort and practical usability remains critical[2]\n- Energy efficiency and battery longevity for wearable applications require continued innovation[2]\n- Standardisation across diverse haptic technologies and platforms still developing\n- Ensuring equitable access and affordability for assistive technology applications\n\n### Research Priorities\n\n- Neurological understanding of simultaneous haptic cue processing[2]\n- Durability improvements for extended-use wearable devices[2]\n- Response time optimisation for real-time applications[2]\n- Integration protocols for seamless AR/VR and robotic system compatibility[2]\n\n---\n\n**Note on Definition Revision:** The original definition accurately captures core functionality but warrants expansion to reflect 2025 developments. Suggested refined definition: *\"Multisensory systems and wearable devices that recreate complex tactile sensations—including vibration, pressure, skin stretch and temperature—through directional force application and actuator technologies, enabling immersive digital interaction, assistive communication and remote manipulation across healthcare, entertainment and industrial applications.\"*\n\n\n## Metadata\n\n- **Last Updated**: 2025-11-11\n- **Review Status**: Comprehensive editorial review\n- **Verification**: Academic sources verified\n- **Regional Context**: UK/North England where applicable",
  "properties": {
    "id": "haptics-ontology",
    "collapsed": "true",
    "- ontology": "true",
    "- term-id": "20153",
    "- source-domain": "metaverse",
    "- status": "draft",
    "- public-access": "true"
  },
  "backlinks": [],
  "wiki_links": [],
  "ontology": {
    "term_id": "20153",
    "preferred_term": "Haptics",
    "definition": "",
    "source_domain": "metaverse",
    "maturity_level": null,
    "authority_score": null
  }
}