{
  "title": "HapticFeedback",
  "content": "- ### OntologyBlock\n  id:: hapticfeedback-ontology\n  collapsed:: true\n\t- ontology:: true\n\t- term-id:: MV-0040\n\t- preferred-term:: HapticFeedback\n\t- source-domain:: metaverse\n\t- status:: draft\n    - public-access:: true\n\t- definition:: A component of the metaverse ecosystem.\n\t- maturity:: draft\n\t- owl:class:: mv:HapticFeedback\n\t- owl:physicality:: ConceptualEntity\n\t- owl:role:: Concept\n\t- is-subclass-of:: [[Blockchain]]\n\t- belongsToDomain:: [[MetaverseDomain]]\n\n## OWL Formal Semantics\n\n```clojure\n;; OWL Functional Syntax\n\n(Declaration (Class :Hapticfeedback))\n\n;; Annotations\n(AnnotationAssertion rdfs:label :Hapticfeedback \"HapticFeedback\"@en)\n(AnnotationAssertion rdfs:comment :Hapticfeedback \"A component of the metaverse ecosystem.\"@en)\n\n;; Data Properties\n(AnnotationAssertion dcterms:identifier :Hapticfeedback \"mv-1761742247930\"^^xsd:string)\n```",
  "properties": {
    "id": "hapticfeedback-ontology",
    "collapsed": "true",
    "- ontology": "true",
    "- term-id": "MV-0040",
    "- preferred-term": "HapticFeedback",
    "- source-domain": "metaverse",
    "- status": "draft",
    "- public-access": "true",
    "- definition": "A component of the metaverse ecosystem.",
    "- maturity": "draft",
    "- owl:class": "mv:HapticFeedback",
    "- owl:physicality": "ConceptualEntity",
    "- owl:role": "Concept",
    "- is-subclass-of": "[[Blockchain]]",
    "- belongsToDomain": "[[MetaverseDomain]]"
  },
  "backlinks": [],
  "wiki_links": [
    "MetaverseDomain",
    "Blockchain"
  ],
  "ontology": {
    "term_id": "MV-0040",
    "preferred_term": "HapticFeedback",
    "definition": "A component of the metaverse ecosystem.",
    "source_domain": "metaverse",
    "maturity_level": null,
    "authority_score": null
  }
}