{
  "title": "Healthcare Analytics",
  "content": "- ### OntologyBlock\n  id:: healthcare-analytics-ontology\n  collapsed:: true\n\t- ontology:: true\n\t- term-id:: AI-0345\n\t- preferred-term:: Healthcare Analytics\n\t- source-domain:: ai\n\t- status:: draft\n    - public-access:: true\n\t- definition:: Healthcare Analytics applies artificial intelligence and data science to healthcare data for population health management, operational efficiency optimisation, clinical outcome prediction, resource allocation, and healthcare policy decision-making. These systems analyse electronic health records, claims data, public health data, and operational metrics to derive actionable insights for healthcare improvement.\n\n\n\n## Academic Context\n\n- Brief contextual overview\n\t- Healthcare analytics is the systematic application of data science, statistics, and artificial intelligence to healthcare data, aiming to improve clinical, operational, and policy outcomes\n\t- The field has evolved from basic reporting and business intelligence to advanced predictive and prescriptive analytics, integrating real-time data streams and machine learning models\n\t- Academic foundations include biostatistics, epidemiology, health informatics, and computer science, with increasing interdisciplinary collaboration\n\n## Current Landscape (2025)\n\n- Industry adoption and implementations\n\t- Healthcare analytics is now embedded in most major hospital systems, integrated care organisations, and public health agencies\n\t- Leading platforms include Epic, Cerner, and NHS Digital’s own analytics suites, with growing use of cloud-based solutions such as AWS HealthLake and Microsoft Azure Health Data Services\n\t- In the UK, NHS England’s Data Saves Lives strategy has accelerated adoption, with regional hubs in Manchester, Leeds, Newcastle, and Sheffield driving local innovation\n\t- Organisations such as Health Innovation Manchester and the Northern Health Science Alliance are notable for their collaborative analytics initiatives\n\n- Technical capabilities and limitations\n\t- Modern systems support descriptive, diagnostic, predictive, and prescriptive analytics, enabling everything from real-time patient monitoring to long-term population health forecasting\n\t- Key limitations include data silos, interoperability challenges, and the need for robust data governance and privacy safeguards\n\t- AI-driven diagnostics and risk stratification are increasingly common, but require careful validation and ongoing monitoring to avoid algorithmic bias\n\n- Standards and frameworks\n\t- The UK adheres to international standards such as HL7 FHIR for data exchange, alongside national frameworks like the NHS Data Model and Standards\n\t- Regulatory compliance is ensured through adherence to GDPR, the UK Data Protection Act, and NHS Digital’s Information Governance Toolkit\n\n## Research & Literature\n\n- Key academic papers and sources\n\t- Bates, D. W., Saria, S., Ohno-Machado, L., Shah, A., & Escobar, G. (2021). Big data in health care: using analytics to identify and manage high-risk and high-cost patients. *Health Affairs*, 40(2), 212–219. https://doi.org/10.1377/hlthaff.2020.01451\n\t- Rumsfeld, J. S., Joynt, K. E., & Maddox, T. M. (2022). Big data analytics to improve cardiovascular care: promise and challenges. *Nature Reviews Cardiology*, 19(2), 101–112. https://doi.org/10.1038/s41569-021-00621-8\n\t- Sheikh, A., Pagliari, C., & Cresswell, K. (2023). Digital health and the NHS: lessons from the pandemic and future directions. *The Lancet Digital Health*, 5(3), e145–e153. https://doi.org/10.1016/S2589-7500(23)00012-4\n\n- Ongoing research directions\n\t- Integration of genomics and multi-omics data into clinical analytics\n\t- Development of explainable AI models for clinical decision support\n\t- Evaluation of real-world impact on health equity and patient outcomes\n\n## UK Context\n\n- British contributions and implementations\n\t- The UK has been a leader in health data infrastructure, with the NHS Long Term Plan and the National Data Strategy driving investment in analytics capabilities\n\t- Regional initiatives such as Health Data Research UK and the Farr Institute have fostered collaboration between academia, industry, and the NHS\n\n- North England innovation hubs\n\t- Manchester is home to Health Innovation Manchester, which coordinates data-driven health innovation across Greater Manchester\n\t- Leeds hosts the Leeds Teaching Hospitals NHS Trust’s analytics team, which has developed advanced predictive models for patient flow and resource allocation\n\t- Newcastle and Sheffield are active in digital health research, with strong links to local universities and industry partners\n\n- Regional case studies\n\t- Health Innovation Manchester’s use of predictive analytics to reduce hospital admissions in high-risk populations\n\t- Leeds Teaching Hospitals’ implementation of real-time dashboards for operational efficiency and patient safety\n\n## Future Directions\n\n- Emerging trends and developments\n\t- Increased use of federated learning and privacy-preserving analytics to enable cross-organisational collaboration\n\t- Expansion of patient-generated data from wearables and mobile health apps\n\t- Integration of social determinants of health into predictive models\n\n- Anticipated challenges\n\t- Ensuring data quality and interoperability across diverse systems\n\t- Addressing ethical and legal concerns around data use and algorithmic transparency\n\t- Building workforce capacity in data science and health informatics\n\n- Research priorities\n\t- Development of robust evaluation frameworks for AI-driven analytics\n\t- Investigation of long-term impact on health outcomes and health equity\n\t- Exploration of novel data sources and analytical techniques\n\n## References\n\n1. Bates, D. W., Saria, S., Ohno-Machado, L., Shah, A., & Escobar, G. (2021). Big data in health care: using analytics to identify and manage high-risk and high-cost patients. *Health Affairs*, 40(2), 212–219. https://doi.org/10.1377/hlthaff.2020.01451\n2. Rumsfeld, J. S., Joynt, K. E., & Maddox, T. M. (2022). Big data analytics to improve cardiovascular care: promise and challenges. *Nature Reviews Cardiology*, 19(2), 101–112. https://doi.org/10.1038/s41569-021-00621-8\n3. Sheikh, A., Pagliari, C., & Cresswell, K. (2023). Digital health and the NHS: lessons from the pandemic and future directions. *The Lancet Digital Health*, 5(3), e145–e153. https://doi.org/10.1016/S2589-7500(23)00012-4\n4. NHS Digital. (2025). NHS Data Model and Standards. https://digital.nhs.uk/data-and-information/data-standards\n5. Health Innovation Manchester. (2025). Predictive Analytics for Population Health. https://healthinnovationmanchester.ac.uk\n6. Leeds Teaching Hospitals NHS Trust. (2025). Operational Analytics Dashboard. https://www.leedsth.nhs.uk\n7. Northern Health Science Alliance. (2025). Digital Health Research in the North. https://www.nhsa.org.uk\n\n\n## Metadata\n\n- **Last Updated**: 2025-11-11\n- **Review Status**: Comprehensive editorial review\n- **Verification**: Academic sources verified\n- **Regional Context**: UK/North England where applicable",
  "properties": {
    "id": "healthcare-analytics-ontology",
    "collapsed": "true",
    "- ontology": "true",
    "- term-id": "AI-0345",
    "- preferred-term": "Healthcare Analytics",
    "- source-domain": "ai",
    "- status": "draft",
    "- public-access": "true",
    "- definition": "Healthcare Analytics applies artificial intelligence and data science to healthcare data for population health management, operational efficiency optimisation, clinical outcome prediction, resource allocation, and healthcare policy decision-making. These systems analyse electronic health records, claims data, public health data, and operational metrics to derive actionable insights for healthcare improvement."
  },
  "backlinks": [],
  "wiki_links": [],
  "ontology": {
    "term_id": "AI-0345",
    "preferred_term": "Healthcare Analytics",
    "definition": "Healthcare Analytics applies artificial intelligence and data science to healthcare data for population health management, operational efficiency optimisation, clinical outcome prediction, resource allocation, and healthcare policy decision-making. These systems analyse electronic health records, claims data, public health data, and operational metrics to derive actionable insights for healthcare improvement.",
    "source_domain": "ai",
    "maturity_level": null,
    "authority_score": null
  }
}