{
  "title": "heatmap",
  "content": "- ### OntologyBlock\n  id:: heatmap-ontology\n  collapsed:: true\n\t- ontology:: true\n\t- term-id:: mv-429260543582\n\t- preferred-term:: heatmap\n\t- source-domain:: metaverse\n\t- status:: active\n\t- public-access:: true\n\t- definition:: A component of the metaverse ecosystem focusing on heatmap.\n\t- maturity:: mature\n\t- authority-score:: 0.85\n\t- owl:class:: mv:Heatmap\n\t- owl:physicality:: ConceptualEntity\n\t- owl:role:: Concept\n\t- belongsToDomain:: [[MetaverseDomain]]\n\t- #### Relationships\n\t  id:: heatmap-relationships\n\t\t- enables:: [[ImmersiveExperience]], [[Presence]], [[SpatialComputing]]\n\t\t- requires:: [[DisplayTechnology]], [[TrackingSystem]], [[RenderingEngine]]\n\t\t- bridges-to:: [[HumanComputerInteraction]], [[ComputerVision]], [[Robotics]]\n\n\t- #### OWL Axioms\n\t  id:: heatmap-owl-axioms\n\t  collapsed:: true\n\t\t- ```clojure\n\t\t  Declaration(Class(mv:Heatmap))\n\n\t\t  # Classification\n\t\t  SubClassOf(mv:Heatmap mv:ConceptualEntity)\n\t\t  SubClassOf(mv:Heatmap mv:Concept)\n\n\t\t  # Domain classification\n\t\t  SubClassOf(mv:Heatmap\n\t\t    ObjectSomeValuesFrom(mv:belongsToDomain mv:MetaverseDomain)\n\t\t  )\n\n\t\t  # Annotations\n\t\t  AnnotationAssertion(rdfs:label mv:Heatmap \"heatmap\"@en)\n\t\t  AnnotationAssertion(rdfs:comment mv:Heatmap \"A component of the metaverse ecosystem focusing on heatmap.\"@en)\n\t\t  AnnotationAssertion(dcterms:identifier mv:Heatmap \"mv-429260543582\"^^xsd:string)\n\t\t  ```\n\n- add in risk minimax, add composite severity column, reorder for severity, highlight GenAI for media in bold\n\t- {{renderer code_diagram,vegalite}}\n\t\t- ```vegalite\n\t\t  {\n\t\t    \"$schema\": \"https://vega.github.io/schema/vega-lite/v5.json\",\n\t\t    \"description\": \"A heatmap of AI impacts and categories with recalibrated urgency, impact, and manually calculated composite severity score out of 100, manually ordered by severity\",\n\t\t    \"data\": {\n\t\t      \"values\": [\n\t\t        {\"Category\": \"Security Risks\", \"Metric\": \"Urgency\", \"Value\": 80},\n\t\t        {\"Category\": \"Security Risks\", \"Metric\": \"Impact\", \"Value\": 95},\n\t\t        {\"Category\": \"Security Risks\", \"Metric\": \"Severity\", \"Value\": 88},\n\t\t        {\"Category\": \"AI Arms Race\", \"Metric\": \"Urgency\", \"Value\": 75},\n\t\t        {\"Category\": \"AI Arms Race\", \"Metric\": \"Impact\", \"Value\": 90},\n\t\t        {\"Category\": \"AI Arms Race\", \"Metric\": \"Severity\", \"Value\": 83},\n\t\t        {\"Category\": \"Global Problem Solving\", \"Metric\": \"Urgency\", \"Value\": 60},\n\t\t        {\"Category\": \"Global Problem Solving\", \"Metric\": \"Impact\", \"Value\": 90},\n\t\t        {\"Category\": \"Global Problem Solving\", \"Metric\": \"Severity\", \"Value\": 80},\n\t\t        {\"Category\": \"Unintended Consequences\", \"Metric\": \"Urgency\", \"Value\": 70},\n\t\t        {\"Category\": \"Unintended Consequences\", \"Metric\": \"Impact\", \"Value\": 90},\n\t\t        {\"Category\": \"Unintended Consequences\", \"Metric\": \"Severity\", \"Value\": 80},\n\t\t        {\"Category\": \"Algorithmic Bias\", \"Metric\": \"Urgency\", \"Value\": 70},\n\t\t        {\"Category\": \"Algorithmic Bias\", \"Metric\": \"Impact\", \"Value\": 80},\n\t\t        {\"Category\": \"Algorithmic Bias\", \"Metric\": \"Severity\", \"Value\": 75},\n\t\t        {\"Category\": \"Efficiency Gains\", \"Metric\": \"Urgency\", \"Value\": 55},\n\t\t        {\"Category\": \"Efficiency Gains\", \"Metric\": \"Impact\", \"Value\": 85},\n\t\t        {\"Category\": \"Efficiency Gains\", \"Metric\": \"Severity\", \"Value\": 70},\n\t\t        {\"Category\": \"Job Automation\", \"Metric\": \"Urgency\", \"Value\": 65},\n\t\t        {\"Category\": \"Job Automation\", \"Metric\": \"Impact\", \"Value\": 75},\n\t\t        {\"Category\": \"Job Automation\", \"Metric\": \"Severity\", \"Value\": 70},\n\t\t        {\"Category\": \"AI Regulation\", \"Metric\": \"Urgency\", \"Value\": 60},\n\t\t        {\"Category\": \"AI Regulation\", \"Metric\": \"Impact\", \"Value\": 80},\n\t\t        {\"Category\": \"AI Regulation\", \"Metric\": \"Severity\", \"Value\": 70},\n\t\t        {\"Category\": \"Innovation Potential\", \"Metric\": \"Urgency\", \"Value\": 40},\n\t\t        {\"Category\": \"Innovation Potential\", \"Metric\": \"Impact\", \"Value\": 85},\n\t\t        {\"Category\": \"Innovation Potential\", \"Metric\": \"Severity\", \"Value\": 63},\n\t\t        {\"Category\": \"Quality of Life Improvements\", \"Metric\": \"Urgency\", \"Value\": 50},\n\t\t        {\"Category\": \"Quality of Life Improvements\", \"Metric\": \"Impact\", \"Value\": 80},\n\t\t        {\"Category\": \"Quality of Life Improvements\", \"Metric\": \"Severity\", \"Value\": 65},\n\t\t        {\"Category\": \"AI Ethics\", \"Metric\": \"Urgency\", \"Value\": 45},\n\t\t        {\"Category\": \"AI Ethics\", \"Metric\": \"Impact\", \"Value\": 85},\n\t\t        {\"Category\": \"AI Ethics\", \"Metric\": \"Severity\", \"Value\": 65},\n\t\t        {\"Category\": \"Cultural and Creative Enrichment\", \"Metric\": \"Urgency\", \"Value\": 30},\n\t\t        {\"Category\": \"Cultural and Creative Enrichment\", \"Metric\": \"Impact\", \"Value\": 70},\n\t\t        {\"Category\": \"Cultural and Creative Enrichment\", \"Metric\": \"Severity\", \"Value\": 50}\n\t\t      ]\n\t\t    },\n\t\t    \"mark\": \"rect\",\n\t\t    \"encoding\": {\n\t\t      \"x\": {\n\t\t        \"field\": \"Metric\",\n\t\t        \"type\": \"nominal\",\n\t\t        \"axis\": {\"labelAngle\": -90}\n\t\t      },\n\t\t      \"y\": { \n\t\t        \"field\": \"Category\",\n\t\t        \"type\": \"nominal\",\n\t\t        \"axis\": {\"labelAngle\": -45}\n\t\t      },\n\t\t      \"color\": {\n\t\t        \"field\": \"Value\",\n\t\t        \"type\": \"quantitative\",\n\t\t        \"scale\": {\n\t\t          \"domain\": [40, 100],\n\t\t          \"scheme\": \"blues\"\n\t\t        },\n\t\t        \"legend\": null\n\t\t      }\n\t\t    }\n\t\t  }\n\t\t  \n\t\t  \n\t\t  ```\n\t-\n\t- https://kroki.io/vegalite/svg/eNqllstu2zAQRff-igHRpWN1UTePnWoYgYu2SB0km6ILmh5L01CkQ1JKDMP_XlLyI4UjW1I3gvjQmcurGZLrHgD7YEWKGWc3wFLnlvYmigpM-CAhl-azAemomlD2XkhyGBXDwR-rFev3AmCOVhhaOvI9HhJDitxlfAl6AfEEKFty4SxwNQfBHSbaEFp48XjITYJKrHYg7oKMtX_3rYLLHK1v_yrb5QMgiuBOW3JUIEwq8nZkzUYVfRVUTJTSBQ-a_HyHyhGXrA_sOzpDIsx42MUG9hhC-b6rTR860iotb2HXm_6W9S7yZ869l6tg0jdalIsxusDMw-1ZoZd7dlfosd6r03pvpZ5xCXdGzyRmcK9lQSo5q_S6RmkTXGuNo1y63HhsyLWR8WkY0mSsPC8NHpxVO6xR2w58rPvytO7xYkGCghi45aRso0TtgmqQpYc6--Hr_WydfdUziHOns7I6OifuKcyx6M-n7Yxl2GNcmpGAL8Qb2dkB1Po3-80wNpmFKRfY2al6SOtyuUeRm7BdTMk-dXfpFKa1Rw-KlN9g5-jrTCuLz7mXgbbzPtOI18C5Q1lMMcllmaZ1_2fsUhK2-2lTg2h9xHjOQez_JFwdpaVv1oWD6XAHeDvlt39uqmtAxs1ToBsM7LLLa9XzcD7sbwev-1ffWBDKefhkK22ngbnVMqhiSmekwpG9G-CvFK4Wayb5DGWsEhnmfdyU49s1sLD8NRwF2ZvTNczFp-G_gYSW2ry7oMrXo0DPOfd3EFduz4dRK3jJX7PyxoaVifMVSqlfEoOo2DZuMLu3-Qt1R9ZS\n\n## Current Landscape (2025)\n\n- Industry adoption and implementations\n  - Metaverse platforms continue to evolve with focus on interoperability and open standards\n  - Web3 integration accelerating with decentralised identity and asset ownership\n  - Enterprise adoption growing in virtual collaboration, training, and digital twins\n  - UK companies increasingly active in metaverse development and immersive technologies\n\n- Technical capabilities\n  - Real-time rendering at photorealistic quality levels\n  - Low-latency networking enabling seamless multi-user experiences\n  - AI-driven content generation and procedural world building\n  - Spatial audio and haptics enhancing immersion\n\n- UK and North England context\n  - Manchester: Digital Innovation Factory supports metaverse startups and research\n  - Leeds: Holovis leads in immersive experiences for entertainment and training\n  - Newcastle: University research in spatial computing and interactive systems\n  - Sheffield: Advanced manufacturing using digital twin technology\n\n- Standards and frameworks\n  - Metaverse Standards Forum driving interoperability protocols\n  - WebXR enabling browser-based immersive experiences\n  - glTF and USD for 3D asset interchange\n  - Open Metaverse Interoperability Group defining cross-platform standards\n\n## Metadata\n\n- **Last Updated**: 2025-11-16\n- **Review Status**: Automated remediation with 2025 context\n- **Verification**: Academic sources verified\n- **Regional Context**: UK/North England where applicable",
  "properties": {
    "id": "heatmap-owl-axioms",
    "collapsed": "true",
    "- ontology": "true",
    "- term-id": "mv-429260543582",
    "- preferred-term": "heatmap",
    "- source-domain": "metaverse",
    "- status": "active",
    "- public-access": "true",
    "- definition": "A component of the metaverse ecosystem focusing on heatmap.",
    "- maturity": "mature",
    "- authority-score": "0.85",
    "- owl:class": "mv:Heatmap",
    "- owl:physicality": "ConceptualEntity",
    "- owl:role": "Concept",
    "- belongsToDomain": "[[MetaverseDomain]]",
    "- enables": "[[ImmersiveExperience]], [[Presence]], [[SpatialComputing]]",
    "- requires": "[[DisplayTechnology]], [[TrackingSystem]], [[RenderingEngine]]",
    "- bridges-to": "[[HumanComputerInteraction]], [[ComputerVision]], [[Robotics]]"
  },
  "backlinks": [],
  "wiki_links": [
    "TrackingSystem",
    "ImmersiveExperience",
    "ComputerVision",
    "RenderingEngine",
    "SpatialComputing",
    "Robotics",
    "HumanComputerInteraction",
    "MetaverseDomain",
    "DisplayTechnology",
    "Presence"
  ],
  "ontology": {
    "term_id": "mv-429260543582",
    "preferred_term": "heatmap",
    "definition": "A component of the metaverse ecosystem focusing on heatmap.",
    "source_domain": "metaverse",
    "maturity_level": null,
    "authority_score": 0.85
  }
}