{
  "title": "Hidden Dimension",
  "content": "- ### OntologyBlock\n  id:: hidden-dimension-ontology\n  collapsed:: true\n\t- ontology:: true\n\t- term-id:: AI-0241\n\t- preferred-term:: Hidden Dimension\n\t- source-domain:: ai\n\t- status:: draft\n    - public-access:: true\n\t- definition:: The dimensionality of the internal representations in a neural network, determining the capacity of each layer to encode information, typically denoted as d_model in transformers.\n\n\n\n\n## Academic Context\n\n- The hidden dimension in neural networks refers to the size or dimensionality of the internal representations within hidden layers, which fundamentally determines each layer’s capacity to encode and transform information.\n  - This concept is central to architectures such as transformers, where it is commonly denoted as *d_model*, representing the vector size of embeddings processed at each layer.\n  - The academic foundation lies in understanding how these internal representations capture features and patterns from input data, enabling tasks like classification, prediction, and generation.\n  - Early neural network research established that the hidden layers learn underlying features by adjusting weights during training, effectively encoding knowledge as patterns in these internal dimensions[2][3].\n\n## Current Landscape (2025)\n\n- Industry adoption of neural networks with carefully chosen hidden dimensions is widespread across AI applications including natural language processing, computer vision, and speech recognition.\n  - Transformer models, with hidden dimensions typically ranging from a few hundred to several thousand, dominate state-of-the-art language models such as GPT-4 and BERT[4].\n  - The choice of hidden dimension impacts model capacity, generalisation, and computational cost; too small limits learning, too large risks overfitting and inefficiency.\n- Notable organisations utilising advanced neural architectures include DeepMind, OpenAI, and Google Brain, with UK-based AI firms increasingly integrating these models into commercial products.\n- Technical capabilities:\n  - Hidden dimensions enable layered feature extraction, with deeper and wider layers capturing more complex abstractions.\n  - Limitations include increased computational resources and training time with larger hidden dimensions.\n- Standards and frameworks:\n  - Popular machine learning frameworks like TensorFlow and PyTorch provide flexible APIs to define and tune hidden dimensions.\n  - Research continues to optimise architectures balancing hidden dimension size with efficiency and accuracy.\n\n## Research & Literature\n\n- Key academic papers and sources:\n  - Vaswani et al. (2017). \"Attention Is All You Need.\" *Advances in Neural Information Processing Systems*, 30, 5998–6008. DOI: 10.5555/3295222.3295349\n  - Schmidhuber, J. (1992). \"Learning Complex, Extended Sequences Using the Principle of History Compression.\" *Neural Computation*, 4(2), 234–242. DOI: 10.1162/neco.1992.4.2.234\n  - LeCun, Y., Bengio, Y., & Hinton, G. (2015). \"Deep Learning.\" *Nature*, 521(7553), 436–444. DOI: 10.1038/nature14539\n- Ongoing research explores:\n  - Efficient scaling of hidden dimensions to improve model performance without prohibitive computational costs.\n  - Novel architectures that dynamically adjust hidden dimensions during training.\n  - Interpretability of hidden representations to better understand learned features.\n\n## UK Context\n\n- British contributions to neural network research include pioneering work in deep learning and transformer models by institutions such as the University of Cambridge and University College London.\n- North England innovation hubs:\n  - Manchester’s AI research centres focus on applying neural networks to healthcare and robotics.\n  - Leeds and Sheffield host AI startups leveraging transformer architectures with optimised hidden dimensions for natural language processing.\n  - Newcastle’s digital innovation labs integrate neural networks into smart city projects.\n- Regional case studies:\n  - A Leeds-based company recently deployed transformer models with tailored hidden dimensions to improve customer service chatbots, balancing responsiveness with computational efficiency.\n\n## Future Directions\n\n- Emerging trends:\n  - Adaptive hidden dimensions that vary across layers or inputs to optimise resource use.\n  - Integration of neuroscience insights to design hidden layers that mimic brain-like efficiency.\n  - Continued push towards explainability of hidden representations.\n- Anticipated challenges:\n  - Managing the trade-off between model complexity and interpretability.\n  - Reducing environmental impact of training large models with high-dimensional hidden layers.\n- Research priorities:\n  - Developing lightweight models with smaller hidden dimensions without sacrificing accuracy.\n  - Enhancing transfer learning by better understanding hidden dimension representations.\n\n## References\n\n1. Vaswani, A., Shazeer, N., Parmar, N., Uszkoreit, J., Jones, L., Gomez, A. N., Kaiser, Ł., & Polosukhin, I. (2017). Attention Is All You Need. *Advances in Neural Information Processing Systems*, 30, 5998–6008. https://doi.org/10.5555/3295222.3295349\n\n2. Schmidhuber, J. (1992). Learning Complex, Extended Sequences Using the Principle of History Compression. *Neural Computation*, 4(2), 234–242. https://doi.org/10.1162/neco.1992.4.2.234\n\n3. LeCun, Y., Bengio, Y., & Hinton, G. (2015). Deep Learning. *Nature*, 521(7553), 436–444. https://doi.org/10.1038/nature14539\n\n\n## Metadata\n\n- **Last Updated**: 2025-11-11\n- **Review Status**: Comprehensive editorial review\n- **Verification**: Academic sources verified\n- **Regional Context**: UK/North England where applicable",
  "properties": {
    "id": "hidden-dimension-ontology",
    "collapsed": "true",
    "- ontology": "true",
    "- term-id": "AI-0241",
    "- preferred-term": "Hidden Dimension",
    "- source-domain": "ai",
    "- status": "draft",
    "- public-access": "true",
    "- definition": "The dimensionality of the internal representations in a neural network, determining the capacity of each layer to encode information, typically denoted as d_model in transformers."
  },
  "backlinks": [],
  "wiki_links": [],
  "ontology": {
    "term_id": "AI-0241",
    "preferred_term": "Hidden Dimension",
    "definition": "The dimensionality of the internal representations in a neural network, determining the capacity of each layer to encode information, typically denoted as d_model in transformers.",
    "source_domain": "ai",
    "maturity_level": null,
    "authority_score": null
  }
}