{
  "title": "Purpose of Talk :",
  "content": "- ### OntologyBlock\n  id:: purpose-of-talk-:-ontology\n  collapsed:: true\n\t- ontology:: true\n\t- term-id:: mv-314937831658\n\t- preferred-term:: Purpose of Talk :\n\t- source-domain:: metaverse\n\t- status:: active\n\t- public-access:: true\n\t- definition:: A component of the metaverse ecosystem focusing on purpose of talk :.\n\t- maturity:: mature\n\t- authority-score:: 0.85\n\t- owl:class:: mv:PurposeOfTalk\n\t- owl:physicality:: ConceptualEntity\n\t- owl:role:: Concept\n\t- belongsToDomain:: [[MetaverseDomain]]\n\t- #### Relationships\n\t  id:: purpose-of-talk-:-relationships\n\t\t- enables:: [[ImmersiveExperience]], [[Presence]], [[SpatialComputing]]\n\t\t- requires:: [[DisplayTechnology]], [[TrackingSystem]], [[RenderingEngine]]\n\t\t- bridges-to:: [[HumanComputerInteraction]], [[ComputerVision]], [[Robotics]]\n\n\t- #### OWL Axioms\n\t  id:: purpose-of-talk-:-owl-axioms\n\t  collapsed:: true\n\t\t- ```clojure\n\t\t  Declaration(Class(mv:PurposeOfTalk))\n\n\t\t  # Classification\n\t\t  SubClassOf(mv:PurposeOfTalk mv:ConceptualEntity)\n\t\t  SubClassOf(mv:PurposeOfTalk mv:Concept)\n\n\t\t  # Domain classification\n\t\t  SubClassOf(mv:PurposeOfTalk\n\t\t    ObjectSomeValuesFrom(mv:belongsToDomain mv:MetaverseDomain)\n\t\t  )\n\n\t\t  # Annotations\n\t\t  AnnotationAssertion(rdfs:label mv:PurposeOfTalk \"Purpose of Talk :\"@en)\n\t\t  AnnotationAssertion(rdfs:comment mv:PurposeOfTalk \"A component of the metaverse ecosystem focusing on purpose of talk :.\"@en)\n\t\t  AnnotationAssertion(dcterms:identifier mv:PurposeOfTalk \"mv-314937831658\"^^xsd:string)\n\t\t  ```\n\n# Purpose of Talk :\n\t- ## A now / next / later flit through generative AI.\n\t- [SDXL QR Code Art Generator\n\t  id:: 659a922a-0f77-4dc5-a0dd-f76f2793423f\n\t\t- v2.0 | Stable Diffusion Workflows | Civitai](https://civitai.com/images/3826284)\n\t\t- ## Question for audience (assuming I don't find out 10-12am)\n\t\t\t- Who knows what [[p(doom)]] refers to?\n\t\t\t\t- (quick show of hands please)\n\t\t\t- Who has access to [[OpenAI]] [[ChatGPT]] Pro subscription, or another [[Proprietary Large Language Models]] subscription\n\t\t\t\t- (quick show of hands please)\n- {{embed ((659a922a-2c71-4899-b2c6-a6e88ef339fa))}}\n- # These are the raw sections, with much more detail:\n- Next [[presentation]] slide [[Overview of Machine Learning Techniques]]\n\n## Current Landscape (2025)\n\n- Industry adoption and implementations\n  - Metaverse platforms continue to evolve with focus on interoperability and open standards\n  - Web3 integration accelerating with decentralised identity and asset ownership\n  - Enterprise adoption growing in virtual collaboration, training, and digital twins\n  - UK companies increasingly active in metaverse development and immersive technologies\n\n- Technical capabilities\n  - Real-time rendering at photorealistic quality levels\n  - Low-latency networking enabling seamless multi-user experiences\n  - AI-driven content generation and procedural world building\n  - Spatial audio and haptics enhancing immersion\n\n- UK and North England context\n  - Manchester: Digital Innovation Factory supports metaverse startups and research\n  - Leeds: Holovis leads in immersive experiences for entertainment and training\n  - Newcastle: University research in spatial computing and interactive systems\n  - Sheffield: Advanced manufacturing using digital twin technology\n\n- Standards and frameworks\n  - Metaverse Standards Forum driving interoperability protocols\n  - WebXR enabling browser-based immersive experiences\n  - glTF and USD for 3D asset interchange\n  - Open Metaverse Interoperability Group defining cross-platform standards\n\n## Metadata\n\n- **Last Updated**: 2025-11-16\n- **Review Status**: Automated remediation with 2025 context\n- **Verification**: Academic sources verified\n- **Regional Context**: UK/North England where applicable",
  "properties": {
    "id": "purpose-of-talk-:-owl-axioms",
    "collapsed": "true",
    "- ontology": "true",
    "- term-id": "mv-314937831658",
    "- preferred-term": "Purpose of Talk :",
    "- source-domain": "metaverse",
    "- status": "active",
    "- public-access": "true",
    "- definition": "A component of the metaverse ecosystem focusing on purpose of talk :.",
    "- maturity": "mature",
    "- authority-score": "0.85",
    "- owl:class": "mv:PurposeOfTalk",
    "- owl:physicality": "ConceptualEntity",
    "- owl:role": "Concept",
    "- belongsToDomain": "[[MetaverseDomain]]",
    "- enables": "[[ImmersiveExperience]], [[Presence]], [[SpatialComputing]]",
    "- requires": "[[DisplayTechnology]], [[TrackingSystem]], [[RenderingEngine]]",
    "- bridges-to": "[[HumanComputerInteraction]], [[ComputerVision]], [[Robotics]]"
  },
  "backlinks": [],
  "wiki_links": [
    "HumanComputerInteraction",
    "RenderingEngine",
    "DisplayTechnology",
    "OpenAI",
    "Proprietary Large Language Models",
    "MetaverseDomain",
    "ImmersiveExperience",
    "SpatialComputing",
    "Presence",
    "p(doom)",
    "TrackingSystem",
    "presentation",
    "Robotics",
    "ChatGPT",
    "ComputerVision",
    "Overview of Machine Learning Techniques"
  ],
  "ontology": {
    "term_id": "mv-314937831658",
    "preferred_term": "Purpose of Talk :",
    "definition": "A component of the metaverse ecosystem focusing on purpose of talk :.",
    "source_domain": "metaverse",
    "maturity_level": null,
    "authority_score": 0.85
  }
}