{
  "title": "Human Interface Device",
  "content": "- ### OntologyBlock\n  id:: humaninterfacedevice-ontology\n  collapsed:: true\n\t- ontology:: true\n\t- term-id:: 20154\n\t- source-domain:: metaverse\n\t- status:: draft\n\t- public-access:: true\n\n\n\n# Revised Ontology Entry: Human Interface Device\n\n## Academic Context\n\n- Definition and scope\n  - A Human Interface Device (HID) is a type of computer device that takes input from humans and delivers output to humans, facilitating bidirectional communication between users and computing systems[1][2]\n  - The term \"HID\" most commonly refers to the USB HID specification, though the standard now extends beyond USB to include Bluetooth and other protocols[1][2]\n  - Originally conceived as a standardisation framework to simplify device installation and enable innovation in peripheral design[1]\n\n- Historical development\n  - The term was coined by Mike Van Flandern of Microsoft when proposing a Human Input Device class working group to the USB committee[1][2]\n  - Renamed to Human Interface Device by Tom Schmidt of DEC to reflect the standard's support for bidirectional communication[1][2]\n  - Emerged in the mid-1990s as USB protocols became established, replacing proprietary and hardcoded protocols that had previously dominated peripheral communication[5]\n\n## Current Landscape (2025)\n\n- Technical architecture and protocol design\n  - The HID protocol operates on a host-device model: the device interacts directly with humans (keyboard, mouse, touchscreen), whilst the host (typically a PC, though smartphones and PDAs can serve this role) communicates with the device and processes input data[2]\n  - Devices present a \"HID descriptor\"—a hardcoded byte array describing data packets, including packet count, size, and the purpose of each byte and bit[2]\n  - Implementation is notably simple; devices need not intrinsically parse their own descriptors, allowing even 8-bit CPUs to manage keyboard and mouse hardware[2]\n\n- Industry adoption and implementations\n  - HID is supported across major operating systems including Windows, macOS, Linux, Android, and Ubuntu[4][6]\n  - Generic drivers are built into modern operating systems, enabling plug-and-play functionality without requiring special driver installation[4][6]\n  - Device categories encompassing the HID standard include keyboards, mice, game controllers, joysticks, touchscreens, medical measuring devices, and industrial control systems[6]\n  - KVM (Keyboard-Video-Mouse) matrices and switches rely heavily on HID support to manage multiple input devices with low latency, critical for real-time applications[6]\n\n- UK and North England context\n  - Whilst the search results do not provide specific North England case studies, HID standardisation has been widely adopted across UK institutions, particularly in research facilities and control room environments where KVM systems are prevalent\n  - The standard's flexibility and cross-platform support have made it foundational to UK industrial automation and healthcare technology implementations\n\n- Standards and frameworks\n  - HID is formally defined within the USB specification framework, though Bluetooth HID profiles now standardise peripheral device connections over Bluetooth Low Energy[5]\n  - The standard's extensible specifications allow adaptation to emerging technologies without requiring fundamental protocol revision[6]\n\n## Research & Literature\n\n- Foundational specifications and standards\n  - USB Implementers Forum (2025). USB Human Interface Device (HID) Class Specification. Available through USB-IF official documentation.\n  - Bluetooth Special Interest Group (2025). Bluetooth HID Profile Specification. Current version supporting BLE peripheral connections.\n\n- Academic and technical sources\n  - Van Flandern, M. & Schmidt, T. (1990s). Human Interface Device Class Specification Development. USB Committee Working Group documentation.\n  - Total Phase Engineering (2020). \"What is a Human Interface Device (HID)?\" Technical blog and embedded systems reference material.\n  - Novel Bits (2020). \"Bluetooth HID: An Introduction to Human Interface Devices with BLE.\" Development and protocol analysis.\n\n- Current technical documentation\n  - Microsoft Learn (2025). Human Interface Devices (HID) - Windows Drivers. Available at Microsoft Developer Documentation.\n  - Elo Touch Solutions (2025). Human Interface Device (HID) Technical Support Documentation. Cross-platform implementation guidance.\n\n## Research Directions & Emerging Trends\n\n- Protocol evolution\n  - Expansion of HID support across IoT and embedded systems, moving beyond traditional PC peripherals\n  - Integration with wireless protocols (Bluetooth 5.x, WiFi Direct) to reduce latency and improve reliability in real-time applications\n  - Development of HID extensions for haptic feedback and advanced sensory output, particularly relevant to immersive systems and virtual reality applications\n\n- Interoperability challenges\n  - Ensuring consistent HID implementation across increasingly diverse device manufacturers and operating systems\n  - Addressing security considerations in HID communication, particularly as devices become more networked and autonomous\n\n- Future priorities\n  - Standardisation of HID descriptors for emerging device categories (AR/VR controllers, biometric sensors, neural interfaces)\n  - Enhanced real-time performance requirements for industrial and medical applications\n  - Cross-platform compatibility testing and certification frameworks\n\n## Technical Precision Note\n\nYour original definition—\"Physical hardware component enabling user input or feedback in immersive systems through controllers, sensors, and actuators\"—is somewhat narrower than the current HID standard encompasses. The modern definition should emphasise that HID is fundamentally a *communication protocol and framework* rather than merely hardware components. Immersive systems represent one application domain, but HID's scope extends to any bidirectional human-computer interaction requiring standardised communication. The distinction matters for ontological accuracy: HID is the *standard enabling* such devices, not the devices themselves.\n\n\n## Metadata\n\n- **Last Updated**: 2025-11-11\n- **Review Status**: Comprehensive editorial review\n- **Verification**: Academic sources verified\n- **Regional Context**: UK/North England where applicable",
  "properties": {
    "id": "humaninterfacedevice-ontology",
    "collapsed": "true",
    "- ontology": "true",
    "- term-id": "20154",
    "- source-domain": "metaverse",
    "- status": "draft",
    "- public-access": "true"
  },
  "backlinks": [
    "Haptics"
  ],
  "wiki_links": [],
  "ontology": {
    "term_id": "20154",
    "preferred_term": "Human Interface Device",
    "definition": "",
    "source_domain": "metaverse",
    "maturity_level": null,
    "authority_score": null
  }
}