{
  "title": "Human vs AI",
  "content": "- ### OntologyBlock\n  id:: human-vs-ai-ontology\n  collapsed:: true\n\t- ontology:: true\n\t- term-id:: mv-587735971874\n\t- preferred-term:: Human vs AI\n\t- source-domain:: metaverse\n\t- status:: active\n\t- public-access:: true\n\t- definition:: A component of the metaverse ecosystem focusing on human vs ai.\n\t- maturity:: mature\n\t- authority-score:: 0.85\n\t- owl:class:: mv:HumanVsAi\n\t- owl:physicality:: ConceptualEntity\n\t- owl:role:: Concept\n\t- belongsToDomain:: [[MetaverseDomain]]\n\t- #### Relationships\n\t  id:: human-vs-ai-relationships\n\t\t- enables:: [[ImmersiveExperience]], [[Presence]], [[SpatialComputing]]\n\t\t- requires:: [[DisplayTechnology]], [[TrackingSystem]], [[RenderingEngine]]\n\t\t- bridges-to:: [[HumanComputerInteraction]], [[ComputerVision]], [[Robotics]]\n\n\t- #### OWL Axioms\n\t  id:: human-vs-ai-owl-axioms\n\t  collapsed:: true\n\t\t- ```clojure\n\t\t  Declaration(Class(mv:HumanVsAi))\n\n\t\t  # Classification\n\t\t  SubClassOf(mv:HumanVsAi mv:ConceptualEntity)\n\t\t  SubClassOf(mv:HumanVsAi mv:Concept)\n\n\t\t  # Domain classification\n\t\t  SubClassOf(mv:HumanVsAi\n\t\t    ObjectSomeValuesFrom(mv:belongsToDomain mv:MetaverseDomain)\n\t\t  )\n\n\t\t  # Annotations\n\t\t  AnnotationAssertion(rdfs:label mv:HumanVsAi \"Human vs AI\"@en)\n\t\t  AnnotationAssertion(rdfs:comment mv:HumanVsAi \"A component of the metaverse ecosystem focusing on human vs ai.\"@en)\n\t\t  AnnotationAssertion(dcterms:identifier mv:HumanVsAi \"mv-587735971874\"^^xsd:string)\n\t\t  ```\n\npublic:: true\n\n- ![](https://m.media-amazon.com/images/I/81+D9XXdrOL._SL1500_.jpg){:height 400, :width 300}\n- Santacaterina, with her background in humanities and international relations, [offers a differntiated perspective](https://www.amazon.co.uk/Adaptive-Resilience-Maria-Santacaterina/dp/1119898188) on the development and deployment of AI. Her critique highlights the potential downsides of AI and advocates for a more human-centric approach. Her concerns can be grouped into several key areas:\n- ### The Limitations of AI in Understanding Life and Human Experience\n\t- Santacaterina argues that attempts to mechanise and quantify the intricacies of life through AI are inherently flawed. She emphasises the impossibility of capturing the complexity, adaptability, and perpetual evolution of living systems within the confines of algorithms. Life, she asserts, is an intricate tapestry woven from countless threads, each one contributing to the overall picture in ways that defy simple quantification or reduction.\n\t- Furthermore, Santacaterina contends that the richness and power of human language cannot be fully grasped by AI models trained on internet data. These models, she argues, operate on a superficial level, lacking the grounding in real-world truth and cultural sensitivity necessary for true comprehension. The nuances of communication, the subtle shades of meaning that emerge from the interplay of words and context, are lost in the translation to binary code.\n\t- Central to Santacaterina's critique is the notion that human intelligence is multidimensional, encompassing social, emotional, cognitive, and intellectual aspects. This complex interplay of factors, she argues, cannot be accurately replicated by AI systems, which operate based on a narrow set of rules and statistical patterns. The reductionist approach of AI, in her view, fails to capture the essence of what makes us human.\n- ### The Erosion of Human Agency, Autonomy, and Creativity\n\t- One of Santacaterina's primary concerns is the growing reliance on AI systems in critical domains such as healthcare, justice, and employment. We can perhaps all see that even human breeding choices are seeded now by algorithms in dating apps. She warns of the dangers of algorithmic decision-making, where individuals are pigeonholed and their opportunities determined by systems that fail to consider unique circumstances and nuances. This overreliance on AI, she argues, erodes human agency and autonomy, as we increasingly cede control over important aspects of our lives to machines.\n\t- Moreover, Santacaterina cautions that the standardisation and control imposed by AI systems risk stifling human creativity and innovation. When conformity and uniformity are prioritised over diversity of thought, we lose the spark that drives progress. The serendipitous insights and unconventional approaches that have fueled human advancement throughout history are threatened by the homogenising influence of AI.\n\t- Santacaterina also raises alarming concerns about the erosion of privacy and personal identity in the age of pervasive AI. The vast amounts of personal data collected and analysed by these systems, often without transparent explanations of how it will be used, pose significant threats to individual autonomy and privacy. As our every action and preference is tracked and fed into algorithms, we risk losing control over our own identities and the narratives of our lives.\n- ### Advocating for a Human-Centric Approach to AI Development\n\t- Calls for a fundamental shift in our approach to AI development. Rather than pursuing ever more powerful AI systems as an end in itself, she urges us to prioritise human well-being and flourishing. This means placing ethical considerations at the forefront of AI development, ensuring that these technologies are designed and deployed in ways that respect human rights, promote fairness and transparency, and align with our values.\n\t- Central to this human-centric approach is the emphasis on nurturing diversity and individuality. Santacaterina argues that the strength and resilience of human societies stem from our diversityâ€”the myriad ways in which we think, feel, and experience the world. By creating AI systems that are flexible and adaptable, that can accommodate the full spectrum of human needs and aspirations, we can harness the power of this technology while preserving the richness of our differences.\n\t- The importance of fostering lifelong learning and critical thinking in the age of AI. As these technologies become increasingly integrated into our lives, it is crucial that we equip individuals with the knowledge and skills necessary to navigate this new landscape effectively. This includes not only technical proficiency but also a deep understanding of the ethical and societal implications of AI, as well as the ability to critically evaluate and engage with these systems.\n-\n- [AI Girlfriend: Challenges and Potential Drawbacks | HealthNews](https://healthnews.com/mental-health/self-care-and-therapy/ai-girlfriends-addressing-the-loneliness-epidemic/)\n\n## Current Landscape (2025)\n\n- Industry adoption and implementations\n  - Metaverse platforms continue to evolve with focus on interoperability and open standards\n  - Web3 integration accelerating with decentralised identity and asset ownership\n  - Enterprise adoption growing in virtual collaboration, training, and digital twins\n  - UK companies increasingly active in metaverse development and immersive technologies\n\n- Technical capabilities\n  - Real-time rendering at photorealistic quality levels\n  - Low-latency networking enabling seamless multi-user experiences\n  - AI-driven content generation and procedural world building\n  - Spatial audio and haptics enhancing immersion\n\n- UK and North England context\n  - Manchester: Digital Innovation Factory supports metaverse startups and research\n  - Leeds: Holovis leads in immersive experiences for entertainment and training\n  - Newcastle: University research in spatial computing and interactive systems\n  - Sheffield: Advanced manufacturing using digital twin technology\n\n- Standards and frameworks\n  - Metaverse Standards Forum driving interoperability protocols\n  - WebXR enabling browser-based immersive experiences\n  - glTF and USD for 3D asset interchange\n  - Open Metaverse Interoperability Group defining cross-platform standards\n\n## Metadata\n\n- **Last Updated**: 2025-11-16\n- **Review Status**: Automated remediation with 2025 context\n- **Verification**: Academic sources verified\n- **Regional Context**: UK/North England where applicable",
  "properties": {
    "id": "human-vs-ai-owl-axioms",
    "collapsed": "true",
    "- ontology": "true",
    "- term-id": "mv-587735971874",
    "- preferred-term": "Human vs AI",
    "- source-domain": "metaverse",
    "- status": "active",
    "- public-access": "true",
    "- definition": "A component of the metaverse ecosystem focusing on human vs ai.",
    "- maturity": "mature",
    "- authority-score": "0.85",
    "- owl:class": "mv:HumanVsAi",
    "- owl:physicality": "ConceptualEntity",
    "- owl:role": "Concept",
    "- belongsToDomain": "[[MetaverseDomain]]",
    "- enables": "[[ImmersiveExperience]], [[Presence]], [[SpatialComputing]]",
    "- requires": "[[DisplayTechnology]], [[TrackingSystem]], [[RenderingEngine]]",
    "- bridges-to": "[[HumanComputerInteraction]], [[ComputerVision]], [[Robotics]]",
    "public": "true"
  },
  "backlinks": [
    "BC-0030-digital-signature",
    "Death of the Internet"
  ],
  "wiki_links": [
    "TrackingSystem",
    "ImmersiveExperience",
    "ComputerVision",
    "RenderingEngine",
    "SpatialComputing",
    "Robotics",
    "HumanComputerInteraction",
    "MetaverseDomain",
    "DisplayTechnology",
    "Presence"
  ],
  "ontology": {
    "term_id": "mv-587735971874",
    "preferred_term": "Human vs AI",
    "definition": "A component of the metaverse ecosystem focusing on human vs ai.",
    "source_domain": "metaverse",
    "maturity_level": null,
    "authority_score": 0.85
  }
}