{
  "title": "Property",
  "content": "- ### OntologyBlock\n  id:: humanpreference-ontology\n  collapsed:: true\n\n  - **Identification**\n    - domain-prefix:: AI\n    - sequence-number:: 0801\n    - filename-history:: [\"AI-0801-humanpreference.md\"]\n    - public-access:: true\n    - ontology:: true\n    - is-subclass-of:: [[ArtificialIntelligenceTechnology]]\n    - term-id:: AI-0801\n    - preferred-term:: Property\n    - source-domain:: ai\n    - status:: complete\n    - version:: 1.0.0\n    - last-updated:: 2025-11-13\n\n  - **Definition**\n    - definition:: Capability for autonomous self-improvement.\n    - maturity:: established\n    - source:: Chimera Prime Research\n    - authority-score:: 0.95\n\n  - **Semantic Classification**\n    - owl:class:: ai:HumanPreference\n    - belongsToDomain:: [[Artificial Intelligence]]\n\n  - #### OWL Restrictions\n    \n    \n    \n    \n    \n    \n    \n    \n    \n    \n    \n    \n    \n    \n    \n    \n\n  - #### CrossDomainBridges\n    - bridges-to:: [[MachineLearning]] via is-subclass-of\n    - bridges-to:: [[MachineLearning]] via is-subclass-of\n    - bridges-to:: [[System]] via is-subclass-of\n    - bridges-to:: [[MachineLearning]] via is-subclass-of\n\n  -",
  "properties": {
    "id": "humanpreference-ontology",
    "collapsed": "true",
    "- domain-prefix": "AI",
    "- sequence-number": "0801",
    "- filename-history": "[\"AI-0801-humanpreference.md\"]",
    "- public-access": "true",
    "- ontology": "true",
    "- is-subclass-of": "[[ArtificialIntelligenceTechnology]]",
    "- term-id": "AI-0801",
    "- preferred-term": "Property",
    "- source-domain": "ai",
    "- status": "complete",
    "- version": "1.0.0",
    "- last-updated": "2025-11-13",
    "- definition": "Capability for autonomous self-improvement.",
    "- maturity": "established",
    "- source": "Chimera Prime Research",
    "- authority-score": "0.95",
    "- owl:class": "ai:HumanPreference",
    "- belongsToDomain": "[[Artificial Intelligence]]",
    "- bridges-to": "[[MachineLearning]] via is-subclass-of"
  },
  "backlinks": [],
  "wiki_links": [
    "ArtificialIntelligenceTechnology",
    "Artificial Intelligence",
    "System",
    "MachineLearning"
  ],
  "ontology": {
    "term_id": "AI-0801",
    "preferred_term": "Property",
    "definition": "Capability for autonomous self-improvement.",
    "source_domain": "ai",
    "maturity_level": null,
    "authority_score": 0.95
  }
}