{
  "title": "HumanRobotInteraction",
  "content": "- ### OntologyBlock\n  id:: humanrobotinteraction-ontology\n  collapsed:: true\n\t- ontology:: true\n\t- term-id:: mv-1761742247935\n\t- preferred-term:: HumanRobotInteraction\n\t- source-domain:: metaverse\n\t- status:: draft\n\t- public-access:: true\n\t- definition:: A component of the metaverse ecosystem.\n\t- maturity:: draft\n\t- owl:class:: mv:HumanRobotInteraction\n\t- owl:physicality:: ConceptualEntity\n\t- owl:role:: Concept\n\t- belongsToDomain:: [[MetaverseDomain]]\n\n## OWL Formal Semantics\n\n```clojure\n;; OWL Functional Syntax\n\n(Declaration (Class :Humanrobotinteraction))\n\n;; Annotations\n(AnnotationAssertion rdfs:label :Humanrobotinteraction \"HumanRobotInteraction\"@en)\n(AnnotationAssertion rdfs:comment :Humanrobotinteraction \"A component of the metaverse ecosystem.\"@en)\n\n;; Data Properties\n(AnnotationAssertion dcterms:identifier :Humanrobotinteraction \"mv-1761742247935\"^^xsd:string)\n```\n\n- ## About HumanRobotInteraction\n\t- A component of the metaverse ecosystem.\n\t-\n\t- ### Original Content\n\t  collapsed:: true\n\t\t- ```\n- # Ontology Block\n\t\t    collapsed:: true\n\t\t    - **Class:** HumanRobotInteraction\n\t\t    - **IRI:** http://metaverse-ontology.org/robotics#HumanRobotInteraction\n\t\t    - **SubClassOf:** InteractionParadigm\n\t\t    - **Source Domain:** robotics\n\t\t    - **Source File:** robotics-ontology-unified.ttl\n\t\t    - **Integration Date:** 2025-10-28\n\t\t    - **TRL:** 6\n\t\t    - **Quality Score:** 0.89\n\t\t    - ```turtle\n\t\t      rb:HumanRobotInteraction rdf:type owl:Class ;\n\t\t          rdfs:label \"Human-Robot Interaction\"@en ;\n\t\t          rdfs:comment \"Study and design of interfaces and interaction modalities between humans and robots for safe, effective, and natural collaboration.\"@en ;\n\t\t          rdfs:subClassOf rb:InteractionParadigm ;\n\t\t          meta:sourceOntology \"rb:\" ;\n\t\t          meta:technologyDomain \"robotics\" ;\n\t\t          meta:disruptiveTechCategory \"autonomous-robotic-systems\" ;\n\t\t          meta:technologyReadinessLevel \"6\"^^xsd:integer ;\n\t\t          meta:qualityScore \"0.89\"^^xsd:float .\n\t\t      ```\n\t\t  \n\t\t  - ## Description\n\t\t    - Facilitates natural interaction between humans and robots\n\t\t    - Includes voice, gesture, touch, and visual interfaces\n\t\t    - Ensures safety in shared workspaces\n\t\t    - Enables intuitive robot programming and control\n\t\t    - Supports collaborative task execution\n\t\t  \n\t\t  - ## Properties\n\t\t    - Object properties\n\t\t      - [[usesModality]] - Interaction modalities (voice, gesture, etc.)\n\t\t      - [[ensuresSafety]] - Safety mechanisms and protocols\n\t\t      - [[enablesCollaboration]] - Collaborative task types\n\t\t      - [[providesInterface]] - User interface types\n\t\t    - Data properties\n\t\t      - safetyRating - Safety certification level\n\t\t      - intuitiveness Score - Ease of interaction\n\t\t      - responseTime - System response latency\n\t\t      - userSatisfaction - User satisfaction metric\n\t\t  \n\t\t  - ## Cross-Domain Relationships\n\t\t    - [[dt:enhancedBy]] → [[NaturalLanguageProcessing]] - Voice commands\n\t\t    - [[dt:uses]] → [[GestureRecognition]] - Gesture-based control\n\t\t    - [[dt:trainedVia]] → [[MachineLearning]] - Learning user preferences\n\t\t    - [[dt:presentedIn]] → [[VirtualReality]] - VR-based robot control\n\t\t    - [[dt:securedBy]] → [[Authentication]] - User authentication\n\t\t  \n\t\t  - ## Related Concepts\n\t\t    - [[CollaborativeRobot]]\n\t\t    - [[SafetyProtocol]]\n\t\t    - [[IntuitiveInterface]]\n\t\t    - [[SharedWorkspace]]\n\t\t    - [[TeachPendant]]\n\t\t  \n\t\t  - ## Use Cases\n\t\t    - Collaborative manufacturing\n\t\t    - Service robots in public spaces\n\t\t    - Assistive robotics\n\t\t    - Telepresence robots\n\t\t    - Educational robots\n\t\t  \n\t\t  ```\n\n\n## Current Landscape (2025)\n\n- Industry adoption and implementations\n  - Metaverse platforms continue to evolve with focus on interoperability and open standards\n  - Web3 integration accelerating with decentralised identity and asset ownership\n  - Enterprise adoption growing in virtual collaboration, training, and digital twins\n  - UK companies increasingly active in metaverse development and immersive technologies\n\n- Technical capabilities\n  - Real-time rendering at photorealistic quality levels\n  - Low-latency networking enabling seamless multi-user experiences\n  - AI-driven content generation and procedural world building\n  - Spatial audio and haptics enhancing immersion\n\n- UK and North England context\n  - Manchester: Digital Innovation Factory supports metaverse startups and research\n  - Leeds: Holovis leads in immersive experiences for entertainment and training\n  - Newcastle: University research in spatial computing and interactive systems\n  - Sheffield: Advanced manufacturing using digital twin technology\n\n- Standards and frameworks\n  - Metaverse Standards Forum driving interoperability protocols\n  - WebXR enabling browser-based immersive experiences\n  - glTF and USD for 3D asset interchange\n  - Open Metaverse Interoperability Group defining cross-platform standards\n\n## Metadata\n\n- **Last Updated**: 2025-11-16\n- **Review Status**: Automated remediation with 2025 context\n- **Verification**: Academic sources verified\n- **Regional Context**: UK/North England where applicable",
  "properties": {
    "id": "humanrobotinteraction-ontology",
    "collapsed": "true",
    "- ontology": "true",
    "- term-id": "mv-1761742247935",
    "- preferred-term": "HumanRobotInteraction",
    "- source-domain": "metaverse",
    "- status": "draft",
    "- public-access": "true",
    "- definition": "A component of the metaverse ecosystem.",
    "- maturity": "draft",
    "- owl:class": "mv:HumanRobotInteraction",
    "- owl:physicality": "ConceptualEntity",
    "- owl:role": "Concept",
    "- belongsToDomain": "[[MetaverseDomain]]"
  },
  "backlinks": [
    "TELE-200-robotic-telepresence",
    "robotics-core-concepts",
    "TELE-CONV-002-robotics-telepresence-bridge"
  ],
  "wiki_links": [
    "CollaborativeRobot",
    "GestureRecognition",
    "SharedWorkspace",
    "dt:trainedVia",
    "providesInterface",
    "Authentication",
    "ensuresSafety",
    "MachineLearning",
    "dt:uses",
    "SafetyProtocol",
    "TeachPendant",
    "VirtualReality",
    "enablesCollaboration",
    "IntuitiveInterface",
    "MetaverseDomain",
    "NaturalLanguageProcessing",
    "usesModality",
    "dt:enhancedBy",
    "dt:presentedIn",
    "dt:securedBy"
  ],
  "ontology": {
    "term_id": "mv-1761742247935",
    "preferred_term": "HumanRobotInteraction",
    "definition": "A component of the metaverse ecosystem.",
    "source_domain": "metaverse",
    "maturity_level": null,
    "authority_score": null
  }
}