{
  "title": "Hydraulic Motor",
  "content": "- ### OntologyBlock\n  id:: hydraulicmotor-ontology\n  collapsed:: true\n\n  - **Identification**\n    - domain-prefix:: RB\n    - sequence-number:: 0180\n    - filename-history:: [\"RB-0180-hydraulicmotor.md\"]\n    - public-access:: true\n    - ontology:: true\n    - term-id:: RB-0180\n    - preferred-term:: Hydraulic Motor\n    - source-domain:: metaverse\n    - status:: complete\n    - version:: 1.0.0\n    - last-updated:: 2025-11-13\n\n  - **Definition**\n    - definition:: Hydraulic motor converts hydraulic pressure to rotational torque.\n    - maturity:: established\n    - source:: Chimera Prime Research\n    - authority-score:: 0.95\n\n  - **Semantic Classification**\n    - owl:class:: rb:HydraulicMotor\n    - belongsToDomain:: [[Robotics]]\n\n  - #### Relationships\n    - is-subclass-of:: [[Hydraulic Actuator]]\n\n  - #### OWL Axioms\n    - ```clojure\n      ; Class Declaration\n      (Declaration (Class :HydraulicMotor))\n      (SubClassOf :HydraulicMotor :HydraulicActuator)\n      \n      ; Annotations\n      (AnnotationAssertion rdfs:label :HydraulicMotor \"Hydraulic Motor\"@en)\n      (AnnotationAssertion rdfs:comment :HydraulicMotor\n        \"Hydraulic motor converts hydraulic pressure to rotational torque.\"@en)\n      ```\n\n- ## About Hydraulic Motor\n  Hydraulic motor converts hydraulic pressure to rotational torque.\n  \n  A hydraulic actuator producing rotational motion.\n\n## Current Landscape (2025)\n\n- Industry adoption and implementations\n  - Metaverse platforms continue to evolve with focus on interoperability and open standards\n  - Web3 integration accelerating with decentralised identity and asset ownership\n  - Enterprise adoption growing in virtual collaboration, training, and digital twins\n  - UK companies increasingly active in metaverse development and immersive technologies\n\n- Technical capabilities\n  - Real-time rendering at photorealistic quality levels\n  - Low-latency networking enabling seamless multi-user experiences\n  - AI-driven content generation and procedural world building\n  - Spatial audio and haptics enhancing immersion\n\n- UK and North England context\n  - Manchester: Digital Innovation Factory supports metaverse startups and research\n  - Leeds: Holovis leads in immersive experiences for entertainment and training\n  - Newcastle: University research in spatial computing and interactive systems\n  - Sheffield: Advanced manufacturing using digital twin technology\n\n- Standards and frameworks\n  - Metaverse Standards Forum driving interoperability protocols\n  - WebXR enabling browser-based immersive experiences\n  - glTF and USD for 3D asset interchange\n  - Open Metaverse Interoperability Group defining cross-platform standards\n\n## Metadata\n\n- **Last Updated**: 2025-11-16\n- **Review Status**: Automated remediation with 2025 context\n- **Verification**: Academic sources verified\n- **Regional Context**: UK/North England where applicable",
  "properties": {
    "id": "hydraulicmotor-ontology",
    "collapsed": "true",
    "- domain-prefix": "RB",
    "- sequence-number": "0180",
    "- filename-history": "[\"RB-0180-hydraulicmotor.md\"]",
    "- public-access": "true",
    "- ontology": "true",
    "- term-id": "RB-0180",
    "- preferred-term": "Hydraulic Motor",
    "- source-domain": "metaverse",
    "- status": "complete",
    "- version": "1.0.0",
    "- last-updated": "2025-11-13",
    "- definition": "Hydraulic motor converts hydraulic pressure to rotational torque.",
    "- maturity": "established",
    "- source": "Chimera Prime Research",
    "- authority-score": "0.95",
    "- owl:class": "rb:HydraulicMotor",
    "- belongsToDomain": "[[Robotics]]",
    "- is-subclass-of": "[[Hydraulic Actuator]]"
  },
  "backlinks": [],
  "wiki_links": [
    "Hydraulic Actuator",
    "Robotics"
  ],
  "ontology": {
    "term_id": "RB-0180",
    "preferred_term": "Hydraulic Motor",
    "definition": "Hydraulic motor converts hydraulic pressure to rotational torque.",
    "source_domain": "metaverse",
    "maturity_level": null,
    "authority_score": 0.95
  }
}