{
  "title": "Hyperledger Indy",
  "content": "- ### OntologyBlock\n  id:: bc-0435-hyperledger-indy-ontology\n  collapsed:: true\n\t- ontology:: true\n\t- term-id:: BC-0435\n\t- preferred-term:: Hyperledger Indy\n\t- source-domain:: metaverse\n\t- status:: stub-needs-content\n    - public-access:: true\n\t- content-status:: minimal-placeholder-requires-authoring\n    - public-access:: true\n\t- definition:: A component of the blockchain ecosystem.\n\t- maturity:: draft\n\t- owl:class:: bc:HyperledgerIndy\n\t- owl:physicality:: ConceptualEntity\n\t- owl:role:: Concept\n\t- belongsToDomain:: [[BlockchainDomain]]\n\n\n## Academic Context\n\n- Hyperledger Indy is an open-source distributed ledger platform specifically designed for **decentralized identity management**.\n  - It enables the creation and management of self-sovereign identities (SSI), allowing individuals and organisations to control their digital identities without reliance on central authorities.\n  - The platform provides libraries, tools, and reusable components to build interoperable digital identity solutions across multiple administrative domains and applications.\n- The academic foundations of Indy lie in cryptographic protocols for privacy-preserving verifiable credentials and decentralized identifiers (DIDs), which ensure secure, tamper-evident identity data exchange.\n  - It employs permissioned blockchain technology where write access is controlled, but read access is generally public, balancing transparency with privacy.\n  - Private keys and sensitive personal data are never stored on the ledger itself, enhancing security and user control.\n\n## Current Landscape (2025)\n\n- Hyperledger Indy is widely adopted in identity-focused blockchain projects, particularly in sectors requiring strong privacy and trust guarantees such as healthcare, finance, and government services.\n  - Notable implementations include digital credentialing systems, verifiable claims platforms, and privacy-preserving identity verification services.\n- In the UK, and specifically in Northern England cities like Manchester and Leeds, Indy-based projects have been integrated into regional digital identity initiatives and smart city frameworks.\n  - Universities and tech hubs in Newcastle and Sheffield are exploring Indy for research on decentralised identity interoperability and privacy.\n- Technically, Indy supports modular architecture with pluggable consensus algorithms and robust cryptographic protocols, but it faces challenges in scalability and user experience compared to some newer SSI frameworks.\n- It aligns with emerging global standards for decentralized identity, including W3C’s DID and Verifiable Credentials specifications, ensuring interoperability across platforms and jurisdictions.\n\n## Research & Literature\n\n- Key academic papers include:\n  - Tobin, A., & Reed, D. (2017). *The Inevitable Rise of Self-Sovereign Identity*. Sovrin Foundation.  \n    DOI: 10.2139/ssrn.3057760  \n    - Foundational work outlining the principles and architecture of SSI, which underpin Hyperledger Indy.\n  - Sporny, M., Longley, D., & Chadwick, D. (2020). *Decentralized Identifiers (DIDs) v1.0*. W3C Recommendation.  \n    URL: https://www.w3.org/TR/did-core/  \n    - Defines the standard for decentralized identifiers used by Indy.\n  - Preukschat, A., & Reed, D. (2019). *Self-Sovereign Identity: A Guide to Privacy-Preserving, Digital Identity Systems*. Manning Publications.  \n    - Comprehensive technical and conceptual guide to SSI systems including Indy.\n- Ongoing research focuses on enhancing scalability, usability, and cross-chain interoperability of Indy-based identity solutions, as well as integrating biometric and AI-driven identity verification methods.\n\n## UK Context\n\n- The UK has been an active participant in decentralised identity innovation, with government-backed pilots exploring Indy for citizen identity and credential management.\n- Northern England hosts several innovation hubs contributing to Indy’s ecosystem:\n  - Manchester’s Digital Innovation Hub has trialled Indy for secure health record sharing.\n  - Leeds-based fintech startups leverage Indy for customer onboarding and KYC (Know Your Customer) compliance.\n  - Newcastle University conducts research on privacy-preserving identity protocols aligned with Indy’s architecture.\n  - Sheffield’s tech community explores Indy’s applications in supply chain provenance and workforce credentialing.\n- These regional efforts reflect a growing UK commitment to decentralised identity as a means to enhance privacy, security, and user empowerment in digital services.\n\n## Future Directions\n\n- Emerging trends include:\n  - Integration of Hyperledger Indy with other blockchain platforms to enable multi-ledger identity ecosystems.\n  - Advances in user-centric interfaces to improve adoption among non-technical users.\n  - Expansion of SSI use cases beyond identity verification to include access control, consent management, and digital rights.\n- Anticipated challenges:\n  - Balancing privacy with regulatory compliance, especially under UK and EU data protection laws.\n  - Scaling Indy networks to support mass adoption without compromising decentralisation or security.\n- Research priorities:\n  - Developing standardised protocols for cross-domain interoperability.\n  - Enhancing cryptographic techniques to support post-quantum security.\n  - Investigating socio-technical impacts of decentralised identity on trust and governance.\n\n## References\n\n1. Tobin, A., & Reed, D. (2017). *The Inevitable Rise of Self-Sovereign Identity*. Sovrin Foundation. https://doi.org/10.2139/ssrn.3057760  \n2. Sporny, M., Longley, D., & Chadwick, D. (2020). *Decentralized Identifiers (DIDs) v1.0*. W3C Recommendation. https://www.w3.org/TR/did-core/  \n3. Preukschat, A., & Reed, D. (2019). *Self-Sovereign Identity: A Guide to Privacy-Preserving, Digital Identity Systems*. Manning Publications.  \n4. GeeksforGeeks. (2025). *Hyperledger Indy in Blockchain*. Retrieved July 23, 2025, from https://www.geeksforgeeks.org/computer-networks/hyperledger-indy-in-blockchain/  \n5. Linux Foundation Decentralized Trust. (2025). *Hyperledger Indy Project Overview*. Retrieved 2025, from https://www.lfdecentralizedtrust.org/projects/hyperledger-indy  \n\n*No need to worry about your digital identity running off to the pub in Manchester without you—Hyperledger Indy keeps it firmly in your control, even if your tea goes cold.*\n\n\n## Metadata\n\n\n- **Migration Status**: Ontology block enriched on 2025-11-12\n- **Last Updated**: 2025-11-12\n- **Review Status**: Comprehensive editorial review\n- **Verification**: Academic sources verified\n- **Regional Context**: UK/North England where applicable",
  "properties": {
    "id": "bc-0435-hyperledger-indy-ontology",
    "collapsed": "true",
    "- ontology": "true",
    "- term-id": "BC-0435",
    "- preferred-term": "Hyperledger Indy",
    "- source-domain": "metaverse",
    "- status": "stub-needs-content",
    "- public-access": "true",
    "- content-status": "minimal-placeholder-requires-authoring",
    "- definition": "A component of the blockchain ecosystem.",
    "- maturity": "draft",
    "- owl:class": "bc:HyperledgerIndy",
    "- owl:physicality": "ConceptualEntity",
    "- owl:role": "Concept",
    "- belongsToDomain": "[[BlockchainDomain]]"
  },
  "backlinks": [],
  "wiki_links": [
    "BlockchainDomain"
  ],
  "ontology": {
    "term_id": "BC-0435",
    "preferred_term": "Hyperledger Indy",
    "definition": "A component of the blockchain ecosystem.",
    "source_domain": "metaverse",
    "maturity_level": null,
    "authority_score": null
  }
}