{
  "title": "Image Segmentation",
  "content": "- ### OntologyBlock\n  id:: imagesegmentation-ontology\n  collapsed:: true\n\n  - **Identification**\n    - domain-prefix:: AI\n    - sequence-number:: 0853\n    - filename-history:: [\"AI-0853-imagesegmentation.md\"]\n    - public-access:: true\n    - ontology:: true\n    - term-id:: AI-0853\n    - preferred-term:: Image Segmentation\n    - source-domain:: ai\n    - status:: complete\n    - version:: 1.0.0\n    - last-updated:: 2025-11-13\n\n  - **Definition**\n    - definition:: \n    - maturity:: established\n    - source:: Chimera Prime Research\n    - authority-score:: 0.95\n\n  - **Semantic Classification**\n    - owl:class:: ai:ImageSegmentation\n    - belongsToDomain:: [[Artificial Intelligence]]\n\n  - #### OWL Restrictions\n    \n\n  - \n### Relationships\n- is-subclass-of:: [[ComputerVision]]",
  "properties": {
    "id": "imagesegmentation-ontology",
    "collapsed": "true",
    "- domain-prefix": "AI",
    "- sequence-number": "0853",
    "- filename-history": "[\"AI-0853-imagesegmentation.md\"]",
    "- public-access": "true",
    "- ontology": "true",
    "- term-id": "AI-0853",
    "- preferred-term": "Image Segmentation",
    "- source-domain": "ai",
    "- status": "complete",
    "- version": "1.0.0",
    "- last-updated": "2025-11-13",
    "- definition": "",
    "- maturity": "established",
    "- source": "Chimera Prime Research",
    "- authority-score": "0.95",
    "- owl:class": "ai:ImageSegmentation",
    "- belongsToDomain": "[[Artificial Intelligence]]"
  },
  "backlinks": [],
  "wiki_links": [
    "Artificial Intelligence",
    "ComputerVision"
  ],
  "ontology": {
    "term_id": "AI-0853",
    "preferred_term": "Image Segmentation",
    "definition": "",
    "source_domain": "ai",
    "maturity_level": null,
    "authority_score": 0.95
  }
}