{
  "title": "Immersion",
  "content": "- ### OntologyBlock\n  id:: immersion-ontology\n  collapsed:: true\n\t- ontology:: true\n\t- term-id:: 20255\n\t- source-domain:: metaverse\n\t- status:: draft\n<<<<<<< HEAD\n=======\n    - public-access:: true\n>>>>>>> 691c6e7cfbf51bb03aef4b19e8bb7f7924266439\n\t- preferred-term:: Immersion\n\t- definition:: Subjective experience of psychological engagement and sense of presence within a virtual environment, characterized by reduced awareness of physical surroundings and absorption in virtual context.\n\t- maturity:: mature\n\t- source:: [[ACM]]\n\t- owl:class:: mv:Immersion\n\t- owl:physicality:: VirtualEntity\n\t- owl:role:: Process\n\t- owl:inferred-class:: mv:VirtualProcess\n\t- owl:functional-syntax:: true\n\t- belongsToDomain:: [[InteractionDomain]]\n\t- implementedInLayer:: [[ApplicationLayer]], [[PresentationLayer]]\n\t- #### Relationships\n\t  id:: immersion-relationships\n\t\t- has-part:: [[Sensory Immersion]], [[Emotional Immersion]], [[Cognitive Immersion]]\n\t\t- requires:: [[Display Technology]], [[Interaction Mechanism]], [[Content Quality]]\n\t\t- enables:: [[Presence]], [[Flow State]], [[User Engagement]]\n\t\t- depends-on:: [[Visual Fidelity]], [[Audio Spatialization]], [[Haptic Feedback]]\n\t- #### OWL Axioms\n\t  id:: immersion-owl-axioms\n\t  collapsed:: true\n\t\t- ```clojure\n\t\t  Declaration(Class(mv:Immersion))\n\n\t\t  # Classification along two primary dimensions\n\t\t  SubClassOf(mv:Immersion mv:VirtualEntity)\n\t\t  SubClassOf(mv:Immersion mv:Process)\n\n\t\t  # Compositional structure - three primary dimensions\n\t\t  SubClassOf(mv:Immersion\n\t\t    ObjectSomeValuesFrom(mv:hasPart mv:SensoryImmersion)\n\t\t  )\n\n\t\t  SubClassOf(mv:Immersion\n\t\t    ObjectSomeValuesFrom(mv:hasPart mv:EmotionalImmersion)\n\t\t  )\n\n\t\t  SubClassOf(mv:Immersion\n\t\t    ObjectSomeValuesFrom(mv:hasPart mv:CognitiveImmersion)\n\t\t  )\n\n\t\t  # Domain classification\n\t\t  SubClassOf(mv:Immersion\n\t\t    ObjectSomeValuesFrom(mv:belongsToDomain mv:InteractionDomain)\n\t\t  )\n\n\t\t  # Layer classification\n\t\t  SubClassOf(mv:Immersion\n\t\t    ObjectSomeValuesFrom(mv:implementedInLayer mv:ApplicationLayer)\n\t\t  )\n\n\t\t  SubClassOf(mv:Immersion\n\t\t    ObjectSomeValuesFrom(mv:implementedInLayer mv:PresentationLayer)\n\t\t  )\n\n\t\t  # Technical requirements\n\t\t  SubClassOf(mv:Immersion\n\t\t    ObjectSomeValuesFrom(mv:requires mv:DisplayTechnology)\n\t\t  )\n\n\t\t  SubClassOf(mv:Immersion\n\t\t    ObjectSomeValuesFrom(mv:requires mv:InteractionMechanism)\n\t\t  )\n\n\t\t  SubClassOf(mv:Immersion\n\t\t    ObjectSomeValuesFrom(mv:requires mv:ContentQuality)\n\t\t  )\n\n\t\t  # Quality dependencies\n\t\t  SubClassOf(mv:Immersion\n\t\t    ObjectSomeValuesFrom(mv:dependsOn mv:VisualFidelity)\n\t\t  )\n\n\t\t  SubClassOf(mv:Immersion\n\t\t    ObjectSomeValuesFrom(mv:dependsOn mv:AudioSpatialization)\n\t\t  )\n\n\t\t  # Enabled experiences\n\t\t  SubClassOf(mv:Immersion\n\t\t    ObjectSomeValuesFrom(mv:enables mv:Presence)\n\t\t  )\n\n\t\t  SubClassOf(mv:Immersion\n\t\t    ObjectSomeValuesFrom(mv:enables mv:FlowState)\n\t\t  )\n\n\t\t  SubClassOf(mv:Immersion\n\t\t    ObjectSomeValuesFrom(mv:enables mv:UserEngagement)\n\t\t  )\n\n  # Property characteristics\n  AsymmetricObjectProperty(dt:requires)\n\n  # Property characteristics\n  AsymmetricObjectProperty(dt:enables)\n\n  # Property characteristics\n  AsymmetricObjectProperty(dt:dependson)\n```",
  "properties": {
    "id": "immersion-owl-axioms",
    "collapsed": "true",
    "- ontology": "true",
    "- term-id": "20255",
    "- source-domain": "metaverse",
    "- status": "draft",
    "- public-access": "true",
    "- preferred-term": "Immersion",
    "- definition": "Subjective experience of psychological engagement and sense of presence within a virtual environment, characterized by reduced awareness of physical surroundings and absorption in virtual context.",
    "- maturity": "mature",
    "- source": "[[ACM]]",
    "- owl:class": "mv:Immersion",
    "- owl:physicality": "VirtualEntity",
    "- owl:role": "Process",
    "- owl:inferred-class": "mv:VirtualProcess",
    "- owl:functional-syntax": "true",
    "- belongsToDomain": "[[InteractionDomain]]",
    "- implementedInLayer": "[[ApplicationLayer]], [[PresentationLayer]]",
    "- has-part": "[[Sensory Immersion]], [[Emotional Immersion]], [[Cognitive Immersion]]",
    "- requires": "[[Display Technology]], [[Interaction Mechanism]], [[Content Quality]]",
    "- enables": "[[Presence]], [[Flow State]], [[User Engagement]]",
    "- depends-on": "[[Visual Fidelity]], [[Audio Spatialization]], [[Haptic Feedback]]"
  },
  "backlinks": [
    "TELE-006-presence",
    "Presence",
    "TELE-001-telepresence"
  ],
  "wiki_links": [
    "Content Quality",
    "Presence",
    "Sensory Immersion",
    "Cognitive Immersion",
    "Audio Spatialization",
    "Display Technology",
    "Visual Fidelity",
    "Haptic Feedback",
    "Interaction Mechanism",
    "ApplicationLayer",
    "ACM",
    "Emotional Immersion",
    "User Engagement",
    "PresentationLayer",
    "InteractionDomain",
    "Flow State"
  ],
  "ontology": {
    "term_id": "20255",
    "preferred_term": "Immersion",
    "definition": "Subjective experience of psychological engagement and sense of presence within a virtual environment, characterized by reduced awareness of physical surroundings and absorption in virtual context.",
    "source_domain": "metaverse",
    "maturity_level": null,
    "authority_score": null
  }
}