{
  "title": "Importer",
  "content": "- ### OntologyBlock\n  id:: importer-ontology\n  collapsed:: true\n\t- ontology:: true\n\t- term-id:: mv-1761742247936\n\t- preferred-term:: Importer\n\t- source-domain:: metaverse\n\t- status:: draft\n    - public-access:: true\n\t- definition:: A natural or legal person located or established in the Union that places on the market an AI system that bears the name or trademark of a natural or legal person established in a third country.\n\n\n\n\n## Academic Context\n\n- The concept of an \"Importer\" in AI regulation primarily refers to a natural or legal person responsible for placing AI systems on the market within a jurisdiction, often bearing the name or trademark of entities established outside that jurisdiction.\n  - This role is critical in ensuring compliance with regional AI laws, particularly concerning safety, transparency, and accountability.\n  - Academic foundations draw from regulatory theory, international trade law, and technology governance, emphasising the importer's responsibility as a gatekeeper for AI system conformity with local standards.\n\n## Current Landscape (2025)\n\n- The EU AI Act, effective in phases since early 2025, defines importers as entities placing AI systems on the EU market that originate from third countries, holding them accountable for compliance with safety, transparency, and risk mitigation requirements.\n  - Importers must ensure that AI systems bear the name or trademark of a third-country person but meet EU standards before market placement.\n  - The UK, while no longer bound by the EU AI Act, has developed a complementary regulatory framework focusing on sector-specific oversight, with importers similarly responsible for compliance under UK law.\n- Notable organisations in the UK, including those in North England hubs such as Manchester and Leeds, actively engage in AI deployment and compliance, reflecting the region's growing AI innovation ecosystem.\n- Technical capabilities of importers include due diligence on AI system conformity, supply chain scrutiny, and cooperation with regulatory bodies like the UK Information Commissioner's Office (ICO).\n- Standards and frameworks guiding importers include the EU AI Act, UK ICO’s AI and Biometrics Strategy (2025), and international norms promoted by OECD and G7.\n\n## Research & Literature\n\n- Key academic sources on AI importers and regulatory compliance include:\n  - Veale, M., & Borgesius, F. Z. (2021). *Demystifying the Draft EU Artificial Intelligence Act*. Computer Law & Security Review, 41, 105567. https://doi.org/10.1016/j.clsr.2021.105567\n  - Wachter, S., Mittelstadt, B., & Floridi, L. (2017). *Why a Right to Explanation of Automated Decision-Making Does Not Exist in the General Data Protection Regulation*. International Data Privacy Law, 7(2), 76–99. https://doi.org/10.1093/idpl/ipx005\n- Ongoing research explores the importer's role in cross-border AI governance, supply chain transparency, and liability frameworks.\n\n## UK Context\n\n- The UK’s approach to AI regulation emphasises flexibility and sector-specific oversight rather than a centralised AI regulator, with importers required to ensure AI systems comply with the UK’s AI principles and data protection laws.\n- North England, particularly cities like Manchester, Leeds, Newcastle, and Sheffield, hosts vibrant AI innovation hubs where importers and developers collaborate closely to meet regulatory expectations.\n  - For example, Manchester’s AI and Digital Hub provides regulatory advice and compliance support to importers and deployers.\n- The UK ICO’s 2025 AI and Biometrics Strategy highlights the importance of importers in maintaining public trust through responsible data handling and compliance with emerging statutory codes of practice.\n\n## Future Directions\n\n- Emerging trends include increased scrutiny of AI supply chains, with importers expected to conduct thorough conformity assessments and maintain documentation demonstrating compliance.\n- Anticipated challenges involve balancing innovation with regulatory demands, especially for importers dealing with AI systems developed in jurisdictions with differing standards.\n- Research priorities focus on enhancing transparency mechanisms for importers, developing harmonised international compliance frameworks, and clarifying liability in cross-border AI deployment.\n\n## References\n\n1. Veale, M., & Borgesius, F. Z. (2021). Demystifying the Draft EU Artificial Intelligence Act. *Computer Law & Security Review*, 41, 105567. https://doi.org/10.1016/j.clsr.2021.105567  \n2. Wachter, S., Mittelstadt, B., & Floridi, L. (2017). Why a Right to Explanation of Automated Decision-Making Does Not Exist in the General Data Protection Regulation. *International Data Privacy Law*, 7(2), 76–99. https://doi.org/10.1093/idpl/ipx005  \n3. King & Spalding. (2025). EU & UK AI Round-up – July 2025.  \n4. Software Improvement Group. (2025). A Comprehensive EU AI Act Summary [August 2025 update].  \n5. UK Information Commissioner’s Office. (2025). AI and Biometrics Strategy.  \n6. Norton Rose Fulbright. (2025). Artificial Intelligence Regulation | United Kingdom.  \n7. GOV.UK. (2025). AI Opportunities Action Plan: Government Response.\n\n\n## Metadata\n\n- **Last Updated**: 2025-11-11\n- **Review Status**: Comprehensive editorial review\n- **Verification**: Academic sources verified\n- **Regional Context**: UK/North England where applicable",
  "properties": {
    "id": "importer-ontology",
    "collapsed": "true",
    "- ontology": "true",
    "- term-id": "mv-1761742247936",
    "- preferred-term": "Importer",
    "- source-domain": "metaverse",
    "- status": "draft",
    "- public-access": "true",
    "- definition": "A natural or legal person located or established in the Union that places on the market an AI system that bears the name or trademark of a natural or legal person established in a third country."
  },
  "backlinks": [],
  "wiki_links": [],
  "ontology": {
    "term_id": "mv-1761742247936",
    "preferred_term": "Importer",
    "definition": "A natural or legal person located or established in the Union that places on the market an AI system that bears the name or trademark of a natural or legal person established in a third country.",
    "source_domain": "metaverse",
    "maturity_level": null,
    "authority_score": null
  }
}