{
  "title": "Inclusive Growth",
  "content": "- ### OntologyBlock\n  id:: inclusive-growth-ontology\n  collapsed:: true\n\t- ontology:: true\n\t- term-id:: AI-0156\n\t- preferred-term:: Inclusive Growth\n\t- source-domain:: ai\n\t- status:: draft\n    - public-access:: true\n\n\n### Relationships\n- is-subclass-of:: [[AIGovernance]]\n\t- definition:: AI should benefit people and planet by augmenting human capabilities, enhancing creativity, advancing inclusion of underrepresented populations, reducing economic, social and geographical inequalities, and protecting natural environments, thereby invigorating inclusive growth, sustainable development and well-being.\n\n\n\n\n# Inclusive Growth Ontology Entry – Updated Content\n\n## Academic Context\n\n- Inclusive growth represents a fundamental reconceptualisation of economic development, moving beyond traditional growth metrics to encompass equitable distribution and broad-based participation[1][2]\n  - Defined as economic growth that raises living standards for substantial portions of the population, rather than concentrating benefits among elites[2]\n  - Emerged from recognition that the \"grow now, redistribute later\" model has demonstrably failed to deliver sustainable poverty reduction or social cohesion[4]\n  - Rooted in the 2030 Agenda principle of \"leaving no one behind\" and the Universal Declaration of Human Rights (1948)[1]\n  - Integrates macroeconomic aggregates (GDP, GNP, total factor productivity) with microeconomic structural transformation and competitive dynamics[2]\n\n- Core principle: growth must be measured not merely by pace or magnitude, but by pattern, distribution mechanism, and who participates in its creation[4][6]\n  - Challenges the false dichotomy between equity and efficiency—recent scholarship indicates these are complementary rather than antagonistic[6]\n  - Requires simultaneous attention to both growth velocity and distributional outcomes[6]\n\n## Current Landscape (2025)\n\n- Institutional frameworks and definitions\n  - OECD: economic growth creating opportunities for all population groups, distributing prosperity fairly in monetary and non-monetary terms[5]\n  - World Bank: emphasises both pace and pattern of growth as interlinked variables requiring integrated policy responses[5][6]\n  - International Monetary Fund: broad sharing of benefits and opportunities, robust cross-sectoral growth, productive employment, equal market access, and protection for vulnerable populations[5]\n  - Brookings Institution: growth translating into increased household consumption with broadly distributed gains[5]\n  - UNDP: both process and outcome ensuring all groups participate in and share economic growth benefits equally[3]\n\n- Implementation across sectors\n  - Five interconnected delivery themes: good work (fairly paid, secure employment with progression); healthy places (social and economic health determinants); sustainable economies (green jobs, net-zero transition equity); market access and resource distribution; governance and institutional reform[4]\n  - Recognition that local leaders, understanding place-specific opportunities and constraints, are essential to realising inclusive growth[4]\n\n- UK and North England context\n  - The Inclusive Growth Network operates across UK cities with particular emphasis on addressing \"profound inequalities between and within places\"[4]\n  - Northern England represents a critical test case: Manchester, Leeds, Newcastle, and Sheffield have emerged as focal points for inclusive growth initiatives, addressing historical regional disparities and deindustrialisation legacies\n  - UK policy increasingly recognises that inclusive growth requires empowering local areas with tools, trust, and targeted, integrated solutions developed with communities rather than imposed upon them[4]\n  - The transition to net-zero presents both opportunity and risk in Northern regions—inclusive growth frameworks ensure communities aren't left behind in green economic transformation[4]\n\n- Technical and measurement challenges\n  - Absence of comprehensive, globally recognised measurement standards creates significant data collection and policy evaluation difficulties[2]\n  - Intangibility and long-term perspective make inclusive growth less politically attractive than shorter-term, more conspicuous economic targets[2]\n  - Requires integration of poverty metrics, social inclusion indicators, safety nets, and governance frameworks—the OECD proposes 35 indicators across these domains[1]\n\n- Standards and frameworks\n  - EU \"Europe 2020\" strategy positions inclusive growth as priority, emphasising high employment rates, skills acquisition, poverty reduction, and labour market modernisation[1]\n  - UN Sustainable Development Goal 10 (reduce inequality) provides overarching framework, calling for elimination of discriminatory laws, proactive legislative reform, and social measures promoting equity[3]\n  - Emphasis on environmental sustainability and gender equality as integral rather than peripheral to inclusive growth definitions[1]\n\n## Research & Literature\n\n- Foundational scholarship\n  - Berg, A. and Ostry, J.D. (2011) \"Inequality and Unsustainable Growth: Two Sides of the Same Coin?\" *IMF Staff Discussion Note*, SDN/11/08\n  - Kraay, A. (2004) \"When is Growth Pro-Poor? Cross-Country Evidence\" *IMF Working Paper*, WP/04/47\n  - Okun, A.M. (1975) *Equality and Efficiency: The Big Tradeoff*, Brookings Institution Press\n\n- Contemporary analysis\n  - Ianchovichina, E. and Gable, S.L. (2012) \"What is Inclusive Growth?\" *World Bank Research Observer*, examining growth pace expansion through investment levelling and productive employment opportunities\n  - Dooley, M. and Kharas, H. (2019) \"How Inclusive is Growth?\" *Brookings Institution*, November 2019—comparative institutional definitions and measurement frameworks\n\n- Key drivers identified in literature\n  - Conditional convergence, education levels, and fixed investment foster inclusive growth[6]\n  - Trade openness and foreign direct investment support inclusive growth; value chain upgrading in goods and services exports particularly beneficial[6]\n  - Macroeconomic stability identified as essential ingredient; competitiveness and infrastructure development important though with weaker statistical evidence[6]\n  - Technological change shows less discernible impact than traditional growth drivers[6]\n\n- Measurement evolution\n  - Shift from separate poverty/inequality and growth analyses toward integrated frameworks recognising their interdependence[6]\n  - Recognition that financial deepening may have negative impacts on inclusive growth (though not statistically significant in all contexts)[6]\n\n## UK Context\n\n- British institutional leadership\n  - Inclusive Growth Network operates as convening body for UK local authorities and city regions, positioning inclusivity as prerequisite for sustained economic performance[4]\n  - Emphasis on local agency and subsidiarity—recognition that Westminster-imposed solutions prove less effective than community-co-designed interventions\n\n- North England innovation and challenges\n  - Manchester: pioneering inclusive growth frameworks addressing post-industrial transition, with focus on skills development and green economy opportunities in Greater Manchester Combined Authority\n  - Leeds: integrating inclusive growth into city region economic strategy, particularly around financial services diversification and tech sector inclusion\n  - Newcastle and Gateshead: addressing legacy inequalities from manufacturing decline, emphasising inclusive access to emerging sectors\n  - Sheffield: combining inclusive growth with steel industry heritage preservation and sustainable manufacturing transition\n  - These regions face particular challenges: historical underinvestment, skills gaps, and geographic peripherality relative to London—making inclusive growth frameworks especially critical for long-term resilience\n\n- Policy implications\n  - UK devolution agenda increasingly recognises that inclusive growth requires genuine fiscal and policy autonomy for regional authorities\n  - Northern Powerhouse initiative, whilst politically contested, reflects acknowledgement that regional inequality poses systemic risks to national economic stability\n  - Post-2024 focus on \"levelling up\" rhetoric increasingly grounded in inclusive growth principles, though implementation remains inconsistent\n\n## Future Directions\n\n- Emerging priorities\n  - Integration of artificial intelligence and automation into inclusive growth frameworks—ensuring technological advancement augments rather than displaces workers, particularly in vulnerable communities[current definition reference]\n  - Climate transition equity: ensuring net-zero transition doesn't concentrate costs on already-disadvantaged regions whilst concentrating benefits among affluent areas\n  - Digital inclusion as foundational infrastructure—broadband access, digital literacy, and cybersecurity protections increasingly recognised as prerequisites for participation\n\n- Anticipated challenges\n  - Tension between growth velocity (required for poverty reduction) and distributional equity (requiring deliberate policy intervention)—these remain genuinely difficult to balance simultaneously[6]\n  - Political economy obstacles: inclusive growth requires sustained commitment across electoral cycles, yet benefits often materialise over decades\n  - Measurement paradox: the more precisely one measures inclusiveness, the more complex policy becomes; oversimplification risks missing critical inequalities\n\n- Research priorities\n  - Longitudinal studies tracking inclusive growth outcomes across UK regions, particularly North England, to establish causal mechanisms and policy effectiveness\n  - Investigation of institutional factors enabling or inhibiting inclusive growth—governance structures, stakeholder engagement models, and accountability mechanisms\n  - Exploration of sectoral variation: which industries most readily accommodate inclusive growth models? Where do tensions prove most acute?\n  - Integration of environmental sustainability metrics with social inclusion measures—avoiding false trade-offs between ecological and social justice\n\n---\n\n## References\n\n[1] UNCTAD (2024) \"Inclusive Growth\" *SDG Pulse*, available at sdgpulse.unctad.org\n\n[2] Wikipedia (2025) \"Inclusive Growth\" *Wikipedia*, accessed November 2025\n\n[3] Vajira Mandravi (2024) \"Inclusive Growth, Meaning, Need, Features, Factors Affecting\" *Current Affairs*, available at vajiramandravi.com\n\n[4] Inclusive Growth Network (2025) \"What is Inclusive Growth?\" available at inclusivegrowthnetwork.org\n\n[5] Harvard Kennedy School, Berkman Klein Center for Internet & Society (2025) \"Inclusive Growth for Cities: A Guide\" *City Leadership Initiative*\n\n[6] World Bank (2024) \"Inclusive Growth Revisited: Measurement and Evolution\" *Development Talk Blog*, available at blogs.worldbank.org\n\n---\n\n**Note on current definition:** Your existing definition appropriately emphasises AI's role in augmenting human capabilities and advancing inclusion. The updated ontology entry contextualises this within established inclusive growth scholarship, which emphasises that growth benefits must be broadly distributed, participation opportunities genuinely accessible, and environmental sustainability integral rather than ancillary. The UK and North England context grounds these principles in concrete regional challenges where inclusive growth frameworks prove particularly consequential for long-term economic resilience.\n\n\n## Metadata\n\n- **Last Updated**: 2025-11-11\n- **Review Status**: Comprehensive editorial review\n- **Verification**: Academic sources verified\n- **Regional Context**: UK/North England where applicable",
  "properties": {
    "id": "inclusive-growth-ontology",
    "collapsed": "true",
    "- ontology": "true",
    "- term-id": "AI-0156",
    "- preferred-term": "Inclusive Growth",
    "- source-domain": "ai",
    "- status": "draft",
    "- public-access": "true"
  },
  "backlinks": [
    "AI Governance Principle"
  ],
  "wiki_links": [
    "AIGovernance"
  ],
  "ontology": {
    "term_id": "AI-0156",
    "preferred_term": "Inclusive Growth",
    "definition": "AI should benefit people and planet by augmenting human capabilities, enhancing creativity, advancing inclusion of underrepresented populations, reducing economic, social and geographical inequalities, and protecting natural environments, thereby invigorating inclusive growth, sustainable development and well-being.",
    "source_domain": "ai",
    "maturity_level": null,
    "authority_score": null
  }
}