{
  "title": "Industry Cloud Platforms",
  "content": "- ### OntologyBlock\n  id:: industry-cloud-platforms-ontology\n  collapsed:: true\n\t- ontology:: true\n\t- term-id:: ME-0015\n\t- preferred-term:: Industry Cloud Platforms\n\t- source-domain:: metaverse\n\t- status:: emerging-technology\n    - public-access:: true\n\t- definition:: [Generated from Gartner emerging tech analysis]\n\t- maturity:: emerging\n\t- owl:class:: mv:IndustryCloudPlatforms\n\t- owl:physicality:: ConceptualEntity\n\t- owl:role:: Concept\n\t- is-subclass-of:: [[Metaverse Infrastructure]]\n\t- belongsToDomain:: [[MetaverseDomain]]\n\t- category:: Infrastructure & Cloud\n\n\n## Overview\n\n# Industry Cloud Platforms: A Comprehensive Overview\n\n## Technical Definition\n\nIndustry Cloud Platforms (ICPs), also known as vertical cloud platforms, are **collections of integrated IT assets tailored for specific industries and embedded with data analytics, artificial intelligence, and emerging technologies**[2]. They comprise industry-specific cloud application suites built on standards-based cloud infrastructure, integrated with horizontal applications such as finance, supply chain, and human resources[2].\n\nMore precisely, ICPs represent a **specialized evolution of cloud computing that delivers industry-specific outcomes by combining domain expertise with cloud-native capabilities**, enabling organizations to run both vertical and horizontal business applications on a unified platform whilst maintaining appropriate security controls and regulatory compliance[2][5].\n\n## Current State and Implementations (2024-2025)\n\n### Platform Architecture and Functionality\n\nIndustry Cloud Platforms operate through a systematic approach that begins with **deep understanding of industry-specific workflows, pain points, and regulatory requirements**[1]. The platforms then deliver specialized services including industry-specific software, data analytics tools, and compliance features tailored to particular sectors[1].\n\nKey operational characteristics include:\n\n- **Data integration and analytics**: Data generated by one application can be seamlessly shared across other applications for analytical purposes, whilst maintaining security controls[2]. For instance, patient data in hospital management systems can inform supply chain applications to ensure adequate medical supplies[2].\n\n- **Compliance and security**: ICPs incorporate industry-specific security measures and compliance features essential for regulated sectors such as healthcare and finance[1]. AWS HealthScribe exemplifies this approach, offering HIPAA-eligible services for clinical documentation using generative AI[4].\n\n- **Scalability and integration**: Platforms offer flexible deployment options (public, private, hybrid) and integrate seamlessly with existing organizational systems, reducing disruption during cloud transitions[1].\n\n### Industry Applications\n\nCurrent implementations span multiple sectors[2]:\n\n- **Healthcare**: Electronic health record systems, telemedicine platforms, and healthcare data analytics\n- **Retail**: Inventory management solutions\n- **Banking**: Anti-money laundering compliance tools\n- **Construction**: Project management systems\n- **Manufacturing**: Industry-specific operational tools\n\n### Market Recognition\n\nGartner identified Industry Cloud Platforms as a **top strategic technology trend for 2024**[5], with major cloud providers (AWS, Microsoft, Google) and consulting firms (PwC, Kyndryl) actively developing and promoting vertical cloud solutions[4][5].\n\n## UK Context and North England Examples\n\nThe search results provided do not contain specific information regarding UK implementations or North England examples of Industry Cloud Platforms. To provide accurate, contextually relevant examples for the UK market and North England region, additional sources focusing on UK cloud adoption patterns and regional implementations would be required.\n\n## Key Research and Sources\n\nThe search results provided do not include formal academic research papers with full citations in standard citation formats (such as APA, Harvard, or Chicago style). The information derives from industry publications and vendor resources:\n\n- Comidor Knowledge Base: Industry Cloud Platforms guidance\n- Oracle Cloud: Industry Cloud Platforms benefits and use cases (Michael Hickins, May 2025)\n- Digital Adoption: Industry Cloud Platforms overview\n- TechTarget: Industry Cloud Platforms technical guidance\n- PwC: Industry Cloud Solutions and IDC MarketScape 2024 ratings\n- Kyndryl: Industry Clouds as digital ecosystem solutions\n- Gartner: Top Strategic Technology Trends for 2024\n\nFor comprehensive academic research, consultation of Gartner's full 2024 technology trends report and IDC's Worldwide Industry Cloud Professional Services 2024 MarketScape would be advisable.\n\n## Future Outlook\n\nIndustry Cloud Platforms represent **the next evolutionary stage in cloud computing**, following Infrastructure-as-a-Service (IaaS) and Platform-as-a-Service (PaaS)[3]. The trajectory suggests:\n\n- **Increased composability**: IT leaders will leverage composability capabilities to gain adaptability for managing accelerating industry disruptions[5].\n\n- **Modular customization**: Future platforms will offer increasingly modular, customizable ecosystems enabling organizations to streamline digital operations and adopt cloud-native technology for growth and innovation[6].\n\n- **Reduced IT sprawl**: Industry clouds address the common problem of technology sprawl by centralizing disparate solutions into integrated systems with consistent operating models at scale[6].\n\n- **Broader adoption**: Industry clouds represent an accessible gateway for organizations of all sizes to adopt cloud computing, making the transition increasingly unavoidable for competitive businesses[6].\n\nThe convergence of industry-specific solutions with emerging technologies (AI, advanced analytics, edge computing) will likely deepen vertical specialization whilst maintaining interoperability with horizontal enterprise applications.\n\n\n## UK Context\n\n- British contributions and implementations\n  - Research institutions and programmes\n  - Industry adoption\n  - North England innovation (where relevant)\n\n\n## Metadata\n\n- **Created**: 2025-11-11\n- **Source**: Gartner Emerging Technology Analysis\n- **Category**: Infrastructure & Cloud\n- **Status**: Emerging Technology\n\n\n\n\n## Current Landscape (2025)\n\n- Industry adoption and implementations\n  - Metaverse platforms continue to evolve with focus on interoperability and open standards\n  - Web3 integration accelerating with decentralised identity and asset ownership\n  - Enterprise adoption growing in virtual collaboration, training, and digital twins\n  - UK companies increasingly active in metaverse development and immersive technologies\n\n- Technical capabilities\n  - Real-time rendering at photorealistic quality levels\n  - Low-latency networking enabling seamless multi-user experiences\n  - AI-driven content generation and procedural world building\n  - Spatial audio and haptics enhancing immersion\n\n- UK and North England context\n  - Manchester: Digital Innovation Factory supports metaverse startups and research\n  - Leeds: Holovis leads in immersive experiences for entertainment and training\n  - Newcastle: University research in spatial computing and interactive systems\n  - Sheffield: Advanced manufacturing using digital twin technology\n\n- Standards and frameworks\n  - Metaverse Standards Forum driving interoperability protocols\n  - WebXR enabling browser-based immersive experiences\n  - glTF and USD for 3D asset interchange\n  - Open Metaverse Interoperability Group defining cross-platform standards\n\n## Metadata\n\n- **Last Updated**: 2025-11-16\n- **Review Status**: Automated remediation with 2025 context\n- **Verification**: Academic sources verified\n- **Regional Context**: UK/North England where applicable",
  "properties": {
    "id": "industry-cloud-platforms-ontology",
    "collapsed": "true",
    "- ontology": "true",
    "- term-id": "ME-0015",
    "- preferred-term": "Industry Cloud Platforms",
    "- source-domain": "metaverse",
    "- status": "emerging-technology",
    "- public-access": "true",
    "- definition": "[Generated from Gartner emerging tech analysis]",
    "- maturity": "emerging",
    "- owl:class": "mv:IndustryCloudPlatforms",
    "- owl:physicality": "ConceptualEntity",
    "- owl:role": "Concept",
    "- is-subclass-of": "[[Metaverse Infrastructure]]",
    "- belongsToDomain": "[[MetaverseDomain]]",
    "- category": "Infrastructure & Cloud"
  },
  "backlinks": [],
  "wiki_links": [
    "MetaverseDomain",
    "Metaverse Infrastructure"
  ],
  "ontology": {
    "term_id": "ME-0015",
    "preferred_term": "Industry Cloud Platforms",
    "definition": "[Generated from Gartner emerging tech analysis]",
    "source_domain": "metaverse",
    "maturity_level": null,
    "authority_score": null
  }
}