{
  "title": "Infrastructure Layer",
  "content": "- ### OntologyBlock\n  id:: infrastructurelayer-ontology\n  collapsed:: true\n\t- ontology:: true\n\t- term-id:: 20169\n\t- source-domain:: metaverse\n\t- status:: draft\n\t- public-access:: true\n\n\n# Infrastructure Layer – Updated Ontology Entry\n\n## Academic Context\n\n- The Infrastructure Layer represents the foundational technological substrate enabling metaverse functionality and scalability[1][2]\n  - Comprises interconnected systems spanning computing, storage, networking, and security domains\n  - Conceptualised within Jon Radoff's seven-layer metaverse framework as the base upon which all higher-order capabilities depend[2]\n  - Distinguished from application layers by its focus on enabling technologies rather than user-facing experiences\n\n- Core architectural principle: abstraction of complexity\n  - Physical hardware and network topology hidden from end-users through standardised APIs and service interfaces\n  - Enables seamless content delivery across heterogeneous devices and geographic locations[1]\n\n## Current Landscape (2025)\n\n- Computing and processing infrastructure\n  - Data centres and server farms optimised for high-performance computing, consuming 20-45 kW per rack versus 5-10 kW for traditional computing[6]\n  - GPU acceleration critical for rendering, AI model inference, and real-time spatial computation[2][3]\n  - Edge computing increasingly distributed to consumer devices, reducing latency and centralised processing bottlenecks[2]\n  - Cloud platforms (AWS, Google Cloud Platform) providing elastic autoscaling for variable user loads[4]\n\n- Network connectivity\n  - 5G networks dramatically improving bandwidth and reducing latency for responsive real-time interactions[2]\n  - 6G infrastructure in development phases, anticipated to further enhance connectivity capabilities[3]\n  - Content Delivery Networks (CDNs) and load balancers distributing content geographically for optimised user experience[4]\n  - InterPlanetary File System (IPFS) enabling decentralised content hosting without centralised server dependency[2]\n\n- Storage and data management\n  - Distributed storage systems supporting persistent digital twins—digital replicas of physical objects and locations fed by real-world data[5]\n  - Blockchain-based storage for immutable asset ownership records and transaction histories[5]\n  - Redundant power systems and failover mechanisms ensuring service continuity[6]\n\n- Security and authentication infrastructure\n  - Encryption protocols protecting user data and privacy across distributed systems[1]\n  - Access control mechanisms and cybersecurity protocols establishing trusted environments[1]\n  - Smart contract auditing and regulatory alignment for blockchain-based asset management[4]\n\n- Energy infrastructure challenges\n  - Advanced cooling systems consuming 30-40% of data centre energy budgets[6]\n  - Projected carbon footprint of 77-125 million metric tonnes CO₂ annually by 2030 if powered by fossil fuels[6]\n  - Renewable energy integration emerging as critical sustainability requirement for scalable deployment[6]\n\n- Standards and frameworks\n  - Service-oriented architecture patterns using Kubernetes and Docker containerisation[4]\n  - ERC-721/ERC-1155 standards for non-fungible token implementation[4]\n  - ERC-20 token standards for in-platform economies and governance mechanisms[4]\n\n## Research & Literature\n\n- Foundational frameworks\n  - Radoff, J. (2021). The Metaverse Value-Chain. *Convergence*. Establishes the seven-layer taxonomy widely adopted across industry and academia[2]\n  - IEEE Metaverse Reality publications documenting infrastructure component integration and persistent digital twin concepts[5]\n\n- Technical infrastructure studies\n  - Emerging research on edge computing distribution and latency optimisation for immersive experiences\n  - Studies examining blockchain scalability constraints for high-concurrency metaverse transactions\n  - Research into AI-driven infrastructure optimisation and predictive resource allocation\n\n- Energy and sustainability research\n  - 8M Solar (2025). Analysis of renewable energy requirements for metaverse infrastructure sustainability[6]\n  - Ongoing research into carbon-neutral data centre operations and grid integration challenges\n\n## UK Context\n\n- British technology contributions\n  - UK-based cloud infrastructure providers and CDN operators supporting metaverse platforms\n  - Research institutions (Imperial College London, University of Manchester) investigating distributed computing architectures and edge computing optimisation\n\n- North England innovation considerations\n  - Manchester's emerging position in digital infrastructure research, particularly around edge computing and distributed systems\n  - Potential for regional data centre development supporting latency-sensitive metaverse applications\n  - Limited but growing involvement in blockchain infrastructure standardisation efforts\n\n- Regulatory environment\n  - UK regulatory framework increasingly addressing data sovereignty and cybersecurity requirements for metaverse infrastructure\n  - Financial Conduct Authority guidance on smart contract compliance and token-based economies\n\n## Future Directions\n\n- Emerging technological trajectories\n  - Neural interfaces and biosensors advancing human-computer interaction beyond current VR/AR headsets[2]\n  - Microelectromechanical systems (MEMS) enabling contact lens-based computing and sensing[3]\n  - 6G networks anticipated to provide unprecedented bandwidth and ultra-low latency capabilities\n\n- Anticipated infrastructure challenges\n  - Scalability bottlenecks as concurrent user populations approach millions\n  - Energy consumption sustainability requiring renewable energy integration at scale[6]\n  - Interoperability standards development across competing metaverse platforms and proprietary systems\n  - Latency reduction requirements for photorealistic real-time rendering and haptic feedback\n\n- Research priorities\n  - Decentralised infrastructure models reducing dependency on centralised data centre operators\n  - AI-driven infrastructure optimisation and predictive resource allocation\n  - Quantum computing applications for cryptographic security and complex spatial computations\n  - Sustainable infrastructure design minimising environmental impact whilst maintaining performance\n\n## Metadata\n\n- Last Updated: 2025-11-11\n- Review Status: Comprehensive editorial review completed\n- Verification: Current academic and industry sources verified as of November 2025\n- Regional Context: UK and North England context integrated where substantively relevant\n- Format: Logseq nested bullet structure with academic precision and cordial tone",
  "properties": {
    "id": "infrastructurelayer-ontology",
    "collapsed": "true",
    "- ontology": "true",
    "- term-id": "20169",
    "- source-domain": "metaverse",
    "- status": "draft",
    "- public-access": "true"
  },
  "backlinks": [],
  "wiki_links": [],
  "ontology": {
    "term_id": "20169",
    "preferred_term": "Infrastructure Layer",
    "definition": "",
    "source_domain": "metaverse",
    "maturity_level": null,
    "authority_score": null
  }
}