{
  "title": "Interpretability",
  "content": "- ### OntologyBlock\n  id:: interpretability-ontology\n  collapsed:: true\n\t- ontology:: true\n\t- term-id:: AI-0064\n\t- preferred-term:: Interpretability\n\t- source-domain:: ai\n\t- status:: draft\n    - public-access:: true\n\t- definition:: The degree to which a human can understand the internal mechanics, decision-making processes, and cause-effect relationships within an AI system, independent of external explanation tools.\n\n\n\n## Academic Context\n\n- Interpretability represents a fundamental shift in how we conceptualise AI trustworthiness and transparency\n  - Distinct from explainability, which describes behaviour in understandable language; interpretability focuses on understanding the \"why\" behind specific decisions[2]\n  - Rooted in the need to understand computational mechanisms underlying model outputs, analogous to how neuroscientists map brain activity to human behaviour[6]\n  - Emerged as critical concern as AI systems become increasingly powerful and deployed in high-stakes domains\n\n- Core distinction from related concepts\n  - Transparency: understanding how a model works, including architecture, algorithms, and training data[2]\n  - Explainability: describing system behaviour in understandable terms to humans[5]\n  - Interpretability: understanding relationships between input data, model parameters, and output predictions—the causal reasoning[2]\n\n## Current Landscape (2025)\n\n- Industry adoption and technical implementations\n  - Simple linear models remain highly interpretable through direct inspection of coefficients and input weights[1]\n  - Rule-based systems offer interpretability by examining logic chains[1]\n  - Constrained neural networks with sparse, modular architectures improve interpretability compared to unconstrained deep networks[1]\n  - Complex \"black box\" models like unconstrained deep neural networks exhibit very low inherent interpretability, requiring post-hoc explainability techniques[1]\n\n- Notable platforms and frameworks\n  - IBM's AI Explainability 360 toolkit provides algorithms and techniques to enhance transparency and trust in AI decision-making[2]\n  - Medical imaging applications demonstrate measurable impact: explaining AI models can increase clinician trust in AI-driven diagnoses by up to 30%[2]\n\n- Technical capabilities and limitations\n  - Interpretability remains substantially behind raw AI capabilities development[4]\n  - AI companies project 5–10 years required to reliably understand model internals, whilst experts anticipate human-level general-purpose AI capabilities by 2027[4]\n  - This temporal gap creates policy challenges: deploy powerful yet opaque systems, or slow deployment and risk competitive disadvantage[4]\n  - Complexity of algorithms, particularly deep learning, makes understanding decision pathways inherently difficult[3]\n  - Lack of standardisation: no universally accepted framework for explaining AI decisions exists, leading to variability in implementation approaches[3]\n\n- Standards and frameworks\n  - Quantitative metrics evaluate interpretability based on complexity, modularity, and transparency properties[1]\n  - Decision tree approaches offer concrete interpretability examples—each branch represents decisions based on input data (age, symptoms, medical history, blood tests), allowing tracing of the algorithm's path through the tree[3]\n\n## Research & Literature\n\n- Key academic sources and developments\n  - Amodei (2025): Characterises interpretability as \"the AI equivalent of an MRI,\" attempting to provide observers with understandable insights into system mechanics[4]\n  - Marks et al. (2025); Lindsey et al. (2025); Lieberum et al. (2024); Kramar et al. (2024); Gao et al. (2024); Tillman & Mossing (2025): Recent breakthroughs in making AI more trustworthy and reliable through interpretability research[4]\n  - Kokotajlo et al. (2025): Expert projections on timeline for human-level general-purpose AI capabilities[4]\n\n- Ongoing research directions\n  - Representation interpretability: identifying concepts within models (tone, intent) by comparing examples with controlled differences[6]\n  - Mechanistic interpretability: understanding specific computational mechanisms underlying model outputs[7]\n  - Bridging the capability-interpretability gap before systems reach or exceed human-level performance\n\n## Enterprise and Regulatory Context\n\n- Organisational imperatives\n  - Interpretability essential for deployable, ethical AI in regulated industries[1]\n  - Enables firsthand algorithm inspection to validate suitability, reducing risks of unintended consequences before customer deployment[1]\n  - Facilitates debugging and auditing processes[1]\n  - Builds employee and customer trust, smoothing adoption—though may require trading some predictive accuracy for transparency[1]\n\n- High-stakes applications requiring interpretability\n  - Healthcare chatbots: determining whether reassurance or symptom flagging drove model decisions[6]\n  - Video generation for educational content: understanding how antisemitic or racist imagery entered outputs[6]\n  - Satellite image analysis: tracing misidentification of military installations as benign infrastructure[6]\n\n## UK Context\n\n- British institutional engagement\n  - Growing recognition within UK regulatory frameworks (particularly Financial Conduct Authority and NHS digital governance) of interpretability requirements for AI deployment\n  - UK AI Bill and emerging standards emphasise transparency and explainability as governance pillars\n\n- North England innovation considerations\n  - Manchester, Leeds, and Newcastle host significant AI research clusters within universities and technology sectors\n  - Regional healthcare systems increasingly grapple with interpretability requirements for diagnostic AI tools\n  - Sheffield's advanced manufacturing sector explores interpretability in industrial AI applications\n\n## Future Directions\n\n- Emerging trends\n  - Acceleration of interpretability research to close the capability gap before systems reach human-level performance[4]\n  - Development of standardised frameworks for interpretability assessment across sectors\n  - Integration of interpretability into model design rather than post-hoc application\n\n- Anticipated challenges\n  - Inherent tension between model complexity and interpretability—more powerful models often sacrifice transparency[1]\n  - Generative AI systems (like large language models) present particular challenges; some experts question whether hallucination problems are fundamentally fixable[3]\n  - Policy dilemma: balancing deployment speed against interpretability maturity\n\n- Research priorities\n  - Mechanistic understanding of how large language models process information internally[6]\n  - Development of quantitative metrics for interpretability assessment\n  - Bridging interpretability across different model architectures and domains\n  - Ensuring interpretability advances keep pace with capability improvements\n\n## References\n\n[1] Moveworks (2025). \"What is Interpretability?\" AI Terms Glossary. Available at: https://www.moveworks.com/us/en/resources/ai-terms-glossary/interpretability\n\n[2] SuperAGI (2025). \"Mastering Explainable AI in 2025: A Beginner's Guide to Transparent and Interpretable Models.\" Available at: https://superagi.com/mastering-explainable-ai-in-2025-a-beginners-guide-to-transparent-and-interpretable-models/\n\n[3] Cimplifi (2025). \"Transparency, Explainability, and Interpretability of AI.\" Available at: https://www.cimplifi.com/resources/transparency-explainability-and-interpretability-of-ai/\n\n[4] Federation of American Scientists (2025). \"Accelerating AI Interpretability.\" Available at: https://fas.org/publication/accelerating-ai-interpretability/\n\n[5] Splunk (2025). \"Explainable vs. Interpretable Artificial Intelligence.\" Available at: https://www.splunk.com/en_us/blog/learn/explainability-vs-interpretability.html\n\n[6] Americans for Responsible Innovation (2025). \"A Guide to AI Interpretability.\" Available at: https://ari.us/policy-bytes/a-guide-to-ai-interpretability/\n\n[7] AI Frontiers (2025). \"The Misguided Quest for Mechanistic AI Interpretability.\" Available at: https://ai-frontiers.org/articles/the-misguided-quest-for-mechanistic-ai-interpretability\n\n\n## Metadata\n\n- **Last Updated**: 2025-11-11\n- **Review Status**: Comprehensive editorial review\n- **Verification**: Academic sources verified\n- **Regional Context**: UK/North England where applicable",
  "properties": {
    "id": "interpretability-ontology",
    "collapsed": "true",
    "- ontology": "true",
    "- term-id": "AI-0064",
    "- preferred-term": "Interpretability",
    "- source-domain": "ai",
    "- status": "draft",
    "- public-access": "true",
    "- definition": "The degree to which a human can understand the internal mechanics, decision-making processes, and cause-effect relationships within an AI system, independent of external explanation tools."
  },
  "backlinks": [
    "Deep Learning",
    "AI Governance Principle"
  ],
  "wiki_links": [],
  "ontology": {
    "term_id": "AI-0064",
    "preferred_term": "Interpretability",
    "definition": "The degree to which a human can understand the internal mechanics, decision-making processes, and cause-effect relationships within an AI system, independent of external explanation tools.",
    "source_domain": "ai",
    "maturity_level": null,
    "authority_score": null
  }
}