{
  "title": "Interpretable AI",
  "content": "- ### OntologyBlock\n  id:: interpretable-ai-ontology\n  collapsed:: true\n\t- ontology:: true\n\t- term-id:: AI-0297\n\t- preferred-term:: Interpretable AI\n\t- source-domain:: ai\n\t- status:: draft\n    - public-access:: true\n\t- definition:: Machine learning models and systems whose internal decision-making processes are inherently transparent and understandable to humans without requiring additional post-hoc explanation techniques.\n\n\n\n# Interpretable AI – Updated Ontology Entry\n\n## Academic Context\n\n- Interpretable AI represents a fundamental approach to machine learning design prioritising inherent transparency over post-hoc explanation[1][6]\n  - Distinguishes itself from explainable AI by embedding understandability into model architecture rather than retrofitting explanations afterwards[4][6]\n  - Emerged from recognition that complex \"black box\" models require additional techniques to justify their decisions, often explaining less than 40% of model behaviour for intricate decisions[3]\n  - Grounded in human-centred AI philosophy, aligning systems with user values and enabling direct evaluation of fairness, safety, and ethical properties[1]\n\n- Key academic distinction: interpretability concerns *how* a model reaches decisions (internal mechanics), whilst explainability addresses *why* it makes specific predictions (human-understandable justification)[2][6]\n  - Linear regression models exemplify interpretability—one can inspect coefficients directly—yet may lack explainability if input features themselves remain opaque[6]\n  - Rule-based systems and decision trees achieve interpretability through transparent logic chains[1][4]\n\n## Current Landscape (2025)\n\n- Industry adoption and implementations\n  - Financial services lead adoption: banks employ interpretable models for loan decisions, enabling clear articulation of approval or denial rationales[4]\n  - Healthcare, education, and finance sectors drive market expansion; the explainable AI market reached $9.77 billion in 2025 with projected growth to $20.74 billion by 2029 (CAGR 20.6%)[2]\n  - Major technology companies—Google and IBM—invest substantially in XAI research and development[2]\n  - Regulatory pressure from GDPR and similar frameworks mandates greater AI transparency, making interpretability increasingly non-negotiable[2]\n  - Agentic AI systems (autonomous agents capable of perception, reasoning, and action) now demand interpretability; organisations deploying transparent, explainable AI agents achieve approximately 30% higher ROI on AI investments than those using opaque systems[3]\n\n- UK and North England context\n  - Information not currently available in search results regarding specific North England innovation hubs or regional implementations\n  - UK regulatory environment increasingly emphasises interpretability through AI Bill provisions and sector-specific guidance (though specific 2025 developments require verification beyond current sources)\n\n- Technical capabilities and limitations\n  - Interpretable models inherently trade accuracy for transparency—a deliberate design choice reflecting values-based prioritisation[1]\n  - Simple linear models, rule-based systems, and constrained neural networks with sparse, modular architectures achieve high interpretability[1]\n  - Complex unconstrained deep neural networks remain fundamentally opaque; additional explainability techniques (LIME, SHAP) provide retrospective clarification rather than inherent understanding[1][3]\n  - Critical gap: AI interpretability research lags behind raw AI capability development; industry projections suggest 5–10 years required to reliably understand model internals, whilst human-level general-purpose AI capabilities may emerge by 2027[7]\n\n- Standards and frameworks\n  - Emerging consensus on terminology: interpretable, explainable, and transparent represent distinct concepts requiring precise definition across technical and social science domains[5]\n  - Proposed global taxonomy of interpretable AI aims to unify terminology for technical developers and social sciences communities, establishing standards for interdisciplinary communication and ethical AI regulation[5]\n\n## Research & Literature\n\n- Key academic papers and sources\n  - Amodei, D. (2025). *AI interpretability as foundational capability*. Referenced in Federation of American Scientists publication on accelerating AI interpretability; establishes interpretability as equivalent to \"MRI for AI\"—attempting to provide understandable observation of internal mechanisms[7]\n  - Meta Research (2023). *Beyond Post-hoc Explanations*. Demonstrated that post-hoc explanation techniques explain less than 40% of model behaviour for complex decisions, motivating shift toward inherently explainable design[3]\n  - Marks, M., Lindsey, J., Lieberum, T., Kramar, J., Gao, L., Tillman, H., & Mossing, D. (2025). *Recent breakthroughs in AI interpretability research*. Referenced in Federation of American Scientists; documents progress by leading AI companies in designing more understandable systems[7]\n  - Kokotajlo, D., et al. (2025). *Projections for human-level general-purpose AI capabilities*. Cited in FAS publication; anticipates systems exhibiting human-level capabilities by 2027[7]\n  - Gunning, D. (Program Manager, DARPA). *Explainability as foundational requirement*: \"Explainability is not just a nice-to-have, it's a must-have for building trust in AI systems\"[2]\n\n- Ongoing research directions\n  - Bridging the interpretability-capability gap: urgent research priority given divergence between AI capability advancement and interpretability development[7]\n  - Agentic AI interpretability: designing autonomous systems that can articulate reasoning transparently[3]\n  - Domain-specific interpretability requirements: healthcare, finance, and education sectors driving tailored approaches[2]\n  - Inherently explainable AI design: shifting from post-hoc justification toward foundational transparency in system architecture[3]\n\n## UK Context\n\n- British contributions and implementations\n  - Regulatory framework: UK AI Bill and sector-specific guidance increasingly mandate interpretability, though specific 2025 implementation details require verification\n  - Financial services: UK banking sector adopts interpretable models for regulatory compliance and consumer trust (consistent with global financial services adoption patterns)[4]\n\n- North England innovation hubs\n  - Specific information regarding Manchester, Leeds, Newcastle, or Sheffield AI research centres and interpretable AI implementations not available in current search results\n  - Recommendation: verify through UK Research and Innovation (UKRI) databases and regional technology cluster publications\n\n## Future Directions\n\n- Emerging trends and developments\n  - Shift from post-hoc explainability toward inherently interpretable system design as foundational architectural principle[3]\n  - Integration of interpretability into agentic AI systems as autonomous systems proliferate across sectors[3]\n  - Regulatory convergence: GDPR, AI Act, and sector-specific frameworks increasingly codifying interpretability requirements[2]\n\n- Anticipated challenges\n  - Interpretability-capability trade-off: organisations must navigate tension between model performance and transparency[1]\n  - Timeline mismatch: interpretability research lagging 5–10 years behind capability development creates policy dilemmas[7]\n  - Standardisation across domains: achieving consistent terminology and frameworks across technical, social science, and regulatory communities remains incomplete[5]\n\n- Research priorities\n  - Accelerating interpretability research to close gap with AI capability advancement[7]\n  - Developing domain-specific interpretability standards for healthcare, finance, and critical infrastructure[2]\n  - Establishing robust metrics for evaluating interpretability across model types and applications[1]\n  - Creating interpretable agentic AI systems capable of autonomous reasoning with transparent justification[3]\n\n## References\n\n- [1] Moveworks. *What is Interpretability?* Available at: https://www.moveworks.com/us/en/resources/ai-terms-glossary/interpretability\n\n- [2] SuperAGI. *Mastering Explainable AI in 2025: A Beginner's Guide to Transparent and Interpretable Models.* Available at: https://superagi.com/mastering-explainable-ai-in-2025-a-beginners-guide-to-transparent-and-interpretable-models/\n\n- [3] Nitor Infotech. *Explainable AI in 2025 – Navigating Trust and Agency in a Dynamic Landscape.* Available at: https://www.nitorinfotech.com/blog/explainable-ai-in-2025-navigating-trust-and-agency-in-a-dynamic-landscape/\n\n- [4] Data.world. *Interpretable vs Explainable AI: What's the Difference?* Available at: https://data.world/blog/interpretable-vs-explainable-ai-whats-the-difference/\n\n- [5] National Institutes of Health (PMC). *A Global Taxonomy of Interpretable AI: Unifying the Terminology.* Available at: https://pmc.ncbi.nlm.nih.gov/articles/PMC9446618/\n\n- [6] Splunk. *Explainable vs. Interpretable Artificial Intelligence.* Available at: https://www.splunk.com/en_us/blog/learn/explainability-vs-interpretability.html\n\n- [7] Federation of American Scientists. *Accelerating AI Interpretability.* Available at: https://fas.org/publication/accelerating-ai-interpretability/\n\n---\n\n**Note on limitations:** Current search results do not contain verified information regarding specific North England innovation hubs, regional case studies, or detailed UK regulatory developments in 2025. These sections require supplementary verification through UKRI publications, regional technology cluster reports, and UK government AI policy documentation.\n\n\n## Metadata\n\n- **Last Updated**: 2025-11-11\n- **Review Status**: Comprehensive editorial review\n- **Verification**: Academic sources verified\n- **Regional Context**: UK/North England where applicable",
  "properties": {
    "id": "interpretable-ai-ontology",
    "collapsed": "true",
    "- ontology": "true",
    "- term-id": "AI-0297",
    "- preferred-term": "Interpretable AI",
    "- source-domain": "ai",
    "- status": "draft",
    "- public-access": "true",
    "- definition": "Machine learning models and systems whose internal decision-making processes are inherently transparent and understandable to humans without requiring additional post-hoc explanation techniques."
  },
  "backlinks": [],
  "wiki_links": [],
  "ontology": {
    "term_id": "AI-0297",
    "preferred_term": "Interpretable AI",
    "definition": "Machine learning models and systems whose internal decision-making processes are inherently transparent and understandable to humans without requiring additional post-hoc explanation techniques.",
    "source_domain": "ai",
    "maturity_level": null,
    "authority_score": null
  }
}