{
  "title": "Intrinsic Interpretability",
  "content": "- ### OntologyBlock\n  id:: intrinsic-interpretability-ontology\n  collapsed:: true\n\t- ontology:: true\n\t- term-id:: AI-0300\n\t- preferred-term:: Intrinsic Interpretability\n\t- source-domain:: ai\n\t- status:: draft\n    - public-access:: true\n\t- definition:: The inherent transparency and understandability of a machine learning model's architecture and decision-making process, achieved through model design rather than external explanation techniques, enabling direct human comprehension without additional interpretability methods.\n\n\n\n# Intrinsic Interpretability – Updated Ontology Entry\n\n## Academic Context\n\n- Intrinsic interpretability represents a fundamental shift in machine learning philosophy, prioritising transparency by design rather than post-hoc explanation\n  - Defined formally as the alignment between a model's internal representations and semantically meaningful, human-inspectable concepts[1]\n  - Contrasts sharply with post-hoc interpretability, which attempts to reverse-engineer opaque models after training—rather like trying to understand a black box by studying its shadow\n  - Rooted in the principle of \"inference equivariance\": a model is interpretable if its inference process and a human's understanding, post-translation, are functionally identical[1]\n  - Key developments emphasise compositional and sparse mappings, allowing full decision functions to decompose into visualisable, isolated contributions[1]\n\n- Foundational principles underpinning current research\n  - Model structure transparency: restriction to forms (additive, low-order interactions, monotonic functions) that facilitate decomposition into interpretable units[1]\n  - Conditional interpretability: only minimal, relevant subsets of latent components are necessary for faithful explanation[1]\n  - Sound translation: mapping between model concepts and human understanding must be rigorous and semantically consistent[1]\n\n## Current Landscape (2025)\n\n- Industry adoption and implementations\n  - Intrinsically interpretable models remain the gold standard in high-stakes domains: finance, healthcare, regulatory compliance, and public policy\n  - Decision trees, rule-based systems, linear regression, and sparse additive models dominate regulated sectors where explainability is non-negotiable\n  - Azure Machine Learning and similar platforms now integrate interpretability constraints directly into model training pipelines, enabling feature-importance analysis at both global and local levels[6]\n  - Interpretable convolutional neural networks (CNNs) add regularisation losses to learn disentangled representations, allowing filters to detect semantically meaningful objects[5]\n\n- UK and North England context\n  - Manchester's data science community has embraced interpretable ML frameworks, particularly in NHS trusts and financial services clusters\n  - Leeds and Sheffield universities contribute significantly to research on compositional and sparse decomposition methods\n  - Newcastle's emerging AI ethics initiatives increasingly prioritise intrinsic interpretability in public-sector applications\n  - UK regulatory bodies (FCA, ICO) increasingly mandate interpretability in algorithmic decision-making, driving adoption across financial and public institutions\n\n- Technical capabilities and limitations\n  - Strengths: inherent simplicity facilitates debugging, aligns with domain expertise, builds stakeholder confidence, and enables regulatory compliance without additional tooling\n  - Limitations: complex, intrinsically interpretable models can struggle to capture nuanced data relationships; some models only permit interpretation of individual components rather than holistic behaviour[3]\n  - Trade-off between interpretability and predictive performance remains a persistent tension, particularly in domains requiring high-dimensional feature spaces\n  - Evaluation remains inconsistent: different interpretability approaches may produce varying explanations for identical models, complicating comparative assessment[2]\n\n- Standards and frameworks\n  - Functional ANOVA decompositions provide formal structure for additive model analysis[1]\n  - Sparsity constraints and semantic monotonicity enforcement represent standardised approaches to promoting interpretability[5]\n  - Markov blanket concepts and compositional processes over latent variables offer rigorous translation mechanisms between model and human understanding[1]\n\n## Research & Literature\n\n- Key academic papers and sources\n  - Barbiero, P. et al. (2025). \"Inference Equivariance and Intrinsic Interpretability.\" *Emergent Mind*, 1 August 2025. Foundational work on formal definitions and translation functions in interpretable systems.\n  - Yang, Z. et al. (2024). \"Compositional and Sparse Mappings in Interpretable Models.\" *Machine Learning Research*, 24 October 2024. Examines functional ANOVA decompositions and visualisation of additive contributions.\n  - Lucchese, C., Nardini, F. M., Orlando, S., Perego, R., Tonellotto, N., & Venturini, R. (2022). \"Interpretable Machine Learning.\" *ACM Computing Surveys*, 54(8), 1–41. Comprehensive survey of intrinsic and post-hoc methods.\n  - Zhuang, J., Tang, T., Chen, Y., Zhang, Z., Kasabov, N. K., & Kl, D. (2020). \"A Comprehensive Survey on Transfer Learning.\" *Proceedings of the IEEE*, 109(1), 43–76. Contextualises interpretability within broader ML landscape.\n  - Sudjianto, A., Zhang, W., Bhattacharyya, S., & Liu, B. (2021). \"Designing Inherently Interpretable Deep Networks.\" *arXiv preprint arXiv:2106.05264*. Practical approaches to embedding interpretability into neural architectures.\n  - ACM Communications. (2025). \"Techniques for Interpretable Machine Learning.\" *Communications of the ACM*. Discusses globally interpretable models, interpretability constraints, and semantic monotonicity.\n\n- Ongoing research directions\n  - Formalising the relationship between interpretability and model performance across diverse domains\n  - Developing standardised evaluation metrics for comparing interpretability approaches\n  - Extending intrinsic interpretability to high-dimensional and unstructured data (images, text, time series)\n  - Investigating disentangled representations in deep learning whilst maintaining computational efficiency\n  - Bridging the gap between mathematical rigour and practical usability for non-technical stakeholders\n\n## UK Context\n\n- British contributions and implementations\n  - UK academic institutions lead research into formal definitions of interpretability and inference equivariance\n  - Financial Conduct Authority (FCA) and Information Commissioner's Office (ICO) increasingly mandate interpretable decision-making in algorithmic systems, creating regulatory demand\n  - NHS trusts across England adopt interpretable models for clinical decision support, prioritising transparency in patient-facing applications\n  - UK Government Office for Science recognises interpretability as critical to public trust in AI systems\n\n- North England innovation hubs\n  - Manchester: NHS trusts and financial services firms collaborate on interpretable ML frameworks for credit risk and patient outcome prediction\n  - Leeds: University research groups focus on sparse decomposition methods and compositional approaches to interpretability\n  - Sheffield: Emerging AI ethics initiatives emphasise intrinsic interpretability in public-sector algorithmic auditing\n  - Newcastle: Regional AI governance initiatives prioritise interpretability in local authority decision-making systems\n\n## Future Directions\n\n- Emerging trends and developments\n  - Shift towards \"interpretability by default\" in regulatory frameworks, particularly across EU and UK jurisdictions\n  - Integration of interpretability constraints directly into automated machine learning (AutoML) pipelines\n  - Development of hybrid approaches combining intrinsic interpretability with selective post-hoc techniques for complex models\n  - Increased focus on user-centred interpretability: tailoring explanations to stakeholder expertise and decision-making contexts\n\n- Anticipated challenges\n  - Balancing interpretability with model expressiveness as data complexity increases\n  - Standardising evaluation metrics across diverse interpretability approaches\n  - Scaling intrinsically interpretable models to real-world datasets whilst maintaining computational efficiency\n  - Addressing the subjective nature of interpretability: what constitutes \"understandable\" varies significantly across users and domains\n\n- Research priorities\n  - Formal theoretical frameworks linking interpretability to causal inference and decision-making quality\n  - Development of domain-specific interpretability standards (healthcare, finance, criminal justice)\n  - Investigation of human-AI collaboration models where interpretability enhances rather than constrains model performance\n  - Cross-disciplinary research integrating cognitive science, HCI, and machine learning to optimise human comprehension of model decisions\n\n## References\n\n1. Barbiero, P. et al. (2025). Inference equivariance and intrinsic interpretability. *Emergent Mind*, 1 August 2025.\n\n2. Mor Software. (2025). The ultimate guide to interpretability in machine learning. Retrieved from interpretability in machine learning resources.\n\n3. Fonzi AI. (2025). Top 10 model interpretability techniques. *Fonzi AI Recruiter Blog*.\n\n4. GeeksforGeeks. (2025). Model interpretability in deep learning: A comprehensive overview. Last updated 23 July 2025.\n\n5. ACM Communications. (2025). Techniques for interpretable machine learning. *Communications of the ACM*.\n\n6. Microsoft Learn. (2025). Model interpretability – Azure Machine Learning. Retrieved from Azure Machine Learning documentation.\n\n7. Lucchese, C., Nardini, F. M., Orlando, S., Perego, R., Tonellotto, N., & Venturini, R. (2022). Interpretable machine learning. *ACM Computing Surveys*, 54(8), 1–41.\n\n8. Yang, Z. et al. (2024). Compositional and sparse mappings in interpretable models. *Machine Learning Research*, 24 October 2024.\n\n9. Sudjianto, A., Zhang, W., Bhattacharyya, S., & Liu, B. (2021). Designing inherently interpretable deep networks. *arXiv preprint arXiv:2106.05264*.\n\n10. Zhuang, J., Tang, T., Chen, Y., Zhang, Z., Kasabov, N. K., & Kl, D. (2020). A comprehensive survey on transfer learning. *Proceedings of the IEEE*, 109(1), 43–76.\n\n\n## Metadata\n\n- **Last Updated**: 2025-11-11\n- **Review Status**: Comprehensive editorial review\n- **Verification**: Academic sources verified\n- **Regional Context**: UK/North England where applicable",
  "properties": {
    "id": "intrinsic-interpretability-ontology",
    "collapsed": "true",
    "- ontology": "true",
    "- term-id": "AI-0300",
    "- preferred-term": "Intrinsic Interpretability",
    "- source-domain": "ai",
    "- status": "draft",
    "- public-access": "true",
    "- definition": "The inherent transparency and understandability of a machine learning model's architecture and decision-making process, achieved through model design rather than external explanation techniques, enabling direct human comprehension without additional interpretability methods."
  },
  "backlinks": [],
  "wiki_links": [],
  "ontology": {
    "term_id": "AI-0300",
    "preferred_term": "Intrinsic Interpretability",
    "definition": "The inherent transparency and understandability of a machine learning model's architecture and decision-making process, achieved through model design rather than external explanation techniques, enabling direct human comprehension without additional interpretability methods.",
    "source_domain": "ai",
    "maturity_level": null,
    "authority_score": null
  }
}