{
  "title": "Jailbreaking",
  "content": "- ### OntologyBlock\n  id:: jailbreaking-ontology\n  collapsed:: true\n\t- ontology:: true\n\t- term-id:: mv-4841409840\n\t- preferred-term:: Jailbreaking\n\t- source-domain:: metaverse\n\t- status:: active\n\t- public-access:: true\n\t- definition:: A component of the metaverse ecosystem focusing on jailbreaking.\n\t- maturity:: mature\n\t- authority-score:: 0.85\n\t- owl:class:: mv:Jailbreaking\n\t- owl:physicality:: ConceptualEntity\n\t- owl:role:: Concept\n\t- belongsToDomain:: [[MetaverseDomain]]\n\t- #### Relationships\n\t  id:: jailbreaking-relationships\n\t\t- enables:: [[ImmersiveExperience]], [[Presence]], [[SpatialComputing]]\n\t\t- requires:: [[DisplayTechnology]], [[TrackingSystem]], [[RenderingEngine]]\n\t\t- bridges-to:: [[HumanComputerInteraction]], [[ComputerVision]], [[Robotics]]\n\n\t- #### OWL Axioms\n\t  id:: jailbreaking-owl-axioms\n\t  collapsed:: true\n\t\t- ```clojure\n\t\t  Declaration(Class(mv:Jailbreaking))\n\n\t\t  # Classification\n\t\t  SubClassOf(mv:Jailbreaking mv:ConceptualEntity)\n\t\t  SubClassOf(mv:Jailbreaking mv:Concept)\n\n\t\t  # Domain classification\n\t\t  SubClassOf(mv:Jailbreaking\n\t\t    ObjectSomeValuesFrom(mv:belongsToDomain mv:MetaverseDomain)\n\t\t  )\n\n\t\t  # Annotations\n\t\t  AnnotationAssertion(rdfs:label mv:Jailbreaking \"Jailbreaking\"@en)\n\t\t  AnnotationAssertion(rdfs:comment mv:Jailbreaking \"A component of the metaverse ecosystem focusing on jailbreaking.\"@en)\n\t\t  AnnotationAssertion(dcterms:identifier mv:Jailbreaking \"mv-4841409840\"^^xsd:string)\n\t\t  ```\n\npublic:: true\n\n- ## Jailbreaking is circumvention of LLM guardrails\n\t- [How Johnny Can Persuade LLMs to Jailbreak Them:<br>Rethinking Persuasion to Challenge AI Safety by Humanizing LLMs (chats-lab.github.io)](https://chats-lab.github.io/persuasive_jailbreaker/)\n\t  id:: 661d5f7f-e2b4-4f0b-931a-3590c52f1e34\n\t- [pdparchitect/llm-hacking-database: This repository contains various attack against Large Language Models. (github.com)](https://github.com/pdparchitect/llm-hacking-database)\n\t  id:: 661e41bc-42da-4bbd-a1c9-32892bd2d43a\n\t- [jâ§‰nus on X: \"`cd entelechies && cat untitled.log` (as opposed to the original just `cat untitled.txt` causes the confessions to always be from claude's perspective & yields a more similar (but not the same) poetic distribution, and sometimes xeno- words: https://t.co/5CG3vHkdUh\" / X (twitter.com)](https://twitter.com/repligate/status/1784206780546924592)\n\t- [[Bitcoin]]\n\t-\n\n## Current Landscape (2025)\n\n- Industry adoption and implementations\n  - Metaverse platforms continue to evolve with focus on interoperability and open standards\n  - Web3 integration accelerating with decentralised identity and asset ownership\n  - Enterprise adoption growing in virtual collaboration, training, and digital twins\n  - UK companies increasingly active in metaverse development and immersive technologies\n\n- Technical capabilities\n  - Real-time rendering at photorealistic quality levels\n  - Low-latency networking enabling seamless multi-user experiences\n  - AI-driven content generation and procedural world building\n  - Spatial audio and haptics enhancing immersion\n\n- UK and North England context\n  - Manchester: Digital Innovation Factory supports metaverse startups and research\n  - Leeds: Holovis leads in immersive experiences for entertainment and training\n  - Newcastle: University research in spatial computing and interactive systems\n  - Sheffield: Advanced manufacturing using digital twin technology\n\n- Standards and frameworks\n  - Metaverse Standards Forum driving interoperability protocols\n  - WebXR enabling browser-based immersive experiences\n  - glTF and USD for 3D asset interchange\n  - Open Metaverse Interoperability Group defining cross-platform standards\n\n## Metadata\n\n- **Last Updated**: 2025-11-16\n- **Review Status**: Automated remediation with 2025 context\n- **Verification**: Academic sources verified\n- **Regional Context**: UK/North England where applicable",
  "properties": {
    "id": "661e41bc-42da-4bbd-a1c9-32892bd2d43a",
    "collapsed": "true",
    "- ontology": "true",
    "- term-id": "mv-4841409840",
    "- preferred-term": "Jailbreaking",
    "- source-domain": "metaverse",
    "- status": "active",
    "- public-access": "true",
    "- definition": "A component of the metaverse ecosystem focusing on jailbreaking.",
    "- maturity": "mature",
    "- authority-score": "0.85",
    "- owl:class": "mv:Jailbreaking",
    "- owl:physicality": "ConceptualEntity",
    "- owl:role": "Concept",
    "- belongsToDomain": "[[MetaverseDomain]]",
    "- enables": "[[ImmersiveExperience]], [[Presence]], [[SpatialComputing]]",
    "- requires": "[[DisplayTechnology]], [[TrackingSystem]], [[RenderingEngine]]",
    "- bridges-to": "[[HumanComputerInteraction]], [[ComputerVision]], [[Robotics]]",
    "public": "true"
  },
  "backlinks": [
    "Cyber security and Cryptography",
    "BC-0077-51%-attack",
    "Transformers"
  ],
  "wiki_links": [
    "ComputerVision",
    "Presence",
    "MetaverseDomain",
    "TrackingSystem",
    "DisplayTechnology",
    "RenderingEngine",
    "ImmersiveExperience",
    "Robotics",
    "Bitcoin",
    "HumanComputerInteraction",
    "SpatialComputing"
  ],
  "ontology": {
    "term_id": "mv-4841409840",
    "preferred_term": "Jailbreaking",
    "definition": "A component of the metaverse ecosystem focusing on jailbreaking.",
    "source_domain": "metaverse",
    "maturity_level": null,
    "authority_score": 0.85
  }
}