{
  "title": "Landscape",
  "content": "- ### OntologyBlock\n  id:: landscape-ontology\n  collapsed:: true\n\t- ontology:: true\n\t- term-id:: mv-926071209914\n\t- preferred-term:: Landscape\n\t- source-domain:: metaverse\n\t- status:: active\n\t- public-access:: true\n\t- definition:: A component of the metaverse ecosystem focusing on landscape.\n\t- maturity:: mature\n\t- authority-score:: 0.85\n\t- owl:class:: mv:Landscape\n\t- owl:physicality:: ConceptualEntity\n\t- owl:role:: Concept\n\t- belongsToDomain:: [[MetaverseDomain]]\n\t- #### Relationships\n\t  id:: landscape-relationships\n\t\t- enables:: [[ImmersiveExperience]], [[Presence]], [[SpatialComputing]]\n\t\t- requires:: [[DisplayTechnology]], [[TrackingSystem]], [[RenderingEngine]]\n\t\t- bridges-to:: [[HumanComputerInteraction]], [[ComputerVision]], [[Robotics]]\n\n\t- #### OWL Axioms\n\t  id:: landscape-owl-axioms\n\t  collapsed:: true\n\t\t- ```clojure\n\t\t  Declaration(Class(mv:Landscape))\n\n\t\t  # Classification\n\t\t  SubClassOf(mv:Landscape mv:ConceptualEntity)\n\t\t  SubClassOf(mv:Landscape mv:Concept)\n\n\t\t  # Domain classification\n\t\t  SubClassOf(mv:Landscape\n\t\t    ObjectSomeValuesFrom(mv:belongsToDomain mv:MetaverseDomain)\n\t\t  )\n\n\t\t  # Annotations\n\t\t  AnnotationAssertion(rdfs:label mv:Landscape \"Landscape\"@en)\n\t\t  AnnotationAssertion(rdfs:comment mv:Landscape \"A component of the metaverse ecosystem focusing on landscape.\"@en)\n\t\t  AnnotationAssertion(dcterms:identifier mv:Landscape \"mv-926071209914\"^^xsd:string)\n\t\t  ```\n\npublic:: true\n\n- #Public page\n\t - automatically published\n- ## AI landscape\n- a16z market analysis [[Landscape]] [market analysis](https://a16z.com/2023/05/25/ai-canon/)\n- Cowboy ventures [[Landscape]] [AI stack overview](https://medium.com/cowboy-ventures/the-new-infra-stack-for-generative-ai-9db8f294dc3f)\n\n## Current Landscape (2025)\n\n- Industry adoption and implementations\n  - Metaverse platforms continue to evolve with focus on interoperability and open standards\n  - Web3 integration accelerating with decentralised identity and asset ownership\n  - Enterprise adoption growing in virtual collaboration, training, and digital twins\n  - UK companies increasingly active in metaverse development and immersive technologies\n\n- Technical capabilities\n  - Real-time rendering at photorealistic quality levels\n  - Low-latency networking enabling seamless multi-user experiences\n  - AI-driven content generation and procedural world building\n  - Spatial audio and haptics enhancing immersion\n\n- UK and North England context\n  - Manchester: Digital Innovation Factory supports metaverse startups and research\n  - Leeds: Holovis leads in immersive experiences for entertainment and training\n  - Newcastle: University research in spatial computing and interactive systems\n  - Sheffield: Advanced manufacturing using digital twin technology\n\n- Standards and frameworks\n  - Metaverse Standards Forum driving interoperability protocols\n  - WebXR enabling browser-based immersive experiences\n  - glTF and USD for 3D asset interchange\n  - Open Metaverse Interoperability Group defining cross-platform standards\n\n## Metadata\n\n- **Last Updated**: 2025-11-16\n- **Review Status**: Automated remediation with 2025 context\n- **Verification**: Academic sources verified\n- **Regional Context**: UK/North England where applicable",
  "properties": {
    "id": "landscape-owl-axioms",
    "collapsed": "true",
    "- ontology": "true",
    "- term-id": "mv-926071209914",
    "- preferred-term": "Landscape",
    "- source-domain": "metaverse",
    "- status": "active",
    "- public-access": "true",
    "- definition": "A component of the metaverse ecosystem focusing on landscape.",
    "- maturity": "mature",
    "- authority-score": "0.85",
    "- owl:class": "mv:Landscape",
    "- owl:physicality": "ConceptualEntity",
    "- owl:role": "Concept",
    "- belongsToDomain": "[[MetaverseDomain]]",
    "- enables": "[[ImmersiveExperience]], [[Presence]], [[SpatialComputing]]",
    "- requires": "[[DisplayTechnology]], [[TrackingSystem]], [[RenderingEngine]]",
    "- bridges-to": "[[HumanComputerInteraction]], [[ComputerVision]], [[Robotics]]",
    "public": "true"
  },
  "backlinks": [
    "Proprietary Image Generation",
    "Landscape",
    "BC-0037-public-key"
  ],
  "wiki_links": [
    "Landscape",
    "ComputerVision",
    "Presence",
    "MetaverseDomain",
    "TrackingSystem",
    "DisplayTechnology",
    "RenderingEngine",
    "ImmersiveExperience",
    "Robotics",
    "HumanComputerInteraction",
    "SpatialComputing"
  ],
  "ontology": {
    "term_id": "mv-926071209914",
    "preferred_term": "Landscape",
    "definition": "A component of the metaverse ecosystem focusing on landscape.",
    "source_domain": "metaverse",
    "maturity_level": null,
    "authority_score": 0.85
  }
}