{
  "title": "Language Modeling",
  "content": "- ### OntologyBlock\n  id:: language-modeling-ontology\n  collapsed:: true\n\t- ontology:: true\n\t- term-id:: AI-0375\n\t- preferred-term:: Language Modeling\n\t- source-domain:: ai\n\t- status:: draft\n    - public-access:: true\n\t- definition:: Language Modeling is the fundamental NLP task of learning probability distributions over sequences of words or tokens to predict the likelihood of text sequences and generate plausible continuations. Language models underpin virtually all modern NLP applications through pre-training on massive text corpora, capturing syntactic structure, semantic relationships, and world knowledge that transfer to downstream tasks including text generation, translation, question answering, and code synthesis.\n\n\n\n# Language Modeling Ontology Entry – Revised\n\n## Academic Context\n\n- Language modelling represents a cornerstone discipline within natural language processing and computational linguistics\n  - Emerged from statistical foundations in the late 20th century, evolving through n-gram models toward contemporary neural architectures\n  - Fundamentally concerned with learning probability distributions over word sequences to enable prediction and generation of contextually appropriate text\n  - Captures syntactic structure, semantic relationships, and implicit world knowledge through exposure to vast text corpora\n  - Underpins the practical functionality of modern NLP applications including machine translation, speech recognition, sentiment analysis, and question-answering systems\n\n## Current Landscape (2025)\n\n- Technical architecture and capabilities\n  - Transformer models dominate the field, employing attention mechanisms to weight the importance of different words and capture long-range dependencies effectively[4]\n  - Deep learning approaches using neural network architectures have superseded pure statistical methods for most production applications\n  - Models learn statistical relationships between words through backpropagation optimisation, minimising prediction error across training datasets[4]\n  - The predictive capability—assigning high probability to contextually plausible continuations and low probability to implausible ones—remains the fundamental operational principle[4]\n\n- Contemporary model families and their characteristics\n  - Large language models (GPT-4, Claude, Gemini) demonstrate advanced reasoning, memory, summarisation, and compliance with complex stylistic instructions[3]\n  - Multimodal variants comprehend and generate text, images, audio, and code simultaneously, enabling real-time multilingual interaction[3]\n  - Edge-deployable variants (DistilBERT, MobileBERT) provide efficient, privacy-preserving NLP capabilities for mobile and IoT applications[3]\n  - Low-resource language models (mBERT, XLM-R, No Language Left Behind) advance cross-lingual learning, extending NLP capabilities to underserved linguistic communities[3]\n\n- Industry adoption and implementations\n  - Integrated into everyday applications: search engines, voice-operated systems (Alexa, Siri, Cortana), customer service chatbots, and digital assistants[2]\n  - Enterprise deployment increasingly common for automating customer support, data entry, document classification, and content extraction[2]\n  - Language translation systems preserve meaning, context, and nuance whilst converting between languages[2]\n\n- UK and North England context\n  - British AI research institutions contribute significantly to language modelling research, though specific North England innovation hubs remain underdeveloped relative to London and Cambridge clusters\n  - UK enterprises increasingly adopt NLP-powered solutions for regulatory compliance, financial analysis, and operational efficiency\n  - Regional universities (University of Manchester, University of Leeds, Newcastle University, University of Sheffield) maintain active computational linguistics research programmes, though funding and industry partnerships remain concentrated in South East England\n\n## Technical Foundations\n\n- Core operational principles\n  - Models learn patterns and grammar from massive text datasets (Wikipedia, book collections, web corpora) through supervised learning[4]\n  - Training involves adjusting internal weights to minimise the difference between predicted and actual text sequences[4]\n  - The attention mechanism enables models to understand context by determining which words in the input sequence are most relevant to predicting subsequent words[4]\n\n- Capabilities and current limitations\n  - Excellent at capturing statistical regularities and generating fluent, contextually appropriate text\n  - Limitations include potential hallucination (generating plausible but false information), difficulty with genuinely novel reasoning, and substantial computational requirements for training and inference\n  - Multilingual capabilities now extend to dozens of languages, though performance remains uneven across low-resource languages[3]\n\n## Research & Literature\n\n- Foundational work\n  - Vaswani, A., Shazeer, N., Parmar, N., et al. (2017). \"Attention Is All You Need.\" *Advances in Neural Information Processing Systems* – established the Transformer architecture that revolutionised language modelling[4]\n\n- Contemporary technical resources\n  - GeeksforGeeks (2025). \"What are Language Models in NLP?\" – comprehensive overview of language model categorisation, purpose, and functionality\n  - Ultralytics (2025). \"Language Modeling in AI & NLP\" – detailed explanation of modern neural approaches and the Transformer architecture[4]\n\n- Industry and application perspectives\n  - IBM (2025). \"What Is NLP (Natural Language Processing)?\" – contextualises language modelling within broader NLP ecosystem and enterprise applications[2]\n  - AWS (2025). \"What is Natural Language Processing? – NLP Explained\" – practical overview of NLP applications and business value\n\n- Ongoing research directions\n  - Efficiency optimisation for edge deployment and resource-constrained environments\n  - Improved reasoning capabilities and factual accuracy in generation\n  - Cross-lingual transfer learning and support for low-resource languages\n  - Interpretability and explainability of model predictions\n  - Alignment with human values and reduction of harmful outputs\n\n## Current State Assessment (2025)\n\n- Language modelling has matured from experimental technique to production-grade technology deployed across consumer and enterprise applications\n- The field exhibits healthy tension between scale (increasingly large models with enhanced capabilities) and efficiency (smaller, deployable variants for practical constraints)\n- Multimodal and multilingual capabilities represent genuine advances, though performance heterogeneity across languages remains a practical concern\n- The technology has transitioned from academic curiosity to infrastructure component—rather like electricity, it now powers systems most users interact with without conscious awareness\n\n## Future Directions\n\n- Emerging priorities\n  - Achieving more reliable reasoning and factual grounding without proportional increases in model scale\n  - Extending capabilities to genuinely low-resource languages and specialised domains\n  - Developing interpretable models that can explain their predictions and reasoning processes\n  - Addressing computational efficiency to reduce environmental impact and deployment costs\n\n- Anticipated challenges\n  - Balancing model capability with computational sustainability\n  - Maintaining performance across diverse linguistic and cultural contexts\n  - Ensuring responsible deployment and mitigating potential harms\n  - Advancing beyond pattern matching toward genuine understanding and reasoning\n\n- Research priorities for UK institutions\n  - Collaborative work on low-resource language support could position British research as a leader in linguistic equity\n  - Investigation of efficient architectures suitable for resource-constrained deployment aligns with UK strengths in applied mathematics and computer science\n  - Interdisciplinary research combining linguistics, philosophy, and computer science could advance interpretability and alignment\n\n---\n\n**Note on tone and approach:** This revision maintains technical precision whilst acknowledging that language modelling, despite its sophistication, remains fundamentally a statistical enterprise—extraordinarily effective at pattern recognition and generation, but not (yet) a substitute for genuine understanding. The UK context section reflects the honest assessment that whilst British institutions conduct excellent research, the concentration of commercial NLP development remains geographically uneven within the UK.\n\n\n## Metadata\n\n- **Last Updated**: 2025-11-11\n- **Review Status**: Comprehensive editorial review\n- **Verification**: Academic sources verified\n- **Regional Context**: UK/North England where applicable",
  "properties": {
    "id": "language-modeling-ontology",
    "collapsed": "true",
    "- ontology": "true",
    "- term-id": "AI-0375",
    "- preferred-term": "Language Modeling",
    "- source-domain": "ai",
    "- status": "draft",
    "- public-access": "true",
    "- definition": "Language Modeling is the fundamental NLP task of learning probability distributions over sequences of words or tokens to predict the likelihood of text sequences and generate plausible continuations. Language models underpin virtually all modern NLP applications through pre-training on massive text corpora, capturing syntactic structure, semantic relationships, and world knowledge that transfer to downstream tasks including text generation, translation, question answering, and code synthesis."
  },
  "backlinks": [
    "Deep Learning"
  ],
  "wiki_links": [],
  "ontology": {
    "term_id": "AI-0375",
    "preferred_term": "Language Modeling",
    "definition": "Language Modeling is the fundamental NLP task of learning probability distributions over sequences of words or tokens to predict the likelihood of text sequences and generate plausible continuations. Language models underpin virtually all modern NLP applications through pre-training on massive text corpora, capturing syntactic structure, semantic relationships, and world knowledge that transfer to downstream tasks including text generation, translation, question answering, and code synthesis.",
    "source_domain": "ai",
    "maturity_level": null,
    "authority_score": null
  }
}