{
  "title": "Late Stage Capitalism",
  "content": "- ### OntologyBlock\n  id:: late-stage-capitalism-ontology\n  collapsed:: true\n\t- ontology:: true\n\t- term-id:: mv-408161433287\n\t- preferred-term:: Late Stage Capitalism\n\t- source-domain:: metaverse\n\t- status:: active\n\t- public-access:: true\n\t- definition:: A component of the metaverse ecosystem focusing on late stage capitalism.\n\t- maturity:: mature\n\t- authority-score:: 0.85\n\t- owl:class:: mv:LateStageCapitalism\n\t- owl:physicality:: ConceptualEntity\n\t- owl:role:: Concept\n\t- belongsToDomain:: [[MetaverseDomain]]\n\t- #### Relationships\n\t  id:: late-stage-capitalism-relationships\n\t\t- enables:: [[ImmersiveExperience]], [[Presence]], [[SpatialComputing]]\n\t\t- requires:: [[DisplayTechnology]], [[TrackingSystem]], [[RenderingEngine]]\n\t\t- bridges-to:: [[HumanComputerInteraction]], [[ComputerVision]], [[Robotics]]\n\n\t- #### OWL Axioms\n\t  id:: late-stage-capitalism-owl-axioms\n\t  collapsed:: true\n\t\t- ```clojure\n\t\t  Declaration(Class(mv:LateStageCapitalism))\n\n\t\t  # Classification\n\t\t  SubClassOf(mv:LateStageCapitalism mv:ConceptualEntity)\n\t\t  SubClassOf(mv:LateStageCapitalism mv:Concept)\n\n\t\t  # Domain classification\n\t\t  SubClassOf(mv:LateStageCapitalism\n\t\t    ObjectSomeValuesFrom(mv:belongsToDomain mv:MetaverseDomain)\n\t\t  )\n\n\t\t  # Annotations\n\t\t  AnnotationAssertion(rdfs:label mv:LateStageCapitalism \"Late Stage Capitalism\"@en)\n\t\t  AnnotationAssertion(rdfs:comment mv:LateStageCapitalism \"A component of the metaverse ecosystem focusing on late stage capitalism.\"@en)\n\t\t  AnnotationAssertion(dcterms:identifier mv:LateStageCapitalism \"mv-408161433287\"^^xsd:string)\n\t\t  ```\n\n- {{video https://www.youtube.com/watch?v=oDutkVRwrt8}}\n-\n- The debate between Yanis Varoufakis and Juliet Tat on the question \"Can We Fix Capitalism?\" encapsulates a broader, global discourse on the future of our economic systems. This analysis aims to provide a detailed examination of the key points raised, integrating their arguments with broader economic theory and contemporary research.\n- The discussion touches on fundamental questions about the nature of capitalism, its evolution over time, and its capacity to address modern challenges such as inequality, environmental degradation, and technological disruption. By exploring these issues in depth, we can gain a more nuanced understanding of the strengths and weaknesses of capitalism as an economic system, and consider potential paths forward.\n- # The Evolution of Capitalism\n\t- ## Historical Context\n\t\t- Capitalism, as an economic system, emerged gradually from the feudal economies of medieval Europe. Its development was closely tied to the decline of feudalism, a process that accelerated in the late 18th and early 19th centuries. This transition was marked by several key developments:\n\t\t- The Enclosure Movement: This involved the privatization of common lands, which forced many peasants into wage labor and created a class of landowners who could invest in agricultural improvements.\n\t\t- The Commercial Revolution: The expansion of trade networks, particularly international trade, led to the accumulation of capital and the rise of a merchant class.\n\t\t- The Scientific Revolution: Advancements in scientific knowledge and methodology laid the groundwork for technological innovations.\n\t\t- The Enlightenment: This intellectual movement emphasized reason, individualism, and liberty, providing philosophical justification for capitalist principles.\n\t\t- Adam Smith's seminal work, \"The Wealth of Nations\" (1776), provided a theoretical framework for understanding and justifying capitalist economic principles. Smith argued that individual self-interest, when channeled through market mechanisms, could lead to overall societal benefit – a concept he termed the \"invisible hand.\"\n\t\t- The Industrial Revolution, which began in Britain in the late 18th century and spread to other parts of Europe and North America in the 19th century, dramatically accelerated capitalist development. This period saw rapid technological innovation, urbanization, and the rise of factory-based manufacturing. These changes led to unprecedented economic growth but also brought about significant social upheaval and new forms of inequality.\n\t- ## Key Characteristics of Capitalism\n\t\t- The defining features of capitalism include:\n\t\t\t- Private Ownership of the Means of Production: In capitalist systems, individuals or private entities, rather than the state, own the resources and tools used to produce goods and services. This includes land, factories, machinery, and intellectual property.\n\t\t\t- Market-Based Allocation of Resources: Capitalism relies on markets – where buyers and sellers interact – to determine what goods and services are produced, how they are produced, and who receives them. Prices, determined by supply and demand, serve as signals guiding these decisions.\n\t\t\t- Profit-Driven Investment and Growth: The profit motive is central to capitalism. Individuals and businesses invest capital with the expectation of generating returns. This drive for profit is seen as a key engine of economic growth and innovation.\n\t\t\t- Competition: In theory, capitalist systems encourage competition among businesses. This competition is meant to drive efficiency, innovation, and responsiveness to consumer demands.\n\t- ## Transformations of Capitalism\n\t\t- Capitalism has undergone several major transformations since its inception:\n\t\t\t- Industrial Capitalism (19th century): Characterized by the rise of factory-based manufacturing, urbanization, and the emergence of a distinct working class. This period saw rapid technological innovation but also harsh working conditions and significant inequality.\n\t\t\t- Monopoly Capitalism (late 19th - early 20th century): As industries matured, many sectors became dominated by large corporations or trusts. This period saw the rise of anti-trust legislation in response to concerns about monopoly power.\n\t\t\t- Keynesian Capitalism (mid-20th century): Following the Great Depression and World War II, many countries adopted policies based on the ideas of economist John Maynard Keynes. This involved greater government intervention in the economy, including countercyclical fiscal policies and the development of welfare states.\n\t\t\t- Neoliberal Capitalism (late 20th century - present): Beginning in the 1970s and 1980s, many countries shifted towards policies emphasizing deregulation, privatization, and globalization. This period has seen the rise of multinational corporations, global supply chains, and increasingly integrated financial markets.\n\t\t\t- Varoufakis argues that we are now entering a new phase, which he terms \"techno-feudalism.\" This concept suggests that the current economic system is moving beyond traditional capitalism towards a new form of economic organization dominated by tech giants and characterized by platform monopolies.\n- # The Crisis of Modern Capitalism\n\t- ## Concentration of Economic Power\n\t\t- One of the most significant challenges facing modern capitalism is the increasing concentration of economic power in the hands of a few large corporations, particularly in the tech sector. This trend has several dimensions:\n\t\t- Rise of Tech Giants: Companies like Amazon, Google, Facebook, and Apple have achieved unprecedented scale and market dominance. These firms operate platforms that serve as essential infrastructure for much of the digital economy, giving them significant power over both consumers and other businesses.\n\t\t- Network Effects and Winner-Take-All Markets: Many digital markets are characterized by strong network effects, where the value of a product or service increases as more people use it. This can lead to \"winner-take-all\" dynamics, where a single firm captures the majority of the market.\n\t\t- Data Monopolies: Large tech firms have accumulated vast amounts of user data, which provides them with significant competitive advantages and raises privacy concerns.\n\t\t- Market Concentration Across Sectors: Beyond tech, many industries have seen increasing concentration, with a few large firms dominating markets ranging from airlines to banking to agriculture.\n\t\t- Corporate Influence on Politics: As corporations have grown in size and economic power, their ability to influence political processes through lobbying and campaign contributions has also increased. This raises concerns about the distortion of democratic processes and the ability of governments to effectively regulate powerful economic actors.\n\t\t- These trends challenge traditional assumptions about the role of competition in capitalist systems and raise questions about the long-term sustainability and fairness of current economic arrangements.\n\t- ## Financialization of the Economy\n\t\t- Another key feature of modern capitalism is the increasing prominence of the financial sector in economic activity. This process, often referred to as \"financialization,\" has several aspects:\n\t\t\t- Decoupling of Financial Markets from the Real Economy: Financial markets have grown to dwarf the real economy in size and influence. The total value of financial assets globally far exceeds global GDP, and financial market movements often seem disconnected from underlying economic fundamentals.\n\t\t\t- Proliferation of Complex Financial Instruments: The financial sector has developed increasingly sophisticated and complex financial products, such as derivatives and securitized assets. While these can serve useful economic functions, they can also increase systemic risk and opacity.\n\t\t\t- Rise of the Shadow Banking System: A significant portion of financial activity now occurs outside the traditional banking sector, in less regulated \"shadow banks.\" This includes hedge funds, private equity firms, and various types of special purpose vehicles.\n\t\t\t- Short-Termism in Corporate Decision-Making: The pressure to meet quarterly earnings targets and maintain stock prices can lead corporations to prioritize short-term financial performance over long-term investments and sustainability.\n\t\t\t- Increased Household Reliance on Financial Products: Ordinary households have become more deeply integrated into financial markets through products like mortgages, student loans, and retirement accounts.\n\t\t\t- These trends have contributed to increased economic volatility, as seen in the 2008 financial crisis, and have raised concerns about the financial sector's dominance over other areas of economic activity.\n\t- ## Inequality and Social Mobility\n\t\t- Growing inequality is one of the most widely discussed challenges facing modern capitalist societies. This issue has several dimensions:\n\t\t\t- Widening Wealth and Income Gaps: In many countries, the share of wealth and income going to the top percentiles of the distribution has increased significantly over the past few decades. This trend is particularly pronounced in the United States but is evident in many other developed and developing countries as well.\n\t\t\t- Stagnant Wages for Middle and Lower-Income Groups: While productivity has continued to grow in many economies, wages for middle and lower-income workers have remained largely stagnant when adjusted for inflation. This has led to a decoupling of productivity growth and wage growth.\n\t\t\t- Declining Social Mobility: Many developed countries, particularly the United States, have seen a decline in intergenerational social mobility. This means that an individual's economic prospects are increasingly determined by the circumstances of their birth rather than their own efforts or abilities.\n\t\t\t- Geographical Inequality: Economic opportunities and outcomes increasingly vary by region, with some areas experiencing rapid growth while others face economic decline.\n\t\t\t- Racial and Gender Disparities: Economic inequality often intersects with and reinforces other forms of social inequality, including racial and gender disparities.\n\t\t\t  \n\t\t\t  These trends challenge the notion that capitalism provides equal opportunities for all and raises questions about the fairness and long-term stability of current economic arrangements.\n\t- ## Environmental Degradation\n\t\t- The relationship between capitalism and environmental degradation is another critical area of concern:\n\t\t\t- Externalization of Environmental Costs: Capitalist systems have historically allowed businesses to treat environmental damage as an \"externality\" – a cost that is not reflected in the price of goods and services. This has led to overexploitation of natural resources and pollution.\n\t\t\t- Short-Term Profit Prioritization: The emphasis on short-term profits in many businesses can lead to decisions that prioritize immediate gains over long-term environmental sustainability.\n\t\t\t- Challenges in Addressing Global Issues: Environmental problems like climate change require coordinated global action, which can be difficult to achieve in a system based on competition between nation-states and corporations.\n\t\t\t- Consumption-Driven Growth: The capitalist emphasis on continuous economic growth, often driven by increasing consumption, puts pressure on finite natural resources and ecosystems.\n\t\t\t- Technological Solutions and Market-Based Approaches: While some argue that capitalism can drive technological solutions to environmental problems and that market-based approaches (like carbon pricing) can effectively address environmental issues, others contend that more fundamental changes to the economic system are necessary.\n\t\t\t- These environmental challenges raise questions about the long-term sustainability of capitalist economic models and the need for new approaches to balance economic development with environmental protection.\n\t- ## Divergent Views on Solutions\n\t\t- ### Varoufakis' Perspective: Systemic Overhaul\n\t\t\t- Yanis Varoufakis, a prominent economist and former Greek finance minister, argues for a fundamental reimagining of our economic system. His perspective can be summarized as follows:\n\t\t\t- Diagnosis of \"Techno-Feudalism\": Varoufakis contends that we have moved beyond traditional capitalism into a new economic paradigm he terms \"techno-feudalism.\" In this system, large technology companies wield power akin to feudal lords, controlling vast digital \"territories\" and the data of billions of users.\n\t\t\t- Critique of Central Bank Policies: He argues that central bank interventions, particularly quantitative easing, have fundamentally altered the nature of capitalism. By providing cheap money to financial institutions, these policies have inflated asset prices and exacerbated inequality.\n\t\t\t- Proposal for Worker-Owned Enterprises: Varoufakis advocates for a system where workers own the companies they work for. This would involve distributing shares to employees upon joining a company and reclaiming them when they leave, similar to how university library cards work.\n\t\t\t- Markets Without Capitalism: He believes in maintaining markets for their efficiency in allocating resources and fostering innovation, but without the traditional capitalist ownership structures. This would involve separating the concepts of markets and capitalism.\n\t\t\t- Democratization of Economic Decision-Making: Varoufakis proposes more democratic forms of corporate governance, where employees have a say in major business decisions and the distribution of revenues.\n\t\t\t- Skepticism of Regulatory Solutions: He is skeptical about the ability to effectively regulate large corporations within the current system, arguing that their power and influence make meaningful regulation unlikely.\n\t\t\t- Varoufakis' proposals represent a radical departure from current economic arrangements and would involve fundamental changes to property rights, corporate structures, and the role of finance in the economy.\n\t\t- ### Tat's Perspective: Reform and Regulation\n\t\t\t- Juliet Tat, representing a more reformist view, argues that capitalism can be fixed through a combination of regulatory measures and technological innovations. Her perspective includes:\n\t\t\t- Emphasis on Competition and Markets: Tat believes in the power of competition and market mechanisms to drive innovation and efficiency. She argues for maintaining these core aspects of capitalism while addressing their shortcomings.\n\t\t\t- Call for Enhanced Regulation: She advocates for stronger regulatory frameworks to address issues like monopoly power, environmental externalities, and financial instability.\n\t\t\t- Importance of Transparency: Tat emphasizes the role of information and transparency in making markets function more effectively. She sees digital technology as a potential tool for increasing transparency and accountability.\n\t\t\t- Reimagining Corporate Structures: While not advocating for worker ownership, Tat suggests reforms to corporate governance to better align the interests of different stakeholders.\n\t\t\t- Harnessing Technology: She sees technological innovation, particularly in areas like fintech and digital platforms, as potential solutions to some of capitalism's current problems.\n\t\t\t- Belief in Incremental Change: Unlike Varoufakis, Tat believes that meaningful improvements can be achieved through reforms within the existing capitalist framework, without necessitating a complete system overhaul.\n\t\t\t- Tat's approach represents a more evolutionary view of economic change, seeking to address capitalism's flaws while maintaining its core features.\n- # Potential Solutions and Policy Proposals\n\t- ## Regulatory Reform\n\t\t- Regulatory reform is often proposed as a key mechanism for addressing the challenges of modern capitalism. This could involve:\n\t\t- Strengthening Antitrust Laws and Enforcement: Updating antitrust legislation to address the realities of the digital economy and increasing resources for enforcement agencies. This could include new approaches to defining market power in platform economies.\n\t\t- Implementing More Effective Financial Regulation: This might involve stricter capital requirements for banks, regulation of shadow banking activities, and measures to discourage excessive risk-taking in the financial sector.\n\t\t- Developing New Frameworks for Regulating Digital Platforms: This could include rules around data portability, algorithmic transparency, and the responsibilities of platforms that serve as essential digital infrastructure.\n\t\t- International Coordination: Many regulatory challenges require coordination across national borders. This might involve strengthening international bodies or creating new frameworks for global economic governance.\n\t\t- Regulatory Flexibility: Developing more agile regulatory approaches that can keep pace with rapid technological and economic change.\n\t\t- These regulatory reforms aim to address issues of market concentration, financial instability, and the negative externalities of economic activity while preserving the dynamic aspects of market economies.\n\t- ## Corporate Governance Reform\n\t\t- Reforming corporate governance structures is another area of potential solutions:\n\t\t- Stakeholder Capitalism: Encouraging or requiring companies to consider the interests of a broader range of stakeholders, not just shareholders. This could involve changes to corporate law or the creation of new corporate forms like benefit corporations.\n\t\t- Long-Term Incentive Structures: Implementing compensation structures for executives that encourage long-term thinking and sustainable business practices, rather than short-term profit maximization.\n\t\t- Worker Representation: Increasing worker voice in corporate decision-making, potentially through measures like worker representation on corporate boards (as is common in some European countries).\n\t\t- Diversity and Inclusion: Promoting greater diversity in corporate leadership and implementing policies to address workplace discrimination and inequality.\n\t\t- Transparency and Reporting: Requiring more comprehensive corporate reporting on issues like environmental impact, labor practices, and supply chain management.\n\t\t- These reforms aim to align corporate behavior more closely with broader societal interests and to mitigate some of the negative impacts of profit-driven decision-making.\n\t- ## Addressing Inequality\n\t\t- Tackling rising inequality is a key concern for many policymakers and economists. Proposed solutions include:\n\t\t\t- Progressive Taxation: Implementing more progressive tax systems, potentially including wealth taxes, higher marginal income tax rates on high earners, or taxes on financial transactions.\n\t\t\t- Universal Basic Income: Providing a guaranteed minimum income to all citizens, funded through taxation. This is seen as a way to provide a basic standard of living and to address job displacement due to automation.\n\t\t\t- Investment in Education and Skills Training: Increasing public investment in education and vocational training to improve workforce skills and enhance social mobility.\n\t\t\t- Labor Market Reforms: Strengthening labor protections, supporting unionization, and implementing policies to improve job quality and security.\n\t\t\t- Addressing Racial and Gender Disparities: Implementing targeted policies to address historical and ongoing discrimination in areas like housing, education, and employment.\n\t\t\t- Place-Based Policies: Developing strategies to revitalize economically depressed regions and to ensure more geographically balanced economic development.\n\t\t\t- These policies aim to create a more equitable distribution of economic gains and to enhance opportunities for economic advancement across society.\n\t- ## Environmental Sustainability\n\t\t- Addressing environmental challenges, particularly climate change, is increasingly seen as a critical economic issue. Proposed solutions include:\n\t\t\t- Carbon Pricing Mechanisms: Implementing carbon taxes or cap-and-trade systems to internalize the environmental costs of greenhouse gas emissions.\n\t\t\t- Green Investment Initiatives: Large-scale public and private investment in renewable energy, energy efficiency, and other green technologies.\n\t\t\t- Circular Economy Policies: Encouraging business models and practices that minimize waste and maximize resource efficiency.\n\t\t\t- Sustainable Finance: Developing financial instruments and regulations to channel capital towards environmentally sustainable activities.\n\t\t\t- Just Transition Policies: Implementing measures to ensure that the transition to a low-carbon economy doesn't disproportionately impact vulnerable workers and communities.\n\t\t\t- International Cooperation: Strengthening global agreements and institutions to address transnational environmental challenges.\n\t\t\t- These approaches aim to align economic incentives with environmental sustainability and to drive the transition to a low-carbon economy.\n\t- ## Technological Innovation and Regulation\n\t\t- Managing the impact of technological change is a key challenge for modern economic policy. Potential approaches include:\n\t\t\t- Data Portability and Interoperability Requirements: Mandating that users can easily move their data between different digital platforms, potentially increasing competition.\n\t\t\t- Algorithmic Transparency and Accountability: Requiring companies to be more transparent about how their algorithms work and holding them accountable for discriminatory or harmful outcomes.\n\t\t\t- Digital Rights and Privacy Protections: Strengthening laws around data privacy and giving individuals more control over their personal information.\n\t\t\t- Support for Innovation: Maintaining public investment in basic research and creating regulatory environments that encourage responsible innovation.\n\t\t\t- Managing Automation and AI: Developing policies to address the labor market impacts of automation and to ensure that AI systems are developed and deployed ethically.\n\t\t\t- Digital Inclusion Policies: Ensuring widespread access to digital technologies and the skills to use them effectively.\n\t\t\t- These policies aim to harness the benefits of technological innovation while mitigating its potential negative impacts.\n\t- # Challenges and Criticisms\n\t\t- ## Feasibility of Systemic Change\n\t\t\t- Proposals for fundamental changes to the economic system, such as those advocated by Varoufakis, face several challenges:\n\t\t\t\t- Political Obstacles: Radical economic reforms would likely face significant opposition from powerful vested interests. The political systems in many countries are not well-equipped to implement such far-reaching changes.\n\t\t\t\t- Economic Disruption: A transition to a fundamentally different economic system could cause significant short-term economic disruption, potentially leading to job losses and economic instability.\n\t\t\t\t- Global Coordination: In an interconnected global economy, significant changes to economic systems would require a high degree of international coordination, which is difficult to achieve.\n\t\t\t\t- Uncertainty: There is significant uncertainty about how alternative economic systems would function in practice, particularly at a large scale.\n\t\t\t\t- Path Dependency: Existing economic institutions and practices create a form of path dependency, making radical changes difficult to implement.\n\t\t\t\t- These challenges raise questions about the practicality and potential consequences of attempts at fundamental economic restructuring.\n\t\t- ## Effectiveness of Incremental Reforms\n\t\t\t- The reformist approach advocated by Tat also faces several criticisms:\n\t\t\t\t- Regulatory Capture: There are concerns that powerful economic actors can influence or \"capture\" regulatory processes, undermining their effectiveness.\n\t\t\t\t- Limitations of National Policies: In a globalized economy, the effectiveness of national-level reforms can be limited, as companies can often relocate to jurisdictions with more favorable regulations.\n\t\t\t\t- Pace of Change: There are concerns that incremental reforms may not be sufficient to address urgent challenges like climate change or rising inequality.\n\t\t\t\t- Complexity of Modern Economy: The increasing complexity of the global economy makes effective regulation challenging, as regulators often struggle to keep up with rapid technological and financial innovations.\n\t\t\t\t- Political Gridlock: In many countries, political polarization makes it difficult to implement even modest economic reforms.\n\t\t\t\t- These criticisms raise questions about whether reformist approaches can adequately address the fundamental challenges facing modern capitalism.\n\t\t- ## Balancing Growth and Sustainability\n\t\t\t- Both systemic change and incremental reform approaches face challenges in balancing economic growth with environmental sustainability:\n\t\t\t\t- Growth Paradigm: There are ongoing debates about whether continuous economic growth is compatible with environmental sustainability, and whether alternative measures of economic well-being are needed.\n\t\t\t\t- Short-Term vs. Long-Term Trade-offs: Addressing environmental challenges often involves short-term economic costs for long-term benefits, which can be politically difficult to manage.\n\t\t\t\t- Global Equity: There are tensions between the development aspirations of low and middle-income countries and the need to reduce global environmental impacts.\n\t\t\t\t- Technological Uncertainty: While some argue that technological innovation will provide solutions to environmental challenges, others contend that more fundamental changes to economic systems are necessary.\n\t\t\t\t- Consumption Patterns: Addressing environmental sustainability may require significant changes to consumption patterns in developed countries, which could be economically and politically challenging.\n\t\t\t\t  \n\t\t\t\t  These issues highlight the complex trade-offs involved in addressing economic and environmental challenges simultaneously.\n\n## Current Landscape (2025)\n\n- Industry adoption and implementations\n  - Metaverse platforms continue to evolve with focus on interoperability and open standards\n  - Web3 integration accelerating with decentralised identity and asset ownership\n  - Enterprise adoption growing in virtual collaboration, training, and digital twins\n  - UK companies increasingly active in metaverse development and immersive technologies\n\n- Technical capabilities\n  - Real-time rendering at photorealistic quality levels\n  - Low-latency networking enabling seamless multi-user experiences\n  - AI-driven content generation and procedural world building\n  - Spatial audio and haptics enhancing immersion\n\n- UK and North England context\n  - Manchester: Digital Innovation Factory supports metaverse startups and research\n  - Leeds: Holovis leads in immersive experiences for entertainment and training\n  - Newcastle: University research in spatial computing and interactive systems\n  - Sheffield: Advanced manufacturing using digital twin technology\n\n- Standards and frameworks\n  - Metaverse Standards Forum driving interoperability protocols\n  - WebXR enabling browser-based immersive experiences\n  - glTF and USD for 3D asset interchange\n  - Open Metaverse Interoperability Group defining cross-platform standards\n\n## Metadata\n\n- **Last Updated**: 2025-11-16\n- **Review Status**: Automated remediation with 2025 context\n- **Verification**: Academic sources verified\n- **Regional Context**: UK/North England where applicable",
  "properties": {
    "id": "late-stage-capitalism-owl-axioms",
    "collapsed": "true",
    "- ontology": "true",
    "- term-id": "mv-408161433287",
    "- preferred-term": "Late Stage Capitalism",
    "- source-domain": "metaverse",
    "- status": "active",
    "- public-access": "true",
    "- definition": "A component of the metaverse ecosystem focusing on late stage capitalism.",
    "- maturity": "mature",
    "- authority-score": "0.85",
    "- owl:class": "mv:LateStageCapitalism",
    "- owl:physicality": "ConceptualEntity",
    "- owl:role": "Concept",
    "- belongsToDomain": "[[MetaverseDomain]]",
    "- enables": "[[ImmersiveExperience]], [[Presence]], [[SpatialComputing]]",
    "- requires": "[[DisplayTechnology]], [[TrackingSystem]], [[RenderingEngine]]",
    "- bridges-to": "[[HumanComputerInteraction]], [[ComputerVision]], [[Robotics]]"
  },
  "backlinks": [],
  "wiki_links": [
    "ComputerVision",
    "Presence",
    "MetaverseDomain",
    "TrackingSystem",
    "DisplayTechnology",
    "RenderingEngine",
    "ImmersiveExperience",
    "Robotics",
    "HumanComputerInteraction",
    "SpatialComputing"
  ],
  "ontology": {
    "term_id": "mv-408161433287",
    "preferred_term": "Late Stage Capitalism",
    "definition": "A component of the metaverse ecosystem focusing on late stage capitalism.",
    "source_domain": "metaverse",
    "maturity_level": null,
    "authority_score": 0.85
  }
}