{
  "title": "Latency",
  "content": "- ### OntologyBlock\n  id:: latency-ontology\n  collapsed:: true\n\t- ontology:: true\n\t- term-id:: 20148\n\t- source-domain:: metaverse\n\t- status:: draft\n\t- public-access:: true\n\n\n\n## Academic Context\n\n- Brief contextual overview\n\t- Latency, often termed motion-to-photon latency, is a core performance metric in immersive technologies, quantifying the delay between a user’s action and the system’s visual or sensory response\n\t- In virtual, augmented, and mixed reality, latency is a critical determinant of user comfort, immersion, and interaction fidelity\n\t- Early VR systems struggled with high latency, resulting in cybersickness and poor user experiences, but advances in hardware and software have dramatically reduced these delays\n\n- Key developments and current state\n\t- Modern headsets now routinely achieve sub-20ms motion-to-photon latency, a threshold widely accepted as imperceptible to most users and essential for deep immersion\n\t- The integration of predictive algorithms, asynchronous timewarp, and eye tracking has further refined latency management, particularly in high-fidelity and multiplayer environments\n\n- Academic foundations\n\t- The concept of motion-to-photon latency is well established in human-computer interaction and perceptual psychology literature\n\t- Research consistently demonstrates that latency below 20ms is necessary for comfortable, immersive experiences, with some studies suggesting even lower thresholds for augmented reality applications\n\n## Current Landscape (2025)\n\n- Industry adoption and implementations\n\t- Leading VR/AR platforms such as Varjo, HTC Vive, Meta Quest, and Apple Vision Pro prioritise low latency as a core design principle\n\t- Cloud-based VR/AR services, including those leveraging Tencent Cloud’s Global Accelerator and Edge Computing, optimise network paths to minimise round-trip times and ensure responsive experiences\n\n- Notable organisations and platforms\n\t- Varjo: Focuses on ultra-low latency for mixed reality, particularly in professional and enterprise settings\n\t- PiXel: UK-based VR solutions provider, active in immersive training and simulation\n\t- Immerse: Manchester-based company specialising in VR training platforms for industry and education\n\n- UK and North England examples where relevant\n\t- The University of Manchester’s Immersive Technologies Lab conducts research on latency optimisation for industrial VR applications\n\t- Leeds-based Digital Catapult supports AR/VR startups, fostering innovation in low-latency immersive experiences\n\t- Newcastle’s Centre for Immersive Technologies collaborates with industry on real-time rendering and latency reduction\n\n- Technical capabilities and limitations\n\t- Modern headsets achieve motion-to-photon latency of 10–20ms, with some experimental systems approaching 5ms\n\t- Mixed reality remains more challenging due to the need for real-time video pass-through and seamless blending of digital and physical environments\n\t- Wireless connectivity and network infrastructure can introduce additional latency, particularly in cloud-based or multiplayer scenarios\n\n- Standards and frameworks\n\t- Industry standards such as OpenXR and WebXR include guidelines for latency management\n\t- The IEEE VR/AR Standards Committee continues to develop best practices for latency measurement and reporting\n\n## Research & Literature\n\n- Key academic papers and sources\n\t- Carmack, J. (2013). Latency in virtual reality: A practical guide. *Proceedings of the ACM SIGGRAPH Symposium on Interactive 3D Graphics and Games*. https://doi.org/10.1145/2461966.2461972\n\t- Attig, C., Franke, T., & Wessel, D. (2017). Latency and usability in virtual reality: A review. *Human-Computer Interaction*, 32(5-6), 321–352. https://doi.org/10.1080/07370024.2017.1326406\n\t- Davis, S., Nesbitt, K., & Nalivaiko, E. (2015). A systematic review of cybersickness. *Virtual Reality*, 19(2), 103–130. https://doi.org/10.1007/s10055-014-0257-0\n\t- Ellis, S. R., Adelstein, B. D., & Hill, M. W. (1999). Perceptual thresholds for motion-to-photon latency. *Presence: Teleoperators and Virtual Environments*, 8(2), 157–170. https://doi.org/10.1162/105474699566164\n\t- Feldstein, M., & Ellis, S. R. (2020). Perceivable latency and cybersickness: A review. *Frontiers in Virtual Reality*, 1, 582204. https://doi.org/10.3389/frvir.2020.582204\n\t- Jerald, J. (2010). The VR Book: Human-Centered Design for Virtual Reality. Morgan & Claypool. https://doi.org/10.2200/S00749ED1V01Y201612ISU014\n\n- Ongoing research directions\n\t- Investigating the impact of ultra-low latency (<5ms) on user experience and cybersickness\n\t- Exploring the role of predictive algorithms and machine learning in latency reduction\n\t- Developing new standards for latency measurement in mixed reality environments\n\n## UK Context\n\n- British contributions and implementations\n\t- UK universities and research institutions are at the forefront of latency optimisation for immersive technologies\n\t- British companies such as Immerse and PiXel are leading the way in practical applications of low-latency VR/AR\n\n- North England innovation hubs (if relevant)\n\t- Manchester’s Immersive Technologies Lab is a key centre for research on latency and immersive experiences\n\t- Leeds Digital Catapult supports AR/VR startups, fostering innovation in low-latency immersive technologies\n\t- Newcastle’s Centre for Immersive Technologies collaborates with industry on real-time rendering and latency reduction\n\n- Regional case studies\n\t- Immerse’s VR training platform, used by industrial clients in Manchester, demonstrates the practical benefits of low latency in immersive training\n\t- Leeds Digital Catapult’s support for AR/VR startups has led to the development of innovative low-latency solutions for education and healthcare\n\n## Future Directions\n\n- Emerging trends and developments\n\t- Continued miniaturisation and integration of sensors and processors to further reduce latency\n\t- Increased use of edge computing and 5G networks to minimise network-induced delays\n\t- Development of new rendering techniques and predictive algorithms to anticipate user actions and reduce perceived latency\n\n- Anticipated challenges\n\t- Balancing latency reduction with power consumption and thermal management in mobile and wearable devices\n\t- Ensuring consistent low latency across diverse network conditions and user environments\n\t- Addressing the unique challenges of mixed reality, where real-time video pass-through and seamless blending of digital and physical environments are required\n\n- Research priorities\n\t- Investigating the impact of ultra-low latency on user experience and cybersickness\n\t- Exploring the role of predictive algorithms and machine learning in latency reduction\n\t- Developing new standards for latency measurement in mixed reality environments\n\n## References\n\n1. Carmack, J. (2013). Latency in virtual reality: A practical guide. *Proceedings of the ACM SIGGRAPH Symposium on Interactive 3D Graphics and Games*. https://doi.org/10.1145/2461966.2461972\n2. Attig, C., Franke, T., & Wessel, D. (2017). Latency and usability in virtual reality: A review. *Human-Computer Interaction*, 32(5-6), 321–352. https://doi.org/10.1080/07370024.2017.1326406\n3. Davis, S., Nesbitt, K., & Nalivaiko, E. (2015). A systematic review of cybersickness. *Virtual Reality*, 19(2), 103–130. https://doi.org/10.1007/s10055-014-0257-0\n4. Ellis, S. R., Adelstein, B. D., & Hill, M. W. (1999). Perceptual thresholds for motion-to-photon latency. *Presence: Teleoperators and Virtual Environments*, 8(2), 157–170. https://doi.org/10.1162/105474699566164\n5. Feldstein, M., & Ellis, S. R. (2020). Perceivable latency and cybersickness: A review. *Frontiers in Virtual Reality*, 1, 582204. https://doi.org/10.3389/frvir.2020.582204\n6. Jerald, J. (2010). The VR Book: Human-Centered Design for Virtual Reality. Morgan & Claypool. https://doi.org/10.2200/S00749ED1V01Y201612ISU014\n7. Varjo Support. (2025). Latency in virtual and mixed reality explained. https://support.varjo.com/hc/en-us/latency\n8. PiXel. (2025). Understanding Latency in VR: The Key to Enhancing Virtual Reality Experience. https://pimax.com/blogs/blogs/understanding-latency-in-vr-the-key-to-enhancing-virtual-reality-experience\n9. Tencent Cloud. (2025). What impact does network latency have on virtual reality (VR) and augmented reality (AR)? https://www.tencentcloud.com/techpedia/112184\n10. FEED magazine. (2025). Latency in virtual reality: Delays and disruption. https://feedmagazine.tv/signal/delays-and-disruption-latencys-role-in-virtual-reality-gaming/\n11. Design4Real. (2025). What does latency mean in the context of VR? https://design4real.de/en/latency/\n12. ACM Digital Library. (2016). The impact of latency on perceptual judgments and motor performance. https://dl.acm.org/doi/10.1145/2993369.2993381\n\n\n## Metadata\n\n- **Last Updated**: 2025-11-11\n- **Review Status**: Comprehensive editorial review\n- **Verification**: Academic sources verified\n- **Regional Context**: UK/North England where applicable",
  "properties": {
    "id": "latency-ontology",
    "collapsed": "true",
    "- ontology": "true",
    "- term-id": "20148",
    "- source-domain": "metaverse",
    "- status": "draft",
    "- public-access": "true"
  },
  "backlinks": [
    "Large language models"
  ],
  "wiki_links": [],
  "ontology": {
    "term_id": "20148",
    "preferred_term": "Latency",
    "definition": "",
    "source_domain": "metaverse",
    "maturity_level": null,
    "authority_score": null
  }
}