{
  "title": "Layer Normalisation",
  "content": "- ### OntologyBlock\n  id:: layer-normalisation-ontology\n  collapsed:: true\n\t- ontology:: true\n\t- term-id:: AI-0203\n\t- preferred-term:: Layer Normalisation\n\t- source-domain:: ai\n\t- status:: draft\n    - public-access:: true\n\t- definition:: A normalisation technique that normalises activations across the feature dimension for each example independently, stabilising deep network training.\n\n\n## Academic Context\n\n- Layer Normalisation is a technique designed to stabilise and accelerate the training of deep neural networks by normalising activations across the feature dimension for each individual example independently.\n  - It addresses issues such as exploding or vanishing gradients by ensuring that the mean activation is zero and variance is one within each layer, thus maintaining stable input distributions during training.\n  - Unlike Batch Normalisation, which normalises across a mini-batch, Layer Normalisation operates within each data sample, making it particularly effective for models where batch sizes vary or are small.\n- The academic foundations of Layer Normalisation trace back to efforts to mitigate internal covariate shift, a phenomenon where the distribution of layer inputs changes during training, slowing convergence.\n  - It is mathematically defined by computing the mean and variance over all neurons in a layer for each sample, followed by scaling and shifting via learnable parameters.\n  - Layer Normalisation has become a key component in transformer architectures and recurrent neural networks, where batch-dependent normalisation is less effective.\n\n## Current Landscape (2025)\n\n- Layer Normalisation is widely adopted in industry, especially in natural language processing and sequence modelling tasks, where it complements or replaces Batch Normalisation.\n  - Major AI platforms and frameworks such as TensorFlow, PyTorch, and JAX include native support for Layer Normalisation.\n  - Organisations leveraging transformer-based models, including those in the UK, routinely employ Layer Normalisation to enhance training stability and performance.\n- In the UK and North England, tech hubs in Manchester and Leeds have integrated Layer Normalisation in AI research and commercial applications, particularly in startups focusing on NLP and computer vision.\n- Technical capabilities:\n  - Layer Normalisation enables stable training with variable batch sizes and is less sensitive to batch composition.\n  - However, it may introduce computational overhead compared to Batch Normalisation and can be less effective in convolutional architectures without adaptation.\n- Standards and frameworks continue to evolve, with Layer Normalisation being a standard layer type in deep learning libraries and recommended in best practice guides for transformer and recurrent models.\n\n## Research & Literature\n\n- Key academic papers:\n  - Ba, J. L., Kiros, J. R., & Hinton, G. E. (2016). *Layer Normalization*. arXiv preprint arXiv:1607.06450. [https://arxiv.org/abs/1607.06450]\n  - Vaswani, A., et al. (2017). *Attention Is All You Need*. Advances in Neural Information Processing Systems, 30, 5998–6008. [https://papers.nips.cc/paper/7181-attention-is-all-you-need.pdf]\n- These foundational works establish Layer Normalisation’s role in transformer models and its mathematical formulation.\n- Ongoing research explores optimising Layer Normalisation for convolutional networks, reducing computational cost, and combining it with other normalisation techniques for hybrid models.\n\n## UK Context\n\n- British AI research institutions, including those in Manchester and Newcastle, contribute to advancing Layer Normalisation applications, particularly in healthcare AI and language technologies.\n- North England innovation hubs foster startups and academic collaborations that implement Layer Normalisation in real-world systems, such as automated document analysis and speech recognition.\n- Regional case studies include Leeds-based AI firms utilising Layer Normalisation to improve model robustness in financial forecasting tools.\n\n## Future Directions\n\n- Emerging trends include adaptive Layer Normalisation variants that dynamically adjust normalisation parameters during training for improved generalisation.\n- Anticipated challenges involve balancing computational efficiency with normalisation benefits, especially for edge devices and real-time applications.\n- Research priorities focus on integrating Layer Normalisation with novel architectures, exploring its role in unsupervised and self-supervised learning, and enhancing interpretability of normalised activations.\n\n## References\n\n1. Ba, J. L., Kiros, J. R., & Hinton, G. E. (2016). *Layer Normalization*. arXiv preprint arXiv:1607.06450. Available at: https://arxiv.org/abs/1607.06450  \n2. Vaswani, A., Shazeer, N., Parmar, N., Uszkoreit, J., Jones, L., Gomez, A. N., Kaiser, Ł., & Polosukhin, I. (2017). *Attention Is All You Need*. Advances in Neural Information Processing Systems, 30, 5998–6008. Available at: https://papers.nips.cc/paper/7181-attention-is-all-you-need.pdf  \n3. GeeksforGeeks. (2025). *What is Layer Normalization?* Last updated 23 July 2025.  \n4. Wikipedia contributors. (2025). *Normalization (machine learning)*. Wikipedia. Retrieved November 2025, from https://en.wikipedia.org/wiki/Normalization_(machine_learning)\n\n\n## Metadata\n\n- **Last Updated**: 2025-11-11\n- **Review Status**: Comprehensive editorial review\n- **Verification**: Academic sources verified\n- **Regional Context**: UK/North England where applicable",
  "properties": {
    "id": "layer-normalisation-ontology",
    "collapsed": "true",
    "- ontology": "true",
    "- term-id": "AI-0203",
    "- preferred-term": "Layer Normalisation",
    "- source-domain": "ai",
    "- status": "draft",
    "- public-access": "true",
    "- definition": "A normalisation technique that normalises activations across the feature dimension for each example independently, stabilising deep network training."
  },
  "backlinks": [],
  "wiki_links": [],
  "ontology": {
    "term_id": "AI-0203",
    "preferred_term": "Layer Normalisation",
    "definition": "A normalisation technique that normalises activations across the feature dimension for each example independently, stabilising deep network training.",
    "source_domain": "ai",
    "maturity_level": null,
    "authority_score": null
  }
}