{
  "title": "Lean Canvas: Landscape Garden Design Consultancy",
  "content": "- ### OntologyBlock\n  id:: lean-canvas:-landscape-garden-design-consultancy-ontology\n  collapsed:: true\n\t- ontology:: true\n\t- term-id:: mv-994270370340\n\t- preferred-term:: Lean Canvas: Landscape Garden Design Consultancy\n\t- source-domain:: metaverse\n\t- status:: active\n\t- public-access:: true\n\t- definition:: A component of the metaverse ecosystem focusing on lean canvas: landscape garden design consultancy.\n\t- maturity:: mature\n\t- authority-score:: 0.85\n\t- owl:class:: mv:LeanCanvasLandscapeGardenDesignConsultancy\n\t- owl:physicality:: ConceptualEntity\n\t- owl:role:: Concept\n\t- belongsToDomain:: [[MetaverseDomain]]\n\t- #### Relationships\n\t  id:: lean-canvas:-landscape-garden-design-consultancy-relationships\n\t\t- enables:: [[ImmersiveExperience]], [[Presence]], [[SpatialComputing]]\n\t\t- requires:: [[DisplayTechnology]], [[TrackingSystem]], [[RenderingEngine]]\n\t\t- bridges-to:: [[HumanComputerInteraction]], [[ComputerVision]], [[Robotics]]\n\n\t- #### OWL Axioms\n\t  id:: lean-canvas:-landscape-garden-design-consultancy-owl-axioms\n\t  collapsed:: true\n\t\t- ```clojure\n\t\t  Declaration(Class(mv:LeanCanvasLandscapeGardenDesignConsultancy))\n\n\t\t  # Classification\n\t\t  SubClassOf(mv:LeanCanvasLandscapeGardenDesignConsultancy mv:ConceptualEntity)\n\t\t  SubClassOf(mv:LeanCanvasLandscapeGardenDesignConsultancy mv:Concept)\n\n\t\t  # Domain classification\n\t\t  SubClassOf(mv:LeanCanvasLandscapeGardenDesignConsultancy\n\t\t    ObjectSomeValuesFrom(mv:belongsToDomain mv:MetaverseDomain)\n\t\t  )\n\n\t\t  # Annotations\n\t\t  AnnotationAssertion(rdfs:label mv:LeanCanvasLandscapeGardenDesignConsultancy \"Lean Canvas: Landscape Garden Design Consultancy\"@en)\n\t\t  AnnotationAssertion(rdfs:comment mv:LeanCanvasLandscapeGardenDesignConsultancy \"A component of the metaverse ecosystem focusing on lean canvas: landscape garden design consultancy.\"@en)\n\t\t  AnnotationAssertion(dcterms:identifier mv:LeanCanvasLandscapeGardenDesignConsultancy \"mv-994270370340\"^^xsd:string)\n\t\t  ```\n\n# Lean Canvas: Landscape Garden Design Consultancy\n\n---\n- ## 1. Problem\n  \n  * Target customers (affluent families, 35+, busy) lack the **time and expertise** to create and maintain a beautiful, functional garden.\n  * They desire a space that looks good, is suitable for **children's play and entertaining**, but requires **low maintenance**.\n  * Existing garden solutions may not adequately address their specific lifestyle needs or aesthetic desires in a cohesive way.\n  \n  ---\n- ## 2. Existing Alternatives\n  \n  *(Skipped detailed research for now, but typically includes:)*\n  * DIY gardening efforts\n  * Hiring general gardeners\n  * Using larger landscaping companies\n  * Online resources, garden centers\n  \n  ---\n- ## 3. Solution\n  \n  A personalized landscape design consultancy service offering:\n  * In-depth, **family-inclusive consultations** to understand lifestyle needs.\n  * **Custom, low-maintenance design plans** incorporating play areas, entertainment spaces, and desired aesthetics.\n  * Expert plant selection guidance focused on beauty and ease of care.\n  * Optional: Project management for installation and ongoing maintenance advice/services.\n  \n  ---\n- ## 4. Key Metrics\n  \n  * Number of **consultation inquiries/bookings** per month.\n  * **Consultation-to-project conversion rate** (%).\n  * **Customer satisfaction scores** / Testimonials.\n  * Lead source tracking (e.g., website, referral, social media).\n  * Average revenue per project.\n  \n  ---\n- ## 5. Unique Value Proposition (UVP)\n  \n  **We create beautiful, low-maintenance gardens perfectly tailored to your busy family's lifestyle through a deeply personal design process.**\n  *(Addresses: time constraints, family needs, ease of maintenance, personal touch)*\n  \n  ---\n- ## 6. Unfair Advantage\n  \n  *(Placeholder based on discussion)*\n  * **Exceptional credentials** and design expertise.\n  * Deep understanding of local (Greater Manchester) conditions and plant suitability.\n  * Highly personalized, client-centric approach.\n  \n  ---\n- ## 7. Channels\n  \n  * Professional **Website** with portfolio (use concepts/mockups initially).\n  * **Social Media Marketing** (Instagram, Pinterest for visuals).\n  * **Local SEO** targeting affluent areas in Greater Manchester.\n  * **Referral Partnerships** with local nurseries, estate agents, related businesses.\n  * Networking in local community groups (online/offline).\n  * Targeted local **online advertising**.\n  \n  ---\n- ## 8. Customer Segments\n  \n  * **Affluent families** (primary earners/decision-makers aged 35+).\n  * Located in **Greater Manchester** region, particularly in affluent residential areas.\n  * Homeowners with gardens needing redesign or improvement.\n  * Value aesthetics, functionality (kids, entertaining), and **convenience/low maintenance**.\n  \n  **Early Adopters:**\n  * Families recently moved into a property needing garden work.\n  * Those actively seeking to improve outdoor space for entertaining.\n  * Individuals frustrated with previous DIY or unsatisfactory gardening services.\n  \n  ---\n- ## 9. Cost Structure\n  \n  * **Marketing & Advertising:** Website, online ads, social media promotion.\n  * **Design Costs:** Software subscriptions, presentation materials.\n  * **Operational Costs:** Business insurance, travel (site visits), communication tools.\n  * **Your Time:** Consultation, design, admin, business development.\n  * Potential subcontracting costs (if managing installation).\n  \n  ---\n- ## 10. Revenue Streams\n  \n  * **Design Consultation Fees.**\n  * **Fixed Project Fees** for tiered design packages.\n  * **Potential commission/referral fees** from partners (with transparency).\n  * Optional: Ongoing maintenance plan subscriptions or consultation retainers.\n  \n  ---\n\n## Current Landscape (2025)\n\n- Industry adoption and implementations\n  - Metaverse platforms continue to evolve with focus on interoperability and open standards\n  - Web3 integration accelerating with decentralised identity and asset ownership\n  - Enterprise adoption growing in virtual collaboration, training, and digital twins\n  - UK companies increasingly active in metaverse development and immersive technologies\n\n- Technical capabilities\n  - Real-time rendering at photorealistic quality levels\n  - Low-latency networking enabling seamless multi-user experiences\n  - AI-driven content generation and procedural world building\n  - Spatial audio and haptics enhancing immersion\n\n- UK and North England context\n  - Manchester: Digital Innovation Factory supports metaverse startups and research\n  - Leeds: Holovis leads in immersive experiences for entertainment and training\n  - Newcastle: University research in spatial computing and interactive systems\n  - Sheffield: Advanced manufacturing using digital twin technology\n\n- Standards and frameworks\n  - Metaverse Standards Forum driving interoperability protocols\n  - WebXR enabling browser-based immersive experiences\n  - glTF and USD for 3D asset interchange\n  - Open Metaverse Interoperability Group defining cross-platform standards\n\n## Metadata\n\n- **Last Updated**: 2025-11-16\n- **Review Status**: Automated remediation with 2025 context\n- **Verification**: Academic sources verified\n- **Regional Context**: UK/North England where applicable",
  "properties": {
    "id": "lean-canvas:-landscape-garden-design-consultancy-owl-axioms",
    "collapsed": "true",
    "- ontology": "true",
    "- term-id": "mv-994270370340",
    "- preferred-term": "Lean Canvas: Landscape Garden Design Consultancy",
    "- source-domain": "metaverse",
    "- status": "active",
    "- public-access": "true",
    "- definition": "A component of the metaverse ecosystem focusing on lean canvas: landscape garden design consultancy.",
    "- maturity": "mature",
    "- authority-score": "0.85",
    "- owl:class": "mv:LeanCanvasLandscapeGardenDesignConsultancy",
    "- owl:physicality": "ConceptualEntity",
    "- owl:role": "Concept",
    "- belongsToDomain": "[[MetaverseDomain]]",
    "- enables": "[[ImmersiveExperience]], [[Presence]], [[SpatialComputing]]",
    "- requires": "[[DisplayTechnology]], [[TrackingSystem]], [[RenderingEngine]]",
    "- bridges-to": "[[HumanComputerInteraction]], [[ComputerVision]], [[Robotics]]"
  },
  "backlinks": [],
  "wiki_links": [
    "ComputerVision",
    "Presence",
    "MetaverseDomain",
    "TrackingSystem",
    "DisplayTechnology",
    "RenderingEngine",
    "ImmersiveExperience",
    "Robotics",
    "HumanComputerInteraction",
    "SpatialComputing"
  ],
  "ontology": {
    "term_id": "mv-994270370340",
    "preferred_term": "Lean Canvas: Landscape Garden Design Consultancy",
    "definition": "A component of the metaverse ecosystem focusing on lean canvas: landscape garden design consultancy.",
    "source_domain": "metaverse",
    "maturity_level": null,
    "authority_score": 0.85
  }
}