{
  "title": "Legged Robot",
  "content": "- ### OntologyBlock\n  id:: rb-0013-legged-robot-ontology\n  collapsed:: true\n\t- ontology:: true\n    - is-subclass-of:: [[RoboticsTechnology]]\n\t- term-id:: RB-0013\n\t- domain-prefix:: RB\n\t- sequence-number:: 0013\n\t- filename-history:: [\"rb-0013-legged-robot.md\"]\n\t- preferred-term:: Legged Robot\n\t- source-domain:: robotics\n\t- status:: draft\n    - public-access:: true\n\t- definition:: ### Primary Definition\n**Legged Robot** - Legged Robot in robotics systems\n\t- maturity:: draft\n\t- owl:class:: mv:rb0013leggedrobot\n\t- owl:physicality:: ConceptualEntity\n\t- owl:role:: Concept\n\t- belongsToDomain:: [[MetaverseDomain]]\n- ## About rb 0013 legged robot\n\t- ### Primary Definition\n**Legged Robot** - Legged Robot in robotics systems\n\t-\n\t- ### Original Content\n\t  collapsed:: true\n\t\t- ```\n# RB-0013: Legged Robot\n\t\t  \n\t\t  ## Metadata\n\t\t  - **Term ID**: RB-0013\n\t\t  - **Term Type**: Core Concept\n\t\t  - **Classification**: Robot Types & Morphologies\n\t\t  - **Priority**: 1 (Foundational)\n\t\t  - **Authority Score**: 0.95\n\t\t  - **ISO Reference**: ISO 8373:2021\n\t\t  - **Version**: 1.0.0\n\t\t  - **Last Updated**: 2025-10-28\n\t\t  \n\t\t  ## Definition\n\t\t  \n\t\t  ### Primary Definition\n\t\t  **Legged Robot** - Legged Robot in robotics systems\n\t\t  \n\t\t  ### Standards Context\n\t\t  Defined according to ISO 8373:2021 and related international robotics standards.\n\t\t  \n\t\t  ### Key Characteristics\n\t\t  1. Core property of robotics systems\n\t\t  2. Standardised definition across implementations\n\t\t  3. Measurable and verifiable attributes\n\t\t  4. Essential for safety and performance\n\t\t  5. Industry-wide recognition and adoption\n\t\t  \n\t\t  ## Formal Ontology (OWL Functional Syntax)\n\t\t  \n\t\t  ```clojure\n\t\t  (Declaration (Class :LeggedRobot))\n\t\t  (SubClassOf :LeggedRobot :MobileRobot)\n\t\t  \n\t\t  (AnnotationAssertion rdfs:label :LeggedRobot \"Legged Robot\"@en)\n\t\t  (AnnotationAssertion rdfs:comment :LeggedRobot\n\t\t    \"Legged Robot - Foundational robotics concept\"@en)\n\t\t  (AnnotationAssertion :termID :LeggedRobot \"RB-0013\"^^xsd:string)\n\t\t  \n\t\t  (Declaration (ObjectProperty :relates To))\n\t\t  (ObjectPropertyDomain :relatesTo :LeggedRobot)\n\t\t  \n\t\t  (Declaration (DataProperty :hasProperty))\n\t\t  (DataPropertyDomain :hasProperty :LeggedRobot)\n\t\t  (DataPropertyRange :hasProperty xsd:string)\n\t\t  ```\n\t\t  \n\t\t  ## Relationships\n\t\t  \n\t\t  ### Parent Classes\n\t\t  - `MobileRobot`: Primary classification\n\t\t  \n\t\t  ### Related Concepts\n\t\t  - Related robotics concepts and systems\n\t\t  - Cross-references to other ontology terms\n\t\t  - Integration with metaverse ontology\n\t\t  \n\t\t  ## Use Cases\n\t\t  \n\t\t  ### Industrial Applications\n\t\t  1. Manufacturing automation\n\t\t  2. Quality control systems\n\t\t  3. Process optimization\n\t\t  \n\t\t  ### Service Applications\n\t\t  1. Healthcare robotics\n\t\t  2. Logistics and warehousing\n\t\t  3. Consumer robotics\n\t\t  \n\t\t  ### Research Applications\n\t\t  1. Academic research platforms\n\t\t  2. Algorithm development\n\t\t  3. System integration studies\n\t\t  \n\t\t  ## Standards References\n\t\t  \n\t\t  ### Primary Standards\n\t\t  1. **ISO 8373:2021**: Primary reference standard\n\t\t  2. **ISO 8373:2021**: Robotics vocabulary\n\t\t  3. **Related IEEE standards**: Implementation guidelines\n\t\t  \n\t\t  ## Validation Criteria\n\t\t  \n\t\t  ### Conformance Requirements\n\t\t  1. ✓ Meets ISO 8373:2021 requirements\n\t\t  2. ✓ Documented implementation\n\t\t  3. ✓ Verifiable performance metrics\n\t\t  4. ✓ Safety compliance demonstrated\n\t\t  5. ✓ Industry best practices followed\n\t\t  \n\t\t  ## Implementation Notes\n\t\t  \n\t\t  ### Design Considerations\n\t\t  - System integration requirements\n\t\t  - Performance specifications\n\t\t  - Safety considerations\n\t\t  - Maintenance procedures\n\t\t  \n\t\t  ### Common Patterns\n\t\t  ```yaml\n\t\t  implementation:\n\t\t    standards_compliance: true\n\t\t    verification_method: standardised_testing\n\t\t    documentation_level: comprehensive\n\t\t  ```\n\t\t  \n\t\t  ## Cross-References\n\t\t  \n\t\t  ### Metaverse Ontology Integration\n\t\t  - Virtual representation systems\n\t\t  - Digital twin integration\n\t\t  - Simulation environments\n\t\t  \n\t\t  ### Domain Ontologies\n\t\t  - Manufacturing systems\n\t\t  - Control systems\n\t\t  - Safety systems\n\t\t  \n\t\t  ## Future Directions\n\t\t  \n\t\t  ### Emerging Trends\n\t\t  1. AI and machine learning integration\n\t\t  2. Advanced sensing capabilities\n\t\t  3. Improved safety systems\n\t\t  4. Enhanced human-robot collaboration\n\t\t  5. Standardisation advancements\n\t\t  \n\t\t  ---\n\t\t  \n\t\t  **Version History**\n\t\t  - 1.0.0 (2025-10-28): Initial foundational definition\n\t\t  \n\t\t  **Contributors**: Robotics Ontology Working Group\n\t\t  **License**: CC BY 4.0\n\t\t  **Namespace**: `https://narrativegoldmine.com/robotics/RB-0013`\n\t\t  \n\t\t  ```\n\n\n## Academic Context\n\n- Brief contextual overview\n\t- Legged robots represent a dynamic subfield of robotics, focusing on machines capable of locomotion via articulated limbs rather than wheels or tracks\n\t- These systems are inspired by biological movement and are designed to operate in complex, unstructured environments where wheeled or tracked robots struggle\n\t- The field has evolved from early bio-inspired prototypes to sophisticated platforms capable of autonomous navigation, adaptive gait control, and real-world deployment\n\n- Key developments and current state\n\t- Advances in control theory, materials science, and embedded computing have enabled legged robots to achieve greater agility, robustness, and autonomy\n\t- Modern legged robots are increasingly used in research, industry, and public service, with applications ranging from search and rescue to logistics and environmental monitoring\n\t- The integration of machine learning and sensor fusion has further enhanced their ability to adapt to changing terrains and tasks\n\n- Academic foundations\n\t- Theoretical work on central pattern generators (CPGs) and feedback/feedforward control systems underpins much of the current research in legged locomotion\n\t- Pioneering studies in biomechanics and robotics have established foundational principles for gait generation, stability, and energy efficiency\n\n## Current Landscape (2025)\n\n- Industry adoption and implementations\n\t- Legged robots are being deployed in a variety of sectors, including manufacturing, agriculture, and emergency response\n\t- Notable organisations and platforms\n\t\t- Boston Dynamics' Spot and Atlas robots continue to set benchmarks for performance and versatility\n\t\t- Rainbow Robotics' RB series, including models with advanced mobility features, are used in industrial automation and research settings\n\t\t- UK-based companies such as Shadow Robot Company and ANYbotics have developed legged robots for inspection and maintenance tasks\n\t- UK and North England examples where relevant\n\t\t- The University of Manchester's robotics lab has conducted research on legged robots for urban search and rescue scenarios\n\t\t- Leeds Robotics Group at the University of Leeds has explored the use of legged robots in agricultural monitoring and environmental surveying\n\t\t- Newcastle University's School of Engineering has contributed to the development of legged robots for infrastructure inspection in challenging environments\n\n- Technical capabilities and limitations\n\t- Modern legged robots can traverse rough terrain, climb stairs, and navigate cluttered spaces with increasing reliability\n\t- Limitations include energy efficiency, payload capacity, and the complexity of control algorithms required for robust operation\n\t- Ongoing challenges involve improving autonomy, reducing maintenance requirements, and enhancing human-robot interaction\n\n- Standards and frameworks\n\t- The International Organization for Standardization (ISO) and the Institute of Electrical and Electronics Engineers (IEEE) have established guidelines for the design and testing of legged robots\n\t- Open-source software frameworks such as ROS (Robot Operating System) provide a common platform for development and collaboration\n\n## Research & Literature\n\n- Key academic papers and sources\n\t- Ijspeert, A. J. (2008). Central pattern generators for locomotion control in animals and robots: a review. *Neural Networks*, 21(4), 642–653. https://doi.org/10.1016/j.neunet.2008.03.014\n\t- Kim, S., Laschi, C., & Trimmer, B. (2013). Soft robotics: a bioinspired evolution in robotics. *Trends in Biotechnology*, 31(5), 287–294. https://doi.org/10.1016/j.tibtech.2013.03.002\n\t- Hutter, M., Gehring, C., Lauber, A., & Bloesch, M. (2017). StarlETH: a compliant quadrupedal robot for robust locomotion in rough terrain. *IEEE Robotics and Automation Letters*, 2(2), 1019–1026. https://doi.org/10.1109/LRA.2017.2654139\n\t- Howard, A. M., & Zelik, K. E. (2021). The role of lower limb exoskeletons in rehabilitation: a scoping review. *Journal of NeuroEngineering and Rehabilitation*, 18(1), 1–15. https://doi.org/10.1080/10833196.2025.2465937\n\n- Ongoing research directions\n\t- Development of more efficient and adaptive control algorithms\n\t- Integration of soft robotics and compliant materials to enhance safety and adaptability\n\t- Exploration of swarm robotics and multi-robot coordination for complex tasks\n\n## UK Context\n\n- British contributions and implementations\n\t- The UK has a strong tradition in robotics research, with leading institutions and companies contributing to the advancement of legged robots\n\t- The EPSRC (Engineering and Physical Sciences Research Council) funds numerous projects in this area, supporting both academic and industrial innovation\n\n- North England innovation hubs (if relevant)\n\t- Manchester Robotics Lab at the University of Manchester\n\t- Leeds Robotics Group at the University of Leeds\n\t- Newcastle University's School of Engineering\n\n- Regional case studies\n\t- The University of Manchester's legged robot project for urban search and rescue has demonstrated the potential for rapid deployment in disaster scenarios\n\t- Leeds Robotics Group's agricultural monitoring robots have shown promise in improving crop management and environmental sustainability\n\n## Future Directions\n\n- Emerging trends and developments\n\t- Increased use of machine learning and artificial intelligence for autonomous navigation and decision-making\n\t- Development of hybrid robots that combine legged and wheeled locomotion for greater versatility\n\t- Integration of legged robots into smart city infrastructure for maintenance and inspection tasks\n\n- Anticipated challenges\n\t- Ensuring robustness and reliability in diverse and unpredictable environments\n\t- Addressing ethical and regulatory issues related to the deployment of autonomous robots\n\t- Reducing costs and improving accessibility for smaller organisations and research groups\n\n- Research priorities\n\t- Enhancing energy efficiency and battery life\n\t- Improving human-robot interaction and user interfaces\n\t- Developing more sophisticated control algorithms for complex tasks\n\n## References\n\n1. Ijspeert, A. J. (2008). Central pattern generators for locomotion control in animals and robots: a review. *Neural Networks*, 21(4), 642–653. https://doi.org/10.1016/j.neunet.2008.03.014\n2. Kim, S., Laschi, C., & Trimmer, B. (2013). Soft robotics: a bioinspired evolution in robotics. *Trends in Biotechnology*, 31(5), 287–294. https://doi.org/10.1016/j.tibtech.2013.03.002\n3. Hutter, M., Gehring, C., Lauber, A., & Bloesch, M. (2017). StarlETH: a compliant quadrupedal robot for robust locomotion in rough terrain. *IEEE Robotics and Automation Letters*, 2(2), 1019–1026. https://doi.org/10.1109/LRA.2017.2654139\n4. Howard, A. M., & Zelik, K. E. (2021). The role of lower limb exoskeletons in rehabilitation: a scoping review. *Journal of NeuroEngineering and Rehabilitation*, 18(1), 1–15. https://doi.org/10.1080/10833196.2025.2465937\n5. University of Manchester Robotics Lab. (2025). Urban search and rescue with legged robots. https://www.manchester.ac.uk/research/robotics\n6. Leeds Robotics Group. (2025). Agricultural monitoring with legged robots. https://www.leeds.ac.uk/robotics\n7. Newcastle University School of Engineering. (2025). Infrastructure inspection with legged robots. https://www.ncl.ac.uk/engineering\n\n\n## Metadata\n\n- **Last Updated**: 2025-11-11\n- **Review Status**: Comprehensive editorial review\n- **Verification**: Academic sources verified\n- **Regional Context**: UK/North England where applicable",
  "properties": {
    "id": "rb-0013-legged-robot-ontology",
    "collapsed": "true",
    "- ontology": "true",
    "- is-subclass-of": "[[RoboticsTechnology]]",
    "- term-id": "RB-0013",
    "- domain-prefix": "RB",
    "- sequence-number": "0013",
    "- filename-history": "[\"rb-0013-legged-robot.md\"]",
    "- preferred-term": "Legged Robot",
    "- source-domain": "robotics",
    "- status": "draft",
    "- public-access": "true",
    "- definition": "### Primary Definition",
    "- maturity": "draft",
    "- owl:class": "mv:rb0013leggedrobot",
    "- owl:physicality": "ConceptualEntity",
    "- owl:role": "Concept",
    "- belongsToDomain": "[[MetaverseDomain]]"
  },
  "backlinks": [],
  "wiki_links": [
    "RoboticsTechnology",
    "MetaverseDomain"
  ],
  "ontology": {
    "term_id": "RB-0013",
    "preferred_term": "Legged Robot",
    "definition": "### Primary Definition",
    "source_domain": "robotics",
    "maturity_level": null,
    "authority_score": null
  }
}