{
  "title": "Libertarian thesis",
  "content": "- ### OntologyBlock\n  id:: libertarian-thesis-ontology\n  collapsed:: true\n\t- ontology:: true\n\t- term-id:: mv-447598994019\n\t- preferred-term:: Libertarian thesis\n\t- source-domain:: metaverse\n\t- status:: active\n\t- public-access:: true\n\t- definition:: A component of the metaverse ecosystem focusing on libertarian thesis.\n\t- maturity:: mature\n\t- authority-score:: 0.85\n\t- owl:class:: mv:LibertarianThesis\n\t- owl:physicality:: ConceptualEntity\n\t- owl:role:: Concept\n\t- belongsToDomain:: [[MetaverseDomain]]\n\t- #### Relationships\n\t  id:: libertarian-thesis-relationships\n\t\t- enables:: [[ImmersiveExperience]], [[Presence]], [[SpatialComputing]]\n\t\t- requires:: [[DisplayTechnology]], [[TrackingSystem]], [[RenderingEngine]]\n\t\t- bridges-to:: [[HumanComputerInteraction]], [[ComputerVision]], [[Robotics]]\n\n\t- #### OWL Axioms\n\t  id:: libertarian-thesis-owl-axioms\n\t  collapsed:: true\n\t\t- ```clojure\n\t\t  Declaration(Class(mv:LibertarianThesis))\n\n\t\t  # Classification\n\t\t  SubClassOf(mv:LibertarianThesis mv:ConceptualEntity)\n\t\t  SubClassOf(mv:LibertarianThesis mv:Concept)\n\n\t\t  # Domain classification\n\t\t  SubClassOf(mv:LibertarianThesis\n\t\t    ObjectSomeValuesFrom(mv:belongsToDomain mv:MetaverseDomain)\n\t\t  )\n\n\t\t  # Annotations\n\t\t  AnnotationAssertion(rdfs:label mv:LibertarianThesis \"Libertarian thesis\"@en)\n\t\t  AnnotationAssertion(rdfs:comment mv:LibertarianThesis \"A component of the metaverse ecosystem focusing on libertarian thesis.\"@en)\n\t\t  AnnotationAssertion(dcterms:identifier mv:LibertarianThesis \"mv-447598994019\"^^xsd:string)\n\t\t  ```\n\n- ---\n  title: Democracy: The God That Failed - A Mind Map\n  markmap:\n    colorFreezeLevel: 2\n  ---\n- # **Democracy: The God That Failed**\n- ## **Hans-Hermann Hoppe**\n- ### Main Themes\n- #### **Critique of Democracy**\n\t- Inherent flaws of democracy\n\t\t- Leads to increased state power\n\t\t- Promotes short-term policies\n\t\t- Erodes individual freedoms\n\t- Moral and ethical deficiencies\n\t\t- Majority rule does not equate to justice\n\t\t- Legitimizes coercion and expropriation\n\t- Historical failures of democracy\n\t\t- Rise of totalitarian regimes\n\t\t- Economic inefficiencies\n- #### **Preference for Monarchy**\n\t- Monarchy as privately owned government\n\t\t- Promotes long-term planning\n\t\t- Incentivizes capital preservation\n\t- Lower time preference of monarchs\n\t\t- Interest in preserving the realm's value\n\t\t- Less incentive for excessive taxation and exploitation\n\t- Historical examples of monarchical benefits\n\t\t- More stable and prosperous societies\n- #### **Advocacy for Natural Order**\n\t- Stateless society based on private property\n\t\t- Voluntary interactions and contracts\n\t\t- Absence of coercion and forced integration\n\t- Role of private defense agencies\n\t\t- Efficient protection of property rights\n\t\t- Market-based solutions for security\n\t- Importance of natural elites\n\t\t- Emergence of leaders based on merit and virtue\n\t\t- Role in maintaining social order\n- #### **Critique of Classical Liberalism**\n\t- Errors in classical liberal thought\n\t\t- Support for limited government\n\t\t- Failure to recognize inherent flaws of the state\n\t- Inconsistency between classical liberalism and democracy\n\t\t- Democracy undermines individual liberties\n\t\t- Leads to expansion of state power\n- #### **Decentralization and Secession**\n\t- Importance of local autonomy\n\t\t- Right of secession as a check on state power\n\t\t- Benefits of smaller, independent political units\n\t- Role in promoting economic freedom\n\t\t- Competition among jurisdictions\n\t\t- Enhanced individual choice and mobility\n\t- Strategy for achieving a free society\n\t\t- Peaceful secession movements\n\t\t- Delegitimization of the central state\n- ### Key Concepts\n- #### **Time Preference**\n\t- Impact on economic behavior\n\t\t- High time preference leads to short-term focus\n\t\t- Low time preference promotes long-term planning\n\t- Role in societal development\n\t\t- Lower time preference in monarchies\n\t\t- Higher time preference in democracies\n- #### **Property Rights**\n\t- Foundation of a free society\n\t\t- Protection of individual liberties\n\t\t- Basis for economic prosperity\n\t- Erosion under democracy\n\t\t- Increased taxation and regulation\n\t\t- Forced integration and redistribution\n- #### **Forced Integration**\n\t- Negative consequences of state-imposed integration\n\t\t- Increased social conflict\n\t\t- Erosion of property values\n\t- Contrast with voluntary association\n\t\t- Benefits of free choice in association\n\t\t- Role in maintaining social harmony\n- #### **Socialism and Desocialization**\n\t- Critique of socialist economic policies\n\t\t- Inefficiencies and misallocation of resources\n\t\t- Lack of incentives for production\n\t- Process of desocialization\n\t\t- Privatization of state-owned assets\n\t\t- Restoration of property rights\n- #### **Role of Elites**\n\t- Natural elites in a free society\n\t\t- Emergence based on merit and achievement\n\t\t- Role in providing leadership and justice\n\t- Corruption of elites under democracy\n\t\t- Rise of political opportunists\n\t\t- Decline of moral and intellectual standards\n- ### Supporting Arguments\n- #### **Historical Evidence**\n\t- Comparison of monarchies and democracies\n\t\t- Examples of successful monarchies\n\t\t- Failures of democratic regimes\n\t- Analysis of historical trends\n\t\t- Rise and fall of civilizations\n\t\t- Impact of political systems on economic development\n- #### **Economic Theory**\n\t- Austrian School of Economics\n\t\t- Emphasis on individual action and subjective value\n\t\t- Critique of state intervention\n\t- Public Choice Theory\n\t\t- Analysis of political decision-making\n\t\t- Incentives faced by politicians and bureaucrats\n- #### **Ethical Considerations**\n\t- Natural rights philosophy\n\t\t- Importance of individual liberty and property rights\n\t\t- Critique of coercion and aggression\n\t- Moral basis of voluntary interactions\n\t\t- Respect for individual autonomy\n\t\t- Condemnation of forced redistribution\n- ### Policy Implications\n- #### **Promoting Secession**\n\t- Encouraging local autonomy and self-governance\n\t\t- Reducing the power of central governments\n\t\t- Allowing for diverse social and economic experiments\n\t- Supporting peaceful secession movements\n\t\t- Recognizing the right of self-determination\n\t\t- Avoiding violent conflict\n- #### **Privatization**\n\t- Transferring state-owned assets to private individuals\n\t\t- Restoring property rights\n\t\t- Enhancing economic efficiency\n\t- Eliminating state monopolies\n\t\t- Promoting competition in all sectors\n\t\t- Allowing for market-based solutions\n- #### **Restricting Immigration**\n\t- Implementing selective immigration policies\n\t\t- Prioritizing skilled and productive immigrants\n\t\t- Protecting the interests of existing citizens\n\t- Avoiding forced integration\n\t\t- Allowing for voluntary association and dissociation\n\t\t- Respecting cultural and social differences\n- #### **Abolishing the Welfare State**\n\t- Eliminating social security, and other welfare programs\n\t\t- Restoring individual responsibility\n\t\t- Reducing dependency on the state\n\t- Promoting private charity and mutual aid\n\t\t- Encouraging voluntary cooperation\n\t\t- Strengthening family and community bonds\n- #### **Critique of Modern Democracy**\n\t- **Erosion of Traditional Values**\n\t\t- Breakdown of family structures\n\t\t- Decline of moral standards\n\t\t- Rise of cultural relativism\n\t- **Expansion of State Power**\n\t\t- Increased taxation and regulation\n\t\t- Growth of bureaucracy\n\t\t- Infringement on individual liberties\n\t- **Economic Consequences**\n\t\t- Misallocation of resources\n\t\t- Inflation and currency debasement\n\t\t- Stifling of economic growth\n\t- **Social Consequences**\n\t\t- Increased crime and social disorder\n\t\t- Dependency on the welfare state\n\t\t- Social fragmentation and conflict\n- #### **Defense of Private Property**\n\t- **Ethical Foundation**\n\t\t- Based on self-ownership and original appropriation\n\t\t- Justification for exclusive control over resources\n\t- **Economic Benefits**\n\t\t- Incentives for production and innovation\n\t\t- Efficient allocation of resources\n\t\t- Protection against aggression and theft\n\t- **Social Implications**\n\t\t- Basis for voluntary cooperation and exchange\n\t\t- Foundation for a free and prosperous society\n- #### **Role of the State**\n\t- **Minimal State vs. Anarcho-Capitalism**\n\t\t- Debate within libertarian thought\n\t\t- Arguments for statelessness\n\t- **State as a Source of Disorder**\n\t\t- Monopoly on coercion leads to abuse of power\n\t\t- State intervention distorts market processes\n\t- **State's Inability to Provide True Security**\n\t\t- Forced integration exacerbates social tensions\n\t\t- State's own actions often threaten individual security\n- #### **Immigration Policy**\n\t- **Critique of Open Borders**\n\t\t- Potential for social and economic disruption\n\t\t- Strain on public resources and welfare systems\n\t- **Advocacy for Controlled Immigration**\n\t\t- Importance of cultural compatibility\n\t\t- Prioritizing skilled and productive immigrants\n\t- **Role of Private Property Owners**\n\t\t- Right to exclude or admit individuals\n\t\t- Decentralized control over immigration\n- #### **Vision of a Free Society**\n\t- **Decentralized Political Order**\n\t\t- Importance of local autonomy and self-governance\n\t\t- Role of secession in limiting state power\n\t- **Market-Based Provision of Security**\n\t\t- Private defense agencies and insurance companies\n\t\t- Competition and innovation in security provision\n\t- **Restoration of Traditional Values**\n\t\t- Emphasis on family, community, and personal responsibility\n\t\t- Rejection of egalitarianism and cultural relativism\n- ### Implications for Action\n- #### **Delegitimization of Democracy**\n\t- Exposing the flaws and failures of democratic governance\n\t- Promoting alternative models of social organization\n\t- Challenging the moral and ethical foundations of democracy\n- #### **Promotion of Libertarian Principles**\n\t- Educating the public about the benefits of free markets and individual liberty\n\t- Advocating for the protection of private property rights\n\t- Emphasizing the importance of voluntary cooperation\n- #### **Support for Secessionist Movements**\n\t- Recognizing the right of self-determination\n\t- Encouraging peaceful separation from oppressive regimes\n\t- Fostering the development of alternative political communities\n- #### **Building Alternative Institutions**\n\t- Supporting the creation of private alternatives to state services\n\t- Promoting the development of free-market solutions to social problems\n\t- Encouraging the formation of voluntary associations and communities\n- #### **Engaging in Civil Disobedience**\n\t- Resisting unjust laws and regulations\n\t- Refusing to cooperate with state aggression\n\t- Promoting a culture of non-compliance with state authority\n- #### **The Non-Aggression Principle (NAP)**\n\t- **Foundation of Libertarian Ethics**\n\t\t- Prohibition against initiating force or fraud\n\t\t- Respect for self-ownership and property rights\n\t- **Implications for Government**\n\t\t- State's monopoly on force inherently violates NAP\n\t\t- Taxation as a form of aggression\n\t- **Application to Immigration**\n\t\t- Forced integration violates NAP\n\t\t- Right of property owners to exclude\n- #### **The Problem of Public Goods**\n\t- **Traditional Argument for State Provision**\n\t\t- Market failure due to free-rider problem\n\t\t- National defense as a supposed public good\n\t- **Critique of the Public Goods Argument**\n\t\t- Many alleged public goods can be privatized\n\t\t- Market solutions often more efficient than state provision\n\t- **Private Provision of Security**\n\t\t- Insurance companies as potential providers\n\t\t- Market incentives for efficient security provision\n- #### **The Role of Culture and Tradition**\n\t- **Critique of Cultural Relativism**\n\t\t- Importance of objective moral standards\n\t\t- Dangers of moral decay and social disintegration\n\t- **Defense of Traditional Institutions**\n\t\t- Family as the foundation of social order\n\t\t- Importance of cultural transmission across generations\n\t- **Relationship to Libertarianism**\n\t\t- Compatibility of libertarian principles with traditional values\n\t\t- Libertarianism as a means of preserving cultural heritage\n- #### **The Dynamics of Political Power**\n\t- **Public Choice Theory Insights**\n\t\t- Politicians and bureaucrats as self-interested actors\n\t\t- Incentives for state expansion and intervention\n\t- **The Iron Law of Oligarchy**\n\t\t- Tendency for power to concentrate in the hands of a few\n\t\t- Implications for democratic governance\n\t- **The Role of Ideology**\n\t\t- Importance of ideas in shaping political outcomes\n\t\t- Need for a counter-ideology to challenge statism\n- #### **Historical Examples and Case Studies**\n\t- **The American Revolution**\n\t\t- A secessionist movement based on libertarian principles\n\t\t- Lessons for contemporary libertarians\n\t- **The Rise and Fall of Classical Liberalism**\n\t\t- Factors contributing to the decline of liberalism\n\t\t- The role of intellectual errors and compromises\n\t- **The Failure of Socialist Experiments**\n\t\t- Economic and social consequences of central planning\n\t\t- Lessons for contemporary welfare states\n\t- **The Swiss Model**\n\t\t- Decentralized political system\n\t\t- Cantons and their autonomy\n\t\t- Limited immigration and its effects\n\t- **Medieval Cities**\n\t\t- Free cities as examples of stateless order\n\t\t- Importance of private law and voluntary associations\n- ### Practical Strategies for Change\n- #### **Education and Outreach**\n\t- Promoting libertarian ideas through various media\n\t- Engaging in intellectual debate and discourse\n\t- Challenging the dominant statist narrative\n- #### **Building Parallel Structures**\n\t- Creating alternative institutions outside the state\n\t- Supporting private education, healthcare, and security services\n\t- Developing free-market solutions to social problems\n- #### **Political Activism**\n\t- Supporting political candidates who advocate for limited government\n\t- Lobbying for policy changes that reduce state power\n\t- Engaging in peaceful civil disobedience\n- #### **Economic Action**\n\t- Promoting entrepreneurship and free enterprise\n\t- Supporting businesses that operate outside the state's control\n\t- Utilizing alternative currencies and financial systems\n- #### **Community Building**\n\t- Fostering voluntary associations and social networks\n\t- Creating intentional communities based on libertarian principles\n\t- Supporting local autonomy and self-governance\n- ### Advanced Considerations and Responses to Potential Criticisms\n- #### **Addressing Criticisms of Anarcho-Capitalism**\n\t- **The Problem of \"Market Failure\"**\n\t\t- Reframing externalities as property rights violations\n\t\t- Internalizing costs through clearly defined property rights\n\t\t- Role of arbitration and restitution in resolving disputes\n\t- **The Issue of Monopolies**\n\t\t- Distinguishing between coercive and market monopolies\n\t\t- Competition as a dynamic process\n\t\t- The role of consumer choice in limiting monopoly power\n\t- **Dealing with Predatory Behavior**\n\t\t- Incentives for private security agencies to prevent crime\n\t\t- The role of reputation and social ostracism\n\t\t- Restitution and punishment in a stateless society\n- #### **The Transition to a Stateless Society**\n\t- **Gradualism vs. Radical Change**\n\t\t- Strategies for reducing state power incrementally\n\t\t- The dangers of gradualism\n\t- **The Role of Public Opinion**\n\t\t- Importance of changing hearts and minds\n\t\t- Delegitimizing the state and its actions\n\t- **The Problem of \"Second Best\"**\n\t\t- Navigating a non-ideal world\n\t\t- Prioritizing reforms that maximize liberty\n- #### **Addressing Criticisms of Secession**\n\t- **Potential for Instability and Conflict**\n\t\t- Importance of peaceful and orderly secession\n\t\t- Role of negotiation and compromise\n\t- **Economic Viability of Small Political Units**\n\t\t- Benefits of free trade and economic integration\n\t\t- Examples of successful small states\n\t- **Dealing with External Threats**\n\t\t- Role of private defense alliances\n\t\t- Deterrence through economic and social strength\n- #### **The Importance of Intellectual Entrepreneurship**\n\t- **Developing and Refining Libertarian Theory**\n\t\t- Addressing unanswered questions and challenges\n\t\t- Integrating insights from other disciplines\n\t- **Communicating Libertarian Ideas**\n\t\t- Reaching a wider audience\n\t\t- Engaging in public discourse and debate\n\t- **Building a Movement for Liberty**\n\t\t- Fostering a culture of liberty\n\t\t- Supporting organizations and institutions that promote libertarian values\n- #### **Long-Term Vision**\n\t- **A World of Voluntary Communities**\n\t\t- Diverse social and legal systems\n\t\t- Peaceful coexistence and cooperation\n\t- **The Flourishing of Human Creativity and Innovation**\n\t\t- Unleashing the potential of free markets and free minds\n\t\t- Solving social problems through voluntary action\n\t- **A Society Based on Respect for Individual Rights**\n\t\t- Protection of life, liberty, and property\n\t\t- The triumph of reason and persuasion over force and coercion\n- ### Conclusion\n- #### **The Importance of Ideas**\n\t- Ideas as the driving force of history\n\t- The power of ideas to shape social and political outcomes\n- #### **The Need for Courage and Conviction**\n\t- Standing up for what is right, even when it is unpopular\n\t- Challenging the status quo and promoting a better future\n- #### **The Promise of Liberty**\n\t- A future of peace, prosperity, and individual flourishing\n\t- A society where individuals are free to pursue their own goals and dreams\n\t- A world where cooperation replaces conflict and voluntary action replaces coercion\n- #### **Call to Action**\n\t- Embrace the principles of liberty and property rights\n\t- Work towards a free society through education, activism, and community building\n\t- Never give up hope for a better future\n- **The Tension:**\n- **Libertarianism/Anarcho-capitalism:** Emphasizes individual liberty, private property, and minimal to no state intervention. This seemingly clashes with the idea of strong border controls, which traditionally require state enforcement.\n- **Strong Borders:** Implies a centralized authority (typically the state) controlling who and what enters a territory. This seems to contradict the libertarian ideal of minimal state intervention.\n- **Local Collective Action:** While local communities can establish rules and norms, they might lack the resources and authority to enforce them effectively against external pressures, especially concerning immigration.\n  \n  **Hoppe's Proposed Solution: Covenant Communities and Private Property Rights**\n  \n  Hoppe's solution is to fully embrace private property rights and extend them to their logical conclusion. He argues that the problem isn't immigration itself, but **forced integration** resulting from:\n- **Public Property:** The existence of public property (roads, parks, etc.) means that once someone is inside a country's borders, they can move relatively freely, potentially ending up in places where they are not wanted.\n- **Centralized State Control:** A central government's immigration policy is a one-size-fits-all approach that does not respect the diverse preferences of individual property owners and communities.\n  \n  **Hoppe's proposed solution rests on these pillars:**\n- **Radical Decentralization and Secession:** Hoppe advocates for radical decentralization, even down to the level of towns, villages, or even individual neighborhoods. This allows for a greater diversity of rules and preferences to be expressed and enforced.\n- **Privatization of \"Public\" Property:** He argues that all land, including roads, should be privately owned. This eliminates the commons problem associated with public property and allows for genuine control over entry and access.\n- **Covenant Communities:** In a stateless society, or even in a society with a drastically reduced state, communities would be formed based on voluntary agreements (covenants) between property owners. These covenants would specify the rules of the community, including who is allowed to enter, reside, or do business there.\n- **Private Security and Defense:** Private security agencies, funded voluntarily by property owners, would enforce the rules of the covenant, including those related to immigration.\n  \n  **How it would work in practice:**\n- **Immigration by Invitation Only:** Individuals could only immigrate to a specific community if they were invited by a property owner within that community. This could involve employment contracts, rental agreements, or other forms of sponsorship.\n- **Enforcement by Private Agencies:** Private security agencies, hired by property owners or associations, would be responsible for enforcing the community's rules, including expelling those who violate the terms of their entry or stay.\n- **Discrimination as a Right:** Property owners would have the right to discriminate based on any criteria they choose when deciding whom to invite or allow onto their property. This could include factors such as skills, cultural background, or even personal preferences.\n- **No \"Right\" to Free Movement:** There would be no inherent right to move freely across different communities. Movement would be contingent on the consent of the property owners in each area.\n  \n  **Hoppe's Argument for Consistency:**\n  \n  Hoppe argues that this system is the only one truly consistent with libertarian principles because it:\n- **Respects Property Rights:** It upholds the absolute right of property owners to control their property, including who is allowed on it.\n- **Eliminates Forced Integration:** It prevents individuals from being forced to associate with others they deem undesirable.\n- **Minimizes State Power:** It removes the state from the business of immigration control, placing it in the hands of private individuals and communities.\n- Hoppe's proposal is highly controversial, even within libertarian circles. Some common criticisms include:\n- **Feasibility:** Critics question whether such a system could be implemented in practice, especially in a world with existing states and large-scale migration pressures.\n- **Potential for Abuse:** Concerns exist that private security agencies could become too powerful and oppressive, potentially replicating the problems of the state.\n- **Discrimination and Inequality:** The system could lead to significant social stratification and discrimination based on wealth, ethnicity, or other factors.\n- **Lack of Uniformity:** Critics argue that a patchwork of different rules and enforcement mechanisms could lead to chaos and conflict.\n  \n  **In conclusion, Hoppe's solution to the tension between free immigration and small government is to advocate for a radical form of libertarianism where private property rights are absolute and extend to all aspects of social life, including immigration control. He believes that only through such a system can individual liberty and voluntary association be truly protected.**\n\n## Current Landscape (2025)\n\n- Industry adoption and implementations\n  - Metaverse platforms continue to evolve with focus on interoperability and open standards\n  - Web3 integration accelerating with decentralised identity and asset ownership\n  - Enterprise adoption growing in virtual collaboration, training, and digital twins\n  - UK companies increasingly active in metaverse development and immersive technologies\n\n- Technical capabilities\n  - Real-time rendering at photorealistic quality levels\n  - Low-latency networking enabling seamless multi-user experiences\n  - AI-driven content generation and procedural world building\n  - Spatial audio and haptics enhancing immersion\n\n- UK and North England context\n  - Manchester: Digital Innovation Factory supports metaverse startups and research\n  - Leeds: Holovis leads in immersive experiences for entertainment and training\n  - Newcastle: University research in spatial computing and interactive systems\n  - Sheffield: Advanced manufacturing using digital twin technology\n\n- Standards and frameworks\n  - Metaverse Standards Forum driving interoperability protocols\n  - WebXR enabling browser-based immersive experiences\n  - glTF and USD for 3D asset interchange\n  - Open Metaverse Interoperability Group defining cross-platform standards\n\n## Metadata\n\n- **Last Updated**: 2025-11-16\n- **Review Status**: Automated remediation with 2025 context\n- **Verification**: Academic sources verified\n- **Regional Context**: UK/North England where applicable",
  "properties": {
    "id": "libertarian-thesis-owl-axioms",
    "collapsed": "true",
    "- ontology": "true",
    "- term-id": "mv-447598994019",
    "- preferred-term": "Libertarian thesis",
    "- source-domain": "metaverse",
    "- status": "active",
    "- public-access": "true",
    "- definition": "A component of the metaverse ecosystem focusing on libertarian thesis.",
    "- maturity": "mature",
    "- authority-score": "0.85",
    "- owl:class": "mv:LibertarianThesis",
    "- owl:physicality": "ConceptualEntity",
    "- owl:role": "Concept",
    "- belongsToDomain": "[[MetaverseDomain]]",
    "- enables": "[[ImmersiveExperience]], [[Presence]], [[SpatialComputing]]",
    "- requires": "[[DisplayTechnology]], [[TrackingSystem]], [[RenderingEngine]]",
    "- bridges-to": "[[HumanComputerInteraction]], [[ComputerVision]], [[Robotics]]"
  },
  "backlinks": [],
  "wiki_links": [
    "TrackingSystem",
    "ImmersiveExperience",
    "ComputerVision",
    "RenderingEngine",
    "SpatialComputing",
    "Robotics",
    "HumanComputerInteraction",
    "MetaverseDomain",
    "DisplayTechnology",
    "Presence"
  ],
  "ontology": {
    "term_id": "mv-447598994019",
    "preferred_term": "Libertarian thesis",
    "definition": "A component of the metaverse ecosystem focusing on libertarian thesis.",
    "source_domain": "metaverse",
    "maturity_level": null,
    "authority_score": 0.85
  }
}