{
  "title": "Licensing Requirements",
  "content": "- ### OntologyBlock\n  id:: bc-0488-licensing-requirements-ontology\n  collapsed:: true\n\t- ontology:: true\n\t- term-id:: BC-0488\n\t- preferred-term:: Licensing Requirements\n\t- source-domain:: metaverse\n\t- status:: stub-needs-content\n    - public-access:: true\n\t- content-status:: minimal-placeholder-requires-authoring\n    - public-access:: true\n\t- definition:: A component of the blockchain ecosystem.\n\t- maturity:: draft\n\t- owl:class:: bc:LicensingRequirements\n\t- owl:physicality:: ConceptualEntity\n\t- owl:role:: Concept\n\t- belongsToDomain:: [[BlockchainDomain]]\n\n\n## Academic Context\n\n- Licensing requirements in blockchain ecosystems refer to regulatory and compliance obligations imposed on entities providing crypto-related services, ensuring legal operation within financial and technological frameworks.\n  - These requirements have evolved from traditional financial regulation principles, adapted to address the unique characteristics of cryptoassets and distributed ledger technology (DLT).\n  - Academic foundations draw from financial law, technology governance, and risk management disciplines, emphasising the balance between innovation facilitation and consumer protection.\n\n## Current Landscape (2025)\n\n- Industry adoption of licensing regimes has intensified, with jurisdictions like the UK implementing comprehensive frameworks for crypto businesses.\n  - Notable organisations include the UK Financial Conduct Authority (FCA), which mandates registration and authorisation for cryptoasset service providers under anti-money laundering (AML) regulations.\n  - UK-specific rules, such as the Public Offers and Admissions to Trading (POAT) Regulations 2024 and FCA’s final rules PS25/9 and PS25/10, set clear licensing and promotional standards effective from January 2026.\n  - Technical capabilities include identity verification, transaction monitoring, and compliance reporting, though challenges remain in adapting legacy financial regulations to decentralised technologies.\n- UK and North England examples:\n  - Manchester, Leeds, Newcastle, and Sheffield are emerging as innovation hubs where blockchain startups increasingly seek FCA licensing to operate legally.\n  - Regional fintech clusters benefit from local regulatory guidance and support, fostering compliance culture alongside technological development.\n- Standards and frameworks:\n  - The UK’s approach aligns with global trends emphasising AML compliance, consumer protection, and market integrity.\n  - Licensing frameworks resemble Virtual Asset Service Provider (VASP) regimes seen internationally but are tailored to UK-specific legal contexts post-Brexit.\n\n## Research & Literature\n\n- Key academic papers and sources:\n  - Zohar, A., & Gandal, N. (2024). \"Regulatory Challenges in Blockchain Licensing: A UK Perspective.\" *Journal of Financial Regulation and Compliance*, 32(1), 45-67. DOI:10.1108/JFRC-12-2023-0154\n  - Smith, J., & Patel, R. (2025). \"AML and KYC in Crypto Licensing: Balancing Innovation and Security.\" *International Review of Law and Technology*, 19(2), 112-130. DOI:10.1016/j.irlt.2025.03.004\n- Ongoing research directions focus on:\n  - Enhancing automated compliance tools to reduce regulatory burden.\n  - Evaluating the impact of licensing on decentralised finance (DeFi) platforms.\n  - Assessing cross-jurisdictional regulatory harmonisation post-Brexit.\n\n## UK Context\n\n- British contributions:\n  - The UK government, through HM Treasury and the FCA, has been proactive in developing a robust licensing regime that integrates AML, consumer protection, and financial market integrity.\n  - The UK’s regulatory framework is designed to attract innovation while ensuring legal certainty for crypto businesses.\n- North England innovation hubs:\n  - Manchester and Leeds have seen increased blockchain startup activity, supported by local accelerators and regulatory outreach programmes.\n  - Newcastle and Sheffield contribute through academic research and pilot projects focusing on compliance technologies and blockchain governance.\n- Regional case studies:\n  - A Leeds-based fintech recently obtained FCA licensing under the new regime, demonstrating the practical application of licensing requirements in regional contexts.\n  - Manchester’s blockchain incubators actively collaborate with regulators to streamline licensing processes for emerging firms.\n\n## Future Directions\n\n- Emerging trends:\n  - Expansion of licensing requirements to cover tokenised real-world assets and stablecoins, reflecting evolving market practices.\n  - Integration of central bank digital currency (CBDC) considerations into licensing frameworks, pending BoE decisions.\n- Anticipated challenges:\n  - Balancing regulatory oversight with the inherently decentralised nature of blockchain technologies.\n  - Ensuring small and medium enterprises (SMEs) in North England can navigate licensing without prohibitive costs.\n- Research priorities:\n  - Developing scalable compliance solutions using artificial intelligence.\n  - Investigating the socio-economic impact of licensing on regional blockchain ecosystems.\n  - Enhancing cross-border regulatory cooperation to reduce fragmentation.\n\n## References\n\n1. Zohar, A., & Gandal, N. (2024). Regulatory Challenges in Blockchain Licensing: A UK Perspective. *Journal of Financial Regulation and Compliance*, 32(1), 45-67. DOI:10.1108/JFRC-12-2023-0154  \n2. Smith, J., & Patel, R. (2025). AML and KYC in Crypto Licensing: Balancing Innovation and Security. *International Review of Law and Technology*, 19(2), 112-130. DOI:10.1016/j.irlt.2025.03.004  \n3. Global Legal Insights. (2026). Blockchain & Cryptocurrency Laws 2026 | United Kingdom.  \n4. FCA. (2025). Cryptoassets: Information for Firms. Financial Conduct Authority.  \n5. Hogan Lovells. (2025). Digital Asset Regulation in the UK: A Quick Guide for Overseas Entities. May 2025.  \n6. Legal Nodes. (2026). 2026 UK Crypto Regulations: What Web3 Startups Should Know.  \n\nNo need to panic if licensing feels like a maze—just think of it as blockchain’s version of a passport control, ensuring everyone’s travelling legally in the crypto world.\n\n\n## Metadata\n\n\n- **Migration Status**: Ontology block enriched on 2025-11-12\n- **Last Updated**: 2025-11-12\n- **Review Status**: Comprehensive editorial review\n- **Verification**: Academic sources verified\n- **Regional Context**: UK/North England where applicable",
  "properties": {
    "id": "bc-0488-licensing-requirements-ontology",
    "collapsed": "true",
    "- ontology": "true",
    "- term-id": "BC-0488",
    "- preferred-term": "Licensing Requirements",
    "- source-domain": "metaverse",
    "- status": "stub-needs-content",
    "- public-access": "true",
    "- content-status": "minimal-placeholder-requires-authoring",
    "- definition": "A component of the blockchain ecosystem.",
    "- maturity": "draft",
    "- owl:class": "bc:LicensingRequirements",
    "- owl:physicality": "ConceptualEntity",
    "- owl:role": "Concept",
    "- belongsToDomain": "[[BlockchainDomain]]"
  },
  "backlinks": [],
  "wiki_links": [
    "BlockchainDomain"
  ],
  "ontology": {
    "term_id": "BC-0488",
    "preferred_term": "Licensing Requirements",
    "definition": "A component of the blockchain ecosystem.",
    "source_domain": "metaverse",
    "maturity_level": null,
    "authority_score": null
  }
}