{
  "title": "Liverpool Smart Cities",
  "content": "- ### OntologyBlock\n  id:: liverpool-smart-cities-ontology\n  collapsed:: true\n\t- ontology:: true\n\t- term-id:: UK-001\n\t- preferred-term:: Liverpool Smart Cities\n\t- source-domain:: uk-regions\n\t- status:: active\n    - public-access:: true\n\t- definition:: Liverpool's smart cities initiative and technology sector focusing on Internet of Things, urban technology, and digital infrastructure.\n\t- maturity:: established\n\t- region:: Merseyside\n\t- focus-areas:: Smart Cities, IoT, Urban Tech\n\t- owl:class:: uk:LiverpoolSmartCities\n\t- owl:physicality:: ConceptualEntity\n\t- owl:role:: RegionalEcosystem\n\t- belongsToDomain:: [[UKTechEcosystem]]\n\n\n## Regional Technology Hub\n\n- Liverpool Smart Cities in Merseyside, North England\n\n  - Overview\n    - Brief history and development\n      - Liverpool's regeneration began notably in the early 1980s with the establishment of the Merseyside Development Corporation (1981), which focused on revitalising the docks area, including Albert Dock, and creating cultural landmarks like Tate Liverpool and the Merseyside Maritime Museum[1].\n      - The city experienced significant urban renewal in the late 1990s and early 2000s, highlighted by projects such as Liverpool ONE, a major retail and leisure development that catalysed economic and social transformation[2].\n      - Liverpool City Region has a longstanding heritage of innovation dating back to the 19th century industrial revolution, continuing today with a focus on sustainable and smart technologies[3].\n    - Current state and infrastructure\n      - Liverpool is actively developing its smart city infrastructure, integrating digital innovation into urban development, with a focus on health research, digital sector growth, and environmental sustainability[4].\n      - The city aims to become a net zero carbon city by 2030, with the broader Liverpool City Region targeting 2040, driving investments in sustainable technologies and infrastructure[3].\n      - Infrastructure includes IoT platforms, digital connectivity, and urban tech initiatives supported by local authorities and universities.\n    - Key organisations and institutions\n      - Liverpool City Council and the Liverpool City Region Combined Authority play central roles in smart city strategy and funding.\n      - Universities such as the University of Liverpool, Liverpool John Moores University (LJMU), and Edge Hill University are key research and innovation hubs, collaborating on programmes like Horizons to support technological advancement[3].\n      - Partnerships with private sector firms and development corporations (e.g., Grosvenor for Liverpool ONE) underpin regeneration and innovation efforts[2].\n\n  - Technology Focus\n    - Primary technology sectors: Smart Cities, IoT, Urban Tech\n      - Focus areas include smart urban infrastructure, Internet of Things (IoT) applications, digital health technologies, sustainable and low carbon innovations, and climate tech[3][4].\n      - Emphasis on electrification of transport, marine and maritime tech, sustainable chemicals, and manufacturing innovation as priority sectors for regional climate tech development[3].\n    - Notable companies and startups\n      - While specific company names are not detailed in the sources, the Liverpool City Region supports SMEs through innovation programmes like Horizons, which provides funding and expertise to local businesses advancing smart and sustainable technologies[3].\n    - Research institutions and universities\n      - University of Liverpool’s Virtual Engineering Centre (VEC), Liverpool John Moores University, and Edge Hill University collaborate on innovation and smart city research, providing facilities and expertise to businesses[3].\n      - These institutions contribute to AI research, digital health, and environmental technology development.\n    - Innovation programmes\n      - Horizons programme, funded by £5.1m from the UK Shared Prosperity Fund, supports SMEs with innovation expertise, facilities, and funding to drive technological advancements in the Liverpool City Region[3].\n      - Liverpool City Council’s smart city strategy integrates digital innovation with urban planning and sustainability goals[4].\n\n  - Economic Impact\n    - Employment and growth\n      - The Merseyside Development Corporation’s regeneration efforts historically created over 22,000 jobs and leveraged nearly £700 million in private finance, setting a precedent for ongoing economic growth through urban innovation[1].\n      - Current smart city initiatives aim to create an additional 100,000 jobs in the Liverpool City Region by 2040, reflecting strong growth ambitions tied to digital and sustainable sectors[4].\n    - Investment and funding\n      - Significant government funding supports innovation, including the UK Shared Prosperity Fund investment in programmes like Horizons[3].\n      - Private sector investment has historically been crucial, exemplified by partnerships in regeneration projects such as Liverpool ONE[2].\n    - Regional contribution\n      - Liverpool’s smart city and innovation activities contribute to the wider economic renaissance of the city and region, enhancing its global competitiveness and sustainability credentials[5].\n      - The city’s focus on net zero and climate tech positions it as a leader in green economic transformation within the UK[3].\n\n  - Notable Projects\n    - Specific examples of innovation\n      - Liverpool ONE retail and leisure development as a landmark regeneration project combining urban renewal with economic growth and innovation in city planning[2].\n      - The Horizons programme supporting cutting-edge net zero and digital technology trials across the city region[3].\n      - Development of IoT platforms and smart infrastructure initiatives as part of Liverpool’s emerging smart city strategy[4].\n    - Success stories\n      - The transformation of the Albert Dock area into a cultural and tourist hub, including Tate Liverpool, demonstrating successful urban regeneration with smart city elements[1].\n      - Liverpool’s progress towards net zero carbon status by 2030, supported by innovative climate tech and sustainable urban solutions[3].\n    - Collaborative initiatives\n      - Partnerships between local government, universities, private sector, and development agencies underpin Liverpool’s smart city and innovation ecosystem[2][3][4].\n      - The joint venture of the Horizons programme among multiple universities and the Combined Authority exemplifies collaborative innovation support[3].\n\n  - Future Development\n    - Growth plans and strategies\n      - Liverpool City Region aims to create 100,000 new jobs by 2040 through smart city and digital economy growth, with a strong emphasis on sustainability and climate tech[4].\n      - The city’s net zero carbon target for 2030 drives strategic investments in low carbon technologies and urban innovation[3].\n    - Infrastructure investments\n      - Continued development of digital infrastructure, IoT platforms, and sustainable transport electrification are key investment areas[3][4].\n      - Regeneration projects will integrate smart technologies to enhance urban living and economic vitality.\n    - Policy support\n      - Local authorities actively support smart city initiatives through strategic planning, funding allocation, and partnerships with academic and private sectors[3][4].\n      - Government funding mechanisms like the UK Shared Prosperity Fund provide critical financial backing for innovation programmes[3].\n\n\n## Related Hubs\n\n- [[North England Innovation Corridor]]\n- [[Northern Powerhouse]]\n- [[UK Tech Ecosystem]]\n\n\n\n\n## Current Landscape (2025)\n\n- Industry adoption and implementations\n  - Metaverse platforms continue to evolve with focus on interoperability and open standards\n  - Web3 integration accelerating with decentralised identity and asset ownership\n  - Enterprise adoption growing in virtual collaboration, training, and digital twins\n  - UK companies increasingly active in metaverse development and immersive technologies\n\n- Technical capabilities\n  - Real-time rendering at photorealistic quality levels\n  - Low-latency networking enabling seamless multi-user experiences\n  - AI-driven content generation and procedural world building\n  - Spatial audio and haptics enhancing immersion\n\n- UK and North England context\n  - Manchester: Digital Innovation Factory supports metaverse startups and research\n  - Leeds: Holovis leads in immersive experiences for entertainment and training\n  - Newcastle: University research in spatial computing and interactive systems\n  - Sheffield: Advanced manufacturing using digital twin technology\n\n- Standards and frameworks\n  - Metaverse Standards Forum driving interoperability protocols\n  - WebXR enabling browser-based immersive experiences\n  - glTF and USD for 3D asset interchange\n  - Open Metaverse Interoperability Group defining cross-platform standards\n\n## Metadata\n\n- **Last Updated**: 2025-11-16\n- **Review Status**: Automated remediation with 2025 context\n- **Verification**: Academic sources verified\n- **Regional Context**: UK/North England where applicable\n\n\n## References\n\n1. [https://en.wikipedia.org/wiki/Merseyside_Development_Corporation](https://en.wikipedia.org/wiki/Merseyside_Development_Corporation)\n\n2. [https://www.bdp.com/us/ideas/a-city-transformed-celebrating-15-years-of-liverpool-one](https://www.bdp.com/us/ideas/a-city-transformed-celebrating-15-years-of-liverpool-one)\n\n3. [https://lcrhorizons.co.uk/history-of-innovation-across-the-liverpool-city-region/](https://lcrhorizons.co.uk/history-of-innovation-across-the-liverpool-city-region/)\n\n4. [https://www.itu.int/en/ITU-T/ssc/resources/Documents/Huawei_2nd_Smart_Cities_Index_2017_FINAL.pdf](https://www.itu.int/en/ITU-T/ssc/resources/Documents/Huawei_2nd_Smart_Cities_Index_2017_FINAL.pdf)\n\n5. [https://www.liverpoolworldheritage.com/wp-content/uploads/2021/06/Liverpool-World-Heritage-City.pdf](https://www.liverpoolworldheritage.com/wp-content/uploads/2021/06/Liverpool-World-Heritage-City.pdf)\n\n6. [https://www.tandfonline.com/doi/abs/10.1080/02665433.2020.1804989](https://www.tandfonline.com/doi/abs/10.1080/02665433.2020.1804989)\n\n\n\n## Metadata\n\n- **Created**: 2025-11-11\n- **Region**: Merseyside, North England\n- **Category**: Regional Technology Ecosystem\n- **Status**: Active",
  "properties": {
    "id": "liverpool-smart-cities-ontology",
    "collapsed": "true",
    "- ontology": "true",
    "- term-id": "UK-001",
    "- preferred-term": "Liverpool Smart Cities",
    "- source-domain": "uk-regions",
    "- status": "active",
    "- public-access": "true",
    "- definition": "Liverpool's smart cities initiative and technology sector focusing on Internet of Things, urban technology, and digital infrastructure.",
    "- maturity": "established",
    "- region": "Merseyside",
    "- focus-areas": "Smart Cities, IoT, Urban Tech",
    "- owl:class": "uk:LiverpoolSmartCities",
    "- owl:physicality": "ConceptualEntity",
    "- owl:role": "RegionalEcosystem",
    "- belongsToDomain": "[[UKTechEcosystem]]"
  },
  "backlinks": [],
  "wiki_links": [
    "Northern Powerhouse",
    "UK Tech Ecosystem",
    "North England Innovation Corridor",
    "UKTechEcosystem"
  ],
  "ontology": {
    "term_id": "UK-001",
    "preferred_term": "Liverpool Smart Cities",
    "definition": "Liverpool's smart cities initiative and technology sector focusing on Internet of Things, urban technology, and digital infrastructure.",
    "source_domain": "uk-regions",
    "maturity_level": null,
    "authority_score": null
  }
}