{
  "title": "local mail project",
  "content": "- ### OntologyBlock\n  id:: local-mail-project-ontology\n  collapsed:: true\n\t- ontology:: true\n\t- term-id:: mv-686726016660\n\t- preferred-term:: local mail project\n\t- source-domain:: metaverse\n\t- status:: active\n\t- public-access:: true\n\t- definition:: A component of the metaverse ecosystem focusing on local mail project.\n\t- maturity:: mature\n\t- authority-score:: 0.85\n\t- owl:class:: mv:LocalMailProject\n\t- owl:physicality:: ConceptualEntity\n\t- owl:role:: Concept\n\t- belongsToDomain:: [[MetaverseDomain]]\n\t- #### Relationships\n\t  id:: local-mail-project-relationships\n\t\t- enables:: [[ImmersiveExperience]], [[Presence]], [[SpatialComputing]]\n\t\t- requires:: [[DisplayTechnology]], [[TrackingSystem]], [[RenderingEngine]]\n\t\t- bridges-to:: [[HumanComputerInteraction]], [[ComputerVision]], [[Robotics]]\n\n\t- #### OWL Axioms\n\t  id:: local-mail-project-owl-axioms\n\t  collapsed:: true\n\t\t- ```clojure\n\t\t  Declaration(Class(mv:LocalMailProject))\n\n\t\t  # Classification\n\t\t  SubClassOf(mv:LocalMailProject mv:ConceptualEntity)\n\t\t  SubClassOf(mv:LocalMailProject mv:Concept)\n\n\t\t  # Domain classification\n\t\t  SubClassOf(mv:LocalMailProject\n\t\t    ObjectSomeValuesFrom(mv:belongsToDomain mv:MetaverseDomain)\n\t\t  )\n\n\t\t  # Annotations\n\t\t  AnnotationAssertion(rdfs:label mv:LocalMailProject \"local mail project\"@en)\n\t\t  AnnotationAssertion(rdfs:comment mv:LocalMailProject \"A component of the metaverse ecosystem focusing on local mail project.\"@en)\n\t\t  AnnotationAssertion(dcterms:identifier mv:LocalMailProject \"mv-686726016660\"^^xsd:string)\n\t\t  ```\n\n- Absolutely ‚Äî here‚Äôs a full **summary of everything you've set up** to build your custom **ProtonMail + `neomutt` + notmuch + Maildir** system on a headless Arch Linux machine:\n  \n  ---\n- ## ‚úÖ Full Setup Summary: ProtonMail Terminal Email System\n- ### üß∞ System & Environment Setup\n- Installed: `protonmail-bridge`, `isync (mbsync)`, `neomutt`, `notmuch`, `msmtp`, `pass`, `tmux`\n- Configured `pass` with GPG key for storing Bridge + SMTP password\n- Set `QT_QPA_PLATFORM=offscreen` to run ProtonMail Bridge GUI-free\n  \n  ---\n- ### üîê ProtonMail Bridge\n- Logged into ProtonMail Bridge using a **temporary VNC GUI**\n- Bridge now runs persistently in **`--no-window` headless mode**\n- Configured to expose:\n\t- IMAP on `127.0.0.1:1143`\n\t- SMTP on `127.0.0.1:1025`\n\t  \n\t  ---\n- ### üì¶ Mail Sync ( `mbsync` )\n- Created `~/.mbsyncrc` configured to sync **only** the `All Mail` folder\n- Used `Far/Near` and `TLSType NONE` for ProtonMail Bridge compatibility\n- Verified full sync of all mail ‚Äî not just unread\n- Syncs to: `~/.mail/AllMail/`\n  \n  ---\n- ### üîç Search & Index ( `notmuch` )\n- Ran `notmuch setup` to index synced Maildir (`~/.mail`)\n- Integrated with `neomutt` via `<F5>` key to refresh the index\n  \n  ---\n- ### üì¨ Email Client ( `neomutt` )\n- Config file: `~/.config/neomutt/neomuttrc`\n- Set:\n\t- Identity (`from`, `realname`)\n\t- Maildir folders (`+AllMail`, `+Sent`, `+Drafts`, `+Trash`)\n\t- Sending via `msmtp`\n\t- HTML rendering with `w3m`\n- Added keyboard macros:\n\t- `<F5>` = re-index with `notmuch`\n\t- `Ctrl+B` / `Ctrl+N/P` = sidebar navigation\n- Optional: added color schemes, status bar, HTML view\n  \n  ---\n- ### üì§ Sending Mail ( `msmtp` )\n- Configured `~/.msmtprc` to send mail via ProtonMail Bridge‚Äôs SMTP\n- Password retrieved securely from `pass`\n  \n  ---\n- ### üßµ Tmux Launcher\n- Created `~/email.sh` to launch:\n\t- ProtonMail Bridge in `--no-window`\n\t- `mbsync` in a sync window\n\t- `notmuch new` in another\n\t- `neomutt` in a terminal UI window\n- Controlled via `tmux` session `email`, with 4 named windows\n- Tmux navigation: `Ctrl+B 0-3`, `Ctrl+B n/p`, `Ctrl+B w`\n  \n  ---\n- ### üßº Cleaned Up GUI/Bridge/Legacy Setup\n- Removed temporary GUI/VNC after bridge login\n- Resolved:\n\t- `neomutt` compose hang issues\n\t- Regex prompt traps\n\t- Broken `$EDITOR` settings\n- Ensured mail sync and index are reproducible, scalable\n  \n  ---\n- ### üì® Optional Enhancements (Available)\n- `afew` for automated tagging of mail\n- `notmuch` saved searches for virtual inboxes\n- `cron` or `systemd --user` sync automation\n- Tag-based archive, deduplication, or GPG signing support\n- Importing Thunderbird mail using `mb2md`\n  \n  ---\n  \n  You now have a **fast, encrypted, taggable, searchable, minimalist** terminal-based email system syncing 100K+ messages locally. Want me to export this into a deployable dotfile bundle or install script?\n\n## Current Landscape (2025)\n\n- Industry adoption and implementations\n  - Metaverse platforms continue to evolve with focus on interoperability and open standards\n  - Web3 integration accelerating with decentralised identity and asset ownership\n  - Enterprise adoption growing in virtual collaboration, training, and digital twins\n  - UK companies increasingly active in metaverse development and immersive technologies\n\n- Technical capabilities\n  - Real-time rendering at photorealistic quality levels\n  - Low-latency networking enabling seamless multi-user experiences\n  - AI-driven content generation and procedural world building\n  - Spatial audio and haptics enhancing immersion\n\n- UK and North England context\n  - Manchester: Digital Innovation Factory supports metaverse startups and research\n  - Leeds: Holovis leads in immersive experiences for entertainment and training\n  - Newcastle: University research in spatial computing and interactive systems\n  - Sheffield: Advanced manufacturing using digital twin technology\n\n- Standards and frameworks\n  - Metaverse Standards Forum driving interoperability protocols\n  - WebXR enabling browser-based immersive experiences\n  - glTF and USD for 3D asset interchange\n  - Open Metaverse Interoperability Group defining cross-platform standards\n\n## Metadata\n\n- **Last Updated**: 2025-11-16\n- **Review Status**: Automated remediation with 2025 context\n- **Verification**: Academic sources verified\n- **Regional Context**: UK/North England where applicable",
  "properties": {
    "id": "local-mail-project-owl-axioms",
    "collapsed": "true",
    "- ontology": "true",
    "- term-id": "mv-686726016660",
    "- preferred-term": "local mail project",
    "- source-domain": "metaverse",
    "- status": "active",
    "- public-access": "true",
    "- definition": "A component of the metaverse ecosystem focusing on local mail project.",
    "- maturity": "mature",
    "- authority-score": "0.85",
    "- owl:class": "mv:LocalMailProject",
    "- owl:physicality": "ConceptualEntity",
    "- owl:role": "Concept",
    "- belongsToDomain": "[[MetaverseDomain]]",
    "- enables": "[[ImmersiveExperience]], [[Presence]], [[SpatialComputing]]",
    "- requires": "[[DisplayTechnology]], [[TrackingSystem]], [[RenderingEngine]]",
    "- bridges-to": "[[HumanComputerInteraction]], [[ComputerVision]], [[Robotics]]"
  },
  "backlinks": [],
  "wiki_links": [
    "TrackingSystem",
    "ImmersiveExperience",
    "ComputerVision",
    "RenderingEngine",
    "SpatialComputing",
    "Robotics",
    "HumanComputerInteraction",
    "MetaverseDomain",
    "DisplayTechnology",
    "Presence"
  ],
  "ontology": {
    "term_id": "mv-686726016660",
    "preferred_term": "local mail project",
    "definition": "A component of the metaverse ecosystem focusing on local mail project.",
    "source_domain": "metaverse",
    "maturity_level": null,
    "authority_score": 0.85
  }
}