{
  "title": "Logseq",
  "content": "- ### OntologyBlock\n  id:: logseq-ontology\n  collapsed:: true\n\t- ontology:: true\n\t- term-id:: mv-183430311235\n\t- preferred-term:: Logseq\n\t- source-domain:: metaverse\n\t- status:: active\n\t- public-access:: true\n\t- definition:: A component of the metaverse ecosystem focusing on logseq.\n\t- maturity:: mature\n\t- authority-score:: 0.85\n\t- owl:class:: mv:Logseq\n\t- owl:physicality:: ConceptualEntity\n\t- owl:role:: Concept\n\t- belongsToDomain:: [[MetaverseDomain]]\n\t- #### Relationships\n\t  id:: logseq-relationships\n\t\t- enables:: [[ImmersiveExperience]], [[Presence]], [[SpatialComputing]]\n\t\t- requires:: [[DisplayTechnology]], [[TrackingSystem]], [[RenderingEngine]]\n\t\t- bridges-to:: [[HumanComputerInteraction]], [[ComputerVision]], [[Robotics]]\n\n\t- #### OWL Axioms\n\t  id:: logseq-owl-axioms\n\t  collapsed:: true\n\t\t- ```clojure\n\t\t  Declaration(Class(mv:Logseq))\n\n\t\t  # Classification\n\t\t  SubClassOf(mv:Logseq mv:ConceptualEntity)\n\t\t  SubClassOf(mv:Logseq mv:Concept)\n\n\t\t  # Domain classification\n\t\t  SubClassOf(mv:Logseq\n\t\t    ObjectSomeValuesFrom(mv:belongsToDomain mv:MetaverseDomain)\n\t\t  )\n\n\t\t  # Annotations\n\t\t  AnnotationAssertion(rdfs:label mv:Logseq \"Logseq\"@en)\n\t\t  AnnotationAssertion(rdfs:comment mv:Logseq \"A component of the metaverse ecosystem focusing on logseq.\"@en)\n\t\t  AnnotationAssertion(dcterms:identifier mv:Logseq \"mv-183430311235\"^^xsd:string)\n\t\t  ```\n\n## Demos in Logseq\n\t- [[Large language models]] [Mixture of Mutli-LoRA local LLM](https://github.com/uukuguy/multi_loras?tab=readme-ov-file#mixture-of-multi-loras)]\n\t- [[ComfyUI]] [[Autogen]] demo?\n\t- [[ComfyUI]] LoRA training demo?\n\t- [[Node based visual interfaces]] demo for NFT creation?\n- docker web version [logseq/docs/docker-web-app-guide.md at master · logseq/logseq (github.com)](https://github.com/logseq/logseq/blob/master/docs/docker-web-app-guide.md)\n- [Custom Prompt for OCR Image using ocr.space · debanjandhar12/logseq-chatgpt-plugin · Discussion #26 (github.com)](https://github.com/debanjandhar12/logseq-chatgpt-plugin/discussions/26)\n- [ahonn/logseq-plugin-ai-assistant: A powerful tool that enhances your Logseq experience by allowing you to interact with AI models like OpenAI's gpt-3.5-turbo. (github.com)](https://github.com/ahonn/logseq-plugin-ai-assistant)\n-\n- # Plugin development\n\t- [LongarMD/logseq-plugin-gpt-generation (github.com)](https://github.com/LongarMD/logseq-plugin-gpt-generation)\n\t-\n-\n-\n\n## Current Landscape (2025)\n\n- Industry adoption and implementations\n  - Metaverse platforms continue to evolve with focus on interoperability and open standards\n  - Web3 integration accelerating with decentralised identity and asset ownership\n  - Enterprise adoption growing in virtual collaboration, training, and digital twins\n  - UK companies increasingly active in metaverse development and immersive technologies\n\n- Technical capabilities\n  - Real-time rendering at photorealistic quality levels\n  - Low-latency networking enabling seamless multi-user experiences\n  - AI-driven content generation and procedural world building\n  - Spatial audio and haptics enhancing immersion\n\n- UK and North England context\n  - Manchester: Digital Innovation Factory supports metaverse startups and research\n  - Leeds: Holovis leads in immersive experiences for entertainment and training\n  - Newcastle: University research in spatial computing and interactive systems\n  - Sheffield: Advanced manufacturing using digital twin technology\n\n- Standards and frameworks\n  - Metaverse Standards Forum driving interoperability protocols\n  - WebXR enabling browser-based immersive experiences\n  - glTF and USD for 3D asset interchange\n  - Open Metaverse Interoperability Group defining cross-platform standards\n\n## Metadata\n\n- **Last Updated**: 2025-11-16\n- **Review Status**: Automated remediation with 2025 context\n- **Verification**: Academic sources verified\n- **Regional Context**: UK/North England where applicable",
  "properties": {
    "id": "logseq-owl-axioms",
    "collapsed": "true",
    "- ontology": "true",
    "- term-id": "mv-183430311235",
    "- preferred-term": "Logseq",
    "- source-domain": "metaverse",
    "- status": "active",
    "- public-access": "true",
    "- definition": "A component of the metaverse ecosystem focusing on logseq.",
    "- maturity": "mature",
    "- authority-score": "0.85",
    "- owl:class": "mv:Logseq",
    "- owl:physicality": "ConceptualEntity",
    "- owl:role": "Concept",
    "- belongsToDomain": "[[MetaverseDomain]]",
    "- enables": "[[ImmersiveExperience]], [[Presence]], [[SpatialComputing]]",
    "- requires": "[[DisplayTechnology]], [[TrackingSystem]], [[RenderingEngine]]",
    "- bridges-to": "[[HumanComputerInteraction]], [[ComputerVision]], [[Robotics]]"
  },
  "backlinks": [
    "Knowledge Graphing",
    "Metaverse Ontology",
    "Introduction to me"
  ],
  "wiki_links": [
    "SpatialComputing",
    "HumanComputerInteraction",
    "MetaverseDomain",
    "ImmersiveExperience",
    "TrackingSystem",
    "Node based visual interfaces",
    "DisplayTechnology",
    "Autogen",
    "RenderingEngine",
    "Presence",
    "ComputerVision",
    "ComfyUI",
    "Robotics",
    "Large language models"
  ],
  "ontology": {
    "term_id": "mv-183430311235",
    "preferred_term": "Logseq",
    "definition": "A component of the metaverse ecosystem focusing on logseq.",
    "source_domain": "metaverse",
    "maturity_level": null,
    "authority_score": 0.85
  }
}