{
  "title": "LoRA DoRA etc",
  "content": "- ### OntologyBlock\n  id:: lora-dora-etc-ontology\n  collapsed:: true\n\t- ontology:: true\n\t- term-id:: mv-984612953767\n\t- preferred-term:: LoRA DoRA etc\n\t- source-domain:: metaverse\n\t- status:: active\n\t- public-access:: true\n\t- definition:: A component of the metaverse ecosystem focusing on lora dora etc.\n\t- maturity:: mature\n\t- authority-score:: 0.85\n\t- owl:class:: mv:LoraDoraEtc\n\t- owl:physicality:: ConceptualEntity\n\t- owl:role:: Concept\n\t- belongsToDomain:: [[MetaverseDomain]]\n\t- #### Relationships\n\t  id:: lora-dora-etc-relationships\n\t\t- enables:: [[ImmersiveExperience]], [[Presence]], [[SpatialComputing]]\n\t\t- requires:: [[DisplayTechnology]], [[TrackingSystem]], [[RenderingEngine]]\n\t\t- bridges-to:: [[HumanComputerInteraction]], [[ComputerVision]], [[Robotics]]\n\n\t- #### OWL Axioms\n\t  id:: lora-dora-etc-owl-axioms\n\t  collapsed:: true\n\t\t- ```clojure\n\t\t  Declaration(Class(mv:LoraDoraEtc))\n\n\t\t  # Classification\n\t\t  SubClassOf(mv:LoraDoraEtc mv:ConceptualEntity)\n\t\t  SubClassOf(mv:LoraDoraEtc mv:Concept)\n\n\t\t  # Domain classification\n\t\t  SubClassOf(mv:LoraDoraEtc\n\t\t    ObjectSomeValuesFrom(mv:belongsToDomain mv:MetaverseDomain)\n\t\t  )\n\n\t\t  # Annotations\n\t\t  AnnotationAssertion(rdfs:label mv:LoraDoraEtc \"LoRA DoRA etc\"@en)\n\t\t  AnnotationAssertion(rdfs:comment mv:LoraDoraEtc \"A component of the metaverse ecosystem focusing on lora dora etc.\"@en)\n\t\t  AnnotationAssertion(dcterms:identifier mv:LoraDoraEtc \"mv-984612953767\"^^xsd:string)\n\t\t  ```\n\npublic:: true\n\n-\n- This paper was submitted to arXiv on June 17, 2021. It proposes a method called **Low-Rank Adaptation, or LoRA, that reduces the number of trainable parameters for downstream tasks in natural language processing. LoRA injects trainable rank decomposition matrices into each layer of the Transformer architecture, which greatly reduces the number of trainable parameters. LoRA performs on-par or better than fine-tuning in model quality on RoBERTa, DeBERTa, GPT-2, and GPT-3, despite having fewer trainable parameters, a higher training throughput, and, unlike adapters, no additional inference latency (time to output). It also works for image diffusion.\n-\n- [Introducing DoRA, a High-Performing Alternative to LoRA for Fine-Tuning | NVIDIA Technical Blog](https://developer.nvidia.com/blog/introducing-dora-a-high-performing-alternative-to-lora-for-fine-tuning/)\n-\n- [catid/dora: Implementation of DoRA (github.com)](https://github.com/catid/dora) new kid?\n\t- ![GGd8HodXoAAL27r.png](../assets/GGd8HodXoAAL27r_1708191335486_0.png)\n-\n-\n-\n- [LoRA training scripts of the world, unite! (huggingface.co)](https://huggingface.co/blog/sdxl_lora_advanced_script)\n- [[2106.09685] LoRA: Low-Rank Adaptation of Large Language Models (arxiv.org)](https://arxiv.org/abs/2106.09685)\n-\n- Huggingface [[Large language models]] [[LoRA DoRA etc]] and [[LoRA DoRA etc]] can be found with a simply filter.\n\t- [Models\n\t\t- Hugging Face](https://huggingface.co/models?pipeline_tag=text-generation&other=lora&sort=trending)\n\n## Current Landscape (2025)\n\n- Industry adoption and implementations\n  - Metaverse platforms continue to evolve with focus on interoperability and open standards\n  - Web3 integration accelerating with decentralised identity and asset ownership\n  - Enterprise adoption growing in virtual collaboration, training, and digital twins\n  - UK companies increasingly active in metaverse development and immersive technologies\n\n- Technical capabilities\n  - Real-time rendering at photorealistic quality levels\n  - Low-latency networking enabling seamless multi-user experiences\n  - AI-driven content generation and procedural world building\n  - Spatial audio and haptics enhancing immersion\n\n- UK and North England context\n  - Manchester: Digital Innovation Factory supports metaverse startups and research\n  - Leeds: Holovis leads in immersive experiences for entertainment and training\n  - Newcastle: University research in spatial computing and interactive systems\n  - Sheffield: Advanced manufacturing using digital twin technology\n\n- Standards and frameworks\n  - Metaverse Standards Forum driving interoperability protocols\n  - WebXR enabling browser-based immersive experiences\n  - glTF and USD for 3D asset interchange\n  - Open Metaverse Interoperability Group defining cross-platform standards\n\n## Metadata\n\n- **Last Updated**: 2025-11-16\n- **Review Status**: Automated remediation with 2025 context\n- **Verification**: Academic sources verified\n- **Regional Context**: UK/North England where applicable",
  "properties": {
    "id": "lora-dora-etc-owl-axioms",
    "collapsed": "true",
    "- ontology": "true",
    "- term-id": "mv-984612953767",
    "- preferred-term": "LoRA DoRA etc",
    "- source-domain": "metaverse",
    "- status": "active",
    "- public-access": "true",
    "- definition": "A component of the metaverse ecosystem focusing on lora dora etc.",
    "- maturity": "mature",
    "- authority-score": "0.85",
    "- owl:class": "mv:LoraDoraEtc",
    "- owl:physicality": "ConceptualEntity",
    "- owl:role": "Concept",
    "- belongsToDomain": "[[MetaverseDomain]]",
    "- enables": "[[ImmersiveExperience]], [[Presence]], [[SpatialComputing]]",
    "- requires": "[[DisplayTechnology]], [[TrackingSystem]], [[RenderingEngine]]",
    "- bridges-to": "[[HumanComputerInteraction]], [[ComputerVision]], [[Robotics]]",
    "public": "true"
  },
  "backlinks": [
    "Advice for developing GenAI",
    "AI Video",
    "BC-0072-node",
    "Daniel AI creative technologist",
    "Model Training",
    "ComfyUI",
    "Stable Diffusion",
    "Flux",
    "LoRA DoRA etc"
  ],
  "wiki_links": [
    "TrackingSystem",
    "ImmersiveExperience",
    "ComputerVision",
    "Large language models",
    "RenderingEngine",
    "SpatialComputing",
    "Robotics",
    "LoRA DoRA etc",
    "HumanComputerInteraction",
    "MetaverseDomain",
    "DisplayTechnology",
    "Presence"
  ],
  "ontology": {
    "term_id": "mv-984612953767",
    "preferred_term": "LoRA DoRA etc",
    "definition": "A component of the metaverse ecosystem focusing on lora dora etc.",
    "source_domain": "metaverse",
    "maturity_level": null,
    "authority_score": 0.85
  }
}