{
  "title": "Loss Function",
  "content": "- ### OntologyBlock\n  id:: loss-function-ontology\n  collapsed:: true\n\t- ontology:: true\n\t- term-id:: AI-0047\n\t- preferred-term:: Loss Function\n\t- source-domain:: ai\n\t- status:: draft\n\t- public-access:: true\n\n\n\n## Academic Context\n\n- Loss functions are fundamental mathematical constructs in machine learning and AI that quantify the discrepancy between predicted outputs and true values, producing a scalar error measure.\n  - They provide the objective signal that training algorithms use to update model parameters via optimisation techniques such as gradient descent.\n  - The concept is well-established in statistical learning theory and optimisation, with roots in classical regression and classification error metrics.\n- Loss functions are categorised primarily by task type: regression (continuous outputs) and classification (discrete labels).\n  - For regression, common losses include Mean Squared Error (MSE) and Mean Absolute Error (MAE).\n  - For classification, losses such as cross-entropy and hinge loss are prevalent.\n- Effective loss functions balance bias and variance, helping to avoid overfitting and underfitting by guiding model generalisation.\n- The distinction between loss function and cost function is important: the loss function measures error on a single example, while the cost function aggregates loss over the entire dataset, often as an average[1][2][3].\n\n## Current Landscape (2025)\n\n- Loss functions remain central to AI model training across domains including computer vision, natural language processing, and reinforcement learning.\n  - In deep learning, specialised loss functions are tailored for generative models (e.g., adversarial loss in GANs) and discriminative tasks (e.g., classification loss)[3].\n- Industry adoption is widespread, with major platforms (Google, IBM, DataRobot) providing extensive tooling and documentation on loss function selection and tuning[4][7][9].\n- UK organisations, including research groups and AI startups in hubs like Manchester and Leeds, actively develop and apply advanced loss functions for domain-specific applications such as healthcare diagnostics and autonomous systems.\n- Technical capabilities have improved with differentiable programming frameworks enabling custom loss functions and hybrid objectives.\n- Limitations persist: loss functions alone are insufficient as sole evaluation metrics, as identical loss values can mask different prediction biases or errors[4].\n- Standards such as ISO/IEC 22989:2022 provide formal definitions and classifications for AI concepts including loss functions, supporting interoperability and clarity[3].\n\n## Research & Literature\n\n- Key academic references include:\n  - Goodfellow, Bengio, and Courville (2016). *Deep Learning*. MIT Press. DOI: 10.5555/3086952\n  - Zhang et al. (2025). \"Loss Functions in Deep Learning: A Comprehensive Review.\" arXiv:2504.04242 [cs.LG]. URL: https://arxiv.org/abs/2504.04242[3]\n  - Bishop, C. M. (2006). *Pattern Recognition and Machine Learning*. Springer.\n- Ongoing research explores:\n  - Designing loss functions that better handle noisy, imbalanced, or adversarial data.\n  - Task-specific losses for emerging AI applications such as multimodal learning and explainability.\n  - Theoretical analysis of loss landscapes and their impact on optimisation dynamics.\n- Empirical studies continue to evaluate the impact of loss function choice on model robustness and fairness.\n\n## UK Context\n\n- The UK AI sector, including centres like the Alan Turing Institute and universities in the North of England (e.g., University of Manchester, University of Leeds), contributes to foundational and applied research on loss functions.\n- Regional innovation hubs focus on healthcare AI, where loss functions are adapted for imbalanced medical datasets and interpretability requirements.\n- Collaborations between academia and industry in Northern England foster development of bespoke loss functions for autonomous vehicles and smart manufacturing.\n- The UK governmentâ€™s AI strategy emphasises ethical and transparent AI, influencing research on loss functions that incorporate fairness and bias mitigation.\n\n## Future Directions\n\n- Emerging trends include:\n  - Integration of multi-objective loss functions balancing accuracy, fairness, and privacy.\n  - Automated loss function design via meta-learning and neural architecture search.\n  - Loss functions tailored for continual learning and adaptation in dynamic environments.\n- Anticipated challenges:\n  - Ensuring loss functions align with real-world performance metrics beyond mathematical error.\n  - Addressing computational complexity in large-scale models.\n  - Balancing interpretability with optimisation efficacy.\n- Research priorities:\n  - Developing loss functions robust to distribution shifts and adversarial attacks.\n  - Formalising loss function evaluation frameworks incorporating domain-specific constraints.\n  - Enhancing UK regional capabilities through targeted funding and interdisciplinary collaboration.\n\n## References\n\n1. DataCamp. Loss Functions in Machine Learning Explained. URL: https://www.datacamp.com/tutorial/loss-function-in-machine-learning  \n2. Built In. 7 Common Loss Functions in Machine Learning. URL: https://builtin.com/machine-learning/common-loss-functions  \n3. Zhang, et al. (2025). Loss Functions in Deep Learning: A Comprehensive Review. arXiv:2504.04242. URL: https://arxiv.org/abs/2504.04242  \n4. C3 AI. Loss Functions - Tuning a Machine Learning Model. URL: https://c3.ai/introduction-what-is-machine-learning/loss-functions/  \n5. GeeksforGeeks. ML | Common Loss Functions. URL: https://www.geeksforgeeks.org/machine-learning/ml-common-loss-functions/  \n6. Google Developers. Linear regression: Loss | Machine Learning Crash Course. URL: https://developers.google.com/machine-learning/crash-course/linear-regression/loss  \n7. IBM. What is Loss Function? URL: https://www.ibm.com/think/topics/loss-function  \n8. Wikipedia. Loss function. URL: https://en.wikipedia.org/wiki/Loss_function  \n9. DataRobot Blog. Introduction to Loss Functions. URL: https://www.datarobot.com/blog/introduction-to-loss-functions/  \n10. Goodfellow, I., Bengio, Y., & Courville, A. (2016). Deep Learning. MIT Press. DOI: 10.5555/3086952  \n\n## Metadata\n\n- Last Updated: 2025-11-11  \n- Review Status: Comprehensive editorial review  \n- Verification: Academic sources verified  \n- Regional Context: UK/North England where applicable",
  "properties": {
    "id": "loss-function-ontology",
    "collapsed": "true",
    "- ontology": "true",
    "- term-id": "AI-0047",
    "- preferred-term": "Loss Function",
    "- source-domain": "ai",
    "- status": "draft",
    "- public-access": "true"
  },
  "backlinks": [
    "Recurrent Neural Network",
    "Deep Learning",
    "Loss-Function"
  ],
  "wiki_links": [],
  "ontology": {
    "term_id": "AI-0047",
    "preferred_term": "Loss Function",
    "definition": "",
    "source_domain": "ai",
    "maturity_level": null,
    "authority_score": null
  }
}