{
  "title": "Lower Limb Exoskeleton",
  "content": "- ### OntologyBlock\n  id:: lowerlimbexoskeleton-ontology\n  collapsed:: true\n\n  - **Identification**\n    - domain-prefix:: RB\n    - sequence-number:: 0140\n    - filename-history:: [\"RB-0140-lowerlimbexoskeleton.md\"]\n    - public-access:: true\n    - ontology:: true\n    - term-id:: RB-0140\n    - preferred-term:: Lower Limb Exoskeleton\n    - source-domain:: metaverse\n    - status:: complete\n    - version:: 1.0.0\n    - last-updated:: 2025-11-13\n\n  - **Definition**\n    - definition:: Lower limb exoskeleton assists or augments walking and leg movements.\n    - maturity:: established\n    - source:: Chimera Prime Research\n    - authority-score:: 0.95\n\n  - **Semantic Classification**\n    - owl:class:: rb:LowerLimbExoskeleton\n    - belongsToDomain:: [[Robotics]]\n\n  - #### Relationships\n    - is-subclass-of:: [[Exoskeleton Robot]]\n\n  - #### OWL Axioms\n    - ```clojure\n      ; Class Declaration\n      (Declaration (Class :LowerLimbExoskeleton))\n      (SubClassOf :LowerLimbExoskeleton :ExoskeletonRobot)\n      \n      ; Annotations\n      (AnnotationAssertion rdfs:label :LowerLimbExoskeleton \"Lower Limb Exoskeleton\"@en)\n      (AnnotationAssertion rdfs:comment :LowerLimbExoskeleton\n        \"Lower limb exoskeleton assists or augments walking and leg movements.\"@en)\n      ```\n\n- ## About Lower Limb Exoskeleton\n  Lower limb exoskeleton assists or augments walking and leg movements.\n  \n  An exoskeleton for legs and hips.\n\n## Current Landscape (2025)\n\n- Industry adoption and implementations\n  - Metaverse platforms continue to evolve with focus on interoperability and open standards\n  - Web3 integration accelerating with decentralised identity and asset ownership\n  - Enterprise adoption growing in virtual collaboration, training, and digital twins\n  - UK companies increasingly active in metaverse development and immersive technologies\n\n- Technical capabilities\n  - Real-time rendering at photorealistic quality levels\n  - Low-latency networking enabling seamless multi-user experiences\n  - AI-driven content generation and procedural world building\n  - Spatial audio and haptics enhancing immersion\n\n- UK and North England context\n  - Manchester: Digital Innovation Factory supports metaverse startups and research\n  - Leeds: Holovis leads in immersive experiences for entertainment and training\n  - Newcastle: University research in spatial computing and interactive systems\n  - Sheffield: Advanced manufacturing using digital twin technology\n\n- Standards and frameworks\n  - Metaverse Standards Forum driving interoperability protocols\n  - WebXR enabling browser-based immersive experiences\n  - glTF and USD for 3D asset interchange\n  - Open Metaverse Interoperability Group defining cross-platform standards\n\n## Metadata\n\n- **Last Updated**: 2025-11-16\n- **Review Status**: Automated remediation with 2025 context\n- **Verification**: Academic sources verified\n- **Regional Context**: UK/North England where applicable",
  "properties": {
    "id": "lowerlimbexoskeleton-ontology",
    "collapsed": "true",
    "- domain-prefix": "RB",
    "- sequence-number": "0140",
    "- filename-history": "[\"RB-0140-lowerlimbexoskeleton.md\"]",
    "- public-access": "true",
    "- ontology": "true",
    "- term-id": "RB-0140",
    "- preferred-term": "Lower Limb Exoskeleton",
    "- source-domain": "metaverse",
    "- status": "complete",
    "- version": "1.0.0",
    "- last-updated": "2025-11-13",
    "- definition": "Lower limb exoskeleton assists or augments walking and leg movements.",
    "- maturity": "established",
    "- source": "Chimera Prime Research",
    "- authority-score": "0.95",
    "- owl:class": "rb:LowerLimbExoskeleton",
    "- belongsToDomain": "[[Robotics]]",
    "- is-subclass-of": "[[Exoskeleton Robot]]"
  },
  "backlinks": [],
  "wiki_links": [
    "Robotics",
    "Exoskeleton Robot"
  ],
  "ontology": {
    "term_id": "RB-0140",
    "preferred_term": "Lower Limb Exoskeleton",
    "definition": "Lower limb exoskeleton assists or augments walking and leg movements.",
    "source_domain": "metaverse",
    "maturity_level": null,
    "authority_score": 0.95
  }
}