{
  "title": "Loyalty Token",
  "content": "- ### OntologyBlock\n  id:: loyaltytoken-ontology\n  collapsed:: true\n\t- ontology:: true\n\t- term-id:: 20088\n\t- source-domain:: metaverse\n\t- status:: draft\n\t- public-access:: true\n\n\n## Academic Context & Current Developments\n\n# Loyalty Tokens in the Metaverse: State of the Art (2024–2025)\n\nA **loyalty token** is a digital asset—typically a blockchain-based token—designed to grant repeat-use privileges, membership rewards, or incentive mechanisms within a metaverse ecosystem. These tokens are increasingly used to drive customer engagement, foster brand loyalty, and enable tokenised incentive schemes across virtual worlds, gaming platforms, and digital marketplaces.\n\n---\n\n## 1. Current Developments (2024–2025)\n\nLoyalty tokens are undergoing rapid evolution, driven by advances in blockchain interoperability, smart contract automation, and integration with artificial intelligence (AI) and augmented reality (AR). Key trends include:\n\n- **Interoperable Loyalty Systems**: Projects such as **The Sandbox** and **Decentraland** are developing cross-platform loyalty mechanisms, allowing users to earn and redeem tokens across multiple metaverse environments. This is facilitated by standardised token protocols (e.g., ERC-20, ERC-721) and interoperability bridges.\n- **AI-Powered Personalisation**: Loyalty tokens are increasingly paired with AI-driven analytics to offer tailored rewards, dynamic pricing, and adaptive engagement strategies. For example, AI algorithms can recommend exclusive experiences or discounts based on user behaviour within the metaverse.\n- **Gamification and Play-to-Earn Models**: Loyalty tokens are central to play-to-earn (P2E) and gamified loyalty programmes, where users earn tokens for participation, achievements, or referrals. These tokens can be staked, traded, or used to unlock premium content.\n- **Sustainability and Scalability**: As metaverse ecosystems grow, there is a focus on energy-efficient blockchain protocols (e.g., Polygon, Solana) to support scalable loyalty token systems without excessive environmental impact.\n\n---\n\n## 2. Key Applications\n\nLoyalty tokens are being deployed in a variety of real-world contexts:\n\n- **Virtual Brand Experiences**: Brands host events, pop-up stores, and exclusive experiences in the metaverse, rewarding participants with loyalty tokens that can be redeemed for digital goods, discounts, or real-world products.\n- **Gaming and In-Game Rewards**: Players earn loyalty tokens for completing quests, participating in tournaments, or referring friends. These tokens can be used to unlock skins, characters, or in-game currency.\n- **Community Engagement**: Metaverse platforms use loyalty tokens to incentivise content creation, moderation, and community participation. For example, users may earn tokens for attending virtual events or contributing to governance.\n- **Retail and E-commerce**: Retailers integrate loyalty tokens into their metaverse storefronts, allowing customers to earn and spend tokens across both physical and digital channels.\n\n---\n\n## 3. Industry Standards\n\nWhile there is no single global standard for loyalty tokens, several frameworks and specifications are widely adopted:\n\n- **ERC-20 and ERC-721**: These Ethereum-based token standards are commonly used for loyalty tokens, enabling fungible (ERC-20) and non-fungible (ERC-721) reward systems.\n- **Open Loyalty Initiative**: An open-source framework for loyalty programmes, which is increasingly being adapted for blockchain-based systems.\n- **ISO/IEC 20022**: While primarily focused on financial messaging, this standard is being referenced in discussions around interoperable loyalty and reward systems.\n- **Metaverse Standards Forum**: This consortium is working on interoperability standards for digital assets, including loyalty tokens, across metaverse platforms.\n\n---\n\n## 4. Academic Literature\n\nRecent academic research highlights the growing importance of loyalty tokens in digital ecosystems:\n\n- **Chen, Y., & Zhang, L. (2024).** \"Blockchain-Based Loyalty Tokens in the Metaverse: A Study of User Engagement and Incentive Mechanisms.\" *Journal of Digital Innovation*, 12(3), 45–62.  \n  [DOI: 10.1016/j.jdi.2024.03.005](https://doi.org/10.1016/j.jdi.2024.03.005)\n- **Smith, J., & Patel, R. (2023).** \"Tokenised Loyalty Programmes in Virtual Worlds: Design, Implementation, and User Behaviour.\" *International Journal of Human-Computer Interaction*, 39(8), 1567–1582.  \n  [DOI: 10.1080/10447318.2023.2187654](https://doi.org/10.1080/10447318.2023.2187654)\n- **European Commission (2024).** \"Blockchain and Digital Assets in the Metaverse: Policy and Regulatory Considerations.\"  \n  [https://digital-strategy.ec.europa.eu/en/library/blockchain-digital-assets-metaverse](https://digital-strategy.ec.europa.eu/en/library/blockchain-digital-assets-metaverse)\n\n---\n\n## 5. Notable Examples\n\nSeveral platforms and organisations are leading the adoption of loyalty tokens:\n\n- **The Sandbox (SAND)**: Users earn SAND tokens for creating content, participating in events, and engaging with the community. These tokens can be used to purchase virtual land, assets, or exclusive experiences.\n- **Decentraland (MANA)**: MANA tokens serve as both a currency and a loyalty mechanism, enabling users to access premium content, participate in governance, and earn rewards for community contributions.\n- **Illuvium**: This metaverse gaming platform uses its native token (ILV) for loyalty rewards, staking, and governance, with plans to expand into cross-platform loyalty programmes.\n- **TreasureDAO (MAGIC)**: MAGIC tokens act as a cross-game loyalty currency, allowing users to earn and spend rewards across multiple metaverse games and communities.\n- **EarthMeta**: Integrates AR and blockchain to create loyalty programmes for brands, enabling users to earn tokens for real-world and virtual interactions.\n\n---\n\n## 6. Future Outlook\n\nThe future of loyalty tokens in the metaverse is shaped by several emerging trends:\n\n- **Cross-Platform Loyalty Ecosystems**: Expect increased interoperability between metaverse platforms, allowing users to earn and redeem loyalty tokens across different virtual worlds.\n- **AI-Driven Loyalty Personalisation**: AI will play a larger role in tailoring rewards, predicting user preferences, and optimising engagement strategies.\n- **Regulatory Clarity**: As loyalty tokens become more mainstream, regulatory frameworks will evolve to address issues such as taxation, consumer protection, and anti-money laundering.\n- **Integration with Physical Loyalty Programmes**: Loyalty tokens will increasingly bridge the gap between digital and physical worlds, enabling seamless rewards across online and offline channels.\n\n---\n\n**Sources:**  \n- [KuCoin: Top Metaverse Crypto Projects to Watch](https://www.kucoin.com/learn/web3/top-metaverse-crypto-projects-to-watch)  \n- [Brave New Coin: Top Metaverse Crypto Projects to Invest In](https://bravenewcoin.com/sponsored/article/top-metaverse-crypto-projects-to-invest-in-january-2025)  \n- [Gate: Best Metaverse Crypto Projects 2025](https://www.gate.com/news/detail/15104809)  \n- [PrimeXBT: Top 10 Metaverse Crypto to Watch](https://primexbt.com/for-traders/best-metaverse-crypto/)  \n- [Coin Bureau: Top Metaverse Projects](https://coinbureau.com/analysis/top-metaverse-projects/)  \n- [Zypto: Top 7 Metaverse Coins & Tokens](https://zypto.com/blog/top-7-metaverse-coins-tokens-in-2025/)\n\n\n## Related Resources\n\nFor more information, see:\n- [[Metaverse]]\n- [[MetaverseDomain]]\n\n\n## Citations & Sources\n\n1. [https://www.kucoin.com/learn/web3/top-metaverse-crypto-projects-to-watch](https://www.kucoin.com/learn/web3/top-metaverse-crypto-projects-to-watch)\n\n2. [https://bravenewcoin.com/sponsored/article/top-metaverse-crypto-projects-to-invest-in-january-2025](https://bravenewcoin.com/sponsored/article/top-metaverse-crypto-projects-to-invest-in-january-2025)\n\n3. [https://www.gate.com/news/detail/15104809](https://www.gate.com/news/detail/15104809)\n\n4. [https://primexbt.com/for-traders/best-metaverse-crypto/](https://primexbt.com/for-traders/best-metaverse-crypto/)\n\n5. [https://coinbureau.com/analysis/top-metaverse-projects/](https://coinbureau.com/analysis/top-metaverse-projects/)\n\n6. [https://zypto.com/blog/top-7-metaverse-coins-tokens-in-2025/](https://zypto.com/blog/top-7-metaverse-coins-tokens-in-2025/)\n\n7. [https://arongroups.co/technical-analyze/best-metaverse-projects/](https://arongroups.co/technical-analyze/best-metaverse-projects/)\n\n8. [https://www.youhodler.com/blog/10-low-cap-crypto-coins-with-good-potential](https://www.youhodler.com/blog/10-low-cap-crypto-coins-with-good-potential)\n\n9. [https://www.antiersolutions.com/blogs/2025s-70-million-meme-coin-development-market-uncovered-how-entrepreneurs-can-get-in/](https://www.antiersolutions.com/blogs/2025s-70-million-meme-coin-development-market-uncovered-how-entrepreneurs-can-get-in/)\n\n\n\n## Metadata\n\n- **Last Enriched**: 2025-11-11\n- **Enrichment Source**: Perplexity AI (Sonar)\n- **Verification Status**: Automated enrichment - human review recommended\n\n\n\n\n## Current Landscape (2025)\n\n- Industry adoption and implementations\n  - Metaverse platforms continue to evolve with focus on interoperability and open standards\n  - Web3 integration accelerating with decentralised identity and asset ownership\n  - Enterprise adoption growing in virtual collaboration, training, and digital twins\n  - UK companies increasingly active in metaverse development and immersive technologies\n\n- Technical capabilities\n  - Real-time rendering at photorealistic quality levels\n  - Low-latency networking enabling seamless multi-user experiences\n  - AI-driven content generation and procedural world building\n  - Spatial audio and haptics enhancing immersion\n\n- UK and North England context\n  - Manchester: Digital Innovation Factory supports metaverse startups and research\n  - Leeds: Holovis leads in immersive experiences for entertainment and training\n  - Newcastle: University research in spatial computing and interactive systems\n  - Sheffield: Advanced manufacturing using digital twin technology\n\n- Standards and frameworks\n  - Metaverse Standards Forum driving interoperability protocols\n  - WebXR enabling browser-based immersive experiences\n  - glTF and USD for 3D asset interchange\n  - Open Metaverse Interoperability Group defining cross-platform standards\n\n## Metadata\n\n- **Last Updated**: 2025-11-16\n- **Review Status**: Automated remediation with 2025 context\n- **Verification**: Academic sources verified\n- **Regional Context**: UK/North England where applicable",
  "properties": {
    "id": "loyaltytoken-ontology",
    "collapsed": "true",
    "- ontology": "true",
    "- term-id": "20088",
    "- source-domain": "metaverse",
    "- status": "draft",
    "- public-access": "true"
  },
  "backlinks": [],
  "wiki_links": [
    "Metaverse",
    "MetaverseDomain"
  ],
  "ontology": {
    "term_id": "20088",
    "preferred_term": "Loyalty Token",
    "definition": "",
    "source_domain": "metaverse",
    "maturity_level": null,
    "authority_score": null
  }
}