{
  "title": "Machine Learning Technique",
  "content": "- ### OntologyBlock\n  id:: machinelearningtechnique-ontology\n  collapsed:: true\n\n  - **Identification**\n    - domain-prefix:: AI\n    - sequence-number:: 0828\n    - filename-history:: [\"AI-0828-machinelearningtechnique.md\"]\n    - public-access:: true\n    - ontology:: true\n    - term-id:: AI-0828\n    - preferred-term:: Machine Learning Technique\n    - source-domain:: ai\n    - status:: complete\n    - version:: 1.0.0\n    - last-updated:: 2025-11-13\n\n  - **Definition**\n    - definition:: \n    - maturity:: established\n    - source:: Chimera Prime Research\n    - authority-score:: 0.95\n\n  - **Semantic Classification**\n    - owl:class:: ai:MachineLearningTechnique\n    - belongsToDomain:: [[Artificial Intelligence]]\n\n  - #### OWL Restrictions\n    \n\n  - #### CrossDomainBridges\n    - bridges-to:: [[MachineLearning]] via is-subclass-of\n\n  - \n### Relationships\n- is-subclass-of:: [[MachineLearning]]",
  "properties": {
    "id": "machinelearningtechnique-ontology",
    "collapsed": "true",
    "- domain-prefix": "AI",
    "- sequence-number": "0828",
    "- filename-history": "[\"AI-0828-machinelearningtechnique.md\"]",
    "- public-access": "true",
    "- ontology": "true",
    "- term-id": "AI-0828",
    "- preferred-term": "Machine Learning Technique",
    "- source-domain": "ai",
    "- status": "complete",
    "- version": "1.0.0",
    "- last-updated": "2025-11-13",
    "- definition": "",
    "- maturity": "established",
    "- source": "Chimera Prime Research",
    "- authority-score": "0.95",
    "- owl:class": "ai:MachineLearningTechnique",
    "- belongsToDomain": "[[Artificial Intelligence]]",
    "- bridges-to": "[[MachineLearning]] via is-subclass-of"
  },
  "backlinks": [],
  "wiki_links": [
    "MachineLearning",
    "Artificial Intelligence"
  ],
  "ontology": {
    "term_id": "AI-0828",
    "preferred_term": "Machine Learning Technique",
    "definition": "",
    "source_domain": "ai",
    "maturity_level": null,
    "authority_score": 0.95
  }
}