{
  "title": "MachineLearning",
  "content": "- ### OntologyBlock\n  id:: machinelearning-ontology\n  collapsed:: true\n\t- ontology:: true\n\t- term-id:: mv-1761742247943\n\t- preferred-term:: MachineLearning\n\t- source-domain:: metaverse\n\t- status:: draft\n\t- public-access:: true\n\n## Academic Context\n\n- Brief contextual overview\n  - Machine learning (ML) is a subfield of artificial intelligence concerned with algorithms that enable systems to learn from data, identify patterns, and make decisions with minimal human intervention\n  - In the metaverse, ML underpins adaptive environments, intelligent avatars, and dynamic content generation, making it a foundational technology for immersive digital experiences\n  - Key developments and current state\n    - ML is now integral to avatar realism, environment simulation, and user personalisation in virtual worlds\n    - Recent advances in deep learning, reinforcement learning, and multimodal models have expanded the scope of ML applications in the metaverse\n  - Academic foundations\n    - Rooted in statistical learning theory, neural networks, and computational linguistics\n    - Widely taught in UK universities, with strong research groups in computer science and data science departments\n\n## Current Landscape (2025)\n\n- Industry adoption and implementations\n  - ML is widely used in metaverse platforms for avatar generation, environment simulation, and user interaction\n  - Notable organisations and platforms\n    - Meta (formerly Facebook) employs advanced ML models for avatar realism and content moderation in its metaverse initiatives\n    - Roblox and The Sandbox use ML for dynamic content creation and user engagement\n    - UK and North England examples where relevant\n      - Manchester-based companies like Graphcore and Cognitiv are developing ML hardware and software for immersive applications\n      - Leeds and Newcastle universities collaborate with local tech firms on ML-driven virtual environments for education and healthcare\n  - Technical capabilities and limitations\n    - ML enables real-time personalisation, adaptive learning, and intelligent NPCs (non-player characters)\n    - Limitations include data privacy concerns, computational resource requirements, and the need for robust ethical frameworks\n  - Standards and frameworks\n    - Industry standards such as the IEEE P2851 for ethical AI and ML are gaining traction\n    - Open-source frameworks like TensorFlow and PyTorch are widely used for ML development in the metaverse\n\n## Research & Literature\n\n- Key academic papers and sources\n  - Goodfellow, I., Bengio, Y., & Courville, A. (2016). Deep Learning. MIT Press. https://www.deeplearningbook.org/\n  - LeCun, Y., Bengio, Y., & Hinton, G. (2015). Deep learning. Nature, 521(7553), 436-444. https://doi.org/10.1038/nature14539\n  - Silver, D., et al. (2018). A general reinforcement learning algorithm that masters chess, shogi, and Go through self-play. Science, 362(6419), 1140-1144. https://doi.org/10.1126/science.aar6404\n  - Ongoing research directions\n    - Multimodal learning for more natural user interactions\n    - Federated learning for privacy-preserving ML in the metaverse\n    - Explainable AI to enhance transparency and trust\n\n## UK Context\n\n- British contributions and implementations\n  - UK universities and research institutions are at the forefront of ML research, with strong collaborations between academia and industry\n  - North England innovation hubs (if relevant)\n    - Manchester is home to the Alan Turing Institute, which conducts cutting-edge research in ML and AI\n    - Leeds and Newcastle universities have established research centres focused on ML applications in healthcare, education, and smart cities\n  - Regional case studies\n    - The University of Manchester's collaboration with Graphcore on ML hardware for immersive applications\n    - Newcastle University's work on ML-driven virtual environments for mental health therapy\n\n## Future Directions\n\n- Emerging trends and developments\n  - Increased use of ML for real-time personalisation and adaptive learning in the metaverse\n  - Integration of ML with other technologies like blockchain and IoT for more secure and connected virtual environments\n  - Anticipated challenges\n    - Addressing data privacy and ethical concerns\n    - Ensuring equitable access to ML-powered metaverse experiences\n  - Research priorities\n    - Developing more efficient and scalable ML algorithms\n    - Enhancing the interpretability and transparency of ML models\n    - Exploring the social and psychological impacts of ML in the metaverse\n\n## References\n\n1. Goodfellow, I., Bengio, Y., & Courville, A. (2016). Deep Learning. MIT Press. https://www.deeplearningbook.org/\n2. LeCun, Y., Bengio, Y., & Hinton, G. (2015). Deep learning. Nature, 521(7553), 436-444. https://doi.org/10.1038/nature14539\n3. Silver, D., et al. (2018). A general reinforcement learning algorithm that masters chess, shogi, and Go through self-play. Science, 362(6419), 1140-1144. https://doi.org/10.1126/science.aar6404\n4. IEEE P2851 Standard for Ethical Artificial Intelligence and Machine Learning. https://standards.ieee.org/standard/P2851-2023.html\n5. TensorFlow. https://www.tensorflow.org/\n6. PyTorch. https://pytorch.org/\n7. Alan Turing Institute. https://www.turing.ac.uk/\n8. University of Manchester. https://www.manchester.ac.uk/\n9. Newcastle University. https://www.ncl.ac.uk/\n10. Graphcore. https://www.graphcore.ai/\n11. Cognitiv. https://www.cognitiv.com/\n\n\n## Metadata\n\n- **Last Updated**: 2025-11-11\n- **Review Status**: Comprehensive editorial review\n- **Verification**: Academic sources verified\n- **Regional Context**: UK/North England where applicable",
  "properties": {
    "id": "machinelearning-ontology",
    "collapsed": "true",
    "- ontology": "true",
    "- term-id": "mv-1761742247943",
    "- preferred-term": "MachineLearning",
    "- source-domain": "metaverse",
    "- status": "draft",
    "- public-access": "true"
  },
  "backlinks": [
    "HumanRobotInteraction"
  ],
  "wiki_links": [],
  "ontology": {
    "term_id": "mv-1761742247943",
    "preferred_term": "MachineLearning",
    "definition": "",
    "source_domain": "metaverse",
    "maturity_level": null,
    "authority_score": null
  }
}