{
  "title": "Manchester Tech Cluster",
  "content": "- ### OntologyBlock\n  id:: manchester-tech-cluster-ontology\n  collapsed:: true\n\t- ontology:: true\n\t- term-id:: UK-001\n\t- preferred-term:: Manchester Tech Cluster\n\t- source-domain:: uk-regions\n\t- status:: active\n    - public-access:: true\n\t- definition:: Manchester's thriving technology ecosystem centred on MediaCityUK, including AI, digital innovation, and financial technology sectors.\n\t- maturity:: established\n\t- region:: Greater Manchester\n\t- focus-areas:: Digital, AI, FinTech\n\t- owl:class:: uk:ManchesterTechCluster\n\t- owl:physicality:: ConceptualEntity\n\t- owl:role:: RegionalEcosystem\n\t- belongsToDomain:: [[UKTechEcosystem]]\n\n\n## Regional Technology Hub\n\n- **Overview**\n  - *Brief history and development*\n    - Manchester evolved from a 19th-century industrial powerhouse, known as the world's first industrial city, into a leading UK tech hub[1][8].\n    - The Manchester Science Park (established 1987) and MediaCityUK were pivotal in transitioning Manchester into the digital era, attracting major media and tech companies like BBC, ITV, and global brands[1].\n    - The city has a rich heritage of scientific breakthroughs, including the first programmable computer ('Manchester Baby') and the discovery of graphene, underpinning its innovation culture[3].\n    - The Greater Manchester Combined Authority (GMCA) has actively supported digital infrastructure and tech growth, reinforcing Manchester’s position as a top UK tech cluster[1][5].\n  - *Current state and infrastructure*\n    - Manchester hosts over 10,000 digital and tech businesses, forming a £5 billion digital ecosystem, making it the UK's second-largest tech hub after London[1][4].\n    - Key infrastructure includes innovation districts like ID Manchester (£1.5 billion development by University of Manchester and Bruntwood SciTech), MediaCityUK, and Manchester Science Park[1][7].\n    - The city benefits from a strong network of incubators, accelerators, co-working spaces, and support organisations such as Manchester Digital[1][4].\n  - *Key organisations and institutions*\n    - Manchester Digital (industry body supporting digital businesses)\n    - University of Manchester and former UMIST (now merged), leading research and innovation institutions[3][7]\n    - Greater Manchester Combined Authority (GMCA), driving digital strategy and investment[5]\n    - Bruntwood SciTech, a major developer of innovation spaces[7]\n\n- **Technology Focus**\n  - *Primary technology sectors*\n    - Digital technology broadly, including eCommerce, cyber security, Internet of Things (IoT), and data analytics[4].\n    - Artificial Intelligence (AI), with Manchester outperforming other UK cities in AI and data research[4].\n    - FinTech, hosting the UK's largest regional FinTech ecosystem[4][6].\n  - *Notable companies and startups*\n    - Unicorns and scaleups: THG (The Hut Group), Blue Prism, The Very Group[2][6].\n    - eCommerce giants: AutoTrader, Boohoo, Booking.com, AO.com[2][4].\n    - Global tech companies with presence: Google, Microsoft, Amazon[2][4].\n  - *Research institutions and universities*\n    - University of Manchester, a world-class research university with strong focus on advanced materials, digital innovation, and life sciences[3][7].\n    - Former UMIST legacy embedded in innovation culture and collaboration[3].\n  - *Innovation programmes*\n    - Greater Manchester Digital Blueprint (launched 2020), a three-year strategic plan to advance digital priorities across the city-region[5].\n    - Innovation clusters supported by Innovation Greater Manchester, including ID Manchester innovation district[7].\n    - Digital City Festival and Digital City Awards, promoting sector collaboration and visibility[5].\n\n- **Economic Impact**\n  - *Employment and growth*\n    - The tech sector employs tens of thousands, with rapid growth in digital and creative companies (70% increase since 2011)[1].\n    - Manchester is recognised as the UK’s most entrepreneurial city outside London, fostering startups and scaleups[4][2].\n  - *Investment and funding*\n    - Greater Manchester has overtaken Cambridge as the UK’s most attractive city for tech investment outside London[2].\n    - Significant inward investment from international companies and venture capital, supported by local government initiatives[2][5].\n    - The IPO of THG in 2020 highlighted the calibre of tech companies in the region, boosting investor confidence[2].\n  - *Regional contribution*\n    - The £5 billion digital ecosystem contributes substantially to Greater Manchester’s economy.\n    - The tech cluster supports broader economic diversification from traditional industries to knowledge-based sectors[1][4].\n\n- **Notable Projects**\n  - *Specific examples of innovation*\n    - Development of AI and data-driven solutions, with Manchester leading UK cities in these fields[4].\n    - ID Manchester innovation district, a £1.5 billion project fostering collaboration between academia and industry[7].\n  - *Success stories*\n    - THG’s rise to a tech unicorn and successful IPO.\n    - Blue Prism’s leadership in robotic process automation (RPA).\n    - Growth of eCommerce platforms like Boohoo and AutoTrader[2][6].\n  - *Collaborative initiatives*\n    - Greater Manchester Digital Blueprint aligning public sector projects and private sector innovation[5].\n    - Digital City Festival fostering networking and knowledge exchange[5].\n    - Partnerships between University of Manchester, Bruntwood SciTech, and industry in innovation districts[7].\n\n- **Future Development**\n  - *Growth plans and strategies*\n    - Continued implementation of the Greater Manchester Digital Blueprint focusing on digital infrastructure, skills, and innovation[5].\n    - Expansion of innovation districts like ID Manchester to attract global talent and companies[7].\n  - *Infrastructure investments*\n    - Investment in digital infrastructure to support AI, cyber security, and FinTech growth.\n    - Development of co-working spaces, incubators, and accelerators to nurture startups and scaleups[1][4][7].\n  - *Policy support*\n    - GMCA’s active role in digital strategy, employment, and skills development to sustain tech ecosystem growth[5].\n    - Supportive entrepreneurial climate enhanced by academic-industry collaboration and investment incentives[2][4].\n\n\n## Related Hubs\n\n- [[North England Innovation Corridor]]\n- [[Northern Powerhouse]]\n- [[UK Tech Ecosystem]]\n\n\n\n\n## Current Landscape (2025)\n\n- Industry adoption and implementations\n  - Metaverse platforms continue to evolve with focus on interoperability and open standards\n  - Web3 integration accelerating with decentralised identity and asset ownership\n  - Enterprise adoption growing in virtual collaboration, training, and digital twins\n  - UK companies increasingly active in metaverse development and immersive technologies\n\n- Technical capabilities\n  - Real-time rendering at photorealistic quality levels\n  - Low-latency networking enabling seamless multi-user experiences\n  - AI-driven content generation and procedural world building\n  - Spatial audio and haptics enhancing immersion\n\n- UK and North England context\n  - Manchester: Digital Innovation Factory supports metaverse startups and research\n  - Leeds: Holovis leads in immersive experiences for entertainment and training\n  - Newcastle: University research in spatial computing and interactive systems\n  - Sheffield: Advanced manufacturing using digital twin technology\n\n- Standards and frameworks\n  - Metaverse Standards Forum driving interoperability protocols\n  - WebXR enabling browser-based immersive experiences\n  - glTF and USD for 3D asset interchange\n  - Open Metaverse Interoperability Group defining cross-platform standards\n\n## Metadata\n\n- **Last Updated**: 2025-11-16\n- **Review Status**: Automated remediation with 2025 context\n- **Verification**: Academic sources verified\n- **Regional Context**: UK/North England where applicable\n\n\n## References\n\n1. [https://www.nucamp.co/blog/coding-bootcamp-united-kingdom-igbr-inside-manchesters-thriving-tech-hub-startups-and-success-stories](https://www.nucamp.co/blog/coding-bootcamp-united-kingdom-igbr-inside-manchesters-thriving-tech-hub-startups-and-success-stories)\n\n2. [https://gmbusinessboard.com/wp-content/uploads/2021/04/Unicorns-Whitepaper-compressed.final_-1.pdf](https://gmbusinessboard.com/wp-content/uploads/2021/04/Unicorns-Whitepaper-compressed.final_-1.pdf)\n\n3. [https://sistermanchester.com/our-heritage](https://sistermanchester.com/our-heritage)\n\n4. [https://www.investinmanchester.com/why-manchester/industry-expertise/digital-and-technology/](https://www.investinmanchester.com/why-manchester/industry-expertise/digital-and-technology/)\n\n5. [https://www.greatermanchester-ca.gov.uk/news/greater-manchester-celebrates-digital-milestones/](https://www.greatermanchester-ca.gov.uk/news/greater-manchester-celebrates-digital-milestones/)\n\n6. [https://www.manchesterdigital.com/post/manchester-digital/12-clusters-of-tech-north-west](https://www.manchesterdigital.com/post/manchester-digital/12-clusters-of-tech-north-west)\n\n7. [https://www.innovationgreatermanchester.com/about-innovation-greater-manchester/innovation-clusters/](https://www.innovationgreatermanchester.com/about-innovation-greater-manchester/innovation-clusters/)\n\n8. [https://www.scienceandindustrymuseum.org.uk/objects-and-stories/worlds-first-industrial-city](https://www.scienceandindustrymuseum.org.uk/objects-and-stories/worlds-first-industrial-city)\n\n\n\n## Metadata\n\n- **Created**: 2025-11-11\n- **Region**: Greater Manchester, North England\n- **Category**: Regional Technology Ecosystem\n- **Status**: Active",
  "properties": {
    "id": "manchester-tech-cluster-ontology",
    "collapsed": "true",
    "- ontology": "true",
    "- term-id": "UK-001",
    "- preferred-term": "Manchester Tech Cluster",
    "- source-domain": "uk-regions",
    "- status": "active",
    "- public-access": "true",
    "- definition": "Manchester's thriving technology ecosystem centred on MediaCityUK, including AI, digital innovation, and financial technology sectors.",
    "- maturity": "established",
    "- region": "Greater Manchester",
    "- focus-areas": "Digital, AI, FinTech",
    "- owl:class": "uk:ManchesterTechCluster",
    "- owl:physicality": "ConceptualEntity",
    "- owl:role": "RegionalEcosystem",
    "- belongsToDomain": "[[UKTechEcosystem]]"
  },
  "backlinks": [],
  "wiki_links": [
    "Northern Powerhouse",
    "UK Tech Ecosystem",
    "North England Innovation Corridor",
    "UKTechEcosystem"
  ],
  "ontology": {
    "term_id": "UK-001",
    "preferred_term": "Manchester Tech Cluster",
    "definition": "Manchester's thriving technology ecosystem centred on MediaCityUK, including AI, digital innovation, and financial technology sectors.",
    "source_domain": "uk-regions",
    "maturity_level": null,
    "authority_score": null
  }
}