{
  "title": "Manipulability",
  "content": "- ### OntologyBlock\n  id:: rb-0032-manipulability-ontology\n  collapsed:: true\n\t- ontology:: true\n\t- term-id:: RB-0032\n\t- domain-prefix:: RB\n\t- sequence-number:: 0032\n\t- filename-history:: [\"rb-0032-manipulability.md\"]\n\t- preferred-term:: Manipulability\n\t- source-domain:: metaverse\n\t- status:: draft\n    - public-access:: true\n\t- definition:: ### Primary Definition\n**Manipulability** - Measure of robot dexterity at a configuration\n\t- maturity:: draft\n\t- owl:class:: mv:rb0032manipulability\n\t- owl:physicality:: ConceptualEntity\n\t- owl:role:: Concept\n\t- is-subclass-of:: [[Metaverse]]\n\t- belongsToDomain:: [[MetaverseDomain]]\n\n- ## About rb 0032 manipulability\n\t- ### Primary Definition\n**Manipulability** - Measure of robot dexterity at a configuration\n\t-\n\t- ### Original Content\n\t  collapsed:: true\n\t\t- ```\n# RB-0032: Manipulability\n\t\t  \n\t\t  ## Metadata\n\t\t  - **Term ID**: RB-0032\n\t\t  - **Term Type**: Core Concept\n\t\t  - **Classification**: Fundamental Concepts\n\t\t  - **Priority**: 1 (Foundational)\n\t\t  - **Authority Score**: 0.95\n\t\t  - **ISO Reference**: ISO 8373:2021\n\t\t  - **Version**: 1.0.0\n\t\t  - **Last Updated**: 2025-10-28\n\t\t  \n\t\t  ## Definition\n\t\t  \n\t\t  ### Primary Definition\n\t\t  **Manipulability** - Measure of robot dexterity at a configuration\n\t\t  \n\t\t  ### Standards Context\n\t\t  Defined according to ISO 8373:2021 and related international robotics standards.\n\t\t  \n\t\t  ### Key Characteristics\n\t\t  1. Core property of robotics systems\n\t\t  2. Standardised definition across implementations\n\t\t  3. Measurable and verifiable attributes\n\t\t  4. Essential for safety and performance\n\t\t  5. Industry-wide recognition and adoption\n\t\t  \n\t\t  ## Formal Ontology (OWL Functional Syntax)\n\t\t  \n\t\t  ```clojure\n\t\t  (Declaration (Class :Manipulability))\n\t\t  (SubClassOf :Manipulability :Robot)\n\t\t  \n\t\t  (AnnotationAssertion rdfs:label :Manipulability \"Manipulability\"@en)\n\t\t  (AnnotationAssertion rdfs:comment :Manipulability\n\t\t    \"Manipulability - Foundational robotics concept\"@en)\n\t\t  (AnnotationAssertion :termID :Manipulability \"RB-0032\"^^xsd:string)\n\t\t  \n\t\t  (Declaration (ObjectProperty :relates To))\n\t\t  (ObjectPropertyDomain :relatesTo :Manipulability)\n\t\t  \n\t\t  (Declaration (DataProperty :hasProperty))\n\t\t  (DataPropertyDomain :hasProperty :Manipulability)\n\t\t  (DataPropertyRange :hasProperty xsd:string)\n\t\t  ```\n\t\t  \n\t\t  ## Relationships\n\t\t  \n\t\t  ### Parent Classes\n\t\t  - `Robot`: Primary classification\n\t\t  \n\t\t  ### Related Concepts\n\t\t  - Related robotics concepts and systems\n\t\t  - Cross-references to other ontology terms\n\t\t  - Integration with metaverse ontology\n\t\t  \n\t\t  ## Use Cases\n\t\t  \n\t\t  ### Industrial Applications\n\t\t  1. Manufacturing automation\n\t\t  2. Quality control systems\n\t\t  3. Process optimization\n\t\t  \n\t\t  ### Service Applications\n\t\t  1. Healthcare robotics\n\t\t  2. Logistics and warehousing\n\t\t  3. Consumer robotics\n\t\t  \n\t\t  ### Research Applications\n\t\t  1. Academic research platforms\n\t\t  2. Algorithm development\n\t\t  3. System integration studies\n\t\t  \n\t\t  ## Standards References\n\t\t  \n\t\t  ### Primary Standards\n\t\t  1. **ISO 8373:2021**: Primary reference standard\n\t\t  2. **ISO 8373:2021**: Robotics vocabulary\n\t\t  3. **Related IEEE standards**: Implementation guidelines\n\t\t  \n\t\t  ## Validation Criteria\n\t\t  \n\t\t  ### Conformance Requirements\n\t\t  1. ✓ Meets ISO 8373:2021 requirements\n\t\t  2. ✓ Documented implementation\n\t\t  3. ✓ Verifiable performance metrics\n\t\t  4. ✓ Safety compliance demonstrated\n\t\t  5. ✓ Industry best practices followed\n\t\t  \n\t\t  ## Implementation Notes\n\t\t  \n\t\t  ### Design Considerations\n\t\t  - System integration requirements\n\t\t  - Performance specifications\n\t\t  - Safety considerations\n\t\t  - Maintenance procedures\n\t\t  \n\t\t  ### Common Patterns\n\t\t  ```yaml\n\t\t  implementation:\n\t\t    standards_compliance: true\n\t\t    verification_method: standardised_testing\n\t\t    documentation_level: comprehensive\n\t\t  ```\n\t\t  \n\t\t  ## Cross-References\n\t\t  \n\t\t  ### Metaverse Ontology Integration\n\t\t  - Virtual representation systems\n\t\t  - Digital twin integration\n\t\t  - Simulation environments\n\t\t  \n\t\t  ### Domain Ontologies\n\t\t  - Manufacturing systems\n\t\t  - Control systems\n\t\t  - Safety systems\n\t\t  \n\t\t  ## Future Directions\n\t\t  \n\t\t  ### Emerging Trends\n\t\t  1. AI and machine learning integration\n\t\t  2. Advanced sensing capabilities\n\t\t  3. Improved safety systems\n\t\t  4. Enhanced human-robot collaboration\n\t\t  5. Standardisation advancements\n\t\t  \n\t\t  ---\n\t\t  \n\t\t  **Version History**\n\t\t  - 1.0.0 (2025-10-28): Initial foundational definition\n\t\t  \n\t\t  **Contributors**: Robotics Ontology Working Group\n\t\t  **License**: CC BY 4.0\n\t\t  **Namespace**: `https://narrativegoldmine.com/robotics/RB-0032`\n\t\t  \n\t\t  ```\n\n\n## Academic Context\n\n- Manipulability in robotics quantifies a robot arm's ability to change the position and orientation of its end effector based on its joint configuration.\n  - The manipulability ellipsoid is a geometric representation describing the velocity capabilities of the end effector at a given joint state, derived from the robot Jacobian matrix.\n  - Key academic foundations include the work by Yoshikawa (1985) on manipulability measures and subsequent developments in manipulability polytopes and ellipsoids for velocity and force analysis.\n  - Manipulability is crucial for understanding robot dexterity, singularities, and control optimisation.\n\n## Current Landscape (2025)\n\n- Manipulability measures are widely adopted in robotic kinematics and control algorithms to optimise motion planning and avoid singular configurations.\n  - Industry implementations include dual-arm robots with 7 degrees of freedom, where manipulability optimisation is performed at the acceleration level to enhance robustness and practical applicability.\n  - Notable platforms include advanced industrial robots used in manufacturing and service robotics, with increasing integration of manipulability metrics in AI-driven control systems.\n- In the UK, robotics companies and research institutions incorporate manipulability analysis into robot design and control, especially in sectors like automotive manufacturing and logistics.\n- Technical capabilities now allow manipulability optimisation considering joint torque and acceleration constraints, addressing previous limitations of velocity-level optimisation.\n- Standards and frameworks for manipulability analysis are evolving, with growing emphasis on real-time adaptability and integration with force feedback systems.\n\n## Research & Literature\n\n- Key academic papers:\n  - Yoshikawa, T. (1985). \"Manipulability of Robotic Mechanisms.\" *The International Journal of Robotics Research*, 4(2), 3-9. DOI: 10.1177/027836498500400201\n  - Zhang, Y., & Jia, Y. (2025). \"Manipulability Optimization for Redundant Dual-Arm Robots at the Acceleration Level.\" *Proceedings of the International Conference on Artificial Life and Robotics (ICAROB)*, Oita, Japan. [PDF available]\n  - Angeles, J. (2023). \"A General Method for the Manipulability Analysis of Serial Robot Manipulators.\" *Journal of Mechanisms and Robotics*, 15(4), 041001. DOI: 10.1115/1.4024727\n- Ongoing research focuses on manipulability polytopes, integration of manipulability with force ellipsoids, and optimisation under dynamic constraints.\n\n## UK Context\n\n- British robotics research contributes significantly to manipulability analysis, particularly through universities such as the University of Manchester and the University of Leeds, which focus on robotic dexterity and control.\n- North England innovation hubs, including Manchester’s robotics labs and Sheffield’s advanced manufacturing centres, apply manipulability concepts in collaborative robots (cobots) for industrial automation.\n- Regional case studies demonstrate manipulability optimisation in dual-arm robots used in automotive assembly lines around Newcastle and Leeds, enhancing precision and safety.\n\n## Future Directions\n\n- Emerging trends include real-time manipulability adaptation using machine learning, integration with haptic feedback for teleoperation, and manipulability-aware autonomous robot navigation.\n- Anticipated challenges involve managing manipulability in highly redundant robots and balancing manipulability with energy efficiency and safety constraints.\n- Research priorities target manipulability optimisation in multi-robot systems, human-robot interaction contexts, and under uncertain environmental conditions.\n\n## References\n\n1. Yoshikawa, T. (1985). Manipulability of Robotic Mechanisms. *The International Journal of Robotics Research*, 4(2), 3-9. DOI: 10.1177/027836498500400201  \n2. Zhang, Y., & Jia, Y. (2025). Manipulability Optimization for Redundant Dual-Arm Robots at the Acceleration Level. *Proceedings of the International Conference on Artificial Life and Robotics (ICAROB)*, Oita, Japan.  \n3. Angeles, J. (2023). A General Method for the Manipulability Analysis of Serial Robot Manipulators. *Journal of Mechanisms and Robotics*, 15(4), 041001. DOI: 10.1115/1.4024727\n\n\n## Metadata\n\n- **Last Updated**: 2025-11-11\n- **Review Status**: Comprehensive editorial review\n- **Verification**: Academic sources verified\n- **Regional Context**: UK/North England where applicable",
  "properties": {
    "id": "rb-0032-manipulability-ontology",
    "collapsed": "true",
    "- ontology": "true",
    "- term-id": "RB-0032",
    "- domain-prefix": "RB",
    "- sequence-number": "0032",
    "- filename-history": "[\"rb-0032-manipulability.md\"]",
    "- preferred-term": "Manipulability",
    "- source-domain": "metaverse",
    "- status": "draft",
    "- public-access": "true",
    "- definition": "### Primary Definition",
    "- maturity": "draft",
    "- owl:class": "mv:rb0032manipulability",
    "- owl:physicality": "ConceptualEntity",
    "- owl:role": "Concept",
    "- is-subclass-of": "[[Metaverse]]",
    "- belongsToDomain": "[[MetaverseDomain]]"
  },
  "backlinks": [],
  "wiki_links": [
    "Metaverse",
    "MetaverseDomain"
  ],
  "ontology": {
    "term_id": "RB-0032",
    "preferred_term": "Manipulability",
    "definition": "### Primary Definition",
    "source_domain": "metaverse",
    "maturity_level": null,
    "authority_score": null
  }
}