{
  "title": "Market Surveillance Authority",
  "content": "- ### OntologyBlock\n  id:: market-surveillance-authority-ontology\n  collapsed:: true\n\t- ontology:: true\n\t- term-id:: AI-0512\n\t- preferred-term:: Market Surveillance Authority\n\t- source-domain:: metaverse\n\t- status:: draft\n    - public-access:: true\n\t- definition:: National authority responsible for carrying out market surveillance activities on AI systems, including inspections, testing, enforcement, and ensuring compliance with EU AI Act requirements within a Member State.\n\n\n## OWL Formal Semantics\n\n```clojure\n;; OWL Functional Syntax\n\n(Declaration (Class :MarketSurveillanceAuthority))\n\n;; Annotations\n(AnnotationAssertion rdfs:label :MarketSurveillanceAuthority \"Market Surveillance Authority\"@en)\n(AnnotationAssertion rdfs:comment :MarketSurveillanceAuthority \"National authority responsible for carrying out market surveillance activities on AI systems, including inspections, testing, enforcement, and ensuring compliance with EU AI Act requirements within a Member State.\"@en)\n\n;; Data Properties\n(AnnotationAssertion dcterms:identifier :MarketSurveillanceAuthority \"mv-1761742247943\"^^xsd:string)\n```\n\n## Source\n\n**Primary**: EU AI Act Article 74\n**Reference**: Market Surveillance Regulation (EU) 2019/1020\n\n## Regulatory Context\n\nMarket surveillance authorities are the front-line enforcement bodies for the EU AI Act at national level. Each Member State designates one or more authorities to monitor AI systems, investigate non-compliance, and take corrective action to protect health, safety, and fundamental rights.\n\n## Designation and Organisation (Article 74)\n\n### Member State Responsibility\nEach Member State must designate market surveillance authority with:\n- **Legal mandate**: National law establishing authority and powers\n- **Competence**: Technical expertise in AI systems\n- **Resources**: Sufficient staff, budget, equipment\n- **Independence**: Operational autonomy from political/economic interests\n\n### Multiple Authorities Possible\nMember States may designate:\n- **Horizontal authority**: Covering all AI systems\n- **Sectoral authorities**: Specialised by domain (finance, healthcare, law enforcement)\n\n**Coordination requirement**: Clear division of responsibilities, single point of contact\n\n### Notification to Commission\nMember States inform Commission of:\n- Designated authorities\n- Scope of responsibilities\n- Contact information\n\n## Powers and Responsibilities (Articles 74-77)\n\n### Market Surveillance Activities\n\n#### 1. Compliance Monitoring\n- **Market overview**: Track AI systems placed on market\n- **Risk assessment**: Identify high-risk non-compliant systems\n- **Sectoral analysis**: Monitor AI use in critical domains\n\n#### 2. Inspections and Testing (Article 75)\n\n**Powers**:\n- **Enter premises**: Providers, importers, distributors\n- **Access documentation**: Technical documentation, logs, quality management records\n- **Examine AI systems**: Test functionality, performance, safety\n- **Take samples**: For laboratory testing\n- **Interview personnel**: Question staff on compliance\n\n**Warrant**: May require judicial authorisation depending on Member State law\n\n#### 3. Information Requests (Article 76)\nRequire operators to provide:\n- Technical documentation\n- EU Declaration of Conformity\n- Quality management system documentation\n- Post-market monitoring data\n- Serious incident reports\n\n**Timeframe**: Reasonable deadline set by authority\n\n**Language**: In language easily understood by authority\n\n### Enforcement Measures (Article 77)\n\n#### Non-Compliance Finding\nWhen AI system does not comply with Act, authority may:\n\n##### Provisional Measures\n- **Corrective action order**: Require provider to bring into compliance within deadline\n- **Market restriction**: Prohibit making available until compliant\n- **Withdrawal order**: Require removal from market\n- **Recall order**: Require return of already deployed systems\n\n##### Definitive Measures (Article 77(2))\nIf non-compliance persists or serious:\n- **Market prohibition**: Ban system from EU market\n- **Public warning**: Alert deployers and public to risks\n- **Administrative fines**: Penalties per Article 99\n\n#### Risk Assessment Approach\nMeasures proportionate to:\n- **Severity**: Health, safety, fundamental rights impact\n- **Likelihood**: Probability of harm occurring\n- **Scope**: Number of affected persons\n- **Provider cooperation**: Willingness to remedy\n\n### Serious Incident Response (Article 73, 77)\n\n#### Upon Receiving Incident Report\n- **Immediate assessment**: Determine severity and scope\n- **Provider contact**: Request additional information\n- **Cross-border notification**: Alert other Member States if multi-state impact\n- **Public communication**: Warn deployers if imminent danger\n\n#### Investigation\n- **Root cause analysis**: Identify failure reason\n- **Systemic assessment**: Determine if similar systems affected\n- **Corrective measure evaluation**: Verify provider's remediation adequate\n\n## Cross-Border Coordination\n\n### Multi-State Incidents (Article 77(6))\nWhen AI system affects multiple Member States:\n- **Lead authority**: Member State where provider established\n- **Cooperation**: Share investigation findings\n- **Harmonised action**: Coordinated enforcement measures\n- **AI Office involvement**: Complex cases requiring EU-level coordination\n\n### Mutual Assistance\nAuthorities assist each other by:\n- **Information exchange**: Share compliance data, testing results\n- **Joint investigations**: Collaborative inspections\n- **Enforcement support**: Recognise and enforce other authorities' decisions\n\n### Dispute Resolution\nIf authorities disagree on:\n- Jurisdiction\n- Compliance interpretation\n- Enforcement approach\n\n**Resolution**: AI Board mediation, Commission arbitration\n\n## Relationship to Other Bodies\n\n### AI Office (Article 64)\n- **GPAI supervision**: AI Office handles general-purpose AI models\n- **Coordination**: AI Office coordinates multi-state surveillance\n- **Guidance**: AI Office provides interpretative guidance\n- **Reporting**: Authorities report enforcement to AI Office\n\n### AI Board (Articles 65-66)\n- **Member representation**: Authorities represent Member States on AI Board\n- **Best practices**: Share experiences via AI Board\n- **Guidelines**: Implement AI Board recommendations\n\n### Notified Bodies (Articles 29-39)\n- **Verification**: Check validity of notified body certificates\n- **Investigation**: Question notified body findings if non-compliance suspected\n- **Coordination**: Work with notifying authority on notified body issues\n\n### Sectoral Regulators\nCoordinate with:\n- **Financial supervisors**: Banking, insurance, securities AI\n- **Healthcare authorities**: Medical device AI\n- **Data protection authorities**: GDPR compliance\n- **Consumer protection agencies**: Unfair commercial practices\n\n## Information Systems\n\n### EU Database for Standalone High-Risk AI (Article 71)\nAuthorities have access to:\n- Registered high-risk AI systems\n- Provider information\n- Conformity certificates\n- Post-market monitoring plans\n\nAuthorities:\n- **Verify registration**: Check provider compliance\n- **Update entries**: Enforcement actions, serious incidents\n- **Query database**: Identify similar systems, patterns\n\n### Law Enforcement Database (Article 49)\nFor law enforcement, migration, border AI:\n- Public logging of use cases\n- Transparency mechanism\n- Authority oversight tool\n\n### Information Exchange Platform\nAuthorities use secure platform for:\n- Incident sharing\n- Investigation coordination\n- Best practice dissemination\n\n## Resources and Capacity Building\n\n### Technical Expertise Requirements\nMarket surveillance authorities need staff with:\n- **AI knowledge**: Machine learning, neural networks, algorithms\n- **Sector expertise**: Healthcare, finance, law enforcement domains\n- **Legal skills**: AI Act interpretation, enforcement procedures\n- **Testing capabilities**: Evaluation tools, benchmarking methodologies\n\n### Commission Support (Article 78)\nCommission provides:\n- **Training programmes**: AI Act implementation, technical assessment\n- **Testing facilities**: Access to AI evaluation infrastructure\n- **Guidance materials**: Enforcement manuals, compliance checklists\n- **Funding**: Digital Europe Programme, Horizon Europe\n\n### International Cooperation\nAuthorities engage with:\n- **Non-EU regulators**: US FTC/NIST, UK AI Safety Institute, Singapore IMDA\n- **Standards bodies**: ISO, IEC, IEEE\n- **Research institutions**: Universities, AI safety organisations\n\n## Penalties (Article 99)\n\nAuthorities may impose administrative fines:\n\n### Prohibited Practices (Article 99(3))\nUp to **€35 million or 7% of global annual turnover**\n\n### High-Risk Obligations (Article 99(4))\nUp to **€15 million or 3% of global annual turnover**\n\n### Information Obligations (Article 99(5))\nUp to €7.5 million or 1.5% of global annual turnover**\n\n### Considerations\n- Infringement severity and duration\n- Provider cooperation\n- Mitigating measures taken\n- Economic benefit derived\n- SME status (reduced penalties)\n\n## Transparency and Accountability\n\n### Public Reporting\nAuthorities publish:\n- **Annual reports**: Enforcement activities, key findings\n- **Non-compliance cases**: Anonymised case studies (learning tool)\n- **Statistical data**: Number of inspections, penalties, serious incidents\n\n### Stakeholder Engagement\nAuthorities consult with:\n- **Industry associations**: Compliance challenges, guidance needs\n- **Civil society**: Fundamental rights concerns\n- **Consumer organisations**: Deployer protection\n- **Research community**: Technical developments\n\n### Complaint Mechanisms (Article 85)\nIndividuals and organisations may:\n- **Lodge complaints**: Report suspected AI Act violations\n- **Provide evidence**: Support investigations\n- **Receive feedback**: Informed of outcomes (subject to confidentiality)\n\n## Practical Implications\n\n### For Providers\n- **Primary contact**: National authority where provider established\n- **Cooperation**: Respond promptly to information requests\n- **Proactive engagement**: Seek clarification before enforcement\n- **Documentation**: Maintain records accessible for inspections\n\n### For Deployers\n- **Report incidents**: Serious incidents to relevant authority\n- **Complaint channel**: Report suspected provider non-compliance\n- **Compliance verification**: Check provider's authority interactions\n\n### For Member States\n- **Resource allocation**: Adequate authority staffing and budget\n- **Coordination**: Clear responsibilities among authorities\n- **Training**: Ongoing AI expertise development\n\n## Related Concepts\n\n- **AI Office** (AI-0132): EU-level GPAI supervision\n- **National Competent Authority** (AI-0136): Broader governance role\n- **Notified Body** (AI-0134): Third-party conformity assessor\n- **Serious Incident** (AI-0123): Reporting trigger\n\n## See Also\n\n- EU AI Act Articles 74-78 (Market Surveillance)\n- Market Surveillance Regulation (EU) 2019/1020\n- Commission Market Surveillance Guidance (expected 2026)\n\t- maturity:: draft\n\t- owl:class:: mv:MarketSurveillanceAuthority\n\t- owl:physicality:: ConceptualEntity\n\t- owl:role:: Concept\n\t- belongsToDomain:: [[MetaverseDomain]]\n- ## About Market Surveillance Authority\n\t- National authority responsible for carrying out market surveillance activities on AI systems, including inspections, testing, enforcement, and ensuring compliance with EU AI Act requirements within a Member State.\n\n## Source\n\n**Primary**: EU AI Act Article 74\n**Reference**: Market Surveillance Regulation (EU) 2019/1020\n\n## Regulatory Context\n\nMarket surveillance authorities are the front-line enforcement bodies for the EU AI Act at national level. Each Member State designates one or more authorities to monitor AI systems, investigate non-compliance, and take corrective action to protect health, safety, and fundamental rights.\n\n## Designation and Organisation (Article 74)\n\n### Member State Responsibility\nEach Member State must designate market surveillance authority with:\n- **Legal mandate**: National law establishing authority and powers\n- **Competence**: Technical expertise in AI systems\n- **Resources**: Sufficient staff, budget, equipment\n- **Independence**: Operational autonomy from political/economic interests\n\n### Multiple Authorities Possible\nMember States may designate:\n- **Horizontal authority**: Covering all AI systems\n- **Sectoral authorities**: Specialised by domain (finance, healthcare, law enforcement)\n\n**Coordination requirement**: Clear division of responsibilities, single point of contact\n\n### Notification to Commission\nMember States inform Commission of:\n- Designated authorities\n- Scope of responsibilities\n- Contact information\n\n## Powers and Responsibilities (Articles 74-77)\n\n### Market Surveillance Activities\n\n#### 1. Compliance Monitoring\n- **Market overview**: Track AI systems placed on market\n- **Risk assessment**: Identify high-risk non-compliant systems\n- **Sectoral analysis**: Monitor AI use in critical domains\n\n#### 2. Inspections and Testing (Article 75)\n\n**Powers**:\n- **Enter premises**: Providers, importers, distributors\n- **Access documentation**: Technical documentation, logs, quality management records\n- **Examine AI systems**: Test functionality, performance, safety\n- **Take samples**: For laboratory testing\n- **Interview personnel**: Question staff on compliance\n\n**Warrant**: May require judicial authorisation depending on Member State law\n\n#### 3. Information Requests (Article 76)\nRequire operators to provide:\n- Technical documentation\n- EU Declaration of Conformity\n- Quality management system documentation\n- Post-market monitoring data\n- Serious incident reports\n\n**Timeframe**: Reasonable deadline set by authority\n\n**Language**: In language easily understood by authority\n\n### Enforcement Measures (Article 77)\n\n#### Non-Compliance Finding\nWhen AI system does not comply with Act, authority may:\n\n##### Provisional Measures\n- **Corrective action order**: Require provider to bring into compliance within deadline\n- **Market restriction**: Prohibit making available until compliant\n- **Withdrawal order**: Require removal from market\n- **Recall order**: Require return of already deployed systems\n\n##### Definitive Measures (Article 77(2))\nIf non-compliance persists or serious:\n- **Market prohibition**: Ban system from EU market\n- **Public warning**: Alert deployers and public to risks\n- **Administrative fines**: Penalties per Article 99\n\n#### Risk Assessment Approach\nMeasures proportionate to:\n- **Severity**: Health, safety, fundamental rights impact\n- **Likelihood**: Probability of harm occurring\n- **Scope**: Number of affected persons\n- **Provider cooperation**: Willingness to remedy\n\n### Serious Incident Response (Article 73, 77)\n\n#### Upon Receiving Incident Report\n- **Immediate assessment**: Determine severity and scope\n- **Provider contact**: Request additional information\n- **Cross-border notification**: Alert other Member States if multi-state impact\n- **Public communication**: Warn deployers if imminent danger\n\n#### Investigation\n- **Root cause analysis**: Identify failure reason\n- **Systemic assessment**: Determine if similar systems affected\n- **Corrective measure evaluation**: Verify provider's remediation adequate\n\n## Cross-Border Coordination\n\n### Multi-State Incidents (Article 77(6))\nWhen AI system affects multiple Member States:\n- **Lead authority**: Member State where provider established\n- **Cooperation**: Share investigation findings\n- **Harmonised action**: Coordinated enforcement measures\n- **AI Office involvement**: Complex cases requiring EU-level coordination\n\n### Mutual Assistance\nAuthorities assist each other by:\n- **Information exchange**: Share compliance data, testing results\n- **Joint investigations**: Collaborative inspections\n- **Enforcement support**: Recognise and enforce other authorities' decisions\n\n### Dispute Resolution\nIf authorities disagree on:\n- Jurisdiction\n- Compliance interpretation\n- Enforcement approach\n\n**Resolution**: AI Board mediation, Commission arbitration\n\n## Relationship to Other Bodies\n\n### AI Office (Article 64)\n- **GPAI supervision**: AI Office handles general-purpose AI models\n- **Coordination**: AI Office coordinates multi-state surveillance\n- **Guidance**: AI Office provides interpretative guidance\n- **Reporting**: Authorities report enforcement to AI Office\n\n### AI Board (Articles 65-66)\n- **Member representation**: Authorities represent Member States on AI Board\n- **Best practices**: Share experiences via AI Board\n- **Guidelines**: Implement AI Board recommendations\n\n### Notified Bodies (Articles 29-39)\n- **Verification**: Check validity of notified body certificates\n- **Investigation**: Question notified body findings if non-compliance suspected\n- **Coordination**: Work with notifying authority on notified body issues\n\n### Sectoral Regulators\nCoordinate with:\n- **Financial supervisors**: Banking, insurance, securities AI\n- **Healthcare authorities**: Medical device AI\n- **Data protection authorities**: GDPR compliance\n- **Consumer protection agencies**: Unfair commercial practices\n\n## Information Systems\n\n### EU Database for Standalone High-Risk AI (Article 71)\nAuthorities have access to:\n- Registered high-risk AI systems\n- Provider information\n- Conformity certificates\n- Post-market monitoring plans\n\nAuthorities:\n- **Verify registration**: Check provider compliance\n- **Update entries**: Enforcement actions, serious incidents\n- **Query database**: Identify similar systems, patterns\n\n### Law Enforcement Database (Article 49)\nFor law enforcement, migration, border AI:\n- Public logging of use cases\n- Transparency mechanism\n- Authority oversight tool\n\n### Information Exchange Platform\nAuthorities use secure platform for:\n- Incident sharing\n- Investigation coordination\n- Best practice dissemination\n\n## Resources and Capacity Building\n\n### Technical Expertise Requirements\nMarket surveillance authorities need staff with:\n- **AI knowledge**: Machine learning, neural networks, algorithms\n- **Sector expertise**: Healthcare, finance, law enforcement domains\n- **Legal skills**: AI Act interpretation, enforcement procedures\n- **Testing capabilities**: Evaluation tools, benchmarking methodologies\n\n### Commission Support (Article 78)\nCommission provides:\n- **Training programmes**: AI Act implementation, technical assessment\n- **Testing facilities**: Access to AI evaluation infrastructure\n- **Guidance materials**: Enforcement manuals, compliance checklists\n- **Funding**: Digital Europe Programme, Horizon Europe\n\n### International Cooperation\nAuthorities engage with:\n- **Non-EU regulators**: US FTC/NIST, UK AI Safety Institute, Singapore IMDA\n- **Standards bodies**: ISO, IEC, IEEE\n- **Research institutions**: Universities, AI safety organisations\n\n## Penalties (Article 99)\n\nAuthorities may impose administrative fines:\n\n### Prohibited Practices (Article 99(3))\nUp to **€35 million or 7% of global annual turnover**\n\n### High-Risk Obligations (Article 99(4))\nUp to **€15 million or 3% of global annual turnover**\n\n### Information Obligations (Article 99(5))\nUp to €7.5 million or 1.5% of global annual turnover**\n\n### Considerations\n- Infringement severity and duration\n- Provider cooperation\n- Mitigating measures taken\n- Economic benefit derived\n- SME status (reduced penalties)\n\n## Transparency and Accountability\n\n### Public Reporting\nAuthorities publish:\n- **Annual reports**: Enforcement activities, key findings\n- **Non-compliance cases**: Anonymised case studies (learning tool)\n- **Statistical data**: Number of inspections, penalties, serious incidents\n\n### Stakeholder Engagement\nAuthorities consult with:\n- **Industry associations**: Compliance challenges, guidance needs\n- **Civil society**: Fundamental rights concerns\n- **Consumer organisations**: Deployer protection\n- **Research community**: Technical developments\n\n### Complaint Mechanisms (Article 85)\nIndividuals and organisations may:\n- **Lodge complaints**: Report suspected AI Act violations\n- **Provide evidence**: Support investigations\n- **Receive feedback**: Informed of outcomes (subject to confidentiality)\n\n## Practical Implications\n\n### For Providers\n- **Primary contact**: National authority where provider established\n- **Cooperation**: Respond promptly to information requests\n- **Proactive engagement**: Seek clarification before enforcement\n- **Documentation**: Maintain records accessible for inspections\n\n### For Deployers\n- **Report incidents**: Serious incidents to relevant authority\n- **Complaint channel**: Report suspected provider non-compliance\n- **Compliance verification**: Check provider's authority interactions\n\n### For Member States\n- **Resource allocation**: Adequate authority staffing and budget\n- **Coordination**: Clear responsibilities among authorities\n- **Training**: Ongoing AI expertise development\n\n## Related Concepts\n\n- **AI Office** (AI-0132): EU-level GPAI supervision\n- **National Competent Authority** (AI-0136): Broader governance role\n- **Notified Body** (AI-0134): Third-party conformity assessor\n- **Serious Incident** (AI-0123): Reporting trigger\n\n## See Also\n\n- EU AI Act Articles 74-78 (Market Surveillance)\n- Market Surveillance Regulation (EU) 2019/1020\n- Commission Market Surveillance Guidance (expected 2026)\n\t-\n\t- ### Original Content\n\t  collapsed:: true\n\t\t- ```\n# Market Surveillance Authority\n\t\t  \n\t\t  **Ontology ID**: AI-0135\n\t\t  **Category**: Regulatory Actors\n\t\t  **Last Updated**: 2025-10-27\n\t\t  \n\t\t  ## Definition\n\t\t  \n\t\t  National authority responsible for carrying out market surveillance activities on AI systems, including inspections, testing, enforcement, and ensuring compliance with EU AI Act requirements within a Member State.\n\t\t  \n\t\t  ## Source\n\t\t  \n\t\t  **Primary**: EU AI Act Article 74\n\t\t  **Reference**: Market Surveillance Regulation (EU) 2019/1020\n\t\t  \n\t\t  ## Regulatory Context\n\t\t  \n\t\t  Market surveillance authorities are the front-line enforcement bodies for the EU AI Act at national level. Each Member State designates one or more authorities to monitor AI systems, investigate non-compliance, and take corrective action to protect health, safety, and fundamental rights.\n\t\t  \n\t\t  ## Designation and Organisation (Article 74)\n\t\t  \n\t\t  ### Member State Responsibility\n\t\t  Each Member State must designate market surveillance authority with:\n\t\t  - **Legal mandate**: National law establishing authority and powers\n\t\t  - **Competence**: Technical expertise in AI systems\n\t\t  - **Resources**: Sufficient staff, budget, equipment\n\t\t  - **Independence**: Operational autonomy from political/economic interests\n\t\t  \n\t\t  ### Multiple Authorities Possible\n\t\t  Member States may designate:\n\t\t  - **Horizontal authority**: Covering all AI systems\n\t\t  - **Sectoral authorities**: Specialised by domain (finance, healthcare, law enforcement)\n\t\t  \n\t\t  **Coordination requirement**: Clear division of responsibilities, single point of contact\n\t\t  \n\t\t  ### Notification to Commission\n\t\t  Member States inform Commission of:\n\t\t  - Designated authorities\n\t\t  - Scope of responsibilities\n\t\t  - Contact information\n\t\t  \n\t\t  ## Powers and Responsibilities (Articles 74-77)\n\t\t  \n\t\t  ### Market Surveillance Activities\n\t\t  \n\t\t  #### 1. Compliance Monitoring\n\t\t  - **Market overview**: Track AI systems placed on market\n\t\t  - **Risk assessment**: Identify high-risk non-compliant systems\n\t\t  - **Sectoral analysis**: Monitor AI use in critical domains\n\t\t  \n\t\t  #### 2. Inspections and Testing (Article 75)\n\t\t  \n\t\t  **Powers**:\n\t\t  - **Enter premises**: Providers, importers, distributors\n\t\t  - **Access documentation**: Technical documentation, logs, quality management records\n\t\t  - **Examine AI systems**: Test functionality, performance, safety\n\t\t  - **Take samples**: For laboratory testing\n\t\t  - **Interview personnel**: Question staff on compliance\n\t\t  \n\t\t  **Warrant**: May require judicial authorisation depending on Member State law\n\t\t  \n\t\t  #### 3. Information Requests (Article 76)\n\t\t  Require operators to provide:\n\t\t  - Technical documentation\n\t\t  - EU Declaration of Conformity\n\t\t  - Quality management system documentation\n\t\t  - Post-market monitoring data\n\t\t  - Serious incident reports\n\t\t  \n\t\t  **Timeframe**: Reasonable deadline set by authority\n\t\t  \n\t\t  **Language**: In language easily understood by authority\n\t\t  \n\t\t  ### Enforcement Measures (Article 77)\n\t\t  \n\t\t  #### Non-Compliance Finding\n\t\t  When AI system does not comply with Act, authority may:\n\t\t  \n\t\t  ##### Provisional Measures\n\t\t  - **Corrective action order**: Require provider to bring into compliance within deadline\n\t\t  - **Market restriction**: Prohibit making available until compliant\n\t\t  - **Withdrawal order**: Require removal from market\n\t\t  - **Recall order**: Require return of already deployed systems\n\t\t  \n\t\t  ##### Definitive Measures (Article 77(2))\n\t\t  If non-compliance persists or serious:\n\t\t  - **Market prohibition**: Ban system from EU market\n\t\t  - **Public warning**: Alert deployers and public to risks\n\t\t  - **Administrative fines**: Penalties per Article 99\n\t\t  \n\t\t  #### Risk Assessment Approach\n\t\t  Measures proportionate to:\n\t\t  - **Severity**: Health, safety, fundamental rights impact\n\t\t  - **Likelihood**: Probability of harm occurring\n\t\t  - **Scope**: Number of affected persons\n\t\t  - **Provider cooperation**: Willingness to remedy\n\t\t  \n\t\t  ### Serious Incident Response (Article 73, 77)\n\t\t  \n\t\t  #### Upon Receiving Incident Report\n\t\t  - **Immediate assessment**: Determine severity and scope\n\t\t  - **Provider contact**: Request additional information\n\t\t  - **Cross-border notification**: Alert other Member States if multi-state impact\n\t\t  - **Public communication**: Warn deployers if imminent danger\n\t\t  \n\t\t  #### Investigation\n\t\t  - **Root cause analysis**: Identify failure reason\n\t\t  - **Systemic assessment**: Determine if similar systems affected\n\t\t  - **Corrective measure evaluation**: Verify provider's remediation adequate\n\t\t  \n\t\t  ## Cross-Border Coordination\n\t\t  \n\t\t  ### Multi-State Incidents (Article 77(6))\n\t\t  When AI system affects multiple Member States:\n\t\t  - **Lead authority**: Member State where provider established\n\t\t  - **Cooperation**: Share investigation findings\n\t\t  - **Harmonised action**: Coordinated enforcement measures\n\t\t  - **AI Office involvement**: Complex cases requiring EU-level coordination\n\t\t  \n\t\t  ### Mutual Assistance\n\t\t  Authorities assist each other by:\n\t\t  - **Information exchange**: Share compliance data, testing results\n\t\t  - **Joint investigations**: Collaborative inspections\n\t\t  - **Enforcement support**: Recognise and enforce other authorities' decisions\n\t\t  \n\t\t  ### Dispute Resolution\n\t\t  If authorities disagree on:\n\t\t  - Jurisdiction\n\t\t  - Compliance interpretation\n\t\t  - Enforcement approach\n\t\t  \n\t\t  **Resolution**: AI Board mediation, Commission arbitration\n\t\t  \n\t\t  ## Relationship to Other Bodies\n\t\t  \n\t\t  ### AI Office (Article 64)\n\t\t  - **GPAI supervision**: AI Office handles general-purpose AI models\n\t\t  - **Coordination**: AI Office coordinates multi-state surveillance\n\t\t  - **Guidance**: AI Office provides interpretative guidance\n\t\t  - **Reporting**: Authorities report enforcement to AI Office\n\t\t  \n\t\t  ### AI Board (Articles 65-66)\n\t\t  - **Member representation**: Authorities represent Member States on AI Board\n\t\t  - **Best practices**: Share experiences via AI Board\n\t\t  - **Guidelines**: Implement AI Board recommendations\n\t\t  \n\t\t  ### Notified Bodies (Articles 29-39)\n\t\t  - **Verification**: Check validity of notified body certificates\n\t\t  - **Investigation**: Question notified body findings if non-compliance suspected\n\t\t  - **Coordination**: Work with notifying authority on notified body issues\n\t\t  \n\t\t  ### Sectoral Regulators\n\t\t  Coordinate with:\n\t\t  - **Financial supervisors**: Banking, insurance, securities AI\n\t\t  - **Healthcare authorities**: Medical device AI\n\t\t  - **Data protection authorities**: GDPR compliance\n\t\t  - **Consumer protection agencies**: Unfair commercial practices\n\t\t  \n\t\t  ## Information Systems\n\t\t  \n\t\t  ### EU Database for Standalone High-Risk AI (Article 71)\n\t\t  Authorities have access to:\n\t\t  - Registered high-risk AI systems\n\t\t  - Provider information\n\t\t  - Conformity certificates\n\t\t  - Post-market monitoring plans\n\t\t  \n\t\t  Authorities:\n\t\t  - **Verify registration**: Check provider compliance\n\t\t  - **Update entries**: Enforcement actions, serious incidents\n\t\t  - **Query database**: Identify similar systems, patterns\n\t\t  \n\t\t  ### Law Enforcement Database (Article 49)\n\t\t  For law enforcement, migration, border AI:\n\t\t  - Public logging of use cases\n\t\t  - Transparency mechanism\n\t\t  - Authority oversight tool\n\t\t  \n\t\t  ### Information Exchange Platform\n\t\t  Authorities use secure platform for:\n\t\t  - Incident sharing\n\t\t  - Investigation coordination\n\t\t  - Best practice dissemination\n\t\t  \n\t\t  ## Resources and Capacity Building\n\t\t  \n\t\t  ### Technical Expertise Requirements\n\t\t  Market surveillance authorities need staff with:\n\t\t  - **AI knowledge**: Machine learning, neural networks, algorithms\n\t\t  - **Sector expertise**: Healthcare, finance, law enforcement domains\n\t\t  - **Legal skills**: AI Act interpretation, enforcement procedures\n\t\t  - **Testing capabilities**: Evaluation tools, benchmarking methodologies\n\t\t  \n\t\t  ### Commission Support (Article 78)\n\t\t  Commission provides:\n\t\t  - **Training programmes**: AI Act implementation, technical assessment\n\t\t  - **Testing facilities**: Access to AI evaluation infrastructure\n\t\t  - **Guidance materials**: Enforcement manuals, compliance checklists\n\t\t  - **Funding**: Digital Europe Programme, Horizon Europe\n\t\t  \n\t\t  ### International Cooperation\n\t\t  Authorities engage with:\n\t\t  - **Non-EU regulators**: US FTC/NIST, UK AI Safety Institute, Singapore IMDA\n\t\t  - **Standards bodies**: ISO, IEC, IEEE\n\t\t  - **Research institutions**: Universities, AI safety organisations\n\t\t  \n\t\t  ## Penalties (Article 99)\n\t\t  \n\t\t  Authorities may impose administrative fines:\n\t\t  \n\t\t  ### Prohibited Practices (Article 99(3))\n\t\t  Up to **€35 million or 7% of global annual turnover**\n\t\t  \n\t\t  ### High-Risk Obligations (Article 99(4))\n\t\t  Up to **€15 million or 3% of global annual turnover**\n\t\t  \n\t\t  ### Information Obligations (Article 99(5))\n\t\t  Up to €7.5 million or 1.5% of global annual turnover**\n\t\t  \n\t\t  ### Considerations\n\t\t  - Infringement severity and duration\n\t\t  - Provider cooperation\n\t\t  - Mitigating measures taken\n\t\t  - Economic benefit derived\n\t\t  - SME status (reduced penalties)\n\t\t  \n\t\t  ## Transparency and Accountability\n\t\t  \n\t\t  ### Public Reporting\n\t\t  Authorities publish:\n\t\t  - **Annual reports**: Enforcement activities, key findings\n\t\t  - **Non-compliance cases**: Anonymised case studies (learning tool)\n\t\t  - **Statistical data**: Number of inspections, penalties, serious incidents\n\t\t  \n\t\t  ### Stakeholder Engagement\n\t\t  Authorities consult with:\n\t\t  - **Industry associations**: Compliance challenges, guidance needs\n\t\t  - **Civil society**: Fundamental rights concerns\n\t\t  - **Consumer organisations**: Deployer protection\n\t\t  - **Research community**: Technical developments\n\t\t  \n\t\t  ### Complaint Mechanisms (Article 85)\n\t\t  Individuals and organisations may:\n\t\t  - **Lodge complaints**: Report suspected AI Act violations\n\t\t  - **Provide evidence**: Support investigations\n\t\t  - **Receive feedback**: Informed of outcomes (subject to confidentiality)\n\t\t  \n\t\t  ## Practical Implications\n\t\t  \n\t\t  ### For Providers\n\t\t  - **Primary contact**: National authority where provider established\n\t\t  - **Cooperation**: Respond promptly to information requests\n\t\t  - **Proactive engagement**: Seek clarification before enforcement\n\t\t  - **Documentation**: Maintain records accessible for inspections\n\t\t  \n\t\t  ### For Deployers\n\t\t  - **Report incidents**: Serious incidents to relevant authority\n\t\t  - **Complaint channel**: Report suspected provider non-compliance\n\t\t  - **Compliance verification**: Check provider's authority interactions\n\t\t  \n\t\t  ### For Member States\n\t\t  - **Resource allocation**: Adequate authority staffing and budget\n\t\t  - **Coordination**: Clear responsibilities among authorities\n\t\t  - **Training**: Ongoing AI expertise development\n\t\t  \n\t\t  ## Related Concepts\n\t\t  \n\t\t  - **AI Office** (AI-0132): EU-level GPAI supervision\n\t\t  - **National Competent Authority** (AI-0136): Broader governance role\n\t\t  - **Notified Body** (AI-0134): Third-party conformity assessor\n\t\t  - **Serious Incident** (AI-0123): Reporting trigger\n\t\t  \n\t\t  ## See Also\n\t\t  \n\t\t  - EU AI Act Articles 74-78 (Market Surveillance)\n\t\t  - Market Surveillance Regulation (EU) 2019/1020\n\t\t  - Commission Market Surveillance Guidance (expected 2026)\n\t\t  \n\t\t  ```\n\n\n## Current Landscape (2025)\n\n- Industry adoption and implementations\n  - Metaverse platforms continue to evolve with focus on interoperability and open standards\n  - Web3 integration accelerating with decentralised identity and asset ownership\n  - Enterprise adoption growing in virtual collaboration, training, and digital twins\n  - UK companies increasingly active in metaverse development and immersive technologies\n\n- Technical capabilities\n  - Real-time rendering at photorealistic quality levels\n  - Low-latency networking enabling seamless multi-user experiences\n  - AI-driven content generation and procedural world building\n  - Spatial audio and haptics enhancing immersion\n\n- UK and North England context\n  - Manchester: Digital Innovation Factory supports metaverse startups and research\n  - Leeds: Holovis leads in immersive experiences for entertainment and training\n  - Newcastle: University research in spatial computing and interactive systems\n  - Sheffield: Advanced manufacturing using digital twin technology\n\n- Standards and frameworks\n  - Metaverse Standards Forum driving interoperability protocols\n  - WebXR enabling browser-based immersive experiences\n  - glTF and USD for 3D asset interchange\n  - Open Metaverse Interoperability Group defining cross-platform standards\n\n## Metadata\n\n- **Last Updated**: 2025-11-16\n- **Review Status**: Automated remediation with 2025 context\n- **Verification**: Academic sources verified\n- **Regional Context**: UK/North England where applicable",
  "properties": {
    "id": "market-surveillance-authority-ontology",
    "collapsed": "true",
    "- ontology": "true",
    "- term-id": "AI-0512",
    "- preferred-term": "Market Surveillance Authority",
    "- source-domain": "metaverse",
    "- status": "draft",
    "- public-access": "true",
    "- definition": "National authority responsible for carrying out market surveillance activities on AI systems, including inspections, testing, enforcement, and ensuring compliance with EU AI Act requirements within a Member State."
  },
  "backlinks": [],
  "wiki_links": [
    "MetaverseDomain"
  ],
  "ontology": {
    "term_id": "AI-0512",
    "preferred_term": "Market Surveillance Authority",
    "definition": "National authority responsible for carrying out market surveillance activities on AI systems, including inspections, testing, enforcement, and ensuring compliance with EU AI Act requirements within a Member State.",
    "source_domain": "metaverse",
    "maturity_level": null,
    "authority_score": null
  }
}