{
  "title": "Maximum Sequence Length",
  "content": "- ### OntologyBlock\n  id:: maximum-sequence-length-ontology\n  collapsed:: true\n\t- ontology:: true\n\t- term-id:: AI-0239\n\t- preferred-term:: Maximum Sequence Length\n\t- source-domain:: ai\n\t- status:: draft\n    - public-access:: true\n\t- definition:: The longest sequence of tokens that a model can process in a single forward pass, constrained by positional encoding scheme and computational resources.\n\n\n\n\n## Academic Context\n\n- Brief contextual overview  \n\t- Maximum sequence length denotes the longest sequence of tokens a language model can process in a single forward pass. It is fundamentally determined by the model’s architecture, particularly its positional encoding scheme, and constrained by available computational resources.  \n\t- This parameter is crucial for tasks involving long-range dependencies such as document summarisation, multi-turn dialogue, and code generation, where retaining extensive context improves performance.  \n- Key developments and current state  \n\t- Early transformer models, including the original Vaswani et al. (2017) architecture, were limited to a few thousand tokens due to the quadratic scaling of memory and computation in self-attention mechanisms.  \n\t- Recent advances have introduced techniques such as sparse attention, local attention, memory-efficient attention, and sequence parallelism, enabling models to handle sequences extending into millions of tokens without prohibitive resource demands.  \n\t- The field remains highly dynamic, with ongoing research pushing the boundaries of maximum sequence length while balancing computational feasibility.  \n- Academic foundations  \n\t- The concept originates from the transformer architecture introduced by Vaswani et al. (2017), which uses positional encodings to maintain token order within sequences (DOI: 10.48550/arXiv.1706.03762).  \n\t- Subsequent research has explored various architectural modifications and training strategies to extend sequence length, including modified positional encoding schemes and attention mechanisms designed to reduce computational complexity (Wang et al., 2024, DOI: 10.48550/arXiv.2402.02244).  \n\n## Current Landscape (2025)\n\n- Industry adoption and implementations  \n\t- Leading AI organisations have developed models supporting extended sequence lengths, reflecting the importance of long-context processing in real-world applications.  \n\t- Meta’s Llama 4 series includes models supporting sequence lengths up to 10 million tokens, demonstrating the feasibility of ultra-long context windows.  \n\t- Salesforce’s XGen-7B model supports sequences up to 8,192 tokens, with ongoing research into extending this limit.  \n\t- Snowflake’s Arctic Long Sequence Training (ALST) framework facilitates training on extended sequences, improving model capabilities for large-scale data processing.  \n- UK and North England examples where relevant  \n\t- UK-based AI research centres, including those in Manchester and Leeds, contribute to advancing efficient transformer architectures that enable longer sequence processing with reduced computational overhead.  \n\t- The Alan Turing Institute in London supports projects investigating scalable attention mechanisms and memory-efficient models, relevant to extending maximum sequence length.  \n- Technical capabilities and limitations  \n\t- Despite advances, increasing maximum sequence length remains computationally expensive due to the quadratic complexity of traditional attention mechanisms, necessitating innovations like sparse or linear attention.  \n\t- Practical deployments often balance sequence length with latency and cost, especially in commercial applications where inference speed and resource consumption are critical.  \n- Standards and frameworks  \n\t- There is no universal standard for maximum sequence length; it varies by model architecture and use case. However, frameworks such as Hugging Face Transformers provide configurable parameters to set or extend sequence length within model-specific limits.  \n\n## Research & Literature\n\n- Key academic papers and sources  \n\t- Vaswani et al., 2017. \"Attention Is All You Need.\" Advances in Neural Information Processing Systems. DOI: 10.48550/arXiv.1706.03762  \n\t- Wang et al., 2024. \"Beyond the Limits: A Survey of Techniques to Extend the Context Length in Large Language Models.\" arXiv preprint. DOI: 10.48550/arXiv.2402.02244  \n\t- Additional relevant surveys and technical reports on efficient attention mechanisms and positional encoding modifications.  \n- Ongoing research directions  \n\t- Exploration of novel positional encoding schemes that scale linearly with sequence length.  \n\t- Development of hybrid attention models combining local and global context to optimise resource use.  \n\t- Investigation into hardware-aware model designs to better leverage emerging accelerators for long-sequence processing.  \n\n## UK Context\n\n- British contributions and implementations  \n\t- The Alan Turing Institute and universities such as Manchester and Leeds actively research transformer efficiency and sequence length extension, contributing to both theoretical and applied advances.  \n\t- UK AI startups focus on optimising large language models for enterprise applications, often addressing sequence length constraints in domain-specific contexts.  \n- North England innovation hubs  \n\t- Manchester’s AI research community has produced work on memory-efficient transformer variants, relevant to extending maximum sequence length without excessive resource use.  \n\t- Leeds hosts initiatives integrating AI with large-scale data analytics, where handling long sequences is essential.  \n- Regional case studies  \n\t- Collaborative projects between academia and industry in North England have demonstrated improved document understanding systems leveraging extended sequence lengths.  \n\n## Future Directions\n\n- Emerging trends and developments  \n\t- Continued refinement of attention mechanisms to reduce computational complexity from quadratic to near-linear with respect to sequence length.  \n\t- Integration of retrieval-augmented generation (RAG) techniques to effectively extend context without increasing raw sequence length.  \n\t- Hardware-software co-design approaches to better support ultra-long sequences in inference and training.  \n- Anticipated challenges  \n\t- Balancing model accuracy with computational cost and latency in real-time applications.  \n\t- Managing memory constraints and energy consumption as sequence lengths grow.  \n\t- Ensuring robustness and generalisation when processing very long contexts.  \n- Research priorities  \n\t- Developing scalable positional encoding methods that maintain performance over millions of tokens.  \n\t- Creating benchmarks and standardised evaluation protocols for long-sequence processing.  \n\t- Investigating domain-specific adaptations where long context is critical, such as legal or biomedical text analysis.  \n\n## References\n\n1. Vaswani, A., Shazeer, N., Parmar, N., Uszkoreit, J., Jones, L., Gomez, A. N., Kaiser, Ł., & Polosukhin, I. (2017). Attention Is All You Need. *Advances in Neural Information Processing Systems*, 30. https://doi.org/10.48550/arXiv.1706.03762  \n2. Wang, X., Salmani, M., Omidi, P., Ren, X., Rezagholizadeh, M., & Eshaghi, A. (2024). Beyond the Limits: A Survey of Techniques to Extend the Context Length in Large Language Models. *arXiv preprint*. https://doi.org/10.48550/arXiv.2402.02244  \n3. DataNorth AI. (2024). Context Length in LLMs: What Is It and Why It Is Important? Retrieved November 2025, from https://datanorth.ai/blog/context-length  \n4. AGI Sphere. (2024). Context length in LLMs: All you need to know. Retrieved November 2025, from https://agi-sphere.com/context-length  \n\n## Metadata\n\n- Last Updated: 2025-11-11  \n- Review Status:",
  "properties": {
    "id": "maximum-sequence-length-ontology",
    "collapsed": "true",
    "- ontology": "true",
    "- term-id": "AI-0239",
    "- preferred-term": "Maximum Sequence Length",
    "- source-domain": "ai",
    "- status": "draft",
    "- public-access": "true",
    "- definition": "The longest sequence of tokens that a model can process in a single forward pass, constrained by positional encoding scheme and computational resources."
  },
  "backlinks": [],
  "wiki_links": [],
  "ontology": {
    "term_id": "AI-0239",
    "preferred_term": "Maximum Sequence Length",
    "definition": "The longest sequence of tokens that a model can process in a single forward pass, constrained by positional encoding scheme and computational resources.",
    "source_domain": "ai",
    "maturity_level": null,
    "authority_score": null
  }
}