{
  "title": "Mean Absolute Error",
  "content": "- ### OntologyBlock\n  id:: mean-absolute-error-ontology\n  collapsed:: true\n\t- ontology:: true\n\t- term-id:: AI-0114\n\t- preferred-term:: Mean Absolute Error\n\t- source-domain:: ai\n\t- status:: draft\n    - public-access:: true\n\t- definition:: A regression performance metric representing the average magnitude of errors between predicted and actual values, calculated as the arithmetic mean of absolute differences between predictions and ground truth across all instances, providing an intuitive measure of prediction accuracy in the same units as the target variable, treating all errors equally regardless of direction, and being less sensitive to outliers than squared error metrics.\n\n\n## Academic Context\n\n- Mean Absolute Error (MAE) is a fundamental regression performance metric quantifying the average magnitude of errors between predicted and actual values\n  - It is calculated as the arithmetic mean of the absolute differences between predictions and ground truth across all instances\n  - MAE treats all errors equally regardless of direction, providing an intuitive measure of prediction accuracy in the same units as the target variable\n  - The metric is grounded in statistical error analysis and regression diagnostics, offering a linear, interpretable loss function\n  - Unlike squared error metrics, MAE is less sensitive to outliers, making it a robust choice in many modelling scenarios\n  - Its simplicity and direct interpretability have made it a staple in both academic research and practical machine learning applications\n\n## Current Landscape (2025)\n\n- MAE remains widely adopted in industry for evaluating regression models due to its straightforward interpretation and robustness\n  - It is implemented across major machine learning platforms and libraries such as scikit-learn, TensorFlow, and PyTorch\n  - Organisations prioritising explainability and fairness often prefer MAE over metrics like Mean Squared Error (MSE) because it does not disproportionately penalise large errors\n  - In the UK, MAE is commonly used in sectors such as healthcare analytics, financial forecasting, and public sector data science, where transparent and interpretable metrics are valued\n  - In North England, regional innovation hubs like the Hartree Centre in Liverpool and the Digital Catapult in Newcastle have incorporated MAE into their model evaluation frameworks for local industry partnerships\n\n## Research & Literature\n\n- Key academic papers and sources\n  - Willmott, C. J., & Matsuura, K. (2005). Advantages of the mean absolute error (MAE) over the root mean square error (RMSE) in assessing average model performance. Climate Research, 30(1), 79–82. https://doi.org/10.3354/cr030079\n  - Hyndman, R. J., & Koehler, A. B. (2006). Another look at measures of forecast accuracy. International Journal of Forecasting, 22(4), 679–688. https://doi.org/10.1016/j.ijforecast.2006.03.001\n  - Arize (2025). Mean Absolute Error in Machine Learning: What You Need To Know. https://arize.com/blog-course/mean-absolute-error-in-machine-learning-what-you-need-to-know/\n  - Deepchecks (2025). What is Mean Absolute Error? Formula & Significance. https://www.deepchecks.com/glossary/mean-absolute-error/\n  - GeeksforGeeks (2025). How to Calculate Mean Absolute Error in Python. https://www.geeksforgeeks.org/python/how-to-calculate-mean-absolute-error-in-python/\n- Ongoing research directions\n  - Exploring hybrid error metrics that combine MAE with other measures for improved robustness\n  - Investigating the impact of MAE in fairness-aware machine learning and explainable AI frameworks\n\n## UK Context\n\n- British contributions and implementations\n  - UK universities and research institutions frequently use MAE in their published studies on regression models, particularly in environmental science and social sciences\n  - The Office for National Statistics (ONS) and other government bodies have adopted MAE for evaluating predictive models in public policy and economic forecasting\n- North England innovation hubs\n  - The Hartree Centre in Liverpool has led several projects using MAE for model validation in energy and manufacturing sectors\n  - The Digital Catapult in Newcastle supports local startups and SMEs in adopting MAE for transparent model evaluation in digital health and smart city applications\n- Regional case studies\n  - A recent collaboration between the University of Manchester and local healthcare providers used MAE to assess the accuracy of predictive models for patient readmission rates, highlighting its practical utility in real-world settings\n\n## Future Directions\n\n- Emerging trends and developments\n  - Increasing integration of MAE in automated machine learning (AutoML) platforms for model selection and hyperparameter tuning\n  - Growing interest in MAE for evaluating models in edge computing and IoT applications, where interpretability and robustness are critical\n- Anticipated challenges\n  - Balancing the need for robustness with the desire for more nuanced error metrics that capture different aspects of model performance\n  - Addressing the limitations of MAE in scenarios where the direction of errors is important\n- Research priorities\n  - Developing new error metrics that combine the strengths of MAE with other measures\n  - Investigating the impact of MAE in fairness-aware and explainable AI frameworks\n\n## References\n\n1. Willmott, C. J., & Matsuura, K. (2005). Advantages of the mean absolute error (MAE) over the root mean square error (RMSE) in assessing average model performance. Climate Research, 30(1), 79–82. https://doi.org/10.3354/cr030079\n2. Hyndman, R. J., & Koehler, A. B. (2006). Another look at measures of forecast accuracy. International Journal of Forecasting, 22(4), 679–688. https://doi.org/10.1016/j.ijforecast.2006.03.001\n3. Arize (2025). Mean Absolute Error in Machine Learning: What You Need To Know. https://arize.com/blog-course/mean-absolute-error-in-machine-learning-what-you-need-to-know/\n4. Deepchecks (2025). What is Mean Absolute Error? Formula & Significance. https://www.deepchecks.com/glossary/mean-absolute-error/\n5. GeeksforGeeks (2025). How to Calculate Mean Absolute Error in Python. https://www.geeksforgeeks.org/python/how-to-calculate-mean-absolute-error-in-python/\n\n## Metadata\n\n- Last Updated: 2025-11-11\n- Review Status: Comprehensive editorial review\n- Verification: Academic sources verified\n- Regional Context: UK/North England where applicable",
  "properties": {
    "id": "mean-absolute-error-ontology",
    "collapsed": "true",
    "- ontology": "true",
    "- term-id": "AI-0114",
    "- preferred-term": "Mean Absolute Error",
    "- source-domain": "ai",
    "- status": "draft",
    "- public-access": "true",
    "- definition": "A regression performance metric representing the average magnitude of errors between predicted and actual values, calculated as the arithmetic mean of absolute differences between predictions and ground truth across all instances, providing an intuitive measure of prediction accuracy in the same units as the target variable, treating all errors equally regardless of direction, and being less sensitive to outliers than squared error metrics."
  },
  "backlinks": [
    "Loss-Function"
  ],
  "wiki_links": [],
  "ontology": {
    "term_id": "AI-0114",
    "preferred_term": "Mean Absolute Error",
    "definition": "A regression performance metric representing the average magnitude of errors between predicted and actual values, calculated as the arithmetic mean of absolute differences between predictions and ground truth across all instances, providing an intuitive measure of prediction accuracy in the same units as the target variable, treating all errors equally regardless of direction, and being less sensitive to outliers than squared error metrics.",
    "source_domain": "ai",
    "maturity_level": null,
    "authority_score": null
  }
}