{
  "title": "Meeting Transcription",
  "content": "- ### OntologyBlock\n  id:: meetingtranscription-ontology\n  collapsed:: true\n\n  - **Identification**\n    - domain-prefix:: AI\n    - sequence-number:: 0855\n    - filename-history:: [\"AI-0855-meetingtranscription.md\"]\n    - public-access:: true\n    - ontology:: true\n    - term-id:: AI-0855\n    - preferred-term:: Meeting Transcription\n    - source-domain:: ai\n    - status:: complete\n    - version:: 1.0.0\n    - last-updated:: 2025-11-13\n\n  - **Definition**\n    - definition:: \n    - maturity:: established\n    - source:: Chimera Prime Research\n    - authority-score:: 0.95\n\n  - **Semantic Classification**\n    - owl:class:: ai:MeetingTranscription\n    - belongsToDomain:: [[Artificial Intelligence]]\n\n  - #### OWL Restrictions\n    \n\n  - #### CrossDomainBridges\n    - bridges-to:: [[SpeechRecognition]] via is-subclass-of\n\n  - \n### Relationships\n- is-subclass-of:: [[SpeechProcessing]]",
  "properties": {
    "id": "meetingtranscription-ontology",
    "collapsed": "true",
    "- domain-prefix": "AI",
    "- sequence-number": "0855",
    "- filename-history": "[\"AI-0855-meetingtranscription.md\"]",
    "- public-access": "true",
    "- ontology": "true",
    "- term-id": "AI-0855",
    "- preferred-term": "Meeting Transcription",
    "- source-domain": "ai",
    "- status": "complete",
    "- version": "1.0.0",
    "- last-updated": "2025-11-13",
    "- definition": "",
    "- maturity": "established",
    "- source": "Chimera Prime Research",
    "- authority-score": "0.95",
    "- owl:class": "ai:MeetingTranscription",
    "- belongsToDomain": "[[Artificial Intelligence]]",
    "- bridges-to": "[[SpeechRecognition]] via is-subclass-of"
  },
  "backlinks": [],
  "wiki_links": [
    "SpeechProcessing",
    "SpeechRecognition",
    "Artificial Intelligence"
  ],
  "ontology": {
    "term_id": "AI-0855",
    "preferred_term": "Meeting Transcription",
    "definition": "",
    "source_domain": "ai",
    "maturity_level": null,
    "authority_score": 0.95
  }
}