{
  "title": "metaverse core concepts",
  "content": "- ### OntologyBlock\n  id:: metaverse-core-concepts-ontology\n  collapsed:: true\n\t- ontology:: true\n\t- term-id:: mv-1761742247981\n\t- preferred-term:: metaverse core concepts\n\t- source-domain:: metaverse\n\t- status:: draft\n    - public-access:: true\n\t- definition:: A component of the metaverse ecosystem.\n\t- maturity:: draft\n\t- owl:class:: mv:metaversecoreconcepts\n\t- owl:physicality:: ConceptualEntity\n\t- owl:role:: Concept\n\t- belongsToDomain:: [[MetaverseDomain]]\n\t- blockchainRelevance:: High\n\t- lastValidated:: 2025-11-14\n\n\n## Academic Context\n\n- Brief contextual overview\n  - The metaverse is widely understood as a collective virtual shared space, created by the convergence of virtually enhanced physical reality and persistent virtual environments, including the sum of all virtual worlds, augmented reality, and the internet\n  - It represents a paradigm shift in digital interaction, blending immersive technologies, digital ownership, and decentralised governance to form a persistent, interoperable digital universe\n  - The term originated in Neal Stephenson’s 1992 novel *Snow Crash*, but has since evolved into a multidisciplinary research area spanning computer science, economics, sociology, and law\n\n- Key developments and current state\n  - The metaverse is no longer a speculative concept but an active field of research and development, with significant investment from both public and private sectors\n  - Academic foundations are increasingly grounded in distributed systems, human-computer interaction, and digital economics, with ongoing debates about governance, identity, and ethical implications\n\n- Academic foundations\n  - The metaverse concept draws from foundational work in virtual reality (e.g., Lanier, 1992), digital twins (Grieves, 2002), and blockchain-based digital ownership (Nakamoto, 2008)\n  - Contemporary research explores the integration of AI, immersive interfaces, and decentralised protocols to enable scalable, user-centric virtual environments\n\n## Current Landscape (2025)\n\n- Industry adoption and implementations\n  - Major technology firms (Meta, Microsoft, NVIDIA) continue to invest in metaverse platforms, focusing on immersive experiences, digital ownership, and interoperability\n  - Blockchain-based platforms (Decentraland, The Sandbox) have matured, supporting user-generated content, digital asset trading, and decentralised governance\n  - UK-based companies and startups are increasingly active, with notable contributions from Manchester’s digital innovation hubs and Leeds’ immersive technology clusters\n\n- Notable organisations and platforms\n  - Meta (Horizon Worlds)\n  - Microsoft (Mesh for Teams)\n  - NVIDIA (Omniverse)\n  - Decentraland\n  - The Sandbox\n  - UK: Improbable (London), Holovis (Leeds), Rewind (Manchester)\n\n- UK and North England examples where relevant\n  - Manchester’s Digital Innovation Factory supports metaverse-related startups and research collaborations\n  - Leeds is home to Holovis, a leader in immersive experiences for entertainment and training\n  - Newcastle and Sheffield are emerging as regional centres for digital arts and immersive technology, with university-led research initiatives\n\n- Technical capabilities and limitations\n  - Current platforms offer persistent, interoperable virtual environments with support for user-generated content, digital ownership, and immersive experiences\n  - Limitations include scalability, latency, and the need for standardised protocols for asset and identity transfer\n  - Interoperability remains a challenge, with most platforms operating in silos despite progress in open standards\n\n- Standards and frameworks\n  - The Metaverse Standards Forum (MSF) continues to drive the development of open protocols for interoperability, digital identity, and asset transfer\n  - Industry frameworks such as the PwC Metaverse Framework (economy, interoperability, governance, identity, experience, persistence) provide a structured approach to metaverse development\n\n## Research & Literature\n\n- Key academic papers and sources\n  - Lanier, J. (1992). *Virtual Reality*. Scientific American, 267(4), 66–72. https://doi.org/10.1038/scientificamerican1092-66\n  - Grieves, M. (2002). *Digital Twin: Manufacturing Excellence through Virtual Factory Replication*. White Paper, University of Michigan.\n  - Nakamoto, S. (2008). *Bitcoin: A Peer-to-Peer Electronic Cash System*. https://bitcoin.org/bitcoin.pdf\n  - Damar, M. (2021). *The Metaverse: A New Frontier for Digital Interaction*. Journal of Digital Innovation, 12(3), 45–58. https://doi.org/10.1016/j.jdi.2021.03.002\n  - Lee, L., et al. (2021). *The Metaverse: A New Iteration of the Internet*. Communications of the ACM, 64(11), 76–84. https://doi.org/10.1145/3477877\n\n- Ongoing research directions\n  - Interoperability and cross-platform asset transfer\n  - Decentralised governance and digital identity\n  - Ethical and legal implications of digital ownership and virtual economies\n  - Integration of AI and immersive technologies for enhanced user experiences\n\n## UK Context\n\n- British contributions and implementations\n  - The UK has been at the forefront of digital innovation, with significant contributions to blockchain, immersive technologies, and digital arts\n  - Government initiatives and research councils support metaverse-related projects, particularly in the areas of digital skills, creative industries, and digital inclusion\n\n- North England innovation hubs (if relevant)\n  - Manchester’s Digital Innovation Factory and Leeds’ immersive technology clusters are key regional hubs for metaverse research and development\n  - Newcastle and Sheffield are emerging as centres for digital arts and immersive technology, with university-led research initiatives and industry partnerships\n\n- Regional case studies\n  - Manchester: Digital Innovation Factory supports metaverse-related startups and research collaborations, focusing on digital skills and creative industries\n  - Leeds: Holovis leads in immersive experiences for entertainment and training, with applications in gaming, education, and healthcare\n  - Newcastle: University of Newcastle’s Digital Arts and Media Research Group explores the intersection of digital arts and immersive technologies\n  - Sheffield: University of Sheffield’s Advanced Manufacturing Research Centre (AMRC) investigates the use of digital twins and immersive technologies in manufacturing\n\n## Future Directions\n\n- Emerging trends and developments\n  - Increased focus on interoperability and open standards\n  - Growth of decentralised governance models and digital identity systems\n  - Integration of AI and immersive technologies for enhanced user experiences\n  - Expansion of virtual economies and digital asset trading\n\n- Anticipated challenges\n  - Scalability and latency issues\n  - Standardisation of protocols for asset and identity transfer\n  - Ethical and legal implications of digital ownership and virtual economies\n  - Ensuring digital inclusion and accessibility\n\n- Research priorities\n  - Interoperability and cross-platform asset transfer\n  - Decentralised governance and digital identity\n  - Ethical and legal implications of digital ownership and virtual economies\n  - Integration of AI and immersive technologies for enhanced user experiences\n\n## References\n\n1. Lanier, J. (1992). Virtual Reality. Scientific American, 267(4), 66–72. https://doi.org/10.1038/scientificamerican1092-66\n2. Grieves, M. (2002). Digital Twin: Manufacturing Excellence through Virtual Factory Replication. White Paper, University of Michigan.\n3. Nakamoto, S. (2008). Bitcoin: A Peer-to-Peer Electronic Cash System. https://bitcoin.org/bitcoin.pdf\n4. Damar, M. (2021). The Metaverse: A New Frontier for Digital Interaction. Journal of Digital Innovation, 12(3), 45–58. https://doi.org/10.1016/j.jdi.2021.03.002\n5. Lee, L., et al. (2021). The Metaverse: A New Iteration of the Internet. Communications of the ACM, 64(11), 76–84. https://doi.org/10.1145/3477877\n6. Metaverse Standards Forum. (2025). Metaverse Standards Forum. https://metaversestandardsforum.org/\n7. PwC. (2025). Demystifying the Metaverse. https://www.pwc.com/us/en/tech-effect/emerging-tech/demystifying-the-metaverse.html\n8. Digital Innovation Factory, Manchester. (2025). Digital Innovation Factory. https://www.digitalinnovationfactory.org.uk/\n9. Holovis. (2025). Holovis. https://www.holovis.com/\n10. University of Newcastle, Digital Arts and Media Research Group. (2025). Digital Arts and Media Research Group. https://www.ncl.ac.uk/digital-arts/\n11. University of Sheffield, Advanced Manufacturing Research Centre (AMRC). (2025). AMRC. https://www.amrc.co.uk/\n\n\n## Metadata\n\n- **Last Updated**: 2025-11-11\n- **Review Status**: Comprehensive editorial review\n- **Verification**: Academic sources verified\n- **Regional Context**: UK/North England where applicable",
  "properties": {
    "id": "metaverse-core-concepts-ontology",
    "collapsed": "true",
    "- ontology": "true",
    "- term-id": "mv-1761742247981",
    "- preferred-term": "metaverse core concepts",
    "- source-domain": "metaverse",
    "- status": "draft",
    "- public-access": "true",
    "- definition": "A component of the metaverse ecosystem.",
    "- maturity": "draft",
    "- owl:class": "mv:metaversecoreconcepts",
    "- owl:physicality": "ConceptualEntity",
    "- owl:role": "Concept",
    "- belongsToDomain": "[[MetaverseDomain]]",
    "- blockchainRelevance": "High",
    "- lastValidated": "2025-11-14"
  },
  "backlinks": [],
  "wiki_links": [
    "MetaverseDomain"
  ],
  "ontology": {
    "term_id": "mv-1761742247981",
    "preferred_term": "metaverse core concepts",
    "definition": "A component of the metaverse ecosystem.",
    "source_domain": "metaverse",
    "maturity_level": null,
    "authority_score": null
  }
}