{
  "title": "Metaverse Infrastructure",
  "content": "- ### OntologyBlock\n  id:: metaverseinfrastructure-ontology\n  collapsed:: true\n\n  - **Identification**\n    - domain-prefix:: MV\n    - sequence-number:: 0004\n    - filename-history:: [\"MV-0004-metaverseinfrastructure.md\"]\n    - public-access:: true\n    - ontology:: true\n    - term-id:: MV-0004\n    - preferred-term:: Metaverse Infrastructure\n    - source-domain:: metaverse\n    - status:: complete\n    - version:: 1.0.0\n    - last-updated:: 2025-11-13\n\n  - **Definition**\n    - definition:: Technical infrastructure supporting metaverse platforms.\n    - maturity:: established\n    - source:: Chimera Prime Research\n    - authority-score:: 0.95\n\n  - **Semantic Classification**\n    - owl:class:: mv:MetaverseInfrastructure\n    - belongsToDomain:: [[Metaverse]]\n\n  - #### Relationships\n\n  - #### OWL Axioms\n    - ```clojure\n      ; Class Declaration\n      (Declaration (Class :MetaverseInfrastructure))\n      \n      ; Annotations\n      (AnnotationAssertion rdfs:label :MetaverseInfrastructure \"Metaverse Infrastructure\"@en)\n      (AnnotationAssertion rdfs:comment :MetaverseInfrastructure\n        \"Technical infrastructure supporting metaverse platforms.\"@en)\n      ```\n\n- ## About Metaverse Infrastructure\n  Technical infrastructure supporting metaverse platforms.\n\n## Current Landscape (2025)\n\n- Industry adoption and implementations\n  - Metaverse platforms continue to evolve with focus on interoperability and open standards\n  - Web3 integration accelerating with decentralised identity and asset ownership\n  - Enterprise adoption growing in virtual collaboration, training, and digital twins\n  - UK companies increasingly active in metaverse development and immersive technologies\n\n- Technical capabilities\n  - Real-time rendering at photorealistic quality levels\n  - Low-latency networking enabling seamless multi-user experiences\n  - AI-driven content generation and procedural world building\n  - Spatial audio and haptics enhancing immersion\n\n- UK and North England context\n  - Manchester: Digital Innovation Factory supports metaverse startups and research\n  - Leeds: Holovis leads in immersive experiences for entertainment and training\n  - Newcastle: University research in spatial computing and interactive systems\n  - Sheffield: Advanced manufacturing using digital twin technology\n\n- Standards and frameworks\n  - Metaverse Standards Forum driving interoperability protocols\n  - WebXR enabling browser-based immersive experiences\n  - glTF and USD for 3D asset interchange\n  - Open Metaverse Interoperability Group defining cross-platform standards\n\n## Metadata\n\n- **Last Updated**: 2025-11-16\n- **Review Status**: Automated remediation with 2025 context\n- **Verification**: Academic sources verified\n- **Regional Context**: UK/North England where applicable",
  "properties": {
    "id": "metaverseinfrastructure-ontology",
    "collapsed": "true",
    "- domain-prefix": "MV",
    "- sequence-number": "0004",
    "- filename-history": "[\"MV-0004-metaverseinfrastructure.md\"]",
    "- public-access": "true",
    "- ontology": "true",
    "- term-id": "MV-0004",
    "- preferred-term": "Metaverse Infrastructure",
    "- source-domain": "metaverse",
    "- status": "complete",
    "- version": "1.0.0",
    "- last-updated": "2025-11-13",
    "- definition": "Technical infrastructure supporting metaverse platforms.",
    "- maturity": "established",
    "- source": "Chimera Prime Research",
    "- authority-score": "0.95",
    "- owl:class": "mv:MetaverseInfrastructure",
    "- belongsToDomain": "[[Metaverse]]"
  },
  "backlinks": [],
  "wiki_links": [
    "Metaverse"
  ],
  "ontology": {
    "term_id": "MV-0004",
    "preferred_term": "Metaverse Infrastructure",
    "definition": "Technical infrastructure supporting metaverse platforms.",
    "source_domain": "metaverse",
    "maturity_level": null,
    "authority_score": 0.95
  }
}