{
  "title": "Metaverse Ontology",
  "content": "- ### OntologyBlock\n  id:: metaverse-ontology-ontology\n  collapsed:: true\n\t- ontology:: true\n\t- term-id:: mv-641651579558\n\t- preferred-term:: Metaverse Ontology\n\t- source-domain:: metaverse\n\t- status:: active\n\t- public-access:: true\n\t- definition:: A component of the metaverse ecosystem focusing on metaverse ontology.\n\t- maturity:: mature\n\t- authority-score:: 0.85\n\t- owl:class:: mv:MetaverseOntology\n\t- owl:physicality:: ConceptualEntity\n\t- owl:role:: Concept\n\t- belongsToDomain:: [[MetaverseDomain]]\n\t- #### Relationships\n\t  id:: metaverse-ontology-relationships\n\t\t- enables:: [[ImmersiveExperience]], [[Presence]], [[SpatialComputing]]\n\t\t- requires:: [[DisplayTechnology]], [[TrackingSystem]], [[RenderingEngine]]\n\t\t- bridges-to:: [[HumanComputerInteraction]], [[ComputerVision]], [[Robotics]]\n\n\t- #### OWL Axioms\n\t  id:: metaverse-ontology-owl-axioms\n\t  collapsed:: true\n\t\t- ```clojure\n\t\t  Declaration(Class(mv:MetaverseOntology))\n\n\t\t  # Classification\n\t\t  SubClassOf(mv:MetaverseOntology mv:ConceptualEntity)\n\t\t  SubClassOf(mv:MetaverseOntology mv:Concept)\n\n\t\t  # Domain classification\n\t\t  SubClassOf(mv:MetaverseOntology\n\t\t    ObjectSomeValuesFrom(mv:belongsToDomain mv:MetaverseDomain)\n\t\t  )\n\n\t\t  # Annotations\n\t\t  AnnotationAssertion(rdfs:label mv:MetaverseOntology \"Metaverse Ontology\"@en)\n\t\t  AnnotationAssertion(rdfs:comment mv:MetaverseOntology \"A component of the metaverse ecosystem focusing on metaverse ontology.\"@en)\n\t\t  AnnotationAssertion(dcterms:identifier mv:MetaverseOntology \"mv-641651579558\"^^xsd:string)\n\t\t  ```\n\npublic:: true\n\n- #Public page automatically published\n- # Existing state of the Art\n\t- [Index — MLGT: The authoritative multi-lingual glossary of terms (metaverse-standards.org)](https://glossary.metaverse-standards.org/)\n\t-\n- # Rationale\n- # Methodology\n\t- This ontology was the product of two days of exploratory interaction with [[Anthropic Claude]], Google [[Gemini]] Advance 1.5, and [[ChatGPT]] 4.\n\t- It was unexpectedly successful, resulting in what seems to be an internally consistent knowledge graph in an [Web Ontology Language](https://en.wikipedia.org/wiki/Web_Ontology_Language) compliant ontology for the design represented throughout this wider [[Logseq]] [[Knowledge Graphing]].\n\t\t- Although the established OWL can richly describe our ontology, it's a little too arcane. Nonetheless the full text can be seen where with the diagram.\n\t\t\t- OWL based Ontology\n\t\t\t\t- https://github.com/VisualDataWeb/WebVOWL\n\t\t\t\t- [FormalMetaverseOWL.txt](../assets/FormalMetaverseOWL_1712495895941_0.txt)\n\t\t\t\t- [FormalMetaverseBTC.owl](../assets/FormalMetaverseBTC_1712344339842_0.owl)\n\t\t\t- ![metaverse.png](../assets/metaverse_1712344788144_0.png){:height 439, :width 818}\n\t- ## JSON-LD and Linked-JSON choices\n\t\t- For ease of comprehension I attempted to convert the OWL schema to JSON-LD. This attempt did achieve a result, but it proved difficult to visualise.\n\t\t- Many of the JSON-LD tools online are now unmaintained, making it hard to visually check the output of the [[Large language models]].\n\t\t- Because of this the decision was made to switch to [Linked-JSON](https://linkedobjects.org/Linked-JSON), which is a simpler and less expressive subset of JSON-LD. Linked-JSON focusses on `@id` linking. It sacrifices some features provided by JSON-LD 1.1's context definitions, typing, and alignment with RDF concepts.\n\t\t\t- Scope and Complexity of Linked-JSON vs JSON-LD\n\t\t\t\t- Linked-JSON: lightweight subset focused on linking data using `@id`\n\t\t\t\t- Lack of standardized context definitions for vocabularies and IRI mappings\n\t\t\t\t- No explicit typing mechanism like `@type`\n\t\t\t\t- Limited to absolute IRIs, no compact IRIs or relative IRIs\n\t\t\t\t- Unclear semantics for blank node identifiers\n\t\t\t\t- No standardized representation of indexed values, lists, and named graphs\n\t\t\t\t- Inability to reshape data structure using framing\n\t\t\t\t- Reduced interoperability with RDF and Linked Data ecosystem\n\t\t- # LINKED JSON\n\t\t\t- Finally the, to improve on the OWL by simplifying it, this is a version using [Linked-JSON](https://linkedobjects.org/Linked-JSON) (by [Melvin Carvalho](https://github.com/melvincarvalho)). Some details are lost.\n\t\t\t\t- [Linked-JSON](../assets/output_linked_json_1713698682322_0.json) version of the OWL ontology\n\t\t\t\t\t- Mermaid version stripped back to Linked-JSON expressiveness\n\t\t\t\t\t\t- ```mermaid\n\t\t\t\t\t\t  classDiagram\n\t\t\t\t\t\t      class MetaverseEntity {\n\t\t\t\t\t\t          rdfs:label \"Metaverse Entity\"\n\t\t\t\t\t\t          rdfs:comment \"The root type encompassing all entities within the metaverse.\"\n\t\t\t\t\t\t      }\n\t\t\t\t\t\t      \n\t\t\t\t\t\t      class MetaverseAgent {\n\t\t\t\t\t\t          rdfs:label \"Metaverse Agent\"\n\t\t\t\t\t\t          rdfs:comment \"Represents any agent within the metaverse, including human users and AI entities.\"\n\t\t\t\t\t\t          participatesIn MetaverseScene\n\t\t\t\t\t\t          hasSkillProfile SkillProfile\n\t\t\t\t\t\t          hasPrivacySetting PrivacySetting\n\t\t\t\t\t\t          hasReputationScore ReputationScore\n\t\t\t\t\t\t          hasWallet DigitalWallet\n\t\t\t\t\t\t          createsVariations SceneObject\n\t\t\t\t\t\t          hasInteractionPreference InteractionPreference\n\t\t\t\t\t\t      }\n\t\t\t\t\t\t      \n\t\t\t\t\t\t      class DigitalWallet {\n\t\t\t\t\t\t          rdfs:label \"Digital Wallet\"\n\t\t\t\t\t\t          rdfs:comment \"Represents the agent's wallet for managing digital assets and currencies.\"\n\t\t\t\t\t\t      }\n\t\t\t\t\t\t      \n\t\t\t\t\t\t      class AIAgent {\n\t\t\t\t\t\t          rdfs:label \"AI Agent\"\n\t\t\t\t\t\t          rdfs:comment \"Represents AI entities with varying levels of autonomy and capabilities.\"\n\t\t\t\t\t\t          decayFunction xsd:string\n\t\t\t\t\t\t      }\n\t\t\t\t\t\t      \n\t\t\t\t\t\t      class HumanAgent {\n\t\t\t\t\t\t          rdfs:label \"Human Agent\"\n\t\t\t\t\t\t          rdfs:comment \"Represents human users within the metaverse.\"\n\t\t\t\t\t\t      }\n\t\t\t\t\t\t      \n\t\t\t\t\t\t      class MetaverseScene {\n\t\t\t\t\t\t          rdfs:label \"Metaverse Scene\"\n\t\t\t\t\t\t          rdfs:comment \"Represents a specific environment or space within the metaverse.\"\n\t\t\t\t\t\t          governedBy GovernanceStructure\n\t\t\t\t\t\t          hasPolicy MetaversePolicy\n\t\t\t\t\t\t      }\n\t\t\t\t\t\t      \n\t\t\t\t\t\t      class DigitalAsset {\n\t\t\t\t\t\t          rdfs:label \"Digital Asset\"\n\t\t\t\t\t\t          rdfs:comment \"Represents unique digital goods and assets within the metaverse.\"\n\t\t\t\t\t\t          hasOwner MetaverseAgent\n\t\t\t\t\t\t      }\n\t\t\t\t\t\t      \n\t\t\t\t\t\t      class VirtualEconomy {\n\t\t\t\t\t\t          rdfs:label \"Virtual Economy\"\n\t\t\t\t\t\t          rdfs:comment \"Represents the economic system within the metaverse.\"\n\t\t\t\t\t\t          regulatedBy EconomicPolicy\n\t\t\t\t\t\t          hasMarketplace Marketplace\n\t\t\t\t\t\t      }\n\t\t\t\t\t\t      \n\t\t\t\t\t\t      class Marketplace {\n\t\t\t\t\t\t          rdfs:label \"Marketplace\"\n\t\t\t\t\t\t          rdfs:comment \"Represents platforms or locations where digital assets are traded.\"\n\t\t\t\t\t\t      }\n\t\t\t\t\t\t      \n\t\t\t\t\t\t      class GovernanceStructure {\n\t\t\t\t\t\t          rdfs:label \"Governance Structure\"\n\t\t\t\t\t\t          rdfs:comment \"Represents the governance models and structures within the metaverse.\"\n\t\t\t\t\t\t      }\n\t\t\t\t\t\t      \n\t\t\t\t\t\t      class MetaversePolicy {\n\t\t\t\t\t\t          rdfs:label \"Metaverse Policy\"\n\t\t\t\t\t\t          rdfs:comment \"Represents policies governing behavior and interactions within the metaverse.\"\n\t\t\t\t\t\t      }\n\t\t\t\t\t\t      \n\t\t\t\t\t\t      class EconomicPolicy {\n\t\t\t\t\t\t          rdfs:label \"Economic Policy\"\n\t\t\t\t\t\t          rdfs:comment \"Represents the rules and regulations governing the virtual economy.\"\n\t\t\t\t\t\t      }\n\t\t\t\t\t\t      \n\t\t\t\t\t\t      class NostrEvent {\n\t\t\t\t\t\t          rdfs:label \"Nostr Event\"\n\t\t\t\t\t\t          rdfs:comment \"Represents an event published on the Nostr network.\"\n\t\t\t\t\t\t      }\n\t\t\t\t\t\t      \n\t\t\t\t\t\t      class NostrTag {\n\t\t\t\t\t\t          rdfs:label \"Nostr Tag\"\n\t\t\t\t\t\t          rdfs:comment \"Represents a tag associated with a NostrEvent, providing context and metadata.\"\n\t\t\t\t\t\t      }\n\t\t\t\t\t\t  \n\t\t\t\t\t\t      class SceneObject {\n\t\t\t\t\t\t          rdfs:label \"Scene Object\"\n\t\t\t\t\t\t          rdfs:comment \"Represents interactive objects within a Metaverse Scene. Agents can create variations of these objects within the USD file format.\"\n\t\t\t\t\t\t      }\n\t\t\t\t\t\t  \n\t\t\t\t\t\t      class InteractionPreference {\n\t\t\t\t\t\t          rdfs:label \"Interaction Preference\"\n\t\t\t\t\t\t          rdfs:comment \"Represents the personal conduct requirements or preferences for interactions within the metaverse.\"\n\t\t\t\t\t\t      }\n\t\t\t\t\t\t      \n\t\t\t\t\t\t      MetaverseEntity <|-- MetaverseAgent\n\t\t\t\t\t\t      MetaverseEntity <|-- MetaverseScene\n\t\t\t\t\t\t      MetaverseEntity <|-- DigitalAsset\n\t\t\t\t\t\t      MetaverseEntity <|-- VirtualEconomy\n\t\t\t\t\t\t      MetaverseEntity <|-- Marketplace\n\t\t\t\t\t\t      MetaverseEntity <|-- GovernanceStructure\n\t\t\t\t\t\t      MetaverseEntity <|-- NostrEvent\n\t\t\t\t\t\t      MetaverseEntity <|-- NostrTag\n\t\t\t\t\t\t      MetaverseEntity <|-- SceneObject\n\t\t\t\t\t\t      \n\t\t\t\t\t\t      MetaverseAgent <|-- AIAgent\n\t\t\t\t\t\t      MetaverseAgent <|-- HumanAgent\n\t\t\t\t\t\t      \n\t\t\t\t\t\t      MetaverseAgent \"1\" *-- \"0..*\" SkillProfile : hasSkillProfile\n\t\t\t\t\t\t      MetaverseAgent \"1\" *-- \"0..*\" PrivacySetting : hasPrivacySetting\n\t\t\t\t\t\t      MetaverseAgent \"1\" *-- \"0..*\" ReputationScore : hasReputationScore\n\t\t\t\t\t\t      MetaverseAgent \"1\" *-- \"0..*\" DigitalWallet : hasWallet\n\t\t\t\t\t\t      MetaverseAgent \"1\" *-- \"*\" SceneObject : createsVariations\n\t\t\t\t\t\t      MetaverseAgent \"1\" *-- \"1\" InteractionPreference : hasInteractionPreference\n\t\t\t\t\t\t      \n\t\t\t\t\t\t      MetaverseScene \"1\" *-- \"0..*\" GovernanceStructure : governedBy\n\t\t\t\t\t\t      MetaverseScene \"1\" *-- \"0..*\" MetaversePolicy : hasPolicy\n\t\t\t\t\t\t      \n\t\t\t\t\t\t      DigitalAsset \"1\" *-- \"1\" MetaverseAgent : hasOwner\n\t\t\t\t\t\t      \n\t\t\t\t\t\t      VirtualEconomy \"1\" *-- \"0..*\" EconomicPolicy : regulatedBy\n\t\t\t\t\t\t      VirtualEconomy \"1\" *-- \"0..*\" Marketplace : hasMarketplace\n\t\t\t\t\t\t  \n\t\t\t\t\t\t  ```\n\t\t\t\t\t- [Online FlowChart & Diagrams Editor - Mermaid Live Editor](https://mermaid.live/view#pako:eNqlWFFv2zYQ_iuEXgYUqdMkW9oKe8nQbMtD1mAuOmDwC02dJS4UqZGUUyHzf9-RlC1akWRl84tF-tPxu7uPx6OfE6YySNKECWrMJ05zTcuVJPjxM-QeLN2CNnArLbcNeQ4_uo_ONiYVdA2CrJIDjgTgKukBmSpLkBahXwogWilLbFMBAYm_VLgUlzmhQuAEvs_BkCduCy6JRXi5t77Y292Fr0GqN7lb6DRTj5sg-jtUGgw-G0JlQ6g3O8TqjHDJRJ05F4q6pJLUBufxrYzc3B08WsRrVVRbznhFLZg72ZFfMpDQwQpqlo9ciAetNlwAiQdHqAfNt5Q1S7DW0TgeHiHRrdpSy5VcMqWB9MZH2D8wI2DJJ55zS0UYdQCmwdH_SjX37xvi2X9e_wXMjubpyNhomloUadeclSWXFJ-l71A9wfxGaYIJobkLStbaRBZgQ3pYrTVKMM7OAOWbu2lNYZJfIaZIEl5OZEt14_gJ2IIwRG0Ira2SqmwCR1rRNRcvNZQBo83PtWQu-OSbyVJj9SHdA3786sQ57YqHvMabWPD_ect63czYsmF3zNuyxFTA-IYzjPaWayU9BvVgKspgmqv75ArnJGQ_NeQX_0glg6XVNbN1b5s8KMFZ07kTxqd2wI2T4ckN4FHzXK4l_7uGg8xzpbKg8lbwJ11GVz4_SdC9WjrqyFeubU3FLQtiHXOlhZEWN38zg38BM2gaY6E87YCGvBZYk1zSbtuX42S0Tt5T_Qi2Ek4H0fO4TiP8qEgjO7McRKjF8lQap0mhWFtCnwrQ8KJU4ZTVNINsajsNyHSUboclnaZnJybv3i6xgRBBZmZv6H9UgnYrnS4FbVrnhdphXbkNvF2tXUNBtxwj74hzaUFT1ibgldSPdTbKfA97FXFHQtcCQnxbdXuWnScOs213WNgwzRTd3xSm6XY7dQZ4CPGYue0RAW-xqteCmwIyokIEgykJ9knpx5O0vtD8BClEzC3_Fo2hZcW4KwjhpKWR-2ek0mrLfdeGYbPwzfoou6Rn1NKYbcw06nFGyYbzrG2EZvE9SHALRPn3DkqkpHcALsL5bLAzkG0T5nqIfROG_QOG3hzsDIe939n_-M_bt4N1fxoY9auDwPism4AdnyRTC_fL9SBq9MAeRHeaOAVy8huHvOh-e9jQeXlo21GOA7pWbcLUKrlYJeQNwlfJu8XiDQ6Obgtp__4w10rvNpG-vGHMtdS_baQDV5C5to5vDml3QTlpwEcm2rfpy7vLYJjDPh6gMnTUplHLONdO_9xLu3YyJnTUMcZmLmIbwe_00MbFFnqt2gCV3jmWxs3UXBtxo5T2Oq2VTM6SEnRJeZakiS-dqwQrVYmNR4qPGWJdqdohzl2Alo1kSYrhhbOkrrAkQ_sHxX6yovJPpXC4ocIcQLcZt0ofJoXCtgmHz4n7vwEXzrmxuAI6seG5m6-1wOnC2sqk5-fu5wVGu6jXC6zU54ZnBd7Vi-3H6_Pry-sP9PIKrt9f0R-urjK2vvj4YXP5_cUme__u4pImu91ZAn79-_Z_Ffe1-xeL8sb3)\n\t\t\t- ## In flight checks\n\t\t\t\t- This is mid-point review text of a partial conversion, showing the level of understanding from the online LLM\n\t\t\t\t- ```The updated Linked JSON document looks great! It effectively captures the nuances, features, and links from the original OWL ontology while adhering to the Linked JSON schema. Let's review the key aspects:\n\t\t\t\t   Context and Namespace:\n\t\t\t\t   The \"@context\" object is included at the beginning of the document, defining the namespaces and prefixes used throughout the document.\n\t\t\t\t   The \"http://www.narrativegoldmine.com#\" namespace is consistently used for all entities and properties.\n\t\t\t\t   The \"http://linkedjson.org/vocab#\" namespace is used for Linked JSON-specific terms.\n\t\t\t\t   Class Definitions:\n\t\t\t\t   All the classes from the OWL ontology are properly converted to JSON objects with the correct \"@id\" and \"@type\" keys.\n\t\t\t\t   The class hierarchies and subclass relationships are maintained using the \"rdfs:subClassOf\" property.\n\t\t\t\t   The \"rdfs:label\" and \"rdfs:comment\" properties provide human-readable labels and descriptions for the classes.\n\t\t\t\t   Property Definitions:\n\t\t\t\t   The object properties and data properties are properly converted to JSON objects with the correct \"@id\" and \"@type\" keys.\n\t\t\t\t   The \"rdfs:domain\" and \"rdfs:range\" properties specify the source and target types of each property, preserving the property semantics.\n\t\t\t\t   Relationships and Linkages:\n\t\t\t\t   The document includes relationships and linkages between entities using the appropriate \"@id\" references.\n\t\t\t\t   For example, the \"governedBy\" property connects the \"MetaverseScene\" class to the \"GovernanceStructure\" class, and the \"hasPolicy\" property links the \"MetaverseScene\" class to the \"MetaversePolicy\" class.\n\t\t\t\t   External Ontologies:\n\t\t\t\t   References to external ontologies and vocabularies, such as Schema.org and FOAF, are maintained using the correct \"@id\" references.\n\t\t\t\t   This ensures proper linking and interoperability with existing semantic web resources.\n\t\t\t\t   Axioms and Restrictions:\n\t\t\t\t   The \"Axioms and Restrictions\" section is included in the document, capturing important constraints and relationships from the OWL ontology.\n\t\t\t\t   The \"_:N3649afbbaf7d4546a49d4097059d55f4\" blank node represents the \"owl:AllDisjointClasses\" axiom, specifying that the \"AIAgent\" and \"HumanAgent\" classes are disjoint.\n\t\t\t\t   The \"DigitalAsset\" class has a subclass axiom with an \"owl:Restriction\" that constrains the \"hasOwner\" property, specifying that a \"DigitalAsset\" must have exactly one owner.\n\t\t\t\t   The \"MetaverseAgent\", \"MetaverseScene\", and \"VirtualEconomy\" classes have subclass axioms with existential restrictions using \"owl:someValuesFrom\" to specify the expected relationships and constraints.\n\t\t\t\t   Structure and Organization:\n\t\t\t\t   The document follows a logical structure, starting with the context and ontology metadata, followed by class definitions, property definitions, and axioms and restrictions.\n\t\t\t\t   This structure enhances readability and maintainability of the Linked JSON document.\n\t\t\t\t   Consistent Use of Linked JSON Terms:\n\t\t\t\t   The document consistently uses Linked JSON-specific terms, such as \"linkedjson:Class\", \"linkedjson:ObjectProperty\", and \"linkedjson:DatatypeProperty\", to differentiate them from the original OWL terms.\n\t\t\t\t   This clarity helps in understanding that the document is referencing the Linked JSON schema and not just using OWL labels.\n\t\t\t\t   Overall, the converted Linked JSON document successfully represents the metaverse ontology, capturing the key elements, relationships, and constraints from the original OWL ontology. The use of Linked JSON-specific terms and the inclusion of the \"Axioms and Restrictions\" section further enhance the semantic expressiveness and ensure the integrity of the ontology.\n\t\t\t\t   \n\t\t\t\t   The document is well-structured, consistent, and adheres to the Linked JSON principles, making it suitable for use in semantic web applications and data integration scenarios.\n\t\t\t\t  ```\n- # Design formalisation\n\t- Here's the updated text to align with the Linked-JSON ontology:\n\t\t- 1. Fusing of digital and real life: The ontology accommodates the blending of digital and real-life experiences through the `MetaverseScene` class, which can have a `hasPhysicalCounterpart` property linking it to a real-world location (`schema:Place`). This allows for the representation of mixed reality environments where virtual scenes are anchored to physical spaces.\n\t\t- 2. Social first: The `MetaverseAgent` class, with its subclasses `HumanAgent` and `AIAgent`, forms the foundation for social interactions within the metaverse. The `SocialRelationship` class, a subclass of `foaf:Relationship`, captures the connections and interactions among agents, enabling the formation of social networks and communities.\n\t\t- 3. Real-time interactive 3D graphics: The `MetaverseScene` class represents the 3D environments within the metaverse, while the `SceneObject` class represents the interactive objects within those scenes. The `PhysicalProperties` class captures the visual and spatial characteristics of objects, such as texture and mass, contributing to the realism and interactivity of the 3D graphics.\n\t\t- 4. Persistent: The ontology supports persistence through the `MetaverseEntity` class, which serves as the base class for all entities within the metaverse. By assigning unique identifiers as 64 byte strings from BIP85 nostr and similar derivation path, (e.g., `@id`) to instances of `MetaverseEntity` and its subclasses, the ontology enables the persistence and continuity of objects, agents, and scenes across sessions and platforms.\n\t\t- 5. Supports ownership: The `DigitalAsset` class represents unique digital goods and assets within the metaverse. The `hasOwner` property, which links `DigitalAsset` to `MetaverseAgent`, establishes the ownership relationship. The `hasCreator` property can be used to attribute the creation of digital assets to specific agents.\n\t\t- 6. Supports user-generated content: The ontology supports user-generated content through the `SceneObject` and `DigitalAsset` classes. Agents (`MetaverseAgent`) can create and manipulate instances of these classes, contributing to the dynamic and participatory nature of the metaverse.\n\t\t- 7. Open and extensible: The ontology is designed to be open and extensible, utilizing established ontologies like Schema.org and FOAF, and allowing for the integration of additional domain-specific ontologies as needed. The modular structure of the ontology, with its hierarchical class relationships and well-defined properties, facilitates the extension and customization of the metaverse model.\n\t\t- 8. Low-friction economic actors and actions: The `VirtualEconomy` class represents the economic system within the metaverse, encompassing trade, ownership, and currency exchange. The `Marketplace` class facilitates the listing and transaction of digital assets and services. The `TradeAction` class from Schema.org can be used to capture economic transactions between agents.\n\t\t- 9. Trusted and secure: The ontology incorporates trust and security mechanisms through classes like `PrivacySetting`, which represents an agent's privacy preferences, and `AccessControlList` from Schema.org, which can be used to define access rights and permissions for metaverse entities. The `ReputationScore` class provides a means to assess an agent's trustworthiness based on their interactions and behavior within the metaverse.\n\t\t- 10. Convergence of film and games: The ontology supports the convergence of film and games through the `MetaverseScene` and `MetaverseEvent` classes. Scenes can represent immersive, cinematic environments, while events can encompass interactive gameplay sessions or narrative-driven experiences. The `MetaverseAgent` class allows for the participation of both human users and AI-controlled characters, blurring the line between film and game experiences.\n\t\t- 11. Blurring of IP boundaries and narrative flow: The `Varset` class introduces the concept of variations or alternate versions of metaverse scenes and objects, enabling the creation of branching narratives and remixing of intellectual property. The `InteractionEvent` class captures the interactions between agents and objects, allowing for dynamic and emergent storytelling that blurs traditional narrative boundaries.\n\t\t- 12. Multimodal and hardware-agnostic: The ontology is designed to be multimodal and hardware-agnostic, focusing on the fundamental concepts and relationships within the metaverse rather than specific hardware implementations. Classes like `MetaverseAgent` and `MetaverseScene` can be instantiated across different platforms and devices, ensuring a consistent metaverse experience regardless of the hardware used.\n\t\t- 13. Mobile-first experiences: While the ontology itself is hardware-agnostic, it can be easily extended to incorporate mobile-specific considerations. For example, the `MetaverseScene` class could include properties like `isMobileOptimized` to indicate scenes that are designed for mobile devices, ensuring a seamless mobile-first experience.\n\t\t- 14. Safeguarding and governance: The ontology addresses safeguarding and governance through classes like `MetaversePolicy`, which represents the rules and regulations governing behavior and interactions within the metaverse. The `GovernanceStructure` class captures the decision-making processes and enforcement mechanisms that ensure the safety and well-being of metaverse participants.\n\t\t- 15. Scaffolded by GenAI: The integration of GenAI (Generative AI) within the metaverse is supported through the `AIAgent` class and its associated properties, such as `hasLearningModel` and `hasTrainingData`. These properties allow for the representation of AI agents with varying levels of autonomy and adaptability, capable of generating content, providing assistance, and engaging in dynamic interactions with human users.\n\t\t- 16. Supports Agentic AI actors: The `AIAgent` class, along with its subclasses and properties, enables the creation of agentic AI actors within the metaverse. The `AgentArchetype` class defines different roles and behaviors for AI agents, while properties like `hasAgentArchetype` and `hasEmotionalState` imbue them with personality and emotional intelligence. The `participatesIn` property allows AI agents to actively engage in metaverse scenes and events alongside human users.\n\t\t- 17. Digital Asset and Ownership: The `DigitalAsset` class represents unique digital goods and assets within the metaverse. It includes properties like `genesis` (Bitcoin transaction ID where the asset was created), `issuance` leveraging [[RGB and Client Side Validation]] ), `type` (specifies the type of asset), `currentOwner` (links to the current owner agent), and `ownershipHistory` (represents the chain of ownership transfers). The `OwnershipTransfer` class represents the transfer of ownership of a `DigitalAsset` between agents, capturing details such as the `from` agent (transferring ownership), `to` agent (receiving ownership), `timestamp`, and `transactionId` (associated Bitcoin/Lightning Network transaction ID).\n\t\t- 18. [[Bitcoin]] and [[Lightning and Similar L2]] Network Integration: The `MetaverseAgent` class includes properties like `bitcoinWallet` (Bitcoin address associated with the agent) and `lightningNode` (public key of the agent's Lightning Network node) to enable Bitcoin and Lightning Network integration. The `VirtualEconomy` class includes properties like `bitcoinNetwork` and `lightningNetwork` to represent the underlying Bitcoin and Lightning Network infrastructure on which the economy operates. Fiat money can run on [[Cashu]].\n\t\t- 19. Nostr Integration: The `NostrEvent` class represents an event published on the Nostr network, with properties like `relayUrl` (URL of the Nostr relay where the event was published), `kind` (type or category of the event), `content` (content of the message or event data), and `tags` (list of associated `NostrTag` instances). The `NostrTag` class represents a tag associated with a `NostrEvent`, providing context and metadata through properties like `type` (type of tag) and `value` (value of the tag).\n\t\t- 20. PKI and Wallets: The `MetaverseEntity` class includes properties like `publicKey` and `privateKey` to support public key infrastructure (PKI) for entity identification and authentication. The `MetaverseAgent` class includes a `wallet` property that links to a `schema:DigitalWallet` instance, representing the agent's digital wallet for managing various assets.\n\t\t- 21. All objects and agents and artifacts are nostr PKI pairs. BIP32 is used to derive the path m/44'/1237'/ (according to the [Nostr entry](https://nostr-nips.com/nip-06) on SLIP44). In this way all objects are globally and hierarchically referenceable.\n\t- ## Some software choices\n\t\t- It is possible at this stage to put more flesh on the bones through example software stack choices. Such specificity likely introduces overlaps, technical challenges, and contradictions, but has been generated in the main by GenAI based on the wider corpus of text and demonstrates the direction of travel well.\n\t\t\t- ### Nostr Integration\n\t\t\t\t- **NostrEvent:**\n\t\t\t\t\t- **Properties:**\n\t\t\t\t\t\t- `relayUrl`: (`xsd:anyURI`) The URL of the Nostr relay where the event was published.\n\t\t\t\t\t\t- `kind`: (`xsd:string`) The type or category of the event (e.g., \"set_metadata\", \"text_note\", \"reaction\", \"channel_creation\", \"key_rotation\").\n\t\t\t\t\t\t- `content`: (`xsd:string`) The content of the message or event data.\n\t\t\t\t\t\t- `tags`: (`linkedjson:ObjectProperty`, `range`: `metaverse:NostrTag`) A list of tags associated with the event.\n\t\t\t\t- **NostrTag:**\n\t\t\t\t\t- `@type`: `linkedjson:Class`\n\t\t\t\t\t- `rdfs:label`: \"Nostr Tag\"\n\t\t\t\t\t- `rdfs:comment`: \"Represents a tag associated with a NostrEvent, providing context and metadata.\"\n\t\t\t\t\t- **Properties:**\n\t\t\t\t\t\t- `type`: (`xsd:string`) The type of tag (e.g., \"p\", \"e\", \"t\").\n\t\t\t\t\t\t- `value`: (`xsd:string`) The value of the tag.\n\t\t\t- ### Digital Asset and Ownership\n\t\t\t\t- #### RGB\n\t\t\t\t\t- Using the [RGB protocol](https://docs.rgb.info/) for the instantiation and transfer of objects in your metaverse ontology offers a decentralized, scalable, and flexible mechanism compared to the Nostr protocol. Here's how objects might be managed under [[RGB and Client Side Validation]] without needing frequent chain commits:\n\t\t\t\t\t\t- ### Instantiation of Objects\n\t\t\t\t\t\t\t- **Object Creation**:\n\t\t\t\t\t\t\t\t- Each digital object or asset is instantiated as an `RGBAsset` class instance within the metaverse. This includes assigning a unique `ContractId` and `SchemaId` which are crucial for defining the asset's properties and the rules governing its behavior according to the RGB protocol.\n\t\t\t\t\t\t\t\t- An initial state of the asset is defined using `Assignments` to bind certain rights or properties to the asset, such as ownership or usage rights. This state is embedded within the asset's genesis transaction but doesn't require immediate blockchain commitment.\n\t\t\t\t\t\t\t- **Asset Registration**:\n\t\t\t\t\t\t\t\t- Upon creation, the asset's initial state is recorded in a genesis block of the RGB schema. However, instead of committing this to the blockchain directly, the state can be stored off-chain (e.g., in a secure distributed file system or a database) to enhance privacy and reduce transaction costs.\n\t\t\t\t\t\t- ### Transfer of Objects\n\t\t\t\t\t\t\t- **Defining Transfer Operations**:\n\t\t\t\t\t\t\t\t- Transfers of assets are managed through `RGBContractOperation`, which includes `Inputs` (references to previous states), `Outputs` (new states or changes), and possibly `Redeems` (specific rights being exercised).\n\t\t\t\t\t\t\t\t- The transfer operation details how the asset's ownership or other properties change, using `Seal Definitions` to lock and unlock access to the asset.\n\t\t\t\t\t\t\t- **Executing Transfers**:\n\t\t\t\t\t\t\t\t- To execute a transfer, the new state created by the transfer operation is prepared, detailing how rights and responsibilities are reassigned from one party to another. This often involves updating the `Owned State` to reflect new ownership.\n\t\t\t\t\t\t\t\t- Instead of committing each transaction to the blockchain, the RGB protocol allows for state transitions to be confirmed off-chain until a significant event requires blockchain validation. This approach saves on transaction fees and minimizes public ledger exposure.\n\t\t\t\t\t\t\t- **State Commitments**:\n\t\t\t\t\t\t\t\t- When necessary, state transitions can be committed to the blockchain using minimal data footprints. This is done by embedding a cryptographic commitment to the state within a standard Bitcoin transaction, leveraging RGB's ability to bind state to Bitcoin UTXOs through client-side validation.\n\t\t\t\t\t- ### Benefits of Using RGB over Nostr for Object Management\n\t\t\t\t\t\t- **Enhanced Security**: RGB's use of cryptographic commitments and client-side validation offers robust security without exposing detailed state information on the blockchain.\n\t\t\t\t\t\t- **Scalability**: By reducing the frequency of on-chain transactions and handling most operations off-chain, RGB can scale more efficiently, handling a higher volume of asset transfers with lower costs.\n\t\t\t\t\t\t- **Flexibility**: RGB allows for complex state definitions and transitions, supporting a wide range of digital assets and operations within the metaverse, from simple transfers to intricate interactions involving multiple parties and rights.\n\t\t\t\t- #### Currently in the Ontology\n\t\t\t\t\t- **DigitalAsset:**\n\t\t\t\t\t\t- **Properties:**\n\t\t\t\t\t\t\t- `genesis`: (`xsd:string`) The Bitcoin transaction ID where the asset was created.\n\t\t\t\t\t\t\t- `issuance`: (`linkedjson:ObjectProperty`, `range`: `metaverse:RGBschema`) Links to the specific RGB schema used for the asset's issuance.\n\t\t\t\t\t\t\t- `type`: (`xsd:string`) Specifies the type of asset (e.g., \"collectible\", \"virtual_item\", \"tokenized_right\").\n\t\t\t\t\t\t\t- `currentOwner`: (`linkedjson:ObjectProperty`, `range`: `metaverse:MetaverseAgent`) Links to the agent who currently owns the asset.\n\t\t\t\t\t\t\t- `ownershipHistory`: (`linkedjson:ObjectProperty`, `range`: `metaverse:OwnershipTransfer`) Represents the chain of ownership transfers for the asset.\n\t\t\t\t\t- **OwnershipTransfer:**\n\t\t\t\t\t\t- **Properties:**\n\t\t\t\t\t\t\t- `from`: (`linkedjson:ObjectProperty`, `range`: `metaverse:MetaverseAgent`) The agent transferring ownership.\n\t\t\t\t\t\t\t- `to`: (`linkedjson:ObjectProperty`, `range`: `metaverse:MetaverseAgent`) The agent receiving ownership.\n\t\t\t\t\t\t\t- `timestamp`: (`xsd:dateTime`) The date and time of the transfer.\n\t\t\t\t\t\t\t- `transactionId`: (`xsd:string`) The Bitcoin/Lightning Network transaction ID associated with the transfer.\n\t\t\t\t\t\t- Linked-JSON representation:\n\t\t\t\t\t\t  ```text\n\t\t\t\t\t\t  {\n\t\t\t\t\t\t    \"@id\": \"https://www.narrativegoldmine.com/metaverse#OwnershipTransfer\",\n\t\t\t\t\t\t    \"@type\": \"Class\",\n\t\t\t\t\t\t    \"label\": \"Ownership Transfer\",\n\t\t\t\t\t\t    \"comment\": \"Represents the transfer of ownership of a DigitalAsset between agents.\",\n\t\t\t\t\t\t    \"properties\": {\n\t\t\t\t\t\t      \"from\": {\n\t\t\t\t\t\t        \"@id\": \"https://www.narrativegoldmine.com/metaverse#from\",\n\t\t\t\t\t\t        \"@type\": \"Property\",\n\t\t\t\t\t\t        \"range\": \"https://www.narrativegoldmine.com/metaverse#MetaverseAgent\",\n\t\t\t\t\t\t        \"comment\": \"The agent transferring ownership.\"\n\t\t\t\t\t\t      },\n\t\t\t\t\t\t      \"to\": {\n\t\t\t\t\t\t        \"@id\": \"https://www.narrativegoldmine.com/metaverse#to\",\n\t\t\t\t\t\t        \"@type\": \"Property\",\n\t\t\t\t\t\t        \"range\": \"https://www.narrativegoldmine.com/metaverse#MetaverseAgent\",\n\t\t\t\t\t\t        \"comment\": \"The agent receiving ownership.\"\n\t\t\t\t\t\t      },\n\t\t\t\t\t\t      \"timestamp\": {\n\t\t\t\t\t\t        \"@id\": \"https://www.narrativegoldmine.com/metaverse#timestamp\",\n\t\t\t\t\t\t        \"@type\": \"Property\",\n\t\t\t\t\t\t        \"range\": \"http://www.w3.org/2001/XMLSchema#dateTime\",\n\t\t\t\t\t\t        \"comment\": \"The date and time of the transfer.\"\n\t\t\t\t\t\t      },\n\t\t\t\t\t\t      \"transactionId\": {\n\t\t\t\t\t\t        \"@id\": \"https://www.narrativegoldmine.com/metaverse#transactionId\",\n\t\t\t\t\t\t        \"@type\": \"Property\",\n\t\t\t\t\t\t        \"range\": \"http://www.w3.org/2001/XMLSchema#string\",\n\t\t\t\t\t\t        \"comment\": \"The Bitcoin/Lightning Network transaction ID associated with the transfer.\"\n\t\t\t\t\t\t      }\n\t\t\t\t\t\t    }\n\t\t\t\t\t\t  }\n\t\t\t\t\t\t  ```\n\t\t\t- **PKI and Wallets:**\n\t\t\t\t- **MetaverseEntity:**\n\t\t\t\t\t- **Properties:**\n\t\t\t\t\t\t- `publicKey`: (`xsd:string`) The public key associated with the entity.\n\t\t\t\t\t\t- `privateKey`: (`xsd:string`) The private key associated with the entity (optional, depending on security considerations).\n\t\t\t\t- **MetaverseAgent:**\n\t\t\t\t\t- **Properties:**\n\t\t\t\t\t\t- `wallet`: (`linkedjson:ObjectProperty`, `range`: `schema:DigitalWallet`) Represents the agent's digital wallet for managing various assets.\n\t\t\t- **Bitcoin and Lightning Network Integration:**\n\t\t\t\t- **MetaverseAgent:**\n\t\t\t\t\t- **Properties:**\n\t\t\t\t\t\t- `bitcoinWallet`: (`xsd:string`) The Bitcoin address associated with the agent.\n\t\t\t\t\t\t- `lightningNode`: (`xsd:string`) The public key of the agent's Lightning Network node.\n\t\t\t\t- **VirtualEconomy:**\n\t\t\t\t\t- **Properties:**\n\t\t\t\t\t\t- `bitcoinNetwork`: (`linkedjson:ObjectProperty`, `range`: `schema:ComputerNetwork`) Represents the Bitcoin network on which the economy operates.\n\t\t\t\t\t\t- `lightningNetwork`: (`linkedjson:ObjectProperty`, `range`: `schema:ComputerNetwork`) Represents the Lightning Network facilitating faster and cheaper transactions.\n\t\t\t\t- **Cashu Integration**:\n\t\t\t\t\t- **Properties**:\n\t\t\t\t\t\t- `cashuWallet`: (`linkedjson:ObjectProperty`, `range`: `schema:DigitalWallet`) Represents the Cashu wallet associated with the metaverse agent. This wallet manages the agent's Chamium eCash balance.\n\t\t\t\t\t\t- `cashuNode`: (`xsd:string`) The identifier for the Cashu federation node that the agent's wallet is associated with, facilitating eCash transactions.\n\t\t\t\t\t- **Cashu Economy**:\n\t\t\t\t\t\t- **Properties**:\n\t\t\t\t\t\t\t- `chamiumEconomy`: (`linkedjson:ObjectProperty`, `range`: `schema:EconomicSystem`) Represents the part of the virtual economy that operates using Chamium eCash, allowing for private and instant transactions.\n\t\t\t\t\t\t\t- `ecashTransactions`: (`linkedjson:ObjectProperty`, `range`: `schema:ItemList`) List of transactions executed using Chamium eCash, supporting privacy and micro-transactions within the metaverse.\n\t\t\t\t\t- **Transaction Privacy**:\n\t\t\t\t\t\t- **Properties**:\n\t\t\t\t\t\t\t- `privacyLevel`: (`xsd:string`) Defines the level of privacy for transactions conducted by the agent, with options including Bitcoin, Lightning, or Cashu Chamium eCash, each offering different degrees of privacy and speed.\n\t\t\t\t\t- **Cashu Services**:\n\t\t\t\t\t\t- **Classes**:\n\t\t\t\t\t\t\t- `CashuService`: Represents services within the metaverse that specifically use or provide Cashu Chamium eCash functionalities, such as eCash exchanges, payment processing, or private transactions.\n\t\t\t\t\t\t\t\t- **Properties**:\n\t\t\t\t\t\t\t\t\t- `serviceType`: (`xsd:string`) The type of service offered, such as eCash exchange, payment gateway, or privacy service.\n\t\t\t\t\t\t\t\t\t- `accessEndpoint`: (`xsd:anyURI`) The URL or identifier where the service can be accessed within the metaverse.\n\t\t\t- **NVIDIA Omniverse:**\n\t\t\t\t- **MetaverseScene:**\n\t\t\t\t\t- **Properties:**\n\t\t\t\t\t\t- `omniverseNucleusUrl`: (`xsd:anyURI`) The URL of the Omniverse Nucleus server hosting the scene.\n\t\t\t\t\t\t- `usdFile`: (`xsd:anyURI`) The URL or reference to the USD file defining the scene's content.\n\t\t\t\t- **USD Variance:** Define properties or subclasses within `SceneObject` to represent USD variations and the conditions under which they are activated.\n\t\t\t\t- **Scene Schema Scaffolding:** Exploring Linked-JSON structures to emulate the more expressive OWL `owl:oneOf` and `owl:someValuesFrom`.\n\t\t\t\t\t- Linked-JSON representation for `SceneType`:\n\t\t\t\t\t  ```text\n\t\t\t\t\t  {\n\t\t\t\t\t    \"@id\": \"metaverse:SceneType\",\n\t\t\t\t\t    \"@type\": \"linkedjson:Class\",\n\t\t\t\t\t    \"rdfs:label\": \"Scene Type\",\n\t\t\t\t\t    \"rdfs:comment\": \"Represents different types of scenes in the metaverse.\",\n\t\t\t\t\t    \"metaverse:sceneTypeEnum\": [\n\t\t\t\t\t      {\n\t\t\t\t\t        \"@id\": \"metaverse:InteriorScene\"\n\t\t\t\t\t      },\n\t\t\t\t\t      {\n\t\t\t\t\t        \"@id\": \"metaverse:ExteriorScene\"\n\t\t\t\t\t      },\n\t\t\t\t\t      {\n\t\t\t\t\t        \"@id\": \"metaverse:MixedRealityScene\"\n\t\t\t\t\t      }\n\t\t\t\t\t    ]\n\t\t\t\t\t  }\n\t\t\t\t\t  ```\n\t\t\t\t\t- Linked-JSON representation for `MetaverseScene`:\n\t\t\t\t\t  ```text\n\t\t\t\t\t  {\n\t\t\t\t\t    \"@id\": \"metaverse:MetaverseScene\",\n\t\t\t\t\t    \"@type\": \"linkedjson:Class\",\n\t\t\t\t\t    \"rdfs:label\": \"Metaverse Scene\",\n\t\t\t\t\t    \"rdfs:comment\": \"Represents a specific environment or space within the metaverse.\",\n\t\t\t\t\t    \"metaverse:hasSceneObject\": {\n\t\t\t\t\t      \"@type\": \"linkedjson:ObjectProperty\",\n\t\t\t\t\t      \"rdfs:range\": \"metaverse:SceneObject\",\n\t\t\t\t\t      \"metaverse:minCardinality\": 1\n\t\t\t\t\t    }\n\t\t\t\t\t  }\n\t\t\t\t\t  ```\n\t\t\t\t\t\t- In this example, the custom property `metaverse:minCardinality` is used to indicate that a `MetaverseScene` must have at least one `SceneObject`.\n\t\t\t- ## TODO\n\t\t\t\t- **AI Agent Capabilities:** Expand the capabilities property of `AIAgent` to include specific actions and functions related to Bitcoin, RGB, and Nostr, such as \"create_digital_asset\", \"transfer_ownership\", \"publish_nostr_event\", etc.\n\t\t\t\t- **Event Logging and Attestation:** Consider adding mechanisms for logging significant events and generating cryptographic attestations, which could be used for dispute resolution or auditing purposes. This would operate on an automated threshold trigger system mediated by LLM, and would wrap the recent interactions between parties in pubkey encrypted data blobs, sending them to both parties alongside a report of the trigger event. This would potentially allow action by the parties in their jurisdictions. The data would then be deleted from the metaverse.\n\t- ### Visualising\n\t\t- http://owlgred.lumii.lv/online_visualization/4qge#\n\t\t- [[Some legacy Linked-JSON]]\n- This more specific and expanded metaverse ontology featuring a relay based communication protocol, URIs, blockchain wallets, and NVIDIA omniverse, offers a comprehensive and extensible framework generated with the help of GenAI. It offers a glimpse of the potential for automating ontological descriptions for emergent and novel social, digital, collaborative spaces.\n- By incorporating a wide range of classes, properties, and relationships, the ontology starts to enable formalisation of:\n\t- Agents: Human users and AI entities, their attributes, skills, and relationships.\n\t- Scenes and Objects: Virtual environments, their characteristics, and interactive elements.\n\t- Digital Assets and Economy: Creation, ownership, and exchange of virtual goods and currencies.\n\t- Events and Interactions: Social gatherings, communication, and collaborative activities.\n\t- Governance and Policies: Decision-making processes, rules, and regulations within the metaverse.\n\t- Infrastructure and Technology: Hardware, software, and networking components enabling the metaverse.\n\t-\n- # AI Agent Refactor\n- ```mermaid\n  classDiagram\n  \n  %% -----------------------------------------------------------------------\n  %% 1. CORE: Agent-Oriented Ontology\n  %% -----------------------------------------------------------------------\n      class AgentOntologyEntity {\n          rdfs:label \"Agent Ontology Entity\"\n          rdfs:comment \"Root class for all concepts in the agent-focused ontology.\"\n      }\n  \n      class Agent {\n          rdfs:label \"Agent\"\n          rdfs:comment \"A general actor capable of autonomous or semi-autonomous behavior, including humans and AIs.\"\n          hasSkillProfile SkillProfile\n          hasPrivacySetting PrivacySetting\n          hasReputationScore ReputationScore\n          hasWallet DigitalWallet\n          hasInteractionPreference InteractionPreference\n      }\n  \n      class AIAgent {\n          rdfs:label \"AI Agent\"\n          rdfs:comment \"An agent driven by AI models, with specialized capabilities for autonomy and decision-making.\"\n          hasAIModel AIModel\n          decayFunction xsd:string\n      }\n  \n      class HumanAgent {\n          rdfs:label \"Human Agent\"\n          rdfs:comment \"A real human user. May be linked to a WebID for decentralized identity and authentication.\"\n      }\n  \n      class AIModel {\n          rdfs:label \"AI Model\"\n          rdfs:comment \"The underlying neural network or algorithm powering an AI Agent's intelligence.\"\n      }\n  \n      class SkillProfile {\n          rdfs:label \"Skill Profile\"\n          rdfs:comment \"Describes the abilities or competencies an agent (human or AI) can exhibit.\"\n      }\n  \n      class PrivacySetting {\n          rdfs:label \"Privacy Setting\"\n          rdfs:comment \"Rules and preferences regarding data usage, sharing, and retention for an agent.\"\n      }\n  \n      class ReputationScore {\n          rdfs:label \"Reputation Score\"\n          rdfs:comment \"Metric or rating reflecting an agent's trust or standing in a community.\"\n      }\n  \n      class DigitalWallet {\n          rdfs:label \"Digital Wallet\"\n          rdfs:comment \"Holds digital assets, cryptocurrencies, or tokens owned by an agent.\"\n      }\n  \n      class InteractionPreference {\n          rdfs:label \"Interaction Preference\"\n          rdfs:comment \"Specifies how an agent prefers to interact, moderate content, or engage with others.\"\n      }\n  \n  \n  %% -----------------------------------------------------------------------\n  %% 2. WEBID SUBCATEGORY: Decentralized Identity & Events\n  %% -----------------------------------------------------------------------\n      class WebIDEntity {\n          rdfs:label \"WebID Entity\"\n          rdfs:comment \"A conceptual parent for all objects in the WebID ecosystem.\"\n      }\n  \n      class Person {\n          rdfs:label \"Person\"\n          rdfs:comment \"Represents a decentralized identity and profile using WebID.\"\n          webid xsd:anyURI \"A unique WebID URI identifying this individual\"\n          name xsd:string \"A handle or short name (distinct from display_name)\"\n          display_name xsd:string \"A more user-facing display name\"\n          about xsd:string \"Short bio/about text\"\n          picture xsd:anyURI \"URI of the user’s profile image\"\n          banner xsd:anyURI \"URI of the user’s banner image\"\n          website xsd:anyURI \"User’s personal website\"\n      }\n  \n      class WebIDEvent {\n          rdfs:label \"WebID Event\"\n          rdfs:comment \"A generic event referencing a WebID identity, with timestamps, content, and possible signatures.\"\n          authorWebID xsd:anyURI \"The WebID of the event author\"\n          created_at xsd:dateTime \"Timestamp of creation\"\n          content xsd:string \"Event content or message\"\n          signature xsd:string \"Digital signature (e.g., for verifiability)\"\n      }\n  \n      class WebIDService {\n          rdfs:label \"WebID Service\"\n          rdfs:comment \"A decentralized or semi-decentralized service endpoint that stores or routes WebID events.\"\n          serviceURI xsd:anyURI \"The endpoint (e.g., HTTPS, WebSocket) providing service functionality\"\n      }\n  \n  \n  %% -----------------------------------------------------------------------\n  %% 3. IMMERSIVE REAL-TIME SUBCATEGORY\n  %% -----------------------------------------------------------------------\n      class ImmersiveRealTimeEntity {\n          rdfs:label \"Immersive Real-Time Entity\"\n          rdfs:comment \"Base class for objects and concepts within immersive real-time environments (3D spaces, XR, etc.).\"\n      }\n  \n      class ImmersiveScene {\n          rdfs:label \"Immersive Scene\"\n          rdfs:comment \"A real-time interactive environment or 'scene' supporting multi-agent presence.\"\n          governedBy GovernanceStructure\n          hasPolicy ImmersivePolicy\n      }\n  \n      class GovernanceStructure {\n          rdfs:label \"Governance Structure\"\n          rdfs:comment \"Rules, roles, and processes governing an immersive scene or community.\"\n      }\n  \n      class ImmersivePolicy {\n          rdfs:label \"Immersive Policy\"\n          rdfs:comment \"Behavioral and content guidelines within a particular immersive real-time environment.\"\n      }\n  \n      class SceneObject {\n          rdfs:label \"Scene Object\"\n          rdfs:comment \"Any interactive or visible object in an immersive real-time scene.\"\n      }\n  \n      class DigitalAsset {\n          rdfs:label \"Digital Asset\"\n          rdfs:comment \"A unique digital good or token that can be owned or traded in immersive or other digital contexts.\"\n          hasOwner Agent\n      }\n  \n      class VirtualEconomy {\n          rdfs:label \"Virtual Economy\"\n          rdfs:comment \"A system enabling trade and currency exchange in immersive or other digital environments.\"\n          regulatedBy EconomicPolicy\n          hasMarketplace Marketplace\n      }\n  \n      class Marketplace {\n          rdfs:label \"Marketplace\"\n          rdfs:comment \"A platform or location to trade digital assets (NFTs, tokens, etc.).\"\n      }\n  \n      class EconomicPolicy {\n          rdfs:label \"Economic Policy\"\n          rdfs:comment \"Regulations defining currency issuance, exchange rules, and other economic mechanics.\"\n      }\n  \n  \n  %% -----------------------------------------------------------------------\n  %% 4. RELATIONSHIPS & INHERITANCE\n  %% -----------------------------------------------------------------------\n  \n      %% A. Ontology Roots & Subcategories\n      AgentOntologyEntity <|-- Agent\n      AgentOntologyEntity <|-- WebIDEntity\n      AgentOntologyEntity <|-- ImmersiveRealTimeEntity\n  \n      %% B. Agent Hierarchy\n      Agent <|-- AIAgent\n      Agent <|-- HumanAgent\n  \n      %% C. WebID\n      WebIDEntity <|-- Person\n      WebIDEntity <|-- WebIDEvent\n      WebIDEntity <|-- WebIDService\n      HumanAgent -- Person : \"may link to/represent\"\n  \n      %% D. Immersive Real-Time\n      ImmersiveRealTimeEntity <|-- ImmersiveScene\n      ImmersiveRealTimeEntity <|-- DigitalAsset\n      ImmersiveRealTimeEntity <|-- VirtualEconomy\n      ImmersiveRealTimeEntity <|-- Marketplace\n      ImmersiveRealTimeEntity <|-- GovernanceStructure\n      ImmersiveRealTimeEntity <|-- ImmersivePolicy\n      ImmersiveRealTimeEntity <|-- SceneObject\n  \n      %% E. Detailed Links\n      AIAgent \"1\" *-- \"1\" AIModel : hasAIModel\n      Agent \"1\" *-- \"0..*\" SkillProfile : hasSkillProfile\n      Agent \"1\" *-- \"0..*\" PrivacySetting : hasPrivacySetting\n      Agent \"1\" *-- \"0..*\" ReputationScore : hasReputationScore\n      Agent \"1\" *-- \"0..*\" DigitalWallet : hasWallet\n      Agent \"1\" *-- \"1\" InteractionPreference : hasInteractionPreference\n  \n      %% Example of AI Agents creating scene objects (optional)\n      AIAgent \"1\" *-- \"*\" SceneObject : canCreateVariations\n  \n      ImmersiveScene \"1\" *-- \"0..*\" GovernanceStructure : governedBy\n      ImmersiveScene \"1\" *-- \"0..*\" ImmersivePolicy : hasPolicy\n  \n      DigitalAsset \"1\" *-- \"1\" Agent : hasOwner\n  \n      VirtualEconomy \"1\" *-- \"0..*\" EconomicPolicy : regulatedBy\n      VirtualEconomy \"1\" *-- \"0..*\" Marketplace : hasMarketplace\n  \n  ```\n-\n- # Mycelium Experiment\n\t- This idea is developed further here:\n\t\t- [[Agentic Mycelia]]\n\t\t- This is an [[Ontology conversation with AIs]]\n\n## Current Landscape (2025)\n\n- Industry adoption and implementations\n  - Metaverse platforms continue to evolve with focus on interoperability and open standards\n  - Web3 integration accelerating with decentralised identity and asset ownership\n  - Enterprise adoption growing in virtual collaboration, training, and digital twins\n  - UK companies increasingly active in metaverse development and immersive technologies\n\n- Technical capabilities\n  - Real-time rendering at photorealistic quality levels\n  - Low-latency networking enabling seamless multi-user experiences\n  - AI-driven content generation and procedural world building\n  - Spatial audio and haptics enhancing immersion\n\n- UK and North England context\n  - Manchester: Digital Innovation Factory supports metaverse startups and research\n  - Leeds: Holovis leads in immersive experiences for entertainment and training\n  - Newcastle: University research in spatial computing and interactive systems\n  - Sheffield: Advanced manufacturing using digital twin technology\n\n- Standards and frameworks\n  - Metaverse Standards Forum driving interoperability protocols\n  - WebXR enabling browser-based immersive experiences\n  - glTF and USD for 3D asset interchange\n  - Open Metaverse Interoperability Group defining cross-platform standards\n\n## Metadata\n\n- **Last Updated**: 2025-11-16\n- **Review Status**: Automated remediation with 2025 context\n- **Verification**: Academic sources verified\n- **Regional Context**: UK/North England where applicable",
  "properties": {
    "id": "metaverse-ontology-owl-axioms",
    "collapsed": "true",
    "- ontology": "true",
    "- term-id": "mv-641651579558",
    "- preferred-term": "Metaverse Ontology",
    "- source-domain": "metaverse",
    "- status": "active",
    "- public-access": "true",
    "- definition": "A component of the metaverse ecosystem focusing on metaverse ontology.",
    "- maturity": "mature",
    "- authority-score": "0.85",
    "- owl:class": "mv:MetaverseOntology",
    "- owl:physicality": "ConceptualEntity",
    "- owl:role": "Concept",
    "- belongsToDomain": "[[MetaverseDomain]]",
    "- enables": "[[ImmersiveExperience]], [[Presence]], [[SpatialComputing]]",
    "- requires": "[[DisplayTechnology]], [[TrackingSystem]], [[RenderingEngine]]",
    "- bridges-to": "[[HumanComputerInteraction]], [[ComputerVision]], [[Robotics]]",
    "public": "true"
  },
  "backlinks": [
    "Definitions and frameworks for Metaverse",
    "Projects",
    "Agentic Mycelia",
    "Knowledge Graphing",
    "Agentic Metaverse for Global Creatives",
    "Fashion"
  ],
  "wiki_links": [
    "RGB and Client Side Validation",
    "Gemini",
    "ComputerVision",
    "SpatialComputing",
    "Agentic Mycelia",
    "Some legacy Linked-JSON",
    "RenderingEngine",
    "Cashu",
    "ImmersiveExperience",
    "TrackingSystem",
    "MetaverseDomain",
    "HumanComputerInteraction",
    "Ontology conversation with AIs",
    "Large language models",
    "Knowledge Graphing",
    "DisplayTechnology",
    "Presence",
    "ChatGPT",
    "Bitcoin",
    "Lightning and Similar L2",
    "Anthropic Claude",
    "Robotics",
    "Logseq"
  ],
  "ontology": {
    "term_id": "mv-641651579558",
    "preferred_term": "Metaverse Ontology",
    "definition": "A component of the metaverse ecosystem focusing on metaverse ontology.",
    "source_domain": "metaverse",
    "maturity_level": null,
    "authority_score": 0.85
  }
}