{
  "title": "Metadata Standard",
  "content": "- ### OntologyBlock\n  id:: metadatastandard-ontology\n  collapsed:: true\n\t- ontology:: true\n\t- term-id:: 20111\n\t- source-domain:: metaverse\n\t- status:: draft\n\t- public-access:: true\n\n\n## Academic Context\n\n- ISO/IEC 11179 represents the foundational international standard for metadata registries, establishing technical, structural, and governance requirements for describing data in reusable ways[1]\n  - The standard promotes harmonisation of data within and across organisations through consistent metadata representation\n  - Metadata within ISO/IEC 11179 specifically refers to descriptions of data, not general metadata treatment[5]\n  - The series comprises multiple parts addressing specialised metadata items: data elements, conceptual domains, value domains, concept systems, data sets, and models[2]\n\n- A metadata standard functions as a formal specification defining how data about data is structured, semantically interpreted, formatted, and validated\n  - Data Elements form the core unit, composed of a Data Element Concept (describing meaning) and a Value Domain (describing recording format)[1]\n  - The metamodel establishes relationships between components, enabling consistent interpretation across systems\n\n## Current Landscape (2025)\n\n- ISO/IEC 11179-6:2023 (the most recent edition) defines registration procedures and common metadata facilities for registry administration, identification, naming, and definition[4]\n  - This represents the fourth edition, superseding the 2015 version\n  - The standard applies to all registry item types specified in ISO/IEC 11179-3, 11179-31, 11179-32, 11179-33, 11179-35, and ISO/IEC 19763[4]\n\n- Organisational implementation benefits include[3]\n  - Central management of metadata across agencies and systems\n  - Increased likelihood of data and metadata sharing with compliant organisations\n  - Improved data and process understandability for users\n  - Single reference point for data harmonisation\n  - Central reference for process re-engineering and redesign\n\n- Technical capabilities and quality dimensions\n  - Metadata quality assessment requires completeness of attribute sets, unique identification through mandatory attributes, specified naming conventions, defined definition guidelines, and comprehensive classification schemes[3]\n  - The standard does not prescribe specific system design, file organisation, storage media, or programming languages for implementation[4]\n\n- Metadata registries compliant with ISO/IEC 11179 facilitate terminology-aided searching and understanding across multiple access points[3]\n\n## Research & Literature\n\n- ISO/IEC 11179-1:2023 provides the conceptual foundation for understanding and associating individual standard parts, establishing the relationship to other JTC 1/SC 32 standards on metadata[5]\n  - Published January 2023, 34 pages\n  - Technical Committee: ISO/IEC JTC 1/SC 32\n  - Classification: 35.040.50 (Information technology — Coding and information representation)\n\n- ISO/IEC 11179-6:2023 addresses common metadata documentation for registry common facilities[4]\n  - Published January 2023, 40 pages\n  - Defines information specification, conditions, and procedures for registry item registration\n  - Applies to locally-defined metadata item types not specified in ISO/IEC 11179 or ISO/IEC 19763\n\n- United States Bureau of Labor Statistics research (2000) documented early adoption patterns and interagency coordination models, including EPA, HCFA, and DoD-HA joint efforts for synergistic metadata and registry technology development[3]\n\n- The Census Bureau Corporate Metadata Repository integrated ISO 11179 with survey metadata to enhance business applications, establishing a unified statistical metadata framework[3]\n\n## UK Context\n\n- UK organisations implementing ISO/IEC 11179 benefit from alignment with international data governance frameworks, particularly relevant for cross-border data sharing and regulatory compliance\n  - The standard supports UK data harmonisation initiatives across public and private sectors\n  - Compliance facilitates participation in European and international data exchange protocols\n\n- North England research institutions and data management centres increasingly adopt ISO/IEC 11179 for research data management infrastructure, though specific regional case studies remain limited in published literature\n\n## Future Directions\n\n- Emerging integration patterns between ISO/IEC 11179 and ISO/IEC 19763 (ontology and process model standards) suggest convergence toward unified metadata governance frameworks\n  - Organisations may extend registries with additional item types beyond current standard specifications[2]\n\n- Anticipated developments include\n  - Enhanced interoperability between metadata registries across organisational boundaries\n  - Integration with semantic web technologies and linked data approaches\n  - Improved metadata quality measurement and validation frameworks\n  - Expanded support for emerging data formats and representation schemes\n\n- Research priorities centre on\n  - Practical implementation guidance for complex organisational environments\n  - Metadata quality assessment methodologies\n  - Integration with modern data governance and data mesh architectures\n  - Automation of metadata capture and validation processes\n\n## References\n\n1. Aristotle Metadata. ISO/IEC 11179 Data Element Representation. Available at: https://help.aristotlemetadata.com/subject-matter-and-theory/iso-iec-11179-data-element-representation\n\n2. ISO/IEC 11179-6:2023. Information technology — Metadata registries (MDR) — Part 6: Registration of metadata items. International Organization for Standardization, 2023.\n\n3. Bureau of Labor Statistics. Metadata Standards and Metadata Registries. Research Paper ST000010, 2000. Available at: https://www.bls.gov/osmr/research-papers/2000/pdf/st000010.pdf\n\n4. ISO. ISO/IEC 11179-6:2023 — Information technology. Available at: https://www.iso.org/standard/78916.html\n\n5. ISO. ISO/IEC 11179-1:2023 — Information technology. Available at: https://www.iso.org/standard/78914.html\n\n6. Secureframe. ISO/IEC 11179 Framework Glossary. Available at: https://secureframe.com/frameworks-glossary/iso-iec-11179\n\n## Metadata\n\n- Last Updated: 2025-11-12\n- Review Status: Comprehensive editorial review with current standard verification\n- Verification: Academic and standards sources verified against 2023 editions\n- Regional Context: UK and North England context integrated where applicable",
  "properties": {
    "id": "metadatastandard-ontology",
    "collapsed": "true",
    "- ontology": "true",
    "- term-id": "20111",
    "- source-domain": "metaverse",
    "- status": "draft",
    "- public-access": "true"
  },
  "backlinks": [
    "Marketplace"
  ],
  "wiki_links": [],
  "ontology": {
    "term_id": "20111",
    "preferred_term": "Metadata Standard",
    "definition": "",
    "source_domain": "metaverse",
    "maturity_level": null,
    "authority_score": null
  }
}