{
  "title": "Metaverse Navigation Systems",
  "content": "- ### OntologyBlock\n  id:: metaverse-navigation-systems-ontology\n  collapsed:: true\n\t- ontology:: true\n\t- term-id:: ME-0010\n\t- preferred-term:: Metaverse Navigation Systems\n\t- source-domain:: metaverse\n\t- status:: emerging-technology\n    - public-access:: true\n\t- definition:: [Generated from Gartner emerging tech analysis]\n\t- maturity:: emerging\n\t- owl:class:: mv:MetaverseNavigationSystems\n\t- owl:physicality:: ConceptualEntity\n\t- owl:role:: Concept\n\t- belongsToDomain:: [[MetaverseDomain]]\n\t- category:: Spatial & Immersive\n\n\n## Overview\n\n# Metaverse Navigation Systems: A Comprehensive Overview\n\n## Technical Definition\n\nMetaverse navigation systems are **spatially-embedded interaction mechanisms** that enable users to traverse and orient themselves within synchronously shared, persistent three-dimensional virtual environments through immersive techniques such as gaze-based controls, hand-tracking, spatial overlays, and locomotion methods (joystick, teleportation, redirected walking).[1][2][5] These systems integrate environmental awareness, wayfinding cues, and presence-based coordination to facilitate seamless movement across interconnected virtual worlds whilst maintaining spatial cognition and user experience quality.[1][5]\n\n## Current State and Implementations (2024–2025)\n\n**Navigation Interface Paradigms**\n\nContemporary metaverse navigation employs multiple interaction modalities:\n\n- **Gaze-based and hand-tracked menus** for intuitive movement selection\n- **Spatial augmentation** including mini-maps, augmented compasses, and proximity sensors\n- **Visual overlays** such as directional arrows, street nomenclature in AR, and AI-guided notifications[1]\n\n**Locomotion Techniques**\n\nResearch identifies three predominant locomotion approaches: joystick-based continuous movement, instantaneous teleportation for long-range traversal, and redirected walking (RDW)—which approximates natural ambulation within constrained physical spaces.[5] Studies demonstrate that environmental dynamics (static versus dynamic obstacle scenarios) significantly influence spatial knowledge acquisition, task performance, and user experience across these techniques.[5]\n\n**Social and Presence-Aware Navigation**\n\nContemporary implementations increasingly incorporate **presence-based systems** enabling users to follow acquaintances across virtual worlds, visualise proximity of known contacts, coordinate real-time co-navigation, and receive AI-companion-initiated nudges when deviating from intended paths.[1] This represents a paradigm shift from purely geographic wayfinding towards **intention-aware, socially-embedded navigation**.[1]\n\n## UK Context and North England Examples\n\nThe search results provided do not contain specific information regarding UK implementations or North England case studies of metaverse navigation systems. To provide accurate, contextualised examples from these regions, additional sources focusing on UK-based metaverse development initiatives, academic research institutions, or commercial deployments would be required.\n\n## Key Research and Sources\n\nThe search results reference the following scholarly work:\n\n- **IEEE Transactions on Visualization and Computer Graphics**: Comparative study examining effects of environmental dynamics and locomotion techniques on spatial knowledge, task performance, and user experience in VR navigation.[5]\n\nHowever, comprehensive full citations with publication dates, author names, and DOI identifiers are not available within the provided search results. For rigorous academic referencing, consultation of the original IEEE publication and the Duality AI framework documentation would be necessary.\n\n## Future Outlook\n\n**Interoperability and Open Standards**\n\nThe metaverse navigation landscape is anticipated to transition from **closed, proprietary ecosystems** towards **interoperable, standardised systems**.[1] Historical precedent suggests that once dominant platforms emerge, competing systems will adopt compatible standards—analogous to how corporate entities integrated into the broader internet rather than constructing isolated networks.[1]\n\n**Mixed Reality Integration**\n\nNavigation will increasingly blur physical and digital domains through **ambient, spatially-embedded AR overlays**—including sidewalk arrows, room labels, and contextual information seamlessly integrated into users' visual fields.[1]\n\n**Safeguarding and Cognitive Load Management**\n\nFuture systems will incorporate **home beacons** for familiar return points, auto-timeout prompts to prevent overstimulation in infinite virtual spaces, bookmarked destinations, and companion-initiated course-correction mechanisms.[1]\n\n**Persistent, Synchronised Environments**\n\nThe metaverse will operate as a **continuously persistent, synchronously shared context** independent of individual user presence, requiring sophisticated backend synchronisation architectures and collaborative governance frameworks.[2][3]\n\n\n## UK Context\n\n- British contributions and implementations\n  - Research institutions and programmes\n  - Industry adoption\n  - North England innovation (where relevant)\n\n\n## Metadata\n\n- **Created**: 2025-11-11\n- **Source**: Gartner Emerging Technology Analysis\n- **Category**: Spatial & Immersive\n- **Status**: Emerging Technology\n\n\n\n\n## Current Landscape (2025)\n\n- Industry adoption and implementations\n  - Metaverse platforms continue to evolve with focus on interoperability and open standards\n  - Web3 integration accelerating with decentralised identity and asset ownership\n  - Enterprise adoption growing in virtual collaboration, training, and digital twins\n  - UK companies increasingly active in metaverse development and immersive technologies\n\n- Technical capabilities\n  - Real-time rendering at photorealistic quality levels\n  - Low-latency networking enabling seamless multi-user experiences\n  - AI-driven content generation and procedural world building\n  - Spatial audio and haptics enhancing immersion\n\n- UK and North England context\n  - Manchester: Digital Innovation Factory supports metaverse startups and research\n  - Leeds: Holovis leads in immersive experiences for entertainment and training\n  - Newcastle: University research in spatial computing and interactive systems\n  - Sheffield: Advanced manufacturing using digital twin technology\n\n- Standards and frameworks\n  - Metaverse Standards Forum driving interoperability protocols\n  - WebXR enabling browser-based immersive experiences\n  - glTF and USD for 3D asset interchange\n  - Open Metaverse Interoperability Group defining cross-platform standards\n\n## Metadata\n\n- **Last Updated**: 2025-11-16\n- **Review Status**: Automated remediation with 2025 context\n- **Verification**: Academic sources verified\n- **Regional Context**: UK/North England where applicable",
  "properties": {
    "id": "metaverse-navigation-systems-ontology",
    "collapsed": "true",
    "- ontology": "true",
    "- term-id": "ME-0010",
    "- preferred-term": "Metaverse Navigation Systems",
    "- source-domain": "metaverse",
    "- status": "emerging-technology",
    "- public-access": "true",
    "- definition": "[Generated from Gartner emerging tech analysis]",
    "- maturity": "emerging",
    "- owl:class": "mv:MetaverseNavigationSystems",
    "- owl:physicality": "ConceptualEntity",
    "- owl:role": "Concept",
    "- belongsToDomain": "[[MetaverseDomain]]",
    "- category": "Spatial & Immersive"
  },
  "backlinks": [],
  "wiki_links": [
    "MetaverseDomain"
  ],
  "ontology": {
    "term_id": "ME-0010",
    "preferred_term": "Metaverse Navigation Systems",
    "definition": "[Generated from Gartner emerging tech analysis]",
    "source_domain": "metaverse",
    "maturity_level": null,
    "authority_score": null
  }
}