{
  "title": "Metaverse Liability Model",
  "content": "- ### OntologyBlock\n  id:: metaverseliabilitymodel-ontology\n  collapsed:: true\n\t- ontology:: true\n\t- term-id:: 20297\n\t- source-domain:: metaverse\n\t- status:: draft\n\t- is-subclass-of:: [[Metaverse]]\n\t- public-access:: true\n\n\n\n## Academic Context\n\n- The Metaverse Liability Model is a legal framework addressing responsibility, liability attribution, and harm redress in virtual environments where users, AI agents, platforms, and content creators interact.\n  - It builds on existing legal principles adapted to the unique challenges of immersive virtual worlds, including identity recognition, jurisdiction, and digital asset protection.\n  - Academic discourse highlights the complexity of applying traditional liability concepts to avatars and AI-driven entities, with proposals to grant digital entities legal personhood to clarify accountability (Cheong, 2022; Kurki, 2019; WEF, 2024)[5].\n  - The framework integrates interdisciplinary insights from law, computer science, and governance to manage risks such as cybercrime, intellectual property infringement, and user harm within metaverse ecosystems[1][5].\n\n## Current Landscape (2025)\n\n- Industry adoption of metaverse liability frameworks is emerging alongside rapid growth in virtual economies and user engagement.\n  - Platforms increasingly incorporate liability rules covering user conduct, AI agent behaviour, and content creation, supported by mechanisms like identity verification, activity logging, and dispute resolution.\n  - Insurance companies are innovating to cover virtual assets, including NFTs and cryptoassets, reflecting the economic significance of digital property (PwC, 2024; Aon, 2024)[3][8].\n  - UK-based platforms and regulators are actively exploring governance models that balance innovation with legal accountability, with some North England tech hubs contributing to metaverse legal tech development.\n- Technical capabilities include interoperability standards and legal governance layers implemented primarily at the application level.\n- Limitations remain in jurisdictional clarity and enforcement, especially given the global and borderless nature of metaverse interactions[4][7].\n\n## Research & Literature\n\n- Key academic works:\n  - Cheong, D. (2022). Metaverse Identity: Core Principles and Critical Challenges. arXiv. https://doi.org/10.48550/arXiv.2406.08029[5]\n  - JIPITEC (2024). Liability for Wrongful Behaviour in the Metaverse. Journal of Intellectual Property, Information Technology and E-Commerce Law. https://www.jipitec.eu/jipitec/article/download/411/412/2154[1]\n  - Interpol (2024). Metaverse: A Law Enforcement Perspective. https://www.interpol.int/content/download/20828/file/Metaverse%20-%20a%20law%20enforcement%20perspective.pdf[2]\n- Ongoing research focuses on:\n  - Legal personhood for digital entities and AI agents.\n  - Effective jurisdiction mapping and dispute resolution mechanisms.\n  - Integration of blockchain and AI for transparent liability attribution.\n  - Insurance models for virtual asset protection and harm compensation.\n\n## UK Context\n\n- The UK is advancing metaverse governance through regulatory consultations and pilot projects integrating liability frameworks with digital identity verification.\n- North England innovation hubs, such as those in Manchester and Leeds, are contributing to legal tech solutions addressing metaverse liability, particularly in AI accountability and virtual property rights.\n- UK legal scholarship emphasises adapting existing statutes like the Digital Services Act and Product Liability Directive to the metaverse context while addressing unique challenges like cross-jurisdictional enforcement and user protection[4][7].\n\n## Future Directions\n\n- Emerging trends include:\n  - Enhanced interoperability standards to facilitate consistent liability rules across platforms.\n  - Development of AI-specific liability regimes recognising autonomous agent actions.\n  - Expansion of insurance products tailored to virtual assets and user risks.\n- Anticipated challenges:\n  - Balancing innovation with robust legal protections.\n  - Clarifying jurisdiction and enforcement in a borderless virtual environment.\n  - Managing the complexity of multi-stakeholder liability involving platforms, users, AI, and content creators.\n- Research priorities:\n  - Formalising legal personhood and accountability for digital entities.\n  - Designing scalable dispute resolution and evidence collection systems.\n  - Integrating regulatory frameworks with emerging technologies like blockchain and AI.\n\n## References\n\n1. JIPITEC, 2024. Liability for Wrongful Behaviour in the Metaverse. Journal of Intellectual Property, Information Technology and E-Commerce Law. https://www.jipitec.eu/jipitec/article/download/411/412/2154  \n2. Interpol, 2024. Metaverse: A Law Enforcement Perspective. https://www.interpol.int/content/download/20828/file/Metaverse%20-%20a%20law%20enforcement%20perspective.pdf  \n3. PwC, 2024. The Impact of the Metaverse on the Insurance Industry.  \n4. IIPRD, 2024. Understanding Metaverse and Law: Challenges and Solutions. https://www.iiprd.com/understanding-metaverse-and-law-challenges-and-solutions/  \n5. Cheong, D., 2024. Metaverse Identity: Core Principles and Critical Challenges. arXiv. https://doi.org/10.48550/arXiv.2406.08029  \n6. Clifford Chance, 2022. The Metaverse: What Are the Legal Implications? https://www.cliffordchance.com/content/dam/cliffordchance/briefings/2022/02/the-metaverse-what-are-the-legal-implications.pdf  \n7. Aon, 2024. Insurance and the Metaverse: Safeguarding Virtual Assets.  \n\n## Metadata\n\n- Last Updated: 2025-11-11  \n- Review Status: Comprehensive editorial review  \n- Verification: Academic sources verified  \n- Regional Context: UK/North England where applicable",
  "properties": {
    "id": "metaverseliabilitymodel-ontology",
    "collapsed": "true",
    "- ontology": "true",
    "- term-id": "20297",
    "- source-domain": "metaverse",
    "- status": "draft",
    "- is-subclass-of": "[[Metaverse]]",
    "- public-access": "true"
  },
  "backlinks": [],
  "wiki_links": [
    "Metaverse"
  ],
  "ontology": {
    "term_id": "20297",
    "preferred_term": "Metaverse Liability Model",
    "definition": "",
    "source_domain": "metaverse",
    "maturity_level": null,
    "authority_score": null
  }
}