{
  "title": "Metaverse Safety Protocol",
  "content": "- ### OntologyBlock\n  id:: metaversesafetyprotocol-ontology\n  collapsed:: true\n\t- ontology:: true\n\t- term-id:: 20188\n\t- source-domain:: metaverse\n\t- status:: draft\n\t- public-access:: true\n\n\n## Academic Context & Current Developments\n\n**1. Current Developments (2024-2025)**  \nRecent advances in metaverse safety protocols focus on **child safety, cybersecurity, and trust & safety frameworks**. Standards Australia released draft standards (DR AS 5402:2024) specifically addressing children’s safety, privacy, and accessibility in the metaverse, highlighting the need for design decisions, content moderation, and parental controls to protect young users[1]. Cybersecurity challenges unique to AR/VR environments—such as authentication, privacy, hacking, and physical security—are increasingly recognised, with businesses urged to implement robust safeguards against phishing, data theft, and other cyber threats[2]. The rise of AI is also transforming metaverse applications, necessitating new standards to ensure safe and interoperable virtual environments[4].\n\n**2. Key Applications**  \n- **Child Safety**: Platforms like Roblox are central to child safety discussions, implementing moderation and parental controls to protect minors from harmful content and interactions[1][5].  \n- **Cybersecurity**: Businesses developing metaverse platforms are adopting cybersecurity best practices to prevent account compromise and data breaches in immersive environments[2].  \n- **Trust & Safety Solutions**: Emerging specialised suppliers provide tools for content moderation, misinformation management, and generative AI oversight, addressing evolving safety challenges in real time[6].  \n- **Healthcare**: Medical XR and immersive healthcare applications are part of ongoing safety discussions, focusing on protecting users during virtual medical procedures and interactions[9].\n\n**3. Industry Standards**  \n- **DR AS 5402:2024 “Children’s Safety in the Metaverse”**: A draft standard by Standards Australia providing a practical framework for protecting children in metaverse environments, covering safety, privacy, and accessibility[1].  \n- **Metaverse Standards Forum**: An industry consortium advancing open, interoperable standards for the metaverse, including protocols that underpin safety and security in spatial computing[4].  \n- **Cybersecurity Certifications**: Increasing emphasis on cybersecurity certifications tailored to metaverse-specific risks, ensuring competence in defending against emerging threats[2].\n\n**4. Academic Literature**  \n- Standards Australia’s draft standard on children’s safety in the metaverse (DR AS 5402:2024) is a key authoritative document outlining safety frameworks[1].  \n- Research articles and reports from think tanks like the Information Technology and Innovation Foundation (ITIF) discuss policy and technological approaches to metaverse safety[1].  \n- Recent cybersecurity analyses highlight the unique challenges of AR/VR security and the need for preventive measures in metaverse ecosystems[2].  \n- The World Economic Forum and other organisations have published insights on digital safety risks in immersive environments, including harassment, extremist content, and privacy breaches[3].\n\n**5. Notable Examples**  \n- **Roblox**: A major platform balancing metaverse development with child safety, implementing content moderation and parental controls while engaging with legislative efforts in the US[5].  \n- **Meta (Facebook)**: Developing immersive VR platforms like Oculus Quest, facing challenges such as user harassment and working on safety reporting mechanisms[3][10].  \n- **Metaverse Standards Forum**: A collaborative body of industry leaders working on standard protocols to ensure safety and interoperability in the metaverse[4].  \n- **Specialised Trust & Safety Providers**: Emerging companies offering AI-driven moderation and safety tools tailored to metaverse environments[6].\n\n**6. Future Outlook**  \n- **Increased Regulation and Standards Development**: Expect more formalised international standards and legislation focused on user safety, especially for vulnerable groups like children[1][5].  \n- **Advanced AI and Automation in Safety**: AI will play a growing role in real-time content moderation, identity verification, and threat detection to enhance psychological and physical safety[6].  \n- **Unified Digital Infrastructure**: Development of interoperable systems that ensure safe real-to-virtual interactions, supported by blockchain for secure transactions and identity management[7][8].  \n- **Expansion of Trust & Safety Ecosystem**: Growth of specialised providers offering tailored safety solutions, driven by the complexity of metaverse use cases and regulatory demands[6].  \n- **Focus on Psychological Safety**: Addressing harassment, abuse, and extremist content will remain critical, with platforms improving reporting tools and moderation policies[3].\n\n---\n\nThis synthesis reflects the state of metaverse safety protocols as of late 2025, grounded in recent standards, industry initiatives, and academic insights.\n\n\n## Related Resources\n\nFor more information, see:\n- [[Metaverse]]\n- [[MetaverseDomain]]\n\n\n## Citations & Sources\n\n1. [https://www2.itif.org/2025-australia-children-metaverse.pdf](https://www2.itif.org/2025-australia-children-metaverse.pdf)\n\n2. [https://www.uscsinstitute.org/cybersecurity-insights/blog/cybersecurity-in-the-metaverse-challenges-and-best-practices-in-2025](https://www.uscsinstitute.org/cybersecurity-insights/blog/cybersecurity-in-the-metaverse-challenges-and-best-practices-in-2025)\n\n3. [https://www.weforum.org/stories/2022/01/metaverse-risks-challenges-digital-safety/](https://www.weforum.org/stories/2022/01/metaverse-risks-challenges-digital-safety/)\n\n4. [https://metaverse-standards.org/news/press-releases/metaverse-standards-forum-2024-annual-report/](https://metaverse-standards.org/news/press-releases/metaverse-standards-forum-2024-annual-report/)\n\n5. [https://www.politico.com/newsletters/digital-future-daily/2024/07/31/the-long-road-to-child-safety-in-the-metaverse-00172137](https://www.politico.com/newsletters/digital-future-daily/2024/07/31/the-long-road-to-child-safety-in-the-metaverse-00172137)\n\n6. [https://www.webpurify.com/blog/how-2024-online-safety-trends-will-shape-2025/](https://www.webpurify.com/blog/how-2024-online-safety-trends-will-shape-2025/)\n\n7. [https://ftsg.com/wp-content/uploads/2025/03/Metaverse-New-Realities_FINAL_LINKED.pdf](https://ftsg.com/wp-content/uploads/2025/03/Metaverse-New-Realities_FINAL_LINKED.pdf)\n\n8. [https://deftsoft.com/top-trends-in-metaverse-in-2024/](https://deftsoft.com/top-trends-in-metaverse-in-2024/)\n\n9. [https://metaversesafetyweek.org/2025-edition/](https://metaversesafetyweek.org/2025-edition/)\n\n10. [https://www.computer.org/csdl/magazine/co/2025/08/11104163/28MaSaVlP4k](https://www.computer.org/csdl/magazine/co/2025/08/11104163/28MaSaVlP4k)\n\n\n\n## Metadata\n\n- **Last Enriched**: 2025-11-11\n- **Enrichment Source**: Perplexity AI (Sonar)\n- **Verification Status**: Automated enrichment - human review recommended\n\n\n\n\n## Current Landscape (2025)\n\n- Industry adoption and implementations\n  - Metaverse platforms continue to evolve with focus on interoperability and open standards\n  - Web3 integration accelerating with decentralised identity and asset ownership\n  - Enterprise adoption growing in virtual collaboration, training, and digital twins\n  - UK companies increasingly active in metaverse development and immersive technologies\n\n- Technical capabilities\n  - Real-time rendering at photorealistic quality levels\n  - Low-latency networking enabling seamless multi-user experiences\n  - AI-driven content generation and procedural world building\n  - Spatial audio and haptics enhancing immersion\n\n- UK and North England context\n  - Manchester: Digital Innovation Factory supports metaverse startups and research\n  - Leeds: Holovis leads in immersive experiences for entertainment and training\n  - Newcastle: University research in spatial computing and interactive systems\n  - Sheffield: Advanced manufacturing using digital twin technology\n\n- Standards and frameworks\n  - Metaverse Standards Forum driving interoperability protocols\n  - WebXR enabling browser-based immersive experiences\n  - glTF and USD for 3D asset interchange\n  - Open Metaverse Interoperability Group defining cross-platform standards\n\n## Metadata\n\n- **Last Updated**: 2025-11-16\n- **Review Status**: Automated remediation with 2025 context\n- **Verification**: Academic sources verified\n- **Regional Context**: UK/North England where applicable",
  "properties": {
    "id": "metaversesafetyprotocol-ontology",
    "collapsed": "true",
    "- ontology": "true",
    "- term-id": "20188",
    "- source-domain": "metaverse",
    "- status": "draft",
    "- public-access": "true"
  },
  "backlinks": [],
  "wiki_links": [
    "Metaverse",
    "MetaverseDomain"
  ],
  "ontology": {
    "term_id": "20188",
    "preferred_term": "Metaverse Safety Protocol",
    "definition": "",
    "source_domain": "metaverse",
    "maturity_level": null,
    "authority_score": null
  }
}