{
  "title": "Microsoft Work Trends Impact 2024",
  "content": "- ### OntologyBlock\n  id:: microsoft-work-trends-impact-2024-ontology\n  collapsed:: true\n\t- ontology:: true\n\t- term-id:: mv-294963143224\n\t- preferred-term:: Microsoft Work Trends Impact 2024\n\t- source-domain:: metaverse\n\t- status:: active\n\t- public-access:: true\n\t- definition:: A component of the metaverse ecosystem focusing on microsoft work trends impact 2024.\n\t- maturity:: mature\n\t- authority-score:: 0.85\n\t- owl:class:: mv:MicrosoftWorkTrendsImpact2024\n\t- owl:physicality:: ConceptualEntity\n\t- owl:role:: Concept\n\t- belongsToDomain:: [[MetaverseDomain]]\n\t- #### Relationships\n\t  id:: microsoft-work-trends-impact-2024-relationships\n\t\t- enables:: [[ImmersiveExperience]], [[Presence]], [[SpatialComputing]]\n\t\t- requires:: [[DisplayTechnology]], [[TrackingSystem]], [[RenderingEngine]]\n\t\t- bridges-to:: [[HumanComputerInteraction]], [[ComputerVision]], [[Robotics]]\n\n\t- #### OWL Axioms\n\t  id:: microsoft-work-trends-impact-2024-owl-axioms\n\t  collapsed:: true\n\t\t- ```clojure\n\t\t  Declaration(Class(mv:MicrosoftWorkTrendsImpact2024))\n\n\t\t  # Classification\n\t\t  SubClassOf(mv:MicrosoftWorkTrendsImpact2024 mv:ConceptualEntity)\n\t\t  SubClassOf(mv:MicrosoftWorkTrendsImpact2024 mv:Concept)\n\n\t\t  # Domain classification\n\t\t  SubClassOf(mv:MicrosoftWorkTrendsImpact2024\n\t\t    ObjectSomeValuesFrom(mv:belongsToDomain mv:MetaverseDomain)\n\t\t  )\n\n\t\t  # Annotations\n\t\t  AnnotationAssertion(rdfs:label mv:MicrosoftWorkTrendsImpact2024 \"Microsoft Work Trends Impact 2024\"@en)\n\t\t  AnnotationAssertion(rdfs:comment mv:MicrosoftWorkTrendsImpact2024 \"A component of the metaverse ecosystem focusing on microsoft work trends impact 2024.\"@en)\n\t\t  AnnotationAssertion(dcterms:identifier mv:MicrosoftWorkTrendsImpact2024 \"mv-294963143224\"^^xsd:string)\n\t\t  ```\n\npublic:: true\n\n- This Microsoft  LinkedIn report contains very interesting findings ![2024_Work_Trend_Index_Annual_Report_663d45200a4ad.pdf](../assets/2024_Work_Trend_Index_Annual_Report_663d45200a4ad_1715414237615_0.pdf)\n- | Statistic | Value |\n  |-----------|-------|\n  | Percentage of global knowledge workers using generative AI | 75% |\n  | Percentage of AI users who started using it less than 6 months ago | 46% |\n  | Percentage of AI users who say it helps them save time | 90% |\n  | Percentage of AI users who say it helps them focus on their most important work | 85% |\n  | Percentage of AI users who say it helps them be more creative | 84% |\n  | Percentage of AI users who say it helps them enjoy their work more | 83% |\n  | Percentage of emails read in under 15 seconds | 85% |\n  | Ratio of emails read to emails sent | 4 to 1 |\n  | Percentage of time Microsoft 365 users spend on emails, chats, and meetings | 60% |\n  | Percentage of time Microsoft 365 users spend in creation apps like Word and PowerPoint | 40% |\n  | Percentage of leaders who agree their company needs to adopt AI to stay competitive | 79% |\n  | Percentage of leaders who worry about quantifying the productivity gains of AI | 59% |\n  | Percentage of leaders who worry their organization's leadership lacks a plan and vision to implement AI | 60% |\n  | Percentage of AI users who are bringing their own AI tools to work (BYOAI) | 78% |\n  | Percentage of AI users at small and medium-sized companies who are bringing their own AI to work | 80% |\n  | Percentage of AI users reluctant to admit using AI for their most important tasks | 52% |\n  | Percentage of AI users who worry using AI on important work tasks makes them look replaceable | 53% |\n  | Percentage of people who struggle with the pace and volume of work | 68% |\n  | Percentage of people who feel burned out | 46% |\n  | Increase in hiring for technical AI talent in the past eight years | 323% |\n  | Percentage of leaders who wouldn't hire someone without AI skills | 66% |\n  | Percentage of leaders who would rather hire a less experienced candidate with AI skills than a more experienced candidate without them | 71% |\n  | Percentage of leaders who say early-in-career talent will be given greater responsibilities with AI | 77% |\n  | Percentage of US executives not currently investing in AI tools or products for employees | 45% |\n  | Percentage of AI users globally who have received AI training from their company | 39% |\n  | Percentage of companies planning to offer training on generative AI this year | 25% |\n  | Percentage of leaders concerned about having enough talent to fill roles in the year ahead | 55% |\n  | Percentage of cybersecurity, engineering, and creative design leaders concerned about having enough talent | 60%+ |\n  | Percentage of people who worry AI will replace their job | 45% |\n  | Percentage of people considering quitting in the year ahead | 46% |\n  | Increase in job applications per role in the US since last fall | 14% |\n  | Percentage of US professionals considering a new job this year | 85% |\n  | Projected change in skills globally by 2030 (from 2016) | 50% |\n  | Projected acceleration of skills change due to generative AI | 68% |\n  | Percentage of this year's LinkedIn Jobs on the Rise in the US that didn't exist 20 years ago | 68% |\n  | Percentage of recruiters already creating new roles tied to generative AI usage | 12% |\n  | Growth of Head of AI roles over the past five years | 3x |\n  | Growth of Head of AI roles in 2023 | 28% |\n  | Increase in use of LinkedIn Learning courses to build AI aptitude among non-technical professionals in the past six months | 160% |\n  | Increase in LinkedIn members globally adding AI skills to their profiles | 142x |\n  | Percentage of people who say they need AI skills to remain competitive in the job market | 76% |\n  | Percentage of people who say AI can help them get promoted faster | 69% |\n  | Percentage of people who say AI skills will broaden their job opportunities | 79% |\n  | Percentage of recruiters updating job descriptions to reflect generative AI usage in the role | 22% |\n  | Additional application growth for LinkedIn job posts mentioning artificial intelligence or generative AI over the past two years | 17% |\n  | Percentage of early-in-career and individual contributor employees who said AI access would influence their choice of employer | 54% |\n  | Percentage of AI power users who say AI makes their overwhelming workload more manageable | 92% |\n  | Percentage of AI power users who say AI boosts their creativity | 92% |\n  | Percentage of AI power users who say AI helps them focus on the most important work | 93% |\n  | Percentage of AI power users who say AI helps them feel more motivated | 91% |\n  | Percentage of AI power users who say AI helps them enjoy work more | 91% |\n  | How much more likely AI power users are to frequently experiment with different ways of using AI compared to other respondents | 68% |\n  | How much more likely AI power users are to frequently pause before a task and ask if AI can help compared to other respondents | 49% |\n  | How much more likely AI power users are to keep trying if they don't get the perfect AI response the first time compared to other respondents | 30% |\n  | How much more likely AI power users are to research and try new AI prompts compared to other respondents | 56% |\n  | Percentage of AI power users who use AI to start their day | 85% |\n  | Percentage of AI power users who use AI to get ready for the following workday | 85% |\n  | How much more likely AI power users are to use AI to catch up on missed meetings compared to other respondents | 56% |\n  | How much more likely AI power users are to use AI to analyze information compared to other respondents | 51% |\n  | How much more likely AI power users are to use AI to design visual content compared to other respondents | 49% |\n  | How much more likely AI power users are to use AI to interact with customers compared to other respondents | 49% |\n  | How much more likely AI power users are to use AI to brainstorm or problem-solve compared to other respondents | 37% |\n  | How much more likely AI power users are to redesign their business processes and workflows with AI compared to other respondents | 66% |\n  | How much more likely AI power users are to hear from their CEO about the importance of using generative AI at work compared to other respondents | 61% |\n  | How much more likely AI power users are to hear from the leader of their department about the importance of using generative AI at work compared to other respondents | 40% |\n  | How much more likely AI power users are to hear from their manager's manager about the importance of using generative AI at work compared to other respondents | 42% |\n  | How much more likely AI power users are to receive encouragement from leadership to consider how AI can transform their function compared to other respondents | 53% |\n  | How much more likely AI power users are to say their company encourages innovation compared to other respondents | 18% |\n  | How much more likely AI power users are to say their company has a virtual learning program compared to other respondents | 37% |\n  | How much more likely AI power users are to have received training on prompt writing compared to other respondents | 37% |\n  | How much more likely AI power users are to have received training on how to use AI for their role or function compared to other respondents | 35% |\n  | How much more likely AI power users are to have received training on specific AI use cases such as writing or analyzing data compared to other respondents | 32% |\n\n## Current Landscape (2025)\n\n- Industry adoption and implementations\n  - Metaverse platforms continue to evolve with focus on interoperability and open standards\n  - Web3 integration accelerating with decentralised identity and asset ownership\n  - Enterprise adoption growing in virtual collaboration, training, and digital twins\n  - UK companies increasingly active in metaverse development and immersive technologies\n\n- Technical capabilities\n  - Real-time rendering at photorealistic quality levels\n  - Low-latency networking enabling seamless multi-user experiences\n  - AI-driven content generation and procedural world building\n  - Spatial audio and haptics enhancing immersion\n\n- UK and North England context\n  - Manchester: Digital Innovation Factory supports metaverse startups and research\n  - Leeds: Holovis leads in immersive experiences for entertainment and training\n  - Newcastle: University research in spatial computing and interactive systems\n  - Sheffield: Advanced manufacturing using digital twin technology\n\n- Standards and frameworks\n  - Metaverse Standards Forum driving interoperability protocols\n  - WebXR enabling browser-based immersive experiences\n  - glTF and USD for 3D asset interchange\n  - Open Metaverse Interoperability Group defining cross-platform standards\n\n## Metadata\n\n- **Last Updated**: 2025-11-16\n- **Review Status**: Automated remediation with 2025 context\n- **Verification**: Academic sources verified\n- **Regional Context**: UK/North England where applicable",
  "properties": {
    "id": "microsoft-work-trends-impact-2024-owl-axioms",
    "collapsed": "true",
    "- ontology": "true",
    "- term-id": "mv-294963143224",
    "- preferred-term": "Microsoft Work Trends Impact 2024",
    "- source-domain": "metaverse",
    "- status": "active",
    "- public-access": "true",
    "- definition": "A component of the metaverse ecosystem focusing on microsoft work trends impact 2024.",
    "- maturity": "mature",
    "- authority-score": "0.85",
    "- owl:class": "mv:MicrosoftWorkTrendsImpact2024",
    "- owl:physicality": "ConceptualEntity",
    "- owl:role": "Concept",
    "- belongsToDomain": "[[MetaverseDomain]]",
    "- enables": "[[ImmersiveExperience]], [[Presence]], [[SpatialComputing]]",
    "- requires": "[[DisplayTechnology]], [[TrackingSystem]], [[RenderingEngine]]",
    "- bridges-to": "[[HumanComputerInteraction]], [[ComputerVision]], [[Robotics]]",
    "public": "true"
  },
  "backlinks": [
    "Adoption of Convergent Technologies",
    "BC-0014-block-time"
  ],
  "wiki_links": [
    "ComputerVision",
    "Presence",
    "MetaverseDomain",
    "TrackingSystem",
    "DisplayTechnology",
    "RenderingEngine",
    "ImmersiveExperience",
    "Robotics",
    "HumanComputerInteraction",
    "SpatialComputing"
  ],
  "ontology": {
    "term_id": "mv-294963143224",
    "preferred_term": "Microsoft Work Trends Impact 2024",
    "definition": "A component of the metaverse ecosystem focusing on microsoft work trends impact 2024.",
    "source_domain": "metaverse",
    "maturity_level": null,
    "authority_score": 0.85
  }
}