{
  "title": "Middleware",
  "content": "- ### OntologyBlock\n  id:: middleware-ontology\n  collapsed:: true\n\t- ontology:: true\n\t- term-id:: 20117\n\t- source-domain:: metaverse\n\t- preferred-term:: Middleware\n\t- definition:: Software layer that mediates between applications and underlying services or infrastructure to enable communication, resource access, and interoperability.\n\t- maturity:: mature\n\t- source:: [[EWG/MSF Taxonomy]], [[ISO/IEC 30170]], [[ETSI GR ARF 010]]\n\t- owl:class:: mv:Middleware\n\t- owl:physicality:: VirtualEntity\n\t- owl:role:: Object\n\t- owl:inferred-class:: mv:VirtualObject\n\t- owl:functional-syntax:: true\n\t- belongsToDomain:: [[InfrastructureDomain]], [[ComputationAndIntelligenceDomain]]\n\t- implementedInLayer:: [[ComputeLayer]], [[DataLayer]]\n\t- #### Relationships\n\t  id:: middleware-relationships\n\t\t- is-subclass-of:: [[Metaverse Infrastructure]]\n\t\t- has-part:: [[Message Queue]], [[Service Registry]], [[Communication Protocol]], [[API Gateway]]\n\t\t- is-part-of:: [[Distributed System]], [[Software Architecture]]\n\t\t- requires:: [[Operating System]], [[Network Infrastructure]], [[Compute Infrastructure]]\n\t\t- depends-on:: [[Communication Protocol]], [[Data Format]], [[Service Discovery]]\n\t\t- enables:: [[Service Integration]], [[Interoperability]], [[Distributed Communication]], [[Resource Abstraction]]\n\t- #### OWL Axioms\n\t  id:: middleware-owl-axioms\n\t  collapsed:: true\n\t\t- ```clojure\n\t\t  Declaration(Class(mv:Middleware))\n\n\t\t  # Classification\n\t\t  SubClassOf(mv:Middleware mv:VirtualEntity)\n\t\t  SubClassOf(mv:Middleware mv:Object)\n\t\t  SubClassOf(mv:Middleware mv:Software)\n\n\t\t  # Middleware must have a communication protocol\n\t\t  SubClassOf(mv:Middleware\n\t\t    ObjectSomeValuesFrom(mv:hasPart mv:CommunicationProtocol)\n\t\t  )\n\n\t\t  # Middleware enables service integration\n\t\t  SubClassOf(mv:Middleware\n\t\t    ObjectSomeValuesFrom(mv:enables mv:ServiceIntegration)\n\t\t  )\n\n\t\t  # Middleware enables interoperability\n\t\t  SubClassOf(mv:Middleware\n\t\t    ObjectSomeValuesFrom(mv:enables mv:Interoperability)\n\t\t  )\n\n\t\t  # Middleware requires operating system\n\t\t  SubClassOf(mv:Middleware\n\t\t    ObjectSomeValuesFrom(mv:requires mv:OperatingSystem)\n\t\t  )\n\n\t\t  # Domain classification\n\t\t  SubClassOf(mv:Middleware\n\t\t    ObjectSomeValuesFrom(mv:belongsToDomain mv:InfrastructureDomain)\n\t\t  )\n\t\t  SubClassOf(mv:Middleware\n\t\t    ObjectSomeValuesFrom(mv:belongsToDomain mv:ComputationAndIntelligenceDomain)\n\t\t  )\n\t\t  SubClassOf(mv:Middleware\n\t\t    ObjectSomeValuesFrom(mv:implementedInLayer mv:ComputeLayer)\n\t\t  )\n\t\t  SubClassOf(mv:Middleware\n\t\t    ObjectSomeValuesFrom(mv:implementedInLayer mv:DataLayer)\n\t\t  )\n\n\t\t  # Supporting classes\n\t\t  Declaration(Class(mv:MessageQueue))\n\t\t  SubClassOf(mv:MessageQueue mv:VirtualObject)\n\n\t\t  Declaration(Class(mv:ServiceRegistry))\n\t\t  SubClassOf(mv:ServiceRegistry mv:VirtualObject)\n\n\t\t  Declaration(Class(mv:ServiceIntegration))\n\t\t  SubClassOf(mv:ServiceIntegration mv:VirtualProcess)\n\n\t\t  Declaration(Class(mv:Interoperability))\n\t\t  SubClassOf(mv:Interoperability mv:Capability)\n\n  # Property characteristics\n  TransitiveObjectProperty(dt:ispartof)\n\n  # Property characteristics\n  AsymmetricObjectProperty(dt:requires)\n\n  # Property characteristics\n  AsymmetricObjectProperty(dt:dependson)\n\n  # Property characteristics\n  AsymmetricObjectProperty(dt:enables)\n```\n\n- ## About Middleware\n  id:: middleware-about\n\t- Middleware is a **software abstraction layer** that sits between application code and lower-level infrastructure services, providing a unified interface for communication, data exchange, and resource access across distributed systems. It shields applications from the complexity of heterogeneous platforms, protocols, and services.\n\t-\n\t- ### Key Characteristics\n\t  id:: middleware-characteristics\n\t\t- Platform and language abstraction\n\t\t- Protocol translation and mediation\n\t\t- Message routing and transformation\n\t\t- Service discovery and registry\n\t\t- Load balancing and failover\n\t\t- Transaction management\n\t\t- Security and authentication integration\n\t\t- Monitoring and logging capabilities\n\t-\n\t- ### Technical Components\n\t  id:: middleware-components\n\t\t- [[Message Queue]] - Asynchronous message passing\n\t\t- [[Service Registry]] - Dynamic service discovery\n\t\t- [[Communication Protocol]] - Standardized message formats\n\t\t- [[API Gateway]] - Unified entry point for services\n\t\t- [[Operating System]] - Underlying platform\n\t\t- [[Network Infrastructure]] - Communication channels\n\t\t- [[Service Discovery]] - Locate available services\n\t\t- Connection pooling and caching\n\t\t- Transaction coordinator\n\t\t- Security and authentication modules\n\t-\n\t- ### Functional Capabilities\n\t  id:: middleware-capabilities\n\t\t- **Service Integration**: Connect disparate applications and services\n\t\t- **Interoperability**: Enable communication across heterogeneous systems\n\t\t- **Distributed Communication**: Facilitate message passing in distributed environments\n\t\t- **Resource Abstraction**: Hide infrastructure complexity from applications\n\t\t- **Protocol Translation**: Convert between different communication protocols\n\t\t- **Message Transformation**: Adapt data formats between systems\n\t\t- **Transaction Management**: Coordinate distributed transactions\n\t\t- **Load Distribution**: Balance requests across service instances\n\t\t- **Fault Tolerance**: Handle failures and maintain availability\n\t\t- **Security Enforcement**: Apply authentication, authorization, encryption\n\t-\n\t- ### Types of Middleware\n\t  id:: middleware-types\n\t\t- **Message-Oriented Middleware (MOM)**: Asynchronous messaging (e.g., RabbitMQ, Kafka)\n\t\t- **Remote Procedure Call (RPC)**: Synchronous request-response (e.g., gRPC, Thrift)\n\t\t- **Object Request Broker (ORB)**: Distributed object communication (e.g., CORBA)\n\t\t- **Enterprise Service Bus (ESB)**: Centralized integration hub\n\t\t- **Database Middleware**: Data access and integration (e.g., ODBC, JDBC)\n\t\t- **Transaction Processing Monitors**: Distributed transaction coordination\n\t\t- **Application Server Middleware**: J2EE, .NET application servers\n\t\t- **Web Middleware**: HTTP servers, web services, REST APIs\n\t\t- **Service Mesh**: Modern microservices communication layer (e.g., Istio, Linkerd)\n\t-\n\t- ### Common Implementations\n\t  id:: middleware-implementations\n\t\t- **Apache Kafka** - Distributed event streaming platform\n\t\t- **RabbitMQ** - Message broker with multiple protocols\n\t\t- **Redis** - In-memory data structure store and message broker\n\t\t- **NATS** - Lightweight messaging system\n\t\t- **gRPC** - High-performance RPC framework\n\t\t- **Apache ActiveMQ** - Java message service (JMS) broker\n\t\t- **ZeroMQ** - High-performance asynchronous messaging library\n\t\t- **Istio** - Service mesh for microservices\n\t\t- **Kong** - API gateway and middleware\n\t\t- **NGINX** - Web server and reverse proxy\n\t\t- **Envoy** - Cloud-native proxy and communication bus\n\t-\n\t- ### Use Cases\n\t  id:: middleware-use-cases\n\t\t- **Microservices Architecture**: Service-to-service communication\n\t\t- **Enterprise Application Integration**: Connect legacy systems\n\t\t- **Event-Driven Systems**: Real-time event streaming and processing\n\t\t- **IoT Platforms**: Device-to-cloud and device-to-device messaging\n\t\t- **Cloud-Native Applications**: Container orchestration and communication\n\t\t- **E-Commerce**: Order processing, payment gateways, inventory systems\n\t\t- **Financial Services**: Transaction processing, fraud detection\n\t\t- **Metaverse Platforms**: Real-time synchronization of virtual worlds\n\t\t- **Gaming**: Multiplayer game state synchronization\n\t\t- **Telecommunications**: Network function virtualization (NFV)\n\t-\n\t- ### Middleware in Metaverse Systems\n\t  id:: middleware-metaverse\n\t\t- **Real-Time Synchronization**: Keep virtual world state consistent across users\n\t\t- **Avatar Communication**: Enable voice, text, and gesture communication\n\t\t- **Asset Distribution**: Deliver 3D models, textures, and media efficiently\n\t\t- **Identity and Authentication**: Federate identity across virtual worlds\n\t\t- **Payment Processing**: Handle virtual economy transactions\n\t\t- **Presence Management**: Track user location and status\n\t\t- **Event Broadcasting**: Distribute world events to participants\n\t\t- **Cross-Platform Integration**: Bridge VR, AR, mobile, and web clients\n\t\t- **Spatial Audio Routing**: Manage positional audio streams\n\t\t- **Physics Synchronization**: Coordinate physics simulations\n\t-\n\t- ### Architectural Patterns\n\t  id:: middleware-patterns\n\t\t- **Publish-Subscribe**: Event-driven message distribution\n\t\t- **Request-Reply**: Synchronous communication pattern\n\t\t- **Point-to-Point**: Direct message queues between services\n\t\t- **Store-and-Forward**: Asynchronous message persistence\n\t\t- **Content-Based Routing**: Intelligent message routing\n\t\t- **Service Registry Pattern**: Dynamic service discovery\n\t\t- **Circuit Breaker**: Fault tolerance and failover\n\t\t- **Saga Pattern**: Distributed transaction coordination\n\t\t- **Event Sourcing**: State management through events\n\t\t- **CQRS (Command Query Responsibility Segregation)**: Separate read/write paths\n\t-\n\t- ### Performance Considerations\n\t  id:: middleware-performance\n\t\t- **Latency**: Minimize message transit time\n\t\t- **Throughput**: Maximize messages processed per second\n\t\t- **Scalability**: Handle increasing load through horizontal scaling\n\t\t- **Reliability**: Ensure message delivery guarantees (at-most-once, at-least-once, exactly-once)\n\t\t- **Backpressure**: Handle producer-consumer rate mismatches\n\t\t- **Resource Efficiency**: Optimize CPU, memory, network usage\n\t\t- **Connection Pooling**: Reuse network connections\n\t\t- **Batching**: Group messages for efficiency\n\t\t- **Compression**: Reduce network payload size\n\t\t- **Caching**: Reduce redundant computations and data fetches\n\t-\n\t- ### Security Aspects\n\t  id:: middleware-security\n\t\t- **Authentication**: Verify identity of communicating parties\n\t\t- **Authorization**: Enforce access control policies\n\t\t- **Encryption**: Protect data in transit (TLS/SSL)\n\t\t- **Message Signing**: Ensure message integrity\n\t\t- **Rate Limiting**: Prevent denial-of-service attacks\n\t\t- **Audit Logging**: Track all communication events\n\t\t- **Secrets Management**: Secure storage of credentials and keys\n\t\t- **Network Isolation**: Segmentation and firewall rules\n\t\t- **Zero Trust**: Verify all communications regardless of origin\n\t-\n\t- ### Challenges and Limitations\n\t  id:: middleware-challenges\n\t\t- **Complexity**: Additional layer increases system complexity\n\t\t- **Single Point of Failure**: Centralized middleware can be a bottleneck\n\t\t- **Latency Overhead**: Adds processing and network hops\n\t\t- **Vendor Lock-In**: Proprietary middleware can limit portability\n\t\t- **Debugging Difficulty**: Distributed tracing across middleware is challenging\n\t\t- **Version Compatibility**: Managing protocol and API versions\n\t\t- **Resource Consumption**: Memory and CPU overhead\n\t\t- **Configuration Management**: Complex setup and tuning\n\t-\n\t- ### Standards and References\n\t  id:: middleware-standards\n\t\t- [[EWG/MSF Taxonomy]] - Metaverse Standards Forum taxonomy\n\t\t- [[ISO/IEC 30170]] - Ruby programming language (middleware frameworks)\n\t\t- [[ETSI GR ARF 010]] - ETSI AR Framework\n\t\t- AMQP (Advanced Message Queuing Protocol) - ISO/IEC 19464\n\t\t- MQTT (Message Queuing Telemetry Transport) - ISO/IEC 20922\n\t\t- JMS (Java Message Service) - JSR 914\n\t\t- CORBA (Common Object Request Broker Architecture) - OMG\n\t\t- OpenAPI Specification - API description standard\n\t\t- CloudEvents - Standardized event data format (CNCF)\n\t-\n\t- ### Related Concepts\n\t  id:: middleware-related\n\t\t- [[VirtualObject]] - Inferred parent class\n\t\t- [[Software]] - Direct parent class\n\t\t- [[API]] - Application programming interface\n\t\t- [[Message Broker]] - Specialized middleware for messaging\n\t\t- [[Service Mesh]] - Modern microservices middleware\n\t\t- [[Enterprise Service Bus]] - Integration middleware\n\t\t- [[Distributed System]] - System architecture using middleware\n\t\t- [[Communication Protocol]] - Underlying protocols\n\t\t- [[Service Integration]] - Primary capability\n\t\t- [[Interoperability]] - Key enabled capability\n\t-\n\t- ### Technology Trends\n\t  id:: middleware-trends\n\t\t- **Service Mesh Adoption**: Moving from ESB to decentralized service mesh\n\t\t- **Serverless Middleware**: Function-as-a-Service integration\n\t\t- **Edge Computing Integration**: Middleware for IoT and edge devices\n\t\t- **WebAssembly Middleware**: Lightweight, portable middleware runtimes\n\t\t- **Zero Trust Security**: Security-first middleware architectures\n\t\t- **Observability**: Built-in tracing, metrics, and logging\n\t\t- **GraphQL Federation**: API gateway evolution\n\t\t- **Event Mesh**: Distributed event routing across clouds\n\t\t- **Quantum-Safe Cryptography**: Future-proof security\n\t\t- **AI-Powered Routing**: Intelligent message and request routing\n- ## Metadata\n  id:: middleware-metadata\n\t- imported-from:: [[Metaverse Glossary Excel]]\n\t- import-date:: [[2025-01-15]]\n\t- ontology-status:: migrated\n    - public-access:: true\n\t- migration-date:: [[2025-10-14]]\n\t- classification-rationale:: Virtual (software layer) + Object (infrastructure component) → VirtualObject\n\n\n# Middleware Ontology Entry – Updated Content\n\n## Academic Context\n\n- Middleware emerged as a formal concept in the late 1960s, though the term gained widespread adoption during the 1980s\n  - Initially conceived as a mediator between application front-ends and back-end resources (databases, mainframes, specialised hardware)[1][5]\n  - Evolved from solving legacy system integration challenges into a foundational architectural pattern for distributed computing[1][2]\n  - Now encompasses far broader scope than original mediator role, including front-end connectivity and cloud-native architectures[5]\n- Defined by IETF (2000) as services positioned above the transport layer (TCP/IP) but below application-level APIs[1]\n  - Conceptually functions as the \"hyphen\" in client-server or the \"-to-\" in peer-to-peer architectures[1]\n  - Often characterised as \"software glue\" binding disparate systems together[1][4][5]\n\n## Current Landscape (2025)\n\n- Industry adoption and implementations\n  - Web servers, application servers, and content management systems represent mainstream middleware deployments[1][2]\n  - Enterprise application integration (EAI) middleware enables seamless data exchange between heterogeneous systems without custom-built interfaces[3]\n  - Message-oriented middleware (MOM), object request brokers (ORBs), and enterprise service buses (ESBs) provide standardised communication patterns[1]\n  - Database access services (ODBC, JDBC, transaction processing monitors) remain critical middleware implementations[1]\n  - SaaS businesses increasingly leverage middleware for integrating self-sustaining applications with continuous software updates[2]\n- Technical capabilities and limitations\n  - Enables applications to communicate beyond native capabilities, supporting systems never originally designed to interoperate[4]\n  - Streamlines application development by abstracting connectivity complexity, allowing developers to focus on business logic rather than integration plumbing[6]\n  - Operates across distributed networks, cloud environments, and hybrid infrastructures[4][5]\n  - Middleware in complex embedded systems (telecom, defence, aerospace) often standardised through Service Availability Forum frameworks[1]\n  - Distinction between human-time services (web request servicing) and machine-time middleware for high-reliability systems[1]\n- Standards and frameworks\n  - IETF workshop definitions provide architectural positioning within network stacks[1]\n  - ObjectWeb framework defines middleware as the software layer between operating system and applications in distributed systems[1]\n  - Service Availability Forum standardisation particularly relevant for mission-critical embedded applications[1]\n\n## Research & Literature\n\n- Key academic and industry sources\n  - Wikipedia contributors (2024). \"Middleware.\" *Wikipedia, The Free Encyclopedia*. Provides historical context and technical taxonomy[1]\n  - IETF Workshop (2000). Middleware positioning relative to transport and application layers – foundational for distributed systems architecture[1]\n  - ObjectWeb Consortium definitions – standardised characterisation of middleware roles in distributed computing[1]\n  - Talend Resources (2024). \"What is Middleware? (And How Does it Work?)\" – contemporary enterprise integration perspective[2]\n  - Xavor (2024). \"What is Middleware Software? A Comprehensive Guide\" – comprehensive taxonomy distinguishing platform middleware from EAI middleware[3]\n  - Okta Identity 101 (2024). \"What Is Middleware? Definition, Guide & Examples\" – security and authentication middleware focus[4]\n  - IBM Think (2024). \"What Is Middleware?\" – enterprise and distributed network applications[5]\n  - Amazon AWS (2024). \"What is Middleware? – Middleware Software Explained\" – cloud-native middleware perspectives[6]\n  - Red Hat (2024). \"What is middleware?\" – open-source and enterprise Linux middleware context[7]\n- Ongoing research directions\n  - Cloud-native middleware patterns and serverless architecture integration\n  - Microservices orchestration and service mesh technologies\n  - API management and protocol standardisation in heterogeneous environments\n  - Security and authentication middleware in zero-trust architectures\n\n## UK Context\n\n- British contributions and implementations\n  - UK financial services sector extensively utilises middleware for legacy system modernisation (particularly relevant given concentration of banking infrastructure in London and regional financial centres)\n  - National Health Service (NHS) digital transformation initiatives increasingly depend on middleware for integrating disparate healthcare systems across trusts and regions\n  - UK Government Digital Service (GDS) standards incorporate middleware principles for cross-departmental data integration\n- North England innovation and adoption\n  - Manchester's growing fintech ecosystem leverages middleware for rapid integration of legacy banking systems with modern platforms\n  - Leeds financial district utilises middleware extensively for payment processing and settlement systems integration\n  - Newcastle's digital innovation initiatives include middleware-based solutions for regional public sector integration\n  - Sheffield's advanced manufacturing sector employs industrial middleware for IoT and embedded systems connectivity\n  - Regional universities (Manchester, Leeds, Sheffield) conduct research into distributed systems and middleware architectures\n\n## Future Directions\n\n- Emerging trends and developments\n  - Convergence of middleware with containerisation and Kubernetes orchestration platforms[6]\n  - Increased emphasis on API-first middleware architectures supporting microservices ecosystems\n  - Edge computing middleware for distributed processing and reduced latency requirements\n  - AI-driven middleware for intelligent routing, load balancing, and adaptive system integration\n  - Zero-trust security models reshaping middleware authentication and authorisation patterns\n- Anticipated challenges\n  - Complexity management as middleware stacks proliferate across hybrid cloud environments\n  - Performance optimisation in latency-sensitive applications\n  - Standardisation efforts across competing open-source and proprietary middleware frameworks\n  - Skills gap in middleware architecture and implementation (particularly acute in regional UK technology markets)\n- Research priorities\n  - Formal verification methods for middleware reliability in mission-critical systems\n  - Sustainable middleware design reducing computational overhead and energy consumption\n  - Interoperability standards for emerging distributed computing paradigms\n  - Human factors in middleware adoption and organisational integration\n\n## References\n\n[1] Wikipedia contributors. \"Middleware.\" *Wikipedia, The Free Encyclopedia*. Accessed November 2025.\n\n[2] Talend. \"What is Middleware? (And How Does it Work?).\" Talend Resources. Accessed November 2025.\n\n[3] Xavor. \"What is Middleware Software? A Comprehensive Guide.\" Xavor Blog. Accessed November 2025.\n\n[4] Okta. \"What Is Middleware? Definition, Guide & Examples.\" Okta Identity 101. Accessed November 2025.\n\n[5] IBM. \"What Is Middleware?\" *IBM Think*. Accessed November 2025.\n\n[6] Amazon Web Services. \"What is Middleware? – Middleware Software Explained.\" AWS Documentation. Accessed November 2025.\n\n[7] Red Hat. \"What is middleware?\" Red Hat Topics. Accessed November 2025.\n\n[8] CloudQix. \"What is Middleware? Examples & Benefits.\" CloudQix Resources Blog. Accessed November 2025.\n\n\n## Metadata\n\n- **Last Updated**: 2025-11-11\n- **Review Status**: Comprehensive editorial review\n- **Verification**: Academic sources verified\n- **Regional Context**: UK/North England where applicable",
  "properties": {
    "id": "middleware-metadata",
    "collapsed": "true",
    "- ontology": "true",
    "- term-id": "20117",
    "- source-domain": "metaverse",
    "- preferred-term": "Middleware",
    "- definition": "Software layer that mediates between applications and underlying services or infrastructure to enable communication, resource access, and interoperability.",
    "- maturity": "mature",
    "- source": "[[EWG/MSF Taxonomy]], [[ISO/IEC 30170]], [[ETSI GR ARF 010]]",
    "- owl:class": "mv:Middleware",
    "- owl:physicality": "VirtualEntity",
    "- owl:role": "Object",
    "- owl:inferred-class": "mv:VirtualObject",
    "- owl:functional-syntax": "true",
    "- belongsToDomain": "[[InfrastructureDomain]], [[ComputationAndIntelligenceDomain]]",
    "- implementedInLayer": "[[ComputeLayer]], [[DataLayer]]",
    "- is-subclass-of": "[[Metaverse Infrastructure]]",
    "- has-part": "[[Message Queue]], [[Service Registry]], [[Communication Protocol]], [[API Gateway]]",
    "- is-part-of": "[[Distributed System]], [[Software Architecture]]",
    "- requires": "[[Operating System]], [[Network Infrastructure]], [[Compute Infrastructure]]",
    "- depends-on": "[[Communication Protocol]], [[Data Format]], [[Service Discovery]]",
    "- enables": "[[Service Integration]], [[Interoperability]], [[Distributed Communication]], [[Resource Abstraction]]",
    "- imported-from": "[[Metaverse Glossary Excel]]",
    "- import-date": "[[2025-01-15]]",
    "- ontology-status": "migrated",
    "- public-access": "true",
    "- migration-date": "[[2025-10-14]]",
    "- classification-rationale": "Virtual (software layer) + Object (infrastructure component) → VirtualObject"
  },
  "backlinks": [],
  "wiki_links": [
    "Software",
    "Service Mesh",
    "Distributed System",
    "VirtualObject",
    "ETSI GR ARF 010",
    "ISO/IEC 30170",
    "Interoperability",
    "API Gateway",
    "Resource Abstraction",
    "Service Discovery",
    "ComputeLayer",
    "Data Format",
    "Operating System",
    "Metaverse Glossary Excel",
    "API",
    "Distributed Communication",
    "Software Architecture",
    "Service Integration",
    "Service Registry",
    "Message Broker",
    "Network Infrastructure",
    "Message Queue",
    "Communication Protocol",
    "ComputationAndIntelligenceDomain",
    "InfrastructureDomain",
    "Metaverse Infrastructure",
    "DataLayer",
    "Enterprise Service Bus",
    "2025-10-14",
    "EWG/MSF Taxonomy",
    "2025-01-15",
    "Compute Infrastructure"
  ],
  "ontology": {
    "term_id": "20117",
    "preferred_term": "Middleware",
    "definition": "Software layer that mediates between applications and underlying services or infrastructure to enable communication, resource access, and interoperability.",
    "source_domain": "metaverse",
    "maturity_level": null,
    "authority_score": null
  }
}