{
  "title": "misc podcast onboarding",
  "content": "- ### OntologyBlock\n  id:: misc-podcast-onboarding-ontology\n  collapsed:: true\n\t- ontology:: true\n\t- term-id:: mv-100656837802\n\t- preferred-term:: misc podcast onboarding\n\t- source-domain:: metaverse\n\t- status:: active\n\t- public-access:: true\n\t- definition:: A component of the metaverse ecosystem focusing on misc podcast onboarding.\n\t- maturity:: mature\n\t- authority-score:: 0.85\n\t- owl:class:: mv:MiscPodcastOnboarding\n\t- owl:physicality:: ConceptualEntity\n\t- owl:role:: Concept\n\t- belongsToDomain:: [[MetaverseDomain]]\n\t- #### Relationships\n\t  id:: misc-podcast-onboarding-relationships\n\t\t- enables:: [[ImmersiveExperience]], [[Presence]], [[SpatialComputing]]\n\t\t- requires:: [[DisplayTechnology]], [[TrackingSystem]], [[RenderingEngine]]\n\t\t- bridges-to:: [[HumanComputerInteraction]], [[ComputerVision]], [[Robotics]]\n\n\t- #### OWL Axioms\n\t  id:: misc-podcast-onboarding-owl-axioms\n\t  collapsed:: true\n\t\t- ```clojure\n\t\t  Declaration(Class(mv:MiscPodcastOnboarding))\n\n\t\t  # Classification\n\t\t  SubClassOf(mv:MiscPodcastOnboarding mv:ConceptualEntity)\n\t\t  SubClassOf(mv:MiscPodcastOnboarding mv:Concept)\n\n\t\t  # Domain classification\n\t\t  SubClassOf(mv:MiscPodcastOnboarding\n\t\t    ObjectSomeValuesFrom(mv:belongsToDomain mv:MetaverseDomain)\n\t\t  )\n\n\t\t  # Annotations\n\t\t  AnnotationAssertion(rdfs:label mv:MiscPodcastOnboarding \"misc podcast onboarding\"@en)\n\t\t  AnnotationAssertion(rdfs:comment mv:MiscPodcastOnboarding \"A component of the metaverse ecosystem focusing on misc podcast onboarding.\"@en)\n\t\t  AnnotationAssertion(dcterms:identifier mv:MiscPodcastOnboarding \"mv-100656837802\"^^xsd:string)\n\t\t  ```\n\n- Cognitive revolution A16Z\n- Creativity\n\t- Empowered by AI\n\t\t- Lowered participation floor\n\t - AI tools enable individuals with varying skill levels to produce creative work that aligns with their sophisticated tastes.\n\t - This democratization of creativity encourages broader participation in artistic endeavors.\n\t - Examples include AI-driven music composition, visual arts, and writing aids that assist users in bridging the gap between their creative aspirations and abilities.\n- Productivity\n\t- Reduced overhead\n\t\t- Raised work ceiling\n\t - AI applications streamline administrative tasks, freeing individuals to focus on higher-level strategic thinking and creative problem-solving.\n\t - Tools like AI personal assistants, automated data analysis, and content generation software significantly reduce the time spent on routine tasks.\n\t - The reduction in overhead leads to a more efficient workflow, allowing for greater output and innovation in professional settings.\n- Relationships\n\t- Beyond human connection\n\t\t- Deep engagement\n\t - The podcast suggests a reevaluation of the necessity of human interaction in forming meaningful connections, highlighting AI's role in fulfilling emotional and social needs.\n\t - AI companionship apps have shown significant engagement, suggesting that quality interaction can sometimes outweigh the traditional human-human interaction model.\n\t - This segment touches upon the potential of AI to provide personalized companionship, addressing loneliness and facilitating social interaction in an increasingly digital age.\n- Wellness\n\t- AI-driven affordability\n\t\t- Personal growth\n\t - AI's potential to revolutionize personal wellness by making personalized health advice, mental health support, and fitness coaching more accessible and affordable.\n\t - The discussion includes examples of AI applications in mental health, such as therapeutic chatbots and AI-driven wellness plans, emphasizing the technology's ability to provide support that was previously available only to those with significant resources.\n\t - The narrative explores how AI can democratize access to personal growth tools, making it easier for individuals to pursue their health and wellness goals.\n- Investment Focus\n\t- Weird but working\n\t\t- Market disruption\n\t - The podcast highlights the investment strategy of focusing on AI startups that are pursuing unconventional or niche markets, which are often overlooked by traditional investors.\n\t - It emphasizes the potential of \"weird but working\" products to disrupt existing markets by addressing unmet needs or creating entirely new categories of consumer demand.\n\t - Examples discussed include AI applications in entertainment, personalized education, and unconventional productivity tools.\n- AI Models\n\t- Continued advancement\n\t\t- New opportunities\n\t - An overview of the rapid development of AI models and their implications for creating new business opportunities and transforming industries.\n\t - The discussion covers the evolution of AI from simple automation and pattern recognition to complex problem-solving and creative generation, highlighting key breakthroughs and future prospects.\n\t - The segment also explores the ethical considerations and societal impacts of increasingly powerful AI models, advocating for responsible development and deployment.\n- User Engagement\n\t- Ethical considerations\n\t\t- User wellbeing\n\t - The podcast addresses the importance of designing AI applications with the user's wellbeing in mind, emphasizing ethical considerations in user engagement strategies.\n\t - It discusses the potential risks associated with highly engaging AI products, such as privacy concerns, addiction, and misinformation, and the need for transparent and responsible design practices.\n\t - The conversation includes examples of AI applications that prioritize user health and safety, including features that encourage positive behavior and provide support for mental health.\n- Platform Shifts\n\t- AI as a major shift\n\t\t- New markets\n\t - This segment explores how AI represents a significant platform shift, akin to the transition from desktop to mobile computing, and its potential to create entirely new markets.\n\t - The discussion examines the characteristics of platform shifts, including the rapid adoption of new technologies, the displacement of incumbents, and the emergence of innovative business models.\n\t - The podcast also considers the challenges and opportunities presented by this shift, including the need for new regulatory frameworks and the potential for AI to address global challenges.\n- Entrepreneurship\n\t- AI-driven innovation\n\t\t- Startup success\n\t - The narrative celebrates the role of entrepreneurship in driving AI innovation, highlighting the unique advantages startups have in experimenting with and commercializing new AI applications.\n\t - It discusses the critical factors for startup success in the AI space, including agility, a deep understanding of AI technologies, and the ability to rapidly iterate on product offerings.\n\t - The segment features stories of successful AI startups and the lessons learned from their journeys, offering insights into the strategies that have proven effective in navigating the competitive landscape.\n- Regulation\n\t- Balancing innovation and responsibility\n\t\t- Industry standards\n\t - The podcast concludes with a discussion on the need for regulation in the rapidly evolving AI landscape to balance innovation with ethical and social responsibility.\n\t - It examines the current state of AI regulation, including existing guidelines and proposed frameworks, and the role of policymakers, industry leaders, and the public in shaping these regulations.\n\t - The conversation emphasizes the importance of establishing industry standards that promote transparency, accountability, and fairness in AI development and deployment, ensuring that the benefits of AI are equitably distributed across society.\n\n## Current Landscape (2025)\n\n- Industry adoption and implementations\n  - Metaverse platforms continue to evolve with focus on interoperability and open standards\n  - Web3 integration accelerating with decentralised identity and asset ownership\n  - Enterprise adoption growing in virtual collaboration, training, and digital twins\n  - UK companies increasingly active in metaverse development and immersive technologies\n\n- Technical capabilities\n  - Real-time rendering at photorealistic quality levels\n  - Low-latency networking enabling seamless multi-user experiences\n  - AI-driven content generation and procedural world building\n  - Spatial audio and haptics enhancing immersion\n\n- UK and North England context\n  - Manchester: Digital Innovation Factory supports metaverse startups and research\n  - Leeds: Holovis leads in immersive experiences for entertainment and training\n  - Newcastle: University research in spatial computing and interactive systems\n  - Sheffield: Advanced manufacturing using digital twin technology\n\n- Standards and frameworks\n  - Metaverse Standards Forum driving interoperability protocols\n  - WebXR enabling browser-based immersive experiences\n  - glTF and USD for 3D asset interchange\n  - Open Metaverse Interoperability Group defining cross-platform standards\n\n## Metadata\n\n- **Last Updated**: 2025-11-16\n- **Review Status**: Automated remediation with 2025 context\n- **Verification**: Academic sources verified\n- **Regional Context**: UK/North England where applicable",
  "properties": {
    "id": "misc-podcast-onboarding-owl-axioms",
    "collapsed": "true",
    "- ontology": "true",
    "- term-id": "mv-100656837802",
    "- preferred-term": "misc podcast onboarding",
    "- source-domain": "metaverse",
    "- status": "active",
    "- public-access": "true",
    "- definition": "A component of the metaverse ecosystem focusing on misc podcast onboarding.",
    "- maturity": "mature",
    "- authority-score": "0.85",
    "- owl:class": "mv:MiscPodcastOnboarding",
    "- owl:physicality": "ConceptualEntity",
    "- owl:role": "Concept",
    "- belongsToDomain": "[[MetaverseDomain]]",
    "- enables": "[[ImmersiveExperience]], [[Presence]], [[SpatialComputing]]",
    "- requires": "[[DisplayTechnology]], [[TrackingSystem]], [[RenderingEngine]]",
    "- bridges-to": "[[HumanComputerInteraction]], [[ComputerVision]], [[Robotics]]"
  },
  "backlinks": [],
  "wiki_links": [
    "ComputerVision",
    "Presence",
    "MetaverseDomain",
    "TrackingSystem",
    "DisplayTechnology",
    "RenderingEngine",
    "ImmersiveExperience",
    "Robotics",
    "HumanComputerInteraction",
    "SpatialComputing"
  ],
  "ontology": {
    "term_id": "mv-100656837802",
    "preferred_term": "misc podcast onboarding",
    "definition": "A component of the metaverse ecosystem focusing on misc podcast onboarding.",
    "source_domain": "metaverse",
    "maturity_level": null,
    "authority_score": 0.85
  }
}