{
  "title": "Mistral and Mixtral",
  "content": "- ### OntologyBlock\n  id:: mistral-and-mixtral-ontology\n  collapsed:: true\n\t- ontology:: true\n\t- term-id:: mv-303578284776\n\t- preferred-term:: Mistral and Mixtral\n\t- source-domain:: metaverse\n\t- status:: active\n\t- public-access:: true\n\t- definition:: A component of the metaverse ecosystem focusing on mistral and mixtral.\n\t- maturity:: mature\n\t- authority-score:: 0.85\n\t- owl:class:: mv:MistralAndMixtral\n\t- owl:physicality:: ConceptualEntity\n\t- owl:role:: Concept\n\t- belongsToDomain:: [[MetaverseDomain]]\n\t- #### Relationships\n\t  id:: mistral-and-mixtral-relationships\n\t\t- enables:: [[ImmersiveExperience]], [[Presence]], [[SpatialComputing]]\n\t\t- requires:: [[DisplayTechnology]], [[TrackingSystem]], [[RenderingEngine]]\n\t\t- bridges-to:: [[HumanComputerInteraction]], [[ComputerVision]], [[Robotics]]\n\n\t- #### OWL Axioms\n\t  id:: mistral-and-mixtral-owl-axioms\n\t  collapsed:: true\n\t\t- ```clojure\n\t\t  Declaration(Class(mv:MistralAndMixtral))\n\n\t\t  # Classification\n\t\t  SubClassOf(mv:MistralAndMixtral mv:ConceptualEntity)\n\t\t  SubClassOf(mv:MistralAndMixtral mv:Concept)\n\n\t\t  # Domain classification\n\t\t  SubClassOf(mv:MistralAndMixtral\n\t\t    ObjectSomeValuesFrom(mv:belongsToDomain mv:MetaverseDomain)\n\t\t  )\n\n\t\t  # Annotations\n\t\t  AnnotationAssertion(rdfs:label mv:MistralAndMixtral \"Mistral and Mixtral\"@en)\n\t\t  AnnotationAssertion(rdfs:comment mv:MistralAndMixtral \"A component of the metaverse ecosystem focusing on mistral and mixtral.\"@en)\n\t\t  AnnotationAssertion(dcterms:identifier mv:MistralAndMixtral \"mv-303578284776\"^^xsd:string)\n\t\t  ```\n\n- [FireAttention — Serving Open Source Models 4x faster than vLLM by quantizing with ~no tradeoffs (fireworks.ai)](https://fireworks.ai/blog/fire-attention-serving-open-source-models-4x-faster-than-vllm-by-quantizing-with-no-tradeoffs)\n-\n- ![Screenshot 2024-02-27 073716.png](../assets/Screenshot_2024-02-27_073716_1709019997214_0.png)\n- [FireAttention — Serving Open Source Models 4x faster than vLLM by quantizing with ~no tradeoffs (fireworks.ai)](https://fireworks.ai/blog/fire-attention-serving-open-source-models-4x-faster-than-vllm-by-quantizing-with-no-tradeoffs)\n- [Introducing Mistral-Large on Azure in partnership with Mistral AI | Microsoft Azure Blog](https://azure.microsoft.com/en-us/blog/microsoft-and-mistral-ai-announce-new-partnership-to-accelerate-ai-innovation-and-introduce-mistral-large-first-on-azure/#:~:text=Mistral%20Large%20is%20a%20general-purpose%20language%20model%20that,German%2C%20Spanish%2C%20and%20Italian%20%28in%20addition%20to%20English%29.)\n- [Mistral's new code model features a 32K context window for unmatched long code support (the-decoder.com)](https://the-decoder.com/mistrals-new-code-model-features-a-32k-context-window-for-unmatched-long-code-support/)\n-\n\n## Current Landscape (2025)\n\n- Industry adoption and implementations\n  - Metaverse platforms continue to evolve with focus on interoperability and open standards\n  - Web3 integration accelerating with decentralised identity and asset ownership\n  - Enterprise adoption growing in virtual collaboration, training, and digital twins\n  - UK companies increasingly active in metaverse development and immersive technologies\n\n- Technical capabilities\n  - Real-time rendering at photorealistic quality levels\n  - Low-latency networking enabling seamless multi-user experiences\n  - AI-driven content generation and procedural world building\n  - Spatial audio and haptics enhancing immersion\n\n- UK and North England context\n  - Manchester: Digital Innovation Factory supports metaverse startups and research\n  - Leeds: Holovis leads in immersive experiences for entertainment and training\n  - Newcastle: University research in spatial computing and interactive systems\n  - Sheffield: Advanced manufacturing using digital twin technology\n\n- Standards and frameworks\n  - Metaverse Standards Forum driving interoperability protocols\n  - WebXR enabling browser-based immersive experiences\n  - glTF and USD for 3D asset interchange\n  - Open Metaverse Interoperability Group defining cross-platform standards\n\n## Metadata\n\n- **Last Updated**: 2025-11-16\n- **Review Status**: Automated remediation with 2025 context\n- **Verification**: Academic sources verified\n- **Regional Context**: UK/North England where applicable",
  "properties": {
    "id": "mistral-and-mixtral-owl-axioms",
    "collapsed": "true",
    "- ontology": "true",
    "- term-id": "mv-303578284776",
    "- preferred-term": "Mistral and Mixtral",
    "- source-domain": "metaverse",
    "- status": "active",
    "- public-access": "true",
    "- definition": "A component of the metaverse ecosystem focusing on mistral and mixtral.",
    "- maturity": "mature",
    "- authority-score": "0.85",
    "- owl:class": "mv:MistralAndMixtral",
    "- owl:physicality": "ConceptualEntity",
    "- owl:role": "Concept",
    "- belongsToDomain": "[[MetaverseDomain]]",
    "- enables": "[[ImmersiveExperience]], [[Presence]], [[SpatialComputing]]",
    "- requires": "[[DisplayTechnology]], [[TrackingSystem]], [[RenderingEngine]]",
    "- bridges-to": "[[HumanComputerInteraction]], [[ComputerVision]], [[Robotics]]"
  },
  "backlinks": [],
  "wiki_links": [
    "TrackingSystem",
    "ImmersiveExperience",
    "ComputerVision",
    "RenderingEngine",
    "SpatialComputing",
    "Robotics",
    "HumanComputerInteraction",
    "MetaverseDomain",
    "DisplayTechnology",
    "Presence"
  ],
  "ontology": {
    "term_id": "mv-303578284776",
    "preferred_term": "Mistral and Mixtral",
    "definition": "A component of the metaverse ecosystem focusing on mistral and mixtral.",
    "source_domain": "metaverse",
    "maturity_level": null,
    "authority_score": 0.85
  }
}