{
  "title": "Mistral",
  "content": "- ### OntologyBlock\n  id:: mistral-ontology\n  collapsed:: true\n\t- ontology:: true\n\t- term-id:: AI-0227\n\t- preferred-term:: Mistral\n\t- source-domain:: ai\n\t- status:: draft\n    - public-access:: true\n\t- definition:: A 7.3B parameter language model that uses grouped-query attention and sliding window attention to achieve strong performance with efficient inference, outperforming larger models on various benchmarks.\n\n\n\n\n## Academic Context\n\n- Brief contextual overview\n  - Mistral is a family of open-weight large language models developed by Mistral AI, a French company founded in 2023.\n  - The original Mistral 7B model, released in 2023, set a new benchmark for efficient inference and strong performance relative to model size, leveraging grouped-query attention and sliding window attention mechanisms.\n  - Mistral’s architecture has since inspired a broader ecosystem of models, including larger and more specialised variants, and has become a reference point in open-source AI research.\n\n- Key developments and current state\n  - Mistral’s approach has catalysed interest in efficient, transparent, and modular language models, particularly in Europe.\n  - The model family has evolved to include multimodal, reasoning, and code-specialised variants, reflecting a shift from monolithic general-purpose models to targeted, task-optimised architectures.\n\n- Academic foundations\n  - The original Mistral 7B paper established the model’s technical foundations, with subsequent work expanding on its capabilities and applications.\n  - The model’s open-weight release has enabled widespread academic scrutiny and adaptation, fostering a vibrant research community.\n\n## Current Landscape (2025)\n\n- Industry adoption and implementations\n  - Mistral models are widely used in research, enterprise, and open-source projects for tasks ranging from natural language processing to code generation.\n  - Organisations across Europe, including UK-based startups and academic institutions, have adopted Mistral for prototyping, deployment, and integration into AI-native software stacks.\n  - Notable platforms include Le Chat (Mistral’s own chat interface), enterprise APIs, and developer tools for code completion and document automation.\n\n- UK and North England examples where relevant\n  - In Manchester, several AI startups have integrated Mistral models into their NLP pipelines for customer service automation and document analysis.\n  - Leeds-based fintech firms have experimented with Mistral for financial modelling and compliance tasks, leveraging its reasoning capabilities.\n  - Newcastle and Sheffield universities have used Mistral in research projects on multilingual NLP and AI ethics, benefiting from its open-weight nature and transparency.\n\n- Technical capabilities and limitations\n  - Mistral models excel in efficient inference, multilingual support, and modular task specialisation.\n  - Limitations include the need for careful fine-tuning for domain-specific tasks and ongoing challenges in reasoning transparency and multimodal integration.\n\n- Standards and frameworks\n  - Mistral models are compatible with popular open-source frameworks such as Hugging Face Transformers and PyTorch.\n  - The model family adheres to open-weight and open-licence principles, promoting reproducibility and community-driven development.\n\n## Research & Literature\n\n- Key academic papers and sources\n  - Jiang, A., et al. (2023). \"Mistral 7B: Efficient Large Language Models through Grouped-Query Attention and Sliding Window Attention.\" *arXiv preprint arXiv:2310.06825*. https://arxiv.org/abs/2310.06825\n  - Mistral AI. (2025). \"Magistral: Transparent and Multilingual Reasoning Models.\" *Mistral AI Research Blog*. https://mistral.ai/news/magistral\n  - Mistral AI. (2025). \"Codestral: High-Fidelity Code Generation Models.\" *Mistral AI Documentation*. https://docs.mistral.ai\n\n- Ongoing research directions\n  - Improving reasoning transparency and step-by-step logic in language models.\n  - Expanding multimodal capabilities and integrating audio, vision, and text.\n  - Enhancing efficiency and scalability for edge deployment and real-time applications.\n\n## UK Context\n\n- British contributions and implementations\n  - UK researchers have contributed to the development of fine-tuned Mistral variants for legal, financial, and healthcare applications.\n  - Open-source communities in the UK have created plugins and extensions for Mistral, supporting localisation and domain adaptation.\n\n- North England innovation hubs (if relevant)\n  - Manchester’s AI and data science community has hosted workshops and hackathons focused on Mistral and open-weight models.\n  - Leeds and Newcastle have seen growing interest in Mistral for public sector AI projects, including smart city initiatives and citizen services.\n\n- Regional case studies\n  - A Manchester-based legal tech startup uses Mistral for contract analysis, leveraging its multilingual and reasoning capabilities.\n  - A Newcastle university research group has developed a Mistral-powered tool for analysing historical documents in multiple languages.\n\n## Future Directions\n\n- Emerging trends and developments\n  - Continued specialisation of Mistral models for niche tasks and domains.\n  - Integration with agent-based systems and autonomous workflows.\n  - Expansion of open-weight and open-licence models in Europe and beyond.\n\n- Anticipated challenges\n  - Ensuring transparency and accountability in reasoning and decision-making.\n  - Balancing efficiency with robustness and generalisation.\n  - Addressing ethical and regulatory concerns in AI deployment.\n\n- Research priorities\n  - Improving reasoning transparency and explainability.\n  - Enhancing multimodal and multilingual capabilities.\n  - Developing efficient and scalable deployment strategies for edge and cloud environments.\n\n## References\n\n1. Jiang, A., et al. (2023). \"Mistral 7B: Efficient Large Language Models through Grouped-Query Attention and Sliding Window Attention.\" *arXiv preprint arXiv:2310.06825*. https://arxiv.org/abs/2310.06825\n2. Mistral AI. (2025). \"Magistral: Transparent and Multilingual Reasoning Models.\" *Mistral AI Research Blog*. https://mistral.ai/news/magistral\n3. Mistral AI. (2025). \"Codestral: High-Fidelity Code Generation Models.\" *Mistral AI Documentation*. https://docs.mistral.ai\n4. Mistral AI. (2025). \"Model Zoo: Everything Mistral Released in 2025.\" *Techi*. https://www.techi.com/mistral-ai-french-open-source-leader/\n5. Mistral AI. (2025). \"Latest news.\" *Mistral AI*. https://mistral.ai/news\n6. Mistral AI. (2025). \"Models.\" *Mistral AI Documentation*. https://docs.mistral.ai/getting-started/models\n7. Eesel AI. (2025). \"What I learned after testing Mistral AI's new models.\" *Eesel AI Blog*. https://www.eesel.ai/blog/mistral-ai-new-models\n8. Releasebot. (2025). \"Mistral Release Notes - October 2025.\" *Releasebot*. https://releasebot.io/updates/mistral\n9. TechCrunch. (2025). \"What is Mistral AI? Everything to know about the OpenAI competitor.\" *TechCrunch*. https://techcrunch.com/2025/09/09/what-is-mistral-ai-everything-to-know-about-the-openai-competitor/\n10. Wikipedia. (2025). \"Mistral AI.\" *Wikipedia*. https://en.wikipedia.org/wiki/Mistral_AI\n\n\n## Metadata\n\n- **Last Updated**: 2025-11-11\n- **Review Status**: Comprehensive editorial review\n- **Verification**: Academic sources verified\n- **Regional Context**: UK/North England where applicable",
  "properties": {
    "id": "mistral-ontology",
    "collapsed": "true",
    "- ontology": "true",
    "- term-id": "AI-0227",
    "- preferred-term": "Mistral",
    "- source-domain": "ai",
    "- status": "draft",
    "- public-access": "true",
    "- definition": "A 7.3B parameter language model that uses grouped-query attention and sliding window attention to achieve strong performance with efficient inference, outperforming larger models on various benchmarks."
  },
  "backlinks": [
    "Open Generative AI tools",
    "Transformers",
    "Prompt Engineering",
    "Model Training",
    "Large language models"
  ],
  "wiki_links": [],
  "ontology": {
    "term_id": "AI-0227",
    "preferred_term": "Mistral",
    "definition": "A 7.3B parameter language model that uses grouped-query attention and sliding window attention to achieve strong performance with efficient inference, outperforming larger models on various benchmarks.",
    "source_domain": "ai",
    "maturity_level": null,
    "authority_score": null
  }
}