{
  "title": "MITIH bid assessment",
  "content": "- ### OntologyBlock\n  id:: mitih-bid-assessment-ontology\n  collapsed:: true\n\t- ontology:: true\n\t- term-id:: mv-797076606678\n\t- preferred-term:: MITIH bid assessment\n\t- source-domain:: metaverse\n\t- status:: active\n\t- public-access:: true\n\t- definition:: A component of the metaverse ecosystem focusing on mitih bid assessment.\n\t- maturity:: mature\n\t- authority-score:: 0.85\n\t- owl:class:: mv:MitihBidAssessment\n\t- owl:physicality:: ConceptualEntity\n\t- owl:role:: Concept\n\t- belongsToDomain:: [[MetaverseDomain]]\n\t- #### Relationships\n\t  id:: mitih-bid-assessment-relationships\n\t\t- enables:: [[ImmersiveExperience]], [[Presence]], [[SpatialComputing]]\n\t\t- requires:: [[DisplayTechnology]], [[TrackingSystem]], [[RenderingEngine]]\n\t\t- bridges-to:: [[HumanComputerInteraction]], [[ComputerVision]], [[Robotics]]\n\n\t- #### OWL Axioms\n\t  id:: mitih-bid-assessment-owl-axioms\n\t  collapsed:: true\n\t\t- ```clojure\n\t\t  Declaration(Class(mv:MitihBidAssessment))\n\n\t\t  # Classification\n\t\t  SubClassOf(mv:MitihBidAssessment mv:ConceptualEntity)\n\t\t  SubClassOf(mv:MitihBidAssessment mv:Concept)\n\n\t\t  # Domain classification\n\t\t  SubClassOf(mv:MitihBidAssessment\n\t\t    ObjectSomeValuesFrom(mv:belongsToDomain mv:MetaverseDomain)\n\t\t  )\n\n\t\t  # Annotations\n\t\t  AnnotationAssertion(rdfs:label mv:MitihBidAssessment \"MITIH bid assessment\"@en)\n\t\t  AnnotationAssertion(rdfs:comment mv:MitihBidAssessment \"A component of the metaverse ecosystem focusing on mitih bid assessment.\"@en)\n\t\t  AnnotationAssertion(dcterms:identifier mv:MitihBidAssessment \"mv-797076606678\"^^xsd:string)\n\t\t  ```\n\n- Bid documents and analysis\n\t- [FW_ Core docst.zip](../assets/FW_Core_docst_1715339739482_0.zip)\n\t- Review this innovate UK bid. review all the documents please. Iteratively build an analysis in a markdown table using a panel of experts chosen for the task. You should invite new panel members as the analysis evolves, if appropriate. Process the documents in sets of two then confirm the approach is working with me.\n\t  The best overall approach would be to discuss each document in turn, demonstrating the understanding as a congenial discussion between the experts. When all documents have been discussed the experts should be reduced to the most productive members and the whole bid scope of documents should be examined again by that sub group, with a more critical eye for problematic details. Please proceed methodically.\n\t\t- **Initial Review**: We'll begin by reviewing the first two documents in detail. This initial analysis will help to establish the discussion's framework and identify key areas for focus.\n\t\t- **Discussion Format**: Each document will be discussed in a congenial manner among a panel of hypothetical experts, each bringing a specialized viewpoint to ensure a comprehensive evaluation.\n\t\t- **Expert Panel**: Initially, we will involve a broad range of expertise. As we progress, we may adjust the panel based on the relevance and productivity of the discussions.\n\t\t- **Iterative Analysis**: After reviewing each pair of documents, we'll summarize the findings in a markdown table and discuss whether the approach is effective or needs adjustment.\n\t\t- **Final Review**: Once all documents have been reviewed, the most productive panel members will re-examine the entire bid scope with a critical eye for detail.\n\t\t- **MediaCity ITIH exploitation_plan v3 draft for InnovateUK review.pdf**\n\t\t- **MediaCity ITIH IGM-InnovateUK Application Final IFS print 1 November 22.pdf**\n\t\t- ### Document Analysis: MediaCity ITIH Exploitation Plan v3 Draft\n\t\t- #### Summary\n\t\t\t- The \"MediaCity ITIH Exploitation Plan v3 Draft\" is a strategic document intended to outline the exploitation strategies for the MediaCity Immersive Technologies Innovation Hub (MITIH). It serves as a \"living document\" that is updated throughout the project to reflect changes in the commercial environment, resource commitments, and stakeholder monitoring.\n\t\t- #### Key Points\n\t\t\t- **Objective**: To confirm the business case for MITIH and detail the partners' activities towards exploitation of the project's results.\n\t\t\t- **Technical Approach**: Engaging with industry and researchers to develop R&D programs that leverage immersive technologies. This approach aims to foster innovation and skills development across various sectors.\n\t\t\t- **Expected Impact**: The plan projects attracting £15 million in industry-led R&D investment over the next three years, specifically targeting the Creative Industries and utilizing immersive technologies to enhance audience engagement and revenue generation.\n\t\t- #### Strengths\n\t\t\t- Comprehensive exploitation strategy aligned with industry needs and technological advancements.\n\t\t\t- Clear focus on immersive technologies as a catalyst for sector-wide innovation and skills development.\n\t\t- #### Weaknesses\n\t\t\t- The draft status of the document suggests that some aspects may not be fully developed or finalized.\n\t\t\t- Potential risks or challenges in execution are not clearly outlined in the provided excerpt.\n\t\t- ### Document Analysis: MediaCity ITIH IGM-InnovateUK Application Final IFS Print\n\t\t- #### Summary\n\t\t\t- The \"MediaCity ITIH IGM-InnovateUK Application Final IFS Print\" provides comprehensive details about the application for the MediaCity Immersive Technologies Innovation Hub. It includes information on the project’s objectives, partners, funding, and timeline.\n\t\t- #### Key Points\n\t\t\t- **Partners and Stakeholders**: Key partners include the University of Salford, Salford City Council, and various private sector entities such as Peel L&P and Landsec.\n\t\t\t- **Project Start and Duration**: The project is planned to start on April 1, 2023, with a duration of 24 months.\n\t\t\t- **Focus Areas**: The innovation hub will focus on R&D around immersive technologies with applications in entertainment, gaming, arts, education, and more.\n\t\t\t- **Goal**: To establish a people-centered innovation hub that strengthens the local Digital & Creative economy and supports Greater Manchester’s frontier sectors.\n\t\t- #### Strengths\n\t\t\t- Strong partnership framework with significant stakeholders involved.\n\t\t\t- Clear focus on R&D in emerging technologies with practical applications across diverse sectors.\n\t\t- #### Weaknesses\n\t\t\t- The document does not detail specific metrics for evaluating the success of the project.\n\t\t\t- Challenges related to coordinating multiple stakeholders and aligning their interests and contributions are not addressed.\n\t\t- | Document Title | Key Objectives | Strengths | Weaknesses |\n\t\t  | ---- | ---- | ---- |\n\t\t  | MediaCity ITIH Exploitation Plan v3 Draft | Develop exploitation strategies for immersive tech R&D | Comprehensive strategy; focus on industry needs | Draft status; lack of detailed risk assessment |\n\t\t  | MediaCity ITIH IGM-InnovateUK Application Final IFS Print | Establish a technology innovation hub | Strong partnerships; diverse application areas | Lack of specific success metrics; potential stakeholder alignment issues |\n\t\t- ### Document Analysis: MediaCity ITIH IGM-InnovateUK Application Q3 Appendix\n\t\t- #### Summary\n\t\t\t- The \"MediaCity ITIH IGM-InnovateUK Application Q3 Appendix\" focuses on identifying the needs or challenges that the project aims to address, as well as the proposed approaches to tackling these issues within the context of immersive technologies and the digital and creative industries.\n\t\t- #### Key Points\n\t\t\t- **Challenge Identification**: The document outlines MediaCity's existing business community and its potential to expand and accelerate R&D activities in immersive technologies.\n\t\t\t- **Innovation Ecosystem**: It emphasizes the creation of an innovation ecosystem that will capture cross-sector opportunities and channel them into appropriate programs.\n\t\t\t- **Programme Structure**: Details a structured journey for opportunities, including recruitment, assignment, and provision of resources. It also mentions the organization of Labs and Events such as workshops, sprints, and hackathons to foster collaboration between industry, supply chain partners, and academia.\n\t\t- #### Strengths\n\t\t\t- Clear definition of the existing challenges and opportunities within MediaCity’s digital and creative sectors.\n\t\t\t- Detailed program structure to ensure effective management and execution of innovation-related activities.\n\t\t- #### Weaknesses\n\t\t\t- The document may lack detailed risk assessment and mitigation strategies for the outlined programs.\n\t\t\t- Specific outcomes or success metrics for the initiatives are not elaborated upon.\n\t\t- ### Document Analysis: MediaCity ITIH IGM-InnovateUK Application Q4 Appendix\n\t\t- #### Summary\n\t\t\t- The \"MediaCity ITIH IGM-InnovateUK Application Q4 Appendix\" provides details about the team and resources dedicated to the MediaCity Immersive Technologies Innovation Hub project, highlighting key personnel and their roles in the initiative.\n\t\t- #### Key Points\n\t\t\t- **Team Composition**: The document lists several key figures involved in the project, including Steven Fry (Assistant Director of Customer and Digital Services at Salford City Council) and Anthony Hatton (Director of Strategic Projects, Peel L&P/Peel Media).\n\t\t\t- **Expertise and Roles**: It details the backgrounds and current roles of the team members, emphasizing their expertise and contributions to the project. For example, Steven Fry is involved in digital and technology services at Salford City Council and serves as Chief Technology and Innovation Officer at HOST.\n\t\t\t- **Academic and Commercial Leadership**: The appendix also introduces Professor Andy Miah from the University of Salford, who brings academic leadership in Science Communication & Future Media.\n\t\t- #### Strengths\n\t\t\t- The document showcases a diverse and experienced team, ensuring a comprehensive approach to the project's execution.\n\t\t\t- Clear delineation of roles and responsibilities provides a strong foundation for project governance.\n\t\t- #### Weaknesses\n\t\t\t- While the document details the team's qualifications, it may not fully describe how these resources will be deployed throughout the project’s timeline.\n\t\t\t- The interdependencies between team roles and project outcomes are not explicitly outlined, which could affect clarity on accountability.\n\t\t- | Document Title | Key Objectives | Strengths | Weaknesses |\n\t\t  | ---- | ---- | ---- |\n\t\t  | MediaCity ITIH IGM-InnovateUK Application Q3 Appendix | Address challenges in digital and creative industries | Detailed program structure; clear challenge identification | Lack of detailed risk assessment; missing success metrics |\n\t\t  | MediaCity ITIH IGM-InnovateUK Application Q4 Appendix | Outline team and resources for the innovation hub | Experienced and diverse team; clear roles | Lack of detailed resource deployment plan; unclear interdependencies |\n\t\t- ### Document Analysis: MediaCity ITIH IGM-InnovateUK Application Q9 Appendix Co-Investment Form\n\t\t- #### Summary\n\t\t\t- The \"MediaCity ITIH IGM-InnovateUK Application Q9 Appendix Co-Investment Form\" outlines the co-investment targets and details for the MediaCity project, including various forms of investment and the confidence levels in securing these investments.\n\t\t- #### Key Points\n\t\t\t- **Co-Investment Targets**: The document specifies targets ranging from £4.9 million to £6.4 million for the first two years (April 2023 - March 2025), with subsequent annual targets of £3 million to £5 million.\n\t\t- **Investment Forms**:\n\t\t\t- **Pledged Co-Investment**: Currently none.\n\t\t\t- **Accompanying Co-Investment**: £386k with high confidence levels in securing additional funds.\n\t\t\t- **Aligned Co-Investment**: To be determined, but with high confidence in opportunities.\n\t\t\t- **Follow-on Investment**: Also to be determined, with high expectations for future investment opportunities.\n\t\t\t- **Specific Partnerships**: Lists partners like AIX Live and Pathway, detailing the contributions and investments from these partners in terms of facilities and resources.\n\t\t- #### Strengths\n\t\t\t- Detailed breakdown of investment types and confidence levels, providing a clear financial roadmap for the project.\n\t\t\t- Strong partnerships with specific contributions outlined, enhancing the project's credibility and feasibility.\n\t\t- #### Weaknesses\n\t\t\t- Some investment categories are still to be determined, indicating potential uncertainty in the full financing of the project.\n\t\t\t- The document does not specify contingency plans if expected investments fail to materialize.\n\t\t- ### Document Analysis: MediaCity ITIH Milestone Plan August 2023\n\t\t- #### Summary\n\t\t\t- The \"MediaCity ITIH Milestone Plan August 2023\" document outlines a detailed schedule and set of milestones for the MediaCity Immersive Technologies Innovation Hub project, covering a timeline from March 2023 through March 2025.\n\t\t- #### Key Points\n\t\t\t- **Timeline and Phases**: The plan spans two years, detailing monthly milestones for various phases including programme management, governance, finance and accounting, business development, commercialisation, and recruitment.\n\t\t\t- **Specific Milestones**:\n\t\t\t\t- **Programme Management**: Includes steps like notification of funding, due diligence, and entering grant agreements.\n\t\t\t\t- **Governance**: Formation of advisory groups, regular meetings, and review/recruitment of new members.\n\t\t\t\t- **Business Development**: Activities such as recruitment of a Business Development Manager, industry partner engagement, and securing co-investment.\n\t\t\t\t- **Commercialisation and IP Management**: Outlining terms and conditions for participation in the hub's activities and managing intellectual property.\n\t\t\t- #### Strengths\n\t\t\t\t- Comprehensive and clear outline of all necessary steps, providing a robust framework for project execution.\n\t\t\t\t- Inclusion of specific, measurable milestones ensures accountability and facilitates tracking progress against goals.\n\t\t\t- #### Weaknesses\n\t\t\t\t- The complexity of the schedule may pose challenges in terms of adaptability and responsiveness to unforeseen delays or changes.\n\t\t\t\t- Dependencies between tasks are not explicitly stated, which could impact the overall flow and success of the project if delays occur in key areas.\n\t\t- ### Comprehensive Summary Table\n\t\t- Here’s a markdown table summarizing all the documents reviewed, including the latest insights:\n\t\t- | Document Title | Key Objectives | Strengths | Weaknesses |\n\t\t  | ---- | ---- | ---- |\n\t\t  | MediaCity ITIH Exploitation Plan v3 Draft | Develop exploitation strategies for immersive tech R&D | Comprehensive strategy; focus on industry needs | Draft status; lack of detailed risk assessment |\n\t\t  | MediaCity ITIH IGM-InnovateUK Application Final IFS Print | Establish a technology innovation hub | Strong partnerships; diverse application areas | Lack of specific success metrics; stakeholder alignment |\n\t\t  | MediaCity ITIH IGM-InnovateUK Application Q3 Appendix | Address challenges in digital and creative industries | Detailed program structure; clear challenge identification | Lack of detailed risk assessment; missing success metrics |\n\t\t  | MediaCity ITIH IGM-InnovateUK Application Q4 Appendix | Outline team and resources for the innovation hub | Experienced and diverse team; clear roles | Lack of detailed resource deployment; unclear dependencies |\n\t\t  | MediaCity ITIH IGM-InnovateUK Application Q9 Appendix Co-Investment | Detail financial co-investment plans for the project | Detailed investment breakdown; strong partnerships | Uncertainties in funding; no contingency plans |\n\t\t  | MediaCity ITIH Milestone Plan August 2023 | Schedule and milestones for project execution | Detailed timeline; specific measurable milestones | Complexity could hinder adaptability; unclear dependencies |\n\t\t- ### Exhaustive Report on High-Level Problems and Mission-Critical Risks\n\t\t- #### 1.  **Funding and Financial Sustainability**\n\t\t\t- **Risk of Unsecured Co-Investment**: The bid relies heavily on co-investment, which includes varying degrees of confidence in securing these funds. This presents a substantial risk if projected funds are not realized, potentially derailing project milestones.\n\t\t\t- **Lack of Contingency Funding Plans**: There is no clear outline of contingency plans in case the initial funding targets are not met, which could compromise the project's financial stability and sustainability.\n\t\t- #### 2.  **Project Management and Governance**\n\t\t\t- **Complexity in Coordination**: The project involves multiple stakeholders and partners, increasing the complexity of coordination. The risk of misalignment in goals, delays in decision-making, or conflicts could impact project timelines and outcomes.\n\t\t\t- **Dependency on Key Personnel**: The project appears heavily dependent on specific individuals for leadership and execution. Any changes in personnel could disrupt project continuity and governance.\n\t\t- #### 3.  **Operational Execution**\n\t\t\t- **Ambiguity in Task Dependencies**: The milestone plan shows a comprehensive timeline but lacks clarity on dependencies between tasks. This omission can lead to bottlenecks where delays in one area could have a cascading effect on the overall project timeline.\n\t\t\t- **Adaptability to Changes**: The detailed schedule may limit the project's ability to adapt to unforeseen changes or opportunities, potentially affecting responsiveness to industry innovations or shifts.\n\t\t- #### 4.  **Strategic Alignment and Stakeholder Engagement**\n\t\t\t- **Insufficient Detail on Stakeholder Roles and Contributions**: While the documents list various partners and their roles, they do not sufficiently detail the specific contributions or expectations from each, which could lead to unmet expectations and reduced stakeholder engagement.\n\t\t\t- **Risk of Inadequate Industry Partner Mobilization**: The project's success is contingent on effective mobilization and sustained commitment from industry partners. Failure to secure or maintain these partnerships could significantly impact project deliverables and outcomes.\n\t\t- #### 5.  **Commercialization and Market Impact**\n\t\t\t- **Unclear Commercialization Strategy**: Although the project aims to foster innovation using immersive technologies, the commercialization paths and strategies to market the developed technologies are not explicitly defined.\n\t\t\t- **Intellectual Property (IP) Management Concerns**: The management and protection of IP are crucial for securing the commercial benefits of innovations. The bid lacks a detailed strategy for IP management, which could hinder potential revenue streams and partnerships.\n\t\t- #### Conclusion\n\t\t\t- The MediaCity ITIH project bid, while ambitious and potentially transformative, exhibits several high-level problems and mission-critical risks that need to be addressed to ensure its viability and success. It is recommended that the project team:\n\t\t\t- Develops a robust contingency plan for funding.\n\t\t\t- Clarifies task dependencies and builds flexibility into the project management approach.\n\t\t\t- Enhances stakeholder engagement strategies.\n\t\t\t- Defines a clear commercialization pathway and strengthens IP management protocols.\n\t\t\t- This analysis can serve as a basis for refining the project strategy and operational planning to mitigate identified risks and enhance the project's likelihood of success. Would you like to discuss any specific aspect of this report further, or is there another area of the bid you would like to explore in more detail?\n\n## Current Landscape (2025)\n\n- Industry adoption and implementations\n  - Metaverse platforms continue to evolve with focus on interoperability and open standards\n  - Web3 integration accelerating with decentralised identity and asset ownership\n  - Enterprise adoption growing in virtual collaboration, training, and digital twins\n  - UK companies increasingly active in metaverse development and immersive technologies\n\n- Technical capabilities\n  - Real-time rendering at photorealistic quality levels\n  - Low-latency networking enabling seamless multi-user experiences\n  - AI-driven content generation and procedural world building\n  - Spatial audio and haptics enhancing immersion\n\n- UK and North England context\n  - Manchester: Digital Innovation Factory supports metaverse startups and research\n  - Leeds: Holovis leads in immersive experiences for entertainment and training\n  - Newcastle: University research in spatial computing and interactive systems\n  - Sheffield: Advanced manufacturing using digital twin technology\n\n- Standards and frameworks\n  - Metaverse Standards Forum driving interoperability protocols\n  - WebXR enabling browser-based immersive experiences\n  - glTF and USD for 3D asset interchange\n  - Open Metaverse Interoperability Group defining cross-platform standards\n\n## Metadata\n\n- **Last Updated**: 2025-11-16\n- **Review Status**: Automated remediation with 2025 context\n- **Verification**: Academic sources verified\n- **Regional Context**: UK/North England where applicable",
  "properties": {
    "id": "mitih-bid-assessment-owl-axioms",
    "collapsed": "true",
    "- ontology": "true",
    "- term-id": "mv-797076606678",
    "- preferred-term": "MITIH bid assessment",
    "- source-domain": "metaverse",
    "- status": "active",
    "- public-access": "true",
    "- definition": "A component of the metaverse ecosystem focusing on mitih bid assessment.",
    "- maturity": "mature",
    "- authority-score": "0.85",
    "- owl:class": "mv:MitihBidAssessment",
    "- owl:physicality": "ConceptualEntity",
    "- owl:role": "Concept",
    "- belongsToDomain": "[[MetaverseDomain]]",
    "- enables": "[[ImmersiveExperience]], [[Presence]], [[SpatialComputing]]",
    "- requires": "[[DisplayTechnology]], [[TrackingSystem]], [[RenderingEngine]]",
    "- bridges-to": "[[HumanComputerInteraction]], [[ComputerVision]], [[Robotics]]"
  },
  "backlinks": [
    "MITIH"
  ],
  "wiki_links": [
    "ComputerVision",
    "Presence",
    "MetaverseDomain",
    "TrackingSystem",
    "DisplayTechnology",
    "RenderingEngine",
    "ImmersiveExperience",
    "Robotics",
    "HumanComputerInteraction",
    "SpatialComputing"
  ],
  "ontology": {
    "term_id": "mv-797076606678",
    "preferred_term": "MITIH bid assessment",
    "definition": "A component of the metaverse ecosystem focusing on mitih bid assessment.",
    "source_domain": "metaverse",
    "maturity_level": null,
    "authority_score": 0.85
  }
}