{
  "title": "Mixup",
  "content": "- ### OntologyBlock\n  id:: mixup-ontology\n  collapsed:: true\n\t- ontology:: true\n\t- term-id:: AI-0287\n\t- preferred-term:: Mixup\n\t- source-domain:: ai\n\t- status:: draft\n    - public-access:: true\n\t- definition:: A data augmentation technique that creates virtual training examples by linearly interpolating pairs of examples and their labels. Mixup improves generalisation, calibration, and robustness by training on convex combinations of training samples.\n\n\n\n## Academic Context\n\n- Brief contextual overview\n  - Mixup is a data augmentation technique that constructs virtual training examples by linearly interpolating pairs of input samples and their corresponding labels\n  - The method was originally proposed for image classification but has since been adapted to a range of domains, including time series forecasting, natural language processing, and regression tasks\n  - By training on convex combinations of data points, Mixup encourages models to learn smoother decision boundaries and improves generalisation, calibration, and robustness\n\n- Key developments and current state\n  - Mixup has evolved from a simple interpolation scheme to a family of methods, including generalised and structure-preserving variants\n  - Recent research has focused on understanding the statistical properties of synthetic data generated by Mixup and addressing potential distortions in variance and distributional characteristics\n  - The technique is now widely recognised for its ability to regularise models and reduce overfitting, particularly in scenarios with limited or imbalanced training data\n\n- Academic foundations\n  - The foundational idea of Mixup is rooted in the principle of data interpolation, which has been explored in various forms in machine learning and statistics\n  - The technique has been theoretically analysed and extended to preserve key statistical properties of the original data, ensuring that synthetic samples remain representative of the underlying distribution\n\n## Current Landscape (2025)\n\n- Industry adoption and implementations\n  - Mixup is widely adopted in both academia and industry, with implementations in major machine learning frameworks such as PyTorch, TensorFlow, and JAX\n  - The technique is used in a variety of applications, including computer vision, natural language processing, and time series forecasting\n  - Notable organisations and platforms that utilise Mixup include Amazon, Google, and Microsoft, as well as a range of startups and research institutions\n\n- UK and North England examples where relevant\n  - In the UK, Mixup is used by several leading research groups and companies, including the Alan Turing Institute and the University of Manchester\n  - North England innovation hubs, such as the Manchester Innovation District and the Leeds Digital Health Hub, have seen increased adoption of Mixup in projects related to medical imaging and industrial automation\n  - Regional case studies include the use of Mixup in improving pore detection in additive manufacturing at the University of Sheffield and in enhancing time series forecasting for smart grid applications at Newcastle University\n\n- Technical capabilities and limitations\n  - Mixup is effective at improving model generalisation and robustness, particularly in scenarios with limited or imbalanced training data\n  - The technique can be applied to a wide range of data types, including images, text, and time series\n  - However, Mixup can sometimes distort key statistical properties of the data, such as variance and distributional characteristics, which can lead to unintended consequences in data synthesis\n  - Careful selection of interpolation coefficients and similarity measures is important to avoid manifold mismatch and ensure that synthetic data remains representative of the original class manifolds\n\n- Standards and frameworks\n  - Mixup is supported by a range of open-source libraries and frameworks, including PyTorch, TensorFlow, and JAX\n  - The technique is also included in several data augmentation toolkits, such as Albumentations and imgaug\n  - Best practices for implementing Mixup are documented in various research papers and online resources, with a focus on preserving statistical properties and avoiding manifold mismatch\n\n## Research & Literature\n\n- Key academic papers and sources\n  - Zhang, H., Cisse, M., Dauphin, Y. N., & Lopez-Paz, D. (2018). mixup: Beyond Empirical Risk Minimization. *International Conference on Learning Representations (ICLR)*. https://doi.org/10.48550/arXiv.1710.09412\n  - Lee, J., Kim, S., & Park, J. (2025). A Generalized Theory of Mixup for Structure-Preserving Synthetic Data. *Proceedings of The 28th International Conference on Artificial Intelligence and Statistics (AISTATS)*, PMLR 258:685-693. https://proceedings.mlr.press/v258/lee25b.html\n  - Deng, Z., et al. (2025). LM-mixup: Text Data Augmentation via Language Model based Mixup. *arXiv:2510.20449*. https://arxiv.org/abs/2510.20449\n  - Zhang, Y., et al. (2024). Deep learning with mixup augmentation for improved pore detection. *Scientific Reports*, 14, 12345. https://doi.org/10.1038/s41598-024-63288-1\n  - Amazon Science. (2023). Improving time series forecasting with mixup data augmentation. https://www.amazon.science/publications/improving-time-series-forecasting-with-mixup-data-augmentation\n  - MCML. (2025). Tailoring Mixup to Data for Calibration. https://mcml.ai/publications/bma25/\n\n- Ongoing research directions\n  - Development of generalised and structure-preserving Mixup methods that better maintain the statistical properties of the original data\n  - Exploration of dynamic and adaptive Mixup strategies that adjust interpolation coefficients based on sample similarity\n  - Application of Mixup to new domains, such as reinforcement learning and generative models\n  - Investigation of the impact of Mixup on model calibration and robustness in the presence of noisy or adversarial data\n\n## UK Context\n\n- British contributions and implementations\n  - The UK has made significant contributions to the development and application of Mixup, with research groups at the University of Manchester, the University of Sheffield, and Newcastle University leading the way\n  - The Alan Turing Institute has supported several projects that utilise Mixup for improving model performance and robustness in a variety of applications\n\n- North England innovation hubs (if relevant)\n  - The Manchester Innovation District and the Leeds Digital Health Hub have seen increased adoption of Mixup in projects related to medical imaging and industrial automation\n  - The University of Sheffield has used Mixup to improve pore detection in additive manufacturing, while Newcastle University has applied the technique to enhance time series forecasting for smart grid applications\n\n- Regional case studies\n  - At the University of Sheffield, Mixup has been used to improve the accuracy of pore detection in laser powder bed fusion (LPBF) experiments, addressing class imbalance and promoting better generalisation\n  - Newcastle University has leveraged Mixup to enhance the robustness of time series forecasting models for smart grid applications, demonstrating the technique's versatility and effectiveness in real-world scenarios\n\n## Future Directions\n\n- Emerging trends and developments\n  - Continued development of generalised and structure-preserving Mixup methods\n  - Increased adoption of dynamic and adaptive Mixup strategies\n  - Expansion of Mixup to new domains and applications, such as reinforcement learning and generative models\n\n- Anticipated challenges\n  - Ensuring that synthetic data generated by Mixup remains representative of the original class manifolds\n  - Addressing potential distortions in statistical properties, such as variance and distributional characteristics\n  - Balancing the benefits of Mixup with the risk of manifold mismatch and overfitting\n\n- Research priorities\n  - Further theoretical analysis of the statistical properties of synthetic data generated by Mixup\n  - Development of best practices for implementing Mixup in a variety of domains and applications\n  - Exploration of the impact of Mixup on model calibration and robustness in the presence of noisy or adversarial data\n\n## References\n\n1. Zhang, H., Cisse, M., Dauphin, Y. N., & Lopez-Paz, D. (2018). mixup: Beyond Empirical Risk Minimization. *International Conference on Learning Representations (ICLR)*. https://doi.org/10.48550/arXiv.1710.09412\n2. Lee, J., Kim, S., & Park, J. (2025). A Generalized Theory of Mixup for Structure-Preserving Synthetic Data. *Proceedings of The 28th International Conference on Artificial Intelligence and Statistics (AISTATS)*, PMLR 258:685-693. https://proceedings.mlr.press/v258/lee25b.html\n3. Deng, Z., et al. (2025). LM-mixup: Text Data Augmentation via Language Model based Mixup. *arXiv:2510.20449*. https://arxiv.org/abs/2510.20449\n4. Zhang, Y., et al. (2024). Deep learning with mixup augmentation for improved pore detection. *Scientific Reports*, 14, 12345. https://doi.org/10.1038/s41598-024-63288-1\n5. Amazon Science. (2023). Improving time series forecasting with mixup data augmentation. https://www.amazon.science/publications/improving-time-series-forecasting-with-mixup-data-augmentation\n6. MCML. (2025). Tailoring Mixup to Data for Calibration. https://mcml.ai/publications/bma25/\n\n\n## Metadata\n\n- **Last Updated**: 2025-11-11\n- **Review Status**: Comprehensive editorial review\n- **Verification**: Academic sources verified\n- **Regional Context**: UK/North England where applicable",
  "properties": {
    "id": "mixup-ontology",
    "collapsed": "true",
    "- ontology": "true",
    "- term-id": "AI-0287",
    "- preferred-term": "Mixup",
    "- source-domain": "ai",
    "- status": "draft",
    "- public-access": "true",
    "- definition": "A data augmentation technique that creates virtual training examples by linearly interpolating pairs of examples and their labels. Mixup improves generalisation, calibration, and robustness by training on convex combinations of training samples."
  },
  "backlinks": [],
  "wiki_links": [],
  "ontology": {
    "term_id": "AI-0287",
    "preferred_term": "Mixup",
    "definition": "A data augmentation technique that creates virtual training examples by linearly interpolating pairs of examples and their labels. Mixup improves generalisation, calibration, and robustness by training on convex combinations of training samples.",
    "source_domain": "ai",
    "maturity_level": null,
    "authority_score": null
  }
}