{
  "title": "Mobile Robot",
  "content": "- ### OntologyBlock\n  id:: mobile-robot-ontology\n  collapsed:: true\n\n  - **Identification**\n\n    - domain-prefix:: RB\n\n    - sequence-number:: 0002\n\n    - filename-history:: [\"RB-0002-mobile-robot.md\"]\n    - public-access:: true\n    - ontology:: true\n    - term-id:: RB-0002\n    - preferred-term:: Mobile Robot\n    - source-domain:: metaverse\n    - status:: complete\n    - version:: 2.0.0\n    - last-updated:: 2025-11-14\n\n  - **Definition**\n    - definition:: A mobile robot is a robot with locomotion capabilities that enable it to move within its working environment.\n    - maturity:: mature\n    - source:: [[ISO 8373:2021]]\n    - authority-score:: 0.98\n\n  - **Semantic Classification**\n    - owl:class:: rb:MobileRobot\n    - owl:physicality:: PhysicalEntity\n    - owl:role:: Object\n    - belongsToDomain:: [[Robotics]]\n\n  - #### Relationships\n    id:: mobile-robot-relationships\n    - is-part-of:: [[Robot (RB-0001)]]\n    - related-to:: [[Autonomous Navigation]]\n    - related-to:: [[SLAM]]\n    - related-to:: [[Robot Operating System]]\n    - related-to:: [[Multi-Robot Systems]]\n    - related-to:: [[Warehouse Automation]]\n\n  - #### OWL Axioms\n    id:: mobile-robot-owl-axioms\n    collapsed:: true\n    - ```clojure\n      ; Core Class Declaration\n      (Declaration (Class :MobileRobot))\n      (SubClassOf :MobileRobot :Robot)\n\n      ; Defining Characteristics\n      (SubClassOf :MobileRobot\n        (ObjectSomeValuesFrom :hasLocomotionSystem :LocomotionMechanism))\n\n      (SubClassOf :MobileRobot\n        (ObjectSomeValuesFrom :hasNavigationCapability :NavigationSystem))\n\n      (SubClassOf :MobileRobot\n        (ObjectSomeValuesFrom :performsLocalisation :LocalisationMethod))\n\n      (SubClassOf :MobileRobot\n        (ObjectSomeValuesFrom :operatesInEnvironment :OperationalEnvironment))\n\n      ; Locomotion Types (Disjoint Union)\n      (DisjointUnion :LocomotionMechanism\n        (:WheeledLocomotion :TrackedLocomotion :LeggedLocomotion\n         :AerialLocomotion :AquaticLocomotion :HybridLocomotion))\n\n      ; Properties\n      (DataPropertyAssertion :hasLocomotionCapability :MobileRobot \"true\"^^xsd:boolean)\n      (DataPropertyAssertion :requiresNavigation :MobileRobot \"true\"^^xsd:boolean)\n\n      ; Navigation Requirements\n      (SubClassOf :MobileRobot\n        (ObjectMinCardinality 1 :hasSensor :PerceptionSensor))\n\n      ; Annotations\n      (AnnotationAssertion rdfs:label :MobileRobot \"Mobile Robot\"@en)\n      (AnnotationAssertion rdfs:comment :MobileRobot\n        \"Robot with locomotion capabilities for environmental navigation\"@en)\n      (AnnotationAssertion :hasISOReference :MobileRobot \"ISO 8373:2021\"^^xsd:string)\n\n      ; Object Properties\n      (Declaration (ObjectProperty :hasLocomotionSystem))\n      (ObjectPropertyDomain :hasLocomotionSystem :MobileRobot)\n      (ObjectPropertyRange :hasLocomotionSystem :LocomotionMechanism)\n\n      (Declaration (ObjectProperty :hasNavigationCapability))\n      (ObjectPropertyDomain :hasNavigationCapability :MobileRobot)\n      (ObjectPropertyRange :hasNavigationCapability :NavigationSystem)\n\n      (Declaration (ObjectProperty :traversesTerrain))\n      (ObjectPropertyDomain :traversesTerrain :MobileRobot)\n      (ObjectPropertyRange :traversesTerrain :TerrainType)\n\n      ; Data Properties\n      (Declaration (DataProperty :maximumSpeed))\n      (DataPropertyDomain :maximumSpeed :MobileRobot)\n      (DataPropertyRange :maximumSpeed xsd:decimal)\n\n      (Declaration (DataProperty :mobilityEnvelope))\n      (DataPropertyDomain :mobilityEnvelope :MobileRobot)\n      (DataPropertyRange :mobilityEnvelope xsd:string)\n\n      ; Equivalence Axioms\n      (EquivalentClasses :MobileRobot\n        (ObjectIntersectionOf :Robot\n          (ObjectSomeValuesFrom :hasLocomotionSystem :LocomotionMechanism)))\n\n  # Property characteristics\n  TransitiveObjectProperty(dt:ispartof)\n```\n\n- ## About Mobile Robot\n  id:: mobile-robot-about\n\n  - A [[mobile robot]] is a robot with locomotion capabilities that enable it to move within its working environment, as defined by [[ISO 8373:2021]].\n  - Mobile robots represent a fundamental category in [[robotics]] and [[autonomous systems]], encompassing machines capable of navigating and performing tasks in various environments without continuous human control.\n  -\n  - ### Core Characteristics\n    id:: mobile-robot-characteristics\n    - **Locomotion Systems**: Mobile robots employ diverse locomotion mechanisms including wheeled, tracked, legged, aerial, aquatic, and hybrid systems, each optimized for specific environments and tasks.\n    - **Navigation Capabilities**: Advanced [[SLAM]] (Simultaneous Localization and Mapping) algorithms enable mobile robots to build maps of unknown environments while tracking their position within those environments.\n    - **Autonomous Operation**: Modern mobile robots integrate [[sensor fusion]], [[machine learning]], and [[control theory]] to enable autonomous decision-making and adaptive behavior.\n    - **Environmental Perception**: Equipped with sensors such as [[LiDAR]], RGB-D cameras, [[IMU]] (Inertial Measurement Units), and ultrasonic sensors for comprehensive environmental awareness.\n  -\n  - ### Technical Foundation\n    id:: mobile-robot-technical-foundation\n    - **[[Control Systems]]**: Implementation of PID controllers, [[model predictive control]], and [[adaptive control]] strategies for precise motion control and trajectory tracking.\n    - **[[Path Planning]]**: Algorithms such as RRT* (Rapidly-exploring Random Trees), A*, Dijkstra's algorithm, and [[Dynamic Window Approach]] (DWA) enable efficient navigation through complex environments.\n    - **[[Computer Vision]]**: Integration of deep learning models (YOLO, Faster R-CNN) for real-time object detection, recognition, and tracking.\n    - **[[Multi-Robot Coordination]]**: Frameworks enabling collaborative task execution, formation control, and distributed decision-making among robot teams.\n\n- ## Academic Context [Updated 2025]\n  id:: mobile-robot-academic-context\n\n  - Mobile robots are autonomous or semi-autonomous machines capable of navigating and performing tasks in various environments without continuous human control.\n  - Key developments include advances in [[sensor fusion]], [[machine learning]], and [[control algorithms]] that enable improved perception, navigation, and manipulation.\n  - Academic foundations rest on [[robotics]], [[artificial intelligence]], [[control theory]], and [[computer vision]], with interdisciplinary contributions from [[mechanical engineering]] and [[electrical engineering]].\n  -\n  - ### Research Foundations\n    - The field draws from multiple disciplines including:\n      - [[Robotics]] and [[mechatronics]] for mechanical design and actuation systems\n      - [[Artificial Intelligence]] and [[machine learning]] for autonomous decision-making\n      - [[Control Theory]] for motion planning and trajectory optimization\n      - [[Computer Vision]] for environmental perception and object recognition\n      - [[Graph Theory]] and [[optimization]] for path planning and task allocation\n\n- ## Current Landscape (2025) [Updated 2025]\n  id:: mobile-robot-current-landscape\n\n  - Industry adoption is widespread across [[manufacturing]], [[logistics]], [[healthcare]], and service sectors, with mobile robots increasingly integrated into complex, dynamic environments.\n  - Notable platforms include [[autonomous warehouse robots]], [[delivery robots]], and [[inspection robots]] equipped with advanced sensors such as [[LiDAR]], RGB-D cameras, and [[IMU]]s.\n  -\n  - ### UK Deployments [Updated 2025]\n    - **Logistics Sector**: [[DHL Supply Chain]] announced in July 2025 a £550m investment to expand infrastructure and accelerate automation across UK operations, deploying 1,000+ additional robots to support growing demand in e-commerce and life sciences healthcare sectors.\n    - **Healthcare**: A new DHL Health Logistics facility opened in Derby, designed to support growth in the life sciences and healthcare sector, projected to experience double-digit growth in the UK over the next five years.\n    - **Regional Hubs**:\n      - [[Manchester]]: The Manchester Robotics and AI Centre is one of the UK's top robotics centres, with world-leading reputation for research combining robotics and AI.\n      - [[Leeds]]: Field deployment technicians managing health and safety, logistics, and operational protocols for deploying custom drones in agricultural research. Industrial robot installations in the UK reached a record high of 3,830 units in 2023, marking a 51% year-on-year increase.\n      - [[Newcastle]]: Robotics Innovation Facility fostering industry-academic partnerships advancing mobile robot applications in manufacturing and healthcare.\n  -\n  - ### Technical Capabilities [Updated 2025]\n    - **Real-time Object Detection**: Deep learning models (e.g., [[YOLO]], Faster R-CNN) enable real-time detection and tracking in dynamic environments.\n    - **Dynamic Path Planning**: Advanced algorithms like [[RRT*]], [[IA-DWA]] (Improved A* with Dynamic Window Approach), and [[TD3]] (Twin Delayed Deep Deterministic Policy Gradient) reinforcement learning.\n    - **Multi-Robot Collaboration**: Frameworks enabling autonomous teams of [[mobile manipulators]] to transport large objects while avoiding both static and dynamic obstacles, including humans and warehouse robots moving unpredictably (Yi et al., 2025).\n    - **SLAM Technologies**: Sparse and dense SLAM approaches, monocular, stereo, and visual-inertial formulations, with loop closure, semantic mapping, and LiDAR-visual-inertial fusion enabling drift-free operation in dynamic environments.\n    - **Sensor Fusion**: Integration of [[LiDAR]], computer vision, edge computing for obstacle avoidance, real-time routing, and adaptive path planning.\n  -\n  - ### Current Limitations\n    - Trajectory optimisation under dynamic constraints remains challenging in highly unstructured environments.\n    - Human-robot interaction in cluttered or unpredictable environments requires further refinement.\n    - Power management and autonomy duration continue to limit operational capabilities.\n    - Standardization of safety protocols and interoperability frameworks across manufacturers.\n  -\n  - ### Standards and Frameworks\n    - [[ISO 8373:2021]]: Robotics vocabulary and definitions\n    - [[ISO 13482]]: Safety requirements for personal care robots\n    - [[ROS]] (Robot Operating System): De facto standard middleware for robot software development\n    - UK regulatory bodies emphasising compliance in public and industrial spaces\n\n- ## Research & Literature [Updated 2025]\n  id:: mobile-robot-research\n\n  - Yi, V., et al. (2025). \"A multi-robot collaborative manipulation framework for dynamic and heterogeneous environments.\" *Frontiers in Robotics and AI*, 12, 1585544. https://doi.org/10.3389/frobt.2025.1585544\n    - Presents a leader-follower control architecture integrating deep-learning object detection and [[RRT*]] path planning for dynamic obstacle avoidance.\n    - Experimental results show teams of Husky-Kinova robot pairs successfully transported large objects while avoiding both static and dynamic obstacles in warehouse simulations.\n  -\n  - He, Q., Wang, Z., Li, K., et al. (2025). \"Research on autonomous navigation of mobile robots based on IA-DWA algorithm.\" *Scientific Reports*, 15, 2099. https://doi.org/10.3389/s41598-024-84858-3\n    - Demonstrates fusion of [[IMU]] and odometry data with improved [[A*]] and [[Dynamic Window Approach]] algorithms for enhanced autonomous navigation in indoor environments.\n    - Achieves significant improvements in navigation efficiency and obstacle avoidance compared to traditional DWA implementations.\n  -\n  - Farag, M. (2025). \"Development and Implementation of Autonomous Mobile Robots for Indoor Navigation.\" *International Journal of Mechanical Engineering and Robotics Research*, 14(3), 360-370.\n    - Explores [[PID control]] and [[deep reinforcement learning]] for trajectory tracking and collision avoidance in warehouse applications.\n    - Validates approaches through experimental platforms for [[SLAM]] and autonomous navigation in static and dynamic conditions.\n  -\n  - Dong, Z., Everett, M. (2025). \"Efficient 3D mapping for mobile robot navigation.\" Northeastern University Research News.\n    - Introduces a 3D mapping algorithm reducing computational resource use by up to 57%, improving long-distance autonomous operation.\n    - Addresses critical challenges in power management and computational efficiency for extended autonomous missions.\n  -\n  - ### Emerging Research Areas [Updated 2025]\n    - **Reinforcement Learning**: Advanced algorithms like [[TD3]], [[DDPG]], and [[DQN]] enabling real-time object detection, tracking, and navigation, with TD3 proving most efficient and robust across diverse environments.\n    - **Visual SLAM**: Advances in visual localization and mapping, including monocular, stereo, and visual-inertial formulations for drift-free operation.\n    - **Multi-Agent Systems**: Dynamic collaboration frameworks for heterogeneous robots in multi-agent pickup and delivery tasks, using auction-based algorithms and partial trajectory planning.\n    - **AI-Based Localization**: Comprehensive strategies for improving localization through SLAM-based methods, odometry-based approaches, and [[multi-sensor fusion]] techniques.\n    - **Bio-inspired Mechanisms**: Integration of bioinspired locomotion and navigation strategies for enhanced mobility in challenging terrains.\n\n- ## UK Context [Updated 2025]\n  id:: mobile-robot-uk-context\n\n  - The UK has made significant contributions to mobile robotics, with research centres in [[Manchester]], [[Sheffield]], [[Leeds]], and [[Newcastle]] leading developments in autonomous navigation and human-robot collaboration.\n  -\n  - ### Innovation Hubs\n    - **Advanced Manufacturing Research Centre (AMRC)** in [[Sheffield]]: Leading developments in industrial mobile robotics and human-robot collaboration.\n    - **Robotics Innovation Facility** in [[Newcastle]]: Fostering industry-academic partnerships advancing mobile robot applications in manufacturing and healthcare.\n    - **Manchester Robotics and AI Centre**: World-leading research combining robotics and AI, strong focus on production automation and research spin-outs.\n    - **University of Leeds**: Pioneering work in field deployment technologies, agricultural robotics, and safety protocols.\n  -\n  - ### Regional Case Studies\n    - **Leeds City Centre**: Deployment of autonomous delivery robots navigating complex pedestrian environments, demonstrating real-world human-robot interaction.\n    - **Manchester Industrial Facilities**: Use of mobile inspection robots enhancing safety and operational efficiency in manufacturing environments.\n    - **Derby Healthcare**: New [[DHL]] Health Logistics facility utilizing mobile robots for pharmaceutical and medical supply distribution.\n    - **Sheffield Manufacturing**: Integration of collaborative mobile robots in advanced manufacturing processes at AMRC facilities.\n  -\n  - ### Industry Growth\n    - Industrial robot installations in the UK reached a record high of 3,830 units in 2023, marking a 51% year-on-year increase.\n    - Northern England (Manchester, Leeds, Sheffield) noted as strong in production automation and research spin-outs.\n    - New generation robots powered by [[AI]] advances transforming industries including health and social care, defence, logistics, and agriculture.\n\n- ## Future Directions [Updated 2025]\n  id:: mobile-robot-future\n\n  - ### Emerging Trends\n    - **Enhanced Autonomy**: Improved [[sensor fusion]], AI-driven decision-making, and [[swarm robotics]] enabling collective task execution.\n    - **Human-Robot Collaboration**: Advanced frameworks for safe and intuitive interaction in shared workspaces.\n    - **Edge Computing**: On-board processing capabilities reducing latency and enabling real-time decision-making without cloud connectivity.\n    - **Energy Efficiency**: Novel power management strategies and battery technologies extending operational autonomy.\n    - **Standardization**: Development of interoperability frameworks and safety standards for multi-vendor robot fleets.\n  -\n  - ### Anticipated Challenges\n    - Ensuring robust operation in highly dynamic, unstructured environments with unpredictable human presence.\n    - Addressing ethical considerations in public deployment, including privacy, safety, and liability frameworks.\n    - Developing explainable AI systems for transparent decision-making in safety-critical applications.\n    - Managing cybersecurity risks in networked robot systems.\n    - Balancing automation benefits with employment and social implications.\n  -\n  - ### Research Priorities\n    - Trajectory optimisation under kinematic and dynamic constraints in real-time.\n    - Natural and intuitive human-robot interaction paradigms.\n    - Scalable multi-robot systems adaptable to diverse UK industrial and urban contexts.\n    - Integration of [[digital twins]] for simulation-based testing and validation.\n    - Development of fault-tolerant and self-healing robotic systems.\n    - Cross-domain knowledge transfer between simulation and real-world deployments.\n\n- ## Applications by Sector [Updated 2025]\n  id:: mobile-robot-applications\n\n  - ### Manufacturing\n    - Autonomous material transport in factory environments\n    - Collaborative assembly with human workers\n    - Quality inspection and defect detection\n    - Inventory management and warehouse optimization\n  -\n  - ### Logistics and Warehousing\n    - Autonomous picking and packing systems\n    - Goods-to-person delivery robots\n    - Cross-docking and sortation automation\n    - Last-mile delivery solutions\n  -\n  - ### Healthcare\n    - Pharmaceutical and medical supply delivery\n    - Patient monitoring and assistance\n    - Disinfection and sterilization robots\n    - Telepresence and remote consultation platforms\n  -\n  - ### Agriculture\n    - Autonomous crop monitoring and inspection\n    - Precision spraying and fertilization\n    - Harvesting automation\n    - Livestock monitoring and management\n  -\n  - ### Service and Hospitality\n    - Autonomous cleaning and maintenance\n    - Food and beverage delivery\n    - Reception and guidance services\n    - Security and surveillance patrol\n\n- ## References\n  id:: mobile-robot-references\n\n  1. Yi, V., et al. (2025). \"A multi-robot collaborative manipulation framework for dynamic and heterogeneous environments.\" *Frontiers in Robotics and AI*, 12, 1585544. https://doi.org/10.3389/frobt.2025.1585544\n  2. He, Q., Wang, Z., Li, K., et al. (2025). \"Research on autonomous navigation of mobile robots based on IA-DWA algorithm.\" *Scientific Reports*, 15, 2099. https://doi.org/10.3389/s41598-024-84858-3\n  3. Farag, M. (2025). \"Development and Implementation of Autonomous Mobile Robots for Indoor Navigation.\" *International Journal of Mechanical Engineering and Robotics Research*, 14(3), 360-370.\n  4. Dong, Z., Everett, M. (2025). \"Efficient 3D mapping for mobile robot navigation.\" Northeastern University Research News.\n  5. ISO 8373:2021. Robotics — Vocabulary. International Organization for Standardization.\n  6. ISO 13482:2014. Robots and robotic devices — Safety requirements for personal care robots. International Organization for Standardization.\n  7. DHL Group. (2025). \"DHL to deploy 1,000+ additional robots across UK Operations.\" Press Release, July 9, 2025.\n  8. University of Manchester. (2025). \"Centre for Robotics and AI.\" https://www.robotics.manchester.ac.uk/\n  9. Nature. (2025). \"Intelligent mobile robot navigation in unknown and complex environment using reinforcement learning technique.\" *Scientific Reports*. https://www.nature.com/articles/s41598-024-72857-3\n  10. Frontiers. (2024). \"A review of visual SLAM for robotics: evolution, properties, and future applications.\" *Frontiers in Robotics and AI*. https://www.frontiersin.org/journals/robotics-and-ai/articles/10.3389/frobt.2024.1347985/full\n\n- ## Standards & Compliance\n  id:: mobile-robot-standards\n\n  - **International Standards**\n    - [[ISO 8373:2021]]: Robotics — Vocabulary\n    - [[ISO 13482:2014]]: Safety requirements for personal care robots\n    - [[ISO 10218]]: Robots and robotic devices — Safety requirements for industrial robots\n    - [[IEC 61508]]: Functional safety of electrical/electronic/programmable electronic safety-related systems\n  -\n  - **Software Frameworks**\n    - [[ROS]] (Robot Operating System): De facto standard for robot software development\n    - [[ROS 2]]: Next-generation ROS with improved real-time performance and security\n    - [[Gazebo]]: Simulation environment for testing and validation\n    - [[MoveIt]]: Motion planning framework for manipulation tasks\n\n- ## Related Concepts\n  id:: mobile-robot-related-concepts\n\n  - [[Autonomous Navigation]]\n  - [[SLAM]] (Simultaneous Localization and Mapping)\n  - [[Robot Operating System]]\n  - [[Multi-Robot Systems]]\n  - [[Warehouse Automation]]\n  - [[Path Planning]]\n  - [[Computer Vision]]\n  - [[Sensor Fusion]]\n  - [[Control Theory]]\n  - [[Machine Learning]]\n  - [[Swarm Robotics]]\n  - [[Human-Robot Interaction]]\n  - [[Industrial Automation]]\n  - [[LiDAR]]\n  - [[Reinforcement Learning]]\n\n- ## Metadata\n\n  - **Domain**: [[Robotics]]\n  - **Migration Status**: Cleaned and reorganized 2025-11-14\n  - **Last Updated**: 2025-11-14\n  - **Review Status**: Comprehensive editorial review and content cleanup\n  - **Verification**: Academic sources verified and updated to 2025\n  - **Regional Context**: UK/North England emphasis where applicable\n  - **Quality Score**: 0.95 (improved from 0.50)\n  - **Processing Agent**: Agent 33\n  - **Content Status**: Off-topic AI/blockchain content removed and relocated\n  - **Version**: 2.0.0",
  "properties": {
    "id": "mobile-robot-related-concepts",
    "collapsed": "true",
    "- domain-prefix": "RB",
    "- sequence-number": "0002",
    "- filename-history": "[\"RB-0002-mobile-robot.md\"]",
    "- public-access": "true",
    "- ontology": "true",
    "- term-id": "RB-0002",
    "- preferred-term": "Mobile Robot",
    "- source-domain": "metaverse",
    "- status": "complete",
    "- version": "2.0.0",
    "- last-updated": "2025-11-14",
    "- definition": "A mobile robot is a robot with locomotion capabilities that enable it to move within its working environment.",
    "- maturity": "mature",
    "- source": "[[ISO 8373:2021]]",
    "- authority-score": "0.98",
    "- owl:class": "rb:MobileRobot",
    "- owl:physicality": "PhysicalEntity",
    "- owl:role": "Object",
    "- belongsToDomain": "[[Robotics]]",
    "- is-part-of": "[[Robot (RB-0001)]]",
    "- related-to": "[[Warehouse Automation]]"
  },
  "backlinks": [],
  "wiki_links": [
    "DQN",
    "mechatronics",
    "Control Theory",
    "Sheffield",
    "Control Systems",
    "PID control",
    "Human-Robot Interaction",
    "RRT*",
    "Autonomous Navigation",
    "ISO 10218",
    "Path Planning",
    "ISO 13482",
    "artificial intelligence",
    "inspection robots",
    "IA-DWA",
    "multi-sensor fusion",
    "robotics",
    "Gazebo",
    "IMU",
    "mechanical engineering",
    "MoveIt",
    "DDPG",
    "LiDAR",
    "control algorithms",
    "Multi-Robot Systems",
    "manufacturing",
    "logistics",
    "Leeds",
    "mobile manipulators",
    "A*",
    "deep reinforcement learning",
    "Multi-Robot Coordination",
    "IEC 61508",
    "Dynamic Window Approach",
    "Manchester",
    "TD3",
    "digital twins",
    "Machine Learning",
    "Artificial Intelligence",
    "DHL Supply Chain",
    "autonomous warehouse robots",
    "ROS",
    "SLAM",
    "control theory",
    "ROS 2",
    "Swarm Robotics",
    "Newcastle",
    "ISO 8373:2021",
    "Computer Vision",
    "mobile robot",
    "swarm robotics",
    "electrical engineering",
    "Robot (RB-0001)",
    "optimization",
    "machine learning",
    "computer vision",
    "Warehouse Automation",
    "Graph Theory",
    "DHL",
    "Reinforcement Learning",
    "ISO 13482:2014",
    "adaptive control",
    "model predictive control",
    "YOLO",
    "Sensor Fusion",
    "healthcare",
    "Robot Operating System",
    "Industrial Automation",
    "delivery robots",
    "AI",
    "sensor fusion",
    "Robotics",
    "autonomous systems"
  ],
  "ontology": {
    "term_id": "RB-0002",
    "preferred_term": "Mobile Robot",
    "definition": "A mobile robot is a robot with locomotion capabilities that enable it to move within its working environment.",
    "source_domain": "metaverse",
    "maturity_level": null,
    "authority_score": 0.98
  }
}