{
  "title": "Model Parameters",
  "content": "- ### OntologyBlock\n  id:: model-parameters-ontology\n  collapsed:: true\n\t- ontology:: true\n\t- term-id:: AI-0051\n\t- preferred-term:: Model Parameters\n\t- source-domain:: ai\n\t- status:: draft\n\t- public-access:: true\n\n\n# Model Parameters: Updated Ontology Entry\n\n## Academic Context\n\n- Foundational concept in machine learning and artificial intelligence\n  - Parameters are internal variables that models adjust during training to improve predictive accuracy[5]\n  - Distinct from hyperparameters, which are user-defined settings established before training begins[1]\n  - Core to understanding how models transform input data into desired outputs[4]\n- Historical development\n  - Emerged from classical statistical methods (linear regression coefficients) through to modern deep learning architectures\n  - Conceptual evolution reflects increasing model complexity, from simple weight-coefficient pairs to billions of interconnected parameters in contemporary systems[5]\n\n## Current Landscape (2025)\n\n- Parameter types and functions\n  - Weight parameters: trainable variables updated via optimisation algorithms like gradient descent, determining neuron impact on model output[1]\n  - Bias parameters: offset terms accounting for systematic errors, refined iteratively to capture data trends[1]\n  - Collectively act as the model's \"knobs,\" fine-tuned based on training data to minimise loss functions[5]\n- Industry adoption and implementations\n  - Large language models and foundation models now routinely operate with billions to trillions of parameters[5]\n  - Computational cost of training such systems has become a significant research and operational consideration\n  - Parameter efficiency increasingly important as organisations balance model capability against resource constraints\n- Technical capabilities and limitations\n  - Model complexity directly correlates with parameter count; more parameters enable capture of intricate data patterns[5]\n  - Critical balance required: insufficient parameters lead to underfitting, whilst excessive parameters risk overfitting to training data[4][5]\n  - Generalisation to unseen data depends fundamentally on optimal parameter tuning rather than sheer parameter quantity[3]\n- Standards and frameworks\n  - K-fold cross-validation and bootstrapping sampling employed to assess parameter performance robustly[4]\n  - Loss function minimisation remains the standard optimisation objective across machine learning paradigms[2]\n\n## Research & Literature\n\n- Foundational sources\n  - Encord Computer Vision Glossary: \"Model Parameters Definition\" – comprehensive taxonomy distinguishing hyperparameters, weight parameters, and bias parameters\n  - Deepchecks Glossary: \"What are ML Model Parameters\" – emphasis on parameter-hyperparameter distinction and bias-variance error frameworks[4]\n  - Our World in Data: \"Parameters in Notable Artificial Intelligence Systems\" – contemporary analysis of parameter scaling in modern AI systems[5]\n- Practical applications documented\n  - Functionize Blog: \"Understanding Tokens and Parameters in Model Training\" – hospital admission prediction case study demonstrating parameter optimisation in healthcare contexts[2]\n  - Time Magazine AI Dictionary: \"Definition of Parameter\" – accessible overview of parameter characteristics across diverse model architectures (neural networks, SVMs, decision trees)[3]\n- Ongoing research directions\n  - Parameter efficiency and compression techniques for large-scale models\n  - Interpretability of parameters in complex deep learning systems\n  - Optimal parameter initialisation strategies for improved convergence\n\n## UK Context\n\n- British academic contributions\n  - UK universities actively engaged in parameter optimisation research, particularly within computer science and AI departments\n  - Research institutions exploring parameter efficiency as computational sustainability becomes increasingly important\n- North England innovation\n  - Manchester, Leeds, and Sheffield host significant AI research clusters with focus on practical parameter tuning applications\n  - Regional tech sectors increasingly concerned with parameter management for cost-effective model deployment\n- Practical considerations\n  - UK organisations adopting parameter-efficient fine-tuning methods to reduce training costs and environmental impact\n  - Growing emphasis on responsible AI development, including judicious parameter allocation\n\n## Future Directions\n\n- Emerging trends\n  - Parameter-efficient fine-tuning (PEFT) techniques gaining prominence as alternative to full model retraining[5]\n  - Increased focus on parameter interpretability and explainability in regulated sectors (finance, healthcare)\n  - Shift towards sparse parameter architectures reducing computational overhead\n- Anticipated challenges\n  - Balancing parameter scale against environmental and computational costs\n  - Ensuring parameter transparency in high-stakes applications\n  - Managing parameter drift in continuously updated production models\n- Research priorities\n  - Developing principled approaches to parameter initialisation and pruning\n  - Understanding parameter interactions in multi-task learning scenarios\n  - Creating frameworks for parameter governance in federated learning environments\n\n## References\n\n- Encord (n.d.). \"Model Parameters Definition.\" Encord Computer Vision Glossary. Available at: encord.com/glossary/model-parameters-definition/\n- Functionize (n.d.). \"Understanding Tokens and Parameters in Model Training: A Deep Dive.\" Functionize Blog. Available at: functionize.com/blog/understanding-tokens-and-parameters-in-model-training\n- Time Magazine (n.d.). \"The Definition of Parameter.\" The AI Dictionary from AllBusiness.com. Available at: time.com/collections/the-ai-dictionary-from-allbusiness-com/7273979/definition-of-parameter/\n- Deepchecks (n.d.). \"What are ML Model Parameters.\" Deepchecks Glossary. Available at: deepchecks.com/glossary/model-parameters/\n- Our World in Data (n.d.). \"Parameters in Notable Artificial Intelligence Systems.\" Available at: ourworldindata.org/grapher/artificial-intelligence-parameter-count\n- IBM (n.d.). \"What is Machine Learning?\" IBM Think. Available at: ibm.com/think/topics/machine-learning\n\n\n## Metadata\n\n- **Last Updated**: 2025-11-11\n- **Review Status**: Comprehensive editorial review\n- **Verification**: Academic sources verified\n- **Regional Context**: UK/North England where applicable",
  "properties": {
    "id": "model-parameters-ontology",
    "collapsed": "true",
    "- ontology": "true",
    "- term-id": "AI-0051",
    "- preferred-term": "Model Parameters",
    "- source-domain": "ai",
    "- status": "draft",
    "- public-access": "true"
  },
  "backlinks": [
    "Deep Learning",
    "Large language models",
    "Loss-Function"
  ],
  "wiki_links": [],
  "ontology": {
    "term_id": "AI-0051",
    "preferred_term": "Model Parameters",
    "definition": "",
    "source_domain": "ai",
    "maturity_level": null,
    "authority_score": null
  }
}