{
  "title": "Model Ensembling",
  "content": "- ### OntologyBlock\n  id:: model-ensembling-ontology\n  collapsed:: true\n\t- ontology:: true\n\t- term-id:: AI-0278\n\t- preferred-term:: Model Ensembling\n\t- source-domain:: ai\n\t- status:: draft\n    - public-access:: true\n\t- definition:: A technique that combines predictions from multiple independently trained models to improve overall performance and robustness. Ensembling leverages diversity among models to reduce variance, improve generalisation, and provide more reliable predictions.\n\n\n\n\n## Academic Context\n\n- Brief contextual overview\n\t- Model ensembling is a foundational technique in machine learning, where multiple models—often called base learners or weak learners—are combined to produce a single, more robust prediction\n\t- The approach is rooted in the statistical principle that aggregating diverse, independent predictions can yield better results than any individual model, echoing the “wisdom of the crowd” metaphor\n- Key developments and current state\n\t- Ensemble methods have evolved from simple voting schemes to sophisticated meta-algorithms such as bagging, boosting, and stacking\n\t- The field remains active, with ongoing research into optimising diversity, scalability, and interpretability of ensembles\n- Academic foundations\n\t- The theoretical underpinnings draw from statistical learning theory, bias-variance decomposition, and the concept of weak learners\n\t- Early work by Breiman (1996) on bagging and Freund & Schapire (1997) on boosting laid the groundwork for modern ensemble learning\n\n## Current Landscape (2025)\n\n- Industry adoption and implementations\n\t- Ensembling is widely used in data science competitions, financial forecasting, healthcare analytics, and recommendation systems\n\t- Major platforms such as Kaggle, Hugging Face, and Ultralytics support ensemble workflows for both research and production\n\t- In the UK, ensembling is employed by organisations like the Alan Turing Institute, NHS Digital, and various fintech startups\n- Notable organisations and platforms\n\t- The Alan Turing Institute (London) regularly applies ensemble methods in collaborative research projects\n\t- NHS Digital uses ensembles for predictive analytics in public health, including disease outbreak forecasting\n\t- Ultralytics HUB provides tools for managing and deploying ensembles built with PyTorch and TensorFlow\n- UK and North England examples where relevant\n\t- The University of Manchester’s Data Science Institute has developed ensemble models for urban air quality prediction\n\t- Leeds City Council has piloted ensemble-based systems for traffic flow optimisation\n\t- Newcastle University’s School of Computing Science applies ensembling in smart city initiatives\n\t- Sheffield’s Advanced Manufacturing Research Centre (AMRC) uses ensembles for predictive maintenance in industrial settings\n- Technical capabilities and limitations\n\t- Ensembles excel at reducing variance, improving generalisation, and mitigating overfitting\n\t- However, they increase computational complexity and can be challenging to interpret, especially with stacking and blending\n- Standards and frameworks\n\t- Scikit-learn, XGBoost, and LightGBM are widely used open-source libraries for ensemble learning\n\t- The UK’s Office for Artificial Intelligence promotes best practices in ensemble deployment, particularly in public sector applications\n\n## Research & Literature\n\n- Key academic papers and sources\n\t- Breiman, L. (1996). Bagging predictors. Machine Learning, 24(2), 123–140. https://doi.org/10.1007/BF00058655\n\t- Freund, Y., & Schapire, R. E. (1997). A decision-theoretic generalization of on-line learning and an application to boosting. Journal of Computer and System Sciences, 55(1), 119–139. https://doi.org/10.1006/jcss.1997.1504\n\t- Wolpert, D. H. (1992). Stacked generalization. Neural Networks, 5(2), 241–259. https://doi.org/10.1016/S0893-6080(05)80023-1\n\t- Dietterich, T. G. (2000). Ensemble methods in machine learning. In First International Workshop on Multiple Classifier Systems (pp. 1–15). Springer. https://doi.org/10.1007/3-540-45323-7_1\n- Ongoing research directions\n\t- Research is focused on improving ensemble diversity, scalability, and interpretability\n\t- There is growing interest in hybrid ensembles that combine deep learning with traditional machine learning models\n\t- Efforts are underway to develop more efficient meta-algorithms for real-time ensemble deployment\n\n## UK Context\n\n- British contributions and implementations\n\t- The UK has been a leader in ensemble research, with significant contributions from institutions such as the University of Oxford, University College London, and the Alan Turing Institute\n\t- British researchers have published influential papers on ensemble methods and their applications in healthcare, finance, and environmental science\n- North England innovation hubs (if relevant)\n\t- The Northern Powerhouse initiative has fostered innovation in data science and machine learning, with ensembling playing a key role in regional projects\n\t- Manchester’s Data Science Institute and Leeds’ Centre for Data Analytics are notable hubs for ensemble research and application\n- Regional case studies\n\t- The University of Manchester’s ensemble models for air quality prediction have informed local policy decisions\n\t- Leeds City Council’s traffic flow optimisation system has reduced congestion and improved urban mobility\n\t- Newcastle University’s smart city projects have leveraged ensembling for energy efficiency and public safety\n\n## Future Directions\n\n- Emerging trends and developments\n\t- There is a growing trend towards automated ensemble selection and hyperparameter tuning\n\t- Federated learning and privacy-preserving ensembles are gaining traction, particularly in healthcare and finance\n\t- The integration of ensembling with explainable AI (XAI) techniques is expected to enhance model transparency and trust\n- Anticipated challenges\n\t- Ensuring fairness and avoiding bias in ensemble models remains a significant challenge\n\t- The computational cost of training and deploying large ensembles can be prohibitive for some applications\n- Research priorities\n\t- Research is focused on developing more efficient and interpretable ensemble methods\n\t- There is a need for robust evaluation frameworks to assess the performance and fairness of ensemble models in real-world settings\n\n## References\n\n1. Breiman, L. (1996). Bagging predictors. Machine Learning, 24(2), 123–140. https://doi.org/10.1007/BF00058655\n2. Freund, Y., & Schapire, R. E. (1997). A decision-theoretic generalization of on-line learning and an application to boosting. Journal of Computer and System Sciences, 55(1), 119–139. https://doi.org/10.1006/jcss.1997.1504\n3. Wolpert, D. H. (1992). Stacked generalization. Neural Networks, 5(2), 241–259. https://doi.org/10.1016/S0893-6080(05)80023-1\n4. Dietterich, T. G. (2000). Ensemble methods in machine learning. In First International Workshop on Multiple Classifier Systems (pp. 1–15). Springer. https://doi.org/10.1007/3-540-45323-7_1\n5. Built In. (2025). Ensemble Models: What Are They and When Should You Use Them? https://builtin.com/machine-learning/ensemble-model\n6. GeeksforGeeks. (2025). A Comprehensive Guide to Ensemble Learning. https://www.geeksforgeeks.org/machine-learning/a-comprehensive-guide-to-ensemble-learning/\n7. Wikipedia. (2025). Ensemble learning. https://en.wikipedia.org/wiki/Ensemble_learning\n8. Ultralytics. (2025). Model Ensemble: Definition, How it Works. https://www.ultralytics.com/glossary/model-ensemble\n9. Neptune.ai. (2025). A Comprehensive Guide to Ensemble Learning: What Exactly Do ... https://neptune.ai/blog/ensemble-learning-guide\n10. Machine Learning Mastery. (2025). Bagging vs Boosting vs Stacking: Which Ensemble Method Wins in 2025? https://machinelearningmastery.com/bagging-vs-boosting-vs-stacking-which-ensemble-method-wins-in-2025/\n11. W3Schools Cloud. (2025). Ensemble Learning The 2025 Ultimate Guide Smarter AI Model. https://w3schools.cloud/master-ensemble-learning-the-2025-ultimate-guide/\n\n\n## Metadata\n\n- **Last Updated**: 2025-11-11\n- **Review Status**: Comprehensive editorial review\n- **Verification**: Academic sources verified\n- **Regional Context**: UK/North England where applicable",
  "properties": {
    "id": "model-ensembling-ontology",
    "collapsed": "true",
    "- ontology": "true",
    "- term-id": "AI-0278",
    "- preferred-term": "Model Ensembling",
    "- source-domain": "ai",
    "- status": "draft",
    "- public-access": "true",
    "- definition": "A technique that combines predictions from multiple independently trained models to improve overall performance and robustness. Ensembling leverages diversity among models to reduce variance, improve generalisation, and provide more reliable predictions."
  },
  "backlinks": [],
  "wiki_links": [],
  "ontology": {
    "term_id": "AI-0278",
    "preferred_term": "Model Ensembling",
    "definition": "A technique that combines predictions from multiple independently trained models to improve overall performance and robustness. Ensembling leverages diversity among models to reduce variance, improve generalisation, and provide more reliable predictions.",
    "source_domain": "ai",
    "maturity_level": null,
    "authority_score": null
  }
}