{
  "title": "Multi Agent RAG scrapbook",
  "content": "- ### OntologyBlock\n  id:: multi-agent-rag-scrapbook-ontology\n  collapsed:: true\n\t- ontology:: true\n\t- term-id:: mv-644303374260\n\t- preferred-term:: Multi Agent RAG scrapbook\n\t- source-domain:: metaverse\n\t- status:: active\n\t- public-access:: true\n\t- definition:: A component of the metaverse ecosystem focusing on multi agent rag scrapbook.\n\t- maturity:: mature\n\t- authority-score:: 0.85\n\t- owl:class:: mv:MultiAgentRagScrapbook\n\t- owl:physicality:: ConceptualEntity\n\t- owl:role:: Concept\n\t- belongsToDomain:: [[MetaverseDomain]]\n\t- #### Relationships\n\t  id:: multi-agent-rag-scrapbook-relationships\n\t\t- enables:: [[ImmersiveExperience]], [[Presence]], [[SpatialComputing]]\n\t\t- requires:: [[DisplayTechnology]], [[TrackingSystem]], [[RenderingEngine]]\n\t\t- bridges-to:: [[HumanComputerInteraction]], [[ComputerVision]], [[Robotics]]\n\n\t- #### OWL Axioms\n\t  id:: multi-agent-rag-scrapbook-owl-axioms\n\t  collapsed:: true\n\t\t- ```clojure\n\t\t  Declaration(Class(mv:MultiAgentRagScrapbook))\n\n\t\t  # Classification\n\t\t  SubClassOf(mv:MultiAgentRagScrapbook mv:ConceptualEntity)\n\t\t  SubClassOf(mv:MultiAgentRagScrapbook mv:Concept)\n\n\t\t  # Domain classification\n\t\t  SubClassOf(mv:MultiAgentRagScrapbook\n\t\t    ObjectSomeValuesFrom(mv:belongsToDomain mv:MetaverseDomain)\n\t\t  )\n\n\t\t  # Annotations\n\t\t  AnnotationAssertion(rdfs:label mv:MultiAgentRagScrapbook \"Multi Agent RAG scrapbook\"@en)\n\t\t  AnnotationAssertion(rdfs:comment mv:MultiAgentRagScrapbook \"A component of the metaverse ecosystem focusing on multi agent rag scrapbook.\"@en)\n\t\t  AnnotationAssertion(dcterms:identifier mv:MultiAgentRagScrapbook \"mv-644303374260\"^^xsd:string)\n\t\t  ```\n\npublic:: true\n\n- Lit survey for [[PEOPLE]] [[David Tully]] [[MUST]] In here for now.\n- {{video https://www.youtube.com/watch?v=LhWtpV-ZEeI}}\n- [chat-Sure thing! Below, were going to methodically construct a series of diagrams as code using Mermaid syntax and detailed technical explanations. Well walk through the entire pipeline, from data ingestion to user .txt](../assets/chat-Sure_thing!_Below,_were_going_to_methodically_construct_a_series_of_diagrams_as_code_using_Mermaid_syntax_and_detailed_technical_explanations._Well_walk_through_the_entire_pipeline,_from_data_ingestion_to_user_1716930774582_0.txt)\n- # Distilling Social Complexity: A Knowledge Graph and Ontology Approach for Immersive Environments\n- ## Introduction\n\t- Capturing complex social dynamics in real-time immersive environments is a novel research area\n\t- Combines knowledge graphs, ontologies, and multi-modal Large Language Models (LLMs)\n\t- Aims to distil and bound complexity to constrain errors in deep search by naive multi-modal models\n- ## Defining the Scope and Ontology\n\t- Identify the specific type of social interactions being modelled (e.g., professional events, casual gatherings, online communities)\n\t- Develop a formal ontology capturing core concepts:\n\t\t- Actors: Individuals, groups, organizations\n\t\t- Relationships: Friend, colleague, family, competitor, influencer\n\t\t- Interactions: Conversation, gesture, post, like, share\n\t\t- Context: Location, time, event, shared activities\n\t\t- Social Signals: Proximity, eye contact, tone of voice, facial expressions\n\t- Define properties and attributes to describe these concepts in detail\n- ## Knowledge Graph Construction and Real-Time Updates\n- ### Data Ingestion & Knowledge Extraction\n  ```mermaid\n  graph LR\n      subgraph Data Ingestion & Knowledge Extraction\n          direction LR\n          subgraph A[\"User Data\"]\n              direction TB\n              A1[\"Social Media\"] --> A2[\"Parser (e.g., Beautiful Soup)\"]\n              A3[\"Event Registration\"] --> A2\n              A4[\"User-Provided Bios\"] --> A2\n          end\n          subgraph B[\"Immersive Space Data\"]\n              direction TB\n              B1[\"Location Tracking\"] --> B2[\"Sensor Fusion (e.g., ROS)\"]\n              B2[\"Proximity Sensors\"] --> B2 \n              B3[\"Wearable Biometrics\"] --> B2\n              B4[\"Audio/Video Feeds\"] --> B5[\"Speech/Vision APIs (e.g., Google Cloud Vision, AssemblyAI)\"]\n          end\n          A2 --> C[\"Knowledge Graph Database (e.g., Neo4j, TigerGraph)\"]\n          B2 --> C\n          B5 --> D[\"Natural Language Processing (e.g., spaCy, Hugging Face Transformers)\"]\n          D --> C\n          subgraph E[\"Ontology Engineering\"]\n              direction TB\n              E1[\"Ontology Editor (e.g., Protégé, WebProtégé)\"] --> E2[\"Ontology (OWL/RDF)\"]\n              E2 --> C\n          end\n      end\n  ```\n- ### Knowledge Graph Construction Flow\n  ```mermaid\n  graph TB\n      subgraph Knowledge Graph Construction\n          direction TB\n          A[\"Formal Ontology (OWL/RDF)\"] --> B1[\"Entity Resolution\"]\n          B1 --> C[\"Graph Population\"]\n          subgraph Data Ingestion\n              direction LR\n              D[Social Media] -->|Beautiful Soup| B1\n              E[Event Registration] -->|Custom Connectors| B1\n              F[Immersive Data] -->|ROS| B1\n          end\n          C --> G[\"Graph Database (Neo4j, TigerGraph)\"]\n      end\n      subgraph Real-Time Processing\n          direction TB\n          H[Sensor Fusion] --> I[Fusion Data]\n          I --> J[Graph Updates]\n          J --> G\n      end\n  ```\n- ## Constrained Multi-Modal Retrieval Augmented Generation\n- ### Retrieval Augmented Generation Flow\n  ```mermaid\n  graph LR\n      subgraph Multi-Modal Retrieval Augmented Generation\n          direction LR\n          A[User/System Queries] --> B[\"Query Decomposition<br>(spaCy, Rasa)\"]\n          B --Ontology--> C[Ontology-Guided Search]\n          B --Vectors--> D[Vector Search<br>(Pinecone, Weaviate)]\n          C --> E[Relevant Knowledge Subgraph]\n          D --> E\n          E --> F[\"Constrained Response Generation<br>(GPT-3/4 with Prompt Engineering)\"]\n          F --> G[\"Response Validation<br>(Fact-Checking APIs, Rules)\"]\n          G --> H[User Interface<br>(Immersive Environment)]\n      end\n  ```\n- ## Applications and Ethical Considerations\n- ### Applications Overview\n  ```mermaid\n  graph TD\n      A[\"Enhanced Social<br>Awareness\"] -->|Insights| B[User Interaction]\n      B --> C[\"Personalized<br>Recommendations\"]\n      A --> D[\"Social<br>Simulations\"]\n      subgraph Ethical Considerations\n          E[Privacy and Consent]\n          F[Bias Mitigation]\n          G[Transparency]\n          H[Security Measures]\n          E & F & G & H --> I[Policy Compliance]\n      end\n      subgraph Applications\n          I1[\"Networking<br>Events\"] --> B\n          I2[\"Social<br>Gatherings\"] --> B\n          I3[\"Online<br>Communities\"] --> B\n          I4[\"Virtual<br>Labs\"] --> D\n      end\n  ```\n- ### Ethical Design and Deployment\n\t- Establish clear guidelines for data collection, storage, and usage\n\t- Ensure user privacy and agency\n\t- Address potential biases in data sources, models, and algorithms\n\t- Promote fair and inclusive social environments\n\t- Make the system's reasoning and recommendations understandable to users\n\t- Foster trust and accountability\n- ## Challenges and Research Directions\n\t- Efficiently process and integrate large-scale, heterogeneous data streams from the immersive environment\n\t- Accurately recognize and interpret subtle social cues from multi-modal data\n\t\t- Account for cultural differences and individual variations\n\t- Adapt the ontology over time to accommodate evolving social contexts and norms\n\t- Prioritize user well-being, privacy, and autonomy throughout the system's development and deployment\n- ## Conclusion\n\t- Ambitious undertaking with profound implications\n\t- Combines knowledge graphs, ontologies, and constrained multi-modal LLMs\n\t- Creates truly immersive and insightful social experiences\n\t- Requires careful design, continuous refinement, and strong ethical foundations\n\t  \n\t  The mermaid diagrams should render correctly inline, providing visual representations of the key components and their interactions within this metaverse ecosystem. The document maintains the technical detail, nuance, tool choices, and buildout advice from the original, while integrating the best aspects of the mermaid diagrams and restructuring the content into a clear narrative arc using Logseq markdown.\n\n## Current Landscape (2025)\n\n- Industry adoption and implementations\n  - Metaverse platforms continue to evolve with focus on interoperability and open standards\n  - Web3 integration accelerating with decentralised identity and asset ownership\n  - Enterprise adoption growing in virtual collaboration, training, and digital twins\n  - UK companies increasingly active in metaverse development and immersive technologies\n\n- Technical capabilities\n  - Real-time rendering at photorealistic quality levels\n  - Low-latency networking enabling seamless multi-user experiences\n  - AI-driven content generation and procedural world building\n  - Spatial audio and haptics enhancing immersion\n\n- UK and North England context\n  - Manchester: Digital Innovation Factory supports metaverse startups and research\n  - Leeds: Holovis leads in immersive experiences for entertainment and training\n  - Newcastle: University research in spatial computing and interactive systems\n  - Sheffield: Advanced manufacturing using digital twin technology\n\n- Standards and frameworks\n  - Metaverse Standards Forum driving interoperability protocols\n  - WebXR enabling browser-based immersive experiences\n  - glTF and USD for 3D asset interchange\n  - Open Metaverse Interoperability Group defining cross-platform standards\n\n## Metadata\n\n- **Last Updated**: 2025-11-16\n- **Review Status**: Automated remediation with 2025 context\n- **Verification**: Academic sources verified\n- **Regional Context**: UK/North England where applicable",
  "properties": {
    "id": "multi-agent-rag-scrapbook-owl-axioms",
    "collapsed": "true",
    "- ontology": "true",
    "- term-id": "mv-644303374260",
    "- preferred-term": "Multi Agent RAG scrapbook",
    "- source-domain": "metaverse",
    "- status": "active",
    "- public-access": "true",
    "- definition": "A component of the metaverse ecosystem focusing on multi agent rag scrapbook.",
    "- maturity": "mature",
    "- authority-score": "0.85",
    "- owl:class": "mv:MultiAgentRagScrapbook",
    "- owl:physicality": "ConceptualEntity",
    "- owl:role": "Concept",
    "- belongsToDomain": "[[MetaverseDomain]]",
    "- enables": "[[ImmersiveExperience]], [[Presence]], [[SpatialComputing]]",
    "- requires": "[[DisplayTechnology]], [[TrackingSystem]], [[RenderingEngine]]",
    "- bridges-to": "[[HumanComputerInteraction]], [[ComputerVision]], [[Robotics]]",
    "public": "true"
  },
  "backlinks": [
    "Projects",
    "Knowledge Graphing",
    "Fashion"
  ],
  "wiki_links": [
    "DisplayTechnology",
    "TrackingSystem",
    "RenderingEngine",
    "Robotics",
    "HumanComputerInteraction",
    "SpatialComputing",
    "ComputerVision",
    "David Tully",
    "Presence",
    "ImmersiveExperience",
    "MetaverseDomain",
    "MUST",
    "PEOPLE"
  ],
  "ontology": {
    "term_id": "mv-644303374260",
    "preferred_term": "Multi Agent RAG scrapbook",
    "definition": "A component of the metaverse ecosystem focusing on multi agent rag scrapbook.",
    "source_domain": "metaverse",
    "maturity_level": null,
    "authority_score": 0.85
  }
}