{
  "title": "Multi-Head Attention",
  "content": "- ### OntologyBlock\n  id:: multiheadattention-ontology\n  collapsed:: true\n\n  - **Identification**\n    - domain-prefix:: AI\n    - sequence-number:: 0810\n    - filename-history:: [\"AI-0810-multiheadattention.md\"]\n    - public-access:: true\n    - ontology:: true\n    - term-id:: AI-0810\n    - preferred-term:: Multi-Head Attention\n    - source-domain:: ai\n    - status:: complete\n    - version:: 1.0.0\n    - last-updated:: 2025-11-13\n\n  - **Definition**\n    - definition:: \n    - maturity:: established\n    - source:: Chimera Prime Research\n    - authority-score:: 0.95\n\n  - **Semantic Classification**\n    - owl:class:: ai:MultiHeadAttention\n    - belongsToDomain:: [[Artificial Intelligence]]\n\n  - #### OWL Restrictions\n    \n\n  - \n### Relationships\n- is-subclass-of:: [[AttentionMechanism]]",
  "properties": {
    "id": "multiheadattention-ontology",
    "collapsed": "true",
    "- domain-prefix": "AI",
    "- sequence-number": "0810",
    "- filename-history": "[\"AI-0810-multiheadattention.md\"]",
    "- public-access": "true",
    "- ontology": "true",
    "- term-id": "AI-0810",
    "- preferred-term": "Multi-Head Attention",
    "- source-domain": "ai",
    "- status": "complete",
    "- version": "1.0.0",
    "- last-updated": "2025-11-13",
    "- definition": "",
    "- maturity": "established",
    "- source": "Chimera Prime Research",
    "- authority-score": "0.95",
    "- owl:class": "ai:MultiHeadAttention",
    "- belongsToDomain": "[[Artificial Intelligence]]"
  },
  "backlinks": [],
  "wiki_links": [
    "AttentionMechanism",
    "Artificial Intelligence"
  ],
  "ontology": {
    "term_id": "AI-0810",
    "preferred_term": "Multi-Head Attention",
    "definition": "",
    "source_domain": "ai",
    "maturity_level": null,
    "authority_score": 0.95
  }
}