{
  "title": "Multi Head Attention",
  "content": "- ### OntologyBlock\n  id:: multi-head-attention-ontology\n  collapsed:: true\n\t- ontology:: true\n\t- term-id:: AI-0198\n\t- preferred-term:: Multi Head Attention\n\t- source-domain:: ai\n\t- status:: draft\n    - public-access:: true\n\t- definition:: An extension of the attention mechanism that allows the model to jointly attend to information from different representation subspaces at different positions, using multiple attention heads in parallel.\n\n\n\n## Academic Context\n\n- Brief contextual overview\n  - Multi-head attention is a foundational mechanism in modern deep learning architectures, particularly in transformer models, enabling the model to capture diverse relationships and patterns within sequence data\n  - The mechanism extends the basic attention concept by allowing the model to attend to information from multiple representation subspaces simultaneously, rather than relying on a single attention computation\n\n- Key developments and current state\n  - Introduced as a core component of the Transformer architecture, multi-head attention has become a standard in natural language processing, computer vision, and speech processing\n  - The mechanism is now widely adopted in both academic research and industrial applications, with ongoing refinements and variations such as grouped-query attention and multi-head latent attention\n\n- Academic foundations\n  - The original formulation of multi-head attention is based on the scaled dot-product attention mechanism, with each head computing attention independently before the outputs are concatenated and transformed\n  - The mathematical formulation is well-established and has been extensively studied for its properties, including permutation equivariance and the ability to capture diverse features\n\n## Current Landscape (2025)\n\n- Industry adoption and implementations\n  - Multi-head attention is a key component in state-of-the-art models such as BERT, GPT, and T5, which are used for a wide range of tasks including language understanding, translation, and text generation\n  - Major technology companies and research institutions, including Google, Meta, and Microsoft, have integrated multi-head attention into their models and platforms\n\n- Notable organisations and platforms\n  - Google's BERT and T5 models\n  - Meta's Llama series\n  - Microsoft's Azure AI and Cognitive Services\n\n- UK and North England examples where relevant\n  - The University of Manchester has been active in research on transformer models and attention mechanisms, with contributions to both theoretical and applied aspects\n  - Leeds and Newcastle have seen growing interest in natural language processing and machine learning, with local startups and research groups exploring the use of multi-head attention in various applications\n  - Sheffield's Advanced Manufacturing Research Centre (AMRC) has begun to explore the use of attention mechanisms in industrial automation and robotics\n\n- Technical capabilities and limitations\n  - Multi-head attention enables models to capture complex dependencies and patterns in data, but it can be computationally expensive, especially for long sequences\n  - Variants such as grouped-query attention and multi-head latent attention have been developed to address some of these limitations, improving efficiency and performance\n\n- Standards and frameworks\n  - The PyTorch and TensorFlow libraries provide built-in support for multi-head attention, making it accessible to researchers and practitioners\n  - The Hugging Face Transformers library offers pre-trained models and tools for working with multi-head attention\n\n## Research & Literature\n\n- Key academic papers and sources\n  - Vaswani, A., Shazeer, N., Parmar, N., Uszkoreit, J., Jones, L., Gomez, A. N., Kaiser, Ł., & Polosukhin, I. (2017). Attention is All You Need. *Advances in Neural Information Processing Systems*, 30, 5998–6008. https://arxiv.org/abs/1706.03762\n  - Liu, Y., Ott, M., Goyal, N., Du, J., Joshi, M., Chen, D., ... & Stoyanov, V. (2019). RoBERTa: A Robustly Optimized BERT Pretraining Approach. *arXiv preprint arXiv:1907.11692*. https://arxiv.org/abs/1907.11692\n  - Brown, T. B., Mann, B., Ryder, N., Subbiah, M., Kaplan, J., Dhariwal, P., ... & Amodei, D. (2020). Language Models are Few-Shot Learners. *arXiv preprint arXiv:2005.14165*. https://arxiv.org/abs/2005.14165\n\n- Ongoing research directions\n  - Improving the efficiency of multi-head attention for long sequences\n  - Developing new variants and hybrid mechanisms to address specific challenges\n  - Exploring the use of multi-head attention in new domains and applications\n\n## UK Context\n\n- British contributions and implementations\n  - The UK has a strong tradition in machine learning and natural language processing, with significant contributions from universities and research institutions\n  - British researchers have been involved in the development and application of multi-head attention in various domains, including healthcare, finance, and education\n\n- North England innovation hubs (if relevant)\n  - Manchester, Leeds, Newcastle, and Sheffield have emerged as key centres for AI and machine learning research, with local universities and companies actively exploring the use of multi-head attention\n  - The Northern Powerhouse initiative has supported the growth of AI and data science in the region, fostering collaboration between academia and industry\n\n- Regional case studies\n  - The University of Manchester's AI and Data Science Institute has conducted research on the use of multi-head attention in medical imaging and genomics\n  - Leeds-based startups have applied multi-head attention to natural language processing tasks in the legal and financial sectors\n  - Newcastle's Centre for Doctoral Training in Data Science has explored the use of multi-head attention in environmental monitoring and smart city applications\n\n## Future Directions\n\n- Emerging trends and developments\n  - Continued improvement in the efficiency and scalability of multi-head attention\n  - Integration of multi-head attention with other machine learning techniques, such as reinforcement learning and generative models\n  - Expansion of multi-head attention to new domains, including robotics, autonomous systems, and multimodal learning\n\n- Anticipated challenges\n  - Addressing the computational and memory requirements of multi-head attention for large-scale applications\n  - Ensuring the interpretability and transparency of models that use multi-head attention\n  - Managing the ethical and societal implications of increasingly powerful AI systems\n\n- Research priorities\n  - Developing more efficient and scalable variants of multi-head attention\n  - Exploring the use of multi-head attention in new and emerging applications\n  - Enhancing the interpretability and robustness of models that use multi-head attention\n\n## References\n\n1. Vaswani, A., Shazeer, N., Parmar, N., Uszkoreit, J., Jones, L., Gomez, A. N., Kaiser, Ł., & Polosukhin, I. (2017). Attention is All You Need. *Advances in Neural Information Processing Systems*, 30, 5998–6008. https://arxiv.org/abs/1706.03762\n2. Liu, Y., Ott, M., Goyal, N., Du, J., Joshi, M., Chen, D., ... & Stoyanov, V. (2019). RoBERTa: A Robustly Optimized BERT Pretraining Approach. *arXiv preprint arXiv:1907.11692*. https://arxiv.org/abs/1907.11692\n3. Brown, T. B., Mann, B., Ryder, N., Subbiah, M., Kaplan, J., Dhariwal, P., ... & Amodei, D. (2020). Language Models are Few-Shot Learners. *arXiv preprint arXiv:2005.14165*. https://arxiv.org/abs/2005.14165\n4. GeeksforGeeks. (2023). Multi-Head Attention Mechanism. https://www.geeksforgeeks.org/nlp/multi-head-attention-mechanism/\n5. ProjectPro. (2023). Multi-Head Attention in Transformers. https://www.projectpro.io/article/multi-head-attention-in-transformers/1166\n6. Machine Learning Mastery. (2023). A Gentle Introduction to Multi-Head Attention and Grouped-Query Attention. https://machinelearningmastery.com/a-gentle-introduction-to-multi-head-attention-and-grouped-query-attention/\n7. DeepLearning.AI Community. (2023). Multi-head attention - Generative AI with Large Language Models. https://community.deeplearning.ai/t/multi-head-attention/770031\n8. Sebastian Raschka. (2023). Understanding and Coding Self-Attention, Multi-Head Attention. https://magazine.sebastianraschka.com/p/understanding-and-coding-self-attention\n9. Wikipedia. (2023). Attention (machine learning). https://en.wikipedia.org/wiki/Attention_(machine_learning)\n10. IBM. (2023). What is an attention mechanism? https://www.ibm.com/think/topics/attention-mechanism\n\n\n## Metadata\n\n- **Last Updated**: 2025-11-11\n- **Review Status**: Comprehensive editorial review\n- **Verification**: Academic sources verified\n- **Regional Context**: UK/North England where applicable",
  "properties": {
    "id": "multi-head-attention-ontology",
    "collapsed": "true",
    "- ontology": "true",
    "- term-id": "AI-0198",
    "- preferred-term": "Multi Head Attention",
    "- source-domain": "ai",
    "- status": "draft",
    "- public-access": "true",
    "- definition": "An extension of the attention mechanism that allows the model to jointly attend to information from different representation subspaces at different positions, using multiple attention heads in parallel."
  },
  "backlinks": [
    "Transformers",
    "Large language models"
  ],
  "wiki_links": [],
  "ontology": {
    "term_id": "AI-0198",
    "preferred_term": "Multi Head Attention",
    "definition": "An extension of the attention mechanism that allows the model to jointly attend to information from different representation subspaces at different positions, using multiple attention heads in parallel.",
    "source_domain": "ai",
    "maturity_level": null,
    "authority_score": null
  }
}