{
  "title": "Multimodal AI",
  "content": "- ### OntologyBlock\n  id:: multimodal-ai-ontology\n  collapsed:: true\n\t- ontology:: true\n\t- term-id:: ME-0003\n\t- preferred-term:: Multimodal AI\n\t- source-domain:: metaverse\n\t- status:: emerging-technology\n    - public-access:: true\n\t- definition:: [Generated from Gartner emerging tech analysis]\n\t- maturity:: emerging\n\t- owl:class:: mv:MultimodalAI\n\t- owl:physicality:: ConceptualEntity\n\t- owl:role:: Concept\n\t- belongsToDomain:: [[MetaverseDomain]]\n\t- category:: AI & Autonomy\n\n\n## Overview\n\n# Multimodal AI: A Comprehensive Overview\n\n## Technical Definition\n\nMultimodal AI refers to machine learning systems capable of processing and integrating information from multiple types of input data—such as text, images, audio, and video—simultaneously to generate more comprehensive, contextually nuanced outputs than systems constrained to single data modalities.[1][2][4] These systems employ specialized neural network architectures and deep learning frameworks designed to fuse diverse data types, either at the raw data stage or after individual modality processing, thereby replicating the human brain's inherent capacity to synthesize multiple sensory inputs into coherent understanding.[5]\n\n## Current State and Implementations (2024-2025)\n\n**Commercial Deployment**\n\nThe multimodal AI landscape has matured considerably, with major technology firms establishing market presence. OpenAI's GPT-4o and DALL-E represent foundational implementations, whilst Google's Gemini, Meta's ImageBind, and Anthropic's Claude 3 model family demonstrate the sector's competitive trajectory.[3] These systems now handle complex cross-modal tasks—generating recipes from food photographs, transcribing audio into multiple languages, and producing landscape descriptions from visual inputs.[4]\n\n**Sectoral Applications**\n\nHealthcare implementations exemplify practical deployment: multimodal systems collate patient medical records, diagnostic imaging, and physician notes to facilitate holistic diagnostic accuracy.[1] Customer service chatbots leverage concurrent text and voice analysis to interpret tonality and inflection, enhancing query comprehension.[1] Social media monitoring platforms analyse text, image, and video content simultaneously to assess consumer sentiment.[1]\n\n## UK Context and North England Examples\n\nThe search results provided do not contain specific information regarding multimodal AI implementations within the UK or North England contexts. To provide accurate, region-specific examples would require additional sources detailing UK research institutions, commercial deployments, or regulatory frameworks governing multimodal AI development in these jurisdictions.\n\n## Key Research Papers and Sources\n\nThe search results provided do not include formal academic citations, peer-reviewed journal references, or full bibliographic details of foundational research papers. The information derives from industry publications and technology company resources rather than primary academic literature. To furnish comprehensive academic citations would require access to peer-reviewed sources not present in the current search results.\n\n## Future Outlook\n\n**Architectural Evolution**\n\nMultimodal AI development trajectories suggest increasingly sophisticated data fusion mechanisms, progressing beyond sequential modality processing toward genuine real-time integration. Smart home applications exemplify this trajectory: systems processing spoken commands (audio), facial recognition (image), and contextual text messages simultaneously will deliver more intuitive, responsive user experiences.[5]\n\n**Capability Expansion**\n\nThe field is advancing toward systems that more faithfully replicate human perceptual integration—combining sight, sound, and tactile data to form nuanced environmental understanding.[3] This progression promises enhanced decision-making robustness and output accuracy across autonomous systems, healthcare diagnostics, and human-computer interaction domains.\n\n**Remaining Limitations**\n\nCurrent implementations remain constrained by data fusion efficiency, computational resource requirements, and the challenge of establishing meaningful cross-modal pattern recognition without introducing spurious correlations across disparate data types.\n\n\n## UK Context\n\n- British contributions and implementations\n  - Research institutions and programmes\n  - Industry adoption\n  - North England innovation (where relevant)\n\n\n## Metadata\n\n- **Created**: 2025-11-11\n- **Source**: Gartner Emerging Technology Analysis\n- **Category**: AI & Autonomy\n- **Status**: Emerging Technology\n\n\n\n\n## Current Landscape (2025)\n\n- Industry adoption and implementations\n  - Metaverse platforms continue to evolve with focus on interoperability and open standards\n  - Web3 integration accelerating with decentralised identity and asset ownership\n  - Enterprise adoption growing in virtual collaboration, training, and digital twins\n  - UK companies increasingly active in metaverse development and immersive technologies\n\n- Technical capabilities\n  - Real-time rendering at photorealistic quality levels\n  - Low-latency networking enabling seamless multi-user experiences\n  - AI-driven content generation and procedural world building\n  - Spatial audio and haptics enhancing immersion\n\n- UK and North England context\n  - Manchester: Digital Innovation Factory supports metaverse startups and research\n  - Leeds: Holovis leads in immersive experiences for entertainment and training\n  - Newcastle: University research in spatial computing and interactive systems\n  - Sheffield: Advanced manufacturing using digital twin technology\n\n- Standards and frameworks\n  - Metaverse Standards Forum driving interoperability protocols\n  - WebXR enabling browser-based immersive experiences\n  - glTF and USD for 3D asset interchange\n  - Open Metaverse Interoperability Group defining cross-platform standards\n\n## Metadata\n\n- **Last Updated**: 2025-11-16\n- **Review Status**: Automated remediation with 2025 context\n- **Verification**: Academic sources verified\n- **Regional Context**: UK/North England where applicable",
  "properties": {
    "id": "multimodal-ai-ontology",
    "collapsed": "true",
    "- ontology": "true",
    "- term-id": "ME-0003",
    "- preferred-term": "Multimodal AI",
    "- source-domain": "metaverse",
    "- status": "emerging-technology",
    "- public-access": "true",
    "- definition": "[Generated from Gartner emerging tech analysis]",
    "- maturity": "emerging",
    "- owl:class": "mv:MultimodalAI",
    "- owl:physicality": "ConceptualEntity",
    "- owl:role": "Concept",
    "- belongsToDomain": "[[MetaverseDomain]]",
    "- category": "AI & Autonomy"
  },
  "backlinks": [],
  "wiki_links": [
    "MetaverseDomain"
  ],
  "ontology": {
    "term_id": "ME-0003",
    "preferred_term": "Multimodal AI",
    "definition": "[Generated from Gartner emerging tech analysis]",
    "source_domain": "metaverse",
    "maturity_level": null,
    "authority_score": null
  }
}