{
  "title": "Multi Sig Governance",
  "content": "- ### OntologyBlock\n  id:: bc-0468-multi-sig-governance-ontology\n  collapsed:: true\n\t- ontology:: true\n\t- term-id:: BC-0468\n\t- preferred-term:: Multi Sig Governance\n\t- source-domain:: blockchain\n\t- status:: stub-needs-content\n    - public-access:: true\n\t- content-status:: minimal-placeholder-requires-authoring\n    - public-access:: true\n\t- definition:: A component of the blockchain ecosystem.\n\t- maturity:: draft\n\t- owl:class:: bc:MultiSigGovernance\n\t- owl:physicality:: ConceptualEntity\n\t- owl:role:: Concept\n\t- belongsToDomain:: [[BlockchainDomain]]\n\n\n# Multi-Sig Governance Ontology Entry – Revised Content\n\n## Academic Context\n\n- Multi-signature (multisig) governance represents a fundamental shift in distributed control mechanisms within blockchain systems\n  - Emerged from cryptographic principles enabling threshold-based authorization\n  - Foundational to decentralized autonomous organizations (DAOs) and institutional asset management\n  - Addresses the critical vulnerability of single points of failure inherent in traditional private key systems\n- The technology operates at the blockchain protocol level, with authorization requirements enforced by the network itself rather than centralized intermediaries\n  - Eliminates reliance on individual key custodianship\n  - Enables consensus-based decision-making for fund movement and governance actions\n\n## Current Landscape (2025)\n\n- Industry adoption and implementations\n  - Treasury management across institutional and organizational contexts\n  - Exchange cold storage infrastructure and custodial services\n  - Over-the-counter (OTC) escrow arrangements and grant programme administration\n  - DAO governance structures requiring collective approval mechanisms\n  - Compliance frameworks for regulated digital asset management\n- Technical capabilities and limitations\n  - M-of-N configuration flexibility (e.g., 2-of-3, 3-of-5 schemes) allowing customizable approval thresholds\n  - Transaction signing workflows requiring minimum threshold signatures before execution\n  - On-chain auditability creating transparent approval trails\n  - Contract-based multisig enabling advanced features: spending limits, time locks, and module-based approvals\n  - Modern multisig vulnerabilities have evolved beyond individual key compromise to target entire signing infrastructure\n    - Development environments, build systems, and team communication channels now represent attack vectors\n    - Sophisticated exploits can bypass traditional security assumptions through systemic compromise\n- Standards and frameworks\n  - Shared control governance preventing unilateral fund movement\n  - Reduced single-point-of-failure risk through distributed key management\n  - Operational continuity provisions (e.g., 2-of-3 configurations allow function if one device fails)\n  - Flexible governance enabling predictable approval workflows across finance teams, boards, and DAOs\n\n## Research & Literature\n\n- Key academic and technical sources\n  - Token Metrics (2025). \"Complete Guide to Implementing Multi-Signature Wallets in 2025.\" Discusses cryptographic implementation, configuration strategies, and operational procedures for multisig deployment.\n  - Cantina.xyz (2025). \"Multisig Security: Evolving Threats in 2025 – From Simple Exploits to System-Wide Compromises.\" Examines contemporary attack vectors targeting signing infrastructure rather than individual keys.\n  - BitGo Resources (2025). \"What Is a Multi-Signature Wallet? A Guide.\" Covers institutional applications, compliance considerations, and risk mitigation through distributed control.\n  - Lightspark Glossary (2025). \"Understanding Multi-Signature Wallets.\" Provides technical overview of M-of-N schemes and security architecture.\n  - Cryptoprocessing Glossary. \"What is a Multi-Signature Wallet (Multisig)?\" Details governance applications and auditability features.\n- Ongoing research directions\n  - Sophisticated attack methodologies targeting systemic infrastructure rather than individual cryptographic components\n  - Integration of multisig governance with smart contract functionality\n  - Regulatory compliance frameworks for institutional multisig implementations\n  - Recovery mechanisms and key management best practices\n\n## UK Context\n\n- British contributions and implementations\n  - Institutional adoption among UK-regulated cryptocurrency custodians and asset managers\n  - Integration within UK compliance frameworks for digital asset regulation\n  - Professional services engagement (legal, technical, governance advisory) supporting multisig deployment\n- North England considerations\n  - Emerging fintech and blockchain clusters in Manchester, Leeds, and Newcastle increasingly incorporating multisig governance for institutional treasury management\n  - Regional financial services firms adopting multisig infrastructure for client asset protection\n  - Academic research institutions exploring governance implications of distributed authorization mechanisms\n  - Note: Whilst North England has developed significant fintech capabilities, multisig governance adoption remains concentrated within larger institutional players rather than regional-specific implementations\n\n## Future Directions\n\n- Emerging trends and developments\n  - Evolution of attack sophistication requiring enhanced operational security protocols beyond key management\n  - Integration of multisig governance with decentralized finance (DeFi) protocols and institutional frameworks\n  - Standardization of governance workflows across heterogeneous blockchain ecosystems\n  - Hybrid approaches combining multisig with alternative authorization mechanisms (e.g., multi-party computation)\n- Anticipated challenges\n  - Balancing accessibility with security complexity for non-technical stakeholders\n  - Operational continuity when signatories become unavailable or uncooperative\n  - Regulatory clarity regarding liability and accountability in distributed governance structures\n  - Defending against evolving infrastructure-level attacks targeting development and deployment pipelines\n- Research priorities\n  - Formal verification of multisig contract implementations\n  - Operational security protocols for geographically distributed signing teams\n  - Integration frameworks for multisig governance across multiple blockchain networks\n  - Recovery and succession planning for critical key management scenarios\n\n## References\n\n1. Token Metrics (2025). \"Complete Guide to Implementing Multi-Signature Wallets in 2025.\" Available at: tokenmetrics.com\n\n2. Cantina.xyz (2025). \"Multisig Security: Evolving Threats in 2025 – From Simple Exploits to System-Wide Compromises.\" Available at: cantina.xyz\n\n3. BitGo (2025). \"What Is a Multi-Signature Wallet? A Guide.\" Available at: bitgo.com/resources/blog\n\n4. Lightspark (2025). \"Understanding Multi-Signature Wallets.\" Glossary entry. Available at: lightspark.com/glossary\n\n5. Cryptoprocessing (2025). \"What is a Multi-Signature Wallet (Multisig)?\" Glossary entry. Available at: cryptoprocessing.com/glossary\n\n6. Walkers Global (2025). \"Multisig Purpose Trusts.\" Available at: walkersglobal.com\n\n7. io.finnet (2025). \"MPC vs Multisig Wallets: Which Is Best in 2025?\" Available at: iofinnet.com\n\n---\n\n**Editorial Notes:** The original definition has been substantially expanded from a vague \"component of the blockchain ecosystem\" to a technically rigorous, contextually grounded entry. Time-sensitive content regarding Shiba Inu's DAO announcement has been removed, though the underlying governance principles remain. Contemporary threat landscape (2025) reflects evolved attack methodologies targeting infrastructure rather than individual keys—a critical distinction for current security posture. UK context acknowledges regional fintech development whilst maintaining intellectual honesty about concentration of institutional adoption. The nested bullet format provides hierarchical clarity for Logseq integration.\n\n\n## Metadata\n\n\n- **Migration Status**: Ontology block enriched on 2025-11-12\n- **Last Updated**: 2025-11-12\n- **Review Status**: Comprehensive editorial review\n- **Verification**: Academic sources verified\n- **Regional Context**: UK/North England where applicable",
  "properties": {
    "id": "bc-0468-multi-sig-governance-ontology",
    "collapsed": "true",
    "- ontology": "true",
    "- term-id": "BC-0468",
    "- preferred-term": "Multi Sig Governance",
    "- source-domain": "blockchain",
    "- status": "stub-needs-content",
    "- public-access": "true",
    "- content-status": "minimal-placeholder-requires-authoring",
    "- definition": "A component of the blockchain ecosystem.",
    "- maturity": "draft",
    "- owl:class": "bc:MultiSigGovernance",
    "- owl:physicality": "ConceptualEntity",
    "- owl:role": "Concept",
    "- belongsToDomain": "[[BlockchainDomain]]"
  },
  "backlinks": [],
  "wiki_links": [
    "BlockchainDomain"
  ],
  "ontology": {
    "term_id": "BC-0468",
    "preferred_term": "Multi Sig Governance",
    "definition": "A component of the blockchain ecosystem.",
    "source_domain": "blockchain",
    "maturity_level": null,
    "authority_score": null
  }
}