{
  "title": "Named Entity Recognition",
  "content": "- ### OntologyBlock\n  id:: named-entity-recognition-ontology\n  collapsed:: true\n\t- ontology:: true\n\t- term-id:: AI-0368\n\t- preferred-term:: Named Entity Recognition\n\t- source-domain:: ai\n\t- status:: draft\n    - public-access:: true\n\t- definition:: Named Entity Recognition (NER) is the NLP task of identifying and classifying named entities (persons, organisations, locations, dates, quantities) within unstructured text into predefined categories. NER systems employ transformer-based models (BERT, RoBERTa) with sequence labelling architectures (CRF, BiLSTM-CRF) to extract structured information from documents, enabling information extraction, knowledge graph construction, and semantic search.\n\n\n\n## Academic Context\n\n- Named Entity Recognition (NER) is a foundational task in natural language processing (NLP) focused on identifying and categorising named entities—such as persons, organisations, locations, dates, and quantities—within unstructured text.\n  - Originating from the Message Understanding Conferences (MUC) in the 1990s, NER has evolved from rule-based systems to sophisticated machine learning and deep learning approaches.\n  - The academic foundations lie in sequence labelling, probabilistic models, and more recently, transformer-based architectures that leverage contextual embeddings for improved accuracy.\n  - NER plays a critical role in semantic understanding, information extraction, and downstream applications like knowledge graph construction and question answering.\n\n## Current Landscape (2025)\n\n- Industry adoption of NER is widespread across sectors including finance, healthcare, legal, and media, where automated extraction of structured data from vast text corpora is essential.\n  - Modern NER systems predominantly employ transformer models such as BERT, RoBERTa, and their derivatives, often combined with sequence labelling layers like Conditional Random Fields (CRF) or BiLSTM-CRF architectures to capture entity boundaries and dependencies.\n  - Despite advances, challenges remain in handling ambiguous entities, domain adaptation, and multilingual contexts.\n- Notable platforms integrating NER include cloud AI services (e.g., AWS Comprehend, Google Cloud NLP), open-source frameworks (SpaCy, Hugging Face Transformers), and specialised enterprise solutions.\n- In the UK, and particularly in North England, organisations and academic institutions increasingly leverage NER for regional data analytics, digital humanities, and public sector information management.\n  - Cities such as Manchester, Leeds, Newcastle, and Sheffield host innovation hubs and research groups focusing on NLP applications, including NER, often collaborating with industry partners.\n- Standards and frameworks for NER evaluation and deployment continue to mature, emphasising reproducibility, fairness, and explainability.\n\n## Research & Literature\n\n- Key academic contributions include:\n  - Lample, G., Ballesteros, M., Subramanian, S., Kawakami, K., & Dyer, C. (2016). *Neural Architectures for Named Entity Recognition*. Proceedings of NAACL-HLT 2016. DOI: 10.18653/v1/N16-1030\n  - Devlin, J., Chang, M.-W., Lee, K., & Toutanova, K. (2019). *BERT: Pre-training of Deep Bidirectional Transformers for Language Understanding*. NAACL-HLT 2019. DOI: 10.18653/v1/N19-1423\n  - Akbik, A., Blythe, D., & Vollgraf, R. (2018). *Contextual String Embeddings for Sequence Labeling*. Proceedings of COLING 2018. URL: https://aclanthology.org/C18-1139/\n- Ongoing research explores:\n  - Cross-lingual and low-resource NER\n  - Incorporation of external knowledge bases for disambiguation\n  - Robustness against noisy and domain-specific data\n  - Explainability and fairness in entity recognition systems\n\n## UK Context\n\n- The UK has a vibrant NLP research community contributing to NER advancements, with institutions such as the University of Manchester and the University of Leeds leading in applied NLP research.\n- North England innovation hubs foster collaborations between academia and industry, focusing on regional language varieties, dialectal challenges, and domain-specific NER applications (e.g., healthcare records in NHS trusts).\n- Regional case studies include projects utilising NER to analyse local government documents, social media data for public sentiment, and historical archives digitisation in Sheffield and Newcastle.\n- The UK government and private sector increasingly deploy NER-powered tools for regulatory compliance, intelligence analysis, and digital transformation initiatives.\n\n## Future Directions\n\n- Emerging trends include:\n  - Integration of multimodal data (text, images, audio) for richer entity recognition\n  - Real-time NER in conversational AI and interactive systems\n  - Enhanced domain adaptation techniques to reduce annotation costs\n  - Greater emphasis on ethical AI, addressing bias and privacy in entity extraction\n- Anticipated challenges:\n  - Balancing model complexity with deployment efficiency\n  - Handling evolving language use and emerging entities dynamically\n  - Ensuring transparency and user trust in automated entity recognition\n- Research priorities focus on:\n  - Developing universally adaptable NER models\n  - Leveraging unsupervised and semi-supervised learning\n  - Expanding NER capabilities to underrepresented languages and dialects, including regional UK English variants\n\n## References\n\n1. Lample, G., Ballesteros, M., Subramanian, S., Kawakami, K., & Dyer, C. (2016). Neural Architectures for Named Entity Recognition. *Proceedings of NAACL-HLT 2016*. DOI: 10.18653/v1/N16-1030\n\n2. Devlin, J., Chang, M.-W., Lee, K., & Toutanova, K. (2019). BERT: Pre-training of Deep Bidirectional Transformers for Language Understanding. *NAACL-HLT 2019*. DOI: 10.18653/v1/N19-1423\n\n3. Akbik, A., Blythe, D., & Vollgraf, R. (2018). Contextual String Embeddings for Sequence Labeling. *Proceedings of COLING 2018*. URL: https://aclanthology.org/C18-1139/\n\n4. Emeritus. (2025). What is the Relevance of Named Entity Recognition in NLP? Retrieved November 2025, from emeritus.org\n\n5. GeeksforGeeks. (2025). Named Entity Recognition. Retrieved October 2025, from geeksforgeeks.org\n\n6. TechTarget. (2025). What Is Named Entity Recognition (NER)? Retrieved November 2025, from techtarget.com\n\n7. Label Your Data. (2025). Named Entity Recognition: A Practical 2025 Guide. Retrieved November 2025, from labelyourdata.com\n\n8. IBM. (2025). What Is Named Entity Recognition? Retrieved November 2025, from ibm.com\n\n9. Universität der Bundeswehr München. (2025). Paper accepted at ACL 2025 on Named Entity Recognition. Retrieved November 2025, from unibw.de\n\n(If you find yourself wondering whether the 'named entities' include your tea or biscuits, rest assured: for now, they remain firmly in the realm of persons, places, and organisations.)\n\n\n## Metadata\n\n- **Last Updated**: 2025-11-11\n- **Review Status**: Comprehensive editorial review\n- **Verification**: Academic sources verified\n- **Regional Context**: UK/North England where applicable",
  "properties": {
    "id": "named-entity-recognition-ontology",
    "collapsed": "true",
    "- ontology": "true",
    "- term-id": "AI-0368",
    "- preferred-term": "Named Entity Recognition",
    "- source-domain": "ai",
    "- status": "draft",
    "- public-access": "true",
    "- definition": "Named Entity Recognition (NER) is the NLP task of identifying and classifying named entities (persons, organisations, locations, dates, quantities) within unstructured text into predefined categories. NER systems employ transformer-based models (BERT, RoBERTa) with sequence labelling architectures (CRF, BiLSTM-CRF) to extract structured information from documents, enabling information extraction, knowledge graph construction, and semantic search."
  },
  "backlinks": [
    "Recurrent Neural Network",
    "Transformers",
    "Telecollaboration and Telepresence"
  ],
  "wiki_links": [],
  "ontology": {
    "term_id": "AI-0368",
    "preferred_term": "Named Entity Recognition",
    "definition": "Named Entity Recognition (NER) is the NLP task of identifying and classifying named entities (persons, organisations, locations, dates, quantities) within unstructured text into predefined categories. NER systems employ transformer-based models (BERT, RoBERTa) with sequence labelling architectures (CRF, BiLSTM-CRF) to extract structured information from documents, enabling information extraction, knowledge graph construction, and semantic search.",
    "source_domain": "ai",
    "maturity_level": null,
    "authority_score": null
  }
}