{
  "title": "Network Hash Rate",
  "content": "- ### OntologyBlock\n  id:: network-hash-rate-ontology\n  collapsed:: true\n\n  - **Identification**\n\n    - domain-prefix:: BC\n\n    - sequence-number:: 0063\n\n    - filename-history:: [\"BC-0063-network-hash-rate.md\"]\n    - public-access:: true\n    - ontology:: true\n    - term-id:: BC-0063\n    - preferred-term:: Network Hash Rate\n    - source-domain:: metaverse\n    - status:: complete\n    - version:: 1.0.0\n    - last-updated:: 2025-10-28\n\n  - **Definition**\n    - definition:: Total computational power within blockchain systems, providing essential functionality for distributed ledger technology operations and properties.\n    - maturity:: mature\n    - source:: [[ISO/IEC 23257:2021]], [[IEEE 2418.1]], [[NIST NISTIR]]\n    - authority-score:: 0.95\n\n  - **Semantic Classification**\n    - owl:class:: bc:NetworkHashRate\n    - owl:physicality:: VirtualEntity\n    - owl:role:: Object\n    - owl:inferred-class:: bc:VirtualObject\n    - belongsToDomain:: [[ConsensusDomain]]\n    - implementedInLayer:: [[ProtocolLayer]]\n\n  - #### Relationships\n    id:: network-hash-rate-relationships\n    - is-subclass-of:: [[Blockchain Entity]], [[ConsensusProtocol]]\n\n  - #### OWL Axioms\n    id:: network-hash-rate-owl-axioms\n    collapsed:: true\n    - ```clojure\n      Prefix(:=<http://metaverse-ontology.org/blockchain#>)\nPrefix(owl:=<http://www.w3.org/2002/07/owl#>)\nPrefix(rdf:=<http://www.w3.org/1999/02/22-rdf-syntax-ns#>)\nPrefix(xml:=<http://www.w3.org/XML/1998/namespace>)\nPrefix(xsd:=<http://www.w3.org/2001/XMLSchema#>)\nPrefix(rdfs:=<http://www.w3.org/2000/01/rdf-schema#>)\nPrefix(dct:=<http://purl.org/dc/terms/>)\n\nOntology(<http://metaverse-ontology.org/blockchain/BC-0063>\n  Import(<http://metaverse-ontology.org/blockchain/core>)\n\n  ## Class Declaration\n  Declaration(Class(:NetworkHashRate))\n\n  ## Subclass Relationships\n  SubClassOf(:NetworkHashRate :ConsensusProtocol)\n  SubClassOf(:NetworkHashRate :BlockchainEntity)\n\n  ## Essential Properties\n  SubClassOf(:NetworkHashRate\n    (ObjectSomeValuesFrom :partOf :Blockchain))\n\n  SubClassOf(:NetworkHashRate\n    (ObjectSomeValuesFrom :hasProperty :Property))\n\n  ## Data Properties\n  DataPropertyAssertion(:hasIdentifier :NetworkHashRate \"BC-0063\"^^xsd:string)\n  DataPropertyAssertion(:hasAuthorityScore :NetworkHashRate \"1.0\"^^xsd:decimal)\n  DataPropertyAssertion(:isFoundational :NetworkHashRate \"true\"^^xsd:boolean)\n\n  ## Object Properties\n  ObjectPropertyAssertion(:enablesFeature :NetworkHashRate :BlockchainFeature)\n  ObjectPropertyAssertion(:relatesTo :NetworkHashRate :RelatedConcept)\n\n  ## Annotations\n  AnnotationAssertion(rdfs:label :NetworkHashRate \"Network Hash Rate\"@en)\n  AnnotationAssertion(rdfs:comment :NetworkHashRate\n    \"Total computational power\"@en)\n  AnnotationAssertion(dct:description :NetworkHashRate\n    \"Foundational blockchain concept with formal ontological definition\"@en)\n  AnnotationAssertion(:termID :NetworkHashRate \"BC-0063\")\n  AnnotationAssertion(:priority :NetworkHashRate \"1\"^^xsd:integer)\n  AnnotationAssertion(:category :NetworkHashRate \"consensus-fundamentals\"@en)\n)\n      ```\n\n- ## About Network Hash Rate\n  id:: network-hash-rate-about\n\n  - Total computational power within blockchain systems, providing essential functionality for distributed ledger technology operations and properties.\n  -\n  - ### Key Characteristics\n    id:: network-hash-rate-characteristics\n    - 1. **Definitional Property**: Core defining characteristic\n    - 2. **Functional Property**: Operational behavior\n    - 3. **Structural Property**: Compositional elements\n    - 4. **Security Property**: Security guarantees provided\n    - 5. **Performance Property**: Efficiency considerations\n  -\n  - ### Technical Components\n    id:: network-hash-rate-components\n    - **Implementation**: How concept is realized technically\n    - **Verification**: Methods for validating correctness\n    - **Interaction**: Relationships with other components\n    - **Constraints**: Technical limitations and requirements\n  -\n  - ### Use Cases\n    id:: network-hash-rate-use-cases\n    - **1. Core Blockchain Operation**\n    - **Application**: Fundamental blockchain functionality\n    - **Example**: Practical implementation in major blockchains\n    - **Requirements**: Technical prerequisites\n    - **Benefits**: Value provided to blockchain systems\n  -\n  - ### Standards & References\n    id:: network-hash-rate-standards\n    - [[ISO/IEC 23257:2021]] - Blockchain and distributed ledger technologies\n    - [[IEEE 2418.1]] - Blockchain and distributed ledger technologies\n    - [[NIST NISTIR]] - Blockchain and distributed ledger technologies\n  -\n\n\n## Academic Context\n\n- The **network hash rate** quantifies the total computational power dedicated to mining and transaction processing on a Proof-of-Work (PoW) blockchain network.\n  - It measures the number of cryptographic hash calculations performed per second, typically expressed in units ranging from terahashes per second (TH/s) to exahashes per second (EH/s).\n  - This metric is fundamental to blockchain security and consensus, as it reflects the collective effort miners invest in solving complex mathematical puzzles to validate transactions and add new blocks.\n- Academically, the hash rate underpins the security model of PoW blockchains by making attacks computationally expensive and impractical.\n  - The higher the hash rate, the more resistant the network is to double-spending and 51% attacks.\n  - Foundational research in distributed consensus and cryptographic security supports the role of hash rate in maintaining blockchain integrity.\n\n## Current Landscape (2025)\n\n- **Industry adoption and implementations**\n  - PoW blockchains like Bitcoin continue to rely heavily on hash rate as a security and performance metric.\n  - Mining operations worldwide contribute to fluctuating hash rates, influenced by hardware efficiency, electricity costs, and regulatory environments.\n- **Notable organisations and platforms**\n  - Major mining pools and hardware manufacturers remain key players in sustaining and advancing network hash rates.\n  - Enterprise blockchain infrastructure providers offer hash rate monitoring and optimisation services to institutional clients.\n- **UK and North England examples**\n  - The UK hosts several blockchain research centres and mining operations, with North England cities such as Manchester and Leeds emerging as innovation hubs for blockchain technology.\n  - Sheffield and Newcastle have seen growing interest in blockchain applications, including PoW infrastructure optimisation.\n- **Technical capabilities and limitations**\n  - Advances in ASIC (Application-Specific Integrated Circuit) technology have increased hash rate efficiency, but energy consumption remains a critical challenge.\n  - Network difficulty adjusts dynamically to maintain block times despite hash rate fluctuations.\n- **Standards and frameworks**\n  - Industry standards for measuring and reporting hash rate have matured, facilitating transparency and interoperability.\n  - Regulatory frameworks in the UK increasingly address the environmental impact of high hash rate mining.\n\n## Research & Literature\n\n- **Key academic papers and sources**\n  - Bonneau, J., Miller, A., Clark, J., Narayanan, A., Kroll, J. A., & Felten, E. W. (2015). \"SoK: Research Perspectives and Challenges for Bitcoin and Cryptocurrencies.\" *IEEE Symposium on Security and Privacy*. DOI: 10.1109/SP.2015.14\n  - Gervais, A., Karame, G. O., Wüst, K., Glykantzis, V., Ritzdorf, H., & Capkun, S. (2016). \"On the Security and Performance of Proof of Work Blockchains.\" *ACM Conference on Computer and Communications Security*. DOI: 10.1145/2976749.2978390\n  - Courtois, N. T., & Bahack, L. (2014). \"On Subversive Miner Strategies and Block Withholding Attack in Bitcoin Digital Currency.\" *arXiv preprint arXiv:1402.1718*. URL: https://arxiv.org/abs/1402.1718\n- **Ongoing research directions**\n  - Exploration of energy-efficient PoW variants and hybrid consensus mechanisms.\n  - Quantitative modelling of hash rate dynamics in response to market and regulatory changes.\n  - Security analysis of hash rate distribution and decentralisation metrics.\n\n## UK Context\n\n- **British contributions and implementations**\n  - UK academic institutions contribute to blockchain security research, focusing on hash rate implications for network resilience.\n  - Several UK-based startups develop mining hardware optimisation and hash rate analytics tools.\n- **North England innovation hubs**\n  - Manchester and Leeds are notable for hosting blockchain incubators and research groups investigating scalable PoW solutions.\n  - Sheffield’s technology sector includes projects on sustainable mining practices, addressing hash rate energy concerns.\n  - Newcastle is emerging as a centre for blockchain education and applied research, including hash rate monitoring technologies.\n- **Regional case studies**\n  - Pilot projects in North England explore integrating renewable energy sources with mining operations to mitigate environmental impact while maintaining competitive hash rates.\n\n## Future Directions\n\n- **Emerging trends and developments**\n  - Increasing integration of renewable energy in mining to address the carbon footprint associated with high hash rates.\n  - Development of more energy-efficient mining hardware and alternative PoW algorithms.\n  - Enhanced real-time hash rate monitoring and predictive analytics for network security management.\n- **Anticipated challenges**\n  - Balancing hash rate growth with environmental sustainability and regulatory compliance.\n  - Preventing centralisation risks as mining power concentrates in fewer hands.\n  - Adapting hash rate metrics to hybrid consensus models combining PoW and Proof-of-Stake elements.\n- **Research priorities**\n  - Investigating the interplay between hash rate fluctuations and blockchain economic incentives.\n  - Designing protocols resilient to hash rate manipulation and attacks.\n  - Evaluating regional policy impacts on hash rate distribution and mining viability.\n\n## References\n\n1. Bonneau, J., Miller, A., Clark, J., Narayanan, A., Kroll, J. A., & Felten, E. W. (2015). SoK: Research Perspectives and Challenges for Bitcoin and Cryptocurrencies. *IEEE Symposium on Security and Privacy*. DOI: 10.1109/SP.2015.14\n\n2. Gervais, A., Karame, G. O., Wüst, K., Glykantzis, V., Ritzdorf, H., & Capkun, S. (2016). On the Security and Performance of Proof of Work Blockchains. *ACM Conference on Computer and Communications Security*. DOI: 10.1145/2976749.2978390\n\n3. Courtois, N. T., & Bahack, L. (2014). On Subversive Miner Strategies and Block Withholding Attack in Bitcoin Digital Currency. *arXiv preprint arXiv:1402.1718*. URL: https://arxiv.org/abs/1402.1718\n\n4. Nadcab Labs. (2024). Blockchain Hash Rate and Its Role in Network Security. Retrieved 2025.\n\n5. Blockchain.com. (2025). Total Hash Rate (TH/s) Charts. Retrieved 2025.\n\n\n## Metadata\n\n\n- **Migration Status**: Ontology block enriched on 2025-11-12\n- **Last Updated**: 2025-11-12\n- **Review Status**: Comprehensive editorial review\n- **Verification**: Academic sources verified\n- **Regional Context**: UK/North England where applicable",
  "properties": {
    "id": "network-hash-rate-standards",
    "collapsed": "true",
    "- domain-prefix": "BC",
    "- sequence-number": "0063",
    "- filename-history": "[\"BC-0063-network-hash-rate.md\"]",
    "- public-access": "true",
    "- ontology": "true",
    "- term-id": "BC-0063",
    "- preferred-term": "Network Hash Rate",
    "- source-domain": "metaverse",
    "- status": "complete",
    "- version": "1.0.0",
    "- last-updated": "2025-10-28",
    "- definition": "Total computational power within blockchain systems, providing essential functionality for distributed ledger technology operations and properties.",
    "- maturity": "mature",
    "- source": "[[ISO/IEC 23257:2021]], [[IEEE 2418.1]], [[NIST NISTIR]]",
    "- authority-score": "0.95",
    "- owl:class": "bc:NetworkHashRate",
    "- owl:physicality": "VirtualEntity",
    "- owl:role": "Object",
    "- owl:inferred-class": "bc:VirtualObject",
    "- belongsToDomain": "[[ConsensusDomain]]",
    "- implementedInLayer": "[[ProtocolLayer]]",
    "- is-subclass-of": "[[Blockchain Entity]], [[ConsensusProtocol]]"
  },
  "backlinks": [
    "Proof of Work"
  ],
  "wiki_links": [
    "ConsensusProtocol",
    "ISO/IEC 23257:2021",
    "ConsensusDomain",
    "ProtocolLayer",
    "IEEE 2418.1",
    "Blockchain Entity",
    "NIST NISTIR"
  ],
  "ontology": {
    "term_id": "BC-0063",
    "preferred_term": "Network Hash Rate",
    "definition": "Total computational power within blockchain systems, providing essential functionality for distributed ledger technology operations and properties.",
    "source_domain": "metaverse",
    "maturity_level": null,
    "authority_score": 0.95
  }
}