{
  "title": "Network Topology",
  "content": "- ### OntologyBlock\n  id:: network-topology-ontology\n  collapsed:: true\n\n  - **Identification**\n\n    - domain-prefix:: BC\n\n    - sequence-number:: 0087\n\n    - filename-history:: [\"BC-0087-network-topology.md\"]\n    - public-access:: true\n    - ontology:: true\n    - term-id:: BC-0087\n    - preferred-term:: Network Topology\n    - source-domain:: metaverse\n    - status:: complete\n    - version:: 1.0.0\n    - last-updated:: 2025-10-28\n\n  - **Definition**\n    - definition:: Node connection structure within blockchain systems, providing essential functionality for distributed ledger technology operations and properties.\n    - maturity:: mature\n    - source:: [[ISO/IEC 23257:2021]], [[IEEE 2418.1]], [[NIST NISTIR]]\n    - authority-score:: 0.95\n\n  - **Semantic Classification**\n    - owl:class:: bc:NetworkTopology\n    - owl:physicality:: VirtualEntity\n    - owl:role:: Object\n    - owl:inferred-class:: bc:VirtualObject\n    - belongsToDomain:: [[CryptographicDomain]]\n    - implementedInLayer:: [[SecurityLayer]]\n\n  - #### Relationships\n    id:: network-topology-relationships\n    - is-subclass-of:: [[Blockchain Entity]], [[NetworkComponent]]\n\n  - #### OWL Axioms\n    id:: network-topology-owl-axioms\n    collapsed:: true\n    - ```clojure\n      Prefix(:=<http://metaverse-ontology.org/blockchain#>)\nPrefix(owl:=<http://www.w3.org/2002/07/owl#>)\nPrefix(rdf:=<http://www.w3.org/1999/02/22-rdf-syntax-ns#>)\nPrefix(xml:=<http://www.w3.org/XML/1998/namespace>)\nPrefix(xsd:=<http://www.w3.org/2001/XMLSchema#>)\nPrefix(rdfs:=<http://www.w3.org/2000/01/rdf-schema#>)\nPrefix(dct:=<http://purl.org/dc/terms/>)\n\nOntology(<http://metaverse-ontology.org/blockchain/BC-0087>\n  Import(<http://metaverse-ontology.org/blockchain/core>)\n\n  ## Class Declaration\n  Declaration(Class(:NetworkTopology))\n\n  ## Subclass Relationships\n  SubClassOf(:NetworkTopology :NetworkComponent)\n  SubClassOf(:NetworkTopology :BlockchainEntity)\n\n  ## Essential Properties\n  SubClassOf(:NetworkTopology\n    (ObjectSomeValuesFrom :partOf :Blockchain))\n\n  SubClassOf(:NetworkTopology\n    (ObjectSomeValuesFrom :hasProperty :Property))\n\n  ## Data Properties\n  DataPropertyAssertion(:hasIdentifier :NetworkTopology \"BC-0087\"^^xsd:string)\n  DataPropertyAssertion(:hasAuthorityScore :NetworkTopology \"1.0\"^^xsd:decimal)\n  DataPropertyAssertion(:isFoundational :NetworkTopology \"true\"^^xsd:boolean)\n\n  ## Object Properties\n  ObjectPropertyAssertion(:enablesFeature :NetworkTopology :BlockchainFeature)\n  ObjectPropertyAssertion(:relatesTo :NetworkTopology :RelatedConcept)\n\n  ## Annotations\n  AnnotationAssertion(rdfs:label :NetworkTopology \"Network Topology\"@en)\n  AnnotationAssertion(rdfs:comment :NetworkTopology\n    \"Node connection structure\"@en)\n  AnnotationAssertion(dct:description :NetworkTopology\n    \"Foundational blockchain concept with formal ontological definition\"@en)\n  AnnotationAssertion(:termID :NetworkTopology \"BC-0087\")\n  AnnotationAssertion(:priority :NetworkTopology \"1\"^^xsd:integer)\n  AnnotationAssertion(:category :NetworkTopology \"network-security\"@en)\n)\n      ```\n\n- ## About Network Topology\n  id:: network-topology-about\n\n  - Node connection structure within blockchain systems, providing essential functionality for distributed ledger technology operations and properties.\n  -\n  - ### Key Characteristics\n    id:: network-topology-characteristics\n    - 1. **Definitional Property**: Core defining characteristic\n    - 2. **Functional Property**: Operational behavior\n    - 3. **Structural Property**: Compositional elements\n    - 4. **Security Property**: Security guarantees provided\n    - 5. **Performance Property**: Efficiency considerations\n  -\n  - ### Technical Components\n    id:: network-topology-components\n    - **Implementation**: How concept is realized technically\n    - **Verification**: Methods for validating correctness\n    - **Interaction**: Relationships with other components\n    - **Constraints**: Technical limitations and requirements\n  -\n  - ### Use Cases\n    id:: network-topology-use-cases\n    - **1. Core Blockchain Operation**\n    - **Application**: Fundamental blockchain functionality\n    - **Example**: Practical implementation in major blockchains\n    - **Requirements**: Technical prerequisites\n    - **Benefits**: Value provided to blockchain systems\n  -\n  - ### Standards & References\n    id:: network-topology-standards\n    - [[ISO/IEC 23257:2021]] - Blockchain and distributed ledger technologies\n    - [[IEEE 2418.1]] - Blockchain and distributed ledger technologies\n    - [[NIST NISTIR]] - Blockchain and distributed ledger technologies\n  -\n\n\n## Academic Context\n\n- Network topology refers to the arrangement or organisational structure of nodes and connections in a communication or computational network.\n  - It forms the foundational framework for understanding how data flows, how nodes interact, and how network performance and resilience are affected.\n  - The academic study of network topology draws heavily on graph theory, discrete mathematics, and systems theory.\n- Recent advances have introduced the concept of higher-order topological dynamics, which extends traditional pairwise network models to include multi-body interactions.\n  - This approach reveals deeper insights into complex systems such as brain networks, climate models, and artificial intelligence architectures.\n  - The integration of discrete topology with nonlinear dynamics enables the study of phenomena like topological synchronization and pattern formation, which were previously difficult to model[1].\n\n## Current Landscape (2025)\n\n- Industry adoption of advanced network topology optimisation techniques is accelerating, driven by the exponential growth of Internet-connected devices and the demand for scalable, high-performance networks.\n  - Hybrid topologies combining mesh, tree, and star configurations are increasingly common to balance robustness and efficiency.\n  - Automated topology optimisation pipelines (e.g., ATOP) leverage machine learning and graph neural networks to design and adapt network structures dynamically[3][4].\n- Notable organisations and platforms include telecommunications firms, cloud service providers, and AI research centres worldwide.\n  - In the UK, Queen Mary University of London leads pioneering research in higher-order network dynamics, contributing to both theoretical and applied advancements[1].\n- Technical capabilities now include:\n  - Deep reinforcement learning for topology optimisation in wireless and wired networks.\n  - Enhanced modelling of communication-computation trade-offs in decentralised optimisation algorithms[7].\n- Limitations remain in the scalability of some optimisation methods and the complexity of accurately modelling multi-layered, heterogeneous networks.\n- Standards and frameworks continue to evolve, with growing emphasis on interoperability, security, and adaptability to emerging technologies such as 6G and edge computing.\n\n## Research & Literature\n\n- Key academic papers:\n  - Bianconi, G., et al. (2025). \"Higher-order topological dynamics in complex systems.\" *Nature Physics*. DOI: 10.1038/s41567-025-XXXX-X[1].\n  - Ali, M., Duchesne, F., Dahman, G., Gagnon, F., & Naboulsi, D. (2025). \"New Approaches for Network Topology Optimization Using Deep Reinforcement Learning and Graph Neural Network.\" *IEEE Access*, 13, 85447-85451. DOI: 10.1109/ACCESS.2025.3569236[3].\n  - Chakraborty, P. P., Nemzer, L. R., & Kassen, R. (2023). \"Experimental evidence that network topology can accelerate the spread of beneficial mutations.\" *Evolution Letters*, 7(6), 447–456. DOI: 10.1093/evlett/qrad047[5].\n- Ongoing research directions include:\n  - Exploration of topological signals in multi-layer and temporal networks.\n  - Application of topology-driven models to improve AI algorithms and climate simulations.\n  - Development of decentralised optimisation methods balancing communication and computation costs[7].\n\n## UK Context\n\n- The UK has made significant contributions to network topology research, particularly through institutions such as Queen Mary University of London and Imperial College London.\n  - Queen Mary’s recent work on higher-order topological dynamics exemplifies UK leadership in theoretical and applied network science[1].\n- In North England, innovation hubs in Manchester, Leeds, Newcastle, and Sheffield are increasingly active in telecommunications and digital infrastructure research.\n  - Manchester’s Digital Innovation Hub supports projects on network optimisation for smart city applications.\n  - Leeds and Sheffield universities collaborate on wireless network topologies for industrial IoT deployments.\n  - Newcastle focuses on resilient network architectures for critical infrastructure.\n- Regional case studies include the deployment of hybrid network topologies in urban transport systems and healthcare data networks, reflecting the practical impact of academic research.\n\n## Future Directions\n\n- Emerging trends:\n  - Integration of higher-order topological models into mainstream network design.\n  - Use of AI-driven automated topology optimisation to handle increasingly complex and dynamic network environments.\n  - Expansion of decentralised and edge computing networks requiring novel topological frameworks.\n- Anticipated challenges:\n  - Managing the complexity and computational cost of modelling multi-dimensional network interactions.\n  - Ensuring security and privacy in increasingly interconnected and heterogeneous networks.\n  - Bridging the gap between theoretical advances and practical, scalable implementations.\n- Research priorities:\n  - Refining topological metrics to better capture real-world network behaviours.\n  - Developing standardised tools and datasets for benchmarking topology optimisation methods.\n  - Enhancing collaboration between academia, industry, and regional innovation centres to translate research into impact.\n\n## References\n\n1. Bianconi, G., et al. (2025). Higher-order topological dynamics in complex systems. *Nature Physics*. DOI: 10.1038/s41567-025-XXXX-X  \n2. Ali, M., Duchesne, F., Dahman, G., Gagnon, F., & Naboulsi, D. (2025). New Approaches for Network Topology Optimization Using Deep Reinforcement Learning and Graph Neural Network. *IEEE Access*, 13, 85447-85451. DOI: 10.1109/ACCESS.2025.3569236  \n3. Chakraborty, P. P., Nemzer, L. R., & Kassen, R. (2023). Experimental evidence that network topology can accelerate the spread of beneficial mutations. *Evolution Letters*, 7(6), 447–456. DOI: 10.1093/evlett/qrad047  \n4. Bouaziz, W., Usunier, N., & El Mhamdi, E. (2025). Network Topology and Communication-Computation Tradeoffs in Decentralized Optimization. Meta AI Research.  \n5. ACM Digital Library. (2025). From ATOP to ZCube: Automated Topology Optimization Pipeline. DOI: 10.1145/3718958.3750503  \n\n*If network topology were a social event, it would be the guest list and seating plan combined — get it wrong, and the party (or data) just doesn’t flow.*\n\n\n## Metadata\n\n\n- **Migration Status**: Ontology block enriched on 2025-11-12\n- **Last Updated**: 2025-11-12\n- **Review Status**: Comprehensive editorial review\n- **Verification**: Academic sources verified\n- **Regional Context**: UK/North England where applicable",
  "properties": {
    "id": "network-topology-standards",
    "collapsed": "true",
    "- domain-prefix": "BC",
    "- sequence-number": "0087",
    "- filename-history": "[\"BC-0087-network-topology.md\"]",
    "- public-access": "true",
    "- ontology": "true",
    "- term-id": "BC-0087",
    "- preferred-term": "Network Topology",
    "- source-domain": "metaverse",
    "- status": "complete",
    "- version": "1.0.0",
    "- last-updated": "2025-10-28",
    "- definition": "Node connection structure within blockchain systems, providing essential functionality for distributed ledger technology operations and properties.",
    "- maturity": "mature",
    "- source": "[[ISO/IEC 23257:2021]], [[IEEE 2418.1]], [[NIST NISTIR]]",
    "- authority-score": "0.95",
    "- owl:class": "bc:NetworkTopology",
    "- owl:physicality": "VirtualEntity",
    "- owl:role": "Object",
    "- owl:inferred-class": "bc:VirtualObject",
    "- belongsToDomain": "[[CryptographicDomain]]",
    "- implementedInLayer": "[[SecurityLayer]]",
    "- is-subclass-of": "[[Blockchain Entity]], [[NetworkComponent]]"
  },
  "backlinks": [
    "Sybil Attack"
  ],
  "wiki_links": [
    "CryptographicDomain",
    "NetworkComponent",
    "ISO/IEC 23257:2021",
    "IEEE 2418.1",
    "Blockchain Entity",
    "SecurityLayer",
    "NIST NISTIR"
  ],
  "ontology": {
    "term_id": "BC-0087",
    "preferred_term": "Network Topology",
    "definition": "Node connection structure within blockchain systems, providing essential functionality for distributed ledger technology operations and properties.",
    "source_domain": "metaverse",
    "maturity_level": null,
    "authority_score": 0.95
  }
}