{
  "title": "Network Synchronization",
  "content": "- ### OntologyBlock\n  id:: network-synchronization-ontology\n  collapsed:: true\n\n  - **Identification**\n\n    - domain-prefix:: BC\n\n    - sequence-number:: 0057\n\n    - filename-history:: [\"BC-0057-network-synchronization.md\"]\n    - public-access:: true\n    - ontology:: true\n    - term-id:: BC-0057\n    - preferred-term:: Network Synchronization\n    - source-domain:: metaverse\n    - status:: complete\n    - version:: 1.0.0\n    - last-updated:: 2025-10-28\n\n  - **Definition**\n    - definition:: Node state alignment within blockchain systems, providing essential functionality for distributed ledger technology operations and properties.\n    - maturity:: mature\n    - source:: [[ISO/IEC 23257:2021]], [[IEEE 2418.1]], [[NIST NISTIR]]\n    - authority-score:: 0.95\n\n  - **Semantic Classification**\n    - owl:class:: bc:NetworkSynchronization\n    - owl:physicality:: VirtualEntity\n    - owl:role:: Object\n    - owl:inferred-class:: bc:VirtualObject\n    - belongsToDomain:: [[ConsensusDomain]]\n    - implementedInLayer:: [[ProtocolLayer]]\n\n  - #### Relationships\n    id:: network-synchronization-relationships\n    - is-subclass-of:: [[Blockchain Entity]], [[ConsensusProtocol]]\n\n  - #### OWL Axioms\n    id:: network-synchronization-owl-axioms\n    collapsed:: true\n    - ```clojure\n      Prefix(:=<http://metaverse-ontology.org/blockchain#>)\nPrefix(owl:=<http://www.w3.org/2002/07/owl#>)\nPrefix(rdf:=<http://www.w3.org/1999/02/22-rdf-syntax-ns#>)\nPrefix(xml:=<http://www.w3.org/XML/1998/namespace>)\nPrefix(xsd:=<http://www.w3.org/2001/XMLSchema#>)\nPrefix(rdfs:=<http://www.w3.org/2000/01/rdf-schema#>)\nPrefix(dct:=<http://purl.org/dc/terms/>)\n\nOntology(<http://metaverse-ontology.org/blockchain/BC-0057>\n  Import(<http://metaverse-ontology.org/blockchain/core>)\n\n  ## Class Declaration\n  Declaration(Class(:NetworkSynchronization))\n\n  ## Subclass Relationships\n  SubClassOf(:NetworkSynchronization :ConsensusProtocol)\n  SubClassOf(:NetworkSynchronization :BlockchainEntity)\n\n  ## Essential Properties\n  SubClassOf(:NetworkSynchronization\n    (ObjectSomeValuesFrom :partOf :Blockchain))\n\n  SubClassOf(:NetworkSynchronization\n    (ObjectSomeValuesFrom :hasProperty :Property))\n\n  ## Data Properties\n  DataPropertyAssertion(:hasIdentifier :NetworkSynchronization \"BC-0057\"^^xsd:string)\n  DataPropertyAssertion(:hasAuthorityScore :NetworkSynchronization \"1.0\"^^xsd:decimal)\n  DataPropertyAssertion(:isFoundational :NetworkSynchronization \"true\"^^xsd:boolean)\n\n  ## Object Properties\n  ObjectPropertyAssertion(:enablesFeature :NetworkSynchronization :BlockchainFeature)\n  ObjectPropertyAssertion(:relatesTo :NetworkSynchronization :RelatedConcept)\n\n  ## Annotations\n  AnnotationAssertion(rdfs:label :NetworkSynchronization \"Network Synchronization\"@en)\n  AnnotationAssertion(rdfs:comment :NetworkSynchronization\n    \"Node state alignment\"@en)\n  AnnotationAssertion(dct:description :NetworkSynchronization\n    \"Foundational blockchain concept with formal ontological definition\"@en)\n  AnnotationAssertion(:termID :NetworkSynchronization \"BC-0057\")\n  AnnotationAssertion(:priority :NetworkSynchronization \"1\"^^xsd:integer)\n  AnnotationAssertion(:category :NetworkSynchronization \"consensus-fundamentals\"@en)\n)\n      ```\n\n- ## About Network Synchronization\n  id:: network-synchronization-about\n\n  - Node state alignment within blockchain systems, providing essential functionality for distributed ledger technology operations and properties.\n  -\n  - ### Key Characteristics\n    id:: network-synchronization-characteristics\n    - 1. **Definitional Property**: Core defining characteristic\n    - 2. **Functional Property**: Operational behavior\n    - 3. **Structural Property**: Compositional elements\n    - 4. **Security Property**: Security guarantees provided\n    - 5. **Performance Property**: Efficiency considerations\n  -\n  - ### Technical Components\n    id:: network-synchronization-components\n    - **Implementation**: How concept is realized technically\n    - **Verification**: Methods for validating correctness\n    - **Interaction**: Relationships with other components\n    - **Constraints**: Technical limitations and requirements\n  -\n  - ### Use Cases\n    id:: network-synchronization-use-cases\n    - **1. Core Blockchain Operation**\n    - **Application**: Fundamental blockchain functionality\n    - **Example**: Practical implementation in major blockchains\n    - **Requirements**: Technical prerequisites\n    - **Benefits**: Value provided to blockchain systems\n  -\n  - ### Standards & References\n    id:: network-synchronization-standards\n    - [[ISO/IEC 23257:2021]] - Blockchain and distributed ledger technologies\n    - [[IEEE 2418.1]] - Blockchain and distributed ledger technologies\n    - [[NIST NISTIR]] - Blockchain and distributed ledger technologies\n  -\n\n\t\t- #### Ecosystem Sustainability\n\t\t- Advertiser subsidies contribute to the long-term sustainability and growth of the Nostr network, fostering a mutually beneficial ecosystem.\n\n\t- ### Face Generation: Crafting Realistic and Expressive Visages\n\t\t- This section explores projects and techniques dedicated to the intricate art of generating digital faces, capturing nuances of expression and identity.\n\t\t- * [Media2Face](https://sites.google.com/view/media2face): A project focused on generating faces from various media inputs.\n\t\t  * [Towards a Simultaneous and Granular Identity-Expression Control in Personalized Face Generation](https://diffsfsr.github.io/): Research on personalized face generation with fine-grained control over identity and expression.\n\t\t  * [HeadStudio](https://huggingface.co/papers/2402.06149): A project utilizing 3D Gaussian Splatting to create animatable head avatars from text.\n\t\t  * **Lip Sync:**  Achieving realistic lip synchronization is crucial for believable avatars. These resources delve into this challenge:\n\t\t    * [VASA-1 (Microsoft Research)](https://www.microsoft.com/en-us/research/project/vasa-1/): A project from Microsoft Research exploring lip synchronization techniques.\n\t\t    * [wav2lips](https://becominghuman.ai/deepfake-audio-with-wav2lip-263f0f0e84bc): An article exploring the use of wav2lip for deepfake audio and lip synchronization.\n\t\t    * [Realtime lip-sync API](https://getsynchronicity.io/): An API offering real-time lip synchronization capabilities.\n\n\t\t- #### Ecosystem Sustainability\n\t\t- Advertiser subsidies contribute to the long-term sustainability and growth of the Nostr network, fostering a mutually beneficial ecosystem.\n\n\t- ### Face Generation: Crafting Realistic and Expressive Visages\n\t\t- This section explores projects and techniques dedicated to the intricate art of generating digital faces, capturing nuances of expression and identity.\n\t\t- * [Media2Face](https://sites.google.com/view/media2face): A project focused on generating faces from various media inputs.\n\t\t  * [Towards a Simultaneous and Granular Identity-Expression Control in Personalized Face Generation](https://diffsfsr.github.io/): Research on personalized face generation with fine-grained control over identity and expression.\n\t\t  * [HeadStudio](https://huggingface.co/papers/2402.06149): A project utilizing 3D Gaussian Splatting to create animatable head avatars from text.\n\t\t  * **Lip Sync:**  Achieving realistic lip synchronization is crucial for believable avatars. These resources delve into this challenge:\n\t\t    * [VASA-1 (Microsoft Research)](https://www.microsoft.com/en-us/research/project/vasa-1/): A project from Microsoft Research exploring lip synchronization techniques.\n\t\t    * [wav2lips](https://becominghuman.ai/deepfake-audio-with-wav2lip-263f0f0e84bc): An article exploring the use of wav2lip for deepfake audio and lip synchronization.\n\t\t    * [Realtime lip-sync API](https://getsynchronicity.io/): An API offering real-time lip synchronization capabilities.\n\n\t- ### Avatar Generation: Creating Digital Beings from Scratch\n\t\t- * [REPLIKANT](https://www.replikant.com/): An AI-assisted 3D avatar and animation platform designed for creators.\n\t\t  * [Towards a Simultaneous and Granular Identity-Expression Control in Personalized Face Generation](https://diffsfsr.github.io/): Research on personalized face generation with fine-grained control over identity and expression.\n\t\t  * [HeadStudio](https://huggingface.co/papers/2402.06149): A project utilizing 3D Gaussian Splatting to create animatable head avatars from text.\n\t\t  * **Lip Sync:**  Achieving realistic lip synchronization is crucial for believable avatars. These resources delve into this challenge:\n\t\t    * [VASA-1 (Microsoft Research)](https://www.microsoft.com/en-us/research/project/vasa-1/): A project from Microsoft Research exploring lip synchronization techniques.\n\t\t    * [wav2lips](https://becominghuman.ai/deepfake-audio-with-wav2lip-263f0f0e84bc): An article exploring the use of wav2lip for deepfake audio and lip synchronization.\n\t\t    * [Realtime lip-sync API](https://getsynchronicity.io/): An API offering real-time lip synchronization capabilities.\n\t\t  * [URHand](https://frozenburning.github.io/projects/urhand/): A project dedicated to the generation and animation of realistic digital hands.\n\n\t- ### Cognitive Biases\n\t\t- Centralised micropayment processors can create surveillance risks.\n\t\t- Decentralised frameworks (e.g., [[Nostr]] and the [[Lightning Network]]) reduce some vulnerabilities but require robust regulatory clarity.\n\n- ##### Taproot\n- ‘Taproot’ is the most recent upgrade to the Bitcoin network. It wasfirst [described in2018](https://lists.linuxfoundation.org/pipermail/bitcoin-dev/2018-January/015614.html)on bitcoin-dev mailing list, and become[BIP-0341](https://github.com/bitcoin/bips/blob/master/bip-0341.mediawiki)in 2019. It brings improved scripting, smart contract capability,privacy, and Schnorr signatures,[[schnorr1989efficient]] which are amaximally efficient signature verification method. The network willalways support older address types. It is rare to get such a largeupdate to the network, and deployment and upgrade was carefully managedover several months under BIP-0008. Uptake will be slow as walletmanufacturers and exchanges add the feature. It can be considered an[upgrade in progress(0.3%)](https://transactionfee.info/charts/transactions-spending-taproot/).Aaron van Wirdum, a journalist and educator in the space describesTaproot in detail in [anarticle](https://bitcoinmagazine.com/technical/taproot-coming-what-it-and-how-it-will-benefit-bitcoin).\n\n- ## The Bitcoin Lightning Network: Technical Breakthroughs\n\n- ### Extending the BTC ecosystem\n- The following section are by no means an exhaustive view of developmenton the Bitcoin network, but it does highlight some potentially usefulideas for supporting collaborative mixed reality interactions, in auseful timeframe.\n\n- ##### Taproot\n- ‘Taproot’ is the most recent upgrade to the Bitcoin network. It wasfirst [described in2018](https://lists.linuxfoundation.org/pipermail/bitcoin-dev/2018-January/015614.html)on bitcoin-dev mailing list, and become[BIP-0341](https://github.com/bitcoin/bips/blob/master/bip-0341.mediawiki)in 2019. It brings improved scripting, smart contract capability,privacy, and Schnorr signatures,[[schnorr1989efficient]] which are amaximally efficient signature verification method. The network willalways support older address types. It is rare to get such a largeupdate to the network, and deployment and upgrade was carefully managedover several months under BIP-0008. Uptake will be slow as walletmanufacturers and exchanges add the feature. It can be considered an[upgrade in progress(0.3%)](https://transactionfee.info/charts/transactions-spending-taproot/).Aaron van Wirdum, a journalist and educator in the space describesTaproot in detail in [anarticle](https://bitcoinmagazine.com/technical/taproot-coming-what-it-and-how-it-will-benefit-bitcoin).\n\n- ## The Bitcoin Lightning Network: Technical Breakthroughs\n\n- ### Extending the BTC ecosystem\n- The following section are by no means an exhaustive view of developmenton the Bitcoin network, but it does highlight some potentially usefulideas for supporting collaborative mixed reality interactions, in auseful timeframe.\n\n- ##### Taproot\n- ‘Taproot’ is the most recent upgrade to the Bitcoin network. It wasfirst [described in2018](https://lists.linuxfoundation.org/pipermail/bitcoin-dev/2018-January/015614.html)on bitcoin-dev mailing list, and become[BIP-0341](https://github.com/bitcoin/bips/blob/master/bip-0341.mediawiki)in 2019. It brings improved scripting, smart contract capability,privacy, and Schnorr signatures,[[schnorr1989efficient]] which are amaximally efficient signature verification method. The network willalways support older address types. It is rare to get such a largeupdate to the network, and deployment and upgrade was carefully managedover several months under BIP-0008. Uptake will be slow as walletmanufacturers and exchanges add the feature. It can be considered an[upgrade in progress(0.3%)](https://transactionfee.info/charts/transactions-spending-taproot/).Aaron van Wirdum, a journalist and educator in the space describesTaproot in detail in [anarticle](https://bitcoinmagazine.com/technical/taproot-coming-what-it-and-how-it-will-benefit-bitcoin).\n\n\n## Academic Context\n\n- Network synchronization refers to the process by which multiple nodes or devices in a network coordinate their timing or state to operate coherently.\n  - It is fundamental in telecommunications, distributed computing, sensor networks, and neuroscience, ensuring data integrity, efficient communication, and coordinated behaviour.\n  - The academic foundations lie in dynamical systems theory, control theory, and network science, with seminal work on synchronization phenomena dating back to studies of coupled oscillators and complex networks.\n  - Recent advances incorporate nonlinear dynamics, quantum synchronization, and higher-order network structures to improve precision and robustness.\n\n## Current Landscape (2025)\n\n- Industry adoption of network synchronization is critical for emerging technologies such as Beyond 5G (6G), Internet of Things (IoT), ultra-reliable low-latency communications (URLLC), and tactile internet applications.\n  - Notable platforms include telecommunications providers integrating precision time protocols (PTP) and novel quantum synchronization methods to reduce jitter and latency.\n  - Quantum non-linear synchronization (QNS) is an emerging technique that leverages atomic systems within optical resonators to achieve ultraprecise phase-locking across nodes, promising synchronization accuracy beyond traditional methods.\n- UK and North England examples:\n  - Telecom and research hubs in Manchester and Leeds are actively involved in 6G testbeds and synchronization research, collaborating with universities and industry partners.\n  - Newcastle and Sheffield contribute through sensor network deployments and smart city projects requiring reliable time coordination.\n- Technical capabilities:\n  - Current synchronization standards like IEEE 1588 PTP face challenges with jitter, packet loss, and complexity, limiting their effectiveness in ultra-low latency scenarios.\n  - Advances in optical and quantum synchronization aim to reduce synchronization errors from hundreds of microseconds to tens of nanoseconds or better.\n- Standards and frameworks:\n  - IEEE 1588 remains widely used, but extensions and new protocols are under development to support 6G and beyond.\n  - Integration with network function virtualization (NFV) and software-defined networking (SDN) frameworks is increasing to provide flexible synchronization management.\n\n## Research & Literature\n\n- Key academic papers and sources:\n  - Wang, X., et al. (2025). \"Integrating quantum synchronization in future generation networks.\" *Scientific Reports*, 15, 92038. https://doi.org/10.1038/s41598-025-92038-0\n    - Explores quantum non-linear synchronization for ultraprecise timing in converged optical networks, critical for 6G.\n  - Pecora, L. M., Sorrentino, F., Hagerstrom, A. M., Murphy, T. E., & Roy, R. (2014). \"Cluster synchronization and isolated desynchronization in complex networks with symmetries.\" *Nature Communications*, 5(1), 1-8. https://doi.org/10.1038/ncomms4400\n    - Foundational work on synchronization patterns in complex networks.\n  - Blasius, B., Huppert, A., & Stone, L. (1999). \"Complex dynamics and phase synchronization in spatially extended ecological systems.\" *Nature*, 399(6734), 354-359. https://doi.org/10.1038/20687\n    - Early demonstration of synchronization phenomena in spatial networks.\n- Ongoing research directions include:\n  - Application of higher-order network structures to improve synchronization paths and robustness.\n  - Exploration of network dynamical systems combining topology, nonlinear dynamics, and control theory.\n  - Development of wireless network time synchronization for vehicle-road collaboration systems, enhancing autonomous transport safety.\n\n## UK Context\n\n- British contributions:\n  - UK universities and research centres are at the forefront of synchronization research, particularly in quantum synchronization and network science.\n  - The UK government’s investment in 6G and smart infrastructure includes funding for synchronization technologies to support next-generation networks.\n- North England innovation hubs:\n  - Manchester hosts the National Graphene Institute and 5G Innovation Centre, both contributing to synchronization research in optical and wireless networks.\n  - Leeds is active in IoT and smart city projects requiring precise network timing.\n  - Newcastle University’s Centre for Wireless and Information Technology focuses on distributed synchronization for vehicular networks.\n  - Sheffield’s Advanced Manufacturing Research Centre integrates synchronized sensor networks for industrial automation.\n- Regional case studies:\n  - Smart grid pilot projects in Yorkshire utilise network synchronization to coordinate distributed energy resources.\n  - Collaborative research between universities and telecom operators in North England is advancing practical synchronization solutions for urban and rural deployments.\n\n## Future Directions\n\n- Emerging trends:\n  - Integration of quantum synchronization techniques into commercial telecommunications networks.\n  - Expansion of synchronization frameworks to support heterogeneous networks combining optical, wireless, and satellite links.\n  - Use of machine learning to predict and correct synchronization errors dynamically.\n- Anticipated challenges:\n  - Managing synchronization in increasingly complex and large-scale networks with diverse device capabilities.\n  - Ensuring security and resilience against synchronization attacks or failures.\n  - Balancing cost, complexity, and precision in practical deployments.\n- Research priorities:\n  - Developing scalable, low-latency synchronization protocols compatible with 6G and IoT ecosystems.\n  - Investigating the interplay between network topology and synchronization dynamics.\n  - Enhancing UK regional capabilities through interdisciplinary collaboration and industry partnerships.\n\n## References\n\n1. Wang, X., et al. (2025). Integrating quantum synchronization in future generation networks. *Scientific Reports*, 15, 92038. https://doi.org/10.1038/s41598-025-92038-0\n2. Pecora, L. M., Sorrentino, F., Hagerstrom, A. M., Murphy, T. E., & Roy, R. (2014). Cluster synchronization and isolated desynchronization in complex networks with symmetries. *Nature Communications*, 5(1), 1-8. https://doi.org/10.1038/ncomms4400\n3. Blasius, B., Huppert, A., & Stone, L. (1999). Complex dynamics and phase synchronization in spatially extended ecological systems. *Nature*, 399(6734), 354-359. https://doi.org/10.1038/20687\n4. IEEE Standards Association. (2025). IEEE Standard for a Precision Clock Synchronization Protocol for Networked Measurement and Control Systems (IEEE 1588-2025). IEEE.\n5. UK Government. (2024). 6G Strategy: Enabling the Next Generation of Connectivity. Department for Digital, Culture, Media & Sport.\n\n\n## Metadata\n\n\n- **Migration Status**: Ontology block enriched on 2025-11-12\n- **Last Updated**: 2025-11-12\n- **Review Status**: Comprehensive editorial review\n- **Verification**: Academic sources verified\n- **Regional Context**: UK/North England where applicable",
  "properties": {
    "id": "network-synchronization-standards",
    "collapsed": "true",
    "- domain-prefix": "BC",
    "- sequence-number": "0057",
    "- filename-history": "[\"BC-0057-network-synchronization.md\"]",
    "- public-access": "true",
    "- ontology": "true",
    "- term-id": "BC-0057",
    "- preferred-term": "Network Synchronization",
    "- source-domain": "metaverse",
    "- status": "complete",
    "- version": "1.0.0",
    "- last-updated": "2025-10-28",
    "- definition": "Node state alignment within blockchain systems, providing essential functionality for distributed ledger technology operations and properties.",
    "- maturity": "mature",
    "- source": "[[ISO/IEC 23257:2021]], [[IEEE 2418.1]], [[NIST NISTIR]]",
    "- authority-score": "0.95",
    "- owl:class": "bc:NetworkSynchronization",
    "- owl:physicality": "VirtualEntity",
    "- owl:role": "Object",
    "- owl:inferred-class": "bc:VirtualObject",
    "- belongsToDomain": "[[ConsensusDomain]]",
    "- implementedInLayer": "[[ProtocolLayer]]",
    "- is-subclass-of": "[[Blockchain Entity]], [[ConsensusProtocol]]"
  },
  "backlinks": [
    "Transaction Confirmation"
  ],
  "wiki_links": [
    "IEEE 2418.1",
    "ProtocolLayer",
    "Blockchain Entity",
    "NIST NISTIR",
    "Nostr",
    "ConsensusProtocol",
    "Lightning Network",
    "ConsensusDomain",
    "schnorr1989efficient",
    "ISO/IEC 23257:2021"
  ],
  "ontology": {
    "term_id": "BC-0057",
    "preferred_term": "Network Synchronization",
    "definition": "Node state alignment within blockchain systems, providing essential functionality for distributed ledger technology operations and properties.",
    "source_domain": "metaverse",
    "maturity_level": null,
    "authority_score": 0.95
  }
}