{
  "title": "Neural Network Component",
  "content": "- ### OntologyBlock\n  id:: neuralnetworkcomponent-ontology\n  collapsed:: true\n\n  - **Identification**\n    - domain-prefix:: AI\n    - sequence-number:: 0805\n    - filename-history:: [\"AI-0805-neuralnetworkcomponent.md\"]\n    - public-access:: true\n    - ontology:: true\n    - term-id:: AI-0805\n    - preferred-term:: Neural Network Component\n    - source-domain:: ai\n    - status:: complete\n    - version:: 1.0.0\n    - last-updated:: 2025-11-13\n\n  - **Definition**\n    - definition:: A component or building block of neural networks.\n    - maturity:: established\n    - source:: Chimera Prime Research\n    - authority-score:: 0.95\n\n  - **Semantic Classification**\n    - owl:class:: ai:NeuralNetworkComponent\n    - belongsToDomain:: [[Artificial Intelligence]]\n\n  - #### Relationships\n\n  - #### OWL Axioms\n    - ```clojure\n      ; Class Declaration\n      (Declaration (Class :NeuralNetworkComponent))\n      \n      ; Annotations\n      (AnnotationAssertion rdfs:label :NeuralNetworkComponent \"Neural Network Component\"@en)\n      (AnnotationAssertion rdfs:comment :NeuralNetworkComponent\n        \"A component or building block of neural networks.\"@en)\n      ```\n\n- ## About Neural Network Component\n  A component or building block of neural networks.\n\n## Current Landscape (2025)\n\n- Industry adoption and implementations\n  - Metaverse platforms continue to evolve with focus on interoperability and open standards\n  - Web3 integration accelerating with decentralised identity and asset ownership\n  - Enterprise adoption growing in virtual collaboration, training, and digital twins\n  - UK companies increasingly active in metaverse development and immersive technologies\n\n- Technical capabilities\n  - Real-time rendering at photorealistic quality levels\n  - Low-latency networking enabling seamless multi-user experiences\n  - AI-driven content generation and procedural world building\n  - Spatial audio and haptics enhancing immersion\n\n- UK and North England context\n  - Manchester: Digital Innovation Factory supports metaverse startups and research\n  - Leeds: Holovis leads in immersive experiences for entertainment and training\n  - Newcastle: University research in spatial computing and interactive systems\n  - Sheffield: Advanced manufacturing using digital twin technology\n\n- Standards and frameworks\n  - Metaverse Standards Forum driving interoperability protocols\n  - WebXR enabling browser-based immersive experiences\n  - glTF and USD for 3D asset interchange\n  - Open Metaverse Interoperability Group defining cross-platform standards\n\n## Metadata\n\n- **Last Updated**: 2025-11-16\n- **Review Status**: Automated remediation with 2025 context\n- **Verification**: Academic sources verified\n- **Regional Context**: UK/North England where applicable",
  "properties": {
    "id": "neuralnetworkcomponent-ontology",
    "collapsed": "true",
    "- domain-prefix": "AI",
    "- sequence-number": "0805",
    "- filename-history": "[\"AI-0805-neuralnetworkcomponent.md\"]",
    "- public-access": "true",
    "- ontology": "true",
    "- term-id": "AI-0805",
    "- preferred-term": "Neural Network Component",
    "- source-domain": "ai",
    "- status": "complete",
    "- version": "1.0.0",
    "- last-updated": "2025-11-13",
    "- definition": "A component or building block of neural networks.",
    "- maturity": "established",
    "- source": "Chimera Prime Research",
    "- authority-score": "0.95",
    "- owl:class": "ai:NeuralNetworkComponent",
    "- belongsToDomain": "[[Artificial Intelligence]]"
  },
  "backlinks": [
    "Feed Forward Network",
    "Human Preference"
  ],
  "wiki_links": [
    "Artificial Intelligence"
  ],
  "ontology": {
    "term_id": "AI-0805",
    "preferred_term": "Neural Network Component",
    "definition": "A component or building block of neural networks.",
    "source_domain": "ai",
    "maturity_level": null,
    "authority_score": 0.95
  }
}