{
  "title": "Neuromorphic Computing",
  "content": "- ### OntologyBlock\n  id:: neuromorphic-computing-ontology\n  collapsed:: true\n\t- ontology:: true\n\t- term-id:: ME-0005\n\t- preferred-term:: Neuromorphic Computing\n\t- source-domain:: metaverse\n\t- status:: emerging-technology\n    - public-access:: true\n\t- definition:: [Generated from Gartner emerging tech analysis]\n\t- maturity:: emerging\n\t- owl:class:: mv:NeuromorphicComputing\n\t- owl:physicality:: ConceptualEntity\n\t- owl:role:: Concept\n\t- belongsToDomain:: [[MetaverseDomain]]\n\t- category:: AI & Autonomy\n\n\n## Overview\n\n# Neuromorphic Computing: A Comprehensive Overview\n\n## Technical Definition\n\nNeuromorphic computing is a computational paradigm that designs hardware and software systems to mirror the structure and function of biological neural networks, integrating memory and processing units to enable parallel, event-driven information processing inspired by how neurons communicate through electrical spikes.[1][2] Unlike traditional von Neumann architectures that separate memory from processing, neuromorphic systems perform computation asynchronously at the location of data, fundamentally restructuring how machines process information.[4][6]\n\n## Current State and Implementations (2024–2025)\n\n**Hardware Development**\n\nThe field has progressed significantly beyond theoretical research. Major technology companies are actively developing neuromorphic chips: Intel's Loihi simulates over one million neurons using merely 70 milliwatts of power, whilst IBM's TrueNorth and BrainChip's Akida represent parallel efforts in this space.[1] These systems operate using spiking neural networks (SNNs), which process information only when sensor inputs change, fundamentally reducing energy consumption by up to 100 times compared to conventional systems.[4]\n\n**Key Advantages in Current Deployment**\n\n- **Ultra-low energy consumption**: Neuromorphic chips reduce idle power use by up to 100 times through event-driven processing[4]\n- **Low latency**: Response times under 100 milliseconds support real-time applications[4]\n- **Parallel processing**: Asynchronous execution handles multiple sensor inputs simultaneously without bottlenecks[4]\n- **Noise tolerance**: Systems process incomplete or unstructured data effectively in chaotic environments[4]\n- **Compact design**: Reduced power and thermal requirements enable embedded device deployment[4]\n\n**Emerging Applications**\n\nCurrent implementations focus on robotics, autonomous vehicles, real-time data processing, and cognitive computing tasks.[2] The technology addresses a critical limitation of modern AI: current computing approaches have proven inefficient, slow, and energy-intensive, particularly as AI systems scale.[3]\n\n## UK Context and North England Examples\n\nThe search results provided do not contain specific information regarding neuromorphic computing research, development, or implementation within the United Kingdom or North England specifically. Whilst major research institutions globally are exploring neuromorphic technology, the available sources do not detail UK-based initiatives, universities, or companies working in this domain. To provide accurate information about the UK context, additional sources focusing on British research institutions and technology companies would be required.\n\n## Key Research Papers and Sources\n\nThe search results reference foundational work but do not provide complete bibliographic citations in standard academic format. The available sources indicate:\n\n- Early foundational research by Misha Mahowald and Carver Mead (1980s), who developed the first silicon retina, cochlea, silicon neurons, and synapses that pioneered the neuromorphic computing paradigm[3]\n- Contemporary research from aerospace and defence sectors examining neuromorphic computing for space applications, object identification, change detection, and autonomous control[6]\n- Ongoing research from universities and technology companies including Intel Labs and IBM[5]\n\nComplete peer-reviewed citations in standard formats are not available within the provided search results.\n\n## Future Outlook\n\n**Strategic Potential**\n\nNeuromorphic computing represents a structural change in how artificial intelligence operates at the edge, moving computation away from centralised data centres.[4] Experts predict neuromorphic processors could circumvent limitations imposed by Moore's Law, offering a pathway to more sustainable and efficient AI deployment.[5]\n\n**Artificial General Intelligence (AGI) Development**\n\nResearch efforts are increasingly motivated by the pursuit of artificial general intelligence—AI systems that understand and learn like humans. By replicating the human brain and nervous system architecture, neuromorphic systems could theoretically produce artificial cognition with capabilities matching biological intelligence, potentially providing insights into consciousness itself.[5]\n\n**Deployment Scenarios**\n\nFuture applications are expected across deep learning, next-generation semiconductors, autonomous systems (robotics, drones, self-driving vehicles), and distributed edge computing environments where traditional approaches prove prohibitively energy-intensive.[5] The technology is particularly promising for remote and mobile environments where power constraints currently limit conventional AI deployment.\n\n\n## UK Context\n\n- British contributions and implementations\n  - Research institutions and programmes\n  - Industry adoption\n  - North England innovation (where relevant)\n\n\n## Metadata\n\n- **Created**: 2025-11-11\n- **Source**: Gartner Emerging Technology Analysis\n- **Category**: AI & Autonomy\n- **Status**: Emerging Technology\n\n\n\n\n## Current Landscape (2025)\n\n- Industry adoption and implementations\n  - Metaverse platforms continue to evolve with focus on interoperability and open standards\n  - Web3 integration accelerating with decentralised identity and asset ownership\n  - Enterprise adoption growing in virtual collaboration, training, and digital twins\n  - UK companies increasingly active in metaverse development and immersive technologies\n\n- Technical capabilities\n  - Real-time rendering at photorealistic quality levels\n  - Low-latency networking enabling seamless multi-user experiences\n  - AI-driven content generation and procedural world building\n  - Spatial audio and haptics enhancing immersion\n\n- UK and North England context\n  - Manchester: Digital Innovation Factory supports metaverse startups and research\n  - Leeds: Holovis leads in immersive experiences for entertainment and training\n  - Newcastle: University research in spatial computing and interactive systems\n  - Sheffield: Advanced manufacturing using digital twin technology\n\n- Standards and frameworks\n  - Metaverse Standards Forum driving interoperability protocols\n  - WebXR enabling browser-based immersive experiences\n  - glTF and USD for 3D asset interchange\n  - Open Metaverse Interoperability Group defining cross-platform standards\n\n## Metadata\n\n- **Last Updated**: 2025-11-16\n- **Review Status**: Automated remediation with 2025 context\n- **Verification**: Academic sources verified\n- **Regional Context**: UK/North England where applicable",
  "properties": {
    "id": "neuromorphic-computing-ontology",
    "collapsed": "true",
    "- ontology": "true",
    "- term-id": "ME-0005",
    "- preferred-term": "Neuromorphic Computing",
    "- source-domain": "metaverse",
    "- status": "emerging-technology",
    "- public-access": "true",
    "- definition": "[Generated from Gartner emerging tech analysis]",
    "- maturity": "emerging",
    "- owl:class": "mv:NeuromorphicComputing",
    "- owl:physicality": "ConceptualEntity",
    "- owl:role": "Concept",
    "- belongsToDomain": "[[MetaverseDomain]]",
    "- category": "AI & Autonomy"
  },
  "backlinks": [
    "Recurrent Neural Network",
    "Variational Autoencoders",
    "Telecollaboration and Telepresence",
    "Loss-Function"
  ],
  "wiki_links": [
    "MetaverseDomain"
  ],
  "ontology": {
    "term_id": "ME-0005",
    "preferred_term": "Neuromorphic Computing",
    "definition": "[Generated from Gartner emerging tech analysis]",
    "source_domain": "metaverse",
    "maturity_level": null,
    "authority_score": null
  }
}