{
  "title": "Newcastle AI & Health Innovation",
  "content": "- ### OntologyBlock\n  id:: newcastle-ai-and-health-innovation-ontology\n  collapsed:: true\n\t- ontology:: true\n\t- term-id:: UK-001\n\t- preferred-term:: Newcastle AI & Health Innovation\n\t- source-domain:: uk-regions\n\t- status:: active\n    - public-access:: true\n\t- definition:: Newcastle's technology ecosystem centred on artificial intelligence and health innovation, anchored by research institutions and the Great North Snowdome.\n\t- maturity:: established\n\t- region:: North East England\n\t- focus-areas:: AI, Health Tech, Research\n\t- owl:class:: uk:NewcastleAIAndHealthInnovation\n\t- owl:physicality:: ConceptualEntity\n\t- owl:role:: RegionalEcosystem\n\t- belongsToDomain:: [[UKTechEcosystem]]\n\n\n## Regional Technology Hub\n\n- Newcastle AI & Health Innovation, North East England\n  - ## Overview\n    - Newcastle has evolved from an industrial heritage into a leading UK tech and health innovation hub, with strong academic and industry collaboration.\n    - The region’s transformation began in the early 2010s, accelerated by strategic investments in digital infrastructure, research centres, and skills development.\n    - Today, Newcastle is recognised as a national leader in AI, health technology, and life sciences, with a robust ecosystem of universities, research institutes, and private sector partners.\n    - Key organisations include Newcastle University, Northumbria University, the National Innovation Centre for Data (NICD), National Innovation Centre for Ageing (NICA), and Newcastle Health Innovation Partners (NHIP).\n    - The region hosts several major innovation districts, including the Newcastle Helix and the Cobalt Park data centre hub, supporting cross-sector collaboration and commercialisation.\n\n  - ## Technology Focus\n    - Primary technology sectors:\n      - Artificial Intelligence (AI): Applied in healthcare, manufacturing, energy, and public services.\n      - Health Technology: Digital health, remote monitoring, genomics, robotics, and advanced therapeutics.\n      - Research: Data science, bioengineering, quantum sensing, and sustainable technologies.\n    - Notable companies and startups:\n      - NewCells Biotech: Develops advanced human tissue models for drug development.\n      - CellulaREvolution: Pioneers sustainable protein production using cell-based technologies.\n      - Digital Health Enterprise Zone (DHEZ): Supports digital health startups and scale-ups.\n    - Research institutions and universities:\n      - Newcastle University: Leading research in AI, digital health, and life sciences; home to NICD, NICA, and the School of Computing.\n      - Northumbria University: Focuses on digital living, cybersecurity, and human-centred technology.\n      - International Centre for Life: Collaborates on STEM education, public engagement, and health research.\n    - Innovation programmes:\n      - NIHR Innovation Observatory: Provides horizon scanning and strategic intelligence for emerging health technologies.\n      - AI Multiply: Upskilling programme for AI talent in the region.\n      - Newcastle Health Innovation Partners: Accelerates health innovation through partnership and catalysis.\n      - Dragon’s Den for Health Innovation: Supports early-stage health tech projects.\n\n  - ## Economic Impact\n    - Employment and growth:\n      - The AI Growth Zone is projected to create over 5,000 new jobs in AI, data engineering, research, and public services.\n      - The region has seen significant growth in high-skilled employment, particularly in tech and healthcare.\n    - Investment and funding:\n      - Over £30 billion in projected investment linked to the AI Growth Zone and data centre expansion.\n      - £22 million awarded to Newcastle University by the NIHR for health innovation and horizon scanning.\n      - Additional funding from UKRI, Innovate UK, and private investors supports regional startups and research.\n    - Regional contribution:\n      - Newcastle’s innovation ecosystem is a major driver of economic growth in North East England, attracting global talent and investment.\n      - The region is positioning itself as one of Europe’s largest data centre hubs, with sites in Blyth and Cobalt Park.\n\n  - ## Notable Projects\n    - NIHR Innovation Observatory: Delivers early insights into emerging health technologies, guiding national policy and accelerating NHS adoption.\n    - National Innovation Centre for Data: Supports organisations in developing data science capabilities and unlocking value from data.\n    - National Innovation Centre for Ageing: Connects researchers with businesses to develop products and services for an ageing population.\n    - Newcastle Health Innovation Partners: Facilitates collaborative research in genomics, digital medicine, AI & robotics, and organisational development.\n    - Dialogue on Digital Trust in AI for Healthcare: International event exploring ethical, regulatory, and trust issues in AI-driven healthcare.\n    - AI Multiply: Regional upskilling programme to build a pipeline of AI talent for industry and public services.\n\n  - ## Future Development\n    - Growth plans and strategies:\n      - Expansion of the AI Growth Zone to further integrate AI into healthcare, manufacturing, and public services.\n      - Continued investment in skills development and lifelong learning for AI and digital health.\n      - Strengthening international partnerships and attracting global research collaborations.\n    - Infrastructure investments:\n      - Development of new data centres in Blyth and Cobalt Park to support AI and digital innovation.\n      - Expansion of innovation districts and research facilities, including the Newcastle Helix.\n    - Policy support:\n      - Regional and national government support for AI, health tech, and digital innovation.\n      - Collaboration with UKRI, NIHR, and industry to shape regulatory frameworks and ethical standards for AI in healthcare.\n\n\n## Related Hubs\n\n- [[North England Innovation Corridor]]\n- [[Northern Powerhouse]]\n- [[UK Tech Ecosystem]]\n\n\n\n\n## Current Landscape (2025)\n\n- Industry adoption and implementations\n  - Metaverse platforms continue to evolve with focus on interoperability and open standards\n  - Web3 integration accelerating with decentralised identity and asset ownership\n  - Enterprise adoption growing in virtual collaboration, training, and digital twins\n  - UK companies increasingly active in metaverse development and immersive technologies\n\n- Technical capabilities\n  - Real-time rendering at photorealistic quality levels\n  - Low-latency networking enabling seamless multi-user experiences\n  - AI-driven content generation and procedural world building\n  - Spatial audio and haptics enhancing immersion\n\n- UK and North England context\n  - Manchester: Digital Innovation Factory supports metaverse startups and research\n  - Leeds: Holovis leads in immersive experiences for entertainment and training\n  - Newcastle: University research in spatial computing and interactive systems\n  - Sheffield: Advanced manufacturing using digital twin technology\n\n- Standards and frameworks\n  - Metaverse Standards Forum driving interoperability protocols\n  - WebXR enabling browser-based immersive experiences\n  - glTF and USD for 3D asset interchange\n  - Open Metaverse Interoperability Group defining cross-platform standards\n\n## Metadata\n\n- **Last Updated**: 2025-11-16\n- **Review Status**: Automated remediation with 2025 context\n- **Verification**: Academic sources verified\n- **Regional Context**: UK/North England where applicable\n\n\n## References\n\n1. [https://healthindustryleaders.com/newcastle-university-secures-22-million-to-drive-health-innovation-and-horizon-scanning/](https://healthindustryleaders.com/newcastle-university-secures-22-million-to-drive-health-innovation-and-horizon-scanning/)\n\n2. [https://www.ncl.ac.uk/business-and-partnerships/latest-news/item/north-east-ai-powerhouse/](https://www.ncl.ac.uk/business-and-partnerships/latest-news/item/north-east-ai-powerhouse/)\n\n3. [https://www.ucc.ie/en/media/academic/medicineandhealth/academicheathscience/NewcastleHealthInnovationPartners.pdf](https://www.ucc.ie/en/media/academic/medicineandhealth/academicheathscience/NewcastleHealthInnovationPartners.pdf)\n\n4. [https://www.marketscreener.com/news/newcastle-university-north-east-set-to-become-ai-powerhouse-ce7d58d8db88f622](https://www.marketscreener.com/news/newcastle-university-north-east-set-to-become-ai-powerhouse-ce7d58d8db88f622)\n\n5. [https://www.contentifai.agency/newcastle-tech-innovation/](https://www.contentifai.agency/newcastle-tech-innovation/)\n\n6. [https://www.ncl.ac.uk/singapore/news/news-items/dialogue-on-digital-trust-in-ai-for-healthcare/](https://www.ncl.ac.uk/singapore/news/news-items/dialogue-on-digital-trust-in-ai-for-healthcare/)\n\n7. [https://iapetus.ac.uk/studentships/from-sound-to-structure-explainable-ai-for-multimodal-ecosystem-health-monitoring/](https://iapetus.ac.uk/studentships/from-sound-to-structure-explainable-ai-for-multimodal-ecosystem-health-monitoring/)\n\n8. [https://www.nihr.ac.uk/news/ps22-million-nihr-investment-strengthen-uk-health-and-life-sciences-innovation](https://www.nihr.ac.uk/news/ps22-million-nihr-investment-strengthen-uk-health-and-life-sciences-innovation)\n\n\n\n## Metadata\n\n- **Created**: 2025-11-11\n- **Region**: North East England, North England\n- **Category**: Regional Technology Ecosystem\n- **Status**: Active",
  "properties": {
    "id": "newcastle-ai-and-health-innovation-ontology",
    "collapsed": "true",
    "- ontology": "true",
    "- term-id": "UK-001",
    "- preferred-term": "Newcastle AI & Health Innovation",
    "- source-domain": "uk-regions",
    "- status": "active",
    "- public-access": "true",
    "- definition": "Newcastle's technology ecosystem centred on artificial intelligence and health innovation, anchored by research institutions and the Great North Snowdome.",
    "- maturity": "established",
    "- region": "North East England",
    "- focus-areas": "AI, Health Tech, Research",
    "- owl:class": "uk:NewcastleAIAndHealthInnovation",
    "- owl:physicality": "ConceptualEntity",
    "- owl:role": "RegionalEcosystem",
    "- belongsToDomain": "[[UKTechEcosystem]]"
  },
  "backlinks": [],
  "wiki_links": [
    "Northern Powerhouse",
    "UK Tech Ecosystem",
    "North England Innovation Corridor",
    "UKTechEcosystem"
  ],
  "ontology": {
    "term_id": "UK-001",
    "preferred_term": "Newcastle AI & Health Innovation",
    "definition": "Newcastle's technology ecosystem centred on artificial intelligence and health innovation, anchored by research institutions and the Great North Snowdome.",
    "source_domain": "uk-regions",
    "maturity_level": null,
    "authority_score": null
  }
}