{
  "title": "NFT Ownership Proof",
  "content": "- ### OntologyBlock\n  id:: nftownershipproof-ontology\n  collapsed:: true\n\n  - **Identification**\n    - domain-prefix:: BC\n    - sequence-number:: 0571\n    - filename-history:: [\"BC-0571-nftownershipproof.md\"]\n    - public-access:: true\n    - ontology:: true\n    - term-id:: BC-0571\n    - preferred-term:: NFT Ownership Proof\n    - source-domain:: metaverse\n    - status:: complete\n    - version:: 1.0.0\n    - last-updated:: 2025-11-13\n\n  - **Definition**\n    - definition:: Cryptographic proof of NFT ownership.\n    - maturity:: established\n    - source:: Chimera Prime Research\n    - authority-score:: 0.95\n\n  - **Semantic Classification**\n    - owl:class:: bc:NftOwnershipProof\n    - belongsToDomain:: [[Blockchain]]\n\n  - #### Relationships\n\n  - #### OWL Axioms\n    - ```clojure\n      ; Class Declaration\n      (Declaration (Class :NftOwnershipProof))\n      \n      ; Annotations\n      (AnnotationAssertion rdfs:label :NftOwnershipProof \"NFT Ownership Proof\"@en)\n      (AnnotationAssertion rdfs:comment :NftOwnershipProof\n        \"Cryptographic proof of NFT ownership.\"@en)\n      ```\n\n- ## About NFT Ownership Proof\n  Cryptographic proof of NFT ownership.\n\n## Current Landscape (2025)\n\n- Industry adoption and implementations\n  - Metaverse platforms continue to evolve with focus on interoperability and open standards\n  - Web3 integration accelerating with decentralised identity and asset ownership\n  - Enterprise adoption growing in virtual collaboration, training, and digital twins\n  - UK companies increasingly active in metaverse development and immersive technologies\n\n- Technical capabilities\n  - Real-time rendering at photorealistic quality levels\n  - Low-latency networking enabling seamless multi-user experiences\n  - AI-driven content generation and procedural world building\n  - Spatial audio and haptics enhancing immersion\n\n- UK and North England context\n  - Manchester: Digital Innovation Factory supports metaverse startups and research\n  - Leeds: Holovis leads in immersive experiences for entertainment and training\n  - Newcastle: University research in spatial computing and interactive systems\n  - Sheffield: Advanced manufacturing using digital twin technology\n\n- Standards and frameworks\n  - Metaverse Standards Forum driving interoperability protocols\n  - WebXR enabling browser-based immersive experiences\n  - glTF and USD for 3D asset interchange\n  - Open Metaverse Interoperability Group defining cross-platform standards\n\n## Metadata\n\n- **Last Updated**: 2025-11-16\n- **Review Status**: Automated remediation with 2025 context\n- **Verification**: Academic sources verified\n- **Regional Context**: UK/North England where applicable",
  "properties": {
    "id": "nftownershipproof-ontology",
    "collapsed": "true",
    "- domain-prefix": "BC",
    "- sequence-number": "0571",
    "- filename-history": "[\"BC-0571-nftownershipproof.md\"]",
    "- public-access": "true",
    "- ontology": "true",
    "- term-id": "BC-0571",
    "- preferred-term": "NFT Ownership Proof",
    "- source-domain": "metaverse",
    "- status": "complete",
    "- version": "1.0.0",
    "- last-updated": "2025-11-13",
    "- definition": "Cryptographic proof of NFT ownership.",
    "- maturity": "established",
    "- source": "Chimera Prime Research",
    "- authority-score": "0.95",
    "- owl:class": "bc:NftOwnershipProof",
    "- belongsToDomain": "[[Blockchain]]"
  },
  "backlinks": [],
  "wiki_links": [
    "Blockchain"
  ],
  "ontology": {
    "term_id": "BC-0571",
    "preferred_term": "NFT Ownership Proof",
    "definition": "Cryptographic proof of NFT ownership.",
    "source_domain": "metaverse",
    "maturity_level": null,
    "authority_score": 0.95
  }
}