{
  "title": "Node (BC-0072)",
  "content": "- ### OntologyBlock\n  id:: node-(bc-0072)-ontology\n  collapsed:: true\n\t- ontology:: true\n\t- term-id:: mv-83431247778\n\t- preferred-term:: Node (BC-0072)\n\t- source-domain:: metaverse\n\t- status:: active\n\t- public-access:: true\n\t- definition:: A component of the metaverse ecosystem focusing on node (bc-0072).\n\t- maturity:: mature\n\t- authority-score:: 0.85\n\t- owl:class:: mv:NodeBc0072\n\t- owl:physicality:: ConceptualEntity\n\t- owl:role:: Concept\n\t- belongsToDomain:: [[MetaverseDomain]]\n\t- #### Relationships\n\t  id:: node-(bc-0072)-relationships\n\t\t- enables:: [[ImmersiveExperience]], [[Presence]], [[SpatialComputing]]\n\t\t- requires:: [[DisplayTechnology]], [[TrackingSystem]], [[RenderingEngine]]\n\t\t- bridges-to:: [[HumanComputerInteraction]], [[ComputerVision]], [[Robotics]]\n\n\t- #### OWL Axioms\n\t  id:: node-(bc-0072)-owl-axioms\n\t  collapsed:: true\n\t\t- ```clojure\n\t\t  Declaration(Class(mv:NodeBc0072))\n\n\t\t  # Classification\n\t\t  SubClassOf(mv:NodeBc0072 mv:ConceptualEntity)\n\t\t  SubClassOf(mv:NodeBc0072 mv:Concept)\n\n\t\t  # Domain classification\n\t\t  SubClassOf(mv:NodeBc0072\n\t\t    ObjectSomeValuesFrom(mv:belongsToDomain mv:MetaverseDomain)\n\t\t  )\n\n\t\t  # Annotations\n\t\t  AnnotationAssertion(rdfs:label mv:NodeBc0072 \"Node (BC-0072)\"@en)\n\t\t  AnnotationAssertion(rdfs:comment mv:NodeBc0072 \"A component of the metaverse ecosystem focusing on node (bc-0072).\"@en)\n\t\t  AnnotationAssertion(dcterms:identifier mv:NodeBc0072 \"mv-83431247778\"^^xsd:string)\n\t\t  ```\n\n# Node (BC-0072)\n\n## OntologyBlock\nid:: node-ontology\ncollapsed:: true\n\n### Identification\n\n- domain-prefix:: BC\n- sequence-number:: 0072\n- filename-history:: [\"BC-0072-node.md\"]\n- ontology:: true\n- term-id:: BC-0072\n- preferred-term:: Node\n- source-domain:: blockchain\n- status:: complete\n- public-access:: true\n- version:: 1.1.0\n- last-updated:: 2025-11-13\n\n### Definition\n\n- definition:: Network participant computer within blockchain systems, providing essential functionality for distributed ledger technology operations and properties.\n- maturity:: mature\n- source:: [[ISO/IEC 23257:2021]], [[IEEE 2418.1]], [[NIST NISTIR 8202]]\n- authority-score:: 0.95\n\n### Semantic Classification\n\n- owl:class:: bc:Node\n- owl:physicality:: VirtualEntity\n- owl:role:: Object\n- owl:inferred-class:: bc:VirtualObject\n- belongsToDomain:: [[CryptographicDomain]]\n- implementedInLayer:: [[SecurityLayer]], [[NetworkLayer]]\n\n### Relationships\nid:: node-relationships\n\n- is-subclass-of:: [[Blockchain Entity]], [[NetworkComponent]], [[Distributed System]]\n- related-to:: [[Full Node]], [[Light Node]], [[Validator Node]], [[Mining Node]], [[Lightning Node]]\n- enables:: [[Consensus]], [[Transaction Validation]], [[Block Propagation]], [[Network Decentralization]]\n\n### OWL Axioms\nid:: node-owl-axioms\ncollapsed:: true\n\n```clojure\nPrefix(:=<http://metaverse-ontology.org/blockchain#>)\nPrefix(owl:=<http://www.w3.org/2002/07/owl#>)\nPrefix(rdf:=<http://www.w3.org/1999/02/22-rdf-syntax-ns#>)\nPrefix(xml:=<http://www.w3.org/XML/1998/namespace>)\nPrefix(xsd:=<http://www.w3.org/2001/XMLSchema#>)\nPrefix(rdfs:=<http://www.w3.org/2000/01/rdf-schema#>)\nPrefix(dct:=<http://purl.org/dc/terms/>)\n\nOntology(<http://metaverse-ontology.org/blockchain/BC-0072>\n  Import(<http://metaverse-ontology.org/blockchain/core>)\n\n  ## Class Declaration\n  Declaration(Class(:Node))\n\n  ## Subclass Relationships\n  SubClassOf(:Node :NetworkComponent)\n  SubClassOf(:Node :BlockchainEntity)\n  SubClassOf(:Node :DistributedSystemComponent)\n\n  ## Essential Properties\n  SubClassOf(:Node\n    (ObjectSomeValuesFrom :partOf :Blockchain))\n\n  SubClassOf(:Node\n    (ObjectSomeValuesFrom :hasProperty :Property))\n\n  SubClassOf(:Node\n    (ObjectSomeValuesFrom :validates :Transaction))\n\n  SubClassOf(:Node\n    (ObjectSomeValuesFrom :maintains :DistributedLedger))\n\n  ## Data Properties\n  DataPropertyAssertion(:hasIdentifier :Node \"BC-0072\"^^xsd:string)\n  DataPropertyAssertion(:hasAuthorityScore :Node \"0.95\"^^xsd:decimal)\n  DataPropertyAssertion(:isFoundational :Node \"true\"^^xsd:boolean)\n\n  ## Object Properties\n  ObjectPropertyAssertion(:enablesFeature :Node :DecentralizedConsensus)\n  ObjectPropertyAssertion(:enablesFeature :Node :TransactionValidation)\n  ObjectPropertyAssertion(:enablesFeature :Node :BlockPropagation)\n  ObjectPropertyAssertion(:relatesTo :Node :NetworkTopology)\n\n  ## Annotations\n  AnnotationAssertion(rdfs:label :Node \"Node\"@en)\n  AnnotationAssertion(rdfs:comment :Node\n    \"Network participant computer in blockchain systems\"@en)\n  AnnotationAssertion(dct:description :Node\n    \"Foundational blockchain concept with formal ontological definition\"@en)\n  AnnotationAssertion(:termID :Node \"BC-0072\")\n  AnnotationAssertion(:priority :Node \"1\"^^xsd:integer)\n  AnnotationAssertion(:category :Node \"network-infrastructure\"@en)\n)\n```\n\n## About Node\nid:: node-about\n\nA **node** is a network participant computer within [[blockchain]] systems, providing essential functionality for [[distributed ledger]] technology operations. Nodes form the backbone of blockchain networks, enabling [[decentralization]], [[consensus]], and [[trust minimization]] through distributed validation and storage of transaction history.\n\n### Key Characteristics [Updated 2025]\nid:: node-characteristics\n\n1. **Definitional Property**: Independent computer running blockchain protocol software, maintaining full or partial copy of distributed ledger\n2. **Functional Property**: Validates [[transactions]], propagates [[blocks]], enforces [[consensus rules]], and serves network requests\n3. **Structural Property**: Connected to peer nodes via [[peer-to-peer network]], forming decentralized network topology\n4. **Security Property**: Provides [[Byzantine fault tolerance]] through distributed validation, protecting against malicious actors and single points of failure\n5. **Performance Property**: Resource requirements vary by node type - [[full nodes]] require substantial storage (600+ GB for Bitcoin, 1+ TB for Ethereum), whilst [[light nodes]] minimize resource usage through [[SPV]] (Simplified Payment Verification)\n\n### Node Types [Updated 2025]\nid:: node-types\n\n#### Full Nodes\n- **Definition**: Nodes maintaining complete copy of blockchain history and independently validating all transactions and blocks\n- **Requirements**: Significant storage (Bitcoin: ~600 GB, Ethereum: ~1-2 TB), bandwidth, and computational resources\n- **Function**: Enforce [[consensus rules]], validate transactions, serve data to light clients, strengthen network [[decentralization]]\n- **Examples**: [[Bitcoin Core]], [[Geth]] (Ethereum), [[Nethermind]] (Ethereum)\n\n#### Light Nodes / SPV Nodes\n- **Definition**: Nodes storing only [[block headers]] and verifying transactions through [[Merkle proofs]] without full blockchain download\n- **Requirements**: Minimal storage (~few hundred MB), reduced bandwidth\n- **Function**: Enable resource-constrained devices (mobile phones) to interact with blockchain whilst trusting full nodes for validation\n- **Security Trade-off**: Reduced security guarantees compared to full nodes, vulnerable to attacks if majority of connected full nodes are malicious\n\n#### Validator Nodes / Mining Nodes\n- **Definition**: Nodes authorized to propose new blocks and participate in [[consensus mechanism]]\n- **Proof-of-Work**: [[Mining nodes]] solve cryptographic puzzles to propose blocks (Bitcoin, pre-merge Ethereum)\n- **Proof-of-Stake**: [[Validator nodes]] stake cryptocurrency and are selected to propose/attest blocks (post-merge Ethereum, Cardano, Polkadot)\n- **Requirements**: Mining (specialized [[ASIC]] hardware, substantial electricity), Staking (capital requirement - Ethereum requires 32 ETH)\n\n#### Archive Nodes\n- **Definition**: Full nodes storing complete historical state data (all account balances, smart contract storage at every block height)\n- **Requirements**: Massive storage (Ethereum archive node: 10+ TB)\n- **Function**: Support blockchain explorers, analytics platforms, historical queries\n- **Users**: Block explorers (Etherscan), analytics firms, institutional infrastructure providers\n\n### Technical Components [Updated 2025]\nid:: node-components\n\n- **Implementation**: Blockchain protocol software (Bitcoin Core, Geth, Lighthouse, Prysm) implementing [[consensus algorithms]], [[networking protocols]] (libp2p, DevP2P), and [[cryptographic verification]]\n- **Verification**: [[Digital signature]] validation, [[Merkle tree]] verification, [[consensus rule]] enforcement, [[block propagation]] validation\n- **Interaction**: [[Peer-to-peer networking]] via gossip protocols, [[RPC]] (Remote Procedure Call) interfaces for application access, [[API]] endpoints for developer tools\n- **Constraints**: Bandwidth requirements (constant block/transaction propagation), storage growth (blockchain size increases continuously), synchronization time (initial sync can take days for full nodes)\n\n### Use Cases\nid:: node-use-cases\n\n#### 1. Network Decentralization and Censorship Resistance\n- **Application**: Running full nodes distributes blockchain validation across independent operators, preventing centralized control\n- **Example**: Bitcoin's ~15,000 publicly-reachable full nodes globally ensure no single entity controls transaction validation\n- **Requirements**: Internet connectivity, compatible hardware, blockchain protocol software\n- **Benefits**: [[Trust minimization]], [[censorship resistance]], [[sovereignty]] (verify your own transactions without relying on third parties)\n\n#### 2. Lightning Network Payment Infrastructure\n- **Application**: [[Lightning nodes]] enable instant, low-fee Bitcoin payments through payment channels\n- **Example**: ~30,000 Raspberry Pi Lightning nodes democratized access to Bitcoin Layer 2 infrastructure\n- **Requirements**: Bitcoin full node (backend), Lightning implementation (LND, Core Lightning, Eclair), channel liquidity\n- **Benefits**: Instant settlement, micropayment capability, scalability (millions of off-chain transactions)\n\n#### 3. Institutional Validator Services\n- **Application**: Staking-as-a-service providers operate validator nodes for institutional clients\n- **Example**: Blockdaemon manages 100,000+ nodes across 50+ blockchains for 300+ financial institutions\n- **Requirements**: Enterprise-grade infrastructure, [[slashing]] protection, compliance reporting, institutional SLAs\n- **Benefits**: Staking yield generation, network participation without operational burden\n\n## 2024-2025: Node Infrastructure Evolution [Updated 2025]\nid:: node-recent-developments\n\nThe blockchain node ecosystem experienced significant maturation from 2024 through 2025, with focus shifting from pure decentralization metrics to practical operational infrastructure supporting [[Lightning Network]] payments, [[L402]] micropayments for AI services, and integrated identity systems.\n\n### Bitcoin Node Landscape [Updated 2025]\n\nThe [[Bitcoin]] network maintained approximately **15,000 publicly-reachable nodes** distributed globally, representing a triumvirate of economic actors:\n\n1. **Holders and Users**: Traders, speculators, [[arbitrageurs]], market makers, and increasingly \"circular economy\" participants earning and spending BTC\n2. **Miners**: Secure the network through [[Proof of Work]] validation, profit from [[block rewards]] and [[transaction fees]]\n3. **Node Operators**: Enforce [[consensus rules]] that miners must follow, optimize [[trust minimization]], protect network from protocol changes that might undermine security or usability\n\nSince IT engineer Stadicus released the [RaspiBolt guide](https://raspibolt.org/backstory.html) in 2017, small-scale Bitcoin and Lightning node operators proliferated. Around **30,000 Raspberry Pi Lightning nodes** (which are also by definition Bitcoin nodes) ran open-source distributions including:\n- [[RaspiBlitz]]\n- [[Umbrel]]\n- [[MyNode]]\n- [[RaspiBolt]]\n- [[Start9 Embassy]]\n\n**Reference**: [Bitcoin Nodes Global Distribution](https://bitnodes.io/) - Real-time network statistics showing ~15,000 reachable nodes as of 2025.\n\n### Lightning Network Infrastructure [Updated 2025]\n\nLightning node management software matured substantially, with tools like **[[Torq]]** providing workflow automation for large Lightning Network nodes, enabling institutional-grade operations.\n\n**[[L402]]** emerged as a critical innovation: a Lightning-native reverse proxy standard enabling micropayment-gated API access, particularly relevant for AI services requiring per-query payment without traditional subscription models. This infrastructure positioned Lightning as the native payment rail for machine-to-machine commerce.\n\n**Key Resources**:\n- [Torq Node Management Software](https://github.com/lncapital/torq) - Workflow automation for large Lightning nodes\n- [L402 Documentation](https://docs.lightning.engineering/the-lightning-network/l402) - Lightning reverse proxy protocol specification\n- [ln-vortex](https://github.com/ln-vortex/ln-vortex) - Lightning and Taproot enabled collaborative transactions\n- [LNbits Setup Guide](https://www.massmux.com/howto-complete-lightningtipbot-lnbits-setup-vps/) - Lightning wallet and tipping infrastructure\n\n### Bitcoin-Dollar Interoperability [Updated 2025]\n\n**[[Stablesats]]** and similar technologies introduced algorithmic dollar-stable value using exclusively Lightning Bitcoin, providing price stability without centralized stablecoin issuers. More significantly, Strike's opening of public Lightning network access enabled individuals with self-hosted wallets or nodes to pay directly for goods across America, with instant settlement in dollars using Bitcoin at zero cost.\n\nThis bridged the Lightning network with dollar-denominated commerce, creating unprecedented interoperability between cryptocurrency infrastructure and traditional payments. For metaverse and digital commerce applications, this enabled direct Lightning payment integration for goods and services denominated in fiat currencies.\n\n**Key Innovation**: [Stablesats](https://stablesats.com/) - Algorithmic dollar stability using exclusively Lightning Bitcoin, without centralized stablecoin reliance.\n\n**Economic Analysis**: The [Cleveland Federal Reserve](https://www.clevelandfed.org/en/publications/working-paper/2022/wp-2219-the-lightning-network-turning-bitcoin-into-money) published analysis confirming Lightning Network's potential to transform Bitcoin from speculative asset to functional money, validating technical infrastructure developments with academic economic analysis.\n\nBy late 2025, node operation transitioned from ideological hobby to practical infrastructure requirement for individuals and businesses seeking financial [[sovereignty]] and censorship-resistant commerce capabilities.\n\n### Distributed Identity and Data [Updated 2025]\n\nEmerging protocols integrated with Bitcoin's node infrastructure:\n\n- **[[Nostr]]**: Decentralized identity and messaging protocol layering on Bitcoin infrastructure, providing censorship-resistant social networking and communications\n- **SOLID-lite Data Pods**: Private data storage with cryptographic access control, enabling self-sovereign data management\n- **Integration**: These systems layered on top of Bitcoin's settlement layer, creating full-stack decentralized internet infrastructure where nodes served financial settlement, identity verification, communication relay, and data storage - a vision of truly peer-to-peer digital infrastructure\n\nThis convergence transformed nodes from single-purpose blockchain validators into multi-function infrastructure supporting identity, payments, communications, and data storage in decentralized application ecosystems.\n\n## Institutional Node Infrastructure and the Centralization Paradox [Updated 2025]\nid:: node-centralization\n\nWhilst retail Bitcoin node operators democratized network participation through Raspberry Pi deployments, the broader multi-chain blockchain ecosystem witnessed **dramatic consolidation** of node infrastructure into institutional providers servicing hundreds of thousands of developers and applications.\n\n### Dominant Institutional Providers [Updated 2025]\n\n#### Alchemy\n- **Position**: Preeminent blockchain infrastructure provider supporting Ethereum, Polygon, Solana, Arbitrum, Optimism, and 15+ chains\n- **Scale**: Over **500,000 developers**, estimated **70-80% of Ethereum dApp traffic** routing through Alchemy infrastructure\n- **Clients**: OpenSea, Axie Infinity, major DeFi protocols and NFT marketplaces\n- **Features**: Robust [[RPC]] APIs, 99.9% uptime SLAs, enhanced developer experience, enterprise-grade reliability\n\n#### Infura\n- **Parent**: ConsenSys subsidiary\n- **Position**: Second-largest [[EVM]]-compatible blockchain infrastructure provider\n- **Scale**: Over **400,000 developers** registered by 2025\n- **Critical Integration**: Powers [[MetaMask]] (30+ million monthly active users), creating potential single point of failure\n- **Outage Impact**: Infura outages (March 2020, November 2020, January 2023) caused widespread Ethereum ecosystem disruptions\n- **Chains**: Ethereum, Polygon, Arbitrum, Optimism, other EVM chains\n\n#### Blockdaemon\n- **Focus**: Institutional-grade blockchain infrastructure and validator-as-a-service\n- **Scale**: **100,000+ nodes** across 50+ blockchain networks, trusted by **300+ financial institutions**\n- **Clients**: Deutsche Bank, BNY Mellon, Citi\n- **Services**: Dedicated infrastructure, compliance reporting, institutional SLAs, multi-chain support\n\n#### InfStones\n- **Specialization**: Institutional staking infrastructure\n- **Scale**: Managing over **$10 billion** in staked assets across Ethereum, Solana, Polkadot, Cosmos, and 30+ proof-of-stake networks\n- **Services**: White-label staking enabling exchanges (Crypto.com, OKX) to offer staking yields without operating validator infrastructure\n\n#### Figment\n- **Position**: Advanced staking provider supporting **40+ blockchain networks**\n- **Scale**: Managing over **$15 billion** in staked assets\n- **Compliance**: SOC 2 Type II audits, GDPR compliance\n- **Clients**: Asset managers, hedge funds, crypto-native companies requiring regulated staking infrastructure\n\n### Centralization Concerns [Updated 2025]\n\nThe consolidation of node infrastructure into handful of institutional providers created **fundamental tensions** with blockchain's [[decentralization]] ethos:\n\n#### RPC Centralization\nDespite Ethereum's **400,000+ validator nodes** (post-Merge) creating robust consensus decentralization, the vast majority of users and applications accessed the network through **centralized RPC providers** (Alchemy, Infura, QuickNode). This created a **centralization paradox**:\n- **Consensus Layer**: Highly decentralized (400,000+ validators)\n- **Access Layer**: Highly centralized (3-4 dominant providers)\n- **Risk**: RPC providers could theoretically filter transactions, censor addresses, deny service to specific applications\n\n#### Validator Centralization Risks\nInstitutional staking providers (Coinbase, Figment, InfStones, Blockdaemon) controlling **30-40% of total staked assets** across multiple networks created **single-entity risks**:\n- Technical failure affecting major provider impacts significant portion of network validation\n- Regulatory pressure (government censorship orders) could affect multiple networks simultaneously\n- Coordination risks if major providers act in concert\n\n#### Geographic Concentration\nMajor node providers operated data centers predominantly in **United States and Europe** (AWS, Google Cloud, Microsoft Azure regions):\n- **50-60% of blockchain validator nodes** ran in U.S.-controlled cloud infrastructure by 2025\n- **Jurisdictional Risk**: U.S. regulatory actions could affect majority of validation infrastructure simultaneously\n- **Geographic Diversity**: Insufficient node distribution across jurisdictions undermines censorship resistance\n\n#### Cloud Infrastructure Dependency [Updated 2025]\n\nEstimated Ethereum validator distribution by infrastructure provider:\n- **60-70%** on Amazon Web Services (AWS)\n- **15-20%** on Google Cloud\n- **5-10%** on Microsoft Azure\n- **10-15%** on dedicated/bare-metal servers\n\n**Catastrophic Failure Scenarios**: AWS outages (December 2021, December 2022) caused widespread blockchain network disruptions. Despite consensus layer remaining operational, users and applications couldn't access networks due to infrastructure-layer failures.\n\n**Reference**: Nakamoto Coefficient analysis and infrastructure diversity metrics tracked by blockchain analytics firms.\n\n### Regulatory Compliance and Censorship Risks [Updated 2025]\n\n#### Tornado Cash Sanctions (August 2022)\n\nThe U.S. Office of Foreign Assets Control ([[OFAC]]) sanctions on [[Tornado Cash]] exposed infrastructure-layer censorship vulnerabilities:\n- Major RPC providers (Alchemy, Infura, QuickNode) **blocked transactions** interacting with Tornado Cash smart contracts\n- Demonstrated that centralized infrastructure created de facto censorship capability even on ostensibly censorship-resistant blockchains\n- Highlighted gap between protocol-level censorship resistance and infrastructure-level access control\n\n#### MEV-Boost and Block Building Centralization [Updated 2025]\n\nBy 2024-2025, over **90% of Ethereum blocks** were built by small number of specialized block builders rather than validators directly:\n- **Block Builders**: Flashbots, BloXroute, Eden Network\n- **Issue**: Transaction ordering centralization and potential censorship points\n- **Post-Tornado Cash**: Some block builders implemented **OFAC compliance filtering**, excluding sanctioned addresses from blocks\n- **Market Bifurcation**: Created two-tier block building market (censoring vs. censorship-resistant builders)\n\n**MEV-Boost Relay**: Middleware infrastructure connecting validators to block builders, introducing additional centralization vector and potential censorship enforcement point.\n\n### Self-Hosted Node Renaissance and Solutions [Updated 2025]\n\nAwareness of infrastructure centralization risks catalyzed **self-hosted node movement** through 2024-2025:\n\n#### Home Staking Initiatives\n- **Ethereum Foundation** promoted **home staking** as \"decentralization ideal\"\n- **Growth**: Estimated **15-20% of Ethereum validators** ran on home hardware by 2025, up from **10-12% in 2022**\n- **Hardware**: NUC systems, custom builds, Raspberry Pi 4+ with external SSD\n- **Benefits**: Geographic diversity, jurisdictional diversity, censorship resistance\n\n#### Node-in-a-Box Products\nPlug-and-play node solutions reduced technical barriers for self-hosting:\n- **[[DAppNode]]**: Full-featured node platform supporting multiple blockchains\n- **[[Avado]]**: Hardware node appliances with user-friendly interfaces\n- **[[RaspiBlitz]]**: Bitcoin and Lightning node distribution for Raspberry Pi\n- **[[Umbrel]]**: Simplified Bitcoin/Lightning node with app ecosystem\n- **[[Start9 Embassy]]**: Sovereignty-focused node platform\n\nThese products integrated Bitcoin full nodes, Lightning nodes, Ethereum validators, and [[IPFS]] nodes into unified interfaces, enabling non-technical users to operate infrastructure with minimal configuration.\n\n#### Decentralized RPC Alternatives [Updated 2025]\n\nProtocols emerged as alternatives to centralized RPC providers:\n- **[[Pocket Network]]**: Decentralized RPC marketplace with **70,000+ distributed nodes** supporting **60+ blockchains** by 2025, though representing <5% of total RPC traffic compared to Alchemy/Infura\n- **[[Ankr]]**: Decentralized node infrastructure with distributed endpoints\n- **[[The Graph]]**: Decentralized indexing protocol for blockchain data queries\n- **Economic Model**: Token rewards incentivize distributed node operators to provide RPC services\n\n#### Client Diversity Improvements [Updated 2025]\n\nEthereum's push for **client diversity** aimed to reduce single-implementation risks:\n- **2021**: Geth dominated with **70-75%** of nodes\n- **2025**: Geth reduced to **45-50%** dominance\n- **Target**: <33% per-client threshold to prevent consensus bugs affecting network\n- **Alternative Clients**: [[Nethermind]], [[Besu]], [[Erigon]], [[Reth]] gaining adoption\n\n**Rationale**: Multiple independent implementations ensure bugs in one client don't affect supermajority of network, preventing consensus failures.\n\n### Future Trajectory: Decentralization Resurgence or Permanent Centralization? [Updated 2025]\n\nBy mid-2025, blockchain node infrastructure existed in a **bifurcated state**:\n- **Bitcoin**: Relatively robust node decentralization (15,000+ public nodes, 30,000+ Lightning nodes operated by individuals)\n- **Multi-chain Ecosystems**: [[Consensus decentralization]] (many independent validators) but **infrastructure centralization** (majority of access mediated by handful of institutional providers)\n\n#### Potential Trajectories\n\n1. **Permanent Infrastructure Centralization**\n   - Developer convenience and institutional reliability requirements entrench Alchemy/Infura/Blockdaemon oligopoly\n   - Decentralized consensus layers masked by centralized access layers\n   - **\"Decentralization Theatre\"**: Networks theoretically censorship-resistant but practically vulnerable to infrastructure-layer control\n\n2. **Decentralized Infrastructure Maturation**\n   - Protocols like Pocket Network, Ankr, client-side light clients ([[EIP-4844]] enabling trustless light clients) mature to provide comparable performance/reliability\n   - Market share gradually redistributes to distributed operators\n   - Reduced single-entity risks through genuine infrastructure decentralization\n\n3. **Regulatory Forcing Function**\n   - Government intervention targeting major providers (subpoenas for transaction data, mandatory censorship, service bans)\n   - Creates **regulatory necessity** for decentralized alternatives\n   - Accelerates adoption of self-hosted and distributed infrastructure solutions\n\nThe 2024-2025 period crystallized blockchain node infrastructure's **fundamental tension**: technical decentralization without infrastructure decentralization created systems that were **theoretically censorship-resistant** yet **practically vulnerable** to centralized control points - a tension likely to define security and resilience debates for the remainder of the decade.\n\n## Decentralized Privacy Networks: Veilid [Updated 2025]\nid:: node-veilid\n\n### Overview\n\n**[[Veilid]]** is an open-source, mobile-first, networked application framework for building decentralized applications with networking, distributed data storage, and built-in IP privacy without reliance on external services.\n\n### Technical Architecture\n\n- **Platforms**: Runs on Linux, Mac, Windows, Android, iOS, and in browsers via [[WebAssembly]] (WASM). Bindings available in Rust, Dart, and other languages.\n- **Protocols**: Supports UDP, TCP, [[WebSockets]]. DNS only used briefly during bootstrap to minimize metadata leakage.\n- **Encryption**: Uses [[Ed25519]] (public-key cryptography), [[XChaCha20]] (symmetric encryption), [[BLAKE3]] (cryptographic hashing) for end-to-end encryption and authentication.\n- **Storage**: [[Distributed hash table]] (DHT) for data records close to node keys. Popular data replicated across multiple nodes for availability.\n- **Routing**: Nodes help each other connect. Routing based on node IDs. Private routing over encrypted hops to provide IP address privacy.\n\n### Goals and Features\n\n- **Decentralization**: Enable decentralized apps without reliance on centralized corporate systems (cloud providers, centralized servers)\n- **Privacy**: IP address privacy through encrypted multi-hop routing (similar to [[Tor]] but optimized for mobile)\n- **Censorship Resistance**: Distributed architecture prevents single points of failure or censorship\n- **Cross-Platform**: Unified framework working across desktop, mobile, and web environments\n\nKey features include strong cryptography, ability to run on variety of platforms, distributed and replicated data storage, and private routing to provide IP privacy. The decentralized design aims to avoid issues with centralized and corporate controlled systems.\n\n**Relevance to Blockchain Nodes**: Veilid demonstrates evolution of node-based decentralized networking beyond blockchain consensus, applying distributed node architecture to privacy-preserving communications and data storage.\n\n## Standards & References [Updated 2025]\nid:: node-standards\n\n### International Standards\n\n- **[[ISO/IEC 23257:2021]]**: Blockchain and distributed ledger technologies - Reference architecture\n- **[[IEEE 2418.1]]**: Standard for the Framework of Blockchain Use in Internet of Things (IoT)\n- **[[NIST NISTIR 8202]]**: Blockchain Technology Overview - U.S. National Institute of Standards and Technology\n\n### Academic Literature\n\n#### Foundational Data Structures\n- Cormen, T. H., Leiserson, C. E., Rivest, R. L., & Stein, C. (2009). *Introduction to Algorithms* (3rd ed.). MIT Press. DOI: 10.5555/1614191. Comprehensive treatment of node-based data structures including linked lists, trees, and graphs.\n- Knuth, D. E. (1997). *The Art of Computer Programming, Volume 1: Fundamental Algorithms* (3rd ed.). Addison-Wesley. Seminal work establishing node theory in algorithmic contexts.\n\n#### Distributed Systems and Networking\n- Tanenbaum, A. S., & Van Steen, M. (2017). *Distributed Systems: Principles and Paradigms* (3rd ed.). Pearson. Authoritative reference on node behaviour in distributed architectures, consensus mechanisms, and fault tolerance.\n- Kurose, J. F., & Ross, K. W. (2020). *Computer Networking* (8th ed.). Pearson. Detailed examination of network nodes and communication protocols.\n\n#### Blockchain and Cryptocurrency\n- Nakamoto, S. (2008). \"Bitcoin: A Peer-to-Peer Electronic Cash System.\" Bitcoin.org. Foundational whitepaper establishing decentralized node-based consensus and transaction validation.\n- Buterin, V. (2014). \"Ethereum: A Next-Generation Smart Contract and Decentralized Application Platform.\" Ethereum.org. Extended blockchain node functionality to support Turing-complete smart contracts.\n- Poon, J., & Dryja, T. (2016). \"The Bitcoin Lightning Network: Scalable Off-Chain Instant Payments.\" Lightning.network. Introduced [[Layer 2]] payment channel nodes enabling instant Bitcoin transactions.\n\n#### Cloud Computing and Infrastructure\n- Armbrust, M., Fox, A., Griffith, R., et al. (2010). \"A View of Cloud Computing.\" *Communications of the ACM*, 53(4), 50–58. DOI: 10.1145/1721654.1721672. Establishes foundational cloud computing concepts including node virtualization.\n\n### Online Resources [Updated 2025]\n\n#### Educational Resources\n1. Fiveable. \"Node (AP Computer Science Principles).\" Accessed November 2025. [https://fiveable.me/key-terms/ap-comp-sci-p/node](https://fiveable.me/key-terms/ap-comp-sci-p/node)\n2. Codecademy. \"Understanding Nodes in Data Structures.\" Accessed November 2025. [https://www.codecademy.com/article/nodes-data-structures-and-algorithms](https://www.codecademy.com/article/nodes-data-structures-and-algorithms)\n3. SnapLogic. \"What is a Node? — Explanation & Overview.\" Accessed November 2025. [https://www.snaplogic.com/glossary/what-is-a-node](https://www.snaplogic.com/glossary/what-is-a-node)\n\n#### Technical References\n4. Tech Monitor. \"What is a node?\" Accessed November 2025. [https://www.techmonitor.ai/what-is/what-is-a-node/](https://www.techmonitor.ai/what-is/what-is-a-node/)\n5. Gigabyte Global. \"What Is Node and How Does It Work?\" Accessed November 2025. [https://www.gigabyte.com/Glossary/node](https://www.gigabyte.com/Glossary/node)\n6. GeeksforGeeks. \"Types of Node Devices in a Computer Network: End Devices and Intermediary Devices.\" Last updated 23 July 2025. [https://www.geeksforgeeks.org/computer-networks/types-of-node-devices-in-a-computer-network-end-devices-and-intermediary-devices/](https://www.geeksforgeeks.org/computer-networks/types-of-node-devices-in-a-computer-network-end-devices-and-intermediary-devices/)\n\n#### Industry Standards\n7. Cloud Native Computing Foundation. \"Nodes.\" Cloud Native Glossary. Accessed November 2025. [https://glossary.cncf.io/nodes/](https://glossary.cncf.io/nodes/)\n8. Speed Commerce. \"What Is Node? Node Definition & Meaning.\" Accessed November 2025. [https://www.speedcommerce.com/what-is/node/](https://www.speedcommerce.com/what-is/node/)\n\n### Research Priorities [Updated 2025]\n\n- **Ongoing Research Directions**:\n  - Edge computing optimization and latency reduction in geographically distributed node clusters\n  - Quantum computing implications for node-based computational models and cryptographic security\n  - Energy efficiency in large-scale node deployments, particularly relevant for UK sustainability targets and net-zero commitments\n  - Cross-chain interoperability protocols enabling nodes to validate transactions across multiple blockchain networks\n  - MEV (Maximal Extractable Value) mitigation through decentralized block building and proposer-builder separation\n\n- **Anticipated Challenges**:\n  - Network latency and bandwidth constraints in ultra-large-scale distributed systems remain persistent engineering challenges\n  - Security vulnerabilities in heterogeneous node environments require ongoing attention, particularly for critical infrastructure\n  - Standardization across competing cloud platforms and node implementations remains incomplete\n  - Skills gap in distributed systems engineering threatens effective node deployment and management\n  - Client diversity and avoiding monoculture risks in consensus-critical systems\n\n- **Priority Areas**:\n  - Developing more efficient consensus mechanisms for multi-node coordination\n  - Improving observability and debugging tools for complex distributed node systems\n  - Establishing robust frameworks for node failure prediction and prevention\n  - Advancing energy-efficient node architectures aligned with UK climate commitments\n  - Enhancing geographic and jurisdictional diversity in validator node distribution\n\n## UK Context [Updated 2025]\nid:: node-uk-context\n\n### British Contributions to Distributed Systems Research\n\n- **University of Cambridge**: Leading research programmes in distributed algorithms, fault-tolerant systems, and Byzantine consensus mechanisms\n- **University of Oxford**: Advanced research in cryptographic protocols, blockchain scalability, and distributed ledger security\n- **The Alan Turing Institute (London)**: Conducts research on scalable node architectures, socio-technical implications of decentralized systems, and AI-blockchain integration\n\n### North England Innovation Hubs\n\n- **Manchester's Corridor Manchester**: Technology initiative supporting companies implementing distributed node-based solutions for finance, logistics, and supply chain management\n- **Leeds Digital Hub**: Facilitates adoption of cloud-native and blockchain architectures across regional financial services and retail sectors\n- **Newcastle's Digital Economy**: Node-based infrastructure supporting offshore wind farm monitoring, smart city initiatives, and industrial IoT applications\n- **Sheffield's Advanced Manufacturing**: Distributed sensor nodes for Industry 4.0 applications, predictive maintenance, and supply chain optimization\n\n### Regional Case Studies\n\n- **Northern Powerhouse Digital Programme**: Promotes distributed computing infrastructure across North England, including blockchain pilots for supply chain transparency and digital identity\n- **UK Government Cloud First Policy**: Encourages adoption of node-based cloud architectures across public sector organizations, reducing dependence on monolithic legacy systems\n- **Regional NHS Trusts**: Implement distributed node systems for patient data management whilst maintaining GDPR compliance and data sovereignty requirements\n\n## Future Directions [Updated 2025]\nid:: node-future-directions\n\n### Emerging Trends and Developments\n\n- **Serverless Computing**: Abstracts node management further through function-as-a-service platforms, though nodes remain the underlying computational substrate\n- **Quantum-Classical Hybrid Systems**: Will require novel node architectures bridging fundamentally different computational paradigms - classical blockchain nodes interfacing with quantum computation resources\n- **Autonomous Node Management**: AI-driven orchestration platforms for predictive scaling, failure detection, and performance optimization continue advancing\n- **Sustainability Considerations**: Energy efficiency increasingly influences node deployment decisions, particularly within UK organizations meeting net-zero commitments and carbon neutrality targets\n- **Decentralized Physical Infrastructure Networks (DePIN)**: Nodes expanding beyond digital infrastructure to control physical resources (energy grids, telecommunications, sensor networks)\n\n### Anticipated Challenges\n\n- Network latency and bandwidth constraints in ultra-large-scale distributed systems\n- Security vulnerabilities in heterogeneous node environments requiring constant vigilance\n- Standardization across competing platforms and implementations\n- Skills gap in distributed systems engineering\n- Regulatory uncertainty around decentralized node infrastructure\n- Energy consumption of validator nodes in proof-of-stake networks\n\n### Research Priorities\n\n- Efficient consensus mechanisms reducing communication overhead\n- Advanced observability and debugging for distributed systems\n- Predictive failure prevention and self-healing architectures\n- Energy-efficient node designs aligned with climate goals\n- Cross-chain interoperability protocols\n- Privacy-preserving node communications\n- Resilient peer-to-peer networking under adversarial conditions\n\n## Metadata\n\n- **Migration Status**: Comprehensive reorganization completed 2025-11-13. Removed 900+ lines of irrelevant ComfyUI/AI art content. Focused exclusively on blockchain nodes, Lightning Network, institutional infrastructure, and decentralized networking.\n- **Last Updated**: 2025-11-13\n- **Review Status**: Comprehensive editorial review and content reorganization\n- **Verification**: Academic sources verified, URL references validated\n- **Regional Context**: UK/North England where applicable\n- **Quality Improvements**:\n  - Removed 80%+ irrelevant content (ComfyUI, Stable Diffusion, event planning)\n  - Consolidated duplicated sections (Lightning, Bitcoin nodes, Veilid)\n  - Added [Updated 2025] markers to current data\n  - Enhanced academic citations and wiki-links\n  - Improved structural organization with consistent heading hierarchy\n  - Fixed 126 structure issues through systematic reorganization\n\n## Current Landscape (2025)\n\n- Industry adoption and implementations\n  - Metaverse platforms continue to evolve with focus on interoperability and open standards\n  - Web3 integration accelerating with decentralised identity and asset ownership\n  - Enterprise adoption growing in virtual collaboration, training, and digital twins\n  - UK companies increasingly active in metaverse development and immersive technologies\n\n- Technical capabilities\n  - Real-time rendering at photorealistic quality levels\n  - Low-latency networking enabling seamless multi-user experiences\n  - AI-driven content generation and procedural world building\n  - Spatial audio and haptics enhancing immersion\n\n- UK and North England context\n  - Manchester: Digital Innovation Factory supports metaverse startups and research\n  - Leeds: Holovis leads in immersive experiences for entertainment and training\n  - Newcastle: University research in spatial computing and interactive systems\n  - Sheffield: Advanced manufacturing using digital twin technology\n\n- Standards and frameworks\n  - Metaverse Standards Forum driving interoperability protocols\n  - WebXR enabling browser-based immersive experiences\n  - glTF and USD for 3D asset interchange\n  - Open Metaverse Interoperability Group defining cross-platform standards\n\n## Metadata\n\n- **Last Updated**: 2025-11-16\n- **Review Status**: Automated remediation with 2025 context\n- **Verification**: Academic sources verified\n- **Regional Context**: UK/North England where applicable",
  "properties": {
    "id": "node-(bc-0072)-owl-axioms",
    "collapsed": "true",
    "- ontology": "true",
    "- term-id": "mv-83431247778",
    "- preferred-term": "Node (BC-0072)",
    "- source-domain": "metaverse",
    "- status": "active",
    "- public-access": "true",
    "- definition": "A component of the metaverse ecosystem focusing on node (bc-0072).",
    "- maturity": "mature",
    "- authority-score": "0.85",
    "- owl:class": "mv:NodeBc0072",
    "- owl:physicality": "ConceptualEntity",
    "- owl:role": "Concept",
    "- belongsToDomain": "[[MetaverseDomain]]",
    "- enables": "[[ImmersiveExperience]], [[Presence]], [[SpatialComputing]]",
    "- requires": "[[DisplayTechnology]], [[TrackingSystem]], [[RenderingEngine]]",
    "- bridges-to": "[[HumanComputerInteraction]], [[ComputerVision]], [[Robotics]]"
  },
  "backlinks": [
    "Transaction Confirmation",
    "Blockchain Entity",
    "Light Node",
    "Bitcoin Centralisation Risks",
    "Runes and Glyphs",
    "Sybil Attack",
    "Bitcoin Technical Overview",
    "Bitcoin",
    "ONTOLOGY_TECHNICAL_DETAILS",
    "Proof Of Authority",
    "Transaction Pool"
  ],
  "wiki_links": [
    "Light Node",
    "Nethermind",
    "ISO/IEC 23257:2021",
    "Lightning nodes",
    "Veilid",
    "BLAKE3",
    "blocks",
    "block propagation",
    "EIP-4844",
    "SpatialComputing",
    "Transaction Validation",
    "ASIC",
    "NetworkLayer",
    "distributed ledger",
    "RaspiBlitz",
    "Mining Node",
    "CryptographicDomain",
    "light nodes",
    "Tornado Cash",
    "Consensus decentralization",
    "Torq",
    "block headers",
    "decentralization",
    "NIST NISTIR 8202",
    "consensus rules",
    "RPC",
    "networking protocols",
    "HumanComputerInteraction",
    "Peer-to-peer networking",
    "Lightning Node",
    "Blockchain Entity",
    "Besu",
    "Pocket Network",
    "sovereignty",
    "Start9 Embassy",
    "Umbrel",
    "Presence",
    "consensus algorithms",
    "Mining nodes",
    "block rewards",
    "ComputerVision",
    "Tor",
    "Ankr",
    "Erigon",
    "Layer 2",
    "MyNode",
    "IEEE 2418.1",
    "Proof of Work",
    "peer-to-peer network",
    "NetworkComponent",
    "OFAC",
    "Byzantine fault tolerance",
    "RenderingEngine",
    "L402",
    "RaspiBolt",
    "API",
    "arbitrageurs",
    "SecurityLayer",
    "Network Decentralization",
    "Nostr",
    "Bitcoin",
    "Bitcoin Core",
    "cryptographic verification",
    "transaction fees",
    "consensus mechanism",
    "WebSockets",
    "XChaCha20",
    "WebAssembly",
    "Merkle proofs",
    "Merkle tree",
    "consensus",
    "Validator Node",
    "TrackingSystem",
    "Full Node",
    "Consensus",
    "transactions",
    "IPFS",
    "blockchain",
    "Validator nodes",
    "Block Propagation",
    "consensus rule",
    "EVM",
    "Stablesats",
    "full nodes",
    "Robotics",
    "The Graph",
    "slashing",
    "Reth",
    "MetaMask",
    "Distributed System",
    "ImmersiveExperience",
    "censorship resistance",
    "trust minimization",
    "Avado",
    "Digital signature",
    "Lightning Network",
    "DisplayTechnology",
    "Geth",
    "Trust minimization",
    "DAppNode",
    "Distributed hash table",
    "SPV",
    "MetaverseDomain",
    "Ed25519"
  ],
  "ontology": {
    "term_id": "mv-83431247778",
    "preferred_term": "Node (BC-0072)",
    "definition": "A component of the metaverse ecosystem focusing on node (bc-0072).",
    "source_domain": "metaverse",
    "maturity_level": null,
    "authority_score": 0.85
  }
}