{
  "title": "Non-Fungible Token (NFT)",
  "content": "- ### OntologyBlock\n  id:: nonfungibletoken-ontology\n  collapsed:: true\n\n  - **Identification**\n    - domain-prefix:: BC\n    - sequence-number:: 0569\n    - filename-history:: [\"BC-0569-nonfungibletoken.md\"]\n    - public-access:: true\n    - ontology:: true\n    - term-id:: BC-0569\n    - preferred-term:: Non-Fungible Token (NFT)\n    - source-domain:: metaverse\n    - status:: complete\n    - version:: 1.0.0\n    - last-updated:: 2025-11-13\n\n  - **Definition**\n    - definition:: Unique digital assets on blockchain.\n    - maturity:: established\n    - source:: Chimera Prime Research\n    - authority-score:: 0.95\n\n  - **Semantic Classification**\n    - owl:class:: bc:NonFungibleToken\n    - belongsToDomain:: [[Blockchain]]\n\n  - #### Relationships\n    - is-subclass-of:: [[Digital Asset]]\n\n  - #### OWL Axioms\n    - ```clojure\n      ; Class Declaration\n      (Declaration (Class :NonFungibleToken))\n      (SubClassOf :NonFungibleToken :DigitalAsset)\n      \n      ; Annotations\n      (AnnotationAssertion rdfs:label :NonFungibleToken \"Non-Fungible Token (NFT)\"@en)\n      (AnnotationAssertion rdfs:comment :NonFungibleToken\n        \"Unique digital assets on blockchain.\"@en)\n      ```\n\n- ## About Non-Fungible Token (NFT)\n  Unique digital assets on blockchain.\n\n## Current Landscape (2025)\n\n- Industry adoption and implementations\n  - Metaverse platforms continue to evolve with focus on interoperability and open standards\n  - Web3 integration accelerating with decentralised identity and asset ownership\n  - Enterprise adoption growing in virtual collaboration, training, and digital twins\n  - UK companies increasingly active in metaverse development and immersive technologies\n\n- Technical capabilities\n  - Real-time rendering at photorealistic quality levels\n  - Low-latency networking enabling seamless multi-user experiences\n  - AI-driven content generation and procedural world building\n  - Spatial audio and haptics enhancing immersion\n\n- UK and North England context\n  - Manchester: Digital Innovation Factory supports metaverse startups and research\n  - Leeds: Holovis leads in immersive experiences for entertainment and training\n  - Newcastle: University research in spatial computing and interactive systems\n  - Sheffield: Advanced manufacturing using digital twin technology\n\n- Standards and frameworks\n  - Metaverse Standards Forum driving interoperability protocols\n  - WebXR enabling browser-based immersive experiences\n  - glTF and USD for 3D asset interchange\n  - Open Metaverse Interoperability Group defining cross-platform standards\n\n## Metadata\n\n- **Last Updated**: 2025-11-16\n- **Review Status**: Automated remediation with 2025 context\n- **Verification**: Academic sources verified\n- **Regional Context**: UK/North England where applicable",
  "properties": {
    "id": "nonfungibletoken-ontology",
    "collapsed": "true",
    "- domain-prefix": "BC",
    "- sequence-number": "0569",
    "- filename-history": "[\"BC-0569-nonfungibletoken.md\"]",
    "- public-access": "true",
    "- ontology": "true",
    "- term-id": "BC-0569",
    "- preferred-term": "Non-Fungible Token (NFT)",
    "- source-domain": "metaverse",
    "- status": "complete",
    "- version": "1.0.0",
    "- last-updated": "2025-11-13",
    "- definition": "Unique digital assets on blockchain.",
    "- maturity": "established",
    "- source": "Chimera Prime Research",
    "- authority-score": "0.95",
    "- owl:class": "bc:NonFungibleToken",
    "- belongsToDomain": "[[Blockchain]]",
    "- is-subclass-of": "[[Digital Asset]]"
  },
  "backlinks": [
    "E R C721 Token"
  ],
  "wiki_links": [
    "Digital Asset",
    "Blockchain"
  ],
  "ontology": {
    "term_id": "BC-0569",
    "preferred_term": "Non-Fungible Token (NFT)",
    "definition": "Unique digital assets on blockchain.",
    "source_domain": "metaverse",
    "maturity_level": null,
    "authority_score": 0.95
  }
}