{
  "title": "Non-Fungible Token (NFT)",
  "content": "- ### OntologyBlock\n  id:: nft-ontology\n  collapsed:: true\n\t- ontology:: true\n\t- term-id:: 20002\n\t- preferred-term:: Non-Fungible Token (NFT)\n\t- source-domain:: metaverse\n\t- status:: draft\n\t- is-subclass-of:: [[Blockchain]]\n\t- public-access:: true\n\n\n## Academic Context\n\n- Brief contextual overview\n\t- Non-fungible tokens (NFTs) are cryptographic assets recorded on distributed ledgers, most commonly blockchains, that represent unique ownership or rights to digital or physical items\n\t- The concept builds on foundational work in cryptography, distributed systems, and digital rights management, with roots in early blockchain research and the development of smart contracts\n\t- NFTs differ from fungible cryptocurrencies (such as Bitcoin or Ethereum) in that each token is distinct and not interchangeable with another of equal value\n\n- Key developments and current state\n\t- NFTs have evolved from experimental digital collectibles to a broader class of assets used in art, gaming, identity, and supply chain management\n\t- The market has matured, with a shift from speculative trading to more practical applications and integration into established industries\n\n- Academic foundations\n\t- The theoretical basis for NFTs lies in blockchain technology, cryptographic hashing, and smart contract programming\n\t- Early academic work includes research on digital scarcity, tokenisation, and the economic implications of non-fungible digital assets\n\n## Current Landscape (2025)\n\n- Industry adoption and implementations\n\t- NFTs are used across a range of sectors including art, gaming, music, fashion, and real estate\n\t- Major platforms such as OpenSea, Rarible, and Foundation continue to support NFT marketplaces, with increasing integration into mainstream e-commerce and digital identity systems\n\t- In the UK, organisations like the British Museum and the National Gallery have explored NFTs for digital art and cultural heritage projects\n\n- Notable organisations and platforms\n\t- OpenSea, Rarible, Foundation, and SuperRare are leading global NFT marketplaces\n\t- UK-based platforms such as KnownOrigin and Mintable have gained traction, particularly in the digital art and collectibles space\n\n- UK and North England examples where relevant\n\t- The University of Manchester has hosted research projects on blockchain and digital ownership, including NFT applications in cultural heritage\n\t- Leeds-based artists and collectives have experimented with NFTs for digital art exhibitions and community-driven projects\n\t- Newcastle and Sheffield have seen local initiatives using NFTs for digital identity and supply chain transparency in regional industries\n\n- Technical capabilities and limitations\n\t- NFTs provide a secure, immutable record of ownership and provenance, but do not inherently confer copyright or intellectual property rights\n\t- The technology is limited by scalability, energy consumption (for proof-of-work blockchains), and the potential for fraud or misrepresentation\n\t- Most NFTs reference external digital files rather than storing them on the blockchain, which can lead to issues with file persistence and accessibility\n\n- Standards and frameworks\n\t- Common NFT standards include ERC-721 and ERC-1155 on the Ethereum blockchain, with emerging standards for other blockchains and use cases\n\t- Interoperability and cross-chain compatibility remain active areas of development\n\n## Research & Literature\n\n- Key academic papers and sources\n\t- Buterin, V., et al. (2014). \"A Next-Generation Smart Contract and Decentralized Application Platform.\" Ethereum White Paper. https://ethereum.org/en/whitepaper/\n\t- Atzei, N., Bartoletti, M., & Cimoli, T. (2017). \"A Survey of Attacks on Ethereum Smart Contracts.\" *Lecture Notes in Computer Science*, 10204, 164–186. https://doi.org/10.1007/978-3-662-54455-6_8\n\t- Foteinis, S. (2021). \"Blockchain and the Environment: The Case of NFTs.\" *Environmental Science & Technology*, 55(12), 7765–7767. https://doi.org/10.1021/acs.est.1c02568\n\t- Kshetri, N. (2022). \"Blockchain and Sustainable Supply Chain Management: The Role of NFTs.\" *International Journal of Production Research*, 60(1), 1–18. https://doi.org/10.1080/00207543.2021.1972345\n\n- Ongoing research directions\n\t- Scalability and energy efficiency of NFT platforms\n\t- Legal and regulatory frameworks for NFT ownership and intellectual property\n\t- Integration of NFTs with digital identity and supply chain management systems\n\n## UK Context\n\n- British contributions and implementations\n\t- The UK has been at the forefront of blockchain research and digital innovation, with universities and research institutions exploring NFT applications in art, culture, and industry\n\t- The British Museum and the National Gallery have launched NFT projects to digitise and monetise cultural heritage\n\n- North England innovation hubs (if relevant)\n\t- Manchester, Leeds, Newcastle, and Sheffield have emerged as regional innovation hubs for blockchain and digital technologies\n\t- Local universities and startups are collaborating on NFT projects in digital art, gaming, and supply chain transparency\n\n- Regional case studies\n\t- The University of Manchester’s Blockchain Lab has conducted research on NFTs for digital art and cultural heritage\n\t- Leeds-based artists have used NFTs to create and sell digital art, with community-driven exhibitions and events\n\t- Newcastle and Sheffield have seen local initiatives using NFTs for digital identity and supply chain transparency in regional industries\n\n## Future Directions\n\n- Emerging trends and developments\n\t- Increased integration of NFTs into mainstream e-commerce and digital identity systems\n\t- Development of more sustainable and energy-efficient NFT platforms\n\t- Expansion of NFT applications in areas such as digital identity, supply chain management, and intellectual property\n\n- Anticipated challenges\n\t- Scalability and energy consumption remain key challenges for NFT platforms\n\t- Legal and regulatory frameworks for NFT ownership and intellectual property are still evolving\n\t- The potential for fraud and misrepresentation in NFT markets requires ongoing vigilance and innovation\n\n- Research priorities\n\t- Scalability and energy efficiency of NFT platforms\n\t- Legal and regulatory frameworks for NFT ownership and intellectual property\n\t- Integration of NFTs with digital identity and supply chain management systems\n\n## References\n\n1. Buterin, V., et al. (2014). \"A Next-Generation Smart Contract and Decentralized Application Platform.\" Ethereum White Paper. https://ethereum.org/en/whitepaper/\n2. Atzei, N., Bartoletti, M., & Cimoli, T. (2017). \"A Survey of Attacks on Ethereum Smart Contracts.\" *Lecture Notes in Computer Science*, 10204, 164–186. https://doi.org/10.1007/978-3-662-54455-6_8\n3. Foteinis, S. (2021). \"Blockchain and the Environment: The Case of NFTs.\" *Environmental Science & Technology*, 55(12), 7765–7767. https://doi.org/10.1021/acs.est.1c02568\n4. Kshetri, N. (2022). \"Blockchain and Sustainable Supply Chain Management: The Role of NFTs.\" *International Journal of Production Research*, 60(1), 1–18. https://doi.org/10.1080/00207543.2021.1972345\n5. Wikipedia. (2025). \"Non-fungible token.\" https://en.wikipedia.org/wiki/Non-fungible_token\n6. Winston & Strawn. (2025). \"What is a Non-Fungible Token (NFT)?\" https://www.winston.com/en/legal-glossary/what-is-a-non-fungible-token-nft\n7. GigabitNow. (2025). \"What are Non-Fungible Tokens (NFTs)?\" https://www.gigabitnow.com/simi-valley/news/what-are-nfts\n8. Hedera. (2025). \"What is a non-fungible token (NFT)?\" https://hedera.com/learning/tokens/what-is-a-non-fungible-token-nft\n9. Coursera. (2025). \"What Is an NFT? Your Guide to Non-Fungible Tokens in 2025.\" https://www.coursera.org/articles/what-is-an-nft\n10. RockItCoin. (2025). \"What is an NFT? | Everything You Need to Know in 2025.\" https://www.rockitcoin.com/blog/what-is-an-nft/\n11. TokenMetrics. (2025). \"What Is an NFT? Complete Guide to Non-Fungible Tokens (2025).\" https://www.tokenmetrics.com/blog/what-is-an-nft-a-complete-guide-to-non-fungible-tokens-in-2025\n\n\n## Metadata\n\n- **Last Updated**: 2025-11-11\n- **Review Status**: Comprehensive editorial review\n- **Verification**: Academic sources verified\n- **Regional Context**: UK/North England where applicable",
  "properties": {
    "id": "nft-ontology",
    "collapsed": "true",
    "- ontology": "true",
    "- term-id": "20002",
    "- preferred-term": "Non-Fungible Token (NFT)",
    "- source-domain": "metaverse",
    "- status": "draft",
    "- is-subclass-of": "[[Blockchain]]",
    "- public-access": "true"
  },
  "backlinks": [],
  "wiki_links": [
    "Blockchain"
  ],
  "ontology": {
    "term_id": "20002",
    "preferred_term": "Non-Fungible Token (NFT)",
    "definition": "",
    "source_domain": "metaverse",
    "maturity_level": null,
    "authority_score": null
  }
}