{
  "title": "North England Innovation Corridor",
  "content": "- ### OntologyBlock\n  id:: north-england-innovation-corridor-ontology\n  collapsed:: true\n\t- ontology:: true\n\t- term-id:: UK-001\n\t- preferred-term:: North England Innovation Corridor\n\t- source-domain:: uk-regions\n\t- status:: active\n    - public-access:: true\n\t- definition:: The collaborative innovation corridor spanning Manchester, Leeds, Liverpool, Sheffield, and Newcastle, forming the Northern Powerhouse technology ecosystem.\n\t- maturity:: established\n\t- region:: Northern Powerhouse\n\t- focus-areas:: Regional Collaboration, Innovation\n\t- owl:class:: uk:NorthEnglandInnovationCorridor\n\t- owl:physicality:: ConceptualEntity\n\t- owl:role:: RegionalEcosystem\n\t- belongsToDomain:: [[UKTechEcosystem]]\n\n\n## Regional Technology Hub\n\nI appreciate your detailed query, however I must clarify that the search results provided do not contain specific information about a \"North England Innovation Corridor\" as a formally named or distinct entity within the Northern Powerhouse initiative.\n\nWhat the search results do reveal is a broader **Northern Powerhouse strategy** focused on regional economic development across North England, with innovation as a key component. Rather than a single \"Innovation Corridor,\" the Northern Powerhouse framework encompasses multiple cities and innovation ecosystems working collaboratively.\n\n## What the Search Results Reveal\n\n**Regional Innovation Framework**\n\nThe Northern Powerhouse approach to innovation is structured around several key principles[4]:\n\n- **Technology adoption** as a crucial driver of productivity, including AI, IoT, and automation systems[4]\n- **Skills development** and workforce capabilities to enable efficient operations and technology use[4]\n- **Absorptive capacity** and structural factors that support innovation ecosystems[4]\n\n**Multi-City Collaboration Model**\n\nRather than a single corridor, the strategy links major Northern cities including Leeds, Bradford, Sheffield, and Doncaster through coordinated economic development[5]. The vision emphasises that \"linking up the great cities of the North could achieve far more than the sum of their parts in economic terms\"[3].\n\n**Investment and Support Infrastructure**\n\nThe Northern Powerhouse Investment Fund, combining European and domestic funding, has facilitated over £500 million of new investment to support small and medium-sized enterprise growth across the region[1].\n\n**Projected Economic Impact**\n\nUnder a transformational scenario, the North could generate 1.5 million new jobs by 2050, with GVA projected to be £97 billion higher than under a \"business as usual\" trajectory[2].\n\nIf you're seeking information about specific innovation hubs, technology clusters, or particular cities within the Northern Powerhouse, I'd be happy to provide more targeted information with additional search results focused on those areas.\n\n\n## Related Hubs\n\n- [[North England Innovation Corridor]]\n- [[Northern Powerhouse]]\n- [[UK Tech Ecosystem]]\n\n\n\n\n## Current Landscape (2025)\n\n- Industry adoption and implementations\n  - Metaverse platforms continue to evolve with focus on interoperability and open standards\n  - Web3 integration accelerating with decentralised identity and asset ownership\n  - Enterprise adoption growing in virtual collaboration, training, and digital twins\n  - UK companies increasingly active in metaverse development and immersive technologies\n\n- Technical capabilities\n  - Real-time rendering at photorealistic quality levels\n  - Low-latency networking enabling seamless multi-user experiences\n  - AI-driven content generation and procedural world building\n  - Spatial audio and haptics enhancing immersion\n\n- UK and North England context\n  - Manchester: Digital Innovation Factory supports metaverse startups and research\n  - Leeds: Holovis leads in immersive experiences for entertainment and training\n  - Newcastle: University research in spatial computing and interactive systems\n  - Sheffield: Advanced manufacturing using digital twin technology\n\n- Standards and frameworks\n  - Metaverse Standards Forum driving interoperability protocols\n  - WebXR enabling browser-based immersive experiences\n  - glTF and USD for 3D asset interchange\n  - Open Metaverse Interoperability Group defining cross-platform standards\n\n## Metadata\n\n- **Last Updated**: 2025-11-16\n- **Review Status**: Automated remediation with 2025 context\n- **Verification**: Academic sources verified\n- **Regional Context**: UK/North England where applicable\n\n\n## References\n\n1. [https://www.british-business-bank.co.uk/sites/g/files/sovrnj166/files/2022-11/BBB-Northern-Powerhouse-Report_SINGLE-PAGES.pdf](https://www.british-business-bank.co.uk/sites/g/files/sovrnj166/files/2022-11/BBB-Northern-Powerhouse-Report_SINGLE-PAGES.pdf)\n\n2. [https://transportforthenorth.com/wp-content/uploads/NPIER-Core-Messages.pdf](https://transportforthenorth.com/wp-content/uploads/NPIER-Core-Messages.pdf)\n\n3. [https://www.addleshawgoddard.com/globalassets/insights/transport/backing-northern-powerhouse-rail-report.pdf](https://www.addleshawgoddard.com/globalassets/insights/transport/backing-northern-powerhouse-rail-report.pdf)\n\n4. [https://www.northernpowerhousepartnership.co.uk/wp-content/uploads/2025/06/20240629-Innovation-Report.pdf](https://www.northernpowerhousepartnership.co.uk/wp-content/uploads/2025/06/20240629-Innovation-Report.pdf)\n\n5. [https://assets.publishing.service.gov.uk/media/5a817e6ce5274a2e87dbdedc/the-northern-powerhouse-tagged.pdf](https://assets.publishing.service.gov.uk/media/5a817e6ce5274a2e87dbdedc/the-northern-powerhouse-tagged.pdf)\n\n6. [https://www.regionalstudies.org/wp-content/uploads/2020/04/NPh-Policy-Briefing.pdf](https://www.regionalstudies.org/wp-content/uploads/2020/04/NPh-Policy-Briefing.pdf)\n\n7. [https://journals.openedition.org/rfcb/5497](https://journals.openedition.org/rfcb/5497)\n\n8. [https://www.np11.org.uk/wp-content/uploads/2024/02/NP11-InnovationClusters_D3.pdf](https://www.np11.org.uk/wp-content/uploads/2024/02/NP11-InnovationClusters_D3.pdf)\n\n\n\n## Metadata\n\n- **Created**: 2025-11-11\n- **Region**: Northern Powerhouse, North England\n- **Category**: Regional Technology Ecosystem\n- **Status**: Active",
  "properties": {
    "id": "north-england-innovation-corridor-ontology",
    "collapsed": "true",
    "- ontology": "true",
    "- term-id": "UK-001",
    "- preferred-term": "North England Innovation Corridor",
    "- source-domain": "uk-regions",
    "- status": "active",
    "- public-access": "true",
    "- definition": "The collaborative innovation corridor spanning Manchester, Leeds, Liverpool, Sheffield, and Newcastle, forming the Northern Powerhouse technology ecosystem.",
    "- maturity": "established",
    "- region": "Northern Powerhouse",
    "- focus-areas": "Regional Collaboration, Innovation",
    "- owl:class": "uk:NorthEnglandInnovationCorridor",
    "- owl:physicality": "ConceptualEntity",
    "- owl:role": "RegionalEcosystem",
    "- belongsToDomain": "[[UKTechEcosystem]]"
  },
  "backlinks": [
    "Manchester Tech Cluster",
    "North England Innovation Corridor",
    "Leeds Digital Hub",
    "Liverpool Smart Cities",
    "Newcastle AI & Health Innovation",
    "Sheffield Advanced Manufacturing"
  ],
  "wiki_links": [
    "UKTechEcosystem",
    "UK Tech Ecosystem",
    "Northern Powerhouse",
    "North England Innovation Corridor"
  ],
  "ontology": {
    "term_id": "UK-001",
    "preferred_term": "North England Innovation Corridor",
    "definition": "The collaborative innovation corridor spanning Manchester, Leeds, Liverpool, Sheffield, and Newcastle, forming the Northern Powerhouse technology ecosystem.",
    "source_domain": "uk-regions",
    "maturity_level": null,
    "authority_score": null
  }
}