{
  "title": "NVIDIA Omniverse",
  "content": "- ### OntologyBlock\n  id:: nvidia-omniverse-ontology\n  collapsed:: true\n\t- ontology:: true\n\t- term-id:: mv-553481313384\n\t- preferred-term:: NVIDIA Omniverse\n\t- source-domain:: metaverse\n\t- status:: active\n\t- public-access:: true\n\t- definition:: A component of the metaverse ecosystem focusing on nvidia omniverse.\n\t- maturity:: mature\n\t- authority-score:: 0.85\n\t- owl:class:: mv:NvidiaOmniverse\n\t- owl:physicality:: ConceptualEntity\n\t- owl:role:: Concept\n\t- belongsToDomain:: [[MetaverseDomain]]\n\t- #### Relationships\n\t  id:: nvidia-omniverse-relationships\n\t\t- enables:: [[ImmersiveExperience]], [[Presence]], [[SpatialComputing]]\n\t\t- requires:: [[DisplayTechnology]], [[TrackingSystem]], [[RenderingEngine]]\n\t\t- bridges-to:: [[HumanComputerInteraction]], [[ComputerVision]], [[Robotics]]\n\n\t- #### OWL Axioms\n\t  id:: nvidia-omniverse-owl-axioms\n\t  collapsed:: true\n\t\t- ```clojure\n\t\t  Declaration(Class(mv:NvidiaOmniverse))\n\n\t\t  # Classification\n\t\t  SubClassOf(mv:NvidiaOmniverse mv:ConceptualEntity)\n\t\t  SubClassOf(mv:NvidiaOmniverse mv:Concept)\n\n\t\t  # Domain classification\n\t\t  SubClassOf(mv:NvidiaOmniverse\n\t\t    ObjectSomeValuesFrom(mv:belongsToDomain mv:MetaverseDomain)\n\t\t  )\n\n\t\t  # Annotations\n\t\t  AnnotationAssertion(rdfs:label mv:NvidiaOmniverse \"NVIDIA Omniverse\"@en)\n\t\t  AnnotationAssertion(rdfs:comment mv:NvidiaOmniverse \"A component of the metaverse ecosystem focusing on nvidia omniverse.\"@en)\n\t\t  AnnotationAssertion(dcterms:identifier mv:NvidiaOmniverse \"mv-553481313384\"^^xsd:string)\n\t\t  ```\n\npublic:: true\n\n- #Public page automatically published\n- # NVIDIA Omniverse\n\t- Omniverse is a collaborative platform developed by NVIDIA that enables users to create, simulate, and render 3D scenes and assets across multiple software applications. At the core of Omniverse lies the Universal Scene Description (USD) format, an open-source 3D scene description and file format that facilitates the interchange of 3D graphics data between different tools and applications.\n- ## Nucleus Server for Omniverse\n\t- Nucleus Server is a core component of the Omniverse platform that enables real-time collaboration, version control, and asset management for 3D scenes and assets. It acts as a central hub for storing, sharing, and synchronizing USD files and other related data across multiple users and applications.\n\t\t- Key features and functionalities of Nucleus Server include:\n\t\t- ### Real-time Collaboration\n\t\t\t- Multi-user editing: Multiple users can simultaneously work on the same USD scene or asset, with changes being synchronized in real-time\n\t\t\t- Presence and awareness: Users can see the presence and activities of other collaborators working on the same project\n\t\t\t- Conflict resolution: Nucleus Server automatically handles conflicts that may arise from simultaneous edits by multiple users\n\t\t- ### Version Control\n\t\t\t- Asset versioning: Nucleus Server maintains a version history of USD files and assets, allowing users to track changes over time\n\t\t\t- Branching and merging: Users can create separate branches of USD files for experimentation or parallel development, and merge changes back into the main branch\n\t\t\t- File locking: Nucleus Server supports file locking to prevent conflicts and ensure exclusive access to assets when needed\n\t\t- ### Asset Management\n\t\t\t- Asset organization: Nucleus Server provides a structured way to organize and manage 3D assets, including USD files, textures, and other related data\n\t\t\t- Metadata and tagging: Users can assign metadata and tags to assets for easier searching, filtering, and categorization\n\t\t\t- Access control: Nucleus Server allows for granular access control, enabling administrators to set permissions and restrict access to specific assets or projects\n\t\t- ### Omniverse Connector Integration\n\t\t\t- Application integration: Nucleus Server integrates with various 3D software applications through the Omniverse Connector plugin, enabling seamless synchronization and exchange of USD data\n\t\t\t- Live updates: Changes made in connected applications are automatically synchronized with Nucleus Server, ensuring that all collaborators have access to the latest version of the assets\n\t\t- ### Scalability and Performance\n\t\t\t- Distributed architecture: Nucleus Server can be deployed in a distributed architecture to handle large-scale projects and high-performance requirements\n\t\t\t- Caching and optimization: Nucleus Server employs caching mechanisms and optimization techniques to improve performance and minimize network bandwidth usage\n- ## Universal Scene Description (USD)\n\t- USD is a powerful and extensible framework for describing, composing, and interchanging 3D scenes and assets. It provides a common language for defining the geometry, shading, lighting, and other properties of 3D objects and scenes. USD allows for the efficient representation of large-scale, complex 3D scenes and supports features such as layering, instancing, and variant management.\n\t\t- Key features of USD include:\n\t\t- Hierarchical scene composition\n\t\t- Layered overrides and customization\n\t\t- Instancing and referencing\n\t\t- **Variant management**\n\t\t- Extensible schema system\n- ## Omniverse Variations (USD-based Object Variance System)\n\t- Omniverse Variations is a powerful feature built on top of USD that enables users to create and manage multiple variations of 3D objects and scenes within a single USD file. This allows for efficient storage and manipulation of different versions or configurations of assets, such as different materials, sizes, or poses.\n\t\t- Key aspects of Omniverse Variations include:\n\t\t- Variant sets: Collections of related variants for a specific purpose (e.g., material variations, level-of-detail variants)\n\t\t- Variant selection: Specifying which variant from each variant set should be active at any given time\n\t\t- Variant authoring: Creating and modifying variants using USD editing tools or supported 3D software applications\n- ## Blender Omniverse Integration with USD\n\t- Blender, a popular open-source 3D modeling and animation software, has been integrated with Omniverse through the USD format. This integration allows Blender users to leverage the collaborative features and pipeline interoperability provided by Omniverse.\n\t\t- Key features of the Blender Omniverse integration include:\n\t\t- USD import and export: Blender can read and write USD files, enabling seamless exchange of 3D data with other USD-compatible applications\n\t\t- Omniverse Connector: A plugin that enables Blender to connect to Omniverse servers for real-time collaboration and synchronization\n\t\t- USD schema support: Blender supports various USD schemas, such as UsdGeom, UsdShade, and UsdSkel, allowing for the preservation of important 3D data when exchanging files\n- ## USD Composer\n\t- USD Composer is a powerful visual programming tool provided by Omniverse that enables users to create and modify USD scenes using a node-based interface. It allows for the composition, layout, and editing of 3D scenes without the need for manual coding.\n\t\t- Key features of USD Composer include:\n\t\t- Node-based scene composition: Users can create and connect nodes representing 3D objects, materials, lights, and other scene elements\n\t\t- Attribute editing: Modify the properties of 3D objects and scene elements using the node interface\n\t\t- Variant management: Create and switch between different variations of objects and scenes\n\t\t- Extensibility: Custom nodes and extensions can be developed to extend the functionality of USD Composer\n- ## USD View\n\t- USD View is a standalone application provided by Omniverse for viewing and inspecting USD files. It allows users to navigate and explore the contents of USD files, including the scene hierarchy, geometry, materials, and other properties.\n\t\t- Key features of USD View include:\n\t\t- Scene hierarchy navigation: Explore the structure and organization of USD scenes\n\t\t- 3D viewport: Visualize and interact with 3D objects and scenes\n\t\t- Property inspection: View and modify the attributes of selected objects and scene elements\n\t\t- Variant switching: Quickly switch between different variations of objects and scenes for visualization and testing\n- ## Key aspects of NVIDIA's roadmap\n\t- **Enhanced Spatial Computing**: Spatial computing extends beyond traditional VR and AR by incorporating familiar elements of desktop computing into 3D space, enhancing user interactions with digital content in a more intuitive and spatially relevant manner.\n\t- **Omniverse Platform**: NVIDIA is pushing the Omniverse platform, which is aimed at achieving full fidelity, interoperability, and scalability in digital creation. It facilitates physically accurate simulations and seamless workflows across various digital creation tools, making it a critical part of NVIDIAâ€™s ecosystem support strategy.\n\t- **Cloud XR and GDN**: NVIDIA is leveraging its expertise in cloud solutions with Cloud XR and GDN (GeForce NOW Developer Network) to enhance the streaming of rich, immersive content. These platforms support expansive computing needs, enabling high-quality rendering and low-latency delivery over the cloud.\n\t- **AI Integration in XR**: NVIDIA is integrating AI into XR to create more dynamic and responsive environments. This includes using AI for real-time content creation and adjustment, enhancing the realism and responsiveness of XR applications.\n\t- **Partnerships and Collaboration**: NVIDIA continues to seek and expand partnerships across various sectors to foster the development and deployment of XR technologies. This is evident in their collaborations with companies like Adidas and automotive brands, using XR and AI to create personalized and enhanced customer experiences.\n\t- **Future Vision and Development**: Looking forward, NVIDIA is focused on further merging AI with XR to enrich user interfaces and experiences. This involves developing tools that facilitate the creation of digital content and simulations that are increasingly indistinguishable from reality.\n-\n- ## Download links\n\t- https://install.launcher.omniverse.nvidia.com/installers/omniverse-launcher-win.exe\n\t- https://install.launcher.omniverse.nvidia.com/installers/omniverse-launcher-linux.AppImage\n- ### Tutorials and tips\n\t- [Omniverse Local Nucleus Server Setup Tutorial - YouTube](https://www.youtube.com/watch?v=xnUTCp_vN8I)\n\t-\n\t-\n\n## Current Landscape (2025)\n\n- Industry adoption and implementations\n  - Metaverse platforms continue to evolve with focus on interoperability and open standards\n  - Web3 integration accelerating with decentralised identity and asset ownership\n  - Enterprise adoption growing in virtual collaboration, training, and digital twins\n  - UK companies increasingly active in metaverse development and immersive technologies\n\n- Technical capabilities\n  - Real-time rendering at photorealistic quality levels\n  - Low-latency networking enabling seamless multi-user experiences\n  - AI-driven content generation and procedural world building\n  - Spatial audio and haptics enhancing immersion\n\n- UK and North England context\n  - Manchester: Digital Innovation Factory supports metaverse startups and research\n  - Leeds: Holovis leads in immersive experiences for entertainment and training\n  - Newcastle: University research in spatial computing and interactive systems\n  - Sheffield: Advanced manufacturing using digital twin technology\n\n- Standards and frameworks\n  - Metaverse Standards Forum driving interoperability protocols\n  - WebXR enabling browser-based immersive experiences\n  - glTF and USD for 3D asset interchange\n  - Open Metaverse Interoperability Group defining cross-platform standards\n\n## Metadata\n\n- **Last Updated**: 2025-11-16\n- **Review Status**: Automated remediation with 2025 context\n- **Verification**: Academic sources verified\n- **Regional Context**: UK/North England where applicable",
  "properties": {
    "id": "nvidia-omniverse-owl-axioms",
    "collapsed": "true",
    "- ontology": "true",
    "- term-id": "mv-553481313384",
    "- preferred-term": "NVIDIA Omniverse",
    "- source-domain": "metaverse",
    "- status": "active",
    "- public-access": "true",
    "- definition": "A component of the metaverse ecosystem focusing on nvidia omniverse.",
    "- maturity": "mature",
    "- authority-score": "0.85",
    "- owl:class": "mv:NvidiaOmniverse",
    "- owl:physicality": "ConceptualEntity",
    "- owl:role": "Concept",
    "- belongsToDomain": "[[MetaverseDomain]]",
    "- enables": "[[ImmersiveExperience]], [[Presence]], [[SpatialComputing]]",
    "- requires": "[[DisplayTechnology]], [[TrackingSystem]], [[RenderingEngine]]",
    "- bridges-to": "[[HumanComputerInteraction]], [[ComputerVision]], [[Robotics]]",
    "public": "true"
  },
  "backlinks": [
    "BC-0030-digital-signature",
    "rb-0087-safety-standard",
    "Client side DCO",
    "Virtual Production",
    "MITIH",
    "Knowhere",
    "Speech and voice",
    "Ai in Games",
    "Parametric",
    "Telecollaboration and Telepresence",
    "Proprietary Video",
    "Safety Standard",
    "BC-0014-block-time",
    "Agentic Metaverse for Global Creatives",
    "BC-0021-input"
  ],
  "wiki_links": [
    "TrackingSystem",
    "ImmersiveExperience",
    "ComputerVision",
    "RenderingEngine",
    "SpatialComputing",
    "Robotics",
    "HumanComputerInteraction",
    "MetaverseDomain",
    "DisplayTechnology",
    "Presence"
  ],
  "ontology": {
    "term_id": "mv-553481313384",
    "preferred_term": "NVIDIA Omniverse",
    "definition": "A component of the metaverse ecosystem focusing on nvidia omniverse.",
    "source_domain": "metaverse",
    "maturity_level": null,
    "authority_score": 0.85
  }
}