{
  "title": "Omnidirectional Robot",
  "content": "- ### OntologyBlock\n  id:: omnidirectionalrobot-ontology\n  collapsed:: true\n\n  - **Identification**\n    - domain-prefix:: RB\n    - sequence-number:: 0116\n    - filename-history:: [\"RB-0116-omnidirectionalrobot.md\"]\n    - public-access:: true\n    - ontology:: true\n    - term-id:: RB-0116\n    - preferred-term:: Omnidirectional Robot\n    - source-domain:: metaverse\n    - status:: complete\n    - version:: 1.0.0\n    - last-updated:: 2025-11-13\n\n  - **Definition**\n    - definition:: Omnidirectional robot uses mecanum wheels or omniwheels for holonomic motion.\n    - maturity:: established\n    - source:: Chimera Prime Research\n    - authority-score:: 0.95\n\n  - **Semantic Classification**\n    - owl:class:: rb:OmnidirectionalRobot\n    - belongsToDomain:: [[Robotics]]\n\n  - #### Relationships\n    - is-subclass-of:: [[Wheeled Robot]]\n\n  - #### OWL Axioms\n    - ```clojure\n      ; Class Declaration\n      (Declaration (Class :OmnidirectionalRobot))\n      (SubClassOf :OmnidirectionalRobot :WheeledRobot)\n      \n      ; Annotations\n      (AnnotationAssertion rdfs:label :OmnidirectionalRobot \"Omnidirectional Robot\"@en)\n      (AnnotationAssertion rdfs:comment :OmnidirectionalRobot\n        \"Omnidirectional robot uses mecanum wheels or omniwheels for holonomic motion.\"@en)\n      ```\n\n- ## About Omnidirectional Robot\n  Omnidirectional robot uses mecanum wheels or omniwheels for holonomic motion.\n  \n  A wheeled robot capable of instantaneous motion in any direction.\n\n## Current Landscape (2025)\n\n- Industry adoption and implementations\n  - Metaverse platforms continue to evolve with focus on interoperability and open standards\n  - Web3 integration accelerating with decentralised identity and asset ownership\n  - Enterprise adoption growing in virtual collaboration, training, and digital twins\n  - UK companies increasingly active in metaverse development and immersive technologies\n\n- Technical capabilities\n  - Real-time rendering at photorealistic quality levels\n  - Low-latency networking enabling seamless multi-user experiences\n  - AI-driven content generation and procedural world building\n  - Spatial audio and haptics enhancing immersion\n\n- UK and North England context\n  - Manchester: Digital Innovation Factory supports metaverse startups and research\n  - Leeds: Holovis leads in immersive experiences for entertainment and training\n  - Newcastle: University research in spatial computing and interactive systems\n  - Sheffield: Advanced manufacturing using digital twin technology\n\n- Standards and frameworks\n  - Metaverse Standards Forum driving interoperability protocols\n  - WebXR enabling browser-based immersive experiences\n  - glTF and USD for 3D asset interchange\n  - Open Metaverse Interoperability Group defining cross-platform standards\n\n## Metadata\n\n- **Last Updated**: 2025-11-16\n- **Review Status**: Automated remediation with 2025 context\n- **Verification**: Academic sources verified\n- **Regional Context**: UK/North England where applicable",
  "properties": {
    "id": "omnidirectionalrobot-ontology",
    "collapsed": "true",
    "- domain-prefix": "RB",
    "- sequence-number": "0116",
    "- filename-history": "[\"RB-0116-omnidirectionalrobot.md\"]",
    "- public-access": "true",
    "- ontology": "true",
    "- term-id": "RB-0116",
    "- preferred-term": "Omnidirectional Robot",
    "- source-domain": "metaverse",
    "- status": "complete",
    "- version": "1.0.0",
    "- last-updated": "2025-11-13",
    "- definition": "Omnidirectional robot uses mecanum wheels or omniwheels for holonomic motion.",
    "- maturity": "established",
    "- source": "Chimera Prime Research",
    "- authority-score": "0.95",
    "- owl:class": "rb:OmnidirectionalRobot",
    "- belongsToDomain": "[[Robotics]]",
    "- is-subclass-of": "[[Wheeled Robot]]"
  },
  "backlinks": [
    "Mecanum Robot"
  ],
  "wiki_links": [
    "Robotics",
    "Wheeled Robot"
  ],
  "ontology": {
    "term_id": "RB-0116",
    "preferred_term": "Omnidirectional Robot",
    "definition": "Omnidirectional robot uses mecanum wheels or omniwheels for holonomic motion.",
    "source_domain": "metaverse",
    "maturity_level": null,
    "authority_score": 0.95
  }
}