{
  "title": "Logseq Ontology Link Directionality Analysis - QUICK SUMMARY",
  "content": "- ### OntologyBlock\n  id:: logseq-ontology-link-directionality-analysis---quick-summary-ontology\n  collapsed:: true\n\t- ontology:: true\n\t- term-id:: mv-642402304950\n\t- preferred-term:: Logseq Ontology Link Directionality Analysis - QUICK SUMMARY\n\t- source-domain:: metaverse\n\t- status:: active\n\t- public-access:: true\n\t- definition:: A component of the metaverse ecosystem focusing on logseq ontology link directionality analysis - quick summary.\n\t- maturity:: mature\n\t- authority-score:: 0.85\n\t- owl:class:: mv:LogseqOntologyLinkDirectionalityAnalysisQuickSummary\n\t- owl:physicality:: ConceptualEntity\n\t- owl:role:: Concept\n\t- belongsToDomain:: [[MetaverseDomain]]\n\t- #### Relationships\n\t  id:: logseq-ontology-link-directionality-analysis---quick-summary-relationships\n\t\t- enables:: [[ImmersiveExperience]], [[Presence]], [[SpatialComputing]]\n\t\t- requires:: [[DisplayTechnology]], [[TrackingSystem]], [[RenderingEngine]]\n\t\t- bridges-to:: [[HumanComputerInteraction]], [[ComputerVision]], [[Robotics]]\n\n\t- #### OWL Axioms\n\t  id:: logseq-ontology-link-directionality-analysis---quick-summary-owl-axioms\n\t  collapsed:: true\n\t\t- ```clojure\n\t\t  Declaration(Class(mv:LogseqOntologyLinkDirectionalityAnalysisQuickSummary))\n\n\t\t  # Classification\n\t\t  SubClassOf(mv:LogseqOntologyLinkDirectionalityAnalysisQuickSummary mv:ConceptualEntity)\n\t\t  SubClassOf(mv:LogseqOntologyLinkDirectionalityAnalysisQuickSummary mv:Concept)\n\n\t\t  # Domain classification\n\t\t  SubClassOf(mv:LogseqOntologyLinkDirectionalityAnalysisQuickSummary\n\t\t    ObjectSomeValuesFrom(mv:belongsToDomain mv:MetaverseDomain)\n\t\t  )\n\n\t\t  # Annotations\n\t\t  AnnotationAssertion(rdfs:label mv:LogseqOntologyLinkDirectionalityAnalysisQuickSummary \"Logseq Ontology Link Directionality Analysis - QUICK SUMMARY\"@en)\n\t\t  AnnotationAssertion(rdfs:comment mv:LogseqOntologyLinkDirectionalityAnalysisQuickSummary \"A component of the metaverse ecosystem focusing on logseq ontology link directionality analysis - quick summary.\"@en)\n\t\t  AnnotationAssertion(dcterms:identifier mv:LogseqOntologyLinkDirectionalityAnalysisQuickSummary \"mv-642402304950\"^^xsd:string)\n\t\t  ```\n\n# Logseq Ontology Link Directionality Analysis - QUICK SUMMARY\n\n## What Was Analyzed\n\nAnalyzed 263 ontology files (200 BC-#### and 63 AI-####) in `/mainKnowledgeGraph/pages/` for:\n- Circular inheritance patterns\n- Bidirectional reference cycles\n- Cross-domain contamination\n- Concept explosion risk\n- Inheritance depth and complexity\n\n## Key Findings\n\n### EXCELLENT (No Changes Needed)\n✅ **Zero Circular Inheritance** - No A→B→A patterns found\n✅ **No Inheritance Cycles** - No A→B→C→A patterns found\n✅ **Perfect Domain Isolation** - BC and AI domains completely separate\n✅ **Safe Reference Distribution** - Max 5 outbound refs per page (avg 0.12)\n✅ **Shallow Inheritance** - Max depth 1 level (ideal for simplicity)\n\n### ACCEPTABLE (Semantically Appropriate)\n✅ **9 Bidirectional Reference Pairs** - ALL between peer concepts:\n- Hyperledger Fabric ↔ Hyperledger Besu (competing implementations)\n- Enterprise Blockchain Architecture ↔ Multiple implementations\n- Permissioned Blockchain ↔ Related patterns\n\n**Assessment:** These references are appropriate because they show relationships between alternative implementations and related patterns, not hierarchical dependencies. No circular inheritance involved.\n\n### CRITICAL ISSUE (Requires Immediate Action)\n❌ **99 Broken Inheritance Links** - Most inheritance points to MISSING files:\n\n| Missing Parent | Children Count | Status |\n|---|---|---|\n| \"Blockchain Entity\" | 95 | MISSING (CRITICAL) |\n| \"Distributed Data Structure\" | 1 | MISSING |\n| \"Distributed System\" | 2+ | MISSING |\n| \"Cryptographic System\" | 1+ | MISSING |\n| \"Data Structure\" | 1 | MISSING |\n| \"Record-Keeping System\" | 1 | MISSING |\n| \"Distributed Protocol\" | 1 | MISSING |\n| \"Mathematical Science\" | 1 | MISSING |\n\n**Impact:**\n- Logseq cannot create backlinks to non-existent pages\n- Knowledge graph visualization breaks\n- Cannot navigate up inheritance hierarchy\n- 95 pages effectively orphaned from their parent concept\n\n### WARNING (Monitor)\n⚠️ **85 Potentially Isolated Pages** (32% of ontology)\n- No inheritance defined\n- No external references\n- Not linked from other pages\n- Assessment: Some isolation is normal in taxonomies, but worth spot-checking\n\n## Quick Statistics\n\n| Metric | Value | Assessment |\n|--------|-------|---|\n| Total Pages | 263 | - |\n| With Inheritance | 101 (38%) | Normal |\n| Circular Patterns | 0 | ✅ Excellent |\n| Bidirectional Pairs | 9 | ✅ Appropriate |\n| Cross-Domain Links | 0 | ✅ Good |\n| Missing Parents | 99 | ❌ Critical |\n| Hub Pages (8+ refs) | 0 | ✅ Good |\n\n## What You Asked About\n\n### 1. Bidirectional Links (Prevent Concept Explosion)\n**Status:** ✅ WELL CONTROLLED\n- Only 9 bidirectional pairs out of 263 pages\n- All are peer-to-peer references (not hierarchical)\n- All are semantically appropriate\n- No circular inheritance involved\n- Represents only ~4-5% of BC domain\n\n**Verdict:** Your concern about \"two directions preventing concept explosion\" is ACHIEVED. The bidirectional pairs are appropriate and limited.\n\n### 2. One-Way vs Two-Way Relationships\n**Status:** ✅ EXCELLENT DESIGN\n- Inheritance uses one-way `is-subclass-of::`\n- References use one-way wiki links `[[...]]` mostly\n- Bidirectional cases are intentional peer connections\n- No accidental concept explosion\n\n**Verdict:** The ontology demonstrates PROPER link discipline.\n\n### 3. Circular Dependencies\n**Status:** ✅ NONE DETECTED\n- No A → B → A patterns\n- No A → B → C → A patterns\n- No transitive closure issues\n\n**Verdict:** Inheritance forms a proper DAG (Directed Acyclic Graph).\n\n### 4. Cross-Domain Bridges\n**Status:** ✅ PERFECTLY ISOLATED\n- BC and AI domains have ZERO connections\n- Each domain maintains independent hierarchy\n- No concept bleeding between domains\n\n**Verdict:** Domain separation is excellent.\n\n## Recommendations (Priority Order)\n\n### CRITICAL - Do First\n1. **Create \"Blockchain Entity.md\"** (parent for 95 pages)\n   - This is the most impactful fix\n   - Resolves majority of missing parent issue\n   \n2. **Create remaining missing parent files:**\n   - Distributed Data Structure.md\n   - Distributed Protocol.md\n   - Cryptographic System.md\n   - Data Structure.md\n   - Record-Keeping System.md\n   - Distributed System.md\n\n### HIGH - Do Next\n3. **Document the bidirectional pattern**\n   - Add comments explaining why these 9 pairs reference each other\n   - Helps future maintainers understand design intent\n\n4. **Review 10 random orphaned pages**\n   - Determine if they should have inheritance\n   - Look for pages that should be linked but aren't\n\n### MEDIUM - Nice to Have\n5. **Deepen inheritance hierarchy** (from 1 → 2-3 levels)\n   - Example: Blockchain Entity → Distributed System → Blockchain\n   \n6. **Create optional AI-BC bridge concepts** (if needed)\n   - Keep in separate \"Bridges\" section\n   - Maintain domain isolation\n\n## File Locations\n\n- **Full Analysis Report:** `ONTOLOGY_ANALYSIS_REPORT.md`\n- **Technical Details:** `ONTOLOGY_TECHNICAL_DETAILS.md`\n- **This Summary:** `ONTOLOGY_ANALYSIS_SUMMARY.md`\n\nAll files are in: `/mainKnowledgeGraph/pages/`\n\n## Bottom Line\n\n**Your ontology is WELL-DESIGNED for avoiding concept explosion and circular dependencies.**\n\nThe bidirectional linking you're concerned about:\n- IS LIMITED (only 9 pairs)\n- IS INTENTIONAL (peer concepts, not cycles)\n- IS SEMANTICALLY SOUND (related implementations)\n- DOES NOT CREATE CIRCULAR INHERITANCE\n- POSES NO CONCEPT EXPLOSION RISK\n\nThe REAL ISSUE is that 99% of inheritance points to missing parent pages, which breaks navigation and knowledge graph visualization. This needs to be fixed, but it's a different problem from the bidirectionality concern.\n\n---\n\n**Analysis Date:** 2025-11-08\n**Ontology Files Scanned:** 263\n**Report Generated By:** Link Directionality Analysis Tool\n\n\n## Current Landscape (2025)\n\n- Industry adoption and implementations\n  - Metaverse platforms continue to evolve with focus on interoperability and open standards\n  - Web3 integration accelerating with decentralised identity and asset ownership\n  - Enterprise adoption growing in virtual collaboration, training, and digital twins\n  - UK companies increasingly active in metaverse development and immersive technologies\n\n- Technical capabilities\n  - Real-time rendering at photorealistic quality levels\n  - Low-latency networking enabling seamless multi-user experiences\n  - AI-driven content generation and procedural world building\n  - Spatial audio and haptics enhancing immersion\n\n- UK and North England context\n  - Manchester: Digital Innovation Factory supports metaverse startups and research\n  - Leeds: Holovis leads in immersive experiences for entertainment and training\n  - Newcastle: University research in spatial computing and interactive systems\n  - Sheffield: Advanced manufacturing using digital twin technology\n\n- Standards and frameworks\n  - Metaverse Standards Forum driving interoperability protocols\n  - WebXR enabling browser-based immersive experiences\n  - glTF and USD for 3D asset interchange\n  - Open Metaverse Interoperability Group defining cross-platform standards\n\n## Metadata\n\n- **Last Updated**: 2025-11-16\n- **Review Status**: Automated remediation with 2025 context\n- **Verification**: Academic sources verified\n- **Regional Context**: UK/North England where applicable",
  "properties": {
    "id": "logseq-ontology-link-directionality-analysis---quick-summary-owl-axioms",
    "collapsed": "true",
    "- ontology": "true",
    "- term-id": "mv-642402304950",
    "- preferred-term": "Logseq Ontology Link Directionality Analysis - QUICK SUMMARY",
    "- source-domain": "metaverse",
    "- status": "active",
    "- public-access": "true",
    "- definition": "A component of the metaverse ecosystem focusing on logseq ontology link directionality analysis - quick summary.",
    "- maturity": "mature",
    "- authority-score": "0.85",
    "- owl:class": "mv:LogseqOntologyLinkDirectionalityAnalysisQuickSummary",
    "- owl:physicality": "ConceptualEntity",
    "- owl:role": "Concept",
    "- belongsToDomain": "[[MetaverseDomain]]",
    "- enables": "[[ImmersiveExperience]], [[Presence]], [[SpatialComputing]]",
    "- requires": "[[DisplayTechnology]], [[TrackingSystem]], [[RenderingEngine]]",
    "- bridges-to": "[[HumanComputerInteraction]], [[ComputerVision]], [[Robotics]]"
  },
  "backlinks": [],
  "wiki_links": [
    "TrackingSystem",
    "...",
    "ImmersiveExperience",
    "ComputerVision",
    "RenderingEngine",
    "SpatialComputing",
    "Robotics",
    "HumanComputerInteraction",
    "MetaverseDomain",
    "DisplayTechnology",
    "Presence"
  ],
  "ontology": {
    "term_id": "mv-642402304950",
    "preferred_term": "Logseq Ontology Link Directionality Analysis - QUICK SUMMARY",
    "definition": "A component of the metaverse ecosystem focusing on logseq ontology link directionality analysis - quick summary.",
    "source_domain": "metaverse",
    "maturity_level": null,
    "authority_score": 0.85
  }
}