{
  "title": "Optimization Algorithm",
  "content": "- ### OntologyBlock\n  id:: optimizationalgorithm-ontology\n  collapsed:: true\n\n  - **Identification**\n    - domain-prefix:: AI\n    - sequence-number:: 0866\n    - filename-history:: [\"AI-0866-optimizationalgorithm.md\"]\n    - public-access:: true\n    - ontology:: true\n    - term-id:: AI-0866\n    - preferred-term:: Optimization Algorithm\n    - source-domain:: ai\n    - status:: complete\n    - version:: 1.0.0\n    - last-updated:: 2025-11-13\n\n  - **Definition**\n    - definition:: \n    - maturity:: established\n    - source:: Chimera Prime Research\n    - authority-score:: 0.95\n\n  - **Semantic Classification**\n    - owl:class:: ai:OptimizationAlgorithm\n    - belongsToDomain:: [[Artificial Intelligence]]\n\n  - #### OWL Restrictions\n    \n\n  - #### CrossDomainBridges\n    - bridges-from:: [[GenerativeDesignTool]] via depends-on\n\n  - \n### Relationships\n- is-subclass-of:: [[MachineLearning]]",
  "properties": {
    "id": "optimizationalgorithm-ontology",
    "collapsed": "true",
    "- domain-prefix": "AI",
    "- sequence-number": "0866",
    "- filename-history": "[\"AI-0866-optimizationalgorithm.md\"]",
    "- public-access": "true",
    "- ontology": "true",
    "- term-id": "AI-0866",
    "- preferred-term": "Optimization Algorithm",
    "- source-domain": "ai",
    "- status": "complete",
    "- version": "1.0.0",
    "- last-updated": "2025-11-13",
    "- definition": "",
    "- maturity": "established",
    "- source": "Chimera Prime Research",
    "- authority-score": "0.95",
    "- owl:class": "ai:OptimizationAlgorithm",
    "- belongsToDomain": "[[Artificial Intelligence]]",
    "- bridges-from": "[[GenerativeDesignTool]] via depends-on"
  },
  "backlinks": [
    "Generative Design Tool"
  ],
  "wiki_links": [
    "GenerativeDesignTool",
    "MachineLearning",
    "Artificial Intelligence"
  ],
  "ontology": {
    "term_id": "AI-0866",
    "preferred_term": "Optimization Algorithm",
    "definition": "",
    "source_domain": "ai",
    "maturity_level": null,
    "authority_score": 0.95
  }
}