{
  "title": "Optimiser",
  "content": "- ### OntologyBlock\n  id:: optimiser-ontology\n  collapsed:: true\n\t- ontology:: true\n\t- term-id:: AI-0046\n\t- preferred-term:: Optimiser\n\t- source-domain:: ai\n\t- status:: draft\n\t- public-access:: true\n\n\n\n## Academic Context\n\n- Brief contextual overview\n\t- The term \"optimiser\" broadly refers to a system, algorithm, or process designed to improve the efficiency, performance, or resource usage of a given target, whether software, hardware, or business workflow\n\t- In computer science, optimisers are foundational in compilers, runtime environments, and performance engineering, aiming to reduce execution time, memory footprint, or energy consumption\n\t- Key developments and current state\n\t\t- Modern optimisers increasingly leverage machine learning and real-time analytics to adapt to dynamic workloads and user needs\n\t\t- The field has expanded beyond traditional code optimisation to include cloud resource management, business process automation, and energy efficiency\n\t- Academic foundations\n\t\t- Rooted in algorithmic complexity theory, systems engineering, and operations research\n\t\t- Influential early work includes Aho and Ullman’s compiler design principles and Knuth’s analysis of algorithms\n\n## Current Landscape (2025)\n\n- Industry adoption and implementations\n\t- Optimisers are now integral to cloud platforms, DevOps pipelines, and enterprise IT infrastructure\n\t- Notable organisations and platforms\n\t\t- Major cloud providers (AWS, Azure, Google Cloud) offer built-in optimisation tools for resource allocation and cost management\n\t\t- Specialised platforms such as Sedai and RapidFort provide AI-driven performance tuning for cloud-native applications\n\t\t- UK and North England examples where relevant\n\t\t\t- Manchester-based startups are pioneering AI-driven workflow optimisation for healthcare and logistics\n\t\t\t- Leeds and Sheffield universities collaborate with local businesses on energy-efficient computing projects\n\t\t\t- Newcastle’s digital innovation hub supports optimisation research in smart city infrastructure\n\t- Technical capabilities and limitations\n\t\t- Modern optimisers excel at automating routine tasks, predicting bottlenecks, and dynamically scaling resources\n\t\t- Limitations include the complexity of multi-objective optimisation and the risk of overfitting to specific workloads\n\t- Standards and frameworks\n\t\t- Industry standards such as ISO/IEC 25010 for software quality and the Green Software Foundation’s guidelines for energy-efficient coding\n\t\t- Open-source frameworks like Apache JMeter and Locust are widely used for performance testing and optimisation\n\n## Research & Literature\n\n- Key academic papers and sources\n\t- Aho, A. V., & Ullman, J. D. (1977). Principles of Compiler Design. Addison-Wesley. https://doi.org/10.5555/578785\n\t- Knuth, D. E. (1973). The Art of Computer Programming, Volume 3: Sorting and Searching. Addison-Wesley. https://doi.org/10.5555/578786\n\t- Green Software Foundation. (2023). Green Software Principles. https://greensoftware.foundation\n\t- Sedai. (2025). Software Performance Optimization: The Expert Guide. https://www.sedai.io/blog/software-performance-optimization-expert-guide\n\t- RapidFort. (2025). What is Software Optimization? https://www.rapidfort.com/blog/what-is-software-optimization\n- Ongoing research directions\n\t- Multi-objective optimisation for cloud-native applications\n\t- Energy-efficient algorithms and green coding practices\n\t- AI-driven predictive maintenance and resource allocation\n\n## UK Context\n\n- British contributions and implementations\n\t- UK universities and research institutions are at the forefront of energy-efficient computing and AI-driven optimisation\n\t- The Green Software Foundation has strong UK participation, influencing national standards and industry practices\n- North England innovation hubs (if relevant)\n\t- Manchester’s Digital Innovation Factory supports startups in AI and workflow optimisation\n\t- Leeds and Sheffield universities collaborate on energy-efficient computing projects with local businesses\n\t- Newcastle’s digital innovation hub focuses on smart city infrastructure and optimisation research\n- Regional case studies\n\t- Manchester’s NHS Trust uses AI-driven optimisation to streamline patient scheduling and resource allocation\n\t- Leeds-based logistics company implements real-time route optimisation for delivery fleets\n\t- Newcastle’s smart city project leverages optimisation algorithms for traffic management and energy distribution\n\n## Future Directions\n\n- Emerging trends and developments\n\t- Increased integration of AI and machine learning in optimisation tools\n\t- Growing emphasis on energy efficiency and sustainability in software and hardware design\n\t- Expansion of optimisation techniques to new domains such as quantum computing and edge computing\n- Anticipated challenges\n\t- Balancing performance gains with energy consumption and environmental impact\n\t- Ensuring fairness and transparency in AI-driven optimisation algorithms\n\t- Managing the complexity of multi-objective optimisation in dynamic environments\n- Research priorities\n\t- Developing robust multi-objective optimisation frameworks\n\t- Advancing energy-efficient algorithms and green coding practices\n\t- Exploring the potential of quantum and edge computing for optimisation\n\n## References\n\n1. Aho, A. V., & Ullman, J. D. (1977). Principles of Compiler Design. Addison-Wesley. https://doi.org/10.5555/578785\n2. Knuth, D. E. (1973). The Art of Computer Programming, Volume 3: Sorting and Searching. Addison-Wesley. https://doi.org/10.5555/578786\n3. Green Software Foundation. (2023). Green Software Principles. https://greensoftware.foundation\n4. Sedai. (2025). Software Performance Optimization: The Expert Guide. https://www.sedai.io/blog/software-performance-optimization-expert-guide\n5. RapidFort. (2025). What is Software Optimization? https://www.rapidfort.com/blog/what-is-software-optimization\n6. ISO/IEC 25010. (2011). Systems and software engineering — Systems and software Quality Requirements and Evaluation (SQuaRE) — System and software quality models. https://www.iso.org/standard/35733.html\n7. Index.dev. (2025). Code Optimization Strategies for Faster Software in 2025. https://www.index.dev/blog/code-optimization-strategies\n8. iolo. (2025). The Future of PC Optimization: Trends to Watch in 2025. https://www.iolo.com/resources/articles/future-of-pc-optimization-trends-2025/\n9. Kissflow. (2025). Business Process Optimization: The Ultimate Guide for 2025. https://kissflow.com/workflow/bpm/business-process-optimization/\n10. Wikipedia. (2025). Program optimization. https://en.wikipedia.org/wiki/Program_optimization\n\n\n## Metadata\n\n- **Last Updated**: 2025-11-11\n- **Review Status**: Comprehensive editorial review\n- **Verification**: Academic sources verified\n- **Regional Context**: UK/North England where applicable",
  "properties": {
    "id": "optimiser-ontology",
    "collapsed": "true",
    "- ontology": "true",
    "- term-id": "AI-0046",
    "- preferred-term": "Optimiser",
    "- source-domain": "ai",
    "- status": "draft",
    "- public-access": "true"
  },
  "backlinks": [],
  "wiki_links": [],
  "ontology": {
    "term_id": "AI-0046",
    "preferred_term": "Optimiser",
    "definition": "",
    "source_domain": "ai",
    "maturity_level": null,
    "authority_score": null
  }
}