{
  "title": "Orphan Block",
  "content": "- ### OntologyBlock\n  id:: orphan-block-ontology\n  collapsed:: true\n\n  - **Identification**\n\n    - domain-prefix:: BC\n\n    - sequence-number:: 0016\n\n    - filename-history:: [\"BC-0016-orphan-block.md\"]\n    - public-access:: true\n    - ontology:: true\n    - term-id:: BC-0016\n    - preferred-term:: Orphan Block\n    - source-domain:: blockchain\n    - status:: complete\n    - version:: 1.0.0\n    - last-updated:: 2025-10-28\n\n  - **Definition**\n    - definition:: Valid block not in longest chain within blockchain systems, providing essential functionality for distributed ledger technology operations and properties.\n    - maturity:: mature\n    - source:: [[ISO/IEC 23257:2021]], [[IEEE 2418.1]], [[NIST NISTIR]]\n    - authority-score:: 0.95\n\n  - **Semantic Classification**\n    - owl:class:: bc:OrphanBlock\n    - owl:physicality:: VirtualEntity\n    - owl:role:: Object\n    - owl:inferred-class:: bc:VirtualObject\n    - belongsToDomain:: [[BlockchainDomain]]\n    - implementedInLayer:: [[ConceptualLayer]]\n\n  - #### Relationships\n    id:: orphan-block-relationships\n    - is-subclass-of:: [[Blockchain Entity]], [[DistributedDataStructure]]\n\n  - #### OWL Axioms\n    id:: orphan-block-owl-axioms\n    collapsed:: true\n    - ```clojure\n      Prefix(:=<http://metaverse-ontology.org/blockchain#>)\nPrefix(owl:=<http://www.w3.org/2002/07/owl#>)\nPrefix(rdf:=<http://www.w3.org/1999/02/22-rdf-syntax-ns#>)\nPrefix(xml:=<http://www.w3.org/XML/1998/namespace>)\nPrefix(xsd:=<http://www.w3.org/2001/XMLSchema#>)\nPrefix(rdfs:=<http://www.w3.org/2000/01/rdf-schema#>)\nPrefix(dct:=<http://purl.org/dc/terms/>)\n\nOntology(<http://metaverse-ontology.org/blockchain/BC-0016>\n  Import(<http://metaverse-ontology.org/blockchain/core>)\n\n  ## Class Declaration\n  Declaration(Class(:OrphanBlock))\n\n  ## Subclass Relationships\n  SubClassOf(:OrphanBlock :DistributedDataStructure)\n  SubClassOf(:OrphanBlock :BlockchainEntity)\n\n  ## Essential Properties\n  SubClassOf(:OrphanBlock\n    (ObjectSomeValuesFrom :partOf :Blockchain))\n\n  SubClassOf(:OrphanBlock\n    (ObjectSomeValuesFrom :hasProperty :Property))\n\n  ## Data Properties\n  DataPropertyAssertion(:hasIdentifier :OrphanBlock \"BC-0016\"^^xsd:string)\n  DataPropertyAssertion(:hasAuthorityScore :OrphanBlock \"1.0\"^^xsd:decimal)\n  DataPropertyAssertion(:isFoundational :OrphanBlock \"true\"^^xsd:boolean)\n\n  ## Object Properties\n  ObjectPropertyAssertion(:enablesFeature :OrphanBlock :BlockchainFeature)\n  ObjectPropertyAssertion(:relatesTo :OrphanBlock :RelatedConcept)\n\n  ## Annotations\n  AnnotationAssertion(rdfs:label :OrphanBlock \"Orphan Block\"@en)\n  AnnotationAssertion(rdfs:comment :OrphanBlock\n    \"Valid block not in longest chain\"@en)\n  AnnotationAssertion(dct:description :OrphanBlock\n    \"Foundational blockchain concept with formal ontological definition\"@en)\n  AnnotationAssertion(:termID :OrphanBlock \"BC-0016\")\n  AnnotationAssertion(:priority :OrphanBlock \"1\"^^xsd:integer)\n  AnnotationAssertion(:category :OrphanBlock \"blockchain-fundamentals\"@en)\n)\n      ```\n\n- ## About Orphan Block\n  id:: orphan-block-about\n\n  - Valid block not in longest chain within blockchain systems, providing essential functionality for distributed ledger technology operations and properties.\n  -\n  - ### Key Characteristics\n    id:: orphan-block-characteristics\n    - 1. **Definitional Property**: Core defining characteristic\n    - 2. **Functional Property**: Operational behavior\n    - 3. **Structural Property**: Compositional elements\n    - 4. **Security Property**: Security guarantees provided\n    - 5. **Performance Property**: Efficiency considerations\n  -\n  - ### Technical Components\n    id:: orphan-block-components\n    - **Implementation**: How concept is realized technically\n    - **Verification**: Methods for validating correctness\n    - **Interaction**: Relationships with other components\n    - **Constraints**: Technical limitations and requirements\n  -\n  - ### Use Cases\n    id:: orphan-block-use-cases\n    - **1. Core Blockchain Operation**\n    - **Application**: Fundamental blockchain functionality\n    - **Example**: Practical implementation in major blockchains\n    - **Requirements**: Technical prerequisites\n    - **Benefits**: Value provided to blockchain systems\n  -\n  - ### Standards & References\n    id:: orphan-block-standards\n    - [[ISO/IEC 23257:2021]] - Blockchain and distributed ledger technologies\n    - [[IEEE 2418.1]] - Blockchain and distributed ledger technologies\n    - [[NIST NISTIR]] - Blockchain and distributed ledger technologies\n  -\n\n\n## Academic Context\n\n- Orphan blocks are valid blocks mined and broadcast to a blockchain network but not included in the main chain due to temporary forks or simultaneous block discoveries.\n  - They arise when two miners produce valid blocks nearly simultaneously, creating competing chains; the network eventually accepts the longest valid chain, discarding the shorter one.\n  - This phenomenon exemplifies the decentralised consensus mechanism fundamental to blockchain security and integrity.\n- Academically, orphan blocks illustrate network stability and fault tolerance in distributed ledger technologies.\n  - They highlight how consensus protocols resolve conflicts and maintain a single, trusted ledger despite network latency and propagation delays.\n\n## Current Landscape (2025)\n\n- Orphan blocks remain an inherent aspect of Proof-of-Work (PoW) blockchains like Bitcoin and Ethereum, despite network upgrades aimed at reducing their frequency.\n  - Improvements such as faster block propagation protocols and optimised peer-to-peer communication have lowered orphan rates, enhancing transaction finality and network efficiency.\n- Major blockchain platforms continue to monitor orphan block occurrences as indicators of network health and miner competition.\n- In the UK, blockchain infrastructure providers and crypto exchanges incorporate orphan block considerations into transaction confirmation policies to mitigate user-facing delays.\n- Technical limitations persist:\n  - Orphan blocks cause temporary transaction confirmation delays as transactions must be re-included in subsequent blocks.\n  - They do not compromise blockchain integrity but require careful handling in wallet and exchange software to avoid user confusion.\n- Standards and frameworks increasingly address orphan blocks in risk disclosures and network performance metrics, reflecting their operational significance.\n\n## Research & Literature\n\n- Key academic sources include:\n  - Sompolinsky, Y., & Zohar, A. (2015). \"Secure High-Rate Transaction Processing in Bitcoin.\" *Financial Cryptography and Data Security*, Lecture Notes in Computer Science, vol 8975. DOI: 10.1007/978-3-662-48051-9_14\n  - Gervais, A., et al. (2016). \"On the Security and Performance of Proof of Work Blockchains.\" *ACM SIGSAC Conference on Computer and Communications Security*. DOI: 10.1145/2976749.2978390\n  - These papers analyse orphan blocks’ impact on security, throughput, and consensus finality.\n- Ongoing research explores:\n  - Protocol enhancements to reduce orphan rates without compromising decentralisation.\n  - Alternative consensus mechanisms (e.g., Proof-of-Stake) that inherently minimise orphan block occurrences.\n  - Network topology optimisation to improve block propagation speed.\n\n## UK Context\n\n- The UK hosts several blockchain innovation hubs, including Manchester and Leeds, where research into blockchain scalability and security incorporates orphan block dynamics.\n- Sheffield and Newcastle-based fintech startups integrate orphan block awareness into their blockchain-based financial products to ensure robust transaction processing.\n- British regulatory bodies, such as the Financial Conduct Authority (FCA), recommend clear communication about transaction finality and orphan block implications to protect consumers.\n- UK academic institutions contribute to blockchain research, focusing on network resilience and consensus mechanisms that address orphan block challenges.\n\n## Future Directions\n\n- Emerging trends include:\n  - Deployment of advanced block propagation protocols (e.g., Fibre, Compact Blocks) to further reduce orphan rates.\n  - Increased adoption of hybrid consensus models blending PoW and PoS to balance security and efficiency.\n  - Enhanced tooling for real-time orphan block detection and analytics to improve network monitoring.\n- Anticipated challenges:\n  - Balancing decentralisation with the need for faster consensus and lower orphan rates.\n  - Educating users and developers on orphan block effects to prevent misinterpretation of transaction delays.\n- Research priorities:\n  - Developing consensus algorithms that minimise orphan blocks without centralising control.\n  - Investigating the socio-technical impact of orphan blocks on user trust and network participation.\n\n## References\n\n1. Sompolinsky, Y., & Zohar, A. (2015). Secure High-Rate Transaction Processing in Bitcoin. *Financial Cryptography and Data Security*, Lecture Notes in Computer Science, 8975, 507–527. DOI: 10.1007/978-3-662-48051-9_14\n2. Gervais, A., Karame, G. O., Wüst, K., Glykantzis, V., Ritzdorf, H., & Capkun, S. (2016). On the Security and Performance of Proof of Work Blockchains. *Proceedings of the 2016 ACM SIGSAC Conference on Computer and Communications Security*, 3–16. DOI: 10.1145/2976749.2978390\n3. Nadcab. (2025). Orphan Block in Blockchain: Role, Impact and Solutions. Retrieved November 2025, from https://www.nadcab.com/blog/orphan-block-in-blockchain\n4. Cash2Bitcoin. (2025). Orphaned Block Meaning. Retrieved November 2025, from https://cash2bitcoin.com/glossary/orphaned-block-meaning/\n5. Cube.Exchange. (2025). What is Orphan Block? Definition, Stale Blocks vs Uncles. Retrieved November 2025, from https://www.cube.exchange/what-is/orphan-block\n\n\n## Metadata\n\n\n- **Migration Status**: Ontology block enriched on 2025-11-12\n- **Last Updated**: 2025-11-12\n- **Review Status**: Comprehensive editorial review\n- **Verification**: Academic sources verified\n- **Regional Context**: UK/North England where applicable",
  "properties": {
    "id": "orphan-block-standards",
    "collapsed": "true",
    "- domain-prefix": "BC",
    "- sequence-number": "0016",
    "- filename-history": "[\"BC-0016-orphan-block.md\"]",
    "- public-access": "true",
    "- ontology": "true",
    "- term-id": "BC-0016",
    "- preferred-term": "Orphan Block",
    "- source-domain": "blockchain",
    "- status": "complete",
    "- version": "1.0.0",
    "- last-updated": "2025-10-28",
    "- definition": "Valid block not in longest chain within blockchain systems, providing essential functionality for distributed ledger technology operations and properties.",
    "- maturity": "mature",
    "- source": "[[ISO/IEC 23257:2021]], [[IEEE 2418.1]], [[NIST NISTIR]]",
    "- authority-score": "0.95",
    "- owl:class": "bc:OrphanBlock",
    "- owl:physicality": "VirtualEntity",
    "- owl:role": "Object",
    "- owl:inferred-class": "bc:VirtualObject",
    "- belongsToDomain": "[[BlockchainDomain]]",
    "- implementedInLayer": "[[ConceptualLayer]]",
    "- is-subclass-of": "[[Blockchain Entity]], [[DistributedDataStructure]]"
  },
  "backlinks": [
    "Transaction Confirmation",
    "Telecollaboration and Telepresence"
  ],
  "wiki_links": [
    "BlockchainDomain",
    "ConceptualLayer",
    "Blockchain Entity",
    "ISO/IEC 23257:2021",
    "DistributedDataStructure",
    "NIST NISTIR",
    "IEEE 2418.1"
  ],
  "ontology": {
    "term_id": "BC-0016",
    "preferred_term": "Orphan Block",
    "definition": "Valid block not in longest chain within blockchain systems, providing essential functionality for distributed ledger technology operations and properties.",
    "source_domain": "blockchain",
    "maturity_level": null,
    "authority_score": 0.95
  }
}