{
  "title": "Ouroboros Consensus",
  "content": "- ### OntologyBlock\n  id:: ouroborosconsensus-ontology\n  collapsed:: true\n\n  - **Identification**\n    - domain-prefix:: BC\n    - sequence-number:: 0553\n    - filename-history:: [\"BC-0553-ouroborosconsensus.md\"]\n    - public-access:: true\n    - ontology:: true\n    - term-id:: BC-0553\n    - preferred-term:: Ouroboros Consensus\n    - source-domain:: metaverse\n    - status:: complete\n    - version:: 1.0.0\n    - last-updated:: 2025-11-13\n\n  - **Definition**\n    - definition:: A mathematically-verified PoS consensus protocol using slot leaders to validate transactions and add blocks. Divides time into epochs and slots, with stake pools randomly selected as slot leaders.\n    - maturity:: established\n    - source:: Chimera Prime Research\n    - authority-score:: 0.95\n\n  - **Semantic Classification**\n    - owl:class:: bc:OuroborosConsensus\n    - belongsToDomain:: [[Blockchain]]\n\n  - #### Relationships\n    - is-subclass-of:: [[Proof Of Stake]]\n\n  - #### OWL Axioms\n    - ```clojure\n      ; Class Declaration\n      (Declaration (Class :OuroborosConsensus))\n      (SubClassOf :OuroborosConsensus :ProofOfStake)\n      \n      ; Annotations\n      (AnnotationAssertion rdfs:label :OuroborosConsensus \"Ouroboros Consensus\"@en)\n      (AnnotationAssertion rdfs:comment :OuroborosConsensus\n        \"A mathematically-verified PoS consensus protocol using slot leaders to validate transactions and add blocks. Divides time into epochs and slots, with stake pools randomly selected as slot leaders.\"@en)\n      ```\n\n- ## About Ouroboros Consensus\n  A mathematically-verified PoS consensus protocol using slot leaders to validate transactions and add blocks. Divides time into epochs and slots, with stake pools randomly selected as slot leaders.\n  \n  Rigorously tested in academic settings. Emphasizes provable security guarantees.\n  \n  ### Examples\n  - Cardano\n  \n  ### Historical Context\n  - Developed by IOHK research team, peer-reviewed at CRYPTO 2017.\n\n## Current Landscape (2025)\n\n- Industry adoption and implementations\n  - Metaverse platforms continue to evolve with focus on interoperability and open standards\n  - Web3 integration accelerating with decentralised identity and asset ownership\n  - Enterprise adoption growing in virtual collaboration, training, and digital twins\n  - UK companies increasingly active in metaverse development and immersive technologies\n\n- Technical capabilities\n  - Real-time rendering at photorealistic quality levels\n  - Low-latency networking enabling seamless multi-user experiences\n  - AI-driven content generation and procedural world building\n  - Spatial audio and haptics enhancing immersion\n\n- UK and North England context\n  - Manchester: Digital Innovation Factory supports metaverse startups and research\n  - Leeds: Holovis leads in immersive experiences for entertainment and training\n  - Newcastle: University research in spatial computing and interactive systems\n  - Sheffield: Advanced manufacturing using digital twin technology\n\n- Standards and frameworks\n  - Metaverse Standards Forum driving interoperability protocols\n  - WebXR enabling browser-based immersive experiences\n  - glTF and USD for 3D asset interchange\n  - Open Metaverse Interoperability Group defining cross-platform standards\n\n## Metadata\n\n- **Last Updated**: 2025-11-16\n- **Review Status**: Automated remediation with 2025 context\n- **Verification**: Academic sources verified\n- **Regional Context**: UK/North England where applicable",
  "properties": {
    "id": "ouroborosconsensus-ontology",
    "collapsed": "true",
    "- domain-prefix": "BC",
    "- sequence-number": "0553",
    "- filename-history": "[\"BC-0553-ouroborosconsensus.md\"]",
    "- public-access": "true",
    "- ontology": "true",
    "- term-id": "BC-0553",
    "- preferred-term": "Ouroboros Consensus",
    "- source-domain": "metaverse",
    "- status": "complete",
    "- version": "1.0.0",
    "- last-updated": "2025-11-13",
    "- definition": "A mathematically-verified PoS consensus protocol using slot leaders to validate transactions and add blocks. Divides time into epochs and slots, with stake pools randomly selected as slot leaders.",
    "- maturity": "established",
    "- source": "Chimera Prime Research",
    "- authority-score": "0.95",
    "- owl:class": "bc:OuroborosConsensus",
    "- belongsToDomain": "[[Blockchain]]",
    "- is-subclass-of": "[[Proof Of Stake]]"
  },
  "backlinks": [
    "Sybil Attack"
  ],
  "wiki_links": [
    "Proof Of Stake",
    "Blockchain"
  ],
  "ontology": {
    "term_id": "BC-0553",
    "preferred_term": "Ouroboros Consensus",
    "definition": "A mathematically-verified PoS consensus protocol using slot leaders to validate transactions and add blocks. Divides time into epochs and slots, with stake pools randomly selected as slot leaders.",
    "source_domain": "metaverse",
    "maturity_level": null,
    "authority_score": 0.95
  }
}