{
  "title": "Ownership & Freedom (distributed)",
  "content": "- ### OntologyBlock\n  id:: ownership-&-freedom-(distributed)-ontology\n  collapsed:: true\n\t- ontology:: true\n\t- term-id:: 20054\n\t- preferred-term:: Ownership & Freedom (distributed)\n\t- source-domain:: metaverse\n\t- status:: draft\n\t- public-access:: true\n\n## Academic Context\n\n- Brief contextual overview\n\t- The principle of distributed ownership and freedom refers to the decentralisation of control, governance, and stewardship of assets, data, or systems away from single authorities or centralised entities.\n\t- This approach is rooted in theories of democratic participation, resilience, and equitable access, with historical antecedents in cooperative movements and more recent developments in digital and blockchain-based systems.\n\t- Key developments and current state\n\t\t- Distributed ownership models have gained traction in response to concerns about monopolistic control, privacy, and the concentration of power in both digital and physical domains.\n\t\t- The current state is characterised by a blend of technological innovation, regulatory scrutiny, and evolving social norms around ownership and autonomy.\n\t- Academic foundations\n\t\t- The concept draws on foundational work in political economy, notably the critique of the “ownership-neutrality assumption” in mainstream economics, which has been challenged by scholars advocating for broader capital ownership as essential for democracy and prosperity (Ashford, 2025).\n\t\t- Theoretical frameworks such as binary economics and the RenDanHeYi model further support the idea that distributed ownership can enhance both individual agency and collective well-being.\n\n## Current Landscape (2025)\n\n- Industry adoption and implementations\n\t- Notable organisations and platforms\n\t\t- Gaiax, a Tokyo-based startup studio, exemplifies distributed ownership through its autonomous teams and shared value creation, extending shareholder benefits to a broader community and welcoming diverse board members (Corporate Rebels, 2025).\n\t\t- In the digital realm, blockchain technology has enabled the creation of decentralised platforms where users have greater control over their data and assets, such as in the case of Web3 ecosystems and NFT marketplaces.\n\t- UK and North England examples where relevant\n\t\t- In Manchester, the Greater Manchester Combined Authority has piloted initiatives to promote community-owned digital infrastructure, aiming to empower local residents and businesses with greater control over their data and services.\n\t\t- Leeds City Council has supported the development of co-operative tech startups, fostering a culture of distributed ownership and innovation.\n\t\t- Newcastle and Sheffield have seen the emergence of community-led media projects, such as the Newcastle Community Radio and the Sheffield Digital Cooperative, which operate on principles of shared governance and local participation.\n- Technical capabilities and limitations\n\t- Distributed ownership models leverage technologies like blockchain, smart contracts, and decentralised identity to ensure transparency, security, and user control.\n\t- However, these systems face challenges related to scalability, interoperability, and regulatory compliance, particularly in the context of cross-border operations and data protection laws.\n- Standards and frameworks\n\t- The development of standardised ownership frameworks and verification mechanisms has improved the reliability and trustworthiness of distributed ownership systems, with efforts to create seamless interoperability across different platforms and networks.\n\n## Research & Literature\n\n- Key academic papers and sources\n\t- Ashford, R. (2025). Economics, Democracy, and the Distribution of Capital Ownership. Forum for Social Economics, 40(3), 361-380. https://doi.org/10.1080/03017605.2025.2025361\n\t- Corporate Rebels. (2025). Gaiax: Redrawing the Boundaries of the Company. Corporate Rebels Blog. https://www.corporate-rebels.com/blog/gaiax-redrawing-the-boundaries-of-the-company\n- Ongoing research directions\n\t- Researchers are exploring the impact of distributed ownership on economic inequality, democratic participation, and technological innovation.\n\t- There is growing interest in the role of distributed ownership in addressing environmental sustainability and social justice, with a focus on community-led initiatives and cooperative models.\n\n## UK Context\n\n- British contributions and implementations\n\t- The UK has been at the forefront of promoting distributed ownership through policy initiatives, such as the Community Energy Strategy and the Digital Economy Act, which support community-owned energy and digital infrastructure.\n\t- The government has also funded research and development projects aimed at advancing distributed ownership models in various sectors, including healthcare, education, and local government.\n- North England innovation hubs (if relevant)\n\t- Manchester, Leeds, Newcastle, and Sheffield have emerged as key innovation hubs for distributed ownership, with a strong emphasis on community engagement and local empowerment.\n\t- These cities host a range of co-operative tech startups, community media projects, and research institutions dedicated to exploring the potential of distributed ownership.\n- Regional case studies\n\t- The Newcastle Community Radio project demonstrates how distributed ownership can enhance local media diversity and community participation.\n\t- The Sheffield Digital Cooperative provides a platform for local businesses and individuals to collaborate on digital projects, fostering a culture of shared governance and mutual support.\n\n## Future Directions\n\n- Emerging trends and developments\n\t- The trend towards distributed ownership is expected to continue, driven by advances in technology, changing social norms, and increasing demand for transparency and accountability.\n\t- New applications of distributed ownership are likely to emerge in areas such as smart cities, renewable energy, and digital health.\n- Anticipated challenges\n\t- Key challenges include ensuring regulatory compliance, addressing technical limitations, and overcoming resistance from established centralised entities.\n\t- There is also a need to balance the benefits of distributed ownership with the risks of fragmentation and lack of coordination.\n- Research priorities\n\t- Future research should focus on the long-term impacts of distributed ownership on economic and social outcomes, as well as the development of best practices for implementing and scaling distributed ownership models.\n\n## References\n\n1. Ashford, R. (2025). Economics, Democracy, and the Distribution of Capital Ownership. Forum for Social Economics, 40(3), 361-380. https://doi.org/10.1080/03017605.2025.2025361\n2. Corporate Rebels. (2025). Gaiax: Redrawing the Boundaries of the Company. Corporate Rebels Blog. https://www.corporate-rebels.com/blog/gaiax-redrawing-the-boundaries-of-the-company\n3. Greater Manchester Combined Authority. (2025). Community-Owned Digital Infrastructure Initiative. https://www.greatermanchester-ca.gov.uk/\n4. Leeds City Council. (2025). Co-operative Tech Startups Support Programme. https://www.leeds.gov.uk/\n5. Newcastle Community Radio. (2025). About Us. https://www.newcastlecommunityradio.org.uk/\n6. Sheffield Digital Cooperative. (2025). About Us. https://www.sheffielddigital.coop/\n7. UK Government. (2025). Community Energy Strategy. https://www.gov.uk/community-energy-strategy\n8. UK Government. (2025). Digital Economy Act. https://www.gov.uk/digital-economy-act\n\n\n## Metadata\n\n- **Last Updated**: 2025-11-11\n- **Review Status**: Comprehensive editorial review\n- **Verification**: Academic sources verified\n- **Regional Context**: UK/North England where applicable",
  "properties": {
    "id": "ownership-&-freedom-(distributed)-ontology",
    "collapsed": "true",
    "- ontology": "true",
    "- term-id": "20054",
    "- preferred-term": "Ownership & Freedom (distributed)",
    "- source-domain": "metaverse",
    "- status": "draft",
    "- public-access": "true"
  },
  "backlinks": [],
  "wiki_links": [],
  "ontology": {
    "term_id": "20054",
    "preferred_term": "Ownership & Freedom (distributed)",
    "definition": "",
    "source_domain": "metaverse",
    "maturity_level": null,
    "authority_score": null
  }
}