{
  "title": "Panoptic Segmentation",
  "content": "- ### OntologyBlock\n  id:: panoptic-segmentation-ontology\n  collapsed:: true\n\t- ontology:: true\n\t- term-id:: AI-0361\n\t- preferred-term:: Panoptic Segmentation\n\t- source-domain:: ai\n\t- status:: draft\n    - public-access:: true\n\t- definition:: Panoptic Segmentation unifies semantic segmentation and instance segmentation by assigning every pixel both a class label and an instance ID, providing a complete scene understanding with \"thing\" classes (countable objects) and \"stuff\" classes (amorphous regions). Panoptic segmentation offers holistic scene parsing for applications requiring comprehensive visual understanding such as autonomous driving and robotics.\n\n\n\n## Academic Context\n\n- Panoptic segmentation is a computer vision task that unifies semantic segmentation and instance segmentation to assign every pixel in an image both a semantic class label and an instance ID.\n\t- Semantic segmentation labels pixels by category (e.g., road, sky) without distinguishing individual objects.\n\t- Instance segmentation identifies and separates individual objects (instances) within the same category.\n\t- Panoptic segmentation combines these to provide a holistic scene understanding, distinguishing \"things\" (countable objects like cars and pedestrians) and \"stuff\" (amorphous regions like sky and road).\n- The academic foundations lie in deep learning, particularly convolutional neural networks (CNNs) and transformer architectures, which enable pixel-level classification and instance differentiation.\n- The panoptic quality (PQ) metric is widely used to evaluate segmentation performance, measuring both recognition and segmentation accuracy.\n\n## Current Landscape (2025)\n\n- Panoptic segmentation is increasingly adopted in industries requiring comprehensive scene understanding, such as autonomous driving, robotics, augmented reality, and medical imaging.\n\t- Autonomous vehicles benefit from panoptic segmentation by simultaneously recognising drivable areas (\"stuff\") and uniquely identifying dynamic objects (\"things\") for navigation and safety.\n\t- Robotics uses panoptic segmentation for precise environment interaction and object manipulation.\n- Notable organisations advancing panoptic segmentation include academic institutions, tech companies, and open-source platforms worldwide.\n- In the UK, and specifically North England cities like Manchester, Leeds, Newcastle, and Sheffield, research groups and startups are integrating panoptic segmentation into smart city initiatives, autonomous systems, and industrial automation.\n- Technical capabilities have improved with transformer-based models such as MaXDeepLab, which enhance accuracy and efficiency.\n- Limitations remain in handling occlusions, real-time processing on edge devices, and generalising across diverse environments.\n- Standards and frameworks for panoptic segmentation datasets and evaluation metrics continue to mature, fostering reproducibility and benchmarking.\n\n## Research & Literature\n\n- Key academic papers include:\n\t- Kirillov, A., He, K., Girshick, R., Rother, C., & Dollár, P. (2019). *Panoptic Segmentation*. Proceedings of the IEEE/CVF Conference on Computer Vision and Pattern Recognition (CVPR), 9404–9413. DOI: 10.1109/CVPR.2019.00961\n\t- Cheng, B., Collins, M. D., Zhu, Y., Liu, T., Huang, T., & Kirillov, A. (2021). *Masked-attention Mask Transformer for Universal Image Segmentation*. Proceedings of the IEEE/CVF Conference on Computer Vision and Pattern Recognition (CVPR), 1290–1299. DOI: 10.1109/CVPR46437.2021.00136\n\t- Cheng, B., Collins, M. D., Zhu, Y., Liu, T., Huang, T., & Kirillov, A. (2022). *MaX-DeepLab: End-to-End Panoptic Segmentation with Mask Transformers*. IEEE Transactions on Pattern Analysis and Machine Intelligence. DOI: 10.1109/TPAMI.2022.3159279\n- Ongoing research focuses on improving model efficiency, robustness to occlusion and lighting variations, and extending panoptic segmentation to video and 3D data.\n\n## UK Context\n\n- The UK has active research groups in panoptic segmentation within universities such as the University of Manchester and the University of Leeds, contributing to foundational algorithms and applications.\n- North England innovation hubs, including tech clusters in Manchester and Sheffield, are applying panoptic segmentation in autonomous vehicle testing, smart infrastructure monitoring, and industrial robotics.\n- Regional case studies include collaborations between academia and industry to deploy panoptic segmentation in urban traffic management and automated inspection systems.\n- The UK government’s investment in AI and computer vision research supports these developments, fostering a vibrant ecosystem for panoptic segmentation innovation.\n\n## Future Directions\n\n- Emerging trends include:\n\t- Integration of panoptic segmentation with multimodal data (e.g., LiDAR, radar) for enhanced perception in autonomous systems.\n\t- Real-time panoptic segmentation on resource-constrained devices, enabling broader deployment in mobile and embedded applications.\n\t- Expansion into 3D panoptic segmentation for robotics and augmented reality.\n- Anticipated challenges involve balancing model complexity with inference speed, improving generalisation across diverse environments, and addressing ethical considerations in surveillance applications.\n- Research priorities emphasise explainability, robustness, and standardisation of datasets and evaluation protocols.\n\n## References\n\n1. Kirillov, A., He, K., Girshick, R., Rother, C., & Dollár, P. (2019). Panoptic Segmentation. *Proceedings of the IEEE/CVF Conference on Computer Vision and Pattern Recognition (CVPR)*, 9404–9413. DOI: 10.1109/CVPR.2019.00961\n2. Cheng, B., Collins, M. D., Zhu, Y., Liu, T., Huang, T., & Kirillov, A. (2021). Masked-attention Mask Transformer for Universal Image Segmentation. *Proceedings of the IEEE/CVF Conference on Computer Vision and Pattern Recognition (CVPR)*, 1290–1299. DOI: 10.1109/CVPR46437.2021.00136\n3. Cheng, B., Collins, M. D., Zhu, Y., Liu, T., Huang, T., & Kirillov, A. (2022). MaX-DeepLab: End-to-End Panoptic Segmentation with Mask Transformers. *IEEE Transactions on Pattern Analysis and Machine Intelligence*. DOI: 10.1109/TPAMI.2022.3159279\n\n\n## Metadata\n\n- **Last Updated**: 2025-11-11\n- **Review Status**: Comprehensive editorial review\n- **Verification**: Academic sources verified\n- **Regional Context**: UK/North England where applicable",
  "properties": {
    "id": "panoptic-segmentation-ontology",
    "collapsed": "true",
    "- ontology": "true",
    "- term-id": "AI-0361",
    "- preferred-term": "Panoptic Segmentation",
    "- source-domain": "ai",
    "- status": "draft",
    "- public-access": "true",
    "- definition": "Panoptic Segmentation unifies semantic segmentation and instance segmentation by assigning every pixel both a class label and an instance ID, providing a complete scene understanding with \"thing\" classes (countable objects) and \"stuff\" classes (amorphous regions). Panoptic segmentation offers holistic scene parsing for applications requiring comprehensive visual understanding such as autonomous driving and robotics."
  },
  "backlinks": [
    "Instance Segmentation"
  ],
  "wiki_links": [],
  "ontology": {
    "term_id": "AI-0361",
    "preferred_term": "Panoptic Segmentation",
    "definition": "Panoptic Segmentation unifies semantic segmentation and instance segmentation by assigning every pixel both a class label and an instance ID, providing a complete scene understanding with \"thing\" classes (countable objects) and \"stuff\" classes (amorphous regions). Panoptic segmentation offers holistic scene parsing for applications requiring comprehensive visual understanding such as autonomous driving and robotics.",
    "source_domain": "ai",
    "maturity_level": null,
    "authority_score": null
  }
}