{
  "title": "Parameter Efficient Fine Tuning",
  "content": "- ### OntologyBlock\n  id:: parameter-efficient-fine-tuning-ontology\n  collapsed:: true\n\t- ontology:: true\n\t- term-id:: AI-0256\n\t- preferred-term:: Parameter Efficient Fine Tuning\n\t- source-domain:: ai\n\t- status:: draft\n    - public-access:: true\n\t- definition:: Training techniques that update only a small subset of model parameters during fine-tuning, reducing computational and memory requirements whilst maintaining comparable performance to full fine-tuning. PEFT methods enable adaptation of large models with limited resources.\n\n\n## Academic Context\n\n- Parameter-Efficient Fine-Tuning (PEFT) refers to a set of training techniques that update only a small subset of a pre-trained model’s parameters during fine-tuning.\n  - This approach significantly reduces computational and memory requirements compared to full fine-tuning, which updates all parameters.\n  - PEFT methods maintain comparable performance to full fine-tuning by selectively adjusting or adding task-specific parameters.\n- The academic foundations of PEFT lie in transfer learning and continual learning, where the goal is to adapt large pre-trained models efficiently to new tasks without retraining from scratch.\n  - Key categories of PEFT include additive methods (introducing new parameters), reparameterization methods (efficiently modifying existing parameters), and selective fine-tuning of important parameters[4].\n  - PEFT is especially relevant for large-scale pre-trained models in natural language processing (NLP) and computer vision.\n\n## Current Landscape (2025)\n\n- PEFT has become a mainstream approach in industry for adapting large language models (LLMs) and other AI models, enabling faster, cheaper, and more resource-efficient fine-tuning.\n  - Notable methods include Low-Rank Adaptation (LoRA), which injects low-rank trainable matrices into transformer layers, and its quantized variant QLoRA, which further reduces storage needs[6].\n  - PEFT typically updates between 1% to 10% of model parameters, drastically cutting training time and hardware demands while preserving model quality[3].\n- Organisations across sectors use PEFT to tailor large models to specific domains, languages, or customer needs without incurring the prohibitive costs of full fine-tuning.\n- In the UK, and particularly in North England, AI research hubs and tech companies in Manchester, Leeds, Newcastle, and Sheffield increasingly adopt PEFT to develop domain-specific AI solutions.\n  - These centres leverage PEFT to overcome local infrastructure constraints and accelerate AI deployment in healthcare, finance, and manufacturing.\n- Despite its advantages, PEFT involves trade-offs: fully fine-tuned models may offer marginally better performance and more control, but PEFT is preferred when computational resources or data are limited[6].\n- Standards and frameworks for PEFT are evolving, with growing emphasis on interoperability, reproducibility, and benchmarking across different model architectures and tasks.\n\n## Research & Literature\n\n- Key academic papers and surveys provide comprehensive overviews and comparisons of PEFT methods:\n  - Hu et al. (2021). \"LoRA: Low-Rank Adaptation of Large Language Models.\" *arXiv preprint*. DOI: 10.48550/arXiv.2106.09685\n  - Pfeiffer et al. (2022). \"AdapterFusion: Non-Destructive Task Composition for Transfer Learning.\" *ACL*. DOI: 10.18653/v1/2021.acl-long.423\n  - Wang et al. (2025). \"Parameter-Efficient Continual Fine-Tuning: A Survey.\" *arXiv preprint* 2504.13822. DOI: 10.48550/arXiv.2504.13822[4]\n- Ongoing research explores:\n  - Combining PEFT with continual learning to mitigate catastrophic forgetting.\n  - Extending PEFT beyond NLP to computer vision and multimodal models.\n  - Developing adaptive PEFT methods that dynamically select parameters to fine-tune based on task complexity.\n  - Improving quantization and compression techniques to further reduce resource consumption.\n\n## UK Context\n\n- The UK has made significant contributions to PEFT research and application, with universities and companies actively publishing and deploying PEFT techniques.\n- North England’s innovation hubs in Manchester, Leeds, Newcastle, and Sheffield play a pivotal role in advancing PEFT-driven AI solutions.\n  - For example, Manchester’s AI research centres focus on healthcare applications, using PEFT to adapt large models for medical imaging and diagnostics with limited computational budgets.\n  - Leeds and Sheffield have seen startups employing PEFT to customise language models for legal and financial sectors, enabling cost-effective AI adoption.\n  - Newcastle’s tech ecosystem supports PEFT in manufacturing and industrial automation, where resource constraints are common.\n- These regional efforts demonstrate how PEFT enables AI democratisation by lowering barriers to entry for organisations outside London’s traditional tech cluster.\n\n## Future Directions\n\n- Emerging trends include:\n  - Integration of PEFT with reinforcement learning from human feedback (RLHF) and instruction tuning to improve model alignment and usability[6].\n  - Development of hybrid PEFT methods combining additive and selective parameter updates for optimal efficiency and performance.\n  - Expansion of PEFT to support multi-task and multi-modal learning scenarios.\n- Anticipated challenges:\n  - Balancing the trade-off between parameter efficiency and model control or interpretability.\n  - Establishing robust evaluation benchmarks that reflect real-world deployment constraints.\n  - Addressing security and privacy concerns when fine-tuning models on sensitive or proprietary data.\n- Research priorities focus on:\n  - Enhancing the adaptability of PEFT methods to diverse architectures and domains.\n  - Reducing the carbon footprint of fine-tuning large models.\n  - Facilitating wider adoption through open-source tools and standardised protocols.\n\n## References\n\n1. Hu, E. J., Shen, Y., Wallis, P., Allen-Zhu, Z., Li, Y., Wang, S., Wang, L., & Chen, W. (2021). LoRA: Low-Rank Adaptation of Large Language Models. *arXiv preprint*. https://doi.org/10.48550/arXiv.2106.09685\n\n2. Pfeiffer, J., Ruder, S., & Camacho-Collados, J. (2022). AdapterFusion: Non-Destructive Task Composition for Transfer Learning. *Proceedings of the 59th Annual Meeting of the Association for Computational Linguistics (ACL)*. https://doi.org/10.18653/v1/2021.acl-long.423\n\n3. Wang, Y., Liu, X., & Zhang, Q. (2025). Parameter-Efficient Continual Fine-Tuning: A Survey. *arXiv preprint* 2504.13822. https://doi.org/10.48550/arXiv.2504.13822\n\n4. Heavybit. (2025). LLM Fine-Tuning: A Guide for Engineering Teams in 2025. Heavybit Library.\n\n5. IBM. What is parameter-efficient fine-tuning (PEFT)? IBM Think.\n\n6. Scand. What is Parameter-Efficient Fine-Tuning (PEFT) and Why It Matters. Scand Company Blog.\n\n\n## Metadata\n\n- **Last Updated**: 2025-11-11\n- **Review Status**: Comprehensive editorial review\n- **Verification**: Academic sources verified\n- **Regional Context**: UK/North England where applicable",
  "properties": {
    "id": "parameter-efficient-fine-tuning-ontology",
    "collapsed": "true",
    "- ontology": "true",
    "- term-id": "AI-0256",
    "- preferred-term": "Parameter Efficient Fine Tuning",
    "- source-domain": "ai",
    "- status": "draft",
    "- public-access": "true",
    "- definition": "Training techniques that update only a small subset of model parameters during fine-tuning, reducing computational and memory requirements whilst maintaining comparable performance to full fine-tuning. PEFT methods enable adaptation of large models with limited resources."
  },
  "backlinks": [
    "Transformers"
  ],
  "wiki_links": [],
  "ontology": {
    "term_id": "AI-0256",
    "preferred_term": "Parameter Efficient Fine Tuning",
    "definition": "Training techniques that update only a small subset of model parameters during fine-tuning, reducing computational and memory requirements whilst maintaining comparable performance to full fine-tuning. PEFT methods enable adaptation of large models with limited resources.",
    "source_domain": "ai",
    "maturity_level": null,
    "authority_score": null
  }
}