{
  "title": "PathPlanning",
  "content": "- ### OntologyBlock\n  id:: pathplanning-ontology\n  collapsed:: true\n\t- ontology:: true\n\t- term-id:: MV-0046\n\t- preferred-term:: PathPlanning\n\t- source-domain:: metaverse\n\t- status:: draft\n    - public-access:: true\n\t- definition:: A component of the metaverse ecosystem.\n\t- maturity:: draft\n\t- owl:class:: mv:PathPlanning\n\t- owl:physicality:: ConceptualEntity\n\t- owl:role:: Concept\n\t- is-subclass-of:: [[ArtificialIntelligence]]\n\t- belongsToDomain:: [[MetaverseDomain]]\n\t- #### CrossDomainBridges\n\t\t- dt:uses:: [[Machine Learning]]\n\t\t- dt:uses:: [[Computer Vision]]\n\n## OWL Formal Semantics\n\n```clojure\n;; OWL Functional Syntax\n\n(Declaration (Class :PathPlanning))\n\n;; Annotations\n(AnnotationAssertion rdfs:label :PathPlanning \"PathPlanning\"@en)\n(AnnotationAssertion rdfs:comment :PathPlanning \"Algorithms and methods for determining optimal routes for autonomous agents or vehicles in metaverse environments.\"@en)\n\n;; Data Properties\n(AnnotationAssertion dcterms:identifier :PathPlanning \"mv-0046\"^^xsd:string)\n```",
  "properties": {
    "id": "pathplanning-ontology",
    "collapsed": "true",
    "- ontology": "true",
    "- term-id": "MV-0046",
    "- preferred-term": "PathPlanning",
    "- source-domain": "metaverse",
    "- status": "draft",
    "- public-access": "true",
    "- definition": "A component of the metaverse ecosystem.",
    "- maturity": "draft",
    "- owl:class": "mv:PathPlanning",
    "- owl:physicality": "ConceptualEntity",
    "- owl:role": "Concept",
    "- is-subclass-of": "[[ArtificialIntelligence]]",
    "- belongsToDomain": "[[MetaverseDomain]]",
    "- dt:uses": "[[Computer Vision]]"
  },
  "backlinks": [
    "Mobile-Robot",
    "Machine Learning",
    "RB-0005-industrial-robot"
  ],
  "wiki_links": [
    "Computer Vision",
    "MetaverseDomain",
    "ArtificialIntelligence",
    "Machine Learning"
  ],
  "ontology": {
    "term_id": "MV-0046",
    "preferred_term": "PathPlanning",
    "definition": "A component of the metaverse ecosystem.",
    "source_domain": "metaverse",
    "maturity_level": null,
    "authority_score": null
  }
}