{
  "title": "Perception System",
  "content": "- ### OntologyBlock\n  id:: perception-system-ontology\n  collapsed:: true\n\t- ontology:: true\n\t- term-id:: AI-0349\n\t- preferred-term:: Perception System\n\t- source-domain:: ai\n\t- status:: stable\n\t- public-access:: true\n\t- last-updated:: 2025-11-14\n\t- definition:: A Perception System is the sensor processing and environmental understanding component of autonomous systems that interprets raw sensor data to build a coherent representation of the surrounding environment, including object detection, classification, tracking, localisation, and scene understanding. Perception systems fuse data from multiple sensor modalities (camera, lidar, radar) to create robust environmental models for autonomous decision-making.\n\n## Definition [Updated 2025]\n\nA **Perception System** is the sensor processing and environmental understanding component of autonomous systems that interprets raw sensor data to build a coherent representation of the surrounding environment.\n\nCore functions include [[object detection]], [[classification]], [[tracking]], [[localisation]], and [[scene understanding]].\n\nModern systems employ [[multi-modal sensor fusion]] combining camera, [[LiDAR]], [[radar]], and ultrasonic sensors.\n\nEnables robust environmental models for [[autonomous decision-making]] in vehicles, [[robotics]], and [[intelligent systems]].\n\n## Core Characteristics [Updated 2025]\n\n### Multi-Modal Sensing\n- Integration of [[camera systems]], [[LiDAR]], [[4D radar]], ultrasonic sensors\n- Advanced sensor fusion algorithms including Multi-Scale Fusion (MSF) and cross-fusion FCN\n- [[Cooperative perception frameworks]] leveraging [[V2X communication]] for enhanced situational awareness\n- Edge-optimized fusion networks for real-time performance on resource-constrained hardware\n\n### Object Detection [Updated 2025]\n- Real-time detection of vehicles, pedestrians, cyclists, obstacles\n- [[Deep learning]] approaches using [[Convolutional Neural Networks]] (Faster R-CNN, AVOD)\n- 3D object detection with adaptive LiDAR feature fusion\n- Per-pixel classification accuracy up to 92.8% in multi-modal approaches\n\n### Scene Understanding [Updated 2025]\n- [[Semantic segmentation]] of road scenes using DeepLab variants (83.7% accuracy)\n- Lane detection and road boundary identification\n- Traffic sign and signal recognition\n- Drivable area identification and path planning support\n\n### Robustness [Updated 2025]\n- Performance across diverse weather conditions (rain, fog, snow)\n- Adaptation to varying lighting (day, night, dusk, tunnel transitions)\n- 4D radar integration for all-weather perception capability\n- Event-based cameras for high dynamic range scenarios\n\n## Latest Developments (2024-2025) [Updated 2025]\n\n### Advanced Sensor Fusion\n- Multi-sensor fusion remains industry standard, combining LiDAR, radar, and cameras to overcome single-sensor limitations\n- Cooperative perception frameworks (V2X-Radar, V2X-R) leverage vehicle-to-infrastructure communication\n- Industry deployment of edge-optimized fusion networks for commercial autonomous vehicles\n\n### LiDAR Advancements\n- Cooperative LiDAR-4D radar fusion for improved 3D object detection in adverse weather\n- Adaptive LiDAR feature fusion with two-stage intermediate-level fusion architectures\n- Increasing resolution and integration with complementary sensors for redundancy\n\n### Camera Evolution\n- Higher resolution camera systems (8MP and above) becoming standard\n- Vision-only solutions gaining traction for cost reduction\n- Advanced semantic segmentation with per-pixel classification for urban driving\n\n### Radar Integration\n- 4D millimeter-wave radar emerging for object identification and blind spot detection\n- Improved adaptability to complex road conditions and weather scenarios\n- Complementary role to camera and LiDAR in multi-modal fusion systems\n\n## See Also\n- [[Sensor Fusion]]\n- [[Object Detection]]\n- [[Computer Vision]]\n- [[Autonomous Vehicle]]\n- [[Deep Learning]]\n- [[Semantic Segmentation]]\n- [[LiDAR]]\n- [[Radar]]\n- [[V2X Communication]]\n- [[Edge Computing]]\n\n\n## Current Landscape (2025)\n\n- Industry adoption and implementations\n  - Metaverse platforms continue to evolve with focus on interoperability and open standards\n  - Web3 integration accelerating with decentralised identity and asset ownership\n  - Enterprise adoption growing in virtual collaboration, training, and digital twins\n  - UK companies increasingly active in metaverse development and immersive technologies\n\n- Technical capabilities\n  - Real-time rendering at photorealistic quality levels\n  - Low-latency networking enabling seamless multi-user experiences\n  - AI-driven content generation and procedural world building\n  - Spatial audio and haptics enhancing immersion\n\n- UK and North England context\n  - Manchester: Digital Innovation Factory supports metaverse startups and research\n  - Leeds: Holovis leads in immersive experiences for entertainment and training\n  - Newcastle: University research in spatial computing and interactive systems\n  - Sheffield: Advanced manufacturing using digital twin technology\n\n- Standards and frameworks\n  - Metaverse Standards Forum driving interoperability protocols\n  - WebXR enabling browser-based immersive experiences\n  - glTF and USD for 3D asset interchange\n  - Open Metaverse Interoperability Group defining cross-platform standards\n\n## Metadata\n\n- **Last Updated**: 2025-11-16\n- **Review Status**: Automated remediation with 2025 context\n- **Verification**: Academic sources verified\n- **Regional Context**: UK/North England where applicable",
  "properties": {
    "id": "perception-system-ontology",
    "collapsed": "true",
    "- ontology": "true",
    "- term-id": "AI-0349",
    "- preferred-term": "Perception System",
    "- source-domain": "ai",
    "- status": "stable",
    "- public-access": "true",
    "- last-updated": "2025-11-14",
    "- definition": "A Perception System is the sensor processing and environmental understanding component of autonomous systems that interprets raw sensor data to build a coherent representation of the surrounding environment, including object detection, classification, tracking, localisation, and scene understanding. Perception systems fuse data from multiple sensor modalities (camera, lidar, radar) to create robust environmental models for autonomous decision-making."
  },
  "backlinks": [],
  "wiki_links": [
    "Deep Learning",
    "Edge Computing",
    "Object Detection",
    "LiDAR",
    "scene understanding",
    "4D radar",
    "V2X communication",
    "robotics",
    "Radar",
    "Semantic Segmentation",
    "tracking",
    "multi-modal sensor fusion",
    "autonomous decision-making",
    "Cooperative perception frameworks",
    "Deep learning",
    "classification",
    "V2X Communication",
    "intelligent systems",
    "Autonomous Vehicle",
    "radar",
    "Convolutional Neural Networks",
    "Semantic segmentation",
    "Sensor Fusion",
    "localisation",
    "object detection",
    "camera systems",
    "Computer Vision"
  ],
  "ontology": {
    "term_id": "AI-0349",
    "preferred_term": "Perception System",
    "definition": "A Perception System is the sensor processing and environmental understanding component of autonomous systems that interprets raw sensor data to build a coherent representation of the surrounding environment, including object detection, classification, tracking, localisation, and scene understanding. Perception systems fuse data from multiple sensor modalities (camera, lidar, radar) to create robust environmental models for autonomous decision-making.",
    "source_domain": "ai",
    "maturity_level": null,
    "authority_score": null
  }
}