{
  "title": "based on",
  "content": "- ### OntologyBlock\n  id:: performancestandard-ontology\n  collapsed:: true\n\n  - **Identification**\n    - domain-prefix:: RB\n    - sequence-number:: 0107\n    - filename-history:: [\"RB-0107-performancestandard.md\"]\n    - public-access:: true\n    - ontology:: true\n    - term-id:: RB-0107\n    - preferred-term:: based on\n    - source-domain:: metaverse\n    - status:: complete\n    - version:: 1.0.0\n    - last-updated:: 2025-11-13\n\n  - **Definition**\n    - definition:: International standard for quality management systems.\n    - maturity:: established\n    - source:: Chimera Prime Research\n    - authority-score:: 0.95\n\n  - **Semantic Classification**\n    - owl:class:: rb:PerformanceStandard\n    - belongsToDomain:: [[Robotics]]\n\n  - #### Relationships\n    - is-subclass-of:: [[Robot Standard]]\n    - is-subclass-of:: [[Safety Standard]]\n    - is-subclass-of:: [[Robot Standard]]\n    - is-subclass-of:: [[Robot Standard]]\n    - is-subclass-of:: [[Robot Standard]]\n    - is-subclass-of:: [[Robot Standard]]\n    - is-subclass-of:: [[Robot Standard]]\n    - also-known-as:: Robot Operating System\n\n  - #### OWL Axioms\n    - ```clojure\n      ; Class Declaration\n      (Declaration (Class :PerformanceStandard))\n      (SubClassOf :PerformanceStandard :RobotStandard)\n      (SubClassOf :PerformanceStandard :SafetyStandard)\n      (SubClassOf :PerformanceStandard :RobotStandard)\n      (SubClassOf :PerformanceStandard :RobotStandard)\n      (SubClassOf :PerformanceStandard :RobotStandard)\n      (SubClassOf :PerformanceStandard :RobotStandard)\n      (SubClassOf :PerformanceStandard :RobotStandard)\n      \n      ; Annotations\n      (AnnotationAssertion rdfs:label :PerformanceStandard \"based on\"@en)\n      (AnnotationAssertion rdfs:comment :PerformanceStandard\n        \"International standard for quality management systems.\"@en)\n      ```\n\n- ## About based on\n  International standard for quality management systems.\n  \n  Standard that this one is based on or derived from.\n\n## Current Landscape (2025)\n\n- Industry adoption and implementations\n  - Metaverse platforms continue to evolve with focus on interoperability and open standards\n  - Web3 integration accelerating with decentralised identity and asset ownership\n  - Enterprise adoption growing in virtual collaboration, training, and digital twins\n  - UK companies increasingly active in metaverse development and immersive technologies\n\n- Technical capabilities\n  - Real-time rendering at photorealistic quality levels\n  - Low-latency networking enabling seamless multi-user experiences\n  - AI-driven content generation and procedural world building\n  - Spatial audio and haptics enhancing immersion\n\n- UK and North England context\n  - Manchester: Digital Innovation Factory supports metaverse startups and research\n  - Leeds: Holovis leads in immersive experiences for entertainment and training\n  - Newcastle: University research in spatial computing and interactive systems\n  - Sheffield: Advanced manufacturing using digital twin technology\n\n- Standards and frameworks\n  - Metaverse Standards Forum driving interoperability protocols\n  - WebXR enabling browser-based immersive experiences\n  - glTF and USD for 3D asset interchange\n  - Open Metaverse Interoperability Group defining cross-platform standards\n\n## Metadata\n\n- **Last Updated**: 2025-11-16\n- **Review Status**: Automated remediation with 2025 context\n- **Verification**: Academic sources verified\n- **Regional Context**: UK/North England where applicable",
  "properties": {
    "id": "performancestandard-ontology",
    "collapsed": "true",
    "- domain-prefix": "RB",
    "- sequence-number": "0107",
    "- filename-history": "[\"RB-0107-performancestandard.md\"]",
    "- public-access": "true",
    "- ontology": "true",
    "- term-id": "RB-0107",
    "- preferred-term": "based on",
    "- source-domain": "metaverse",
    "- status": "complete",
    "- version": "1.0.0",
    "- last-updated": "2025-11-13",
    "- definition": "International standard for quality management systems.",
    "- maturity": "established",
    "- source": "Chimera Prime Research",
    "- authority-score": "0.95",
    "- owl:class": "rb:PerformanceStandard",
    "- belongsToDomain": "[[Robotics]]",
    "- is-subclass-of": "[[Robot Standard]]",
    "- also-known-as": "Robot Operating System"
  },
  "backlinks": [],
  "wiki_links": [
    "Robotics",
    "Robot Standard",
    "Safety Standard"
  ],
  "ontology": {
    "term_id": "RB-0107",
    "preferred_term": "based on",
    "definition": "International standard for quality management systems.",
    "source_domain": "metaverse",
    "maturity_level": null,
    "authority_score": 0.95
  }
}