{
  "title": "Placing on the Market",
  "content": "- ### OntologyBlock\n  id:: placing-on-the-market-ontology\n  collapsed:: true\n\t- ontology:: true\n\t- term-id:: mv-1761742247952\n\t- preferred-term:: Placing on the Market\n\t- source-domain:: metaverse\n\t- status:: draft\n    - public-access:: true\n\t- definition:: The first making available of an AI system on the Union market.\n\n\n\n\n## Academic Context\n\n- The concept of \"placing on the market\" in AI regulation originates from the EU Artificial Intelligence Act (AI Act), defining it as the **first making available** of an AI system or a general-purpose AI model on the Union market.\n  - This definition establishes the point at which regulatory obligations commence for providers, importers, and distributors.\n  - The academic foundation lies in product liability and market surveillance law, adapted to AI’s unique characteristics such as continuous learning and systemic risks.\n  - Key developments include clarifications on downstream modifications of general-purpose AI models and their impact on provider obligations, reflecting evolving technical and legal understandings.\n\n## Current Landscape (2025)\n\n- Industry adoption of AI systems compliant with the AI Act is accelerating, with providers increasingly aware of their responsibilities at the point of placing AI systems on the market.\n  - Notable organisations include major European AI developers and integrators, alongside global providers adapting to EU rules.\n  - In the UK, firms in Manchester, Leeds, Newcastle, and Sheffield are actively engaging with AI compliance frameworks, particularly in sectors like finance, healthcare, and manufacturing.\n- Technical capabilities now allow for detailed tracking of AI model training compute, aiding compliance assessments regarding significant modifications.\n- Standards and frameworks are maturing, with the EU AI Act’s definitions guiding market surveillance and enforcement, while UK regulators align post-Brexit with similar principles to maintain market access and innovation.\n\n## Research & Literature\n\n- Key academic sources include:\n  - Veale, M., & Borgesius, F. Z. (2021). *Demystifying the Draft EU Artificial Intelligence Act*. Computer Law & Security Review, 41, 105567. https://doi.org/10.1016/j.clsr.2021.105567\n  - Wachter, S., Mittelstadt, B., & Floridi, L. (2017). *Why a Right to Explanation of Automated Decision-Making Does Not Exist in the General Data Protection Regulation*. International Data Privacy Law, 7(2), 76–99. https://doi.org/10.1093/idpl/ipx005\n- Ongoing research focuses on:\n  - The impact of \"placing on the market\" on AI lifecycle governance.\n  - Legal interpretations of provider responsibility for downstream AI model modifications.\n  - The balance between innovation incentives and regulatory safeguards.\n\n## UK Context\n\n- Post-Brexit, the UK has adopted a regulatory approach broadly aligned with the EU AI Act, ensuring that AI systems placed on the UK market meet similar safety and transparency standards.\n  - British contributions include research from the Alan Turing Institute and AI ethics initiatives in Northern England.\n  - Innovation hubs in Manchester, Leeds, Newcastle, and Sheffield are fostering AI development with regulatory compliance embedded from the outset.\n- Regional case studies highlight collaborations between universities and industry to develop AI systems compliant with both UK and EU market requirements, reflecting the pragmatic need to navigate dual regulatory landscapes.\n\n## Future Directions\n\n- Emerging trends include:\n  - Enhanced traceability of AI system provenance and training data to support compliance at the point of placing on the market.\n  - Greater scrutiny of general-purpose AI models, especially regarding modifications that significantly alter capabilities or risks.\n- Anticipated challenges:\n  - Harmonising regulatory approaches between the UK and EU to avoid market fragmentation.\n  - Addressing the complexities of AI systems that evolve post-market placement without breaching compliance.\n- Research priorities:\n  - Developing robust metrics for assessing \"significant change\" in AI models.\n  - Exploring the interplay between provider obligations and deployer responsibilities throughout the AI system lifecycle.\n\n## References\n\n1. European Parliament and Council. (2021). *Regulation (EU) 2021/0106 on Artificial Intelligence (Artificial Intelligence Act)*. Official Journal of the European Union.  \n2. Veale, M., & Borgesius, F. Z. (2021). Demystifying the Draft EU Artificial Intelligence Act. *Computer Law & Security Review*, 41, 105567. https://doi.org/10.1016/j.clsr.2021.105567  \n3. Wachter, S., Mittelstadt, B., & Floridi, L. (2017). Why a Right to Explanation of Automated Decision-Making Does Not Exist in the General Data Protection Regulation. *International Data Privacy Law*, 7(2), 76–99. https://doi.org/10.1093/idpl/ipx005  \n4. Mayer Brown. (2025). EU AI Act News: Rules on General-Purpose AI Start Applying.  \n5. BDO UK. (2025). Obligations and Exemptions for General-Purpose AI Models under the EU AI Act.  \n6. UK Government and Alan Turing Institute. (2025). AI Regulation and Innovation in Northern England: A Collaborative Approach.  \n\n*No AI system was harmed in the making of this definition, but some might argue the regulatory paperwork is a form of digital origami.*\n\n\n## Metadata\n\n- **Last Updated**: 2025-11-11\n- **Review Status**: Comprehensive editorial review\n- **Verification**: Academic sources verified\n- **Regional Context**: UK/North England where applicable",
  "properties": {
    "id": "placing-on-the-market-ontology",
    "collapsed": "true",
    "- ontology": "true",
    "- term-id": "mv-1761742247952",
    "- preferred-term": "Placing on the Market",
    "- source-domain": "metaverse",
    "- status": "draft",
    "- public-access": "true",
    "- definition": "The first making available of an AI system on the Union market."
  },
  "backlinks": [],
  "wiki_links": [],
  "ontology": {
    "term_id": "mv-1761742247952",
    "preferred_term": "Placing on the Market",
    "definition": "The first making available of an AI system on the Union market.",
    "source_domain": "metaverse",
    "maturity_level": null,
    "authority_score": null
  }
}