{
  "title": "Planning Kanban - currently broken",
  "content": "- ### OntologyBlock\n  id:: planning-kanban---currently-broken-ontology\n  collapsed:: true\n\t- ontology:: true\n\t- term-id:: mv-910289072312\n\t- preferred-term:: Planning Kanban - currently broken\n\t- source-domain:: metaverse\n\t- status:: active\n\t- public-access:: true\n\t- definition:: A component of the metaverse ecosystem focusing on planning kanban - currently broken.\n\t- maturity:: mature\n\t- authority-score:: 0.85\n\t- owl:class:: mv:PlanningKanbanCurrentlyBroken\n\t- owl:physicality:: ConceptualEntity\n\t- owl:role:: Concept\n\t- belongsToDomain:: [[MetaverseDomain]]\n\t- #### Relationships\n\t  id:: planning-kanban---currently-broken-relationships\n\t\t- enables:: [[ImmersiveExperience]], [[Presence]], [[SpatialComputing]]\n\t\t- requires:: [[DisplayTechnology]], [[TrackingSystem]], [[RenderingEngine]]\n\t\t- bridges-to:: [[HumanComputerInteraction]], [[ComputerVision]], [[Robotics]]\n\n\t- #### OWL Axioms\n\t  id:: planning-kanban---currently-broken-owl-axioms\n\t  collapsed:: true\n\t\t- ```clojure\n\t\t  Declaration(Class(mv:PlanningKanbanCurrentlyBroken))\n\n\t\t  # Classification\n\t\t  SubClassOf(mv:PlanningKanbanCurrentlyBroken mv:ConceptualEntity)\n\t\t  SubClassOf(mv:PlanningKanbanCurrentlyBroken mv:Concept)\n\n\t\t  # Domain classification\n\t\t  SubClassOf(mv:PlanningKanbanCurrentlyBroken\n\t\t    ObjectSomeValuesFrom(mv:belongsToDomain mv:MetaverseDomain)\n\t\t  )\n\n\t\t  # Annotations\n\t\t  AnnotationAssertion(rdfs:label mv:PlanningKanbanCurrentlyBroken \"Planning Kanban - currently broken\"@en)\n\t\t  AnnotationAssertion(rdfs:comment mv:PlanningKanbanCurrentlyBroken \"A component of the metaverse ecosystem focusing on planning kanban - currently broken.\"@en)\n\t\t  AnnotationAssertion(dcterms:identifier mv:PlanningKanbanCurrentlyBroken \"mv-910289072312\"^^xsd:string)\n\t\t  ```\n\n- {{renderer :kboard-query, High level Projects View, progress, TODO, DOING, DONE, cover, 260px}}\n\t- {{query (and [[PlayerTwo]] (property :progress))}}\n\t- {{query (and [[KnoWhere]] (property :progress))}}\n- {{query (and [[Training Material]] (property :progress))}}\n- {{query (and [[Pete Woodbridge]] (property :progress))}}\n- {{query (and [[ParentsGuideToAI]] (property :progress))}}\n- {{query (and [[NLW education discord]] (property :progress))}}\n\n## Current Landscape (2025)\n\n- Industry adoption and implementations\n  - Metaverse platforms continue to evolve with focus on interoperability and open standards\n  - Web3 integration accelerating with decentralised identity and asset ownership\n  - Enterprise adoption growing in virtual collaboration, training, and digital twins\n  - UK companies increasingly active in metaverse development and immersive technologies\n\n- Technical capabilities\n  - Real-time rendering at photorealistic quality levels\n  - Low-latency networking enabling seamless multi-user experiences\n  - AI-driven content generation and procedural world building\n  - Spatial audio and haptics enhancing immersion\n\n- UK and North England context\n  - Manchester: Digital Innovation Factory supports metaverse startups and research\n  - Leeds: Holovis leads in immersive experiences for entertainment and training\n  - Newcastle: University research in spatial computing and interactive systems\n  - Sheffield: Advanced manufacturing using digital twin technology\n\n- Standards and frameworks\n  - Metaverse Standards Forum driving interoperability protocols\n  - WebXR enabling browser-based immersive experiences\n  - glTF and USD for 3D asset interchange\n  - Open Metaverse Interoperability Group defining cross-platform standards\n\n## Metadata\n\n- **Last Updated**: 2025-11-16\n- **Review Status**: Automated remediation with 2025 context\n- **Verification**: Academic sources verified\n- **Regional Context**: UK/North England where applicable",
  "properties": {
    "id": "planning-kanban---currently-broken-owl-axioms",
    "collapsed": "true",
    "- ontology": "true",
    "- term-id": "mv-910289072312",
    "- preferred-term": "Planning Kanban - currently broken",
    "- source-domain": "metaverse",
    "- status": "active",
    "- public-access": "true",
    "- definition": "A component of the metaverse ecosystem focusing on planning kanban - currently broken.",
    "- maturity": "mature",
    "- authority-score": "0.85",
    "- owl:class": "mv:PlanningKanbanCurrentlyBroken",
    "- owl:physicality": "ConceptualEntity",
    "- owl:role": "Concept",
    "- belongsToDomain": "[[MetaverseDomain]]",
    "- enables": "[[ImmersiveExperience]], [[Presence]], [[SpatialComputing]]",
    "- requires": "[[DisplayTechnology]], [[TrackingSystem]], [[RenderingEngine]]",
    "- bridges-to": "[[HumanComputerInteraction]], [[ComputerVision]], [[Robotics]]"
  },
  "backlinks": [],
  "wiki_links": [
    "ParentsGuideToAI",
    "NLW education discord",
    "ImmersiveExperience",
    "RenderingEngine",
    "PlayerTwo",
    "TrackingSystem",
    "ComputerVision",
    "MetaverseDomain",
    "Pete Woodbridge",
    "Training Material",
    "SpatialComputing",
    "Presence",
    "DisplayTechnology",
    "Robotics",
    "HumanComputerInteraction",
    "KnoWhere"
  ],
  "ontology": {
    "term_id": "mv-910289072312",
    "preferred_term": "Planning Kanban - currently broken",
    "definition": "A component of the metaverse ecosystem focusing on planning kanban - currently broken.",
    "source_domain": "metaverse",
    "maturity_level": null,
    "authority_score": 0.85
  }
}