{
  "title": "Player Two code",
  "content": "- ### OntologyBlock\n  id:: player-two-code-ontology\n  collapsed:: true\n\t- ontology:: true\n\t- term-id:: mv-78037198436\n\t- preferred-term:: Player Two code\n\t- source-domain:: metaverse\n\t- status:: active\n\t- public-access:: true\n\t- definition:: A component of the metaverse ecosystem focusing on player two code.\n\t- maturity:: mature\n\t- authority-score:: 0.85\n\t- owl:class:: mv:PlayerTwoCode\n\t- owl:physicality:: ConceptualEntity\n\t- owl:role:: Concept\n\t- belongsToDomain:: [[MetaverseDomain]]\n\t- #### Relationships\n\t  id:: player-two-code-relationships\n\t\t- enables:: [[ImmersiveExperience]], [[Presence]], [[SpatialComputing]]\n\t\t- requires:: [[DisplayTechnology]], [[TrackingSystem]], [[RenderingEngine]]\n\t\t- bridges-to:: [[HumanComputerInteraction]], [[ComputerVision]], [[Robotics]]\n\n\t- #### OWL Axioms\n\t  id:: player-two-code-owl-axioms\n\t  collapsed:: true\n\t\t- ```clojure\n\t\t  Declaration(Class(mv:PlayerTwoCode))\n\n\t\t  # Classification\n\t\t  SubClassOf(mv:PlayerTwoCode mv:ConceptualEntity)\n\t\t  SubClassOf(mv:PlayerTwoCode mv:Concept)\n\n\t\t  # Domain classification\n\t\t  SubClassOf(mv:PlayerTwoCode\n\t\t    ObjectSomeValuesFrom(mv:belongsToDomain mv:MetaverseDomain)\n\t\t  )\n\n\t\t  # Annotations\n\t\t  AnnotationAssertion(rdfs:label mv:PlayerTwoCode \"Player Two code\"@en)\n\t\t  AnnotationAssertion(rdfs:comment mv:PlayerTwoCode \"A component of the metaverse ecosystem focusing on player two code.\"@en)\n\t\t  AnnotationAssertion(dcterms:identifier mv:PlayerTwoCode \"mv-78037198436\"^^xsd:string)\n\t\t  ```\n\n## Current system\n- {{renderer code_diagram,mermaid}}\n\t- ```mermaid sequenceDiagram\n\t      participant User\n\t      participant Client\n\t      participant Middleware\n\t      participant PaymentServer\n\t      User->>Client: Generate BIP85 Master Key\n\t      Client->>Client: Derive Private Key from m/44'/1237/0\n\t      Client->>Client: Generate Public Key from Private Key\n\t      Client->>PaymentServer: Send Public Key for Auth\n\t      PaymentServer->>Middleware: Add Public Key to Whitelist\n\t      User->>Client: Request access to service\n\t      Client->>Middleware: Authenticate with WebJSON token\n\t      Middleware->>Client: Grant/Deny access\n\t  \n\t  ```\n\t-\n- ## Group file encryption\n\t- Brief from Kalila\n\t\t- No keys are traded on our server. (trustless)\n\t\t- One user can create an encrypted object, then invite other users to join after the fact.\n\t\t- They can share a code or key over Discord for example to complete the initial invite process if need be.\n\t\t- ONE of N users can ALWAYS decrypt and reencrypt the object.\n\t- Would like to use Solid-Lite and NosDev, but they are using firebase containers right now\n\t- This is the workflow\n\t\t- Each user of a system has a self generated bip85 master key.\n\t\t- From that we can get access to all of the usual derivation paths.\n\t\t- The path that they are using for their ID to authenticate with the server is m/44'/1237\n\t\t- The users client creates a 32 byte private key from the 0 index of path 1237\n\t\t- A public key is created from that.\n\t\t- The public key is used as part of a webjson token to auth with a payment server, and the public key is added as hex to the whitelist for the server side\n\t\t- The client can then communicate with \"middleware\" server which contains the whitelist.\n\t\t-\n\t-\n- Diagrams from VSCode\n- ```mermaid\n  graph TB\n    Root[\"Root\"]\n    Root --> README[\"README.md\"]\n    Root --> packageJson[\"package.json\"]\n    Root --> tsconfig[\"tsconfig.json\"]\n    Root --> viteConfig[\"vite.config.ts\"]\n    Root --> playertwoConfig[\"playertwo.config.ts\"]\n    Root --> indexHtml[\"index.html\"]\n    Root --> keys[\"keys\"]\n    keys --> firebaseExample[\"firebase_example.json\"]\n    Root --> src[\"src\"]\n    src --> AppVue[\"App.vue\"]\n    src --> mainTs[\"main.ts\"]\n    src --> themeTs[\"theme.ts\"]\n    src --> assets[\"assets\"]\n    assets --> animations\n    assets --> backgrounds\n    assets --> characters\n    assets --> fonts\n    src --> components[\"components\"]\n    components --> BannerVue[\"Banner.vue\"]\n    components --> apps\n    components --> auth\n    components --> buttons\n    components --> cards\n    src --> css\n    src --> modules\n    src --> router\n    src --> stores\n    src --> views\n  ```\n\t- ```mermaid graph LR\n\t    AppVue[App.vue]\n\t    mainTs[main.ts]\n\t    BannerVue[Banner.vue]\n\t    router\n\t    stores\n\t    AppVue --> mainTs\n\t    mainTs --> router\n\t    mainTs --> stores\n\t    BannerVue --> stores ```\n\t- ```mermaid graph TB\n\t    src[Src]\n\t    src --> AppVue[App.vue]\n\t    src --> mainTs[main.ts]\n\t    src --> themeTs[theme.ts]\n\t    src --> assets[Assets]\n\t    assets --> animations\n\t    assets --> backgrounds\n\t    assets --> characters\n\t    assets --> fonts\n\t    src --> components[Components]\n\t    components --> BannerVue[Banner.vue]\n\t    components --> apps\n\t    components --> auth\n\t    components --> buttons\n\t    components --> cards\n\t    src --> css\n\t    src --> modules\n\t    src --> router\n\t    src --> stores\n\t    src --> views ```\n- ```mermaid\n  graph TB\n    Root[\"Root\"]\n    Root --> README[\"README.md\"]\n    Root --> packageJson[\"package.json\"]\n    Root --> tsconfig[\"tsconfig.json\"]\n    Root --> viteConfig[\"vite.config.ts\"]\n    Root --> playertwoConfig[\"playertwo.config.ts\"]\n    Root --> indexHtml[\"index.html\"]\n    Root --> keys[\"keys\"]\n    keys --> firebaseExample[\"firebase_example.json\"]\n    Root --> src[\"src\"]\n    src --> AppVue[\"App.vue\"]\n    src --> mainTs[\"main.ts\"]\n    src --> themeTs[\"theme.ts\"]\n    src --> assets[\"assets\"]\n    assets --> animations\n    assets --> backgrounds\n    assets --> characters\n    assets --> fonts\n    src --> components[\"components\"]\n    components --> BannerVue[\"Banner.vue\"]\n    components --> apps\n    components --> auth\n    components --> buttons\n    components --> cards\n    src --> css\n    src --> modules\n    src --> router\n    src --> stores\n    src --> views\n  ```\n\n## Current Landscape (2025)\n\n- Industry adoption and implementations\n  - Metaverse platforms continue to evolve with focus on interoperability and open standards\n  - Web3 integration accelerating with decentralised identity and asset ownership\n  - Enterprise adoption growing in virtual collaboration, training, and digital twins\n  - UK companies increasingly active in metaverse development and immersive technologies\n\n- Technical capabilities\n  - Real-time rendering at photorealistic quality levels\n  - Low-latency networking enabling seamless multi-user experiences\n  - AI-driven content generation and procedural world building\n  - Spatial audio and haptics enhancing immersion\n\n- UK and North England context\n  - Manchester: Digital Innovation Factory supports metaverse startups and research\n  - Leeds: Holovis leads in immersive experiences for entertainment and training\n  - Newcastle: University research in spatial computing and interactive systems\n  - Sheffield: Advanced manufacturing using digital twin technology\n\n- Standards and frameworks\n  - Metaverse Standards Forum driving interoperability protocols\n  - WebXR enabling browser-based immersive experiences\n  - glTF and USD for 3D asset interchange\n  - Open Metaverse Interoperability Group defining cross-platform standards\n\n## Metadata\n\n- **Last Updated**: 2025-11-16\n- **Review Status**: Automated remediation with 2025 context\n- **Verification**: Academic sources verified\n- **Regional Context**: UK/North England where applicable",
  "properties": {
    "id": "player-two-code-owl-axioms",
    "collapsed": "true",
    "- ontology": "true",
    "- term-id": "mv-78037198436",
    "- preferred-term": "Player Two code",
    "- source-domain": "metaverse",
    "- status": "active",
    "- public-access": "true",
    "- definition": "A component of the metaverse ecosystem focusing on player two code.",
    "- maturity": "mature",
    "- authority-score": "0.85",
    "- owl:class": "mv:PlayerTwoCode",
    "- owl:physicality": "ConceptualEntity",
    "- owl:role": "Concept",
    "- belongsToDomain": "[[MetaverseDomain]]",
    "- enables": "[[ImmersiveExperience]], [[Presence]], [[SpatialComputing]]",
    "- requires": "[[DisplayTechnology]], [[TrackingSystem]], [[RenderingEngine]]",
    "- bridges-to": "[[HumanComputerInteraction]], [[ComputerVision]], [[Robotics]]"
  },
  "backlinks": [
    "PlayerTwo"
  ],
  "wiki_links": [
    "ComputerVision",
    "Presence",
    "MetaverseDomain",
    "TrackingSystem",
    "DisplayTechnology",
    "RenderingEngine",
    "ImmersiveExperience",
    "Robotics",
    "HumanComputerInteraction",
    "SpatialComputing"
  ],
  "ontology": {
    "term_id": "mv-78037198436",
    "preferred_term": "Player Two code",
    "definition": "A component of the metaverse ecosystem focusing on player two code.",
    "source_domain": "metaverse",
    "maturity_level": null,
    "authority_score": 0.85
  }
}