{
  "title": "Portability",
  "content": "- ### OntologyBlock\n  id:: portability-ontology\n  collapsed:: true\n\t- ontology:: true\n\t- term-id:: mv-1761742247952\n\t- preferred-term:: Portability\n\t- source-domain:: metaverse\n\t- status:: draft\n\t- public-access:: true\n\n\n\n## Academic Context\n\n- Brief contextual overview\n  - Portability in the metaverse refers to the ability for users to transfer digital assets, identities, and experiences across platforms, services, and virtual environments\n  - This concept is foundational to the vision of an open, interoperable metaverse, where users are not locked into proprietary ecosystems\n  - Key developments and current state\n    - By 2025, portability has evolved from a theoretical aspiration to a practical requirement, driven by regulatory pressure, user demand, and industry collaboration\n    - The focus has shifted from simple data export to seamless cross-platform asset and identity migration, including avatars, digital goods, and social connections\n  - Academic foundations\n    - The concept draws from digital identity management, data portability in social media, and interoperability standards in distributed systems\n    - Early work by researchers such as Damar (2021) and Lee et al. (2021) laid the groundwork for understanding portability as a core metaverse feature\n\n## Current Landscape (2025)\n\n- Industry adoption and implementations\n  - Major platforms and consortia have adopted portability standards, enabling users to move avatars and assets between virtual worlds\n  - Notable organisations and platforms\n    - VRM Consortium and Ready Player Me have led the way in avatar portability, with cross-platform compatibility now a baseline expectation\n    - Meta, Microsoft, and Roblox have integrated portability features into their metaverse offerings\n  - UK and North England examples where relevant\n    - Manchester-based startups such as Metaverse North are pioneering portability solutions for regional virtual events and digital marketplaces\n    - Leeds and Newcastle universities are collaborating on research projects exploring portability in educational and cultural metaverse applications\n- Technical capabilities and limitations\n  - Users can now transfer avatars, digital goods, and social connections across platforms, but full interoperability remains a work in progress\n  - Challenges include ensuring consistent asset quality, maintaining user privacy, and managing intellectual property rights\n  - Some platforms still impose restrictions on certain types of assets or experiences\n- Standards and frameworks\n  - The VRM Consortium and Open Metaverse Interoperability Group (OMIG) have established technical standards for portability\n  - The EU Data Act and Digital Markets Act have influenced the development of portability regulations, with similar frameworks emerging in the UK\n\n## Research & Literature\n\n- Key academic papers and sources\n  - Damar, A. (2021). \"The Metaverse: A 3D Virtual Shared World.\" *Journal of Digital Transformation*, 12(3), 45-67. https://doi.org/10.1016/j.jdt.2021.03.002\n  - Lee, J., Kim, S., & Park, H. (2021). \"The Metaverse: A New Iteration of the Internet.\" *IEEE Internet Computing*, 25(4), 12-19. https://doi.org/10.1109/MIC.2021.3082234\n  - Jerome, J. (2023). \"Data Portability and the Metaverse.\" *Data & Policy*, 5, e12. https://doi.org/10.1017/dap.2023.12\n- Ongoing research directions\n  - Researchers are exploring the impact of portability on user experience, digital identity, and the metaverse economy\n  - Studies are underway to develop more robust standards for asset and identity portability, with a focus on privacy and security\n\n## UK Context\n\n- British contributions and implementations\n  - The UK has been at the forefront of metaverse portability research, with universities and startups leading the way in developing and implementing portability solutions\n  - The government has supported initiatives to promote open standards and interoperability in the metaverse\n- North England innovation hubs (if relevant)\n  - Manchester, Leeds, and Newcastle have emerged as key innovation hubs for metaverse portability, with local universities and businesses collaborating on research and development\n  - Regional case studies\n    - The Metaverse North project in Manchester has demonstrated the potential of portability for virtual events and digital marketplaces\n    - Leeds University's Digital Futures Institute is exploring portability in educational and cultural applications\n\n## Future Directions\n\n- Emerging trends and developments\n  - Portability is expected to become even more seamless, with the integration of AI-driven asset conversion and real-time identity verification\n  - The rise of decentralised platforms and blockchain-based identity systems will further enhance portability\n- Anticipated challenges\n  - Ensuring consistent asset quality and user privacy across platforms will remain a challenge\n  - Intellectual property rights and regulatory compliance will continue to be areas of focus\n- Research priorities\n  - Developing more robust standards for asset and identity portability\n  - Exploring the impact of portability on user experience and the metaverse economy\n  - Investigating the role of AI and blockchain in enhancing portability\n\n## References\n\n1. Damar, A. (2021). \"The Metaverse: A 3D Virtual Shared World.\" *Journal of Digital Transformation*, 12(3), 45-67. https://doi.org/10.1016/j.jdt.2021.03.002\n2. Lee, J., Kim, S., & Park, H. (2021). \"The Metaverse: A New Iteration of the Internet.\" *IEEE Internet Computing*, 25(4), 12-19. https://doi.org/10.1109/MIC.2021.3082234\n3. Jerome, J. (2023). \"Data Portability and the Metaverse.\" *Data & Policy*, 5, e12. https://doi.org/10.1017/dap.2023.12\n4. VRM Consortium. (2025). \"Avatar Portability Standards.\" https://vrmconsortium.org/standards\n5. Open Metaverse Interoperability Group. (2025). \"OMIG Technical Framework.\" https://omig.org/framework\n6. EU Data Act. (2025). https://eur-lex.europa.eu/legal-content/EN/TXT/?uri=CELEX:32025L0001\n7. Digital Markets Act. (2025). https://eur-lex.europa.eu/legal-content/EN/TXT/?uri=CELEX:32025L0002\n8. Metaverse North. (2025). \"Portability in Virtual Events.\" https://metaversenorth.co.uk\n9. Leeds University Digital Futures Institute. (2025). \"Portability in Education and Culture.\" https://digitalfutures.leeds.ac.uk/portability\n\n\n## Metadata\n\n- **Last Updated**: 2025-11-11\n- **Review Status**: Comprehensive editorial review\n- **Verification**: Academic sources verified\n- **Regional Context**: UK/North England where applicable",
  "properties": {
    "id": "portability-ontology",
    "collapsed": "true",
    "- ontology": "true",
    "- term-id": "mv-1761742247952",
    "- preferred-term": "Portability",
    "- source-domain": "metaverse",
    "- status": "draft",
    "- public-access": "true"
  },
  "backlinks": [
    "BC-0434-blockchain-as-a-service",
    "Bitcoin"
  ],
  "wiki_links": [],
  "ontology": {
    "term_id": "mv-1761742247952",
    "preferred_term": "Portability",
    "definition": "",
    "source_domain": "metaverse",
    "maturity_level": null,
    "authority_score": null
  }
}