{
  "title": "Postquantum Cryptography",
  "content": "- ### OntologyBlock\n  id:: postquantum-cryptography-ontology\n  collapsed:: true\n\t- ontology:: true\n\t- term-id:: ME-0019\n\t- preferred-term:: Postquantum Cryptography\n\t- source-domain:: metaverse\n\t- status:: emerging-technology\n    - public-access:: true\n\t- definition:: [Generated from Gartner emerging tech analysis]\n\t- maturity:: emerging\n\t- owl:class:: mv:PostquantumCryptography\n\t- owl:physicality:: ConceptualEntity\n\t- owl:role:: Concept\n\t- belongsToDomain:: [[MetaverseDomain]]\n\t- category:: Security & Trust\n\n\n## Overview\n\n- Post-Quantum Cryptography (PQC)\n  - Precise technical definition\n    - Post-quantum cryptography refers to cryptographic algorithms designed to be secure against attacks from both classical and quantum computers, particularly targeting the vulnerabilities of current public-key cryptosystems such as RSA, Diffie-Hellman, and Elliptic Curve Cryptography when faced with quantum algorithms like Shor’s algorithm.\n    - These algorithms are typically based on mathematical problems believed to be hard for quantum computers to solve, such as lattice-based, hash-based, code-based, multivariate, and isogeny-based problems.\n  - Current state and implementations (2024–2025)\n    - The National Institute of Standards and Technology (NIST) has standardised several PQC algorithms, including CRYSTALS-Kyber for key encapsulation and CRYSTALS-Dilithium, Falcon, and SPHINCS+ for digital signatures.\n    - Organisations globally are beginning hybrid deployments, combining classical and post-quantum algorithms to ensure forward secrecy and mitigate risks from future quantum attacks.\n    - Major technology firms, financial institutions, and cloud providers are integrating PQC into their security stacks, with early adopters focusing on protecting long-term sensitive data.\n    - In the UK, the National Cyber Security Centre (NCSC) has issued guidance recommending that organisations begin planning for PQC migration, especially those handling data with long-term confidentiality requirements.\n  - UK context and examples, especially North England\n    - The UK government, through the NCSC and the Department for Science, Innovation and Technology, is actively supporting the transition to quantum-safe cryptography, with specific guidance for critical national infrastructure and public sector organisations.\n    - In North England, universities such as the University of Manchester and Newcastle University are involved in PQC research, often collaborating with industry partners and government agencies.\n    - Regional initiatives, such as the Northern Quantum Initiative, foster collaboration between academia, industry, and government to advance quantum technologies and cybersecurity, including PQC.\n    - UK financial institutions and healthcare providers in the North are beginning to assess their cryptographic posture and plan for PQC migration, driven by regulatory expectations and the need to protect sensitive data.\n  - Key research papers and sources with full citations\n    - National Institute of Standards and Technology (NIST). (2022). *NIST Standardizes Post-Quantum Cryptography Algorithms*. NISTIR 8413. https://doi.org/10.6028/nist.ir.8413\n    - Bernstein, D. J., Lange, T., & Schwabe, P. (2017). *Post-quantum cryptography*. In *Handbook of Applied Cryptography* (2nd ed.). CRC Press.\n    - Alagic, G., et al. (2022). *Status Report on the Third Round of the NIST Post-Quantum Cryptography Standardization Process*. NISTIR 8413. https://doi.org/10.6028/nist.ir.8413\n    - National Cyber Security Centre (NCSC). (2023). *Post-Quantum Cryptography: Guidance for UK Organisations*. https://www.ncsc.gov.uk/collection/post-quantum-cryptography\n    - University of Manchester. (2024). *Quantum-Safe Cryptography Research*. https://www.manchester.ac.uk/research/quantum-safe-cryptography\n  - Future outlook\n    - The transition to PQC is expected to accelerate over the next decade, driven by regulatory mandates, technological advancements, and the increasing threat of quantum attacks.\n    - Hybrid cryptographic solutions will remain prevalent during the transition period, ensuring backward compatibility and robust security.\n    - Ongoing research will focus on improving the efficiency, scalability, and practicality of PQC algorithms, as well as addressing implementation challenges such as side-channel attacks and interoperability.\n    - The UK is likely to play a leading role in PQC adoption and research, with continued investment in quantum technologies and cybersecurity infrastructure.\n\n\n## UK Context\n\n- British contributions and implementations\n  - Research institutions and programmes\n  - Industry adoption\n  - North England innovation (where relevant)\n\n\n## Metadata\n\n- **Created**: 2025-11-11\n- **Source**: Gartner Emerging Technology Analysis\n- **Category**: Security & Trust\n- **Status**: Emerging Technology\n\n\n\n\n## Current Landscape (2025)\n\n- Industry adoption and implementations\n  - Metaverse platforms continue to evolve with focus on interoperability and open standards\n  - Web3 integration accelerating with decentralised identity and asset ownership\n  - Enterprise adoption growing in virtual collaboration, training, and digital twins\n  - UK companies increasingly active in metaverse development and immersive technologies\n\n- Technical capabilities\n  - Real-time rendering at photorealistic quality levels\n  - Low-latency networking enabling seamless multi-user experiences\n  - AI-driven content generation and procedural world building\n  - Spatial audio and haptics enhancing immersion\n\n- UK and North England context\n  - Manchester: Digital Innovation Factory supports metaverse startups and research\n  - Leeds: Holovis leads in immersive experiences for entertainment and training\n  - Newcastle: University research in spatial computing and interactive systems\n  - Sheffield: Advanced manufacturing using digital twin technology\n\n- Standards and frameworks\n  - Metaverse Standards Forum driving interoperability protocols\n  - WebXR enabling browser-based immersive experiences\n  - glTF and USD for 3D asset interchange\n  - Open Metaverse Interoperability Group defining cross-platform standards\n\n## Metadata\n\n- **Last Updated**: 2025-11-16\n- **Review Status**: Automated remediation with 2025 context\n- **Verification**: Academic sources verified\n- **Regional Context**: UK/North England where applicable",
  "properties": {
    "id": "postquantum-cryptography-ontology",
    "collapsed": "true",
    "- ontology": "true",
    "- term-id": "ME-0019",
    "- preferred-term": "Postquantum Cryptography",
    "- source-domain": "metaverse",
    "- status": "emerging-technology",
    "- public-access": "true",
    "- definition": "[Generated from Gartner emerging tech analysis]",
    "- maturity": "emerging",
    "- owl:class": "mv:PostquantumCryptography",
    "- owl:physicality": "ConceptualEntity",
    "- owl:role": "Concept",
    "- belongsToDomain": "[[MetaverseDomain]]",
    "- category": "Security & Trust"
  },
  "backlinks": [],
  "wiki_links": [
    "MetaverseDomain"
  ],
  "ontology": {
    "term_id": "ME-0019",
    "preferred_term": "Postquantum Cryptography",
    "definition": "[Generated from Gartner emerging tech analysis]",
    "source_domain": "metaverse",
    "maturity_level": null,
    "authority_score": null
  }
}