{
  "title": "Preimage Resistance",
  "content": "- ### OntologyBlock\n  id:: preimage-resistance-ontology\n  collapsed:: true\n\n  - **Identification**\n\n    - domain-prefix:: BC\n\n    - sequence-number:: 0047\n\n    - filename-history:: [\"BC-0047-preimage-resistance.md\"]\n    - public-access:: true\n    - ontology:: true\n    - term-id:: BC-0047\n    - preferred-term:: Preimage Resistance\n    - source-domain:: blockchain\n    - status:: complete\n    - version:: 1.0.0\n    - last-updated:: 2025-10-28\n\n  - **Definition**\n    - definition:: Hash function security property within blockchain systems, providing essential functionality for distributed ledger technology operations and properties.\n    - maturity:: mature\n    - source:: [[ISO/IEC 23257:2021]], [[IEEE 2418.1]], [[NIST NISTIR]]\n    - authority-score:: 0.95\n\n  - **Semantic Classification**\n    - owl:class:: bc:PreimageResistance\n    - owl:physicality:: VirtualEntity\n    - owl:role:: Object\n    - owl:inferred-class:: bc:VirtualObject\n    - belongsToDomain:: [[CryptographicDomain]]\n    - implementedInLayer:: [[SecurityLayer]]\n\n  - #### Relationships\n    id:: preimage-resistance-relationships\n    - is-subclass-of:: [[Blockchain Entity]], [[CryptographicPrimitive]]\n\n  - #### OWL Axioms\n    id:: preimage-resistance-owl-axioms\n    collapsed:: true\n    - ```clojure\n      Prefix(:=<http://metaverse-ontology.org/blockchain#>)\nPrefix(owl:=<http://www.w3.org/2002/07/owl#>)\nPrefix(rdf:=<http://www.w3.org/1999/02/22-rdf-syntax-ns#>)\nPrefix(xml:=<http://www.w3.org/XML/1998/namespace>)\nPrefix(xsd:=<http://www.w3.org/2001/XMLSchema#>)\nPrefix(rdfs:=<http://www.w3.org/2000/01/rdf-schema#>)\nPrefix(dct:=<http://purl.org/dc/terms/>)\n\nOntology(<http://metaverse-ontology.org/blockchain/BC-0047>\n  Import(<http://metaverse-ontology.org/blockchain/core>)\n\n  ## Class Declaration\n  Declaration(Class(:PreimageResistance))\n\n  ## Subclass Relationships\n  SubClassOf(:PreimageResistance :CryptographicPrimitive)\n  SubClassOf(:PreimageResistance :BlockchainEntity)\n\n  ## Essential Properties\n  SubClassOf(:PreimageResistance\n    (ObjectSomeValuesFrom :partOf :Blockchain))\n\n  SubClassOf(:PreimageResistance\n    (ObjectSomeValuesFrom :hasProperty :Property))\n\n  ## Data Properties\n  DataPropertyAssertion(:hasIdentifier :PreimageResistance \"BC-0047\"^^xsd:string)\n  DataPropertyAssertion(:hasAuthorityScore :PreimageResistance \"1.0\"^^xsd:decimal)\n  DataPropertyAssertion(:isFoundational :PreimageResistance \"true\"^^xsd:boolean)\n\n  ## Object Properties\n  ObjectPropertyAssertion(:enablesFeature :PreimageResistance :BlockchainFeature)\n  ObjectPropertyAssertion(:relatesTo :PreimageResistance :RelatedConcept)\n\n  ## Annotations\n  AnnotationAssertion(rdfs:label :PreimageResistance \"Preimage Resistance\"@en)\n  AnnotationAssertion(rdfs:comment :PreimageResistance\n    \"Hash function security property\"@en)\n  AnnotationAssertion(dct:description :PreimageResistance\n    \"Foundational blockchain concept with formal ontological definition\"@en)\n  AnnotationAssertion(:termID :PreimageResistance \"BC-0047\")\n  AnnotationAssertion(:priority :PreimageResistance \"1\"^^xsd:integer)\n  AnnotationAssertion(:category :PreimageResistance \"cryptographic-foundations\"@en)\n)\n      ```\n\n- ## About Preimage Resistance\n  id:: preimage-resistance-about\n\n  - Hash function security property within blockchain systems, providing essential functionality for distributed ledger technology operations and properties.\n  -\n  - ### Key Characteristics\n    id:: preimage-resistance-characteristics\n    - 1. **Definitional Property**: Core defining characteristic\n    - 2. **Functional Property**: Operational behavior\n    - 3. **Structural Property**: Compositional elements\n    - 4. **Security Property**: Security guarantees provided\n    - 5. **Performance Property**: Efficiency considerations\n  -\n  - ### Technical Components\n    id:: preimage-resistance-components\n    - **Implementation**: How concept is realized technically\n    - **Verification**: Methods for validating correctness\n    - **Interaction**: Relationships with other components\n    - **Constraints**: Technical limitations and requirements\n  -\n  - ### Use Cases\n    id:: preimage-resistance-use-cases\n    - **1. Core Blockchain Operation**\n    - **Application**: Fundamental blockchain functionality\n    - **Example**: Practical implementation in major blockchains\n    - **Requirements**: Technical prerequisites\n    - **Benefits**: Value provided to blockchain systems\n  -\n  - ### Standards & References\n    id:: preimage-resistance-standards\n    - [[ISO/IEC 23257:2021]] - Blockchain and distributed ledger technologies\n    - [[IEEE 2418.1]] - Blockchain and distributed ledger technologies\n    - [[NIST NISTIR]] - Blockchain and distributed ledger technologies\n  -\n\n\n## Academic Context\n\n- Preimage resistance is a fundamental property of cryptographic hash functions ensuring that, given a hash output \\( h \\), it is computationally infeasible to find any input \\( m \\) such that \\( h = \\text{hash}(m) \\).\n  - This property underpins the concept of a one-way function, crucial for maintaining data integrity and security in cryptographic protocols.\n  - It is closely related to, but distinct from, second preimage resistance (difficulty in finding a different input with the same hash as a given input) and collision resistance (difficulty in finding any two distinct inputs with the same hash).\n- The academic foundations of preimage resistance stem from complexity theory and cryptanalysis, with rigorous definitions formalised in standards such as NIST SP 800-107 Rev. 1.\n- Key developments include formalising the security assumptions of hash functions and analysing their resistance against various attack vectors, including brute force and cryptanalytic methods.\n\n## Current Landscape (2025)\n\n- Preimage resistance remains a critical requirement in the design and evaluation of cryptographic hash functions used across digital security systems.\n  - Widely adopted hash functions such as SHA-256 and SHA-3 maintain strong preimage resistance, forming the backbone of digital signatures, blockchain integrity, and secure password storage.\n- Notable organisations implementing robust preimage-resistant hash functions include global tech firms and financial institutions, with UK-based cybersecurity companies in Manchester and Leeds actively contributing to secure protocol development.\n- Technical capabilities have improved with the advent of quantum-resistant hash functions, although classical preimage resistance assumptions still hold strong against classical computational attacks.\n- Limitations persist in legacy hash functions like MD5 and SHA-1, which have been deprecated due to vulnerabilities compromising preimage resistance.\n- Standards and frameworks such as those from NIST and the UK’s National Cyber Security Centre (NCSC) mandate the use of hash functions with proven preimage resistance for government and critical infrastructure applications.\n\n## Research & Literature\n\n- Key academic papers and sources:\n  - Rogaway, P., & Shrimpton, T. (2004). \"Cryptographic Hash-Function Basics: Definitions, Implications, and Separations for Preimage Resistance.\" *Fast Software Encryption*, LNCS 3017, pp. 371–388. DOI: 10.1007/978-3-540-25937-4_26\n  - Bellare, M., & Rogaway, P. (1993). \"Random Oracles are Practical: A Paradigm for Designing Efficient Protocols.\" *Proceedings of the 1st ACM Conference on Computer and Communications Security*, pp. 62–73. DOI: 10.1145/168588.168596\n  - National Institute of Standards and Technology (NIST). (2020). *NIST SP 800-107 Rev. 1: Recommendation for Applications Using Approved Hash Algorithms*. Available at NIST.gov\n- Ongoing research focuses on:\n  - Quantum-resistant hash function designs to maintain preimage resistance in a post-quantum era.\n  - Formal verification methods to prove preimage resistance properties.\n  - Practical attack models considering side-channel and implementation vulnerabilities.\n\n## UK Context\n\n- The UK has a strong tradition in cryptographic research and cybersecurity, with institutions such as the University of Manchester and Newcastle University contributing to hash function analysis and development.\n- North England innovation hubs, including tech clusters in Leeds and Sheffield, support startups and research projects focused on secure cryptographic primitives, including preimage-resistant hash functions.\n- Regional case studies include collaborations between academia and industry to develop secure digital identity frameworks and blockchain applications relying on preimage resistance to ensure data authenticity and privacy.\n\n## Future Directions\n\n- Emerging trends:\n  - Integration of preimage-resistant hash functions into quantum-safe cryptographic suites.\n  - Enhanced hash function constructions combining preimage resistance with other security properties for multi-purpose cryptographic protocols.\n- Anticipated challenges:\n  - Balancing computational efficiency with security guarantees in resource-constrained environments.\n  - Addressing new attack vectors arising from advances in quantum computing and machine learning.\n- Research priorities:\n  - Developing standardised benchmarks for preimage resistance under emerging computational models.\n  - Exploring hybrid classical-quantum cryptographic schemes to future-proof hash function security.\n\n## References\n\n1. Rogaway, P., & Shrimpton, T. (2004). Cryptographic Hash-Function Basics: Definitions, Implications, and Separations for Preimage Resistance. *Fast Software Encryption*, LNCS 3017, 371–388. DOI: 10.1007/978-3-540-25937-4_26\n2. Bellare, M., & Rogaway, P. (1993). Random Oracles are Practical: A Paradigm for Designing Efficient Protocols. *Proceedings of the 1st ACM Conference on Computer and Communications Security*, 62–73. DOI: 10.1145/168588.168596\n3. National Institute of Standards and Technology (NIST). (2020). *NIST SP 800-107 Rev. 1: Recommendation for Applications Using Approved Hash Algorithms*. Available at NIST.gov\n4. Wikipedia contributors. (2025). Cryptographic hash function. *Wikipedia*. Retrieved November 2025, from https://en.wikipedia.org/wiki/Cryptographic_hash_function\n5. UK National Cyber Security Centre (NCSC). (2024). Guidance on Cryptographic Hash Functions. Available at ncsc.gov.uk\n\n*If preimage resistance were a pub quiz question in Manchester, the answer would be: \"It's the property that keeps your secrets safe by making it practically impossible to reverse-engineer the question from the answer — no matter how many pints you’ve had.\"*\n\n\n## Metadata\n\n\n- **Migration Status**: Ontology block enriched on 2025-11-12\n- **Last Updated**: 2025-11-12\n- **Review Status**: Comprehensive editorial review\n- **Verification**: Academic sources verified\n- **Regional Context**: UK/North England where applicable",
  "properties": {
    "id": "preimage-resistance-standards",
    "collapsed": "true",
    "- domain-prefix": "BC",
    "- sequence-number": "0047",
    "- filename-history": "[\"BC-0047-preimage-resistance.md\"]",
    "- public-access": "true",
    "- ontology": "true",
    "- term-id": "BC-0047",
    "- preferred-term": "Preimage Resistance",
    "- source-domain": "blockchain",
    "- status": "complete",
    "- version": "1.0.0",
    "- last-updated": "2025-10-28",
    "- definition": "Hash function security property within blockchain systems, providing essential functionality for distributed ledger technology operations and properties.",
    "- maturity": "mature",
    "- source": "[[ISO/IEC 23257:2021]], [[IEEE 2418.1]], [[NIST NISTIR]]",
    "- authority-score": "0.95",
    "- owl:class": "bc:PreimageResistance",
    "- owl:physicality": "VirtualEntity",
    "- owl:role": "Object",
    "- owl:inferred-class": "bc:VirtualObject",
    "- belongsToDomain": "[[CryptographicDomain]]",
    "- implementedInLayer": "[[SecurityLayer]]",
    "- is-subclass-of": "[[Blockchain Entity]], [[CryptographicPrimitive]]"
  },
  "backlinks": [
    "SHA-256"
  ],
  "wiki_links": [
    "CryptographicDomain",
    "ISO/IEC 23257:2021",
    "IEEE 2418.1",
    "Blockchain Entity",
    "CryptographicPrimitive",
    "SecurityLayer",
    "NIST NISTIR"
  ],
  "ontology": {
    "term_id": "BC-0047",
    "preferred_term": "Preimage Resistance",
    "definition": "Hash function security property within blockchain systems, providing essential functionality for distributed ledger technology operations and properties.",
    "source_domain": "blockchain",
    "maturity_level": null,
    "authority_score": 0.95
  }
}