{
  "title": "Presence",
  "content": "- ### OntologyBlock\n  id:: presence-ontology\n  collapsed:: true\n\t- ontology:: true\n\t- term-id:: 20256\n\t- source-domain:: metaverse\n\t- status:: draft\n<<<<<<< HEAD\n=======\n    - public-access:: true\n>>>>>>> 691c6e7cfbf51bb03aef4b19e8bb7f7924266439\n\t- preferred-term:: Presence\n\t- definition:: Perceptual state in which a user feels located inside a virtual or mixed environment, experiencing spatial, social, and self presence.\n\t- maturity:: mature\n\t- source:: [[ACM]]\n\t- owl:class:: mv:Presence\n\t- owl:physicality:: VirtualEntity\n\t- owl:role:: Object\n\t- owl:inferred-class:: mv:VirtualObject\n\t- owl:functional-syntax:: true\n\t- belongsToDomain:: [[InteractionDomain]]\n\t- implementedInLayer:: [[ComputeLayer]]\n\t- #### Relationships\n\t  id:: presence-relationships\n\t\t- is-enabled-by:: [[Extended Reality (XR)]], [[Immersion]], [[Human Interface Layer (HIL)]], [[Experience Layer]]\n\t\t- has-part:: [[Spatial Presence]], [[Social Presence]], [[Self Presence]]\n\t\t- is-part-of:: [[Immersive Experience]]\n\t\t- requires:: [[Sensory Feedback]], [[Haptic Device]], [[Visual Display]]\n\t\t- depends-on:: [[Latency]], [[Frame Rate]], [[Field of View]]\n\t\t- enables:: [[Engagement]], [[Embodiment]], [[Social Connection]]\n\t- #### OWL Axioms\n\t  id:: presence-owl-axioms\n\t  collapsed:: true\n\t\t- ```clojure\n\t\t  Declaration(Class(mv:Presence))\n\n\t\t  # Classification along two primary dimensions\n\t\t  SubClassOf(mv:Presence mv:VirtualEntity)\n\t\t  SubClassOf(mv:Presence mv:Object)\n\n\t\t  # Presence is a psychological construct that can be measured\n\t\t  SubClassOf(mv:Presence\n\t\t    ObjectSomeValuesFrom(mv:hasMeasurableAttribute mv:PresenceMetric)\n\t\t  )\n\n\t\t  # Presence has distinct dimensional components\n\t\t  SubClassOf(mv:Presence\n\t\t    ObjectSomeValuesFrom(mv:hasPart mv:SpatialPresence)\n\t\t  )\n\n\t\t  SubClassOf(mv:Presence\n\t\t    ObjectSomeValuesFrom(mv:hasPart mv:SocialPresence)\n\t\t  )\n\n\t\t  SubClassOf(mv:Presence\n\t\t    ObjectSomeValuesFrom(mv:hasPart mv:SelfPresence)\n\t\t  )\n\n\t\t  # Presence requires sensory feedback to manifest\n\t\t  SubClassOf(mv:Presence\n\t\t    ObjectSomeValuesFrom(mv:requires mv:SensoryFeedback)\n\t\t  )\n\n\t\t  # Presence depends on technical performance factors\n\t\t  SubClassOf(mv:Presence\n\t\t    ObjectSomeValuesFrom(mv:dependsOn mv:Latency)\n\t\t  )\n\n\t\t  SubClassOf(mv:Presence\n\t\t    ObjectSomeValuesFrom(mv:dependsOn mv:FrameRate)\n\t\t  )\n\n\t\t  # Presence enables immersive experiences\n\t\t  SubClassOf(mv:Presence\n\t\t    ObjectSomeValuesFrom(mv:enables mv:Immersion)\n\t\t  )\n\n\t\t  # Presence is part of immersive experiences\n\t\t  SubClassOf(mv:Presence\n\t\t    ObjectSomeValuesFrom(mv:isPartOf mv:ImmersiveExperience)\n\t\t  )\n\n\t\t  # Domain classification\n\t\t  SubClassOf(mv:Presence\n\t\t    ObjectSomeValuesFrom(mv:belongsToDomain mv:InteractionDomain)\n\t\t  )\n\n\t\t  # Layer classification\n\t\t  SubClassOf(mv:Presence\n\t\t    ObjectSomeValuesFrom(mv:implementedInLayer mv:ComputeLayer)\n\t\t  )\n\n  # Property characteristics\n  AsymmetricObjectProperty(dt:isenabledby)\n\n  # Property characteristics\n  TransitiveObjectProperty(dt:ispartof)\n\n  # Property characteristics\n  AsymmetricObjectProperty(dt:requires)\n\n  # Property characteristics\n  AsymmetricObjectProperty(dt:dependson)\n\n  # Property characteristics\n  AsymmetricObjectProperty(dt:enables)\n```",
  "properties": {
    "id": "presence-owl-axioms",
    "collapsed": "true",
    "- ontology": "true",
    "- term-id": "20256",
    "- source-domain": "metaverse",
    "- status": "draft",
    "- public-access": "true",
    "- preferred-term": "Presence",
    "- definition": "Perceptual state in which a user feels located inside a virtual or mixed environment, experiencing spatial, social, and self presence.",
    "- maturity": "mature",
    "- source": "[[ACM]]",
    "- owl:class": "mv:Presence",
    "- owl:physicality": "VirtualEntity",
    "- owl:role": "Object",
    "- owl:inferred-class": "mv:VirtualObject",
    "- owl:functional-syntax": "true",
    "- belongsToDomain": "[[InteractionDomain]]",
    "- implementedInLayer": "[[ComputeLayer]]",
    "- is-enabled-by": "[[Extended Reality (XR)]], [[Immersion]], [[Human Interface Layer (HIL)]], [[Experience Layer]]",
    "- has-part": "[[Spatial Presence]], [[Social Presence]], [[Self Presence]]",
    "- is-part-of": "[[Immersive Experience]]",
    "- requires": "[[Sensory Feedback]], [[Haptic Device]], [[Visual Display]]",
    "- depends-on": "[[Latency]], [[Frame Rate]], [[Field of View]]",
    "- enables": "[[Engagement]], [[Embodiment]], [[Social Connection]]"
  },
  "backlinks": [
    "Immersion",
    "Latency"
  ],
  "wiki_links": [
    "Latency",
    "Embodiment",
    "Social Connection",
    "Engagement",
    "Immersion",
    "Extended Reality (XR)",
    "Social Presence",
    "Self Presence",
    "Haptic Device",
    "Immersive Experience",
    "ACM",
    "Sensory Feedback",
    "Visual Display",
    "InteractionDomain",
    "Human Interface Layer (HIL)",
    "Experience Layer",
    "Spatial Presence",
    "Field of View",
    "Frame Rate",
    "ComputeLayer"
  ],
  "ontology": {
    "term_id": "20256",
    "preferred_term": "Presence",
    "definition": "Perceptual state in which a user feels located inside a virtual or mixed environment, experiencing spatial, social, and self presence.",
    "source_domain": "metaverse",
    "maturity_level": null,
    "authority_score": null
  }
}