{
  "title": "Pretrained Model",
  "content": "- ### OntologyBlock\n  id:: pretrainedmodel-ontology\n  collapsed:: true\n\n  - **Identification**\n    - domain-prefix:: AI\n    - sequence-number:: 0875\n    - filename-history:: [\"AI-0875-pretrainedmodel.md\"]\n    - public-access:: true\n    - ontology:: true\n    - term-id:: AI-0875\n    - preferred-term:: Pretrained Model\n    - source-domain:: ai\n    - status:: complete\n    - version:: 1.0.0\n    - last-updated:: 2025-11-13\n\n  - **Definition**\n    - definition:: \n    - maturity:: established\n    - source:: Chimera Prime Research\n    - authority-score:: 0.95\n\n  - **Semantic Classification**\n    - owl:class:: ai:PretrainedModel\n    - belongsToDomain:: [[Artificial Intelligence]]\n\n  - #### OWL Restrictions\n    \n\n  - \n### Relationships\n- is-subclass-of:: [[MachineLearning]]",
  "properties": {
    "id": "pretrainedmodel-ontology",
    "collapsed": "true",
    "- domain-prefix": "AI",
    "- sequence-number": "0875",
    "- filename-history": "[\"AI-0875-pretrainedmodel.md\"]",
    "- public-access": "true",
    "- ontology": "true",
    "- term-id": "AI-0875",
    "- preferred-term": "Pretrained Model",
    "- source-domain": "ai",
    "- status": "complete",
    "- version": "1.0.0",
    "- last-updated": "2025-11-13",
    "- definition": "",
    "- maturity": "established",
    "- source": "Chimera Prime Research",
    "- authority-score": "0.95",
    "- owl:class": "ai:PretrainedModel",
    "- belongsToDomain": "[[Artificial Intelligence]]"
  },
  "backlinks": [],
  "wiki_links": [
    "Artificial Intelligence",
    "MachineLearning"
  ],
  "ontology": {
    "term_id": "AI-0875",
    "preferred_term": "Pretrained Model",
    "definition": "",
    "source_domain": "ai",
    "maturity_level": null,
    "authority_score": 0.95
  }
}