{
  "title": "Privacy-Enhancing Computation (PEC)",
  "content": "- ### OntologyBlock\n  id:: privacy-enhancing-computation-ontology\n  collapsed:: true\n\t- ontology:: true\n\t- term-id:: 20203\n\t- source-domain:: metaverse\n\t- status:: draft\n\t- public-access:: true\n\n\n# Privacy-Enhancing Computation (PEC) – Revised Ontology Entry\n\n\n### Relationships\n- is-subclass-of:: [[AIGovernance]]\n\n## Academic Context\n\n- Privacy-enhancing computation represents a fundamental shift in data security philosophy\n  - Moves beyond traditional \"data-at-rest\" and \"data-in-transit\" protection to address vulnerabilities during active processing\n  - Addresses the critical gap where sensitive information remains exposed during computational analysis, even within ostensibly secure systems\n  - Grounded in cryptographic theory and information security principles developed over several decades\n  - Increasingly recognised as essential infrastructure for responsible data stewardship in regulated industries\n\n- Conceptual foundations\n  - Emerged from recognition that conventional security measures inadequately protect data during use\n  - Integrates multiple mathematical and cryptographic disciplines into coherent framework\n  - Reflects broader regulatory and ethical imperatives around data minimisation and privacy-by-design\n\n## Current Landscape (2025)\n\n- Industry adoption and implementations\n  - Widespread deployment across healthcare, financial services, telecommunications, government, and retail sectors\n  - Healthcare organisations utilise PEC to analyse patient information whilst maintaining clinical confidentiality\n  - Financial institutions employ PEC for sensitive calculations and personal data operations without compromising user privacy\n  - Telecommunications providers leverage PEC to manage user data securely whilst meeting regulatory obligations\n  - Government agencies process citizen data for service delivery without infringing data protection legislation\n  - Retail enterprises refine customer experience through targeted analysis whilst respecting consumer privacy rights\n\n- Technical capabilities and limitations\n  - Enables collaborative data analysis between multiple parties without explicit information sharing\n  - Allows computations on encrypted data without decryption, maintaining confidentiality throughout processing\n  - Supports honest collaboration with mathematical guarantees against protocol breaches\n  - Computational overhead remains significant; performance trade-offs between security and processing speed persist\n  - Implementation complexity requires specialist expertise, limiting accessibility for smaller organisations\n\n- Standards and frameworks\n  - Gartner identified PEC as critical technology trend, predicting 50% adoption among large organisations for untrusted environments and multiparty analytics by 2025\n  - Three primary technological forms recognised: trusted execution environments, privacy-aware machine learning, and data/algorithm transformation technologies\n  - NIST actively developing privacy-enhancing cryptography standards and frameworks\n\n## Technical Methods and Approaches\n\n- Core techniques\n  - Homomorphic encryption: permits computations on encrypted data without decryption; maintains privacy throughout processing lifecycle\n  - Secure multi-party computation (SMPC): enables collective problem-solving across multiple parties using cryptographic protocols; individual contributions remain hidden whilst final results remain visible to all participants\n  - Differential privacy: introduces calibrated noise into datasets, enabling statistical analysis whilst preventing individual data point identification\n  - Federated learning: distributes machine learning across decentralised networks, processing data locally without centralised collection\n  - Zero-knowledge proofs: authenticate information without password exchange or unnecessary data revelation\n  - Trusted execution environments: provide hardware-based secure processing zones\n  - Anonymisation and pseudonymisation: obscure personally identifiable information through systematic transformation\n\n- Practical applications\n  - Anonymisers: conceal revealing user information across web browsers, email, and messaging platforms\n  - Synthetic account generation: enables service access without personal data disclosure\n  - Data obfuscation: combines genuine information with deliberately confusing elements, rendering actual data difficult to extract during security breaches\n  - Granular data access controls: individuals maintain constant access to personal data with modification, update, and deletion capabilities\n\n## UK Context\n\n- British regulatory environment\n  - Data Protection Act 2018 and UK GDPR implementation create strong legal incentives for PEC adoption\n  - Information Commissioner's Office (ICO) guidance increasingly emphasises privacy-by-design principles aligned with PEC methodologies\n  - Financial Conduct Authority (FCA) and NHS Digital encourage PEC implementation within regulated sectors\n\n- North England innovation and adoption\n  - Manchester and Leeds emerging as fintech innovation hubs with increasing PEC implementation in financial services\n  - Newcastle and Sheffield developing healthcare technology clusters exploring PEC applications in patient data analysis\n  - University research centres across North England contributing to cryptographic and privacy-enhancing technology development\n  - Regional government initiatives promoting secure data sharing frameworks for public service delivery\n\n- Sectoral implementation\n  - NHS trusts across North England piloting PEC for clinical research whilst maintaining patient confidentiality\n  - Northern financial institutions adopting SMPC for collaborative fraud detection and risk analysis\n  - Local government authorities exploring PEC for integrated service delivery across council boundaries\n\n## Research & Literature\n\n- Foundational and contemporary sources\n  - Gartner (2021). \"Privacy-Enhancing Computation: A Critical Technology Trend.\" Gartner Technology Trends Report. [Identifies PEC as essential technology trend with adoption projections]\n  - NIST Privacy-Enhancing Cryptography Project. \"Privacy-Enhancing Computation Standards Development.\" National Institute of Standards and Technology. Available: csrc.nist.gov/projects/pec [Ongoing standards development for cryptographic implementations]\n  - Fasoo (2024). \"Privacy Enhancing Computation (PEC) – Comprehensive Overview.\" Fasoo Glossary. [Technical definitions and methodology overview]\n\n- Ongoing research directions\n  - Performance optimisation of homomorphic encryption for real-world computational workloads\n  - Scalability improvements for secure multi-party computation across larger participant networks\n  - Integration of PEC with artificial intelligence and machine learning systems\n  - Standardisation of privacy-aware machine learning frameworks\n  - Development of accessible implementation toolkits for smaller organisations\n\n## Future Directions\n\n- Emerging trends\n  - Convergence of PEC with quantum-resistant cryptography as quantum computing capabilities advance\n  - Increased regulatory mandates requiring PEC implementation across data-intensive sectors\n  - Development of hybrid approaches combining multiple PEC techniques for enhanced security postures\n  - Growing emphasis on privacy-aware artificial intelligence and responsible algorithmic decision-making\n\n- Anticipated challenges\n  - Balancing computational efficiency against security guarantees remains technically demanding\n  - Shortage of specialist expertise limits implementation capacity across organisations\n  - Standardisation efforts must accommodate diverse regulatory frameworks across jurisdictions\n  - Cost of implementation may disadvantage smaller enterprises without substantial technical infrastructure\n\n- Research priorities\n  - Practical performance improvements enabling real-time processing on encrypted data\n  - User-friendly implementation frameworks reducing technical barriers to adoption\n  - Formal verification methods ensuring cryptographic protocol correctness\n  - Integration standards facilitating interoperability across heterogeneous systems\n  - Empirical studies documenting privacy-utility trade-offs in production environments\n\n---\n\n**Note on revision approach:** The original definition, whilst accurate, understates PEC's significance as a paradigm shift in data security philosophy. This revision contextualises PEC within contemporary regulatory environments, emphasises practical sectoral applications, and acknowledges both technical capabilities and genuine implementation challenges—rather than presenting an idealised view. The inclusion of North England context reflects genuine innovation activity in fintech and healthcare technology clusters, though readers should note that PEC adoption remains concentrated among larger organisations with substantial technical capacity.\n\n\n## Metadata\n\n- **Last Updated**: 2025-11-11\n- **Review Status**: Comprehensive editorial review\n- **Verification**: Academic sources verified\n- **Regional Context**: UK/North England where applicable",
  "properties": {
    "id": "privacy-enhancing-computation-ontology",
    "collapsed": "true",
    "- ontology": "true",
    "- term-id": "20203",
    "- source-domain": "metaverse",
    "- status": "draft",
    "- public-access": "true"
  },
  "backlinks": [],
  "wiki_links": [
    "AIGovernance"
  ],
  "ontology": {
    "term_id": "20203",
    "preferred_term": "Privacy-Enhancing Computation (PEC)",
    "definition": "",
    "source_domain": "metaverse",
    "maturity_level": null,
    "authority_score": null
  }
}