{
  "title": "Private Key",
  "content": "- ### OntologyBlock\n  id:: private-key-ontology\n  collapsed:: true\n\n  - **Identification**\n\n    - domain-prefix:: BC\n\n    - sequence-number:: 0036\n\n    - filename-history:: [\"BC-0036-private-key.md\"]\n    - public-access:: true\n    - ontology:: true\n    - is-subclass-of:: [[BlockchainTechnology]]\n    - term-id:: BC-0036\n    - preferred-term:: Private Key\n    - source-domain:: blockchain\n    - status:: complete\n    - version:: 1.0.0\n    - last-updated:: 2025-10-28\n\n  - **Definition**\n    - definition:: Secret cryptographic key within blockchain systems, providing essential functionality for distributed ledger technology operations and properties.\n    - maturity:: mature\n    - source:: [[ISO/IEC 23257:2021]], [[IEEE 2418.1]], [[NIST NISTIR]]\n    - authority-score:: 0.95\n\n  - **Semantic Classification**\n    - owl:class:: bc:PrivateKey\n    - owl:physicality:: VirtualEntity\n    - owl:role:: Object\n    - owl:inferred-class:: bc:VirtualObject\n    - belongsToDomain:: [[CryptographicDomain]]\n\n  - #### OWL Restrictions\n    \n    \n\n  - #### CrossDomainBridges\n    - bridges-to:: [[BlockchainEntity]] via is-subclass-of\n\n  -",
  "properties": {
    "id": "private-key-ontology",
    "collapsed": "true",
    "- domain-prefix": "BC",
    "- sequence-number": "0036",
    "- filename-history": "[\"BC-0036-private-key.md\"]",
    "- public-access": "true",
    "- ontology": "true",
    "- is-subclass-of": "[[BlockchainTechnology]]",
    "- term-id": "BC-0036",
    "- preferred-term": "Private Key",
    "- source-domain": "blockchain",
    "- status": "complete",
    "- version": "1.0.0",
    "- last-updated": "2025-10-28",
    "- definition": "Secret cryptographic key within blockchain systems, providing essential functionality for distributed ledger technology operations and properties.",
    "- maturity": "mature",
    "- source": "[[ISO/IEC 23257:2021]], [[IEEE 2418.1]], [[NIST NISTIR]]",
    "- authority-score": "0.95",
    "- owl:class": "bc:PrivateKey",
    "- owl:physicality": "VirtualEntity",
    "- owl:role": "Object",
    "- owl:inferred-class": "bc:VirtualObject",
    "- belongsToDomain": "[[CryptographicDomain]]",
    "- bridges-to": "[[BlockchainEntity]] via is-subclass-of"
  },
  "backlinks": [
    "Runes and Glyphs"
  ],
  "wiki_links": [
    "IEEE 2418.1",
    "BlockchainTechnology",
    "NIST NISTIR",
    "CryptographicDomain",
    "BlockchainEntity",
    "ISO/IEC 23257:2021"
  ],
  "ontology": {
    "term_id": "BC-0036",
    "preferred_term": "Private Key",
    "definition": "Secret cryptographic key within blockchain systems, providing essential functionality for distributed ledger technology operations and properties.",
    "source_domain": "blockchain",
    "maturity_level": null,
    "authority_score": 0.95
  }
}