{
  "title": "Procedural Texture",
  "content": "- ### OntologyBlock\n  id:: proceduraltexture-ontology\n  collapsed:: true\n\t- ontology:: true\n\t- term-id:: 20193\n\t- source-domain:: metaverse\n\t- status:: draft\n\t- is-subclass-of:: [[Metaverse Infrastructure]]\n\t- public-access:: true\n\n\n\n# Procedural Texture – Updated Ontology Entry\n\n## Academic Context\n\n- Procedural texturing represents a fundamental paradigm shift in computer graphics, moving away from storage-intensive image-based approaches\n  - Mathematically defined surfaces computed in real-time rather than pre-rendered and stored\n  - Emerged from early computer graphics research seeking memory-efficient alternatives to traditional texture mapping\n  - Solid texturing methodology evaluates texture-generating functions across three-dimensional space at each visible surface point, ensuring material properties depend on 3D position rather than parametrised 2D surface coordinates[2]\n  - Eliminates distortions inherent in surface parameter space, particularly problematic near spherical poles and across adjacent patch boundaries[2]\n\n## Current Landscape (2025)\n\n- Industry adoption and implementations\n  - Procedural textures remain standard in professional 3D graphics pipelines, particularly for large-scale environments where memory efficiency proves critical\n  - LightWave 3D and comparable professional rendering platforms integrate procedural texture layers as seamless alternatives to image maps, requiring no projection method specification[3]\n  - Algorithmically generated patterns create marble, wood grain, granite, stone, and metal surfaces dynamically without increasing memory footprint[2][4]\n  - Scalability and parametric control make procedural approaches ideal for generating endless variations and customisable details difficult to achieve manually[4]\n  - Game engines and real-time rendering systems leverage procedural textures for infinite texture resolution and adaptive detail levels\n  \n- Technical capabilities and limitations\n  - Fractal noise and turbulence functions provide numerical representations of natural randomness, typically implemented via Simplex or Perlin noise algorithms[2]\n  - Current techniques span structured regular textures (brick walls), structured irregular textures (stonewalls), and purely stochastic patterns[2]\n  - Texture Value parameters define intensity at peak points; semi-transparent areas blend with underlying layers, enabling sophisticated layering workflows[3]\n  - Automatic sizing functionality assists practitioners in calibrating scale values relative to surface dimensions, though manual adjustment remains necessary for precise control[3]\n  - Computational overhead during rendering can exceed pre-computed image lookups in certain scenarios, though this trade-off typically favours procedural approaches for memory-constrained environments\n\n- Standards and frameworks\n  - Physically Based Rendering (PBR) frameworks increasingly incorporate procedural textures to simulate real-world material properties—roughness, reflectivity, and light scattering behaviour—ensuring consistency across diverse lighting conditions[6]\n  - Shader-based implementations define procedural textures through mathematical instructions executed by rendering software, bridging texturing and shading workflows[6]\n\n## Research & Literature\n\n- Key academic and technical sources\n  - Perlin, K. (1985). \"An Image Synthesizer.\" *SIGGRAPH Computer Graphics*, 19(3), 287–296. DOI: 10.1145/325165.325247 – Foundational work establishing noise functions for procedural texture generation\n  - Simplex noise implementations and improvements documented in contemporary graphics literature, providing superior computational efficiency compared to classical Perlin noise\n  - Tutorials Point. \"Procedural 3D Textures for Texture Mapping.\" Comprehensive technical overview addressing mathematical function mapping (denoted as cr(p)) from 3D points to RGB colours[1]\n  - Scratch a Pixel. \"Procedural Texturing – Introduction to Shading.\" Educational resource explaining procedural texturing principles and mathematical equation-based pattern generation[5]\n  - LightWave 3D Documentation (2025). \"Texture Mapping: Procedural Textures.\" Current software implementation guidance demonstrating practical workflow integration[3]\n\n- Ongoing research directions\n  - Symbolic differentiation approaches for procedural surface definition, as demonstrated in contemporary Microsoft Research initiatives[7]\n  - Hybrid methodologies combining procedural generation with machine learning for adaptive texture synthesis\n  - Real-time procedural texture streaming optimisation for bandwidth-constrained environments\n\n## UK Context\n\n- British contributions and implementations\n  - UK-based visual effects studios and game development companies extensively utilise procedural texturing for large-scale environmental assets, particularly within the thriving games industry centred around Cambridge, Guildford, and other technology hubs\n  - Academic research in procedural graphics continues at leading UK institutions, though specific North England contributions to procedural texture methodology remain dispersed across general computer graphics research programmes\n  \n- North England considerations\n  - Manchester, Leeds, and Sheffield host growing game development and digital media sectors where procedural texturing proves essential for cost-effective asset production\n  - No region-specific procedural texture frameworks or standards have emerged; adoption follows international best practices and industry-standard tools\n  - Educational institutions across North England incorporate procedural texturing into computer graphics curricula as part of standard 3D graphics training\n\n## Future Directions\n\n- Emerging trends and developments\n  - Integration with generative AI systems for intelligent procedural texture synthesis based on high-level descriptive parameters\n  - Real-time procedural texture modification during gameplay, enabling dynamic environmental adaptation without asset reloading\n  - Improved symbolic differentiation techniques enabling more sophisticated mathematical texture definitions with reduced computational overhead\n  \n- Anticipated challenges\n  - Balancing computational cost against visual fidelity as procedural complexity increases\n  - Standardising procedural texture interchange formats across disparate rendering platforms and engines\n  - Maintaining artistic control whilst leveraging algorithmic generation—a perennial tension in procedural workflows (rather like asking a mathematician to paint, though with marginally better results)\n  \n- Research priorities\n  - Efficient procedural texture caching and memoisation strategies for real-time applications\n  - Cross-platform procedural texture portability and standardisation\n  - Hybrid approaches combining procedural generation with neural networks for photorealistic material synthesis\n\n## References\n\n1. Tutorials Point. \"Procedural 3D Textures for Texture Mapping.\" Available at: tutorialspoint.com/computer_graphics/procedural_3d_textures_for_texture_mapping.htm\n\n2. Wikipedia. \"Procedural Texture.\" Available at: en.wikipedia.org/wiki/Procedural_texture\n\n3. LightWave 3D Documentation (2025). \"Texture Mapping: Procedural Textures.\" Available at: docs.lightwave3d.com/2025/layer-type-procedural-texture.html\n\n4. Lenovo. \"Texture Mapping in 3D Graphics: Definition, Types & How It Works.\" Available at: lenovo.com/us/en/glossary/texture-mapping/\n\n5. Scratch a Pixel. \"Procedural Texturing – Introduction to Shading.\" Available at: scratchapixel.com/lessons/3d-basic-rendering/introduction-to-shading/procedural-texturing.html\n\n6. CADA. \"Unveiling the Artistry of 3D Texturing.\" Available at: cada-edu.com/guides/texturing\n\n7. Microsoft Research. \"Procedural Texture.\" Video demonstration of procedural surfaces defined using symbolic differentiation. Available at: microsoft.com/en-us/research/video/procedural-texture/\n\n\n## Metadata\n\n- **Last Updated**: 2025-11-11\n- **Review Status**: Comprehensive editorial review\n- **Verification**: Academic sources verified\n- **Regional Context**: UK/North England where applicable",
  "properties": {
    "id": "proceduraltexture-ontology",
    "collapsed": "true",
    "- ontology": "true",
    "- term-id": "20193",
    "- source-domain": "metaverse",
    "- status": "draft",
    "- is-subclass-of": "[[Metaverse Infrastructure]]",
    "- public-access": "true"
  },
  "backlinks": [],
  "wiki_links": [
    "Metaverse Infrastructure"
  ],
  "ontology": {
    "term_id": "20193",
    "preferred_term": "Procedural Texture",
    "definition": "",
    "source_domain": "metaverse",
    "maturity_level": null,
    "authority_score": null
  }
}