{
  "title": "Projects",
  "content": "- ### OntologyBlock\n  id:: projects-ontology\n  collapsed:: true\n\t- ontology:: true\n\t- term-id:: mv-221207825242\n\t- preferred-term:: Projects\n\t- source-domain:: metaverse\n\t- status:: active\n\t- public-access:: true\n\t- definition:: A component of the metaverse ecosystem focusing on projects.\n\t- maturity:: mature\n\t- authority-score:: 0.85\n\t- owl:class:: mv:Projects\n\t- owl:physicality:: ConceptualEntity\n\t- owl:role:: Concept\n\t- belongsToDomain:: [[MetaverseDomain]]\n\t- #### Relationships\n\t  id:: projects-relationships\n\t\t- enables:: [[ImmersiveExperience]], [[Presence]], [[SpatialComputing]]\n\t\t- requires:: [[DisplayTechnology]], [[TrackingSystem]], [[RenderingEngine]]\n\t\t- bridges-to:: [[HumanComputerInteraction]], [[ComputerVision]], [[Robotics]]\n\n\t- #### OWL Axioms\n\t  id:: projects-owl-axioms\n\t  collapsed:: true\n\t\t- ```clojure\n\t\t  Declaration(Class(mv:Projects))\n\n\t\t  # Classification\n\t\t  SubClassOf(mv:Projects mv:ConceptualEntity)\n\t\t  SubClassOf(mv:Projects mv:Concept)\n\n\t\t  # Domain classification\n\t\t  SubClassOf(mv:Projects\n\t\t    ObjectSomeValuesFrom(mv:belongsToDomain mv:MetaverseDomain)\n\t\t  )\n\n\t\t  # Annotations\n\t\t  AnnotationAssertion(rdfs:label mv:Projects \"Projects\"@en)\n\t\t  AnnotationAssertion(rdfs:comment mv:Projects \"A component of the metaverse ecosystem focusing on projects.\"@en)\n\t\t  AnnotationAssertion(dcterms:identifier mv:Projects \"mv-221207825242\"^^xsd:string)\n\t\t  ```\n\n- Fashion 3D objects\n\t- TODO write a script to start the docker for CRM\n\t\t- ```text\n\t\t  machinelearn@MLAI:/mnt/mldata/GenerativeAI/ComfyUI$ docker ps\n\t\t  CONTAINER ID   IMAGE                                  COMMAND                  CREATED        STATUS        PORTS                                       NAMES\n\t\t  d8bc0b15a890   yanwk/comfyui-boot:megapak             \"bash /runner-script…\"   9 hours ago    Up 9 hours    0.0.0.0:8188->8188/tcp, :::8188->8188/tcp   comfyui-mega\n\t\t  7428acfbd648   ghcr.io/open-webui/open-webui:ollama   \"bash start.sh\"          27 hours ago   Up 22 hours   0.0.0.0:3000->8080/tcp, :::3000->8080/tcp   open-webui\n\t\t  machinelearn@MLAI:/mnt/mldata/GenerativeAI/ComfyUI$ docker stop comfyui-mega\n\t\t  comfyui-mega\n\t\t  \n\t\t  ```\n\t- DONE Bind it to llama3\n- Binding social immersive spaces with AI\n\t- [[Metaverse Ontology]]\n\t- [[Ontology conversation with AIs]]\n\t- [[Knowledge Graphing]]\n\t- [[Agentic Mycelia]]\n\t- [[Agentic Metaverse for Global Creatives]]\n\t- [[Multi Agent RAG scrapbook]]\n\t-\n-\n\n## Current Landscape (2025)\n\n- Industry adoption and implementations\n  - Metaverse platforms continue to evolve with focus on interoperability and open standards\n  - Web3 integration accelerating with decentralised identity and asset ownership\n  - Enterprise adoption growing in virtual collaboration, training, and digital twins\n  - UK companies increasingly active in metaverse development and immersive technologies\n\n- Technical capabilities\n  - Real-time rendering at photorealistic quality levels\n  - Low-latency networking enabling seamless multi-user experiences\n  - AI-driven content generation and procedural world building\n  - Spatial audio and haptics enhancing immersion\n\n- UK and North England context\n  - Manchester: Digital Innovation Factory supports metaverse startups and research\n  - Leeds: Holovis leads in immersive experiences for entertainment and training\n  - Newcastle: University research in spatial computing and interactive systems\n  - Sheffield: Advanced manufacturing using digital twin technology\n\n- Standards and frameworks\n  - Metaverse Standards Forum driving interoperability protocols\n  - WebXR enabling browser-based immersive experiences\n  - glTF and USD for 3D asset interchange\n  - Open Metaverse Interoperability Group defining cross-platform standards\n\n## Metadata\n\n- **Last Updated**: 2025-11-16\n- **Review Status**: Automated remediation with 2025 context\n- **Verification**: Academic sources verified\n- **Regional Context**: UK/North England where applicable",
  "properties": {
    "id": "projects-owl-axioms",
    "collapsed": "true",
    "- ontology": "true",
    "- term-id": "mv-221207825242",
    "- preferred-term": "Projects",
    "- source-domain": "metaverse",
    "- status": "active",
    "- public-access": "true",
    "- definition": "A component of the metaverse ecosystem focusing on projects.",
    "- maturity": "mature",
    "- authority-score": "0.85",
    "- owl:class": "mv:Projects",
    "- owl:physicality": "ConceptualEntity",
    "- owl:role": "Concept",
    "- belongsToDomain": "[[MetaverseDomain]]",
    "- enables": "[[ImmersiveExperience]], [[Presence]], [[SpatialComputing]]",
    "- requires": "[[DisplayTechnology]], [[TrackingSystem]], [[RenderingEngine]]",
    "- bridges-to": "[[HumanComputerInteraction]], [[ComputerVision]], [[Robotics]]",
    "d8bc0b15a890   yanwk/comfyui-boot:megapak             \"bash /runner-script…\"   9 hours ago    Up 9 hours    0.0.0.0:8188->8188/tcp,": ":8188->8188/tcp   comfyui-mega",
    "7428acfbd648   ghcr.io/open-webui/open-webui:ollama   \"bash start.sh\"          27 hours ago   Up 22 hours   0.0.0.0:3000->8080/tcp,": ":3000->8080/tcp   open-webui"
  },
  "backlinks": [
    "AI Search",
    "Open Webui and Pipelines",
    "Knowledge Graphing",
    "BC-0037-public-key",
    "Agentic Alliance"
  ],
  "wiki_links": [
    "RenderingEngine",
    "Agentic Mycelia",
    "SpatialComputing",
    "Multi Agent RAG scrapbook",
    "Presence",
    "Ontology conversation with AIs",
    "Metaverse Ontology",
    "ComputerVision",
    "Robotics",
    "MetaverseDomain",
    "DisplayTechnology",
    "Knowledge Graphing",
    "TrackingSystem",
    "ImmersiveExperience",
    "HumanComputerInteraction",
    "Agentic Metaverse for Global Creatives"
  ],
  "ontology": {
    "term_id": "mv-221207825242",
    "preferred_term": "Projects",
    "definition": "A component of the metaverse ecosystem focusing on projects.",
    "source_domain": "metaverse",
    "maturity_level": null,
    "authority_score": 0.85
  }
}