{
  "title": "Project BroBots",
  "content": "- ### OntologyBlock\n  id:: project-brobots-ontology\n  collapsed:: true\n\t- ontology:: true\n\t- term-id:: mv-950883424226\n\t- preferred-term:: Project BroBots\n\t- source-domain:: metaverse\n\t- status:: active\n\t- public-access:: true\n\t- definition:: A component of the metaverse ecosystem focusing on project brobots.\n\t- maturity:: mature\n\t- authority-score:: 0.85\n\t- owl:class:: mv:ProjectBrobots\n\t- owl:physicality:: ConceptualEntity\n\t- owl:role:: Concept\n\t- belongsToDomain:: [[MetaverseDomain]]\n\t- #### Relationships\n\t  id:: project-brobots-relationships\n\t\t- enables:: [[ImmersiveExperience]], [[Presence]], [[SpatialComputing]]\n\t\t- requires:: [[DisplayTechnology]], [[TrackingSystem]], [[RenderingEngine]]\n\t\t- bridges-to:: [[HumanComputerInteraction]], [[ComputerVision]], [[Robotics]]\n\n\t- #### OWL Axioms\n\t  id:: project-brobots-owl-axioms\n\t  collapsed:: true\n\t\t- ```clojure\n\t\t  Declaration(Class(mv:ProjectBrobots))\n\n\t\t  # Classification\n\t\t  SubClassOf(mv:ProjectBrobots mv:ConceptualEntity)\n\t\t  SubClassOf(mv:ProjectBrobots mv:Concept)\n\n\t\t  # Domain classification\n\t\t  SubClassOf(mv:ProjectBrobots\n\t\t    ObjectSomeValuesFrom(mv:belongsToDomain mv:MetaverseDomain)\n\t\t  )\n\n\t\t  # Annotations\n\t\t  AnnotationAssertion(rdfs:label mv:ProjectBrobots \"Project BroBots\"@en)\n\t\t  AnnotationAssertion(rdfs:comment mv:ProjectBrobots \"A component of the metaverse ecosystem focusing on project brobots.\"@en)\n\t\t  AnnotationAssertion(dcterms:identifier mv:ProjectBrobots \"mv-950883424226\"^^xsd:string)\n\t\t  ```\n\npublic:: true\n\n- # Project: BroBots\n- ## Mission Statement\n\t- To address the negative impacts of toxic online behavior by developing a multi-agent system that can identify and counter harmful content.\n- ## Problem Space\n\t- The internet is increasingly populated by bots and trolls that spread misinformation and engage in harassment. This has a negative impact on online discourse and can lead to real-world harm.\n- ## Proposed Solution\n\t- We propose to build a multi-agent system that can:\n\t\t- **Identify harmful content:** Use natural language processing (NLP) to identify toxic language, hate speech, and misinformation.\n\t\t- **Counter harmful content:** Generate counter-narratives and engage with users in a positive and constructive way.\n\t\t- **Promote healthy online communities:** Encourage positive online behavior and create a more welcoming and inclusive online environment.\n- ## Tech Stack\n\t- **Large Language Models:** Llama 3 70B, Mixtral 8B\n\t- **Fine-tuning:** Fine-tune a smaller model on a corpus of Reddit data to identify and classify harmful content.\n\t- **Agent Framework:** Use the Agentic Alliance tech stack to build and deploy the multi-agent system.\n\t- **Data Sources:** Reddit API (if available), other social media platforms.\n- ## Challenges\n\t- **Data availability:** Access to social media data is becoming increasingly restricted.\n\t- **Defining \"harmful content\":** What constitutes harmful content is subjective and can vary depending on the context.\n\t- **Ethical considerations:** It is important to ensure that the multi-agent system is used in a responsible and ethical way.\n- ## See Also\n\t- [[Digital Society Harms]]\n\t- [[Death of the Internet]]\n\t- [[Agents]]\n\t- [[Agentic Alliance]]\n\n## Current Landscape (2025)\n\n- Industry adoption and implementations\n  - Metaverse platforms continue to evolve with focus on interoperability and open standards\n  - Web3 integration accelerating with decentralised identity and asset ownership\n  - Enterprise adoption growing in virtual collaboration, training, and digital twins\n  - UK companies increasingly active in metaverse development and immersive technologies\n\n- Technical capabilities\n  - Real-time rendering at photorealistic quality levels\n  - Low-latency networking enabling seamless multi-user experiences\n  - AI-driven content generation and procedural world building\n  - Spatial audio and haptics enhancing immersion\n\n- UK and North England context\n  - Manchester: Digital Innovation Factory supports metaverse startups and research\n  - Leeds: Holovis leads in immersive experiences for entertainment and training\n  - Newcastle: University research in spatial computing and interactive systems\n  - Sheffield: Advanced manufacturing using digital twin technology\n\n- Standards and frameworks\n  - Metaverse Standards Forum driving interoperability protocols\n  - WebXR enabling browser-based immersive experiences\n  - glTF and USD for 3D asset interchange\n  - Open Metaverse Interoperability Group defining cross-platform standards\n\n## Metadata\n\n- **Last Updated**: 2025-11-16\n- **Review Status**: Automated remediation with 2025 context\n- **Verification**: Academic sources verified\n- **Regional Context**: UK/North England where applicable",
  "properties": {
    "id": "project-brobots-owl-axioms",
    "collapsed": "true",
    "- ontology": "true",
    "- term-id": "mv-950883424226",
    "- preferred-term": "Project BroBots",
    "- source-domain": "metaverse",
    "- status": "active",
    "- public-access": "true",
    "- definition": "A component of the metaverse ecosystem focusing on project brobots.",
    "- maturity": "mature",
    "- authority-score": "0.85",
    "- owl:class": "mv:ProjectBrobots",
    "- owl:physicality": "ConceptualEntity",
    "- owl:role": "Concept",
    "- belongsToDomain": "[[MetaverseDomain]]",
    "- enables": "[[ImmersiveExperience]], [[Presence]], [[SpatialComputing]]",
    "- requires": "[[DisplayTechnology]], [[TrackingSystem]], [[RenderingEngine]]",
    "- bridges-to": "[[HumanComputerInteraction]], [[ComputerVision]], [[Robotics]]",
    "public": "true"
  },
  "backlinks": [],
  "wiki_links": [
    "RenderingEngine",
    "Robotics",
    "Death of the Internet",
    "ComputerVision",
    "Digital Society Harms",
    "HumanComputerInteraction",
    "Agentic Alliance",
    "TrackingSystem",
    "ImmersiveExperience",
    "Agents",
    "DisplayTechnology",
    "SpatialComputing",
    "Presence",
    "MetaverseDomain"
  ],
  "ontology": {
    "term_id": "mv-950883424226",
    "preferred_term": "Project BroBots",
    "definition": "A component of the metaverse ecosystem focusing on project brobots.",
    "source_domain": "metaverse",
    "maturity_level": null,
    "authority_score": 0.85
  }
}