{
  "title": "Proof of Authority",
  "content": "- ### OntologyBlock\n  id:: proofofauthority-ontology\n  collapsed:: true\n\n  - **Identification**\n    - domain-prefix:: BC\n    - sequence-number:: 0547\n    - filename-history:: [\"BC-0547-proofofauthority.md\"]\n    - public-access:: true\n    - ontology:: true\n    - term-id:: BC-0547\n    - preferred-term:: Proof of Authority\n    - source-domain:: metaverse\n    - status:: complete\n    - version:: 1.0.0\n    - last-updated:: 2025-11-13\n\n  - **Definition**\n    - definition:: A consensus mechanism where pre-approved validators (authorities) with verified identities are authorized to validate transactions and create blocks.\n    - maturity:: established\n    - source:: Chimera Prime Research\n    - authority-score:: 0.95\n\n  - **Semantic Classification**\n    - owl:class:: bc:ProofOfAuthority\n    - is-subclass-of:: [[Blockchain]]\n    - belongsToDomain:: [[Blockchain]]\n\n  - #### OWL Restrictions\n    \n\n  -",
  "properties": {
    "id": "proofofauthority-ontology",
    "collapsed": "true",
    "- domain-prefix": "BC",
    "- sequence-number": "0547",
    "- filename-history": "[\"BC-0547-proofofauthority.md\"]",
    "- public-access": "true",
    "- ontology": "true",
    "- term-id": "BC-0547",
    "- preferred-term": "Proof of Authority",
    "- source-domain": "metaverse",
    "- status": "complete",
    "- version": "1.0.0",
    "- last-updated": "2025-11-13",
    "- definition": "A consensus mechanism where pre-approved validators (authorities) with verified identities are authorized to validate transactions and create blocks.",
    "- maturity": "established",
    "- source": "Chimera Prime Research",
    "- authority-score": "0.95",
    "- owl:class": "bc:ProofOfAuthority",
    "- is-subclass-of": "[[Blockchain]]",
    "- belongsToDomain": "[[Blockchain]]"
  },
  "backlinks": [],
  "wiki_links": [
    "Blockchain"
  ],
  "ontology": {
    "term_id": "BC-0547",
    "preferred_term": "Proof of Authority",
    "definition": "A consensus mechanism where pre-approved validators (authorities) with verified identities are authorized to validate transactions and create blocks.",
    "source_domain": "metaverse",
    "maturity_level": null,
    "authority_score": 0.95
  }
}