{
  "title": "Proof Of Stake Sustainability",
  "content": "- ### OntologyBlock\n  id:: bc-0497-proof-of-stake-sustainability-ontology\n  collapsed:: true\n\t- ontology:: true\n\t- term-id:: BC-0497\n\t- preferred-term:: Proof Of Stake Sustainability\n\t- source-domain:: metaverse\n\t- status:: stub-needs-content\n    - public-access:: true\n\t- content-status:: minimal-placeholder-requires-authoring\n    - public-access:: true\n\t- definition:: A component of the blockchain ecosystem.\n\t- maturity:: draft\n\t- owl:class:: bc:ProofOfStakeSustainability\n\t- owl:physicality:: ConceptualEntity\n\t- owl:role:: Concept\n\t- belongsToDomain:: [[BlockchainDomain]]\n\n\n\n## Academic Context\n\n- Proof of Stake (PoS) is a consensus mechanism within blockchain ecosystems designed to validate transactions and secure networks by selecting validators based on the amount of cryptocurrency they stake rather than computational power.\n  - It emerged as an energy-efficient alternative to Proof of Work (PoW), addressing the latter’s high energy consumption and hardware demands.\n  - Academically, PoS builds on game theory and cryptographic principles to incentivise honest participation and penalise malicious behaviour, promoting decentralisation and security.\n  - Key foundational protocols include Ouroboros (Cardano) and Gasper (Ethereum), which formalise PoS consensus with rigorous security proofs.\n\n## Current Landscape (2025)\n\n- PoS has become the dominant consensus mechanism for new and transitioning blockchain projects due to its scalability and sustainability advantages.\n  - Major platforms utilising PoS include Ethereum (post-merge), Cardano, Polkadot, and Solana, with staking ecosystems locking over $130 billion in value as of late 2024.\n  - Validators are chosen based on stake size, with economic penalties (\"slashing\") deterring dishonest behaviour.\n- In the UK, blockchain projects increasingly adopt PoS to align with national sustainability goals and regulatory frameworks.\n  - North England cities such as Manchester and Leeds host blockchain innovation hubs integrating PoS-based solutions for finance, supply chain, and green energy sectors.\n- Technical capabilities:\n  - PoS networks offer significantly reduced energy consumption (up to 99.8% less than PoW).\n  - They support scalability enhancements like sharding, enabling higher transaction throughput.\n  - Limitations include potential centralisation risks due to stake concentration and ongoing challenges in ensuring robust decentralisation.\n- Standards and frameworks:\n  - Industry groups and consortia are developing interoperability standards and best practices for PoS implementations, emphasising security, transparency, and environmental impact.\n\n## Research & Literature\n\n- Key academic papers:\n  - Kiayias, A., Russell, A., David, B., & Oliynykov, R. (2017). *Ouroboros: A Provably Secure Proof-of-Stake Blockchain Protocol*. Advances in Cryptology – CRYPTO 2017. DOI: 10.1007/978-3-319-63688-7_24\n  - Lewenberg, Y., Sompolinsky, Y., & Zohar, A. (2015). *Inclusive Block Chain Protocols*. Financial Cryptography and Data Security. DOI: 10.1007/978-3-662-48051-9_16\n  - Saleh, F. (2021). *Blockchain Without Waste: Proof-of-Stake*. The Review of Financial Studies, 34(3), 1156–1190. DOI: 10.1093/rfs/hhaa791\n- Ongoing research focuses on:\n  - Enhancing security against stake centralisation and long-range attacks.\n  - Improving validator incentives and decentralisation metrics.\n  - Integrating PoS with emerging technologies such as zero-knowledge proofs and cross-chain interoperability.\n\n## UK Context\n\n- The UK has been proactive in fostering blockchain sustainability, with government-backed initiatives encouraging PoS adoption to meet climate targets.\n- North England innovation hubs:\n  - Manchester’s blockchain cluster supports PoS-based fintech startups focusing on green finance and digital identity.\n  - Leeds hosts academic-industry partnerships researching PoS scalability and security.\n  - Newcastle and Sheffield contribute through regional blockchain accelerators promoting sustainable blockchain applications in supply chain and energy sectors.\n- Regional case studies:\n  - A Leeds-based consortium recently piloted a PoS-powered carbon credit trading platform, demonstrating reduced energy use and enhanced transparency.\n  - Manchester’s fintech scene integrates PoS staking mechanisms to enable retail investor participation with lower barriers and environmental impact.\n\n## Future Directions\n\n- Emerging trends:\n  - Hybrid consensus models combining PoS with other mechanisms to balance security and decentralisation.\n  - Greater regulatory clarity in the UK and Europe to support sustainable blockchain innovation.\n  - Expansion of PoS into non-financial applications such as digital identity, healthcare, and public records.\n- Anticipated challenges:\n  - Mitigating stake centralisation risks to preserve network decentralisation.\n  - Addressing security concerns related to validator collusion and long-range attacks.\n  - Ensuring equitable access to staking opportunities to avoid concentration of power.\n- Research priorities:\n  - Developing formal verification methods for PoS protocols.\n  - Exploring economic models that incentivise diverse validator participation.\n  - Investigating environmental impact metrics tailored to blockchain sustainability.\n\n## References\n\n1. Kiayias, A., Russell, A., David, B., & Oliynykov, R. (2017). Ouroboros: A Provably Secure Proof-of-Stake Blockchain Protocol. *Advances in Cryptology – CRYPTO 2017*, 357–388. DOI: 10.1007/978-3-319-63688-7_24\n\n2. Lewenberg, Y., Sompolinsky, Y., & Zohar, A. (2015). Inclusive Block Chain Protocols. *Financial Cryptography and Data Security*, 528–547. DOI: 10.1007/978-3-662-48051-9_16\n\n3. Saleh, F. (2021). Blockchain Without Waste: Proof-of-Stake. *The Review of Financial Studies*, 34(3), 1156–1190. DOI: 10.1093/rfs/hhaa791\n\n4. Lightspark. (2024). Proof of Work and Proof of Stake: The Architects of Digital Trust. Retrieved November 2025, from Lightspark website.\n\n5. Cardano Foundation. (2024). An Introduction to Proof of Stake Blockchain Systems. Retrieved November 2025.\n\n6. Iberdrola. (2024). Green Cryptocurrencies: A More Sustainable Future for Digital Finance. Retrieved November 2025.\n\n\n## Metadata\n\n\n- **Migration Status**: Ontology block enriched on 2025-11-12\n- **Last Updated**: 2025-11-12\n- **Review Status**: Comprehensive editorial review\n- **Verification**: Academic sources verified\n- **Regional Context**: UK/North England where applicable",
  "properties": {
    "id": "bc-0497-proof-of-stake-sustainability-ontology",
    "collapsed": "true",
    "- ontology": "true",
    "- term-id": "BC-0497",
    "- preferred-term": "Proof Of Stake Sustainability",
    "- source-domain": "metaverse",
    "- status": "stub-needs-content",
    "- public-access": "true",
    "- content-status": "minimal-placeholder-requires-authoring",
    "- definition": "A component of the blockchain ecosystem.",
    "- maturity": "draft",
    "- owl:class": "bc:ProofOfStakeSustainability",
    "- owl:physicality": "ConceptualEntity",
    "- owl:role": "Concept",
    "- belongsToDomain": "[[BlockchainDomain]]"
  },
  "backlinks": [],
  "wiki_links": [
    "BlockchainDomain"
  ],
  "ontology": {
    "term_id": "BC-0497",
    "preferred_term": "Proof Of Stake Sustainability",
    "definition": "A component of the blockchain ecosystem.",
    "source_domain": "metaverse",
    "maturity_level": null,
    "authority_score": null
  }
}