{
  "title": "Proprietary Large Language Models",
  "content": "- ### OntologyBlock\n  id:: proprietary-large-language-models-ontology\n  collapsed:: true\n\t- ontology:: true\n\t- term-id:: mv-816522063571\n\t- preferred-term:: Proprietary Large Language Models\n\t- source-domain:: metaverse\n\t- status:: active\n\t- public-access:: true\n\t- definition:: A component of the metaverse ecosystem focusing on proprietary large language models.\n\t- maturity:: mature\n\t- authority-score:: 0.85\n\t- owl:class:: mv:ProprietaryLargeLanguageModels\n\t- owl:physicality:: ConceptualEntity\n\t- owl:role:: Concept\n\t- belongsToDomain:: [[MetaverseDomain]]\n\t- #### Relationships\n\t  id:: proprietary-large-language-models-relationships\n\t\t- enables:: [[ImmersiveExperience]], [[Presence]], [[SpatialComputing]]\n\t\t- requires:: [[DisplayTechnology]], [[TrackingSystem]], [[RenderingEngine]]\n\t\t- bridges-to:: [[HumanComputerInteraction]], [[ComputerVision]], [[Robotics]]\n\n\t- #### OWL Axioms\n\t  id:: proprietary-large-language-models-owl-axioms\n\t  collapsed:: true\n\t\t- ```clojure\n\t\t  Declaration(Class(mv:ProprietaryLargeLanguageModels))\n\n\t\t  # Classification\n\t\t  SubClassOf(mv:ProprietaryLargeLanguageModels mv:ConceptualEntity)\n\t\t  SubClassOf(mv:ProprietaryLargeLanguageModels mv:Concept)\n\n\t\t  # Domain classification\n\t\t  SubClassOf(mv:ProprietaryLargeLanguageModels\n\t\t    ObjectSomeValuesFrom(mv:belongsToDomain mv:MetaverseDomain)\n\t\t  )\n\n\t\t  # Annotations\n\t\t  AnnotationAssertion(rdfs:label mv:ProprietaryLargeLanguageModels \"Proprietary Large Language Models\"@en)\n\t\t  AnnotationAssertion(rdfs:comment mv:ProprietaryLargeLanguageModels \"A component of the metaverse ecosystem focusing on proprietary large language models.\"@en)\n\t\t  AnnotationAssertion(dcterms:identifier mv:ProprietaryLargeLanguageModels \"mv-816522063571\"^^xsd:string)\n\t\t  ```\n\npublic:: true\n\n- #Public page\n\t- automatically published\n- ## Closed source Large Language Models: and [[AI Companies]]\n\t- ![1712680210067.jpeg](../assets/1712680210067_1712686278817_0.jpeg)\n\t- [LinkedIn post from Peter Gostev](https://www.linkedin.com/posts/peter-gostev_we-are-seeing-some-clear-categories-emerge-activity-7183501457684365314-iihT?)\n\t-\n\t- ### OpenAI & ChatGPT\n\t\t- ðŸŸ¢ ChatGPT mobile [app revenue suggests](https://techcrunch.com/2023/10/09/chatgpts-mobile-app-hit-record-4-58m-in-revenue-last-month-but-growth-is-slowing/) around 250,000 users of their pro service **globally**. That is much lower than I thought... Let's assume only one in ten paying users install the app. That's still 2.5M users, which is about 0.003% of the eligible population.\n\t\t- They have released a [Prompt engineering\n\t\t- OpenAI API](https://platform.openai.com/docs/guides/prompt-engineering) guide.\n\t\t- I have a [[Prompt Engineering]] section too.\n\t\t- The GPT \"store\" / app experience.\n\t\t- A note about GPTs. They really are quite powerful. Think of them as an app builder, containing an AI agent, in a box, with [bidirectional internet](https://medium.com/@michaelev3/connecting-custom-gpts-to-google-apis-726dc2cdb54d), and the ability to build code. (such as which is an excellent coding assistant [Grimoire](https://chat.openai.com/g/g-n7Rs0IK86-grimoire)). - ðŸŸ¢ They are the most advantage you can get for $20 a month, if you have tasks that you repeat, and you're not a coder. **\n\t\t- Note they now want $25 if you want to keep your data out of their training set.**\n\t\t\t- {{{tweet https://twitter.com/ConsensusNLP/status/1724872225780625419}}}\n\t\t- This is called \"Actions\" and is only in the GPTs or via the API (or both)\n\t\t- ðŸŸ¢ Microsoft integrates OpenAI right across their suites under the [[Microsoft CoPilot]] brand.\n\t\t  id:: 659a922a-e819-4baa-b323-c07b3cf85290\n\t\t- This is pure speculation, but it feels like Microsoft might eventually effectively take over, being more experienced, mature, and canny.\n\t\t- The novel structural reason for OpenAI existing the way it did (a non-profit with a \"fuse\" for runaway AI) has been broken.\n\t\t- Keep an eye out for the remaining canary in the coal mine which is OpenAI declaring [[Artificial Intelligence]], isolating Microsoft from that element of their models. They might pretend [[Artificial Superintelligence]] for commercial reasons.\n\t- ### Anthropic\n\t\t- Smaller, unsure how much smaller, it's a fork of people from OpenAI, but has radically exceeded earning expectations.\n\t\t- [[Constitutional AI]], like Asimov's laws of robotics\n\t\t- ðŸŸ¢ [anthropics/sleeper-agents-paper: Contains random samples referenced in the paper \"Sleeper Agents: Training Robustly Deceptive LLMs that Persist Through Safety Training\". (github.com)](https://github.com/anthropics/sleeper-agents-paper)\n\t\t- {{twitter https://twitter.com/natfriedman/status/1777739863678386268/photo/1}}\n\t- ### Grok from Musk is pretty bad, but..\n\t\t- People haven't appreciated the strength of the business model Musk has\n\t\t- His is the only unified language and vision company in the world at this scale that can handle real world interactions.\n\t- ### Google Gemini\n\t\t- Incredible million token context and [[Multimodal]]\n\t\t- Not as capable as Claude3 but writes more human readable text than ChatGPT\n\t\t- [Gemini 1.5 and Googleâ€™s Nature â€“ Stratechery by Ben Thompson](https://stratechery.com/2024/gemini-1-5-and-googles-nature/)\n\t\t- For me the interesting one is Nano, which is natively multimodal (4 bit 1-3B) and fits in a phone.\n\t\t- I think we'll look back at Nano as having signalled the future.\n\t- ### Salesforce\n\t\t- Slack. Don't discount Salesforce. Again, if you use slack, stick with this for now. **All** of the tools are coming to **all** of the platforms.\n- # Actionable LLM advice:\n\t- Stick with the tools in the ecosystem you have already bought, until you need more. If your data is in Google use Google. If it's in Microsoft use Microsoft. If you use Runway / Mid journey then please do continue.\n\t- The edge isn't between vendors, it's a deep understanding of what problems you need it to solve, and the disposition of your data, or business technical edge.\n\t- Importance of unique business strategies over proprietary technology. [Harvard Business Review](https://hbr.org/2023/12/strategy-not-technology-is-the-key-to-winning-with-genai).\n\t\t- Necessity for firms to create value beyond technical features.\n\t\t- Focus on building strong brands and exceptional customer experiences.\n\t\t- Significance of strategic human resource management, including talent retention and skill development.\n\t- Sort your data management protocols out. Nobody wants to, but things are getting confusing. For me that's as simple as logseq and github.\n\t\t- Nearly 10,000 data points that reach well into active code and research. (graph).\n\t- The OpenAI kerfuffle last year has alerted companies to the fragility of single providers.\n\t- Consider how business critical the tooling is becoming over time for your business. Have a **NOW / NEXT / LATER** plan. Have and understand options but don't waste too much time exploring them, focus is king.\n\t- There are now many cloud middleware solutions that will handle the prompt realignment, load balancing, pricing etc across the whole [[Proprietary Large Language Models]] [[landscape]].\n\t- I think open source will win in the end because SO many people in the world will be forced and/or want not to use these few hyper centralised providers. **This is a contentious opinion**.\n\t- {{embed ((659fe0be-a52a-42ef-8f50-73695a802945))}}\n\t- https://www.reddit.com/r/StableDiffusion/comments/18tqyn4/midjourney_v60_vs_sdxl_exact_same_prompts_using/\n\t- If your business needs custom **models** then still do as much with off the shelf as you can. You need to be mindful of ethics and the law. This is non-trivial. The team here can help.\n\t- Regardless of the scale and technical proficiency of your team, these tools, especially the open source ones, can provide a rapid way to ask your customers **\"is this what you mean?\"**. People are bad at specifying, but good at instinctive validation. You can then go and manufacture a properly optimised and legally compliant toolchain.\n- This is a [[presentation]] side, and the next slide is [[Proprietary Image Generation]]\n\n## Current Landscape (2025)\n\n- Industry adoption and implementations\n  - Metaverse platforms continue to evolve with focus on interoperability and open standards\n  - Web3 integration accelerating with decentralised identity and asset ownership\n  - Enterprise adoption growing in virtual collaboration, training, and digital twins\n  - UK companies increasingly active in metaverse development and immersive technologies\n\n- Technical capabilities\n  - Real-time rendering at photorealistic quality levels\n  - Low-latency networking enabling seamless multi-user experiences\n  - AI-driven content generation and procedural world building\n  - Spatial audio and haptics enhancing immersion\n\n- UK and North England context\n  - Manchester: Digital Innovation Factory supports metaverse startups and research\n  - Leeds: Holovis leads in immersive experiences for entertainment and training\n  - Newcastle: University research in spatial computing and interactive systems\n  - Sheffield: Advanced manufacturing using digital twin technology\n\n- Standards and frameworks\n  - Metaverse Standards Forum driving interoperability protocols\n  - WebXR enabling browser-based immersive experiences\n  - glTF and USD for 3D asset interchange\n  - Open Metaverse Interoperability Group defining cross-platform standards\n\n## Metadata\n\n- **Last Updated**: 2025-11-16\n- **Review Status**: Automated remediation with 2025 context\n- **Verification**: Academic sources verified\n- **Regional Context**: UK/North England where applicable",
  "properties": {
    "id": "659a922a-e819-4baa-b323-c07b3cf85290",
    "collapsed": "true",
    "- ontology": "true",
    "- term-id": "mv-816522063571",
    "- preferred-term": "Proprietary Large Language Models",
    "- source-domain": "metaverse",
    "- status": "active",
    "- public-access": "true",
    "- definition": "A component of the metaverse ecosystem focusing on proprietary large language models.",
    "- maturity": "mature",
    "- authority-score": "0.85",
    "- owl:class": "mv:ProprietaryLargeLanguageModels",
    "- owl:physicality": "ConceptualEntity",
    "- owl:role": "Concept",
    "- belongsToDomain": "[[MetaverseDomain]]",
    "- enables": "[[ImmersiveExperience]], [[Presence]], [[SpatialComputing]]",
    "- requires": "[[DisplayTechnology]], [[TrackingSystem]], [[RenderingEngine]]",
    "- bridges-to": "[[HumanComputerInteraction]], [[ComputerVision]], [[Robotics]]",
    "public": "true"
  },
  "backlinks": [
    "Suggested Reading Order",
    "Proprietary Large Language Models",
    "Technical History (extended CV)",
    "State of the art in AI",
    "HOST January 17th Presentation",
    "Overview of Machine Learning Techniques",
    "Hardware and Edge",
    "BC-0014-block-time"
  ],
  "wiki_links": [
    "MetaverseDomain",
    "TrackingSystem",
    "landscape",
    "Constitutional AI",
    "Microsoft CoPilot",
    "ImmersiveExperience",
    "Robotics",
    "SpatialComputing",
    "Multimodal",
    "AI Companies",
    "Proprietary Image Generation",
    "Artificial Intelligence",
    "presentation",
    "RenderingEngine",
    "DisplayTechnology",
    "Prompt Engineering",
    "Presence",
    "Artificial Superintelligence",
    "ComputerVision",
    "HumanComputerInteraction",
    "Proprietary Large Language Models"
  ],
  "ontology": {
    "term_id": "mv-816522063571",
    "preferred_term": "Proprietary Large Language Models",
    "definition": "A component of the metaverse ecosystem focusing on proprietary large language models.",
    "source_domain": "metaverse",
    "maturity_level": null,
    "authority_score": 0.85
  }
}