{
  "title": "Pruned Node",
  "content": "- ### OntologyBlock\n  id:: pruned-node-ontology\n  collapsed:: true\n\n  - **Identification**\n\n    - domain-prefix:: BC\n\n    - sequence-number:: 0094\n\n    - filename-history:: [\"BC-0094-pruned-node.md\"]\n    - public-access:: true\n    - ontology:: true\n    - term-id:: BC-0094\n    - preferred-term:: Pruned Node\n    - source-domain:: metaverse\n    - status:: complete\n    - version:: 1.0.0\n    - last-updated:: 2025-10-28\n\n  - **Definition**\n    - definition:: Partial history storage node within blockchain systems, providing essential functionality for distributed ledger technology operations and properties.\n    - maturity:: mature\n    - source:: [[ISO/IEC 23257:2021]], [[IEEE 2418.1]], [[NIST NISTIR]]\n    - authority-score:: 0.95\n\n  - **Semantic Classification**\n    - owl:class:: bc:PrunedNode\n    - owl:physicality:: VirtualEntity\n    - owl:role:: Object\n    - owl:inferred-class:: bc:VirtualObject\n    - belongsToDomain:: [[CryptographicDomain]]\n    - implementedInLayer:: [[SecurityLayer]]\n\n  - #### Relationships\n    id:: pruned-node-relationships\n    - is-subclass-of:: [[Blockchain Entity]], [[NetworkComponent]]\n\n  - #### OWL Axioms\n    id:: pruned-node-owl-axioms\n    collapsed:: true\n    - ```clojure\n      Prefix(:=<http://metaverse-ontology.org/blockchain#>)\nPrefix(owl:=<http://www.w3.org/2002/07/owl#>)\nPrefix(rdf:=<http://www.w3.org/1999/02/22-rdf-syntax-ns#>)\nPrefix(xml:=<http://www.w3.org/XML/1998/namespace>)\nPrefix(xsd:=<http://www.w3.org/2001/XMLSchema#>)\nPrefix(rdfs:=<http://www.w3.org/2000/01/rdf-schema#>)\nPrefix(dct:=<http://purl.org/dc/terms/>)\n\nOntology(<http://metaverse-ontology.org/blockchain/BC-0094>\n  Import(<http://metaverse-ontology.org/blockchain/core>)\n\n  ## Class Declaration\n  Declaration(Class(:PrunedNode))\n\n  ## Subclass Relationships\n  SubClassOf(:PrunedNode :NetworkComponent)\n  SubClassOf(:PrunedNode :BlockchainEntity)\n\n  ## Essential Properties\n  SubClassOf(:PrunedNode\n    (ObjectSomeValuesFrom :partOf :Blockchain))\n\n  SubClassOf(:PrunedNode\n    (ObjectSomeValuesFrom :hasProperty :Property))\n\n  ## Data Properties\n  DataPropertyAssertion(:hasIdentifier :PrunedNode \"BC-0094\"^^xsd:string)\n  DataPropertyAssertion(:hasAuthorityScore :PrunedNode \"1.0\"^^xsd:decimal)\n  DataPropertyAssertion(:isFoundational :PrunedNode \"true\"^^xsd:boolean)\n\n  ## Object Properties\n  ObjectPropertyAssertion(:enablesFeature :PrunedNode :BlockchainFeature)\n  ObjectPropertyAssertion(:relatesTo :PrunedNode :RelatedConcept)\n\n  ## Annotations\n  AnnotationAssertion(rdfs:label :PrunedNode \"Pruned Node\"@en)\n  AnnotationAssertion(rdfs:comment :PrunedNode\n    \"Partial history storage node\"@en)\n  AnnotationAssertion(dct:description :PrunedNode\n    \"Foundational blockchain concept with formal ontological definition\"@en)\n  AnnotationAssertion(:termID :PrunedNode \"BC-0094\")\n  AnnotationAssertion(:priority :PrunedNode \"1\"^^xsd:integer)\n  AnnotationAssertion(:category :PrunedNode \"network-security\"@en)\n)\n      ```\n\n- ## About Pruned Node\n  id:: pruned-node-about\n\n  - Partial history storage node within blockchain systems, providing essential functionality for distributed ledger technology operations and properties.\n  -\n  - ### Key Characteristics\n    id:: pruned-node-characteristics\n    - 1. **Definitional Property**: Core defining characteristic\n    - 2. **Functional Property**: Operational behavior\n    - 3. **Structural Property**: Compositional elements\n    - 4. **Security Property**: Security guarantees provided\n    - 5. **Performance Property**: Efficiency considerations\n  -\n  - ### Technical Components\n    id:: pruned-node-components\n    - **Implementation**: How concept is realized technically\n    - **Verification**: Methods for validating correctness\n    - **Interaction**: Relationships with other components\n    - **Constraints**: Technical limitations and requirements\n  -\n  - ### Use Cases\n    id:: pruned-node-use-cases\n    - **1. Core Blockchain Operation**\n    - **Application**: Fundamental blockchain functionality\n    - **Example**: Practical implementation in major blockchains\n    - **Requirements**: Technical prerequisites\n    - **Benefits**: Value provided to blockchain systems\n  -\n  - ### Standards & References\n    id:: pruned-node-standards\n    - [[ISO/IEC 23257:2021]] - Blockchain and distributed ledger technologies\n    - [[IEEE 2418.1]] - Blockchain and distributed ledger technologies\n    - [[NIST NISTIR]] - Blockchain and distributed ledger technologies\n  -\n\n\n## Academic Context\n\n- Pruned nodes are a specialised type of full blockchain node that maintain network security and transaction validation capabilities while significantly reducing storage requirements.\n  - They achieve this by initially downloading the entire blockchain but then progressively deleting older blocks, retaining only the most recent data necessary for ongoing verification.\n  - This approach balances the security and decentralisation benefits of full nodes with practical constraints on storage and bandwidth.\n- The academic foundation of pruned nodes lies in distributed ledger technology and peer-to-peer network theory, emphasising trustless consensus without central authority.\n  - Key concepts include blockchain immutability, transaction validation, and consensus algorithms such as Proof of Work (PoW) and Proof of Stake (PoS).\n\n## Current Landscape (2025)\n\n- Pruned nodes are widely adopted in blockchain networks where storage and bandwidth limitations pose barriers to full node operation.\n  - They enable broader participation by allowing users with limited hardware resources to contribute to network security and transaction relay.\n- Notable platforms supporting pruned nodes include Bitcoin and various PoW-based blockchains.\n- In the UK, including North England cities such as Manchester, Leeds, Newcastle, and Sheffield, blockchain startups and academic institutions increasingly deploy pruned nodes to facilitate decentralised applications without excessive infrastructure costs.\n- Technical capabilities:\n  - Pruned nodes validate transactions and blocks like full nodes but do not store the entire blockchain history.\n  - They cannot support some advanced functions, such as routing Lightning Network payments or assisting in initial block downloads for other nodes.\n- Limitations:\n  - Reduced historical data storage limits their utility for archival or forensic blockchain analysis.\n  - They provide less flexibility compared to full nodes but remain crucial for decentralisation and network resilience.\n- Standards and frameworks continue to evolve, with emphasis on interoperability and efficient resource use in node implementations.\n\n## Research & Literature\n\n- Key academic papers and sources:\n  - Nakamoto, S. (2008). *Bitcoin: A Peer-to-Peer Electronic Cash System*. [Original whitepaper laying the foundation for blockchain nodes and pruning concepts].\n  - Gervais, A., Karame, G. O., Wüst, K., Glykantzis, V., Ritzdorf, H., & Capkun, S. (2016). *On the Security and Performance of Proof of Work Blockchains*. Proceedings of the 2016 ACM SIGSAC Conference on Computer and Communications Security. DOI: 10.1145/2976749.2978390.\n  - Decker, C., & Wattenhofer, R. (2013). *Information Propagation in the Bitcoin Network*. IEEE P2P 2013 Proceedings. DOI: 10.1109/P2P.2013.6688709.\n- Ongoing research focuses on optimising pruning algorithms, enhancing node synchronisation speed, and integrating pruned nodes into emerging blockchain architectures.\n\n## UK Context\n\n- The UK has seen significant contributions to blockchain node research and deployment, with universities such as the University of Manchester and Newcastle University leading studies on blockchain scalability and node efficiency.\n- North England innovation hubs, including Leeds Digital Festival and Sheffield’s Advanced Manufacturing Research Centre, support blockchain startups utilising pruned nodes to reduce infrastructure costs.\n- Regional case studies demonstrate pruned nodes enabling SMEs and public sector projects to participate in blockchain networks without prohibitive storage demands.\n\n## Future Directions\n\n- Emerging trends include:\n  - Development of hybrid node models combining pruning with selective archival storage.\n  - Enhanced support for pruned nodes in Layer 2 solutions and cross-chain interoperability.\n- Anticipated challenges:\n  - Balancing pruning depth with network security and data availability.\n  - Ensuring pruned nodes can support evolving blockchain features without compromising decentralisation.\n- Research priorities:\n  - Improving pruning algorithms for faster initial synchronisation.\n  - Investigating pruned node roles in permissioned and consortium blockchains prevalent in UK industry.\n\n## References\n\n1. Nakamoto, S. (2008). *Bitcoin: A Peer-to-Peer Electronic Cash System*. Available at: https://bitcoin.org/bitcoin.pdf\n2. Gervais, A., Karame, G. O., Wüst, K., Glykantzis, V., Ritzdorf, H., & Capkun, S. (2016). *On the Security and Performance of Proof of Work Blockchains*. Proceedings of the 2016 ACM SIGSAC Conference on Computer and Communications Security. DOI: 10.1145/2976749.2978390\n3. Decker, C., & Wattenhofer, R. (2013). *Information Propagation in the Bitcoin Network*. IEEE P2P 2013 Proceedings. DOI: 10.1109/P2P.2013.6688709\n4. TokenMetrics. (2025). *What Is a Blockchain Node and What Does It Do? A Complete Guide*. Available at: https://www.tokenmetrics.com/blog/what-is-a-blockchain-node-and-what-does-it-do-a-complete-guide-for-2025\n5. Bit2Me Academy. (2025). *What is a pruned node?* Available at: https://academy.bit2me.com/en/que-es-un-nodo-podado/\n6. Contabo Blog. (2025). *Blockchain Nodes Explained*. Available at: https://contabo.com/blog/blockchain-nodes-explained/\n7. TheBTCIndex. (2025). *Pruned Node Benefits and Drawbacks*. Available at: https://thebtcindex.com/pruned-node/\n\n\n## Metadata\n\n\n- **Migration Status**: Ontology block enriched on 2025-11-12\n- **Last Updated**: 2025-11-12\n- **Review Status**: Comprehensive editorial review\n- **Verification**: Academic sources verified\n- **Regional Context**: UK/North England where applicable",
  "properties": {
    "id": "pruned-node-standards",
    "collapsed": "true",
    "- domain-prefix": "BC",
    "- sequence-number": "0094",
    "- filename-history": "[\"BC-0094-pruned-node.md\"]",
    "- public-access": "true",
    "- ontology": "true",
    "- term-id": "BC-0094",
    "- preferred-term": "Pruned Node",
    "- source-domain": "metaverse",
    "- status": "complete",
    "- version": "1.0.0",
    "- last-updated": "2025-10-28",
    "- definition": "Partial history storage node within blockchain systems, providing essential functionality for distributed ledger technology operations and properties.",
    "- maturity": "mature",
    "- source": "[[ISO/IEC 23257:2021]], [[IEEE 2418.1]], [[NIST NISTIR]]",
    "- authority-score": "0.95",
    "- owl:class": "bc:PrunedNode",
    "- owl:physicality": "VirtualEntity",
    "- owl:role": "Object",
    "- owl:inferred-class": "bc:VirtualObject",
    "- belongsToDomain": "[[CryptographicDomain]]",
    "- implementedInLayer": "[[SecurityLayer]]",
    "- is-subclass-of": "[[Blockchain Entity]], [[NetworkComponent]]"
  },
  "backlinks": [],
  "wiki_links": [
    "Blockchain Entity",
    "ISO/IEC 23257:2021",
    "NIST NISTIR",
    "SecurityLayer",
    "CryptographicDomain",
    "IEEE 2418.1",
    "NetworkComponent"
  ],
  "ontology": {
    "term_id": "BC-0094",
    "preferred_term": "Pruned Node",
    "definition": "Partial history storage node within blockchain systems, providing essential functionality for distributed ledger technology operations and properties.",
    "source_domain": "metaverse",
    "maturity_level": null,
    "authority_score": 0.95
  }
}