{
  "title": "Python and PyTorch",
  "content": "- ### OntologyBlock\n  id:: python-and-pytorch-ontology\n  collapsed:: true\n\t- ontology:: true\n\t- term-id:: mv-682405397089\n\t- preferred-term:: Python and PyTorch\n\t- source-domain:: metaverse\n\t- status:: active\n\t- public-access:: true\n\t- definition:: A component of the metaverse ecosystem focusing on python and pytorch.\n\t- maturity:: mature\n\t- authority-score:: 0.85\n\t- owl:class:: mv:PythonAndPytorch\n\t- owl:physicality:: ConceptualEntity\n\t- owl:role:: Concept\n\t- belongsToDomain:: [[MetaverseDomain]]\n\t- #### Relationships\n\t  id:: python-and-pytorch-relationships\n\t\t- enables:: [[ImmersiveExperience]], [[Presence]], [[SpatialComputing]]\n\t\t- requires:: [[DisplayTechnology]], [[TrackingSystem]], [[RenderingEngine]]\n\t\t- bridges-to:: [[HumanComputerInteraction]], [[ComputerVision]], [[Robotics]]\n\n\t- #### OWL Axioms\n\t  id:: python-and-pytorch-owl-axioms\n\t  collapsed:: true\n\t\t- ```clojure\n\t\t  Declaration(Class(mv:PythonAndPytorch))\n\n\t\t  # Classification\n\t\t  SubClassOf(mv:PythonAndPytorch mv:ConceptualEntity)\n\t\t  SubClassOf(mv:PythonAndPytorch mv:Concept)\n\n\t\t  # Domain classification\n\t\t  SubClassOf(mv:PythonAndPytorch\n\t\t    ObjectSomeValuesFrom(mv:belongsToDomain mv:MetaverseDomain)\n\t\t  )\n\n\t\t  # Annotations\n\t\t  AnnotationAssertion(rdfs:label mv:PythonAndPytorch \"Python and PyTorch\"@en)\n\t\t  AnnotationAssertion(rdfs:comment mv:PythonAndPytorch \"A component of the metaverse ecosystem focusing on python and pytorch.\"@en)\n\t\t  AnnotationAssertion(dcterms:identifier mv:PythonAndPytorch \"mv-682405397089\"^^xsd:string)\n\t\t  ```\n\n- https://intel.github.io/intel-extension-for-pytorch/#introduction [[Python and PyTorch]]\n- https://github.com/pydn/ComfyUI-to-Python-Extension [[Python and PyTorch]] [[ComfyUI]] convert to python code\n- [spaCy Â· Industrial-strength Natural Language Processing in Python](https://spacy.io/) [[Python and PyTorch]] [[Machine Learning]]\n- https://pytorch.org/blog/flexattention/ [[Python and PyTorch]] [[Large language models]]\n- [[Nostr protocol]] https://alashazam.wordpress.com/2024/07/04/python-nostr-third-program/ [[Python and PyTorch]]\n\n## Current Landscape (2025)\n\n- Industry adoption and implementations\n  - Metaverse platforms continue to evolve with focus on interoperability and open standards\n  - Web3 integration accelerating with decentralised identity and asset ownership\n  - Enterprise adoption growing in virtual collaboration, training, and digital twins\n  - UK companies increasingly active in metaverse development and immersive technologies\n\n- Technical capabilities\n  - Real-time rendering at photorealistic quality levels\n  - Low-latency networking enabling seamless multi-user experiences\n  - AI-driven content generation and procedural world building\n  - Spatial audio and haptics enhancing immersion\n\n- UK and North England context\n  - Manchester: Digital Innovation Factory supports metaverse startups and research\n  - Leeds: Holovis leads in immersive experiences for entertainment and training\n  - Newcastle: University research in spatial computing and interactive systems\n  - Sheffield: Advanced manufacturing using digital twin technology\n\n- Standards and frameworks\n  - Metaverse Standards Forum driving interoperability protocols\n  - WebXR enabling browser-based immersive experiences\n  - glTF and USD for 3D asset interchange\n  - Open Metaverse Interoperability Group defining cross-platform standards\n\n## Metadata\n\n- **Last Updated**: 2025-11-16\n- **Review Status**: Automated remediation with 2025 context\n- **Verification**: Academic sources verified\n- **Regional Context**: UK/North England where applicable",
  "properties": {
    "id": "python-and-pytorch-owl-axioms",
    "collapsed": "true",
    "- ontology": "true",
    "- term-id": "mv-682405397089",
    "- preferred-term": "Python and PyTorch",
    "- source-domain": "metaverse",
    "- status": "active",
    "- public-access": "true",
    "- definition": "A component of the metaverse ecosystem focusing on python and pytorch.",
    "- maturity": "mature",
    "- authority-score": "0.85",
    "- owl:class": "mv:PythonAndPytorch",
    "- owl:physicality": "ConceptualEntity",
    "- owl:role": "Concept",
    "- belongsToDomain": "[[MetaverseDomain]]",
    "- enables": "[[ImmersiveExperience]], [[Presence]], [[SpatialComputing]]",
    "- requires": "[[DisplayTechnology]], [[TrackingSystem]], [[RenderingEngine]]",
    "- bridges-to": "[[HumanComputerInteraction]], [[ComputerVision]], [[Robotics]]"
  },
  "backlinks": [
    "Python and PyTorch",
    "ollama"
  ],
  "wiki_links": [
    "MetaverseDomain",
    "Presence",
    "Python and PyTorch",
    "Machine Learning",
    "SpatialComputing",
    "Nostr protocol",
    "RenderingEngine",
    "TrackingSystem",
    "DisplayTechnology",
    "HumanComputerInteraction",
    "ImmersiveExperience",
    "Robotics",
    "ComputerVision",
    "ComfyUI",
    "Large language models"
  ],
  "ontology": {
    "term_id": "mv-682405397089",
    "preferred_term": "Python and PyTorch",
    "definition": "A component of the metaverse ecosystem focusing on python and pytorch.",
    "source_domain": "metaverse",
    "maturity_level": null,
    "authority_score": 0.85
  }
}