{
  "title": "Question Answering",
  "content": "- ### OntologyBlock\n  id:: question-answering-ontology\n  collapsed:: true\n\t- ontology:: true\n\t- term-id:: AI-0371\n\t- preferred-term:: Question Answering\n\t- source-domain:: ai\n\t- status:: draft\n    - public-access:: true\n\t- definition:: Question Answering (QA) is the NLP task of automatically generating accurate answers to natural language questions posed by users, either by extracting answers from text passages (extractive QA) or generating free-form responses (generative QA). QA systems employ reading comprehension models, retrieval-augmented generation, and knowledge reasoning to power applications including search engines, virtual assistants, and customer support.\n\n\n\n## Academic Context\n\n- Question Answering (QA) is a specialised task within natural language processing (NLP) and information retrieval focused on automatically providing accurate answers to questions posed in natural language.\n  - It builds on foundational fields such as computational linguistics, machine learning, and knowledge representation.\n  - Early QA systems relied on rule-based and keyword matching techniques; modern systems leverage deep learning, transformers, and knowledge graphs to understand and generate responses.\n  - The academic community has extensively studied extractive QA (selecting answers from texts) and generative QA (producing free-form answers), with ongoing research into hybrid approaches combining retrieval and generation.\n\n## Current Landscape (2025)\n\n- QA systems are widely adopted across industries including search engines, virtual assistants, customer support, healthcare, and education.\n  - Leading platforms integrate retrieval-augmented generation (RAG) models, combining large language models (LLMs) with external knowledge sources for improved accuracy and context-awareness.\n  - Notable organisations include Google, Microsoft, OpenAI, and IBM Watson, which continue to push the boundaries of QA capabilities.\n- In the UK, and particularly in North England, universities and tech hubs in Manchester, Leeds, Newcastle, and Sheffield contribute to QA research and development, often collaborating with industry partners.\n- Technical capabilities:\n  - Modern QA systems handle complex queries, multi-hop reasoning, and context retention across dialogues.\n  - Limitations remain in handling ambiguous or highly specialised domain questions, robustness to noisy data, and ensuring factual correctness in generative outputs.\n- Standards and frameworks:\n  - QA development increasingly follows open benchmarks such as SQuAD, Natural Questions, and the MRQA shared tasks.\n  - Ethical guidelines and transparency standards are emerging to address biases and explainability in QA systems.\n\n## Research & Literature\n\n- Key academic papers and sources:\n  - Rajpurkar, P., et al. (2016). \"SQuAD: 100,000+ Questions for Machine Comprehension of Text.\" *EMNLP*. DOI: 10.18653/v1/D16-1264\n  - Kwiatkowski, T., et al. (2019). \"Natural Questions: A Benchmark for Question Answering Research.\" *Transactions of the Association for Computational Linguistics*, 7, 453–466. DOI: 10.1162/tacl_a_00276\n  - Lewis, M., et al. (2020). \"Retrieval-Augmented Generation for Knowledge-Intensive NLP Tasks.\" *NeurIPS*. URL: https://arxiv.org/abs/2005.11401\n  - Chen, D., et al. (2023). \"Advances in Question Answering: Insights from NAACL 2025 Papers.\" *NAACL Proceedings*.\n- Ongoing research directions:\n  - Enhancing multi-modal QA integrating text, images, and structured data.\n  - Improving interpretability and trustworthiness of generative QA.\n  - Domain adaptation for specialised fields such as law, medicine, and finance.\n  - Addressing low-resource languages and dialects, including regional UK variants.\n\n## UK Context\n\n- The UK has a strong tradition in NLP and QA research, with institutions like the University of Manchester and University of Leeds leading projects in language understanding and AI.\n- North England innovation hubs:\n  - Manchester’s AI and Data Science Institute focuses on applied NLP and QA for healthcare and public services.\n  - Leeds Digital Hub supports startups developing conversational AI and QA tools for customer service automation.\n  - Newcastle and Sheffield universities collaborate on knowledge graph construction and semantic QA.\n- Regional case studies:\n  - Deployment of QA systems in NHS digital services to improve patient information access.\n  - Local government initiatives in Leeds utilising QA chatbots for citizen engagement and service queries.\n\n## Future Directions\n\n- Emerging trends:\n  - Integration of QA with AI agents capable of multi-turn, context-rich conversations.\n  - Expansion of QA into multi-modal and cross-lingual domains.\n  - Greater emphasis on ethical AI, reducing bias, and enhancing user trust.\n- Anticipated challenges:\n  - Balancing generative creativity with factual accuracy to avoid “hallucinations.”\n  - Ensuring privacy and data security in QA systems accessing sensitive information.\n  - Addressing the digital divide to make QA technologies accessible across diverse UK populations.\n- Research priorities:\n  - Developing robust evaluation metrics beyond accuracy, including fairness and explainability.\n  - Enhancing QA systems’ ability to handle ambiguous or incomplete queries.\n  - Fostering interdisciplinary collaboration between linguistics, computer science, and social sciences.\n\n## References\n\n1. Rajpurkar, P., Jia, R., & Liang, P. (2016). SQuAD: 100,000+ Questions for Machine Comprehension of Text. *EMNLP*. DOI: 10.18653/v1/D16-1264  \n2. Kwiatkowski, T., Palomaki, J., Redfield, O., Collins, M., Parikh, A., Alberti, C., ... & Petrov, S. (2019). Natural Questions: A Benchmark for Question Answering Research. *Transactions of the Association for Computational Linguistics*, 7, 453–466. DOI: 10.1162/tacl_a_00276  \n3. Lewis, M., Perez, E., Piktus, A., Petroni, F., Karpukhin, V., Goyal, N., ... & Riedel, S. (2020). Retrieval-Augmented Generation for Knowledge-Intensive NLP Tasks. *NeurIPS*. URL: https://arxiv.org/abs/2005.11401  \n4. Chen, D., et al. (2023). Advances in Question Answering: Insights from NAACL 2025 Papers. *NAACL Proceedings*.  \n5. Oracle. (2025). An Introduction to NLP (Natural Language Processing). Oracle AI Blog.  \n6. MarketMuse. (2025). Question Answering Definition. MarketMuse Blog.\n\n\n## Metadata\n\n- **Last Updated**: 2025-11-11\n- **Review Status**: Comprehensive editorial review\n- **Verification**: Academic sources verified\n- **Regional Context**: UK/North England where applicable",
  "properties": {
    "id": "question-answering-ontology",
    "collapsed": "true",
    "- ontology": "true",
    "- term-id": "AI-0371",
    "- preferred-term": "Question Answering",
    "- source-domain": "ai",
    "- status": "draft",
    "- public-access": "true",
    "- definition": "Question Answering (QA) is the NLP task of automatically generating accurate answers to natural language questions posed by users, either by extracting answers from text passages (extractive QA) or generating free-form responses (generative QA). QA systems employ reading comprehension models, retrieval-augmented generation, and knowledge reasoning to power applications including search engines, virtual assistants, and customer support."
  },
  "backlinks": [
    "Transformers",
    "Large language models"
  ],
  "wiki_links": [],
  "ontology": {
    "term_id": "AI-0371",
    "preferred_term": "Question Answering",
    "definition": "Question Answering (QA) is the NLP task of automatically generating accurate answers to natural language questions posed by users, either by extracting answers from text passages (extractive QA) or generating free-form responses (generative QA). QA systems employ reading comprehension models, retrieval-augmented generation, and knowledge reasoning to power applications including search engines, virtual assistants, and customer support.",
    "source_domain": "ai",
    "maturity_level": null,
    "authority_score": null
  }
}