{
  "title": "Radiology AI",
  "content": "- ### OntologyBlock\n  id:: radiology-ai-ontology\n  collapsed:: true\n\t- ontology:: true\n\t- term-id:: AI-0339\n\t- preferred-term:: Radiology AI\n\t- source-domain:: ai\n\t- status:: draft\n    - public-access:: true\n\t- definition:: Radiology AI refers to artificial intelligence systems specifically designed for the interpretation and analysis of radiological imaging modalities including X-ray, computed tomography (CT), magnetic resonance imaging (MRI), and ultrasound. These systems automate detection, classification, and quantification tasks whilst integrating with PACS workflows and providing radiologist-level diagnostic performance validated through clinical trials.\n\n\n\n## Academic Context\n\n- Radiology AI represents one of the most significant advances in medical imaging since the introduction of digital radiography[1]\n  - Machine learning algorithms now detect subtle patterns in imaging data that might escape experienced radiologists, particularly in early-stage disease identification[1]\n  - The field has evolved from simple automation to sophisticated autonomous systems capable of independent operation and adaptive learning[3]\n  - Radiology's early embrace of technological innovation—from X-rays through MRI to contemporary AI systems—positions it as the vanguard of cognitive automation in healthcare[4]\n\n- Current state reflects maturation beyond proof-of-concept\n  - Hundreds of AI-enabled tools have received regulatory clearance for medical imaging tasks[2]\n  - Adoption by clinicians is growing, though unevenly distributed globally[2]\n  - The technology now assists across multiple dimensions: image interpretation, workflow triage, and preliminary report generation[2]\n\n## Current Landscape (2025)\n\n- Regulatory approvals and industry deployment\n  - By mid-2025, the FDA had approved 115 radiology AI algorithms, bringing the total to approximately 873 across all medical specialties, making medical imaging the single largest AI target[2]\n  - Leading vendors include GE Healthcare (96 cleared tools), Siemens Healthineers (80), Philips (42), Canon (35), United Imaging (32), and Aidoc (30), alongside numerous startups[2]\n  - Hundreds of AI-enabled tools now operate in production environments across hospitals and imaging centres[6]\n\n- Technical capabilities and clinical applications\n  - Workflow enhancement through automated triage of time-critical studies, prioritising cases such as suspected fractures, pneumothorax, or pleural effusion[6]\n  - Diagnostic precision via advanced pattern recognition across multiple imaging modalities: pulmonary nodule detection in chest CT, retinal abnormality identification in ophthalmologic imaging[1]\n  - Structured reporting automation, with systems such as RadGPT generating comprehensive reports from abdominal CT scans whilst contextualising findings against current medical literature[3]\n  - Administrative automation including intelligent study triage based on urgency, optimal imaging protocol recommendations, and collation of patient histories from disparate electronic health records[3]\n  - Quantifiable efficiency gains: radiologists report time savings of 60+ minutes per shift through automated impression generation[7]\n\n- Current limitations and adoption barriers\n  - Widespread adoption remains limited, often confined to specific use cases such as chest, neuro, and musculoskeletal imaging[4]\n  - Persistent concerns regarding transparency, explainability, and ethical deployment of AI systems[4]\n  - Unresolved questions about workload redistribution, liability frameworks, and reimbursement models[4]\n  - Psychological and cultural barriers, including concerns about job displacement and professional autonomy, continue to slow acceptance[4]\n\n- UK and North England context\n  - Information regarding specific North England implementations (Manchester, Leeds, Newcastle, Sheffield) is not currently available in contemporary literature\n  - UK healthcare systems, particularly NHS trusts, are integrating AI tools into radiology workflows, though adoption rates and regional variations remain underreported in peer-reviewed sources\n  - The NHS's digital transformation agenda creates opportunities for coordinated AI deployment, though centralised guidance on standards and procurement remains limited\n\n## Technical Foundations\n\n- Core technologies and methodologies\n  - Convolutional neural networks (CNNs) for image analysis and pattern recognition[2]\n  - Foundation models capable of linking images with text, representing first-generation multimodal systems[2]\n  - Personalised screening models, exemplified by MIT's Mirai for breast cancer risk stratification[2]\n  - Automated triage platforms such as Viz.ai for stroke detection[2]\n\n- Integration with existing infrastructure\n  - PACS (Picture Archiving and Communication Systems) workflow integration remains essential for clinical deployment[current definition]\n  - Structured reporting systems that populate findings automatically whilst maintaining radiologist oversight[3]\n  - Interoperability with electronic health records for comprehensive clinical contextualisation[3]\n\n## Research & Literature\n\n- Key academic sources and developments\n  - Langlotz, C.P. et al. (2024). \"The Future of Radiology: AI's Transformative Role in Medical Imaging.\" RSNA 2024 Plenary Session. Emphasis on human-machine collaboration and the principle that machine intelligence is different, not better than human intelligence[5]\n  - Recent literature (2025) emphasises AI agents in radiology toward autonomous and adaptive intelligence, with applications in administrative automation, image analysis, and structured reporting[3]\n  - PMC review (2025): \"Navigating the AI revolution: will radiology sink or soar?\" Comprehensive analysis of opportunities, barriers, and the necessity of radiologist oversight in maintaining clinical governance[4]\n\n- Ongoing research directions\n  - Development of transparent, explainable AI systems addressing current concerns about algorithmic opacity[5]\n  - Expansion of foundation models capable of multimodal analysis linking imaging with clinical text and patient data[2]\n  - Investigation of fair and representative AI model design through diverse interdisciplinary teams[5]\n  - Research into workload redistribution and professional identity preservation as AI assumes routine tasks[4]\n\n## Future Directions\n\n- Emerging trends and anticipated developments\n  - Autonomous AI agents capable of orchestrating complex clinical workflows whilst preserving final decision-making authority with radiologists[3]\n  - Increased personalisation of screening and diagnostic models tailored to individual patient risk profiles[2]\n  - Borderless collaboration enabled by global data networks and AI-powered platforms, allowing radiologists to focus on complex decision-making and patient interaction[4]\n  - Integration of AI education into medical training curricula to ensure incoming radiologists possess requisite competencies[4]\n\n- Anticipated challenges and research priorities\n  - Establishing robust frameworks for transparency and explainability, particularly for high-stakes diagnostic decisions[4][5]\n  - Resolving liability and reimbursement models that fairly compensate radiologists whilst incentivising AI adoption[4]\n  - Ensuring equitable access to AI tools across diverse healthcare settings, preventing widening of diagnostic capability gaps[5]\n  - Maintaining radiologist clinical oversight and professional autonomy as systems become increasingly autonomous—a matter of both governance and professional identity[4]\n  - Addressing data accessibility and diversity to ensure AI models perform equitably across populations and imaging protocols[5]\n\n## References\n\n[1] AMN Healthcare. (2025). \"AI in Radiology: What Clinicians Need to Know in 2025.\" Available at: https://www.amnhealthcare.com/blog/physician/perm/ai-in-radiology-what-clinicians-need-to-know-in-2025/\n\n[2] Intuition Labs. (2025). \"AI in Radiology: 2025 Trends, FDA Approvals & Adoption.\" Available at: https://intuitionlabs.ai/articles/ai-radiology-trends-2025\n\n[3] Directorate of Radiology. (2025). \"AI agents in radiology: toward autonomous and adaptive intelligence.\" *Diagnostic and Interventional Radiology*, 2025(253470). Available at: https://dirjournal.org/articles/ai-agents-in-radiology-toward-autonomous-and-adaptive-intelligence/dir.2025.253470\n\n[4] PMC/NIH. (2025). \"Navigating the AI revolution: will radiology sink or soar?\" *PMC National Center for Biotechnology Information*, PMC12479635. Available at: https://pmc.ncbi.nlm.nih.gov/articles/PMC12479635/\n\n[5] Langlotz, C.P. (2025). \"The Future of Radiology: AI's Transformative Role in Medical Imaging.\" *RSNA News*, January 2025. Available at: https://www.rsna.org/news/2025/january/role-of-ai-in-medical-imaging\n\n[6] AZmed. (2025). \"Clinically proven benefits of AI in radiology in 2025.\" Available at: https://www.azmed.co/news-post/what-are-the-benefits-of-ai-in-radiology-5-clinically-proven-benefits-in-2025\n\n[7] Rad AI. (2025). \"Save Time and Decrease Burnout with Radiology AI Software.\" Available at: https://www.radai.com\n\n[8] Rayscape. (2025). \"Radiology AI in 2025: A Revolution in Diagnostic Imaging.\" Available at: https://rayscape.ai/single-article?id=Y9jsgRIAACEAgG2-\n\n\n## Metadata\n\n- **Last Updated**: 2025-11-11\n- **Review Status**: Comprehensive editorial review\n- **Verification**: Academic sources verified\n- **Regional Context**: UK/North England where applicable",
  "properties": {
    "id": "radiology-ai-ontology",
    "collapsed": "true",
    "- ontology": "true",
    "- term-id": "AI-0339",
    "- preferred-term": "Radiology AI",
    "- source-domain": "ai",
    "- status": "draft",
    "- public-access": "true",
    "- definition": "Radiology AI refers to artificial intelligence systems specifically designed for the interpretation and analysis of radiological imaging modalities including X-ray, computed tomography (CT), magnetic resonance imaging (MRI), and ultrasound. These systems automate detection, classification, and quantification tasks whilst integrating with PACS workflows and providing radiologist-level diagnostic performance validated through clinical trials."
  },
  "backlinks": [],
  "wiki_links": [],
  "ontology": {
    "term_id": "AI-0339",
    "preferred_term": "Radiology AI",
    "definition": "Radiology AI refers to artificial intelligence systems specifically designed for the interpretation and analysis of radiological imaging modalities including X-ray, computed tomography (CT), magnetic resonance imaging (MRI), and ultrasound. These systems automate detection, classification, and quantification tasks whilst integrating with PACS workflows and providing radiologist-level diagnostic performance validated through clinical trials.",
    "source_domain": "ai",
    "maturity_level": null,
    "authority_score": null
  }
}