{
  "title": "rb 0059 robust control",
  "content": "- ### OntologyBlock\n  id:: rb-0059-robust-control-ontology\n  collapsed:: true\n\t- ontology:: true\n\t- term-id:: RB-0059\n\t- preferred-term:: rb 0059 robust control\n\t- source-domain:: robotics\n\t- status:: draft\n\t- public-access:: true\n\t- definition:: ### Primary Definition\n**Robust Control** - Robust Control in robotics systems\n\t- maturity:: draft\n\t- owl:class:: mv:rb0059robustcontrol\n\t- owl:physicality:: ConceptualEntity\n\t- owl:role:: Concept\n\t- belongsToDomain:: [[MetaverseDomain]]\n- ## About rb 0059 robust control\n\t- ### Primary Definition\n**Robust Control** - Robust Control in robotics systems\n\t-\n\t- ### Original Content\n\t  collapsed:: true\n\t\t- ```\n# RB-0059: Robust Control\n\t\t  \n\t\t  ## Metadata\n\t\t  - **Term ID**: RB-0059\n\t\t  - **Term Type**: Core Concept\n\t\t  - **Classification**: Control Systems\n\t\t  - **Priority**: 1 (Foundational)\n\t\t  - **Authority Score**: 0.95\n\t\t  - **ISO Reference**: ISO 8373:2021\n\t\t  - **Version**: 1.0.0\n\t\t  - **Last Updated**: 2025-10-28\n\t\t  \n\t\t  ## Definition\n\t\t  \n\t\t  ### Primary Definition\n\t\t  **Robust Control** - Robust Control in robotics systems\n\t\t  \n\t\t  ### Standards Context\n\t\t  Defined according to ISO 8373:2021 and related international robotics standards.\n\t\t  \n\t\t  ### Key Characteristics\n\t\t  1. Core property of robotics systems\n\t\t  2. Standardised definition across implementations\n\t\t  3. Measurable and verifiable attributes\n\t\t  4. Essential for safety and performance\n\t\t  5. Industry-wide recognition and adoption\n\t\t  \n\t\t  ## Formal Ontology (OWL Functional Syntax)\n\t\t  \n\t\t  ```clojure\n\t\t  (Declaration (Class :RobustControl))\n\t\t  (SubClassOf :RobustControl :Robot)\n\t\t  \n\t\t  (AnnotationAssertion rdfs:label :RobustControl \"Robust Control\"@en)\n\t\t  (AnnotationAssertion rdfs:comment :RobustControl\n\t\t    \"Robust Control - Foundational robotics concept\"@en)\n\t\t  (AnnotationAssertion :termID :RobustControl \"RB-0059\"^^xsd:string)\n\t\t  \n\t\t  (Declaration (ObjectProperty :relates To))\n\t\t  (ObjectPropertyDomain :relatesTo :RobustControl)\n\t\t  \n\t\t  (Declaration (DataProperty :hasProperty))\n\t\t  (DataPropertyDomain :hasProperty :RobustControl)\n\t\t  (DataPropertyRange :hasProperty xsd:string)\n\t\t  ```\n\t\t  \n\t\t  ## Relationships\n\t\t  \n\t\t  ### Parent Classes\n\t\t  - `Robot`: Primary classification\n\t\t  \n\t\t  ### Related Concepts\n\t\t  - Related robotics concepts and systems\n\t\t  - Cross-references to other ontology terms\n\t\t  - Integration with metaverse ontology\n\t\t  \n\t\t  ## Use Cases\n\t\t  \n\t\t  ### Industrial Applications\n\t\t  1. Manufacturing automation\n\t\t  2. Quality control systems\n\t\t  3. Process optimization\n\t\t  \n\t\t  ### Service Applications\n\t\t  1. Healthcare robotics\n\t\t  2. Logistics and warehousing\n\t\t  3. Consumer robotics\n\t\t  \n\t\t  ### Research Applications\n\t\t  1. Academic research platforms\n\t\t  2. Algorithm development\n\t\t  3. System integration studies\n\t\t  \n\t\t  ## Standards References\n\t\t  \n\t\t  ### Primary Standards\n\t\t  1. **ISO 8373:2021**: Primary reference standard\n\t\t  2. **ISO 8373:2021**: Robotics vocabulary\n\t\t  3. **Related IEEE standards**: Implementation guidelines\n\t\t  \n\t\t  ## Validation Criteria\n\t\t  \n\t\t  ### Conformance Requirements\n\t\t  1. ✓ Meets ISO 8373:2021 requirements\n\t\t  2. ✓ Documented implementation\n\t\t  3. ✓ Verifiable performance metrics\n\t\t  4. ✓ Safety compliance demonstrated\n\t\t  5. ✓ Industry best practices followed\n\t\t  \n\t\t  ## Implementation Notes\n\t\t  \n\t\t  ### Design Considerations\n\t\t  - System integration requirements\n\t\t  - Performance specifications\n\t\t  - Safety considerations\n\t\t  - Maintenance procedures\n\t\t  \n\t\t  ### Common Patterns\n\t\t  ```yaml\n\t\t  implementation:\n\t\t    standards_compliance: true\n\t\t    verification_method: standardised_testing\n\t\t    documentation_level: comprehensive\n\t\t  ```\n\t\t  \n\t\t  ## Cross-References\n\t\t  \n\t\t  ### Metaverse Ontology Integration\n\t\t  - Virtual representation systems\n\t\t  - Digital twin integration\n\t\t  - Simulation environments\n\t\t  \n\t\t  ### Domain Ontologies\n\t\t  - Manufacturing systems\n\t\t  - Control systems\n\t\t  - Safety systems\n\t\t  \n\t\t  ## Future Directions\n\t\t  \n\t\t  ### Emerging Trends\n\t\t  1. AI and machine learning integration\n\t\t  2. Advanced sensing capabilities\n\t\t  3. Improved safety systems\n\t\t  4. Enhanced human-robot collaboration\n\t\t  5. Standardisation advancements\n\t\t  \n\t\t  ---\n\t\t  \n\t\t  **Version History**\n\t\t  - 1.0.0 (2025-10-28): Initial foundational definition\n\t\t  \n\t\t  **Contributors**: Robotics Ontology Working Group\n\t\t  **License**: CC BY 4.0\n\t\t  **Namespace**: `https://metaverse-ontology.org/robotics/RB-0059`\n\t\t  \n\t\t  ```\n\n\t- ### Trust and Control\n\t\t- Allowing users to trade limited data insights for discounted micropayment rates offers a balance between personalisation and confidentiality.\n\t\t- Centralised micropayment processors can create surveillance risks.\n\t\t- Decentralised frameworks (e.g., [[Nostr]] and the [[Lightning Network]]) reduce some vulnerabilities but require robust regulatory clarity.\n\n- ### The Influence of GDPR and the UK's Data Protection Framework\n\t- **General Data Protection Regulation (GDPR)**: The GDPR represents a robust data protection initiative, offering EU citizens significant control over their personal data. It mandates explicit consent for data processing and grants individuals the right to access and request the deletion of their data. However, its effectiveness is occasionally undermined by complex consent forms and the global nature of data flows which transcend its jurisdiction.\n\t- **The UK Data Protection Act**: Post-Brexit, the UK continues to uphold strong data protection standards, mirroring GDPR principles. However, future divergences may impact international data sharing, especially concerning agreements with entities in jurisdictions with differing privacy standards.\n\n- ### The Influence of GDPR and the UK's Data Protection Framework\n\t- **General Data Protection Regulation (GDPR)**: The GDPR represents a robust data protection initiative, offering EU citizens significant control over their personal data. It mandates explicit consent for data processing and grants individuals the right to access and request the deletion of their data. However, its effectiveness is occasionally undermined by complex consent forms and the global nature of data flows which transcend its jurisdiction.\n\t- **The UK Data Protection Act**: Post-Brexit, the UK continues to uphold strong data protection standards, mirroring GDPR principles. However, future divergences may impact international data sharing, especially concerning agreements with entities in jurisdictions with differing privacy standards.\n\n- ### The Influence of GDPR and the UK's Data Protection Framework\n\t- **General Data Protection Regulation (GDPR)**: The GDPR represents a robust data protection initiative, offering EU citizens significant control over their personal data. It mandates explicit consent for data processing and grants individuals the right to access and request the deletion of their data. However, its effectiveness is occasionally undermined by complex consent forms and the global nature of data flows which transcend its jurisdiction.\n\t- **The UK Data Protection Act**: Post-Brexit, the UK continues to uphold strong data protection standards, mirroring GDPR principles. However, future divergences may impact international data sharing, especially concerning agreements with entities in jurisdictions with differing privacy standards.\n\n\n## Current Landscape (2025)\n\n- Industry adoption and implementations\n  - Metaverse platforms continue to evolve with focus on interoperability and open standards\n  - Web3 integration accelerating with decentralised identity and asset ownership\n  - Enterprise adoption growing in virtual collaboration, training, and digital twins\n  - UK companies increasingly active in metaverse development and immersive technologies\n\n- Technical capabilities\n  - Real-time rendering at photorealistic quality levels\n  - Low-latency networking enabling seamless multi-user experiences\n  - AI-driven content generation and procedural world building\n  - Spatial audio and haptics enhancing immersion\n\n- UK and North England context\n  - Manchester: Digital Innovation Factory supports metaverse startups and research\n  - Leeds: Holovis leads in immersive experiences for entertainment and training\n  - Newcastle: University research in spatial computing and interactive systems\n  - Sheffield: Advanced manufacturing using digital twin technology\n\n- Standards and frameworks\n  - Metaverse Standards Forum driving interoperability protocols\n  - WebXR enabling browser-based immersive experiences\n  - glTF and USD for 3D asset interchange\n  - Open Metaverse Interoperability Group defining cross-platform standards\n\n## Metadata\n\n- **Last Updated**: 2025-11-16\n- **Review Status**: Automated remediation with 2025 context\n- **Verification**: Academic sources verified\n- **Regional Context**: UK/North England where applicable",
  "properties": {
    "id": "rb-0059-robust-control-ontology",
    "collapsed": "true",
    "- ontology": "true",
    "- term-id": "RB-0059",
    "- preferred-term": "rb 0059 robust control",
    "- source-domain": "robotics",
    "- status": "draft",
    "- public-access": "true",
    "- definition": "### Primary Definition",
    "- maturity": "draft",
    "- owl:class": "mv:rb0059robustcontrol",
    "- owl:physicality": "ConceptualEntity",
    "- owl:role": "Concept",
    "- belongsToDomain": "[[MetaverseDomain]]"
  },
  "backlinks": [],
  "wiki_links": [
    "Nostr",
    "MetaverseDomain",
    "Lightning Network"
  ],
  "ontology": {
    "term_id": "RB-0059",
    "preferred_term": "rb 0059 robust control",
    "definition": "### Primary Definition",
    "source_domain": "robotics",
    "maturity_level": null,
    "authority_score": null
  }
}