{
  "title": "rb 0048 pid controller",
  "content": "- ### OntologyBlock\n  id:: rb-0048-pid-controller-ontology\n  collapsed:: true\n\t- ontology:: true\n\t- term-id:: RB-0048\n\t- preferred-term:: rb 0048 pid controller\n\t- source-domain:: robotics\n\t- status:: draft\n\t- public-access:: true\n\t- definition:: ### Primary Definition\n**PID Controller** - PID Controller in robotics systems\n\t- maturity:: draft\n\t- owl:class:: mv:rb0048pidcontroller\n\t- owl:physicality:: ConceptualEntity\n\t- owl:role:: Concept\n\t- belongsToDomain:: [[MetaverseDomain]]\n- ## About rb 0048 pid controller\n\t- ### Primary Definition\n**PID Controller** - PID Controller in robotics systems\n\t-\n\t- ### Original Content\n\t  collapsed:: true\n\t\t- ```\n# RB-0048: PID Controller\n\t\t  \n\t\t  ## Metadata\n\t\t  - **Term ID**: RB-0048\n\t\t  - **Term Type**: Core Concept\n\t\t  - **Classification**: Control Systems\n\t\t  - **Priority**: 1 (Foundational)\n\t\t  - **Authority Score**: 0.95\n\t\t  - **ISO Reference**: ISO 8373:2021\n\t\t  - **Version**: 1.0.0\n\t\t  - **Last Updated**: 2025-10-28\n\t\t  \n\t\t  ## Definition\n\t\t  \n\t\t  ### Primary Definition\n\t\t  **PID Controller** - PID Controller in robotics systems\n\t\t  \n\t\t  ### Standards Context\n\t\t  Defined according to ISO 8373:2021 and related international robotics standards.\n\t\t  \n\t\t  ### Key Characteristics\n\t\t  1. Core property of robotics systems\n\t\t  2. Standardised definition across implementations\n\t\t  3. Measurable and verifiable attributes\n\t\t  4. Essential for safety and performance\n\t\t  5. Industry-wide recognition and adoption\n\t\t  \n\t\t  ## Formal Ontology (OWL Functional Syntax)\n\t\t  \n\t\t  ```clojure\n\t\t  (Declaration (Class :PIDController))\n\t\t  (SubClassOf :PIDController :Robot)\n\t\t  \n\t\t  (AnnotationAssertion rdfs:label :PIDController \"PID Controller\"@en)\n\t\t  (AnnotationAssertion rdfs:comment :PIDController\n\t\t    \"PID Controller - Foundational robotics concept\"@en)\n\t\t  (AnnotationAssertion :termID :PIDController \"RB-0048\"^^xsd:string)\n\t\t  \n\t\t  (Declaration (ObjectProperty :relates To))\n\t\t  (ObjectPropertyDomain :relatesTo :PIDController)\n\t\t  \n\t\t  (Declaration (DataProperty :hasProperty))\n\t\t  (DataPropertyDomain :hasProperty :PIDController)\n\t\t  (DataPropertyRange :hasProperty xsd:string)\n\t\t  ```\n\t\t  \n\t\t  ## Relationships\n\t\t  \n\t\t  ### Parent Classes\n\t\t  - `Robot`: Primary classification\n\t\t  \n\t\t  ### Related Concepts\n\t\t  - Related robotics concepts and systems\n\t\t  - Cross-references to other ontology terms\n\t\t  - Integration with metaverse ontology\n\t\t  \n\t\t  ## Use Cases\n\t\t  \n\t\t  ### Industrial Applications\n\t\t  1. Manufacturing automation\n\t\t  2. Quality control systems\n\t\t  3. Process optimization\n\t\t  \n\t\t  ### Service Applications\n\t\t  1. Healthcare robotics\n\t\t  2. Logistics and warehousing\n\t\t  3. Consumer robotics\n\t\t  \n\t\t  ### Research Applications\n\t\t  1. Academic research platforms\n\t\t  2. Algorithm development\n\t\t  3. System integration studies\n\t\t  \n\t\t  ## Standards References\n\t\t  \n\t\t  ### Primary Standards\n\t\t  1. **ISO 8373:2021**: Primary reference standard\n\t\t  2. **ISO 8373:2021**: Robotics vocabulary\n\t\t  3. **Related IEEE standards**: Implementation guidelines\n\t\t  \n\t\t  ## Validation Criteria\n\t\t  \n\t\t  ### Conformance Requirements\n\t\t  1. ✓ Meets ISO 8373:2021 requirements\n\t\t  2. ✓ Documented implementation\n\t\t  3. ✓ Verifiable performance metrics\n\t\t  4. ✓ Safety compliance demonstrated\n\t\t  5. ✓ Industry best practices followed\n\t\t  \n\t\t  ## Implementation Notes\n\t\t  \n\t\t  ### Design Considerations\n\t\t  - System integration requirements\n\t\t  - Performance specifications\n\t\t  - Safety considerations\n\t\t  - Maintenance procedures\n\t\t  \n\t\t  ### Common Patterns\n\t\t  ```yaml\n\t\t  implementation:\n\t\t    standards_compliance: true\n\t\t    verification_method: standardised_testing\n\t\t    documentation_level: comprehensive\n\t\t  ```\n\t\t  \n\t\t  ## Cross-References\n\t\t  \n\t\t  ### Metaverse Ontology Integration\n\t\t  - Virtual representation systems\n\t\t  - Digital twin integration\n\t\t  - Simulation environments\n\t\t  \n\t\t  ### Domain Ontologies\n\t\t  - Manufacturing systems\n\t\t  - Control systems\n\t\t  - Safety systems\n\t\t  \n\t\t  ## Future Directions\n\t\t  \n\t\t  ### Emerging Trends\n\t\t  1. AI and machine learning integration\n\t\t  2. Advanced sensing capabilities\n\t\t  3. Improved safety systems\n\t\t  4. Enhanced human-robot collaboration\n\t\t  5. Standardisation advancements\n\t\t  \n\t\t  ---\n\t\t  \n\t\t  **Version History**\n\t\t  - 1.0.0 (2025-10-28): Initial foundational definition\n\t\t  \n\t\t  **Contributors**: Robotics Ontology Working Group\n\t\t  **License**: CC BY 4.0\n\t\t  **Namespace**: `https://metaverse-ontology.org/robotics/RB-0048`\n\t\t  \n\t\t  ```\n\n\t- ## EMG Wristbands\n\t\t- Meta's EMG wristbands use electromyography to interpret electrical signals from the brain that control hand movements[1](https://blogs.expandreality.io/meta-are-enhancing-vr-experiences-with-neural-wristbands). This technology allows for seamless and precise interactions with digital objects in virtual and augmented reality environments without the need for external cameras or sensors[1](https://blogs.expandreality.io/meta-are-enhancing-vr-experiences-with-neural-wristbands).The wristbands contain embedded sensors that capture subtle electrical signals transmitted from the brain to the hands. These signals are then translated into precise commands, enabling real-time interaction with virtual environments[1](https://blogs.expandreality.io/meta-are-enhancing-vr-experiences-with-neural-wristbands).\n\t\t\t\t- Finger taps (index and middle finger\n\t\t\t\t- D-pad-like gestures\n\t\t\t\t- Simple hand movements[2](https://mixed-news.com/en/bosworth-on-emg-wristband-as-quest-controller/)\n\t\t\t- While these inputs are currently limited, Meta's CTO Andrew Bosworth suggests that the technology could evolve to become an increasingly universal interface over time[2](https://mixed-news.com/en/bosworth-on-emg-wristband-as-quest-controller/).\n\n\t\t- #### Hardware\n\t\t\t- Camera: 12 MP ultra-wide camera for photos and 1080p video recording\n\t\t\t- Available in Wayfarer and new Headliner styles\n\t\t\t- Multiple color options, including transparent frames\n\t\t\t- Prescription-lens compatible\n\t\t\t\t- Simple hand movements[2](https://mixed-news.com/en/bosworth-on-emg-wristband-as-quest-controller/)\n\t\t\t- While these inputs are currently limited, Meta's CTO Andrew Bosworth suggests that the technology could evolve to become an increasingly universal interface over time[2](https://mixed-news.com/en/bosworth-on-emg-wristband-as-quest-controller/).\n\n- ##### Accessibility\n-\n\t- Mouse and keyboard\n-\n\t- Games controller\n-\n\t- Body tracking\n-\n\t- Hand tracking and gesture\n-\n\t- Voice\n-\n\t- Microgestures\n-\n\t- Eye gaze\n-\n\t- Assumption systems\n-\n\t- [Playstation programmable controller](https://blog.playstation.com/2023/01/04/introducing-project-leonardo-for-playstation-5-a-highly-customizable-accessibility-controller-kit/)\n-\n\t- [XBOX accessibility controller](https://www.xbox.com/en-GB/accessories/controllers/xbox-adaptive-controller)\n\n- #### Controllers, gestures, interfaces\n\n- ##### Accessibility\n-\n\t- Mouse and keyboard\n-\n\t- Games controller\n-\n\t- Body tracking\n-\n\t- Hand tracking and gesture\n-\n\t- Voice\n-\n\t- Microgestures\n-\n\t- Eye gaze\n-\n\t- Assumption systems\n-\n\t- [Playstation programmable controller](https://blog.playstation.com/2023/01/04/introducing-project-leonardo-for-playstation-5-a-highly-customizable-accessibility-controller-kit/)\n-\n\t- [XBOX accessibility controller](https://www.xbox.com/en-GB/accessories/controllers/xbox-adaptive-controller)\n\n- #### Controllers, gestures, interfaces\n\n\n## Current Landscape (2025)\n\n- Industry adoption and implementations\n  - Metaverse platforms continue to evolve with focus on interoperability and open standards\n  - Web3 integration accelerating with decentralised identity and asset ownership\n  - Enterprise adoption growing in virtual collaboration, training, and digital twins\n  - UK companies increasingly active in metaverse development and immersive technologies\n\n- Technical capabilities\n  - Real-time rendering at photorealistic quality levels\n  - Low-latency networking enabling seamless multi-user experiences\n  - AI-driven content generation and procedural world building\n  - Spatial audio and haptics enhancing immersion\n\n- UK and North England context\n  - Manchester: Digital Innovation Factory supports metaverse startups and research\n  - Leeds: Holovis leads in immersive experiences for entertainment and training\n  - Newcastle: University research in spatial computing and interactive systems\n  - Sheffield: Advanced manufacturing using digital twin technology\n\n- Standards and frameworks\n  - Metaverse Standards Forum driving interoperability protocols\n  - WebXR enabling browser-based immersive experiences\n  - glTF and USD for 3D asset interchange\n  - Open Metaverse Interoperability Group defining cross-platform standards\n\n## Metadata\n\n- **Last Updated**: 2025-11-16\n- **Review Status**: Automated remediation with 2025 context\n- **Verification**: Academic sources verified\n- **Regional Context**: UK/North England where applicable",
  "properties": {
    "id": "rb-0048-pid-controller-ontology",
    "collapsed": "true",
    "- ontology": "true",
    "- term-id": "RB-0048",
    "- preferred-term": "rb 0048 pid controller",
    "- source-domain": "robotics",
    "- status": "draft",
    "- public-access": "true",
    "- definition": "### Primary Definition",
    "- maturity": "draft",
    "- owl:class": "mv:rb0048pidcontroller",
    "- owl:physicality": "ConceptualEntity",
    "- owl:role": "Concept",
    "- belongsToDomain": "[[MetaverseDomain]]"
  },
  "backlinks": [],
  "wiki_links": [
    "MetaverseDomain"
  ],
  "ontology": {
    "term_id": "RB-0048",
    "preferred_term": "rb 0048 pid controller",
    "definition": "### Primary Definition",
    "source_domain": "robotics",
    "maturity_level": null,
    "authority_score": null
  }
}