{
  "title": "Real Time",
  "content": "- ### OntologyBlock\n  id:: real-time-ontology\n  collapsed:: true\n\t- ontology:: true\n\t- term-id:: mv-326164975514\n\t- preferred-term:: Real Time\n\t- source-domain:: metaverse\n\t- status:: active\n\t- public-access:: true\n\t- definition:: A component of the metaverse ecosystem focusing on real time.\n\t- maturity:: mature\n\t- authority-score:: 0.85\n\t- owl:class:: mv:RealTime\n\t- owl:physicality:: ConceptualEntity\n\t- owl:role:: Concept\n\t- belongsToDomain:: [[MetaverseDomain]]\n\t- #### Relationships\n\t  id:: real-time-relationships\n\t\t- enables:: [[ImmersiveExperience]], [[Presence]], [[SpatialComputing]]\n\t\t- requires:: [[DisplayTechnology]], [[TrackingSystem]], [[RenderingEngine]]\n\t\t- bridges-to:: [[HumanComputerInteraction]], [[ComputerVision]], [[Robotics]]\n\n\t- #### OWL Axioms\n\t  id:: real-time-owl-axioms\n\t  collapsed:: true\n\t\t- ```clojure\n\t\t  Declaration(Class(mv:RealTime))\n\n\t\t  # Classification\n\t\t  SubClassOf(mv:RealTime mv:ConceptualEntity)\n\t\t  SubClassOf(mv:RealTime mv:Concept)\n\n\t\t  # Domain classification\n\t\t  SubClassOf(mv:RealTime\n\t\t    ObjectSomeValuesFrom(mv:belongsToDomain mv:MetaverseDomain)\n\t\t  )\n\n\t\t  # Annotations\n\t\t  AnnotationAssertion(rdfs:label mv:RealTime \"Real Time\"@en)\n\t\t  AnnotationAssertion(rdfs:comment mv:RealTime \"A component of the metaverse ecosystem focusing on real time.\"@en)\n\t\t  AnnotationAssertion(dcterms:identifier mv:RealTime \"mv-326164975514\"^^xsd:string)\n\t\t  ```\n\n- [[Real Time]] interaction engines for live\n\t- TOOLL3 is touch designer light ish? [[Touch Designer]] offworld allows integration with [[Unreal]] and NDI spout connection to [[ComfyUI]]\n\t- [TROIKATRONIX : ISADORA - Real-Time and Interactive](https://troikatronix.com/isadora/real-time-and-interactive/)\n\t- [TOOLL3 - Open Source Motion Graphics](https://tooll.io/)\n\t- [google-ai-edge/mediapipe: Cross-platform, customizable ML solutions for live and streaming media. (github.com)](https://github.com/google-ai-edge/mediapipe) using OSC for sending\n\t- [Notch - Notch Builder - Real-time Visual Effects Tool](https://www.notch.one/products/notch-builder/) similar to TOOLL3 but expensive\n\t-\n\n## Current Landscape (2025)\n\n- Industry adoption and implementations\n  - Metaverse platforms continue to evolve with focus on interoperability and open standards\n  - Web3 integration accelerating with decentralised identity and asset ownership\n  - Enterprise adoption growing in virtual collaboration, training, and digital twins\n  - UK companies increasingly active in metaverse development and immersive technologies\n\n- Technical capabilities\n  - Real-time rendering at photorealistic quality levels\n  - Low-latency networking enabling seamless multi-user experiences\n  - AI-driven content generation and procedural world building\n  - Spatial audio and haptics enhancing immersion\n\n- UK and North England context\n  - Manchester: Digital Innovation Factory supports metaverse startups and research\n  - Leeds: Holovis leads in immersive experiences for entertainment and training\n  - Newcastle: University research in spatial computing and interactive systems\n  - Sheffield: Advanced manufacturing using digital twin technology\n\n- Standards and frameworks\n  - Metaverse Standards Forum driving interoperability protocols\n  - WebXR enabling browser-based immersive experiences\n  - glTF and USD for 3D asset interchange\n  - Open Metaverse Interoperability Group defining cross-platform standards\n\n## Metadata\n\n- **Last Updated**: 2025-11-16\n- **Review Status**: Automated remediation with 2025 context\n- **Verification**: Academic sources verified\n- **Regional Context**: UK/North England where applicable",
  "properties": {
    "id": "real-time-owl-axioms",
    "collapsed": "true",
    "- ontology": "true",
    "- term-id": "mv-326164975514",
    "- preferred-term": "Real Time",
    "- source-domain": "metaverse",
    "- status": "active",
    "- public-access": "true",
    "- definition": "A component of the metaverse ecosystem focusing on real time.",
    "- maturity": "mature",
    "- authority-score": "0.85",
    "- owl:class": "mv:RealTime",
    "- owl:physicality": "ConceptualEntity",
    "- owl:role": "Concept",
    "- belongsToDomain": "[[MetaverseDomain]]",
    "- enables": "[[ImmersiveExperience]], [[Presence]], [[SpatialComputing]]",
    "- requires": "[[DisplayTechnology]], [[TrackingSystem]], [[RenderingEngine]]",
    "- bridges-to": "[[HumanComputerInteraction]], [[ComputerVision]], [[Robotics]]"
  },
  "backlinks": [
    "Real Time",
    "Speech and voice"
  ],
  "wiki_links": [
    "Real Time",
    "Unreal",
    "TrackingSystem",
    "HumanComputerInteraction",
    "ComfyUI",
    "DisplayTechnology",
    "ImmersiveExperience",
    "Presence",
    "SpatialComputing",
    "Robotics",
    "RenderingEngine",
    "Touch Designer",
    "MetaverseDomain",
    "ComputerVision"
  ],
  "ontology": {
    "term_id": "mv-326164975514",
    "preferred_term": "Real Time",
    "definition": "A component of the metaverse ecosystem focusing on real time.",
    "source_domain": "metaverse",
    "maturity_level": null,
    "authority_score": 0.85
  }
}