{
  "title": "Reliability",
  "content": "- ### OntologyBlock\n  id:: reliability-ontology\n  collapsed:: true\n\t- ontology:: true\n\t- term-id:: AI-0069\n\t- preferred-term:: Reliability\n\t- source-domain:: ai\n\t- status:: draft\n    - public-access:: true\n\t- definition:: The degree to which an AI system performs its intended function consistently and accurately over time and across repeated operations, producing predictable and dependable results under specified conditions.\n\n\n\n# Reliability.md - Updated Ontology Entry\n\n## Academic Context\n\n- Foundational definition and evolution\n  - AI reliability encompasses consistent, correct performance from systems over time and across different conditions\n  - Extends beyond simple accuracy to include robustness, predictability and dependability under specified operational parameters\n  - Integral component of the broader trustworthy AI framework alongside explainability, fairness, security and safety[1][2]\n  - Reliability functions as prerequisite for system accountability and user confidence in AI-driven decision-making\n\n- Key developments and current state\n  - Recognition that reliable AI begins with reliable data—a somewhat obvious but frequently overlooked principle[3]\n  - Shift from isolated model evaluation toward continuous monitoring and observability in production environments\n  - Growing emphasis on model drift detection and performance degradation across real-world deployment scenarios\n\n## Current Landscape (2025)\n\n- Industry adoption and implementations\n  - Widespread integration across professional services, financial analysis and legal technology sectors\n  - Thomson Reuters Institute data indicates 80% of professionals anticipate AI will have high or transformational influence within five years[4]\n  - Enterprise adoption increasingly demands transparent, auditable AI outputs—particularly critical as agentic AI systems perform multi-step processes autonomously[4]\n  - Smaller, more efficient models now achieving performance thresholds previously requiring vastly larger architectures (Microsoft's Phi-3-mini with 3.8 billion parameters matches performance that required 540 billion parameters in 2022)[6]\n\n- Technical capabilities and limitations\n  - Complex reasoning remains problematic; even advanced systems struggle reliably with arithmetic, planning and logical problems beyond training distribution[6]\n  - AI agents demonstrate early promise in short time-horizon tasks (outperforming human experts four-fold in two-hour scenarios) but performance degrades significantly with extended timeframes[6]\n  - Adversarial robustness and unexpected input handling remain active challenges in production environments\n\n- Standards and frameworks\n  - NIST AI Risk Management Framework provides benchmark for assessing AI system risks and trustworthiness metrics[1]\n  - Emerging evaluation benchmarks including HELM Safety, AIR-Bench and FACTS offer standardised assessment tools[6]\n  - Gap persists between industry recognition of responsible AI risks and meaningful implementation of mitigation strategies[6]\n\n## Research & Literature\n\n- Key academic and institutional sources\n  - IBM (2024). \"What is Trustworthy AI?\" *IBM Think*. Defines reliability as ability to function as intended without failure under specified conditions; emphasises secure, robust systems with protection mechanisms against adversarial attacks[1]\n  - Maxim AI (2024). \"AI Reliability: How to Build Trustworthy AI Systems.\" Outlines core principles including accountability, explainability, fairness, interpretability, privacy, security and robustness[2]\n  - Monte Carlo Data (2024). \"The AI Reliability Guide: How To Build Reliable AI Models.\" Emphasises data quality, diversity and continuous updates as foundational to reliability; advocates thorough data cleaning and validation pipelines[3]\n  - Thomson Reuters Institute (2024). \"Accurate and Reliable AI: Five Key Ingredients.\" Identifies high-quality data, domain expertise, security, ethics and human-in-the-loop approaches as essential components[4]\n  - Lark (2025). \"AI Reliability.\" Defines reliability as consistent delivery of expected outcomes regardless of operational conditions; emphasises role in business operations and competitive advantage[5]\n  - Stanford HAI (2025). \"Artificial Intelligence Index Report 2025.\" Comprehensive analysis of AI landscape including performance metrics, reasoning limitations and responsible AI ecosystem development[6]\n\n- Ongoing research directions\n  - Development of more robust evaluation methodologies for complex reasoning tasks\n  - Investigation of model drift detection and mitigation in long-running production systems\n  - Standardisation of responsible AI evaluation practices across industrial model developers\n  - Enhancement of agentic AI reliability and transparency mechanisms\n\n## UK Context\n\n- British contributions and implementations\n  - NIST framework adoption increasingly referenced in UK regulatory discussions, though UK-specific governance frameworks remain under development\n  - Financial services sector (particularly London-based institutions) leading adoption of reliable AI systems for risk assessment and compliance\n  - Growing emphasis on AI reliability within NHS digital transformation initiatives, though implementation remains inconsistent across trusts\n\n- North England innovation and adoption\n  - Manchester and Leeds emerging as regional technology hubs with increasing AI implementation in professional services and manufacturing sectors\n  - Sheffield's advanced manufacturing cluster exploring AI reliability in industrial automation and predictive maintenance applications\n  - Newcastle's digital economy initiatives incorporating AI reliability standards in emerging fintech and data analytics companies\n  - Regional universities (Manchester, Leeds, Sheffield) conducting research into trustworthy AI systems, though specific reliability-focused publications remain limited\n\n- Regulatory landscape\n  - UK approach to AI governance emphasises principles-based regulation rather than prescriptive standards\n  - Financial Conduct Authority increasingly requiring demonstrable AI reliability in algorithmic decision-making systems\n  - Data protection considerations under UK GDPR influencing reliability requirements, particularly regarding model transparency and auditability\n\n## Future Directions\n\n- Emerging trends and developments\n  - Shift toward smaller, more efficient models maintaining reliability whilst reducing computational overhead and environmental impact\n  - Integration of continuous monitoring and observability platforms as standard practice rather than optional enhancement\n  - Growing demand for explainability mechanisms that enable stakeholders to audit and verify AI reliability claims\n  - Expansion of agentic AI systems requiring substantially more rigorous reliability frameworks than current generation models\n\n- Anticipated challenges\n  - Balancing model complexity with interpretability—larger models often perform better but become increasingly difficult to audit for reliability\n  - Addressing model drift in rapidly evolving domains where training data quickly becomes unrepresentative\n  - Establishing standardised evaluation methodologies across diverse AI applications and industries\n  - Managing stakeholder expectations regarding AI reliability limitations, particularly in high-stakes applications\n\n- Research priorities\n  - Development of robust evaluation frameworks for complex reasoning and planning tasks\n  - Investigation of data governance practices that maintain reliability across extended deployment periods\n  - Standardisation of responsible AI evaluation practices to reduce current implementation gaps\n  - Enhancement of transparency mechanisms for agentic AI systems operating with minimal human oversight\n\n## References\n\n[1] IBM (2024). \"What is Trustworthy AI?\" *IBM Think*. Available at: https://www.ibm.com/think/topics/trustworthy-ai\n\n[2] Maxim AI (2024). \"AI Reliability: How to Build Trustworthy AI Systems.\" Available at: https://www.getmaxim.ai/articles/ai-reliability-how-to-build-trustworthy-ai-systems/\n\n[3] Monte Carlo Data (2024). \"The AI Reliability Guide: How To Build Reliable AI Models That Don't Fail.\" Available at: https://www.montecarlodata.com/blog-ai-reliability/\n\n[4] Thomson Reuters Institute (2024). \"Accurate and Reliable AI: Five Key Ingredients.\" *Thomson Reuters Legal Blog*. Available at: https://legal.thomsonreuters.com/blog/key-ingredients-to-accurate-and-reliable-ai/\n\n[5] Lark (2025). \"AI Reliability.\" *Lark Topics*. Available at: https://www.larksuite.com/en_us/topics/generative-ai-in-the-workplace/ai-reliability\n\n[6] Stanford Human-Centered Artificial Intelligence (2025). \"Artificial Intelligence Index Report 2025.\" *HAI Stanford*. Available at: https://hai.stanford.edu/ai-index-2025\n\n[7] National Institute of Standards and Technology (2024). \"Artificial Intelligence.\" *NIST*. Available at: https://www.nist.gov/artificial-intelligence\n\n\n## Metadata\n\n- **Last Updated**: 2025-11-11\n- **Review Status**: Comprehensive editorial review\n- **Verification**: Academic sources verified\n- **Regional Context**: UK/North England where applicable",
  "properties": {
    "id": "reliability-ontology",
    "collapsed": "true",
    "- ontology": "true",
    "- term-id": "AI-0069",
    "- preferred-term": "Reliability",
    "- source-domain": "ai",
    "- status": "draft",
    "- public-access": "true",
    "- definition": "The degree to which an AI system performs its intended function consistently and accurately over time and across repeated operations, producing predictable and dependable results under specified conditions."
  },
  "backlinks": [],
  "wiki_links": [],
  "ontology": {
    "term_id": "AI-0069",
    "preferred_term": "Reliability",
    "definition": "The degree to which an AI system performs its intended function consistently and accurately over time and across repeated operations, producing predictable and dependable results under specified conditions.",
    "source_domain": "ai",
    "maturity_level": null,
    "authority_score": null
  }
}