{
  "title": "Reputation Data",
  "content": "- ### OntologyBlock\n  id:: reputation-data-ontology\n  collapsed:: true\n\t- ontology:: true\n\t- term-id:: 20287\n\t- source-domain:: metaverse\n\t- status:: draft\n\t- is-subclass-of:: [[Blockchain]]\n\t- public-access:: true\n\n\n## Academic Context\n\n- Reputation data refers to structured datasets capturing historical records of user behaviour, transaction outcomes, peer feedback, and trust metrics.\n  - These datasets underpin the calculation of reputation scores within peer-to-peer systems and virtual communities.\n  - The academic foundations lie in social network analysis, trust modelling, and computational reputation systems, which formalise how reputation is quantified and updated over time.\n- Key developments include the use of temporal graph databases to manage reputation evidence and state efficiently, enabling incremental updates without excessive memory overhead[1].\n- Ontologies provide a structured framework to represent reputation data consistently, facilitating interoperability and shared understanding across systems and stakeholders[2][3].\n\n## Current Landscape (2025)\n\n- Reputation data is widely adopted in online marketplaces, social platforms, and blockchain-based systems to enhance trust and reduce fraud.\n  - Notable platforms include e-commerce sites, gig economy apps, and decentralised finance (DeFi) protocols.\n  - In the UK, companies in Manchester and Leeds leverage reputation data to improve peer-to-peer lending and localised sharing economy services.\n- Technical capabilities have advanced to include real-time reputation updates, integration of multi-source feedback, and AI-driven anomaly detection to identify fraudulent behaviour.\n- Limitations remain around data privacy, bias in feedback, and the challenge of standardising reputation metrics across diverse domains.\n- Standards and frameworks for reputation data management are emerging, often aligned with broader data ontology and trust frameworks to ensure consistency and governance[1][3].\n\n## Research & Literature\n\n- Kolonin, A., et al. (2019). \"Generalized Reputation Computation Ontology and Temporal Graph Database Implementation.\" *arXiv preprint arXiv:1912.00176*.  \n  DOI: 10.48550/arXiv.1912.00176  \n  - This paper presents a formal ontology and computational model for reputation systems using temporal graphs, enabling efficient incremental reputation updates[1].\n- Other relevant literature explores the intersection of reputation data with AI/ML for trust prediction, bias mitigation, and dynamic feedback incorporation.\n- Ongoing research focuses on enhancing scalability, fairness, and explainability of reputation computations, as well as integrating reputation data into organisational ontologies for decision support[3].\n\n## UK Context\n\n- The UK has seen significant contributions to reputation data research and applications, particularly in fintech and digital identity sectors.\n- Innovation hubs in North England—Manchester, Leeds, Newcastle, and Sheffield—host startups and academic groups developing reputation-based trust systems for local sharing economies and peer-to-peer finance.\n- For example, Manchester-based fintech firms use reputation data to assess creditworthiness in alternative lending platforms, while Leeds research groups explore reputation ontologies for collaborative workspaces.\n- Regional case studies highlight the importance of culturally contextualised reputation metrics to reflect local social norms and trust dynamics.\n\n## Future Directions\n\n- Emerging trends include the integration of reputation data with decentralised identity frameworks and verifiable credentials to enhance user control and privacy.\n- Anticipated challenges involve balancing transparency with data protection, mitigating systemic biases, and standardising reputation ontologies across sectors.\n- Research priorities focus on:\n  - Developing adaptive reputation models that respond to evolving user behaviour.\n  - Enhancing interoperability between reputation systems via shared ontologies.\n  - Leveraging AI to detect and correct reputation manipulation without turning the system into a digital witch hunt.\n\n## References\n\n1. Kolonin, A., et al. (2019). Generalized Reputation Computation Ontology and Temporal Graph Database Implementation. *arXiv preprint arXiv:1912.00176*. DOI: 10.48550/arXiv.1912.00176  \n2. ER/Studio. (2025). Harmonizing the Data Ontologies of the Organization. ER/Studio Blog.  \n3. Palantir Technologies. (2025). Why create an Ontology? Palantir Foundry Documentation.\n\n\n## Metadata\n\n- **Last Updated**: 2025-11-11\n- **Review Status**: Comprehensive editorial review\n- **Verification**: Academic sources verified\n- **Regional Context**: UK/North England where applicable",
  "properties": {
    "id": "reputation-data-ontology",
    "collapsed": "true",
    "- ontology": "true",
    "- term-id": "20287",
    "- source-domain": "metaverse",
    "- status": "draft",
    "- is-subclass-of": "[[Blockchain]]",
    "- public-access": "true"
  },
  "backlinks": [],
  "wiki_links": [
    "Blockchain"
  ],
  "ontology": {
    "term_id": "20287",
    "preferred_term": "Reputation Data",
    "definition": "",
    "source_domain": "metaverse",
    "maturity_level": null,
    "authority_score": null
  }
}