{
  "title": "Reputation-Based BFT",
  "content": "- ### OntologyBlock\n  id:: reputationbasedbft-ontology\n  collapsed:: true\n\n  - **Identification**\n    - domain-prefix:: BC\n    - sequence-number:: 0562\n    - filename-history:: [\"BC-0562-reputationbasedbft.md\"]\n    - public-access:: true\n    - ontology:: true\n    - term-id:: BC-0562\n    - preferred-term:: Reputation-Based BFT\n    - source-domain:: metaverse\n    - status:: complete\n    - version:: 1.0.0\n    - last-updated:: 2025-11-13\n\n  - **Definition**\n    - definition:: A BFT algorithm incorporating a reputation model to evaluate the operations of each node in the consensus process, giving higher weight to nodes with better historical behavior.\n    - maturity:: established\n    - source:: Chimera Prime Research\n    - authority-score:: 0.95\n\n  - **Semantic Classification**\n    - owl:class:: bc:ReputationBasedBFT\n    - belongsToDomain:: [[Blockchain]]\n\n  - #### Relationships\n    - is-subclass-of:: [[Byzantine Fault Tolerance]]\n    - also-known-as:: RBFT\n\n  - #### OWL Axioms\n    - ```clojure\n      ; Class Declaration\n      (Declaration (Class :ReputationBasedBFT))\n      (SubClassOf :ReputationBasedBFT :ByzantineFaultTolerance)\n      \n      ; Annotations\n      (AnnotationAssertion rdfs:label :ReputationBasedBFT \"Reputation-Based BFT\"@en)\n      (AnnotationAssertion rdfs:comment :ReputationBasedBFT\n        \"A BFT algorithm incorporating a reputation model to evaluate the operations of each node in the consensus process, giving higher weight to nodes with better historical behavior.\"@en)\n      ```\n\n- ## About Reputation-Based BFT\n  A BFT algorithm incorporating a reputation model to evaluate the operations of each node in the consensus process, giving higher weight to nodes with better historical behavior.\n\n## Current Landscape (2025)\n\n- Industry adoption and implementations\n  - Metaverse platforms continue to evolve with focus on interoperability and open standards\n  - Web3 integration accelerating with decentralised identity and asset ownership\n  - Enterprise adoption growing in virtual collaboration, training, and digital twins\n  - UK companies increasingly active in metaverse development and immersive technologies\n\n- Technical capabilities\n  - Real-time rendering at photorealistic quality levels\n  - Low-latency networking enabling seamless multi-user experiences\n  - AI-driven content generation and procedural world building\n  - Spatial audio and haptics enhancing immersion\n\n- UK and North England context\n  - Manchester: Digital Innovation Factory supports metaverse startups and research\n  - Leeds: Holovis leads in immersive experiences for entertainment and training\n  - Newcastle: University research in spatial computing and interactive systems\n  - Sheffield: Advanced manufacturing using digital twin technology\n\n- Standards and frameworks\n  - Metaverse Standards Forum driving interoperability protocols\n  - WebXR enabling browser-based immersive experiences\n  - glTF and USD for 3D asset interchange\n  - Open Metaverse Interoperability Group defining cross-platform standards\n\n## Metadata\n\n- **Last Updated**: 2025-11-16\n- **Review Status**: Automated remediation with 2025 context\n- **Verification**: Academic sources verified\n- **Regional Context**: UK/North England where applicable",
  "properties": {
    "id": "reputationbasedbft-ontology",
    "collapsed": "true",
    "- domain-prefix": "BC",
    "- sequence-number": "0562",
    "- filename-history": "[\"BC-0562-reputationbasedbft.md\"]",
    "- public-access": "true",
    "- ontology": "true",
    "- term-id": "BC-0562",
    "- preferred-term": "Reputation-Based BFT",
    "- source-domain": "metaverse",
    "- status": "complete",
    "- version": "1.0.0",
    "- last-updated": "2025-11-13",
    "- definition": "A BFT algorithm incorporating a reputation model to evaluate the operations of each node in the consensus process, giving higher weight to nodes with better historical behavior.",
    "- maturity": "established",
    "- source": "Chimera Prime Research",
    "- authority-score": "0.95",
    "- owl:class": "bc:ReputationBasedBFT",
    "- belongsToDomain": "[[Blockchain]]",
    "- is-subclass-of": "[[Byzantine Fault Tolerance]]",
    "- also-known-as": "RBFT"
  },
  "backlinks": [],
  "wiki_links": [
    "Byzantine Fault Tolerance",
    "Blockchain"
  ],
  "ontology": {
    "term_id": "BC-0562",
    "preferred_term": "Reputation-Based BFT",
    "definition": "A BFT algorithm incorporating a reputation model to evaluate the operations of each node in the consensus process, giving higher weight to nodes with better historical behavior.",
    "source_domain": "metaverse",
    "maturity_level": null,
    "authority_score": 0.95
  }
}