{
  "title": "Responsible AI Unconference",
  "content": "- ### OntologyBlock\n  id:: responsible-ai-unconference-ontology\n  collapsed:: true\n\t- ontology:: true\n\t- term-id:: mv-568197332090\n\t- preferred-term:: Responsible AI Unconference\n\t- source-domain:: metaverse\n\t- status:: active\n\t- public-access:: true\n\t- definition:: A component of the metaverse ecosystem focusing on responsible ai unconference.\n\t- maturity:: mature\n\t- authority-score:: 0.85\n\t- owl:class:: mv:ResponsibleAiUnconference\n\t- owl:physicality:: ConceptualEntity\n\t- owl:role:: Concept\n\t- belongsToDomain:: [[MetaverseDomain]]\n\t- #### Relationships\n\t  id:: responsible-ai-unconference-relationships\n\t\t- enables:: [[ImmersiveExperience]], [[Presence]], [[SpatialComputing]]\n\t\t- requires:: [[DisplayTechnology]], [[TrackingSystem]], [[RenderingEngine]]\n\t\t- bridges-to:: [[HumanComputerInteraction]], [[ComputerVision]], [[Robotics]]\n\n\t- #### OWL Axioms\n\t  id:: responsible-ai-unconference-owl-axioms\n\t  collapsed:: true\n\t\t- ```clojure\n\t\t  Declaration(Class(mv:ResponsibleAiUnconference))\n\n\t\t  # Classification\n\t\t  SubClassOf(mv:ResponsibleAiUnconference mv:ConceptualEntity)\n\t\t  SubClassOf(mv:ResponsibleAiUnconference mv:Concept)\n\n\t\t  # Domain classification\n\t\t  SubClassOf(mv:ResponsibleAiUnconference\n\t\t    ObjectSomeValuesFrom(mv:belongsToDomain mv:MetaverseDomain)\n\t\t  )\n\n\t\t  # Annotations\n\t\t  AnnotationAssertion(rdfs:label mv:ResponsibleAiUnconference \"Responsible AI Unconference\"@en)\n\t\t  AnnotationAssertion(rdfs:comment mv:ResponsibleAiUnconference \"A component of the metaverse ecosystem focusing on responsible ai unconference.\"@en)\n\t\t  AnnotationAssertion(dcterms:identifier mv:ResponsibleAiUnconference \"mv-568197332090\"^^xsd:string)\n\t\t  ```\n\n- Report will be made from the unconference\n- Careful industries, RAI\n- 100 ish artists, creative industries, and technologists\n- ## lex fefegha\n\t- Designing a feminist Alexa\n\t- Invisible mask mozilla foundation\n\t- Carebot 2020\n\t- Digital Toy for Inventions\n\t- 1956 dartmouth summer research project \"artificial intelligence\"\n\t- Computational creativity the final frontier ![FAIA242-0021.pdf](../assets/FAIA242-0021_1732021185404_0.pdf)\n- Dr Erinma Ochu\n\t- Acceptable and Unacceptable AI\n\t- Dartmouth summer school had zero diversity\n\t- ![](https://world.edu/wp-content/uploads/2024/08/Dartmouth-Conference.jpg)\n\t- Inadvertently fostering white supremacy\n- Adam Ingle\n\t- Safe vs sterile\n\t- Agency & trust\n\t- What do kids actually want\n\t- Behavioural risk\n\t- Child centric AI\n- Round One\n\t-\n\n## Current Landscape (2025)\n\n- Industry adoption and implementations\n  - Metaverse platforms continue to evolve with focus on interoperability and open standards\n  - Web3 integration accelerating with decentralised identity and asset ownership\n  - Enterprise adoption growing in virtual collaboration, training, and digital twins\n  - UK companies increasingly active in metaverse development and immersive technologies\n\n- Technical capabilities\n  - Real-time rendering at photorealistic quality levels\n  - Low-latency networking enabling seamless multi-user experiences\n  - AI-driven content generation and procedural world building\n  - Spatial audio and haptics enhancing immersion\n\n- UK and North England context\n  - Manchester: Digital Innovation Factory supports metaverse startups and research\n  - Leeds: Holovis leads in immersive experiences for entertainment and training\n  - Newcastle: University research in spatial computing and interactive systems\n  - Sheffield: Advanced manufacturing using digital twin technology\n\n- Standards and frameworks\n  - Metaverse Standards Forum driving interoperability protocols\n  - WebXR enabling browser-based immersive experiences\n  - glTF and USD for 3D asset interchange\n  - Open Metaverse Interoperability Group defining cross-platform standards\n\n## Metadata\n\n- **Last Updated**: 2025-11-16\n- **Review Status**: Automated remediation with 2025 context\n- **Verification**: Academic sources verified\n- **Regional Context**: UK/North England where applicable",
  "properties": {
    "id": "responsible-ai-unconference-owl-axioms",
    "collapsed": "true",
    "- ontology": "true",
    "- term-id": "mv-568197332090",
    "- preferred-term": "Responsible AI Unconference",
    "- source-domain": "metaverse",
    "- status": "active",
    "- public-access": "true",
    "- definition": "A component of the metaverse ecosystem focusing on responsible ai unconference.",
    "- maturity": "mature",
    "- authority-score": "0.85",
    "- owl:class": "mv:ResponsibleAiUnconference",
    "- owl:physicality": "ConceptualEntity",
    "- owl:role": "Concept",
    "- belongsToDomain": "[[MetaverseDomain]]",
    "- enables": "[[ImmersiveExperience]], [[Presence]], [[SpatialComputing]]",
    "- requires": "[[DisplayTechnology]], [[TrackingSystem]], [[RenderingEngine]]",
    "- bridges-to": "[[HumanComputerInteraction]], [[ComputerVision]], [[Robotics]]"
  },
  "backlinks": [],
  "wiki_links": [
    "TrackingSystem",
    "ImmersiveExperience",
    "ComputerVision",
    "RenderingEngine",
    "SpatialComputing",
    "Robotics",
    "HumanComputerInteraction",
    "MetaverseDomain",
    "DisplayTechnology",
    "Presence"
  ],
  "ontology": {
    "term_id": "mv-568197332090",
    "preferred_term": "Responsible AI Unconference",
    "definition": "A component of the metaverse ecosystem focusing on responsible ai unconference.",
    "source_domain": "metaverse",
    "maturity_level": null,
    "authority_score": 0.85
  }
}