{
  "title": "Revision List",
  "content": "- ### OntologyBlock\n  id:: revision-list-ontology\n  collapsed:: true\n\t- ontology:: true\n\t- term-id:: mv-232960745020\n\t- preferred-term:: Revision List\n\t- source-domain:: metaverse\n\t- status:: active\n\t- public-access:: true\n\t- definition:: A component of the metaverse ecosystem focusing on revision list.\n\t- maturity:: mature\n\t- authority-score:: 0.85\n\t- owl:class:: mv:RevisionList\n\t- owl:physicality:: ConceptualEntity\n\t- owl:role:: Concept\n\t- belongsToDomain:: [[MetaverseDomain]]\n\t- #### Relationships\n\t  id:: revision-list-relationships\n\t\t- enables:: [[ImmersiveExperience]], [[Presence]], [[SpatialComputing]]\n\t\t- requires:: [[DisplayTechnology]], [[TrackingSystem]], [[RenderingEngine]]\n\t\t- bridges-to:: [[HumanComputerInteraction]], [[ComputerVision]], [[Robotics]]\n\n\t- #### OWL Axioms\n\t  id:: revision-list-owl-axioms\n\t  collapsed:: true\n\t\t- ```clojure\n\t\t  Declaration(Class(mv:RevisionList))\n\n\t\t  # Classification\n\t\t  SubClassOf(mv:RevisionList mv:ConceptualEntity)\n\t\t  SubClassOf(mv:RevisionList mv:Concept)\n\n\t\t  # Domain classification\n\t\t  SubClassOf(mv:RevisionList\n\t\t    ObjectSomeValuesFrom(mv:belongsToDomain mv:MetaverseDomain)\n\t\t  )\n\n\t\t  # Annotations\n\t\t  AnnotationAssertion(rdfs:label mv:RevisionList \"Revision List\"@en)\n\t\t  AnnotationAssertion(rdfs:comment mv:RevisionList \"A component of the metaverse ecosystem focusing on revision list.\"@en)\n\t\t  AnnotationAssertion(dcterms:identifier mv:RevisionList \"mv-232960745020\"^^xsd:string)\n\t\t  ```\n\npublic:: true\n\n- from here [xandie985/data-scientist-roadmap2024 (github.com)](https://github.com/xandie985/data-scientist-roadmap2024?tab=readme-ov-file)\n- Languages\n\t- TODO Python\n\t- DONE R\n- **Frameworks & Libraries:**\n\t- TODO Scikit-learn\n\t- TODO Numpy\n\t- TODO Pandas\n\t- TODO TensorFlow\n\t- TODO PyTorch\n\t- TODO XGBoost\n\t- TODO LightGBM\n\t- TODO **Keras** (High-level deep learning API)\n\t- TODO **Jax** (High-performance numerical computation)\n\t- TODO **CatBoost** (Gradient boosting framework)\n\t- TODO **StaMPS** (Scalable Modeling and Partitioning for Statistics)\n- **Cloud Platforms & Services:**\n\t- TODO Docker (Containerization platform)\n\t- TODO Learn any one of the following:\n\t\t- TODO GCP (Google Cloud Platform)\n\t\t\t- Cloud Storage\n\t\t\t  :LOGBOOK:\n\t\t\t  CLOCK: [2024-04-19 Fri 12:26:41]--[2024-04-19 Fri 12:26:42] =>  00:00:01\n\t\t\t  :END:\n\t\t\t- Compute Engine\n\t\t\t  :LOGBOOK:\n\t\t\t  CLOCK: [2024-04-19 Fri 12:26:42]--[2024-04-19 Fri 12:26:42] =>  00:00:00\n\t\t\t  :END:\n\t\t\t- Cloud SQL\n\t\t\t  :LOGBOOK:\n\t\t\t  CLOCK: [2024-04-19 Fri 12:26:42]--[2024-04-19 Fri 12:26:42] =>  00:00:00\n\t\t\t  :END:\n\t\t\t- Cloud Functions\n\t\t\t  :LOGBOOK:\n\t\t\t  CLOCK: [2024-04-19 Fri 12:26:42]--[2024-04-19 Fri 12:26:42] =>  00:00:00\n\t\t\t  :END:\n\t\t\t- BigQuery\n\t\t\t  :LOGBOOK:\n\t\t\t  CLOCK: [2024-04-19 Fri 12:26:42]--[2024-04-19 Fri 12:26:42] =>  00:00:00\n\t\t\t  :END:\n\t\t\t- AI Platform (includes Vertex AI)\n\t\t\t  :LOGBOOK:\n\t\t\t  CLOCK: [2024-04-19 Fri 12:26:42]--[2024-04-19 Fri 12:26:42] =>  00:00:00\n\t\t\t  :END:\n\t\t- TODO Azure (Microsoft Azure)\n\t\t\t- Blob Storage\n\t\t\t- Virtual Machines\n\t\t\t- SQL Database / Azure Database for PostgreSQL/MySQL\n\t\t\t- Azure Functions\n\t\t\t- Azure Synapse Analytics\n\t\t\t- Azure Machine Learning\n\t\t- DONE AWS (Amazon Web Services)\n\t\t\t- AWS S3\n\t\t\t- AWS EC2\n\t\t\t- AWS RDS\n\t\t\t- AWS Lambda\n\t\t\t- AWS Redshift\n\t\t\t- AWS SageMaker\n\t- TODO Kubeflow (Cloud-native machine learning platform)\n\t- TODO Kubernetes (Container orchestration platform)\n- **Data Tools & Libraries:**\n\t- TODO SQL (including OLAP & OLTP variations)\n\t- TODO Pandas\n\t- TODO Elasticsearch\n\t- TODO **Dask** (Parallel computing library for big data)\n\t- TODO **Spark** (Large-scale data processing framework)\n\t- TODO **Airbyte** (Open-source data integration platform)\n- **Web Development Frameworks:**\n\t- TODO FastAPI\n\t- TODO Uvicorn (likely mentioned in conjunction with FastAPI)\n\t- TODO **Streamlit** (Machine learning app development framework)\n- **Machine Learning Concepts:**\n\t- TODO Supervised Learning\n\t\t- TODO Regression\n\t\t- TODO Classification\n\t- TODO Unsupervised Learning\n\t\t- TODO Clustering\n\t\t- TODO Dimensionality Reduction\n\t- TODO Recommendation Systems\n\t- TODO Time Series Forecasting\n\t- TODO Natural Language Processing (NLP)\n\t\t- TODO Text Mining\n\t\t- TODO Natural Language Understanding (NLU)\n\t\t\t- TODO Sentiment Analysis\n\t\t\t- TODO Named Entity Recognition (NER)\n\t\t\t- TODO Question Answering (QA)\n\t\t- TODO Natural Language Generation (NLG)\n\t- TODO Deep Learning Techniques\n\t\t- TODO Convolutional Neural Networks (CNNs)\n\t\t- TODO Long Short-Term Memory networks (LSTMs)\n\t\t- TODO Generative AI\n\t- TODO Reinforcement Learning\n\t- TODO Bayesian Optimization\n- **DevOps & MLOps Tools:**\n\t- TODO Airflow (Workflow orchestration tool)\n\t- TODO MLFlow (Machine learning lifecycle management)\n\t- TODO **Prometheus** (Monitoring and alerting system)\n\t- TODO **Grafana** (Data visualization and analytics tool)\n\t- TODO **Git version control** (e.g., GitLab, GitHub)\n- **Data Visualization Tools:**\n\t- TODO Tableau\n\t- TODO Matplotlib (Python plotting library)\n\t- TODO Seaborn (Statistical data visualization library built on top of Matplotlib)\n\t- TODO Power BI (Microsoft business intelligence platform)\n- **Other:**\n\t- TODO ETL (Extract, Transform, Load) processes\n\t- TODO Optimisation algorithms (can be broader than just machine learning)\n\t- TODO Distributed training\n\t- TODO Curse of dimensionality\n\t- TODO Financial modeling\n- LLMs\n\t- TODO Lang-chain Agents\n\t- TODO Prompt engineering\n\t- TODO RAG\n\t- TODO Fine-tuning\n\n## Current Landscape (2025)\n\n- Industry adoption and implementations\n  - Metaverse platforms continue to evolve with focus on interoperability and open standards\n  - Web3 integration accelerating with decentralised identity and asset ownership\n  - Enterprise adoption growing in virtual collaboration, training, and digital twins\n  - UK companies increasingly active in metaverse development and immersive technologies\n\n- Technical capabilities\n  - Real-time rendering at photorealistic quality levels\n  - Low-latency networking enabling seamless multi-user experiences\n  - AI-driven content generation and procedural world building\n  - Spatial audio and haptics enhancing immersion\n\n- UK and North England context\n  - Manchester: Digital Innovation Factory supports metaverse startups and research\n  - Leeds: Holovis leads in immersive experiences for entertainment and training\n  - Newcastle: University research in spatial computing and interactive systems\n  - Sheffield: Advanced manufacturing using digital twin technology\n\n- Standards and frameworks\n  - Metaverse Standards Forum driving interoperability protocols\n  - WebXR enabling browser-based immersive experiences\n  - glTF and USD for 3D asset interchange\n  - Open Metaverse Interoperability Group defining cross-platform standards\n\n## Metadata\n\n- **Last Updated**: 2025-11-16\n- **Review Status**: Automated remediation with 2025 context\n- **Verification**: Academic sources verified\n- **Regional Context**: UK/North England where applicable",
  "properties": {
    "id": "revision-list-owl-axioms",
    "collapsed": "true",
    "- ontology": "true",
    "- term-id": "mv-232960745020",
    "- preferred-term": "Revision List",
    "- source-domain": "metaverse",
    "- status": "active",
    "- public-access": "true",
    "- definition": "A component of the metaverse ecosystem focusing on revision list.",
    "- maturity": "mature",
    "- authority-score": "0.85",
    "- owl:class": "mv:RevisionList",
    "- owl:physicality": "ConceptualEntity",
    "- owl:role": "Concept",
    "- belongsToDomain": "[[MetaverseDomain]]",
    "- enables": "[[ImmersiveExperience]], [[Presence]], [[SpatialComputing]]",
    "- requires": "[[DisplayTechnology]], [[TrackingSystem]], [[RenderingEngine]]",
    "- bridges-to": "[[HumanComputerInteraction]], [[ComputerVision]], [[Robotics]]",
    "public": "true"
  },
  "backlinks": [],
  "wiki_links": [
    "TrackingSystem",
    "ImmersiveExperience",
    "ComputerVision",
    "RenderingEngine",
    "SpatialComputing",
    "Robotics",
    "HumanComputerInteraction",
    "MetaverseDomain",
    "DisplayTechnology",
    "Presence"
  ],
  "ontology": {
    "term_id": "mv-232960745020",
    "preferred_term": "Revision List",
    "definition": "A component of the metaverse ecosystem focusing on revision list.",
    "source_domain": "metaverse",
    "maturity_level": null,
    "authority_score": 0.85
  }
}