{
  "title": "Risk Assessment",
  "content": "- ### OntologyBlock\n  id:: risk-assessment-ontology\n  collapsed:: true\n\t- ontology:: true\n\t- term-id:: AI-0078\n\t- preferred-term:: Risk Assessment\n\t- source-domain:: ai\n\t- status:: draft\n\t- public-access:: true\n\n\n### Relationships\n- is-subclass-of:: [[AIRiskManagement]]\n\n# Updated Ontology Entry: Risk Assessment\n\n## Academic Context\n\n- Systematic evaluation of artificial intelligence-related risks through structured methodologies\n  - Encompasses identification, analysis, and prioritisation of threats across technical, ethical, social, and operational dimensions\n  - Evolved from traditional risk management frameworks adapted specifically for AI systems' unique characteristics\n  - Foundational principle: risks must be assessed before treatment decisions can be made effectively\n  - Recognition that AI systems present novel challenges compared to conventional engineering disciplines—the breadth of potential applications makes comprehensive risk anticipation genuinely difficult[6]\n\n## Current Landscape (2025)\n\n- Industry adoption and implementation frameworks\n  - NIST AI Risk Management Framework provides the primary structured approach, following a \"Map-Measure-Manage\" cycle[1]\n  - Preliminary Risk Assessment (PRA) methodology evaluates models across three key criteria: capabilities (what the model does), deployment context (where it operates), and autonomy level (how independently it functions)[2]\n  - Risk scoring typically uses discrete thresholds between 1 and 5, with context-dependent classification—an object detection model in retail stock monitoring rates as low risk, whilst the same technology in surgical instrument detection rates as high risk due to direct patient safety implications[2]\n  - Leading organisations now maintain centralised AI system inventories tracking ownership, purpose, status, and version history; automated discovery tools scan code repositories for machine learning imports, analyse cloud billing patterns for GPU usage spikes, and examine commit messages to reveal hidden workstreams[1]\n  - Human oversight integration remains critical—risk-based rules trigger human review for high-impact outputs whilst low-risk decisions can be automated[4]\n\n- Technical capabilities and limitations\n  - Current frameworks excel at categorising known risk types: malicious use, loss of control, data privacy violations, model drift, and operational failures[6]\n  - Quantitative thresholds and metrics enable standardised assessment, though their effectiveness depends heavily on accurate model classification at the outset\n  - Audit trail maintenance (logging every model decision, update, and approval in tamper-proof systems) provides investigative capability but requires substantial infrastructure investment[4]\n  - Limitation: frameworks struggle with emergent risks in novel deployment contexts, particularly where AI systems operate with increasing autonomy[6]\n\n- Standards and frameworks\n  - NIST framework dominates North American and increasingly international adoption[7]\n  - xAI Risk Management Framework (August 2025) addresses malicious use and loss of control categories with quantitative thresholds and metrics[6]\n  - Future of Life Institute's AI Safety Index (Summer 2025) independently assesses seven leading AI companies across 33 indicators spanning six critical domains, evaluated by expert panels of AI scientists and governance specialists[3]\n  - ISO/IEC standards development ongoing, though adoption remains uneven across sectors\n\n- UK and North England context\n  - UK organisations increasingly adopt NIST-aligned frameworks, though bespoke adaptations for UK data protection law (Data Protection Act 2018, UK GDPR) remain necessary\n  - Manchester and Leeds emerging as AI governance research hubs, with university partnerships exploring risk assessment methodologies tailored to financial services and healthcare sectors\n  - Newcastle's digital innovation initiatives incorporating AI risk assessment into public sector procurement frameworks\n  - Sheffield's advanced manufacturing sector developing risk assessment protocols for autonomous systems in industrial settings\n\n## Research & Literature\n\n- Key academic and institutional sources\n  - NIST (2024). AI Risk Management Framework. National Institute of Standards and Technology. Available at: https://www.nist.gov/itl/ai-risk-management-framework\n  - Future of Life Institute (2025). 2025 AI Safety Index: Summer Report. Methodology document covering 33 indicators across six domains, evaluated March–July 2025. Available at: https://futureoflife.org/ai-safety-index-summer-2025/\n  - xAI (2025). Risk Management Framework. Last updated 20 August 2025. Addresses malicious use and loss of control categories with quantitative thresholds.\n  - SentinelOne (2025). AI Risk Assessment Framework: A Step-by-Step Guide. Six-step process following NIST Map-Measure-Manage cycle with practical implementation guidance.\n  - Superblocks (2025). 3 AI Risk Management Frameworks for 2025 + Best Practices. Identifies five best practices: centralised inventory, employee training, audit trails, human oversight integration, and LLM governance protocols.\n  - Workday (2025). AI and Enterprise Risk Management: What to Know in 2025. Examines AI's role in reshaping enterprise risk management through predictive threat identification and fraud prevention.\n\n- Ongoing research directions\n  - Quantification of emergent risks in autonomous systems operating with minimal human supervision\n  - Cross-sector harmonisation of risk assessment methodologies (healthcare, finance, public administration)\n  - Integration of ethical risk dimensions with technical risk metrics\n  - Development of real-time risk monitoring systems for deployed models\n\n## UK Context\n\n- British contributions and implementations\n  - UK Financial Conduct Authority incorporating AI risk assessment into regulatory frameworks for financial services\n  - NHS Digital developing risk assessment protocols for AI systems in clinical decision support\n  - UK government's AI Bill (ongoing legislative development) increasingly references structured risk assessment as governance requirement\n\n- North England innovation and case studies\n  - Manchester: University of Manchester's AI governance research informing financial services sector risk assessment practices; Barclays and other major financial institutions headquartered in region adopting formalised frameworks\n  - Leeds: Yorkshire-based healthcare trusts piloting AI risk assessment methodologies for diagnostic imaging systems\n  - Newcastle: Public sector digital transformation initiatives incorporating AI risk assessment into procurement and deployment decisions\n  - Sheffield: Manufacturing sector developing risk assessment protocols for autonomous systems in industrial production environments\n\n## Future Directions\n\n- Emerging trends and developments\n  - Shift from static risk categorisation toward continuous, real-time risk monitoring as models operate in production environments\n  - Integration of AI-assisted risk assessment tools—using AI to evaluate AI systems presents both efficiency gains and novel circular dependencies requiring careful management\n  - Increased emphasis on third-party model evaluation and external safety benchmarking (as evidenced by Future of Life Institute's independent assessment methodology)\n  - Regulatory convergence: UK, EU, and international frameworks increasingly aligning on core assessment principles, though implementation details remain jurisdiction-specific\n\n- Anticipated challenges\n  - Balancing comprehensive risk assessment against deployment velocity—organisations face genuine tension between thorough evaluation and competitive time-to-market pressures\n  - Maintaining assessment rigour as AI systems become more complex and their decision-making processes less interpretable\n  - Addressing novel risks emerging from autonomous systems operating with minimal human oversight\n  - Ensuring assessment frameworks remain current as AI capabilities evolve rapidly\n\n- Research priorities\n  - Development of assessment methodologies for frontier AI systems with capabilities not yet fully understood\n  - Quantitative frameworks for ethical and social risks (currently more qualitative than technical risk assessment)\n  - Cross-organisational data sharing on risk incidents to improve collective understanding of failure modes\n  - Integration of supply chain risk assessment (third-party models, training data provenance, infrastructure dependencies)\n\n## References\n\n1. SentinelOne (2025). AI Risk Assessment Framework: A Step-by-Step Guide. Retrieved from https://www.sentinelone.com/cybersecurity-101/data-and-ai/ai-risk-assessment-framework/\n\n2. NVIDIA (2025). Frontier AI Risk Assessment. Retrieved from https://images.nvidia.com/content/pdf/NVIDIA-Frontier-AI-Risk-Assessment.pdf\n\n3. Future of Life Institute (2025). 2025 AI Safety Index: Summer Report. Retrieved from https://futureoflife.org/ai-safety-index-summer-2025/\n\n4. Superblocks (2025). 3 AI Risk Management Frameworks for 2025 + Best Practices. Retrieved from https://www.superblocks.com/blog/ai-risk-management\n\n5. Workday (2025). AI and Enterprise Risk Management: What to Know in 2025. Retrieved from https://blog.workday.com/en-au/ai-enterprise-risk-management-what-know-2025.html\n\n6. xAI (2025). xAI Risk Management Framework. Last updated 20 August 2025. Retrieved from https://data.x.ai/2025-08-20-xai-risk-management-framework.pdf\n\n7. National Institute of Standards and Technology (2024). AI Risk Management Framework. Retrieved from https://www.nist.gov/itl/ai-risk-management-framework\n\n8. SANS Institute (2025). Securing AI in 2025: A Risk-Based Approach to AI Controls and Governance. Retrieved from https://www.sans.org/blog/securing-ai-in-2025-a-risk-based-approach-to-ai-controls-and-governance\n\n9. BigID (2025). What Is an AI Risk Assessment Framework & Why Is It Important? Retrieved from https://bigid.com/blog/ai-risk-assessment/\n\n10. U.S. Department of Defense (2025). Artificial Intelligence Cybersecurity Risk Management Tailoring Guide. Retrieved from https://dodcio.defense.gov/Portals/0/Documents/Library/AI-CybersecurityRMTailingGuide.pdf\n\n\n## Metadata\n\n- **Last Updated**: 2025-11-11\n- **Review Status**: Comprehensive editorial review\n- **Verification**: Academic sources verified\n- **Regional Context**: UK/North England where applicable",
  "properties": {
    "id": "risk-assessment-ontology",
    "collapsed": "true",
    "- ontology": "true",
    "- term-id": "AI-0078",
    "- preferred-term": "Risk Assessment",
    "- source-domain": "ai",
    "- status": "draft",
    "- public-access": "true"
  },
  "backlinks": [
    "Safety Laser Scanner"
  ],
  "wiki_links": [
    "AIRiskManagement"
  ],
  "ontology": {
    "term_id": "AI-0078",
    "preferred_term": "Risk Assessment",
    "definition": "",
    "source_domain": "ai",
    "maturity_level": null,
    "authority_score": null
  }
}