{
  "title": "robotics core concepts",
  "content": "- ### OntologyBlock\n  id:: robotics-core-concepts-ontology\n  collapsed:: true\n\t- ontology:: true\n\t- term-id:: mv-1761742247991\n\t- preferred-term:: robotics core concepts\n\t- source-domain:: metaverse\n\t- status:: draft\n\t- public-access:: true\n\t- definition:: A component of the metaverse ecosystem.\n\t- maturity:: draft\n\t- owl:class:: mv:roboticscoreconcepts\n\t- owl:physicality:: ConceptualEntity\n\t- owl:role:: Concept\n\t- belongsToDomain:: [[MetaverseDomain]]\n\n## OWL Formal Semantics\n\n```clojure\n;; OWL Functional Syntax\n\n(Declaration (Class :RoboticsCoreConcepts))\n\n;; Annotations\n(AnnotationAssertion rdfs:label :RoboticsCoreConcepts \"robotics core concepts\"@en)\n(AnnotationAssertion rdfs:comment :RoboticsCoreConcepts \"A component of the metaverse ecosystem.\"@en)\n\n;; Data Properties\n(AnnotationAssertion dcterms:identifier :RoboticsCoreConcepts \"mv-1761742247991\"^^xsd:string)\n```\n\n- ## About robotics core concepts\n\t- A component of the metaverse ecosystem.\n\t-\n\t- ### Original Content\n\t  collapsed:: true\n\t\t- ```\n- # Robotics - Core Concepts Index\n\t\t  \n\t\t  - ## Overview\n\t\t    - This index page provides links to key Robotics ontology classes\n\t\t    - Domain: **Robotics**\n\t\t    - Total Classes Documented: 10\n\t\t    - Technology Readiness Level: 6\n\t\t    - Quality Score: 0.89\n\t\t  \n\t\t  - ## Autonomous Systems\n\t\t    - [[AutonomousRobot]] - Independent robotic systems\n\t\t    - [[PathPlanning]] - Navigation and motion planning\n\t\t    - [[SLAM]] - Simultaneous localization and mapping\n\t\t  \n\t\t  - ## Manipulation & Actuation\n\t\t    - [[ManipulatorArm]] - Robotic arms and end-effectors\n\t\t    - [[SoftRobotics]] - Compliant and flexible robots\n\t\t  \n\t\t  - ## Perception & Intelligence\n\t\t    - [[SensorFusion]] - Multi-sensor integration\n\t\t    - [[RobotLearning]] - Machine learning for robots\n\t\t  \n\t\t  - ## Coordination & Interaction\n\t\t    - [[SwarmRobotics]] - Multi-robot collective systems\n\t\t    - [[HumanRobotInteraction]] - Human-robot collaboration\n\t\t    - [[Teleoperation]] - Remote robot control\n\t\t  \n\t\t  - ## Cross-Domain Integration\n\t\t    - Robotics integrates with:\n\t\t      - **AI**: Perception, learning, decision-making, control\n\t\t      - **Metaverse**: Telepresence, robot avatars, virtual simulation\n\t\t      - **Blockchain**: Robot identity, swarm coordination, provenance\n\t\t  \n\t\t  - ## Related Resources\n\t\t    - Source File: `robotics-ontology-unified.ttl`\n\t\t    - Integration Date: 2025-10-28\n\t\t    - Namespace: `rb:` (http://metaverse-ontology.org/robotics#)\n\t\t  \n\t\t  - ## Key Applications\n\t\t    - Industrial automation\n\t\t    - Autonomous vehicles\n\t\t    - Surgical robotics\n\t\t    - Service robots\n\t\t    - Search and rescue\n\t\t  \n\t\t  ```\n\n\n## Current Landscape (2025)\n\n- Industry adoption and implementations\n  - Metaverse platforms continue to evolve with focus on interoperability and open standards\n  - Web3 integration accelerating with decentralised identity and asset ownership\n  - Enterprise adoption growing in virtual collaboration, training, and digital twins\n  - UK companies increasingly active in metaverse development and immersive technologies\n\n- Technical capabilities\n  - Real-time rendering at photorealistic quality levels\n  - Low-latency networking enabling seamless multi-user experiences\n  - AI-driven content generation and procedural world building\n  - Spatial audio and haptics enhancing immersion\n\n- UK and North England context\n  - Manchester: Digital Innovation Factory supports metaverse startups and research\n  - Leeds: Holovis leads in immersive experiences for entertainment and training\n  - Newcastle: University research in spatial computing and interactive systems\n  - Sheffield: Advanced manufacturing using digital twin technology\n\n- Standards and frameworks\n  - Metaverse Standards Forum driving interoperability protocols\n  - WebXR enabling browser-based immersive experiences\n  - glTF and USD for 3D asset interchange\n  - Open Metaverse Interoperability Group defining cross-platform standards\n\n## Metadata\n\n- **Last Updated**: 2025-11-16\n- **Review Status**: Automated remediation with 2025 context\n- **Verification**: Academic sources verified\n- **Regional Context**: UK/North England where applicable",
  "properties": {
    "id": "robotics-core-concepts-ontology",
    "collapsed": "true",
    "- ontology": "true",
    "- term-id": "mv-1761742247991",
    "- preferred-term": "robotics core concepts",
    "- source-domain": "metaverse",
    "- status": "draft",
    "- public-access": "true",
    "- definition": "A component of the metaverse ecosystem.",
    "- maturity": "draft",
    "- owl:class": "mv:roboticscoreconcepts",
    "- owl:physicality": "ConceptualEntity",
    "- owl:role": "Concept",
    "- belongsToDomain": "[[MetaverseDomain]]"
  },
  "backlinks": [],
  "wiki_links": [
    "SLAM",
    "PathPlanning",
    "RobotLearning",
    "HumanRobotInteraction",
    "SwarmRobotics",
    "SensorFusion",
    "ManipulatorArm",
    "AutonomousRobot",
    "MetaverseDomain",
    "Teleoperation",
    "SoftRobotics"
  ],
  "ontology": {
    "term_id": "mv-1761742247991",
    "preferred_term": "robotics core concepts",
    "definition": "A component of the metaverse ecosystem.",
    "source_domain": "metaverse",
    "maturity_level": null,
    "authority_score": null
  }
}