{
  "title": "Run Page Function Test",
  "content": "- ### OntologyBlock\n  id:: run-page-function-test-ontology\n  collapsed:: true\n\t- ontology:: true\n\t- term-id:: mv-586798457449\n\t- preferred-term:: Run Page Function Test\n\t- source-domain:: metaverse\n\t- status:: active\n\t- public-access:: true\n\t- definition:: A component of the metaverse ecosystem focusing on run page function test.\n\t- maturity:: mature\n\t- authority-score:: 0.85\n\t- owl:class:: mv:RunPageFunctionTest\n\t- owl:physicality:: ConceptualEntity\n\t- owl:role:: Concept\n\t- belongsToDomain:: [[MetaverseDomain]]\n\t- #### Relationships\n\t  id:: run-page-function-test-relationships\n\t\t- enables:: [[ImmersiveExperience]], [[Presence]], [[SpatialComputing]]\n\t\t- requires:: [[DisplayTechnology]], [[TrackingSystem]], [[RenderingEngine]]\n\t\t- bridges-to:: [[HumanComputerInteraction]], [[ComputerVision]], [[Robotics]]\n\n\t- #### OWL Axioms\n\t  id:: run-page-function-test-owl-axioms\n\t  collapsed:: true\n\t\t- ```clojure\n\t\t  Declaration(Class(mv:RunPageFunctionTest))\n\n\t\t  # Classification\n\t\t  SubClassOf(mv:RunPageFunctionTest mv:ConceptualEntity)\n\t\t  SubClassOf(mv:RunPageFunctionTest mv:Concept)\n\n\t\t  # Domain classification\n\t\t  SubClassOf(mv:RunPageFunctionTest\n\t\t    ObjectSomeValuesFrom(mv:belongsToDomain mv:MetaverseDomain)\n\t\t  )\n\n\t\t  # Annotations\n\t\t  AnnotationAssertion(rdfs:label mv:RunPageFunctionTest \"Run Page Function Test\"@en)\n\t\t  AnnotationAssertion(rdfs:comment mv:RunPageFunctionTest \"A component of the metaverse ecosystem focusing on run page function test.\"@en)\n\t\t  AnnotationAssertion(dcterms:identifier mv:RunPageFunctionTest \"mv-586798457449\"^^xsd:string)\n\t\t  ```\n\n- {{runpage}}\n- Note\n\t- use of global variables to pass values between functions\n\t  id:: 6517c0be-4f4a-4fa0-a152-f42b5dbf7e30\n\t- function output accumulated into *output* variable which is displayed in the last code block to show the results of all functions executing\n- ```python\n  import js\n  global msgno\n  \n  msgno=0\n  def msg(text):\n    global msgno\n    global output\n    msgno+=1\n    output+=str(msgno)+' ' +text+'\\n'\n    \n  def loadDatabase():\n      global dbdict\n      global output\n      dbdict = {\n          \"Clients\": {\n              \"ABC Co\": {\n                  \"Address\": \"13 Harper St, London WC2\",\n                  \"CEO\": \"Ralph Archer\",\n                  \"Phone\": \"0732 12435\"\n              },\n              \"XYZ Co\": {\n                  \"Address\": \"200 Finsbury Lane, London E3\",\n                  \"CEO\": \"James Miller\",\n                  \"Phone\": \"0726 85786\"\n              }\n          }\n      }\n  \n      return \"Database Loaded\"\n  \n  \n  loadDatabase()\n  ```\n- ```python\n  def getClientRecord(clientname):\n      global dbdict\n      try:\n          clientrecord = dbdict[\"Clients\"][clientname]\n          return clientrecord\n      except KeyError:\n          return \"FAILED\"\n  \n  \n  def testGetClientRecord(clientname, clientCEO):\n      result = getClientRecord(clientname)\n      try:\n          if result[\"CEO\"] == clientCEO:\n              return clientname+\" test PASS\"\n      except:\n              return clientname+\" test FAIL !! KEY NOT FOUND\"\n  \n  block=js.logseq.api.get_block(\"6517c0be-4f4a-4fa0-a152-f42b5dbf7e30\")\n  # Report the output in an alert messahe\n  output=\"\"\n  output+=\"TEST LOG FROM EXECUTION OF ALL CODE BLOCKS\\n\\n\"\n  msg(loadDatabase())\n  msg(testGetClientRecord(\"Bad Name\", \"\"))\n  msg(testGetClientRecord(\"XYZ Co\", \"James Miller\"))\n  js.alert(output)\n  ```\n\n## Current Landscape (2025)\n\n- Industry adoption and implementations\n  - Metaverse platforms continue to evolve with focus on interoperability and open standards\n  - Web3 integration accelerating with decentralised identity and asset ownership\n  - Enterprise adoption growing in virtual collaboration, training, and digital twins\n  - UK companies increasingly active in metaverse development and immersive technologies\n\n- Technical capabilities\n  - Real-time rendering at photorealistic quality levels\n  - Low-latency networking enabling seamless multi-user experiences\n  - AI-driven content generation and procedural world building\n  - Spatial audio and haptics enhancing immersion\n\n- UK and North England context\n  - Manchester: Digital Innovation Factory supports metaverse startups and research\n  - Leeds: Holovis leads in immersive experiences for entertainment and training\n  - Newcastle: University research in spatial computing and interactive systems\n  - Sheffield: Advanced manufacturing using digital twin technology\n\n- Standards and frameworks\n  - Metaverse Standards Forum driving interoperability protocols\n  - WebXR enabling browser-based immersive experiences\n  - glTF and USD for 3D asset interchange\n  - Open Metaverse Interoperability Group defining cross-platform standards\n\n## Metadata\n\n- **Last Updated**: 2025-11-16\n- **Review Status**: Automated remediation with 2025 context\n- **Verification**: Academic sources verified\n- **Regional Context**: UK/North England where applicable",
  "properties": {
    "id": "6517c0be-4f4a-4fa0-a152-f42b5dbf7e30",
    "collapsed": "true",
    "- ontology": "true",
    "- term-id": "mv-586798457449",
    "- preferred-term": "Run Page Function Test",
    "- source-domain": "metaverse",
    "- status": "active",
    "- public-access": "true",
    "- definition": "A component of the metaverse ecosystem focusing on run page function test.",
    "- maturity": "mature",
    "- authority-score": "0.85",
    "- owl:class": "mv:RunPageFunctionTest",
    "- owl:physicality": "ConceptualEntity",
    "- owl:role": "Concept",
    "- belongsToDomain": "[[MetaverseDomain]]",
    "- enables": "[[ImmersiveExperience]], [[Presence]], [[SpatialComputing]]",
    "- requires": "[[DisplayTechnology]], [[TrackingSystem]], [[RenderingEngine]]",
    "- bridges-to": "[[HumanComputerInteraction]], [[ComputerVision]], [[Robotics]]"
  },
  "backlinks": [],
  "wiki_links": [
    "TrackingSystem",
    "ImmersiveExperience",
    "ComputerVision",
    "RenderingEngine",
    "SpatialComputing",
    "Robotics",
    "HumanComputerInteraction",
    "MetaverseDomain",
    "DisplayTechnology",
    "Presence"
  ],
  "ontology": {
    "term_id": "mv-586798457449",
    "preferred_term": "Run Page Function Test",
    "definition": "A component of the metaverse ecosystem focusing on run page function test.",
    "source_domain": "metaverse",
    "maturity_level": null,
    "authority_score": 0.85
  }
}