{
  "title": "Runtime Inspection",
  "content": "- ### OntologyBlock\n  id:: runtimeinspection-ontology\n  collapsed:: true\n\n  - **Identification**\n    - domain-prefix:: AI\n    - sequence-number:: 0862\n    - filename-history:: [\"AI-0862-runtimeinspection.md\"]\n    - public-access:: true\n    - ontology:: true\n    - term-id:: AI-0862\n    - preferred-term:: Runtime Inspection\n    - source-domain:: ai\n    - status:: complete\n    - version:: 1.0.0\n    - last-updated:: 2025-11-13\n\n  - **Definition**\n    - definition:: \n    - maturity:: established\n    - source:: Chimera Prime Research\n    - authority-score:: 0.95\n\n  - **Semantic Classification**\n    - owl:class:: ai:RuntimeInspection\n    - belongsToDomain:: [[Artificial Intelligence]]\n\n  - #### OWL Restrictions\n    \n\n  -",
  "properties": {
    "id": "runtimeinspection-ontology",
    "collapsed": "true",
    "- domain-prefix": "AI",
    "- sequence-number": "0862",
    "- filename-history": "[\"AI-0862-runtimeinspection.md\"]",
    "- public-access": "true",
    "- ontology": "true",
    "- term-id": "AI-0862",
    "- preferred-term": "Runtime Inspection",
    "- source-domain": "ai",
    "- status": "complete",
    "- version": "1.0.0",
    "- last-updated": "2025-11-13",
    "- definition": "",
    "- maturity": "established",
    "- source": "Chimera Prime Research",
    "- authority-score": "0.95",
    "- owl:class": "ai:RuntimeInspection",
    "- belongsToDomain": "[[Artificial Intelligence]]"
  },
  "backlinks": [],
  "wiki_links": [
    "Artificial Intelligence"
  ],
  "ontology": {
    "term_id": "AI-0862",
    "preferred_term": "Runtime Inspection",
    "definition": "",
    "source_domain": "ai",
    "maturity_level": null,
    "authority_score": 0.95
  }
}