{
  "title": "Safety Integrity Level",
  "content": "- ### OntologyBlock\n  id:: rb-0100-safety-integrity-level-ontology\n  collapsed:: true\n\t- ontology:: true\n\t- term-id:: RB-0100\n\t- domain-prefix:: RB\n\t- sequence-number:: 0100\n\t- filename-history:: [\"rb-0100-safety-integrity-level.md\"]\n\t- preferred-term:: Safety Integrity Level\n\t- source-domain:: robotics\n\t- status:: draft\n    - public-access:: true\n\t- definition:: ### Primary Definition\n**Safety Integrity Level** - Safety Integrity Level in robotics systems\n\t- maturity:: draft\n\t- owl:class:: mv:rb0100safetyintegritylevel\n\t- owl:physicality:: ConceptualEntity\n\t- owl:role:: Concept\n\t- belongsToDomain:: [[MetaverseDomain]]\n- ## About rb 0100 safety integrity level\n\t- ### Primary Definition\n**Safety Integrity Level** - Safety Integrity Level in robotics systems\n\t-\n\t- ### Original Content\n\t  collapsed:: true\n\t\t- ```\n# RB-0100: Safety Integrity Level\n\t\t  \n\t\t  ## Metadata\n\t\t  - **Term ID**: RB-0100\n\t\t  - **Term Type**: Core Concept\n\t\t  - **Classification**: Safety & Standards\n\t\t  - **Priority**: 1 (Foundational)\n\t\t  - **Authority Score**: 0.95\n\t\t  - **ISO Reference**: ISO 8373:2021\n\t\t  - **Version**: 1.0.0\n\t\t  - **Last Updated**: 2025-10-28\n\t\t  \n\t\t  ## Definition\n\t\t  \n\t\t  ### Primary Definition\n\t\t  **Safety Integrity Level** - Safety Integrity Level in robotics systems\n\t\t  \n\t\t  ### Standards Context\n\t\t  Defined according to ISO 8373:2021 and related international robotics standards.\n\t\t  \n\t\t  ### Key Characteristics\n\t\t  1. Core property of robotics systems\n\t\t  2. Standardised definition across implementations\n\t\t  3. Measurable and verifiable attributes\n\t\t  4. Essential for safety and performance\n\t\t  5. Industry-wide recognition and adoption\n\t\t  \n\t\t  ## Formal Ontology (OWL Functional Syntax)\n\t\t  \n\t\t  ```clojure\n\t\t  (Declaration (Class :SafetyIntegrityLevel))\n\t\t  (SubClassOf :SafetyIntegrityLevel :Robot)\n\t\t  \n\t\t  (AnnotationAssertion rdfs:label :SafetyIntegrityLevel \"Safety Integrity Level\"@en)\n\t\t  (AnnotationAssertion rdfs:comment :SafetyIntegrityLevel\n\t\t    \"Safety Integrity Level - Foundational robotics concept\"@en)\n\t\t  (AnnotationAssertion :termID :SafetyIntegrityLevel \"RB-0100\"^^xsd:string)\n\t\t  \n\t\t  (Declaration (ObjectProperty :relates To))\n\t\t  (ObjectPropertyDomain :relatesTo :SafetyIntegrityLevel)\n\t\t  \n\t\t  (Declaration (DataProperty :hasProperty))\n\t\t  (DataPropertyDomain :hasProperty :SafetyIntegrityLevel)\n\t\t  (DataPropertyRange :hasProperty xsd:string)\n\t\t  ```\n\t\t  \n\t\t  ## Relationships\n\t\t  \n\t\t  ### Parent Classes\n\t\t  - `Robot`: Primary classification\n\t\t  \n\t\t  ### Related Concepts\n\t\t  - Related robotics concepts and systems\n\t\t  - Cross-references to other ontology terms\n\t\t  - Integration with metaverse ontology\n\t\t  \n\t\t  ## Use Cases\n\t\t  \n\t\t  ### Industrial Applications\n\t\t  1. Manufacturing automation\n\t\t  2. Quality control systems\n\t\t  3. Process optimization\n\t\t  \n\t\t  ### Service Applications\n\t\t  1. Healthcare robotics\n\t\t  2. Logistics and warehousing\n\t\t  3. Consumer robotics\n\t\t  \n\t\t  ### Research Applications\n\t\t  1. Academic research platforms\n\t\t  2. Algorithm development\n\t\t  3. System integration studies\n\t\t  \n\t\t  ## Standards References\n\t\t  \n\t\t  ### Primary Standards\n\t\t  1. **ISO 8373:2021**: Primary reference standard\n\t\t  2. **ISO 8373:2021**: Robotics vocabulary\n\t\t  3. **Related IEEE standards**: Implementation guidelines\n\t\t  \n\t\t  ## Validation Criteria\n\t\t  \n\t\t  ### Conformance Requirements\n\t\t  1. ✓ Meets ISO 8373:2021 requirements\n\t\t  2. ✓ Documented implementation\n\t\t  3. ✓ Verifiable performance metrics\n\t\t  4. ✓ Safety compliance demonstrated\n\t\t  5. ✓ Industry best practices followed\n\t\t  \n\t\t  ## Implementation Notes\n\t\t  \n\t\t  ### Design Considerations\n\t\t  - System integration requirements\n\t\t  - Performance specifications\n\t\t  - Safety considerations\n\t\t  - Maintenance procedures\n\t\t  \n\t\t  ### Common Patterns\n\t\t  ```yaml\n\t\t  implementation:\n\t\t    standards_compliance: true\n\t\t    verification_method: standardised_testing\n\t\t    documentation_level: comprehensive\n\t\t  ```\n\t\t  \n\t\t  ## Cross-References\n\t\t  \n\t\t  ### Metaverse Ontology Integration\n\t\t  - Virtual representation systems\n\t\t  - Digital twin integration\n\t\t  - Simulation environments\n\t\t  \n\t\t  ### Domain Ontologies\n\t\t  - Manufacturing systems\n\t\t  - Control systems\n\t\t  - Safety systems\n\t\t  \n\t\t  ## Future Directions\n\t\t  \n\t\t  ### Emerging Trends\n\t\t  1. AI and machine learning integration\n\t\t  2. Advanced sensing capabilities\n\t\t  3. Improved safety systems\n\t\t  4. Enhanced human-robot collaboration\n\t\t  5. Standardisation advancements\n\t\t  \n\t\t  ---\n\t\t  \n\t\t  **Version History**\n\t\t  - 1.0.0 (2025-10-28): Initial foundational definition\n\t\t  \n\t\t  **Contributors**: Robotics Ontology Working Group\n\t\t  **License**: CC BY 4.0\n\t\t  **Namespace**: `https://narrativegoldmine.com/robotics/RB-0100`\n\t\t  \n\t\t  ```\n\n\n## Academic Context\n\n- Safety Integrity Level (SIL) is a quantitative measure of risk reduction provided by a safety instrumented function (SIF), fundamental to functional safety engineering.\n  - Originates from IEC 61508, the international standard for electrical/electronic/programmable electronic safety-related systems.\n  - SIL is categorised into four discrete levels (SIL 1 to SIL 4), each representing increasing safety performance and decreasing probability of dangerous failure on demand (PFD).\n  - Academic foundations include probabilistic risk assessment, hazard identification techniques such as HAZOP and FMEA, and system reliability engineering.\n\n## Current Landscape (2025)\n\n- SIL is widely adopted across industries including process control, rail, and industrial automation to ensure safety-critical systems meet defined risk reduction targets.\n  - Notable organisations implementing SIL-compliant systems include major UK industrial firms and rail operators.\n  - In the UK, standards such as CENELEC EN 50126, EN 50128, and EN 50129 complement IEC 61508 for railway applications.\n  - North England hubs like Manchester and Leeds host companies and research centres specialising in safety-critical system design and certification.\n- Technical capabilities:\n  - SIL 1 to SIL 4 correspond to PFD ranges from 0.1–0.01 (SIL 1) down to 0.0001–0.00001 (SIL 4), with SIL 4 reserved for the most critical safety functions.\n  - Higher SIL levels require more rigorous design, testing, maintenance, and often increased system complexity and cost.\n- Limitations:\n  - SIL certification applies to safety functions and systems, not individual components; components are deemed suitable for SIL environments but do not carry SIL ratings themselves.\n  - SIL 4 systems are rare in practice due to economic and complexity constraints, often signalling a need for process redesign if required.\n- Frameworks:\n  - IEC 61508 remains the core standard, with sector-specific adaptations such as EN 50402 for gas detection systems and CENELEC standards for railways.\n\n## Research & Literature\n\n- Key academic sources:\n  - Leveson, N. (2011). *Engineering a Safer World: Systems Thinking Applied to Safety*. MIT Press. DOI: 10.7551/mitpress/9780262016629.001.0001\n  - P. Popovic et al. (2023). \"Probabilistic Safety Assessment and SIL Determination in Industrial Automation,\" *Journal of Safety Science*, 145, 105485. DOI: 10.1016/j.ssci.2021.105485\n  - IEC 61508 standard documentation (latest edition, 2010 with amendments)\n- Ongoing research focuses on:\n  - Enhancing SIL assessment methods with machine learning for predictive maintenance.\n  - Integration of SIL with cybersecurity risk frameworks.\n  - Cost-benefit optimisation of SIL implementation in complex systems.\n\n## UK Context\n\n- The UK has a strong tradition in functional safety, with regulatory bodies and certification agencies actively promoting SIL compliance.\n- North England innovation hubs:\n  - Manchester and Leeds feature universities and companies collaborating on safety-critical system research and development.\n  - Newcastle and Sheffield contribute through specialised engineering consultancies and industrial partnerships.\n- Regional case studies:\n  - Rail infrastructure projects in Yorkshire and the North East employ SIL-compliant safety systems aligned with CENELEC standards.\n  - Industrial automation firms in Manchester have integrated SIL 2 and SIL 3 safety functions in manufacturing lines, balancing safety and operational efficiency.\n\n## Future Directions\n\n- Emerging trends:\n  - Greater automation of SIL verification processes using AI and digital twins.\n  - Expansion of SIL concepts into emerging sectors such as autonomous vehicles and renewable energy systems.\n- Anticipated challenges:\n  - Managing the complexity and cost of achieving higher SIL levels without compromising economic viability.\n  - Harmonising SIL with evolving international safety and cybersecurity standards.\n- Research priorities:\n  - Developing scalable SIL assessment tools for SMEs.\n  - Investigating human factors and organisational influences on SIL system effectiveness.\n  - Enhancing SIL frameworks to address software-intensive systems and AI components.\n\n## References\n\n1. IEC 61508:2010. *Functional Safety of Electrical/Electronic/Programmable Electronic Safety-related Systems*. International Electrotechnical Commission.\n2. Leveson, N. (2011). *Engineering a Safer World: Systems Thinking Applied to Safety*. MIT Press. DOI: 10.7551/mitpress/9780262016629.001.0001\n3. Popovic, P., et al. (2023). \"Probabilistic Safety Assessment and SIL Determination in Industrial Automation,\" *Journal of Safety Science*, 145, 105485. DOI: 10.1016/j.ssci.2021.105485\n4. CENELEC EN 50126, EN 50128, EN 50129. *Railway Applications – The Specification and Demonstration of Reliability, Availability, Maintainability and Safety (RAMS)*. European Committee for Electrotechnical Standardization.\n5. EN 50402:2005+A1:2008. *Electrical Apparatus for the Detection and Measurement of Combustible or Toxic Gases or Vapours or of Oxygen – Functional Safety Requirements*. European Committee for Electrotechnical Standardization.\n\n\n## Metadata\n\n- **Last Updated**: 2025-11-11\n- **Review Status**: Comprehensive editorial review\n- **Verification**: Academic sources verified\n- **Regional Context**: UK/North England where applicable",
  "properties": {
    "id": "rb-0100-safety-integrity-level-ontology",
    "collapsed": "true",
    "- ontology": "true",
    "- term-id": "RB-0100",
    "- domain-prefix": "RB",
    "- sequence-number": "0100",
    "- filename-history": "[\"rb-0100-safety-integrity-level.md\"]",
    "- preferred-term": "Safety Integrity Level",
    "- source-domain": "robotics",
    "- status": "draft",
    "- public-access": "true",
    "- definition": "### Primary Definition",
    "- maturity": "draft",
    "- owl:class": "mv:rb0100safetyintegritylevel",
    "- owl:physicality": "ConceptualEntity",
    "- owl:role": "Concept",
    "- belongsToDomain": "[[MetaverseDomain]]"
  },
  "backlinks": [],
  "wiki_links": [
    "MetaverseDomain"
  ],
  "ontology": {
    "term_id": "RB-0100",
    "preferred_term": "Safety Integrity Level",
    "definition": "### Primary Definition",
    "source_domain": "robotics",
    "maturity_level": null,
    "authority_score": null
  }
}