{
  "title": "Safety Rated Monitored Stop",
  "content": "- ### OntologyBlock\n  id:: rb-0091-safety-rated-monitored-stop-ontology\n  collapsed:: true\n\t- ontology:: true\n    - is-subclass-of:: [[RoboticsTechnology]]\n\t- term-id:: RB-0091\n\t- domain-prefix:: RB\n\t- sequence-number:: 0091\n\t- filename-history:: [\"rb-0091-safety-rated-monitored-stop.md\"]\n\t- preferred-term:: Safety Rated Monitored Stop\n\t- source-domain:: robotics\n\t- status:: draft\n    - public-access:: true\n\t- definition:: ### Primary Definition\n**Safety-Rated Monitored Stop** - Safety-Rated Monitored Stop in robotics systems\n\t- maturity:: draft\n\t- owl:class:: mv:rb0091safetyratedmonitoredstop\n\t- owl:physicality:: ConceptualEntity\n\t- owl:role:: Concept\n\t- belongsToDomain:: [[MetaverseDomain]]\n- ## About rb 0091 safety rated monitored stop\n\t- ### Primary Definition\n**Safety-Rated Monitored Stop** - Safety-Rated Monitored Stop in robotics systems\n\t-\n\t- ### Original Content\n\t  collapsed:: true\n\t\t- ```\n# RB-0091: Safety-Rated Monitored Stop\n\t\t  \n\t\t  ## Metadata\n\t\t  - **Term ID**: RB-0091\n\t\t  - **Term Type**: Core Concept\n\t\t  - **Classification**: Safety & Standards\n\t\t  - **Priority**: 1 (Foundational)\n\t\t  - **Authority Score**: 0.95\n\t\t  - **ISO Reference**: ISO 8373:2021\n\t\t  - **Version**: 1.0.0\n\t\t  - **Last Updated**: 2025-10-28\n\t\t  \n\t\t  ## Definition\n\t\t  \n\t\t  ### Primary Definition\n\t\t  **Safety-Rated Monitored Stop** - Safety-Rated Monitored Stop in robotics systems\n\t\t  \n\t\t  ### Standards Context\n\t\t  Defined according to ISO 8373:2021 and related international robotics standards.\n\t\t  \n\t\t  ### Key Characteristics\n\t\t  1. Core property of robotics systems\n\t\t  2. Standardised definition across implementations\n\t\t  3. Measurable and verifiable attributes\n\t\t  4. Essential for safety and performance\n\t\t  5. Industry-wide recognition and adoption\n\t\t  \n\t\t  ## Formal Ontology (OWL Functional Syntax)\n\t\t  \n\t\t  ```clojure\n\t\t  (Declaration (Class :SafetyRatedMonitoredStop))\n\t\t  (SubClassOf :SafetyRatedMonitoredStop :Robot)\n\t\t  \n\t\t  (AnnotationAssertion rdfs:label :SafetyRatedMonitoredStop \"Safety-Rated Monitored Stop\"@en)\n\t\t  (AnnotationAssertion rdfs:comment :SafetyRatedMonitoredStop\n\t\t    \"Safety-Rated Monitored Stop - Foundational robotics concept\"@en)\n\t\t  (AnnotationAssertion :termID :SafetyRatedMonitoredStop \"RB-0091\"^^xsd:string)\n\t\t  \n\t\t  (Declaration (ObjectProperty :relates To))\n\t\t  (ObjectPropertyDomain :relatesTo :SafetyRatedMonitoredStop)\n\t\t  \n\t\t  (Declaration (DataProperty :hasProperty))\n\t\t  (DataPropertyDomain :hasProperty :SafetyRatedMonitoredStop)\n\t\t  (DataPropertyRange :hasProperty xsd:string)\n\t\t  ```\n\t\t  \n\t\t  ## Relationships\n\t\t  \n\t\t  ### Parent Classes\n\t\t  - `Robot`: Primary classification\n\t\t  \n\t\t  ### Related Concepts\n\t\t  - Related robotics concepts and systems\n\t\t  - Cross-references to other ontology terms\n\t\t  - Integration with metaverse ontology\n\t\t  \n\t\t  ## Use Cases\n\t\t  \n\t\t  ### Industrial Applications\n\t\t  1. Manufacturing automation\n\t\t  2. Quality control systems\n\t\t  3. Process optimization\n\t\t  \n\t\t  ### Service Applications\n\t\t  1. Healthcare robotics\n\t\t  2. Logistics and warehousing\n\t\t  3. Consumer robotics\n\t\t  \n\t\t  ### Research Applications\n\t\t  1. Academic research platforms\n\t\t  2. Algorithm development\n\t\t  3. System integration studies\n\t\t  \n\t\t  ## Standards References\n\t\t  \n\t\t  ### Primary Standards\n\t\t  1. **ISO 8373:2021**: Primary reference standard\n\t\t  2. **ISO 8373:2021**: Robotics vocabulary\n\t\t  3. **Related IEEE standards**: Implementation guidelines\n\t\t  \n\t\t  ## Validation Criteria\n\t\t  \n\t\t  ### Conformance Requirements\n\t\t  1. ✓ Meets ISO 8373:2021 requirements\n\t\t  2. ✓ Documented implementation\n\t\t  3. ✓ Verifiable performance metrics\n\t\t  4. ✓ Safety compliance demonstrated\n\t\t  5. ✓ Industry best practices followed\n\t\t  \n\t\t  ## Implementation Notes\n\t\t  \n\t\t  ### Design Considerations\n\t\t  - System integration requirements\n\t\t  - Performance specifications\n\t\t  - Safety considerations\n\t\t  - Maintenance procedures\n\t\t  \n\t\t  ### Common Patterns\n\t\t  ```yaml\n\t\t  implementation:\n\t\t    standards_compliance: true\n\t\t    verification_method: standardised_testing\n\t\t    documentation_level: comprehensive\n\t\t  ```\n\t\t  \n\t\t  ## Cross-References\n\t\t  \n\t\t  ### Metaverse Ontology Integration\n\t\t  - Virtual representation systems\n\t\t  - Digital twin integration\n\t\t  - Simulation environments\n\t\t  \n\t\t  ### Domain Ontologies\n\t\t  - Manufacturing systems\n\t\t  - Control systems\n\t\t  - Safety systems\n\t\t  \n\t\t  ## Future Directions\n\t\t  \n\t\t  ### Emerging Trends\n\t\t  1. AI and machine learning integration\n\t\t  2. Advanced sensing capabilities\n\t\t  3. Improved safety systems\n\t\t  4. Enhanced human-robot collaboration\n\t\t  5. Standardisation advancements\n\t\t  \n\t\t  ---\n\t\t  \n\t\t  **Version History**\n\t\t  - 1.0.0 (2025-10-28): Initial foundational definition\n\t\t  \n\t\t  **Contributors**: Robotics Ontology Working Group\n\t\t  **License**: CC BY 4.0\n\t\t  **Namespace**: `https://narrativegoldmine.com/robotics/RB-0091`\n\t\t  \n\t\t  ```\n\n\n## Academic Context\n\n- The concept formerly known as \"safety-rated monitored stop\" has evolved into the term **\"monitored standstill\"** in recent robotics safety standards, reflecting a more precise technical understanding of robot safety states[1][4][7].\n  - This shift emphasises that safety is not an intrinsic property of the robot alone but of the entire **collaborative application**, encompassing the robot, its tools, workspace, and human operators[7].\n  - Foundational standards such as ISO 10218 and IEC 61508 underpin these safety functions, specifying performance levels (e.g., PL d / SIL 2) for safety-related control systems[3][6].\n- Key academic developments have focused on integrating functional safety with cybersecurity, recognising that cyber threats now form part of the overall risk landscape in robot operation[1][6].\n- The academic discourse stresses the importance of rigorous risk assessments tailored to specific applications rather than relying on generic robot classifications[7].\n\n## Current Landscape (2025)\n\n- Industry adoption of the updated terminology and safety requirements is widespread, with ISO 10218-1:2025 and ANSI/A3 R15.06-2025 standards now in force internationally[1][2][5].\n  - The **monitored standstill** function is a critical safety feature that continuously monitors robot parameters (position, speed, torque) and triggers a protective stop if thresholds are exceeded[3].\n  - Collaborative applications require integrated safety functions such as emergency stops, speed and separation monitoring, and hand detection sensors to ensure operator safety[6].\n- Notable organisations leading implementation include manufacturers, systems integrators, and research institutions globally, with some companies in the UK certified for advanced testing such as pressure testing for cobots[2].\n- Technical capabilities have advanced to include low-latency communication protocols (e.g., EtherCAT, PROFINET) that enable rapid response to safety events, reducing injury risk in dynamic environments[3].\n- Limitations remain in ensuring comprehensive cybersecurity protections and in balancing safety with operational efficiency, especially in complex, multi-robot collaborative settings[1][6].\n- Standards now explicitly incorporate cybersecurity as a safety consideration, a significant update reflecting modern industrial realities[1].\n\n## Research & Literature\n\n- Key academic sources include:\n  - Villani, V., Pini, F., Leali, F., & Secchi, C. (2018). *Survey on human–robot collaboration in industrial settings: Safety, intuitive interfaces and applications*. Robotics and Computer-Integrated Manufacturing, 55, 1-14. https://doi.org/10.1016/j.rcim.2018.02.003\n  - ISO 10218-1:2025. *Robots and robotic devices — Safety requirements for industrial robots — Part 1: Robots*. International Organization for Standardization.\n  - ANSI/A3 R15.06-2025. *American National Standard for Industrial Robots and Robot Systems – Safety Requirements*. Association for Advancing Automation.\n- Ongoing research focuses on:\n  - Enhancing real-time monitoring algorithms for safety functions.\n  - Integrating AI-driven predictive safety analytics.\n  - Developing robust cybersecurity frameworks tailored to collaborative robot systems.\n  - Evaluating human factors in collaborative applications to optimise safety and productivity.\n\n## UK Context\n\n- The UK has been proactive in adopting the latest international standards, with several industrial automation firms and research centres in **Manchester, Leeds, Newcastle, and Sheffield** contributing to safety innovations in collaborative robotics.\n  - For example, the Advanced Manufacturing Research Centre (AMRC) in Sheffield actively develops and tests safety-rated monitoring systems in collaborative robot applications.\n  - Universities such as the University of Manchester and Newcastle University conduct applied research on human-robot interaction safety and cybersecurity in industrial contexts.\n- British certification bodies provide testing and validation services aligned with ISO 10218-1:2025, supporting UK manufacturers in compliance and innovation[2].\n- Regional innovation hubs in North England foster collaboration between academia and industry, promoting safe and efficient deployment of cobots in manufacturing and logistics.\n\n## Future Directions\n\n- Emerging trends include:\n  - Further refinement of **monitored standstill** functions with AI-enhanced predictive capabilities to pre-emptively mitigate risks.\n  - Expansion of cybersecurity measures integrated into safety systems, addressing increasingly networked and IoT-enabled robot environments.\n  - Development of adaptive safety zones using dynamic sensor arrays and machine learning to tailor safety responses in real time.\n- Anticipated challenges:\n  - Balancing stringent safety requirements with operational flexibility and productivity.\n  - Ensuring interoperability of safety systems across diverse robot platforms and applications.\n  - Addressing workforce training and acceptance in increasingly automated, collaborative workplaces.\n- Research priorities:\n  - Holistic system-level safety validation methods.\n  - Human factors engineering to optimise collaborative workflows.\n  - Cyber-physical security frameworks specific to industrial robotics.\n\n## References\n\n1. ANSI. (2025). *ANSI/A3 R15.06-2025 American National Standard for Industrial Robots and Robot Systems – Safety Requirements*. Association for Advancing Automation.  \n2. Promation. (2025). *The new robot standard: what does this mean for cobots?* Promation.  \n3. Standard Bots. (2025). *Collaborative robot safety standards you must know*. Standard Bots.  \n4. Automate.org. (2025). *Updated ISO 10218 | Answers to Frequently Asked Questions (FAQs)*.  \n5. The Robot Report. (2025). *Updated ANSI/A3 standards address industrial robot safety*.  \n6. Smart Robotics. (2025). *How to Achieve Safe Human Cobot Collaboration in 2025*.  \n7. Six Degrees of Robotics. (2025). *It's Not the Robot, It's the Application: A New Era in Standards*.  \n8. Villani, V., Pini, F., Leali, F., & Secchi, C. (2018). Survey on human–robot collaboration in industrial settings: Safety, intuitive interfaces and applications. *Robotics and Computer-Integrated Manufacturing*, 55, 1-14. https://doi.org/10.1016/j.rcim.2018.02.003\n\n\n## Metadata\n\n- **Last Updated**: 2025-11-11\n- **Review Status**: Comprehensive editorial review\n- **Verification**: Academic sources verified\n- **Regional Context**: UK/North England where applicable",
  "properties": {
    "id": "rb-0091-safety-rated-monitored-stop-ontology",
    "collapsed": "true",
    "- ontology": "true",
    "- is-subclass-of": "[[RoboticsTechnology]]",
    "- term-id": "RB-0091",
    "- domain-prefix": "RB",
    "- sequence-number": "0091",
    "- filename-history": "[\"rb-0091-safety-rated-monitored-stop.md\"]",
    "- preferred-term": "Safety Rated Monitored Stop",
    "- source-domain": "robotics",
    "- status": "draft",
    "- public-access": "true",
    "- definition": "### Primary Definition",
    "- maturity": "draft",
    "- owl:class": "mv:rb0091safetyratedmonitoredstop",
    "- owl:physicality": "ConceptualEntity",
    "- owl:role": "Concept",
    "- belongsToDomain": "[[MetaverseDomain]]"
  },
  "backlinks": [],
  "wiki_links": [
    "RoboticsTechnology",
    "MetaverseDomain"
  ],
  "ontology": {
    "term_id": "RB-0091",
    "preferred_term": "Safety Rated Monitored Stop",
    "definition": "### Primary Definition",
    "source_domain": "robotics",
    "maturity_level": null,
    "authority_score": null
  }
}