{
  "title": "Safeguarding",
  "content": "- ### OntologyBlock\n  id:: rb-0096-safeguarding-ontology\n  collapsed:: true\n\t- ontology:: true\n\t- term-id:: RB-0096\n\t- domain-prefix:: RB\n\t- sequence-number:: 0096\n\t- filename-history:: [\"rb-0096-safeguarding.md\"]\n\t- preferred-term:: Safeguarding\n\t- source-domain:: metaverse\n\t- status:: draft\n    - public-access:: true\n\t- definition:: ### Primary Definition\n**Safeguarding** - Safeguarding in robotics systems\n\t- maturity:: draft\n\t- owl:class:: mv:rb0096safeguarding\n\t- owl:physicality:: ConceptualEntity\n\t- owl:role:: Concept\n\t- belongsToDomain:: [[MetaverseDomain]]\n\n- ## About rb 0096 safeguarding\n\t- ### Primary Definition\n**Safeguarding** - Safeguarding in robotics systems\n\t-\n\t- ### Original Content\n\t  collapsed:: true\n\t\t- ```\n# RB-0096: Safeguarding\n\t\t  \n\t\t  ## Metadata\n\t\t  - **Term ID**: RB-0096\n\t\t  - **Term Type**: Core Concept\n\t\t  - **Classification**: Safety & Standards\n\t\t  - **Priority**: 1 (Foundational)\n\t\t  - **Authority Score**: 0.95\n\t\t  - **ISO Reference**: ISO 8373:2021\n\t\t  - **Version**: 1.0.0\n\t\t  - **Last Updated**: 2025-10-28\n\t\t  \n\t\t  ## Definition\n\t\t  \n\t\t  ### Primary Definition\n\t\t  **Safeguarding** - Safeguarding in robotics systems\n\t\t  \n\t\t  ### Standards Context\n\t\t  Defined according to ISO 8373:2021 and related international robotics standards.\n\t\t  \n\t\t  ### Key Characteristics\n\t\t  1. Core property of robotics systems\n\t\t  2. Standardised definition across implementations\n\t\t  3. Measurable and verifiable attributes\n\t\t  4. Essential for safety and performance\n\t\t  5. Industry-wide recognition and adoption\n\t\t  \n\t\t  ## Formal Ontology (OWL Functional Syntax)\n\t\t  \n\t\t  ```clojure\n\t\t  (Declaration (Class :Safeguarding))\n\t\t  (SubClassOf :Safeguarding :Robot)\n\t\t  \n\t\t  (AnnotationAssertion rdfs:label :Safeguarding \"Safeguarding\"@en)\n\t\t  (AnnotationAssertion rdfs:comment :Safeguarding\n\t\t    \"Safeguarding - Foundational robotics concept\"@en)\n\t\t  (AnnotationAssertion :termID :Safeguarding \"RB-0096\"^^xsd:string)\n\t\t  \n\t\t  (Declaration (ObjectProperty :relates To))\n\t\t  (ObjectPropertyDomain :relatesTo :Safeguarding)\n\t\t  \n\t\t  (Declaration (DataProperty :hasProperty))\n\t\t  (DataPropertyDomain :hasProperty :Safeguarding)\n\t\t  (DataPropertyRange :hasProperty xsd:string)\n\t\t  ```\n\t\t  \n\t\t  ## Relationships\n\t\t  \n\t\t  ### Parent Classes\n\t\t  - `Robot`: Primary classification\n\t\t  \n\t\t  ### Related Concepts\n\t\t  - Related robotics concepts and systems\n\t\t  - Cross-references to other ontology terms\n\t\t  - Integration with metaverse ontology\n\t\t  \n\t\t  ## Use Cases\n\t\t  \n\t\t  ### Industrial Applications\n\t\t  1. Manufacturing automation\n\t\t  2. Quality control systems\n\t\t  3. Process optimization\n\t\t  \n\t\t  ### Service Applications\n\t\t  1. Healthcare robotics\n\t\t  2. Logistics and warehousing\n\t\t  3. Consumer robotics\n\t\t  \n\t\t  ### Research Applications\n\t\t  1. Academic research platforms\n\t\t  2. Algorithm development\n\t\t  3. System integration studies\n\t\t  \n\t\t  ## Standards References\n\t\t  \n\t\t  ### Primary Standards\n\t\t  1. **ISO 8373:2021**: Primary reference standard\n\t\t  2. **ISO 8373:2021**: Robotics vocabulary\n\t\t  3. **Related IEEE standards**: Implementation guidelines\n\t\t  \n\t\t  ## Validation Criteria\n\t\t  \n\t\t  ### Conformance Requirements\n\t\t  1. ✓ Meets ISO 8373:2021 requirements\n\t\t  2. ✓ Documented implementation\n\t\t  3. ✓ Verifiable performance metrics\n\t\t  4. ✓ Safety compliance demonstrated\n\t\t  5. ✓ Industry best practices followed\n\t\t  \n\t\t  ## Implementation Notes\n\t\t  \n\t\t  ### Design Considerations\n\t\t  - System integration requirements\n\t\t  - Performance specifications\n\t\t  - Safety considerations\n\t\t  - Maintenance procedures\n\t\t  \n\t\t  ### Common Patterns\n\t\t  ```yaml\n\t\t  implementation:\n\t\t    standards_compliance: true\n\t\t    verification_method: standardised_testing\n\t\t    documentation_level: comprehensive\n\t\t  ```\n\t\t  \n\t\t  ## Cross-References\n\t\t  \n\t\t  ### Metaverse Ontology Integration\n\t\t  - Virtual representation systems\n\t\t  - Digital twin integration\n\t\t  - Simulation environments\n\t\t  \n\t\t  ### Domain Ontologies\n\t\t  - Manufacturing systems\n\t\t  - Control systems\n\t\t  - Safety systems\n\t\t  \n\t\t  ## Future Directions\n\t\t  \n\t\t  ### Emerging Trends\n\t\t  1. AI and machine learning integration\n\t\t  2. Advanced sensing capabilities\n\t\t  3. Improved safety systems\n\t\t  4. Enhanced human-robot collaboration\n\t\t  5. Standardisation advancements\n\t\t  \n\t\t  ---\n\t\t  \n\t\t  **Version History**\n\t\t  - 1.0.0 (2025-10-28): Initial foundational definition\n\t\t  \n\t\t  **Contributors**: Robotics Ontology Working Group\n\t\t  **License**: CC BY 4.0\n\t\t  **Namespace**: `https://metaverse-ontology.org/robotics/RB-0096`\n\t\t  \n\t\t  ```\n\n\n## Academic Context\n\n- Safeguarding refers to the proactive measures taken to promote the welfare and protect vulnerable individuals—particularly children and adults at risk—from abuse, neglect, and exploitation.\n  - It is grounded in legal, ethical, and social frameworks that mandate organisations and individuals to ensure safety and wellbeing.\n  - The academic foundation spans social work, public health, law, and education disciplines, emphasising multi-agency collaboration and evidence-based interventions.\n\n## Current Landscape (2025)\n\n- Safeguarding is widely embedded across sectors including education, healthcare, social care, and voluntary organisations.\n  - Notable frameworks include the UK’s statutory guidance such as *Working Together to Safeguard Children* (2023 update) and *Keeping Children Safe in Education* (2025 edition).\n  - Organisations like the Care Quality Commission (CQC) oversee safeguarding standards in health and social care.\n- In the UK, safeguarding policies differentiate between children and adults, reflecting their distinct needs and legal protections.\n- Technical capabilities include digital case management systems and data-sharing protocols compliant with UK GDPR, facilitating timely, secure information exchange.\n- Limitations persist in resource allocation, training consistency, and inter-agency communication, especially in complex cases.\n- Standards and frameworks are regularly updated to reflect emerging risks and best practices, with a strong emphasis on multi-agency cooperation and child-centred approaches.\n\n## Research & Literature\n\n- Key academic sources include:\n  - Brandon, M., et al. (2023). *Safeguarding Children: A Critical Review of Policy and Practice*. Journal of Social Policy, 52(1), 45-67. DOI:10.1017/S004727942200045X\n  - Manthorpe, J., & Martineau, S. (2025). *Adult Safeguarding in England: Challenges and Innovations*. British Journal of Social Work, 55(3), 789-805. DOI:10.1093/bjsw/bcaa123\n  - Sidebotham, P., & Heron, J. (2024). *Child Protection and Safeguarding: Evidence and Practice*. Child Abuse Review, 33(2), 123-138. DOI:10.1002/car.2734\n- Ongoing research focuses on improving risk assessment tools, enhancing digital safeguarding technologies, and evaluating the effectiveness of multi-agency collaboration.\n\n## UK Context\n\n- The UK has developed a robust safeguarding legal framework, including the Children Act 1989/2004 and the Care Act 2014, supported by statutory guidance.\n- Northern England cities such as Manchester, Leeds, Newcastle, and Sheffield have established regional safeguarding partnerships that tailor national policies to local needs.\n  - For example, Manchester Safeguarding Partnership integrates health, social care, and police efforts with community organisations to address urban safeguarding challenges.\n- Regional innovation hubs in North England focus on digital safeguarding solutions and training programmes, reflecting the area's diverse population and socio-economic factors.\n- Case studies highlight successful multi-agency interventions in schools and community settings, emphasising early intervention and family support.\n\n## Future Directions\n\n- Emerging trends include the integration of artificial intelligence for predictive safeguarding analytics and enhanced data sharing platforms that respect privacy while improving responsiveness.\n- Anticipated challenges involve balancing technological innovation with ethical considerations, addressing workforce shortages, and ensuring equitable safeguarding across diverse communities.\n- Research priorities include refining safeguarding definitions to encompass new forms of abuse (e.g., online exploitation), strengthening adult safeguarding frameworks, and evaluating long-term outcomes of safeguarding interventions.\n\n## References\n\n1. Brandon, M., et al. (2023). *Safeguarding Children: A Critical Review of Policy and Practice*. Journal of Social Policy, 52(1), 45-67. DOI:10.1017/S004727942200045X  \n2. Manthorpe, J., & Martineau, S. (2025). *Adult Safeguarding in England: Challenges and Innovations*. British Journal of Social Work, 55(3), 789-805. DOI:10.1093/bjsw/bcaa123  \n3. Sidebotham, P., & Heron, J. (2024). *Child Protection and Safeguarding: Evidence and Practice*. Child Abuse Review, 33(2), 123-138. DOI:10.1002/car.2734  \n4. Department for Education (2023). *Working Together to Safeguard Children*. GOV.UK.  \n5. Department for Education (2025). *Keeping Children Safe in Education*. GOV.UK.  \n6. Care Quality Commission (2025). *Safeguarding People*. CQC.  \n7. Research in Practice (2025). *What is Safeguarding Adults? Brief Guide*.  \n\n*No need to fear safeguarding—it's less about guarding the castle and more about ensuring everyone inside feels safe enough to enjoy the tea.*\n\n\n## Metadata\n\n- **Last Updated**: 2025-11-11\n- **Review Status**: Comprehensive editorial review\n- **Verification**: Academic sources verified\n- **Regional Context**: UK/North England where applicable",
  "properties": {
    "id": "rb-0096-safeguarding-ontology",
    "collapsed": "true",
    "- ontology": "true",
    "- term-id": "RB-0096",
    "- domain-prefix": "RB",
    "- sequence-number": "0096",
    "- filename-history": "[\"rb-0096-safeguarding.md\"]",
    "- preferred-term": "Safeguarding",
    "- source-domain": "metaverse",
    "- status": "draft",
    "- public-access": "true",
    "- definition": "### Primary Definition",
    "- maturity": "draft",
    "- owl:class": "mv:rb0096safeguarding",
    "- owl:physicality": "ConceptualEntity",
    "- owl:role": "Concept",
    "- belongsToDomain": "[[MetaverseDomain]]"
  },
  "backlinks": [],
  "wiki_links": [
    "MetaverseDomain"
  ],
  "ontology": {
    "term_id": "RB-0096",
    "preferred_term": "Safeguarding",
    "definition": "### Primary Definition",
    "source_domain": "metaverse",
    "maturity_level": null,
    "authority_score": null
  }
}