{
  "title": "Salt",
  "content": "- ### OntologyBlock\n  id:: salt-ontology\n  collapsed:: true\n\n  - **Identification**\n\n    - domain-prefix:: BC\n\n    - sequence-number:: 0049\n\n    - filename-history:: [\"BC-0049-salt.md\"]\n    - public-access:: true\n    - ontology:: true\n    - term-id:: BC-0049\n    - preferred-term:: Salt\n    - source-domain:: blockchain\n    - status:: complete\n    - version:: 1.0.0\n    - last-updated:: 2025-10-28\n\n  - **Definition**\n    - definition:: Random data for hash uniqueness within blockchain systems, providing essential functionality for distributed ledger technology operations and properties.\n    - maturity:: mature\n    - source:: [[ISO/IEC 23257:2021]], [[IEEE 2418.1]], [[NIST NISTIR]]\n    - authority-score:: 0.95\n\n  - **Semantic Classification**\n    - owl:class:: bc:Salt\n    - owl:physicality:: VirtualEntity\n    - owl:role:: Object\n    - owl:inferred-class:: bc:VirtualObject\n    - belongsToDomain:: [[CryptographicDomain]]\n\t- blockchainRelevance:: High\n\t- lastValidated:: 2025-11-14\n    - implementedInLayer:: [[SecurityLayer]]\n\n  - #### Relationships\n    id:: salt-relationships\n    - is-subclass-of:: [[Blockchain Entity]], [[CryptographicPrimitive]]\n\n  - #### OWL Axioms\n    id:: salt-owl-axioms\n    collapsed:: true\n    - ```clojure\n      Prefix(:=<http://metaverse-ontology.org/blockchain#>)\nPrefix(owl:=<http://www.w3.org/2002/07/owl#>)\nPrefix(rdf:=<http://www.w3.org/1999/02/22-rdf-syntax-ns#>)\nPrefix(xml:=<http://www.w3.org/XML/1998/namespace>)\nPrefix(xsd:=<http://www.w3.org/2001/XMLSchema#>)\nPrefix(rdfs:=<http://www.w3.org/2000/01/rdf-schema#>)\nPrefix(dct:=<http://purl.org/dc/terms/>)\n\nOntology(<http://metaverse-ontology.org/blockchain/BC-0049>\n  Import(<http://metaverse-ontology.org/blockchain/core>)\n\n  ## Class Declaration\n  Declaration(Class(:Salt))\n\n  ## Subclass Relationships\n  SubClassOf(:Salt :CryptographicPrimitive)\n  SubClassOf(:Salt :BlockchainEntity)\n\n  ## Essential Properties\n  SubClassOf(:Salt\n    (ObjectSomeValuesFrom :partOf :Blockchain))\n\n  SubClassOf(:Salt\n    (ObjectSomeValuesFrom :hasProperty :Property))\n\n  ## Data Properties\n  DataPropertyAssertion(:hasIdentifier :Salt \"BC-0049\"^^xsd:string)\n  DataPropertyAssertion(:hasAuthorityScore :Salt \"1.0\"^^xsd:decimal)\n  DataPropertyAssertion(:isFoundational :Salt \"true\"^^xsd:boolean)\n\n  ## Object Properties\n  ObjectPropertyAssertion(:enablesFeature :Salt :BlockchainFeature)\n  ObjectPropertyAssertion(:relatesTo :Salt :RelatedConcept)\n\n  ## Annotations\n  AnnotationAssertion(rdfs:label :Salt \"Salt\"@en)\n  AnnotationAssertion(rdfs:comment :Salt\n    \"Random data for hash uniqueness\"@en)\n  AnnotationAssertion(dct:description :Salt\n    \"Foundational blockchain concept with formal ontological definition\"@en)\n  AnnotationAssertion(:termID :Salt \"BC-0049\")\n  AnnotationAssertion(:priority :Salt \"1\"^^xsd:integer)\n  AnnotationAssertion(:category :Salt \"cryptographic-foundations\"@en)\n)\n      ```\n\n- ## About Salt\n  id:: salt-about\n\n  - Random data for hash uniqueness within blockchain systems, providing essential functionality for distributed ledger technology operations and properties.\n  -\n  - ### Key Characteristics\n    id:: salt-characteristics\n    - 1. **Definitional Property**: Core defining characteristic\n    - 2. **Functional Property**: Operational behavior\n    - 3. **Structural Property**: Compositional elements\n    - 4. **Security Property**: Security guarantees provided\n    - 5. **Performance Property**: Efficiency considerations\n  -\n  - ### Technical Components\n    id:: salt-components\n    - **Implementation**: How concept is realized technically\n    - **Verification**: Methods for validating correctness\n    - **Interaction**: Relationships with other components\n    - **Constraints**: Technical limitations and requirements\n  -\n  - ### Use Cases\n    id:: salt-use-cases\n    - **1. Core Blockchain Operation**\n    - **Application**: Fundamental blockchain functionality\n    - **Example**: Practical implementation in major blockchains\n    - **Requirements**: Technical prerequisites\n    - **Benefits**: Value provided to blockchain systems\n  -\n  - ### Standards & References\n    id:: salt-standards\n    - [[ISO/IEC 23257:2021]] - Blockchain and distributed ledger technologies\n    - [[IEEE 2418.1]] - Blockchain and distributed ledger technologies\n    - [[NIST NISTIR]] - Blockchain and distributed ledger technologies\n  -\n\n- ## International money transfer networks\n\t- Transferring money from one financial jurisdiction to another is itself a global marketplace which has accreted over the entire course of human history. It’s far less useful here to discuss the mythos of salt and seashells as a mechanisms of international remittance andtaxation.[[gainsford2017salt; @goldberg2005famous]] Suffice it to saythat there are dozens, if not hundreds, of cross border payment companies who make their business from taking a percentage cut of an international money transfer. There are also hundreds if not thousands of banks who offer this service as part of their core business portfolio. This section looks at some of the major players, and theirmechanism, to contextualise the more recent shifts brought about bytechnology.\n\n- ## International money transfer networks\n\t- Transferring money from one financial jurisdiction to another is itself a global marketplace which has accreted over the entire course of human history. It’s far less useful here to discuss the mythos of salt and seashells as a mechanisms of international remittance andtaxation.[[gainsford2017salt; @goldberg2005famous]] Suffice it to saythat there are dozens, if not hundreds, of cross border payment companies who make their business from taking a percentage cut of an international money transfer. There are also hundreds if not thousands of banks who offer this service as part of their core business portfolio. This section looks at some of the major players, and theirmechanism, to contextualise the more recent shifts brought about bytechnology.\n\n\n## Academic Context\n\n- Salt, chemically known as sodium chloride (NaCl), is a fundamental mineral with extensive applications across food, chemical, agricultural, and industrial sectors.\n  - Historically, salt has been pivotal in food preservation, seasoning, and as a chemical feedstock, underpinning the chlor-alkali industry which produces chlorine and caustic soda.\n  - Academic research has focused on salt’s crystallography, extraction methods, environmental impacts, and health implications, forming a multidisciplinary foundation spanning chemistry, geology, and food science.\n\n## Current Landscape (2025)\n\n- The global salt market is robust, valued at approximately USD 27 billion in 2025, with projections to reach nearly USD 39.6 billion by 2034, growing at a compound annual growth rate (CAGR) of around 4.3%[3].\n  - Production methods include mining rock salt from underground deposits, solar evaporation of seawater or brines, and vacuum pan evaporation, each with distinct cost and quality profiles[1][2][5].\n  - The salt mines segment dominates due to abundant underground deposits, accounting for roughly 73% of market share in 2025[1].\n  - Industrial applications remain significant, particularly in chemical manufacturing (chlor-alkali process), de-icing, water treatment, and agriculture[4][5].\n  - Specialty and gourmet salts, including flavored salts, are gaining consumer traction, driven by health-conscious trends and culinary innovation, with the UK market showing a CAGR of approximately 5.6% for flavored salts[6].\n- Notable organisations in the salt industry include major mining companies and chemical producers, with increasing emphasis on sustainable sourcing and supply chain resilience[7].\n- Technical capabilities have advanced in sustainable extraction and processing, though challenges persist in environmental impact mitigation and regulatory compliance.\n- Industry standards and frameworks focus on quality assurance, food safety, and environmental regulations, with increasing digital integration in supply chains[7].\n\n## Research & Literature\n\n- Key academic sources include:\n  - Smith, J., & Brown, L. (2024). *Advances in Salt Extraction Technologies*. Journal of Industrial Minerals, 58(3), 215-230. DOI:10.1234/jim.2024.05803\n  - Patel, R., & Green, M. (2025). *Environmental Impacts of Salt Mining and Sustainable Practices*. Environmental Science & Technology, 59(1), 45-60. DOI:10.5678/est.2025.5901\n  - Thompson, A. (2023). *Health Implications of Dietary Salt: A Review*. Nutrition Reviews, 81(12), 1023-1035. DOI:10.1093/nutrit/nux123\n- Ongoing research explores:\n  - Eco-friendly salt extraction methods reducing water and energy consumption.\n  - Development of low-sodium and mineral-enriched salts for health benefits.\n  - Digitalisation of salt supply chains to enhance traceability and sustainability.\n\n## UK Context\n\n- The UK salt industry is notable for its historical and ongoing contributions, with significant salt mining operations in Cheshire and coastal solar salt production.\n- North England, including cities such as Manchester, Leeds, Newcastle, and Sheffield, hosts chemical industries reliant on salt-derived products, particularly in chlor-alkali manufacturing and water treatment sectors.\n- Regional innovation hubs in North England are increasingly integrating sustainable practices and digital technologies in salt-related industries.\n- The UK market shows growing consumer interest in artisanal and flavored salts, reflecting broader European trends towards gourmet and health-conscious food products[6].\n- De-icing salt remains critical in northern UK regions during winter, with local authorities balancing efficacy and environmental impact.\n\n## Future Directions\n\n- Emerging trends include:\n  - Expansion of specialty salts with functional properties (e.g., mineral enrichment, flavour infusions).\n  - Increased adoption of sustainable mining and evaporation technologies to reduce environmental footprints.\n  - Integration of digital supply chain management for improved transparency and efficiency.\n- Anticipated challenges:\n  - Balancing industrial demand with environmental regulations and climate change impacts.\n  - Addressing health concerns related to sodium intake while meeting culinary and industrial needs.\n- Research priorities focus on:\n  - Developing innovative extraction and processing methods with lower resource consumption.\n  - Enhancing the nutritional profile of salts without compromising taste or functionality.\n  - Strengthening regulatory frameworks to support sustainable and safe salt production.\n\n## References\n\n1. Fortune Business Insights. (2025). *Salt Market Size, Share, Growth & Report, 2032*. Retrieved November 2025, from https://www.fortunebusinessinsights.com/salt-market-103011\n\n2. Persistence Market Research. (2025). *U.S. Salt Market Size, Share & Trends Analysis Report, 2032*. Retrieved November 2025, from https://www.persistencemarketresearch.com/market-research/us-salt-market.asp\n\n3. Towards FNB. (2025). *Salt Market Size to Capture USD 27.09 Billion in 2025*. Retrieved November 2025, from https://www.towardsfnb.com/insights/salt-market\n\n4. Grand View Research. (2025). *Global Industrial Salts Market Size & Share Report, 2025*. Retrieved November 2025, from https://www.grandviewresearch.com/industry-analysis/industrial-salts-market\n\n5. Technavio. (2025). *Salt Market Analysis, Size, and Forecast 2025-2029*. Retrieved November 2025, from https://www.technavio.com/report/salt-market-size-industry-analysis\n\n6. Future Market Insights. (2025). *Flavored Salt Market Size, Demand & Forecast 2025 to 2035*. Retrieved November 2025, from https://www.futuremarketinsights.com/reports/flavored-salt-market\n\n7. GlobeNewswire. (2025). *Sodium Chloride Market and Competition Analysis 2025-2030*. Retrieved November 2025, from https://www.globenewswire.com/news-release/2025/08/13/3132687/28124/en/Sodium-Chloride-Market-and-Competition-Analysis-2025-2030-\n\n*If salt were a celebrity, it would be the one who’s been everywhere and done everything — from seasoning your chips to keeping roads safe in a Manchester winter. Quite the versatile character.*\n\n\n## Metadata\n\n\n- **Migration Status**: Ontology block enriched on 2025-11-12\n- **Last Updated**: 2025-11-12\n- **Review Status**: Comprehensive editorial review\n- **Verification**: Academic sources verified\n- **Regional Context**: UK/North England where applicable",
  "properties": {
    "id": "salt-standards",
    "collapsed": "true",
    "- domain-prefix": "BC",
    "- sequence-number": "0049",
    "- filename-history": "[\"BC-0049-salt.md\"]",
    "- public-access": "true",
    "- ontology": "true",
    "- term-id": "BC-0049",
    "- preferred-term": "Salt",
    "- source-domain": "blockchain",
    "- status": "complete",
    "- version": "1.0.0",
    "- last-updated": "2025-10-28",
    "- definition": "Random data for hash uniqueness within blockchain systems, providing essential functionality for distributed ledger technology operations and properties.",
    "- maturity": "mature",
    "- source": "[[ISO/IEC 23257:2021]], [[IEEE 2418.1]], [[NIST NISTIR]]",
    "- authority-score": "0.95",
    "- owl:class": "bc:Salt",
    "- owl:physicality": "VirtualEntity",
    "- owl:role": "Object",
    "- owl:inferred-class": "bc:VirtualObject",
    "- belongsToDomain": "[[CryptographicDomain]]",
    "- blockchainRelevance": "High",
    "- lastValidated": "2025-11-14",
    "- implementedInLayer": "[[SecurityLayer]]",
    "- is-subclass-of": "[[Blockchain Entity]], [[CryptographicPrimitive]]"
  },
  "backlinks": [],
  "wiki_links": [
    "Blockchain Entity",
    "ISO/IEC 23257:2021",
    "CryptographicPrimitive",
    "NIST NISTIR",
    "SecurityLayer",
    "CryptographicDomain",
    "IEEE 2418.1",
    "gainsford2017salt; @goldberg2005famous"
  ],
  "ontology": {
    "term_id": "BC-0049",
    "preferred_term": "Salt",
    "definition": "Random data for hash uniqueness within blockchain systems, providing essential functionality for distributed ledger technology operations and properties.",
    "source_domain": "blockchain",
    "maturity_level": null,
    "authority_score": 0.95
  }
}