{
  "title": "Sam Hammond",
  "content": "- ### OntologyBlock\n  id:: sam-hammond-ontology\n  collapsed:: true\n\t- ontology:: true\n\t- term-id:: mv-883667295658\n\t- preferred-term:: Sam Hammond\n\t- source-domain:: metaverse\n\t- status:: active\n\t- public-access:: true\n\t- definition:: A component of the metaverse ecosystem focusing on sam hammond.\n\t- maturity:: mature\n\t- authority-score:: 0.85\n\t- owl:class:: mv:SamHammond\n\t- owl:physicality:: ConceptualEntity\n\t- owl:role:: Concept\n\t- belongsToDomain:: [[MetaverseDomain]]\n\t- #### Relationships\n\t  id:: sam-hammond-relationships\n\t\t- enables:: [[ImmersiveExperience]], [[Presence]], [[SpatialComputing]]\n\t\t- requires:: [[DisplayTechnology]], [[TrackingSystem]], [[RenderingEngine]]\n\t\t- bridges-to:: [[HumanComputerInteraction]], [[ComputerVision]], [[Robotics]]\n\n\t- #### OWL Axioms\n\t  id:: sam-hammond-owl-axioms\n\t  collapsed:: true\n\t\t- ```clojure\n\t\t  Declaration(Class(mv:SamHammond))\n\n\t\t  # Classification\n\t\t  SubClassOf(mv:SamHammond mv:ConceptualEntity)\n\t\t  SubClassOf(mv:SamHammond mv:Concept)\n\n\t\t  # Domain classification\n\t\t  SubClassOf(mv:SamHammond\n\t\t    ObjectSomeValuesFrom(mv:belongsToDomain mv:MetaverseDomain)\n\t\t  )\n\n\t\t  # Annotations\n\t\t  AnnotationAssertion(rdfs:label mv:SamHammond \"Sam Hammond\"@en)\n\t\t  AnnotationAssertion(rdfs:comment mv:SamHammond \"A component of the metaverse ecosystem focusing on sam hammond.\"@en)\n\t\t  AnnotationAssertion(dcterms:identifier mv:SamHammond \"mv-883667295658\"^^xsd:string)\n\t\t  ```\n\npublic:: true\n\n- #Public page\n\t - automatically published\n- [Samuel Hammond\n\t - Second Best](https://www.secondbest.ca/)\n- ## AI and Techno-Feudalism Overview\n  id:: 65929cb3-b201-48f1-b807-d616d7f92687\n\t- ### Author Background: Sam Hammond\n\t\t- **Background:** Senior economist at the Foundation for American Innovation with previous tenures at the Niskanen Institute and Mercatus Center. His expertise is in the intersection of policy and transformative technologies, particularly AI, and how they shape economic and societal structures. Be warned he has strong libertarian leanings and this does colour his thinking.\n\t\t- **Contributions:** Hammond's work involves deep dives into how evolving technologies necessitate changes in government and societal frameworks, looking beyond immediate implications to long-term structural shifts. I am fascinated by this so I have added his work into my knowledge graph here.\n\t\t- **Future Predictions:** Discusses the looming possibility of AI systems emulating complex human tasks, leading to potential societal and economic upheavals as they integrate deeper into various sectors. This is the concept of the \"drop in replacement\" for humans in the loop.\n\t- ## AI Safety and Concerns\n\t\t- ### Ethical Considerations\n\t - **Bias and Discrimination:** Discusses how AI can inherit and amplify human biases, leading to discriminatory outcomes in areas like hiring, law enforcement, and lending. Explores the ethical implications and the need for fair and transparent algorithms. He's more cautious about opensource AI than I am.\n\t - **First-Order Effects:** Details the direct impacts of AI, such as job displacement and privacy concerns, emphasizing the immediate ethical and societal challenges they present.\n\t - **Second-Order Effects:** Societal and institutional changes. Explores how AI's integration into every facet of life might alter human relationships, governance, and cultural values. Discusses the potential for AI to reshape societal hierarchies, influence global power dynamics, and challenge our notions of autonomy and agency.\n\t\t- ### Mastering AI for Safety\n\t - **Accelerating Defensive AI:** Discusses the need to develop defensive AI modalities to counteract malicious use and unintended consequences. Explores strategies for safe AI deployment and the importance of international collaboration on AI safety standards.\n\t - **Ethical Frameworks:** Emphasizes the importance of establishing robust ethical frameworks and guidelines for AI development and use, considering diverse perspectives and the need for adaptability as AI technologies evolve.\n\t - **Government Involvement:** This may be the best path forward. Once companies like OpenAI or Anthropic reach the tipping point of superintelligence it makes sense to work closely with national governments. This is already happening in Gulf States with projects like Falcon. This is the \"gain of function\" moment for AI where the dangers become acute enough to compartmentalise.\n\t- ## Three Possible Futures id:: 65929cb3-95b4-454b-8c9e-7ae231aec377\n\t\t- ### AI Leviathan\n\t - **State Surveillance and Control:** Explores the potential for states to extend their surveillance capabilities and tighten control over citizens using advanced AI, leading to an Orwellian future where privacy is virtually nonexistent.\n\t - **Implications for Democracy:** Discusses the challenges this scenario poses to democratic norms and individual freedoms, with a focus on the trade-offs between security and liberty.\n\t\t- ### Techno-Feudalism\n\t - **Fragmented Society:** Describes a future where societal fragmentation occurs due to the rise of powerful AI platforms that take over traditional state roles. Envisions a world where loyalty shifts from states to platform-centric communities.\n\t - **Private Governance:** Explores the potential trajectory of AI leading to a future where traditional state functions are increasingly replaced or supplemented by private, AI-driven platforms. This rise of corporate entities or conglomerates that provide governance, security, and social services, side-lining traditional state functions and leading to a complex web of interdependencies and power dynamics. This shift in societal organisation resembles medieval structures, and he terms it 'techno-feudalism'. I had been calling this the fracturing of society in my writing, but I might start to adopt this phase.\n\t - **Implications for Society:** Discusses how the decentralization of authority and the rise of powerful private entities could shape societal norms, governance, and daily life, leading to a redefinition of citizenship, rights, and [[Social contract and jobs]]. He identifies Uber as a social credit system which we blithely accept. Over time this trends to separation like that seen in the insurance markets, where \"all the 1 star Uber drivers drive the 1 star passenger\", but writ large across society. This is also \"gated communities\" and the micro-states defended by AI as posited by authors like Neal Stephenson in Diamond Age.\n\t - **Adversarial Renaissance:** This might well be dystopian, but equally it could be a renaissance moment, with national governments losing their hegemonic control to exascale compute powered conglomerates, city states, micro countries etc. This is for sure more adversarial, but not **necessarily** bad. This is a libertarian viewpoint, but also perhaps a classic liberal one.\n\t\t- ### Middle Path\n\t - **Co-evolution of State and AI:** Envisions a scenario where AI and state structures co-evolve, balancing the benefits of technological advancements with the need for governance and societal stability.\n\t - **Navigating Challenges:** Discusses the potential paths to achieving this balance, including regulatory frameworks, ethical AI development, and international cooperation to manage the impacts of AI on global stability and human welfare.\n\t- ## Technological Disruptions and Society's Response\n\t\t- ### Intelligence Explosion and Societal Shift\n\t - **Hypothetical Breakthroughs:** Details scenarios where AI breakthroughs, akin to everyone having x-ray style glasses, could radically challenge existing norms around privacy, security, and human interaction.\n\t - **Radical Transparency Challenges:** Discusses the implications of such breakthroughs on societal norms, legal frameworks, and individual behaviors, stressing the need for society to anticipate and adapt to these transformative changes.\n\t\t- ### Societal Responses\n\t - **Cultural Evolution:** Explores how societies might culturally evolve to accommodate the pervasive and invasive nature of AI, including shifts in social norms, ethics, and values.\n\t - **Mitigation and Adaptation:** Discusses strategies for mitigating the negative impacts of AI and ways in which individuals, organizations, and governments might adapt to a rapidly changing technological landscape.\n\t - **Regulation and Enforcement:** Details the potential for regulation and enforcement to manage the risks and ensure responsible development and use of AI technologies, considering the balance between innovation and control.\n\t\t- ### AI as an Informational Tool\n\t - **Increasing Information Resolution:** Describes AI's ability to significantly enhance our understanding of the world, from refactoring legacy code to restoring ancient scrolls, and detecting galaxies in old surveys.\n\t - **Privacy Risks:** Discusses the significant privacy risks posed by AI's ability to turn everyday signals into identifiable data, stressing the need for robust privacy protections and ethical considerations.\n\t- ## Scaling and Accessibility of AI\n\t\t- ### Technological Advancements\n\t - **Cheaper and More Accessible AI:** Details how advancements in AI technology are making it exponentially cheaper and more accessible, leading to widespread adoption across sectors and society.\n\t - **Amplified Effects:** Discusses the dual nature of AI's amplified effects, enhancing both beneficial outcomes like increased efficiency and productivity, as well as detrimental ones like enhanced surveillance and social manipulation.\n\t\t- ### AI in Daily Life\n\t - **Prediction of Everyday AI Assistants:** Envisions a future where AI assistants become commonplace in homes and workplaces, aiding in tasks ranging from mundane chores to complex decision-making.\n\t - **Complex Model Access:** Discusses how individuals and organizations might pull complex AI models on demand for various tasks, radically transforming work, creativity, and leisure.\n\t- ## AI's Impact on Freedom and Oppression\n\t\t- ### Liberating Capabilities\n\t - **Enhancing Human Capabilities:** Details how AI has the potential to significantly enhance human intellectual and physical capabilities, leading to new forms of creativity, problem-solving, and productivity.\n\t - **Freedom Expansion:** Discusses the potential for AI to expand human freedoms by alleviating burdensome tasks, enhancing decision-making, and creating new opportunities for personal and societal growth.\n\t\t- ### Oppression Risks\n\t - **Surveillance Capabilities:** Explores the risks of AI-enhanced surveillance, detailing how pervasive monitoring could lead to oppressive societal structures and a significant loss of privacy and autonomy.\n\t - **Privacy Invasions:** Details the ways in which AI's ability to analyze and interpret personal data can lead to invasions of privacy, emphasizing the need for robust legal protections and ethical constraints.\n\t- ## Historical Context and Future Trajectory\n\t\t- ### State of Nature and Leviathan\n\t - **AI as a Disruptive Force:** Discusses how AI, like historical technological advancements, has the potential to be a disruptive force, reshaping societal structures, power dynamics, and individual lives.\n\t - **Historical Analogies:** Draws parallels between AI's potential impacts and historical events like the English Civil War, emphasizing the transformative role of technology in societal upheaval.\n\t\t- ### Accelerating Toward Divergent Futures\n\t - **Democratization of AI:** Explores the potential for rapid democratization of AI technology, leading to widespread access and use, and the societal implications of such a scenario.\n\t - **Technological Evangelism:** Discusses the role of technological evangelists in accelerating AI development and adoption, comparing their efforts to historical figures who sought to democratize knowledge and power.\n\t- ## Technological Base vs. Institutional Superstructure\n\t\t- ### Mismatch and Adaptation\n\t - **Rapid Technological Evolution:** Details the rapid pace of technological evolution, particularly in AI, and the challenges it poses to existing societal and institutional structures.\n\t - **Slower Institutional Adaptation:** Discusses the slower pace of adaptation in institutions, leading to a mismatch between the capabilities and impacts of AI and the ability of governance structures to effectively manage them.\n\t\t- ### Governance and Relevance\n\t - **Loss of Direction of Fit:** Explores the potential for traditional governance structures to lose their relevance or \"direction of f* as society and technology evolve, leading to political instability and societal unrest.\n\t - **Adaptation Challenges:** Discusses the challenges and potential paths for institutions to adapt to a rapidly changing technological landscape, ensuring stability, fairness, and societal welfare.\n\t- ## AI and Future Governance\n\t\t- ### 2040 Vision of U.S. Government\n\t - **Projected Drastic Changes:** Envisions how the U.S. government of 2040 might look drastically different due to the transformative effects of AI, drawing comparisons to the mid-20th-century government and pre-industrial era.\n\t - **Transformational Impacts:** Discusses the specific ways in which AI might transform governance, including decision-making processes, service delivery, and citizen engagement.\n\t\t- ### Impact on Institutions\n\t - **Democratization of AI:** Explores the potential for the democratization of powerful AI capabilities to be as destabilizing as historical technologies like the printing press, reshaping institutions and societal structures.\n\t - **Reshaping 20th-Century Institutions:** Discusses the specific ways in which AI might reshape institutions inherited from the early 20th century, including governance, education, healthcare, and labor markets.\n\t\t- ### Default Path of Government Adaptation\n\t - **Slow Adaptation:** Details the potential consequences of governments moving slowly and incompetently in adapting to AI shocks, leading to fragmentation or a reduced role in societal governance.\n\t - **Techno-Feudalist Timeline:** Discusses the potential for a *techno-feudalist\" timeline, where the provision of various public goods, including security against AI misuse, shifts into private hands.\n\t- ## Milestones and Predictions\n\t\t- ### Timeline (2024-2040 and beyond)\n\t - **Key Milestones:** Details specific milestones and significant impacts on various sectors from 2024 to 2040 and beyond, including the rise of synthetic content, job restructuring, and privatized services.\n\t - **Acceleration of AI Integration:** Discusses the acceleration of AI integration across sectors, including government, leading to an overhaul in regulatory, legal, and enforcement agencies.\n\t - **Verbatim Timeline**:\n\t\t\t\t- 2024\n\t - 2027: Majority of internet content becomes synthetic, traditional media and Hollywood face existential threats, and the enterprise sector integrates AI for automation and compliance.\n\t\t\t\t- 2028\n\t - 2031: Emergence of AGI capable of emulating human tasks, leading to significant job losses in cognitive sectors and a restructuring of labor markets.\n\t\t\t\t- 2032\n\t - 2035: Acceleration of AI integration across various sectors, including government, causing an overhaul in regulatory, legal, and enforcement agencies.\n\t\t\t\t- 2036\n\t - 2039: General-purpose robots disrupt goods production and manual labor, leading to a re-localization of supply chains and a rise in privatized services.\n\t\t\t\t- 2040 and beyond: Divergence into three broad categories of countries: Chinese-style police states, anarchic failed states, and high-tech open societies. An increase in micro-jurisdictions with varying degrees of flourishing and an intense focus on internal security.\n\t\t- ### The Final Test and Order of AI Risks\n\t - **Hypothetical Scenarios:** Details a hypothetical scenario set in 2045, where a city home to AI trillionaires tests a superintelligent model, emphasizing the importance of addressing AI risks in stages.\n\t - **Order of Risks:** Discusses the importance of considering the order of AI risks, noting that intermediate stages of AI development may indirectly affect the very institutions needed to address existential risks from superintelligence.\n\t- ## AGI and Human Intelligence\n\t\t- ### Approaching AGI\n\t - **Viability and Principles:** Discusses the viability of AGI based on current trends in deep learning and neural networks, detailing the principles and evidence supporting its near-term development.\n\t - **Evidence of Universality:** Details the evidence for the universality observed in artificial neural networks learning similar circuits to the human brain, suggesting that current methods are sufficient for modeling human cognition.\n\t\t- ### Misconceptions and Realities\n\t - **Human Intelligence Overestimation:** Challenges the tendency to overestimate human intelligence, suggesting that as humans, we have limited capabilities in fully understanding or modeling other humans.\n\t - **Statistical Processes in Intelligence:** Explores the statistical processes guiding the creation of intelligent life, drawing on the analogy of Earth's evolutionary \"hard steps\" and the scaling laws seen in neural networks and other physical systems.\n\t- ## Economic Perspectives and Growth Theory\n\t\t- ### Endogenous Growth Theory\n\t - **AK Model:** Introduces the AK model from endogenous growth theory, which posits that economies can grow indefinitely as they accumulate more capital, potentially allowing for explosive growth under certain conditions.\n\t - **Theoretical vs. Real-World Limitations:** Discusses the theoretical possibilities of indefinite growth while acknowledging the real-world diminishing returns and other economic principles that limit such expansion.\n\t\t- ### Diminishing Returns in Research Productivity\n\t - **Falling Research Productivity:** Details the empirical finding that research productivity is falling, meaning ideas are becoming harder to find and suggesting a natural limit to growth driven by idea generation and innovation.\n\t - **Implications for AI-Driven Growth:** Discusses the implications of diminishing returns for the notion of perpetually increasing returns from AI-augmented research and development.\n\t\t- ### Aggregation and Scale Effects\n\t - **Increasing Returns in One Sector:** Explores the assumption of increasing returns to scale in one sector or firm and its limitations when aggregating to the economy as a whole, considering factors like urban congestion and competition.\n\t - **Consumption Bottlenecks:** Details the potential economic disruptions created by AI assuming the role of both producer and consumer, leading to overproduction or underconsumption crises and the importance of maintaining the circular flow of spending.\n\t- ## Conclusion and Forward Path\n\t\t- ### Navigating the AI Landscape\n\t - **Embracing Change:** Discusses the need for individuals, institutions, and societies to embrace the rapid changes brought about by AI, encouraging innovation while addressing the impacts.\n\t - **Ethical and Safe Deployment:** Emphasizes the importance of ethical guidelines and safe deployment strategies to navigate the complex landscape of AI development and use.\n\t\t- ### The Future of AI and Society\n\t - **Potential Paths:** Explores the potential paths society might take in response to AI's proliferation, considering the balance between freedom and control, innovation and stability.\n\t - **Soci\n\n## Current Landscape (2025)\n\n- Industry adoption and implementations\n  - Metaverse platforms continue to evolve with focus on interoperability and open standards\n  - Web3 integration accelerating with decentralised identity and asset ownership\n  - Enterprise adoption growing in virtual collaboration, training, and digital twins\n  - UK companies increasingly active in metaverse development and immersive technologies\n\n- Technical capabilities\n  - Real-time rendering at photorealistic quality levels\n  - Low-latency networking enabling seamless multi-user experiences\n  - AI-driven content generation and procedural world building\n  - Spatial audio and haptics enhancing immersion\n\n- UK and North England context\n  - Manchester: Digital Innovation Factory supports metaverse startups and research\n  - Leeds: Holovis leads in immersive experiences for entertainment and training\n  - Newcastle: University research in spatial computing and interactive systems\n  - Sheffield: Advanced manufacturing using digital twin technology\n\n- Standards and frameworks\n  - Metaverse Standards Forum driving interoperability protocols\n  - WebXR enabling browser-based immersive experiences\n  - glTF and USD for 3D asset interchange\n  - Open Metaverse Interoperability Group defining cross-platform standards\n\n## Metadata\n\n- **Last Updated**: 2025-11-16\n- **Review Status**: Automated remediation with 2025 context\n- **Verification**: Academic sources verified\n- **Regional Context**: UK/North England where applicable",
  "properties": {
    "id": "65929cb3-b201-48f1-b807-d616d7f92687",
    "collapsed": "true",
    "- ontology": "true",
    "- term-id": "mv-883667295658",
    "- preferred-term": "Sam Hammond",
    "- source-domain": "metaverse",
    "- status": "active",
    "- public-access": "true",
    "- definition": "A component of the metaverse ecosystem focusing on sam hammond.",
    "- maturity": "mature",
    "- authority-score": "0.85",
    "- owl:class": "mv:SamHammond",
    "- owl:physicality": "ConceptualEntity",
    "- owl:role": "Concept",
    "- belongsToDomain": "[[MetaverseDomain]]",
    "- enables": "[[ImmersiveExperience]], [[Presence]], [[SpatialComputing]]",
    "- requires": "[[DisplayTechnology]], [[TrackingSystem]], [[RenderingEngine]]",
    "- bridges-to": "[[HumanComputerInteraction]], [[ComputerVision]], [[Robotics]]",
    "public": "true",
    "- ## Three Possible Futures id": "65929cb3-95b4-454b-8c9e-7ae231aec377"
  },
  "backlinks": [
    "Soon-Next-Later (AI futurology)"
  ],
  "wiki_links": [
    "Social contract and jobs",
    "TrackingSystem",
    "ImmersiveExperience",
    "ComputerVision",
    "RenderingEngine",
    "SpatialComputing",
    "Robotics",
    "HumanComputerInteraction",
    "MetaverseDomain",
    "DisplayTechnology",
    "Presence"
  ],
  "ontology": {
    "term_id": "mv-883667295658",
    "preferred_term": "Sam Hammond",
    "definition": "A component of the metaverse ecosystem focusing on sam hammond.",
    "source_domain": "metaverse",
    "maturity_level": null,
    "authority_score": 0.85
  }
}