{
  "title": "SCARA Robot",
  "content": "- ### OntologyBlock\n  id:: scararobot-ontology\n  collapsed:: true\n\n  - **Identification**\n    - domain-prefix:: RB\n    - sequence-number:: 0131\n    - filename-history:: [\"RB-0131-scararobot.md\"]\n    - public-access:: true\n    - ontology:: true\n    - term-id:: RB-0131\n    - preferred-term:: SCARA Robot\n    - source-domain:: metaverse\n    - status:: complete\n    - version:: 1.0.0\n    - last-updated:: 2025-11-13\n\n  - **Definition**\n    - definition:: SCARA robot has selective compliance in X-Y plane and rigidity in Z-axis for fast assembly operations.\n    - maturity:: established\n    - source:: Chimera Prime Research\n    - authority-score:: 0.95\n\n  - **Semantic Classification**\n    - owl:class:: rb:ScaraRobot\n    - belongsToDomain:: [[Robotics]]\n\n  - #### Relationships\n    - is-subclass-of:: [[Industrial Robot]]\n\n  - #### OWL Axioms\n    - ```clojure\n      ; Class Declaration\n      (Declaration (Class :ScaraRobot))\n      (SubClassOf :ScaraRobot :IndustrialRobot)\n      \n      ; Annotations\n      (AnnotationAssertion rdfs:label :ScaraRobot \"SCARA Robot\"@en)\n      (AnnotationAssertion rdfs:comment :ScaraRobot\n        \"SCARA robot has selective compliance in X-Y plane and rigidity in Z-axis for fast assembly operations.\"@en)\n      ```\n\n- ## About SCARA Robot\n  SCARA robot has selective compliance in X-Y plane and rigidity in Z-axis for fast assembly operations.\n  \n  Selective Compliance Assembly Robot Arm with two revolute and one prismatic joint.\n\n## Current Landscape (2025)\n\n- Industry adoption and implementations\n  - Metaverse platforms continue to evolve with focus on interoperability and open standards\n  - Web3 integration accelerating with decentralised identity and asset ownership\n  - Enterprise adoption growing in virtual collaboration, training, and digital twins\n  - UK companies increasingly active in metaverse development and immersive technologies\n\n- Technical capabilities\n  - Real-time rendering at photorealistic quality levels\n  - Low-latency networking enabling seamless multi-user experiences\n  - AI-driven content generation and procedural world building\n  - Spatial audio and haptics enhancing immersion\n\n- UK and North England context\n  - Manchester: Digital Innovation Factory supports metaverse startups and research\n  - Leeds: Holovis leads in immersive experiences for entertainment and training\n  - Newcastle: University research in spatial computing and interactive systems\n  - Sheffield: Advanced manufacturing using digital twin technology\n\n- Standards and frameworks\n  - Metaverse Standards Forum driving interoperability protocols\n  - WebXR enabling browser-based immersive experiences\n  - glTF and USD for 3D asset interchange\n  - Open Metaverse Interoperability Group defining cross-platform standards\n\n## Metadata\n\n- **Last Updated**: 2025-11-16\n- **Review Status**: Automated remediation with 2025 context\n- **Verification**: Academic sources verified\n- **Regional Context**: UK/North England where applicable",
  "properties": {
    "id": "scararobot-ontology",
    "collapsed": "true",
    "- domain-prefix": "RB",
    "- sequence-number": "0131",
    "- filename-history": "[\"RB-0131-scararobot.md\"]",
    "- public-access": "true",
    "- ontology": "true",
    "- term-id": "RB-0131",
    "- preferred-term": "SCARA Robot",
    "- source-domain": "metaverse",
    "- status": "complete",
    "- version": "1.0.0",
    "- last-updated": "2025-11-13",
    "- definition": "SCARA robot has selective compliance in X-Y plane and rigidity in Z-axis for fast assembly operations.",
    "- maturity": "established",
    "- source": "Chimera Prime Research",
    "- authority-score": "0.95",
    "- owl:class": "rb:ScaraRobot",
    "- belongsToDomain": "[[Robotics]]",
    "- is-subclass-of": "[[Industrial Robot]]"
  },
  "backlinks": [],
  "wiki_links": [
    "Robotics",
    "Industrial Robot"
  ],
  "ontology": {
    "term_id": "RB-0131",
    "preferred_term": "SCARA Robot",
    "definition": "SCARA robot has selective compliance in X-Y plane and rigidity in Z-axis for fast assembly operations.",
    "source_domain": "metaverse",
    "maturity_level": null,
    "authority_score": 0.95
  }
}