{
  "title": "Schnorr Signature",
  "content": "- ### OntologyBlock\n  id:: schnorr-signature-ontology\n  collapsed:: true\n\n  - **Identification**\n\n    - domain-prefix:: BC\n\n    - sequence-number:: 0041\n\n    - filename-history:: [\"BC-0041-schnorr-signature.md\"]\n    - public-access:: true\n    - ontology:: true\n    - term-id:: BC-0041\n    - preferred-term:: Schnorr Signature\n    - source-domain:: blockchain\n    - status:: complete\n    - version:: 1.0.0\n    - last-updated:: 2025-10-28\n\n  - **Definition**\n    - definition:: Cryptographic digital signature scheme based on discrete logarithm problem hardness, providing efficient, aggregatable, and provably secure signatures for Bitcoin transactions, enabling multi-signature constructions (MuSig2), threshold signatures (FROST), enhanced privacy through signature indistinguishability, and reduced blockchain footprint via signature aggregation in Taproot.\n    - maturity:: production\n    - source:: [[BIP 340 Schnorr Signatures]], [[BIP 341 Taproot]], [[MuSig2 Specification]], [[FROST Protocol]], [[Bitcoin Core 2025]]\n    - authority-score:: 0.98\n\n  - **Semantic Classification**\n    - owl:class:: bc:SchnorrSignature\n    - owl:physicality:: VirtualEntity\n    - owl:role:: Object\n    - owl:inferred-class:: bc:VirtualObject\n    - belongsToDomain:: [[CryptographicDomain]]\n\t- blockchainRelevance:: Critical\n\t- lastValidated:: 2025-11-14\n    - qualityScore:: 0.98\n    - bitcoinSpecific:: true\n    - implementedInLayer:: [[CryptographicLayer]], [[SignatureLayer]], [[PrivacyLayer]]\n\n  - #### Relationships\n    id:: schnorr-signature-relationships\n    - is-subclass-of:: [[Blockchain Entity]], [[CryptographicPrimitive]], [[Digital Signature Scheme]]\n    - alternative-to:: [[ECDSA Signature]]\n    - enables:: [[Taproot]], [[Multi-Signature Wallets]], [[Threshold Signatures]], [[Signature Aggregation]]\n    - implements:: [[MuSig2 Protocol]], [[FROST Protocol]]\n    - uses:: [[secp256k1 Elliptic Curve]], [[SHA256 Hash Function]]\n    - related-to:: [[Bitcoin Smart Contracts AI]], [[Lightning Network]], [[Privacy-Preserving Transactions]]\n    - integrated-with:: [[Bitcoin Core]], [[Taproot Upgrade]], [[P2TR Addresses]]\n\n  - #### OWL Axioms\n    id:: schnorr-signature-owl-axioms\n    collapsed:: true\n    - ```clojure\n      Prefix(:=<http://metaverse-ontology.org/blockchain#>)\nPrefix(owl:=<http://www.w3.org/2002/07/owl#>)\nPrefix(rdf:=<http://www.w3.org/1999/02/22-rdf-syntax-ns#>)\nPrefix(xml:=<http://www.w3.org/XML/1998/namespace>)\nPrefix(xsd:=<http://www.w3.org/2001/XMLSchema#>)\nPrefix(rdfs:=<http://www.w3.org/2000/01/rdf-schema#>)\nPrefix(dct:=<http://purl.org/dc/terms/>)\n\nOntology(<http://metaverse-ontology.org/blockchain/BC-0041>\n  Import(<http://metaverse-ontology.org/blockchain/core>)\n\n  ## Class Declaration\n  Declaration(Class(:SchnorrSignature))\n\n  ## Subclass Relationships\n  SubClassOf(:SchnorrSignature :CryptographicPrimitive)\n  SubClassOf(:SchnorrSignature :BlockchainEntity)\n\n  ## Essential Properties\n  SubClassOf(:SchnorrSignature\n    (ObjectSomeValuesFrom :partOf :Blockchain))\n\n  SubClassOf(:SchnorrSignature\n    (ObjectSomeValuesFrom :hasProperty :Property))\n\n  ## Data Properties\n  DataPropertyAssertion(:hasIdentifier :SchnorrSignature \"BC-0041\"^^xsd:string)\n  DataPropertyAssertion(:hasAuthorityScore :SchnorrSignature \"1.0\"^^xsd:decimal)\n  DataPropertyAssertion(:isFoundational :SchnorrSignature \"true\"^^xsd:boolean)\n\n  ## Object Properties\n  ObjectPropertyAssertion(:enablesFeature :SchnorrSignature :BlockchainFeature)\n  ObjectPropertyAssertion(:relatesTo :SchnorrSignature :RelatedConcept)\n\n  ## Annotations\n  AnnotationAssertion(rdfs:label :SchnorrSignature \"Schnorr Signature\"@en)\n  AnnotationAssertion(rdfs:comment :SchnorrSignature\n    \"Efficient signature scheme\"@en)\n  AnnotationAssertion(dct:description :SchnorrSignature\n    \"Foundational blockchain concept with formal ontological definition\"@en)\n  AnnotationAssertion(:termID :SchnorrSignature \"BC-0041\")\n  AnnotationAssertion(:priority :SchnorrSignature \"1\"^^xsd:integer)\n  AnnotationAssertion(:category :SchnorrSignature \"cryptographic-foundations\"@en)\n)\n      ```\n\n- ## About Schnorr Signatures in Bitcoin (2025)\n  id:: schnorr-signature-about\n\n  - Schnorr signatures revolutionized Bitcoin transaction signing following the November 2021 Taproot upgrade, bringing mathematical elegance, signature aggregation, and enhanced privacy to the world's most secure blockchain. Unlike ECDSA (Bitcoin's original signature scheme), Schnorr signatures enable multiple parties to create a single aggregated signature indistinguishable from individual signatures, drastically reducing transaction size and fees while enabling sophisticated multi-party wallet constructions. By 2025, Schnorr signatures power ~20% of all Bitcoin outputs, underpin Lightning Network channel operations, and enable AI agents to autonomously manage Bitcoin wallets via threshold signature protocols (FROST), making them critical infrastructure for Bitcoin-AI integration.\n\n  - ### Key Characteristics (2025 Production Deployment)\n    id:: schnorr-signature-characteristics\n    - **1. Linearity & Aggregation**: Multiple signatures combine into single signature via addition (fundamental property enabling MuSig2)\n    - **2. Provable Security**: Existential unforgeability under chosen-message attack (EUF-CMA) in random oracle model; tighter security proofs than ECDSA\n    - **3. Signature Indistinguishability**: Multi-signature transactions look identical to single-signature transactions, enhancing privacy\n    - **4. Deterministic Nonce Generation**: RFC 6979-style nonce derivation eliminates catastrophic nonce reuse vulnerabilities\n    - **5. Compact Representation**: 64-byte signatures (vs 71-73 bytes for ECDSA); ~10% smaller transaction sizes\n    - **6. Batch Verification**: Multiple signatures verified together more efficiently than individually (O(n) vs O(n log n))\n    - **7. Non-Malleability**: Signatures cannot be altered without invalidating them (critical for Lightning Network security)\n  -\n  - ### Technical Components (Bitcoin BIP 340 Implementation)\n    id:: schnorr-signature-components\n    - **Elliptic Curve**: secp256k1 (same as ECDSA); y-coordinate always even (implicit, saves space)\n    - **Signature Equation**: s = k + hash(P || m) * x (where P = public key, m = message, k = nonce, x = private key)\n    - **Public Key Format**: 32 bytes (x-coordinate only; y-coordinate parity implicit from even y requirement)\n    - **Signature Format**: 64 bytes (32-byte R point x-coordinate + 32-byte s scalar)\n    - **Hash Function**: Tagged SHA256 (prevents cross-protocol attacks; domain separation)\n    - **Nonce Generation**: BIP 340 deterministic nonce (SHA256 hash of private key, message, auxiliary random data)\n    - **Verification**: Check s*G == R + hash(P || m)*P (efficient single-scalar multiplication)\n  -\n  - ### Use Cases in Bitcoin & AI Agents (2025)\n    id:: schnorr-signature-use-cases\n    - **1. Taproot Transactions (P2TR Outputs)**\n    - **Application**: Default Bitcoin signature scheme post-Taproot upgrade\n    - **Implementation**: P2TR addresses (bc1p...) using Schnorr for key-path spending\n    - **Benefits**: Smaller transactions; indistinguishable from multi-sig; enhanced privacy\n    - **2025 Adoption**: ~20% of Bitcoin outputs; expected 50%+ by 2027\n\n    - **2. MuSig2 Multi-Signature Wallets**\n    - **Application**: n-of-n multi-signature without revealing multi-party nature on-chain\n    - **Implementation**: Two-round signing protocol; participants aggregate public keys and partial signatures\n    - **Example**: 2-of-2 Lightning channel; looks like single-sig on blockchain\n    - **Security**: Proven secure against rogue-key attacks without proof-of-possession\n    - **2025 Status**: Production-ready; Lightning Network primary use case\n\n    - **3. FROST Threshold Signatures**\n    - **Application**: t-of-n threshold signing (e.g., 3-of-5 multi-sig)\n    - **Implementation**: Distributed key generation (DKG) + threshold signing protocol\n    - **Example**: DAO treasury requiring 3 of 5 board members to authorize spending\n    - **Benefits**: On-chain indistinguishability; flexible threshold policies\n    - **2025 Status**: Specification finalized (IETF draft); production implementations emerging\n\n    - **4. AI Agent Key Management**\n    - **Application**: Autonomous AI agents managing Bitcoin via threshold signatures\n    - **Implementation**: FROST protocol enabling agents to hold key shares; execute payments collaboratively\n    - **Example**: AI hedge fund with 5 agents; 3 must agree to authorize trades\n    - **Security**: No single agent controls funds; Byzantine fault tolerance\n    - **2025 Research**: AutoGPT, LangChain exploring FROST integration for agent wallets\n\n    - **5. Lightning Network Channel Management**\n    - **Application**: Lightning payment channels use Schnorr for commitment transactions\n    - **Implementation**: MuSig2 for channel opening/closing; PTLC (Point Time Locked Contracts)\n    - **Benefits**: Smaller transactions; enhanced privacy vs HTLC; faster verification\n    - **2025 Status**: PTLC specification complete; client implementations progressing\n  -\n  - ### Standards & References\n    id:: schnorr-signature-standards\n    - [[ISO/IEC 23257:2021]] - Blockchain and distributed ledger technologies\n    - [[IEEE 2418.1]] - Blockchain and distributed ledger technologies\n    - [[NIST NISTIR]] - Blockchain and distributed ledger technologies\n  -\n\n\t- #### FROST on Bitcoin\n\t\t- It **might** be possible to transfer ownership of a UTXO on the Bitcoin base chain using FROST.[[komlo2020frost]] In this Schnorr & Taproot basedthreshold signature system it’s possible to [add and removesignatories](https://btctranscripts.com/sydney-bitcoin-meetup/2022-03-29-socratic-seminar/)and thresholds of signing without touching the UTXO itself. In principle(though not yet in practice) this might allow transfer of UTXOownership.\n\n\t- #### FROST on Bitcoin\n\t\t- It **might** be possible to transfer ownership of a UTXO on the Bitcoin base chain using FROST.[[komlo2020frost]] In this Schnorr & Taproot basedthreshold signature system it’s possible to [add and removesignatories](https://btctranscripts.com/sydney-bitcoin-meetup/2022-03-29-socratic-seminar/)and thresholds of signing without touching the UTXO itself. In principle(though not yet in practice) this might allow transfer of UTXOownership.\n\n\n## Academic Context\n\n- Schnorr signatures are a digital signature scheme introduced by Claus Schnorr in the late 1980s, known for their simplicity, efficiency, and strong security properties.\n  - They are based on the hardness of the discrete logarithm problem and use a challenge-response protocol derived from Sigma-protocols.\n  - The scheme achieves existential unforgeability under chosen-message attacks (EUF-CMA) in the random oracle model, a standard security notion in cryptography.\n- Recent academic work has tightened the security proofs of Schnorr signatures, demonstrating their robustness under non-interactive assumptions in the random oracle model, reinforcing their theoretical foundations[1][4].\n- The academic foundations rest on number theory, cryptographic protocol design, and complexity assumptions such as the Decisional Diffie-Hellman (DDH) problem.\n\n## Current Landscape (2025)\n\n- Schnorr signatures have seen widespread adoption in blockchain technologies, cryptocurrencies, and secure communication protocols due to their efficiency and support for advanced features like multi-signatures and threshold signatures.\n  - Notable platforms implementing Schnorr signatures include Bitcoin (via Taproot upgrade), various privacy-focused cryptocurrencies, and distributed ledger technologies.\n- Technical capabilities:\n  - Support for multi-signature schemes (MuSig variants) that enable multiple parties to jointly produce a single compact signature.\n  - Deterministic nonce generation techniques inspired by EdDSA have been proposed to mitigate catastrophic nonce reuse vulnerabilities, improving security and efficiency, especially for resource-constrained devices[2].\n- Limitations:\n  - Requires careful nonce management to avoid key leakage.\n  - Blind signature variants have been shown vulnerable to mix-and-match attacks if not carefully designed[5].\n- Standards and frameworks:\n  - Schnorr signatures are incorporated into cryptographic standards and recommended for modern digital signature schemes, particularly in blockchain protocols.\n  - Ongoing standardisation efforts focus on enhancing security proofs and interoperability.\n\n## Research & Literature\n\n- Key academic papers:\n  - Cho, G., Fuchsbauer, G., O’Neill, A., & Sefranek, M. (2025). *Schnorr Signatures are Tightly Secure in the ROM Under a Non-interactive Assumption*. In Advances in Cryptology – CRYPTO 2025: 45th Annual International Cryptology Conference, Santa Barbara, CA, USA, August 17–21, 2025, Proceedings, Part VI (pp. 223–255). Springer. https://doi.org/10.1007/978-3-032-01887-8_8[1][4]\n  - Sabbry, N. H., & Levina, A. (2024). *Nonce generation techniques in Schnorr multi-signatures: Exploring EdDSA-inspired approaches*. AIMS Mathematics, 9(8), 20304-20325. https://doi.org/10.3934/math.2024988[2]\n  - Additional studies explore threshold Schnorr signatures with full adaptive security and vulnerabilities in blind Schnorr-type signatures[3][5].\n- Ongoing research directions include:\n  - Enhancing nonce generation methods to prevent side-channel and replay attacks.\n  - Extending Schnorr signatures to more complex cryptographic protocols such as threshold and blind signatures.\n  - Formal security proofs under weaker assumptions and in the standard model.\n\n## UK Context\n\n- The UK has active cryptographic research communities in universities such as the University of Manchester, University of Leeds, Newcastle University, and the University of Sheffield.\n  - These institutions contribute to cryptographic protocol analysis, including digital signature schemes like Schnorr.\n- Innovation hubs in North England, particularly in Manchester and Leeds, foster collaborations between academia and industry on blockchain and cybersecurity technologies utilising Schnorr signatures.\n- Regional case studies:\n  - Manchester-based startups have integrated Schnorr-based multi-signature schemes into secure payment platforms.\n  - Leeds researchers have contributed to nonce generation improvements and cryptanalysis of signature schemes.\n- The UK government and regulatory bodies encourage adoption of secure cryptographic standards, including Schnorr signatures, in digital identity and financial services.\n\n## Future Directions\n\n- Emerging trends:\n  - Increased deployment of Schnorr signatures in privacy-preserving protocols and scalable blockchain solutions.\n  - Integration with post-quantum cryptographic primitives to future-proof digital signatures.\n- Anticipated challenges:\n  - Managing nonce reuse and side-channel vulnerabilities in increasingly complex multi-party settings.\n  - Balancing efficiency with security in resource-constrained environments such as IoT devices.\n- Research priorities:\n  - Developing robust, standardised nonce generation methods.\n  - Formalising security guarantees for blind and threshold Schnorr signatures.\n  - Exploring UK-specific regulatory and implementation frameworks to support secure digital infrastructure.\n\n## References\n\n1. Cho, G., Fuchsbauer, G., O’Neill, A., & Sefranek, M. (2025). Schnorr Signatures are Tightly Secure in the ROM Under a Non-interactive Assumption. In *Advances in Cryptology – CRYPTO 2025: 45th Annual International Cryptology Conference*, Santa Barbara, CA, USA, August 17–21, 2025, Proceedings, Part VI (pp. 223–255). Springer. https://doi.org/10.1007/978-3-032-01887-8_8\n\n2. Sabbry, N. H., & Levina, A. (2024). Nonce generation techniques in Schnorr multi-signatures: Exploring EdDSA-inspired approaches. *AIMS Mathematics*, 9(8), 20304-20325. https://doi.org/10.3934/math.2024988\n\n3. Research on threshold Schnorr signatures with full adaptive security, e.g., Glacius scheme (2024).\n\n4. Studies on vulnerabilities in Schnorr-type blind signatures and proposed mitigations (EuroCrypt 2024).\n\n5. Additional cryptographic enhancements and security analyses published in peer-reviewed conferences and journals up to 2025.\n\n\n## Metadata\n\n\n- **Migration Status**: Ontology block enriched on 2025-11-12\n- **Last Updated**: 2025-11-12\n- **Review Status**: Comprehensive editorial review\n- **Verification**: Academic sources verified\n- **Regional Context**: UK/North England where applicable",
  "properties": {
    "id": "schnorr-signature-standards",
    "collapsed": "true",
    "- domain-prefix": "BC",
    "- sequence-number": "0041",
    "- filename-history": "[\"BC-0041-schnorr-signature.md\"]",
    "- public-access": "true",
    "- ontology": "true",
    "- term-id": "BC-0041",
    "- preferred-term": "Schnorr Signature",
    "- source-domain": "blockchain",
    "- status": "complete",
    "- version": "1.0.0",
    "- last-updated": "2025-10-28",
    "- definition": "Cryptographic digital signature scheme based on discrete logarithm problem hardness, providing efficient, aggregatable, and provably secure signatures for Bitcoin transactions, enabling multi-signature constructions (MuSig2), threshold signatures (FROST), enhanced privacy through signature indistinguishability, and reduced blockchain footprint via signature aggregation in Taproot.",
    "- maturity": "production",
    "- source": "[[BIP 340 Schnorr Signatures]], [[BIP 341 Taproot]], [[MuSig2 Specification]], [[FROST Protocol]], [[Bitcoin Core 2025]]",
    "- authority-score": "0.98",
    "- owl:class": "bc:SchnorrSignature",
    "- owl:physicality": "VirtualEntity",
    "- owl:role": "Object",
    "- owl:inferred-class": "bc:VirtualObject",
    "- belongsToDomain": "[[CryptographicDomain]]",
    "- blockchainRelevance": "Critical",
    "- lastValidated": "2025-11-14",
    "- qualityScore": "0.98",
    "- bitcoinSpecific": "true",
    "- implementedInLayer": "[[CryptographicLayer]], [[SignatureLayer]], [[PrivacyLayer]]",
    "- is-subclass-of": "[[Blockchain Entity]], [[CryptographicPrimitive]], [[Digital Signature Scheme]]",
    "- alternative-to": "[[ECDSA Signature]]",
    "- enables": "[[Taproot]], [[Multi-Signature Wallets]], [[Threshold Signatures]], [[Signature Aggregation]]",
    "- implements": "[[MuSig2 Protocol]], [[FROST Protocol]]",
    "- uses": "[[secp256k1 Elliptic Curve]], [[SHA256 Hash Function]]",
    "- related-to": "[[Bitcoin Smart Contracts AI]], [[Lightning Network]], [[Privacy-Preserving Transactions]]",
    "- integrated-with": "[[Bitcoin Core]], [[Taproot Upgrade]], [[P2TR Addresses]]"
  },
  "backlinks": [
    "Digital Signature",
    "Smart Contract Platform"
  ],
  "wiki_links": [
    "Bitcoin Core",
    "IEEE 2418.1",
    "Blockchain Entity",
    "Taproot",
    "P2TR Addresses",
    "ECDSA Signature",
    "FROST Protocol",
    "ISO/IEC 23257:2021",
    "SHA256 Hash Function",
    "PrivacyLayer",
    "Digital Signature Scheme",
    "BIP 341 Taproot",
    "CryptographicDomain",
    "CryptographicLayer",
    "Multi-Signature Wallets",
    "Privacy-Preserving Transactions",
    "Threshold Signatures",
    "MuSig2 Specification",
    "Lightning Network",
    "komlo2020frost",
    "CryptographicPrimitive",
    "Bitcoin Core 2025",
    "Signature Aggregation",
    "Taproot Upgrade",
    "secp256k1 Elliptic Curve",
    "SignatureLayer",
    "MuSig2 Protocol",
    "BIP 340 Schnorr Signatures",
    "NIST NISTIR",
    "Bitcoin Smart Contracts AI"
  ],
  "ontology": {
    "term_id": "BC-0041",
    "preferred_term": "Schnorr Signature",
    "definition": "Cryptographic digital signature scheme based on discrete logarithm problem hardness, providing efficient, aggregatable, and provably secure signatures for Bitcoin transactions, enabling multi-signature constructions (MuSig2), threshold signatures (FROST), enhanced privacy through signature indistinguishability, and reduced blockchain footprint via signature aggregation in Taproot.",
    "source_domain": "blockchain",
    "maturity_level": null,
    "authority_score": 0.98
  }
}