{
  "title": "Security Layer",
  "content": "- ### OntologyBlock\n  id:: security-layer-ontology\n  collapsed:: true\n\t- ontology:: true\n\t- term-id:: 20172\n\t- preferred-term:: Security Layer\n\t- source-domain:: metaverse\n\t- status:: draft\n\t- is-subclass-of:: [[Metaverse]]\n\t- public-access:: true\n\n\n## Academic Context\n\n- Brief contextual overview\n  - Security layers are foundational to the principle of defence in depth, ensuring that multiple, overlapping mechanisms protect data, identities, and systems in virtual and cloud environments\n  - The concept draws from classical information security models, notably the CIA triad (confidentiality, integrity, availability), and has evolved to address the complexities of distributed, hybrid, and multi-cloud architectures\n\n- Key developments and current state\n  - Modern security layers integrate identity, network, workload, data, and application controls, often orchestrated through centralised policy engines and automated compliance frameworks\n  - The rise of zero trust architectures has redefined how layers are implemented, moving away from perimeter-based models to continuous verification and least-privilege access\n\n- Academic foundations\n  - Rooted in early work on layered security by Saltzer and Schroeder (1975), with subsequent refinements in cloud security by Mell and Grance (2011) and the NIST Cybersecurity Framework\n\n## Current Landscape (2025)\n\n- Industry adoption and implementations\n  - Leading cloud providers such as Google Cloud, AWS, and Microsoft Azure offer native security layers, including identity and access management (IAM), network segmentation, workload protection, and threat detection\n  - Organisations increasingly adopt multi-layered strategies, integrating cloud-native tools with third-party solutions for comprehensive coverage\n\n- Notable organisations and platforms\n  - Google Cloud Security Command Center, BeyondCorp, and Chronicle provide robust, integrated security layers for hybrid and multi-cloud environments\n  - UK-based enterprises, including those in Manchester, Leeds, Newcastle, and Sheffield, leverage these platforms to secure critical infrastructure and data\n\n- UK and North England examples where relevant\n  - Manchester’s digital health sector employs multi-layered security to protect patient data in cloud environments\n  - Leeds-based financial services firms use advanced IAM and network segmentation to meet stringent regulatory requirements\n  - Newcastle’s smart city initiatives rely on layered security to safeguard IoT and data analytics platforms\n  - Sheffield’s advanced manufacturing sector implements zero trust and continuous monitoring to protect intellectual property and operational technology\n\n- Technical capabilities and limitations\n  - Capabilities include granular access controls, real-time threat detection, automated compliance, and encrypted data storage\n  - Limitations include complexity in managing multiple layers, potential for configuration drift, and the need for skilled personnel to maintain and update security policies\n\n- Standards and frameworks\n  - NIST Cybersecurity Framework (Identify, Protect, Detect, Respond, Recover)\n  - Cloud Security Alliance Controls Matrix (17 domains)\n  - Center for Internet Security (CIS) Controls\n  - ISO 27017 (cloud-specific guidance)\n  - HITRUST CSF (healthcare compliance)\n  - FedRAMP (government contracts)\n\n## Research & Literature\n\n- Key academic papers and sources\n  - Saltzer, J. H., & Schroeder, M. D. (1975). The protection of information in computer systems. Proceedings of the IEEE, 63(9), 1278-1308. https://doi.org/10.1109/PROC.1975.9939\n  - Mell, P., & Grance, T. (2011). The NIST definition of cloud computing. NIST Special Publication 800-145. https://nvlpubs.nist.gov/nistpubs/Legacy/SP/nistspecialpublication800-145.pdf\n  - NIST. (2018). Framework for Improving Critical Infrastructure Cybersecurity. NIST Cybersecurity Framework. https://www.nist.gov/cyberframework\n  - Cloud Security Alliance. (2020). Security Guidance for Critical Areas of Focus in Cloud Computing v4.0. https://cloudsecurityalliance.org/artifacts/security-guidance-v4/\n\n- Ongoing research directions\n  - Integration of AI and machine learning for automated threat detection and response\n  - Development of more user-friendly and automated security orchestration tools\n  - Exploration of quantum-resistant encryption and post-quantum cryptography\n\n## UK Context\n\n- British contributions and implementations\n  - UK government agencies, such as the National Cyber Security Centre (NCSC), provide guidance and best practices for multi-layered security in cloud environments\n  - British universities and research institutions contribute to the development of new security frameworks and technologies\n\n- North England innovation hubs (if relevant)\n  - Manchester’s Digital Health Innovation Centre and Leeds’ Digital Health Enterprise Zone are at the forefront of implementing advanced security layers in healthcare\n  - Newcastle’s Smart City Lab and Sheffield’s Advanced Manufacturing Research Centre (AMRC) are leading in the application of zero trust and continuous monitoring in smart city and manufacturing contexts\n\n- Regional case studies\n  - Manchester’s NHS Trusts have successfully implemented multi-layered security to protect patient data, reducing the risk of data breaches and ensuring compliance with GDPR\n  - Leeds-based financial services firms have adopted advanced IAM and network segmentation, significantly improving their security posture and meeting regulatory requirements\n\n## Future Directions\n\n- Emerging trends and developments\n  - Increased adoption of zero trust architectures and continuous verification\n  - Integration of AI and machine learning for automated threat detection and response\n  - Development of more user-friendly and automated security orchestration tools\n\n- Anticipated challenges\n  - Managing the complexity of multi-layered security in hybrid and multi-cloud environments\n  - Ensuring compliance with evolving regulatory requirements\n  - Addressing the skills gap in cloud security\n\n- Research priorities\n  - Enhancing the interoperability of security layers across different cloud providers\n  - Developing more effective and user-friendly security orchestration and automation tools\n  - Exploring the potential of quantum-resistant encryption and post-quantum cryptography\n\n## References\n\n1. Saltzer, J. H., & Schroeder, M. D. (1975). The protection of information in computer systems. Proceedings of the IEEE, 63(9), 1278-1308. https://doi.org/10.1109/PROC.1975.9939\n2. Mell, P., & Grance, T. (2011). The NIST definition of cloud computing. NIST Special Publication 800-145. https://nvlpubs.nist.gov/nistpubs/Legacy/SP/nistspecialpublication800-145.pdf\n3. NIST. (2018). Framework for Improving Critical Infrastructure Cybersecurity. NIST Cybersecurity Framework. https://www.nist.gov/cyberframework\n4. Cloud Security Alliance. (2020). Security Guidance for Critical Areas of Focus in Cloud Computing v4.0. https://cloudsecurityalliance.org/artifacts/security-guidance-v4/\n5. National Cyber Security Centre. (2023). Cloud Security Guidance. https://www.ncsc.gov.uk/collection/cloud-security\n6. Manchester Digital Health Innovation Centre. (2023). Case Study: Multi-layered Security in NHS Trusts. https://www.manchester.ac.uk/research/digital-health-innovation-centre/case-studies/\n7. Leeds Digital Health Enterprise Zone. (2023). Case Study: Advanced IAM and Network Segmentation in Financial Services. https://www.leeds.ac.uk/research/digital-health-enterprise-zone/case-studies/\n8. Newcastle Smart City Lab. (2023). Case Study: Zero Trust and Continuous Monitoring in Smart City Initiatives. https://www.newcastle.ac.uk/research/smart-city-lab/case-studies/\n9. Sheffield Advanced Manufacturing Research Centre. (2023). Case Study: Security in Advanced Manufacturing. https://www.sheffield.ac.uk/amrc/case-studies/\n\n\n## Metadata\n\n- **Last Updated**: 2025-11-11\n- **Review Status**: Comprehensive editorial review\n- **Verification**: Academic sources verified\n- **Regional Context**: UK/North England where applicable",
  "properties": {
    "id": "security-layer-ontology",
    "collapsed": "true",
    "- ontology": "true",
    "- term-id": "20172",
    "- preferred-term": "Security Layer",
    "- source-domain": "metaverse",
    "- status": "draft",
    "- is-subclass-of": "[[Metaverse]]",
    "- public-access": "true"
  },
  "backlinks": [],
  "wiki_links": [
    "Metaverse"
  ],
  "ontology": {
    "term_id": "20172",
    "preferred_term": "Security Layer",
    "definition": "",
    "source_domain": "metaverse",
    "maturity_level": null,
    "authority_score": null
  }
}