{
  "title": "Self Attention",
  "content": "- ### OntologyBlock\n  id:: self-attention-ontology\n  collapsed:: true\n\t- ontology:: true\n\t- term-id:: AI-0197\n\t- preferred-term:: Self Attention\n\t- source-domain:: ai\n\t- status:: draft\n    - public-access:: true\n\t- definition:: An attention mechanism where every token in a sequence attends to every other token in the same sequence, allowing the model to capture intra-sequence dependencies.\n\n\n\n## Academic Context\n\n- Self-attention is an attention mechanism where every token in a sequence attends to every other token within the same sequence, enabling models to capture intra-sequence dependencies effectively.\n  - It forms the core of the Transformer architecture introduced by Vaswani et al. (2017), which revolutionised natural language processing by replacing recurrent structures with parallelisable attention layers.\n  - The mechanism uses learned weight matrices to project input embeddings into queries, keys, and values, which interact via scaled dot-product attention to compute context-aware representations.\n  - This approach allows models to weigh the relevance of different tokens dynamically, improving understanding of long-range dependencies without the sequential bottlenecks of RNNs or LSTMs.\n\n## Current Landscape (2025)\n\n- Self-attention is widely adopted across industry, powering large language models (LLMs), vision transformers, and graph attention networks.\n  - Notable platforms include OpenAI’s GPT series, Google’s BERT and T5, and various open-source frameworks utilising Transformer-based architectures.\n  - Recent innovations focus on efficiency improvements, such as \"shared weight self-attention\" which reduces parameters by over 60% while maintaining or improving performance on benchmarks like GLUE and SQuAD.\n- In the UK, especially in North England, AI research hubs in Manchester and Leeds are integrating self-attention mechanisms into NLP and bioinformatics applications.\n  - For example, Manchester’s AI research groups have contributed to optimising Transformer models for domain-specific tasks, including healthcare data analysis.\n- Technical capabilities:\n  - Self-attention excels at modelling complex dependencies but remains computationally intensive, especially for very long sequences.\n  - Current research addresses scaling challenges through sparse attention, low-rank approximations, and parameter sharing.\n- Standards and frameworks:\n  - Transformer-based models with self-attention are standardised in many machine learning libraries (e.g., Hugging Face Transformers, TensorFlow, PyTorch).\n  - Benchmarks like GLUE, SuperGLUE, and SQuAD remain key for evaluating self-attention model performance.\n\n## Research & Literature\n\n- Key academic papers:\n  - Vaswani, A., Shazeer, N., Parmar, N., et al. (2017). *Attention Is All You Need*. Advances in Neural Information Processing Systems, 30, 5998–6008. [DOI: 10.5555/3295222.3295349]\n  - Kowsher, M., Prottasha, N. J., Yu, C.-N., Garibay, O. O., & Yousefi, N. (2025). *Shared Weight Self-Attention: Parameter-Efficient Transformer Models*. arXiv preprint arXiv:2412.00359. [URL: https://arxiv.org/abs/2412.00359]\n  - Bahdanau, D., Cho, K., & Bengio, Y. (2014). *Neural Machine Translation by Jointly Learning to Align and Translate*. arXiv preprint arXiv:1409.0473.\n- Ongoing research directions:\n  - Efficiency improvements via parameter sharing and sparse attention.\n  - Extending self-attention to non-sequential data such as graphs.\n  - Robustness to noisy and out-of-domain data.\n  - Interpretability and explainability of attention weights.\n\n## UK Context\n\n- The UK has a strong presence in Transformer and self-attention research, with institutions like the University of Manchester and University of Leeds leading projects on NLP and healthcare AI.\n  - Manchester’s AI research centres focus on adapting self-attention for clinical text analysis and patient data modelling.\n  - Leeds is notable for applying attention mechanisms in environmental and chemical data modelling.\n- North England innovation hubs:\n  - Sheffield and Newcastle are emerging centres for AI startups leveraging self-attention in natural language understanding and computer vision.\n  - Collaborative initiatives between academia and industry in these cities foster practical applications of self-attention models.\n- Regional case studies:\n  - A Manchester-based project successfully applied self-attention models to improve diagnostic accuracy in radiology reports, demonstrating the mechanism’s utility beyond pure language tasks.\n\n## Future Directions\n\n- Emerging trends:\n  - Development of more parameter- and compute-efficient self-attention variants to enable deployment on edge devices.\n  - Integration of self-attention with other modalities (e.g., audio, video, sensor data) for multimodal AI systems.\n  - Advances in unsupervised and few-shot learning leveraging self-attention’s contextual capabilities.\n- Anticipated challenges:\n  - Balancing model complexity with interpretability.\n  - Managing the environmental impact of large-scale self-attention models.\n  - Addressing biases encoded in attention patterns.\n- Research priorities:\n  - Enhancing robustness and generalisation in diverse real-world settings.\n  - Exploring biologically inspired attention mechanisms to inform artificial models.\n  - Expanding UK and North England’s role in global self-attention research through collaborative funding and infrastructure.\n\n## References\n\n1. Vaswani, A., Shazeer, N., Parmar, N., Uszkoreit, J., Jones, L., Gomez, A. N., Kaiser, Ł., & Polosukhin, I. (2017). Attention Is All You Need. *Advances in Neural Information Processing Systems*, 30, 5998–6008. https://doi.org/10.5555/3295222.3295349\n\n2. Kowsher, M., Prottasha, N. J., Yu, C.-N., Garibay, O. O., & Yousefi, N. (2025). Shared Weight Self-Attention: Parameter-Efficient Transformer Models. *arXiv preprint* arXiv:2412.00359. https://arxiv.org/abs/2412.00359\n\n3. Bahdanau, D., Cho, K., & Bengio, Y. (2014). Neural Machine Translation by Jointly Learning to Align and Translate. *arXiv preprint* arXiv:1409.0473. https://arxiv.org/abs/1409.0473\n\n4. Additional sources include technical blogs and IBM’s overview on attention mechanisms, which provide accessible explanations without compromising technical accuracy.\n\n\n## Metadata\n\n- **Last Updated**: 2025-11-11\n- **Review Status**: Comprehensive editorial review\n- **Verification**: Academic sources verified\n- **Regional Context**: UK/North England where applicable",
  "properties": {
    "id": "self-attention-ontology",
    "collapsed": "true",
    "- ontology": "true",
    "- term-id": "AI-0197",
    "- preferred-term": "Self Attention",
    "- source-domain": "ai",
    "- status": "draft",
    "- public-access": "true",
    "- definition": "An attention mechanism where every token in a sequence attends to every other token in the same sequence, allowing the model to capture intra-sequence dependencies."
  },
  "backlinks": [
    "Deep Learning",
    "Transformers",
    "Variational Autoencoders",
    "Large language models"
  ],
  "wiki_links": [],
  "ontology": {
    "term_id": "AI-0197",
    "preferred_term": "Self Attention",
    "definition": "An attention mechanism where every token in a sequence attends to every other token in the same sequence, allowing the model to capture intra-sequence dependencies.",
    "source_domain": "ai",
    "maturity_level": null,
    "authority_score": null
  }
}