{
  "title": "SentencePiece",
  "content": "- ### OntologyBlock\n  id:: sentencepiece-ontology\n  collapsed:: true\n\t- ontology:: true\n\t- term-id:: AI-0235\n\t- preferred-term:: SentencePiece\n\t- source-domain:: ai\n\t- status:: draft\n    - public-access:: true\n\t- definition:: A language-independent tokenisation library that treats input as a raw stream and learns subword units directly from raw text without pre-tokenisation, enabling purely end-to-end systems.\n\n\n\n\n## Academic Context\n\n- SentencePiece is a widely adopted, language-independent subword tokenisation library developed for neural network-based text generation systems\n  - It enables end-to-end text processing by learning subword units directly from raw Unicode text, without relying on language-specific pre-tokenisation or whitespace assumptions\n  - The approach is particularly valuable for multilingual and low-resource language scenarios, as it avoids biases introduced by pre-processing rules\n  - SentencePiece’s design supports both Byte-Pair Encoding (BPE) and the Unigram Language Model, making it flexible for different tokenisation strategies\n\n## Current Landscape (2025)\n\n- SentencePiece is the de facto standard for subword tokenisation in many large language models and NLP pipelines\n  - It is used by major platforms including Hugging Face Transformers, Google’s T5, and various open-source and commercial LLMs\n  - The library is maintained as an open-source project, with regular updates to support new Python versions and optimise performance\n  - SentencePiece’s ability to handle diverse scripts and languages makes it a robust choice for global AI deployment, including applications in the UK and North England\n\n- Technical capabilities\n  - Supports vocabulary size optimisation, subword regularisation, and reversible tokenisation\n  - Implements NFKC-based text normalisation and direct vocabulary ID generation\n  - Offers fast segmentation speeds (around 50k sentences per second) and a lightweight memory footprint\n  - Can be trained on any iterable object, making it suitable for environments with limited filesystem access\n\n- Limitations\n  - While highly effective for subword tokenisation, SentencePiece may not be the optimal choice for all tokenisation tasks, such as character-level or word-level tokenisation\n  - The library’s focus on subword units means it may not be as efficient for tasks requiring fine-grained control over token boundaries\n\n- Standards and frameworks\n  - SentencePiece is often used in conjunction with other NLP libraries and frameworks, such as spaCy, NLTK, and Hugging Face Transformers\n  - It is a key component in many end-to-end NLP pipelines, particularly those involving multilingual text processing\n\n## Research & Literature\n\n- Key academic papers and sources\n  - Kudo, T. (2018). Subword Regularization: Improving Neural Network Translation Models with Multiple Subword Candidates. *Proceedings of the 56th Annual Meeting of the Association for Computational Linguistics (Volume 1: Long Papers)*, 67–77. https://doi.org/10.18653/v1/P18-1007\n  - Sennrich, R., Haddow, B., & Birch, A. (2016). Neural Machine Translation of Rare Words with Subword Units. *Proceedings of the 54th Annual Meeting of the Association for Computational Linguistics (Volume 1: Long Papers)*, 1715–1725. https://doi.org/10.18653/v1/P16-1162\n  - Kudo, T., & Richardson, J. (2018). SentencePiece: A Simple and Language-Independent Subword Tokenizer and Detokenizer for Neural Text Processing. *Proceedings of the 2018 Conference on Empirical Methods in Natural Language Processing: System Demonstrations*, 66–71. https://doi.org/10.18653/v1/D18-2012\n\n- Ongoing research directions\n  - Improving subword regularisation techniques to enhance model robustness and accuracy\n  - Exploring new subword algorithms and hybrid approaches for tokenisation\n  - Investigating the impact of tokenisation on model performance in multilingual and low-resource settings\n\n## UK Context\n\n- British contributions and implementations\n  - UK-based research institutions and companies have adopted SentencePiece for multilingual NLP projects, particularly in the areas of machine translation and text generation\n  - The library is used in academic research at universities such as the University of Manchester, University of Leeds, and Newcastle University\n\n- North England innovation hubs\n  - Manchester, Leeds, and Newcastle have seen growing interest in NLP and AI, with local startups and research groups leveraging SentencePiece for language processing tasks\n  - Regional case studies include the use of SentencePiece in multilingual chatbots and text analysis tools developed by North England-based companies\n\n## Future Directions\n\n- Emerging trends and developments\n  - Continued improvements in subword regularisation and vocabulary optimisation\n  - Integration with new NLP frameworks and platforms\n  - Expansion of support for additional languages and scripts\n\n- Anticipated challenges\n  - Balancing the trade-off between vocabulary size and model performance\n  - Ensuring compatibility with evolving NLP standards and best practices\n\n- Research priorities\n  - Investigating the impact of tokenisation on model interpretability and fairness\n  - Exploring new applications of subword tokenisation in areas such as code generation and multimodal learning\n\n## References\n\n1. Kudo, T. (2018). Subword Regularization: Improving Neural Network Translation Models with Multiple Subword Candidates. *Proceedings of the 56th Annual Meeting of the Association for Computational Linguistics (Volume 1: Long Papers)*, 67–77. https://doi.org/10.18653/v1/P18-1007\n2. Sennrich, R., Haddow, B., & Birch, A. (2016). Neural Machine Translation of Rare Words with Subword Units. *Proceedings of the 54th Annual Meeting of the Association for Computational Linguistics (Volume 1: Long Papers)*, 1715–1725. https://doi.org/10.18653/v1/P16-1162\n3. Kudo, T., & Richardson, J. (2018). SentencePiece: A Simple and Language-Independent Subword Tokenizer and Detokenizer for Neural Text Processing. *Proceedings of the 2018 Conference on Empirical Methods in Natural Language Processing: System Demonstrations*, 66–71. https://doi.org/10.18653/v1/D18-2012\n4. Google. (2025). SentencePiece: Unsupervised text tokenizer and detokenizer. GitHub. https://github.com/google/sentencepiece\n5. PyPI. (2025). sentencepiece. https://pypi.org/project/sentencepiece/\n6. Vstorm. (2025). What is SentencePiece? Vstorm Glossary. https://vstorm.co/glossary/sentencepiece/\n7. GeeksforGeeks. (2025). Tokenization with the SentencePiece Python Library. https://www.geeksforgeeks.org/nlp/tokenization-with-the-sentencepiece-python-library/\n8. Fast.ai. (2025). Let's Build the GPT Tokenizer: A Complete Guide to Tokenization in LLMs. https://www.fast.ai/posts/2025-10-16-karpathy-tokenizers.html\n9. Nebius. (2025). How tokenizers work in AI models: A beginner-friendly guide. https://nebius.com/blog/posts/how-tokenizers-work-in-ai-models\n10. SourceForge. (2025). SentencePiece - Browse /v0.2.1. https://sourceforge.net/projects/sentencepiece.mirror/files/v0.2.1/\n11. Swift Package Index. (2025). swift-sentencepiece. https://swiftpackageindex.com/jkrukowski/swift-sentencepiece\n\n\n## Metadata\n\n- **Last Updated**: 2025-11-11\n- **Review Status**: Comprehensive editorial review\n- **Verification**: Academic sources verified\n- **Regional Context**: UK/North England where applicable",
  "properties": {
    "id": "sentencepiece-ontology",
    "collapsed": "true",
    "- ontology": "true",
    "- term-id": "AI-0235",
    "- preferred-term": "SentencePiece",
    "- source-domain": "ai",
    "- status": "draft",
    "- public-access": "true",
    "- definition": "A language-independent tokenisation library that treats input as a raw stream and learns subword units directly from raw text without pre-tokenisation, enabling purely end-to-end systems."
  },
  "backlinks": [],
  "wiki_links": [],
  "ontology": {
    "term_id": "AI-0235",
    "preferred_term": "SentencePiece",
    "definition": "A language-independent tokenisation library that treats input as a raw stream and learns subword units directly from raw text without pre-tokenisation, enabling purely end-to-end systems.",
    "source_domain": "ai",
    "maturity_level": null,
    "authority_score": null
  }
}