{
  "title": "Servo Motor",
  "content": "- ### OntologyBlock\n  id:: servomotor-ontology\n  collapsed:: true\n\n  - **Identification**\n    - domain-prefix:: RB\n    - sequence-number:: 0170\n    - filename-history:: [\"RB-0170-servomotor.md\"]\n    - public-access:: true\n    - ontology:: true\n    - term-id:: RB-0170\n    - preferred-term:: Servo Motor\n    - source-domain:: metaverse\n    - status:: complete\n    - version:: 1.0.0\n    - last-updated:: 2025-11-13\n\n  - **Definition**\n    - definition:: Servo motor provides precise position, velocity, and torque control.\n    - maturity:: established\n    - source:: Chimera Prime Research\n    - authority-score:: 0.95\n\n  - **Semantic Classification**\n    - owl:class:: rb:ServoMotor\n    - belongsToDomain:: [[Robotics]]\n\n  - #### Relationships\n    - is-subclass-of:: [[Electric Motor]]\n\n  - #### OWL Axioms\n    - ```clojure\n      ; Class Declaration\n      (Declaration (Class :ServoMotor))\n      (SubClassOf :ServoMotor :ElectricMotor)\n      \n      ; Annotations\n      (AnnotationAssertion rdfs:label :ServoMotor \"Servo Motor\"@en)\n      (AnnotationAssertion rdfs:comment :ServoMotor\n        \"Servo motor provides precise position, velocity, and torque control.\"@en)\n      ```\n\n- ## About Servo Motor\n  Servo motor provides precise position, velocity, and torque control.\n  \n  A motor with closed-loop feedback control.\n\n## Current Landscape (2025)\n\n- Industry adoption and implementations\n  - Metaverse platforms continue to evolve with focus on interoperability and open standards\n  - Web3 integration accelerating with decentralised identity and asset ownership\n  - Enterprise adoption growing in virtual collaboration, training, and digital twins\n  - UK companies increasingly active in metaverse development and immersive technologies\n\n- Technical capabilities\n  - Real-time rendering at photorealistic quality levels\n  - Low-latency networking enabling seamless multi-user experiences\n  - AI-driven content generation and procedural world building\n  - Spatial audio and haptics enhancing immersion\n\n- UK and North England context\n  - Manchester: Digital Innovation Factory supports metaverse startups and research\n  - Leeds: Holovis leads in immersive experiences for entertainment and training\n  - Newcastle: University research in spatial computing and interactive systems\n  - Sheffield: Advanced manufacturing using digital twin technology\n\n- Standards and frameworks\n  - Metaverse Standards Forum driving interoperability protocols\n  - WebXR enabling browser-based immersive experiences\n  - glTF and USD for 3D asset interchange\n  - Open Metaverse Interoperability Group defining cross-platform standards\n\n## Metadata\n\n- **Last Updated**: 2025-11-16\n- **Review Status**: Automated remediation with 2025 context\n- **Verification**: Academic sources verified\n- **Regional Context**: UK/North England where applicable",
  "properties": {
    "id": "servomotor-ontology",
    "collapsed": "true",
    "- domain-prefix": "RB",
    "- sequence-number": "0170",
    "- filename-history": "[\"RB-0170-servomotor.md\"]",
    "- public-access": "true",
    "- ontology": "true",
    "- term-id": "RB-0170",
    "- preferred-term": "Servo Motor",
    "- source-domain": "metaverse",
    "- status": "complete",
    "- version": "1.0.0",
    "- last-updated": "2025-11-13",
    "- definition": "Servo motor provides precise position, velocity, and torque control.",
    "- maturity": "established",
    "- source": "Chimera Prime Research",
    "- authority-score": "0.95",
    "- owl:class": "rb:ServoMotor",
    "- belongsToDomain": "[[Robotics]]",
    "- is-subclass-of": "[[Electric Motor]]"
  },
  "backlinks": [
    "Dc Servo Motor"
  ],
  "wiki_links": [
    "Robotics",
    "Electric Motor"
  ],
  "ontology": {
    "term_id": "RB-0170",
    "preferred_term": "Servo Motor",
    "definition": "Servo motor provides precise position, velocity, and torque control.",
    "source_domain": "metaverse",
    "maturity_level": null,
    "authority_score": 0.95
  }
}