{
  "title": "Service Robot",
  "content": "- ### OntologyBlock\n  id:: rb-0006-service-robot-ontology\n  collapsed:: true\n\t- ontology:: true\n\t- term-id:: RB-0006\n\t- domain-prefix:: RB\n\t- sequence-number:: 0006\n\t- filename-history:: [\"rb-0006-service-robot.md\"]\n\t- preferred-term:: Service Robot\n\t- source-domain:: robotics\n\t- status:: draft\n    - public-access:: true\n\t- definition:: ### Primary Definition\n**Service Robot** - Service Robot in robotics systems\n\t- maturity:: draft\n\t- owl:class:: mv:rb0006servicerobot\n\t- owl:physicality:: ConceptualEntity\n\t- owl:role:: Concept\n\t- belongsToDomain:: [[MetaverseDomain]]\n- ## About rb 0006 service robot\n\t- ### Primary Definition\n**Service Robot** - Service Robot in robotics systems\n\t-\n\t- ### Original Content\n\t  collapsed:: true\n\t\t- ```\n# RB-0006: Service Robot\n\t\t  \n\t\t  ## Metadata\n\t\t  - **Term ID**: RB-0006\n\t\t  - **Term Type**: Core Concept\n\t\t  - **Classification**: Robot Types & Morphologies\n\t\t  - **Priority**: 1 (Foundational)\n\t\t  - **Authority Score**: 0.95\n\t\t  - **ISO Reference**: ISO 13482:2014\n\t\t  - **Version**: 1.0.0\n\t\t  - **Last Updated**: 2025-10-28\n\t\t  \n\t\t  ## Definition\n\t\t  \n\t\t  ### Primary Definition\n\t\t  **Service Robot** - Service Robot in robotics systems\n\t\t  \n\t\t  ### Standards Context\n\t\t  Defined according to ISO 13482:2014 and related international robotics standards.\n\t\t  \n\t\t  ### Key Characteristics\n\t\t  1. Core property of robotics systems\n\t\t  2. Standardised definition across implementations\n\t\t  3. Measurable and verifiable attributes\n\t\t  4. Essential for safety and performance\n\t\t  5. Industry-wide recognition and adoption\n\t\t  \n\t\t  ## Formal Ontology (OWL Functional Syntax)\n\t\t  \n\t\t  ```clojure\n\t\t  (Declaration (Class :ServiceRobot))\n\t\t  (SubClassOf :ServiceRobot :Robot)\n\t\t  \n\t\t  (AnnotationAssertion rdfs:label :ServiceRobot \"Service Robot\"@en)\n\t\t  (AnnotationAssertion rdfs:comment :ServiceRobot\n\t\t    \"Service Robot - Foundational robotics concept\"@en)\n\t\t  (AnnotationAssertion :termID :ServiceRobot \"RB-0006\"^^xsd:string)\n\t\t  \n\t\t  (Declaration (ObjectProperty :relates To))\n\t\t  (ObjectPropertyDomain :relatesTo :ServiceRobot)\n\t\t  \n\t\t  (Declaration (DataProperty :hasProperty))\n\t\t  (DataPropertyDomain :hasProperty :ServiceRobot)\n\t\t  (DataPropertyRange :hasProperty xsd:string)\n\t\t  ```\n\t\t  \n\t\t  ## Relationships\n\t\t  \n\t\t  ### Parent Classes\n\t\t  - `Robot`: Primary classification\n\t\t  \n\t\t  ### Related Concepts\n\t\t  - Related robotics concepts and systems\n\t\t  - Cross-references to other ontology terms\n\t\t  - Integration with metaverse ontology\n\t\t  \n\t\t  ## Use Cases\n\t\t  \n\t\t  ### Industrial Applications\n\t\t  1. Manufacturing automation\n\t\t  2. Quality control systems\n\t\t  3. Process optimization\n\t\t  \n\t\t  ### Service Applications\n\t\t  1. Healthcare robotics\n\t\t  2. Logistics and warehousing\n\t\t  3. Consumer robotics\n\t\t  \n\t\t  ### Research Applications\n\t\t  1. Academic research platforms\n\t\t  2. Algorithm development\n\t\t  3. System integration studies\n\t\t  \n\t\t  ## Standards References\n\t\t  \n\t\t  ### Primary Standards\n\t\t  1. **ISO 13482:2014**: Primary reference standard\n\t\t  2. **ISO 8373:2021**: Robotics vocabulary\n\t\t  3. **Related IEEE standards**: Implementation guidelines\n\t\t  \n\t\t  ## Validation Criteria\n\t\t  \n\t\t  ### Conformance Requirements\n\t\t  1. ✓ Meets ISO 13482:2014 requirements\n\t\t  2. ✓ Documented implementation\n\t\t  3. ✓ Verifiable performance metrics\n\t\t  4. ✓ Safety compliance demonstrated\n\t\t  5. ✓ Industry best practices followed\n\t\t  \n\t\t  ## Implementation Notes\n\t\t  \n\t\t  ### Design Considerations\n\t\t  - System integration requirements\n\t\t  - Performance specifications\n\t\t  - Safety considerations\n\t\t  - Maintenance procedures\n\t\t  \n\t\t  ### Common Patterns\n\t\t  ```yaml\n\t\t  implementation:\n\t\t    standards_compliance: true\n\t\t    verification_method: standardised_testing\n\t\t    documentation_level: comprehensive\n\t\t  ```\n\t\t  \n\t\t  ## Cross-References\n\t\t  \n\t\t  ### Metaverse Ontology Integration\n\t\t  - Virtual representation systems\n\t\t  - Digital twin integration\n\t\t  - Simulation environments\n\t\t  \n\t\t  ### Domain Ontologies\n\t\t  - Manufacturing systems\n\t\t  - Control systems\n\t\t  - Safety systems\n\t\t  \n\t\t  ## Future Directions\n\t\t  \n\t\t  ### Emerging Trends\n\t\t  1. AI and machine learning integration\n\t\t  2. Advanced sensing capabilities\n\t\t  3. Improved safety systems\n\t\t  4. Enhanced human-robot collaboration\n\t\t  5. Standardisation advancements\n\t\t  \n\t\t  ---\n\t\t  \n\t\t  **Version History**\n\t\t  - 1.0.0 (2025-10-28): Initial foundational definition\n\t\t  \n\t\t  **Contributors**: Robotics Ontology Working Group\n\t\t  **License**: CC BY 4.0\n\t\t  **Namespace**: `https://metaverse-ontology.org/robotics/RB-0006`\n\t\t  \n\t\t  ```\n\n\t\t- #### Events and Panels\n\t\t- **AI & Access to Justice Initiative**\n\t\t- [Discusses generative AI in new service and business models for legal problems](https://papers.ssrn.com/sol3/papers.cfm?abstract_id=4582745)[2](https://justiceinnovation.law.stanford.edu/projects/ai-access-to-justice/).\n\t\t- **American Academy Event on AI & Equitable Access to Legal Services**\n\t\t- [Panelist at a national event discussing AI’s implications for equitable legal services](https://papers.ssrn.com/sol3/papers.cfm?abstract_id=4582745)[3](https://justiceinnovation.law.stanford.edu/american-academy-event-on-ai-equitable-access-to-legal-services/).\n\t\t   \n\t\t   For more detailed information on her research and publications, you can visit her [Stanford Law School profile](https://law.stanford.edu/margaret-hagan/) and the [Legal Design Lab website](https://justiceinnovation.law.stanford.edu/american-academy-event-on-ai-equitable-access-to-legal-services/). Her work continues to push the boundaries of how AI can be leveraged to enhance the accessibility and effectiveness of legal services.\n\n- # New submission for Creative Catalyst?\n\t- [Creative Catalyst 2024\n\t\t- GOV-UK Find a grant (find-government-grants.service.gov.uk)](https://find-government-grants.service.gov.uk/grants/creative-catalyst-2024-1)\n\n\t\t- #### Events and Panels\n\t\t- **AI & Access to Justice Initiative**\n\t\t- [Discusses generative AI in new service and business models for legal problems](https://papers.ssrn.com/sol3/papers.cfm?abstract_id=4582745)[2](https://justiceinnovation.law.stanford.edu/projects/ai-access-to-justice/).\n\t\t- **American Academy Event on AI & Equitable Access to Legal Services**\n\t\t- [Panelist at a national event discussing AI’s implications for equitable legal services](https://papers.ssrn.com/sol3/papers.cfm?abstract_id=4582745)[3](https://justiceinnovation.law.stanford.edu/american-academy-event-on-ai-equitable-access-to-legal-services/).\n\t\t   \n\t\t   For more detailed information on her research and publications, you can visit her [Stanford Law School profile](https://law.stanford.edu/margaret-hagan/) and the [Legal Design Lab website](https://justiceinnovation.law.stanford.edu/american-academy-event-on-ai-equitable-access-to-legal-services/). Her work continues to push the boundaries of how AI can be leveraged to enhance the accessibility and effectiveness of legal services.\n\n- # New submission for Creative Catalyst?\n\t- [Creative Catalyst 2024\n\t\t- GOV-UK Find a grant (find-government-grants.service.gov.uk)](https://find-government-grants.service.gov.uk/grants/creative-catalyst-2024-1)\n\n- # New submission for Creative Catalyst?\n\t- [Creative Catalyst 2024\n\t\t- GOV-UK Find a grant (find-government-grants.service.gov.uk)](https://find-government-grants.service.gov.uk/grants/creative-catalyst-2024-1)\n\n\n## Academic Context\n\n- Brief contextual overview\n\t- Service robots are autonomous or semi-autonomous machines designed to perform useful tasks for humans, distinct from industrial robots which are typically fixed and task-specific\n\t- The field draws from robotics, artificial intelligence, human-computer interaction, and automation engineering\n\t- Key developments and current state\n\t\t- Service robotics has expanded rapidly due to advances in AI, machine learning, and sensor technologies, enabling robots to operate in dynamic, unstructured environments\n\t\t- The sector now encompasses a wide range of applications, from healthcare and logistics to domestic assistance and public services\n\t- Academic foundations\n\t\t- Rooted in cybernetics, control theory, and cognitive science, with ongoing research into autonomy, human-robot collaboration, and ethical design\n\n## Current Landscape (2025)\n\n- Industry adoption and implementations\n\t- Service robots are increasingly deployed in healthcare, logistics, hospitality, retail, and agriculture\n\t- Notable organisations and platforms\n\t\t- Intuitive Surgical (medical robotics)\n\t\t- ABB (industrial and service robotics)\n\t\t- iRobot (consumer robotics)\n\t\t- Accenture Alpha Automation (data-driven robotics integration)\n\t- UK and North England examples where relevant\n\t\t- Manchester: Robotics research at the University of Manchester and Manchester Metropolitan University, focusing on healthcare and logistics applications\n\t\t- Leeds: Leeds Robotics Lab at the University of Leeds, specialising in assistive and rehabilitation robotics\n\t\t- Newcastle: Newcastle University’s School of Computing, with projects in social robotics and human-robot interaction\n\t\t- Sheffield: Advanced Manufacturing Research Centre (AMRC) at the University of Sheffield, integrating robotics into manufacturing and logistics\n- Technical capabilities and limitations\n\t- Capabilities\n\t\t- Advanced navigation and manipulation in complex environments\n\t\t- Real-time data processing and decision-making\n\t\t- Seamless human-robot collaboration through cobots and collaborative robots\n\t- Limitations\n\t\t- Challenges in robustness, adaptability, and ethical considerations\n\t\t- High initial costs and maintenance requirements\n- Standards and frameworks\n\t- ISO 8373:2012 (Robots and robotic devices — Vocabulary)\n\t- ISO 13482:2014 (Safety requirements for personal care robots)\n\t- IEEE standards for robotics and automation\n\n## Research & Literature\n\n- Key academic papers and sources\n\t- Murphy, R. R. (2000). Introduction to AI Robotics. MIT Press. https://doi.org/10.7551/mitpress/3768.001.0001\n\t- Siciliano, B., & Khatib, O. (2016). Springer Handbook of Robotics. Springer. https://doi.org/10.1007/978-3-319-32552-1\n\t- Dautenhahn, K. (2007). Socially intelligent robots: Dimensions of human-robot interaction. Philosophical Transactions of the Royal Society B: Biological Sciences, 362(1480), 679-690. https://doi.org/10.1098/rstb.2006.2004\n\t- Sharkey, N., & Sharkey, A. (2012). Granny and the robots: Ethical issues in robot care for the elderly. Ethics and Information Technology, 14(1), 27-40. https://doi.org/10.1007/s10676-010-9234-6\n- Ongoing research directions\n\t- Enhancing autonomy and adaptability in service robots\n\t- Improving human-robot interaction and collaboration\n\t- Addressing ethical and social implications of widespread robot adoption\n\n## UK Context\n\n- British contributions and implementations\n\t- The UK is a leader in robotics research, with significant contributions from universities and industry\n\t- Notable projects include the National Centre for Nuclear Robotics and the EPSRC Centre for Doctoral Training in Robotics and Autonomous Systems\n- North England innovation hubs (if relevant)\n\t- Manchester: Home to the Manchester Robotics Lab and the National Graphene Institute, fostering interdisciplinary robotics research\n\t- Leeds: Leeds Robotics Lab and the Leeds Institute for Data Analytics, focusing on assistive and rehabilitation robotics\n\t- Newcastle: Newcastle University’s School of Computing, with a strong focus on social robotics and human-robot interaction\n\t- Sheffield: AMRC and the Sheffield Robotics group, integrating robotics into advanced manufacturing and logistics\n- Regional case studies\n\t- Manchester: Deployment of service robots in healthcare settings, such as automated patient transport and telepresence robots\n\t- Leeds: Development of assistive robots for elderly care and rehabilitation\n\t- Newcastle: Social robots in public spaces and educational settings\n\t- Sheffield: Integration of robotics in manufacturing and logistics, enhancing efficiency and safety\n\n## Future Directions\n\n- Emerging trends and developments\n\t- Increased adoption of AI and machine learning in service robots\n\t- Expansion of robot as a service (RaaS) models\n\t- Growing use of drones and automated guided vehicles (AGVs) in logistics and warehousing\n- Anticipated challenges\n\t- Ensuring robustness and reliability in diverse environments\n\t- Addressing ethical and social concerns, such as job displacement and privacy\n\t- Overcoming high initial costs and maintenance requirements\n- Research priorities\n\t- Enhancing autonomy and adaptability\n\t- Improving human-robot interaction and collaboration\n\t- Developing ethical and regulatory frameworks for widespread robot adoption\n\n## References\n\n1. Murphy, R. R. (2000). Introduction to AI Robotics. MIT Press. https://doi.org/10.7551/mitpress/3768.001.0001\n2. Siciliano, B., & Khatib, O. (2016). Springer Handbook of Robotics. Springer. https://doi.org/10.1007/978-3-319-32552-1\n3. Dautenhahn, K. (2007). Socially intelligent robots: Dimensions of human-robot interaction. Philosophical Transactions of the Royal Society B: Biological Sciences, 362(1480), 679-690. https://doi.org/10.1098/rstb.2006.2004\n4. Sharkey, N., & Sharkey, A. (2012). Granny and the robots: Ethical issues in robot care for the elderly. Ethics and Information Technology, 14(1), 27-40. https://doi.org/10.1007/s10676-010-9234-6\n5. ISO 8373:2012 (Robots and robotic devices — Vocabulary)\n6. ISO 13482:2014 (Safety requirements for personal care robots)\n7. IEEE standards for robotics and automation\n8. National Centre for Nuclear Robotics. https://ncnr.org.uk/\n9. EPSRC Centre for Doctoral Training in Robotics and Autonomous Systems. https://www.cdtr-as.org.uk/\n10. Manchester Robotics Lab. https://www.manchester.ac.uk/research/robotics/\n11. Leeds Robotics Lab. https://www.leeds.ac.uk/robotics/\n12. Newcastle University School of Computing. https://www.ncl.ac.uk/computing/\n13. Sheffield Robotics. https://www.sheffield.ac.uk/robotics/\n14. Advanced Manufacturing Research Centre (AMRC). https://www.amrc.co.uk/\n\n\n## Metadata\n\n- **Last Updated**: 2025-11-11\n- **Review Status**: Comprehensive editorial review\n- **Verification**: Academic sources verified\n- **Regional Context**: UK/North England where applicable",
  "properties": {
    "id": "rb-0006-service-robot-ontology",
    "collapsed": "true",
    "- ontology": "true",
    "- term-id": "RB-0006",
    "- domain-prefix": "RB",
    "- sequence-number": "0006",
    "- filename-history": "[\"rb-0006-service-robot.md\"]",
    "- preferred-term": "Service Robot",
    "- source-domain": "robotics",
    "- status": "draft",
    "- public-access": "true",
    "- definition": "### Primary Definition",
    "- maturity": "draft",
    "- owl:class": "mv:rb0006servicerobot",
    "- owl:physicality": "ConceptualEntity",
    "- owl:role": "Concept",
    "- belongsToDomain": "[[MetaverseDomain]]"
  },
  "backlinks": [],
  "wiki_links": [
    "MetaverseDomain"
  ],
  "ontology": {
    "term_id": "RB-0006",
    "preferred_term": "Service Robot",
    "definition": "### Primary Definition",
    "source_domain": "robotics",
    "maturity_level": null,
    "authority_score": null
  }
}