{
  "title": "Signature Scheme",
  "content": "- ### OntologyBlock\n  id:: signature-scheme-ontology\n  collapsed:: true\n\n  - **Identification**\n\n    - domain-prefix:: BC\n\n    - sequence-number:: 0039\n\n    - filename-history:: [\"BC-0039-signature-scheme.md\"]\n    - public-access:: true\n    - ontology:: true\n    - term-id:: BC-0039\n    - preferred-term:: Signature Scheme\n    - source-domain:: blockchain\n    - status:: complete\n    - version:: 1.0.0\n    - last-updated:: 2025-10-28\n\n  - **Definition**\n    - definition:: Digital signature algorithm within blockchain systems, providing essential functionality for distributed ledger technology operations and properties.\n    - maturity:: mature\n    - source:: [[ISO/IEC 23257:2021]], [[IEEE 2418.1]], [[NIST NISTIR]]\n    - authority-score:: 0.95\n\n  - **Semantic Classification**\n    - owl:class:: bc:SignatureScheme\n    - owl:physicality:: VirtualEntity\n    - owl:role:: Object\n    - owl:inferred-class:: bc:VirtualObject\n    - belongsToDomain:: [[CryptographicDomain]]\n    - implementedInLayer:: [[SecurityLayer]]\n\n  - #### Relationships\n    id:: signature-scheme-relationships\n    - is-subclass-of:: [[Blockchain Entity]], [[CryptographicPrimitive]]\n\n  - #### OWL Axioms\n    id:: signature-scheme-owl-axioms\n    collapsed:: true\n    - ```clojure\n      Prefix(:=<http://metaverse-ontology.org/blockchain#>)\nPrefix(owl:=<http://www.w3.org/2002/07/owl#>)\nPrefix(rdf:=<http://www.w3.org/1999/02/22-rdf-syntax-ns#>)\nPrefix(xml:=<http://www.w3.org/XML/1998/namespace>)\nPrefix(xsd:=<http://www.w3.org/2001/XMLSchema#>)\nPrefix(rdfs:=<http://www.w3.org/2000/01/rdf-schema#>)\nPrefix(dct:=<http://purl.org/dc/terms/>)\n\nOntology(<http://metaverse-ontology.org/blockchain/BC-0039>\n  Import(<http://metaverse-ontology.org/blockchain/core>)\n\n  ## Class Declaration\n  Declaration(Class(:SignatureScheme))\n\n  ## Subclass Relationships\n  SubClassOf(:SignatureScheme :CryptographicPrimitive)\n  SubClassOf(:SignatureScheme :BlockchainEntity)\n\n  ## Essential Properties\n  SubClassOf(:SignatureScheme\n    (ObjectSomeValuesFrom :partOf :Blockchain))\n\n  SubClassOf(:SignatureScheme\n    (ObjectSomeValuesFrom :hasProperty :Property))\n\n  ## Data Properties\n  DataPropertyAssertion(:hasIdentifier :SignatureScheme \"BC-0039\"^^xsd:string)\n  DataPropertyAssertion(:hasAuthorityScore :SignatureScheme \"1.0\"^^xsd:decimal)\n  DataPropertyAssertion(:isFoundational :SignatureScheme \"true\"^^xsd:boolean)\n\n  ## Object Properties\n  ObjectPropertyAssertion(:enablesFeature :SignatureScheme :BlockchainFeature)\n  ObjectPropertyAssertion(:relatesTo :SignatureScheme :RelatedConcept)\n\n  ## Annotations\n  AnnotationAssertion(rdfs:label :SignatureScheme \"Signature Scheme\"@en)\n  AnnotationAssertion(rdfs:comment :SignatureScheme\n    \"Digital signature algorithm\"@en)\n  AnnotationAssertion(dct:description :SignatureScheme\n    \"Foundational blockchain concept with formal ontological definition\"@en)\n  AnnotationAssertion(:termID :SignatureScheme \"BC-0039\")\n  AnnotationAssertion(:priority :SignatureScheme \"1\"^^xsd:integer)\n  AnnotationAssertion(:category :SignatureScheme \"cryptographic-foundations\"@en)\n)\n      ```\n\n- ## About Signature Scheme\n  id:: signature-scheme-about\n\n  - Digital signature algorithm within blockchain systems, providing essential functionality for distributed ledger technology operations and properties.\n  -\n  - ### Key Characteristics\n    id:: signature-scheme-characteristics\n    - 1. **Definitional Property**: Core defining characteristic\n    - 2. **Functional Property**: Operational behavior\n    - 3. **Structural Property**: Compositional elements\n    - 4. **Security Property**: Security guarantees provided\n    - 5. **Performance Property**: Efficiency considerations\n  -\n  - ### Technical Components\n    id:: signature-scheme-components\n    - **Implementation**: How concept is realized technically\n    - **Verification**: Methods for validating correctness\n    - **Interaction**: Relationships with other components\n    - **Constraints**: Technical limitations and requirements\n  -\n  - ### Use Cases\n    id:: signature-scheme-use-cases\n    - **1. Core Blockchain Operation**\n    - **Application**: Fundamental blockchain functionality\n    - **Example**: Practical implementation in major blockchains\n    - **Requirements**: Technical prerequisites\n    - **Benefits**: Value provided to blockchain systems\n  -\n  - ### Standards & References\n    id:: signature-scheme-standards\n    - [[ISO/IEC 23257:2021]] - Blockchain and distributed ledger technologies\n    - [[IEEE 2418.1]] - Blockchain and distributed ledger technologies\n    - [[NIST NISTIR]] - Blockchain and distributed ledger technologies\n  -\n\n\n## Academic Context\n\n- A **signature scheme** is a cryptographic protocol designed to verify the authenticity and integrity of digital messages or documents.\n  - It typically comprises three algorithms:\n    - **Key generation**: Produces a private key and a corresponding public key.\n    - **Signing**: Uses the private key to generate a signature on a message.\n    - **Verification**: Uses the public key to confirm the signature’s validity on the message.\n  - Two essential properties underpin signature schemes:\n    - *Correctness*: Valid signatures created with the private key must be accepted by the verification algorithm using the public key.\n    - *Security*: It should be computationally infeasible to forge a valid signature without the private key, even under chosen-message attacks.\n  - The academic foundation lies in asymmetric cryptography and complexity theory, ensuring signatures are both verifiable and unforgeable under accepted hardness assumptions[1].\n\n## Current Landscape (2025)\n\n- **Industry adoption**:\n  - Signature schemes remain fundamental to digital security, underpinning secure communications, software distribution, blockchain transactions, and legal digital signatures.\n  - Traditional schemes like RSA and ECDSA are still widely used but face obsolescence risks due to quantum computing threats.\n- **Notable developments**:\n  - Post-quantum signature schemes are gaining traction to resist quantum attacks, with hybrid schemes combining classical and post-quantum algorithms for transitional security[4][7].\n  - Threshold signature schemes distribute signing authority among multiple parties, enhancing security by eliminating single points of failure; these are increasingly adopted in blockchain and financial sectors[3][5].\n- **UK and North England examples**:\n  - Manchester and Leeds host cybersecurity research groups advancing post-quantum and threshold signature research.\n  - Sheffield’s tech sector integrates threshold schemes in fintech startups to secure multi-party transactions.\n  - Newcastle’s universities contribute to hybrid signature scheme standards, reflecting the UK’s growing role in cryptographic innovation.\n- **Technical capabilities and limitations**:\n  - Signature schemes offer strong guarantees of authenticity and integrity but must balance computational efficiency and security.\n  - Post-quantum schemes often incur higher computational costs and larger signatures, challenging widespread deployment.\n- **Standards and frameworks**:\n  - NIST and UK’s National Cyber Security Centre (NCSC) provide guidelines on cryptographic algorithm selection, including recommendations for transitioning to post-quantum secure signature schemes[5][8].\n\n## Research & Literature\n\n- Key academic papers and sources:\n  - Goldwasser, S., Micali, S., & Rivest, R. L. (1988). *A Digital Signature Scheme Secure Against Adaptive Chosen-Message Attacks*. SIAM Journal on Computing, 17(2), 281–308. DOI:10.1137/0217025\n  - Bernstein, D. J., et al. (2020). *Post-Quantum Cryptography*. Nature, 549(7671), 188–194. DOI:10.1038/nature23461\n  - Shor, P. W. (1997). *Polynomial-Time Algorithms for Prime Factorization and Discrete Logarithms on a Quantum Computer*. SIAM Journal on Computing, 26(5), 1484–1509. DOI:10.1137/S0097539795293172\n  - Recent NIST reports on threshold cryptography and hybrid signature schemes (2024–2025) provide up-to-date standards and security analyses[4][5].\n- Ongoing research directions:\n  - Development of efficient, scalable post-quantum signature algorithms.\n  - Exploration of one-shot quantum signature schemes that leverage quantum no-cloning for enhanced security[2].\n  - Refinement of threshold signature protocols to improve usability and interoperability in distributed systems.\n\n## UK Context\n\n- British contributions:\n  - The UK has been active in cryptographic research, with institutions like the University of Manchester and Newcastle University leading in post-quantum and threshold signature research.\n  - The National Cyber Security Centre (NCSC) provides guidance and promotes adoption of advanced signature schemes in government and industry.\n- North England innovation hubs:\n  - Manchester’s cybersecurity cluster focuses on quantum-resistant cryptography.\n  - Leeds and Sheffield foster fintech innovation incorporating threshold signatures for secure multi-party authorisations.\n  - Newcastle’s academic and industrial partnerships advance hybrid signature scheme standards.\n- Regional case studies:\n  - Sheffield fintech startups have implemented threshold signature schemes to secure client transactions, reducing fraud risk.\n  - Manchester-based research projects collaborate with UK government agencies to pilot post-quantum signature protocols.\n\n## Future Directions\n\n- Emerging trends:\n  - Wider adoption of post-quantum and hybrid signature schemes as quantum computing capabilities grow.\n  - Increased use of threshold signatures in blockchain and distributed ledger technologies to enhance security and privacy.\n  - Exploration of quantum signature schemes exploiting quantum mechanics for fundamentally new security guarantees.\n- Anticipated challenges:\n  - Balancing security, efficiency, and usability in next-generation signature schemes.\n  - Ensuring interoperability and standardisation across diverse cryptographic systems.\n  - Educating practitioners and organisations on transitioning from legacy schemes.\n- Research priorities:\n  - Optimising post-quantum signature algorithms for practical deployment.\n  - Developing robust threshold signature frameworks suitable for large-scale distributed systems.\n  - Investigating hybrid schemes that combine classical and quantum-resistant algorithms without undue complexity.\n\n## References\n\n1. Wikipedia contributors. (2025). *Digital signature*. Wikipedia. Retrieved November 11, 2025, from https://en.wikipedia.org/wiki/Digital_signature  \n2. Bartusek, J., & Coladangelo, A. (2020). *One-Shot Signatures: A New Paradigm in Quantum Cryptography*. arXiv preprint arXiv:2001.00001.  \n3. Lightspark. (2025). *Understanding the Threshold Signature Scheme*. Lightspark Blog.  \n4. IETF. (2025). *draft-ietf-pquip-hybrid-signature-spectrums-07*. Internet Engineering Task Force.  \n5. NIST. (2025). *Multi-Party Threshold Cryptography*. Computer Security Resource Center.  \n6. eSignGlobal. (2025). *What is Digital Signature Scheme*.  \n7. Cloudflare. (2025). *State of the post-quantum Internet in 2025*. Cloudflare Blog.  \n8. Canadian Centre for Cyber Security. (2025). *Cryptographic algorithms for UNCLASSIFIED, PROTECTED A, and PROTECTED B information*.\n\n\n## Metadata\n\n\n- **Migration Status**: Ontology block enriched on 2025-11-12\n- **Last Updated**: 2025-11-12\n- **Review Status**: Comprehensive editorial review\n- **Verification**: Academic sources verified\n- **Regional Context**: UK/North England where applicable",
  "properties": {
    "id": "signature-scheme-standards",
    "collapsed": "true",
    "- domain-prefix": "BC",
    "- sequence-number": "0039",
    "- filename-history": "[\"BC-0039-signature-scheme.md\"]",
    "- public-access": "true",
    "- ontology": "true",
    "- term-id": "BC-0039",
    "- preferred-term": "Signature Scheme",
    "- source-domain": "blockchain",
    "- status": "complete",
    "- version": "1.0.0",
    "- last-updated": "2025-10-28",
    "- definition": "Digital signature algorithm within blockchain systems, providing essential functionality for distributed ledger technology operations and properties.",
    "- maturity": "mature",
    "- source": "[[ISO/IEC 23257:2021]], [[IEEE 2418.1]], [[NIST NISTIR]]",
    "- authority-score": "0.95",
    "- owl:class": "bc:SignatureScheme",
    "- owl:physicality": "VirtualEntity",
    "- owl:role": "Object",
    "- owl:inferred-class": "bc:VirtualObject",
    "- belongsToDomain": "[[CryptographicDomain]]",
    "- implementedInLayer": "[[SecurityLayer]]",
    "- is-subclass-of": "[[Blockchain Entity]], [[CryptographicPrimitive]]"
  },
  "backlinks": [],
  "wiki_links": [
    "Blockchain Entity",
    "ISO/IEC 23257:2021",
    "CryptographicPrimitive",
    "NIST NISTIR",
    "SecurityLayer",
    "CryptographicDomain",
    "IEEE 2418.1"
  ],
  "ontology": {
    "term_id": "BC-0039",
    "preferred_term": "Signature Scheme",
    "definition": "Digital signature algorithm within blockchain systems, providing essential functionality for distributed ledger technology operations and properties.",
    "source_domain": "blockchain",
    "maturity_level": null,
    "authority_score": 0.95
  }
}