{
  "title": "SLAM",
  "content": "- ### OntologyBlock\n  id:: slam-ontology\n  collapsed:: true\n\t- ontology:: true\n\t- term-id:: MV-0052\n\t- preferred-term:: SLAM\n\t- source-domain:: metaverse\n\t- status:: draft\n    - public-access:: true\n\t- definition:: A component of the metaverse ecosystem.\n\t- maturity:: draft\n\t- owl:class:: mv:SLAM\n\t- owl:physicality:: ConceptualEntity\n\t- owl:role:: Concept\n\t- is-subclass-of:: [[Extended Reality (XR)]]\n\t- belongsToDomain:: [[MetaverseDomain]]\n\n## OWL Formal Semantics\n\n```clojure\n;; OWL Functional Syntax\n\n(Declaration (Class :Slam))\n\n;; Annotations\n(AnnotationAssertion rdfs:label :Slam \"SLAM\"@en)\n(AnnotationAssertion rdfs:comment :Slam \"A component of the metaverse ecosystem.\"@en)\n\n;; Data Properties\n(AnnotationAssertion dcterms:identifier :Slam \"mv-1761742247966\"^^xsd:string)\n```",
  "properties": {
    "id": "slam-ontology",
    "collapsed": "true",
    "- ontology": "true",
    "- term-id": "MV-0052",
    "- preferred-term": "SLAM",
    "- source-domain": "metaverse",
    "- status": "draft",
    "- public-access": "true",
    "- definition": "A component of the metaverse ecosystem.",
    "- maturity": "draft",
    "- owl:class": "mv:SLAM",
    "- owl:physicality": "ConceptualEntity",
    "- owl:role": "Concept",
    "- is-subclass-of": "[[Extended Reality (XR)]]",
    "- belongsToDomain": "[[MetaverseDomain]]"
  },
  "backlinks": [
    "Augmented Reality (AR)",
    "Virtual Production",
    "Spatial Computing",
    "TELE-051-3d-gaussian-splatting",
    "Variational Autoencoders",
    "Acceleration"
  ],
  "wiki_links": [
    "MetaverseDomain",
    "Extended Reality (XR)"
  ],
  "ontology": {
    "term_id": "MV-0052",
    "preferred_term": "SLAM",
    "definition": "A component of the metaverse ecosystem.",
    "source_domain": "metaverse",
    "maturity_level": null,
    "authority_score": null
  }
}