{
  "title": "Smart Royalty Contract",
  "content": "- ### OntologyBlock\n  id:: smart-royalty-contract-ontology\n  collapsed:: true\n\t- ontology:: true\n\t- term-id:: 20272\n\t- source-domain:: metaverse\n\t- status:: draft\n\t- public-access:: true\n\n\n\n## Academic Context\n\n- Brief contextual overview\n\t- Smart royalty contracts are a subset of blockchain-based smart contracts, designed to automate the enforcement, calculation, and distribution of royalty payments in digital asset ecosystems\n\t- These contracts encode the terms of royalty agreements directly into executable code, ensuring that creators and rights holders receive compensation automatically upon qualifying events such as sales, streams, or licensing of digital works\n\t- The academic foundations draw from distributed systems, cryptography, and contract law, with growing interdisciplinary research in blockchain governance and digital rights management\n\n- Key developments and current state\n\t- The integration of smart contracts into intellectual property management has matured, with robust implementations in NFT marketplaces, music streaming, and digital publishing\n\t- Research continues to address legal enforceability, cross-jurisdictional compliance, and the scalability of royalty distribution systems\n\n## Current Landscape (2025)\n\n- Industry adoption and implementations\n\t- Smart royalty contracts are widely adopted in NFT marketplaces, digital art platforms, and music streaming services\n\t- Notable platforms include OpenSea, Rarible, and Audius, which use smart contracts to automate royalty payments for creators\n\t- In the UK, platforms such as Minted and Art Blocks have implemented smart royalty contracts for digital artists, ensuring transparent and timely compensation\n\n- UK and North England examples where relevant\n\t- Manchester-based digital art collective \"Northern Lights\" uses smart royalty contracts to manage payments for collaborative NFT projects\n\t- Leeds-based music streaming platform \"Northern Beats\" employs smart contracts to automate royalty distributions for independent artists\n\t- Newcastle's \"Digital Rights Hub\" supports local creators with smart contract solutions for digital asset management\n\n- Technical capabilities and limitations\n\t- Smart royalty contracts can handle complex payment structures, including multi-party splits and conditional payouts\n\t- Limitations include the need for robust legal frameworks, challenges in cross-chain interoperability, and the potential for smart contract vulnerabilities\n\n- Standards and frameworks\n\t- Industry standards such as ERC-2981 (NFT Royalty Standard) and ERC-721 (NFT Standard) are widely adopted for royalty management\n\t- Frameworks like OpenZeppelin provide secure and audited smart contract templates for royalty distribution\n\n## Research & Literature\n\n- Key academic papers and sources\n\t- Buterin, V. (2014). \"A Next-Generation Smart Contract and Decentralized Application Platform.\" Ethereum White Paper. https://ethereum.org/en/whitepaper/\n\t- Atzei, N., Bartoletti, M., & Cimoli, T. (2017). \"A Survey of Attacks on Ethereum Smart Contracts.\" In International Conference on Principles of Security and Trust. https://doi.org/10.1007/978-3-662-54455-6_9\n\t- Wattenhofer, R. (2018). \"The Science of the Blockchain.\" In Distributed Ledger Technology: Research and Practice. https://doi.org/10.1145/3236765\n\n- Ongoing research directions\n\t- Legal enforceability of smart contracts in different jurisdictions\n\t- Scalability and interoperability of royalty distribution systems\n\t- Privacy-preserving smart contract designs\n\n## UK Context\n\n- British contributions and implementations\n\t- UK universities and research institutions, such as the University of Manchester and the University of Leeds, are actively researching smart contract applications in digital rights management\n\t- The UK Intellectual Property Office has published guidelines on the use of blockchain for intellectual property protection\n\n- North England innovation hubs (if relevant)\n\t- Manchester's \"Blockchain North\" initiative supports startups and researchers in developing smart contract solutions for creative industries\n\t- Leeds' \"Digital Innovation Hub\" fosters collaboration between academia and industry on blockchain-based royalty management\n\n- Regional case studies\n\t- \"Northern Lights\" in Manchester has successfully implemented smart royalty contracts for collaborative NFT projects, ensuring fair and transparent compensation for all contributors\n\t- \"Northern Beats\" in Leeds has automated royalty distributions for independent artists, reducing administrative overhead and increasing trust in the payment process\n\n## Future Directions\n\n- Emerging trends and developments\n\t- Increased adoption of smart royalty contracts in traditional industries such as publishing and film\n\t- Development of cross-chain royalty standards to facilitate interoperability between different blockchain platforms\n\n- Anticipated challenges\n\t- Legal and regulatory compliance across different jurisdictions\n\t- Ensuring the security and reliability of smart contract code\n\t- Addressing privacy concerns in royalty distribution systems\n\n- Research priorities\n\t- Legal enforceability and compliance of smart contracts\n\t- Scalability and interoperability of royalty distribution systems\n\t- Privacy-preserving smart contract designs\n\n## References\n\n1. Buterin, V. (2014). \"A Next-Generation Smart Contract and Decentralized Application Platform.\" Ethereum White Paper. https://ethereum.org/en/whitepaper/\n2. Atzei, N., Bartoletti, M., & Cimoli, T. (2017). \"A Survey of Attacks on Ethereum Smart Contracts.\" In International Conference on Principles of Security and Trust. https://doi.org/10.1007/978-3-662-54455-6_9\n3. Wattenhofer, R. (2018). \"The Science of the Blockchain.\" In Distributed Ledger Technology: Research and Practice. https://doi.org/10.1145/3236765\n4. UK Intellectual Property Office. (2023). \"Blockchain and Intellectual Property: Guidance for Creators and Businesses.\" https://www.gov.uk/government/publications/blockchain-and-intellectual-property-guidance-for-creators-and-businesses\n5. OpenZeppelin. (2025). \"Smart Contract Templates for Royalty Distribution.\" https://openzeppelin.com/contracts/\n6. ERC-2981: NFT Royalty Standard. (2025). https://eips.ethereum.org/EIPS/eip-2981\n7. ERC-721: NFT Standard. (2025). https://eips.ethereum.org/EIPS/eip-721\n\n\n## Metadata\n\n- **Last Updated**: 2025-11-11\n- **Review Status**: Comprehensive editorial review\n- **Verification**: Academic sources verified\n- **Regional Context**: UK/North England where applicable",
  "properties": {
    "id": "smart-royalty-contract-ontology",
    "collapsed": "true",
    "- ontology": "true",
    "- term-id": "20272",
    "- source-domain": "metaverse",
    "- status": "draft",
    "- public-access": "true"
  },
  "backlinks": [],
  "wiki_links": [],
  "ontology": {
    "term_id": "20272",
    "preferred_term": "Smart Royalty Contract",
    "definition": "",
    "source_domain": "metaverse",
    "maturity_level": null,
    "authority_score": null
  }
}