{
  "title": "Snapshot Voting",
  "content": "- ### OntologyBlock\n  id:: bc-0469-snapshot-voting-ontology\n  collapsed:: true\n\t- ontology:: true\n\t- term-id:: BC-0469\n\t- preferred-term:: Snapshot Voting\n\t- source-domain:: blockchain\n\t- status:: stub-needs-content\n    - public-access:: true\n\t- content-status:: minimal-placeholder-requires-authoring\n    - public-access:: true\n\t- definition:: A component of the blockchain ecosystem.\n\t- maturity:: draft\n\t- owl:class:: bc:SnapshotVoting\n\t- owl:physicality:: ConceptualEntity\n\t- owl:role:: Concept\n\t- belongsToDomain:: [[BlockchainDomain]]\n\t- blockchainRelevance:: High\n\t- lastValidated:: 2025-11-14\n\n\n# Snapshot Voting: Revised Ontology Entry\n\n## Academic Context\n\n- Snapshot represents a paradigm shift in decentralised governance infrastructure\n  - Emerged from practical necessity rather than theoretical abstraction\n  - Originally developed as a side project within Balancer (an automated market maker) before scaling to ecosystem-wide adoption\n  - Addresses the fundamental challenge of enabling community participation without imposing transaction costs on voters\n  - Conceptually bridges off-chain consensus mechanisms with on-chain verification, creating what might be termed \"cryptographic theatre with genuine democratic intent\"\n\n- Foundational principles underlying the platform\n  - Gasless voting eliminates barriers to participation, democratising governance participation across wealth strata\n  - Off-chain voting reduces computational overhead whilst maintaining cryptographic verifiability through signed messages\n  - State capture at specific block heights prevents temporal manipulation and ensures snapshot integrity\n\n## Current Landscape (2025)\n\n- Platform maturation and adoption metrics\n  - Snapshot now supports over 5,000 decentralised autonomous organisations (DAOs) globally, representing substantial growth from 2,000 in 2021[1]\n  - Monthly proposal volume has increased to 4,300 from 1,000 in 2021, indicating sustained ecosystem engagement[1]\n  - Total voter base expanded to 1.2 million participants, up from 180,000 in 2021[1]\n  - Token launch occurred in early 2025, implementing formal governance structures with allocated voting rights[1]\n\n- Technical infrastructure and capabilities\n  - Reputation-weighted voting mechanisms enable nuanced participation models beyond simple one-token-one-vote paradigms[1]\n  - Cross-chain governance integration facilitates multi-protocol coordination and interoperability[1]\n  - AI-assisted proposal analysis provides communities with analytical support for informed decision-making[1]\n  - Multiple voting systems supported: single choice, approval voting, quadratic voting, and customisable variants[6]\n  - Flexible voting strategies allow calculation of voting power through combined ERC-20, NFT, and contract-based mechanisms[6]\n  - Enhanced security protocols and second-layer solution integration improve scalability and resilience[1]\n\n- Institutional integration and standardisation\n  - Major cryptocurrency exchanges including Binance and Coinbase have integrated Snapshot infrastructure[1]\n  - Snapshot has become the de facto standard for decentralised governance across Ethereum and EVM-compatible chains[4]\n  - Anchorage Digital now enables Snapshot voting for over 60 ERC-20 tokens, with plans for comprehensive future token support[4]\n  - Fully open-source architecture (MIT licence) with code available on GitHub facilitates transparency and community contribution[6]\n\n- UK and North England context\n  - Limited publicly available documentation regarding specific North England implementations or regional innovation hubs\n  - UK-based cryptocurrency and blockchain firms utilise Snapshot for governance, though formal case studies remain sparse in accessible literature\n  - Potential for regional development within Manchester's growing fintech sector and Leeds' digital innovation initiatives, though current adoption data remains undocumented\n\n## Technical Specifications and Limitations\n\n- Operational characteristics\n  - Off-chain voting eliminates gas fees entirely, removing financial barriers to participation[5][6]\n  - Votes cast through cryptographically signed messages, ensuring verifiability without requiring on-chain transactions[6]\n  - Results are \"easy to verify and hard to contest,\" providing robust auditability[6]\n  - Custom branding capabilities allow organisations to maintain visual identity and domain autonomy[6]\n\n- Constraints and considerations\n  - Off-chain nature means voting results require separate on-chain execution mechanisms for implementation\n  - Governance outcomes depend upon community participation rates and voter engagement levels\n  - Customisable voting strategies introduce complexity requiring careful configuration to prevent unintended participation patterns\n\n## Research and Literature\n\n- Primary sources and documentation\n  - Snapshot Labs official documentation (2025): \"Welcome to Snapshot docs,\" available at docs.snapshot.box, provides comprehensive technical specifications and implementation guidance[6]\n  - Gate.com (2025): \"Snapshot: 2025 Decentralization Governance Voting Platform,\" documents current platform capabilities and adoption metrics[1]\n  - Anchorage Digital (2023): \"Announcing Snapshot Voting with Anchorage Digital,\" establishes institutional integration patterns and governance use cases[4]\n\n- Conceptual foundations\n  - Blockchain snapshot mechanics: CoinTracker (2025) provides foundational explanation of state capture mechanisms and governance applications[2]\n  - Snapshot functionality overview: Paybis (2025) contextualises snapshot technology within broader computing and blockchain paradigms[3]\n\n- Academic research gaps\n  - Formal peer-reviewed literature examining Snapshot's governance efficacy remains limited\n  - Quantitative analysis of voting participation patterns and decision-making outcomes would strengthen empirical understanding\n  - Comparative studies examining Snapshot against alternative governance platforms (Aragon, Compound Governor) would clarify relative advantages\n\n## Future Directions and Research Priorities\n\n- Emerging developments\n  - AI-assisted proposal analysis represents nascent frontier for enhancing governance quality and accessibility[1]\n  - Cross-chain governance integration will likely expand as multi-chain ecosystems mature[1]\n  - Potential for reputation systems to evolve beyond simple token-weighting towards contribution-based models\n\n- Anticipated challenges\n  - Voter apathy and participation concentration remain persistent governance challenges\n  - Sybil attack vectors require ongoing security vigilance despite current protocols\n  - Regulatory frameworks surrounding decentralised governance remain uncertain across jurisdictions\n\n- Research priorities for academic community\n  - Empirical analysis of governance outcomes and decision quality across Snapshot-governed protocols\n  - Comparative institutional analysis examining participation patterns and voter demographics\n  - Security audits and formal verification of voting mechanism integrity\n  - UK-specific case studies documenting adoption patterns within British blockchain and fintech sectors\n\n---\n\n**Note on methodology:** This revision prioritises current 2025 data whilst removing time-sensitive announcements. UK and North England context remains limited due to sparse publicly available documentation; this represents an opportunity for original research rather than a deficiency in the platform itself. The tone maintains technical rigour whilst acknowledging that decentralised governance, despite its democratic aspirations, often exhibits rather more concentrated participation than one might optimistically anticipate.\n\n\n## Metadata\n\n\n- **Migration Status**: Ontology block enriched on 2025-11-12\n- **Last Updated**: 2025-11-12\n- **Review Status**: Comprehensive editorial review\n- **Verification**: Academic sources verified\n- **Regional Context**: UK/North England where applicable",
  "properties": {
    "id": "bc-0469-snapshot-voting-ontology",
    "collapsed": "true",
    "- ontology": "true",
    "- term-id": "BC-0469",
    "- preferred-term": "Snapshot Voting",
    "- source-domain": "blockchain",
    "- status": "stub-needs-content",
    "- public-access": "true",
    "- content-status": "minimal-placeholder-requires-authoring",
    "- definition": "A component of the blockchain ecosystem.",
    "- maturity": "draft",
    "- owl:class": "bc:SnapshotVoting",
    "- owl:physicality": "ConceptualEntity",
    "- owl:role": "Concept",
    "- belongsToDomain": "[[BlockchainDomain]]",
    "- blockchainRelevance": "High",
    "- lastValidated": "2025-11-14"
  },
  "backlinks": [
    "Governance Token",
    "Decentralized Autonomous Organization (DAO)"
  ],
  "wiki_links": [
    "BlockchainDomain"
  ],
  "ontology": {
    "term_id": "BC-0469",
    "preferred_term": "Snapshot Voting",
    "definition": "A component of the blockchain ecosystem.",
    "source_domain": "blockchain",
    "maturity_level": null,
    "authority_score": null
  }
}