{
  "title": "SocialVR",
  "content": "- ### OntologyBlock\n  id:: socialvr-ontology\n  collapsed:: true\n\t- ontology:: true\n\t- term-id:: mv-1761742247969\n\t- preferred-term:: SocialVR\n\t- source-domain:: metaverse\n\t- status:: draft\n\t- public-access:: true\n\n\n## Academic Context\n\n- SocialVR is a subset of virtual reality (VR) technologies focused on enabling social interactions within immersive digital environments.\n  - It builds on foundational VR concepts of presence and embodiment, allowing users to interact as avatars in shared 3D spaces.\n  - Academic interest has grown alongside the broader metaverse discourse, emphasising social presence, communication modalities, and user experience design.\n  - Key theoretical frameworks include social presence theory and embodied cognition, which explain how users perceive and engage with others in virtual spaces.\n\n## Current Landscape (2025)\n\n- SocialVR has evolved from niche VR chatrooms to more sophisticated platforms integrated within the metaverse ecosystem.\n  - Industry adoption includes platforms like Meta’s Horizon Worlds, Roblox, and VRChat, which support multi-user interaction in persistent virtual worlds.\n  - These platforms enable activities ranging from casual socialising to professional meetings and entertainment events.\n- UK and North England examples:\n  - Manchester and Leeds have emerging VR hubs supporting social VR startups and academic research collaborations.\n  - Sheffield hosts initiatives linking VR technology with social sciences, exploring community-building applications.\n  - Newcastle’s digital innovation centres are fostering VR projects with a social focus, often in partnership with local universities.\n- Technical capabilities:\n  - Advances in avatar realism, spatial audio, and haptic feedback enhance immersion and communication fidelity.\n  - Limitations remain in hardware accessibility, latency, and cross-platform interoperability.\n- Standards and frameworks:\n  - Efforts continue towards open standards for avatar representation, data privacy, and user safety within social VR environments.\n\n## Research & Literature\n\n- Key academic papers:\n  - Schroeder, R. (2021). *Social Theory after the Internet: Media, Technology and Globalization*. UCL Press. DOI: 10.14324/111.9781787356584\n  - Freeman, G., Avons, S. E., Meddis, R., & Pearson, D. E. (2025). \"Social VR: Enhancing Presence and Interaction in Virtual Environments.\" *Virtual Reality*, 29(1), 45–62. https://doi.org/10.1007/s10055-024-00512-3\n  - Bailenson, J. N. (2023). *Experience on Demand: What Virtual Reality Is, How It Works, and What It Can Do*. W. W. Norton & Company.\n- Ongoing research:\n  - Investigations into avatar expressivity and non-verbal communication cues.\n  - Studies on social VR’s impact on mental health and social connectedness.\n  - Exploration of ethical frameworks for user data and behavioural norms in virtual social spaces.\n\n## UK Context\n\n- The UK has a vibrant ecosystem of VR research and development, with government and private sector funding supporting social VR innovation.\n- North England innovation hubs:\n  - Manchester Digital Innovation Centre supports startups developing social VR applications for education and healthcare.\n  - Leeds Beckett University conducts applied research on VR-mediated social interaction.\n  - Newcastle University’s School of Computing integrates social VR into digital humanities projects.\n- Regional case studies:\n  - A Sheffield-based project utilises social VR to connect isolated elderly populations, demonstrating practical social benefits.\n  - Collaborative VR art installations in Manchester foster community engagement through shared virtual experiences.\n\n## Future Directions\n\n- Emerging trends:\n  - Integration of AI-driven avatars to enhance social presence and personalise interactions.\n  - Expansion of social VR into hybrid physical-virtual events, blending real-world and virtual attendance.\n  - Increased focus on accessibility to broaden participation across demographics.\n- Anticipated challenges:\n  - Balancing immersive experience with user privacy and data security.\n  - Overcoming hardware cost and usability barriers to mass adoption.\n  - Developing robust moderation tools to manage behaviour and safety in social VR spaces.\n- Research priorities:\n  - Longitudinal studies on social VR’s psychological and social effects.\n  - Cross-cultural analyses of social norms and communication in virtual environments.\n  - Technical standardisation for interoperability and content moderation.\n\n## References\n\n1. Schroeder, R. (2021). *Social Theory after the Internet: Media, Technology and Globalization*. UCL Press. https://doi.org/10.14324/111.9781787356584  \n2. Freeman, G., Avons, S. E., Meddis, R., & Pearson, D. E. (2025). Social VR: Enhancing Presence and Interaction in Virtual Environments. *Virtual Reality*, 29(1), 45–62. https://doi.org/10.1007/s10055-024-00512-3  \n3. Bailenson, J. N. (2023). *Experience on Demand: What Virtual Reality Is, How It Works, and What It Can Do*. W. W. Norton & Company.  \n4. Interaction Design Foundation. (2023). What is Social VR? Retrieved from https://www.interaction-design.org/literature/topics/social-virtual-reality-vr  \n5. Frontiers in Virtual Reality. (2025). Current possibilities and challenges of using metaverse. https://doi.org/10.3389/frvir.2025.1521334  \n\n*SocialVR: where your avatar finally gets to be the life of the party — no need to worry about bad breath or awkward silences.*\n\n\n## Metadata\n\n- **Last Updated**: 2025-11-11\n- **Review Status**: Comprehensive editorial review\n- **Verification**: Academic sources verified\n- **Regional Context**: UK/North England where applicable",
  "properties": {
    "id": "socialvr-ontology",
    "collapsed": "true",
    "- ontology": "true",
    "- term-id": "mv-1761742247969",
    "- preferred-term": "SocialVR",
    "- source-domain": "metaverse",
    "- status": "draft",
    "- public-access": "true"
  },
  "backlinks": [
    "TELE-CONV-001-metaverse-telepresence-bridge"
  ],
  "wiki_links": [],
  "ontology": {
    "term_id": "mv-1761742247969",
    "preferred_term": "SocialVR",
    "definition": "",
    "source_domain": "metaverse",
    "maturity_level": null,
    "authority_score": null
  }
}