{
  "title": "SoftRobotics",
  "content": "- ### OntologyBlock\n  id:: softrobotics-ontology\n  collapsed:: true\n\t- ontology:: true\n\t- term-id:: MV-0056\n\t- preferred-term:: SoftRobotics\n\t- source-domain:: metaverse\n\t- status:: draft\n    - public-access:: true\n\t- definition:: A component of the metaverse ecosystem.\n\t- maturity:: draft\n\t- owl:class:: mv:SoftRobotics\n\t- owl:physicality:: ConceptualEntity\n\t- owl:role:: Concept\n\t- is-subclass-of:: [[Extended Reality (XR)]]\n\t- belongsToDomain:: [[MetaverseDomain]]\n\n## OWL Formal Semantics\n\n```clojure\n;; OWL Functional Syntax\n\n(Declaration (Class :Softrobotics))\n\n;; Annotations\n(AnnotationAssertion rdfs:label :Softrobotics \"SoftRobotics\"@en)\n(AnnotationAssertion rdfs:comment :Softrobotics \"A component of the metaverse ecosystem.\"@en)\n\n;; Data Properties\n(AnnotationAssertion dcterms:identifier :Softrobotics \"mv-1761742247969\"^^xsd:string)\n```",
  "properties": {
    "id": "softrobotics-ontology",
    "collapsed": "true",
    "- ontology": "true",
    "- term-id": "MV-0056",
    "- preferred-term": "SoftRobotics",
    "- source-domain": "metaverse",
    "- status": "draft",
    "- public-access": "true",
    "- definition": "A component of the metaverse ecosystem.",
    "- maturity": "draft",
    "- owl:class": "mv:SoftRobotics",
    "- owl:physicality": "ConceptualEntity",
    "- owl:role": "Concept",
    "- is-subclass-of": "[[Extended Reality (XR)]]",
    "- belongsToDomain": "[[MetaverseDomain]]"
  },
  "backlinks": [],
  "wiki_links": [
    "MetaverseDomain",
    "Extended Reality (XR)"
  ],
  "ontology": {
    "term_id": "MV-0056",
    "preferred_term": "SoftRobotics",
    "definition": "A component of the metaverse ecosystem.",
    "source_domain": "metaverse",
    "maturity_level": null,
    "authority_score": null
  }
}