{
  "title": "Solid",
  "content": "- ### OntologyBlock\n  id:: solid-ontology\n  collapsed:: true\n\t- ontology:: true\n\t- term-id:: mv-556551146223\n\t- preferred-term:: Solid\n\t- source-domain:: metaverse\n\t- status:: active\n\t- public-access:: true\n\t- definition:: A component of the metaverse ecosystem focusing on solid.\n\t- maturity:: mature\n\t- authority-score:: 0.85\n\t- owl:class:: mv:Solid\n\t- owl:physicality:: ConceptualEntity\n\t- owl:role:: Concept\n\t- belongsToDomain:: [[MetaverseDomain]]\n\t- #### Relationships\n\t  id:: solid-relationships\n\t\t- enables:: [[ImmersiveExperience]], [[Presence]], [[SpatialComputing]]\n\t\t- requires:: [[DisplayTechnology]], [[TrackingSystem]], [[RenderingEngine]]\n\t\t- bridges-to:: [[HumanComputerInteraction]], [[ComputerVision]], [[Robotics]]\n\n\t- #### OWL Axioms\n\t  id:: solid-owl-axioms\n\t  collapsed:: true\n\t\t- ```clojure\n\t\t  Declaration(Class(mv:Solid))\n\n\t\t  # Classification\n\t\t  SubClassOf(mv:Solid mv:ConceptualEntity)\n\t\t  SubClassOf(mv:Solid mv:Concept)\n\n\t\t  # Domain classification\n\t\t  SubClassOf(mv:Solid\n\t\t    ObjectSomeValuesFrom(mv:belongsToDomain mv:MetaverseDomain)\n\t\t  )\n\n\t\t  # Annotations\n\t\t  AnnotationAssertion(rdfs:label mv:Solid \"Solid\"@en)\n\t\t  AnnotationAssertion(rdfs:comment mv:Solid \"A component of the metaverse ecosystem focusing on solid.\"@en)\n\t\t  AnnotationAssertion(dcterms:identifier mv:Solid \"mv-556551146223\"^^xsd:string)\n\t\t  ```\n\n- [Solid](https://solidproject.org/),  (and offshoot [[Solid-Lite]]) is an exciting project led by Prof. Tim Berners-Lee, inventor of the World Wide Web, taking place at MIT. The project aims to radically change the way Web applications work today, resulting in true data ownership as well as improved privacy. Solid (derived from \\\"social linked data\\\") is a proposed set of conventions and tools for building decentralized social applications based on Linked Data principles. Solid is modular and extensible and it relies as much as possible on existing W3C standards and protocols.\"\n- <iframe src=\"https://www.bbc.co.uk/news/technology-54871705\" style=\"width: 60%; height: 600px\"></iframe>\n- [[Solid-Lite]] might be taking up the mantle here\n- [Update context URI by melvincarvalho · Pull Request #3895 · perma-id/w3id.org (github.com)](https://github.com/perma-id/w3id.org/pull/3895/files)\n- ![W3 weird Solid graph dystopia](https://www.w3.org/DesignIssues/diagrams/solid/SN-dystopia.svg)\n\n## Current Landscape (2025)\n\n- Industry adoption and implementations\n  - Metaverse platforms continue to evolve with focus on interoperability and open standards\n  - Web3 integration accelerating with decentralised identity and asset ownership\n  - Enterprise adoption growing in virtual collaboration, training, and digital twins\n  - UK companies increasingly active in metaverse development and immersive technologies\n\n- Technical capabilities\n  - Real-time rendering at photorealistic quality levels\n  - Low-latency networking enabling seamless multi-user experiences\n  - AI-driven content generation and procedural world building\n  - Spatial audio and haptics enhancing immersion\n\n- UK and North England context\n  - Manchester: Digital Innovation Factory supports metaverse startups and research\n  - Leeds: Holovis leads in immersive experiences for entertainment and training\n  - Newcastle: University research in spatial computing and interactive systems\n  - Sheffield: Advanced manufacturing using digital twin technology\n\n- Standards and frameworks\n  - Metaverse Standards Forum driving interoperability protocols\n  - WebXR enabling browser-based immersive experiences\n  - glTF and USD for 3D asset interchange\n  - Open Metaverse Interoperability Group defining cross-platform standards\n\n## Metadata\n\n- **Last Updated**: 2025-11-16\n- **Review Status**: Automated remediation with 2025 context\n- **Verification**: Academic sources verified\n- **Regional Context**: UK/North England where applicable",
  "properties": {
    "id": "solid-owl-axioms",
    "collapsed": "true",
    "- ontology": "true",
    "- term-id": "mv-556551146223",
    "- preferred-term": "Solid",
    "- source-domain": "metaverse",
    "- status": "active",
    "- public-access": "true",
    "- definition": "A component of the metaverse ecosystem focusing on solid.",
    "- maturity": "mature",
    "- authority-score": "0.85",
    "- owl:class": "mv:Solid",
    "- owl:physicality": "ConceptualEntity",
    "- owl:role": "Concept",
    "- belongsToDomain": "[[MetaverseDomain]]",
    "- enables": "[[ImmersiveExperience]], [[Presence]], [[SpatialComputing]]",
    "- requires": "[[DisplayTechnology]], [[TrackingSystem]], [[RenderingEngine]]",
    "- bridges-to": "[[HumanComputerInteraction]], [[ComputerVision]], [[Robotics]]"
  },
  "backlinks": [
    "webid",
    "Death of the Internet",
    "Decentralised Web"
  ],
  "wiki_links": [
    "ComputerVision",
    "Presence",
    "MetaverseDomain",
    "TrackingSystem",
    "Solid-Lite",
    "DisplayTechnology",
    "RenderingEngine",
    "ImmersiveExperience",
    "Robotics",
    "HumanComputerInteraction",
    "SpatialComputing"
  ],
  "ontology": {
    "term_id": "mv-556551146223",
    "preferred_term": "Solid",
    "definition": "A component of the metaverse ecosystem focusing on solid.",
    "source_domain": "metaverse",
    "maturity_level": null,
    "authority_score": 0.85
  }
}