{
  "title": "Solo Mining",
  "content": "- ### OntologyBlock\n  id:: solo-mining-ontology\n  collapsed:: true\n\n  - **Identification**\n\n    - domain-prefix:: BC\n\n    - sequence-number:: 0065\n\n    - filename-history:: [\"BC-0065-solo-mining.md\"]\n    - public-access:: true\n    - ontology:: true\n    - term-id:: BC-0065\n    - preferred-term:: Solo Mining\n    - source-domain:: blockchain\n    - status:: complete\n    - version:: 1.0.0\n    - last-updated:: 2025-10-28\n\n  - **Definition**\n    - definition:: Individual miner operation within blockchain systems, providing essential functionality for distributed ledger technology operations and properties.\n    - maturity:: mature\n    - source:: [[ISO/IEC 23257:2021]], [[IEEE 2418.1]], [[NIST NISTIR]]\n    - authority-score:: 0.95\n\n  - **Semantic Classification**\n    - owl:class:: bc:SoloMining\n    - owl:physicality:: VirtualEntity\n    - owl:role:: Object\n    - owl:inferred-class:: bc:VirtualObject\n    - belongsToDomain:: [[ConsensusDomain]]\n\t- blockchainRelevance:: High\n\t- lastValidated:: 2025-11-14\n    - implementedInLayer:: [[ProtocolLayer]]\n\n  - #### Relationships\n    id:: solo-mining-relationships\n    - is-subclass-of:: [[Blockchain Entity]], [[ConsensusProtocol]]\n\n  - #### OWL Axioms\n    id:: solo-mining-owl-axioms\n    collapsed:: true\n    - ```clojure\n      Prefix(:=<http://metaverse-ontology.org/blockchain#>)\nPrefix(owl:=<http://www.w3.org/2002/07/owl#>)\nPrefix(rdf:=<http://www.w3.org/1999/02/22-rdf-syntax-ns#>)\nPrefix(xml:=<http://www.w3.org/XML/1998/namespace>)\nPrefix(xsd:=<http://www.w3.org/2001/XMLSchema#>)\nPrefix(rdfs:=<http://www.w3.org/2000/01/rdf-schema#>)\nPrefix(dct:=<http://purl.org/dc/terms/>)\n\nOntology(<http://metaverse-ontology.org/blockchain/BC-0065>\n  Import(<http://metaverse-ontology.org/blockchain/core>)\n\n  ## Class Declaration\n  Declaration(Class(:SoloMining))\n\n  ## Subclass Relationships\n  SubClassOf(:SoloMining :ConsensusProtocol)\n  SubClassOf(:SoloMining :BlockchainEntity)\n\n  ## Essential Properties\n  SubClassOf(:SoloMining\n    (ObjectSomeValuesFrom :partOf :Blockchain))\n\n  SubClassOf(:SoloMining\n    (ObjectSomeValuesFrom :hasProperty :Property))\n\n  ## Data Properties\n  DataPropertyAssertion(:hasIdentifier :SoloMining \"BC-0065\"^^xsd:string)\n  DataPropertyAssertion(:hasAuthorityScore :SoloMining \"1.0\"^^xsd:decimal)\n  DataPropertyAssertion(:isFoundational :SoloMining \"true\"^^xsd:boolean)\n\n  ## Object Properties\n  ObjectPropertyAssertion(:enablesFeature :SoloMining :BlockchainFeature)\n  ObjectPropertyAssertion(:relatesTo :SoloMining :RelatedConcept)\n\n  ## Annotations\n  AnnotationAssertion(rdfs:label :SoloMining \"Solo Mining\"@en)\n  AnnotationAssertion(rdfs:comment :SoloMining\n    \"Individual miner operation\"@en)\n  AnnotationAssertion(dct:description :SoloMining\n    \"Foundational blockchain concept with formal ontological definition\"@en)\n  AnnotationAssertion(:termID :SoloMining \"BC-0065\")\n  AnnotationAssertion(:priority :SoloMining \"1\"^^xsd:integer)\n  AnnotationAssertion(:category :SoloMining \"consensus-fundamentals\"@en)\n)\n      ```\n\n- ## About Solo Mining\n  id:: solo-mining-about\n\n  - Individual miner operation within blockchain systems, providing essential functionality for distributed ledger technology operations and properties.\n  -\n  - ### Key Characteristics\n    id:: solo-mining-characteristics\n    - 1. **Definitional Property**: Core defining characteristic\n    - 2. **Functional Property**: Operational behavior\n    - 3. **Structural Property**: Compositional elements\n    - 4. **Security Property**: Security guarantees provided\n    - 5. **Performance Property**: Efficiency considerations\n  -\n  - ### Technical Components\n    id:: solo-mining-components\n    - **Implementation**: How concept is realized technically\n    - **Verification**: Methods for validating correctness\n    - **Interaction**: Relationships with other components\n    - **Constraints**: Technical limitations and requirements\n  -\n  - ### Use Cases\n    id:: solo-mining-use-cases\n    - **1. Core Blockchain Operation**\n    - **Application**: Fundamental blockchain functionality\n    - **Example**: Practical implementation in major blockchains\n    - **Requirements**: Technical prerequisites\n    - **Benefits**: Value provided to blockchain systems\n  -\n  - ### Standards & References\n    id:: solo-mining-standards\n    - [[ISO/IEC 23257:2021]] - Blockchain and distributed ledger technologies\n    - [[IEEE 2418.1]] - Blockchain and distributed ledger technologies\n    - [[NIST NISTIR]] - Blockchain and distributed ledger technologies\n  -\n\n\n## Academic Context\n\n- Brief contextual overview\n  - Solo mining refers to the independent validation of cryptocurrency transactions and the attempt to add new blocks to a blockchain without joining a mining pool\n  - The process relies on the Proof of Work (PoW) consensus mechanism, where miners compete to solve cryptographic puzzles using computational resources\n  - Key developments and current state\n    - The rise of large-scale mining operations and centralised pools has made solo mining increasingly rare for major cryptocurrencies like Bitcoin\n    - Solo mining remains a niche but conceptually important activity, contributing to network decentralisation and serving as a practical demonstration of PoW principles\n  - Academic foundations\n    - The concept is rooted in Nakamoto’s original Bitcoin whitepaper, which outlines the mechanics of PoW and block rewards\n    - Subsequent research has explored the economic and game-theoretic implications of solo versus pooled mining strategies\n\n## Current Landscape (2025)\n\n- Industry adoption and implementations\n  - Solo mining is primarily pursued by enthusiasts, researchers, and small-scale operators rather than commercial entities\n  - Notable organisations and platforms\n    - Paybis, Bitdeer, and Sazmining provide guides and tools for solo miners, though most focus on pool mining\n    - Hardware manufacturers such as Bitmain (Antminer), MicroBT (Whatsminer), and Canaan (AvalonMiner) continue to release ASIC miners suitable for solo mining\n  - UK and North England examples where relevant\n    - In North England, solo mining is occasionally practiced by hobbyists in cities like Manchester, Leeds, Newcastle, and Sheffield, often as part of local tech meetups or university projects\n    - Some small-scale operations in these regions use repurposed industrial spaces or home setups, reflecting the region’s legacy of innovation and adaptability\n- Technical capabilities and limitations\n  - Solo mining requires substantial computational power, typically provided by ASIC miners designed for specific algorithms (e.g., SHA-256 for Bitcoin)\n  - The probability of successfully mining a block is extremely low for individual miners due to the high network difficulty and competition from large-scale operations\n  - Success is largely stochastic, with the expected time to find a block ranging from months to years for most solo miners\n- Standards and frameworks\n  - The Bitcoin network’s consensus rules and block reward structure are defined by the Bitcoin Improvement Proposal (BIP) process\n  - Solo mining software must comply with these standards to be compatible with the network\n\n## Research & Literature\n\n- Key academic papers and sources\n  - Nakamoto, S. (2008). Bitcoin: A Peer-to-Peer Electronic Cash System. https://bitcoin.org/bitcoin.pdf\n  - Eyal, I., & Sirer, E. G. (2014). Majority is not enough: Bitcoin mining is vulnerable. In Financial Cryptography and Data Security (pp. 436–454). Springer. https://doi.org/10.1007/978-3-662-45472-5_28\n  - Rosenfeld, M. (2011). Analysis of Bitcoin pooled mining reward systems. arXiv preprint arXiv:1112.4980. https://arxiv.org/abs/1112.4980\n- Ongoing research directions\n  - The economic viability of solo mining in the face of increasing network difficulty and centralisation\n  - The impact of solo mining on network decentralisation and security\n  - The development of new consensus mechanisms that may reduce the reliance on PoW and thus the relevance of solo mining\n\n## UK Context\n\n- British contributions and implementations\n  - The UK has a vibrant community of cryptocurrency enthusiasts and researchers, with several universities and tech hubs exploring blockchain and mining technologies\n  - Solo mining is occasionally featured in academic projects and public demonstrations, highlighting the educational value of the practice\n- North England innovation hubs (if relevant)\n  - Cities like Manchester, Leeds, Newcastle, and Sheffield have active tech scenes and are home to several blockchain startups and research groups\n  - Local meetups and hackathons sometimes include solo mining challenges, fostering a spirit of innovation and collaboration\n- Regional case studies\n  - A small group of hobbyists in Manchester recently set up a solo mining rig using repurposed industrial equipment, demonstrating the region’s resourcefulness and technical expertise\n\n## Future Directions\n\n- Emerging trends and developments\n  - The continued centralisation of mining power may further marginalise solo mining, but new cryptocurrencies and consensus mechanisms could provide opportunities for independent miners\n  - Advances in hardware efficiency and energy management may make solo mining more accessible to a broader audience\n- Anticipated challenges\n  - The high cost of entry and the low probability of success remain significant barriers to solo mining\n  - Regulatory changes and environmental concerns may impact the feasibility of mining operations, particularly in regions with strict energy policies\n- Research priorities\n  - Investigating the long-term sustainability of solo mining in the context of evolving network dynamics\n  - Exploring the potential for new consensus mechanisms that support decentralised and independent mining\n\n## References\n\n1. Nakamoto, S. (2008). Bitcoin: A Peer-to-Peer Electronic Cash System. https://bitcoin.org/bitcoin.pdf\n2. Eyal, I., & Sirer, E. G. (2014). Majority is not enough: Bitcoin mining is vulnerable. In Financial Cryptography and Data Security (pp. 436–454). Springer. https://doi.org/10.1007/978-3-662-45472-5_28\n3. Rosenfeld, M. (2011). Analysis of Bitcoin pooled mining reward systems. arXiv preprint arXiv:1112.4980. https://arxiv.org/abs/1112.4980\n4. Paybis. (2025). What is Solo Mining? Solo Bitcoin Mining. https://paybis.com/blog/glossary/solo-mining/\n5. Bitdeer. (2025). Bitdeer's Guide For Solo Mining In 2025. https://www.bitdeer.com/learn/bitdeers-guide-for-solo-mining-in-2025\n6. Sazmining. (2025). How 5 solo Bitcoin miners cashed in over $350K each in 2025. https://www.sazmining.com/blog/solo-bitcoin-miners-cashed-in\n7. FastBull. (2025). Solo Mining Bitcoin in 2025: ROI & How Hard Is It Really? https://www.fastbull.com/news-detail/solo-mining-bitcoin-in-2025-roi--how-4352725_0\n8. EZ Blockchain. (2025). Solo Bitcoin Mining In 2025: Opportunity Or Obsolete Strategy? https://ezblockchain.net/article/will-solo-bitcoin-mining-still-be-worth-it-in-2025/\n9. Coingecko. (2025). How Hard Is It to Mine Bitcoin? Solo Mining Odds & Reality. https://www.coingecko.com/learn/can-you-mine-bitcoin-solo\n10. BitPinas. (2025). What You Should Know About Bitcoin Mining in 2025. https://www.bitpinas.com/pr/mining-faq/\n\n\n## Metadata\n\n\n- **Migration Status**: Ontology block enriched on 2025-11-12\n- **Last Updated**: 2025-11-12\n- **Review Status**: Comprehensive editorial review\n- **Verification**: Academic sources verified\n- **Regional Context**: UK/North England where applicable",
  "properties": {
    "id": "solo-mining-standards",
    "collapsed": "true",
    "- domain-prefix": "BC",
    "- sequence-number": "0065",
    "- filename-history": "[\"BC-0065-solo-mining.md\"]",
    "- public-access": "true",
    "- ontology": "true",
    "- term-id": "BC-0065",
    "- preferred-term": "Solo Mining",
    "- source-domain": "blockchain",
    "- status": "complete",
    "- version": "1.0.0",
    "- last-updated": "2025-10-28",
    "- definition": "Individual miner operation within blockchain systems, providing essential functionality for distributed ledger technology operations and properties.",
    "- maturity": "mature",
    "- source": "[[ISO/IEC 23257:2021]], [[IEEE 2418.1]], [[NIST NISTIR]]",
    "- authority-score": "0.95",
    "- owl:class": "bc:SoloMining",
    "- owl:physicality": "VirtualEntity",
    "- owl:role": "Object",
    "- owl:inferred-class": "bc:VirtualObject",
    "- belongsToDomain": "[[ConsensusDomain]]",
    "- blockchainRelevance": "High",
    "- lastValidated": "2025-11-14",
    "- implementedInLayer": "[[ProtocolLayer]]",
    "- is-subclass-of": "[[Blockchain Entity]], [[ConsensusProtocol]]"
  },
  "backlinks": [],
  "wiki_links": [
    "ConsensusProtocol",
    "ISO/IEC 23257:2021",
    "ConsensusDomain",
    "ProtocolLayer",
    "IEEE 2418.1",
    "Blockchain Entity",
    "NIST NISTIR"
  ],
  "ontology": {
    "term_id": "BC-0065",
    "preferred_term": "Solo Mining",
    "definition": "Individual miner operation within blockchain systems, providing essential functionality for distributed ledger technology operations and properties.",
    "source_domain": "blockchain",
    "maturity_level": null,
    "authority_score": 0.95
  }
}