{
  "title": "SPARQL EXAMPLES",
  "content": "- ### OntologyBlock\n  id:: sparql-examples-ontology\n  collapsed:: true\n\t- ontology:: true\n\t- term-id:: mv-1761742247966\n\t- preferred-term:: SPARQL EXAMPLES\n\t- source-domain:: metaverse\n\t- status:: draft\n\t- public-access:: true\n\n## Academic Context\n\n- SPARQL (pronounced \"sparkle\") is a semantic query language and protocol for querying and manipulating data stored in the Resource Description Framework (RDF) format.\n  - It was standardised by the World Wide Web Consortium (W3C) with SPARQL 1.0 becoming a recommendation in 2008, followed by SPARQL 1.1 in 2013, and the latest SPARQL 1.2 specification published in 2023.\n  - The language allows queries to consist of triple patterns, conjunctions, disjunctions, optional patterns, filters, aggregates, and path expressions, enabling complex querying of graph-structured data.\n- Academically, SPARQL is foundational to the semantic web and linked data research, providing a formal syntax and semantics for querying heterogeneous data sources.\n  - It supports multiple query forms such as SELECT (tabular results), CONSTRUCT (new RDF graphs), ASK (boolean), and DESCRIBE (resource descriptions).\n  - The language is underpinned by formal graph pattern matching and logical constraints, making it a subject of ongoing theoretical and applied research.\n\n## Current Landscape (2025)\n\n- SPARQL is widely adopted in industry for querying RDF data across domains including knowledge graphs, cultural heritage, bioinformatics, and linked open data.\n  - Major platforms supporting SPARQL include Apache Jena, GraphDB, Virtuoso, and Stardog, with extensive tooling for query construction, optimisation, and federation.\n  - The language supports multiple result formats such as XML, JSON, CSV, and TSV for interoperability.\n- In the UK, and particularly in North England cities like Manchester, Leeds, Newcastle, and Sheffield, SPARQL is used in academic projects, public sector open data initiatives, and commercial knowledge graph applications.\n  - For example, universities in Manchester and Leeds incorporate SPARQL in semantic web research and data science curricula.\n  - Regional innovation hubs leverage SPARQL-enabled linked data for smart city projects and cultural data integration.\n- Technical capabilities include expressive querying of RDF graphs, federated queries across distributed endpoints, and update operations (INSERT, DELETE).\n  - Limitations remain in query optimisation for very large graphs and in user-friendly query authoring, though advances in tooling and AI-assisted query generation are mitigating these.\n- Standards and frameworks continue to evolve, with SPARQL 1.2 introducing refinements and service description vocabularies to improve discoverability and interoperability of SPARQL endpoints.\n\n## Research & Literature\n\n- Key academic papers include:\n  - Gashkov, A., Perevalov, A., Eltsova, M., & Both, A. (2025). *SPARQL Query Generation with LLMs*. International Conference on Web Engineering (ICWE 2025). arXiv:2507.13859.  \n    This paper explores the use of large language models to generate SPARQL queries from natural language, highlighting advances and challenges in zero-shot and knowledge-injected approaches.\n  - Prud’hommeaux, E., & Seaborne, A. (2008). *SPARQL Query Language for RDF*. W3C Recommendation.  \n    The foundational specification defining SPARQL 1.0.\n  - Harris, S., & Seaborne, A. (2013). *SPARQL 1.1 Query Language*. W3C Recommendation.  \n    The extended specification introducing subqueries, aggregates, and update operations.\n- Ongoing research directions focus on:\n  - Enhancing SPARQL query generation via AI and natural language processing.\n  - Improving federated query performance and optimisation.\n  - Extending SPARQL for richer graph analytics and integration with property graph models.\n  - Developing user-friendly interfaces and visual query builders.\n\n## UK Context\n\n- The UK has been active in semantic web research and SPARQL adoption, with contributions from institutions such as the University of Manchester, University of Leeds, and Newcastle University.\n  - These universities participate in projects involving linked open data, cultural heritage datasets, and smart city data integration using SPARQL.\n- North England innovation hubs, including Manchester’s Digital Innovation Hub and Leeds’ Data City initiative, employ SPARQL-enabled knowledge graphs to support urban analytics and public services.\n- Regional case studies include:\n  - The use of SPARQL in integrating transport and environmental data in Newcastle for real-time urban monitoring.\n  - Cultural heritage projects in Sheffield leveraging SPARQL to query linked museum and archive data.\n- British companies and public sector bodies increasingly use SPARQL for data interoperability and semantic enrichment, reflecting the UK’s commitment to open data and digital innovation.\n\n## Future Directions\n\n- Emerging trends:\n  - Integration of SPARQL with AI-driven query generation and natural language interfaces to lower the barrier for non-expert users.\n  - Expansion of SPARQL capabilities to support graph analytics and machine learning workflows.\n  - Enhanced federation and distributed querying across heterogeneous data sources.\n- Anticipated challenges:\n  - Scaling SPARQL query performance for very large and dynamic RDF datasets.\n  - Balancing expressivity with usability in query language design.\n  - Ensuring robust security and privacy in linked data querying.\n- Research priorities:\n  - Developing hybrid query languages combining RDF and property graph paradigms.\n  - Improving explainability and debugging tools for complex SPARQL queries.\n  - Exploring SPARQL’s role in emerging metaverse and digital twin ecosystems (though it is not itself a metaverse component, despite some misconceptions).\n\n## References\n\n1. Gashkov, A., Perevalov, A., Eltsova, M., & Both, A. (2025). SPARQL Query Generation with LLMs. *International Conference on Web Engineering (ICWE 2025)*. arXiv:2507.13859.  \n2. Prud’hommeaux, E., & Seaborne, A. (2008). SPARQL Query Language for RDF. *W3C Recommendation*.  \n3. Harris, S., & Seaborne, A. (2013). SPARQL 1.1 Query Language. *W3C Recommendation*.  \n4. W3C. (2023). SPARQL 1.2 Query Language. *W3C Recommendation*.  \n5. Ontotext. (2025). The SPARQL Query Language — GraphDB Documentation.  \n6. Apache Jena. (2025). SPARQL Tutorial.  \n7. Landbase. (2025). Companies Using SPARQL in 2025.  \n\nIf SPARQL were a person, it would be that quietly brilliant librarian who knows exactly where every piece of data lives — and can fetch it with a wink and a well-formed query.\n\n\n## Metadata\n\n- **Last Updated**: 2025-11-11\n- **Review Status**: Comprehensive editorial review\n- **Verification**: Academic sources verified\n- **Regional Context**: UK/North England where applicable",
  "properties": {
    "id": "sparql-examples-ontology",
    "collapsed": "true",
    "- ontology": "true",
    "- term-id": "mv-1761742247966",
    "- preferred-term": "SPARQL EXAMPLES",
    "- source-domain": "metaverse",
    "- status": "draft",
    "- public-access": "true"
  },
  "backlinks": [],
  "wiki_links": [],
  "ontology": {
    "term_id": "mv-1761742247966",
    "preferred_term": "SPARQL EXAMPLES",
    "definition": "",
    "source_domain": "metaverse",
    "maturity_level": null,
    "authority_score": null
  }
}