{
  "title": "SpatialComputing",
  "content": "- ### OntologyBlock\n  id:: spatialcomputing-ontology\n  collapsed:: true\n\t- ontology:: true\n\t- term-id:: MV-0006\n\t- preferred-term:: SpatialComputing\n\t- source-domain:: metaverse\n\t- status:: active\n\t- public-access:: true\n\t- definition:: Computing paradigm that blends digital content with the physical world, enabling natural interaction with 3D data through gestures, voice, and gaze in physical space.\n\t- maturity:: mature\n\t- owl:class:: mv:SpatialComputing\n\t- owl:physicality:: Technology\n\t- owl:role:: System\n\t- belongsToDomain:: [[MetaverseDomain]]\n\n## OWL Formal Semantics\n\n```clojure\n;; OWL Functional Syntax\n\n(Declaration (Class :Spatialcomputing))\n\n;; Annotations\n(AnnotationAssertion rdfs:label :Spatialcomputing \"SpatialComputing\"@en)\n(AnnotationAssertion rdfs:comment :Spatialcomputing \"A component of the metaverse ecosystem.\"@en)\n\n;; Data Properties\n(AnnotationAssertion dcterms:identifier :Spatialcomputing \"mv-1761742247973\"^^xsd:string)\n```",
  "properties": {
    "id": "spatialcomputing-ontology",
    "collapsed": "true",
    "- ontology": "true",
    "- term-id": "MV-0006",
    "- preferred-term": "SpatialComputing",
    "- source-domain": "metaverse",
    "- status": "active",
    "- public-access": "true",
    "- definition": "Computing paradigm that blends digital content with the physical world, enabling natural interaction with 3D data through gestures, voice, and gaze in physical space.",
    "- maturity": "mature",
    "- owl:class": "mv:SpatialComputing",
    "- owl:physicality": "Technology",
    "- owl:role": "System",
    "- belongsToDomain": "[[MetaverseDomain]]"
  },
  "backlinks": [
    "TELE-021-augmented-reality-collaboration",
    "TELE-CONV-001-metaverse-telepresence-bridge",
    "Spatial Mapping"
  ],
  "wiki_links": [
    "MetaverseDomain"
  ],
  "ontology": {
    "term_id": "MV-0006",
    "preferred_term": "SpatialComputing",
    "definition": "Computing paradigm that blends digital content with the physical world, enabling natural interaction with 3D data through gestures, voice, and gaze in physical space.",
    "source_domain": "metaverse",
    "maturity_level": null,
    "authority_score": null
  }
}