{
  "title": "Stable Coins",
  "content": "- ### OntologyBlock\n  id:: stable-coins-ontology\n  collapsed:: true\n\t- ontology:: true\n\t- term-id:: mv-772722851786\n\t- preferred-term:: Stable Coins\n\t- source-domain:: metaverse\n\t- status:: active\n\t- public-access:: true\n\t- definition:: A component of the metaverse ecosystem focusing on stable coins.\n\t- maturity:: mature\n\t- authority-score:: 0.85\n\t- owl:class:: mv:StableCoins\n\t- owl:physicality:: ConceptualEntity\n\t- owl:role:: Concept\n\t- belongsToDomain:: [[MetaverseDomain]]\n\t- #### Relationships\n\t  id:: stable-coins-relationships\n\t\t- enables:: [[ImmersiveExperience]], [[Presence]], [[SpatialComputing]]\n\t\t- requires:: [[DisplayTechnology]], [[TrackingSystem]], [[RenderingEngine]]\n\t\t- bridges-to:: [[HumanComputerInteraction]], [[ComputerVision]], [[Robotics]]\n\n\t- #### OWL Axioms\n\t  id:: stable-coins-owl-axioms\n\t  collapsed:: true\n\t\t- ```clojure\n\t\t  Declaration(Class(mv:StableCoins))\n\n\t\t  # Classification\n\t\t  SubClassOf(mv:StableCoins mv:ConceptualEntity)\n\t\t  SubClassOf(mv:StableCoins mv:Concept)\n\n\t\t  # Domain classification\n\t\t  SubClassOf(mv:StableCoins\n\t\t    ObjectSomeValuesFrom(mv:belongsToDomain mv:MetaverseDomain)\n\t\t  )\n\n\t\t  # Annotations\n\t\t  AnnotationAssertion(rdfs:label mv:StableCoins \"Stable Coins\"@en)\n\t\t  AnnotationAssertion(rdfs:comment mv:StableCoins \"A component of the metaverse ecosystem focusing on stable coins.\"@en)\n\t\t  AnnotationAssertion(dcterms:identifier mv:StableCoins \"mv-772722851786\"^^xsd:string)\n\t\t  ```\n\npublic:: true\n\n- ![stablecoinRelativeVolume.png](../assets/stablecoinRelativeVolume_1721858969653_0.png)\n- [Stablecoins Circulating - DefiLlama](https://defillama.com/stablecoins)\n- <iframe src=\"https://defillama.com/stablecoins\" style=\"width: 100%; height: 600px\"></iframe>\n- ## Stable-coins\n\t- [Jeremy Allaire](https://x.com/jerallaire/status/1803432989113593890)\n\t\t- ```\n\t\t  What does it look like when 10% of global economic money is stablecoins, \n\t\t  and when credit intermediation moves from fractional reserve lending to \n\t\t  onchain credit markets built from the ground up on safer, digital cash \n\t\t  instruments (e.g. stables), and opens up credit and debt to the long tail\n\t\t  of supply and demand in the same way that Amazon did for commerce and \n\t\t  AdWords did for advertising?\n\t\t  All of this is achievable over the next 10+ years.  \n\t\t  The time goes by fast, but when you zoom out and look at what has\n\t\t  been accomplished and how that sets us up for the future, \n\t\t  it‚Äôs hard not to be insanely optimistic right now.\n\t\t  ```\n\t- Stable Coins are ‚Äòcrypto like‚Äô instruments which are ‚Äòpegged‚Äô at a 1:1ratio with nationally issued Fiat currencies. In fact they usually correspond to units of privately issued debt underwritten by a variety of different assets. This is (depending on the issuing company‚Äôs model)a [far morerisky](https://www.americanbanker.com/opinion/ststablecoins-are-backed-by-reserves-give-us-a-break)unit of money than the nominal currency that they represent, but they offer significant utility. They allow the user to self custody the cryptographic bearer instrument representing the money themselves, as with blockchain. This may afford the user less friction in that they can transmit the instrument through the newer financial rails which are emerging. Once again, this is likely a product most useful to [emergingmarkets](https://www.cigionline.org/articles/the-future-of-fintech-is-unfolding-in-africa/?),those living under oppressive regimes, currencies [suffering from highinflation](https://www.bloomberg.com/news/articles/2022-07-03/argentines-seek-hedging-in-crypto-after-economy-minister-resigns),and countries who rely on the dollar as their currency, and within digitally native metaverse applications. These are enormous global uses though. The use in the west is prominently for ‚Äòtraders‚Äô on exchanges at this time. /par The caveat of such products is that such ‚Äòunits‚Äô of money can be frozen by the issuer, and they are subject to the third party risk of the issuer defaulting on the underlying instrument, instantly wiping out the value.\n\t- <iframe src=\"https://medium.com/@nic__carter/five-perspectives-on-stablecoins-5bc20076270a\" style=\"width: 100%; height: 600px\"></iframe>\n\t- [Five perspectives on stablecoins. Evaluating the state of the academic‚Ä¶ | by Nic Carter | May, 2024 | Medium](https://medium.com/@nic__carter/five-perspectives-on-stablecoins-5bc20076270a)\n\t- Klages-Mundt et al. wrote a paper in 2020, which explains the details ofthe different mechanisms and risks.\n\t- The following text paraphrases Spencer noon of on-chain analytics company ‚ÄúOurNetwork‚Äù, who provides an [usefulsummary](https://twitter.com/spencernoon/status/1524752048121466883) of the paper.\n\t- There are two major classes of stablecoins:\n\t\t- Custodial: entrusted by off-chain collateral assets like fiat dollars that sit in a bank. Requires trust in third party.\n\t\t- Non-custodial (aka decentralized): fully on-chain and backed by smart contracts & economics. No trusted parties.\n\t- In custodial stablecoins, custodians hold a combination of assets(currencies, bonds, commodities, etc.) off-chain, allowing issuers(possibly the same entity) to offer digital tokens of an reserve asset.The top 2 custodial stablecoins today are USDT and USDC. There are 3types of custodial stablecoins.\n\t\t- Reserve Fund: 100% reserve ratio. Each stablecoin is backed by a unit of the reserve asset held by the custodian. A useful example of this the [USDF banking consortium](https://www.americanbanker.com/news/bank-stablecoin-consortium-usdf-gets-a-ceo-grows-to-9-members).\n\t\t- Fractional Reserve Fund: The stablecoin is backed by a mix of both reserve assets and other capital assets.\n\t\t- Central Bank Digital Currency (CBDC): A digital form of central bank money that is widely available to the general public. CBDCs are in their nascency as today only 9 countries/territories have launched them, many of them small.\n\t- Custodial stablecoins have three major risks:\n\t\t- Counterparty Risk (fraud, theft, govt seizure, etc.)\n\t\t- Censorship Risk (operations blocked by regulators, etc.)\n\t\t- Economic Risk (off-chain assets go down in value)\n\t- Each can result in the stablecoin value going to zero.\n\t- [Stablecoins and national security: Learning the lessons of Eurodollars | Brookings](https://www.brookings.edu/articles/stablecoins-and-national-security-learning-the-lessons-of-eurodollars/)\n\t- They are collectively likely to outstrip VISA this year\n\t\t- ![Image](https://pbs.twimg.com/media/GCAQhOBaoAAqs-D?format=jpg&name=medium)\n\t- Over 1/3 Made a Purchase in Stablecoins in Latin America, Says Latest MasterCard New Payments Index 2022: Reporting on Fintech,\n\t- Crypto, and Blockchain Activity in Africa<https://bitcoinke.io/2022/07/latin-america-in-mastercard-new-payments-index-2022/>\n\t- According to the latest MasterCard New Payments Index 2022, over one third of people in Latin America made a purchase using\n\t- stablecoins in the past year.\n\t      *  https://bitcoinmagazine.com/legal/u-s-treasury-introduces-cbdc-digital-dollar-working-group\n\t      rbi monetary museum: India's e-rupee unpopular as central banks push digital currency\n\t\t- The Economic Times https://economictimes.indiatimes.com/industry/banking/finance/banking/indias-e-rupee-unpopular-as-central-banks-push-digital-currency/articleshow/99049236.cms?from=mdr\n- ## Stripe Acquires Bridge\n\t- **Stripe Acquisition**\n\t\t- On October 22nd, fintech giant Stripe acquired stablecoin infrastructure firm Bridge for $1.1 billion, marking the largest acquisition in crypto history and Stripe's most significant purchase to date.\n\t\t- Bridge provides business-facing software that enables companies to accept stablecoin payments, enhancing Stripe's capabilities in the stablecoin payments sector.\n\t\t- At the time of acquisition, Bridge was last valued at $200 million during their Series A funding, representing a substantial markup and a significant exit for founders and investors.\n\t- **Stripe's Strategic Intent**\n\t\t- The acquisition underscores Stripe's commitment to stablecoins as the future of payments, signaling their intention to double down on stablecoin infrastructure.\n\t\t- Patrick Collison, CEO of Stripe, stated, \"Stable coins are room temperature superconductors for financial services. Thanks to stable coins, businesses around the world will benefit from significant speed, coverage, and cost improvements in the coming years.\"\\r\\n\n\t\t- Stripe aims to build the world's best stablecoin infrastructure, integrating multiple stablecoins and partnering with firms like Paxos for backend infrastructure.\n\t\t- Bridge's platform facilitates stablecoin payments across 70 countries, with impressive early adoption metrics reported by Stripe.\n\t\t- The integration of Bridge enhances Stripe's ability to provide instant, global, dollar-based payment rails, reducing crypto complexity for businesses.\n\t- **Positive Endorsements**\n\t\t- Simon Taylor of fintech Brain Fruit praised the acquisition, likening it to an \"Instagram-like all-time great acquisition\" that addresses long-term challenges for Stripe.\n\t\t- Overdraft's head of macro at Lightspeed Ventures highlighted the shift from crypto being price-centric to focusing on business value.\n\t\t- Jeremy Black, principal at fintech firm Kinvey, noted that Stripe's $1 billion investment communicates a strong market signal to customers and partners, discouraging competitors.\n\t\t- Rob Boadock, general partner at Dragonfly Capital, emphasized that the acquisition broadens Stripe's business from merchant dependence to establishing its own global payment network.\n\t\t- Jacob Horn, co-founder of LER 2 Zora, indicated that Bridge and Stripe's collaboration will enable any app to have stablecoin on-ramps and off-ramps similar to Coinbase, with enhanced regional support.\n\t\t- Chia Wang of Alliance Dow suggested that the acquisition signals to venture capitalists that stablecoin startups have clearer paths to significant exits, potentially leading to increased funding and entrepreneurial activity in the stablecoin space.\n\t\t- Nick Carter of Castle Island predicted that the Bridge acquisition would \"turbocharge\" the stablecoin market, aligning with broader industry enthusiasm.\n\t- **Stablecoins in Financial Infrastructure**\n\t\t- Stablecoins are increasingly recognized as essential to future financial infrastructure, especially in regions with limited access to traditional banking.\n\t\t- The acquisition by Stripe reflects a broader industry acknowledgment of stablecoins' role in facilitating seamless, global transactions.\\r\\n\n\t- **Market Trends and Adoption**\n\t\t- Stablecoins have maintained a steady ascent, becoming integral to various financial services beyond speculative trading, including payments, remittances, and decentralized finance (DeFi).\n\t\t- Institutional interest in stablecoins is growing, driven by their potential to enhance payment speed, reduce costs, and provide stable value storage.\n\t\t- As stablecoins become more embedded in the financial system, regulatory frameworks will likely evolve to address associated risks and ensure compliance.\n\t\t- The ongoing collaboration between traditional financial institutions and blockchain-based firms like Stripe and Bridge suggests a converging future for fintech and crypto sectors.\n- ## By the numbers\n\t- It‚Äôs worth taking a look at these tokens individually, to get a feel forthe trade-offs, and figure out how they might be useful for us in our proposed metaverse applications. It‚Äôs important to know that these tokenised dollars and/or other currencies are issued on top of the public blockchains we have been detailing throughout. Which tokens areon what blockchains is constantly evolving, so it‚Äôs not really worth enumerating specifics. In a metaverse application it would be necessary to manage both the underlying public blockchain and the stablecoin issued on top of it, making the interaction with the global financial system perversely more not less complex. In the following list of a fewof the major coins, the first hyperlink is the whitepaper if it‚Äôs available.\n\t\t- [USDC](https://f.hubspotusercontent30.net/hubfs/9304636/PDF/centre-whitepaper.pdf) is a dollar and Euro backed coin issued by a consortium of major players in the space, most notably Circle, and Coinbase. It‚Äôs has a better transparency record than tether but is still not backed 1:1 by actual dollars in reserve. It may or may not be a fractional reserve asset. It‚Äôs well positioned to take advantage of regulatory changes in the USA, and seems to be quietly lobbying to be the choice of a government endorsed digital dollar, at least a significant part of a central bank digital currency initiative. It‚Äôs too early to tell how this will work out, but it has [substantial ‚Äòlegacy finance backing‚Äô](https://www.forbes.com/sites/ninabambysheva/2022/04/13/blackrocks-newest-investment-paves-the-way-for-digital-assets-on-wall-street/?). It is the only stablecoin to increase slightly in value (depegging upward) in the wake of the UST implosion. This ‚Äòflight to quality‚Äô shows the advantage of the work that CENTRE put into regulatory compliance. It runs on Ethereum, Algorand, Solana, Stellar, Tron, Hedera, Avalanche and Flow blockchains. At this time USDC may be [under speculative attack](https://twitter.com/Excellion/status/1567472488589963264) by Chinese exchange Binance, in favour of their own offering BUSD, and is losing market share. Payment provider Stripe supports USDC as of 2024.\n\t\t- Circle has received a major boost as the [only stablecoin allowed in the EU.](https://www.circle.com/en/pressroom/circle-is-first-global-stablecoin-issuer-to-comply-with-mica-eus-landmark-crypto-law)\n\t\t\t- https://twitter.com/collision/status/1783559623511011535\n\t\t\t- {{twitter https://twitter.com/collision/status/1783559623511011535}}\n\t\t- Binance USD is the dollar equivalent token from global crypto exchange behemoth Binance. It‚Äôs released in partnership with Paxos, who have a strong record for compliance, and transparency. Paxos also offer USDP. Both these stablecoins claim to be 100% backed by dollars, or US treasuries. They are regulated under the more restrictive New York state financial services and have a monthly [attestation report](https://paxos.com/attestations/).\n\t\t- [MakerDAO Dai](https://makerdao.com/en/whitepaper#abstract) is an Ethereum based stablecoin and one of the older offerings. It‚Äôs been ‚Äògoverned‚Äô by a DAO since 2014. ‚ÄòExcess collateral‚Äô, above the value of the dai-dollars to be minted, is voted upon before being committed to the systems‚Äô cryptographic ‚Äòvaults‚Äô as a backing for the currency. These dai can then be used across the Ethereum network. Despite the problems with DAOs, and the problems with Ethereum, DAI is well liked by its community of users and has a healthy billion dollars of issuance. They may be [dangerously exposed](https://thedefiant.io/tornado-impact-makerdao-dai) to the new crackdown in the USA, and there is [internal talk](https://twitter.com/bantg/status/1557733094899138560) of pro-actively abandoning DAI altogether.\n\t\t- [TrueUSD](https://trueusd.com/pdf/TUSD_WhitePaper.pdf) claims to be fully backed by US dollars, held in escrow. It runs on the Ethereum blockchain. They have attestation reports [available on demand](https://real-time-attest.trustexplorer.io/truecurrencies) and claim fully insured deposits. It‚Äôs not quite that simple in that a portion of the backing is ‚Äòcash equivalents‚Äô.\n\t\t- [Gemini GUSD](https://www.gemini.com/static/dollar/gemini-dollar-whitepaper.pdf) claim reserves are ‚Äúheld and maintained at State Street Bank and Trust Company and within a money market fund managed by Goldman Sachs Asset Management, invested only in U.S. Treasury obligations.‚Äù which seems pretty clear.\n\t\t- [TerraUSD](https://assets.website-files.com/611153e7af981472d8da199c/618b02d13e938ae1f8ad1e45_Terra_White_paper.pdf) (UST) **was** a more experimental stable coin, and one of a set of currency representations within the network. It worked in concert with the LUNA token on the Cosmos blockchain in order to keep it‚Äôs dollar stability. It was not backed in the same way as the other tokens, instead relying on an arbitrage mechanism using LUNA. In essence the protocol paid users to destroy LUNA and mint UST when the price was above one dollar, and vice versa. This theoretically maintained the dollar peg. There was much concern that this model of [‚Äòalgorithmic stable coin‚Äô](https://mirror.xyz/damsondao.eth/OVeBrmrfcWm7uKLlA2Q4W1XTVkFU3cMKfNWhgf7mQuM) is unstable.[[clements2021built]] The developers of the Terra tried to address this concern by [buying enormous amounts](https://etherscan.io/address/0xad41bd1cf3fd753017ef5c0da8df31a3074ea1ea) of Bitcoin, which they quickly had to employ to address UST drifting downward from $1. This failed to address the ‚Äògreat depegging‚Äô, with LUNA crashing to essentially zero, destroying some $50B of capital. It will now likely act as a cautionary tale to other institutions considering Bitcoin as a ‚Äòreserve asset‚Äô. An [earlier version of this book](https://github.com/GMCyberFoundry/Metaverse/blob/b06547bf290392d2ff02e5142dae7386d888a9de/Book/04_money.tex#L186) highlighted the specific variation of the risk which quickly manifested.\n\t\t- ### Tether\n\t\t\t- [Tether](https://tether.to/en/whitepaper/) is the largest of the stablecoins, with some $70B in circulation, and the third largest ‚Äòcrypto‚Äô. This has been a meteoric rise, attracting the ire and scrutiny of [regulators](https://www.cftc.gov/PressRoom/PressReleases/8450-21) and [investigators](https://www.bloomberg.com/news/features/2021-10-07/crypto-mystery-where-s-the-69-billion-backing-the-stablecoin-tether). There was considerable doubt that Tether had sufficient assets backing their synthetic dollars, but the market seems not to mind. Recently however they have transitioned to being backed by US treasury bills, a perfect asset for this use case. It‚Äôs resilience against ‚Äòbank runs‚Äô was tested in May 2022 when $9B was redeemed directly for dollars in a few days following the UST crash (more on this later). They are [shortly to launch](https://tether.to/en/tether-to-launch-gbpt-tether-tokens-pegged-to-the-british-pound-sterling/) a GBP version for the UK. It‚Äôs an important technology for this metaverse conversation because of intersections with Bitcoin through the Lightning network. Tether might actually provide everything needed. It‚Äôs only as safe as the trust invested in the central issuer though, and the leadership and history of the company [are questionable](https://www.wsj.com/articles/tether-ownership-and-company-weaknesses-revealed-in-documents-11675363340). It‚Äôs notable and somewhat ironic that it‚Äôs perhaps better and more transparently backed than most banks, and probably all novel fiat fintech products. We can employ the asset through the Taro technology described earlier but we would rather use something with higher regulatory assurances.\n\t\t\t\t- [Paolo Ardoino üçê on X: \"Today Tether takes the majority stake in @BlackrockNeuro_ and unveils the ultimate pillar of its long term vision and strategy: Tether Evoüß†ü¶æ First of all, this investment (same as energy, mining, ...) is done outside of stablecoin reserves, with our own company profits (last‚Ä¶\" / X (twitter.com)](https://twitter.com/paoloardoino/status/1784938950525661578)\n\t\t\t\t- {{twitter https://twitter.com/paoloardoino/status/1784938950525661578}}\n\t\t\t- Paolo Ardoino, Tether‚Äôs chief technology officer, said in a¬†podcast episode¬†with The Block that USDT is increasingly used for value transfers, making up about **40**% of all token usage, compared to 60% of crypto trading.\n\t\t\t\t- 40% of USDT is now real world use cases, with Tron emerging as the blockchain of the moment.\n\t\t\t\t- Tether as a company makes billions of dollars of profit per year and has global adoption and network effect. The company has around 20 employees. They will likely remain pre-eminent in the synthetic dollar market.\n\t\t\t\t- The USA is positioning to exclude USDT within it's borders, by capping such assets at $10B for [National security reasons.](https://www.brookings.edu/articles/stablecoins-and-national-security-learning-the-lessons-of-eurodollars/)\n\t\t\t\t- Tether is potentially the natural inheritor of the global [[Eurodollar]] system.\n-\n-\n\n## Current Landscape (2025)\n\n- Industry adoption and implementations\n  - Metaverse platforms continue to evolve with focus on interoperability and open standards\n  - Web3 integration accelerating with decentralised identity and asset ownership\n  - Enterprise adoption growing in virtual collaboration, training, and digital twins\n  - UK companies increasingly active in metaverse development and immersive technologies\n\n- Technical capabilities\n  - Real-time rendering at photorealistic quality levels\n  - Low-latency networking enabling seamless multi-user experiences\n  - AI-driven content generation and procedural world building\n  - Spatial audio and haptics enhancing immersion\n\n- UK and North England context\n  - Manchester: Digital Innovation Factory supports metaverse startups and research\n  - Leeds: Holovis leads in immersive experiences for entertainment and training\n  - Newcastle: University research in spatial computing and interactive systems\n  - Sheffield: Advanced manufacturing using digital twin technology\n\n- Standards and frameworks\n  - Metaverse Standards Forum driving interoperability protocols\n  - WebXR enabling browser-based immersive experiences\n  - glTF and USD for 3D asset interchange\n  - Open Metaverse Interoperability Group defining cross-platform standards\n\n## Metadata\n\n- **Last Updated**: 2025-11-16\n- **Review Status**: Automated remediation with 2025 context\n- **Verification**: Academic sources verified\n- **Regional Context**: UK/North England where applicable",
  "properties": {
    "id": "stable-coins-owl-axioms",
    "collapsed": "true",
    "- ontology": "true",
    "- term-id": "mv-772722851786",
    "- preferred-term": "Stable Coins",
    "- source-domain": "metaverse",
    "- status": "active",
    "- public-access": "true",
    "- definition": "A component of the metaverse ecosystem focusing on stable coins.",
    "- maturity": "mature",
    "- authority-score": "0.85",
    "- owl:class": "mv:StableCoins",
    "- owl:physicality": "ConceptualEntity",
    "- owl:role": "Concept",
    "- belongsToDomain": "[[MetaverseDomain]]",
    "- enables": "[[ImmersiveExperience]], [[Presence]], [[SpatialComputing]]",
    "- requires": "[[DisplayTechnology]], [[TrackingSystem]], [[RenderingEngine]]",
    "- bridges-to": "[[HumanComputerInteraction]], [[ComputerVision]], [[Robotics]]",
    "public": "true"
  },
  "backlinks": [
    "Blockchain",
    "Technical History (extended CV)",
    "BC-0037-public-key"
  ],
  "wiki_links": [
    "ComputerVision",
    "Presence",
    "MetaverseDomain",
    "TrackingSystem",
    "DisplayTechnology",
    "RenderingEngine",
    "clements2021built",
    "ImmersiveExperience",
    "Robotics",
    "Eurodollar",
    "HumanComputerInteraction",
    "SpatialComputing"
  ],
  "ontology": {
    "term_id": "mv-772722851786",
    "preferred_term": "Stable Coins",
    "definition": "A component of the metaverse ecosystem focusing on stable coins.",
    "source_domain": "metaverse",
    "maturity_level": null,
    "authority_score": 0.85
  }
}