{
  "title": "State Space and Other Approaches",
  "content": "- ### OntologyBlock\n  id:: state-space-and-other-approaches-ontology\n  collapsed:: true\n\t- ontology:: true\n\t- term-id:: mv-78989361676\n\t- preferred-term:: State Space and Other Approaches\n\t- source-domain:: metaverse\n\t- status:: active\n\t- public-access:: true\n\t- definition:: A component of the metaverse ecosystem focusing on state space and other approaches.\n\t- maturity:: mature\n\t- authority-score:: 0.85\n\t- owl:class:: mv:StateSpaceAndOtherApproaches\n\t- owl:physicality:: ConceptualEntity\n\t- owl:role:: Concept\n\t- belongsToDomain:: [[MetaverseDomain]]\n\t- #### Relationships\n\t  id:: state-space-and-other-approaches-relationships\n\t\t- enables:: [[ImmersiveExperience]], [[Presence]], [[SpatialComputing]]\n\t\t- requires:: [[DisplayTechnology]], [[TrackingSystem]], [[RenderingEngine]]\n\t\t- bridges-to:: [[HumanComputerInteraction]], [[ComputerVision]], [[Robotics]]\n\n\t- #### OWL Axioms\n\t  id:: state-space-and-other-approaches-owl-axioms\n\t  collapsed:: true\n\t\t- ```clojure\n\t\t  Declaration(Class(mv:StateSpaceAndOtherApproaches))\n\n\t\t  # Classification\n\t\t  SubClassOf(mv:StateSpaceAndOtherApproaches mv:ConceptualEntity)\n\t\t  SubClassOf(mv:StateSpaceAndOtherApproaches mv:Concept)\n\n\t\t  # Domain classification\n\t\t  SubClassOf(mv:StateSpaceAndOtherApproaches\n\t\t    ObjectSomeValuesFrom(mv:belongsToDomain mv:MetaverseDomain)\n\t\t  )\n\n\t\t  # Annotations\n\t\t  AnnotationAssertion(rdfs:label mv:StateSpaceAndOtherApproaches \"State Space and Other Approaches\"@en)\n\t\t  AnnotationAssertion(rdfs:comment mv:StateSpaceAndOtherApproaches \"A component of the metaverse ecosystem focusing on state space and other approaches.\"@en)\n\t\t  AnnotationAssertion(dcterms:identifier mv:StateSpaceAndOtherApproaches \"mv-78989361676\"^^xsd:string)\n\t\t  ```\n\npublic:: true\n\n\t- # Mamba: Linear-Time Sequence Modelling with Selective State Spaces\n\t\t- [Mamba: Linear-Time Sequence Modeling with Selective State Spaces](https://arxiv.org/pdf/2312.00752.pdf)\n\t\t- **Research Design & Rationale**: The study introduces a new architecture, Mamba, which incorporates a selection mechanism and hardware-aware computation into structured state space models.\n\t\t- **Significance**: Addresses the inefficiency of Transformer models with a novel architecture that scales linearly and achieves superior performance.\n\t\t- **Real-world Implications**: Potential to improve a wide range of applications in natural language processing, bioinformatics, and other areas where sequence data is prevalent.\n\t\t- **Takeaways**: Mamba architecture improves upon structured state space models (SSMs) by adding selectivity and hardware-aware algorithms, achieving linear-time modeling with high-quality performance across several modalities.\n\t\t- **Practical Implications**: Provides a more efficient alternative to Transformers, especially beneficial for long sequence data.\n\t\t- **Potential Impact**: Could influence future developments in sequence modeling and foundational models across various domains.\n\t\t- **Abstract in a nutshell**: Mamba is a novel architecture for sequence modeling that enhances structured state space models (SSMs) with selective mechanisms and hardware-aware algorithms, achieving superior performance and efficiency.\n\t\t- **Gap/Need**: Traditional Transformer models have significant computational inefficiency, especially for long sequences. Mamba addresses this by incorporating a selection mechanism and hardware-aware computation in SSMs.\n\t\t- **Innovation**: Introduces a selection mechanism in SSMs, allowing input-dependent parameterization and a simplified architecture without attention or MLP blocks, enabling linear-time computation with maintained or enhanced performance.\n\t\t- ### Key Quotes\n\t\t- \"Mamba enjoys fast inference (5√ó higher throughput than Transformers) and linear scaling in sequence length and its performance improves on real data up to million-length sequences.\"\n\t\t- **\"This class of models can be computed very efficiently as either a recurrence or convolution with linear or near-linear scaling in sequence length.\"**\n\t\t- \"Selective SSMs and by extension the Mamba architecture are fully recurrent models with key properties that make them suitable as the backbone of general foundation models operating on sequences.\"\n\t\t- **How does Mamba achieve linear-time modeling?**: By introducing a selection mechanism in structured state space models and designing a hardware-aware algorithm that avoids materializing expanded states, thereby enhancing computational efficiency.\n\t\t- **What improvements does Mamba offer over traditional models?**: It achieves faster inference, linear scaling with sequence length, and competitive or superior performance across various data modalities including language, audio, and genomics.\n\t\t- **Can Mamba handle long sequences efficiently?**: Yes, it is specifically designed to address the computational inefficiencies of traditional models like Transformers in handling long sequences, offering linear scaling and improved performance.\n\t\t- Mamba outperforms Transformers of the same size in language modelling and matches Transformers twice its size both in pretraining and downstream evaluation, demonstrating its efficiency and effectiveness.\n\t\t- **Authors' Views**: The authors propose Mamba as a significant step forward in sequence modeling, addressing the inefficiency of Transformers while maintaining or improving performance.\n\t\t- **Comparative Analysis**: Mamba is positioned as superior to existing models, particularly Transformers, in terms of efficiency and scalability\n- ## Quick lit survey.  (based on [Mamba-Palooza](https://www.youtube.com/watch?v=Bg1LQ_jWliU))\n\t- Over 30 new papers and projects since original Mamba paper, with new ones coming out every 1-2 days\n\t- 60% of papers address vision/image processing, 25% natural language, and the rest cover various applications\n\t- 80% of papers modified the original Mamba architecture in some way\n\t- 73% of papers reported state-of-the-art results (though not independently verified yet)\n\t- Handling of state in Mamba architecture is not always clear in papers, more research needed\n\t- Swapping out selective state space portion of Mamba in MoE architectures could be an interesting avenue to explore\n\t- Infrastructure and capital advantages for big tech incumbents in deploying large-scale MoE models\n\t- ## Mamba Learning Theory and Interpretability\n\t\t- ### In-Context Learning (Is Mamba Capable of In-Context Learning?)\n\t\t\t- Mamba can do in-context learning, gradually optimizing internal representations through layers\n\t\t\t- Similar pattern to Transformers: elevation of concepts and more accurate activations through layers, then collapse at final prediction\n\t\t- ### Learning Rules from Sequences (Othello Mamba)\n\t\t\t- Mamba learns rules of Othello from just a sequence of moves, achieving higher board accuracy than OthelloGPT\n\t\t\t- More data efficient, but becomes less accurate as game progresses and requires longer training than same-sized Transformer\n\t\t- ### Strengths and Weaknesses (Can Mamba Learn How to Learn?)\n\t\t\t- Mamba outperforms Transformers on tasks with irrelevance and noise\n\t\t\t- Mamba struggles with high-precision memory recall compared to Transformers\n\t\t\t- Hybrid MambaFormer model outperforms both Transformer and Mamba on various evaluation tasks\n\t- ## Mixture of Experts (MoE) Architectures\n\t\t- Major force driving frontier models (e.g., GPT-4, Gemini 1.5)\n\t\t- MoE-Mamba (MoE-Mamba) achieved same loss as original Mamba with 2.2x less training steps, scaling up to 32 experts\n\t\t- BlackMamba scaled up to 2.8B parameters and 8 experts, with generation latency well below Transformer, Transformer MoE, and Mamba\n\t- # Vision Mamba\n\t\t- Majority of Mamba papers (over 60%) address vision/image processing, especially biomedical image segmentation\n\t\t- Key themes:\n\t\t\t- Representing data as sequences is crucial\n\t\t\t- Images are not inherently sequential like language, music, or DNA\n\t\t\t- Multi-scan approaches enable handling non-sequential data\n\t\t\t- Hybrid architectures leverage strengths of different models\n\t\t- Open questions and challenges:\n\t\t\t- Scaling to larger models and datasets\n\t\t\t- Developing state regularization methods\n\t\t\t- Integrating Mamba with other architectural advances (e.g., memory tokens)\n\t\t- Potential for transformative impact, especially in biology and vision applications\n\t\t- Approaches:\n\t\t\t- U-Mamba (U-Mamba): Hybrid CNN-SSM architecture outperforming CNN and Transformers in biomedical image segmentation\n\t\t\t- Swin-UMamba (Swin-UMamba): Combines Mamba with ImageNet pre-training, outperforms U-Mamba\n\t\t\t- Vision Mamba: Bidirectional (forward and backward) scanning for learning visual representations\n\t\t\t- VMamba: Four-way \"cross-scan\" starting at each corner, combining representations\n\t\t\t- VM-UNet (VM-UNet): Applies VMamba's four-way scan to medical image segmentation\n\t\t\t- Mamba-ND: Multi-dimensional sequencing for video and weather data, using sequential SSMs\n\t\t\t- SegMamba: 3D image segmentation with three-way scan, handling long sequences\n\t\t\t- Vivim: Three-way scan for video\n\t\t\t- MambaMorph: Aligns two input images by generating deformation field\n\t\t- Key insights:\n\t\t\t- Turning images into sequences is crucial, can be done through multi-scan approaches\n\t\t\t- Combining scans sequentially may be more effective than parallel\n\t\t\t- Mamba enables memory-efficient processing of high-resolution images, promising for edge applications (e.g., robotics)\n\t- # Mixture of Experts (MoE) Architectures\n\t\t- Major force in frontier models (GPT-4, Gemini 1.5)\n\t\t- MoE-Mamba and BlackMamba demonstrate MoE's effectiveness with Mamba\n\t\t- Open questions around scaling and infrastructure requirements for large-scale MoE-Mamba models\n\t\t- [Introducing Jamba: AI21's Groundbreaking SSM-Transformer Model](https://www.ai21.com/blog/announcing-jamba)\n\t- # Long Context Modeling\n\t\t- LongMamba (LongMamba): Generalizes to 40k tokens after training on 16k, nearly perfect on \"needle in a haystack\" task\n\t\t- Evo: Models long DNA sequences, learning a \"cell model\" analogous to language models' \"world model\"\n\t\t- Potential challenges:\n\t\t\t- Eventual \"rotting\" of internal states with extreme context lengths\n\t\t\t- Need for state regularization or \"pruning\" to maintain performance\n\t\t- Implications for biology: Foundation models could revolutionize drug discovery and biological research\n\t- # Potential Applications\n\t\t- ## Climate Science?\n\t\t\t- To approach the problem of using Mamba to analyze space-acquired time series image-based climate data from multi-spectrum sensors, we can draw upon several techniques and architectures discussed in the Mamba literature. Here's a proposed approach:\n\t\t\t\t- Data Preprocessing:\n\t\t\t\t\t- Combine multi-spectrum sensor data:\n\t\t\t\t\t\t- Use techniques like MambaMorph to align and merge data from different sensors\n\t\t\t\t\t\t- Generate deformation fields to spatially align images from various sources\n\t\t\t\t- Normalize data to ensure consistent scales and ranges across sensors\n\t\t\t\t\t- Temporal alignment:\n\t\t\t\t\t\t- Use techniques like dynamic time warping (DTW) to align time series data temporally\n\t\t\t\t\t\t- Handle missing data points and inconsistent sampling frequencies\n\t\t\t\t- Create a unified temporal grid for all data sources\n\t\t\t\t\t- Incorporate historical data:\n\t\t\t\t\t\t- Preprocess and align historical records (e.g., weather station data, satellite imagery) with the space-acquired data\n\t\t\t\t\t\t- Use techniques like transfer learning or domain adaptation to handle differences in data modalities and distributions\n\t\t\t\t- Mamba Architecture:\n\t\t\t\t\t- Multi-dimensional sequencing (Mamba-ND):\n\t\t\t\t\t\t- Treat the aligned and preprocessed data as a multi-dimensional sequence (e.g., spatial dimensions, time, and spectral channels)\n\t\t\t\t\t\t- Apply Mamba-ND to capture dependencies across all dimensions\n\t\t\t\t\t- Cross-scanning (VMamba or SegMamba):\n\t\t\t\t\t\t- Perform multi-directional scans (e.g., four-way or three-way) to capture spatial dependencies\n\t\t\t\t\t\t- Combine the representations from different scans to obtain a comprehensive understanding of the data\n\t\t\t\t\t- Hybrid architectures (U-Mamba or Swin-UMamba):\n\t\t\t\t\t\t- Incorporate convolutional layers (CNN) for local feature extraction\n\t\t\t\t\t\t- Use Mamba layers for capturing long-range dependencies and global context\n\t\t\t- Leverage pre-training on large-scale datasets (e.g., ImageNet) to improve performance\n\t\t\t  high-level diagram of the proposed approach using Mermaid:\n\t\t\t- ```mermaid\n\t\t\t  graph TD\n\t\t\t      A[Multi-spectrum Sensor Data] --> B{Data Preprocessing}\n\t\t\t      C[Historical Data] --> B\n\t\t\t      \n\t\t\t      subgraph Data Preprocessing\n\t\t\t          B --> D[Combine Multi-spectrum Data]\n\t\t\t          B --> E[Temporal Alignment]\n\t\t\t          B --> F[Incorporate Historical Data]\n\t\t\t          \n\t\t\t          D --> G[MambaMorph for Alignment]\n\t\t\t          D --> H[Generate Deformation Fields]\n\t\t\t          D --> I[Normalize Data]\n\t\t\t          \n\t\t\t          E --> J[Dynamic Time Warping]\n\t\t\t          E --> K[Handle Missing Data]\n\t\t\t          E --> L[Create Unified Temporal Grid]\n\t\t\t          \n\t\t\t          F --> M[Align Historical Records]\n\t\t\t          F --> N[Transfer Learning/Domain Adaptation]\n\t\t\t      end\n\t\t\t      \n\t\t\t      B --> O{Mamba Architecture}\n\t\t\t      \n\t\t\t      subgraph Mamba Architecture\n\t\t\t          O --> P[Multi-dimensional Sequencing]\n\t\t\t          O --> Q[Cross-scanning]\n\t\t\t          O --> R[Hybrid Architectures]\n\t\t\t          \n\t\t\t          P --> S[Mamba-ND]\n\t\t\t          P --> T[Capture Dependencies Across Dimensions]\n\t\t\t          \n\t\t\t          Q --> U[VMamba/SegMamba]\n\t\t\t          Q --> V[Multi-directional Scans]\n\t\t\t          Q --> W[Combine Scan Representations]\n\t\t\t          \n\t\t\t          R --> X[U-Mamba/Swin-UMamba]\n\t\t\t          R --> Y[Convolutional Layers for Local Features]\n\t\t\t          R --> Z[Mamba Layers for Long-range Dependencies]\n\t\t\t          R --> AA[Pre-training on Large-scale Datasets]\n\t\t\t      end\n\t\t\t      \n\t\t\t      O --> AB[Comprehensive Data Representation]\n\t\t\t      AB --> AC[Predictive Component]\n\t\t\t      AB --> AD[Up-to-date Data vs. Historical Context]\n\t\t\t      \n\t\t\t      subgraph Additional Considerations\n\t\t\t          AE[Handle Data Quality Issues]\n\t\t\t          AF[Incorporate Domain Knowledge]\n\t\t\t          AG[Leverage Transfer Learning]\n\t\t\t          AH[Evaluate Model Performance]\n\t\t\t          AI[Interpret and Visualize Representations]\n\t\t\t      end\n\t\t\t      \n\t\t\t      AC --> AJ{Output Formats}\n\t\t\t      AJ --> AK[Short-term Forecasts]\n\t\t\t      AJ --> AL[Long-term Projections]\n\t\t\t      \n\t\t\t      AE --> AB\n\t\t\t      AF --> AB\n\t\t\t      AG --> AB\n\t\t\t      AH --> AB\n\t\t\t      AI --> AB\n\t\t\t  ```\n\t\t-\n\t\t\t- # Mamba2: A Deep Dive into Enhanced Efficiency and Scalability\n\t\t\t\t- [Mamba2](https://arxiv.org/abs/2405.21060) represents a significant advancement in the realm of structured state space models (SSMs), cleverly marrying theoretical elegance with practical efficiency. Building upon the foundation laid by its predecessor, Mamba, this architecture tackles the inherent computational challenges of sequence modelling, particularly for long sequences, by introducing a series of innovations that leverage the power of modern hardware. This section delves into the technical intricacies of Mamba2, guided by the insights from the paper \"Transformers are SSMs: Generalised Models and Efficient Algorithms Through Structured State Space Duality\".\n\t\t\t\t- ## Bridging the Gap: SSMs, Attention, and Structured Matrices\n\t\t\t\t\t- Before diving into the specifics of Mamba2, the paper establishes a crucial theoretical framework that connects three seemingly disparate concepts: structured state space models (SSMs), attention mechanisms, and structured matrices. This framework, termed \"structured state space duality\" (SSD), lays the groundwork for understanding the core innovations of Mamba2 and its relationship to existing sequence modelling paradigms.\n\t\t\t\t\t- The paper reveals a fundamental truth about SSMs: they can be viewed as matrix transformations operating on input sequences. This insight reframes the computation of SSMs as a matrix multiplication problem, where the matrix itself exhibits a specific structure known as semiseparability. Semiseparable matrices are characterized by low-rank submatrices, a property that Mamba2 cleverly exploits for efficiency gains.\n\t\t\t\t\t- A particularly important class of semiseparable matrices, the 1-semiseparable matrices, take center stage in understanding the efficiency of autoregressive sequence modelling. These matrices correspond to simple scalar recurrences, the building blocks of many efficient SSM algorithms. The paper demonstrates that the efficient computation of autoregressive attention, a crucial capability for language modelling, is intrinsically linked to the properties of semiseparable matrices.\n\t\t\t\t- ## Mamba2's Core: The State Space Dual (SSD) Layer\n\t\t\t\t\t- The heart of Mamba2 lies in the State Space Dual (SSD) layer, a refined core SSM layer that replaces the S6 layer from Mamba. This layer embodies the principle of sacrificing some expressivity for substantial gains in computational efficiency, achieved by:\n\t\t\t\t\t- Unlike Mamba, which allows each element in the state vector to decay independently, Mamba2 groups these elements into chunks and applies the same decay factor to each chunk. This seemingly minor modification unlocks significant speedups by allowing the algorithm to leverage matrix multiplications, operations highly optimised on modern hardware like GPUs with their specialised tensor cores.\n\t\t\t\t\t- The chunking strategy in the SSD layer allows Mamba2 to embrace the computational power of matrix multiplications. This shift away from element-wise operations, which are less efficient on modern hardware, results in substantial reductions in training time. The paper's benchmarks show the SSD algorithm to be 2-8x faster than Mamba's optimised selective scan implementation.\n\t\t\t\t\t- While the reduced granularity of state decay in the SSD layer might appear to limit the model's expressivity, the paper argues that this can also be viewed as a form of inductive bias. By constraining the model's flexibility, the chunking strategy might actually guide it towards learning more generalisable representations, potentially improving performance on certain tasks.\n\t\t\t\t- ## Beyond the SSD Layer: Architectural Enhancements\n\t\t\t\t\t- Mamba2 goes beyond the SSD layer, incorporating architectural refinements inspired by the established techniques and understanding of attention mechanisms in Transformers:\n\t\t\t\t\t\t- **Sequence Parallelism:**¬†Mamba2 enables splitting the input sequence into smaller chunks and processing them concurrently across multiple devices. This technique is a natural extension of the block decomposition strategy used in the SSD algorithm, further enhancing efficiency for long sequences.\n\t\t\t\t\t\t- **Tensor Parallelism:**¬†The computationally intensive matrix multiplications within Mamba2 are distributed across multiple devices, accelerating training and paving the way for training even larger models. The Mamba2 block is specifically designed to minimise synchronisation points, reducing communication overhead and maximising parallel efficiency.\n\t\t\t\t\t\t- **Parallel Parameter Projections:**¬†Mamba2 streamlines the computation of SSM parameters (A, B, C, X) by computing them in parallel at the beginning of the block, a departure from Mamba's sequential approach. This simplification contributes to faster training and aligns better with parallelisation strategies commonly used in Transformers.\n\t\t\t\t\t\t- **Extra Normalisation:**¬†An additional normalisation layer, such as LayerNorm, GroupNorm, or RMSNorm, is strategically placed before the final output projection to enhance training stability. This addition proves especially beneficial for larger Mamba2 models, mitigating potential instabilities that can arise during training.\n\t\t\t\t- ## Multi-head Patterns: Learning from Transformers\n\t\t\t\t\t- Mamba2 leverages the concept of multi-head attention, a cornerstone of Transformer architectures, to create multiple \"heads\" of its sequence transformation. Each head operates on a portion of the input sequence with its own set of parameters, allowing the model to capture diverse aspects of the sequential data.\n\t\t\t\t\t- The paper reveals a key difference between SSMs and Transformers in how they implement multi-head computations. Mamba2, like its predecessor, adopts a \"multi-value attention\" (MVA) pattern, where the expansion and contraction matrices (B and C) are shared across all heads. This pattern, a natural outcome of the SSM formulation, stands in contrast to the multi-query attention (MQA) pattern commonly used in Transformers. Empirical evidence suggests that the MVA pattern, unique to SSMs, might contribute to Mamba2's strong performance.\n\t\t\t\t- ## Trade-offs, Potentials, and Open Questions\n\t\t\t\t\t- Despite its advancements, Mamba2 is not without its trade-offs and areas for further exploration.\n\t\t\t\t\t- While Mamba2 excels in training efficiency, its impact on inference speed remains an open question. This aspect is particularly crucial for real-world applications where fast inference is paramount. Further research is needed to investigate how to optimise Mamba2 specifically for inference, potentially through state size adjustments or by leveraging specialised hardware.\n\t\t\t\t\t- The reduced expressivity of the SSD layer, a consequence of its chunking strategy, is an area that demands deeper understanding. While the paper offers a compelling argument for this as a form of inductive bias, a more detailed analysis is needed to ascertain its impact on specific tasks. Exploring whether this trade-off consistently yields benefits across diverse sequence modelling problems is a crucial direction for future research.\n\t\t\t\t\t- The paper hints at the potential of hybrid architectures that combine the strengths of both SSD layers and attention mechanisms. Initial results suggest that a judicious blend of these two paradigms can lead to models that outperform both pure Transformer and pure Mamba2 architectures. Further research into the optimal balance and placement of these layers within a hybrid architecture is a promising avenue for achieving even better performance and efficiency.\n\t\t\t-\n\t\t\t- # Things to do\n\t\t\t\t- TODO What is the spatial and temporal resolution of the space-acquired data?\n\t\t\t\t- TODO How far back does the historical data go, and at what resolution?\n\t\t\t\t- TODO Are there any specific climate variables or phenomena of interest (e.g., temperature, precipitation, extreme events)?\n\t\t\t\t- TODO What is the desired output format for the predictive component (e.g., short-term forecasts, long-term projections)?\n\t\t\t\t- TODO Handling data quality issues (e.g., cloud cover, sensor noise)\n\t\t\t\t- TODO Incorporating domain knowledge (e.g., physical constraints, climate models)\n\t\t\t\t- TODO Leveraging transfer learning from pre-trained models on similar datasets\n\t\t\t\t- TODO Evaluating the model's performance using appropriate metrics and validation techniques\n\t\t\t\t- TODO Interpreting and visualizing the learned representations for stakeholder communication\n\t\t- ## Ontological Layer for Metaverse\n\t\t\t- To approach the problem of using Mamba to analyze formal ontological graphs as used by the W3C, we can draw upon several techniques and architectures discussed in the Mamba literature. Here's a proposed approach:\n\t\t\t- Data Preprocessing:\n\t\t\t\t- Graph Normalization:\n\t\t\t\t\t- Ensure consistent formatting and structure of the ontological graphs\n\t\t\t\t\t- Handle missing or inconsistent data\n\t\t\t\t\t- Normalize node and edge labels\n\t\t\t\t- Graph Merging:\n\t\t\t\t\t- Combine multiple ontological graphs into a single unified graph\n\t\t\t\t\t- Resolve conflicts and inconsistencies between different ontologies\n\t\t\t\t\t- Establish mappings between equivalent concepts across ontologies\n\t\t\t\t- Graph Embedding:\n\t\t\t\t\t- Generate low-dimensional vector representations of nodes and edges\n\t\t\t\t\t- Preserve the semantic relationships and structure of the ontological graphs\n\t\t\t\t\t- Use techniques like RDF2Vec, TransE, or Graph Convolutional Networks (GCNs)\n\t\t\t- Mamba Architecture:\n\t\t\t\t- Graph-Mamba:\n\t\t\t\t\t- Adapt the Mamba architecture to handle graph-structured data\n\t\t\t\t\t- Utilize the selective state space mechanism to capture long-range dependencies in the ontological graphs\n\t\t\t\t\t- Achieve efficient memory usage and reduced computational complexity compared to traditional graph neural networks (GNNs)\n\t\t\t\t- Multi-dimensional Sequencing (Mamba-ND):\n\t\t\t\t\t- Treat the ontological graphs as multi-dimensional sequences (e.g., node features, edge types, and graph structure)\n\t\t\t\t\t- Apply Mamba-ND to capture dependencies across all dimensions\n\t\t\t- Hybrid Architectures:\n\t\t\t\t- Combine Graph-Mamba with other graph neural network architectures (e.g., GCNs, GraphSAGE)\n\t\t\t\t- Leverage the strengths of both approaches to capture local and global patterns in the ontological graphs\n\t\t\t\t-\n\t\t\t\t-\n\t\t\t- ```mermaid\n\t\t\t  graph TD\n\t\t\t   A[Ontological Graphs] --> B(Data Preprocessing)\n\t\t\t   B --> C{Mamba Architecture}\n\t\t\t   C --> D[Graph-Mamba]\n\t\t\t   C --> E[Multi-dimensional Sequencing Mamba-ND]\n\t\t\t   C --> F[Hybrid Architectures]\n\t\t\t   D --> G[Comprehensive Graph Representation]\n\t\t\t   E --> G\n\t\t\t   F --> G\n\t\t\t   G --> H[Ontology Alignment]\n\t\t\t   G --> I[Knowledge Graph Completion]\n\t\t\t   G --> J[Semantic Similarity]\n\t\t\t   ```\n\t\t\t\t-\n\t\t\t\t- TODO What are the specific ontologies being used (e.g., RDF, OWL)?\n\t\t\t\t- TODO Are there any domain-specific requirements or constraints to consider?\n\t\t\t\t- TODO What are the desired output tasks (e.g., ontology alignment, knowledge graph completion, semantic similarity)?\n\t\t\t\t- TODO How large and complex are the ontological graphs being analyzed?\n\t\t\t\t- TODO Handling scalability issues for large-scale ontological graphs\n\t\t\t\t- TODO Incorporating domain knowledge and ontology-specific constraints\n\t\t\t\t- TODO Leveraging transfer learning from pre-trained models on similar ontological graphs\n\t\t\t\t- TODO Evaluating the model's performance using appropriate graph-based metrics and validation techniques\n\t\t\t\t- TODO Interpreting and visualizing the learned graph representations for ontology engineers and domain experts\n- ## Implementations\n\t- https://www.statespace.info/  Lots of tracked projects here. This is the best place.\n\t- Can use the https://huggingface.co/docs/accelerate/usage_guides/fsdp for sharded training\n\t- [[2401.04081] MoE-Mamba: Efficient Selective State Space Models with Mixture of Experts (arxiv.org)](https://arxiv.org/abs/2401.04081)\n\t- [havenhq/mamba-chat: Mamba-Chat: A chat LLM based on the state-space model architecture üêç (github.com)](https://github.com/havenhq/mamba-chat)\n\t- [[2401.13660] MambaByte: Token-free Selective State Space Model (arxiv.org)](https://arxiv.org/abs/2401.13660) doesn't need tokens!!\n-\n- # Kolmogorov-Arnold Networks (KANs)\n\t- A novel type of neural network architecture that has recently gained attention in the field of artificial intelligence. Here are the key points about KANs:\n\t- Inspiration and design:\n\t\t- KANs are inspired by the Kolmogorov-Arnold representation theorem from the 1950s[](https://theaiinsider.tech/2024/05/27/what-are-kolmogorov-arnold-networks-a-guide-to-what-might-be-the-next-big-thing-in-artificial-intelligence/)[](https://arxiv.org/html/2404.19756v4).\n\t\t- Unlike traditional Multi-Layer Perceptrons (MLPs) that have fixed activation functions on nodes, KANs have learnable activation functions on edges[](https://theaiinsider.tech/2024/05/27/what-are-kolmogorov-arnold-networks-a-guide-to-what-might-be-the-next-big-thing-in-artificial-intelligence/)[](https://arxiv.org/html/2404.19756v4).\n\t- Key differences from MLPs:\n\t\t- KANs replace linear weights with univariate functions parametrized as splines[](https://www.reddit.com/r/MachineLearning/comments/1chrafb/r_kan_kolmogorovarnold_networks/).\n\t\t- They have no linear weights at all - every weight parameter is a learnable univariate function[](https://www.reddit.com/r/MachineLearning/comments/1chrafb/r_kan_kolmogorovarnold_networks/).\n\t- Potential advantages:\n\t\t- Improved accuracy: Smaller KANs can achieve comparable or better accuracy than larger MLPs in data fitting and PDE solving[](https://www.reddit.com/r/MachineLearning/comments/1chrafb/r_kan_kolmogorovarnold_networks/).\n\t\t- Better interpretability: KANs can be intuitively visualized and easily interact with human users[](https://www.reddit.com/r/MachineLearning/comments/1chrafb/r_kan_kolmogorovarnold_networks/).\n\t\t- Faster neural scaling laws: KANs potentially scale better than traditional neural networks[](https://www.reddit.com/r/MachineLearning/comments/1chrafb/r_kan_kolmogorovarnold_networks/)[](https://arxiv.org/html/2404.19756v4).\n\t- Applications:\n\t\t- KANs show promise in image processing, speech recognition, and financial modeling[](https://theaiinsider.tech/2024/05/27/what-are-kolmogorov-arnold-networks-a-guide-to-what-might-be-the-next-big-thing-in-artificial-intelligence/).\n\t\t- They have been used to help scientists (re)discover mathematical and physical laws[](https://www.reddit.com/r/MachineLearning/comments/1chrafb/r_kan_kolmogorovarnold_networks/).\n\t- Challenges:\n\t\t- KANs are more complex to design and implement than traditional neural networks[](https://theaiinsider.tech/2024/05/27/what-are-kolmogorov-arnold-networks-a-guide-to-what-might-be-the-next-big-thing-in-artificial-intelligence/).\n\t\t- They require specialized knowledge and are not yet widely adopted[](https://theaiinsider.tech/2024/05/27/what-are-kolmogorov-arnold-networks-a-guide-to-what-might-be-the-next-big-thing-in-artificial-intelligence/).\n\t\t- Training speed is currently slower (about 10 times) compared to MLPs of the same size[](https://www.reddit.com/r/MachineLearning/comments/1chrafb/r_kan_kolmogorovarnold_networks/).\n\t- Implementation:\n\t\t- A Python library called \"pykan\" is available for implementing KANs[](https://www.reddit.com/r/MachineLearning/comments/1chrafb/r_kan_kolmogorovarnold_networks/)\n\t\t  \n\t\t  4\n\t\t  \n\t\t  .\n\t\t  \n\t\t  While KANs show promising results and potential advantages over traditional neural networks, they are still in the early stages of development and research. Further studies and real-world applications are needed to fully understand their capabilities and limitations compared to established neural network architectures.\n\n## Current Landscape (2025)\n\n- Industry adoption and implementations\n  - Metaverse platforms continue to evolve with focus on interoperability and open standards\n  - Web3 integration accelerating with decentralised identity and asset ownership\n  - Enterprise adoption growing in virtual collaboration, training, and digital twins\n  - UK companies increasingly active in metaverse development and immersive technologies\n\n- Technical capabilities\n  - Real-time rendering at photorealistic quality levels\n  - Low-latency networking enabling seamless multi-user experiences\n  - AI-driven content generation and procedural world building\n  - Spatial audio and haptics enhancing immersion\n\n- UK and North England context\n  - Manchester: Digital Innovation Factory supports metaverse startups and research\n  - Leeds: Holovis leads in immersive experiences for entertainment and training\n  - Newcastle: University research in spatial computing and interactive systems\n  - Sheffield: Advanced manufacturing using digital twin technology\n\n- Standards and frameworks\n  - Metaverse Standards Forum driving interoperability protocols\n  - WebXR enabling browser-based immersive experiences\n  - glTF and USD for 3D asset interchange\n  - Open Metaverse Interoperability Group defining cross-platform standards\n\n## Metadata\n\n- **Last Updated**: 2025-11-16\n- **Review Status**: Automated remediation with 2025 context\n- **Verification**: Academic sources verified\n- **Regional Context**: UK/North England where applicable",
  "properties": {
    "id": "state-space-and-other-approaches-owl-axioms",
    "collapsed": "true",
    "- ontology": "true",
    "- term-id": "mv-78989361676",
    "- preferred-term": "State Space and Other Approaches",
    "- source-domain": "metaverse",
    "- status": "active",
    "- public-access": "true",
    "- definition": "A component of the metaverse ecosystem focusing on state space and other approaches.",
    "- maturity": "mature",
    "- authority-score": "0.85",
    "- owl:class": "mv:StateSpaceAndOtherApproaches",
    "- owl:physicality": "ConceptualEntity",
    "- owl:role": "Concept",
    "- belongsToDomain": "[[MetaverseDomain]]",
    "- enables": "[[ImmersiveExperience]], [[Presence]], [[SpatialComputing]]",
    "- requires": "[[DisplayTechnology]], [[TrackingSystem]], [[RenderingEngine]]",
    "- bridges-to": "[[HumanComputerInteraction]], [[ComputerVision]], [[Robotics]]",
    "public": "true"
  },
  "backlinks": [
    "Overview of Machine Learning Techniques"
  ],
  "wiki_links": [
    "ComputerVision",
    "Presence",
    "MetaverseDomain",
    "TrackingSystem",
    "DisplayTechnology",
    "RenderingEngine",
    "ImmersiveExperience",
    "Robotics",
    "HumanComputerInteraction",
    "SpatialComputing"
  ],
  "ontology": {
    "term_id": "mv-78989361676",
    "preferred_term": "State Space and Other Approaches",
    "definition": "A component of the metaverse ecosystem focusing on state space and other approaches.",
    "source_domain": "metaverse",
    "maturity_level": null,
    "authority_score": 0.85
  }
}