{
  "title": "State of the art in AI",
  "content": "- ### OntologyBlock\n  id:: state-of-the-art-in-ai-ontology\n  collapsed:: true\n\t- ontology:: true\n\t- term-id:: mv-564158265963\n\t- preferred-term:: State of the art in AI\n\t- source-domain:: metaverse\n\t- status:: active\n\t- public-access:: true\n\t- definition:: A component of the metaverse ecosystem focusing on state of the art in ai.\n\t- maturity:: mature\n\t- authority-score:: 0.85\n\t- owl:class:: mv:StateOfTheArtInAi\n\t- owl:physicality:: ConceptualEntity\n\t- owl:role:: Concept\n\t- belongsToDomain:: [[MetaverseDomain]]\n\t- #### Relationships\n\t  id:: state-of-the-art-in-ai-relationships\n\t\t- enables:: [[ImmersiveExperience]], [[Presence]], [[SpatialComputing]]\n\t\t- requires:: [[DisplayTechnology]], [[TrackingSystem]], [[RenderingEngine]]\n\t\t- bridges-to:: [[HumanComputerInteraction]], [[ComputerVision]], [[Robotics]]\n\n\t- #### OWL Axioms\n\t  id:: state-of-the-art-in-ai-owl-axioms\n\t  collapsed:: true\n\t\t- ```clojure\n\t\t  Declaration(Class(mv:StateOfTheArtInAi))\n\n\t\t  # Classification\n\t\t  SubClassOf(mv:StateOfTheArtInAi mv:ConceptualEntity)\n\t\t  SubClassOf(mv:StateOfTheArtInAi mv:Concept)\n\n\t\t  # Domain classification\n\t\t  SubClassOf(mv:StateOfTheArtInAi\n\t\t    ObjectSomeValuesFrom(mv:belongsToDomain mv:MetaverseDomain)\n\t\t  )\n\n\t\t  # Annotations\n\t\t  AnnotationAssertion(rdfs:label mv:StateOfTheArtInAi \"State of the art in AI\"@en)\n\t\t  AnnotationAssertion(rdfs:comment mv:StateOfTheArtInAi \"A component of the metaverse ecosystem focusing on state of the art in ai.\"@en)\n\t\t  AnnotationAssertion(dcterms:identifier mv:StateOfTheArtInAi \"mv-564158265963\"^^xsd:string)\n\t\t  ```\n\npublic:: true\n\n- #Public page automatically published\n- # A look at 2023\n  id:: 65a2a968-c150-4dca-8ddc-902f29a8d7e0\n\t- <iframe src=\"https://spectrum.ieee.org/ai-index-2024\" style=\"width: 100%; height: 600px\"></iframe>\n- # Looking ahead\n\t- ## Humans are horrible at forecasting.\n\t\t- These are the same biases identified in [Confusion Of Confusions 1688 : Joseph de la Vega](https://archive.org/details/confusion-of-confusions-1688). We are just awful at it.\n\t\t\t- Authority bias\n\t\t\t- Recency bias\n\t\t\t- Impatience and \"do something syndrome\"\n\t\t- ```With so much changing so quickly, we need to take predictions with a grain of salt, but that doesn‚Äôt mean we can‚Äôt say anything useful about the coming year in AI. To ground ourselves, we can start with two quotes that should inform any estimates about the future. The first is¬†Amara‚Äôs Law ‚ÄúWe tend to overestimate the effect of a technology in the short run and underestimate the effect in the long run.‚Äù Social change is slower than technological change. We should not expect to see immediate global effects of AI in a major way, no matter how fast its adoption (and it is remarkably fast), yet we certainly will see it sooner than many people think.```\n\t\t\t- - from [Signs and Portent by Ethan Mollick\n\t\t\t\t- [One Useful Thing](https://www.oneusefulthing.org/p/signs-and-portents)\n\t\t- [[Update Cycle]] reminder to update this page!\n\t\t\t- [Roy Amara Oxford Reference](https://www.oxfordreference.com/display/10.1093/acref/9780191826719.001.0001/q-oro-ed4-00018679)\n\t\t\t- [AI Index Report 2024 ‚Äì Artificial Intelligence Index (stanford.edu)](https://aiindex.stanford.edu/report/)\n\t\t\t- [I. From GPT-4 to AGI: Counting the OOMs - SITUATIONAL AWARENESS (situational-awareness.ai)](https://situational-awareness.ai/from-gpt-4-to-agi/)\n\t\t\t- ![photo_2024-06-05_08-47-39.jpg](../assets/photo_2024-06-05_08-47-39_1717573793476_0.jpg){:width 600}\n\t- ## [[Hardware and Edge]] because SO much compute is just idling in pockets and desks.\n\t\t- Mercedes and VW now have ChatGPT4 integrated into their cars. Ford have Alexa, and when that inevitably upgrades so will all Fords.\n\t\t- Lots more hardware for consumer AI, lots more Edge and task specific inferencing. Lot more edge meets cloud. Some more local inferencing.\n\t\t- {{tweet [https://twitter.com/llama_index/status/1745148547560059277}}\n\t\t- {{embed ((659e5979-c2de-4138-b2df-ede79790ee6d))}}\n\t- ## [[Social contract and jobs]]\n\t\t- {{embed ((659a9229-e9c0-485f-b58a-601b68b7edd0))}}\n\t- ## [[Politics, Law, Privacy]]\n\t\t- üü¢ Half the world goes to the polls this year. More than 50 countries, 4B people.\n\t\t- [How OpenAI is approaching 2024 worldwide elections](https://openai.com/blog/how-openai-is-approaching-2024-worldwide-elections)\n\t\t- It's not just deepfakes, but adverts, and influencer material on social media. 100x the number with 1/10th the engagement is still a 10x positive for free.\n\t\t\t- üü¢ This is Professor [Ethan Mollick | LinkedIn](https://www.linkedin.com/in/emollick/) using HeyGen and 30s of footage to create a deepfake.\n\t\t\t- [One Useful Thing | Ethan Mollick | Substack](https://www.oneusefulthing.org/) [[Education and AI]] and [[Proprietary Large Language Models]] blog\n\t\t\t\t- His most recent post is [Signs and Portents](https://www.oneusefulthing.org/p/signs-and-portents) and you should check it.\n\t\t\t- ![1704433632082.mp4](../assets/1704433632082_1704449202180_0.mp4)\n\t\t- Autodial chatbots that can have plausible and convincing conversations with voters. I briefly saw someone had made one of these using a $20 GPT subscription.\n\t\t- ![image.png](../assets/image_1704292836040_0.png)\n\t\t- [Kyle Taylor: books, biography](https://www.amazon.co.uk/stores/Kyle-Taylor/author/B09G759JR3?)\n\t\t- He talks about something I have similarly been saying:\n\t\t\t- In the event of a complete breakdown of trust in digital information channels people will simply choose only to trust their priors.\n\t\t\t- This is a fracturing of the information space, effectively bubbles of one. [[Death of the Internet]] [[Social contract and jobs]]\n\t\t- ### The UK situation.\n\t\t- Every time a phase change of technology has been introduced there has been a fundamental shift in governance structures. These take time to play out. Electronic communication allowed global awareness of corruption, and there is a well documented breakdown of [[Privacy, Trust and Safety]] since. We can perhaps see this in the way that leaders are abandoning the pretence of 'norms' in the West.\n\t\t- More agile (emerging?) economies / countries may be able to take far more advantage, if they are allowed to, but make no mistake, the UK is currently well positioned. - üü¢ The UK is systemically well positioned to deal with sudden change, because the vertical integration of ministries allows them to be spun up and down in response to change regardless of the leadership. An agile AND persistent civil service can be effective in times of stress.\n\t\t\t- [Ian Hogarth to lead UK‚Äôs AI Foundation Model Taskforce\n\t\t- he's actually a great choice](https://www.gov.uk/government/news/tech-entrepreneur-ian-hogarth-to-lead-uks-ai-foundation-model-taskforce)\n\t\t\t- [Welcome to State of AI Report 2023](https://www.stateof.ai/)\n\t\t\t- America is supportive of UK positioning around [[Privacy, Trust and Safety]]. They have a compatible legal framework, and we are doing useful work that they are ill positioned to do in exploring the legal space.\n\t\t\t- This perhaps explains the ¬£2.5B [[Infrastructure]] and training investment plan by Microsoft.\n\t\t\t- These companies are **as big** as the UK. Beware tech bros bearing gifts?\n\t\t\t  ![image.png](../assets/image_1704045603470_0.png)\n\t\t\t- All this makes funding seem disproportionately risk sensitive right now.\n\t- ## The big remaining shoe to drop is the robots. 2-5 years?\n\t- [This robot can tidy a room without any help | MIT Technology Review](https://www.technologyreview.com/2024/02/01/1087445/this-robot-can-tidy-a-room-without-any-help/)\n\t- <iframe src=\"https://arxiv.org/pdf/2401.12202.pdf\" style=\"width: 100%; height: 600px\"></iframe>\n\t- ![1705344178256.mp4](../assets/1705344178256_1705352121045_0.mp4)\n\t- # To Close\n\t\t- ## The age of the informational Agent\n\t\t\t- As trust in the internet evolves, the situation will change and adapt as people learn to use informational agents. Intentional UX will allow users to ask their AI to bring them the information they want from a far more decentralised and confusing internet. This will promote incredible diversity in humans as they fracture somewhat into informational enclaves.\n\t\t\t- Two future scenarios include the rise of AI in Truth Verification and Education. AI will become sophisticated enough to verify the truthfulness of information on the internet, combating the spread of misinformation and ensuring that users have access to accurate and reliable informa- tion. AI will also become an integral part of education, acting as a personalised tutor that adapts to each student's learning style and pace, revolutionising the way we learn and acquire new skills.\n\t\t\t- Money will change: Next -Later¬† : Money will increasingly be spent by machines on behalf of human intent. Algorithms will bargain and arbitrage on behalf of their owner/user, for human and machine services, and for ideas, algorithms, and good; globally. This will smooth out the operation of money globally.\n\t\t\t- Ubiquitous multi-modal UX: Next to Later The future will see the rise of ubiquitous displays, computing [43], and interfaces\n\t\t\t- screens and projections seamlessly integrated into our environments. These displays will not only provide information and entertainment but will serve as interfaces for our interactions with AI. Gesture may come to the fore, and subvocalisation to talk to personal AIs will be possible.\n\t- ### [Industry perspective](https://chat.openai.com/g/g-xhDmZxdJW-industry-predictions-engine/)  << this is 133 industry reports in a GPT I have made.\n\t- <iframe src=\"https://chat.openai.com/share/bbe7c775-b764-40c3-b87e-cf87fdd1a3a7\" style=\"width: 100%; height: 600px\"></iframe>\n- [[rework based on gpt]]\n- This is a [[presentation]] slide and the next slide is\n\n## Current Landscape (2025)\n\n- Industry adoption and implementations\n  - Metaverse platforms continue to evolve with focus on interoperability and open standards\n  - Web3 integration accelerating with decentralised identity and asset ownership\n  - Enterprise adoption growing in virtual collaboration, training, and digital twins\n  - UK companies increasingly active in metaverse development and immersive technologies\n\n- Technical capabilities\n  - Real-time rendering at photorealistic quality levels\n  - Low-latency networking enabling seamless multi-user experiences\n  - AI-driven content generation and procedural world building\n  - Spatial audio and haptics enhancing immersion\n\n- UK and North England context\n  - Manchester: Digital Innovation Factory supports metaverse startups and research\n  - Leeds: Holovis leads in immersive experiences for entertainment and training\n  - Newcastle: University research in spatial computing and interactive systems\n  - Sheffield: Advanced manufacturing using digital twin technology\n\n- Standards and frameworks\n  - Metaverse Standards Forum driving interoperability protocols\n  - WebXR enabling browser-based immersive experiences\n  - glTF and USD for 3D asset interchange\n  - Open Metaverse Interoperability Group defining cross-platform standards\n\n## Metadata\n\n- **Last Updated**: 2025-11-16\n- **Review Status**: Automated remediation with 2025 context\n- **Verification**: Academic sources verified\n- **Regional Context**: UK/North England where applicable",
  "properties": {
    "id": "65a2a968-c150-4dca-8ddc-902f29a8d7e0",
    "collapsed": "true",
    "- ontology": "true",
    "- term-id": "mv-564158265963",
    "- preferred-term": "State of the art in AI",
    "- source-domain": "metaverse",
    "- status": "active",
    "- public-access": "true",
    "- definition": "A component of the metaverse ecosystem focusing on state of the art in ai.",
    "- maturity": "mature",
    "- authority-score": "0.85",
    "- owl:class": "mv:StateOfTheArtInAi",
    "- owl:physicality": "ConceptualEntity",
    "- owl:role": "Concept",
    "- belongsToDomain": "[[MetaverseDomain]]",
    "- enables": "[[ImmersiveExperience]], [[Presence]], [[SpatialComputing]]",
    "- requires": "[[DisplayTechnology]], [[TrackingSystem]], [[RenderingEngine]]",
    "- bridges-to": "[[HumanComputerInteraction]], [[ComputerVision]], [[Robotics]]",
    "public": "true"
  },
  "backlinks": [
    "Suggested Reading Order"
  ],
  "wiki_links": [
    "Politics, Law, Privacy",
    "Social contract and jobs",
    "presentation",
    "TrackingSystem",
    "Infrastructure",
    "DisplayTechnology",
    "ComputerVision",
    "Robotics",
    "rework based on gpt",
    "Privacy, Trust and Safety",
    "Hardware and Edge",
    "HumanComputerInteraction",
    "SpatialComputing",
    "ImmersiveExperience",
    "Presence",
    "Update Cycle",
    "Proprietary Large Language Models",
    "MetaverseDomain",
    "Death of the Internet",
    "Education and AI",
    "RenderingEngine"
  ],
  "ontology": {
    "term_id": "mv-564158265963",
    "preferred_term": "State of the art in AI",
    "definition": "A component of the metaverse ecosystem focusing on state of the art in ai.",
    "source_domain": "metaverse",
    "maturity_level": null,
    "authority_score": 0.85
  }
}