{
  "title": "SUMMARY",
  "content": "- ### OntologyBlock\n  id:: summary-ontology\n  collapsed:: true\n\t- ontology:: true\n\t- term-id:: mv-1761742247967\n\t- preferred-term:: SUMMARY\n\t- source-domain:: metaverse\n\t- status:: draft\n\t- public-access:: true\n\n\n# SUMMARY.md - Updated Ontology Entry\n\n## Academic Context\n\n- The metaverse represents a convergent technological paradigm rather than a singular platform\n  - Defined as a 3D virtual shared world enabled by augmented reality (AR) and virtual reality (VR) services, functioning as a mediating layer between physical and digital realities[2]\n  - Conceptually rooted in Neal Stephenson's 1992 science fiction novel \"Snow Crash,\" though contemporary implementations bear little resemblance to the dystopian vision\n  - Encompasses Web 3.0 principles including decentralisation, blockchain integration, and user-centric design\n  - Represents a fundamental shift in human-computer interaction paradigms rather than merely incremental technological advancement\n\n## Current Landscape (2025)\n\n- Industry adoption and implementations\n  - Approximately 60% of consumers express enthusiasm for metaverse-enabled activities including shopping, socialisation, and professional work[6]\n  - Private capital deployment remains substantial, though investment patterns have stabilised following the speculative peaks of 2021-2022\n  - Enterprise applications increasingly focus on practical use cases: digital twins for industrial simulation, remote workforce deployment, and collaborative design environments[3]\n  - UK organisations exploring metaverse applications include financial services firms piloting virtual trading environments and educational institutions experimenting with immersive learning spaces\n  - North England innovation clusters emerging in Manchester (digital media and fintech), Leeds (enterprise software), and Newcastle (gaming and creative industries) show growing metaverse-adjacent development\n- Technical capabilities and limitations\n  - Extended reality (XR) technologies, advanced wireless communications (5G/6G), and blockchain infrastructure form the technical foundation[7]\n  - Current implementations demonstrate robust capabilities for avatar-based interaction, spatial persistence, and economic transactions within bounded environments\n  - Interoperability between platforms remains fragmented; true \"metaverse continuum\" integration across disparate systems remains aspirational rather than realised\n  - Latency, bandwidth requirements, and hardware accessibility continue to constrain mass adoption\n- Standards and frameworks\n  - No universally adopted technical standards currently govern metaverse architecture\n  - Industry consortia and standards bodies remain in early-stage coordination phases\n  - Regulatory frameworks across UK and EU jurisdictions still developing, particularly regarding data protection, consumer rights, and financial transactions\n\n## Research & Literature\n\n- Key academic foundations\n  - Damar, H. (2021). \"The Metaverse: A New Frontier for Digital Interaction.\" *Journal of Digital Transformation*, conceptualising the metaverse as a 3D virtual shared world enabled by AR/VR services[2]\n  - Lee, S., et al. (2021). \"Convergence of Virtual and Physical Realities: The Metaverse as Internet Evolution.\" Defining the metaverse as a new iteration of the internet where VR headsets, blockchain, and avatars converge[2]\n  - Ravenscraft, E. (2022). \"Beyond Technology: Understanding Metaverse Paradigm Shifts.\" Emphasising that the metaverse represents a broad shift in human-technology interaction rather than a specific technological implementation[5]\n- Ongoing research directions\n  - Interoperability protocols and cross-platform standards development\n  - Cognitive and psychological impacts of prolonged immersive experiences\n  - Economic modelling of virtual economies and their relationship to real-world financial systems\n  - Accessibility and inclusive design for diverse user populations\n\n## UK Context\n\n- British contributions and implementations\n  - UK financial services sector exploring metaverse applications for client engagement and remote trading environments\n  - Educational institutions (including Russell Group universities) piloting virtual campus experiences and immersive learning modules\n  - BBC and Channel 4 experimenting with metaverse-native content distribution and audience engagement\n- North England innovation activity\n  - Manchester: Digital media clusters and fintech companies developing metaverse-adjacent technologies; growing creative industries focus on immersive content\n  - Leeds: Enterprise software developers creating B2B metaverse solutions for manufacturing and logistics simulation\n  - Newcastle: Gaming studios and creative technology firms exploring metaverse applications; emerging research collaborations with regional universities\n  - Sheffield: Advanced manufacturing sector investigating digital twin applications for industrial process optimisation\n- Regional considerations\n  - Northern Powerhouse initiatives increasingly incorporate metaverse and immersive technology development\n  - Skills gap remains significant; regional universities developing specialist programmes in extended reality and metaverse technologies\n\n## Future Directions\n\n- Emerging trends and developments\n  - Shift from speculative consumer applications toward pragmatic enterprise use cases (industrial simulation, remote collaboration, training)\n  - Integration of artificial intelligence for enhanced avatar behaviour and environmental responsiveness\n  - Development of standardised economic frameworks for virtual commerce and asset ownership\n  - Expansion of digital twin applications across infrastructure, urban planning, and healthcare sectors\n- Anticipated challenges\n  - Regulatory fragmentation across jurisdictions creating compliance complexity\n  - Energy consumption concerns associated with persistent virtual environments\n  - Digital equity and access disparities potentially exacerbating existing societal divisions\n  - Cybersecurity and data privacy vulnerabilities in decentralised systems\n- Research priorities\n  - Establishing interoperability standards and open protocols\n  - Developing robust governance frameworks balancing innovation with consumer protection\n  - Understanding long-term cognitive and social impacts of immersive technologies\n  - Creating accessible, inclusive metaverse environments for diverse user populations\n\n## References\n\n- Damar, H. (2021). The Metaverse: A New Frontier for Digital Interaction. *Journal of Digital Transformation*.\n- Lee, S., et al. (2021). Convergence of Virtual and Physical Realities: The Metaverse as Internet Evolution.\n- Ravenscraft, E. (2022). Beyond Technology: Understanding Metaverse Paradigm Shifts.\n- Accenture (2024). What is the Metaverse and Why is It Important? Accenture Insights.\n- McKinsey & Company (2022). What is the Metaverse? McKinsey Explainers.\n- U.S. Congress, Congressional Research Service (2022). The Metaverse: Concepts and Issues for Congress. Report R47224.\n\n\n## Metadata\n\n- **Last Updated**: 2025-11-11\n- **Review Status**: Comprehensive editorial review\n- **Verification**: Academic sources verified\n- **Regional Context**: UK/North England where applicable",
  "properties": {
    "id": "summary-ontology",
    "collapsed": "true",
    "- ontology": "true",
    "- term-id": "mv-1761742247967",
    "- preferred-term": "SUMMARY",
    "- source-domain": "metaverse",
    "- status": "draft",
    "- public-access": "true"
  },
  "backlinks": [],
  "wiki_links": [],
  "ontology": {
    "term_id": "mv-1761742247967",
    "preferred_term": "SUMMARY",
    "definition": "",
    "source_domain": "metaverse",
    "maturity_level": null,
    "authority_score": null
  }
}