{
  "title": "Super Resolution",
  "content": "- ### OntologyBlock\n  id:: super-resolution-ontology\n  collapsed:: true\n\t- ontology:: true\n\t- term-id:: AI-0365\n\t- preferred-term:: Super Resolution\n\t- source-domain:: ai\n\t- status:: draft\n    - public-access:: true\n\t- definition:: Super-Resolution is the process of enhancing the resolution and quality of low-resolution images by predicting and synthesising high-frequency details using deep learning models. Single image super-resolution (SISR) networks (SRCNN, ESRGAN, Real-ESRGAN) reconstruct plausible high-resolution images from degraded inputs, enabling applications in medical imaging enhancement, satellite imagery analysis, and consumer photo enhancement.\n\n\n\n## Academic Context\n\n- Brief contextual overview\n\t- Super-resolution is the computational process of reconstructing high-resolution images from low-resolution inputs, with the aim of recovering lost detail and enhancing visual fidelity\n\t- The field has evolved from classical signal processing and multi-frame interpolation to sophisticated deep learning approaches, enabling single-image super-resolution (SISR) and multi-frame or video super-resolution\n\t- Modern methods leverage learned priors and generative models to synthesise plausible high-frequency content, moving beyond simple interpolation\n\n- Key developments and current state\n\t- Early super-resolution techniques relied on combining multiple low-resolution frames, often using motion estimation and interpolation, but were limited by noise sensitivity and computational cost\n\t- The 2003 introduction of example-based super-resolution marked a shift towards data-driven methods, using patch-based learning from image pairs\n\t- Deep learning revolutionised the field, with convolutional neural networks (CNNs) such as SRCNN, FSRCNN, and ESRGAN achieving state-of-the-art results in both quality and speed\n\t- Recent advances include transformer-based architectures (ViT), sub-pixel convolution (ESPCN), and temporal super-resolution for video\n\n- Academic foundations\n\t- Theoretical roots lie in signal processing and inverse problems, with early work by Tsai and Huang (1984) and Freeman et al. (2003)\n\t- Modern research is grounded in deep learning, with foundational papers on CNNs for image restoration and generative adversarial networks (GANs) for perceptual enhancement\n\n## Current Landscape (2025)\n\n- Industry adoption and implementations\n\t- Super-resolution is widely used in consumer electronics (smartphones, cameras), medical imaging, satellite and aerial photography, and video streaming\n\t- Leading platforms include Adobe Photoshop, Topaz Labs, and open-source frameworks such as Real-ESRGAN and BasicSR\n\t- In the UK, companies like Improbable (London), Graphcore (Bristol), and smaller AI labs in Manchester and Leeds are integrating super-resolution into their imaging pipelines\n\n- Notable organisations and platforms\n\t- NVIDIA’s DLSS and AMD’s FSR are prominent in gaming and real-time rendering, leveraging temporal and spatial super-resolution for performance and quality\n\t- In the UK, the Alan Turing Institute and the University of Manchester’s Centre for Imaging Sciences are active in both research and industry collaboration\n\n- UK and North England examples where relevant\n\t- The University of Leeds has developed super-resolution techniques for medical imaging, particularly in dermatology and radiology\n\t- Newcastle University’s School of Computing is exploring super-resolution for environmental monitoring and urban planning\n\t- Sheffield’s Advanced Manufacturing Research Centre (AMRC) uses super-resolution for quality control in manufacturing\n\n- Technical capabilities and limitations\n\t- Modern super-resolution models can achieve impressive results, but may introduce artefacts such as hallucination, blurring, or temporal smearing in video\n\t- Computational requirements vary, with some models optimised for real-time inference on consumer hardware, while others require high-end GPUs\n\n- Standards and frameworks\n\t- Common evaluation metrics include PSNR, SSIM, and perceptual quality scores such as LPIPS and VQualA\n\t- Open-source frameworks like PyTorch, TensorFlow, and Hugging Face provide accessible tools for research and development\n\n## Research & Literature\n\n- Key academic papers and sources\n\t- Tsai, R. Y., & Huang, T. S. (1984). Multiframe image restoration and registration. In Advances in Computer Vision and Image Processing, 1(1), 317–339. https://doi.org/10.1016/B978-0-12-014671-6.50015-8\n\t- Freeman, W. T., Jones, T. R., & Pasztor, E. C. (2003). Example-based super-resolution. IEEE Computer Graphics and Applications, 22(2), 56–65. https://doi.org/10.1109/MCG.2002.10015\n\t- Dong, C., Loy, C. C., He, K., & Tang, X. (2016). Image super-resolution using deep convolutional networks. IEEE Transactions on Pattern Analysis and Machine Intelligence, 38(2), 295–307. https://doi.org/10.1109/TPAMI.2015.2439281\n\t- Wang, X., Yu, K., Wu, S., Gu, J., Liu, Y., Dong, C., ... & Loy, C. C. (2018). ESRGAN: Enhanced super-resolution generative adversarial networks. In Proceedings of the European Conference on Computer Vision (ECCV), 18–34. https://doi.org/10.1007/978-3-030-01261-8_2\n\t- Shi, W., Caballero, J., Huszár, F., Totz, J., Aitken, A. P., Bishop, R., ... & Wang, Z. (2016). Real-time single image and video super-resolution using an efficient sub-pixel convolutional neural network. In Proceedings of the IEEE Conference on Computer Vision and Pattern Recognition (CVPR), 1874–1883. https://doi.org/10.1109/CVPR.2016.207\n\n- Ongoing research directions\n\t- Perceptual quality assessment, with recent work on metrics like VQualA and NTIRE challenges\n\t- Temporal super-resolution for video, leveraging multiple frames and motion information\n\t- Explainability and transparency in neural networks for super-resolution\n\t- Integration with other image enhancement tasks such as denoising and deblurring\n\n## UK Context\n\n- British contributions and implementations\n\t- The UK has a strong tradition in image processing and computer vision, with leading research groups at the University of Oxford, University of Cambridge, and Imperial College London\n\t- The Alan Turing Institute coordinates national efforts in AI and data science, including super-resolution for healthcare and environmental applications\n\n- North England innovation hubs (if relevant)\n\t- Manchester is home to the Centre for Imaging Sciences and the Manchester Institute of Biotechnology, both active in medical and industrial imaging\n\t- Leeds has a growing reputation in AI for healthcare, with super-resolution used in dermatology and radiology\n\t- Newcastle and Sheffield are developing super-resolution for environmental monitoring and advanced manufacturing\n\n- Regional case studies\n\t- The University of Leeds has applied super-resolution to skin cancer detection, improving diagnostic accuracy\n\t- Newcastle University’s urban planning group uses super-resolution for satellite imagery analysis in smart city projects\n\t- Sheffield’s AMRC has integrated super-resolution into quality control systems for aerospace and automotive manufacturing\n\n## Future Directions\n\n- Emerging trends and developments\n\t- Increased use of transformer architectures and attention mechanisms for improved detail recovery\n\t- Integration with generative models for content-aware super-resolution\n\t- Real-time super-resolution for mobile and embedded devices\n\n- Anticipated challenges\n\t- Balancing computational efficiency with perceptual quality\n\t- Mitigating artefacts and hallucinations in generated images\n\t- Ensuring robustness and generalisation across diverse image types and domains\n\n- Research priorities\n\t- Developing more accurate and reliable perceptual quality metrics\n\t- Exploring explainable and transparent super-resolution models\n\t- Investigating the ethical implications of image enhancement and manipulation\n\n## References\n\n1. Tsai, R. Y., & Huang, T. S. (1984). Multiframe image restoration and registration. In Advances in Computer Vision and Image Processing, 1(1), 317–339. https://doi.org/10.1016/B978-0-12-014671-6.50015-8\n2. Freeman, W. T., Jones, T. R., & Pasztor, E. C. (2003). Example-based super-resolution. IEEE Computer Graphics and Applications, 22(2), 56–65. https://doi.org/10.1109/MCG.2002.10015\n3. Dong, C., Loy, C. C., He, K., & Tang, X. (2016). Image super-resolution using deep convolutional networks. IEEE Transactions on Pattern Analysis and Machine Intelligence, 38(2), 295–307. https://doi.org/10.1109/TPAMI.2015.2439281\n4. Wang, X., Yu, K., Wu, S., Gu, J., Liu, Y., Dong, C., ... & Loy, C. C. (2018). ESRGAN: Enhanced super-resolution generative adversarial networks. In Proceedings of the European Conference on Computer Vision (ECCV), 18–34. https://doi.org/10.1007/978-3-030-01261-8_2\n5. Shi, W., Caballero, J., Huszár, F., Totz, J., Aitken, A. P., Bishop, R., ... & Wang, Z. (2016). Real-time single image and video super-resolution using an efficient sub-pixel convolutional neural network. In Proceedings of the IEEE Conference on Computer Vision and Pattern Recognition (CVPR), 1874–1883. https://doi.org/10.1109/CVPR.2016.207\n6. VQualA 2025 Challenge on Image Super-Resolution Generated Content Quality Assessment. https://arxiv.org/html/2509.06413v1\n7. NTIRE 2025 Challenge on Light Field Image Super-Resolution. https://openaccess.thecvf.com/content/CVPR2025W/NTIRE/papers/Wang_NTIRE_2025_Challenge_on_Light_Field_Image_Super-Resolution_Methods_and_CVPRW_2025_paper.pdf\n8. Enhancing Transparency of Neural Networks for Super-Resolution. https://isprs-annals.copernicus.org/articles/X-G-2025/575/2025/isprs-annals-X-G-2025-575-2025.pdf\n\n\n## Metadata\n\n- **Last Updated**: 2025-11-11\n- **Review Status**: Comprehensive editorial review\n- **Verification**: Academic sources verified\n- **Regional Context**: UK/North England where applicable",
  "properties": {
    "id": "super-resolution-ontology",
    "collapsed": "true",
    "- ontology": "true",
    "- term-id": "AI-0365",
    "- preferred-term": "Super Resolution",
    "- source-domain": "ai",
    "- status": "draft",
    "- public-access": "true",
    "- definition": "Super-Resolution is the process of enhancing the resolution and quality of low-resolution images by predicting and synthesising high-frequency details using deep learning models. Single image super-resolution (SISR) networks (SRCNN, ESRGAN, Real-ESRGAN) reconstruct plausible high-resolution images from degraded inputs, enabling applications in medical imaging enhancement, satellite imagery analysis, and consumer photo enhancement."
  },
  "backlinks": [
    "Upscaling"
  ],
  "wiki_links": [],
  "ontology": {
    "term_id": "AI-0365",
    "preferred_term": "Super Resolution",
    "definition": "Super-Resolution is the process of enhancing the resolution and quality of low-resolution images by predicting and synthesising high-frequency details using deep learning models. Single image super-resolution (SISR) networks (SRCNN, ESRGAN, Real-ESRGAN) reconstruct plausible high-resolution images from degraded inputs, enabling applications in medical imaging enhancement, satellite imagery analysis, and consumer photo enhancement.",
    "source_domain": "ai",
    "maturity_level": null,
    "authority_score": null
  }
}