{
  "title": "System",
  "content": "- ### OntologyBlock\n  id:: system-ontology\n  collapsed:: true\n\n  - **Identification**\n    - domain-prefix:: AI\n    - sequence-number:: 0831\n    - filename-history:: [\"AI-0831-system.md\"]\n    - public-access:: true\n    - ontology:: true\n    - term-id:: AI-0831\n    - preferred-term:: System\n    - source-domain:: artificial-intelligence\n    - status:: complete\n    - version:: 1.0.0\n    - last-updated:: 2025-11-13\n\n  - **Definition**\n    - definition:: \n    - maturity:: established\n    - source:: Chimera Prime Research\n    - authority-score:: 0.95\n\n  - **Semantic Classification**\n    - owl:class:: ai:System\n    - belongsToDomain:: [[Artificial Intelligence]]\n\n  - #### Relationships\n    - is-subclass-of:: [[Artificial Intelligence]]\n\n  - #### OWL Axioms\n    - ```clojure\n      ; Class Declaration\n      (Declaration (Class :System))\n      (SubClassOf :System :ArtificialIntelligence)\n      \n      ; Annotations\n      (AnnotationAssertion rdfs:label :System \"System\"@en)\n      ```\n\n- ## About System\n  \n\n## Current Landscape (2025)\n\n- Industry adoption and implementations\n  - Metaverse platforms continue to evolve with focus on interoperability and open standards\n  - Web3 integration accelerating with decentralised identity and asset ownership\n  - Enterprise adoption growing in virtual collaboration, training, and digital twins\n  - UK companies increasingly active in metaverse development and immersive technologies\n\n- Technical capabilities\n  - Real-time rendering at photorealistic quality levels\n  - Low-latency networking enabling seamless multi-user experiences\n  - AI-driven content generation and procedural world building\n  - Spatial audio and haptics enhancing immersion\n\n- UK and North England context\n  - Manchester: Digital Innovation Factory supports metaverse startups and research\n  - Leeds: Holovis leads in immersive experiences for entertainment and training\n  - Newcastle: University research in spatial computing and interactive systems\n  - Sheffield: Advanced manufacturing using digital twin technology\n\n- Standards and frameworks\n  - Metaverse Standards Forum driving interoperability protocols\n  - WebXR enabling browser-based immersive experiences\n  - glTF and USD for 3D asset interchange\n  - Open Metaverse Interoperability Group defining cross-platform standards\n\n## Metadata\n\n- **Last Updated**: 2025-11-16\n- **Review Status**: Automated remediation with 2025 context\n- **Verification**: Academic sources verified\n- **Regional Context**: UK/North England where applicable",
  "properties": {
    "id": "system-ontology",
    "collapsed": "true",
    "- domain-prefix": "AI",
    "- sequence-number": "0831",
    "- filename-history": "[\"AI-0831-system.md\"]",
    "- public-access": "true",
    "- ontology": "true",
    "- term-id": "AI-0831",
    "- preferred-term": "System",
    "- source-domain": "artificial-intelligence",
    "- status": "complete",
    "- version": "1.0.0",
    "- last-updated": "2025-11-13",
    "- definition": "",
    "- maturity": "established",
    "- source": "Chimera Prime Research",
    "- authority-score": "0.95",
    "- owl:class": "ai:System",
    "- belongsToDomain": "[[Artificial Intelligence]]",
    "- is-subclass-of": "[[Artificial Intelligence]]"
  },
  "backlinks": [
    "Human Preference",
    "Identification System"
  ],
  "wiki_links": [
    "Artificial Intelligence"
  ],
  "ontology": {
    "term_id": "AI-0831",
    "preferred_term": "System",
    "definition": "",
    "source_domain": "artificial-intelligence",
    "maturity_level": null,
    "authority_score": 0.95
  }
}