{
  "title": "Real-Time Language Translation",
  "content": "# Real-Time Language Translation\n\n### OntologyBlock\nid:: real-time-translation-ontology\ncollapsed:: true\n- ontology:: true\n- term-id:: TELE-105\n- preferred-term:: Real-Time Language Translation\n- alternate-terms::\n  - Live Translation\n  - Simultaneous Translation\n  - AI Translation for Telepresence\n  - Speech-to-Speech Translation\n- source-domain:: tele\n- status:: active\n- public-access:: true\n- definition:: \"The use of artificial intelligence-powered natural language processing to automatically translate spoken or written communication between languages during live telepresence interactions with sub-second latency, enabling cross-lingual collaboration without human interpreters through neural machine translation, speech recognition, and text-to-speech synthesis.\"\n- maturity:: developing\n- authority-score:: 0.88\n- owl:class:: tele:RealTimeLanguageTranslation\n- owl:physicality:: ConceptualEntity\n- owl:role:: Process\n- belongsToDomain::\n  - [[TELE-0000-telepresence-domain]]\n  - [[AIEnhancedCollaboration]]\n- bridges-to::\n  - [[AIDomain]]\n\n#### Relationships\nid:: real-time-translation-relationships\n- is-subclass-of:: [[LanguageTranslation]], [[ArtificialIntelligence]]\n- enables:: [[CrossLingualCollaboration]], [[GlobalTeamwork]], [[MulticulturalMeetings]]\n- requires:: [[NeuralMachineTranslation]], [[SpeechRecognition]], [[TextToSpeech]], [[LowLatencyNetworking]]\n- has-component:: [[TELE-106-speech-to-speech-translation]], [[AutomaticSpeechRecognition]], [[LanguageModels]]\n- related-to:: [[TELE-002-telecollaboration]], [[TELE-107-ai-meeting-assistants]], [[NaturalLanguageProcessing]]\n\n#### OWL Axioms\nid:: real-time-translation-owl-axioms\ncollapsed:: true\n- ```clojure\n  Declaration(Class(tele:RealTimeLanguageTranslation))\n\n  SubClassOf(tele:RealTimeLanguageTranslation tele:AIEnhancedCollaboration)\n  SubClassOf(tele:RealTimeLanguageTranslation ai:NaturalLanguageProcessing)\n\n  SubClassOf(tele:RealTimeLanguageTranslation\n    ObjectSomeValuesFrom(tele:belongsToDomain tele:TelecollaborationDomain)\n  )\n\n  SubClassOf(tele:RealTimeLanguageTranslation\n    ObjectSomeValuesFrom(tele:enables tele:CrossLingualCollaboration)\n  )\n\n  SubClassOf(tele:RealTimeLanguageTranslation\n    ObjectSomeValuesFrom(tele:bridgesTo ai:AIDomain)\n  )\n\n  AnnotationAssertion(rdfs:label tele:RealTimeLanguageTranslation \"Real-Time Language Translation\"@en-GB)\n  AnnotationAssertion(rdfs:comment tele:RealTimeLanguageTranslation \"AI-powered live translation for telepresence\"@en-GB)\n  AnnotationAssertion(dcterms:identifier tele:RealTimeLanguageTranslation \"TELE-105\"^^xsd:string)\n  AnnotationAssertion(dcterms:created tele:RealTimeLanguageTranslation \"2025-11-16\"^^xsd:date)\n  ```\n\n## Definition\n\n**Real-Time Language Translation** enables participants in telepresence sessions to communicate fluently across language barriers through AI systems that automatically translate speech or text with latencies under 1 second. These systems integrate three AI capabilities: automatic speech recognition (ASR) converting spoken words to text, neural machine translation (NMT) translating text between languages, and text-to-speech (TTS) synthesising translated speech in the target language whilst preserving speaker voice characteristics and emotional tone.\n\nModern real-time translation achieves near-human quality for common language pairs (English-Spanish, English-Mandarin) with word error rates below 5% and translation BLEU scores exceeding 50. Integration into telepresence platforms ([[TELE-020-virtual-reality-telepresence]], [[TELE-002-telecollaboration]]) enables global teams to collaborate naturally: English speakers hear Chinese participants in English with their original voice timbre, whilst Chinese speakers simultaneously hear English rendered in Mandarin. This dissolves linguistic barriers that historically restricted cross-border collaboration.\n\n## Current Landscape (2025)\n\nReal-time translation has achieved mainstream deployment in 2025, with major telepresence platforms offering built-in translation and standalone apps providing universal translation services.\n\n**Adoption Statistics**:\n- 62% of multinational companies use real-time translation in video conferences (Gartner Survey, 2025)\n- Google Translate processes 1.1 billion translation requests daily (Google, 2025)\n- Microsoft Teams supports 40+ languages with live captions/translation\n- Average latency: 400-800ms speech-to-translated-speech\n\n**Technology Capabilities (2025)**:\n- **Languages**: 100+ languages supported (Google, Microsoft, Meta)\n- **Accuracy**: 95%+ for high-resource languages, 80-90% for low-resource\n- **Voice Preservation**: TTS maintains speaker's prosody, gender, accent\n- **Context Awareness**: Transformer models understand multi-turn conversations\n\n**UK Context**:\n- **NHS**: Uses real-time translation for non-English-speaking patients (Language Line integration)\n- **University of Edinburgh**: Research on Scottish Gaelic-English neural translation\n- **UK Government**: Foreign Office pilots real-time translation for diplomatic calls\n- **DeepL (UK users)**: German company's high-accuracy translation service widely adopted in UK\n\n## Technical Architecture\n\n### Pipeline Components\n\n1. **Automatic Speech Recognition (ASR)**\n   - **Input**: Audio stream from microphone\n   - **Processing**: Acoustic model → phoneme probabilities → language model → text transcription\n   - **Models**: Whisper (OpenAI), wav2vec 2.0 (Meta), Google ASR\n   - **Latency**: 100-300ms\n\n2. **Neural Machine Translation (NMT)**\n   - **Input**: Source language text\n   - **Processing**: Transformer encoder-decoder architecture\n   - **Models**: GPT-4 Turbo, Google Neural Machine Translation, DeepL\n   - **Latency**: 50-200ms\n\n3. **Text-to-Speech (TTS)**\n   - **Input**: Translated text\n   - **Processing**: Voice cloning neural vocoder (e.g., VITS, Tacotron 2)\n   - **Models**: ElevenLabs, Microsoft Azure TTS, Google WaveNet\n   - **Latency**: 200-400ms\n\n**Total Latency**: 350-900ms (perceived as \"real-time\" for most users)\n\n### Neural Models\n\n**Transformer Architecture** (Vaswani et al., 2017):\n- Attention mechanism enables context-aware translation\n- Encoder processes source sentence, decoder generates translation\n- Handles long-range dependencies (e.g., gender agreement across sentence)\n\n**Multilingual Models**:\n- **M2M-100** (Meta): Translates 100 languages without English pivot\n- **NLLB-200** (Meta): 200 languages including low-resource (Yoruba, Kazakh)\n- **GPT-4**: Multilingual understanding, translation as instruction-following task\n\n**Voice Cloning**:\n- **Zero-Shot TTS**: Synthesise any voice from 3-second sample\n- **Voice Conversion**: Maintain original speaker's characteristics in translation\n- **Emotion Preservation**: Retain excitement, sadness, urgency in translated speech\n\n## Major Platforms and Services\n\n### Google Translate (Interpreter Mode)\n- **Features**: 100+ languages, real-time bidirectional speech translation\n- **Integration**: Google Meet (live captions/translation)\n- **Accuracy**: 95% for English-Spanish, 85% for English-Arabic\n- **Cost**: Free for personal use\n\n### Microsoft Translator (Azure Cognitive Services)\n- **Features**: 40 languages speech translation, custom glossaries (industry terms)\n- **Integration**: Microsoft Teams (live transcription/translation)\n- **Accuracy**: 94% average (high-resource languages)\n- **Cost**: £7.50 per audio hour\n\n### Meta's Seamless Communication\n- **Features**: Streaming translation (start translating before sentence finishes)\n- **Models**: SeamlessM4T (multilingual, multimodal)\n- **Integration**: Meta Quest VR (experimental)\n- **Cost**: Research preview (not yet commercial)\n\n### Apple Translate\n- **Features**: On-device translation (11 languages), conversation mode\n- **Integration**: FaceTime (live captions), Safari (webpage translation)\n- **Privacy**: All processing on iPhone/Mac (no cloud transmission)\n- **Cost**: Free with Apple devices\n\n### DeepL\n- **Features**: 31 languages, highest-accuracy general translation\n- **Integration**: API for custom applications, document translation\n- **Accuracy**: Human evaluation ranks DeepL above Google Translate (multiple studies)\n- **Cost**: £5.99/month personal, £25/month Pro\n\n## Applications\n\n### Global Business Meetings\n- Executives in London, Tokyo, São Paulo converse naturally\n- Real-time captions display in each participant's language\n- AI meeting assistants ([[TELE-107-ai-meeting-assistants]]) generate multilingual summaries\n\n### International Education\n- Students attend lectures delivered in foreign languages\n- Real-time subtitles enable participation without language barriers\n- Example: UK universities with international student bodies\n\n### Healthcare\n- Doctors communicate with non-English-speaking patients via real-time translation\n- NHS Language Line provides phone interpretation; AI translation augments this\n- Critical for emergency consultations where interpreters unavailable\n\n### Customer Service\n- Call centres handle global customers without multilingual staff\n- AI translates customer speech to agent's language and vice versa\n- Example: British Airways customer service for international passengers\n\n### Diplomacy and International Relations\n- United Nations experiments with AI interpretation (not yet official)\n- UK Foreign Office uses translation for informal diplomatic calls\n- Risk: Nuanced diplomatic language requires human verification\n\n## Challenges and Limitations\n\n### Technical Challenges\n- **Latency**: Sub-second translation challenging for simultaneous interpretation\n- **Accuracy**: Idiomatic expressions, cultural references often mistranslated\n- **Homonyms**: \"Bank\" (financial institution vs. river bank) context-dependent\n- **Low-Resource Languages**: 90% of 7,000+ languages lack sufficient training data\n\n### Cultural and Social Challenges\n- **Tone and Formality**: Japanese honorifics, German Sie/du (formal/informal \"you\") hard to preserve\n- **Humour and Sarcasm**: Often lost in translation\n- **Bias**: Training data biases (e.g., gendered translations: \"doctor\" → male pronouns)\n- **Trust**: Users doubt AI accuracy, fear miscommunication in high-stakes contexts\n\n### Ethical Considerations\n- **Privacy**: Voice data sensitive; cloud translation transmits audio to servers\n- **Unemployment**: Human interpreters face job displacement\n- **Misinformation**: Errors could have serious consequences (medical, legal)\n- **Dependency**: Over-reliance on AI may reduce language learning motivation\n\n## UK-Specific Context\n\n### Languages Supported\n- **British English**: Recognised as distinct from American English (spelling, vocabulary)\n- **Regional Languages**: Welsh (well-supported), Scottish Gaelic (improving), Irish (limited)\n- **Immigration**: Arabic, Urdu, Polish, Romanian well-supported for UK immigrant communities\n\n### Regulatory Environment\n- **GDPR**: Voice data subject to strict privacy protections (UK GDPR post-Brexit)\n- **NHS Guidelines**: Translation services must be human-verified for clinical decisions\n- **Education Standards**: AI translation permitted for coursework with disclosure\n\n## Future Directions\n\n**Near-Term (2025-2027)**:\n- **<100ms Latency**: Streaming translation (simultaneous, not consecutive)\n- **200+ Languages**: Coverage of all major world languages\n- **Emotion Detection**: Translate not just words but emotional intent\n\n**Medium-Term (2027-2030)**:\n- **Real-Time Dialect Adaptation**: Translate British English to Indian English whilst preserving formality\n- **Cultural Localisation**: Automatically adapt idioms, jokes, cultural references\n- **Holographic Translation**: Translated speech synced to AI avatar lip movements\n\n**Long-Term (2030+)**:\n- **Brain-Computer Interfaces**: Direct thought-to-translation bypassing speech\n- **Universal Translators**: Wearable devices providing instant translation (Star Trek-style)\n- **Extinct Language Revival**: AI translating ancient texts, reconstructing dead languages\n\n## Related Concepts\n\n- [[TELE-002-telecollaboration]]\n- [[TELE-020-virtual-reality-telepresence]]\n- [[TELE-106-speech-to-speech-translation]]\n- [[TELE-107-ai-meeting-assistants]]\n- [[NaturalLanguageProcessing]]\n- [[NeuralMachineTranslation]]\n\n## Academic References\n\n1. Vaswani, A., et al. (2017). \"Attention Is All You Need\". *NeurIPS 2017*.\n2. Bahdanau, D., et al. (2014). \"Neural Machine Translation by Jointly Learning to Align and Translate\". *ICLR 2015*.\n3. Salesky, E., et al. (2023). \"The Multilingual TEDx Corpus for Speech Recognition and Translation\". *ACL 2023*.\n\n## Metadata\n\n- **Term-ID**: TELE-105\n- **Last Updated**: 2025-11-16\n- **Maturity**: Developing\n- **Authority Score**: 0.88\n- **UK Context**: High (NHS, education, government)\n- **Cross-Domain**: Bridges to AI",
  "properties": {},
  "backlinks": [
    "TELE-CONV-001-metaverse-telepresence-bridge",
    "TELE-028-horizon-workrooms",
    "TELE-001-telepresence",
    "TELE-002-telecollaboration"
  ],
  "wiki_links": [
    "SpeechRecognition",
    "ArtificialIntelligence",
    "MulticulturalMeetings",
    "LowLatencyNetworking",
    "TELE-106-speech-to-speech-translation",
    "TELE-0000-telepresence-domain",
    "AIEnhancedCollaboration",
    "TextToSpeech",
    "LanguageModels",
    "LanguageTranslation",
    "NeuralMachineTranslation",
    "NaturalLanguageProcessing",
    "GlobalTeamwork",
    "AIDomain",
    "TELE-002-telecollaboration",
    "TELE-020-virtual-reality-telepresence",
    "CrossLingualCollaboration",
    "AutomaticSpeechRecognition",
    "TELE-107-ai-meeting-assistants"
  ],
  "ontology": {
    "term_id": "TELE-105",
    "preferred_term": "Real-Time Language Translation",
    "definition": "\"The use of artificial intelligence-powered natural language processing to automatically translate spoken or written communication between languages during live telepresence interactions with sub-second latency, enabling cross-lingual collaboration without human interpreters through neural machine translation, speech recognition, and text-to-speech synthesis.\"",
    "source_domain": "tele",
    "maturity_level": null,
    "authority_score": 0.88
  }
}