{
  "title": "AI Avatars",
  "content": "# AI Avatars\n\n- ### OntologyBlock\n  id:: ai-avatars-ontology\n  collapsed:: true\n  - ontology:: true\n  - term-id:: TELE-100\n  - preferred-term:: AI Avatars\n  - alternate-terms::\n  - Artificial Intelligence Avatars\n  - AI-Driven Avatars\n  - Intelligent Virtual Humans\n  - Autonomous Avatars\n  - source-domain:: tele\n  - status:: active\n  - public-access:: true\n  - definition:: \"Virtual representations of human users generated and animated by artificial intelligence systems, employing machine learning models to synthesise photorealistic appearance, facial expressions, body movements, and speech from sensor inputs or user intentions, enabling realistic telepresence without explicit keyframe animation.\"\n  - maturity:: developing\n  - authority-score:: 0.87\n  - owl:class:: tele:AIAvatars\n  - owl:physicality:: VirtualEntity\n  - owl:role:: Agent\n  - belongsToDomain::\n  - [[TELE-0000-telepresence-domain]]\n  - [[AIEnhancedCollaboration]]\n  - bridges-to::\n  - [[AIDomain]]\n  - [[MetaverseDomain]]\n\n\n#### Relationships\nid:: ai-avatars-relationships\n- is-subclass-of:: [[Avatar]], [[ArtificialIntelligence]]\n- enables:: [[PhotorealisticTelepresence]], [[AsynchronousPresence]], [[ScalableCollaboration]]\n- requires:: [[NeuralNetworks]], [[FacialTracking]], [[MotionCapture]], [[SpeechSynthesis]]\n- has-component:: [[TELE-102-codec-avatars]], [[TELE-103-metahuman-creator]], [[TELE-104-readyplayerme]]\n- related-to:: [[TELE-001-telepresence]], [[TELE-114-lip-sync-technology]], [[TELE-116-facial-expression-analysis]]\n\n#### OWL Axioms\nid:: ai-avatars-owl-axioms\ncollapsed:: true\n- ```clojure\n  Declaration(Class(tele:AIAvatars))\n\n  SubClassOf(tele:AIAvatars tele:AIEnhancedCollaboration)\n  SubClassOf(tele:AIAvatars tele:VirtualEntity)\n  SubClassOf(tele:AIAvatars ai:ArtificialIntelligence)\n\n  SubClassOf(tele:AIAvatars\n    ObjectSomeValuesFrom(tele:belongsToDomain tele:TelecollaborationDomain)\n  )\n\n  SubClassOf(tele:AIAvatars\n    ObjectSomeValuesFrom(tele:requires ai:NeuralNetworks)\n  )\n\n  SubClassOf(tele:AIAvatars\n    ObjectSomeValuesFrom(tele:bridgesTo ai:AIDomain)\n  )\n  SubClassOf(tele:AIAvatars\n    ObjectSomeValuesFrom(tele:bridgesTo mv:MetaverseDomain)\n  )\n\n  AnnotationAssertion(rdfs:label tele:AIAvatars \"AI Avatars\"@en-GB)\n  AnnotationAssertion(rdfs:comment tele:AIAvatars \"AI-generated virtual human representations for telepresence\"@en-GB)\n  AnnotationAssertion(dcterms:identifier tele:AIAvatars \"TELE-100\"^^xsd:string)\n  AnnotationAssertion(dcterms:created tele:AIAvatars \"2025-11-16\"^^xsd:date)\n  ```\n\n## Definition\n\n**AI Avatars** are virtual representations of human users wherein artificial intelligence models automate the generation of appearance, animation, and behaviour, eliminating the need for manual 3D modelling, rigging, and keyframe animation. These avatars leverage deep learning techniques including generative adversarial networks (GANs), diffusion models, and transformer-based architectures to synthesise photorealistic facial geometry, skin textures, hair, clothing, and real-time facial expressions from minimal sensor inputs such as webcam video, smartphone selfies, or even audio alone.\n\nUnlike traditional avatars requiring extensive motion capture studios, AI avatars democratise photorealistic telepresence by enabling users to create lifelike digital twins from a single photograph or brief video capture. Neural rendering techniques ([[TELE-051-3d-gaussian-splatting]], [[TELE-052-neural-radiance-fields]]) render these avatars in real-time, whilst machine learning models drive facial animation from tracked expressions ([[TELE-116-facial-expression-analysis]]), generate speech-synchronised lip movements ([[TELE-114-lip-sync-technology]]), and synthesise natural gestures from voice prosody.\n\n## Current Landscape (2025)\n\nAI avatar technology has achieved mainstream adoption in 2025, with consumer applications, enterprise telepresence platforms, and metaverse environments routinely employing AI-generated virtual humans.\n\n**Adoption Statistics**:\n- 52% of metaverse users employ AI-generated avatars (Metaverse Standards Forum Survey, 2025)\n- 89% of corporate VR meetings use AI avatars over stylised avatars (Gartner XR Trends)\n- AI avatar generation services process 430M avatar creations monthly (Statista, 2025)\n\n**Technology Capabilities (2025)**:\n- **Creation Time**: Photorealistic avatar from smartphone video in <3 minutes\n- **Real-Time Performance**: 60 FPS rendering on consumer VR headsets\n- **Facial Fidelity**: 512 blend shape parameters for sub-millimetre expressions\n- **Audio-Driven Animation**: Speech-to-animation with <30ms latency\n\n**UK Context**:\n- **Dimension Studio** (Newcastle): Produces volumetric AI avatars for broadcasting\n- **Synthesia** (London): AI video avatars for corporate communications (unicorn valuation Â£1B+)\n- **Soul Machines** (Manchester office): Autonomous digital humans with emotional intelligence\n- **University of Cambridge**: Research in neural avatar rendering and deepfake detection\n\n## Types of AI Avatars\n\n### Codec Avatars ([[TELE-102-codec-avatars]])\n**Meta Reality Labs** technology encoding high-fidelity facial scans into compressed neural representations:\n- **Capture**: 132-camera light stage records facial expressions\n- **Encoding**: Neural network compresses geometry/texture to 2KB/frame\n- **Decoding**: Real-time neural renderer reconstructs photorealistic face\n- **Fidelity**: Pore-level skin detail, eye moisture, hair strand dynamics\n- **Limitation**: Requires extensive capture session in Meta facility\n\n### MetaHuman Creator ([[TELE-103-metahuman-creator]])\n**Epic Games** cloud-based tool for creating realistic digital humans:\n- **Interface**: Web-based character customisation (facial features, body type, clothing)\n- **Database**: 10,000+ scanned faces for blend shape generation\n- **Output**: Unreal Engine-compatible avatars with 100+ facial blend shapes\n- **Animation**: Compatible with iPhone ARKit facial tracking, motion capture\n- **Use Cases**: Game development, virtual production, VR telepresence\n\n### ReadyPlayerMe ([[TELE-104-readyplayerme]])\n**Cross-platform** avatar system with AI-assisted creation:\n- **Input**: Single selfie photograph\n- **Processing**: AI generates 3D head mesh with texture\n- **Customisation**: 1,000+ clothing/accessory options\n- **Interoperability**: Compatible with 5,000+ apps/games (VRChat, Spatial, Mozilla Hubs)\n- **Privacy**: Blockchain-based identity (self-sovereign avatar ownership)\n\n### Autonomous AI Avatars\n**Fully AI-driven** avatars with independent behaviour:\n- **Examples**: Soul Machines Digital People, Synthesia AI presenters\n- **Capabilities**: Respond to user voice/text, generate natural speech, display emotional reactions\n- **Use Cases**: Customer service, education, asynchronous video messages\n- **Limitation**: Not real-time representations of human users (autonomous agents)\n\n## Technical Architecture\n\n### Avatar Generation Pipeline\n\n1. **Capture**: User provides input data\n   - Smartphone selfie (2D image)\n   - Short video (5-10 seconds)\n   - Depth sensor scan (iPhone LiDAR)\n   - Professional light-stage capture (high-end)\n\n2. **3D Reconstruction**: AI models generate geometry\n   - Depth estimation from single image (monocular depth nets)\n   - Multi-view stereo from video\n   - Neural radiance field (NeRF) encoding\n\n3. **Texture Synthesis**: AI generates photorealistic skin\n   - Generative adversarial networks (GANs) for texture completion\n   - Diffusion models for high-frequency detail (pores, wrinkles)\n   - Inverse rendering for lighting-independent albedo\n\n4. **Rigging**: Automated skeletal and blend shape setup\n   - Landmark detection for facial feature points\n   - Automated weight painting for deformation\n   - Blend shape generation from expression database\n\n5. **Real-Time Animation**: Driving avatar from live input\n   - Facial tracking from webcam/headset cameras\n   - Audio-driven animation (speech-to-blend shapes)\n   - Inverse kinematics for body gestures\n\n### Machine Learning Models\n\n**Facial Geometry**:\n- **FLAME** (Faces Learned with an Articulated Model and Expressions): Parametric face model\n- **EG3D** (Efficient Geometry-aware 3D GANs): Neural radiance field avatar generation\n- **PixelCodec**: Neural compression for real-time streaming\n\n**Animation**:\n- **LiveSpeech**: Audio-to-expression transformer model (Meta, 2024)\n- **EMOTE**: Emotional gesture synthesis from voice prosody\n- **Neural Blend Shapes**: ML-generated facial blend shapes exceeding artist-created fidelity\n\n**Rendering**:\n- **3D Gaussian Splatting** ([[TELE-051-3d-gaussian-splatting]]): Real-time photorealistic rendering\n- **Instant-NGP** ([[TELE-060-instant-ngp]]): Fast neural radiance field training\n- **Codec Avatars**: Neural texture compression\n\n## Applications\n\n### Enterprise Telepresence\n- Executive meetings with photorealistic avatars in VR ([[TELE-020-virtual-reality-telepresence]])\n- Asynchronous video messages (record once, AI lip-syncs translated versions)\n- Virtual receptionists and customer service agents\n\n### Education and Training\n- AI teaching assistants represented as avatars\n- Historical figures recreated for immersive lessons\n- Language learning with culturally appropriate avatars\n\n### Healthcare\n- AI therapist avatars for mental health counselling\n- Patient education with empathetic virtual clinicians\n- Telemedicine consultations with AI-generated doctor avatars\n\n### Entertainment\n- Virtual influencers and streamers\n- Game NPCs with photorealistic appearance\n- Virtual concerts with AI-generated performers\n\n## Ethical and Social Considerations\n\n### Deepfake Concerns\n**Risk**: AI avatars enable impersonation and synthetic media manipulation\n**Mitigations**:\n- Cryptographic signing of authentic avatars (digital watermarks)\n- Blockchain-based identity verification\n- AI detection tools (e.g., University of Cambridge deepfake classifiers)\n- Legislation: UK Online Safety Act (2024) mandates labelling synthetic media\n\n### Uncanny Valley\n**Challenge**: Near-photorealistic avatars can appear \"creepy\" if not perfect\n**Solutions**:\n- Stylised avatars (ReadyPlayerMe) avoiding photorealism\n- Progressive enhancement (start stylised, add realism as tech improves)\n- Emotional authenticity over visual fidelity\n\n### Privacy\n**Risk**: Biometric data capture (facial geometry, expressions) for avatar creation\n**Protections**:\n- GDPR compliance for facial data storage (UK, EU)\n- Local processing (on-device avatar generation)\n- User control over avatar distribution\n\n### Inclusivity\n**Risk**: AI training data biases towards certain demographics\n**Solutions**:\n- Diverse training datasets (Meta's Casual Conversations v2: 5,500 people, 45 countries)\n- Customisation tools for underrepresented features\n- Accessibility features (signing avatars for deaf users)\n\n## Future Directions\n\n**Near-Term (2025-2027)**:\n- Real-time full-body AI avatars with clothing simulation\n- Emotion-aware animation responding to conversation context\n- Cross-platform avatar portability (single avatar used across all metaverse platforms)\n\n**Medium-Term (2027-2030)**:\n- Holographic AI avatars projected without headsets\n- Thought-driven avatars controlled by brain-computer interfaces\n- Autonomous AI avatars acting as asynchronous representatives\n\n**Long-Term (2030+)**:\n- Indistinguishable photorealism (surpassing human perception thresholds)\n- Sentient AI avatars with independent personalities\n- Legal personhood for AI avatars (digital identity rights)\n\n## Related Concepts\n\n- [[TELE-001-telepresence]]\n- [[TELE-020-virtual-reality-telepresence]]\n- [[TELE-102-codec-avatars]]\n- [[TELE-103-metahuman-creator]]\n- [[TELE-104-readyplayerme]]\n- [[TELE-114-lip-sync-technology]]\n- [[TELE-116-facial-expression-analysis]]\n\n## Academic References\n\n1. Wei, S. E., et al. (2019). \"Codec Avatars: Photorealistic Telepresence at Scale\". *ACM SIGGRAPH 2019*.\n2. Li, T., et al. (2023). \"Audio-Driven 3D Facial Animation from In-the-Wild Videos\". *CVPR 2023*.\n3. Chan, E. R., et al. (2022). \"Efficient Geometry-aware 3D Generative Adversarial Networks\". *CVPR 2022*.\n\n## Metadata\n\n- **Term-ID**: TELE-100\n- **Last Updated**: 2025-11-16\n- **Maturity**: Developing\n- **Authority Score**: 0.87\n- **UK Context**: High (Synthesia, Soul Machines, Dimension Studio)\n- **Cross-Domain**: Bridges to AI, Metaverse",
  "properties": {},
  "backlinks": [
    "TELE-021-augmented-reality-collaboration",
    "TELE-006-presence",
    "TELE-020-virtual-reality-telepresence",
    "TELE-CONV-001-metaverse-telepresence-bridge",
    "TELE-028-horizon-workrooms",
    "TELE-003-social-presence-theory",
    "TELE-001-telepresence",
    "TELE-004-media-richness-theory",
    "TELE-002-telecollaboration"
  ],
  "wiki_links": [
    "TELE-102-codec-avatars",
    "AIDomain",
    "FacialTracking",
    "MetaverseDomain",
    "TELE-114-lip-sync-technology",
    "AIEnhancedCollaboration",
    "TELE-051-3d-gaussian-splatting",
    "NeuralNetworks",
    "SpeechSynthesis",
    "TELE-001-telepresence",
    "TELE-0000-telepresence-domain",
    "PhotorealisticTelepresence",
    "TELE-103-metahuman-creator",
    "TELE-020-virtual-reality-telepresence",
    "AsynchronousPresence",
    "ScalableCollaboration",
    "Avatar",
    "TELE-060-instant-ngp",
    "TELE-052-neural-radiance-fields",
    "ArtificialIntelligence",
    "TELE-104-readyplayerme",
    "MotionCapture",
    "TELE-116-facial-expression-analysis"
  ],
  "ontology": {
    "term_id": "TELE-100",
    "preferred_term": "AI Avatars",
    "definition": "\"Virtual representations of human users generated and animated by artificial intelligence systems, employing machine learning models to synthesise photorealistic appearance, facial expressions, body movements, and speech from sensor inputs or user intentions, enabling realistic telepresence without explicit keyframe animation.\"",
    "source_domain": "tele",
    "maturity_level": null,
    "authority_score": 0.87
  }
}