{
  "title": "Augmented Reality Collaboration",
  "content": "# Augmented Reality Collaboration\n\n### OntologyBlock\nid:: ar-collaboration-ontology\ncollapsed:: true\n- ontology:: true\n- term-id:: TELE-021\n- preferred-term:: Augmented Reality Collaboration\n- alternate-terms::\n  - AR Collaboration\n  - Mixed Reality Teamwork\n  - Spatial Collaboration\n  - Augmented Telepresence\n- source-domain:: tele\n- status:: active\n- public-access:: true\n- definition:: \"Collaborative work where geographically distributed team members share a common augmented reality environment, viewing and manipulating virtual 3D objects overlaid on their respective physical spaces whilst communicating via spatial audio and holographic avatars, enabling hybrid physical-virtual cooperation through AR headsets or mobile devices.\"\n- maturity:: developing\n- authority-score:: 0.85\n- owl:class:: tele:AugmentedRealityCollaboration\n- owl:physicality:: VirtualEntity\n- owl:role:: Process\n- belongsToDomain::\n  - [[TELE-0000-telepresence-domain]]\n  - [[XRCollaborationPlatforms]]\n- bridges-to::\n  - [[MetaverseDomain]]\n  - [[AIDomain]]\n\n#### Relationships\nid:: ar-collaboration-relationships\n- is-subclass-of:: [[TELE-001-telepresence]], [[TELE-002-telecollaboration]], [[AugmentedReality]]\n- enables:: [[HybridWorkspace]], [[SpatialAnnotation]], [[RemoteAssistance]], [[CollaborativeDesign]]\n- requires:: [[ARHeadset]], [[SpatialMapping]], [[ObjectTracking]], [[TELE-150-webrtc]]\n- has-component:: [[TELE-025-microsoft-hololens]], [[SpatialAnchors]], [[SharedHolograms]]\n- related-to:: [[TELE-020-virtual-reality-telepresence]], [[TELE-026-microsoft-mesh]], [[MixedReality]]\n\n#### OWL Axioms\nid:: ar-collaboration-owl-axioms\ncollapsed:: true\n- ```clojure\n  Declaration(Class(tele:AugmentedRealityCollaboration))\n\n  SubClassOf(tele:AugmentedRealityCollaboration tele:Telepresence)\n  SubClassOf(tele:AugmentedRealityCollaboration tele:Telecollaboration)\n  SubClassOf(tele:AugmentedRealityCollaboration mv:AugmentedReality)\n\n  SubClassOf(tele:AugmentedRealityCollaboration\n    ObjectSomeValuesFrom(tele:belongsToDomain tele:TelecollaborationDomain)\n  )\n\n  SubClassOf(tele:AugmentedRealityCollaboration\n    ObjectSomeValuesFrom(tele:bridgesTo mv:MetaverseDomain)\n  )\n\n  AnnotationAssertion(rdfs:label tele:AugmentedRealityCollaboration \"Augmented Reality Collaboration\"@en-GB)\n  AnnotationAssertion(rdfs:comment tele:AugmentedRealityCollaboration \"Shared AR environments for distributed teamwork\"@en-GB)\n  AnnotationAssertion(dcterms:identifier tele:AugmentedRealityCollaboration \"TELE-021\"^^xsd:string)\n  AnnotationAssertion(dcterms:created tele:AugmentedRealityCollaboration \"2025-11-16\"^^xsd:date)\n  ```\n\n## Definition\n\n**Augmented Reality Collaboration** enables distributed teams to work together in shared spatial contexts where virtual 3D content is overlaid on physical environments visible through AR headsets (Microsoft HoloLens, Magic Leap) or mobile devices (smartphones, tablets). Unlike VR telepresence ([[TELE-020-virtual-reality-telepresence]]) that immerses users entirely in virtual worlds, AR collaboration preserves awareness of the physical workspace whilst adding digital layers—holographic avatars, 3D CAD models, annotations, data visualisations—that multiple remote participants view and manipulate simultaneously from their respective locations.\n\nAR collaboration leverages spatial computing: headsets map the physical environment (SLAM - Simultaneous Localisation and Mapping), track user position/orientation, and anchor digital content to real-world coordinates via spatial anchors. When an engineer in London places a holographic engine component on their desk, a colleague in Tokyo sees the same hologram on their desk, enabling co-manipulation of shared 3D objects despite geographical separation. Spatial audio renders voices directionally, whilst holographic avatars (photorealistic or stylised) represent remote participants, creating hybrid physical-virtual collaboration.\n\n## Current Landscape (2025)\n\nAR collaboration has evolved from experimental demonstrations to enterprise deployments in manufacturing, healthcare, field service, and architecture, with the global market reaching £3.2 billion (MarketsandMarkets, 2025).\n\n**Adoption Statistics**:\n- 23% of UK manufacturers use AR collaboration for remote assistance (Made Smarter Review, 2025)\n- 12% of architecture firms employ AR for client presentations (AIA Technology Survey)\n- Microsoft HoloLens 2: 300,000+ units deployed globally, 18,000 in UK\n- Magic Leap 2: 50,000 units (enterprise-focused)\n\n**Technology Capabilities (2025)**:\n- **Field of View**: 52° diagonal (HoloLens 2), 70° (Magic Leap 2)\n- **Hand Tracking**: Gesture control without controllers\n- **Spatial Mapping**: Real-time environment meshing at 10 Hz\n- **Occlusion**: Virtual objects occluded by physical objects (realistic depth)\n\n**UK Context**:\n- **Rolls-Royce**: AR remote assistance for engine maintenance (HoloLens 2)\n- **Bentley Systems**: AR BIM collaboration for construction projects\n- **Imperial College London**: Surgical training via AR collaboration\n- **UK Ministry of Defence**: AR tactical planning and training\n\n## Platforms and Technologies\n\n### Microsoft HoloLens 2 ([[TELE-025-microsoft-hololens]])\n- **Form Factor**: Standalone AR headset, wireless\n- **Optics**: Waveguide displays, 52° diagonal FOV, 2K resolution per eye\n- **Interaction**: Hand tracking, eye tracking, voice commands\n- **Collaboration**: Microsoft Mesh integration for multi-user AR sessions\n- **Price**: £3,150\n\n### Microsoft Mesh ([[TELE-026-microsoft-mesh]])\n- **Platform**: Cloud-based AR/VR collaboration service\n- **Features**: Shared holographic spaces, persistent content, multi-platform (HoloLens, Quest, PC)\n- **Integration**: Microsoft Teams, Azure Digital Twins\n- **Use Case**: Hybrid meetings (AR users, VR users, video participants)\n\n### Apple Vision Pro (visionOS)\n- **Passthrough Mode**: High-fidelity video passthrough enables AR collaboration\n- **Personas**: Photorealistic holographic avatars\n- **SharePlay**: Shared AR experiences (co-viewing 3D models)\n- **Price**: £3,499\n\n### Magic Leap 2\n- **Form Factor**: Lightweight enterprise AR headset\n- **Optics**: 70° diagonal FOV, dimming technology for outdoor use\n- **Targeting**: Healthcare, manufacturing, field service\n- **Price**: £2,999\n\n### Mobile AR (ARKit, ARCore)\n- **Devices**: iPhones, iPads, Android smartphones/tablets\n- **Collaboration**: Multi-user AR sessions via ARKit Collaborative Session, ARCore Cloud Anchors\n- **Advantage**: No headset required (billions of compatible devices)\n- **Limitation**: Holding device vs. hands-free headset\n\n## Applications\n\n### Remote Assistance\n- Field technician wears AR headset, remote expert sees technician's view\n- Expert annotates technician's view with arrows, circles, 3D instructions\n- Spatial audio enables natural conversation\n- **Example**: BT Engineers use HoloLens for network equipment repairs\n\n### Collaborative Design\n- Architects, clients view 3D building models at scale in physical space\n- Co-manipulate: Rotate, scale, modify materials in real-time\n- Multiple stakeholders join from different locations\n- **Example**: Bentley Systems iTwin for infrastructure design review\n\n### Medical Collaboration\n- Surgeons view 3D patient scans overlaid on patient during surgery\n- Remote specialists annotate surgical plan in AR\n- Medical students observe procedures via holographic avatars\n- **Example**: Imperial College Hamlyn Centre surgical AR research\n\n### Manufacturing\n- Engineers overlay CAD models on physical prototypes\n- Identify design-manufacture discrepancies\n- Remote quality inspections via AR annotations\n- **Example**: Airbus uses AR for aircraft assembly guidance\n\n### Education and Training\n- Distributed students manipulate shared 3D molecular models\n- Remote instructors demonstrate procedures via holographic presence\n- Hands-on training without physical proximity\n- **Example**: University of Cambridge chemistry education AR\n\n## Advantages and Limitations\n\n### Advantages\n- **Contextual**: Work on physical objects whilst viewing digital overlays\n- **Hands-Free**: Headsets enable manipulation whilst viewing instructions\n- **Spatial Understanding**: 3D depth perception superior to 2D screens\n- **Hybrid Meetings**: AR users collaborate with VR and video participants\n- **Safety**: Maintain physical environment awareness (vs. VR blindness)\n\n### Limitations\n- **Field of View**: Limited FOV creates \"keyhole\" viewing (52-70° vs. 180° human vision)\n- **Weight**: Headsets cause neck strain after 60-90 minutes\n- **Brightness**: Holograms difficult to see in bright sunlight\n- **Cost**: £3,000+ headsets prohibitive for consumer adoption\n- **Social Acceptance**: Wearing headsets in public perceived as awkward\n\n## Future Directions\n\n**Near-Term (2025-2027)**:\n- Lightweight AR glasses (100g vs. 566g HoloLens 2)\n- Wider FOV (100°+) for immersive AR\n- Neural rendering for photorealistic holographic avatars [[TELE-100-ai-avatars]]\n\n**Medium-Term (2027-2030)**:\n- Contact-lens AR (eliminating external hardware)\n- Haptic feedback for touching holograms [[TELE-203-haptic-feedback-telepresence]]\n- AI-generated AR content from voice descriptions\n\n**Long-Term (2030+)**:\n- Retinal projection AR (direct light to retina)\n- Brain-computer interface AR control\n- Persistent AR metaverse overlay on entire physical world\n\n## Related Concepts\n\n- [[TELE-001-telepresence]]\n- [[TELE-020-virtual-reality-telepresence]]\n- [[TELE-025-microsoft-hololens]]\n- [[TELE-026-microsoft-mesh]]\n- [[AugmentedReality]]\n- [[MixedReality]]\n- [[SpatialComputing]]\n\n## Academic References\n\n1. Billinghurst, M., & Kato, H. (2002). \"Collaborative Augmented Reality\". *Communications of the ACM*, 45(7), 64-70.\n2. Ens, B., et al. (2021). \"Revisiting Collaboration through Mixed Reality: The Evolution of Groupware\". *International Journal of Human-Computer Studies*, 131, 81-98.\n\n## Metadata\n\n- **Term-ID**: TELE-021\n- **Last Updated**: 2025-11-16\n- **Maturity**: Developing\n- **Authority Score**: 0.85\n- **UK Context**: High (Rolls-Royce, BT, universities)\n- **Cross-Domain**: Bridges to Metaverse, AI",
  "properties": {},
  "backlinks": [
    "TELE-020-virtual-reality-telepresence",
    "TELE-001-telepresence"
  ],
  "wiki_links": [
    "TELE-026-microsoft-mesh",
    "AIDomain",
    "ARHeadset",
    "TELE-0000-telepresence-domain",
    "TELE-002-telecollaboration",
    "SpatialComputing",
    "MixedReality",
    "CollaborativeDesign",
    "TELE-150-webrtc",
    "SpatialMapping",
    "RemoteAssistance",
    "TELE-100-ai-avatars",
    "TELE-020-virtual-reality-telepresence",
    "AugmentedReality",
    "TELE-001-telepresence",
    "HybridWorkspace",
    "XRCollaborationPlatforms",
    "TELE-203-haptic-feedback-telepresence",
    "SpatialAnchors",
    "SharedHolograms",
    "ObjectTracking",
    "TELE-025-microsoft-hololens",
    "MetaverseDomain",
    "SpatialAnnotation"
  ],
  "ontology": {
    "term_id": "TELE-021",
    "preferred_term": "Augmented Reality Collaboration",
    "definition": "\"Collaborative work where geographically distributed team members share a common augmented reality environment, viewing and manipulating virtual 3D objects overlaid on their respective physical spaces whilst communicating via spatial audio and holographic avatars, enabling hybrid physical-virtual cooperation through AR headsets or mobile devices.\"",
    "source_domain": "tele",
    "maturity_level": null,
    "authority_score": 0.85
  }
}