{
  "title": "Telecollaboration",
  "content": "# Telecollaboration\n\n### OntologyBlock\nid:: telecollaboration-ontology\ncollapsed:: true\n- ontology:: true\n- term-id:: TELE-002\n- preferred-term:: Telecollaboration\n- alternate-terms::\n  - Remote Collaboration\n  - Distributed Collaboration\n  - Virtual Collaboration\n  - Distance Collaboration\n- source-domain:: tele\n- status:: active\n- public-access:: true\n- definition:: \"The process of individuals or groups working together towards shared goals across geographical distances through technology-mediated communication and coordination tools, integrating synchronous and asynchronous interaction modalities to achieve collaborative outcomes comparable to or exceeding co-located teamwork.\"\n- maturity:: mature\n- authority-score:: 0.92\n- owl:class:: tele:Telecollaboration\n- owl:physicality:: ConceptualEntity\n- owl:role:: Process\n- belongsToDomain::\n  - [[TELE-0000-telepresence-domain]]\n  - [[TelepresenceFoundations]]\n- bridges-to::\n  - [[AIDomain]]\n  - [[BlockchainDomain]]\n\n#### Relationships\nid:: telecollaboration-relationships\n- is-subclass-of:: [[Collaboration]], [[DistributedWork]]\n- enables:: [[CrossBorderTeamwork]], [[AsynchronousCoordination]], [[KnowledgeSharing]], [[VirtualTeams]]\n- requires:: [[TELE-001-telepresence]], [[CommunicationPlatform]], [[CoordinationMechanisms]], [[SharedWorkspace]]\n- has-component:: [[TELE-010-synchronous-collaboration]], [[TELE-011-asynchronous-collaboration]], [[TELE-005-common-ground-theory]]\n- related-to:: [[DistributedSystems]], [[HumanComputerInteraction]], [[ComputerSupportedCooperativeWork]]\n\n#### OWL Axioms\nid:: telecollaboration-owl-axioms\ncollapsed:: true\n- ```clojure\n  Declaration(Class(tele:Telecollaboration))\n\n  # Classification\n  SubClassOf(tele:Telecollaboration tele:FoundationalConcept)\n  SubClassOf(tele:Telecollaboration tele:ConceptualEntity)\n  SubClassOf(tele:Telecollaboration tele:Process)\n\n  # Domain classification\n  SubClassOf(tele:Telecollaboration\n    ObjectSomeValuesFrom(tele:belongsToDomain tele:TelecollaborationDomain)\n  )\n\n  # Dependencies\n  SubClassOf(tele:Telecollaboration\n    ObjectSomeValuesFrom(tele:requires tele:Telepresence)\n  )\n  SubClassOf(tele:Telecollaboration\n    ObjectSomeValuesFrom(tele:hasComponent tele:SynchronousCollaboration)\n  )\n  SubClassOf(tele:Telecollaboration\n    ObjectSomeValuesFrom(tele:hasComponent tele:AsynchronousCollaboration)\n  )\n\n  # Capabilities\n  SubClassOf(tele:Telecollaboration\n    ObjectSomeValuesFrom(tele:enables tele:KnowledgeSharing)\n  )\n\n  # Cross-domain bridges\n  SubClassOf(tele:Telecollaboration\n    ObjectSomeValuesFrom(tele:bridgesTo ai:AIDomain)\n  )\n  SubClassOf(tele:Telecollaboration\n    ObjectSomeValuesFrom(tele:bridgesTo bc:BlockchainDomain)\n  )\n\n  # Annotations\n  AnnotationAssertion(rdfs:label tele:Telecollaboration \"Telecollaboration\"@en-GB)\n  AnnotationAssertion(rdfs:comment tele:Telecollaboration \"Technology-mediated distributed collaborative work\"@en-GB)\n  AnnotationAssertion(dcterms:identifier tele:Telecollaboration \"TELE-002\"^^xsd:string)\n  AnnotationAssertion(dcterms:created tele:Telecollaboration \"2025-11-16\"^^xsd:date)\n  ```\n\n## Definition\n\n**Telecollaboration** is the structured process whereby geographically distributed individuals or teams coordinate efforts towards common objectives through technology-mediated communication systems. Unlike simple remote communication, telecollaboration encompasses the full spectrum of collaborative activities: joint planning, parallel execution, iterative feedback, knowledge co-creation, and collective decision-making conducted across spatial and temporal boundaries.\n\nThe term gained prominence in the 1990s with the emergence of Computer-Supported Cooperative Work (CSCW) research, which identified fundamental challenges in distributed teamwork: maintaining shared context, coordinating asynchronous contributions, building trust without face-to-face interaction, and managing cultural differences across dispersed teams. Modern telecollaboration integrates immersive telepresence technologies ([[TELE-001-telepresence]]), AI-powered coordination tools ([[TELE-107-ai-meeting-assistants]]), and blockchain-based governance mechanisms ([[TELE-252-dao-governance-telecollaboration]]) to address these challenges.\n\nTelecollaboration manifests across two primary temporal modes: **synchronous collaboration** ([[TELE-010-synchronous-collaboration]]), where participants interact in real-time through video conferencing or shared virtual environments, and **asynchronous collaboration** ([[TELE-011-asynchronous-collaboration]]), where contributions occur at different times via shared documents, version control systems, or project management platforms.\n\n## Current Landscape (2025)\n\nThe global shift to hybrid and remote work accelerated by the COVID-19 pandemic has established telecollaboration as the dominant mode of knowledge work, with 72% of UK knowledge workers engaging in distributed collaboration at least weekly (UK Office for National Statistics, 2025).\n\n**Technology Adoption**:\n- **Immersive Platforms**: 43% of UK enterprises use VR/AR collaboration tools (Meta Quest, HoloLens, Vision Pro)\n- **AI Integration**: 68% employ AI meeting assistants for transcription, summarisation, and action tracking\n- **Blockchain Coordination**: 12% of tech startups use DAO governance for distributed decision-making\n- **Hybrid Workspaces**: 89% combine physical and virtual collaboration modalities\n\n**Productivity Metrics** (2025 Studies):\n- Distributed teams achieve 23% higher output when using immersive telepresence vs. video calls (Microsoft Research)\n- AI-assisted collaboration reduces meeting time by 31% whilst improving decision quality (PwC Study)\n- Asynchronous documentation via shared knowledge bases increases team alignment by 47% (Atlassian State of Teams Report)\n\n**UK Context**:\nBritish companies lead European telecollaboration adoption, particularly in financial services (City of London), creative industries (Soho, Manchester), and research institutions. The UK Government's Digital Strategy (2024) mandates telepresence capabilities for all civil service departments by 2026.\n\nNorth England contributes significant research:\n- **University of Leeds**: Human factors in distributed collaboration\n- **University of Manchester**: AI-mediated teamwork dynamics\n- **Newcastle University**: Blockchain governance for remote organisations\n\n## Theoretical Foundations\n\n### Common Ground Theory\n**Common Ground Theory** (Clark & Brennan, 1991) explains how collaborators establish shared understanding despite communication constraints. Telecollaboration systems must compensate for reduced \"grounding\" cues (gestures, eye contact, spatial deixis) through explicit mechanisms:\n- Persistent chat logs and shared documents provide conversational memory\n- Screen sharing and co-editing enable joint visual attention\n- Turn-taking protocols (raised hand indicators) replace physical interruption cues\n\n### Coordination Theory\n**Coordination Theory** (Malone & Crowston, 1994) identifies three fundamental coordination mechanisms:\n1. **Mutual Adjustment**: Direct communication for dynamic coordination (video calls, instant messaging)\n2. **Standardisation**: Predefined workflows and protocols (project templates, approval chains)\n3. **Plans and Schedules**: Temporal coordination across time zones (shared calendars, asynchronous handoffs)\n\nTelecollaboration platforms integrate all three mechanisms, with AI agents increasingly automating routine coordination tasks.\n\n### Distributed Cognition\nDistributed cognition theory (Hutchins, 1995) views collaboration as collective intelligence distributed across people and artefacts. Telecollaboration tools serve as cognitive artefacts that externalise memory (wikis), structure thinking (Kanban boards), and aggregate knowledge (shared data dashboards).\n\n## Modes of Telecollaboration\n\n### Synchronous Collaboration ([[TELE-010-synchronous-collaboration]])\nReal-time interaction requiring simultaneous presence:\n- **Video Conferencing**: Zoom, Microsoft Teams, Google Meet\n- **VR Meeting Rooms**: [[TELE-028-horizon-workrooms]], [[TELE-026-microsoft-mesh]]\n- **Co-editing**: Google Docs, Figma, Miro whiteboards\n- **Pair Programming**: Visual Studio Live Share, JetBrains Code With Me\n\n**Advantages**: Rapid feedback, social presence, spontaneous ideation\n**Challenges**: Time zone constraints, scheduling overhead, synchronisation latency\n\n### Asynchronous Collaboration ([[TELE-011-asynchronous-collaboration]])\nTime-independent contributions coordinated through shared artefacts:\n- **Version Control**: Git/GitHub for code collaboration\n- **Documentation**: Notion, Confluence, Obsidian for knowledge bases\n- **Project Management**: Jira, Asana, Linear for task tracking\n- **Design Systems**: Figma, Storybook for design handoffs\n\n**Advantages**: Flexible schedules, deep work periods, global accessibility\n**Challenges**: Slower feedback cycles, potential misalignment, reduced social bonding\n\n### Hybrid Collaboration\nMost effective telecollaboration blends synchronous and asynchronous modes:\n- Asynchronous documentation of decisions made in synchronous meetings\n- Synchronous clarification of ambiguities in asynchronous work\n- AI agents summarising asynchronous activity for synchronous review\n\n## Enabling Technologies\n\n### Communication Infrastructure\n- **Real-Time Protocols**: [[TELE-150-webrtc]] for peer-to-peer video, [[TELE-151-real-time-protocols]] for low-latency streaming\n- **5G/6G Networks**: [[TELE-153-5g-telepresence]] enabling mobile immersive collaboration\n- **Edge Computing**: Local rendering and processing to minimise latency\n\n### AI Enhancements\n- **Meeting Intelligence**: [[TELE-107-ai-meeting-assistants]] transcribing, summarising, extracting action items\n- **Translation**: [[TELE-105-real-time-language-translation]] enabling cross-lingual teamwork\n- **Avatars**: [[TELE-100-ai-avatars]] representing remote participants photorealistically\n\n### Blockchain Coordination\n- **Smart Contracts**: [[TELE-251-smart-contract-coordination]] for automated task allocation and payment\n- **DAO Governance**: [[TELE-252-dao-governance-telecollaboration]] for democratic decision-making\n- **Tokenised Incentives**: Cryptocurrency rewards for contributions\n\n### Immersive Environments\n- **Virtual Offices**: [[TELE-301-virtual-office-spaces]] providing persistent shared spaces\n- **Shared Whiteboards**: [[TELE-302-shared-whiteboards]] for visual collaboration\n- **3D Manipulation**: [[3D Object Manipulation]] for product design and engineering\n\n## Cross-Domain Applications\n\n### Software Development\nDistributed engineering teams use version control (Git), continuous integration (GitHub Actions), code review (pull requests), and pair programming tools. 94% of open-source development is telecollaborative (GitHub Octoverse Report, 2025).\n\n### Scientific Research\nGlobal research collaborations leverage shared data repositories (Zenodo, Dryad), computational notebooks (Jupyter, Observable), and virtual lab meetings. The Large Hadron Collider involves 10,000+ physicists telecollaborating across 100+ institutions.\n\n### Creative Industries\nFilm production, game development, and architectural design employ real-time co-creation tools (Unreal Engine multi-user editing, Blender shared sessions) and cloud rendering farms for distributed teams.\n\n### Healthcare\nTelemedicine enables specialist consultations across regions, whilst multi-disciplinary care teams coordinate patient treatment through shared electronic health records and secure messaging platforms.\n\n### Education\nOnline learning platforms facilitate student collaboration through discussion forums, group projects, and peer assessment systems. Virtual campuses in platforms like [[TELE-027-spatial-platform]] enable immersive educational experiences.\n\n## Challenges and Solutions\n\n### Trust Building\n**Challenge**: Establishing interpersonal trust without physical co-location\n**Solutions**:\n- Regular video calls with cameras enabled\n- Virtual social events and casual check-ins\n- Transparent progress tracking via shared dashboards\n- Team building in VR environments\n\n### Communication Overhead\n**Challenge**: Coordinating across time zones with information overload\n**Solutions**:\n- AI summarisation of asynchronous updates\n- Core overlap hours for synchronous touchpoints\n- Written communication culture (RFCs, design docs)\n- Notification management and batching\n\n### Cultural Differences\n**Challenge**: Navigating diverse work norms, languages, and expectations\n**Solutions**:\n- Real-time translation tools\n- Cultural awareness training\n- Explicit documentation of team norms\n- Rotating meeting times to share timezone burdens\n\n### Technology Barriers\n**Challenge**: Unequal access to high-bandwidth internet and advanced devices\n**Solutions**:\n- Graceful degradation (audio-only fallbacks)\n- Employer-provided equipment subsidies\n- Asynchronous-first workflows reducing sync requirements\n- Low-bandwidth-optimised protocols\n\n## Future Directions\n\n**Near-Term (2025-2027)**:\n- **AI Mediators**: Intelligent agents facilitating multi-party discussions, managing turn-taking, and resolving conflicts\n- **Haptic Collaboration**: Force-feedback devices enabling tactile co-manipulation of virtual objects\n- **Brain-Computer Interfaces**: Thought-based communication for paralysed individuals or ultra-low-latency interaction\n\n**Medium-Term (2027-2030)**:\n- **Holographic Telepresence**: Life-size 3D projections eliminating headsets\n- **Quantum Networks**: Zero-latency global communication\n- **Persistent Metaverse Workspaces**: Virtual offices existing continuously, accessible 24/7\n\n**Long-Term (2030+)**:\n- **Neural Links**: Direct brain-to-brain communication bypassing language\n- **Digital Twins**: AI agents representing individuals in asynchronous collaboration\n- **Global Collective Intelligence**: Humanity-scale collaboration on existential challenges (climate, pandemics)\n\n## Related Concepts\n\n**Foundational Concepts**:\n- [[TELE-001-telepresence]] - Enabling technology for immersive collaboration\n- [[TELE-003-social-presence-theory]] - Theoretical basis for remote interaction\n- [[TELE-005-common-ground-theory]] - Coordination in distributed communication\n\n**Collaboration Modes**:\n- [[TELE-010-synchronous-collaboration]] - Real-time interaction\n- [[TELE-011-asynchronous-collaboration]] - Time-independent coordination\n\n**Technologies**:\n- [[TELE-107-ai-meeting-assistants]] - AI-powered collaboration support\n- [[TELE-251-smart-contract-coordination]] - Blockchain-based coordination\n- [[TELE-301-virtual-office-spaces]] - Persistent collaborative environments\n\n## Academic References\n\n1. Clark, H. H., & Brennan, S. E. (1991). \"Grounding in Communication\". *Perspectives on Socially Shared Cognition*, 13, 127-149.\n2. Malone, T. W., & Crowston, K. (1994). \"The Interdisciplinary Study of Coordination\". *ACM Computing Surveys*, 26(1), 87-119.\n3. Hutchins, E. (1995). *Cognition in the Wild*. MIT Press.\n4. Olson, G. M., & Olson, J. S. (2000). \"Distance Matters\". *Human-Computer Interaction*, 15(2-3), 139-178.\n5. Hinds, P. J., & Bailey, D. E. (2003). \"Out of Sight, Out of Sync: Understanding Conflict in Distributed Teams\". *Organization Science*, 14(6), 615-632.\n6. Cramton, C. D. (2001). \"The Mutual Knowledge Problem and Its Consequences for Dispersed Collaboration\". *Organization Science*, 12(3), 346-371.\n\n## Standards and Organisations\n\n- **Computer-Supported Cooperative Work (CSCW)**: Academic conference series on collaboration technologies\n- **ACM Conference on Human Factors in Computing Systems (CHI)**: Research on collaboration interfaces\n- **International Association for the Study of Cooperation**: Theoretical foundations\n- **Metaverse Standards Forum**: Interoperability for virtual collaboration spaces\n\n## Metadata\n\n- **Term-ID**: TELE-002\n- **Last Updated**: 2025-11-16\n- **Verification Status**: Mature\n- **Authority Score**: 0.92\n- **UK Context**: High (widespread adoption in knowledge economy)\n- **Cross-Domain**: Bridges to AI, Blockchain domains",
  "properties": {},
  "backlinks": [
    "TELE-301-virtual-office-spaces",
    "TELE-021-augmented-reality-collaboration",
    "TELE-250-blockchain-collaboration",
    "TELE-105-real-time-language-translation",
    "TELE-253-cryptocurrency-remuneration",
    "TELE-302-shared-whiteboards",
    "TELE-251-smart-contract-coordination",
    "TELE-003-social-presence-theory",
    "TELE-252-dao-governance-telecollaboration",
    "TELE-300-digital-twin-collaboration",
    "TELE-001-telepresence"
  ],
  "wiki_links": [
    "ComputerSupportedCooperativeWork",
    "TELE-301-virtual-office-spaces",
    "3D Object Manipulation",
    "TELE-252-dao-governance-telecollaboration",
    "AsynchronousCoordination",
    "CrossBorderTeamwork",
    "TELE-001-telepresence",
    "TELE-0000-telepresence-domain",
    "KnowledgeSharing",
    "SharedWorkspace",
    "HumanComputerInteraction",
    "TELE-150-webrtc",
    "DistributedWork",
    "TELE-302-shared-whiteboards",
    "TELE-028-horizon-workrooms",
    "BlockchainDomain",
    "TELE-251-smart-contract-coordination",
    "TELE-027-spatial-platform",
    "DistributedSystems",
    "TELE-026-microsoft-mesh",
    "TELE-105-real-time-language-translation",
    "TelepresenceFoundations",
    "TELE-005-common-ground-theory",
    "TELE-003-social-presence-theory",
    "TELE-010-synchronous-collaboration",
    "TELE-107-ai-meeting-assistants",
    "CommunicationPlatform",
    "Collaboration",
    "AIDomain",
    "VirtualTeams",
    "TELE-100-ai-avatars",
    "CoordinationMechanisms",
    "TELE-011-asynchronous-collaboration",
    "TELE-151-real-time-protocols",
    "TELE-153-5g-telepresence"
  ],
  "ontology": {
    "term_id": "TELE-002",
    "preferred_term": "Telecollaboration",
    "definition": "\"The process of individuals or groups working together towards shared goals across geographical distances through technology-mediated communication and coordination tools, integrating synchronous and asynchronous interaction modalities to achieve collaborative outcomes comparable to or exceeding co-located teamwork.\"",
    "source_domain": "tele",
    "maturity_level": null,
    "authority_score": 0.92
  }
}