{
  "title": "Digital Twin Collaboration",
  "content": "# Digital Twin Collaboration\n\n- ### OntologyBlock\n  id:: digital-twin-collaboration-ontology\n  collapsed:: true\n  - ontology:: true\n  - term-id:: TELE-300\n  - preferred-term:: Digital Twin Collaboration\n  - alternate-terms::\n  - Collaborative Digital Twins\n  - Shared Digital Twins\n  - Multi-User Digital Twin Environments\n  - source-domain:: tele\n  - status:: active\n  - public-access:: true\n  - definition:: \"The use of shared virtual replicas of physical assets, processes, or environments as collaborative workspaces where geographically distributed teams simultaneously inspect, analyse, simulate, and modify digital representations synchronised with real-world counterparts through sensor data streams, enabling remote collaboration on physical systems.\"\n  - maturity:: developing\n  - authority-score:: 0.85\n  - owl:class:: tele:DigitalTwinCollaboration\n  - owl:physicality:: VirtualEntity\n  - owl:role:: Object\n  - belongsToDomain::\n  - [[TELE-0000-telepresence-domain]]\n  - [[DigitalTwinCollaboration]]\n  - bridges-to::\n  - [[AIDomain]]\n  - [[MetaverseDomain]]\n\n\n#### Relationships\nid:: digital-twin-collaboration-relationships\n- is-subclass-of:: [[TELE-002-telecollaboration]], [[DigitalTwin]]\n- enables:: [[RemoteInspection]], [[CollaborativeSimulation]], [[PredictiveMaintenance]], [[VirtualCommissioning]]\n- requires:: [[SensorData]], [[3DModelling]], [[RealTimeSync]], [[CloudComputing]]\n- has-component:: [[TELE-301-virtual-office-spaces]], [[TELE-302-shared-whiteboards]], [[3DObjectManipulation]]\n- related-to:: [[IoT]], [[IndustryFourPointZero]], [[BIM]], [[SimulationSoftware]]\n\n#### OWL Axioms\nid:: digital-twin-collaboration-owl-axioms\ncollapsed:: true\n- ```clojure\n  Declaration(Class(tele:DigitalTwinCollaboration))\n\n  SubClassOf(tele:DigitalTwinCollaboration tele:Telecollaboration)\n  SubClassOf(tele:DigitalTwinCollaboration tele:VirtualEntity)\n\n  SubClassOf(tele:DigitalTwinCollaboration\n    ObjectSomeValuesFrom(tele:belongsToDomain tele:TelecollaborationDomain)\n  )\n\n  SubClassOf(tele:DigitalTwinCollaboration\n    ObjectSomeValuesFrom(tele:requires tele:SensorData)\n  )\n\n  SubClassOf(tele:DigitalTwinCollaboration\n    ObjectSomeValuesFrom(tele:bridgesTo ai:AIDomain)\n  )\n\n  AnnotationAssertion(rdfs:label tele:DigitalTwinCollaboration \"Digital Twin Collaboration\"@en-GB)\n  AnnotationAssertion(rdfs:comment tele:DigitalTwinCollaboration \"Shared virtual replicas for distributed teamwork\"@en-GB)\n  AnnotationAssertion(dcterms:identifier tele:DigitalTwinCollaboration \"TELE-300\"^^xsd:string)\n  AnnotationAssertion(dcterms:created tele:DigitalTwinCollaboration \"2025-11-16\"^^xsd:date)\n  ```\n\n## Definition\n\n**Digital Twin Collaboration** leverages high-fidelity virtual replicas of physical assets—factories, buildings, vehicles, infrastructure—as shared 3D workspaces where distributed teams collaborate on design, operation, and maintenance without physical proximity to the asset. These digital twins ingest real-time sensor data (temperature, vibration, GPS, video feeds) from IoT devices, synchronising the virtual model with physical reality to enable remote monitoring, predictive analytics, and collaborative troubleshooting.\n\nFor example, aerospace engineers in Bristol and Seattle can simultaneously inspect a digital twin of an aircraft engine, visualising thermal stress patterns from embedded sensors, annotating components in 3D, running failure simulations, and coordinating maintenance schedules—all whilst the physical engine operates 10,000 kilometres away. The digital twin serves as a \"collaboration substrate\": a shared object of joint attention where distributed cognition occurs through manipulation of persistent 3D artefacts.\n\nDigital twin collaboration integrates telepresence technologies ([[TELE-020-virtual-reality-telepresence]]) for immersive inspection, AI analytics for predictive insights, and real-time communication ([[TELE-150-webrtc]]) for team coordination. This paradigm transforms industries requiring physical asset management (manufacturing, energy, construction, healthcare) by enabling global expertise to be applied locally through virtualised access.\n\n## Current Landscape (2025)\n\nDigital twin collaboration has matured from niche simulation tools to mainstream platforms deployed across manufacturing, infrastructure, and smart cities, with the global market reaching £12.8 billion (MarketsandMarkets, 2025).\n\n**Adoption Statistics**:\n- 78% of UK manufacturers use digital twins for production optimisation (Made Smarter Review, 2025)\n- 43% of infrastructure projects employ collaborative digital twins (UK Infrastructure & Projects Authority)\n- £2.1B UK government investment in digital twin standards (National Digital Twin Programme)\n- 92% of Fortune 500 industrial firms deploy digital twin platforms (Gartner, 2025)\n\n**Technology Capabilities (2025)**:\n- **Real-Time Sync**: <100ms latency between physical sensor updates and virtual model\n- **Scale**: City-scale digital twins (London, Singapore) with billions of data points\n- **Users**: 100+ simultaneous collaborators in VR/AR digital twin environments\n- **AI Integration**: Predictive maintenance, anomaly detection, optimisation algorithms\n\n**UK Context**:\n- **National Digital Twin Programme**: Standardising interoperable digital twins across infrastructure\n- **Cambridge Centre for Digital Built Britain**: Research on collaborative digital twins for construction\n- **Rolls-Royce**: Engine digital twins for predictive maintenance (TotalCare service)\n- **Thames Water**: Water infrastructure digital twin for leak detection\n- **Heathrow Airport**: Airport operations digital twin for capacity optimisation\n\n## Applications\n\n### Manufacturing\n- **Virtual Commissioning**: Test production line configurations in digital twin before physical build\n- **Predictive Maintenance**: AI detects anomalies in machinery vibration patterns, alerts distributed teams\n- **Quality Control**: Remote engineers inspect product defects via digital twin visualisation\n- **Example**: Siemens uses Tecnomatix Plant Simulation for collaborative factory planning\n\n### Infrastructure and Construction\n- **Building Information Modelling (BIM)**: Architects, engineers, contractors collaborate on 3D building models\n- **Asset Management**: Facility managers monitor HVAC, lighting, elevators via digital twin dashboards\n- **Urban Planning**: City planners simulate traffic flow, energy consumption, disaster scenarios\n- **Example**: UK's National Digital Twin Programme for cross-sector infrastructure coordination\n\n### Energy and Utilities\n- **Wind Farm Monitoring**: Distributed turbines represented as digital twins, engineers diagnose faults remotely\n- **Power Grid Optimisation**: AI optimises electricity distribution via digital twin simulations\n- **Nuclear Plant Safety**: Reactor digital twins enable remote safety analysis without radiation exposure\n- **Example**: EDF Energy uses digital twins for UK nuclear fleet management\n\n### Healthcare\n- **Patient-Specific Digital Twins**: Personalised models for treatment planning (heart surgery simulation)\n- **Hospital Operations**: Digital twin of hospital for bed capacity, staffing optimisation\n- **Remote Surgery Planning**: Surgeons collaboratively plan procedures using patient anatomical digital twins\n- **Example**: Great Ormond Street Hospital digital twin for paediatric cardiac surgery\n\n### Aerospace\n- **Aircraft Health Monitoring**: Engine, airframe digital twins track wear, predict failures\n- **Collaborative Maintenance**: Global MRO (Maintenance, Repair, Overhaul) teams share digital twin access\n- **Flight Simulation**: Test flight scenarios in digital twin before physical flight\n- **Example**: Rolls-Royce TotalCare (50,000+ engine digital twins)\n\n## Technical Architecture\n\n### Data Ingestion\n- **Sensors**: IoT devices transmit telemetry (temperature, pressure, vibration, GPS)\n- **Protocols**: MQTT, OPC UA, DDS for industrial IoT communication\n- **Frequency**: Real-time (1 Hz - 10 kHz depending on application)\n- **Storage**: Time-series databases (InfluxDB, TimescaleDB)\n\n### 3D Modelling\n- **CAD Integration**: Import models from SolidWorks, AutoCAD, Revit\n- **Procedural Generation**: AI generates 3D models from point cloud scans (LiDAR, photogrammetry)\n- **Level of Detail**: Multiple resolutions for performance (high-detail close-up, low-detail distant)\n\n### Simulation Engine\n- **Physics**: Computational fluid dynamics (CFD), finite element analysis (FEA), thermal simulation\n- **AI**: Machine learning models predict equipment failures, optimise configurations\n- **Real-Time**: GPU-accelerated solvers enable interactive simulation\n\n### Collaboration Layer\n- **Multi-User Access**: 10-100 users simultaneously viewing/editing digital twin\n- **VR/AR Integration**: [[TELE-020-virtual-reality-telepresence]] for immersive inspection\n- **Annotation**: 3D markup tools for commenting on components\n- **Communication**: Voice chat ([[TELE-150-webrtc]]), video conferencing, shared whiteboards ([[TELE-302-shared-whiteboards]])\n\n### Platforms\n- **Siemens MindSphere**: Industrial IoT and digital twin platform\n- **Microsoft Azure Digital Twins**: Cloud-based digital twin service with 3D visualisation\n- **Bentley Systems iTwin**: Infrastructure digital twins (buildings, bridges, utilities)\n- **Dassault Systèmes 3DEXPERIENCE**: Product lifecycle management with collaborative digital twins\n- **Unity Reflect**: Real-time 3D collaboration for BIM models\n\n## Standards and Interoperability\n\n### UK National Digital Twin Programme\n**Gemini Principles** (2018):\n1. **Public Good**: Digital twins serve societal benefit\n2. **Value Creation**: Economic, environmental, social value\n3. **Insight**: Data-driven decision-making\n4. **Security**: Cybersecurity by design\n5. **Openness**: Open standards for interoperability\n6. **Quality**: Trustworthy data and models\n7. **Federation**: Interconnected digital twins\n8. **Curation**: Maintained and updated\n\n**Information Management Framework (IMF)**:\n- Standardises data exchange between digital twins (ISO 19650 BIM standard)\n- Enables digital twins from different vendors/sectors to interoperate\n\n### International Standards\n- **ISO 23247**: Digital twin framework for manufacturing\n- **IEC 63278**: Asset administration shell for Industry 4.0\n- **OGC CityGML**: 3D city models for urban digital twins\n\n## Advantages and Challenges\n\n### Advantages\n- **Remote Expertise**: Global specialists collaborate without travel\n- **Risk Reduction**: Test configurations virtually before physical implementation\n- **Predictive Maintenance**: AI anticipates failures, reduces downtime\n- **Transparency**: Shared visualisation aligns stakeholders\n- **Training**: Safe environment for operator training\n\n### Challenges\n- **Data Quality**: Digital twin only as accurate as sensor data (\"garbage in, garbage out\")\n- **Complexity**: High-fidelity models computationally expensive\n- **Interoperability**: Proprietary platforms hinder data sharing\n- **Cybersecurity**: Digital twins attractive targets for cyberattacks (e.g., ransomware on infrastructure)\n- **Cost**: Initial investment £100K-£10M+ depending on scale\n- **Skills Gap**: Requires expertise in IoT, 3D modelling, simulation, data science\n\n## Future Directions\n\n**Near-Term (2025-2027)**:\n- AI-generated digital twins from smartphone video scans\n- Blockchain-based digital twin data marketplaces (sell sensor data securely)\n- Haptic feedback for tactile inspection of digital twins ([[TELE-203-haptic-feedback-telepresence]])\n\n**Medium-Term (2027-2030)**:\n- Autonomous digital twins (self-optimising without human intervention)\n- City-scale digital twins for climate change simulation\n- Quantum computing for complex digital twin simulations\n\n**Long-Term (2030+)**:\n- Human digital twins for personalised medicine (full-body physiological models)\n- Planetary digital twins for Earth system science\n- Digital twin consciousness upload (speculative)\n\n## Related Concepts\n\n- [[TELE-002-telecollaboration]]\n- [[TELE-020-virtual-reality-telepresence]]\n- [[TELE-301-virtual-office-spaces]]\n- [[TELE-302-shared-whiteboards]]\n- [[DigitalTwin]]\n- [[IoT]]\n- [[IndustryFourPointZero]]\n\n## Academic References\n\n1. Grieves, M., & Vickers, J. (2017). \"Digital Twin: Mitigating Unpredictable, Undesirable Emergent Behavior in Complex Systems\". *Transdisciplinary Perspectives on Complex Systems*, 85-113.\n2. Bolton, A., et al. (2018). *Gemini Principles*. Centre for Digital Built Britain, University of Cambridge.\n3. Tao, F., et al. (2018). \"Digital Twin in Industry: State-of-the-Art\". *IEEE Transactions on Industrial Informatics*, 15(4), 2405-2415.\n\n## Metadata\n\n- **Term-ID**: TELE-300\n- **Last Updated**: 2025-11-16\n- **Maturity**: Developing\n- **Authority Score**: 0.85\n- **UK Context**: Very High (National Digital Twin Programme, infrastructure projects)\n- **Cross-Domain**: Bridges to AI, Metaverse",
  "properties": {},
  "backlinks": [
    "TELE-301-virtual-office-spaces",
    "TELE-CONV-001-metaverse-telepresence-bridge"
  ],
  "wiki_links": [
    "SimulationSoftware",
    "RemoteInspection",
    "PredictiveMaintenance",
    "TELE-301-virtual-office-spaces",
    "3DObjectManipulation",
    "TELE-002-telecollaboration",
    "CollaborativeSimulation",
    "DigitalTwinCollaboration",
    "SensorData",
    "TELE-150-webrtc",
    "IoT",
    "3DModelling",
    "TELE-302-shared-whiteboards",
    "BIM",
    "MetaverseDomain",
    "AIDomain",
    "CloudComputing",
    "TELE-020-virtual-reality-telepresence",
    "VirtualCommissioning",
    "DigitalTwin",
    "TELE-0000-telepresence-domain",
    "IndustryFourPointZero",
    "TELE-203-haptic-feedback-telepresence",
    "RealTimeSync"
  ],
  "ontology": {
    "term_id": "TELE-300",
    "preferred_term": "Digital Twin Collaboration",
    "definition": "\"The use of shared virtual replicas of physical assets, processes, or environments as collaborative workspaces where geographically distributed teams simultaneously inspect, analyse, simulate, and modify digital representations synchronised with real-world counterparts through sensor data streams, enabling remote collaboration on physical systems.\"",
    "source_domain": "tele",
    "maturity_level": null,
    "authority_score": 0.85
  }
}