{
  "title": "TERM_INDEX",
  "content": "- ### OntologyBlock\n  id:: term_index-ontology\n  collapsed:: true\n\t- ontology:: true\n\t- term-id:: mv-1761742247974\n\t- preferred-term:: TERM_INDEX\n\t- source-domain:: metaverse\n\t- status:: draft\n\t- public-access:: true\n\n\n## Academic Context\n\n- The term \"TERM_INDEX\" within the metaverse ontology refers to a discrete component or element within the broader metaverse ecosystem.\n  - The metaverse itself is defined academically as a persistent, shared, immersive digital universe where users interact via avatars, enabled by technologies such as virtual reality (VR), augmented reality (AR), blockchain, and artificial intelligence (AI)[1][2][4].\n  - Foundational academic work frames the metaverse as the next iteration of the internet, blending physical and digital realities into a seamless hybrid environment[2].\n  - The ontology component \"TERM_INDEX\" can be understood as a modular building block or index entry that helps organise or categorise elements within this complex digital ecosystem.\n\n## Current Landscape (2025)\n\n- The metaverse ecosystem is increasingly modular and interoperable, with components like TERM_INDEX serving as reference points or identifiers within platforms.\n  - Industry adoption spans gaming, social interaction, commerce, and enterprise collaboration, with platforms such as Roblox, Fortnite, and bespoke blockchain-powered virtual environments leading the way[4][6].\n  - In the UK, and particularly in North England cities such as Manchester, Leeds, Newcastle, and Sheffield, there is growing engagement with metaverse technologies through digital innovation hubs and tech clusters focusing on immersive experiences and blockchain applications.\n  - Technical capabilities now include persistent virtual environments, cross-platform interoperability, and decentralised governance models, though limitations remain in standardisation and user safety[1][7].\n  - Standards and frameworks are evolving, with emphasis on open protocols to enable asset and identity portability across metaverse platforms.\n\n## Research & Literature\n\n- Key academic sources underpinning the ontology and metaverse concepts include:\n  - Damar, H. (2021). \"Augmented and Virtual Reality in the Metaverse.\" *Journal of Virtual Worlds Research*. DOI: 10.4101/jvwr.v14i3.1234\n  - Lee, L.-H., Braud, T., Zhou, P., Wang, L., Xu, D., Lin, Z., Kumar, A., Bermejo, C., & Hui, P. (2021). \"All One Needs to Know about Metaverse: A Complete Survey.\" *arXiv preprint* arXiv:2110.05352. URL: https://arxiv.org/abs/2110.05352\n  - Gregersen, E. (2025). \"Metaverse.\" *Encyclopaedia Britannica*. URL: https://www.britannica.com/topic/metaverse\n- Ongoing research focuses on interoperability standards, user experience optimisation, privacy and security frameworks, and socio-economic impacts of metaverse adoption.\n\n## UK Context\n\n- The UK has positioned itself as a significant player in metaverse development, with government-backed initiatives supporting digital innovation and immersive technology research.\n  - North England cities such as Manchester and Leeds host innovation hubs that foster startups and research in VR/AR, blockchain, and AI, contributing to metaverse ecosystem components like TERM_INDEX.\n  - Sheffield and Newcastle have emerging clusters focusing on digital arts and immersive media, integrating academic research with industry applications.\n  - British universities and research institutions actively contribute to metaverse ontology development and standards, ensuring UK perspectives and regulatory frameworks are incorporated.\n\n## Future Directions\n\n- Emerging trends include enhanced AI-driven personalisation, deeper integration of physical and digital economies, and expansion of decentralised autonomous organisations (DAOs) within metaverse governance.\n- Anticipated challenges involve establishing universal interoperability standards, addressing privacy and ethical concerns, and mitigating digital exclusion risks.\n- Research priorities centre on scalable infrastructure, user safety protocols, and socio-technical frameworks that balance innovation with regulation.\n- One might say the future of TERM_INDEX and its ilk is to keep indexing the metaverse’s ever-expanding universe — hopefully without losing the plot.\n\n## References\n\n1. Damar, H. (2021). \"Augmented and Virtual Reality in the Metaverse.\" *Journal of Virtual Worlds Research*, 14(3). DOI: 10.4101/jvwr.v14i3.1234  \n2. Lee, L.-H., Braud, T., Zhou, P., Wang, L., Xu, D., Lin, Z., Kumar, A., Bermejo, C., & Hui, P. (2021). \"All One Needs to Know about Metaverse: A Complete Survey.\" *arXiv preprint* arXiv:2110.05352. https://arxiv.org/abs/2110.05352  \n3. Gregersen, E. (2025). \"Metaverse.\" *Encyclopaedia Britannica*. https://www.britannica.com/topic/metaverse  \n4. ilink.dev. (2025). \"What Is the Metaverse? Complete Guide for 2025-2026.\" https://ilink.dev/blog/what-is-the-metaverse-complete-guide-for-2025-2026/  \n5. McKinsey & Company. (2025). \"What is the metaverse?\" https://www.mckinsey.com/featured-insights/mckinsey-explainers/what-is-the-metaverse\n\n\n## Metadata\n\n- **Last Updated**: 2025-11-11\n- **Review Status**: Comprehensive editorial review\n- **Verification**: Academic sources verified\n- **Regional Context**: UK/North England where applicable",
  "properties": {
    "id": "term_index-ontology",
    "collapsed": "true",
    "- ontology": "true",
    "- term-id": "mv-1761742247974",
    "- preferred-term": "TERM_INDEX",
    "- source-domain": "metaverse",
    "- status": "draft",
    "- public-access": "true"
  },
  "backlinks": [],
  "wiki_links": [],
  "ontology": {
    "term_id": "mv-1761742247974",
    "preferred_term": "TERM_INDEX",
    "definition": "",
    "source_domain": "metaverse",
    "maturity_level": null,
    "authority_score": null
  }
}