{
  "title": "Text Generation",
  "content": "- ### OntologyBlock\n  id:: text-generation-ontology\n  collapsed:: true\n\t- ontology:: true\n\t- term-id:: AI-0374\n\t- preferred-term:: Text Generation\n\t- source-domain:: ai\n\t- status:: draft\n    - public-access:: true\n\t- definition:: Text Generation is the NLP task of producing coherent, contextually appropriate natural language text using neural language models, including applications such as story generation, article writing, code generation, and creative content production. Modern text generation employs transformer-based language models (GPT, T5, BLOOM) with autoregressive or sequence-to-sequence architectures, controllable generation techniques, and prompt engineering to produce human-quality text across diverse domains and styles.\n\n\n\n## Academic Context\n\n- Brief contextual overview\n  - Text generation is a core task within natural language processing (NLP) that involves the automated production of coherent, contextually appropriate natural language text using computational models\n  - The field has evolved from early rule-based systems to modern neural approaches, with a strong emphasis on learning from large-scale textual corpora\n\n- Key developments and current state\n  - Contemporary text generation is dominated by transformer-based language models, which leverage self-attention mechanisms to capture long-range dependencies and generate high-quality text\n  - The rise of large language models (LLMs) has enabled unprecedented flexibility in style, domain, and task adaptation, supporting applications from creative writing to technical documentation\n\n- Academic foundations\n  - Rooted in computational linguistics and machine learning, text generation draws on theories of language modelling, sequence prediction, and probabilistic inference\n  - Foundational work includes n-gram models, recurrent neural networks (RNNs), and more recently, transformer architectures\n\n## Current Landscape (2025)\n\n- Industry adoption and implementations\n  - Text generation is widely deployed across sectors including media, customer service, software development, and education\n  - Major platforms such as OpenAI’s GPT series, Google’s Gemini, and Meta’s Llama are used for content creation, chatbots, and code generation\n\n- Notable organisations and platforms\n  - UK-based companies like DeepMind (London), Faculty (London), and Holistic AI (London) are active in developing and deploying text generation technologies\n  - North England sees growing activity in AI research and application, with hubs in Manchester, Leeds, Newcastle, and Sheffield\n\n- UK and North England examples where relevant\n  - The University of Manchester’s NLP group contributes to research on controllable text generation and ethical AI\n  - Leeds-based startups are exploring text generation for legal and healthcare documentation\n  - Newcastle University’s Centre for Doctoral Training in Natural Language Processing supports innovation in language technologies\n  - Sheffield’s Advanced Manufacturing Research Centre (AMRC) applies text generation for technical reporting and knowledge management\n\n- Technical capabilities and limitations\n  - Modern models excel at producing fluent, contextually relevant text across diverse domains and styles\n  - Challenges remain in ensuring factual accuracy, avoiding bias, and maintaining coherence over long passages\n  - Controllable generation techniques and prompt engineering allow for fine-tuning output to specific requirements\n\n- Standards and frameworks\n  - Industry standards include the use of transformer architectures, autoregressive and sequence-to-sequence models, and evaluation metrics such as BLEU, ROUGE, and human assessment\n  - Frameworks like Hugging Face Transformers and PyTorch Lightning facilitate rapid prototyping and deployment\n\n## Research & Literature\n\n- Key academic papers and sources\n  - Vaswani, A., et al. (2017). Attention is All You Need. Advances in Neural Information Processing Systems, 30. https://proceedings.neurips.cc/paper/2017/file/3f5ee243547dee91fbd053c1c4a845aa-Paper.pdf\n  - Brown, T., et al. (2020). Language Models are Few-Shot Learners. Advances in Neural Information Processing Systems, 33. https://proceedings.neurips.cc/paper/2020/file/1457c0d6bfcb4967418bfb8ac142f64a-Paper.pdf\n  - Raffel, C., et al. (2020). Exploring the Limits of Transfer Learning with a Unified Text-to-Text Transformer. Journal of Machine Learning Research, 21(140), 1-67. http://jmlr.org/papers/v21/20-074.html\n\n- Ongoing research directions\n  - Improving controllability and interpretability of generated text\n  - Addressing ethical concerns such as bias, misinformation, and privacy\n  - Developing more efficient and scalable models for real-time applications\n\n## UK Context\n\n- British contributions and implementations\n  - The UK has a strong tradition in NLP and AI research, with leading institutions and industry players driving innovation in text generation\n  - Government initiatives and funding support the development of ethical and trustworthy AI systems\n\n- North England innovation hubs (if relevant)\n  - Manchester, Leeds, Newcastle, and Sheffield are emerging as key centres for AI and NLP research, with collaborations between universities, startups, and industry partners\n  - Regional innovation hubs foster interdisciplinary research and practical applications in areas such as healthcare, manufacturing, and public services\n\n- Regional case studies\n  - The University of Manchester’s NLP group has developed text generation tools for summarising scientific literature and generating educational content\n  - Leeds-based startups are using text generation to automate legal document drafting and improve customer service chatbots\n  - Newcastle University’s Centre for Doctoral Training in Natural Language Processing supports research on ethical AI and responsible text generation\n  - Sheffield’s AMRC applies text generation for technical reporting and knowledge management in advanced manufacturing\n\n## Future Directions\n\n- Emerging trends and developments\n  - Integration of multimodal and multilingual capabilities in text generation models\n  - Increased focus on explainability and transparency in AI-generated text\n  - Development of low-resource language models to support underserved communities\n\n- Anticipated challenges\n  - Ensuring the reliability and trustworthiness of generated text\n  - Balancing automation with human oversight and creativity\n  - Addressing the environmental impact of large-scale language models\n\n- Research priorities\n  - Advancing controllable and interpretable text generation\n  - Promoting ethical and inclusive AI practices\n  - Exploring new applications in education, healthcare, and public services\n\n## References\n\n1. Vaswani, A., Shazeer, N., Parmar, N., Uszkoreit, J., Jones, L., Gomez, A. N., Kaiser, Ł., & Polosukhin, I. (2017). Attention is All You Need. Advances in Neural Information Processing Systems, 30. https://proceedings.neurips.cc/paper/2017/file/3f5ee243547dee91fbd053c1c4a845aa-Paper.pdf\n2. Brown, T., Mann, B., Ryder, N., Subbiah, M., Kaplan, J., Dhariwal, P., ... & Amodei, D. (2020). Language Models are Few-Shot Learners. Advances in Neural Information Processing Systems, 33. https://proceedings.neurips.cc/paper/2020/file/1457c0d6bfcb4967418bfb8ac142f64a-Paper.pdf\n3. Raffel, C., Shazeer, N., Roberts, A., Lee, K., Narang, S., Matena, M., ... & Liu, P. J. (2020). Exploring the Limits of Transfer Learning with a Unified Text-to-Text Transformer. Journal of Machine Learning Research, 21(140), 1-67. http://jmlr.org/papers/v21/20-074.html\n\n\n## Metadata\n\n- **Last Updated**: 2025-11-11\n- **Review Status**: Comprehensive editorial review\n- **Verification**: Academic sources verified\n- **Regional Context**: UK/North England where applicable",
  "properties": {
    "id": "text-generation-ontology",
    "collapsed": "true",
    "- ontology": "true",
    "- term-id": "AI-0374",
    "- preferred-term": "Text Generation",
    "- source-domain": "ai",
    "- status": "draft",
    "- public-access": "true",
    "- definition": "Text Generation is the NLP task of producing coherent, contextually appropriate natural language text using neural language models, including applications such as story generation, article writing, code generation, and creative content production. Modern text generation employs transformer-based language models (GPT, T5, BLOOM) with autoregressive or sequence-to-sequence architectures, controllable generation techniques, and prompt engineering to produce human-quality text across diverse domains and styles."
  },
  "backlinks": [
    "Transformers",
    "Variational Autoencoders",
    "Large language models",
    "Generative AI"
  ],
  "wiki_links": [],
  "ontology": {
    "term_id": "AI-0374",
    "preferred_term": "Text Generation",
    "definition": "Text Generation is the NLP task of producing coherent, contextually appropriate natural language text using neural language models, including applications such as story generation, article writing, code generation, and creative content production. Modern text generation employs transformer-based language models (GPT, T5, BLOOM) with autoregressive or sequence-to-sequence architectures, controllable generation techniques, and prompt engineering to produce human-quality text across diverse domains and styles.",
    "source_domain": "ai",
    "maturity_level": null,
    "authority_score": null
  }
}