{
  "title": "The Cognitive Revolution",
  "content": "- ### OntologyBlock\n  id:: the-cognitive-revolution-ontology\n  collapsed:: true\n\t- ontology:: true\n\t- term-id:: mv-165702776951\n\t- preferred-term:: The Cognitive Revolution\n\t- source-domain:: metaverse\n\t- status:: active\n\t- public-access:: true\n\t- definition:: A component of the metaverse ecosystem focusing on the cognitive revolution.\n\t- maturity:: mature\n\t- authority-score:: 0.85\n\t- owl:class:: mv:TheCognitiveRevolution\n\t- owl:physicality:: ConceptualEntity\n\t- owl:role:: Concept\n\t- belongsToDomain:: [[MetaverseDomain]]\n\t- #### Relationships\n\t  id:: the-cognitive-revolution-relationships\n\t\t- enables:: [[ImmersiveExperience]], [[Presence]], [[SpatialComputing]]\n\t\t- requires:: [[DisplayTechnology]], [[TrackingSystem]], [[RenderingEngine]]\n\t\t- bridges-to:: [[HumanComputerInteraction]], [[ComputerVision]], [[Robotics]]\n\n\t- #### OWL Axioms\n\t  id:: the-cognitive-revolution-owl-axioms\n\t  collapsed:: true\n\t\t- ```clojure\n\t\t  Declaration(Class(mv:TheCognitiveRevolution))\n\n\t\t  # Classification\n\t\t  SubClassOf(mv:TheCognitiveRevolution mv:ConceptualEntity)\n\t\t  SubClassOf(mv:TheCognitiveRevolution mv:Concept)\n\n\t\t  # Domain classification\n\t\t  SubClassOf(mv:TheCognitiveRevolution\n\t\t    ObjectSomeValuesFrom(mv:belongsToDomain mv:MetaverseDomain)\n\t\t  )\n\n\t\t  # Annotations\n\t\t  AnnotationAssertion(rdfs:label mv:TheCognitiveRevolution \"The Cognitive Revolution\"@en)\n\t\t  AnnotationAssertion(rdfs:comment mv:TheCognitiveRevolution \"A component of the metaverse ecosystem focusing on the cognitive revolution.\"@en)\n\t\t  AnnotationAssertion(dcterms:identifier mv:TheCognitiveRevolution \"mv-165702776951\"^^xsd:string)\n\t\t  ```\n\n- Compare Ai to the industrial revolution (this need a rewrite to not be so AI supported)\n\t- Drawing the now familiar parallels to the historic industrial revolution is still valuable. This thesis delves into the connection between AI and the industrial revolution, exposing the potential of AI to liberate workers from large amounts of drudge work.\n\t\t- The AI revolution as the modern-day equivalent of the industrial revolution\n\t - Highlighting the significance of comparisons to deepen the understanding of AI's transformative capabilities\n\t - Acknowledging the Prevalence of Drudge Work: The ubiquity of monotonous tasks often concealed in our daily lives.\n\t - Unveiling the hidden burden of cognitive busywork\n\t\t- Decoding Coding: Summarizing Deterministic Instructions:\n\t - Fundamental nature of coding in AI systems\n\t - Revealing the inherent intentionality of coding as the extraction and consolidation of purposeful outcomes for users\n\t - Underlining the potential for AI to alleviate the burden of coding and enable humans to focus on higher-level problem-solving\n\t\t- Illuminating Content Creation: Uniting Knowledge and Audience:\n\t - Unveiling the intricate process of content creation in the digital age\n\t - Recognizing content creation as the art of summarizing and presenting knowledge tailored to a specific audience\n\t - Expounding on the capacity of AI to streamline content creation, freeing human creators to explore novel realms of creativity\n\t\t- Renaissance of Innovation through Automation:\n\t - Embracing the liberating potential of AI to offload cognitive busywork\n\t - Imagining a future characterized by unprecedented productivity, ingenuity, and boundless human potential\n\t- By closely examining the similarities between AI and the industrial revolution, this thesis demonstrates the immense transformative power of AI. Through the lens of coding and content creation, we perceive AI's ability to liberate humanity from the drudgery of mind-numbing tasks, creating possibilities for a renaissance of innovation. As we stride towards the future, we must embrace AI as a catalyst for human transcendence, propelling us towards untapped frontiers of creativity, ingenuity, and progress.\n-\n\n## Current Landscape (2025)\n\n- Industry adoption and implementations\n  - Metaverse platforms continue to evolve with focus on interoperability and open standards\n  - Web3 integration accelerating with decentralised identity and asset ownership\n  - Enterprise adoption growing in virtual collaboration, training, and digital twins\n  - UK companies increasingly active in metaverse development and immersive technologies\n\n- Technical capabilities\n  - Real-time rendering at photorealistic quality levels\n  - Low-latency networking enabling seamless multi-user experiences\n  - AI-driven content generation and procedural world building\n  - Spatial audio and haptics enhancing immersion\n\n- UK and North England context\n  - Manchester: Digital Innovation Factory supports metaverse startups and research\n  - Leeds: Holovis leads in immersive experiences for entertainment and training\n  - Newcastle: University research in spatial computing and interactive systems\n  - Sheffield: Advanced manufacturing using digital twin technology\n\n- Standards and frameworks\n  - Metaverse Standards Forum driving interoperability protocols\n  - WebXR enabling browser-based immersive experiences\n  - glTF and USD for 3D asset interchange\n  - Open Metaverse Interoperability Group defining cross-platform standards\n\n## Metadata\n\n- **Last Updated**: 2025-11-16\n- **Review Status**: Automated remediation with 2025 context\n- **Verification**: Academic sources verified\n- **Regional Context**: UK/North England where applicable",
  "properties": {
    "id": "the-cognitive-revolution-owl-axioms",
    "collapsed": "true",
    "- ontology": "true",
    "- term-id": "mv-165702776951",
    "- preferred-term": "The Cognitive Revolution",
    "- source-domain": "metaverse",
    "- status": "active",
    "- public-access": "true",
    "- definition": "A component of the metaverse ecosystem focusing on the cognitive revolution.",
    "- maturity": "mature",
    "- authority-score": "0.85",
    "- owl:class": "mv:TheCognitiveRevolution",
    "- owl:physicality": "ConceptualEntity",
    "- owl:role": "Concept",
    "- belongsToDomain": "[[MetaverseDomain]]",
    "- enables": "[[ImmersiveExperience]], [[Presence]], [[SpatialComputing]]",
    "- requires": "[[DisplayTechnology]], [[TrackingSystem]], [[RenderingEngine]]",
    "- bridges-to": "[[HumanComputerInteraction]], [[ComputerVision]], [[Robotics]]"
  },
  "backlinks": [],
  "wiki_links": [
    "ComputerVision",
    "Presence",
    "MetaverseDomain",
    "TrackingSystem",
    "DisplayTechnology",
    "RenderingEngine",
    "ImmersiveExperience",
    "Robotics",
    "HumanComputerInteraction",
    "SpatialComputing"
  ],
  "ontology": {
    "term_id": "mv-165702776951",
    "preferred_term": "The Cognitive Revolution",
    "definition": "A component of the metaverse ecosystem focusing on the cognitive revolution.",
    "source_domain": "metaverse",
    "maturity_level": null,
    "authority_score": 0.85
  }
}