{
  "title": "Time Series Forecasting",
  "content": "- ### OntologyBlock\n  id:: time-series-forecasting-ontology\n  collapsed:: true\n\t- ontology:: true\n\t- term-id:: mv-468661437604\n\t- preferred-term:: Time Series Forecasting\n\t- source-domain:: metaverse\n\t- status:: active\n\t- public-access:: true\n\t- definition:: A component of the metaverse ecosystem focusing on time series forecasting.\n\t- maturity:: mature\n\t- authority-score:: 0.85\n\t- owl:class:: mv:TimeSeriesForecasting\n\t- owl:physicality:: ConceptualEntity\n\t- owl:role:: Concept\n\t- belongsToDomain:: [[MetaverseDomain]]\n\t- #### Relationships\n\t  id:: time-series-forecasting-relationships\n\t\t- enables:: [[ImmersiveExperience]], [[Presence]], [[SpatialComputing]]\n\t\t- requires:: [[DisplayTechnology]], [[TrackingSystem]], [[RenderingEngine]]\n\t\t- bridges-to:: [[HumanComputerInteraction]], [[ComputerVision]], [[Robotics]]\n\n\t- #### OWL Axioms\n\t  id:: time-series-forecasting-owl-axioms\n\t  collapsed:: true\n\t\t- ```clojure\n\t\t  Declaration(Class(mv:TimeSeriesForecasting))\n\n\t\t  # Classification\n\t\t  SubClassOf(mv:TimeSeriesForecasting mv:ConceptualEntity)\n\t\t  SubClassOf(mv:TimeSeriesForecasting mv:Concept)\n\n\t\t  # Domain classification\n\t\t  SubClassOf(mv:TimeSeriesForecasting\n\t\t    ObjectSomeValuesFrom(mv:belongsToDomain mv:MetaverseDomain)\n\t\t  )\n\n\t\t  # Annotations\n\t\t  AnnotationAssertion(rdfs:label mv:TimeSeriesForecasting \"Time Series Forecasting\"@en)\n\t\t  AnnotationAssertion(rdfs:comment mv:TimeSeriesForecasting \"A component of the metaverse ecosystem focusing on time series forecasting.\"@en)\n\t\t  AnnotationAssertion(dcterms:identifier mv:TimeSeriesForecasting \"mv-468661437604\"^^xsd:string)\n\t\t  ```\n\npublic:: true\n\n- #Public page\n\t - automatically published\n-\n- [Yes, Transformers are Effective for Time Series Forecasting (+ Autoformer) (huggingface.co)](https://huggingface.co/blog/autoformer)\n- [CERC-AAI Lab\n\t - Lag-LLaMA (google.com)](https://sites.google.com/view/irinalab/blog/lag-llama)\n- [amorphousdata.com/blog/time-series-vs-regression](https://www.amorphousdata.com/blog/time-series-vs-regression)\n- [M4 Forecasting Competition: Introducing a New Hybrid ES-RNN Model | Uber Blog](https://www.uber.com/en-GB/blog/m4-forecasting-competition/)\n- [[2310.06625] iTransformer: Inverted Transformers Are Effective for Time Series Forecasting (arxiv.org)](https://arxiv.org/abs/2310.06625)\n- [A decoder-only foundation model for time-series forecasting â€“ Google Research Blog](https://blog.research.google/2024/02/a-decoder-only-foundation-model-for.html)\n-\n-\n\n## Current Landscape (2025)\n\n- Industry adoption and implementations\n  - Metaverse platforms continue to evolve with focus on interoperability and open standards\n  - Web3 integration accelerating with decentralised identity and asset ownership\n  - Enterprise adoption growing in virtual collaboration, training, and digital twins\n  - UK companies increasingly active in metaverse development and immersive technologies\n\n- Technical capabilities\n  - Real-time rendering at photorealistic quality levels\n  - Low-latency networking enabling seamless multi-user experiences\n  - AI-driven content generation and procedural world building\n  - Spatial audio and haptics enhancing immersion\n\n- UK and North England context\n  - Manchester: Digital Innovation Factory supports metaverse startups and research\n  - Leeds: Holovis leads in immersive experiences for entertainment and training\n  - Newcastle: University research in spatial computing and interactive systems\n  - Sheffield: Advanced manufacturing using digital twin technology\n\n- Standards and frameworks\n  - Metaverse Standards Forum driving interoperability protocols\n  - WebXR enabling browser-based immersive experiences\n  - glTF and USD for 3D asset interchange\n  - Open Metaverse Interoperability Group defining cross-platform standards\n\n## Metadata\n\n- **Last Updated**: 2025-11-16\n- **Review Status**: Automated remediation with 2025 context\n- **Verification**: Academic sources verified\n- **Regional Context**: UK/North England where applicable",
  "properties": {
    "id": "time-series-forecasting-owl-axioms",
    "collapsed": "true",
    "- ontology": "true",
    "- term-id": "mv-468661437604",
    "- preferred-term": "Time Series Forecasting",
    "- source-domain": "metaverse",
    "- status": "active",
    "- public-access": "true",
    "- definition": "A component of the metaverse ecosystem focusing on time series forecasting.",
    "- maturity": "mature",
    "- authority-score": "0.85",
    "- owl:class": "mv:TimeSeriesForecasting",
    "- owl:physicality": "ConceptualEntity",
    "- owl:role": "Concept",
    "- belongsToDomain": "[[MetaverseDomain]]",
    "- enables": "[[ImmersiveExperience]], [[Presence]], [[SpatialComputing]]",
    "- requires": "[[DisplayTechnology]], [[TrackingSystem]], [[RenderingEngine]]",
    "- bridges-to": "[[HumanComputerInteraction]], [[ComputerVision]], [[Robotics]]",
    "public": "true"
  },
  "backlinks": [],
  "wiki_links": [
    "TrackingSystem",
    "ImmersiveExperience",
    "ComputerVision",
    "RenderingEngine",
    "SpatialComputing",
    "Robotics",
    "HumanComputerInteraction",
    "MetaverseDomain",
    "DisplayTechnology",
    "Presence"
  ],
  "ontology": {
    "term_id": "mv-468661437604",
    "preferred_term": "Time Series Forecasting",
    "definition": "A component of the metaverse ecosystem focusing on time series forecasting.",
    "source_domain": "metaverse",
    "maturity_level": null,
    "authority_score": 0.85
  }
}