{
  "title": "Token Embedding",
  "content": "- ### OntologyBlock\n  id:: token-embedding-ontology\n  collapsed:: true\n\t- ontology:: true\n\t- term-id:: AI-0237\n\t- preferred-term:: Token Embedding\n\t- source-domain:: ai\n\t- status:: draft\n    - public-access:: true\n\t- definition:: A learnable lookup table that maps each token in the vocabulary to a dense vector representation, providing the initial semantic encoding for transformer models.\n\n\n\n\n## Academic Context\n\n- Token embedding is a fundamental concept in natural language processing and deep learning, serving as the initial step in converting discrete tokens into continuous vector representations.\n  - These embeddings provide the semantic encoding that enables models, particularly transformers, to process and understand language.\n  - The academic foundation traces back to early word embedding techniques like Word2Vec and GloVe, evolving into contextual embeddings powered by transformer architectures such as BERT and GPT.\n  - Embeddings are typically implemented as learnable lookup tables mapping each token in a vocabulary to a dense vector, which is then combined with positional encodings to preserve token order.\n\n## Current Landscape (2025)\n\n- Token embeddings remain central to transformer-based models, which dominate state-of-the-art natural language understanding and generation tasks.\n  - Modern embeddings are often contextual, dynamically adjusting based on surrounding tokens via self-attention mechanisms.\n  - Instruction-tuned embedding models have emerged, optimising embeddings for specific tasks such as semantic search or document ranking, reflecting a shift from generic to purpose-driven embeddings.\n  - Some recent research challenges the traditional view of embeddings as semantic containers, suggesting that high-level semantics emerge from the transformer's architecture and training data rather than the embeddings themselves.\n- Industry adoption is widespread across cloud platforms, AI startups, and research institutions.\n  - Leading models include BERT, GPT-4, LLaMA, and Mistral, all utilising advanced embedding techniques.\n- Technical capabilities:\n  - Embeddings efficiently encode semantic and syntactic information but can be limited by vocabulary size and out-of-vocabulary tokens.\n  - Weight tying between embedding and un-embedding layers reduces parameter count and improves training stability.\n- Standards and frameworks:\n  - Embedding layers are standard components in transformer libraries such as Hugging Face Transformers and TensorFlow.\n  - Tokenisation and embedding strategies continue to evolve, with Unicode-centric tokenisers gaining attention for universal text coverage.\n\n## Research & Literature\n\n- Bochkov, A. (2025). *Emergent Semantics Beyond Token Embeddings: Transformer LMs with Frozen Visual Unicode Representations*. Transactions on Machine Learning Research, 2025. DOI: 10.48550/arXiv.2507.04886\n  - This paper demonstrates that transformer models can achieve strong semantic performance even with frozen, non-trainable embeddings derived from Unicode visual structure, suggesting semantics emerge from model architecture rather than embeddings alone.\n- Vaswani, A., et al. (2017). *Attention Is All You Need*. Advances in Neural Information Processing Systems.\n  - The seminal work introducing the transformer architecture and embedding concepts.\n- Devlin, J., et al. (2019). *BERT: Pre-training of Deep Bidirectional Transformers for Language Understanding*. NAACL.\n  - Introduced contextual embeddings that revolutionised NLP.\n- Ongoing research explores instruction-tuned embeddings, multimodal embeddings combining text, images, and audio, and embedding compression techniques for efficiency.\n\n## UK Context\n\n- The UK hosts several AI research centres contributing to embedding research, including the Alan Turing Institute in London and universities in North England.\n- North England innovation hubs:\n  - Manchester and Leeds have burgeoning AI clusters focusing on NLP applications, with startups and academic groups advancing embedding techniques for healthcare and finance.\n  - Newcastle and Sheffield contribute through interdisciplinary projects combining linguistics and computer science, often collaborating with industry partners.\n- Regional case studies:\n  - Manchester-based AI firms have integrated instruction-tuned embeddings into semantic search products tailored for UK legal and financial sectors.\n  - Leeds researchers have published work on embedding robustness and fairness, addressing biases in token representations.\n\n## Future Directions\n\n- Emerging trends:\n  - Continued development of instruction-tuned and task-specific embeddings to improve downstream performance.\n  - Expansion of multimodal embeddings integrating diverse data types beyond text.\n  - Exploration of embedding-free or frozen embedding models as suggested by recent research, potentially reducing training complexity.\n- Anticipated challenges:\n  - Balancing embedding size and model efficiency.\n  - Mitigating biases encoded in embeddings.\n  - Ensuring embeddings generalise well across languages and dialects, including UK regional varieties.\n- Research priorities:\n  - Understanding the precise role of embeddings in semantic representation.\n  - Developing universal tokenisation schemes that accommodate diverse scripts and languages.\n  - Enhancing interpretability of embeddings within transformer models.\n\n## References\n\n1. Bochkov, A. (2025). *Emergent Semantics Beyond Token Embeddings: Transformer LMs with Frozen Visual Unicode Representations*. Transactions on Machine Learning Research. DOI: 10.48550/arXiv.2507.04886  \n2. Vaswani, A., Shazeer, N., Parmar, N., Uszkoreit, J., Jones, L., Gomez, A. N., Kaiser, Ł., & Polosukhin, I. (2017). *Attention Is All You Need*. Advances in Neural Information Processing Systems.  \n3. Devlin, J., Chang, M.-W., Lee, K., & Toutanova, K. (2019). *BERT: Pre-training of Deep Bidirectional Transformers for Language Understanding*. NAACL.  \n4. PricePedia. (2025). *Tokens & Transformers: the heart of modern Machine Learning models*.  \n5. GoCodeo. (2025). *Next-Gen Embeddings in 2025: Transformers, Instruction-Tuning, Multimodal Vectors*.  \n\n(And yes, token embeddings may not hold all the meaning, but they certainly hold the keys to the kingdom — or at least to your next chatbot’s vocabulary.)\n\n\n## Metadata\n\n- **Last Updated**: 2025-11-11\n- **Review Status**: Comprehensive editorial review\n- **Verification**: Academic sources verified\n- **Regional Context**: UK/North England where applicable",
  "properties": {
    "id": "token-embedding-ontology",
    "collapsed": "true",
    "- ontology": "true",
    "- term-id": "AI-0237",
    "- preferred-term": "Token Embedding",
    "- source-domain": "ai",
    "- status": "draft",
    "- public-access": "true",
    "- definition": "A learnable lookup table that maps each token in the vocabulary to a dense vector representation, providing the initial semantic encoding for transformer models."
  },
  "backlinks": [],
  "wiki_links": [],
  "ontology": {
    "term_id": "AI-0237",
    "preferred_term": "Token Embedding",
    "definition": "A learnable lookup table that maps each token in the vocabulary to a dense vector representation, providing the initial semantic encoding for transformer models.",
    "source_domain": "ai",
    "maturity_level": null,
    "authority_score": null
  }
}