{
  "title": "Tokenization",
  "content": "- ### OntologyBlock\n  id:: tokenization-ontology\n  collapsed:: true\n\t- ontology:: true\n\t- term-id:: 20212\n\t- source-domain:: metaverse\n\t- status:: draft\n    - public-access:: true\n\t- preferred-term:: Tokenization\n\t- definition:: Process of representing real-world or virtual assets as digital tokens on a blockchain through cryptographic mechanisms and smart contract protocols.\n\t- maturity:: mature\n\t- source:: [[Reed Smith + OMA3]]\n\t- owl:class:: mv:Tokenization\n\t- owl:physicality:: VirtualEntity\n\t- owl:role:: Process\n\t- owl:inferred-class:: mv:VirtualProcess\n\t- owl:functional-syntax:: true\n\t- belongsToDomain:: [[VirtualEconomyDomain]]\n\t- implementedInLayer:: [[MiddlewareLayer]]\n\t- #### Relationships\n\t  id:: tokenization-relationships\n\t\t- is-subclass-of:: [[Blockchain]]\n\t\t- has-part:: [[Smart Contract]], [[Token Standard]], [[Asset Metadata]], [[Blockchain Transaction]]\n\t\t- requires:: [[Blockchain Network]], [[Cryptographic Keys]], [[Token Standard Protocol]], [[Digital Wallet]]\n\t\t- enables:: [[NFT Minting]], [[Asset Trading]], [[Ownership Transfer]], [[Fractional Ownership]]\n\t\t- depends-on:: [[Distributed Ledger]], [[Consensus Mechanism]], [[Digital Signature]]\n\t\t- is-part-of:: [[Digital Asset Management]], [[Blockchain Economy]]\n\t- #### OWL Axioms\n\t  id:: tokenization-owl-axioms\n\t  collapsed:: true\n\t\t- ```clojure\n\t\t  Declaration(Class(mv:Tokenization))\n\n\t\t  # Classification along two primary dimensions\n\t\t  SubClassOf(mv:Tokenization mv:VirtualEntity)\n\t\t  SubClassOf(mv:Tokenization mv:Process)\n\n\t\t  # Domain-specific constraints\n\t\t  SubClassOf(mv:Tokenization\n\t\t    ObjectSomeValuesFrom(mv:hasInput mv:DigitalAsset)\n\t\t  )\n\n\t\t  SubClassOf(mv:Tokenization\n\t\t    ObjectSomeValuesFrom(mv:hasOutput bc:BlockchainToken)\n\t\t  )\n\n\t\t  SubClassOf(mv:Tokenization\n\t\t    ObjectSomeValuesFrom(mv:executesOn bc:BlockchainNetwork)\n\t\t  )\n\n\t\t  SubClassOf(mv:Tokenization\n\t\t    ObjectSomeValuesFrom(mv:requiresComponent bc:SmartContract)\n\t\t  )\n\n\t\t  SubClassOf(mv:Tokenization\n\t\t    ObjectSomeValuesFrom(mv:utilizesStandard mv:TokenStandard)\n\t\t  )\n\n\t\t  # Domain classification\n\t\t  SubClassOf(mv:Tokenization\n\t\t    ObjectSomeValuesFrom(mv:belongsToDomain mv:VirtualEconomyDomain)\n\t\t  )\n\n\t\t  # Layer classification\n\t\t  SubClassOf(mv:Tokenization\n\t\t    ObjectSomeValuesFrom(mv:implementedInLayer mv:MiddlewareLayer)\n\t\t  )\n\n\t\t  # Process characteristics\n\t\t  SubClassOf(mv:Tokenization\n\t\t    ObjectSomeValuesFrom(mv:enablesCapability mv:AssetDigitization)\n\t\t  )\n\n\t\t  SubClassOf(mv:Tokenization\n\t\t    ObjectSomeValuesFrom(mv:producesRecord bc:BlockchainTransaction)\n\t\t  )\n\n  # Property characteristics\n  AsymmetricObjectProperty(dt:requires)\n\n  # Property characteristics\n  AsymmetricObjectProperty(dt:enables)\n\n  # Property characteristics\n  AsymmetricObjectProperty(dt:dependson)\n\n  # Property characteristics\n  TransitiveObjectProperty(dt:ispartof)\n```\n\n- ## About Tokenization\n  id:: tokenization-about\n\t- Tokenization is the fundamental blockchain process that transforms real-world or virtual assets into digital tokens with verifiable ownership and transferability. This process establishes a cryptographic representation of value on distributed ledger technology, enabling assets to participate in decentralized economies with programmable behavior and automated enforcement of ownership rules.\n\t- ### Key Characteristics\n\t  id:: tokenization-characteristics\n\t\t- **Blockchain-Based Representation**: Assets are encoded as tokens on distributed ledger networks with cryptographic proof of authenticity\n\t\t- **Smart Contract Automation**: Token behavior, transfers, and ownership rules are enforced through self-executing contract code\n\t\t- **Immutable Record Creation**: Each tokenization event creates permanent, tamper-proof records on the blockchain\n\t\t- **Standard Protocol Compliance**: Follows established token standards (ERC-721, ERC-1155, etc.) for interoperability\n\t\t- **Programmable Asset Behavior**: Tokens can embed royalties, transfer restrictions, and other automated functionality\n\t- ### Technical Components\n\t  id:: tokenization-components\n\t\t- [[Smart Contract]] - Self-executing code that defines token behavior, minting, and transfer rules\n\t\t- [[Token Standard]] - Protocol specification (ERC-721, ERC-1155) ensuring compatibility and interoperability\n\t\t- [[Asset Metadata]] - On-chain and off-chain data describing token properties and linked resources\n\t\t- [[Blockchain Transaction]] - Cryptographically signed operations recording token creation and transfers\n\t\t- [[Cryptographic Keys]] - Public-private key pairs establishing ownership and authorization\n\t\t- [[Distributed Ledger]] - Decentralized database recording all token state and transaction history\n\t- ### Functional Capabilities\n\t  id:: tokenization-capabilities\n\t\t- **Asset Digitization**: Converts physical or conceptual assets into blockchain-verifiable digital representations\n\t\t- **Ownership Verification**: Provides cryptographic proof of token ownership through blockchain state\n\t\t- **Transfer Automation**: Enables peer-to-peer asset transfers without intermediary approval\n\t\t- **Fractional Ownership**: Allows single assets to be divided into multiple tradeable token units\n\t\t- **Royalty Enforcement**: Automates creator compensation on secondary market transactions\n\t\t- **Interoperability**: Tokens can move across compatible platforms and marketplaces\n\t- ### Use Cases\n\t  id:: tokenization-use-cases\n\t\t- **Virtual Real Estate**: Tokenizing metaverse land parcels for ownership, trading, and development rights\n\t\t- **Digital Art and Collectibles**: Creating unique NFTs representing artwork, music, or limited edition items\n\t\t- **In-Game Assets**: Tokenizing game items, characters, and resources for cross-platform portability\n\t\t- **Virtual Identity Credentials**: Representing membership, achievements, or access rights as tokens\n\t\t- **Intellectual Property Rights**: Tokenizing licenses, patents, or content usage rights\n\t\t- **Physical Asset Linkage**: Creating digital twins of real-world assets with blockchain-verified ownership\n\t- ### Standards & References\n\t  id:: tokenization-standards\n\t\t- [[ISO 24165]] - Metaverse terminology and digital asset standards\n\t\t- [[ETSI GR ARF 010]] - Metaverse architecture and tokenization frameworks\n\t\t- [[ERC-721]] - Non-fungible token standard for unique digital assets\n\t\t- [[ERC-1155]] - Multi-token standard supporting both fungible and non-fungible tokens\n\t\t- [[OMA3 Media Working Group]] - Open metaverse alliance tokenization guidelines\n\t\t- [[Reed Smith Legal Framework]] - Legal considerations for blockchain asset tokenization\n\t- ### Related Concepts\n\t  id:: tokenization-related\n\t\t- [[NFT Minting]] - The specific act of creating a new token instance\n\t\t- [[NFT Renting]] - Temporal rights transfer enabled by tokenized assets\n\t\t- [[NFT Swapping]] - Peer-to-peer exchange mechanisms for tokenized assets\n\t\t- [[Smart Contract]] - Executable code implementing tokenization logic\n\t\t- [[Blockchain Network]] - Infrastructure platform hosting tokenized assets\n\t\t- [[VirtualProcess]] - Parent ontology class for blockchain operations\n\n\n\n## Academic Context\n\n- Tokenization represents a fundamental shift in how ownership and value transfer occur within digital ecosystems\n  - Defined as the process of converting real-world assets (RWAs) into cryptographically secured digital representations on distributed ledger technology (DLT)[1][2]\n  - Encompasses both tangible assets (real estate, commodities, art) and intangible assets (intellectual property, voting rights, fund units)[1][3]\n  - Distinguishes between \"native\" tokens (cryptocurrencies deriving value from market dynamics) and \"linked\" tokens (representing securities or legal positions)[2]\n  - Blockchain technology provides the foundational infrastructure, though tokenization itself is not legally defined across most jurisdictions—a distinction worth noting for practitioners[2]\n\n- Key developments and current state\n  - The \"tokenization wave\" initially focused on digital bonds before expanding to investment funds, equities, and diverse asset classes[2]\n  - 2025 marks a watershed moment for institutional adoption, with major financial institutions integrating tokenization to enhance operational efficiency[1]\n  - Regulatory frameworks are crystallising globally, with the UK positioning itself as a leader in asset tokenization policy[1]\n\n## Current Landscape (2025)\n\n- Industry adoption and implementations\n  - Institutional participation has accelerated significantly, with organisations such as Janus Henderson exploring conversion of fund units into digital tokens to streamline operations[1]\n  - Tokenization enables fractional ownership, democratising access to previously illiquid or high-value asset classes[1]\n  - Settlement times have compressed dramatically—near-real-time settlement on blockchain networks versus traditional multi-day reconciliation processes[5]\n  - UK and North England context: The UK government has prioritised asset tokenization as a strategic financial innovation, establishing supportive regulatory frameworks alongside initiatives in Singapore and Luxembourg[1]\n\n- Technical capabilities and limitations\n  - Advantages include enhanced transparency through immutable distributed ledgers, reduced information asymmetry, and improved auditability for financial regulators[5]\n  - Challenges persist in several areas: limited interoperability between blockchain networks and legacy infrastructure, unclear legal frameworks for tokenized assets in many jurisdictions, and liquidity concerns in secondary markets[5]\n  - Design considerations require careful navigation—permissioned versus permissionless ledgers, settlement asset selection (stablecoins, central bank digital currencies, fiat), and cybersecurity protocols[5]\n  - Counterparty risks emerge when third parties tokenize securities they hold in custody, rather than issuers tokenizing their own instruments[6]\n\n- Standards and frameworks\n  - Germany and Luxembourg have established distinct securities laws for digital assets[2]\n  - Switzerland has introduced ledger-based securities into private law to ensure level playing fields and facilitate transfer of tokenized securities across market participants[2]\n  - The US Securities and Exchange Commission has clarified that tokenized securities remain securities under federal law, requiring adherence to existing disclosure obligations and securities regulations[6]\n  - Distributed ledger technology standards are evolving, though comprehensive interoperability standards remain nascent[5]\n\n## Research & Literature\n\n- Key academic and institutional sources\n  - Baker McKenzie (2025). \"Tokenization in Financial Services.\" Provides comprehensive legal and practical analysis of tokenization mechanisms, distinguishing between native and linked tokens, with particular focus on regulatory developments across multiple jurisdictions[2]\n  - Gemini Cryptopedia (2025). \"What Is Tokenization in Blockchain?\" Explores security tokens, utility tokens, and cryptocurrencies, examining implications for liquidity, transaction efficiency, and transparency across sectors[3]\n  - World Economic Forum (2025). \"How will asset tokenization transform the future of finance?\" Analyses settlement acceleration, transparency mechanisms, and challenges including interoperability and legal frameworks[5]\n  - Sidley Austin (2025). \"2025 Will Be a Brave New Tokenized World.\" Examines tokenized RWAs, business opportunities, and legislative directions, including testimony before the US House Financial Services Committee[4]\n  - SEC Commissioner Hester M. Peirce (July 9, 2025). \"Enchanting, but Not Magical: A Statement on the Tokenization of Securities.\" Clarifies that tokenization does not exempt securities from federal securities laws[6]\n  - Blockchain App Factory (2025). \"Tokenization Takeover: The Future of Real-World Assets in 2025.\" Surveys institutional adoption and regulatory developments[1]\n\n- Ongoing research directions\n  - Standardisation of cross-chain interoperability protocols\n  - Legal harmonisation of tokenized asset frameworks across jurisdictions\n  - Secondary market liquidity mechanisms for tokenized assets\n  - Cybersecurity and privacy protocols for permissioned and permissionless systems\n  - Integration pathways between tokenized markets and legacy financial infrastructure\n\n## UK Context\n\n- British contributions and implementations\n  - The UK has positioned itself as a global leader in asset tokenization policy, establishing regulatory frameworks to support digital asset innovation[1]\n  - The Financial Conduct Authority and Treasury have signalled support for tokenization as a strategic financial technology priority\n  - Regulatory clarity has attracted institutional participation from major UK and international financial services firms\n\n- North England innovation hubs\n  - Manchester, Leeds, Newcastle, and Sheffield have emerging fintech ecosystems, though specific tokenization initiatives remain limited in publicly available documentation\n  - Regional financial centres are increasingly engaging with distributed ledger technology infrastructure, positioning themselves for participation in tokenized asset markets\n  - University research institutions across the North are contributing to blockchain and cryptographic research underpinning tokenization technologies\n\n- Regional case studies\n  - UK-based financial institutions are exploring tokenization pilots for fund management and securities distribution\n  - Cross-border settlement improvements are particularly relevant for North England-based trading and logistics firms managing international transactions\n\n## Future Directions\n\n- Emerging trends and developments\n  - Expansion beyond securities and real estate into commodities, intellectual property, and infrastructure assets[1][3]\n  - Central bank digital currencies (CBDCs) as settlement layers for tokenized asset markets[5]\n  - Interoperability protocols enabling seamless asset transfer across multiple blockchain networks\n  - Institutional custody solutions maturing to support large-scale tokenized asset holdings\n\n- Anticipated challenges\n  - Regulatory fragmentation across jurisdictions may slow adoption—harmonisation efforts remain ongoing[5]\n  - Liquidity in secondary markets for tokenized assets requires critical mass of participants and standardised trading infrastructure\n  - Legacy financial infrastructure integration presents technical and operational hurdles[5]\n  - Cybersecurity threats and privacy considerations demand continuous evolution of protective mechanisms\n\n- Research priorities\n  - Development of standardised legal frameworks for tokenized assets across major financial centres\n  - Empirical analysis of market efficiency gains from tokenization versus traditional settlement mechanisms\n  - Investigation of systemic risks arising from widespread tokenization adoption\n  - Exploration of tokenization applications in emerging markets and developing economies\n\n## References\n\n[1] Blockchain App Factory (2025). \"Tokenization Takeover: The Future of Real-World Assets in 2025.\" Available at: blockchainappfactory.com\n\n[2] Baker McKenzie (2025). \"Tokenization in Financial Services.\" Available at: bakermckenzie.com\n\n[3] Gemini (2025). \"What Is Tokenization in Blockchain?\" Cryptopedia. Updated August 22, 2025. Available at: gemini.com/cryptopedia\n\n[4] Sidley Austin (2025). \"2025 Will Be a Brave New Tokenized World.\" Data Matters. Available at: datamatters.sidley.com\n\n[5] World Economic Forum (2025). \"How will asset tokenization transform the future of finance?\" Available at: weforum.org\n\n[6] Securities and Exchange Commission (2025). \"Enchanting, but Not Magical: A Statement on the Tokenization of Securities.\" Statement by Commissioner Hester M. Peirce, July 9, 2025. Available at: sec.gov\n\n\n## Metadata\n\n- **Last Updated**: 2025-11-11\n- **Review Status**: Comprehensive editorial review\n- **Verification**: Academic sources verified\n- **Regional Context**: UK/North England where applicable",
  "properties": {
    "id": "tokenization-related",
    "collapsed": "true",
    "- ontology": "true",
    "- term-id": "20212",
    "- source-domain": "metaverse",
    "- status": "draft",
    "- public-access": "true",
    "- preferred-term": "Tokenization",
    "- definition": "Process of representing real-world or virtual assets as digital tokens on a blockchain through cryptographic mechanisms and smart contract protocols.",
    "- maturity": "mature",
    "- source": "[[Reed Smith + OMA3]]",
    "- owl:class": "mv:Tokenization",
    "- owl:physicality": "VirtualEntity",
    "- owl:role": "Process",
    "- owl:inferred-class": "mv:VirtualProcess",
    "- owl:functional-syntax": "true",
    "- belongsToDomain": "[[VirtualEconomyDomain]]",
    "- implementedInLayer": "[[MiddlewareLayer]]",
    "- is-subclass-of": "[[Blockchain]]",
    "- has-part": "[[Smart Contract]], [[Token Standard]], [[Asset Metadata]], [[Blockchain Transaction]]",
    "- requires": "[[Blockchain Network]], [[Cryptographic Keys]], [[Token Standard Protocol]], [[Digital Wallet]]",
    "- enables": "[[NFT Minting]], [[Asset Trading]], [[Ownership Transfer]], [[Fractional Ownership]]",
    "- depends-on": "[[Distributed Ledger]], [[Consensus Mechanism]], [[Digital Signature]]",
    "- is-part-of": "[[Digital Asset Management]], [[Blockchain Economy]]"
  },
  "backlinks": [
    "BC-0030-digital-signature",
    "Digital Signature",
    "BC-0071-blockchain-network",
    "Decentralized Finance"
  ],
  "wiki_links": [
    "NFT Swapping",
    "Asset Trading",
    "Reed Smith + OMA3",
    "Fractional Ownership",
    "Digital Signature",
    "NFT Renting",
    "Blockchain",
    "Smart Contract",
    "Reed Smith Legal Framework",
    "VirtualProcess",
    "MiddlewareLayer",
    "Blockchain Economy",
    "NFT Minting",
    "Token Standard",
    "ERC-1155",
    "OMA3 Media Working Group",
    "ISO 24165",
    "Cryptographic Keys",
    "Distributed Ledger",
    "Ownership Transfer",
    "ETSI GR ARF 010",
    "Blockchain Transaction",
    "Digital Asset Management",
    "Consensus Mechanism",
    "ERC-721",
    "Digital Wallet",
    "Token Standard Protocol",
    "VirtualEconomyDomain",
    "Asset Metadata",
    "Blockchain Network"
  ],
  "ontology": {
    "term_id": "20212",
    "preferred_term": "Tokenization",
    "definition": "Process of representing real-world or virtual assets as digital tokens on a blockchain through cryptographic mechanisms and smart contract protocols.",
    "source_domain": "metaverse",
    "maturity_level": null,
    "authority_score": null
  }
}