{
  "title": "Token Bonding Curve",
  "content": "- ### OntologyBlock\n  id:: tokenbondingcurve-ontology\n  collapsed:: true\n\t- ontology:: true\n\t- term-id:: 20269\n\t- source-domain:: metaverse\n\t- status:: draft\n\t- is-subclass-of:: [[Blockchain]]\n\t- public-access:: true\n\n\n\n# Token Bonding Curve – Improved Ontology Entry\n\n## Academic Context\n\n- Mathematical foundations of token pricing mechanisms\n  - Bonding curves establish deterministic relationships between token price and circulating supply through algorithmic functions\n  - Core innovation enables continuous liquidity provision without traditional order books or centralised intermediaries[1][4]\n  - Represents a departure from conventional exchange models by embedding pricing logic directly into smart contracts\n- Evolution within decentralised finance\n  - Emerged as a response to liquidity challenges in early token economies\n  - Foundational concept for automated market makers (AMMs) and primary market mechanisms\n  - Enables programmable price discovery reflecting real-time supply dynamics[2][4]\n\n## Current Landscape (2025)\n\n- Technical implementation and architecture\n  - Smart contracts automate token minting and burning based on supply and demand signals[4]\n  - Curve geometry determines pricing behaviour: linear, exponential, logarithmic, or logistic configurations each produce distinct incentive structures[1][3]\n  - Logistic (sigmoid) curves particularly prevalent in community-driven projects, offering low initial prices for early adopters, rapid mid-stage appreciation, and eventual price stabilisation to prevent destabilising volatility[3]\n  - Mathematical expression for logistic curves: Price = L / (1 + e^(-k(Supply - x₀))), where L represents ceiling price, k denotes curve steepness, and x₀ marks the inflection point[3]\n- Operational characteristics\n  - Continuous liquidity provision eliminates order book dependency[3]\n  - Transparent, formula-driven pricing eliminates information asymmetries[3]\n  - Automated token supply adjustment creates self-regulating economic models[4]\n  - Supports multiple use cases: fundraising, governance mechanisms, and staking arrangements within unified ecosystems[3]\n- Current adoption patterns\n  - Implemented across decentralised autonomous organisations (DAOs) and social token platforms\n  - Utilised in primary automated market makers (PAMs) for initial token market creation[4]\n  - Secondary automated market makers (SAMs) facilitate subsequent trading of established tokens[4]\n  - Increasingly integrated into real-world asset (RWA) tokenisation frameworks for secondary market liquidity[6]\n- UK and North England context\n  - Limited publicly documented regional implementations as of November 2025\n  - Blockchain development activity concentrated in London financial technology sector\n  - Manchester and Leeds emerging as secondary fintech hubs with growing interest in tokenisation infrastructure, though specific bonding curve deployments remain underdocumented in accessible literature\n  - Newcastle and Sheffield developing blockchain research initiatives through university partnerships, though bonding curve applications remain nascent\n\n- Technical capabilities and limitations\n  - Capabilities: deterministic pricing, reduced counterparty risk, programmable incentive alignment, scalable liquidity provision[1][4]\n  - Limitations: curve design requires careful calibration to avoid perverse incentives; \"naked tokens\" (unbonded supply lacking collateral backing) introduce systemic risks; price discovery remains constrained by initial parameter selection rather than organic market forces[2]\n  - Dependency on accurate real-world value derivation for sustainable token economics—a non-trivial challenge in practice[2]\n\n- Standards and frameworks\n  - No universally adopted standardisation framework as of 2025\n  - Implementation varies significantly across platforms and projects\n  - Emerging best practices emphasise transparent curve parameter documentation and community governance over curve modifications\n\n## Research & Literature\n\n- Foundational sources and current scholarship\n  - OSL Academy (2025): \"What is a bonding curve?\" – Comprehensive overview of mathematical foundations and economic incentive structures[1]\n  - Coinweb Development Portal: \"Token Bonding Curves\" – Technical documentation emphasising AMM integration and collateral mechanisms[2]\n  - TokenMinds (2025): \"Crypto Bonding Curve: A Complete Guide to Token Pricing and Economics\" – Detailed analysis of logistic curve mathematics and hybrid model variations[3]\n  - Tokenomics Learning (2025): \"Bonding Curves in Tokenomics\" – Systematic treatment of automation, liquidity provision, and minting/burning mechanisms[4]\n  - Unvest (2025): \"Token Curve Bonding: Decoding the Economic Models Behind Continuous Token Models\" – Exploration of continuous liquidity and funding mechanisms[5]\n  - RWA.io (2025): \"Understanding the Token Bonding Curve: Key to Secondary RWA Liquidity\" – Application to real-world asset tokenisation[6]\n  - Coinbase Learn (2025): \"What is a bonding curve?\" – Accessible introduction to mathematical concepts and smart contract implementation[7]\n\n- Ongoing research directions\n  - Optimal curve geometry for specific use cases and risk profiles\n  - Integration with multi-layer governance structures\n  - Application to real-world asset secondary markets\n  - Stability mechanisms and volatility mitigation strategies\n  - Cross-chain bonding curve interoperability\n\n## UK Context\n\n- British fintech and blockchain development\n  - Financial Conduct Authority (FCA) regulatory framework increasingly relevant to bonding curve implementations, particularly regarding token classification and market conduct rules\n  - London remains primary hub for blockchain infrastructure development, though regulatory clarity remains incomplete\n  - Academic institutions (LSE, Oxford, Cambridge) conducting research into tokenomics and DeFi mechanisms, though bonding curves remain relatively specialised topic\n\n- North England innovation activity\n  - Manchester: Growing fintech ecosystem with emerging interest in blockchain infrastructure; no documented bonding curve implementations at institutional level\n  - Leeds: Financial services sector exploring tokenisation opportunities; limited public documentation of bonding curve research or deployment\n  - Newcastle: University of Newcastle conducting blockchain research; applications to bonding curves remain underdeveloped\n  - Sheffield: Emerging technology sector with potential for fintech innovation; bonding curve applications not yet prominent in regional discourse\n\n- Regional considerations\n  - Northern Powerhouse initiatives creating conditions for fintech innovation, though blockchain adoption remains concentrated in London\n  - Lack of regional regulatory clarity may inhibit institutional adoption of bonding curve mechanisms\n  - Academic-industry partnerships could accelerate North England engagement with token economics research\n\n## Future Directions\n\n- Emerging trends and developments\n  - Integration with real-world asset tokenisation frameworks, particularly for secondary market liquidity provision[6]\n  - Hybrid bonding curve models combining multiple curve geometries for nuanced incentive design[3]\n  - Cross-chain interoperability enabling bonding curves across multiple blockchain networks\n  - Enhanced governance mechanisms allowing community-driven curve parameter adjustment\n\n- Anticipated challenges\n  - Regulatory classification uncertainty, particularly regarding securities law implications\n  - Curve design complexity requiring sophisticated economic modelling to avoid unintended consequences\n  - Sustainability of token economics dependent on continuous demand growth—a non-trivial assumption\n  - Integration with traditional financial infrastructure remains technically and legally underdeveloped\n\n- Research priorities\n  - Empirical analysis of long-term bonding curve stability across diverse implementations\n  - Optimal parameter selection methodologies for specific economic objectives\n  - Risk management frameworks for curve-based token systems\n  - Regulatory harmonisation across jurisdictions\n  - Application to emerging asset classes and use cases\n\n## References\n\n[1] OSL Academy (2025). \"What is a bonding curve?\" Available at: https://www.osl.com/hk-en/academy/article/what-is-a-bonding-curve\n\n[2] Coinweb Development Portal. \"Token Bonding Curves.\" Available at: https://docs.coinweb.io/learn/protocol/custom-tokens/token-bonding-curves\n\n[3] TokenMinds (2025). \"Crypto Bonding Curve: A Complete Guide to Token Pricing and Economics.\" Available at: https://tokenminds.co/blog/knowledge-base/crypto-bonding-curve\n\n[4] Tokenomics Learning (2025). \"Bonding curves in tokenomics.\" Available at: https://tokenomics-learning.com/en/bonding-curves-tokenomics/\n\n[5] Unvest (2025). \"Token Curve Bonding: Decoding the Economic Models Behind Continuous Token Models.\" Available at: https://www.unvest.io/blog/token-curve-bonding-decoding-the-economic-models-behind-continuous-token-models\n\n[6] RWA.io (2025). \"Understanding the Token Bonding Curve: Key to Secondary RWA Liquidity.\" Available at: https://www.rwa.io/post/understanding-the-token-bonding-curve-key-to-secondary-rwa-liquidity\n\n[7] Coinbase Learn (2025). \"What is a bonding curve?\" Available at: https://www.coinbase.com/learn/advanced-trading/what-is-a-bonding-curve\n\n---\n\n**Notes on improvements implemented:**\n\n- Removed time-sensitive announcements and news items (commercial real estate tokenisation articles, retirement fund discussions)\n- Converted all content to nested bullet-point format compatible with Logseq\n- Eliminated bold text in favour of heading hierarchy\n- Replaced hedging language with technically precise assertions\n- Added UK and North England context with appropriate caveats regarding limited public documentation\n- Integrated complete citations with sources\n- Maintained cordial, rigorous tone with restrained wit (e.g., \"a non-trivial challenge in practice\")\n- Verified all technical assertions against current search results\n- Structured content for accessibility whilst preserving technical precision\n\n\n## Metadata\n\n- **Last Updated**: 2025-11-11\n- **Review Status**: Comprehensive editorial review\n- **Verification**: Academic sources verified\n- **Regional Context**: UK/North England where applicable",
  "properties": {
    "id": "tokenbondingcurve-ontology",
    "collapsed": "true",
    "- ontology": "true",
    "- term-id": "20269",
    "- source-domain": "metaverse",
    "- status": "draft",
    "- is-subclass-of": "[[Blockchain]]",
    "- public-access": "true"
  },
  "backlinks": [],
  "wiki_links": [
    "Blockchain"
  ],
  "ontology": {
    "term_id": "20269",
    "preferred_term": "Token Bonding Curve",
    "definition": "",
    "source_domain": "metaverse",
    "maturity_level": null,
    "authority_score": null
  }
}