{
  "title": "Tokenomics",
  "content": "- ### OntologyBlock\n  id:: tokenomics-ontology\n  collapsed:: true\n\n  - **Identification**\n    - domain-prefix:: BC\n    - sequence-number:: 0576\n    - filename-history:: [\"BC-0576-tokenomics.md\"]\n    - public-access:: true\n    - ontology:: true\n    - is-subclass-of:: [[BlockchainTechnology]]\n    - term-id:: BC-0576\n    - preferred-term:: Tokenomics\n    - source-domain:: blockchain\n    - status:: complete\n    - version:: 1.0.0\n    - last-updated:: 2025-11-13\n\n  - **Definition**\n    - definition:: Economic model of token systems.\n    - maturity:: established\n    - source:: Chimera Prime Research\n    - authority-score:: 0.95\n\n  - **Semantic Classification**\n    - owl:class:: bc:Tokenomics\n    - belongsToDomain:: [[Blockchain]]\n\n  - #### CrossDomainBridges\n    - bridges-from:: [[PlayToEarnP2e]] via has-part\n\n  - #### Relationships\n\n  - #### OWL Axioms\n    - ```clojure\n      ; Class Declaration\n      (Declaration (Class :Tokenomics))\n      \n      ; Annotations\n      (AnnotationAssertion rdfs:label :Tokenomics \"Tokenomics\"@en)\n      (AnnotationAssertion rdfs:comment :Tokenomics\n        \"Economic model of token systems.\"@en)\n      ```",
  "properties": {
    "id": "tokenomics-ontology",
    "collapsed": "true",
    "- domain-prefix": "BC",
    "- sequence-number": "0576",
    "- filename-history": "[\"BC-0576-tokenomics.md\"]",
    "- public-access": "true",
    "- ontology": "true",
    "- is-subclass-of": "[[BlockchainTechnology]]",
    "- term-id": "BC-0576",
    "- preferred-term": "Tokenomics",
    "- source-domain": "blockchain",
    "- status": "complete",
    "- version": "1.0.0",
    "- last-updated": "2025-11-13",
    "- definition": "Economic model of token systems.",
    "- maturity": "established",
    "- source": "Chimera Prime Research",
    "- authority-score": "0.95",
    "- owl:class": "bc:Tokenomics",
    "- belongsToDomain": "[[Blockchain]]",
    "- bridges-from": "[[PlayToEarnP2e]] via has-part"
  },
  "backlinks": [
    "Runes and Glyphs",
    "BC 0112 inflationary token",
    "ETSI Domain Virtual Society",
    "BC 0117 circulating supply"
  ],
  "wiki_links": [
    "PlayToEarnP2e",
    "Blockchain",
    "BlockchainTechnology"
  ],
  "ontology": {
    "term_id": "BC-0576",
    "preferred_term": "Tokenomics",
    "definition": "Economic model of token systems.",
    "source_domain": "blockchain",
    "maturity_level": null,
    "authority_score": 0.95
  }
}