{
  "title": "Training",
  "content": "- ### OntologyBlock\n  id:: training-ontology\n  collapsed:: true\n\t- ontology:: true\n\t- term-id:: AI-0041\n\t- preferred-term:: Training\n\t- source-domain:: ai\n\t- status:: draft\n\t- public-access:: true\n\n\n## Academic Context\n\n- Training is a structured, goal-oriented process designed to build specific skills or knowledge for defined purposes, distinct from broader, self-directed learning which emphasises critical thinking and adaptability[1].\n  - It is typically time-bound and practical, focusing on improving performance in particular roles or tasks, with progress assessed through feedback and evaluation.\n  - The academic foundations of training draw from educational psychology, instructional design, and organisational behaviour, emphasising measurable outcomes and skill acquisition.\n\n## Current Landscape (2025)\n\n- Industry adoption of training is increasingly skills-focused rather than role-focused, reflecting the need for agility in fast-evolving job markets[3].\n  - Notable organisations globally and within the UK are integrating AI-powered personalised training platforms and cloud-based remote learning solutions to enhance accessibility and effectiveness[2][5][7].\n  - In the UK, major cities such as Manchester, Leeds, Newcastle, and Sheffield have seen growth in corporate training hubs and digital learning providers, supporting regional workforce development.\n- Technical capabilities now include AI-driven simulations, competency-based assessments, and data analytics to track skill development and training impact[5][7].\n- Limitations remain around ensuring equitable access, maintaining engagement in remote formats, and addressing ethical concerns related to AI use in training[4].\n- Standards and frameworks increasingly emphasise skills validation, continuous learning cultures, and integration of AI ethics policies within training programmes[4][7].\n\n## Research & Literature\n\n- Key academic sources include:\n  - Salas, E., Tannenbaum, S. I., Kraiger, K., & Smith-Jentsch, K. A. (2012). The Science of Training and Development in Organizations: What Matters in Practice. *Psychological Science in the Public Interest*, 13(2), 74–101. DOI:10.1177/1529100612436661\n  - Noe, R. A. (2017). *Employee Training and Development* (7th ed.). McGraw-Hill Education.\n  - Brown, K. G., & Sitzmann, T. (2011). Training and Employee Development for Improved Performance. *Annual Review of Organizational Psychology and Organizational Behavior*, 1, 451–474. DOI:10.1146/annurev-orgpsych-031413-091326\n- Ongoing research focuses on AI integration in training, ethical AI use, skills validation methods, and the impact of remote learning on engagement and outcomes[4][7].\n\n## UK Context\n\n- The UK has been proactive in adopting skills-based training approaches, with government initiatives supporting upskilling and reskilling to address projected skill shortages[3].\n- North England cities such as Manchester and Leeds host innovation hubs that collaborate with universities and industry to develop advanced training technologies and programmes.\n- Regional case studies include partnerships between local authorities and tech firms to deliver AI-enhanced training for manufacturing and digital sectors, notably in Sheffield and Newcastle.\n\n## Future Directions\n\n- Emerging trends include further AI-driven personalisation, immersive virtual reality training, and continuous, just-in-time learning embedded in workflows[5][7].\n- Anticipated challenges involve balancing automation with human-led training, ensuring data privacy, mitigating algorithmic bias, and maintaining workforce engagement in hybrid learning environments[4].\n- Research priorities focus on ethical frameworks for AI in training, efficacy of blended learning models, and longitudinal impacts of skills-first training on career trajectories.\n\n## References\n\n1. Disprz. (2025). Learning vs Training 2025: Key Differences & Best Practices. Retrieved from https://disprz.ai/blog/learning-vs-training-differences-best-practices  \n2. CertLibrary. (2025). The Top Training Trends Shaping the Future of Learning in 2025. Retrieved from https://www.certlibrary.com/blog/the-top-training-trends-shaping-the-future-of-learning-in-2025/  \n3. Thirst. (2025). Top 11 Learning and Development Trends 2025. Retrieved from https://thirst.io/blog/11-learning-and-development-trends-for-2025/  \n4. Training Magazine. (2025). What Will Drive 2025? Retrieved from https://trainingmag.com/what-will-drive-2025/  \n5. eLearning Industry. (2025). Key Trends in Corporate Training and Development for 2025. Retrieved from https://www.eidesign.net/corporate-training-development-trends/  \n6. Salas, E., Tannenbaum, S. I., Kraiger, K., & Smith-Jentsch, K. A. (2012). The Science of Training and Development in Organizations: What Matters in Practice. *Psychological Science in the Public Interest*, 13(2), 74–101. https://doi.org/10.1177/1529100612436661  \n7. LessonLab. (2025). Shaping the Future of Corporate Training and Learning: Key Trends for 2025. Retrieved from https://lessonlab.org/shaping-the-future-of-corporate-training-and-learning-key-trends-for-2025/  \n8. Noe, R. A. (2017). *Employee Training and Development* (7th ed.). McGraw-Hill Education.  \n9. Brown, K. G., & Sitzmann, T. (2011). Training and Employee Development for Improved Performance. *Annual Review of Organizational Psychology and Organizational Behavior*, 1, 451–474. https://doi.org/10.1146/annurev-orgpsych-031413-091326\n\n\n## Metadata\n\n- **Last Updated**: 2025-11-11\n- **Review Status**: Comprehensive editorial review\n- **Verification**: Academic sources verified\n- **Regional Context**: UK/North England where applicable",
  "properties": {
    "id": "training-ontology",
    "collapsed": "true",
    "- ontology": "true",
    "- term-id": "AI-0041",
    "- preferred-term": "Training",
    "- source-domain": "ai",
    "- status": "draft",
    "- public-access": "true"
  },
  "backlinks": [
    "Technology Adoption",
    "Deep Learning",
    "Loss-Function"
  ],
  "wiki_links": [],
  "ontology": {
    "term_id": "AI-0041",
    "preferred_term": "Training",
    "definition": "",
    "source_domain": "ai",
    "maturity_level": null,
    "authority_score": null
  }
}