{
  "title": "Training and fine tuning",
  "content": "- ### OntologyBlock\n  id:: training-and-fine-tuning-ontology\n  collapsed:: true\n\t- ontology:: true\n\t- term-id:: mv-861712475170\n\t- preferred-term:: Training and fine tuning\n\t- source-domain:: metaverse\n\t- status:: active\n\t- public-access:: true\n\t- definition:: A component of the metaverse ecosystem focusing on training and fine tuning.\n\t- maturity:: mature\n\t- authority-score:: 0.85\n\t- owl:class:: mv:TrainingAndFineTuning\n\t- owl:physicality:: ConceptualEntity\n\t- owl:role:: Concept\n\t- belongsToDomain:: [[MetaverseDomain]]\n\t- #### Relationships\n\t  id:: training-and-fine-tuning-relationships\n\t\t- enables:: [[ImmersiveExperience]], [[Presence]], [[SpatialComputing]]\n\t\t- requires:: [[DisplayTechnology]], [[TrackingSystem]], [[RenderingEngine]]\n\t\t- bridges-to:: [[HumanComputerInteraction]], [[ComputerVision]], [[Robotics]]\n\n\t- #### OWL Axioms\n\t  id:: training-and-fine-tuning-owl-axioms\n\t  collapsed:: true\n\t\t- ```clojure\n\t\t  Declaration(Class(mv:TrainingAndFineTuning))\n\n\t\t  # Classification\n\t\t  SubClassOf(mv:TrainingAndFineTuning mv:ConceptualEntity)\n\t\t  SubClassOf(mv:TrainingAndFineTuning mv:Concept)\n\n\t\t  # Domain classification\n\t\t  SubClassOf(mv:TrainingAndFineTuning\n\t\t    ObjectSomeValuesFrom(mv:belongsToDomain mv:MetaverseDomain)\n\t\t  )\n\n\t\t  # Annotations\n\t\t  AnnotationAssertion(rdfs:label mv:TrainingAndFineTuning \"Training and fine tuning\"@en)\n\t\t  AnnotationAssertion(rdfs:comment mv:TrainingAndFineTuning \"A component of the metaverse ecosystem focusing on training and fine tuning.\"@en)\n\t\t  AnnotationAssertion(dcterms:identifier mv:TrainingAndFineTuning \"mv-861712475170\"^^xsd:string)\n\t\t  ```\n\npublic:: true\n\n- #Public page\n\t - automatically published\n- # Training and Refining Large Language Models\n  \n  Large Language Models (LLMs), such as the GPT series, have significantly advanced the field of Natural Language Processing (NLP) by generating human-like text, translating languages, and answering questions. The development of these models involves a multi-stage process, including data collection, preprocessing, training, fine-tuning, and advanced refinement techniques to enhance performance and alignment with human preferences.\n- ## Data Collection and Preprocessing\n\t- The training of LLMs starts with the collection of vast datasets from diverse sources such as books, articles, and code, which is crucial for the model's knowledge and fluency. Following collection, the data undergoes preprocessing to remove irrelevant elements like HTML tags and tokenize the text using techniques such as Byte-Pair Encoding (BPE) [Byte-Pair Encoding (BPE): https://en.wikipedia.org/wiki/Byte_pair_encoding], ensuring the model can efficiently process the information.\n- ## Model Training\n\t- ### Pre-Training\n\t\t- LLMs, typically based on the Transformer architecture [Transformer Architecture: https://arxiv.org/abs/1706.03762], are initialized with random weights. They are then trained unsupervised to predict the next word or masked words in sentences, a process that helps them learn the underlying patterns of language [Masked Language Modeling: https://arxiv.org/abs/1810.04805].\n\t- ### Supervised Fine-Tuning\n\t\t- For specific tasks like question-answering or translation, LLMs are fine-tuned with labeled datasets, adjusting the model's weights to optimize performance on these tasks.\n- ## Advanced Refinement Techniques\n\t- To further improve their alignment with human preferences, LLMs undergo additional refinement:\n\t- ### Reinforcement Learning from Human Feedback (RLHF)\n\t\t- Human-rated outputs train a reward model, and reinforcement learning techniques fine-tune the LLM to maximize these rewards, enhancing output quality [RLHF: https://arxiv.org/abs/1706.03762].\n\t- ### Decision Transformers based on Preference-Ordering (DPO)\n\t\t- Decision models, trained on human preference data, guide the LLM towards preferred outputs, incorporating logic that reflects learned preferences [Decision Transformers: https://arxiv.org/abs/2106.01345].\n\t- ### In-context Learning and Retrieval-Augmented Generation (RAG)\n\t\t- LLMs demonstrate the ability to adapt to new tasks with minimal examples (few-shot learning) and can enhance their responses with information retrieved from databases or document collections for improved accuracy [Few-Shot Learning: https://arxiv.org/abs/2005.14165; RAG: https://arxiv.org/abs/2005.11401].\n- ## Deployment and Continuous Improvement\n\t- Once deployed, LLMs are continuously improved through cycles of user feedback and performance monitoring using techniques like RLHF and DPO, aiming to enhance capabilities and alignment with user needs.\n- ## Additional Considerations\n\t- It is increasingly clear that the input data quality is of huge importance. Even duplicated high quality data can significantly impact responses. There are also considerations regarding data sources, specialized applications such as domain adaptation, and the integration of multimodal data for broader applications [Domain Adaptation: https://aclanthology.org/2020.acl-main.357/; Multimodal LLMs: https://arxiv.org/abs/2202.07724].\n\t- Moreover, the potential for further refinement techniques like safety and alignment measures, knowledge distillation for model efficiency, and the use of benchmarks for evaluation is highlighted, suggesting areas for future expansion and research [Knowledge Distillation: https://arxiv.org/abs/1503.02531; SuperGLUE Benchmark: https://super.gluebenchmark.com/].\n- ## Semantic Annotation and Knowledge Graphs\n\t- LLMs benefit from training on semantically annotated datasets and knowledge graphs, facilitating a deeper understanding of language and knowledge representation. Incorporating structured knowledge from sources like WordNet or DBpedia can significantly enhance model capabilities [WordNet: Miller, G. A. (1995). Communications of the ACM; DBpedia: Lehmann, J., et al. (2015). Semantic Web].\n\t- There are challenges in maintaining ontology quality and consistency, the need for adaptability in ontologies, and directions for future research.\n\n## Current Landscape (2025)\n\n- Industry adoption and implementations\n  - Metaverse platforms continue to evolve with focus on interoperability and open standards\n  - Web3 integration accelerating with decentralised identity and asset ownership\n  - Enterprise adoption growing in virtual collaboration, training, and digital twins\n  - UK companies increasingly active in metaverse development and immersive technologies\n\n- Technical capabilities\n  - Real-time rendering at photorealistic quality levels\n  - Low-latency networking enabling seamless multi-user experiences\n  - AI-driven content generation and procedural world building\n  - Spatial audio and haptics enhancing immersion\n\n- UK and North England context\n  - Manchester: Digital Innovation Factory supports metaverse startups and research\n  - Leeds: Holovis leads in immersive experiences for entertainment and training\n  - Newcastle: University research in spatial computing and interactive systems\n  - Sheffield: Advanced manufacturing using digital twin technology\n\n- Standards and frameworks\n  - Metaverse Standards Forum driving interoperability protocols\n  - WebXR enabling browser-based immersive experiences\n  - glTF and USD for 3D asset interchange\n  - Open Metaverse Interoperability Group defining cross-platform standards\n\n## Metadata\n\n- **Last Updated**: 2025-11-16\n- **Review Status**: Automated remediation with 2025 context\n- **Verification**: Academic sources verified\n- **Regional Context**: UK/North England where applicable",
  "properties": {
    "id": "training-and-fine-tuning-owl-axioms",
    "collapsed": "true",
    "- ontology": "true",
    "- term-id": "mv-861712475170",
    "- preferred-term": "Training and fine tuning",
    "- source-domain": "metaverse",
    "- status": "active",
    "- public-access": "true",
    "- definition": "A component of the metaverse ecosystem focusing on training and fine tuning.",
    "- maturity": "mature",
    "- authority-score": "0.85",
    "- owl:class": "mv:TrainingAndFineTuning",
    "- owl:physicality": "ConceptualEntity",
    "- owl:role": "Concept",
    "- belongsToDomain": "[[MetaverseDomain]]",
    "- enables": "[[ImmersiveExperience]], [[Presence]], [[SpatialComputing]]",
    "- requires": "[[DisplayTechnology]], [[TrackingSystem]], [[RenderingEngine]]",
    "- bridges-to": "[[HumanComputerInteraction]], [[ComputerVision]], [[Robotics]]",
    "public": "true"
  },
  "backlinks": [
    "Client side DCO",
    "Prompt Engineering",
    "Knowledge Graphing"
  ],
  "wiki_links": [
    "TrackingSystem",
    "ImmersiveExperience",
    "ComputerVision",
    "RenderingEngine",
    "SpatialComputing",
    "Robotics",
    "HumanComputerInteraction",
    "MetaverseDomain",
    "DisplayTechnology",
    "Presence"
  ],
  "ontology": {
    "term_id": "mv-861712475170",
    "preferred_term": "Training and fine tuning",
    "definition": "A component of the metaverse ecosystem focusing on training and fine tuning.",
    "source_domain": "metaverse",
    "maturity_level": null,
    "authority_score": 0.85
  }
}