{
  "title": "Transformer Architecture",
  "content": "- ### OntologyBlock\n  id:: transformer-architecture-ontology\n  collapsed:: true\n\t- ontology:: true\n\t- term-id:: AI-0196\n\t- preferred-term:: Transformer Architecture\n\t- source-domain:: ai\n\t- status:: draft\n    - public-access:: true\n\t- definition:: A neural network architecture based solely on attention mechanisms, dispensing with recurrence and convolutions entirely, designed for sequence-to-sequence tasks.\n\n\n# Transformer Architecture – Updated Ontology Entry\n\n## Academic Context\n\n- Neural network architecture fundamentally based on multi-head attention mechanisms\n  - Eliminates recurrent and convolutional components entirely, enabling parallel processing\n  - Originally developed for sequence-to-sequence tasks, particularly machine translation\n  - Proposed in seminal 2017 paper \"Attention Is All You Need\" by Google researchers[5]\n  - Represents paradigm shift from RNN/LSTM approaches by removing sequential bottlenecks\n\n- Core innovation: self-attention mechanism\n  - Allows each token to attend to every other token in the input sequence simultaneously\n  - Computes relevance weights between sequence components, capturing contextual relationships\n  - Enables the model to identify which words matter most for understanding meaning[2]\n  - Linear transformation at each layer, followed by non-linear feed-forward sublayers[4]\n\n## Current Landscape (2025)\n\n- Encoder-decoder architecture remains foundational\n  - Encoder transforms input sequence into contextual representation (context vector)\n  - Decoder generates output sequence iteratively, consuming encoder output and previously generated tokens[4]\n  - Original design: 6 encoder and 6 decoder layers (now variable based on task requirements)[1]\n  - Each layer comprises multi-head self-attention sublayer plus position-wise feed-forward network[2]\n\n- Adapted architectures dominate modern applications\n  - Decoder-only models: GPT family predicts next token in sequence[5]\n  - Encoder-only models: BERT performs masked token prediction for bidirectional context[5]\n  - Reflects practical finding that full encoder-decoder architecture unnecessary for many tasks\n  - Significantly reduces computational requirements compared to original design\n\n- Technical components and processing pipeline\n  - Embedding layer converts tokens into fixed-size vectors capturing semantic nuance[2]\n  - Positional embeddings compensate for transformers' lack of inherent sequential awareness[2]\n  - Linear and softmax blocks convert internal representations into probability distributions over vocabulary[3]\n  - Residual connections and layer normalisation stabilise training across deep architectures[2]\n\n- Industry adoption and implementations\n  - Large language models (LLMs) trained on massive datasets now standard across technology sector\n  - Applications span machine translation, speech recognition, protein sequence analysis, computer vision (vision transformers), reinforcement learning, multimodal learning, and robotics[5]\n  - Pre-trained transformer systems enable transfer learning across diverse downstream tasks\n  - Computational efficiency advantages over RNNs enable training on unprecedented dataset scales[5]\n\n- UK and North England context\n  - DeepMind (London-based, Alphabet subsidiary) continues foundational AI research utilising transformer architectures\n  - University of Manchester hosts significant machine learning research groups exploring transformer applications in healthcare and scientific computing\n  - Leeds and Sheffield universities contribute to NLP research and industrial applications\n  - UK AI sector increasingly adopts transformers for financial services, healthcare diagnostics, and language processing applications\n\n## Research & Literature\n\n- Foundational work\n  - Vaswani, A., Shazeer, N., Parmar, N., et al. (2017). \"Attention Is All You Need.\" *Advances in Neural Information Processing Systems (NeurIPS)*. Established transformer architecture as alternative to sequence-to-sequence RNN models.[5]\n\n- Architectural developments\n  - Devlin, J., Chang, M.-W., Lee, K., & Toutanova, K. (2018). \"BERT: Pre-training of Deep Bidirectional Transformers for Language Understanding.\" *arXiv preprint arXiv:1810.04805*. Demonstrated encoder-only transformer effectiveness for bidirectional context understanding.[5]\n\n- Comprehensive technical resources\n  - DataCamp Tutorial: \"How Transformers Work: A Detailed Exploration\" – accessible explanation of encoder-decoder mechanics and layer composition[1]\n  - AWS Documentation: \"What are Transformers in Artificial Intelligence?\" – practical overview of transformer components and use cases[3]\n  - Machine Learning Mastery: \"A Gentle Introduction to Attention and Transformer Models\" – detailed explanation of attention mechanisms and feed-forward sublayers[4]\n\n- Current research directions\n  - Efficiency improvements: sparse attention mechanisms, knowledge distillation, quantisation\n  - Scaling laws and optimal model sizing for specific tasks\n  - Multimodal transformer extensions combining text, vision, and audio\n  - Long-context handling and efficient attention approximations\n\n## Technical Capabilities and Limitations (2025)\n\n- Strengths\n  - Parallel processing capability eliminates sequential bottleneck of RNNs\n  - Self-attention mechanism captures long-range dependencies effectively\n  - Transfer learning via pre-training enables rapid adaptation to downstream tasks\n  - Scalability demonstrated across model sizes from millions to hundreds of billions of parameters\n\n- Limitations and ongoing challenges\n  - Quadratic computational complexity in sequence length (attention computation scales as O(n²))\n  - Context window limitations restrict maximum input sequence length\n  - Requires substantial computational resources for training and inference\n  - Interpretability challenges: understanding which attention patterns drive predictions remains difficult\n  - Positional encoding schemes still somewhat ad hoc; relative position representations continue evolving\n\n## UK Context\n\n- British contributions to transformer research\n  - DeepMind's continued work on transformer-based systems and their applications\n  - University of Cambridge, Oxford, and Imperial College London maintain active NLP research programmes\n  - British AI safety research increasingly focuses on transformer model behaviour and alignment\n\n- North England innovation\n  - University of Manchester: active research in transformer applications for biomedical NLP and healthcare AI\n  - University of Leeds: contributions to natural language understanding and information extraction using transformer architectures\n  - University of Sheffield: research in speech recognition and multimodal transformers\n  - Growing technology sector adoption in Manchester and Leeds for enterprise AI applications\n\n- Regional case studies\n  - Manchester's emerging AI cluster increasingly leverages transformer models for financial services and healthcare applications\n  - NHS trusts exploring transformer-based systems for clinical note analysis and diagnostic support\n  - UK financial institutions adopting transformers for fraud detection and natural language processing of regulatory documents\n\n## Future Directions\n\n- Emerging trends\n  - Mixture-of-Experts (MoE) architectures scaling model capacity without proportional computational increase\n  - Retrieval-augmented generation combining transformers with external knowledge bases\n  - Efficient attention mechanisms (linear attention, sparse patterns) addressing quadratic complexity\n  - Multimodal and cross-modal transformer extensions\n\n- Anticipated challenges\n  - Energy consumption and environmental impact of large-scale transformer training\n  - Data quality and synthetic data requirements for continued scaling\n  - Regulatory frameworks governing transformer-based systems (particularly in EU and UK contexts)\n  - Robustness and adversarial vulnerability of deployed transformer systems\n\n- Research priorities\n  - Interpretability and explainability of transformer decision-making\n  - Efficient fine-tuning methods reducing computational barriers to adaptation\n  - Context window expansion enabling processing of longer documents\n  - Theoretical understanding of why transformers generalise so effectively\n\n## References\n\n- Vaswani, A., Shazeer, N., Parmar, N., et al. (2017). Attention Is All You Need. *Advances in Neural Information Processing Systems (NeurIPS)*.\n\n- Devlin, J., Chang, M.-W., Lee, K., & Toutanova, K. (2018). BERT: Pre-training of Deep Bidirectional Transformers for Language Understanding. *arXiv preprint arXiv:1810.04805*.\n\n- DataCamp. How Transformers Work: A Detailed Exploration of Transformer Architecture. Retrieved from datacamp.com/tutorial/how-transformers-work\n\n- Swimm. Transformer Neural Networks: Ultimate 2025 Guide. Retrieved from swimm.io/learn/large-language-models/transformer-neural-networks-ultimate-2025-guide\n\n- Amazon Web Services. What are Transformers in Artificial Intelligence? Retrieved from aws.amazon.com/what-is/transformers-in-artificial-intelligence/\n\n- Machine Learning Mastery. A Gentle Introduction to Attention and Transformer Models. Retrieved from machinelearningmastery.com/a-gentle-introduction-to-attention-and-transformer-models/\n\n- Wikipedia. Transformer (deep learning architecture). Retrieved from en.wikipedia.org/wiki/Transformer_(deep_learning_architecture)\n\n- IBM. What is a Transformer Model? Retrieved from ibm.com/think/topics/transformer-model\n\n\n## Metadata\n\n- **Last Updated**: 2025-11-11\n- **Review Status**: Comprehensive editorial review\n- **Verification**: Academic sources verified\n- **Regional Context**: UK/North England where applicable",
  "properties": {
    "id": "transformer-architecture-ontology",
    "collapsed": "true",
    "- ontology": "true",
    "- term-id": "AI-0196",
    "- preferred-term": "Transformer Architecture",
    "- source-domain": "ai",
    "- status": "draft",
    "- public-access": "true",
    "- definition": "A neural network architecture based solely on attention mechanisms, dispensing with recurrence and convolutions entirely, designed for sequence-to-sequence tasks."
  },
  "backlinks": [],
  "wiki_links": [],
  "ontology": {
    "term_id": "AI-0196",
    "preferred_term": "Transformer Architecture",
    "definition": "A neural network architecture based solely on attention mechanisms, dispensing with recurrence and convolutions entirely, designed for sequence-to-sequence tasks.",
    "source_domain": "ai",
    "maturity_level": null,
    "authority_score": null
  }
}