{
  "title": "Transformer",
  "content": "- ### OntologyBlock\n  id:: transformer-ontology\n  collapsed:: true\n\t- ontology:: true\n\t- term-id:: AI-0037\n\t- preferred-term:: Transformer\n\t- source-domain:: metaverse\n\t- status:: mature\n    - public-access:: true\n\t- definition:: ### Primary Definition\nA **Transformer** is a neural network architecture relying on self-attention mechanisms rather than recurrence or convolution. Transformers process entire sequences in parallel, enabling efficient training on large datasets and serving as the foundation for most modern large language models.\n\t- maturity:: mature\n\t- owl:class:: ai:Transformer\n\t- owl:physicality:: ConceptualEntity\n\t- owl:role:: Concept\n\t- belongsToDomain:: [[MetaverseDomain]]",
  "properties": {
    "id": "transformer-ontology",
    "collapsed": "true",
    "- ontology": "true",
    "- term-id": "AI-0037",
    "- preferred-term": "Transformer",
    "- source-domain": "metaverse",
    "- status": "mature",
    "- public-access": "true",
    "- definition": "### Primary Definition",
    "- maturity": "mature",
    "- owl:class": "ai:Transformer",
    "- owl:physicality": "ConceptualEntity",
    "- owl:role": "Concept",
    "- belongsToDomain": "[[MetaverseDomain]]"
  },
  "backlinks": [
    "Variational Autoencoders",
    "Large language models",
    "Generative AI"
  ],
  "wiki_links": [
    "MetaverseDomain"
  ],
  "ontology": {
    "term_id": "AI-0037",
    "preferred_term": "Transformer",
    "definition": "### Primary Definition",
    "source_domain": "metaverse",
    "maturity_level": null,
    "authority_score": null
  }
}