{
  "title": "Transaction Pool",
  "content": "- ### OntologyBlock\n  id:: transaction-pool-ontology\n  collapsed:: true\n\n  - **Identification**\n\n    - domain-prefix:: BC\n\n    - sequence-number:: 0018\n\n    - filename-history:: [\"BC-0018-transaction-pool.md\"]\n    - public-access:: true\n    - ontology:: true\n    - is-subclass-of:: [[BlockchainTechnology]]\n    - term-id:: BC-0018\n    - preferred-term:: Transaction Pool\n    - source-domain:: blockchain\n    - status:: complete\n    - version:: 1.0.0\n    - last-updated:: 2025-10-28\n\n  - **Definition**\n    - definition:: Pending unconfirmed transactions within blockchain systems, providing essential functionality for distributed ledger technology operations and properties.\n    - maturity:: mature\n    - source:: [[ISO/IEC 23257:2021]], [[IEEE 2418.1]], [[NIST NISTIR]]\n    - authority-score:: 0.95\n\n  - **Semantic Classification**\n    - owl:class:: bc:TransactionPool\n    - owl:physicality:: VirtualEntity\n    - owl:role:: Object\n    - owl:inferred-class:: bc:VirtualObject\n    - belongsToDomain:: [[BlockchainDomain]]\n\n  - #### OWL Restrictions\n    \n    \n\n  - #### CrossDomainBridges\n    - bridges-to:: [[BlockchainEntity]] via is-subclass-of\n    - bridges-to:: [[Distributeddatastructure]] via is-subclass-of\n\n  -",
  "properties": {
    "id": "transaction-pool-ontology",
    "collapsed": "true",
    "- domain-prefix": "BC",
    "- sequence-number": "0018",
    "- filename-history": "[\"BC-0018-transaction-pool.md\"]",
    "- public-access": "true",
    "- ontology": "true",
    "- is-subclass-of": "[[BlockchainTechnology]]",
    "- term-id": "BC-0018",
    "- preferred-term": "Transaction Pool",
    "- source-domain": "blockchain",
    "- status": "complete",
    "- version": "1.0.0",
    "- last-updated": "2025-10-28",
    "- definition": "Pending unconfirmed transactions within blockchain systems, providing essential functionality for distributed ledger technology operations and properties.",
    "- maturity": "mature",
    "- source": "[[ISO/IEC 23257:2021]], [[IEEE 2418.1]], [[NIST NISTIR]]",
    "- authority-score": "0.95",
    "- owl:class": "bc:TransactionPool",
    "- owl:physicality": "VirtualEntity",
    "- owl:role": "Object",
    "- owl:inferred-class": "bc:VirtualObject",
    "- belongsToDomain": "[[BlockchainDomain]]",
    "- bridges-to": "[[Distributeddatastructure]] via is-subclass-of"
  },
  "backlinks": [
    "BC-0019-mempool"
  ],
  "wiki_links": [
    "NIST NISTIR",
    "Distributeddatastructure",
    "IEEE 2418.1",
    "BlockchainTechnology",
    "BlockchainEntity",
    "ISO/IEC 23257:2021",
    "BlockchainDomain"
  ],
  "ontology": {
    "term_id": "BC-0018",
    "preferred_term": "Transaction Pool",
    "definition": "Pending unconfirmed transactions within blockchain systems, providing essential functionality for distributed ledger technology operations and properties.",
    "source_domain": "blockchain",
    "maturity_level": null,
    "authority_score": 0.95
  }
}