{
  "title": "Transaction Confirmation",
  "content": "- ### OntologyBlock\n  id:: transaction-confirmation-ontology\n  collapsed:: true\n\n  - **Identification**\n\n    - domain-prefix:: BC\n\n    - sequence-number:: 0020\n\n    - filename-history:: [\"BC-0020-transaction-confirmation.md\"]\n    - public-access:: true\n    - ontology:: true\n    - is-subclass-of:: [[BlockchainTechnology]]\n    - term-id:: BC-0020\n    - preferred-term:: Transaction Confirmation\n    - source-domain:: blockchain\n    - status:: complete\n    - version:: 1.1.0\n    - last-updated:: 2025-11-15\n    - quality-score:: 0.92\n    - completeness:: 0.94\n    - technical-depth:: 0.91\n    - citation-quality:: 0.90\n\n  - **Definition**\n    - definition:: Inclusion in blockchain within blockchain systems, providing essential functionality for distributed ledger technology operations and properties.\n    - maturity:: mature\n    - source:: [[ISO/IEC 23257:2021]], [[IEEE 2418.1]], [[NIST NISTIR]]\n    - authority-score:: 0.95\n\n  - **Semantic Classification**\n    - owl:class:: bc:TransactionConfirmation\n    - owl:physicality:: VirtualEntity\n    - owl:role:: Object\n    - owl:inferred-class:: bc:VirtualObject\n    - belongsToDomain:: [[BlockchainDomain]]\n\n  - #### OWL Restrictions\n    \n    \n\n  - #### CrossDomainBridges\n    - bridges-to:: [[BlockchainEntity]] via is-subclass-of\n    - bridges-to:: [[Distributeddatastructure]] via is-subclass-of\n\n  -",
  "properties": {
    "id": "transaction-confirmation-ontology",
    "collapsed": "true",
    "- domain-prefix": "BC",
    "- sequence-number": "0020",
    "- filename-history": "[\"BC-0020-transaction-confirmation.md\"]",
    "- public-access": "true",
    "- ontology": "true",
    "- is-subclass-of": "[[BlockchainTechnology]]",
    "- term-id": "BC-0020",
    "- preferred-term": "Transaction Confirmation",
    "- source-domain": "blockchain",
    "- status": "complete",
    "- version": "1.1.0",
    "- last-updated": "2025-11-15",
    "- quality-score": "0.92",
    "- completeness": "0.94",
    "- technical-depth": "0.91",
    "- citation-quality": "0.90",
    "- definition": "Inclusion in blockchain within blockchain systems, providing essential functionality for distributed ledger technology operations and properties.",
    "- maturity": "mature",
    "- source": "[[ISO/IEC 23257:2021]], [[IEEE 2418.1]], [[NIST NISTIR]]",
    "- authority-score": "0.95",
    "- owl:class": "bc:TransactionConfirmation",
    "- owl:physicality": "VirtualEntity",
    "- owl:role": "Object",
    "- owl:inferred-class": "bc:VirtualObject",
    "- belongsToDomain": "[[BlockchainDomain]]",
    "- bridges-to": "[[Distributeddatastructure]] via is-subclass-of"
  },
  "backlinks": [],
  "wiki_links": [
    "ISO/IEC 23257:2021",
    "IEEE 2418.1",
    "BlockchainTechnology",
    "NIST NISTIR",
    "BlockchainDomain",
    "Distributeddatastructure",
    "BlockchainEntity"
  ],
  "ontology": {
    "term_id": "BC-0020",
    "preferred_term": "Transaction Confirmation",
    "definition": "Inclusion in blockchain within blockchain systems, providing essential functionality for distributed ledger technology operations and properties.",
    "source_domain": "blockchain",
    "maturity_level": null,
    "authority_score": 0.95
  }
}