{
  "title": "Underfitting",
  "content": "- ### OntologyBlock\n  id:: underfitting-ontology\n  collapsed:: true\n\t- ontology:: true\n\t- term-id:: AI-0055\n\t- preferred-term:: Underfitting\n\t- source-domain:: metaverse\n\t- status:: draft\n    - public-access:: true\n\t- definition:: ### Primary Definition\n**Underfitting** occurs when a model is too simple to capture the underlying patterns in the training data, resulting in poor performance on both training and test data. Underfitted models have insufficient capacity or training.\n\t- maturity:: draft\n\t- owl:class:: mv:Underfitting\n\t- owl:physicality:: ConceptualEntity\n\t- owl:role:: Concept\n\t- belongsToDomain:: [[MetaverseDomain]]",
  "properties": {
    "id": "underfitting-ontology",
    "collapsed": "true",
    "- ontology": "true",
    "- term-id": "AI-0055",
    "- preferred-term": "Underfitting",
    "- source-domain": "metaverse",
    "- status": "draft",
    "- public-access": "true",
    "- definition": "### Primary Definition",
    "- maturity": "draft",
    "- owl:class": "mv:Underfitting",
    "- owl:physicality": "ConceptualEntity",
    "- owl:role": "Concept",
    "- belongsToDomain": "[[MetaverseDomain]]"
  },
  "backlinks": [
    "Loss Function"
  ],
  "wiki_links": [
    "MetaverseDomain"
  ],
  "ontology": {
    "term_id": "AI-0055",
    "preferred_term": "Underfitting",
    "definition": "### Primary Definition",
    "source_domain": "metaverse",
    "maturity_level": null,
    "authority_score": null
  }
}