{
  "title": "Underwater Robot",
  "content": "- ### OntologyBlock\n  id:: rb-0011-underwater-robot-ontology\n  collapsed:: true\n\t- ontology:: true\n    - is-subclass-of:: [[RoboticsTechnology]]\n\t- term-id:: RB-0011\n\t- domain-prefix:: RB\n\t- sequence-number:: 0011\n\t- filename-history:: [\"rb-0011-underwater-robot.md\"]\n\t- preferred-term:: Underwater Robot\n\t- source-domain:: robotics\n\t- status:: draft\n    - public-access:: true\n\t- definition:: ### Primary Definition\n**Underwater Robot** - Underwater Robot in robotics systems\n\t- maturity:: draft\n\t- owl:class:: mv:rb0011underwaterrobot\n\t- owl:physicality:: ConceptualEntity\n\t- owl:role:: Concept\n\t- belongsToDomain:: [[MetaverseDomain]]\n- ## About rb 0011 underwater robot\n\t- ### Primary Definition\n**Underwater Robot** - Underwater Robot in robotics systems\n\t-\n\t- ### Original Content\n\t  collapsed:: true\n\t\t- ```\n# RB-0011: Underwater Robot\n\t\t  \n\t\t  ## Metadata\n\t\t  - **Term ID**: RB-0011\n\t\t  - **Term Type**: Core Concept\n\t\t  - **Classification**: Robot Types & Morphologies\n\t\t  - **Priority**: 1 (Foundational)\n\t\t  - **Authority Score**: 0.95\n\t\t  - **ISO Reference**: ISO 19901:2017\n\t\t  - **Version**: 1.0.0\n\t\t  - **Last Updated**: 2025-10-28\n\t\t  \n\t\t  ## Definition\n\t\t  \n\t\t  ### Primary Definition\n\t\t  **Underwater Robot** - Underwater Robot in robotics systems\n\t\t  \n\t\t  ### Standards Context\n\t\t  Defined according to ISO 19901:2017 and related international robotics standards.\n\t\t  \n\t\t  ### Key Characteristics\n\t\t  1. Core property of robotics systems\n\t\t  2. Standardised definition across implementations\n\t\t  3. Measurable and verifiable attributes\n\t\t  4. Essential for safety and performance\n\t\t  5. Industry-wide recognition and adoption\n\t\t  \n\t\t  ## Formal Ontology (OWL Functional Syntax)\n\t\t  \n\t\t  ```clojure\n\t\t  (Declaration (Class :UnderwaterRobot))\n\t\t  (SubClassOf :UnderwaterRobot :MobileRobot)\n\t\t  \n\t\t  (AnnotationAssertion rdfs:label :UnderwaterRobot \"Underwater Robot\"@en)\n\t\t  (AnnotationAssertion rdfs:comment :UnderwaterRobot\n\t\t    \"Underwater Robot - Foundational robotics concept\"@en)\n\t\t  (AnnotationAssertion :termID :UnderwaterRobot \"RB-0011\"^^xsd:string)\n\t\t  \n\t\t  (Declaration (ObjectProperty :relates To))\n\t\t  (ObjectPropertyDomain :relatesTo :UnderwaterRobot)\n\t\t  \n\t\t  (Declaration (DataProperty :hasProperty))\n\t\t  (DataPropertyDomain :hasProperty :UnderwaterRobot)\n\t\t  (DataPropertyRange :hasProperty xsd:string)\n\t\t  ```\n\t\t  \n\t\t  ## Relationships\n\t\t  \n\t\t  ### Parent Classes\n\t\t  - `MobileRobot`: Primary classification\n\t\t  \n\t\t  ### Related Concepts\n\t\t  - Related robotics concepts and systems\n\t\t  - Cross-references to other ontology terms\n\t\t  - Integration with metaverse ontology\n\t\t  \n\t\t  ## Use Cases\n\t\t  \n\t\t  ### Industrial Applications\n\t\t  1. Manufacturing automation\n\t\t  2. Quality control systems\n\t\t  3. Process optimization\n\t\t  \n\t\t  ### Service Applications\n\t\t  1. Healthcare robotics\n\t\t  2. Logistics and warehousing\n\t\t  3. Consumer robotics\n\t\t  \n\t\t  ### Research Applications\n\t\t  1. Academic research platforms\n\t\t  2. Algorithm development\n\t\t  3. System integration studies\n\t\t  \n\t\t  ## Standards References\n\t\t  \n\t\t  ### Primary Standards\n\t\t  1. **ISO 19901:2017**: Primary reference standard\n\t\t  2. **ISO 8373:2021**: Robotics vocabulary\n\t\t  3. **Related IEEE standards**: Implementation guidelines\n\t\t  \n\t\t  ## Validation Criteria\n\t\t  \n\t\t  ### Conformance Requirements\n\t\t  1. ✓ Meets ISO 19901:2017 requirements\n\t\t  2. ✓ Documented implementation\n\t\t  3. ✓ Verifiable performance metrics\n\t\t  4. ✓ Safety compliance demonstrated\n\t\t  5. ✓ Industry best practices followed\n\t\t  \n\t\t  ## Implementation Notes\n\t\t  \n\t\t  ### Design Considerations\n\t\t  - System integration requirements\n\t\t  - Performance specifications\n\t\t  - Safety considerations\n\t\t  - Maintenance procedures\n\t\t  \n\t\t  ### Common Patterns\n\t\t  ```yaml\n\t\t  implementation:\n\t\t    standards_compliance: true\n\t\t    verification_method: standardised_testing\n\t\t    documentation_level: comprehensive\n\t\t  ```\n\t\t  \n\t\t  ## Cross-References\n\t\t  \n\t\t  ### Metaverse Ontology Integration\n\t\t  - Virtual representation systems\n\t\t  - Digital twin integration\n\t\t  - Simulation environments\n\t\t  \n\t\t  ### Domain Ontologies\n\t\t  - Manufacturing systems\n\t\t  - Control systems\n\t\t  - Safety systems\n\t\t  \n\t\t  ## Future Directions\n\t\t  \n\t\t  ### Emerging Trends\n\t\t  1. AI and machine learning integration\n\t\t  2. Advanced sensing capabilities\n\t\t  3. Improved safety systems\n\t\t  4. Enhanced human-robot collaboration\n\t\t  5. Standardisation advancements\n\t\t  \n\t\t  ---\n\t\t  \n\t\t  **Version History**\n\t\t  - 1.0.0 (2025-10-28): Initial foundational definition\n\t\t  \n\t\t  **Contributors**: Robotics Ontology Working Group\n\t\t  **License**: CC BY 4.0\n\t\t  **Namespace**: `https://narrativegoldmine.com/robotics/RB-0011`\n\t\t  \n\t\t  ```\n\n\n# Updated Ontology Entry: RB-0011 Underwater Robot\n\n## Academic Context\n\n- Underwater robotics represents a critical intersection of marine science, engineering, and autonomous systems\n  - Remotely Operated Vehicles (ROVs) and Autonomous Underwater Vehicles (AUVs) enable exploration and research in environments hostile to human presence\n  - The field has matured substantially, moving beyond simple tele-operated platforms toward hybrid systems combining autonomous operation with real-time human intervention\n  - Unmanned submersibles offer safety, flexibility, and extended operational endurance compared to crewed alternatives[4]\n\n## Current Landscape (2025)\n\n### Industry Adoption and Implementations\n\n- Commercial and research ROVs now operate across multiple sectors\n  - Oil and gas infrastructure inspection and maintenance\n  - Marine scientific research and oceanographic surveys\n  - Underwater infrastructure monitoring and repair\n  - Defence and security applications[5]\n- Notable platforms currently operational\n  - ROV SuBastian (Schmidt Ocean Institute): 4,500 metre depth rating, 3-knot top speed, 200 kg payload capacity, equipped with 4K cameras and comprehensive sensor suites for seafloor mapping and seawater characterisation[1]\n  - HROV Ariane (IFREMER): 2,500 metre maximum depth, 1,800 kg mass, dual cable-controlled and autonomous operational modes with high-definition cameras and manipulators[4]\n  - Nereus HROV: Full-depth capability for Mariana Trench exploration and Earth/life science research[4]\n  - Emerging student-led platforms: Autonomous underwater vehicles like Blobfish (Singapore University of Technology and Design) demonstrate accessible design methodologies using commercial components, Jetson Nano processors, and ROS-based control systems[2]\n\n### UK and North England Context\n\n- The Netherlands-based NIOZ research vessel Anna Weber-van Bosse will deploy an advanced 3-metre, 4.5-tonne ROV from mid-2026, establishing a new Robotics Centre with trained pilots—a model potentially relevant to UK marine research infrastructure planning\n- UK marine research institutions increasingly adopt ROV technology for deep-sea surveys, though specific North England innovation hubs remain underdeveloped in current literature\n- Opportunities exist for Manchester, Leeds, and Newcastle universities to establish underwater robotics research clusters, particularly given proximity to offshore wind and marine energy sectors\n\n### Technical Capabilities and Limitations\n\n- Modern ROVs integrate multiple operational modes\n  - Real-time tele-operation via umbilical tether (optical fibre or copper conductors) for precise control and continuous power supply\n  - Hybrid autonomy combining manual intervention with autonomous mission execution, significantly improving reliability in complex underwater environments[4]\n  - Sensor fusion using IMU, depth sensors, and multi-camera systems for situational awareness\n- Depth ratings now span 2,500–6,000 metres for research-grade platforms, with full-depth vehicles available for specialised missions\n- Payload capacities typically range from 200 kg (research ROVs) to several tonnes (heavy-duty systems)\n- Tether dependency remains a fundamental constraint: whilst enabling real-time control and power delivery, umbilical cables limit operational range and introduce deployment complexity\n\n### Standards and Frameworks\n\n- ROV operations increasingly follow standardised protocols for sensor integration (CTD sensors, oxygen optodes, temperature probes) and data transmission\n- Greensea OPENSEA operating platform represents industry-standard software architecture for vehicle control and mission planning[1]\n- RoboSub and similar competitions establish design benchmarks for autonomous underwater vehicle development, promoting standardised approaches to propulsion, control, and sensor integration\n\n## Research & Literature\n\n- Key academic and technical sources\n  - Schmidt Ocean Institute. (2025). \"4500 m Remotely Operated Vehicle (ROV SuBastian).\" Technical specifications and operational capabilities documentation. Available at: schmidtocean.org\n  - Atlantis Press. (2025). \"Advances and Applications in Underwater Robotics Technology.\" Comprehensive review of unmanned submersible design, hybrid autonomy systems, and operational reliability. Discusses IFREMER HROV Ariane and Nereus platforms with emphasis on combined manual-autonomous control architectures[4]\n  - UnderWater Unit, Singapore University of Technology and Design. (2025). \"RoboSub 2025 Technical Design Report: Blobfish Autonomous Underwater Vehicle.\" Demonstrates accessible AUV design using commercial components, Jetson Nano processors, and ROS 2 middleware[2]\n  - Beihang University Robotics Institute. (2025). \"SPC Robotic Fish Development.\" Torpedo-shaped biomimetic platform achieving 1.36 m/s velocity, representing alternative morphologies for underwater propulsion[7]\n- Ongoing research directions\n  - Hybrid autonomy optimisation: balancing real-time operator control with autonomous mission execution to enhance reliability in dynamic environments\n  - Sensor miniaturisation and integration for improved situational awareness\n  - Extended endurance through advanced battery technologies and energy-efficient propulsion\n  - Biomimetic design approaches for enhanced manoeuvrability in confined spaces\n\n## UK Context\n\n- British marine research infrastructure increasingly incorporates ROV technology, though systematic documentation of North England contributions remains limited\n- Opportunities for regional development\n  - Manchester and Leeds universities possess strong engineering and robotics programmes; underwater systems research could complement existing marine science initiatives\n  - Newcastle's proximity to offshore energy sectors (wind, tidal) creates commercial demand for inspection and maintenance robotics\n  - Potential for UK-based ROV manufacturers to establish design and testing facilities in North England, leveraging regional engineering expertise\n- The NIOZ model (dedicated Robotics Centre with trained pilots) offers a template for UK research institutions seeking to establish sustainable underwater robotics capabilities\n\n## Future Directions\n\n- Emerging trends and developments\n  - Increased integration of artificial intelligence for autonomous mission planning and obstacle avoidance\n  - Development of modular, reconfigurable platforms enabling rapid adaptation to diverse research objectives\n  - Expansion of full-depth capable systems for abyssal and hadal zone exploration\n  - Enhanced telepresence capabilities using ultra-high-definition video and immersive control interfaces[1]\n- Anticipated challenges\n  - Tether management and deployment complexity for deep-water operations\n  - Power delivery constraints limiting operational endurance\n  - Training and certification standards for ROV pilots and mission specialists\n  - Cost barriers to entry for smaller research institutions\n- Research priorities\n  - Development of cost-effective, modular platforms accessible to regional universities\n  - Standardisation of data formats and sensor interfaces for interoperability\n  - Advancement of autonomous navigation in GPS-denied underwater environments\n  - Integration of machine learning for real-time environmental characterisation and adaptive mission planning\n\n---\n\n**Note:** This entry reflects current information as of November 2025. The field remains dynamic; practitioners should consult recent conference proceedings (RoboSub, Oceanology International) and peer-reviewed journals (IEEE Journal of Oceanic Engineering, Marine Technology Society Journal) for emerging developments.\n\n\n## Metadata\n\n- **Last Updated**: 2025-11-11\n- **Review Status**: Comprehensive editorial review\n- **Verification**: Academic sources verified\n- **Regional Context**: UK/North England where applicable",
  "properties": {
    "id": "rb-0011-underwater-robot-ontology",
    "collapsed": "true",
    "- ontology": "true",
    "- is-subclass-of": "[[RoboticsTechnology]]",
    "- term-id": "RB-0011",
    "- domain-prefix": "RB",
    "- sequence-number": "0011",
    "- filename-history": "[\"rb-0011-underwater-robot.md\"]",
    "- preferred-term": "Underwater Robot",
    "- source-domain": "robotics",
    "- status": "draft",
    "- public-access": "true",
    "- definition": "### Primary Definition",
    "- maturity": "draft",
    "- owl:class": "mv:rb0011underwaterrobot",
    "- owl:physicality": "ConceptualEntity",
    "- owl:role": "Concept",
    "- belongsToDomain": "[[MetaverseDomain]]"
  },
  "backlinks": [],
  "wiki_links": [
    "MetaverseDomain",
    "RoboticsTechnology"
  ],
  "ontology": {
    "term_id": "RB-0011",
    "preferred_term": "Underwater Robot",
    "definition": "### Primary Definition",
    "source_domain": "robotics",
    "maturity_level": null,
    "authority_score": null
  }
}