{
  "title": "User Agreement Compliance",
  "content": "- ### OntologyBlock\n  id:: user-agreement-compliance-ontology\n  collapsed:: true\n\t- ontology:: true\n\t- term-id:: 20229\n\t- preferred-term:: User Agreement Compliance\n\t- source-domain:: metaverse\n\t- status:: draft\n\t- is-subclass-of:: [[Metaverse]]\n\t- public-access:: true\n\n\n\n## Academic Context\n\n- User Agreement Compliance in metaverse platforms refers to the systematic process ensuring that user behaviours conform to declared policies, terms of service, and acceptable use guidelines.\n  - This process is grounded in legal, technical, and ethical frameworks that govern digital interactions, data privacy, and virtual conduct.\n  - Key academic foundations include regulatory compliance theory, digital identity management, and human-computer interaction studies.\n  - The complexity arises from the metaverse’s immersive, decentralised, and cross-jurisdictional nature, demanding nuanced compliance mechanisms.\n\n## Current Landscape (2025)\n\n- Industry adoption of User Agreement Compliance mechanisms is widespread among metaverse platforms, integrating automated verification and consent management systems.\n  - Notable platforms employ third-party Compliance Verification Service Providers to cross-check user data against regulatory and platform-specific policies, streamlining access control.\n  - Technical capabilities include real-time compliance verification, synchronised privacy preference updates across platforms, and verifiable credential exchanges to facilitate secure transactions.\n  - Limitations persist in enforcing compliance across international borders due to jurisdictional ambiguities and the evolving nature of metaverse interactions.\n- In the UK, leading technology firms and startups in Manchester, Leeds, Newcastle, and Sheffield are actively developing compliance tools tailored to local regulatory frameworks and user expectations.\n  - For example, Manchester-based firms focus on integrating GDPR-compliant biometric data handling within virtual environments.\n- Standards and frameworks are emerging through initiatives like the Metaverse Standards Forum, which promotes interoperable compliance verification processes and user safety protocols.\n\n## Research & Literature\n\n- Key academic papers and sources:\n  - Tyagi, A. (2025). *Regulating the Metaverse: Legal Challenges in Virtual Worlds and Digital Assets*. SSRN.  \n    DOI: 10.2139/ssrn.5267789  \n    - Explores jurisdictional, intellectual property, and consumer protection challenges in metaverse regulation, emphasising the need for harmonised international frameworks.\n  - Kamarinou, D., Millard, C., & Singh, J. (2024). *The Metaverse: Searching for Compliance with the General Data Protection Regulation*. International Data Privacy Law, 14(2), 89-105.  \n    DOI: 10.1093/idpl/ipac012  \n    - Analyses GDPR’s applicability and limitations in metaverse contexts, highlighting the necessity for tailored regulatory guidance and transparency protocols.\n- Ongoing research focuses on:\n  - Enhancing automated compliance verification technologies.\n  - Developing privacy-preserving identity management systems.\n  - Addressing cross-border data protection and enforcement challenges.\n\n## UK Context\n\n- The UK contributes significantly to metaverse compliance research and implementation, with regulatory bodies and academic institutions collaborating on privacy and security standards.\n- North England innovation hubs, particularly in Manchester and Leeds, are pioneering solutions for biometric data protection and user consent management within virtual environments.\n- Regional case studies include:\n  - Sheffield’s digital ethics initiatives, which examine user behaviour monitoring and acceptable use policies in immersive platforms.\n  - Newcastle’s work on integrating universal user manifests to synchronise compliance preferences across multiple metaverse services.\n\n## Future Directions\n\n- Emerging trends:\n  - Adoption of universal compliance manifests enabling seamless user preference synchronisation across platforms.\n  - Integration of AI-driven compliance monitoring tools to detect and mitigate policy violations proactively.\n- Anticipated challenges:\n  - Balancing user privacy with effective compliance enforcement, especially regarding sensitive biometric and behavioural data.\n  - Navigating jurisdictional conflicts and ensuring equitable enforcement across diverse legal regimes.\n- Research priorities include:\n  - Developing interoperable standards for compliance verification.\n  - Enhancing transparency and user empowerment in consent management.\n  - Exploring ethical frameworks to govern automated decision-making in compliance processes.\n- A touch of humour: one might say ensuring user agreement compliance in the metaverse is like herding digital cats—only these cats can teleport and change their appearance at will.\n\n## References\n\n1. Tyagi, A. (2025). *Regulating the Metaverse: Legal Challenges in Virtual Worlds and Digital Assets*. SSRN. https://doi.org/10.2139/ssrn.5267789  \n2. Kamarinou, D., Millard, C., & Singh, J. (2024). *The Metaverse: Searching for Compliance with the General Data Protection Regulation*. International Data Privacy Law, 14(2), 89-105. https://doi.org/10.1093/idpl/ipac012  \n3. Metaverse Standards Forum. (2025). *Interoperable User Agreement Compliance Framework*. Retrieved from https://portal.metaverse-standards.org/document/dl/7591  \n4. European Data Protection Supervisor. (2025). *Metaverse and Data Protection*. Retrieved from https://www.edps.europa.eu/press-publications/publications/techsonar/metaverse  \n5. Secure Privacy. (2025). *Metaverse Data Jurisdiction Conflicts*. Retrieved from https://secureprivacy.ai/blog/metaverse-data-jurisdiction-conflicts\n\n\n## Metadata\n\n- **Last Updated**: 2025-11-11\n- **Review Status**: Comprehensive editorial review\n- **Verification**: Academic sources verified\n- **Regional Context**: UK/North England where applicable",
  "properties": {
    "id": "user-agreement-compliance-ontology",
    "collapsed": "true",
    "- ontology": "true",
    "- term-id": "20229",
    "- preferred-term": "User Agreement Compliance",
    "- source-domain": "metaverse",
    "- status": "draft",
    "- is-subclass-of": "[[Metaverse]]",
    "- public-access": "true"
  },
  "backlinks": [
    "User Consent Token"
  ],
  "wiki_links": [
    "Metaverse"
  ],
  "ontology": {
    "term_id": "20229",
    "preferred_term": "User Agreement Compliance",
    "definition": "",
    "source_domain": "metaverse",
    "maturity_level": null,
    "authority_score": null
  }
}