{
  "title": "UTXO Model",
  "content": "- ### OntologyBlock\n  id:: utxo-model-ontology\n  collapsed:: true\n\n  - **Identification**\n\n    - domain-prefix:: BC\n\n    - sequence-number:: 0007\n\n    - filename-history:: [\"BC-0007-utxo-model.md\"]\n    - public-access:: true\n    - ontology:: true\n    - term-id:: BC-0007\n    - preferred-term:: UTXO Model\n    - source-domain:: blockchain\n    - status:: complete\n    - version:: 1.0.0\n    - last-updated:: 2025-10-28\n\n  - **Definition**\n    - definition:: Unspent Transaction Output accounting model within blockchain systems, providing essential functionality for distributed ledger technology operations and properties.\n    - maturity:: mature\n    - source:: [[ISO/IEC 23257:2021]], [[IEEE 2418.1]], [[NIST NISTIR]]\n    - authority-score:: 0.95\n\n  - **Semantic Classification**\n    - owl:class:: bc:UTXOModel\n    - owl:physicality:: VirtualEntity\n    - owl:role:: Object\n    - owl:inferred-class:: bc:VirtualObject\n    - belongsToDomain:: [[BlockchainDomain]]\n    - implementedInLayer:: [[ConceptualLayer]]\n\n  - #### Relationships\n    id:: utxo-model-relationships\n    - is-subclass-of:: [[Blockchain Entity]], [[DistributedDataStructure]]\n\n  - #### OWL Axioms\n    id:: utxo-model-owl-axioms\n    collapsed:: true\n    - ```clojure\n      Prefix(:=<http://metaverse-ontology.org/blockchain#>)\nPrefix(owl:=<http://www.w3.org/2002/07/owl#>)\nPrefix(rdf:=<http://www.w3.org/1999/02/22-rdf-syntax-ns#>)\nPrefix(xml:=<http://www.w3.org/XML/1998/namespace>)\nPrefix(xsd:=<http://www.w3.org/2001/XMLSchema#>)\nPrefix(rdfs:=<http://www.w3.org/2000/01/rdf-schema#>)\nPrefix(dct:=<http://purl.org/dc/terms/>)\n\nOntology(<http://metaverse-ontology.org/blockchain/BC-0007>\n  Import(<http://metaverse-ontology.org/blockchain/core>)\n\n  ## Class Declaration\n  Declaration(Class(:UTXOModel))\n\n  ## Subclass Relationships\n  SubClassOf(:UTXOModel :DistributedDataStructure)\n  SubClassOf(:UTXOModel :BlockchainEntity)\n\n  ## Essential Properties\n  SubClassOf(:UTXOModel\n    (ObjectSomeValuesFrom :partOf :Blockchain))\n\n  SubClassOf(:UTXOModel\n    (ObjectSomeValuesFrom :hasProperty :Property))\n\n  ## Data Properties\n  DataPropertyAssertion(:hasIdentifier :UTXOModel \"BC-0007\"^^xsd:string)\n  DataPropertyAssertion(:hasAuthorityScore :UTXOModel \"1.0\"^^xsd:decimal)\n  DataPropertyAssertion(:isFoundational :UTXOModel \"true\"^^xsd:boolean)\n\n  ## Object Properties\n  ObjectPropertyAssertion(:enablesFeature :UTXOModel :BlockchainFeature)\n  ObjectPropertyAssertion(:relatesTo :UTXOModel :RelatedConcept)\n\n  ## Annotations\n  AnnotationAssertion(rdfs:label :UTXOModel \"UTXO Model\"@en)\n  AnnotationAssertion(rdfs:comment :UTXOModel\n    \"Unspent Transaction Output accounting model\"@en)\n  AnnotationAssertion(dct:description :UTXOModel\n    \"Foundational blockchain concept with formal ontological definition\"@en)\n  AnnotationAssertion(:termID :UTXOModel \"BC-0007\")\n  AnnotationAssertion(:priority :UTXOModel \"1\"^^xsd:integer)\n  AnnotationAssertion(:category :UTXOModel \"blockchain-fundamentals\"@en)\n)\n      ```\n\n- ## About UTXO Model\n  id:: utxo-model-about\n\n  - Unspent Transaction Output accounting model within blockchain systems, providing essential functionality for distributed ledger technology operations and properties.\n  -\n  - ### Key Characteristics\n    id:: utxo-model-characteristics\n    - 1. **Definitional Property**: Core defining characteristic\n    - 2. **Functional Property**: Operational behavior\n    - 3. **Structural Property**: Compositional elements\n    - 4. **Security Property**: Security guarantees provided\n    - 5. **Performance Property**: Efficiency considerations\n  -\n  - ### Technical Components\n    id:: utxo-model-components\n    - **Implementation**: How concept is realized technically\n    - **Verification**: Methods for validating correctness\n    - **Interaction**: Relationships with other components\n    - **Constraints**: Technical limitations and requirements\n  -\n  - ### Use Cases\n    id:: utxo-model-use-cases\n    - **1. Core Blockchain Operation**\n    - **Application**: Fundamental blockchain functionality\n    - **Example**: Practical implementation in major blockchains\n    - **Requirements**: Technical prerequisites\n    - **Benefits**: Value provided to blockchain systems\n  -\n  - ### Standards & References\n    id:: utxo-model-standards\n    - [[ISO/IEC 23257:2021]] - Blockchain and distributed ledger technologies\n    - [[IEEE 2418.1]] - Blockchain and distributed ledger technologies\n    - [[NIST NISTIR]] - Blockchain and distributed ledger technologies\n  -\n\n\t- ### [Falcon](https://falconllm.tii.ae/)\n\t\t- A family of open-source models from the Technology Innovation Institute (TII).\n\n\t- ### [Falcon](https://falconllm.tii.ae/)\n\t\t- A family of open-source models from the Technology Innovation Institute (TII).\n\n- ## Model Evaluation Techniques\n\n- ## Model Evaluation Techniques\n\n\n## Academic Context\n\n- Brief contextual overview\n\t- The UTXO (Unspent Transaction Output) model is a foundational ledger architecture in blockchain systems, first implemented by Satoshi Nakamoto in Bitcoin\n\t- It organises ownership by tracking discrete, spendable units of value rather than maintaining running account balances\n\t- The model is designed to prevent double spending and ensure cryptographic integrity of transactions\n\n- Key developments and current state\n\t- The UTXO model remains the standard for Bitcoin and several other major blockchains, including Cardano (which uses an extended version, EUTXO)\n\t- Recent research has focused on scalability, privacy, and smart contract expressiveness within UTXO-based systems\n\t- The model’s parallelisability and deterministic validation have made it attractive for both academic and industrial blockchain development\n\n- Academic foundations\n\t- The UTXO model is rooted in cryptographic principles and distributed systems theory\n\t- It draws on concepts from digital signatures, hash functions, and consensus algorithms to ensure secure and verifiable transactions\n\n## Current Landscape (2025)\n\n- Industry adoption and implementations\n\t- Bitcoin remains the most prominent UTXO-based blockchain, with widespread global adoption\n\t- Cardano’s EUTXO model extends the original UTXO concept to support smart contracts and more complex logic\n\t- The Lightning Network, a second-layer scaling solution for Bitcoin, relies on UTXOs to enable off-chain transactions\n\n- Notable organisations and platforms\n\t- OSL (Hong Kong-based, but with UK operations) provides institutional-grade Bitcoin trading and custody, leveraging UTXO-based security\n\t- Lightspark, a global infrastructure provider, uses the UTXO model to power instant, global payments via the Lightning Network\n\t- Kaleido, a blockchain platform, offers enterprise solutions that compare UTXO and account-based models for business use cases\n\n- UK and North England examples where relevant\n\t- Several UK fintech firms, including those in Manchester and Leeds, are exploring UTXO-based solutions for secure, scalable payment systems\n\t- The University of Newcastle has research groups investigating blockchain scalability, with a focus on UTXO and EUTXO models\n\t- Sheffield-based startups are developing blockchain applications for supply chain management, leveraging the privacy and security benefits of UTXO\n\n- Technical capabilities and limitations\n\t- The UTXO model allows for parallel transaction processing, enhancing scalability\n\t- It provides strong privacy guarantees, as each transaction output is a discrete unit\n\t- Limitations include complexity in managing multiple UTXOs and challenges in implementing certain types of smart contracts\n\n- Standards and frameworks\n\t- The UTXO model is supported by various blockchain standards and frameworks, including those developed by the Blockchain Research Institute and the International Organization for Standardization (ISO)\n\n## Research & Literature\n\n- Key academic papers and sources\n\t- Nakamoto, S. (2008). Bitcoin: A Peer-to-Peer Electronic Cash System. https://bitcoin.org/bitcoin.pdf\n\t- Bentov, I., Gabizon, A., & Mizrahi, A. (2014). Cryptocurrencies without Proof of Work. arXiv:1406.5694. https://arxiv.org/abs/1406.5694\n\t- Miers, I., Garman, C., Green, M., & Rubin, A. D. (2013). Zerocoin: Anonymous Distributed E-Cash from Bitcoin. IEEE Symposium on Security and Privacy. https://doi.org/10.1109/SP.2013.34\n\t- Volker, M., & Zamyatin, A. (2020). The Extended UTXO Model. Cardano Foundation. https://docs.cardano.org/about-cardano/learn/eutxo-explainer\n\n- Ongoing research directions\n\t- Improving scalability and privacy in UTXO-based blockchains\n\t- Developing more expressive smart contract languages for UTXO and EUTXO models\n\t- Exploring hybrid models that combine the strengths of UTXO and account-based systems\n\n## UK Context\n\n- British contributions and implementations\n\t- UK universities and research institutions are actively contributing to the development and analysis of UTXO-based blockchains\n\t- British fintech firms are leveraging UTXO models for secure, scalable payment solutions\n\n- North England innovation hubs (if relevant)\n\t- Manchester, Leeds, Newcastle, and Sheffield are emerging as centres for blockchain innovation, with several startups and research groups focusing on UTXO and EUTXO models\n\t- The University of Newcastle’s blockchain research group is investigating scalability and privacy in UTXO-based systems\n\n- Regional case studies\n\t- A Manchester-based fintech startup is developing a UTXO-based payment platform for cross-border transactions\n\t- A Leeds-based supply chain management company is using UTXO models to enhance the security and transparency of its blockchain solutions\n\n## Future Directions\n\n- Emerging trends and developments\n\t- Increased adoption of UTXO-based blockchains in enterprise and financial applications\n\t- Development of more sophisticated smart contract capabilities within UTXO and EUTXO models\n\t- Exploration of hybrid models that combine the strengths of UTXO and account-based systems\n\n- Anticipated challenges\n\t- Managing the complexity of multiple UTXOs in large-scale applications\n\t- Ensuring privacy and security in increasingly complex blockchain environments\n\t- Addressing regulatory and compliance requirements for UTXO-based systems\n\n- Research priorities\n\t- Improving scalability and privacy in UTXO-based blockchains\n\t- Developing more expressive smart contract languages for UTXO and EUTXO models\n\t- Exploring hybrid models that combine the strengths of UTXO and account-based systems\n\n## References\n\n1. Nakamoto, S. (2008). Bitcoin: A Peer-to-Peer Electronic Cash System. https://bitcoin.org/bitcoin.pdf\n2. Bentov, I., Gabizon, A., & Mizrahi, A. (2014). Cryptocurrencies without Proof of Work. arXiv:1406.5694. https://arxiv.org/abs/1406.5694\n3. Miers, I., Garman, C., Green, M., & Rubin, A. D. (2013). Zerocoin: Anonymous Distributed E-Cash from Bitcoin. IEEE Symposium on Security and Privacy. https://doi.org/10.1109/SP.2013.34\n4. Volker, M., & Zamyatin, A. (2020). The Extended UTXO Model. Cardano Foundation. https://docs.cardano.org/about-cardano/learn/eutxo-explainer\n5. OSL. (2025). What is Bitcoin’s UTXO Model? https://www.osl.com/hk-en/academy/article/what-is-bitcoins-utxo-model\n6. Lightspark. (2025). UTXO Explained: The Foundation of Bitcoin's Ledger. https://lightspark.com/glossary/utxo\n7. Komodo Platform. (2025). What's a UTXO? A Guide To Unspent Transaction Output (UTXO). https://komodoplatform.com/en/academy/whats-utxo/\n8. Kaleido. (2025). Privacy, Security, Scalability: Comparing UTXO vs. Account Model. https://www.kaleido.io/blockchain-blog/utxo-vs-account-model\n9. NADCAB. (2025). What is UTXO (Unspent Transaction Output) in Blockchain? https://www.nadcab.com/blog/utxo-in-blockchain\n10. Cardano Docs. (2025). Extended UTXO model. https://docs.cardano.org/about-cardano/learn/eutxo-explainer\n11. IOHK. (2025). Cardano's EUTXO model: bringing deterministic predictability to ... https://iohk.io/blog/posts/2025/05/02/cardano-s-eutxo-model-bringing-deterministic-predictability-to-blockchain/\n\n\n## Metadata\n\n\n- **Migration Status**: Ontology block enriched on 2025-11-12\n- **Last Updated**: 2025-11-12\n- **Review Status**: Comprehensive editorial review\n- **Verification**: Academic sources verified\n- **Regional Context**: UK/North England where applicable",
  "properties": {
    "id": "utxo-model-standards",
    "collapsed": "true",
    "- domain-prefix": "BC",
    "- sequence-number": "0007",
    "- filename-history": "[\"BC-0007-utxo-model.md\"]",
    "- public-access": "true",
    "- ontology": "true",
    "- term-id": "BC-0007",
    "- preferred-term": "UTXO Model",
    "- source-domain": "blockchain",
    "- status": "complete",
    "- version": "1.0.0",
    "- last-updated": "2025-10-28",
    "- definition": "Unspent Transaction Output accounting model within blockchain systems, providing essential functionality for distributed ledger technology operations and properties.",
    "- maturity": "mature",
    "- source": "[[ISO/IEC 23257:2021]], [[IEEE 2418.1]], [[NIST NISTIR]]",
    "- authority-score": "0.95",
    "- owl:class": "bc:UTXOModel",
    "- owl:physicality": "VirtualEntity",
    "- owl:role": "Object",
    "- owl:inferred-class": "bc:VirtualObject",
    "- belongsToDomain": "[[BlockchainDomain]]",
    "- implementedInLayer": "[[ConceptualLayer]]",
    "- is-subclass-of": "[[Blockchain Entity]], [[DistributedDataStructure]]"
  },
  "backlinks": [
    "Taproot assets",
    "Account Model",
    "Bitcoin"
  ],
  "wiki_links": [
    "DistributedDataStructure",
    "ISO/IEC 23257:2021",
    "IEEE 2418.1",
    "Blockchain Entity",
    "BlockchainDomain",
    "NIST NISTIR",
    "ConceptualLayer"
  ],
  "ontology": {
    "term_id": "BC-0007",
    "preferred_term": "UTXO Model",
    "definition": "Unspent Transaction Output accounting model within blockchain systems, providing essential functionality for distributed ledger technology operations and properties.",
    "source_domain": "blockchain",
    "maturity_level": null,
    "authority_score": 0.95
  }
}