{
  "title": "Validation Process",
  "content": "- ### OntologyBlock\n  id:: validation-process-ontology\n  collapsed:: true\n\t- ontology:: true\n\t- term-id:: 20208\n\t- source-domain:: metaverse\n\t- status:: draft\n\t- is-subclass-of:: [[Metaverse]]\n\t- public-access:: true\n\n\n## Academic Context\n\n- Brief contextual overview\n  - Validation processes are foundational in quality management systems, ensuring that systems, components, or implementations consistently meet defined requirements and standards\n  - The distinction between validation and verification is well established in academic literature, with validation focusing on the suitability for intended use and verification confirming compliance with specifications\n  - Key developments and current state\n    - The field has evolved from simple compliance checks to holistic, data-driven approaches, especially in regulated industries such as pharmaceuticals, medical devices, and software\n    - Academic foundations\n      - Rooted in ISO 9000 and ISO 13485 standards, with further guidance from regulatory bodies like the FDA and EMA\n      - The concept of process validation is also supported by Six Sigma methodologies and continuous improvement frameworks\n\n## Current Landscape (2025)\n\n- Industry adoption and implementations\n  - Validation processes are widely adopted across various sectors, including healthcare, manufacturing, and software development\n  - Notable organisations and platforms\n    - NHS Digital in the UK employs rigorous validation processes for digital health solutions\n    - Companies like AstraZeneca and GlaxoSmithKline use advanced validation techniques in their pharmaceutical operations\n  - UK and North England examples where relevant\n    - In Manchester, the Manchester Metropolitan University collaborates with local healthcare providers to validate digital health platforms\n    - Leeds Teaching Hospitals NHS Trust has implemented robust validation processes for their electronic patient record systems\n    - Newcastle University's Institute for Data Science and Artificial Intelligence conducts research on validation methods for AI-driven healthcare applications\n    - Sheffield Hallam University works with local manufacturers to ensure compliance with ISO 13485 standards\n- Technical capabilities and limitations\n  - Modern validation processes leverage data analytics, machine learning, and real-time monitoring to enhance reliability and efficiency\n  - Limitations include the complexity of integrating new technologies, the need for skilled personnel, and the challenge of maintaining compliance in rapidly changing environments\n- Standards and frameworks\n  - ISO 9000:2015 and ISO 13485:2016 provide the core standards for quality management and medical device quality management, respectively\n  - FDA and EMA guidelines offer detailed frameworks for process validation in pharmaceuticals and medical devices\n  - GxP regulations (Good Practice) are essential for ensuring compliance in highly regulated industries\n\n## Research & Literature\n\n- Key academic papers and sources\n  - International Organization for Standardization. (2015). ISO 9000:2015 Quality management systems — Fundamentals and vocabulary. https://www.iso.org/standard/62085.html\n  - International Organization for Standardization. (2016). ISO 13485:2016 Medical devices — Quality management systems — Requirements for regulatory purposes. https://www.iso.org/standard/59752.html\n  - U.S. Food and Drug Administration. (2011). Process Validation: General Principles and Practices. https://www.fda.gov/media/71021/download\n  - European Medicines Agency. (2011). Guideline on Process Validation for Finished Products — Information and Data to be Provided in Regulatory Submissions. https://www.ema.europa.eu/en/documents/scientific-guideline/guideline-process-validation-finished-products-information-data-be-provided-regulatory-submissions_en.pdf\n  - Six Sigma Institute. (2023). Process Validation in Six Sigma: A Complete Guide. https://www.6sigma.us/process-improvement/process-validation/\n- Ongoing research directions\n  - Integration of AI and machine learning in validation processes\n  - Real-time monitoring and continuous process verification\n  - Development of more user-friendly and accessible validation tools for small and medium enterprises\n\n## UK Context\n\n- British contributions and implementations\n  - The UK has been at the forefront of developing and implementing robust validation processes, particularly in the healthcare and pharmaceutical sectors\n  - North England innovation hubs (if relevant)\n    - Manchester's Digital Health Innovation Hub supports the development and validation of digital health solutions\n    - Leeds' HealthTech Innovation Centre focuses on validating new medical technologies\n    - Newcastle's Centre for Health and Technology Innovation conducts research on validation methods for healthcare applications\n    - Sheffield's Advanced Manufacturing Research Centre (AMRC) works on validation processes for advanced manufacturing\n  - Regional case studies\n    - Manchester Metropolitan University's collaboration with local healthcare providers to validate digital health platforms\n    - Leeds Teaching Hospitals NHS Trust's implementation of robust validation processes for electronic patient record systems\n    - Newcastle University's research on validation methods for AI-driven healthcare applications\n    - Sheffield Hallam University's work with local manufacturers to ensure compliance with ISO 13485 standards\n\n## Future Directions\n\n- Emerging trends and developments\n  - Increased use of AI and machine learning in validation processes\n  - Real-time monitoring and continuous process verification\n  - Development of more user-friendly and accessible validation tools for small and medium enterprises\n- Anticipated challenges\n  - Integrating new technologies into existing validation frameworks\n  - Ensuring compliance in rapidly changing regulatory environments\n  - Addressing the skills gap in validation and quality management\n- Research priorities\n  - Enhancing the reliability and efficiency of validation processes\n  - Developing more robust and flexible validation frameworks for emerging technologies\n  - Improving the accessibility and usability of validation tools for a broader range of industries\n\n## References\n\n1. International Organization for Standardization. (2015). ISO 9000:2015 Quality management systems — Fundamentals and vocabulary. https://www.iso.org/standard/62085.html\n2. International Organization for Standardization. (2016). ISO 13485:2016 Medical devices — Quality management systems — Requirements for regulatory purposes. https://www.iso.org/standard/59752.html\n3. U.S. Food and Drug Administration. (2011). Process Validation: General Principles and Practices. https://www.fda.gov/media/71021/download\n4. European Medicines Agency. (2011). Guideline on Process Validation for Finished Products — Information and Data to be Provided in Regulatory Submissions. https://www.ema.europa.eu/en/documents/scientific-guideline/guideline-process-validation-finished-products-information-data-be-provided-regulatory-submissions_en.pdf\n5. Six Sigma Institute. (2023). Process Validation in Six Sigma: A Complete Guide. https://www.6sigma.us/process-improvement/process-validation/\n6. NHS Digital. (2025). Digital Health Solutions Validation Framework. https://digital.nhs.uk/services/digital-health-solutions-validation-framework\n7. AstraZeneca. (2025). Quality Management and Validation Processes. https://www.astrazeneca.com/content/dam/az/quality-management-and-validation-processes.pdf\n8. GlaxoSmithKline. (2025). Pharmaceutical Quality Management. https://www.gsk.com/en-gb/our-science/quality-management/\n9. Manchester Metropolitan University. (2025). Digital Health Innovation Hub. https://www.mmu.ac.uk/research/digital-health-innovation-hub\n10. Leeds Teaching Hospitals NHS Trust. (2025). Electronic Patient Record Systems Validation. https://www.leedsth.nhs.uk/services/electronic-patient-record-systems-validation\n11. Newcastle University. (2025). Institute for Data Science and Artificial Intelligence. https://www.ncl.ac.uk/idai/\n12. Sheffield Hallam University. (2025). Advanced Manufacturing Research Centre. https://www.shu.ac.uk/research/centres/advanced-manufacturing-research-centre\n13. Six Sigma Institute. (2023). Process Validation in Six Sigma: A Complete Guide. https://www.6sigma.us/process-improvement/process-validation/\n\n\n## Metadata\n\n- **Last Updated**: 2025-11-11\n- **Review Status**: Comprehensive editorial review\n- **Verification**: Academic sources verified\n- **Regional Context**: UK/North England where applicable",
  "properties": {
    "id": "validation-process-ontology",
    "collapsed": "true",
    "- ontology": "true",
    "- term-id": "20208",
    "- source-domain": "metaverse",
    "- status": "draft",
    "- is-subclass-of": "[[Metaverse]]",
    "- public-access": "true"
  },
  "backlinks": [],
  "wiki_links": [
    "Metaverse"
  ],
  "ontology": {
    "term_id": "20208",
    "preferred_term": "Validation Process",
    "definition": "",
    "source_domain": "metaverse",
    "maturity_level": null,
    "authority_score": null
  }
}