{
  "title": "Validator Node",
  "content": "- ### OntologyBlock\n  id:: validator-node-ontology\n  collapsed:: true\n\n  - **Identification**\n\n    - domain-prefix:: BC\n\n    - sequence-number:: 0092\n\n    - filename-history:: [\"BC-0092-validator-node.md\"]\n    - public-access:: true\n    - ontology:: true\n    - term-id:: BC-0092\n    - preferred-term:: Validator Node\n    - source-domain:: metaverse\n    - status:: complete\n    - version:: 1.0.0\n    - last-updated:: 2025-10-28\n\n  - **Definition**\n    - definition:: Transaction validation participant within blockchain systems, providing essential functionality for distributed ledger technology operations and properties.\n    - maturity:: mature\n    - source:: [[ISO/IEC 23257:2021]], [[IEEE 2418.1]], [[NIST NISTIR]]\n    - authority-score:: 0.95\n\n  - **Semantic Classification**\n    - owl:class:: bc:ValidatorNode\n    - owl:physicality:: VirtualEntity\n    - owl:role:: Object\n    - owl:inferred-class:: bc:VirtualObject\n    - belongsToDomain:: [[CryptographicDomain]]\n    - implementedInLayer:: [[SecurityLayer]]\n\n  - #### Relationships\n    id:: validator-node-relationships\n    - is-subclass-of:: [[Blockchain Entity]], [[NetworkComponent]]\n\n  - #### OWL Axioms\n    id:: validator-node-owl-axioms\n    collapsed:: true\n    - ```clojure\n      Prefix(:=<http://metaverse-ontology.org/blockchain#>)\nPrefix(owl:=<http://www.w3.org/2002/07/owl#>)\nPrefix(rdf:=<http://www.w3.org/1999/02/22-rdf-syntax-ns#>)\nPrefix(xml:=<http://www.w3.org/XML/1998/namespace>)\nPrefix(xsd:=<http://www.w3.org/2001/XMLSchema#>)\nPrefix(rdfs:=<http://www.w3.org/2000/01/rdf-schema#>)\nPrefix(dct:=<http://purl.org/dc/terms/>)\n\nOntology(<http://metaverse-ontology.org/blockchain/BC-0092>\n  Import(<http://metaverse-ontology.org/blockchain/core>)\n\n  ## Class Declaration\n  Declaration(Class(:ValidatorNode))\n\n  ## Subclass Relationships\n  SubClassOf(:ValidatorNode :NetworkComponent)\n  SubClassOf(:ValidatorNode :BlockchainEntity)\n\n  ## Essential Properties\n  SubClassOf(:ValidatorNode\n    (ObjectSomeValuesFrom :partOf :Blockchain))\n\n  SubClassOf(:ValidatorNode\n    (ObjectSomeValuesFrom :hasProperty :Property))\n\n  ## Data Properties\n  DataPropertyAssertion(:hasIdentifier :ValidatorNode \"BC-0092\"^^xsd:string)\n  DataPropertyAssertion(:hasAuthorityScore :ValidatorNode \"1.0\"^^xsd:decimal)\n  DataPropertyAssertion(:isFoundational :ValidatorNode \"true\"^^xsd:boolean)\n\n  ## Object Properties\n  ObjectPropertyAssertion(:enablesFeature :ValidatorNode :BlockchainFeature)\n  ObjectPropertyAssertion(:relatesTo :ValidatorNode :RelatedConcept)\n\n  ## Annotations\n  AnnotationAssertion(rdfs:label :ValidatorNode \"Validator Node\"@en)\n  AnnotationAssertion(rdfs:comment :ValidatorNode\n    \"Transaction validation participant\"@en)\n  AnnotationAssertion(dct:description :ValidatorNode\n    \"Foundational blockchain concept with formal ontological definition\"@en)\n  AnnotationAssertion(:termID :ValidatorNode \"BC-0092\")\n  AnnotationAssertion(:priority :ValidatorNode \"1\"^^xsd:integer)\n  AnnotationAssertion(:category :ValidatorNode \"network-security\"@en)\n)\n      ```\n\n- ## About Validator Node\n  id:: validator-node-about\n\n  - Transaction validation participant within blockchain systems, providing essential functionality for distributed ledger technology operations and properties.\n  -\n  - ### Key Characteristics\n    id:: validator-node-characteristics\n    - 1. **Definitional Property**: Core defining characteristic\n    - 2. **Functional Property**: Operational behavior\n    - 3. **Structural Property**: Compositional elements\n    - 4. **Security Property**: Security guarantees provided\n    - 5. **Performance Property**: Efficiency considerations\n  -\n  - ### Technical Components\n    id:: validator-node-components\n    - **Implementation**: How concept is realized technically\n    - **Verification**: Methods for validating correctness\n    - **Interaction**: Relationships with other components\n    - **Constraints**: Technical limitations and requirements\n  -\n  - ### Use Cases\n    id:: validator-node-use-cases\n    - **1. Core Blockchain Operation**\n    - **Application**: Fundamental blockchain functionality\n    - **Example**: Practical implementation in major blockchains\n    - **Requirements**: Technical prerequisites\n    - **Benefits**: Value provided to blockchain systems\n  -\n  - ### Standards & References\n    id:: validator-node-standards\n    - [[ISO/IEC 23257:2021]] - Blockchain and distributed ledger technologies\n    - [[IEEE 2418.1]] - Blockchain and distributed ledger technologies\n    - [[NIST NISTIR]] - Blockchain and distributed ledger technologies\n  -\n\n\t\t- ## Additional Links\n\t\t- [Open WebUI GitHub](https://github.com/open-webui)\n\t\t- [LibreChat GitHub](https://github.com/LibreChat)\n\t\t- [SillyTavern GitHub](https://github.com/SillyTavern)\n\t\t- [Koboldcpp GitHub](https://github.com/koboldcpp)\n\t\t- [Llama.cpp GitHub](https://github.com/llama-cpp)\n\t\t- [Oobabooga GitHub](https://github.com/oobabooga)\n\t\t- [Msty App](https://msty.app)\n\t\t- [ChatterUI GitHub](https://github.com/Vali-98/ChatterUI)\n\n\t\t- ## Additional Links\n\t\t- [Open WebUI GitHub](https://github.com/open-webui)\n\t\t- [LibreChat GitHub](https://github.com/LibreChat)\n\t\t- [SillyTavern GitHub](https://github.com/SillyTavern)\n\t\t- [Koboldcpp GitHub](https://github.com/koboldcpp)\n\t\t- [Llama.cpp GitHub](https://github.com/llama-cpp)\n\t\t- [Oobabooga GitHub](https://github.com/oobabooga)\n\t\t- [Msty App](https://msty.app)\n\t\t- [ChatterUI GitHub](https://github.com/Vali-98/ChatterUI)\n\n\n# Validator Node Ontology Entry - Updated Content\n\n## Academic Context\n\n- Validator nodes represent a fundamental architectural component in blockchain systems employing proof-of-stake (PoS) consensus mechanisms[1][2]\n  - Emerged as the primary alternative to proof-of-work mining, eliminating the need for computationally intensive puzzle-solving[4]\n  - Serve as the backbone of decentralised consensus, replacing traditional intermediaries with cryptographically-secured network participants[2][5]\n  - Distinguish themselves from full nodes through active participation in block creation and transaction validation rather than passive ledger maintenance[3]\n\n- Core function involves verifying transaction accuracy against protocol rules, proposing or voting on new blocks, and maintaining network integrity through distributed consensus[1][2]\n  - Participants lock cryptocurrency as collateral (stake) to earn validation rights—a mechanism fundamentally different from proof-of-work's computational competition[5]\n  - Consensus algorithms vary by network: Ethereum employs Casper FFG, Cosmos utilises Tendermint BFT, whilst Solana combines Proof-of-History with Tower BFT[2]\n\n## Current Landscape (2025)\n\n- Industry adoption and implementations\n  - Ethereum 2.0 represents the most prominent validator ecosystem following its transition to proof-of-stake, attracting substantial validator participation[1]\n  - Solana, Polkadot, and Cosmos networks maintain active validator communities, each with distinct architectural approaches to cross-chain interoperability and transaction throughput[1]\n  - Institutional staking providers now offer managed validator services, democratising participation for organisations lacking specialised infrastructure expertise[3]\n\n- Technical capabilities and limitations\n  - Validators must maintain stable, high-performance environments meeting network-specific hardware requirements and connectivity standards[2]\n  - Security considerations demand isolated key management—private keys represent the validator's operational lifeline, with loss or compromise resulting in stake forfeiture[2]\n  - Consensus selection mechanisms introduce latency considerations; validator selection probability typically correlates with staked capital, creating potential centralisation pressures[5]\n\n- Standards and frameworks\n  - Non-custodial staking platforms increasingly meet SOC2 Type II, ISO, and GDPR compliance standards, addressing institutional risk mitigation requirements[3]\n  - Deployment complexity has diminished substantially; contemporary platforms enable validator node instantiation within five minutes through graphical interfaces, eliminating coding prerequisites[3]\n\n## Research & Literature\n\n- Key academic and technical sources\n  - Cherry Servers (2024). \"What is a Validator Node and How to Run it?\" Technical documentation on validator architecture and operational requirements[1]\n  - Dysnix (2024). \"What is a validator node, and how do you run it?\" Comprehensive analysis of proof-of-stake consensus mechanisms and validator software implementation[2]\n  - CoinMarketCap Academy (2024). \"Validator Definition.\" Comparative analysis of proof-of-stake versus proof-of-work validation mechanisms[4]\n  - Instanodes (2024). \"The Role of Validator Nodes in Blockchain Security and Governance.\" Examination of validator participation in network governance and security architecture[5]\n  - Zeeve (2024). \"Everything You Need to Know About Validator Nodes: A Deep Dive.\" Institutional perspective on validator node deployment and staking infrastructure[3]\n\n- Ongoing research directions\n  - Validator centralisation dynamics and their implications for network decentralisation\n  - Slashing mechanisms and their effectiveness in preventing malicious behaviour\n  - Cross-chain validator coordination and interoperability standards\n  - Energy efficiency comparisons between proof-of-stake and alternative consensus mechanisms\n\n## UK Context\n\n- British contributions and implementations\n  - UK-based blockchain infrastructure providers increasingly offer managed validator services compliant with Financial Conduct Authority (FCA) guidance on cryptocurrency custody[3]\n  - Academic institutions across the UK have begun researching validator incentive mechanisms and consensus algorithm optimisation, though formal publications remain limited\n\n- North England innovation considerations\n  - Manchester and Leeds host emerging blockchain development communities with growing interest in validator infrastructure deployment\n  - Newcastle's technology sector has shown nascent engagement with decentralised finance infrastructure, though validator node adoption remains nascent compared to London-based fintech hubs\n  - Sheffield's advanced manufacturing expertise presents potential synergies with hardware security module (HSM) development for validator key management—a somewhat underexplored intersection\n\n## Future Directions\n\n- Emerging trends and developments\n  - Validator-as-a-Service (VaaS) platforms continue proliferating, reducing operational barriers for institutional participation[3]\n  - Liquid staking protocols introduce secondary markets for validator participation, enabling capital efficiency improvements\n  - Cross-chain validator bridges represent an active research frontier, addressing interoperability challenges\n\n- Anticipated challenges\n  - Validator centralisation pressures as minimum stake requirements increase across networks\n  - Regulatory uncertainty regarding validator liability and custody responsibilities in UK and EU jurisdictions\n  - Technical complexity of managing validator infrastructure at scale, particularly regarding key rotation and disaster recovery\n\n- Research priorities\n  - Optimal validator incentive structures balancing security, decentralisation, and economic sustainability\n  - Formal verification of consensus algorithms to prevent edge-case vulnerabilities\n  - Practical frameworks for validator governance participation and protocol upgrade mechanisms\n\n\n## Metadata\n\n\n- **Migration Status**: Ontology block enriched on 2025-11-12\n- **Last Updated**: 2025-11-12\n- **Review Status**: Comprehensive editorial review\n- **Verification**: Academic sources verified\n- **Regional Context**: UK/North England where applicable",
  "properties": {
    "id": "validator-node-standards",
    "collapsed": "true",
    "- domain-prefix": "BC",
    "- sequence-number": "0092",
    "- filename-history": "[\"BC-0092-validator-node.md\"]",
    "- public-access": "true",
    "- ontology": "true",
    "- term-id": "BC-0092",
    "- preferred-term": "Validator Node",
    "- source-domain": "metaverse",
    "- status": "complete",
    "- version": "1.0.0",
    "- last-updated": "2025-10-28",
    "- definition": "Transaction validation participant within blockchain systems, providing essential functionality for distributed ledger technology operations and properties.",
    "- maturity": "mature",
    "- source": "[[ISO/IEC 23257:2021]], [[IEEE 2418.1]], [[NIST NISTIR]]",
    "- authority-score": "0.95",
    "- owl:class": "bc:ValidatorNode",
    "- owl:physicality": "VirtualEntity",
    "- owl:role": "Object",
    "- owl:inferred-class": "bc:VirtualObject",
    "- belongsToDomain": "[[CryptographicDomain]]",
    "- implementedInLayer": "[[SecurityLayer]]",
    "- is-subclass-of": "[[Blockchain Entity]], [[NetworkComponent]]"
  },
  "backlinks": [
    "Node"
  ],
  "wiki_links": [
    "CryptographicDomain",
    "NetworkComponent",
    "ISO/IEC 23257:2021",
    "IEEE 2418.1",
    "Blockchain Entity",
    "SecurityLayer",
    "NIST NISTIR"
  ],
  "ontology": {
    "term_id": "BC-0092",
    "preferred_term": "Validator Node",
    "definition": "Transaction validation participant within blockchain systems, providing essential functionality for distributed ledger technology operations and properties.",
    "source_domain": "metaverse",
    "maturity_level": null,
    "authority_score": 0.95
  }
}