{
  "title": "Value Transfer",
  "content": "- ### OntologyBlock\n  id:: value-transfer-ontology\n  collapsed:: true\n\n  - **Identification**\n    - public-access:: true\n    - ontology:: true\n    - term-id:: DT-0001\n    - preferred-term:: Value Transfer\n    - source-domain:: metaverse\n    - status:: complete\n    - version:: 1.0.0\n    - last-updated:: 2025-11-15\n    - qualityScore:: 0.94\n\n  - **Definition**\n    - definition:: The mechanism and process by which economic value, rights, or utility are exchanged between parties across physical, digital, and virtual domains, encompassing monetary systems, token-based systems, resource allocation, and rights transfer protocols.\n    - maturity:: mature\n    - source:: [[ISO/IEC 23257:2021]], [[BIS Innovation Hub]], [[W3C Web Payments]]\n    - authority-score:: 1.0\n\n  - **Semantic Classification**\n    - owl:class:: dt:ValueTransfer\n    - owl:physicality:: ConceptualEntity\n    - owl:role:: Process\n    - owl:inferred-class:: dt:ConceptualProcess\n    - is-subclass-of:: [[Metaverse]]\n    - belongsToDomain:: [[EconomicSystemDomain]], [[BlockchainDomain]], [[MetaverseDomain]], [[AI-GroundedDomain]], [[RoboticsDomain]]\n\n  - #### OWL Restrictions\n    - implemented-by some PaymentSystem\n    - implemented-by some SmartContract\n    - requires some ValueRepresentation\n    - enables some EconomicExchange\n    - enables some Commerce\n    - has-part some RightsTransfer\n    - has-part some ResourceAllocation\n    - implemented-by some ExchangeProtocol\n    - enables some Trade\n    - implemented-by some Transaction\n    - enables some Payment\n    - is-enabled-by some Stablecoin\n    - has-part some DigitalCurrency\n    - has-part some Money\n    - enables some Settlement\n    - has-part some Token\n    - has-part some BarterSystem\n    - requires some TransferProtocol\n    - is-enabled-by some DigitalAsset\n    - requires some TrustMechanism\n\n  - #### CrossDomainBridges\n    - bridges-to:: [[SmartContract]] via implemented-by\n    - bridges-to:: [[Token]] via has-part\n    - bridges-to:: [[BarterSystem]] via has-part\n    - bridges-to:: [[Transaction]] via implemented-by\n    - bridges-to:: [[DigitalCurrency]] via has-part\n    - bridges-from:: [[Bitcoin]] via bridges-to\n\n  -",
  "properties": {
    "id": "value-transfer-ontology",
    "collapsed": "true",
    "- public-access": "true",
    "- ontology": "true",
    "- term-id": "DT-0001",
    "- preferred-term": "Value Transfer",
    "- source-domain": "metaverse",
    "- status": "complete",
    "- version": "1.0.0",
    "- last-updated": "2025-11-15",
    "- qualityScore": "0.94",
    "- definition": "The mechanism and process by which economic value, rights, or utility are exchanged between parties across physical, digital, and virtual domains, encompassing monetary systems, token-based systems, resource allocation, and rights transfer protocols.",
    "- maturity": "mature",
    "- source": "[[ISO/IEC 23257:2021]], [[BIS Innovation Hub]], [[W3C Web Payments]]",
    "- authority-score": "1.0",
    "- owl:class": "dt:ValueTransfer",
    "- owl:physicality": "ConceptualEntity",
    "- owl:role": "Process",
    "- owl:inferred-class": "dt:ConceptualProcess",
    "- is-subclass-of": "[[Metaverse]]",
    "- belongsToDomain": "[[EconomicSystemDomain]], [[BlockchainDomain]], [[MetaverseDomain]], [[AI-GroundedDomain]], [[RoboticsDomain]]",
    "- bridges-to": "[[DigitalCurrency]] via has-part",
    "- bridges-from": "[[Bitcoin]] via bridges-to"
  },
  "backlinks": [
    "Stablecoin",
    "Bitcoin"
  ],
  "wiki_links": [
    "Token",
    "RoboticsDomain",
    "W3C Web Payments",
    "BlockchainDomain",
    "SmartContract",
    "AI-GroundedDomain",
    "BIS Innovation Hub",
    "ISO/IEC 23257:2021",
    "Transaction",
    "Metaverse",
    "DigitalCurrency",
    "EconomicSystemDomain",
    "BarterSystem",
    "Bitcoin",
    "MetaverseDomain"
  ],
  "ontology": {
    "term_id": "DT-0001",
    "preferred_term": "Value Transfer",
    "definition": "The mechanism and process by which economic value, rights, or utility are exchanged between parties across physical, digital, and virtual domains, encompassing monetary systems, token-based systems, resource allocation, and rights transfer protocols.",
    "source_domain": "metaverse",
    "maturity_level": null,
    "authority_score": 1.0
  }
}