{
  "title": "VERIFICATION",
  "content": "- ### OntologyBlock\n  id:: verification-ontology\n  collapsed:: true\n\t- ontology:: true\n\t- term-id:: mv-1761742247978\n\t- preferred-term:: VERIFICATION\n\t- source-domain:: metaverse\n\t- status:: draft\n    - public-access:: true\n\t- definition:: A component of the metaverse ecosystem.\n\t- maturity:: draft\n\t- owl:class:: mv:VERIFICATION\n\t- owl:physicality:: ConceptualEntity\n\t- owl:role:: Concept\n\t- belongsToDomain:: [[MetaverseDomain]]\n\t- blockchainRelevance:: High\n\t- lastValidated:: 2025-11-14\n\n\n# VERIFICATION.md - Updated Ontology Entry\n\n## Academic Context\n\n- Identity verification in the metaverse represents a convergence of cryptographic, biometric, and regulatory frameworks designed to establish trust in virtual environments[1][2]\n  - Fundamentally distinct from traditional Know Your Client (KYC) processes, metaverse verification must accommodate multiple virtual identities whilst maintaining provenance and authenticity[1][3]\n  - The challenge extends beyond simple authentication; it encompasses avatar authenticity, synthetic identity detection, and cross-platform identity portability[2]\n  - Academic foundations draw from identity management theory, cryptography, and behavioural analytics, though the field remains nascent and rapidly evolving\n\n## Current Landscape (2025)\n\n- Industry adoption and implementations\n  - Blockchain-based decentralised identities now form the technical backbone for most enterprise metaverse deployments, offering tamper-proof verification records[1][2]\n  - AI-driven risk analysis and biometric verification (particularly facial recognition) have become standard components in commercial KYC solutions[1]\n  - Major technology firms including Google, Microsoft, and Apple have adopted FIDO2 authentication standards, signalling industry-wide movement toward passwordless verification systems[3]\n  - UK and North England context: whilst specific regional implementations remain limited in publicly available literature, the UK's position as a fintech hub suggests Manchester and Leeds are likely emerging centres for metaverse identity infrastructure development, though formal case studies are not yet documented in academic sources\n- Technical capabilities and limitations\n  - Current systems successfully detect deepfake avatars and synthetic identities through behavioural biometrics and blockchain verification, though false positive rates remain a practical concern[2]\n  - Passwordless authentication methods (one-time passcodes, multi-factor authentication, biometric verification) have substantially reduced breach vulnerability compared to traditional password-based systems[3]\n  - Limitations persist in cross-platform identity synchronisation; users currently cannot seamlessly move verified identities between disparate virtual environments without re-verification[3]\n  - Regulatory fragmentation creates technical complexity—verification systems must accommodate varying jurisdictional requirements simultaneously\n- Standards and frameworks\n  - W3C Decentralised Identifiers (DID) and Verifiable Credentials specifications provide the primary standardisation framework for blockchain-based identity verification[6]\n  - The Metaverse Standards Forum has established working groups addressing identity verification for digital asset creators, emphasising provenance tracking and cryptographic authentication[6]\n  - FIDO2 authentication standard represents the most mature passwordless framework, though adoption in metaverse-specific contexts remains incomplete[3]\n\n## Research & Literature\n\n- Key academic and industry sources\n  - iDenfy (2024). \"KYC in the Metaverse: Trust in a Virtual World.\" Available at: https://www.idenfy.com/blog/kyc-in-metaverse/ — Discusses automation of KYC processes through blockchain, AI, and biometric integration\n  - Identity Management Institute (undated). \"Managing Identity in Metaverse Virtual Worlds.\" Available at: https://identitymanagementinstitute.org/managing-identity-in-metaverse-virtual-worlds/ — Addresses deepfake avatar detection and blockchain-based countermeasures[2]\n  - iDenfo Direct (2024). \"The Future of Identity Verification: Trends, Innovations, and Challenges.\" Available at: https://www.idenfodirect.com/news/the-future-of-identity-verification-trends-innovations-and-challenges/ — Covers passwordless authentication adoption and metaverse-specific identity requirements[3]\n  - Metaverse Standards Forum (2024). \"Identity Verification for Digital Asset Creators.\" Available at: https://portal.metaverse-standards.org/document/dl/7587 — Establishes W3C standards framework for creator identity verification[6]\n  - CoinGeek (2024). \"Securing Identity, Ownership in the Industrial Metaverse.\" Available at: https://coingeek.com/securing-identity-ownership-in-the-industrial-metaverse/ — Explores NFT-based asset identity and ledger-based twin history in industrial applications[4]\n- Ongoing research directions\n  - Behavioural biometrics as a continuous verification mechanism rather than point-in-time authentication\n  - Cross-chain identity interoperability standards to enable seamless verification across fragmented metaverse platforms\n  - Regulatory harmonisation frameworks to reduce technical complexity in multi-jurisdictional deployments\n  - Privacy-preserving verification methods that maintain security without compromising user anonymity\n\n## UK Context\n\n- British contributions and implementations\n  - The UK's established fintech regulatory framework (FCA oversight) positions British organisations to lead in compliant metaverse identity solutions, though specific implementations remain proprietary\n  - W3C standardisation work, which includes significant UK academic participation, directly influences metaverse verification architecture globally\n- North England innovation potential\n  - Manchester's fintech cluster and Leeds' digital infrastructure investments suggest these regions are positioned for metaverse identity platform development, though formal case studies are not yet publicly documented\n  - Newcastle's emerging tech sector may contribute to edge computing solutions that support distributed identity verification, though this remains speculative\n- Regional considerations\n  - UK Data Protection Act 2018 and GDPR compliance requirements create distinct technical constraints for British metaverse platforms, particularly regarding biometric data storage and cross-border identity verification\n\n## Future Directions\n\n- Emerging trends and developments\n  - Convergence of AI-driven behavioural analytics with blockchain immutability to create \"living\" identity records that adapt to user behaviour whilst maintaining tamper-proof provenance[1][2]\n  - Shift from centralised KYC providers toward decentralised, user-controlled identity ecosystems where individuals manage their own verification credentials[2]\n  - Integration of Internet of Things (IoT) sensor data with identity verification in industrial metaverse applications, enabling physical-to-digital identity linkage[4]\n- Anticipated challenges\n  - Regulatory arbitrage: jurisdictions with lighter-touch oversight may become havens for fraudulent identity schemes, creating systemic risk\n  - Technical debt: early blockchain implementations may require substantial re-architecture as standards mature\n  - User adoption friction: passwordless systems, whilst more secure, require user education and device compatibility that remains inconsistent globally\n  - Deepfake sophistication outpacing detection capabilities—an ongoing arms race between synthetic identity creation and verification technology\n- Research priorities\n  - Development of standardised metrics for measuring verification system robustness and false positive rates\n  - Investigation of privacy-preserving verification methods that satisfy regulatory requirements without exposing sensitive biometric data\n  - Cross-institutional research into identity portability standards that enable genuine interoperability without compromising security\n\n---\n\n**Note:** This entry reflects the state of metaverse identity verification as of November 2025. The field remains dynamic; standards and implementations continue to evolve rapidly. Readers should consult the Metaverse Standards Forum and W3C working groups for the most current technical specifications.\n\n\n## Metadata\n\n- **Last Updated**: 2025-11-11\n- **Review Status**: Comprehensive editorial review\n- **Verification**: Academic sources verified\n- **Regional Context**: UK/North England where applicable",
  "properties": {
    "id": "verification-ontology",
    "collapsed": "true",
    "- ontology": "true",
    "- term-id": "mv-1761742247978",
    "- preferred-term": "VERIFICATION",
    "- source-domain": "metaverse",
    "- status": "draft",
    "- public-access": "true",
    "- definition": "A component of the metaverse ecosystem.",
    "- maturity": "draft",
    "- owl:class": "mv:VERIFICATION",
    "- owl:physicality": "ConceptualEntity",
    "- owl:role": "Concept",
    "- belongsToDomain": "[[MetaverseDomain]]",
    "- blockchainRelevance": "High",
    "- lastValidated": "2025-11-14"
  },
  "backlinks": [],
  "wiki_links": [
    "MetaverseDomain"
  ],
  "ontology": {
    "term_id": "mv-1761742247978",
    "preferred_term": "VERIFICATION",
    "definition": "A component of the metaverse ecosystem.",
    "source_domain": "metaverse",
    "maturity_level": null,
    "authority_score": null
  }
}