{
  "title": "Virtual World",
  "content": "- ### OntologyBlock\n  id:: virtual-world-ontology\n  collapsed:: true\n\t- ontology:: true\n\t- term-id:: 20314\n\t- source-domain:: metaverse\n\t- status:: draft\n\t- is-subclass-of:: [[Metaverse]]\n\t- public-access:: true\n\n\n# Virtual World Ontology Entry – Revised\n\n## Academic Context\n\n- Definition and conceptual foundations\n  - Computer-simulated immersive environments enabling real-time user interaction[1][2]\n  - Shared, three-dimensional spaces supporting social, economic, and creative activities across geographical boundaries[2][3]\n  - Distinction from gaming: virtual worlds encompass broader applications including education, healthcare, industrial simulation, and cultural experiences[1]\n  - Technological substrate: augmented reality, virtual reality, spatial computing, and artificial intelligence converging to create embodied experiences[3]\n\n- Terminology clarification\n  - \"Virtual world\" and \"metaverse\" used interchangeably in contemporary discourse (metaverse being a contraction of \"meta\" and \"universe\")[3]\n  - Often conflated with gaming platforms, though the scope extends considerably further—rather like confusing a library with a single bookshelf\n\n## Current Landscape (2025)\n\n- Market trajectory and adoption\n  - Global virtual worlds market valued at €27 billion in 2022, projected to reach €800 billion by 2030[1]\n  - Automotive sector particularly active: €1.9 billion market size in 2022, estimated to rise to €16.5 billion by 2030[1]\n  - Approximately 3,700 firms, research institutions, and government bodies engaged in virtual worlds development across the EU[1]\n  - Youth engagement: young people anticipated to spend at least one hour daily in metaverse environments by 2026[3]\n\n- Sectoral implementations\n  - Healthcare: surgical simulation and emergency response training reducing complications and improving diagnostic accuracy[1]\n  - Industrial manufacturing: virtual environments projected to reduce vehicle delivery times by 60% and manufacturing carbon footprint by 50% (according to European automotive manufacturers)[1]\n  - Education: experiential learning environments accelerating student comprehension and engagement[1][3]\n  - Cultural heritage and arts: immersive museum experiences, concerts, theatrical performances, and visual arts creation[1]\n\n- Technical capabilities\n  - Real-time interactivity and persistent state management[2]\n  - Spatial properties enabling navigation and object manipulation[2]\n  - Multi-user synchronisation across distributed networks[2]\n  - Integration of embodied experience with collaborative functionality[3]\n\n- Current limitations and considerations\n  - Regulatory frameworks still developing (particularly regarding data protection, intellectual property, and user rights)[5]\n  - Meaningfulness and intentionality often overlooked in implementation—gamification techniques applied without substantive purpose[4]\n  - Infrastructure and accessibility challenges remain significant barriers to equitable adoption\n\n## Research & Literature\n\n- Foundational sources\n  - European Commission Digital Strategy (2025). \"Virtual Worlds: Shaping Europe's Digital Future.\" Available at: digital-strategy.ec.europa.eu/en/factpages/virtual-worlds. Provides comprehensive market analysis and sectoral applications across EU context.\n  - Di Porto, F. (2025). \"Defining Virtual Worlds: Main Features and Regulatory Challenges.\" Centre on Regulation in Europe (CERRE). Addresses conceptualisation across development phases and emerging regulatory requirements.\n\n- Definitional and conceptual frameworks\n  - Fiveable Media Literacy Series (2025). \"Virtual Worlds.\" Emphasises real-time interaction, social and economic activity, and cross-geographical connectivity as defining characteristics.\n  - Excelia Group (2025). \"Understanding the Concept of a Virtual World.\" Identifies three core features: immersion, real-time interactivity, and infinite use potential.\n\n- Emerging scholarship\n  - Radoff, J. (2025). \"The Meaning of Virtual Worlds.\" Metavert Meditations. Critiques technology-centric approaches lacking intentionality; emphasises meaning-making as essential to virtual world design.\n\n- Ongoing research directions\n  - Regulatory harmonisation across jurisdictions\n  - Accessibility and inclusive design standards\n  - Psychological and social impacts of prolonged immersion\n  - Interoperability protocols between disparate virtual environments\n\n## UK Context\n\n- Institutional engagement\n  - UK research institutions increasingly active in virtual worlds development, particularly within computer science and human-computer interaction disciplines\n  - Growing interest from cultural institutions (museums, galleries, heritage organisations) in immersive digital experiences\n\n- North England innovation landscape\n  - Manchester: emerging technology sector engagement with spatial computing and immersive environments; university research groups exploring metaverse applications\n  - Leeds: digital media and creative industries exploring virtual world platforms for cultural heritage preservation\n  - Newcastle: growing interest in virtual worlds applications within healthcare simulation and medical training\n  - Sheffield: manufacturing and advanced engineering sectors investigating industrial virtual environments for design and prototyping\n\n- Regulatory context\n  - UK regulatory approach developing independently post-Brexit, with particular attention to data protection (UK GDPR), online safety frameworks, and intellectual property considerations\n  - Financial Conduct Authority monitoring virtual economy implications and potential consumer protection requirements\n\n## Future Directions\n\n- Emerging trends\n  - Convergence of artificial intelligence with virtual environments for dynamic, adaptive experiences[1]\n  - Expansion into industrial and enterprise applications beyond consumer-facing platforms[1]\n  - Integration with green transition initiatives: 3D environmental modelling for climate impact simulation and mitigation strategy development[1]\n  - Anticipated creation of 860,000 new jobs in extended reality across Europe by 2025[1]\n\n- Anticipated challenges\n  - Balancing immersion and engagement with user wellbeing and digital literacy\n  - Establishing meaningful standards for interoperability and data portability\n  - Addressing equity concerns regarding access and participation\n  - Developing robust governance frameworks without stifling innovation\n\n- Research priorities\n  - Longitudinal studies on cognitive and social impacts of sustained virtual world engagement\n  - Technical standards for seamless cross-platform experiences\n  - Ethical frameworks for virtual economy regulation\n  - Accessibility protocols ensuring inclusive participation across diverse user populations\n\n---\n\n**Note on revision approach:** The original definition remains conceptually sound but has been substantially contextualised within current market realities, regulatory developments, and sectoral applications. The 2025 perspective reveals virtual worlds transitioning from speculative technology to practical industrial and educational infrastructure—a rather significant shift from the \"metaverse as gaming platform\" narrative that dominated 2021–2023 discourse. UK and North England contexts have been integrated where institutional and sectoral engagement is evident, though comprehensive regional case studies would benefit from additional primary research.\n\n\n## Metadata\n\n- **Last Updated**: 2025-11-11\n- **Review Status**: Comprehensive editorial review\n- **Verification**: Academic sources verified\n- **Regional Context**: UK/North England where applicable",
  "properties": {
    "id": "virtual-world-ontology",
    "collapsed": "true",
    "- ontology": "true",
    "- term-id": "20314",
    "- source-domain": "metaverse",
    "- status": "draft",
    "- is-subclass-of": "[[Metaverse]]",
    "- public-access": "true"
  },
  "backlinks": [
    "Game Engine",
    "Metaverse",
    "Physics Engine"
  ],
  "wiki_links": [
    "Metaverse"
  ],
  "ontology": {
    "term_id": "20314",
    "preferred_term": "Virtual World",
    "definition": "",
    "source_domain": "metaverse",
    "maturity_level": null,
    "authority_score": null
  }
}