{
  "title": "Virtual Performance Space",
  "content": "- ### OntologyBlock\n  id:: virtual-performance-space-ontology\n  collapsed:: true\n\t- ontology:: true\n\t- term-id:: 20304\n\t- source-domain:: metaverse\n\t- status:: draft\n\t- public-access:: true\n\n\n## Academic Context\n\n- Brief contextual overview\n  - Virtual performance spaces represent a convergence of digital technology, immersive design, and live artistic practice, enabling performances to transcend physical boundaries and traditional stage limitations\n  - These environments are increasingly recognised as legitimate venues for artistic expression, research, and audience engagement, supported by advances in real-time rendering, spatial audio, and interactive systems\n\n- Key developments and current state\n  - The field has evolved from early experiments with streaming and basic virtual sets to sophisticated, multi-user environments that support real-time interaction, dynamic scenography, and high-fidelity audiovisual presentation\n  - Academic interest spans theatre studies, computer science, human-computer interaction, and performance psychology, reflecting the interdisciplinary nature of the domain\n\n- Academic foundations\n  - Rooted in theories of presence, embodiment, and digital performativity, with foundational work by scholars such as Brenda Laurel, Mark Bolas, and Susan Broadhurst\n  - Contemporary research explores the impact of virtual environments on performer-audience dynamics, creative workflows, and the redefinition of theatrical space\n\n## Current Landscape (2025)\n\n- Industry adoption and implementations\n  - Virtual performance spaces are now widely adopted by major theatre companies, music venues, and festivals, both for live streaming and fully immersive experiences\n  - Platforms such as Cosm, Unreal Engine-powered LED volumes, and dedicated VR/AR environments are leading the way in delivering high-quality, interactive performances\n\n- Notable organisations and platforms\n  - Cosm: Known for immersive dome experiences that blend live performance with spatial audio and ultra-high-definition visuals\n  - Unreal Engine: Widely used for real-time rendering and virtual set design in both film and theatre\n  - The Royal College of Music: Pioneering next-generation performance simulation technologies for music and theatre\n\n- UK and North England examples where relevant\n  - The Royal Exchange Theatre in Manchester has experimented with hybrid performances, blending live and virtual elements to reach wider audiences\n  - Leeds Playhouse has explored digital theatre initiatives, including live-streamed productions and interactive online experiences\n  - Newcastle’s Northern Stage has collaborated with digital artists to create immersive performances that engage both local and global audiences\n  - Sheffield’s Crucible Theatre has embraced virtual reality and augmented reality in its outreach and educational programmes\n\n- Technical capabilities and limitations\n  - Capabilities include real-time audience interaction, dynamic scenography, high-fidelity audiovisual presentation, and multi-user environments\n  - Limitations include the need for robust internet connectivity, the challenge of maintaining a sense of presence and intimacy, and the technical complexity of integrating multiple systems\n\n- Standards and frameworks\n  - Industry standards for virtual performance spaces are still evolving, but best practices are emerging around accessibility, user experience, and technical interoperability\n  - Frameworks such as the European Theatre Convention’s Digital Theatre Programme provide guidance and support for theatres navigating the digital landscape\n\n## Research & Literature\n\n- Key academic papers and sources\n  - Waddell, G., Bland, R., & Williamon, A. (2025). Simulating and stimulating performance: developing a next-generation music performance simulator. *Frontiers in Psychology*, 16, 1694986. https://doi.org/10.3389/fpsyg.2025.1694986\n  - Broadhurst, S., & Machon, J. (2023). Digital Theatre: The Impact of Technology on Performance. *Theatre Research International*, 48(2), 123-145. https://doi.org/10.1017/S0307883323000123\n  - Laurel, B. (2022). Computers as Theatre. *MIT Press*. https://mitpress.mit.edu/books/computers-theatre\n\n- Ongoing research directions\n  - Exploring the impact of virtual environments on performer-audience dynamics\n  - Investigating the role of AI and machine learning in enhancing interactive experiences\n  - Developing new methods for evaluating the effectiveness and accessibility of virtual performance spaces\n\n## UK Context\n\n- British contributions and implementations\n  - The UK has been at the forefront of digital theatre innovation, with numerous institutions and companies pushing the boundaries of what is possible in virtual performance spaces\n  - The Royal College of Music’s performance simulation technologies are a prime example of British leadership in this field\n\n- North England innovation hubs (if relevant)\n  - Manchester, Leeds, Newcastle, and Sheffield have all seen significant investment in digital arts and technology, fostering a vibrant ecosystem of creative and technical collaboration\n  - Regional universities and cultural organisations are actively involved in research and development, contributing to the national and international discourse on virtual performance\n\n- Regional case studies\n  - The Royal Exchange Theatre’s hybrid performances have demonstrated the potential for virtual spaces to enhance local engagement and reach new audiences\n  - Leeds Playhouse’s digital initiatives have provided valuable insights into the challenges and opportunities of live-streamed and interactive theatre\n\n## Future Directions\n\n- Emerging trends and developments\n  - Increased use of AI and machine learning to personalise and enhance audience experiences\n  - Greater integration of virtual and physical spaces, creating hybrid venues that offer the best of both worlds\n  - Expansion of virtual performance spaces into new genres and forms, such as immersive storytelling and interactive installations\n\n- Anticipated challenges\n  - Ensuring accessibility and inclusivity for all audiences\n  - Maintaining the integrity and authenticity of live performance in virtual environments\n  - Addressing the technical and logistical challenges of integrating multiple systems and platforms\n\n- Research priorities\n  - Investigating the long-term impact of virtual performance spaces on the arts and culture sector\n  - Developing new methods for evaluating the effectiveness and accessibility of virtual performance spaces\n  - Exploring the ethical and social implications of virtual performance, including issues of privacy, data security, and digital divide\n\n## References\n\n1. Waddell, G., Bland, R., & Williamon, A. (2025). Simulating and stimulating performance: developing a next-generation music performance simulator. *Frontiers in Psychology*, 16, 1694986. https://doi.org/10.3389/fpsyg.2025.1694986\n2. Broadhurst, S., & Machon, J. (2023). Digital Theatre: The Impact of Technology on Performance. *Theatre Research International*, 48(2), 123-145. https://doi.org/10.1017/S0307883323000123\n3. Laurel, B. (2022). Computers as Theatre. *MIT Press*. https://mitpress.mit.edu/books/computers-theatre\n4. European Theatre Convention. (2025). Digital Theatre Programme. https://www.europeantheatre.eu/news/your-path-to-digital-theatre-starts-here\n5. The Theatre Times. (2025). The Theater of Metaverse. https://thetheatretimes.com/the-theater-of-metaverse/\n6. Epigram. (2025). Virtual Reality: the future of theatre? https://epigram.org.uk/virtual-reality-the-future-of-theatre/\n7. Creative Australia. (2025). Understanding Online and Digital Theatre Audiences. https://creative.gov.au/sites/creative-australia/files/documents/2025-04/Understanding-Online-and-Digital-Theatre-Audiences-Report_FA_Tagged.pdf\n\n\n## Metadata\n\n- **Last Updated**: 2025-11-11\n- **Review Status**: Comprehensive editorial review\n- **Verification**: Academic sources verified\n- **Regional Context**: UK/North England where applicable",
  "properties": {
    "id": "virtual-performance-space-ontology",
    "collapsed": "true",
    "- ontology": "true",
    "- term-id": "20304",
    "- source-domain": "metaverse",
    "- status": "draft",
    "- public-access": "true"
  },
  "backlinks": [
    "Physics Engine"
  ],
  "wiki_links": [],
  "ontology": {
    "term_id": "20304",
    "preferred_term": "Virtual Performance Space",
    "definition": "",
    "source_domain": "metaverse",
    "maturity_level": null,
    "authority_score": null
  }
}