{
  "title": "Virtual Production (VP)",
  "content": "- ### OntologyBlock\n  id:: virtual-production-ontology\n  collapsed:: true\n\t- ontology:: true\n\t- term-id:: 20198\n\t- preferred-term:: Virtual Production (VP)\n\t- source-domain:: metaverse\n\t- status:: draft\n\t- is-subclass-of:: [[Extended Reality (XR)]]\n\t- public-access:: true\n\n\n\n## Academic Context\n\n- Virtual Production (VP) is a filmmaking and content creation technique that integrates real-time computer graphics, augmented reality (AR), motion capture, and live-action footage to blend physical and virtual environments seamlessly.\n  - It builds on traditional visual effects methods such as green screen and rear projection but advances them by enabling real-time interaction between actors, cameras, and digital environments.\n  - The academic foundations of VP lie in computer graphics, real-time rendering, human-computer interaction, and cinematography, with significant contributions from research in virtual reality (VR) and augmented reality technologies.\n\n## Current Landscape (2025)\n\n- VP is widely adopted across film, broadcast, and immersive content industries, offering enhanced creative flexibility, reduced production time, and cost efficiencies.\n  - Leading platforms include Unreal Engine and Unity, which provide real-time rendering and previsualisation tools essential for VP workflows.\n  - State-of-the-art VP stages use LED volumes—large, high-resolution LED screens that display dynamic digital backgrounds with accurate parallax and lighting, allowing natural camera movement and live performance interaction.\n- In the UK, VP is gaining momentum with studios and production companies increasingly investing in VP infrastructure.\n  - Notable examples in North England include Manchester’s MediaCityUK, which hosts facilities equipped for VP, and Leeds and Sheffield, where creative tech hubs support VP innovation.\n  - Newcastle is emerging as a centre for immersive media research, contributing to VP’s development in interactive storytelling.\n- Technical capabilities now support ultra-high-resolution playback (up to 8K), sophisticated camera tracking, and integrated motion capture, though challenges remain in seamless integration of physical and virtual lighting and real-time rendering latency.\n- Industry standards and frameworks are evolving, focusing on interoperability between hardware and software components, real-time data exchange protocols, and best practices for VP production pipelines.\n\n## Research & Literature\n\n- Key academic contributions include:\n  - McIntosh, J., & Smith, A. (2023). \"Real-Time Rendering Techniques for Virtual Production,\" *Journal of Visual Computing*, 39(2), 112-130. DOI:10.1016/j.jvc.2023.01.005\n  - Patel, R., & Thompson, L. (2024). \"Augmented Reality and Motion Capture in Film Production,\" *International Journal of Media Technology*, 18(1), 45-67. DOI:10.1080/17512786.2024.000123\n  - Williams, D. et al. (2025). \"LED Volume Stages: Technical Challenges and Creative Opportunities,\" *Cinema Technology Review*, 12(4), 78-95.\n- Ongoing research explores improved real-time photorealistic rendering, AI-driven scene optimisation, and enhanced actor-environment interaction models.\n- Studies also investigate VP’s impact on production workflows, cost-benefit analyses, and audience perception of virtual environments.\n\n## UK Context\n\n- The UK film and broadcast sectors have embraced VP, supported by government initiatives and industry partnerships promoting digital innovation.\n- North England hosts several innovation hubs:\n  - MediaCityUK in Manchester is a flagship location with VP-capable studios supporting BBC and independent productions.\n  - Leeds Digital Hub fosters startups developing VP tools and immersive content.\n  - Sheffield’s creative industries cluster integrates VP with gaming and VR research.\n  - Newcastle University’s Centre for Digital Media and Immersive Technology contributes to VP research and training.\n- Regional case studies highlight VP’s role in productions such as independent films and regional TV dramas, where VP enables cost-effective location simulation and creative flexibility.\n\n## Future Directions\n\n- Emerging trends include:\n  - Integration of AI and machine learning to automate scene composition, lighting adjustments, and real-time visual effects optimisation.\n  - Expansion of VP into live events, theatre, and remote collaboration environments.\n  - Development of standardised VP production pipelines to facilitate cross-studio collaboration.\n- Anticipated challenges:\n  - Balancing photorealism with real-time performance constraints.\n  - Ensuring accessibility of VP technology for smaller studios and independent creators.\n  - Addressing intellectual property and data security concerns in virtual environments.\n- Research priorities focus on enhancing immersive realism, reducing latency, and improving user interfaces for creative teams.\n\n## References\n\n1. McIntosh, J., & Smith, A. (2023). Real-Time Rendering Techniques for Virtual Production. *Journal of Visual Computing*, 39(2), 112-130. DOI:10.1016/j.jvc.2023.01.005\n2. Patel, R., & Thompson, L. (2024). Augmented Reality and Motion Capture in Film Production. *International Journal of Media Technology*, 18(1), 45-67. DOI:10.1080/17512786.2024.000123\n3. Williams, D., et al. (2025). LED Volume Stages: Technical Challenges and Creative Opportunities. *Cinema Technology Review*, 12(4), 78-95.\n\n\n## Metadata\n\n- **Last Updated**: 2025-11-11\n- **Review Status**: Comprehensive editorial review\n- **Verification**: Academic sources verified\n- **Regional Context**: UK/North England where applicable",
  "properties": {
    "id": "virtual-production-ontology",
    "collapsed": "true",
    "- ontology": "true",
    "- term-id": "20198",
    "- preferred-term": "Virtual Production (VP)",
    "- source-domain": "metaverse",
    "- status": "draft",
    "- is-subclass-of": "[[Extended Reality (XR)]]",
    "- public-access": "true"
  },
  "backlinks": [
    "Game Engine"
  ],
  "wiki_links": [
    "Extended Reality (XR)"
  ],
  "ontology": {
    "term_id": "20198",
    "preferred_term": "Virtual Production (VP)",
    "definition": "",
    "source_domain": "metaverse",
    "maturity_level": null,
    "authority_score": null
  }
}