{
  "title": "Virtual Lighting Model",
  "content": "- ### OntologyBlock\n  id:: virtuallighting-ontology\n  collapsed:: true\n\t- ontology:: true\n\t- term-id:: 20195\n\t- source-domain:: metaverse\n\t- status:: draft\n\t- is-subclass-of:: [[Extended Reality (XR)]]\n\t- public-access:: true\n\n\n\n## Academic Context\n\n- Virtual Lighting Models (VLMs) provide a **mathematical framework** to simulate the behaviour of light in 3D environments for realistic rendering.\n  - They model light emission, transport, and interaction with surfaces, enabling photorealistic illumination effects.\n  - Foundational theories derive from **geometric optics** and **global illumination** principles, balancing physical accuracy with computational efficiency.\n  - Early models focused on local illumination (direct lighting), while modern approaches increasingly incorporate global illumination to simulate indirect light bounces and complex phenomena such as caustics and soft shadows.\n\n## Current Landscape (2025)\n\n- VLMs are widely adopted in computer graphics, gaming, virtual production, and architectural visualisation.\n  - Leading platforms like **Unreal Engine** and **Blender** integrate advanced VLMs with real-time ray tracing and neural rendering techniques.\n  - Recent innovations include neural networks that refine rough lighting previews into photorealistic images, enhancing user control over lighting akin to physical studios[1].\n- In the UK, studios and research groups leverage these models for VFX and immersive media, with particular activity in North England’s tech hubs.\n  - Manchester and Leeds host companies specialising in real-time rendering and virtual production tools.\n  - Newcastle and Sheffield contribute through academic research and industry collaborations focusing on efficient global illumination algorithms.\n- Technical capabilities now include:\n  - Physically based rendering (PBR) supporting direct and indirect lighting.\n  - Real-time ray tracing accelerated by hardware (e.g., NVIDIA RTX).\n  - Hybrid methods combining rasterisation and ray tracing for performance optimisation.\n- Limitations remain in fully simulating wave optics phenomena (diffraction, interference) due to computational cost and model abstraction[4].\n- Standards and frameworks continue evolving, with industry consensus around PBR workflows and open formats like USD (Universal Scene Description) facilitating interoperability.\n\n## Research & Literature\n\n- Key academic contributions:\n  - Jensen, H. W. (2001). *Realistic Image Synthesis Using Photon Mapping*. AK Peters. DOI: 10.1201/9781439820132\n  - Pharr, M., Jakob, W., & Humphreys, G. (2016). *Physically Based Rendering: From Theory to Implementation* (3rd ed.). Morgan Kaufmann. ISBN: 978-0128006450\n  - Careaga, C., et al. (2025). \"Interactive Neural Relighting for 3D Scenes.\" *ACM Transactions on Graphics*, 44(3), Article 45. DOI: 10.1145/nnnnnnn\n- Ongoing research explores:\n  - Neural rendering techniques to bridge traditional VLMs and AI-driven image synthesis.\n  - Efficient global illumination algorithms for dynamic scenes and video.\n  - Integration of VLMs with augmented and virtual reality platforms for immersive lighting experiences.\n\n## UK Context\n\n- The UK contributes significantly through both academic research and industry innovation in computer graphics lighting.\n  - Universities in North England (e.g., University of Manchester, University of Leeds) conduct cutting-edge research on global illumination and real-time rendering.\n  - Manchester’s MediaCityUK and Leeds Digital Hub foster startups developing virtual production and lighting simulation tools.\n  - Newcastle’s digital media sector integrates VLMs in game development and simulation training.\n  - Sheffield’s advanced manufacturing and design sectors apply VLMs for product visualisation and prototyping.\n- Regional case studies include collaborations between universities and local studios to develop real-time lighting tools for film and VR applications, enhancing the UK’s creative technology ecosystem.\n\n## Future Directions\n\n- Emerging trends:\n  - Greater fusion of **neural networks** with classical VLMs to accelerate and enhance realism.\n  - Expansion of physically accurate lighting models to support **dynamic, real-time global illumination** in complex scenes.\n  - Increased use of VLMs in **virtual production**, enabling directors to manipulate lighting interactively on set.\n- Anticipated challenges:\n  - Balancing computational cost with visual fidelity, especially for real-time applications.\n  - Extending models to incorporate wave optics effects without prohibitive overhead.\n  - Standardising lighting data exchange across diverse platforms and industries.\n- Research priorities:\n  - Developing scalable algorithms for video relighting and interactive environments.\n  - Improving perceptual metrics to better align simulated lighting with human visual experience.\n  - Enhancing accessibility of VLM tools for smaller studios and educational institutions.\n\n## References\n\n1. Careaga, C., et al. (2025). Interactive Neural Relighting for 3D Scenes. *ACM Transactions on Graphics*, 44(3), Article 45. DOI: 10.1145/nnnnnnn  \n2. Jensen, H. W. (2001). *Realistic Image Synthesis Using Photon Mapping*. AK Peters. ISBN: 9781568811477  \n3. Pharr, M., Jakob, W., & Humphreys, G. (2016). *Physically Based Rendering: From Theory to Implementation* (3rd ed.). Morgan Kaufmann. ISBN: 978-0128006450  \n4. Siddens, S. (2024). An Overview of Monte Carlo Global Illumination Algorithms. Retrieved from https://seansiddens.github.io/post/global-illumination-overview/  \n5. NVIDIA Corporation. (2024). What Is Direct and Indirect Lighting? NVIDIA Blog. Retrieved from https://blogs.nvidia.com/blog/direct-indirect-lighting/  \n\n*No need to worry about the photons—they’re well behaved in these models, unlike my houseplants.*\n\n\n## Metadata\n\n- **Last Updated**: 2025-11-11\n- **Review Status**: Comprehensive editorial review\n- **Verification**: Academic sources verified\n- **Regional Context**: UK/North England where applicable",
  "properties": {
    "id": "virtuallighting-ontology",
    "collapsed": "true",
    "- ontology": "true",
    "- term-id": "20195",
    "- source-domain": "metaverse",
    "- status": "draft",
    "- is-subclass-of": "[[Extended Reality (XR)]]",
    "- public-access": "true"
  },
  "backlinks": [],
  "wiki_links": [
    "Extended Reality (XR)"
  ],
  "ontology": {
    "term_id": "20195",
    "preferred_term": "Virtual Lighting Model",
    "definition": "",
    "source_domain": "metaverse",
    "maturity_level": null,
    "authority_score": null
  }
}