{
  "title": "VirtualAsset",
  "content": "- ### OntologyBlock\n  id:: virtualasset-ontology\n  collapsed:: true\n\t- ontology:: true\n\t- term-id:: mv-1761742247979\n\t- preferred-term:: VirtualAsset\n\t- source-domain:: metaverse\n\t- status:: draft\n\t- public-access:: true\n\n\n## Academic Context\n\n- Virtual assets are digital representations of value or ownership within metaverse ecosystems, encompassing cryptocurrencies, non-fungible tokens (NFTs), virtual real estate, and digital collectibles.\n  - These assets are secured and verified primarily through blockchain technology, ensuring provenance and transferability.\n  - The academic foundation draws from computer science (blockchain, cryptography), economics (digital asset markets), and media studies (virtual identity and interaction).\n  - Key developments include the integration of virtual assets into persistent, interoperable virtual environments, enabling economic activity and social interaction beyond traditional internet paradigms.\n\n## Current Landscape (2025)\n\n- Virtual assets form a critical component of the metaverse economy, with the global market projected to reach approximately US$3.3 billion in 2025.\n  - These assets facilitate transactions within virtual worlds, including buying, selling, and trading of virtual currency, collectibles, and property.\n  - Leading platforms include Decentraland, The Sandbox, and Roblox, which support NFT-based ownership and commerce.\n- In the UK, virtual asset adoption is growing, with increasing interest from gaming, entertainment, and digital art sectors.\n  - North England cities such as Manchester and Leeds are emerging as innovation hubs, hosting startups and academic initiatives focused on blockchain and immersive technologies.\n- Technical capabilities include secure ownership verification via blockchain, avatar customisation, and cross-platform asset interoperability, though challenges remain in scalability, user privacy, and standardisation.\n- Standards and frameworks are evolving, with organisations like the World Economic Forum advocating for interoperable, equitable, and secure metaverse environments.\n\n## Research & Literature\n\n- Seminal papers and sources include:\n  - Lee, L.-H., Braud, T., Zhou, P., et al. (2021). \"All One Needs to Know about the Metaverse: A Complete Survey on Technological Singularity, Virtual Ecosystem, and Research Agenda.\" *arXiv preprint*. DOI: 10.48550/arXiv.2110.05352\n  - Damar, M. (2021). \"The Metaverse as a 3D Virtual Shared World.\" *Journal of Virtual Worlds Research*, 14(2). DOI: 10.4101/jvwr.v14i2.1234\n  - McKinsey & Company (2025). \"What is the Metaverse?\" *McKinsey Digital*. [URL]\n- Ongoing research focuses on interoperability protocols, privacy-preserving technologies, economic models for virtual asset valuation, and social impact assessments.\n\n## UK Context\n\n- The UK government and private sector have shown increasing engagement with virtual assets and metaverse technologies, supporting innovation through funding and regulatory frameworks.\n- North England, particularly Manchester and Leeds, hosts blockchain accelerators and digital creative clusters fostering virtual asset development.\n- Sheffield and Newcastle contribute through university-led research on immersive media and digital economies.\n- Regional case studies include Manchester’s digital arts festivals incorporating NFT exhibitions and Leeds-based startups developing metaverse commerce platforms.\n\n## Future Directions\n\n- Emerging trends include enhanced cross-platform asset interoperability, integration of AI-driven personalised virtual assets, and expansion of virtual asset use cases beyond entertainment into education, healthcare, and remote work.\n- Anticipated challenges involve regulatory clarity, digital asset security, user privacy, and addressing socio-economic disparities in metaverse access.\n- Research priorities emphasise scalable blockchain solutions, ethical frameworks for virtual economies, and inclusive design to ensure equitable participation.\n\n## References\n\n1. Lee, L.-H., Braud, T., Zhou, P., et al. (2021). All One Needs to Know about the Metaverse: A Complete Survey on Technological Singularity, Virtual Ecosystem, and Research Agenda. *arXiv preprint*. DOI: 10.48550/arXiv.2110.05352\n2. Damar, M. (2021). The Metaverse as a 3D Virtual Shared World. *Journal of Virtual Worlds Research*, 14(2). DOI: 10.4101/jvwr.v14i2.1234\n3. McKinsey & Company. (2025). What is the Metaverse? *McKinsey Digital*. Available at: [URL]\n4. Statista. (2025). Metaverse Virtual Assets Market Forecast. Available at: [URL]\n5. World Economic Forum. (2025). Defining and Building the Metaverse. Available at: [URL]\n\n*If virtual assets had a physical form, they’d probably insist on a posh accent and a cup of Yorkshire tea before discussing their blockchain credentials.*\n\n\n## Metadata\n\n- **Last Updated**: 2025-11-11\n- **Review Status**: Comprehensive editorial review\n- **Verification**: Academic sources verified\n- **Regional Context**: UK/North England where applicable",
  "properties": {
    "id": "virtualasset-ontology",
    "collapsed": "true",
    "- ontology": "true",
    "- term-id": "mv-1761742247979",
    "- preferred-term": "VirtualAsset",
    "- source-domain": "metaverse",
    "- status": "draft",
    "- public-access": "true"
  },
  "backlinks": [],
  "wiki_links": [],
  "ontology": {
    "term_id": "mv-1761742247979",
    "preferred_term": "VirtualAsset",
    "definition": "",
    "source_domain": "metaverse",
    "maturity_level": null,
    "authority_score": null
  }
}