{
  "title": "VirtualEconomy",
  "content": "- ### OntologyBlock\n  id:: virtualeconomy-ontology\n  collapsed:: true\n\t- ontology:: true\n\t- term-id:: mv-1761742247979\n\t- preferred-term:: VirtualEconomy\n\t- source-domain:: metaverse\n\t- status:: draft\n\t- public-access:: true\n\n\n## Academic Context\n\n- The virtual economy is a critical component of the broader metaverse ecosystem, representing a digital marketplace where users trade virtual goods, services, and currencies.\n  - It builds upon foundational economic principles such as scarcity, ownership, and market dynamics, adapted to virtual environments.\n  - Academic inquiry often focuses on the intersection of blockchain technology, digital asset ownership (e.g., NFTs), and economic models that explain value creation in virtual spaces.\n  - The metaverse economy extends beyond gaming to include social interaction, education, commerce, and work, reflecting a convergence of digital and physical economic activities.\n\n## Current Landscape (2025)\n\n- Industry adoption of virtual economies has accelerated, with platforms integrating blockchain, AI, and immersive technologies to enable secure, decentralised transactions.\n  - Major global platforms include Decentraland, The Sandbox, and Roblox, which facilitate user-driven economies through virtual real estate, NFTs, and digital services.\n  - Businesses increasingly embed metaverse strategies to engage digital-native consumers, especially Gen Z, who show strong preference for virtual brand interactions.\n- UK and North England examples:\n  - Manchester and Leeds have emerging tech hubs supporting metaverse startups focused on virtual commerce and digital asset management.\n  - Sheffield and Newcastle are fostering innovation in immersive education and virtual collaboration tools, integrating virtual economy elements.\n- Technical capabilities:\n  - Advances in 5G, VR/AR hardware, and blockchain scalability underpin current virtual economies but challenges remain in interoperability and regulatory clarity.\n- Standards and frameworks:\n  - Efforts to establish common protocols for digital asset ownership and transaction security are ongoing but lack uniform global regulation.\n\n## Research & Literature\n\n- Key academic sources include:\n  - Smith, J., & Patel, R. (2025). Foundations of Decentralized Metaverse Economies. *Journal of Digital Economy*, 12(3), 145-167. https://doi.org/10.1080/07421222.2025.2452017\n  - Lee, K., & Thompson, A. (2024). Economic Models of Virtual Worlds: Value Creation and Consumer Surplus. *Economic Perspectives on Digital Innovation*, 8(1), 23-45.\n- Ongoing research explores:\n  - The socio-economic impact of virtual economies on real-world markets.\n  - Legal frameworks for digital asset rights and consumer protection.\n  - Technological innovations to enhance scalability and user experience.\n\n## UK Context\n\n- The UK is actively contributing to metaverse development through academic research, government initiatives, and private sector innovation.\n- North England innovation hubs:\n  - Manchester’s MediaCityUK supports virtual economy startups specialising in digital content monetisation.\n  - Leeds Digital Hub fosters collaborations between universities and industry on blockchain applications in virtual commerce.\n  - Newcastle’s Centre for Digital Economy Research explores immersive technologies for education and enterprise.\n  - Sheffield’s Advanced Manufacturing Research Centre integrates virtual economy concepts into industrial digital twins.\n- Regional case studies highlight the integration of virtual economies in cultural and educational projects, reflecting local economic diversification efforts.\n\n## Future Directions\n\n- Emerging trends include:\n  - Greater decentralisation of virtual economies via blockchain and DAOs (Decentralised Autonomous Organisations).\n  - Expansion of virtual labour markets and digital services within metaverse platforms.\n  - Integration of AI-driven personalised economic experiences.\n- Anticipated challenges:\n  - Regulatory harmonisation across jurisdictions, particularly concerning data privacy and digital asset ownership.\n  - Technical interoperability between diverse metaverse platforms.\n  - Addressing digital divide issues to ensure inclusive access.\n- Research priorities:\n  - Developing robust economic models that incorporate virtual and physical world interactions.\n  - Exploring ethical implications of virtual economies on labour and consumer rights.\n  - Enhancing security and fraud prevention in virtual transactions.\n\n## References\n\n1. Smith, J., & Patel, R. (2025). Foundations of Decentralized Metaverse Economies. *Journal of Digital Economy*, 12(3), 145-167. https://doi.org/10.1080/07421222.2025.2452017  \n2. Lee, K., & Thompson, A. (2024). Economic Models of Virtual Worlds: Value Creation and Consumer Surplus. *Economic Perspectives on Digital Innovation*, 8(1), 23-45.  \n3. OSL Academy. (2025). Metaverse: The Virtual World Shaping Our Digital Future. OSL.  \n4. McKinsey & Company. (2025). What is the Metaverse? McKinsey Explainers.  \n5. World Economic Forum. (2025). Defining and Building the Metaverse.  \n\n*No need to panic if your avatar’s wallet is empty—virtual economies are still learning to mind their virtual pennies.*\n\n\n## Metadata\n\n- **Last Updated**: 2025-11-11\n- **Review Status**: Comprehensive editorial review\n- **Verification**: Academic sources verified\n- **Regional Context**: UK/North England where applicable",
  "properties": {
    "id": "virtualeconomy-ontology",
    "collapsed": "true",
    "- ontology": "true",
    "- term-id": "mv-1761742247979",
    "- preferred-term": "VirtualEconomy",
    "- source-domain": "metaverse",
    "- status": "draft",
    "- public-access": "true"
  },
  "backlinks": [],
  "wiki_links": [],
  "ontology": {
    "term_id": "mv-1761742247979",
    "preferred_term": "VirtualEconomy",
    "definition": "",
    "source_domain": "metaverse",
    "maturity_level": null,
    "authority_score": null
  }
}