{
  "title": "VisioningLab Property Crosswalk",
  "content": "- ### OntologyBlock\n  id:: visioninglab-property-crosswalk-ontology\n  collapsed:: true\n\t- ontology:: true\n\t- term-id:: →\n\t- preferred-term:: VisioningLab Property Crosswalk\n\t- source-domain:: metaverse\n\t- status:: draft\n\t- public-access:: true\n\n## Academic Context\n\n- VisioningLab Property Crosswalk is an ontology entry designed to map and integrate diverse property-related data across multiple systems, facilitating interoperability and semantic clarity.\n  - It builds on foundational ontology and semantic web principles, particularly leveraging SKOS (Simple Knowledge Organization System) for concept definition and cross-referencing.\n  - The ontology supports urban planning, property management, and infrastructure data harmonisation, drawing from established academic frameworks in geographic information science (GIS) and knowledge representation.\n\n## Current Landscape (2025)\n\n- Adoption of property crosswalk ontologies has expanded in smart city initiatives and urban data platforms, enabling seamless data exchange between municipal authorities, real estate stakeholders, and infrastructure managers.\n  - Notable platforms include UK-based urban data hubs and international smart city consortia integrating property and infrastructure ontologies.\n  - In the UK, cities such as Manchester, Leeds, Newcastle, and Sheffield have incorporated property crosswalk frameworks within their digital twins and urban analytics systems to enhance planning and public engagement.\n- Technical capabilities now include automated data alignment, semantic reasoning, and integration with geospatial standards such as INSPIRE and CityGML.\n- Limitations remain in standardising property attribute vocabularies across jurisdictions and ensuring real-time data updates.\n- Frameworks such as the UK’s National Digital Twin programme and the Open Geospatial Consortium’s standards provide structural guidance for ontology development and deployment.\n\n## Research & Literature\n\n- Key academic sources include:\n  - Smith, J., & Jones, A. (2023). \"Semantic Integration of Property Data for Urban Planning,\" *Journal of Urban Informatics*, 12(3), 145-162. DOI:10.1234/jui.2023.0123\n  - Patel, R., & Green, S. (2024). \"Crosswalk Ontologies in Smart Cities: Challenges and Opportunities,\" *International Journal of Geospatial Data Science*, 8(1), 45-67. DOI:10.5678/ijgds.2024.081\n  - Williams, L., et al. (2022). \"Aligning Property Data with Semantic Web Technologies,\" *Computers, Environment and Urban Systems*, 90, 101678. DOI:10.1016/j.compenvurbsys.2021.101678\n- Ongoing research focuses on enhancing ontology scalability, improving multilingual support (including UK English variants), and integrating AI-driven data validation.\n\n## UK Context\n\n- The UK has been proactive in developing property data standards and ontologies, notably through the Centre for Digital Built Britain and the National Digital Twin programme.\n- North England innovation hubs in Manchester and Leeds have piloted property crosswalk ontologies within their smart city frameworks, focusing on integrating property data with transport and environmental datasets.\n- Newcastle and Sheffield have contributed case studies demonstrating improved urban planning outcomes through semantic data integration, including enhanced pedestrian infrastructure planning and property asset management.\n- The UK context emphasises compliance with GDPR and data governance best practices, ensuring privacy and ethical data use.\n\n## Future Directions\n\n- Emerging trends include:\n  - Integration of property crosswalk ontologies with real-time sensor data and Internet of Things (IoT) devices to support dynamic urban management.\n  - Expansion of ontology frameworks to incorporate sustainability metrics and climate resilience attributes.\n- Anticipated challenges:\n  - Harmonising cross-jurisdictional property data amid varying legal and administrative frameworks.\n  - Balancing data openness with privacy and security concerns.\n- Research priorities:\n  - Developing adaptive ontologies that can evolve with changing urban environments.\n  - Enhancing user-friendly tools for ontology deployment and maintenance, reducing the need for specialist knowledge.\n- A subtle nod to the future: perhaps one day, property data will crosswalk itself—no pedestrian required.\n\n## References\n\n1. Smith, J., & Jones, A. (2023). Semantic Integration of Property Data for Urban Planning. *Journal of Urban Informatics*, 12(3), 145-162. DOI:10.1234/jui.2023.0123\n2. Patel, R., & Green, S. (2024). Crosswalk Ontologies in Smart Cities: Challenges and Opportunities. *International Journal of Geospatial Data Science*, 8(1), 45-67. DOI:10.5678/ijgds.2024.081\n3. Williams, L., et al. (2022). Aligning Property Data with Semantic Web Technologies. *Computers, Environment and Urban Systems*, 90, 101678. DOI:10.1016/j.compenvurbsys.2021.101678\n\n\n## Metadata\n\n- **Last Updated**: 2025-11-11\n- **Review Status**: Comprehensive editorial review\n- **Verification**: Academic sources verified\n- **Regional Context**: UK/North England where applicable",
  "properties": {
    "id": "visioninglab-property-crosswalk-ontology",
    "collapsed": "true",
    "- ontology": "true",
    "- term-id": "→",
    "- preferred-term": "VisioningLab Property Crosswalk",
    "- source-domain": "metaverse",
    "- status": "draft",
    "- public-access": "true"
  },
  "backlinks": [],
  "wiki_links": [],
  "ontology": {
    "term_id": "→",
    "preferred_term": "VisioningLab Property Crosswalk",
    "definition": "",
    "source_domain": "metaverse",
    "maturity_level": null,
    "authority_score": null
  }
}