{
  "title": "VP robotics project",
  "content": "- ### OntologyBlock\n  id:: vp-robotics-project-ontology\n  collapsed:: true\n\t- ontology:: true\n\t- term-id:: mv-765735727723\n\t- preferred-term:: VP robotics project\n\t- source-domain:: metaverse\n\t- status:: active\n\t- public-access:: true\n\t- definition:: A component of the metaverse ecosystem focusing on vp robotics project.\n\t- maturity:: mature\n\t- authority-score:: 0.85\n\t- owl:class:: mv:VpRoboticsProject\n\t- owl:physicality:: ConceptualEntity\n\t- owl:role:: Concept\n\t- belongsToDomain:: [[MetaverseDomain]]\n\t- #### Relationships\n\t  id:: vp-robotics-project-relationships\n\t\t- enables:: [[ImmersiveExperience]], [[Presence]], [[SpatialComputing]]\n\t\t- requires:: [[DisplayTechnology]], [[TrackingSystem]], [[RenderingEngine]]\n\t\t- bridges-to:: [[HumanComputerInteraction]], [[ComputerVision]], [[Robotics]]\n\n\t- #### OWL Axioms\n\t  id:: vp-robotics-project-owl-axioms\n\t  collapsed:: true\n\t\t- ```clojure\n\t\t  Declaration(Class(mv:VpRoboticsProject))\n\n\t\t  # Classification\n\t\t  SubClassOf(mv:VpRoboticsProject mv:ConceptualEntity)\n\t\t  SubClassOf(mv:VpRoboticsProject mv:Concept)\n\n\t\t  # Domain classification\n\t\t  SubClassOf(mv:VpRoboticsProject\n\t\t    ObjectSomeValuesFrom(mv:belongsToDomain mv:MetaverseDomain)\n\t\t  )\n\n\t\t  # Annotations\n\t\t  AnnotationAssertion(rdfs:label mv:VpRoboticsProject \"VP robotics project\"@en)\n\t\t  AnnotationAssertion(rdfs:comment mv:VpRoboticsProject \"A component of the metaverse ecosystem focusing on vp robotics project.\"@en)\n\t\t  AnnotationAssertion(dcterms:identifier mv:VpRoboticsProject \"mv-765735727723\"^^xsd:string)\n\t\t  ```\n\npublic:: true\n\n- #Public page\n\t- automatically published\n-\n- ## Old Pitch Deck\n- https://docs.google.com/presentation/d/1DQcc9ybYcozzT6ROX8X0nKhKHzx4e_sQrJ452vLXF4E/edit?usp=sharing\n- # New submission for Creative Catalyst?\n\t- [Creative Catalyst 2024\n\t\t- GOV-UK Find a grant (find-government-grants.service.gov.uk)](https://find-government-grants.service.gov.uk/grants/creative-catalyst-2024-1)\n\t- ## **Project Details**:\n\t\t- Partners: SM Robotics Ltd (Lead), Flossverse Ltd.\n\t\t- Competition: Feasibility studies for AI solutions.\n\t\t- Application Name: VisionFlow.\n\t\t- Duration: 5 months, starting 11 September 2023.\n\t\t- Research Category: Feasibility studies.\n\t\t- Summary: VisionFlow aims to develop pre-visualization workflows integrating machine learning and robot control software for virtual production.\n\t- ## **Project Summary and Public Description**:\n\t\t- VisionFlow will develop innovative workflows for the virtual production industry.\n\t\t- It inverts existing workflows, focusing on scene-driven camera motion.\n\t\t- Key features include the use of open-source AI and a simpler interface for non-artists to create 3D environments.\n\t\t- The project will build upon the open-source Flossverse telecollaboration stack.\n\t- ## **InnovateUK Feedback**:\n\t\t- Aligns with the competition's focus on integrating machine learning in video production.\n\t\t- Assessor Feedback: Generally considered in scope, but involvement of a video production company could strengthen alignment.\n\t- ## **Need or Challenge**:\n\t\t- The project addresses the reluctance in the film industry to adopt AI and ML technologies due to tight margins and complexity.\n\t\t- VisionFlow introduces \"parallax plates as a service\", integrating robotics with ML-based video generation.\n\t\t- Key benefits include increased productivity in pre-visualization and improved collaboration.\n\t\t- Assessor Feedback: Positive recognition of the project's potential to improve productivity in video content production. However, a closer association with a video production company could enhance the application's relevance and impact.\n\t- ## **Approach and Innovation**:\n\t\t- VisionFlow will integrate AI-generated video with robotics for innovative virtual production.\n\t\t- Plans to develop new tele-collaboration technologies for virtual production.\n\t\t- Focus on disrupting traditional workflows with more efficient solutions.\n\t\t- Assessor Feedback: The approach is plausible but lacks detailed deliverables and milestones for monitoring progress. A more comprehensive analysis of the competitive landscape is suggested.\n\t- ## **Team and Resources**:\n\t\t- Dr. Sean Chase Mandrake Hill and Dr. John O'Hare lead the project with significant expertise in robotics and tele-collaboration.\n\t\t- Potential collaborations with G6Moco and Pathway XR Innovation Lab.\n\t\t- Assessor Feedback: The team is well-qualified but would benefit from direct involvement with a video production company.\n\t- ## **Market Awareness**:\n\t\t- The project targets the rapidly growing virtual production market.\n\t\t- Potential for significant savings in both small and large-scale virtual production facilities.\n\t\t- Assessor Feedback: Good market understanding but requires further research on barriers to entry and secondary markets.\n\t- ## **Outcomes and Route to Market**:\n\t\t- Focuses on demonstrating cost savings and efficiency in virtual production.\n\t\t- Plans to engage with early adopters and expand to global markets.\n\t\t- Assessor Feedback: Credible route to market but needs more detailed financial projections and dissemination plans.\n\t- ## **Wider Impacts**:\n\t\t- **Economic Benefits**:\n\t\t- Potential savings for virtual production facilities, reducing costs.\n\t\t- End-users benefit from reduced production costs.\n\t\t- Drives innovation in virtual production, encouraging market growth.\n\t\t- Contributes to UK's economic growth by attracting investments and creating jobs.\n\t\t- **Impact on Government Priorities**:\n\t\t- Supports government focus on creative industries and digital technologies.\n\t\t- **Environmental Impacts**:\n\t\t- Positive: Reduces film industry's ecological footprint.\n\t\t- Negative: Potential increase in energy consumption due to digital technologies.\n\t\t- **Regional Impacts and Job Creation**:\n\t\t- Supports regional virtual production hubs in the UK.\n\t\t- Encourages job creation and fosters creative communities.\n\t\t- **Diversity and Social Inclusion**:\n\t\t- Democratizes access to virtual production tools, promoting diversity in film and media.\n\t\t- **Health, Safety, and Quality of Life**:\n\t\t- Improves safety in film production by reducing on-location shoot risks.\n\t- ## **Risks**:\n\t\t- ### *Technical Risks*:\n\t\t- Integration challenges, limitations of AI, compatibility issues.\n\t\t- ### **Commercial Risks**:\n\t\t- Market adoption uncertainty, competition, monetization challenges.\n\t\t- ### **Managerial Risks**:\n\t\t- Collaboration efficiency, scope and timeline management, expertise recruitment.\n\t\t- ### **Legal Risks**:\n\t\t- Data protection and AI risk analysis.\n\t\t- ### **Mitigation Strategies**:\n\t\t- Dedicate resources for testing and refining, focus on achievable goals, conduct market analysis, establish clear communication, and management practices.\n\n## Current Landscape (2025)\n\n- Industry adoption and implementations\n  - Metaverse platforms continue to evolve with focus on interoperability and open standards\n  - Web3 integration accelerating with decentralised identity and asset ownership\n  - Enterprise adoption growing in virtual collaboration, training, and digital twins\n  - UK companies increasingly active in metaverse development and immersive technologies\n\n- Technical capabilities\n  - Real-time rendering at photorealistic quality levels\n  - Low-latency networking enabling seamless multi-user experiences\n  - AI-driven content generation and procedural world building\n  - Spatial audio and haptics enhancing immersion\n\n- UK and North England context\n  - Manchester: Digital Innovation Factory supports metaverse startups and research\n  - Leeds: Holovis leads in immersive experiences for entertainment and training\n  - Newcastle: University research in spatial computing and interactive systems\n  - Sheffield: Advanced manufacturing using digital twin technology\n\n- Standards and frameworks\n  - Metaverse Standards Forum driving interoperability protocols\n  - WebXR enabling browser-based immersive experiences\n  - glTF and USD for 3D asset interchange\n  - Open Metaverse Interoperability Group defining cross-platform standards\n\n## Metadata\n\n- **Last Updated**: 2025-11-16\n- **Review Status**: Automated remediation with 2025 context\n- **Verification**: Academic sources verified\n- **Regional Context**: UK/North England where applicable",
  "properties": {
    "id": "vp-robotics-project-owl-axioms",
    "collapsed": "true",
    "- ontology": "true",
    "- term-id": "mv-765735727723",
    "- preferred-term": "VP robotics project",
    "- source-domain": "metaverse",
    "- status": "active",
    "- public-access": "true",
    "- definition": "A component of the metaverse ecosystem focusing on vp robotics project.",
    "- maturity": "mature",
    "- authority-score": "0.85",
    "- owl:class": "mv:VpRoboticsProject",
    "- owl:physicality": "ConceptualEntity",
    "- owl:role": "Concept",
    "- belongsToDomain": "[[MetaverseDomain]]",
    "- enables": "[[ImmersiveExperience]], [[Presence]], [[SpatialComputing]]",
    "- requires": "[[DisplayTechnology]], [[TrackingSystem]], [[RenderingEngine]]",
    "- bridges-to": "[[HumanComputerInteraction]], [[ComputerVision]], [[Robotics]]",
    "public": "true"
  },
  "backlinks": [],
  "wiki_links": [
    "TrackingSystem",
    "ImmersiveExperience",
    "ComputerVision",
    "RenderingEngine",
    "SpatialComputing",
    "Robotics",
    "HumanComputerInteraction",
    "MetaverseDomain",
    "DisplayTechnology",
    "Presence"
  ],
  "ontology": {
    "term_id": "mv-765735727723",
    "preferred_term": "VP robotics project",
    "definition": "A component of the metaverse ecosystem focusing on vp robotics project.",
    "source_domain": "metaverse",
    "maturity_level": null,
    "authority_score": 0.85
  }
}