{
  "title": "Remote development over SSH tips.",
  "content": "- ### OntologyBlock\n  id:: remote-development-over-ssh-tips.-ontology\n  collapsed:: true\n\t- ontology:: true\n\t- term-id:: mv-959859783096\n\t- preferred-term:: Remote development over SSH tips.\n\t- source-domain:: metaverse\n\t- status:: active\n\t- public-access:: true\n\t- definition:: A component of the metaverse ecosystem focusing on remote development over ssh tips..\n\t- maturity:: mature\n\t- authority-score:: 0.85\n\t- owl:class:: mv:RemoteDevelopmentOverSshTips\n\t- owl:physicality:: ConceptualEntity\n\t- owl:role:: Process\n\t- belongsToDomain:: [[MetaverseDomain]]\n\n\t- #### OWL Axioms\n\t  id:: remote-development-over-ssh-tips.-owl-axioms\n\t  collapsed:: true\n\t\t- ```clojure\n\t\t  Declaration(Class(mv:RemoteDevelopmentOverSshTips))\n\n\t\t  # Classification\n\t\t  SubClassOf(mv:RemoteDevelopmentOverSshTips mv:ConceptualEntity)\n\t\t  SubClassOf(mv:RemoteDevelopmentOverSshTips mv:Process)\n\n\t\t  # Domain classification\n\t\t  SubClassOf(mv:RemoteDevelopmentOverSshTips\n\t\t    ObjectSomeValuesFrom(mv:belongsToDomain mv:MetaverseDomain)\n\t\t  )\n\n\t\t  # Annotations\n\t\t  AnnotationAssertion(rdfs:label mv:RemoteDevelopmentOverSshTips \"Remote development over SSH tips.\"@en)\n\t\t  AnnotationAssertion(rdfs:comment mv:RemoteDevelopmentOverSshTips \"A component of the metaverse ecosystem focusing on remote development over ssh tips..\"@en)\n\t\t  AnnotationAssertion(dcterms:identifier mv:RemoteDevelopmentOverSshTips \"mv-959859783096\"^^xsd:string)\n\t\t  ```\n\n# Remote development over SSH tips.\n\t- ## Overview\n\t\t- This guide provides a comprehensive approach to maximizing SSH connection stability and ensuring persistent development sessions when using VS Code Remote SSH. By combining robust keepalive settings with tmux session management, you'll maintain productive remote development workflows even with unstable network connections.\n\t- ## Goals\n\t\t- **Prevent SSH timeouts** with comprehensive keepalive configurations\n\t\t- **Maintain persistent sessions** using tmux for process continuity\n\t\t- **Automate reconnection** to the same working environment\n\t\t- **Minimize connection overhead** with SSH multiplexing\n\t- ## 1. Client-Side SSH Configuration\n\t\t- ### Basic Keepalive Settings\n\t\t- Edit `~/.ssh/config` on your local machine and add or update your host entry:\n\t\t  \n\t\t  ```\n\t\t  Host my-remote\n\t\t    HostName example.com\n\t\t    User myuser\n\t\t    ServerAliveInterval 30\n\t\t    ServerAliveCountMax 4\n\t\t    TCPKeepAlive yes\n\t\t    ControlMaster auto\n\t\t    ControlPersist 10m\n\t\t    ControlPath ~/.ssh/cm-%r@%h:%p\n\t\t  ```\n\t\t- ### Configuration Explained\n\t\t- | \n\t\t  | Setting | \n\t\t  | Purpose | \n\t\t  |\n\t\t  \n\t\t  | ---- |\n\t\t  \n\t\t  | \n\t\t  | `ServerAliveInterval 30` | \n\t\t  | Send keepalive packet every 30 seconds | \n\t\t  |\n\t\t  \n\t\t  | \n\t\t  | `ServerAliveCountMax 4` | \n\t\t  | Disconnect after 4 failed keepalive attempts | \n\t\t  |\n\t\t  \n\t\t  | \n\t\t  | `TCPKeepAlive yes` | \n\t\t  | Enable TCP-layer keepalive packets | \n\t\t  |\n\t\t  \n\t\t  | \n\t\t  | `ControlMaster auto` | \n\t\t  | Enable connection multiplexing | \n\t\t  |\n\t\t  \n\t\t  | \n\t\t  | `ControlPersist 10m` | \n\t\t  | Keep master connection alive for 10 minutes after last session closes | \n\t\t  |\n\t\t  \n\t\t  | \n\t\t  | `ControlPath` | \n\t\t  | Define socket file location for multiplexed connections | \n\t\t  |\n\t- ## 2. Server-Side SSH Configuration (Optional)\n\t- ### Configuring sshd for Better Stability\n\t  \n\t  Edit `/etc/ssh/sshd_config` on the remote server (requires sudo):\n\t  \n\t  ```\n\t  ClientAliveInterval 60\n\t  ClientAliveCountMax 3\n\t  TCPKeepAlive yes\n\t  ```\n\t  \n\t  Apply changes:\n\t  \n\t  ```\n\t  sudo systemctl restart sshd\n\t  ```\n\t  \n\t  > \n\t  \n\t  **Note:** Server-side keepalive helps detect dead clients faster and maintains cleaner session state.\n\t- ## 3. VS Code Terminal Integration with tmux\n\t- ### Automatic tmux Session Management\n\t  \n\t  Configure VS Code to automatically use tmux for all remote terminals. Add to your VS Code settings (`settings.json`):\n\t  \n\t  ```\n\t  {\n\t  \"terminal.integrated.profiles.linux\": {\n\t    \"tmux\": {\n\t      \"path\": \"tmux\",\n\t      \"args\": [\"new-session\", \"-A\", \"-s\", \"vscode:${workspaceFolderBasename}\"]\n\t    }\n\t  },\n\t  \"terminal.integrated.defaultProfile.linux\": \"tmux\"\n\t  }\n\t  ```\n\t- ### Benefits\n\t- **Workspace-specific sessions**: Each project gets its own tmux session\n\t- **Automatic attachment**: `new-session -A` attaches to existing sessions or creates new ones\n\t- **Persistent state**: Terminal sessions survive VS Code restarts and disconnections\n\t- ## 4. Shell-Based Auto-Attachment\n\t- ### Automatic tmux for SSH Sessions\n\t  \n\t  Add to your remote user's `~/.bashrc` or `~/.zshrc`:\n\t  \n\t  ```\n\t  # Auto-attach to tmux for SSH sessions only\n\t  if [[ $- =~ i ]] && [[ -z \"$TMUX\" ]] && [[ -n \"$SSH_TTY\" ]]; then\n\t    tmux attach-session -t ssh_tmux || tmux new-session -s ssh_tmux\n\t  fi\n\t  ```\n\t  \n\t  This ensures:\n\t- Only interactive SSH sessions trigger tmux\n\t- Local terminal sessions remain unaffected\n\t- Seamless persistence across all SSH clients\n\t- ## 5. Quick Connection Methods\n\t- ### One-Liner SSH with tmux\n\t  \n\t  For quick connections or aliases:\n\t  \n\t  ```\n\t  ssh -t my-remote \"tmux new-session -A -s vscode\"\n\t  ```\n\t- ### Creating Useful Aliases\n\t  \n\t  Add to your local `~/.bashrc` or `~/.zshrc`:\n\t  \n\t  ```\n\t  alias dev-remote='ssh -t my-remote \"tmux new-session -A -s dev\"'\n\t  alias work-remote='ssh -t my-remote \"tmux new-session -A -s work\"'\n\t  ```\n\t- ## 6. tmux Best Practices\n\t- ### Essential tmux Commands\n\t  \n\t  | \n\t  | Command | \n\t  | Action | \n\t  |\n\t  \n\t  | ---- |\n\t  \n\t  | \n\t  | `Ctrl+b d` | \n\t  | Detach from session | \n\t  |\n\t  \n\t  | \n\t  | `tmux ls` | \n\t  | List all sessions | \n\t  |\n\t  \n\t  | \n\t  | `tmux attach -t session-name` | \n\t  | Attach to specific session | \n\t  |\n\t  \n\t  | \n\t  | `Ctrl+b c` | \n\t  | Create new window | \n\t  |\n\t  \n\t  | \n\t  | `Ctrl+b n/p` | \n\t  | Next/Previous window | \n\t  |\n\t  \n\t  | \n\t  | `Ctrl+b %` | \n\t  | Split pane vertically | \n\t  |\n\t  \n\t  | \n\t  | `Ctrl+b \"` | \n\t  | Split pane horizontally | \n\t  |\n\t- ### Session Organization\n\t  \n\t  ```\n\t  # Create project-specific sessions\n\t  tmux new-session -s project-frontend\n\t  tmux new-session -s project-backend\n\t  tmux new-session -s project-database\n\t  \n\t  # Switch between sessions\n\t  Ctrl+b s  # Interactive session selector\n\t  ```\n\t- ## 7. Handling VS Code Reconnections\n\t- ### What Persists\n\t  \n\t  ✅ **Persisted through disconnections:**\n\t- Terminal sessions and running processes\n\t- tmux windows and panes layout\n\t- Command history within tmux\n\t- Background jobs and services\n\t  \n\t  ❌ **Not persisted (VS Code specific):**\n\t- Debug sessions\n\t- VS Code UI state\n\t- Extension states\n\t- Unsaved file changes\n\t- ### Recovery Workflow\n\t- **Reconnect to VS Code Remote SSH**\n\t- **Open integrated terminal** (automatically attaches to tmux)\n\t- **Resume work** with all processes intact\n\t- ## 8. Advanced Resilience Strategies\n\t- ### For Unstable Networks\n\t  \n\t  ```\n\t  # More aggressive keepalive for mobile/WiFi\n\t  Host mobile-remote\n\t    HostName example.com\n\t    User myuser\n\t    ServerAliveInterval 15\n\t    ServerAliveCountMax 6\n\t    ConnectTimeout 30\n\t    ConnectionAttempts 3\n\t  ```\n\t- ### Handling Long-Running Tasks\n\t  \n\t  ```\n\t  # Use tmux for long-running processes\n\t  tmux new-session -d -s batch-job 'python long_running_script.py'\n\t  \n\t  # Check status later\n\t  tmux attach -t batch-job\n\t  ```\n\t- ### Network Recovery Script\n\t  \n\t  Create `~/.local/bin/reconnect-vscode`:\n\t  \n\t  ```\n\t  #!/bin/bash\n\t  # Kill stale connections\n\t  pkill -f \"ssh.*my-remote\"\n\t  # Clear control socket\n\t  rm -f ~/.ssh/cm-*\n\t  # Reconnect\n\t  code --remote ssh-remote+my-remote /path/to/project\n\t  ```\n\t- ## 9. Troubleshooting\n\t- ### Common Issues and Solutions\n\t- #### SSH Connection Drops Frequently\n\t  \n\t  ```\n\t  # Test connection stability\n\t  while true; do \n\t    date\n\t    ssh my-remote \"echo 'Connection alive'\"\n\t    sleep 60\n\t  done\n\t  ```\n\t- #### tmux Sessions Not Persisting\n\t  \n\t  ```\n\t  # Check tmux server status\n\t  tmux info\n\t  # Verify session exists\n\t  tmux ls\n\t  # Force new server if corrupted\n\t  tmux kill-server\n\t  ```\n\t- #### VS Code Not Attaching to tmux\n\t- Verify terminal profile in settings\n\t- Check remote shell configuration\n\t- Test manual tmux attachment\n\t- ## 10. Performance Optimization\n\t- ### SSH Compression for Slow Networks\n\t  \n\t  ```\n\t  Host slow-remote\n\t    Compression yes\n\t    CompressionLevel 6\n\t  ```\n\t- ### Reducing Connection Overhead\n\t  \n\t  ```\n\t  # Reuse SSH connections for git\n\t  Host github.com\n\t    ControlMaster auto\n\t    ControlPersist 600\n\t  ```\n\t- ## Quick Start Checklist\n\t- [ ] Configure local SSH client (`~/.ssh/config`)\n\t- [ ] Set up VS Code terminal profiles\n\t- [ ] Install tmux on remote server\n\t- [ ] Configure shell auto-attachment (optional)\n\t- [ ] Test connection stability\n\t- [ ] Create project-specific tmux sessions\n\t- [ ] Set up recovery aliases\n\t- ## Conclusion\n\t  \n\t  This configuration provides a robust foundation for remote development with VS Code. The combination of SSH keepalive settings and tmux session management ensures that network interruptions become minor inconveniences rather than productivity killers. Your development environment remains exactly as you left it, ready for immediate resumption of work.\n\t  \n\t  <!--EndFragment-->\n\n## Current Landscape (2025)\n\n- Industry adoption and implementations\n  - Metaverse platforms continue to evolve with focus on interoperability and open standards\n  - Web3 integration accelerating with decentralised identity and asset ownership\n  - Enterprise adoption growing in virtual collaboration, training, and digital twins\n  - UK companies increasingly active in metaverse development and immersive technologies\n\n- Technical capabilities\n  - Real-time rendering at photorealistic quality levels\n  - Low-latency networking enabling seamless multi-user experiences\n  - AI-driven content generation and procedural world building\n  - Spatial audio and haptics enhancing immersion\n\n- UK and North England context\n  - Manchester: Digital Innovation Factory supports metaverse startups and research\n  - Leeds: Holovis leads in immersive experiences for entertainment and training\n  - Newcastle: University research in spatial computing and interactive systems\n  - Sheffield: Advanced manufacturing using digital twin technology\n\n- Standards and frameworks\n  - Metaverse Standards Forum driving interoperability protocols\n  - WebXR enabling browser-based immersive experiences\n  - glTF and USD for 3D asset interchange\n  - Open Metaverse Interoperability Group defining cross-platform standards\n\n## Metadata\n\n- **Last Updated**: 2025-11-16\n- **Review Status**: Automated remediation with 2025 context\n- **Verification**: Academic sources verified\n- **Regional Context**: UK/North England where applicable",
  "properties": {
    "id": "remote-development-over-ssh-tips.-owl-axioms",
    "collapsed": "true",
    "- ontology": "true",
    "- term-id": "mv-959859783096",
    "- preferred-term": "Remote development over SSH tips.",
    "- source-domain": "metaverse",
    "- status": "active",
    "- public-access": "true",
    "- definition": "A component of the metaverse ecosystem focusing on remote development over ssh tips..",
    "- maturity": "mature",
    "- authority-score": "0.85",
    "- owl:class": "mv:RemoteDevelopmentOverSshTips",
    "- owl:physicality": "ConceptualEntity",
    "- owl:role": "Process",
    "- belongsToDomain": "[[MetaverseDomain]]"
  },
  "backlinks": [],
  "wiki_links": [
    " -n \"$SSH_TTY\" ",
    " $- =~ i ",
    " -z \"$TMUX\" ",
    "MetaverseDomain"
  ],
  "ontology": {
    "term_id": "mv-959859783096",
    "preferred_term": "Remote development over SSH tips.",
    "definition": "A component of the metaverse ecosystem focusing on remote development over ssh tips..",
    "source_domain": "metaverse",
    "maturity_level": null,
    "authority_score": 0.85
  }
}