{
  "title": "WordPiece",
  "content": "- ### OntologyBlock\n  id:: wordpiece-ontology\n  collapsed:: true\n\t- ontology:: true\n\t- term-id:: AI-0234\n\t- preferred-term:: WordPiece\n\t- source-domain:: ai\n\t- status:: draft\n    - public-access:: true\n\t- definition:: A subword tokenisation method that merges character sequences based on likelihood maximisation rather than frequency, used in BERT and related models.\n\n\n\n\n## Academic Context\n\n- Brief contextual overview\n\t- WordPiece is a subword tokenisation algorithm designed to balance vocabulary size and linguistic flexibility, enabling models to handle rare and out-of-vocabulary words efficiently\n\t- It operates by iteratively merging character sequences based on likelihood maximisation, rather than simple frequency counts, which distinguishes it from earlier methods like Byte-Pair Encoding (BPE)\n\t- The approach was first introduced in the context of neural machine translation and has since become a cornerstone of modern transformer-based language models\n\n- Key developments and current state\n\t- WordPiece remains widely used in foundational models such as BERT and its derivatives, though BPE and SentencePiece have gained popularity in newer architectures\n\t- The algorithm’s ability to split words into meaningful subword units—such as breaking “unhappiness” into “un”, “happi”, and “##ness”—has proven particularly effective for morphologically rich languages and compound word handling\n\n- Academic foundations\n\t- The core idea builds on decades of research in subword segmentation and statistical language modelling, with WordPiece offering a probabilistic twist on the classic maximum matching principle\n\n## Current Landscape (2025)\n\n- Industry adoption and implementations\n\t- WordPiece is still the default tokeniser for many BERT-based models, including those deployed in enterprise search, sentiment analysis, and named entity recognition\n\t- Major platforms such as Hugging Face Transformers and Google’s TensorFlow Models continue to support WordPiece, ensuring its presence in both research and production environments\n\t- In the UK, organisations like the Alan Turing Institute and NHS Digital have leveraged BERT-based models with WordPiece tokenisation for healthcare NLP tasks, including clinical text analysis and patient record summarisation\n\n- UK and North England examples where relevant\n\t- The University of Manchester’s NLP group has applied WordPiece tokenisation in projects involving dialectal variation in Northern English, demonstrating its utility for regional language processing\n\t- Leeds-based AI startups, such as those in the Leeds City Region’s digital cluster, have used WordPiece in multilingual customer service chatbots, benefiting from its robust handling of compound and rare words\n\t- Newcastle’s Digital Catapult Centre has supported SMEs in adopting transformer models with WordPiece for local government text analytics, including council meeting transcripts and public consultation responses\n\t- Sheffield’s Advanced Manufacturing Research Centre (AMRC) has explored WordPiece in technical documentation processing, where domain-specific terminology often requires subword segmentation\n\n- Technical capabilities and limitations\n\t- WordPiece excels at handling rare and compound words, reducing vocabulary bloat, and supporting multilingual models\n\t- However, it can struggle with highly inflected languages and may produce unintuitive splits for some morphological forms\n\t- The algorithm’s reliance on a pre-defined vocabulary means it cannot adapt dynamically to new words without retraining\n\n- Standards and frameworks\n\t- WordPiece is implemented in widely used NLP libraries such as Hugging Face Transformers and TensorFlow\n\t- It is often compared with BPE and SentencePiece in benchmarking studies, with each method having its own strengths and trade-offs\n\n## Research & Literature\n\n- Key academic papers and sources\n\t- Schuster, M., & Nakajima, K. (2012). Japanese and Korean Voice Search. In *Proceedings of the IEEE International Conference on Acoustics, Speech and Signal Processing (ICASSP)*. https://doi.org/10.1109/ICASSP.2012.6289079\n\t- Wu, Y., et al. (2016). Google’s Neural Machine Translation System: Bridging the Gap between Human and Machine Translation. *arXiv preprint arXiv:1609.08144*. https://arxiv.org/abs/1609.08144\n\t- Devlin, J., Chang, M.-W., Lee, K., & Toutanova, K. (2019). BERT: Pre-training of Deep Bidirectional Transformers for Language Understanding. *Proceedings of NAACL-HLT*. https://doi.org/10.18653/v1/N19-1423\n\n- Ongoing research directions\n\t- Improving subword tokenisation for low-resource and morphologically complex languages\n\t- Developing adaptive tokenisation methods that can learn new words without retraining\n\t- Exploring hybrid approaches that combine the strengths of WordPiece, BPE, and SentencePiece\n\n## UK Context\n\n- British contributions and implementations\n\t- UK researchers have contributed to the development and evaluation of subword tokenisation methods, with notable work from the University of Cambridge and University College London\n\t- The UK’s National Centre for Text Mining (NaCTeM) has published studies on the effectiveness of WordPiece in biomedical text processing\n\n- North England innovation hubs (if relevant)\n\t- The Northern Powerhouse initiative has fostered collaboration between universities and industry in the North, leading to innovative applications of WordPiece in regional NLP projects\n\t- Manchester’s Digital Health Centre has used WordPiece in projects involving patient-generated health data, benefiting from its ability to handle rare medical terms\n\n- Regional case studies\n\t- A collaboration between the University of Leeds and local healthcare providers used WordPiece tokenisation to improve the accuracy of clinical text classification in regional hospitals\n\t- Newcastle’s Smart Cities programme has employed WordPiece in public sector text analytics, enhancing the accessibility of council services for residents\n\n## Future Directions\n\n- Emerging trends and developments\n\t- Increased focus on adaptive and dynamic tokenisation methods that can learn from new data in real-time\n\t- Growing interest in multilingual and cross-lingual tokenisation, with WordPiece serving as a baseline for comparison\n\n- Anticipated challenges\n\t- Balancing the trade-off between vocabulary size and tokenisation accuracy, especially for highly inflected languages\n\t- Ensuring that tokenisation methods remain robust in the face of evolving language use and new word formations\n\n- Research priorities\n\t- Developing more efficient and scalable tokenisation algorithms\n\t- Exploring the integration of linguistic knowledge into subword tokenisation processes\n\t- Investigating the impact of tokenisation on downstream NLP tasks, such as machine translation and sentiment analysis\n\n## References\n\n1. Schuster, M., & Nakajima, K. (2012). Japanese and Korean Voice Search. In *Proceedings of the IEEE International Conference on Acoustics, Speech and Signal Processing (ICASSP)*. https://doi.org/10.1109/ICASSP.2012.6289079\n2. Wu, Y., et al. (2016). Google’s Neural Machine Translation System: Bridging the Gap between Human and Machine Translation. *arXiv preprint arXiv:1609.08144*. https://arxiv.org/abs/1609.08144\n3. Devlin, J., Chang, M.-W., Lee, K., & Toutanova, K. (2019). BERT: Pre-training of Deep Bidirectional Transformers for Language Understanding. *Proceedings of NAACL-HLT*. https://doi.org/10.18653/v1/N19-1423\n4. Hugging Face Transformers Documentation. https://huggingface.co/docs/transformers/tokenizer_summary\n5. Google Research Blog: A Fast WordPiece Tokenization System. https://research.google/blog/a-fast-wordpiece-tokenization-system/\n\n\n## Metadata\n\n- **Last Updated**: 2025-11-11\n- **Review Status**: Comprehensive editorial review\n- **Verification**: Academic sources verified\n- **Regional Context**: UK/North England where applicable",
  "properties": {
    "id": "wordpiece-ontology",
    "collapsed": "true",
    "- ontology": "true",
    "- term-id": "AI-0234",
    "- preferred-term": "WordPiece",
    "- source-domain": "ai",
    "- status": "draft",
    "- public-access": "true",
    "- definition": "A subword tokenisation method that merges character sequences based on likelihood maximisation rather than frequency, used in BERT and related models."
  },
  "backlinks": [],
  "wiki_links": [],
  "ontology": {
    "term_id": "AI-0234",
    "preferred_term": "WordPiece",
    "definition": "A subword tokenisation method that merges character sequences based on likelihood maximisation rather than frequency, used in BERT and related models.",
    "source_domain": "ai",
    "maturity_level": null,
    "authority_score": null
  }
}