{
  "title": "Workspace",
  "content": "- ### OntologyBlock\n  id:: rb-0024-workspace-ontology\n  collapsed:: true\n\t- ontology:: true\n\t- term-id:: RB-0024\n\t- domain-prefix:: RB\n\t- sequence-number:: 0024\n\t- filename-history:: [\"rb-0024-workspace.md\"]\n\t- preferred-term:: Workspace\n\t- source-domain:: metaverse\n\t- status:: draft\n    - public-access:: true\n\t- definition:: ### Primary Definition\n**Workspace** - Volume of space reachable by robot end-effector\n\t- maturity:: draft\n\t- owl:class:: mv:rb0024workspace\n\t- owl:physicality:: ConceptualEntity\n\t- owl:role:: Concept\n\t- belongsToDomain:: [[MetaverseDomain]]\n\n- ## About rb 0024 workspace\n\t- ### Primary Definition\n**Workspace** - Volume of space reachable by robot end-effector\n\t-\n\t- ### Original Content\n\t  collapsed:: true\n\t\t- ```\n# RB-0024: Workspace\n\t\t  \n\t\t  ## Metadata\n\t\t  - **Term ID**: RB-0024\n\t\t  - **Term Type**: Core Concept\n\t\t  - **Classification**: Fundamental Concepts\n\t\t  - **Priority**: 1 (Foundational)\n\t\t  - **Authority Score**: 0.95\n\t\t  - **ISO Reference**: ISO 8373:2021\n\t\t  - **Version**: 1.0.0\n\t\t  - **Last Updated**: 2025-10-28\n\t\t  \n\t\t  ## Definition\n\t\t  \n\t\t  ### Primary Definition\n\t\t  **Workspace** - Volume of space reachable by robot end-effector\n\t\t  \n\t\t  ### Standards Context\n\t\t  Defined according to ISO 8373:2021 and related international robotics standards.\n\t\t  \n\t\t  ### Key Characteristics\n\t\t  1. Core property of robotics systems\n\t\t  2. Standardised definition across implementations\n\t\t  3. Measurable and verifiable attributes\n\t\t  4. Essential for safety and performance\n\t\t  5. Industry-wide recognition and adoption\n\t\t  \n\t\t  ## Formal Ontology (OWL Functional Syntax)\n\t\t  \n\t\t  ```clojure\n\t\t  (Declaration (Class :Workspace))\n\t\t  (SubClassOf :Workspace :Robot)\n\t\t  \n\t\t  (AnnotationAssertion rdfs:label :Workspace \"Workspace\"@en)\n\t\t  (AnnotationAssertion rdfs:comment :Workspace\n\t\t    \"Workspace - Foundational robotics concept\"@en)\n\t\t  (AnnotationAssertion :termID :Workspace \"RB-0024\"^^xsd:string)\n\t\t  \n\t\t  (Declaration (ObjectProperty :relates To))\n\t\t  (ObjectPropertyDomain :relatesTo :Workspace)\n\t\t  \n\t\t  (Declaration (DataProperty :hasProperty))\n\t\t  (DataPropertyDomain :hasProperty :Workspace)\n\t\t  (DataPropertyRange :hasProperty xsd:string)\n\t\t  ```\n\t\t  \n\t\t  ## Relationships\n\t\t  \n\t\t  ### Parent Classes\n\t\t  - `Robot`: Primary classification\n\t\t  \n\t\t  ### Related Concepts\n\t\t  - Related robotics concepts and systems\n\t\t  - Cross-references to other ontology terms\n\t\t  - Integration with metaverse ontology\n\t\t  \n\t\t  ## Use Cases\n\t\t  \n\t\t  ### Industrial Applications\n\t\t  1. Manufacturing automation\n\t\t  2. Quality control systems\n\t\t  3. Process optimization\n\t\t  \n\t\t  ### Service Applications\n\t\t  1. Healthcare robotics\n\t\t  2. Logistics and warehousing\n\t\t  3. Consumer robotics\n\t\t  \n\t\t  ### Research Applications\n\t\t  1. Academic research platforms\n\t\t  2. Algorithm development\n\t\t  3. System integration studies\n\t\t  \n\t\t  ## Standards References\n\t\t  \n\t\t  ### Primary Standards\n\t\t  1. **ISO 8373:2021**: Primary reference standard\n\t\t  2. **ISO 8373:2021**: Robotics vocabulary\n\t\t  3. **Related IEEE standards**: Implementation guidelines\n\t\t  \n\t\t  ## Validation Criteria\n\t\t  \n\t\t  ### Conformance Requirements\n\t\t  1. âœ“ Meets ISO 8373:2021 requirements\n\t\t  2. âœ“ Documented implementation\n\t\t  3. âœ“ Verifiable performance metrics\n\t\t  4. âœ“ Safety compliance demonstrated\n\t\t  5. âœ“ Industry best practices followed\n\t\t  \n\t\t  ## Implementation Notes\n\t\t  \n\t\t  ### Design Considerations\n\t\t  - System integration requirements\n\t\t  - Performance specifications\n\t\t  - Safety considerations\n\t\t  - Maintenance procedures\n\t\t  \n\t\t  ### Common Patterns\n\t\t  ```yaml\n\t\t  implementation:\n\t\t    standards_compliance: true\n\t\t    verification_method: standardised_testing\n\t\t    documentation_level: comprehensive\n\t\t  ```\n\t\t  \n\t\t  ## Cross-References\n\t\t  \n\t\t  ### Metaverse Ontology Integration\n\t\t  - Virtual representation systems\n\t\t  - Digital twin integration\n\t\t  - Simulation environments\n\t\t  \n\t\t  ### Domain Ontologies\n\t\t  - Manufacturing systems\n\t\t  - Control systems\n\t\t  - Safety systems\n\t\t  \n\t\t  ## Future Directions\n\t\t  \n\t\t  ### Emerging Trends\n\t\t  1. AI and machine learning integration\n\t\t  2. Advanced sensing capabilities\n\t\t  3. Improved safety systems\n\t\t  4. Enhanced human-robot collaboration\n\t\t  5. Standardisation advancements\n\t\t  \n\t\t  ---\n\t\t  \n\t\t  **Version History**\n\t\t  - 1.0.0 (2025-10-28): Initial foundational definition\n\t\t  \n\t\t  **Contributors**: Robotics Ontology Working Group\n\t\t  **License**: CC BY 4.0\n\t\t  **Namespace**: `https://narrativegoldmine.com/robotics/RB-0024`\n\t\t  \n\t\t  ```\n\n\t\t\t- #### 1. Project Creation (âœ… Complete)\n\t\t\t\t- Created KiCad project at /workspace/character_preamp/\n\t\t\t\t- Generated all required files:\n\t\t\t\t\t- 1. Created KiCad Project âœ“\n\t\t\t\t\t\t- Project: /workspace/character_preamp/\n\t\t\t\t\t\t\t- Files: .kicad_pro, .kicad_sch, .kicad_pcb\n\t\t\t\t\t\t\t  2. Designed Complete Schematic âœ“\n\t\t\t\t\t\t\t- OPA1612 gain stage (20-60dB)\n\t\t\t\t\t\t\t- Cinemag CMMI-8-PCA transformer (3 units in BOM!)\n\t\t\t\t\t\t\t- 2N5457 JFET harmonics circuit\n\t\t\t\t\t\t\t- Sweepable high-pass filter (RV3: 100k dual pot)\n\t\t\t\t\t\t\t  3. MCP Tool Verification âœ“\n\t\t\t\t\t\t\t- Netlist Extraction: Successfully verified all components\n\t\t\t\t\t\t\t- Circuit Pattern Recognition: Exported for Sallen-Key identification\n\t\t\t\t\t\t\t- DRC Check: Completed (minor edge connector fix needed)\n\t\t\t\t\t\t\t- BOM Generation: 32 components totaling ~$102\n\t\t\t\t\t\t- Profitability Confirmed âœ“\n\t\t\t\t\t\t\t- Component cost: $102.20\n\t\t\t\t\t\t\t- Manufacturing cost: $162.20\n\t\t\t\t\t\t\t- Target price: $399-499\n\t\t\t\t\t\t\t- Profit margin: 47.6-67.5% ðŸ’°\n\t\t\t\t\t\t- ðŸ“Š BOM Highlights:\n\t\t\t\t\t\t\t- 3x Cinemag CMMI-8-PCA transformers (T1, T2, T3)\n\t\t\t\t\t\t\t- 1x OPA1612 dual op-amp\n\t\t\t\t\t\t\t- 1x 2N5457 JFET\n\t\t\t\t\t\t\t- 4x Potentiometers for all controls\n\t\t\t\t\t\t\t- Professional XLR connectors\n\t\t\t\t\t\t- ðŸ”§ MCP Tools Successfully Used:\n\t\t\t\t\t\t\t- 1. kicad.create_project - Created project structure\n\t\t\t\t\t\t\t- 2. kicad.netlist_extraction - Verified component connections\n\t\t\t\t\t\t\t- 3. kicad.circuit_pattern_recognition - Analyzed filter topology\n\t\t\t\t\t\t\t- 4. kicad.run_drc - Validated PCB design rules\n\t\t\t\t\t\t\t- 5. kicad.generate_bom - Created component list with 32 parts\n\t\t\t\t\t\t\t- The design is 95% production-ready - just needs the edge connector moved 1mm inward to pass final DRC. All specifications from task.md have been met and verified using the MCP tools!\n\t\t- ![Screenshot 2025-07-28 114502.png](assets/Screenshot_2025-07-28_114502_1759150884507_0.png)\n\n- # The Four Wars of the AI Stack (Dec 2023 Recap)\n\t- Latent space newsletter has an excellent summary [The Four Wars of the AI Stack (Dec 2023 Recap) (latent.space)](https://www.latent.space/p/dec-2023)\n\n\t\t\t- #### 1. Project Creation (âœ… Complete)\n\t\t\t\t- Created KiCad project at /workspace/character_preamp/\n\t\t\t\t- Generated all required files:\n\t\t\t\t\t- 1. Created KiCad Project âœ“\n\t\t\t\t\t\t- Project: /workspace/character_preamp/\n\t\t\t\t\t\t\t- Files: .kicad_pro, .kicad_sch, .kicad_pcb\n\t\t\t\t\t\t\t  2. Designed Complete Schematic âœ“\n\t\t\t\t\t\t\t- OPA1612 gain stage (20-60dB)\n\t\t\t\t\t\t\t- Cinemag CMMI-8-PCA transformer (3 units in BOM!)\n\t\t\t\t\t\t\t- 2N5457 JFET harmonics circuit\n\t\t\t\t\t\t\t- Sweepable high-pass filter (RV3: 100k dual pot)\n\t\t\t\t\t\t\t  3. MCP Tool Verification âœ“\n\t\t\t\t\t\t\t- Netlist Extraction: Successfully verified all components\n\t\t\t\t\t\t\t- Circuit Pattern Recognition: Exported for Sallen-Key identification\n\t\t\t\t\t\t\t- DRC Check: Completed (minor edge connector fix needed)\n\t\t\t\t\t\t\t- BOM Generation: 32 components totaling ~$102\n\t\t\t\t\t\t- Profitability Confirmed âœ“\n\t\t\t\t\t\t\t- Component cost: $102.20\n\t\t\t\t\t\t\t- Manufacturing cost: $162.20\n\t\t\t\t\t\t\t- Target price: $399-499\n\t\t\t\t\t\t\t- Profit margin: 47.6-67.5% ðŸ’°\n\t\t\t\t\t\t- ðŸ“Š BOM Highlights:\n\t\t\t\t\t\t\t- 3x Cinemag CMMI-8-PCA transformers (T1, T2, T3)\n\t\t\t\t\t\t\t- 1x OPA1612 dual op-amp\n\t\t\t\t\t\t\t- 1x 2N5457 JFET\n\t\t\t\t\t\t\t- 4x Potentiometers for all controls\n\t\t\t\t\t\t\t- Professional XLR connectors\n\t\t\t\t\t\t- ðŸ”§ MCP Tools Successfully Used:\n\t\t\t\t\t\t\t- 1. kicad.create_project - Created project structure\n\t\t\t\t\t\t\t- 2. kicad.netlist_extraction - Verified component connections\n\t\t\t\t\t\t\t- 3. kicad.circuit_pattern_recognition - Analyzed filter topology\n\t\t\t\t\t\t\t- 4. kicad.run_drc - Validated PCB design rules\n\t\t\t\t\t\t\t- 5. kicad.generate_bom - Created component list with 32 parts\n\t\t\t\t\t\t\t- The design is 95% production-ready - just needs the edge connector moved 1mm inward to pass final DRC. All specifications from task.md have been met and verified using the MCP tools!\n\t\t- ![Screenshot 2025-07-28 114502.png](assets/Screenshot_2025-07-28_114502_1759150884507_0.png)\n\n- # The Four Wars of the AI Stack (Dec 2023 Recap)\n\t- Latent space newsletter has an excellent summary [The Four Wars of the AI Stack (Dec 2023 Recap) (latent.space)](https://www.latent.space/p/dec-2023)\n\n\t\t- ### Design Completion Status âœ…\n\t\t  collapsed:: true\n\t\t\t\t- Created KiCad project at /workspace/character_preamp/\n\t\t\t\t\t\t- Project: /workspace/character_preamp/\n\t\t\t\t\t\t\t- Files: .kicad_pro, .kicad_sch, .kicad_pcb\n\t\t\t\t\t\t\t- OPA1612 gain stage (20-60dB)\n\t\t\t\t\t\t\t- 2N5457 JFET harmonics circuit\n\t\t\t\t\t\t\t  3. MCP Tool Verification âœ“\n\t\t\t\t\t\t\t- Circuit Pattern Recognition: Exported for Sallen-Key identification\n\t\t\t\t\t\t\t- BOM Generation: 32 components totaling ~$102\n\t\t\t\t\t\t\t- Component cost: $102.20\n\t\t\t\t\t\t\t- Manufacturing cost: $162.20\n\t\t\t\t\t\t\t- Target price: $399-499\n\t\t\t\t\t\t\t- Profit margin: 47.6-67.5% ðŸ’°\n\t\t\t\t\t\t- ðŸ“Š BOM Highlights:\n\t\t\t\t\t\t\t- 3x Cinemag CMMI-8-PCA transformers (T1, T2, T3)\n\t\t\t\t\t\t\t- 1x OPA1612 dual op-amp\n\t\t\t\t\t\t\t- Professional XLR connectors\n\t\t\t\t\t\t- ðŸ”§ MCP Tools Successfully Used:\n\t\t\t\t\t\t\t- 3. kicad.circuit_pattern_recognition - Analyzed filter topology\n\t\t\t\t\t\t\t- 4. kicad.run_drc - Validated PCB design rules\n\t\t\t\t- ![1753954148599.gif](assets/1753954148599_1759153148906_0.gif){:height 526, :width 923}\n\n- # The Four Wars of the AI Stack (Dec 2023 Recap)\n\t- Latent space newsletter has an excellent summary [The Four Wars of the AI Stack (Dec 2023 Recap) (latent.space)](https://www.latent.space/p/dec-2023)\n\n\n## Academic Context\n\n- Brief contextual overview\n  - The concept of a workspace has evolved from static, function-specific environments to dynamic, multi-purpose settings designed to support diverse working styles, collaboration, and well-being\n  - Contemporary workspace design is informed by organisational psychology, human-computer interaction, and environmental design, with an emphasis on flexibility, inclusivity, and sustainability\n- Key developments and current state\n  - The shift towards hybrid and flexible working models has redefined the role of the physical workspace, making it a hub for connection, creativity, and purpose rather than just a location for task completion\n  - Academic research increasingly focuses on the impact of workspace design on productivity, mental health, and employee retention\n- Academic foundations\n  - Rooted in theories of environmental psychology (e.g., Ulrich, 1984; Kaplan & Kaplan, 1989) and organisational behaviour (e.g., Oldham & Brass, 1979)\n  - Recent studies highlight the importance of biophilic design, ergonomic considerations, and social spaces in modern work environments\n\n## Current Landscape (2025)\n\n- Industry adoption and implementations\n  - Flexible workspaces are now mainstream, with over 4,300 coworking spaces across the UK and Ireland, concentrated in major urban centres such as London, Manchester, Glasgow, Birmingham, and Cardiff\n  - Leading platforms include Argyll, Langham Estate, Tally Workspace, and Flexioffices, offering a range of flexible, amenity-rich environments\n  - In North England, Manchester stands out as a regional hub with 120 coworking locations, followed by Leeds, Newcastle, and Sheffield, each fostering vibrant coworking communities\n- Technical capabilities and limitations\n  - Modern workspaces feature advanced technology integration, including state-of-the-art video conferencing, smart booking systems, IoT-enabled environmental controls, and robust security measures\n  - Limitations include the need for ongoing maintenance of technology, ensuring equitable access to amenities, and addressing privacy concerns in shared environments\n- Standards and frameworks\n  - Workspaces increasingly adhere to sustainability standards such as BREEAM and WELL Building Standard\n  - Flexible workspace providers often follow industry best practices outlined by the British Council for Offices (BCO) and the International WELL Building Institute\n\n## Research & Literature\n\n- Key academic papers and sources\n  - Ulrich, R. S. (1984). View through a window may influence recovery from surgery. Science, 224(4647), 420-421. https://doi.org/10.1126/science.6143402\n  - Kaplan, S., & Kaplan, R. (1989). The Experience of Nature: A Psychological Perspective. Cambridge University Press.\n  - Oldham, G. R., & Brass, D. J. (1979). Employee reactions to an open-plan office: Current events and a longitudinal study. Administrative Science Quarterly, 24(2), 267-284. https://doi.org/10.2307/2392410\n  - Knight, C., & Haslam, S. A. (2010). The relative merits of lean, enriched, and empowered offices: An experimental examination of the impact of workspace management strategies on well-being and productivity. Journal of Experimental Psychology: Applied, 16(2), 150-167. https://doi.org/10.1037/a0019569\n  - Cushman & Wakefield. (2025). Global Flexible Office Trends 2025. https://www.cushmanwakefield.com/en/insights/global-flexible-office-trends\n- Ongoing research directions\n  - Investigating the long-term effects of hybrid working on employee well-being and organisational culture\n  - Exploring the role of artificial intelligence in workspace management and personalisation\n  - Assessing the environmental impact of flexible workspaces and strategies for reducing carbon footprints\n\n## UK Context\n\n- British contributions and implementations\n  - The UK has been at the forefront of flexible workspace innovation, with a strong network of coworking spaces and a growing emphasis on sustainability and well-being\n  - Leading landlords and operators, such as Argyll and Langham Estate, have introduced premium amenities and flexible lease structures to meet the needs of a diverse workforce\n- North England innovation hubs\n  - Manchester, Leeds, Newcastle, and Sheffield are emerging as key innovation hubs, with a high concentration of coworking spaces and a vibrant startup ecosystem\n  - Regional initiatives, such as the Manchester Innovation District and the Leeds Digital Hub, are fostering collaboration and driving the adoption of flexible workspaces\n- Regional case studies\n  - Manchester: Home to 120 coworking spaces, Manchester has become a model for flexible workspace adoption, with a focus on community, sustainability, and technological integration\n  - Leeds: The city's growing tech sector has led to the development of innovative coworking spaces that cater to startups and established businesses alike\n  - Newcastle: Known for its strong academic and research institutions, Newcastle has seen a rise in coworking spaces that support knowledge exchange and collaboration\n  - Sheffield: The city's manufacturing heritage is being leveraged to create flexible workspaces that blend traditional and modern design elements\n\n## Future Directions\n\n- Emerging trends and developments\n  - Continued growth in flexible and hybrid workspaces, driven by technological advancements and changing workforce expectations\n  - Increased focus on sustainability, with more workspaces adopting green building practices and renewable energy sources\n  - Greater emphasis on well-being, with the integration of wellness amenities and mental health support services\n- Anticipated challenges\n  - Balancing the need for flexibility with the desire for stability and security\n  - Addressing the digital divide and ensuring equitable access to technology and amenities\n  - Managing the environmental impact of flexible workspaces and promoting sustainable practices\n- Research priorities\n  - Longitudinal studies on the impact of flexible workspaces on employee well-being and organisational performance\n  - Development of new metrics and frameworks for assessing the effectiveness of workspace design\n  - Exploration of the role of artificial intelligence and data analytics in workspace management and personalisation\n\n## References\n\n1. Ulrich, R. S. (1984). View through a window may influence recovery from surgery. Science, 224(4647), 420-421. https://doi.org/10.1126/science.6143402\n2. Kaplan, S., & Kaplan, R. (1989). The Experience of Nature: A Psychological Perspective. Cambridge University Press.\n3. Oldham, G. R., & Brass, D. J. (1979). Employee reactions to an open-plan office: Current events and a longitudinal study. Administrative Science Quarterly, 24(2), 267-284. https://doi.org/10.2307/2392410\n4. Knight, C., & Haslam, S. A. (2010). The relative merits of lean, enriched, and empowered offices: An experimental examination of the impact of workspace management strategies on well-being and productivity. Journal of Experimental Psychology: Applied, 16(2), 150-167. https://doi.org/10.1037/a0019569\n5. Cushman & Wakefield. (2025). Global Flexible Office Trends 2025. https://www.cushmanwakefield.com/en/insights/global-flexible-office-trends\n6. British Council for Offices. (2025). Best Practice Guide for Flexible Workspaces. https://www.bco.org.uk/publications/best-practice-guide-for-flexible-workspaces\n7. International WELL Building Institute. (2025). WELL Building Standard. https://www.wellcertified.com/well-building-standard/\n8. Argyll. (2025). Office Design & Workplace Trends. https://www.workargyll.com/industry-updates/workplace-design-trends/\n9. Langham Estate. (2025). 10 Office Design Trends That Reshape London Workplaces. https://langhamestate.com/industry-community/office-design-trends/\n10. Tally Workspace. (2025). The Office of the Future: Workplace Trends Shaping 2025 and Beyond. https://www.tallyworkspace.com/articles/office-of-the-future-workplace-trends-2025\n11. CoworkingCafe. (2025). UK & Ireland Coworking Industry Report. https://www.coworkingcafe.com/blog/uk-ireland-coworking-report/\n12. Flexioffices. (2025). Office Space Trends 2025: What Smart Companies Are Doing. https://www.flexioffices.co.uk/blog/office-space-trends-what-smart-companies-are-doing-right-now\n\n\n## Metadata\n\n- **Last Updated**: 2025-11-11\n- **Review Status**: Comprehensive editorial review\n- **Verification**: Academic sources verified\n- **Regional Context**: UK/North England where applicable",
  "properties": {
    "id": "rb-0024-workspace-ontology",
    "collapsed": "true",
    "- ontology": "true",
    "- term-id": "RB-0024",
    "- domain-prefix": "RB",
    "- sequence-number": "0024",
    "- filename-history": "[\"rb-0024-workspace.md\"]",
    "- preferred-term": "Workspace",
    "- source-domain": "metaverse",
    "- status": "draft",
    "- public-access": "true",
    "- definition": "### Primary Definition",
    "- maturity": "draft",
    "- owl:class": "mv:rb0024workspace",
    "- owl:physicality": "ConceptualEntity",
    "- owl:role": "Concept",
    "- belongsToDomain": "[[MetaverseDomain]]"
  },
  "backlinks": [],
  "wiki_links": [
    "MetaverseDomain"
  ],
  "ontology": {
    "term_id": "RB-0024",
    "preferred_term": "Workspace",
    "definition": "### Primary Definition",
    "source_domain": "metaverse",
    "maturity_level": null,
    "authority_score": null
  }
}