{
  "title": "XLNet",
  "content": "- ### OntologyBlock\n  id:: xlnet-ontology\n  collapsed:: true\n\t- ontology:: true\n\t- term-id:: AI-0221\n\t- preferred-term:: XLNet\n\t- source-domain:: ai\n\t- status:: draft\n    - public-access:: true\n\t- definition:: A generalised autoregressive pre-training method that learns bidirectional contexts by maximising expected likelihood over all permutations of the factorisation order, overcoming limitations of BERT's masked language modelling.\n\n\n\n\n## Academic Context\n\n- XLNet is a **generalised autoregressive pre-training method** that models language by maximising expected likelihood over all permutations of the factorisation order, enabling it to learn bidirectional contexts without masking tokens, unlike BERT.\n  - It builds upon the Transformer-XL architecture, which introduces recurrence in the attention mechanism to capture long-range dependencies beyond fixed-length contexts.\n  - The model employs a **two-stream self-attention mechanism**: a Content Stream encoding token semantics and a Query Stream maintaining positional dependencies, preventing information leakage from future tokens.\n  - This permutation-based training objective allows XLNet to integrate the strengths of autoregressive models (like GPT) and autoencoding models (like BERT), overcoming their respective limitations.\n- Since its initial release in 2019, XLNet has been foundational in advancing natural language understanding tasks such as question answering, natural language inference, sentiment analysis, and document ranking.\n\n## Current Landscape (2025)\n\n- XLNet remains influential in industry and academia for tasks requiring nuanced contextual understanding and long-range dependency modelling.\n  - It is widely adopted in platforms requiring robust language models, including search engines, conversational AI, and document analysis systems.\n  - Notable organisations continue to integrate XLNet or its derivatives for enhanced performance, often combining it with vector search frameworks like Milvus for scalable retrieval.\n- In the UK, especially in North England, research groups and AI startups in Manchester and Leeds leverage XLNet-based models for applications in healthcare NLP and legal document analysis, benefiting from its ability to process complex, lengthy texts.\n- Technical capabilities:\n  - XLNet excels at capturing bidirectional context without token masking, improving over BERT’s limitations.\n  - Its Transformer-XL backbone allows efficient handling of longer sequences, a critical advantage for document-level understanding.\n- Limitations include computational intensity due to permutation sampling during training, which remains an area for optimisation.\n- XLNet adheres to open standards in transformer architectures and is compatible with widely used frameworks such as PyTorch and TensorFlow.\n\n## Research & Literature\n\n- Key academic paper:\n  - Yang, Z., Dai, Z., Yang, Y., Carbonell, J., Salakhutdinov, R., & Le, Q. V. (2019). *XLNet: Generalized Autoregressive Pretraining for Language Understanding*. Advances in Neural Information Processing Systems, 32, 5753–5763.  \n    DOI: 10.48550/arXiv.1906.08237\n- Additional studies highlight XLNet’s enhanced contextual representations and superior handling of long-range dependencies compared to BERT and LSTM models (INCOFT 2025).\n- Ongoing research focuses on:\n  - Efficient training techniques to reduce computational costs.\n  - Domain-specific fine-tuning, particularly in finance, healthcare, and legal sectors.\n  - Multimodal extensions integrating text with images or audio for richer AI understanding.\n\n## UK Context\n\n- British AI research institutions, including those in Manchester and Newcastle, contribute to advancing XLNet applications, particularly in healthcare NLP and legal tech.\n- North England innovation hubs foster startups utilising XLNet for document analysis and sentiment detection, benefiting from the region’s strong academic-industry collaborations.\n- Regional case studies demonstrate XLNet’s utility in processing NHS clinical notes and legal contracts, where long-range context and bidirectional understanding are crucial.\n\n## Future Directions\n\n- Emerging trends:\n  - Development of more computationally efficient permutation-based models.\n  - Expansion into multimodal AI systems combining XLNet’s language understanding with other data types.\n  - Enhanced domain adaptation techniques for specialised industries.\n- Anticipated challenges include balancing model complexity with deployment efficiency and addressing ethical considerations in language model applications.\n- Research priorities emphasise sustainable AI practices, interpretability of permutation-based models, and integration with knowledge graphs for improved reasoning.\n\n## References\n\n1. Yang, Z., Dai, Z., Yang, Y., Carbonell, J., Salakhutdinov, R., & Le, Q. V. (2019). XLNet: Generalized Autoregressive Pretraining for Language Understanding. *Advances in Neural Information Processing Systems*, 32, 5753–5763. DOI: 10.48550/arXiv.1906.08237  \n2. INCOFT 2025. Enhanced Natural Language Understanding Using XLNet. *International Conference on Futuristic Technology*, 814–821.  \n3. RBC Borealis Research Blog. Understanding XLNet: Autoregressive Language Modelling with Permutations. 2025.  \n4. GitHub Repository: zihangdai/xlnet. (2019). XLNet: Generalized Permutation Language Modeling.  \n5. Zilliz. XLNet Explained: Generalized Autoregressive Pretraining for Enhanced Language Understanding. 2025.\n\n\n## Metadata\n\n- **Last Updated**: 2025-11-11\n- **Review Status**: Comprehensive editorial review\n- **Verification**: Academic sources verified\n- **Regional Context**: UK/North England where applicable",
  "properties": {
    "id": "xlnet-ontology",
    "collapsed": "true",
    "- ontology": "true",
    "- term-id": "AI-0221",
    "- preferred-term": "XLNet",
    "- source-domain": "ai",
    "- status": "draft",
    "- public-access": "true",
    "- definition": "A generalised autoregressive pre-training method that learns bidirectional contexts by maximising expected likelihood over all permutations of the factorisation order, overcoming limitations of BERT's masked language modelling."
  },
  "backlinks": [],
  "wiki_links": [],
  "ontology": {
    "term_id": "AI-0221",
    "preferred_term": "XLNet",
    "definition": "A generalised autoregressive pre-training method that learns bidirectional contexts by maximising expected likelihood over all permutations of the factorisation order, overcoming limitations of BERT's masked language modelling.",
    "source_domain": "ai",
    "maturity_level": null,
    "authority_score": null
  }
}