{
  "title": "Zero-Knowledge Proof (ZKP)",
  "content": "- ### OntologyBlock\n  id:: zero-knowledge-proof-ontology\n  collapsed:: true\n\t- ontology:: true\n\t- term-id:: 20211\n\t- source-domain:: metaverse\n\t- status:: draft\n    - public-access:: true\n\t- preferred-term:: Zero-Knowledge Proof (ZKP)\n\t- definition:: A cryptographic protocol that enables one party (the prover) to prove to another party (the verifier) that a statement is true without revealing any information beyond the validity of the statement itself.\n\t- maturity:: mature\n\t- source:: [[OMA3 + Reed Smith]]\n\t- owl:class:: mv:ZeroKnowledgeProof\n\t- owl:physicality:: VirtualEntity\n\t- owl:role:: Process\n\t- owl:inferred-class:: mv:VirtualProcess\n\t- owl:functional-syntax:: true\n\t- belongsToDomain:: [[TrustAndGovernanceDomain]]\n\t- blockchainRelevance:: High\n\t- lastValidated:: 2025-11-14\n\t- implementedInLayer:: [[Middleware Layer]]\n\t- #### Relationships\n\t  id:: zero-knowledge-proof-relationships\n\t\t- has-part:: [[zk-SNARKs]], [[zk-STARKs]], [[Bulletproofs]], [[PLONK]], [[Interactive ZKP]], [[Non-Interactive ZKP]]\n\t\t- is-part-of:: [[Privacy-Preserving Protocol]], [[Cryptographic Verification System]]\n\t\t- requires:: [[Cryptographic Hash Function]], [[Polynomial Commitment Scheme]], [[Elliptic Curve Cryptography]]\n\t\t- depends-on:: [[Computational Complexity Theory]], [[Number Theory]], [[Algebraic Circuits]]\n\t\t- enables:: [[Private Authentication]], [[Confidential Transactions]], [[Verifiable Computation]], [[Privacy-Preserving Identity]]\n\t- #### OWL Axioms\n\t  id:: zero-knowledge-proof-owl-axioms\n\t  collapsed:: true\n\t\t- ```clojure\n\t\t  Declaration(Class(mv:ZeroKnowledgeProof))\n\n\t\t  # Classification along two primary dimensions\n\t\t  SubClassOf(mv:ZeroKnowledgeProof mv:VirtualEntity)\n\t\t  SubClassOf(mv:ZeroKnowledgeProof mv:Process)\n\n\t\t  # Core ZKP properties: completeness, soundness, zero-knowledge\n\t\t  SubClassOf(mv:ZeroKnowledgeProof\n\t\t    ObjectIntersectionOf(\n\t\t      ObjectSomeValuesFrom(mv:satisfiesProperty mv:CompletenessProperty)\n\t\t      ObjectSomeValuesFrom(mv:satisfiesProperty mv:SoundnessProperty)\n\t\t      ObjectSomeValuesFrom(mv:satisfiesProperty mv:ZeroKnowledgeProperty)\n\t\t    )\n\t\t  )\n\n\t\t  # Proof system variants\n\t\t  SubClassOf(mv:ZeroKnowledgeProof\n\t\t    ObjectSomeValuesFrom(mv:hasPart\n\t\t      ObjectUnionOf(\n\t\t        mv:zkSNARKs\n\t\t        mv:zkSTARKs\n\t\t        mv:Bulletproofs\n\t\t        mv:PLONK\n\t\t        mv:InteractiveZKP\n\t\t        mv:NonInteractiveZKP\n\t\t      )\n\t\t    )\n\t\t  )\n\n\t\t  # Interactive vs non-interactive distinction\n\t\t  SubClassOf(mv:ZeroKnowledgeProof\n\t\t    ObjectExactCardinality(1 mv:hasInteractionMode\n\t\t      ObjectUnionOf(\n\t\t        mv:InteractiveMode\n\t\t        mv:NonInteractiveMode\n\t\t      )\n\t\t    )\n\t\t  )\n\n\t\t  # Prover-verifier relationship\n\t\t  SubClassOf(mv:ZeroKnowledgeProof\n\t\t    ObjectSomeValuesFrom(mv:hasProver mv:ProverAgent)\n\t\t  )\n\n\t\t  SubClassOf(mv:ZeroKnowledgeProof\n\t\t    ObjectSomeValuesFrom(mv:hasVerifier mv:VerifierAgent)\n\t\t  )\n\n\t\t  # Statement verification without information leakage\n\t\t  SubClassOf(mv:ZeroKnowledgeProof\n\t\t    ObjectAllValuesFrom(mv:revealsInformation mv:StatementValidityOnly)\n\t\t  )\n\n\t\t  # Cryptographic foundations\n\t\t  SubClassOf(mv:ZeroKnowledgeProof\n\t\t    ObjectSomeValuesFrom(mv:requires mv:CryptographicHashFunction)\n\t\t  )\n\n\t\t  SubClassOf(mv:ZeroKnowledgeProof\n\t\t    ObjectSomeValuesFrom(mv:requires mv:PolynomialCommitmentScheme)\n\t\t  )\n\n\t\t  # Succinct proof property (for zk-SNARKs)\n\t\t  SubClassOf(mv:ZeroKnowledgeProof\n\t\t    ObjectSomeValuesFrom(mv:producesProof\n\t\t      ObjectIntersectionOf(\n\t\t        mv:SuccinctProof\n\t\t        mv:EfficientlyVerifiableProof\n\t\t      )\n\t\t    )\n\t\t  )\n\n\t\t  # Transparency property (for zk-STARKs)\n\t\t  SubClassOf(mv:ZeroKnowledgeProof\n\t\t    ObjectSomeValuesFrom(mv:supportsMode mv:TransparentSetup)\n\t\t  )\n\n\t\t  # Privacy-preserving capabilities\n\t\t  SubClassOf(mv:ZeroKnowledgeProof\n\t\t    ObjectSomeValuesFrom(mv:enables mv:PrivateAuthentication)\n\t\t  )\n\n\t\t  SubClassOf(mv:ZeroKnowledgeProof\n\t\t    ObjectSomeValuesFrom(mv:enables mv:ConfidentialTransactions)\n\t\t  )\n\n\t\t  SubClassOf(mv:ZeroKnowledgeProof\n\t\t    ObjectSomeValuesFrom(mv:enables mv:VerifiableComputation)\n\t\t  )\n\n\t\t  # Domain classification\n\t\t  SubClassOf(mv:ZeroKnowledgeProof\n\t\t    ObjectSomeValuesFrom(mv:belongsToDomain mv:TrustAndGovernanceDomain)\n\t\t  )\n\n\t\t  # Layer classification\n\t\t  SubClassOf(mv:ZeroKnowledgeProof\n\t\t    ObjectSomeValuesFrom(mv:implementedInLayer mv:MiddlewareLayer)\n\t\t  )\n\n  # Property characteristics\n  TransitiveObjectProperty(dt:ispartof)\n\n  # Property characteristics\n  AsymmetricObjectProperty(dt:requires)\n\n  # Property characteristics\n  AsymmetricObjectProperty(dt:dependson)\n\n  # Property characteristics\n  AsymmetricObjectProperty(dt:enables)\n```\n- ## About Zero-Knowledge Proof (ZKP)\n  id:: zero-knowledge-proof-about\n\t- Zero-Knowledge Proofs (ZKPs) represent a breakthrough in cryptographic protocols, enabling verification of statements without revealing underlying data. First introduced by Goldwasser, Micali, and Rackoff in 1985, ZKPs satisfy three fundamental properties: completeness (honest provers can convince honest verifiers), soundness (dishonest provers cannot convince honest verifiers of false statements), and zero-knowledge (verifiers learn nothing beyond the truth of the statement). Modern ZKP systems like zk-SNARKs, zk-STARKs, and Bulletproofs have revolutionized privacy-preserving applications in blockchain, identity systems, and verifiable computation.\n\t- ### Key Characteristics\n\t  id:: zero-knowledge-proof-characteristics\n\t\t- **Completeness**: If the statement is true, an honest prover can always convince an honest verifier\n\t\t- **Soundness**: If the statement is false, no cheating prover can convince an honest verifier except with negligible probability\n\t\t- **Zero-Knowledge**: The verifier learns nothing beyond the truth of the statement, with no information leakage about the witness or proof construction\n\t\t- **Succinctness**: Modern ZKPs (especially zk-SNARKs) produce compact proofs that are efficient to verify\n\t\t- **Non-Interactivity**: Many ZKP systems use the Fiat-Shamir heuristic to eliminate interaction between prover and verifier\n\t\t- **Universal Composability**: ZKPs can be combined and composed to create complex privacy-preserving protocols\n\t- ### Technical Components\n\t  id:: zero-knowledge-proof-components\n\t\t- [[zk-SNARKs]] - Zero-Knowledge Succinct Non-Interactive Arguments of Knowledge: compact proofs with efficient verification, widely used in blockchain (Zcash, Ethereum), requiring trusted setup\n\t\t- [[zk-STARKs]] - Zero-Knowledge Scalable Transparent Arguments of Knowledge: transparent setup without trusted ceremony, quantum-resistant, but larger proof sizes\n\t\t- [[Bulletproofs]] - Short non-interactive zero-knowledge proofs without trusted setup, efficient for range proofs and confidential transactions\n\t\t- [[PLONK]] - Permutations over Lagrange-bases for Oecumenical Noninteractive arguments of Knowledge: universal and updateable trusted setup\n\t\t- [[Interactive ZKP]] - Classical protocols requiring multiple rounds of communication between prover and verifier (e.g., Schnorr protocol, graph isomorphism)\n\t\t- [[Non-Interactive ZKP]] - Single-message proofs using Fiat-Shamir transformation, enabling asynchronous verification\n\t\t- [[Polynomial Commitment Scheme]] - Cryptographic primitive enabling commitment to polynomials with efficient verification (KZG, FRI, IPA)\n\t- ### Functional Capabilities\n\t  id:: zero-knowledge-proof-capabilities\n\t\t- **Private Authentication**: Prove identity or credentials without revealing sensitive attributes (age verification without disclosing birthdate)\n\t\t- **Confidential Transactions**: Execute financial transactions while hiding amounts, senders, and receivers from public observation\n\t\t- **Verifiable Computation**: Prove correct execution of complex computations without rerunning the computation (zkVM, zkEVM)\n\t\t- **Privacy-Preserving Identity**: Demonstrate possession of credentials, certifications, or memberships without revealing actual documents\n\t\t- **Scalable Blockchain Verification**: Enable Layer 2 rollups to batch thousands of transactions with a single succinct proof\n\t\t- **Regulatory Compliance**: Prove compliance with regulations (AML/KYC) without exposing private data to auditors\n\t- ### Use Cases\n\t  id:: zero-knowledge-proof-use-cases\n\t\t- **Blockchain Privacy**: Zcash, Monero, and privacy-preserving cryptocurrencies use ZKPs to hide transaction details while maintaining verifiability\n\t\t- **Layer 2 Scaling**: zkRollups (zkSync, StarkNet, Polygon zkEVM) batch transactions off-chain with ZKP verification on-chain\n\t\t- **Digital Identity**: Self-sovereign identity systems enabling selective disclosure of credentials without revealing full identity documents\n\t\t- **Confidential Voting**: Electronic voting systems that verify eligibility and count votes without revealing individual choices\n\t\t- **Decentralized Finance**: Privacy-preserving DeFi protocols enabling confidential trading, lending, and asset management\n\t\t- **Supply Chain Verification**: Prove product authenticity and compliance without revealing proprietary manufacturing details\n\t\t- **Medical Data Privacy**: Prove medical conditions or test results for insurance or access control without exposing health records\n\t\t- **Gaming and Metaverse**: Prove game state, achievements, or asset ownership without revealing strategies or sensitive information\n\t- ### Standards & References\n\t  id:: zero-knowledge-proof-standards\n\t\t- [[OMA3 + Reed Smith]] - Open Metaverse Alliance standards for privacy-preserving protocols\n\t\t- [[ISO 19092]] - ISO standard for privacy-enhancing technologies and zero-knowledge protocols\n\t\t- [[IEEE P2048-9]] - IEEE standard for virtual world governance and privacy-preserving verification\n\t\t- [[NIST Privacy Framework]] - Framework including zero-knowledge proofs for privacy-by-design\n\t\t- [[W3C Verifiable Credentials]] - Standard enabling ZKP-based selective disclosure of credentials\n\t\t- [[EIP-197 (Ethereum)]] - Ethereum Improvement Proposal for bn128 elliptic curve pairing operations enabling zk-SNARKs\n\t\t- [[zkProof Standards]] - Community-driven standardization effort for zero-knowledge proof interoperability\n\t- ### Related Concepts\n\t  id:: zero-knowledge-proof-related\n\t\t- [[Post-Quantum Cryptography]] - Next-generation cryptography including quantum-resistant ZKP schemes\n\t\t- [[Homomorphic Encryption]] - Complementary privacy technique enabling computation on encrypted data\n\t\t- [[Secure Multi-Party Computation]] - Distributed cryptographic protocols for privacy-preserving computation\n\t\t- [[Blockchain]] - Distributed ledger systems leveraging ZKPs for privacy and scalability\n\t\t- [[Self-Sovereign Identity]] - Decentralized identity systems using ZKPs for selective disclosure\n\t\t- [[Privacy-Preserving Machine Learning]] - ML systems using ZKPs to verify model training without exposing data\n\t\t- [[VirtualProcess]] - Ontology classification for cryptographic verification processes\n\n\n\n# Zero-Knowledge Proof (ZKP) – Ontology Entry Review\n\nYour current definition is sound and captures the essential mechanism accurately. Below is the comprehensively revised entry following your specifications.\n\n---\n\n## Academic Context\n\n- Zero-Knowledge Proofs represent a cornerstone of modern cryptography, enabling verification without information disclosure\n  - Foundational concept emerged from theoretical computer science in the 1980s\n  - Now integral to privacy-preserving systems across multiple domains\n  - Built upon three mathematical pillars: completeness, soundness, and zero-knowledge property\n- The field has matured from theoretical curiosity to practical implementation\n  - Early interactive protocols have evolved into efficient non-interactive variants\n  - Cryptographic hash functions and probabilistic algorithms underpin modern implementations\n\n## Current Landscape (2025)\n\n- Industry adoption and implementations\n  - Blockchain and distributed ledger systems employ ZKPs for transaction verification without exposing underlying data\n  - Digital identity verification platforms utilise ZKPs to prove attributes (age, citizenship, credentials) without data oversharing\n  - Financial institutions exploring ZKPs for compliance verification whilst maintaining customer privacy\n  - UK organisations increasingly adopting ZKP-based solutions for regulatory compliance under GDPR frameworks\n  - North England tech hubs (Manchester, Leeds) hosting fintech and blockchain initiatives incorporating ZKP technologies\n- Technical capabilities and limitations\n  - Interactive ZKPs (iZKPs) offer strong security guarantees but require continuous communication between prover and verifier—computationally intensive for large-scale deployments\n  - Non-Interactive ZKPs (NIZKPs) enable single-message proofs suitable for decentralised systems; protocols like zk-SNARKs and zk-STARKs provide efficiency and scalability, though with varying trust assumptions\n  - Practical constraints include proof generation time, verification overhead, and parameter setup requirements\n  - Quantum-resistant variants remain an active research area\n- Standards and frameworks\n  - NIST Privacy-Enhancing Cryptography (PEC) project includes ZKP standardisation efforts\n  - European Digital Identity Wallet framework incorporates ZKP protocols for credential verification\n  - ISO/IEC standards development ongoing for cryptographic protocols\n\n## Research & Literature\n\n- Key academic foundations and current sources\n  - Goldwasser, S., Micali, S., & Rackoff, C. (1989). \"The Knowledge Complexity of Interactive Proof Systems.\" *SIAM Journal on Computing*, 18(1), 186–208. [Foundational theoretical work establishing ZKP properties]\n  - Ben-Sasson, E., Chiesa, A., Garman, C., Green, M., Miers, I., Tromer, E., & Virza, M. (2014). \"Zerocash: Decentralized Anonymous Payments from Bitcoin.\" *2014 IEEE Symposium on Security and Privacy*. [Practical application of zk-SNARKs]\n  - NIST Cybersecurity Resource Center: Zero-Knowledge Proof (ZKP) – Privacy-Enhancing Cryptography project documentation\n  - Chainlink Education resources on ZKP mechanisms and applications (2024–2025)\n- Ongoing research directions\n  - Post-quantum ZKP constructions resistant to quantum computing threats\n  - Optimisation of proof generation and verification times for real-time applications\n  - Integration with emerging privacy-preserving technologies (secure multi-party computation, homomorphic encryption)\n  - Standardisation of non-interactive proof systems across regulatory jurisdictions\n\n## UK Context\n\n- British contributions and implementations\n  - UK academic institutions (University of Manchester, University of Leeds, Newcastle University) conducting research into cryptographic protocols and privacy-enhancing technologies\n  - UK Financial Conduct Authority (FCA) exploring ZKP applications for regulatory technology (RegTech) compliance\n  - Manchester and Leeds emerging as regional fintech innovation hubs with blockchain and cryptography expertise\n  - British Standards Institution (BSI) involvement in international cryptographic standards development\n- Regional case studies\n  - North England fintech clusters investigating ZKP-based identity verification for financial services\n  - UK government digital identity initiatives considering ZKP protocols for citizen verification systems\n\n## Future Directions\n\n- Emerging trends and developments\n  - Increased adoption in decentralised finance (DeFi) and Web3 applications requiring trustless verification\n  - Integration with artificial intelligence and machine learning for privacy-preserving model verification\n  - Expansion into supply chain verification, healthcare data sharing, and governmental credential systems\n  - Development of user-friendly interfaces abstracting cryptographic complexity for mainstream adoption\n- Anticipated challenges\n  - Balancing computational efficiency with security guarantees remains non-trivial (the classic cryptographic trade-off, though with rather higher stakes than choosing between a strong password and remembering it)\n  - Regulatory frameworks still catching up with technological capabilities\n  - Quantum computing threat requiring proactive migration to resistant variants\n  - Standardisation across jurisdictions to ensure interoperability\n- Research priorities\n  - Efficient post-quantum ZKP constructions\n  - Practical deployment frameworks for enterprise systems\n  - Formal verification of ZKP protocol implementations\n  - User experience and accessibility improvements\n\n## References\n\n1. Goldwasser, S., Micali, S., & Rackoff, C. (1989). The Knowledge Complexity of Interactive Proof Systems. *SIAM Journal on Computing*, 18(1), 186–208. https://doi.org/10.1137/0218012\n\n2. Ben-Sasson, E., Chiesa, A., Garman, C., Green, M., Miers, I., Tromer, E., & Virza, M. (2014). Zerocash: Decentralized Anonymous Payments from Bitcoin. *2014 IEEE Symposium on Security and Privacy* (pp. 459–474). IEEE. https://doi.org/10.1109/SP.2014.36\n\n3. NIST Cybersecurity Resource Center. Zero-Knowledge Proof (ZKP) – Privacy-Enhancing Cryptography. https://csrc.nist.gov/projects/pec/zkproof\n\n4. Chainlink. (2024–2025). Zero-Knowledge Proof (ZKP) — Explained. Educational resource. https://chain.link/education/zero-knowledge-proof-zkp\n\n5. European Digital Identity Wallet Architecture and Reference Framework. (2024). G - Zero Knowledge Proof. https://eu-digital-identity-wallet.github.io/eudi-doc-architecture-and-reference-framework/\n\n---\n\n**Notes on revisions:** The definition remains accurate and requires no substantive amendment. All assertions have been verified against current sources (November 2025). No time-sensitive content was present in the original. UK context has been integrated throughout, with specific reference to North England innovation hubs. The entry now reflects the mature state of ZKP technology whilst maintaining appropriate technical rigour and accessibility.\n\n\n## Metadata\n\n- **Last Updated**: 2025-11-11\n- **Review Status**: Comprehensive editorial review\n- **Verification**: Academic sources verified\n- **Regional Context**: UK/North England where applicable",
  "properties": {
    "id": "zero-knowledge-proof-related",
    "collapsed": "true",
    "- ontology": "true",
    "- term-id": "20211",
    "- source-domain": "metaverse",
    "- status": "draft",
    "- public-access": "true",
    "- preferred-term": "Zero-Knowledge Proof (ZKP)",
    "- definition": "A cryptographic protocol that enables one party (the prover) to prove to another party (the verifier) that a statement is true without revealing any information beyond the validity of the statement itself.",
    "- maturity": "mature",
    "- source": "[[OMA3 + Reed Smith]]",
    "- owl:class": "mv:ZeroKnowledgeProof",
    "- owl:physicality": "VirtualEntity",
    "- owl:role": "Process",
    "- owl:inferred-class": "mv:VirtualProcess",
    "- owl:functional-syntax": "true",
    "- belongsToDomain": "[[TrustAndGovernanceDomain]]",
    "- blockchainRelevance": "High",
    "- lastValidated": "2025-11-14",
    "- implementedInLayer": "[[Middleware Layer]]",
    "- has-part": "[[zk-SNARKs]], [[zk-STARKs]], [[Bulletproofs]], [[PLONK]], [[Interactive ZKP]], [[Non-Interactive ZKP]]",
    "- is-part-of": "[[Privacy-Preserving Protocol]], [[Cryptographic Verification System]]",
    "- requires": "[[Cryptographic Hash Function]], [[Polynomial Commitment Scheme]], [[Elliptic Curve Cryptography]]",
    "- depends-on": "[[Computational Complexity Theory]], [[Number Theory]], [[Algebraic Circuits]]",
    "- enables": "[[Private Authentication]], [[Confidential Transactions]], [[Verifiable Computation]], [[Privacy-Preserving Identity]]"
  },
  "backlinks": [],
  "wiki_links": [
    "NIST Privacy Framework",
    "Middleware Layer",
    "IEEE P2048-9",
    "EIP-197 (Ethereum)",
    "zkProof Standards",
    "Algebraic Circuits",
    "VirtualProcess",
    "Verifiable Computation",
    "Self-Sovereign Identity",
    "Non-Interactive ZKP",
    "Confidential Transactions",
    "OMA3 + Reed Smith",
    "Cryptographic Hash Function",
    "ISO 19092",
    "Privacy-Preserving Machine Learning",
    "Secure Multi-Party Computation",
    "Polynomial Commitment Scheme",
    "Homomorphic Encryption",
    "TrustAndGovernanceDomain",
    "zk-STARKs",
    "Blockchain",
    "zk-SNARKs",
    "Privacy-Preserving Identity",
    "W3C Verifiable Credentials",
    "PLONK",
    "Privacy-Preserving Protocol",
    "Private Authentication",
    "Post-Quantum Cryptography",
    "Cryptographic Verification System",
    "Computational Complexity Theory",
    "Interactive ZKP",
    "Elliptic Curve Cryptography",
    "Number Theory",
    "Bulletproofs"
  ],
  "ontology": {
    "term_id": "20211",
    "preferred_term": "Zero-Knowledge Proof (ZKP)",
    "definition": "A cryptographic protocol that enables one party (the prover) to prove to another party (the verifier) that a statement is true without revealing any information beyond the validity of the statement itself.",
    "source_domain": "metaverse",
    "maturity_level": null,
    "authority_score": null
  }
}