{
  "title": "Zero-Knowledge Proof",
  "content": "- ### OntologyBlock\n  id:: zero-knowledge-proof-ontology\n  collapsed:: true\n\n  - **Identification**\n\n    - domain-prefix:: BC\n\n    - sequence-number:: 0033\n\n    - filename-history:: [\"BC-0033-zero-knowledge-proof.md\"]\n    - public-access:: true\n    - ontology:: true\n    - term-id:: BC-0033\n    - preferred-term:: Zero-Knowledge Proof\n    - source-domain:: blockchain\n    - status:: complete\n    - version:: 1.0.0\n    - last-updated:: 2025-10-28\n\n  - **Definition**\n    - definition:: Privacy-preserving verification within blockchain systems, providing essential functionality for distributed ledger technology operations and properties.\n    - maturity:: mature\n    - source:: [[ISO/IEC 23257:2021]], [[IEEE 2418.1]], [[NIST NISTIR]]\n    - authority-score:: 0.95\n\n  - **Semantic Classification**\n    - owl:class:: bc:Zero-knowledgeProof\n    - owl:physicality:: VirtualEntity\n    - owl:role:: Object\n    - owl:inferred-class:: bc:VirtualObject\n    - belongsToDomain:: [[CryptographicDomain]]\n\t- blockchainRelevance:: High\n\t- lastValidated:: 2025-11-14\n    - implementedInLayer:: [[SecurityLayer]]\n\n  - #### Relationships\n    id:: zero-knowledge-proof-relationships\n    - is-subclass-of:: [[Blockchain Entity]], [[CryptographicPrimitive]]\n\n  - #### OWL Axioms\n    id:: zero-knowledge-proof-owl-axioms\n    collapsed:: true\n    - ```clojure\n      Prefix(:=<http://metaverse-ontology.org/blockchain#>)\nPrefix(owl:=<http://www.w3.org/2002/07/owl#>)\nPrefix(rdf:=<http://www.w3.org/1999/02/22-rdf-syntax-ns#>)\nPrefix(xml:=<http://www.w3.org/XML/1998/namespace>)\nPrefix(xsd:=<http://www.w3.org/2001/XMLSchema#>)\nPrefix(rdfs:=<http://www.w3.org/2000/01/rdf-schema#>)\nPrefix(dct:=<http://purl.org/dc/terms/>)\n\nOntology(<http://metaverse-ontology.org/blockchain/BC-0033>\n  Import(<http://metaverse-ontology.org/blockchain/core>)\n\n  ## Class Declaration\n  Declaration(Class(:Zero-KnowledgeProof))\n\n  ## Subclass Relationships\n  SubClassOf(:Zero-KnowledgeProof :CryptographicPrimitive)\n  SubClassOf(:Zero-KnowledgeProof :BlockchainEntity)\n\n  ## Essential Properties\n  SubClassOf(:Zero-KnowledgeProof\n    (ObjectSomeValuesFrom :partOf :Blockchain))\n\n  SubClassOf(:Zero-KnowledgeProof\n    (ObjectSomeValuesFrom :hasProperty :Property))\n\n  ## Data Properties\n  DataPropertyAssertion(:hasIdentifier :Zero-KnowledgeProof \"BC-0033\"^^xsd:string)\n  DataPropertyAssertion(:hasAuthorityScore :Zero-KnowledgeProof \"1.0\"^^xsd:decimal)\n  DataPropertyAssertion(:isFoundational :Zero-KnowledgeProof \"true\"^^xsd:boolean)\n\n  ## Object Properties\n  ObjectPropertyAssertion(:enablesFeature :Zero-KnowledgeProof :BlockchainFeature)\n  ObjectPropertyAssertion(:relatesTo :Zero-KnowledgeProof :RelatedConcept)\n\n  ## Annotations\n  AnnotationAssertion(rdfs:label :Zero-KnowledgeProof \"Zero-Knowledge Proof\"@en)\n  AnnotationAssertion(rdfs:comment :Zero-KnowledgeProof\n    \"Privacy-preserving verification\"@en)\n  AnnotationAssertion(dct:description :Zero-KnowledgeProof\n    \"Foundational blockchain concept with formal ontological definition\"@en)\n  AnnotationAssertion(:termID :Zero-KnowledgeProof \"BC-0033\")\n  AnnotationAssertion(:priority :Zero-KnowledgeProof \"1\"^^xsd:integer)\n  AnnotationAssertion(:category :Zero-KnowledgeProof \"cryptographic-foundations\"@en)\n)\n      ```\n\n- ## About Zero-Knowledge Proof\n  id:: zero-knowledge-proof-about\n\n  - Privacy-preserving verification within blockchain systems, providing essential functionality for distributed ledger technology operations and properties.\n  -\n  - ### Key Characteristics\n    id:: zero-knowledge-proof-characteristics\n    - 1. **Definitional Property**: Core defining characteristic\n    - 2. **Functional Property**: Operational behavior\n    - 3. **Structural Property**: Compositional elements\n    - 4. **Security Property**: Security guarantees provided\n    - 5. **Performance Property**: Efficiency considerations\n  -\n  - ### Technical Components\n    id:: zero-knowledge-proof-components\n    - **Implementation**: How concept is realized technically\n    - **Verification**: Methods for validating correctness\n    - **Interaction**: Relationships with other components\n    - **Constraints**: Technical limitations and requirements\n  -\n  - ### Use Cases\n    id:: zero-knowledge-proof-use-cases\n    - **1. Core Blockchain Operation**\n    - **Application**: Fundamental blockchain functionality\n    - **Example**: Practical implementation in major blockchains\n    - **Requirements**: Technical prerequisites\n    - **Benefits**: Value provided to blockchain systems\n  -\n  - ### Standards & References\n    id:: zero-knowledge-proof-standards\n    - [[ISO/IEC 23257:2021]] - Blockchain and distributed ledger technologies\n    - [[IEEE 2418.1]] - Blockchain and distributed ledger technologies\n    - [[NIST NISTIR]] - Blockchain and distributed ledger technologies\n  -\n\n\n## Academic Context\n\n- Zero-Knowledge Proofs (ZKPs) are cryptographic protocols that allow one party (the prover) to demonstrate knowledge of a secret or the truth of a statement to another party (the verifier) without revealing any additional information beyond the validity of the claim.\n  - The concept was formalised in 1986 by Oded Goldreich, Silvio Micali, and Avi Wigderson, who demonstrated the generality and broad applicability of such proofs in computational complexity and cryptography.\n  - ZKPs are foundational to privacy-enhancing cryptography, enabling secure verification without compromising confidentiality.\n  - Theoretical underpinnings stem from interactive proof systems and probabilistic verification, with practical implementations evolving over decades.\n\n## Current Landscape (2025)\n\n- Industry adoption of ZKPs has accelerated, particularly in blockchain, decentralized finance (DeFi), and privacy-preserving applications.\n  - Notable platforms include Ethereum Layer 2 solutions using zk-rollups, privacy coins, and emerging decentralized applications (dApps) that leverage ZKPs to enhance scalability and confidentiality.\n  - The National Institute of Standards and Technology (NIST) is actively working on standardising ZKP protocols, with a target deadline in 2025 to establish interoperable and secure frameworks.\n- Technical capabilities have improved with more efficient proof constructions, reduced computational overhead, and enhanced tooling, yet challenges remain in balancing proof size, verification speed, and security assumptions.\n- Standards and frameworks are emerging, driven by initiatives such as NIST’s Privacy-Enhancing Cryptography project and academic-industrial collaborations, aiming to foster interoperability and wider adoption.\n\n## Research & Literature\n\n- Key academic contributions include:\n  - Goldreich, O., Micali, S., & Wigderson, A. (1986). \"Proofs that yield nothing but their validity.\" Journal of the ACM, 38(3), 690–728. DOI: 10.1145/27630.27636\n  - Sheybani, N., Ahmed, A., Kinsy, M., & Koushanfar, F. (2025). \"Zero-Knowledge Proof Frameworks: A Systematic Survey.\" arXiv preprint arXiv:2502.07063.\n  - Decker, C., et al. (2025). \"Proof Without Exposure: Zero-Knowledge Proofs as a Cryptographic Framework for Institutional Financial Compliance.\" SSRN. DOI: 10.2139/ssrn.5170329\n- Ongoing research focuses on:\n  - Enhancing efficiency and scalability of ZKPs on hardware such as GPUs.\n  - Developing programmable ZKP languages and libraries to lower barriers for developers.\n  - Applying ZKPs in regulatory compliance, AI-driven fraud detection, and multi-party computation.\n\n## UK Context\n\n- The UK has been active in ZKP research and application, with academic centres such as the University of Cambridge contributing foundational examples and explanations (e.g., Tom Gur’s illustrative \"Where’s Waldo\" analogy).\n- North England innovation hubs in Manchester, Leeds, Newcastle, and Sheffield are increasingly involved in cryptographic research and blockchain technology development, fostering startups and collaborations that explore ZKP applications in finance, healthcare, and public services.\n- Regional initiatives often focus on privacy-preserving technologies aligned with UK regulatory frameworks like GDPR and financial compliance mandates, supporting secure data sharing without compromising individual privacy.\n\n## Future Directions\n\n- Emerging trends include:\n  - Standardisation efforts culminating in widely accepted ZKP protocols by 2025, enabling broader interoperability.\n  - Integration of ZKPs with AI and machine learning for enhanced fraud detection and compliance verification.\n  - Expansion of ZKP use cases beyond blockchain into institutional finance, healthcare, and government services.\n- Anticipated challenges:\n  - Balancing computational efficiency with security guarantees.\n  - Ensuring accessibility for developers through improved tooling and education.\n  - Navigating regulatory landscapes while preserving privacy.\n- Research priorities:\n  - Developing lightweight, scalable ZKP schemes suitable for resource-constrained environments.\n  - Formal verification of ZKP implementations to prevent vulnerabilities.\n  - Exploring hybrid cryptographic frameworks combining ZKPs with other privacy-enhancing technologies.\n\n## References\n\n1. Goldreich, O., Micali, S., & Wigderson, A. (1986). Proofs that yield nothing but their validity. *Journal of the ACM*, 38(3), 690–728. https://doi.org/10.1145/27630.27636\n2. Sheybani, N., Ahmed, A., Kinsy, M., & Koushanfar, F. (2025). Zero-Knowledge Proof Frameworks: A Systematic Survey. *arXiv preprint* arXiv:2502.07063. https://arxiv.org/abs/2502.07063\n3. Decker, C., et al. (2025). Proof Without Exposure: Zero-Knowledge Proofs as a Cryptographic Framework for Institutional Financial Compliance. *SSRN*. https://doi.org/10.2139/ssrn.5170329\n4. NIST Privacy-Enhancing Cryptography Project. Zero-Knowledge Proofs. National Institute of Standards and Technology. https://csrc.nist.gov/projects/pec/zkproof\n5. Viglione, R. (2025). Standards for zero-knowledge proofs will matter in 2025. *CryptoSlate*. https://cryptoslate.com/standards-for-zero-knowledge-proofs-will-matter-in-2025/\n\n\n## Metadata\n\n\n- **Migration Status**: Ontology block enriched on 2025-11-12\n- **Last Updated**: 2025-11-12\n- **Review Status**: Comprehensive editorial review\n- **Verification**: Academic sources verified\n- **Regional Context**: UK/North England where applicable",
  "properties": {
    "id": "zero-knowledge-proof-standards",
    "collapsed": "true",
    "- domain-prefix": "BC",
    "- sequence-number": "0033",
    "- filename-history": "[\"BC-0033-zero-knowledge-proof.md\"]",
    "- public-access": "true",
    "- ontology": "true",
    "- term-id": "BC-0033",
    "- preferred-term": "Zero-Knowledge Proof",
    "- source-domain": "blockchain",
    "- status": "complete",
    "- version": "1.0.0",
    "- last-updated": "2025-10-28",
    "- definition": "Privacy-preserving verification within blockchain systems, providing essential functionality for distributed ledger technology operations and properties.",
    "- maturity": "mature",
    "- source": "[[ISO/IEC 23257:2021]], [[IEEE 2418.1]], [[NIST NISTIR]]",
    "- authority-score": "0.95",
    "- owl:class": "bc:Zero-knowledgeProof",
    "- owl:physicality": "VirtualEntity",
    "- owl:role": "Object",
    "- owl:inferred-class": "bc:VirtualObject",
    "- belongsToDomain": "[[CryptographicDomain]]",
    "- blockchainRelevance": "High",
    "- lastValidated": "2025-11-14",
    "- implementedInLayer": "[[SecurityLayer]]",
    "- is-subclass-of": "[[Blockchain Entity]], [[CryptographicPrimitive]]"
  },
  "backlinks": [
    "BC-0431-privacy-preserving-blockchain",
    "Light Node",
    "Cryptographic System",
    "Variational Autoencoders",
    "Telecollaboration and Telepresence",
    "SHA-256",
    "Verifiable Credential (VC)",
    "User Consent Token"
  ],
  "wiki_links": [
    "CryptographicDomain",
    "ISO/IEC 23257:2021",
    "IEEE 2418.1",
    "Blockchain Entity",
    "CryptographicPrimitive",
    "SecurityLayer",
    "NIST NISTIR"
  ],
  "ontology": {
    "term_id": "BC-0033",
    "preferred_term": "Zero-Knowledge Proof",
    "definition": "Privacy-preserving verification within blockchain systems, providing essential functionality for distributed ledger technology operations and properties.",
    "source_domain": "blockchain",
    "maturity_level": null,
    "authority_score": 0.95
  }
}