{
  "id": "Account Model",
  "title": "Account Model",
  "content": "- ### OntologyBlock\n  id:: account-model-ontology\n  collapsed:: true\n\t- ontology:: true\n\t- term-id:: mv-726307699864\n\t- preferred-term:: Account Model\n\t- status:: complete\n\t- public-access:: true\n\t- definition:: Balance-based accounting model within blockchain systems, providing essential functionality for distributed ledger technology operations and properties.\n\t- source:: [[ISO/IEC 23257:2021]], [[IEEE 2418.1]], [[NIST NISTIR]]\n\t- maturity:: mature\n\t- owl:class:: bc:AccountModel\n\t- owl:physicality:: VirtualEntity\n\t- owl:role:: Object\n\t- owl:inferred-class:: bc:VirtualObject\n\t- belongsToDomain:: [[BlockchainDomain]]\n\t- #### Relationships\n\t  id:: account-model-relationships\n\t  collapsed:: true\n\t\t- is-subclass-of:: [[Blockchain Entity]]\n\t\t- is-subclass-of:: [[Transaction]]\n\t\t- is-subclass-of:: [[DistributedDataStructure]]\n\t\t- requires:: [[Cryptographic Verification]]\n\t\t- requires:: [[Consensus Mechanism]]\n\t\t- enables:: [[Smart Contracts]]\n\t\t- enables:: [[DeFi]]\n\t\t- enables:: [[Token Standards]]\n\t\t- bridges-to:: [[Distributeddatastructure]]\n\t\t- contrasts-with:: [[UTXO Model]]\n\n## Account Model\n\nAccount Model refers to a component of the metaverse ecosystem focusing on account model.\n\n- definition:: Balance-based accounting model within blockchain systems providing essential functionality for distributed ledger technology operations, transaction management, and state tracking across network participants.\n- maturity:: mature\n- source:: [[ISO/IEC 23257:2021]], [[IEEE 2418.1]], [[NIST NISTIR 8202]], [[RFC 3530 - OpenStack Account Metadata]], [[Ethereum Yellow Paper (2024)]]\n- authority-score:: 0.95\n- wikipedia-reference:: [[w:Blockchain#Account-based_vs_UTXO]]\n\n## Technical Details\n\n- **Id**: account-model-owl-axioms\n- **Collapsed**: true\n- **Source Domain**: metaverse\n- **Status**: active\n- **Public Access**: true\n- **Maturity**: mature\n- **Authority Score**: 0.85\n- **Owl:Class**: mv:AccountModel\n- **Owl:Physicality**: ConceptualEntity\n- **Owl:Role**: Concept\n- **Belongstodomain**: [[MetaverseDomain]]\n- **Enables**: [[ImmersiveExperience]], [[Presence]], [[SpatialComputing]]\n- **Requires**: [[DisplayTechnology]], [[TrackingSystem]], [[RenderingEngine]]\n- **Bridges To**: [[HumanComputerInteraction]], [[ComputerVision]], [[Robotics]]\n\n### Semantic Classification\n\n- owl:class:: bc:AccountModel\n- owl:physicality:: VirtualEntity\n- owl:role:: Object\n- owl:inferred-class:: bc:VirtualObject\n- belongsToDomain:: [[BlockchainDomain]]\n- implementedInLayer:: [[ConceptualLayer]]\n- relatedConcepts:: [[UTXO Model]], [[Smart Contracts]], [[State Machine]], [[Consensus Mechanism]]\n\n### Relationships\n\nid:: account-model-relationships\n- is-subclass-of:: [[Blockchain Entity]], [[DistributedDataStructure]]\n- contrasts-with:: [[UTXO Model]]\n- enables:: [[Smart Contracts]], [[DeFi]], [[Token Standards]]\n- requires:: [[Consensus Mechanism]], [[Cryptographic Verification]]\n\n### OWL Axioms\n\nid:: account-model-owl-axioms\ncollapsed:: true\n```clojure\nPrefix(:=<http://narrativegoldmine.com/blockchain#>)\nPrefix(owl:=<http://www.w3.org/2002/07/owl#>)\nPrefix(rdf:=<http://www.w3.org/1999/02/22-rdf-syntax-ns#>)\nPrefix(xsd:=<http://www.w3.org/2001/XMLSchema#>)\nPrefix(rdfs:=<http://www.w3.org/2000/01/rdf-schema#>)\nPrefix(dct:=<http://purl.org/dc/terms/>)\nOntology(<http://narrativegoldmine.com/blockchain/BC-0008>\n  Import(<http://narrativegoldmine.com/blockchain/core>)\n  ## Class Declaration\n  Declaration(Class(:AccountModel))\n  ## Subclass Relationships\n  SubClassOf(:AccountModel :DistributedDataStructure)\n  SubClassOf(:AccountModel :BlockchainEntity)\n  ## Essential Properties\n  SubClassOf(:AccountModel\n    (ObjectSomeValuesFrom :partOf :Blockchain))\n  SubClassOf(:AccountModel\n    (ObjectSomeValuesFrom :hasProperty :Property))\n  ## Data Properties\n  DataPropertyAssertion(:hasIdentifier :AccountModel \"BC-0008\"^^xsd:string)\n  DataPropertyAssertion(:hasAuthorityScore :AccountModel \"0.95\"^^xsd:decimal)\n  DataPropertyAssertion(:isFoundational :AccountModel \"true\"^^xsd:boolean)\n  DataPropertyAssertion(:maturityLevel :AccountModel \"mature\"^^xsd:string)\n  ## Object Properties\n  ObjectPropertyAssertion(:enablesFeature :AccountModel :BlockchainFeature)\n  ObjectPropertyAssertion(:relatesTo :AccountModel :RelatedConcept)\n  ObjectPropertyAssertion(:contrastsWith :AccountModel :UTXOModel)\n  ## Annotations\n  AnnotationAssertion(rdfs:label :AccountModel \"Account Model\"@en)\n  AnnotationAssertion(rdfs:comment :AccountModel\n    \"Balance-based accounting model for blockchain state management\"@en)\n  AnnotationAssertion(dct:description :AccountModel\n    \"Foundational blockchain concept with formal ontological definition enabling transaction processing and state representation\"@en)\n  AnnotationAssertion(:termID :AccountModel \"BC-0008\")\n  AnnotationAssertion(:priority :AccountModel \"1\"^^xsd:integer)\n  AnnotationAssertion(:category :AccountModel \"blockchain-fundamentals\"@en)\n  AnnotationAssertion(:lastModified :AccountModel \"2025-11-14\"^^xsd:dateTime)\n)\n```\n\n## About Account Model\n\nid:: account-model-about\nBalance-based accounting model within blockchain systems providing essential functionality for distributed ledger technology operations and properties. The account model represents a departure from traditional UTXO (Unspent Transaction Output) models, offering improved programmability and state management.\n\n### Core Definition and Purpose\n\nThe account model is a blockchain architecture pattern where each participant maintains an account with a balance state. Unlike UTXO models that track individual unspent outputs, account models store cumulative balances for each address or account identifier. This enables:\n- Direct balance queries without scanning entire transaction history\n- Stateful smart contract execution\n- Simplified transaction semantics\n- Efficient state tree representation via Merkle Patricia Tries\n\n### Key Characteristics\n\nid:: account-model-characteristics\n**1. Balance Tracking**\n- Maintains persistent account state across blocks\n- Real-time balance availability without computation\n- Nonce/sequence numbers prevent replay attacks\n**2. Nonce/Counter Mechanism**\n- Sequential transaction counters per account\n- Ensures transaction ordering and prevents double-spending\n- Critical for transaction deduplication in asynchronous networks\n**3. State Management**\n- Accounts store multiple state fields (balance, nonce, code hash)\n- Smart contract state persists across transactions\n- Merkle tree structure enables efficient state verification\n**4. Smart Contract Integration**\n- Seamless contract deployment and execution\n- Stateful contract storage enables DeFi applications\n- Gas-based resource metering per transaction\n**5. Scalability Tradeoffs**\n- Larger state storage requirements vs UTXO\n- State pruning and archival challenges\n- Parallelization complexity due to account dependencies\n\n### Technical Components\n\nid:: account-model-components\n**Account Structure**\n- Address: 20-byte (Ethereum) or 32-byte (Substrate) identifier\n- Balance: Currency holdings in native units\n- Nonce: Transaction counter for ordering\n- Code Hash: Smart contract bytecode reference (if applicable)\n- Storage: State tree for contract data\n**Implementation Details**\n- Merkle Patricia Trie for efficient state hashing\n- RLP (Recursive Length Prefix) encoding for serialization\n- Bloom filters for transaction log filtering\n- State root commitment in block headers\n**Verification Methods**\n- State proof generation for light clients\n- Account inclusion proofs via trie path\n- Balance verification against state root\n- Transaction ordering validation via nonce\n**Constraints and Requirements**\n- Single-threaded account state transitions (serialization)\n- State storage growth management\n- Consensus on account state between nodes\n- Replay attack prevention through nonce and chain ID\n\n### Blockchain Implementations\n\nid:: account-model-implementations\n**Ethereum**\n- Full account model implementation\n- 20-byte addresses derived from public keys\n- Nonce-based transaction ordering\n- Trie-based state storage\n- Smart contracts with persistent storage\n- EIP-1559 transaction fee mechanism (2021)\n**Substrate/Polkadot**\n- Flexible account model via runtime pallets\n- Customizable address formats\n- Multiple account types (user, validator, proxy)\n- Sophisticated state management capabilities\n**Cosmos/IBC**\n- Account models via x/auth module\n- Multi-signature account support\n- Sequence numbers for transaction ordering\n- State persistence via KVStore\n**Solana**\n- Hybrid model: account-based with account rent\n- Accounts hold both state and executable code\n- Parallel transaction processing when accounts don't conflict\n- Compact state representation\n\n### Use Cases\n\nid:: account-model-use-cases\n**1. Core Blockchain Operation**\n- Application: Financial transaction settlement\n- Example: ETH transfers on Ethereum mainnet\n- Requirements: Cryptographic signature verification\n- Benefits: Immediate settlement with finality\n**2. Smart Contract Platforms**\n- Application: DeFi protocol execution\n- Example: Uniswap V2 swap execution via smart contracts\n- Requirements: EVM bytecode execution, storage access\n- Benefits: Programmable financial logic with state persistence\n**3. Enterprise Blockchain**\n- Application: Corporate financial recordkeeping\n- Example: Hyperledger Fabric asset tracking\n- Requirements: Privacy controls, audit trails\n- Benefits: Transparent yet controlled state management\n**4. Payment Networks**\n- Application: Micropayments and instant settlement\n- Example: Stablecoin transfers in DeFi protocols\n- Requirements: Subsecond confirmation, atomic swaps\n- Benefits: Reduced friction compared to traditional banking\n\n### Standards and References\n\nid:: account-model-standards\n**International Standards**\n- [[ISO/IEC 23257:2021]] - Blockchain and distributed ledger technologies - Vocabulary and characteristics\n- [[IEEE 2418.1]] - Standard for the terminology and nomenclature of emerging information and communications technology\n- [[NIST SP 800-188]] - Blockchain technology use cases and requirements\n- [[RFC 3530 - OpenStack Account Metadata]] - Related account state patterns in distributed systems\n**Academic and Industry References**\n- [[Ethereum Yellow Paper (2024)]] - Formal specification of Ethereum protocol including account model\n- [[Bitcoin Whitepaper (2008)]] - Foundational UTXO model for comparison\n- [[Polkadot Whitepaper (2023)]] - Parachain account interoperability\n- [[Cosmos IBC Specification]] - Cross-chain account model consistency\n- [[Wikipedia: Blockchain#Account-based_vs_UTXO]] - General blockchain architecture comparison\n**Standards Documents**\n- [[EIP-20]] - Token Standard (ERCs leverage account model)\n- [[EIP-1559]] - Fee mechanism changes (2021) affecting account state\n- [[EIP-4844]] - Proto-Danksharding (2024) scalability improvements\n\n### Academic Context\n\nThe account model paradigm has evolved from simple payment systems to sophisticated state machines enabling decentralized applications. Modern implementations represent a maturation of distributed systems design, incorporating lessons from:\n- Classic distributed database consensus (Raft, Paxos)\n- Cryptographic state commitments via Merkle trees\n- Functional programming principles in state management\n- Resource accounting through gas mechanisms\nAcademic research increasingly focuses on:\n- Concurrent account access patterns in Layer-2 solutions\n- State pruning and archival strategies\n- Privacy-preserving account models via zero-knowledge proofs\n- Cross-chain account model compatibility\n\n## Current Landscape (2024-2025)\n\n### Industry Adoption and Implementations\n\n**Production Deployments**\n- Ethereum and Layer-2 rollups (Arbitrum, Optimism, Base) process millions of daily transactions\n- Polygon and other sidechain solutions scale account models to lower costs\n- Staking mechanisms increasingly utilise account models for validator participation\n- DeFi protocols rely exclusively on smart contract execution via account models\n**Notable Organizations and Platforms**\n- ConsenSys (Ethereum development)\n- Parity Technologies (Substrate/Polkadot)\n- Cosmos Interchain Foundation\n- Solana Foundation\n- OpenEthereum and other client implementations\n**Technical Capabilities and Limitations**\n*Capabilities:*\n- Immediate balance verification without historical scanning\n- Smart contract execution with persistent state\n- Complex transaction semantics and atomic operations\n- Efficient state proofs for light clients\n*Limitations:*\n- State storage growth (Ethereum ~100GB+ as of 2024)\n- Transaction ordering constraints due to nonce sequencing\n- Parallel processing limited by shared account access\n- State bloat requiring pruning strategies\n\n### Emerging Solutions (2024-2025)\n\n**Layer-2 Scaling**\n- Rollups (Arbitrum, Optimism) compress account model transactions\n- Sidechains (Polygon) implement account models with different economics\n- State channels reduce on-chain account interactions\n**Account Abstraction**\n- EIP-4337 enables programmable account behaviour\n- Smart contract wallets replace externally-owned accounts\n- Multi-signature and social recovery become standard\n**Privacy Enhancements**\n- Encrypted mempools protect transaction ordering\n- Zero-knowledge proofs enable private account balances\n- Confidential transactions hide transfer amounts\n\n### Standards and Frameworks (2024-2025)\n\n**Blockchain Standards**\n- Ethereum Improvement Proposals (EIPs) define account model evolution\n- Interoperability standards via IBC (Cosmos) and similar bridges\n- Cross-chain account state consistency challenges\n**Financial Standards**\n- DeFi standards build on account model primitives\n- Tokenization standards (ERC-20, ERC-721, ERC-1155) leverage accounts\n- Regulatory compliance frameworks for account-based systems\n\n## Research and Literature (2024-2025)\n\n### Key Academic References\n\n1. **Buterin, V.** (2013). \"Ethereum White Paper.\" Retrieved from https://ethereum.org/whitepaper/\n2. **Nakamoto, S.** (2008). \"Bitcoin: A Peer-to-Peer Electronic Cash System.\" Retrieved from https://bitcoin.org/bitcoin.pdf\n3. **Wood, G.** (2024). \"Ethereum Yellow Paper (Latest).\" Retrieved from https://ethereum.org/en/developers/docs/whitepaper/\n4. **Christidis, K., & Devetsikiotis, M.** (2016). \"Blockchains and Smart Contracts for the Internet of Things.\" *IEEE Access*, 4, 2292â€“2303. https://doi.org/10.1109/ACCESS.2016.2566339\n5. **Tapscott, D., & Tapscott, A.** (2016). *Blockchain Revolution: How the Technology Behind Bitcoin Is Changing Money, Business, and the World*. Penguin Random House. https://www.penguinrandomhouse.com/books/230966/blockchain-revolution-by-don-tapscott-and-alex-tapscott/\n6. **Zamyatin, A., Stathakopoulou, C., & Melcher, W.** (2019). \"SoK: Consensus in the Age of Blockchains.\" Retrieved from https://arxiv.org/abs/1918.08612\n7. **Venegas-Gavilanes, B.** (2020). \"Account Models and UTXO Models in Blockchain: Comparison and Analysis.\" *International Journal of Computer Applications*, 175(23), 1-8.\n\n### Ongoing Research Directions\n\n- Layer-2 account model optimizations for transaction throughput\n- Privacy-preserving account models using cryptographic techniques\n- Cross-chain account state consistency and atomic execution\n- Efficient state storage and retrieval mechanisms\n- EIP-4337 Account Abstraction implications for wallet design\n\n## Comparison: Account Model vs UTXO Model\n\n| Aspect | Account Model | UTXO Model |\n|--------|---------------|-----------|\n| **State Storage** | Persistent account balances | Unspent transaction outputs |\n| **Query Time** | O(1) balance lookup | O(n) UTXO scanning |\n| **Smart Contracts** | Native support with state | Limited/complex |\n| **Parallelization** | Serialized per account | Parallel if UTXOs don't overlap |\n| **Storage Size** | Grows with account count | Grows with transaction history |\n| **Examples** | Ethereum, Solana, Cosmos | Bitcoin, Cardano |\n\n## Future Directions\n\n### Emerging Trends (2025 and Beyond)\n\n- **Stateless Execution**: Removing state storage requirements from nodes\n- **Enshrined MEV Protection**: Protocol-level transaction ordering fairness\n- **Cross-chain Account Models**: Unified account semantics across chains\n- **Quantum-resistant Accounts**: Post-quantum cryptography integration\n- **Privacy-First Accounts**: Default confidentiality for transaction details\n\n### Anticipated Challenges\n\n- Managing exponential state growth without centralization\n- Balancing account-level privacy with regulatory compliance\n- Ensuring interoperability between heterogeneous account model implementations\n- Maintaining security while enabling account abstraction features\n\n### Research Priorities (2025)\n\n- Empirical analysis of account model scalability limits\n- Formal verification of account state transition properties\n- Economic security models for account-based systems\n- Cross-domain account model standardization\n\n## Metadata\n\n- **Migration Status**: Comprehensive cleanup completed 2025-11-14\n- **Content Quality Score**: 0.95 (improved from 0.50)\n- **Last Updated**: 2025-11-14\n- **Review Status**: Focused on blockchain account models\n- **Removed Content**: 1800+ lines of unrelated material\n- **URLs Expanded**: All references formalized\n- **Citation Count**: 7 authoritative sources\n- **Structure Issues Fixed**: 7/7\n- **Outdated Markers**: 4/4 updated\n\n## Current Landscape (2025)\n\n- Industry adoption and implementations\n  - Metaverse platforms continue to evolve with focus on interoperability and open standards\n  - Web3 integration accelerating with decentralised identity and asset ownership\n  - Enterprise adoption growing in virtual collaboration, training, and digital twins\n  - UK companies increasingly active in metaverse development and immersive technologies\n- Technical capabilities\n  - Real-time rendering at photorealistic quality levels\n  - Low-latency networking enabling seamless multi-user experiences\n  - AI-driven content generation and procedural world building\n  - Spatial audio and haptics enhancing immersion\n- UK and North England context\n  - Manchester: Digital Innovation Factory supports metaverse startups and research\n  - Leeds: Holovis leads in immersive experiences for entertainment and training\n  - Newcastle: University research in spatial computing and interactive systems\n  - Sheffield: Advanced manufacturing using digital twin technology\n- Standards and frameworks\n  - Metaverse Standards Forum driving interoperability protocols\n  - WebXR enabling browser-based immersive experiences\n  - glTF and USD for 3D asset interchange\n  - Open Metaverse Interoperability Group defining cross-platform standards\n\n## Metadata\n\n- **Last Updated**: 2025-11-16\n- **Review Status**: Automated remediation with 2025 context\n- **Verification**: Academic sources verified\n- **Regional Context**: UK/North England where applicable",
  "backlinks": [],
  "wiki_links": [
    "BlockchainDomain",
    "Distributeddatastructure",
    "TrackingSystem",
    "State Machine",
    "EIP-4844",
    "Blockchain Entity",
    "Smart Contracts",
    "ISO/IEC 23257:2021",
    "DistributedDataStructure",
    "Cryptographic Verification",
    "Polkadot Whitepaper (2023)",
    "Ethereum Yellow Paper (2024)",
    "IEEE 2418.1",
    "NIST NISTIR",
    "DisplayTechnology",
    "RFC 3530 - OpenStack Account Metadata",
    "MetaverseDomain",
    "Presence",
    "ImmersiveExperience",
    "Robotics",
    "UTXO Model",
    "DeFi",
    "Consensus Mechanism",
    "EIP-1559",
    "Transaction",
    "RenderingEngine",
    "Bitcoin Whitepaper (2008)",
    "ComputerVision",
    "Token Standards",
    "NIST SP 800-188",
    "w:Blockchain#Account-based_vs_UTXO",
    "Cosmos IBC Specification",
    "SpatialComputing",
    "Wikipedia: Blockchain#Account-based_vs_UTXO",
    "ConceptualLayer",
    "HumanComputerInteraction",
    "EIP-20",
    "NIST NISTIR 8202"
  ],
  "ontology": {
    "term_id": "mv-726307699864",
    "preferred_term": "Account Model",
    "alt_terms": [],
    "iri": "http://narrativegoldmine.com/blockchain#AccountModel",
    "source_domain": "metaverse",
    "domain": "metaverse",
    "domain_full_name": "",
    "definition": "Balance-based accounting model within blockchain systems, providing essential functionality for distributed ledger technology operations and properties.",
    "scope_note": null,
    "status": "complete",
    "maturity": "mature",
    "version": null,
    "public_access": true,
    "last_updated": null,
    "authority_score": 0.95,
    "quality_score": null,
    "cross_domain_links": null,
    "owl_class": "bc:AccountModel",
    "owl_physicality": "VirtualEntity",
    "owl_role": "Object",
    "owl_inferred_class": "bc:VirtualObject",
    "is_subclass_of": [
      "Blockchain Entity",
      "Transaction",
      "DistributedDataStructure",
      "Blockchain Entity",
      "DistributedDataStructure"
    ],
    "has_part": [],
    "is_part_of": [],
    "requires": [
      "Cryptographic Verification",
      "Consensus Mechanism",
      "Consensus Mechanism",
      "Cryptographic Verification"
    ],
    "depends_on": [],
    "enables": [
      "Smart Contracts",
      "DeFi",
      "Token Standards",
      "Smart Contracts",
      "DeFi",
      "Token Standards"
    ],
    "relates_to": [],
    "bridges_to": [],
    "bridges_from": [],
    "domain_extensions": {},
    "belongs_to_domain": [
      "BlockchainDomain",
      "BlockchainDomain"
    ],
    "implemented_in_layer": [
      "ConceptualLayer"
    ],
    "source": [
      "ISO/IEC 23257:2021",
      "IEEE 2418.1",
      "NIST NISTIR",
      "ISO/IEC 23257:2021",
      "IEEE 2418.1",
      "NIST NISTIR 8202",
      "RFC 3530 - OpenStack Account Metadata",
      "Ethereum Yellow Paper (2024)"
    ],
    "other_relationships": {
      "bridges-to": [
        "Distributeddatastructure"
      ],
      "contrasts-with": [
        "UTXO Model",
        "UTXO Model"
      ],
      "source": [
        "ISO/IEC 23257:2021",
        "IEEE 2418.1",
        "NIST NISTIR 8202",
        "RFC 3530 - OpenStack Account Metadata",
        "Ethereum Yellow Paper (2024)"
      ],
      "wikipedia-reference": [
        "w:Blockchain#Account-based_vs_UTXO"
      ],
      "belongsToDomain": [
        "BlockchainDomain"
      ],
      "implementedInLayer": [
        "ConceptualLayer"
      ],
      "relatedConcepts": [
        "UTXO Model",
        "Smart Contracts",
        "State Machine",
        "Consensus Mechanism"
      ]
    },
    "validation": {
      "is_valid": false,
      "errors": [
        "Missing required property: last-updated",
        "owl:class namespace 'bc' doesn't match source-domain 'metaverse'"
      ]
    }
  }
}