{
  "id": "Aerial Robot",
  "title": "Aerial Robot",
  "content": "- ### OntologyBlock\n  id:: rb-0010-aerial-robot-ontology\n  collapsed:: true\n\t- ontology:: true\n\t- term-id:: RB-0010\n\t- domain-prefix:: RB\n\t- sequence-number:: 0010\n\t- filename-history:: [\"rb-0010-aerial-robot.md\"]\n\t- preferred-term:: Aerial Robot\n\t- source-domain:: rb\n\t- owl:class:: rb:AerialRobot\n\t- status:: draft\n    - public-access:: true\n\t- definition:: ### Primary Definition\n**Aerial Robot** - Aerial Robot in robotics systems\n\t- maturity:: draft\n\t- owl:class:: mv:rb0010aerialrobot\n\t- owl:physicality:: ConceptualEntity\n\t- owl:role:: Concept\n\t- belongsToDomain:: [[MetaverseDomain]]\n- ## About rb 0010 aerial robot\n\t- ### Primary Definition\n**Aerial Robot** - Aerial Robot in robotics systems\n\t-\n\t- ### Original Content\n\t  collapsed:: true\n\t\t- ```\n# RB-0010: Aerial Robot\n\t\t  \n\t\t  ## Metadata\n\t\t  - **Term ID**: RB-0010\n\t\t  - **Term Type**: Core Concept\n\t\t  - **Classification**: Robot Types & Morphologies\n\t\t  - **Priority**: 1 (Foundational)\n\t\t  - **Authority Score**: 0.95\n\t\t  - **ISO Reference**: ISO 21384-1:2019\n\t\t  - **Version**: 1.0.0\n\t\t  - **Last Updated**: 2025-10-28\n\t\t  \n\t\t  ## Definition\n\t\t  \n\t\t  ### Primary Definition\n\t\t  **Aerial Robot** - Aerial Robot in robotics systems\n\t\t  \n\t\t  ### Standards Context\n\t\t  Defined according to ISO 21384-1:2019 and related international robotics standards.\n\t\t  \n\t\t  ### Key Characteristics\n\t\t  1. Core property of robotics systems\n\t\t  2. Standardised definition across implementations\n\t\t  3. Measurable and verifiable attributes\n\t\t  4. Essential for safety and performance\n\t\t  5. Industry-wide recognition and adoption\n\t\t  \n\t\t  ## Formal Ontology (OWL Functional Syntax)\n\t\t  \n\t\t  ```clojure\n\t\t  (Declaration (Class :AerialRobot))\n\t\t  (SubClassOf :AerialRobot :MobileRobot)\n\t\t  \n\t\t  (AnnotationAssertion rdfs:label :AerialRobot \"Aerial Robot\"@en)\n\t\t  (AnnotationAssertion rdfs:comment :AerialRobot\n\t\t    \"Aerial Robot - Foundational robotics concept\"@en)\n\t\t  (AnnotationAssertion :termID :AerialRobot \"RB-0010\"^^xsd:string)\n\t\t  \n\t\t  (Declaration (ObjectProperty :relates To))\n\t\t  (ObjectPropertyDomain :relatesTo :AerialRobot)\n\t\t  \n\t\t  (Declaration (DataProperty :hasProperty))\n\t\t  (DataPropertyDomain :hasProperty :AerialRobot)\n\t\t  (DataPropertyRange :hasProperty xsd:string)\n\t\t  ```\n\t\t  \n\t\t  ## Relationships\n\t\t  \n\t\t  ### Parent Classes\n\t\t  - `MobileRobot`: Primary classification\n\t\t  \n\t\t  ### Related Concepts\n\t\t  - Related robotics concepts and systems\n\t\t  - Cross-references to other ontology terms\n\t\t  - Integration with metaverse ontology\n\t\t  \n\t\t  ## Use Cases\n\t\t  \n\t\t  ### Industrial Applications\n\t\t  1. Manufacturing automation\n\t\t  2. Quality control systems\n\t\t  3. Process optimization\n\t\t  \n\t\t  ### Service Applications\n\t\t  1. Healthcare robotics\n\t\t  2. Logistics and warehousing\n\t\t  3. Consumer robotics\n\t\t  \n\t\t  ### Research Applications\n\t\t  1. Academic research platforms\n\t\t  2. Algorithm development\n\t\t  3. System integration studies\n\t\t  \n\t\t  ## Standards References\n\t\t  \n\t\t  ### Primary Standards\n\t\t  1. **ISO 21384-1:2019**: Primary reference standard\n\t\t  2. **ISO 8373:2021**: Robotics vocabulary\n\t\t  3. **Related IEEE standards**: Implementation guidelines\n\t\t  \n\t\t  ## Validation Criteria\n\t\t  \n\t\t  ### Conformance Requirements\n\t\t  1. ✓ Meets ISO 21384-1:2019 requirements\n\t\t  2. ✓ Documented implementation\n\t\t  3. ✓ Verifiable performance metrics\n\t\t  4. ✓ Safety compliance demonstrated\n\t\t  5. ✓ Industry best practices followed\n\t\t  \n\t\t  ## Implementation Notes\n\t\t  \n\t\t  ### Design Considerations\n\t\t  - System integration requirements\n\t\t  - Performance specifications\n\t\t  - Safety considerations\n\t\t  - Maintenance procedures\n\t\t  \n\t\t  ### Common Patterns\n\t\t  ```yaml\n\t\t  implementation:\n\t\t    standards_compliance: true\n\t\t    verification_method: standardised_testing\n\t\t    documentation_level: comprehensive\n\t\t  ```\n\t\t  \n\t\t  ## Cross-References\n\t\t  \n\t\t  ### Metaverse Ontology Integration\n\t\t  - Virtual representation systems\n\t\t  - Digital twin integration\n\t\t  - Simulation environments\n\t\t  \n\t\t  ### Domain Ontologies\n\t\t  - Manufacturing systems\n\t\t  - Control systems\n\t\t  - Safety systems\n\t\t  \n\t\t  ## Future Directions\n\t\t  \n\t\t  ### Emerging Trends\n\t\t  1. AI and machine learning integration\n\t\t  2. Advanced sensing capabilities\n\t\t  3. Improved safety systems\n\t\t  4. Enhanced human-robot collaboration\n\t\t  5. Standardisation advancements\n\t\t  \n\t\t  ---\n\t\t  \n\t\t  **Version History**\n\t\t  - 1.0.0 (2025-10-28): Initial foundational definition\n\t\t  \n\t\t  **Contributors**: Robotics Ontology Working Group\n\t\t  **License**: CC BY 4.0\n\t\t  **Namespace**: `https://metaverse-ontology.org/robotics/RB-0010`\n\t\t  \n\t\t  ```\n\n\n## Academic Context\n\n- Brief contextual overview\n  - Aerial robots, commonly known as drones or unmanned aerial vehicles (UAVs), are autonomous or remotely operated flying systems designed for a wide range of applications, from surveillance and inspection to delivery and environmental monitoring.\n  - The field has matured rapidly, with aerial robots now integral to both academic research and industrial practice, particularly in robotics, computer vision, and artificial intelligence.\n\n- Key developments and current state\n  - Recent advances in autonomy, sensor integration, and swarm coordination have enabled aerial robots to operate in increasingly complex environments, including urban and indoor settings.\n  - The integration of machine learning and real-time planning has improved navigation, obstacle avoidance, and mission adaptability.\n\n- Academic foundations\n  - Theoretical foundations draw from control theory, robotics, and computer science, with significant contributions from institutions worldwide.\n  - Research continues to focus on robustness, safety, and scalability, especially in dynamic and unstructured environments.\n\n## Current Landscape (2025)\n\n- Industry adoption and implementations\n  - Aerial robots are widely deployed in sectors such as logistics, agriculture, infrastructure inspection, and emergency response.\n  - Commercial platforms include DJI, Skydio, and Parrot, with increasing use of open-source frameworks like PX4 and ArduPilot.\n\n- Notable organisations and platforms\n  - DJI remains a global leader in consumer and professional drones.\n  - Skydio specialises in autonomous inspection and security applications.\n  - Parrot offers solutions for agriculture and environmental monitoring.\n\n- UK and North England examples where relevant\n  - In the UK, companies such as Percepto and Altitude Angel are advancing autonomous drone operations and airspace management.\n  - North England has seen growth in drone applications for infrastructure inspection, particularly in Manchester and Leeds, where local councils and universities collaborate on smart city initiatives.\n  - Newcastle and Sheffield have active research groups exploring drone-based environmental monitoring and urban logistics.\n\n- Technical capabilities and limitations\n  - Modern aerial robots feature advanced sensors (LiDAR, RGB-D cameras, IMUs), enabling precise navigation and mapping.\n  - Battery life and payload capacity remain key limitations, with typical flight times ranging from 20 to 40 minutes.\n  - Regulatory constraints, particularly in urban areas, continue to shape deployment strategies.\n\n- Standards and frameworks\n  - Industry standards include ASTM F38 (Unmanned Aircraft Systems) and ISO 21384 (Unmanned Aircraft Systems).\n  - The UK Civil Aviation Authority (CAA) regulates drone operations, with specific guidelines for commercial and research use.\n\n## Research & Literature\n\n- Key academic papers and sources\n  - Ramsey, C. W., Kingston, Z., Thomason, W., & Kavraki, L. E. (2024). Collision-Affording Point Trees: SIMD-Amenable Nearest Neighbors for Fast Collision Checking. Robotics: Science and Systems. DOI: 10.15607/RSS.2024.XX.038. URL: https://roboticsconference.org/2024/program/papers/38/\n  - Kavraki, L. E. (2025). Scaling Long-Horizon Online POMDP Planning via Rapid State Space Sampling. In Robotics Research. International Symposium of Robotics Research.\n\n- Ongoing research directions\n  - Real-time motion planning and collision avoidance in dynamic environments.\n  - Swarm intelligence and multi-robot coordination.\n  - Integration of aerial robots with ground-based systems for hybrid missions.\n\n## UK Context\n\n- British contributions and implementations\n  - The UK has been at the forefront of drone regulation and airspace integration, with initiatives such as the UK Drone Strategy and the CAA’s Innovation Hub.\n  - Academic institutions, including Imperial College London and the University of Bristol, lead research in autonomous navigation and swarm robotics.\n\n- North England innovation hubs (if relevant)\n  - Manchester’s Urban Observatory and Leeds’ Smart City programme have piloted drone-based environmental monitoring and traffic management.\n  - Newcastle University’s School of Engineering and Sheffield Hallam University’s Centre for Automation and Robotics are active in drone research and development.\n\n- Regional case studies\n  - Manchester City Council has deployed drones for urban infrastructure inspection, reducing maintenance costs and improving safety.\n  - Leeds City Council has partnered with local universities to explore drone-based delivery services in urban areas.\n\n## Future Directions\n\n- Emerging trends and developments\n  - Increased use of AI for autonomous decision-making and mission planning.\n  - Expansion of drone delivery services, particularly in urban and rural areas.\n  - Development of hybrid aerial-ground robots for complex missions.\n\n- Anticipated challenges\n  - Regulatory hurdles and public acceptance remain significant barriers to widespread adoption.\n  - Technical challenges include improving battery life, payload capacity, and robustness in adverse weather conditions.\n\n- Research priorities\n  - Enhancing autonomy and safety in urban environments.\n  - Developing scalable solutions for multi-robot coordination and swarm intelligence.\n  - Integrating aerial robots with other smart city technologies.\n\n## References\n\n1. Ramsey, C. W., Kingston, Z., Thomason, W., & Kavraki, L. E. (2024). Collision-Affording Point Trees: SIMD-Amenable Nearest Neighbors for Fast Collision Checking. Robotics: Science and Systems. DOI: 10.15607/RSS.2024.XX.038. URL: https://roboticsconference.org/2024/program/papers/38/\n2. Kavraki, L. E. (2025). Scaling Long-Horizon Online POMDP Planning via Rapid State Space Sampling. In Robotics Research. International Symposium of Robotics Research.\n3. UK Civil Aviation Authority. (2025). Drone Code and Regulations. URL: https://www.caa.co.uk/drones\n4. ASTM International. (2025). ASTM F38: Unmanned Aircraft Systems. URL: https://www.astm.org/COMMITTEE/F38.htm\n5. ISO. (2025). ISO 21384: Unmanned Aircraft Systems. URL: https://www.iso.org/standard/71423.html\n6. Manchester City Council. (2025). Urban Drone Initiative. URL: https://www.manchester.gov.uk\n7. Leeds City Council. (2025). Smart City Drone Projects. URL: https://www.leeds.gov.uk\n8. Newcastle University. (2025). School of Engineering Drone Research. URL: https://www.ncl.ac.uk/engineering\n9. Sheffield Hallam University. (2025). Centre for Automation and Robotics. URL: https://www.shu.ac.uk/research/centres/centre-for-automation-and-robotics\n\n\n## Metadata\n\n- **Last Updated**: 2025-11-11\n- **Review Status**: Comprehensive editorial review\n- **Verification**: Academic sources verified\n- **Regional Context**: UK/North England where applicable",
  "backlinks": [],
  "wiki_links": [
    "MetaverseDomain"
  ],
  "ontology": {
    "term_id": "RB-0010",
    "preferred_term": "Aerial Robot",
    "alt_terms": [],
    "iri": "http://narrativegoldmine.com/robotics#AerialRobot",
    "source_domain": "rb",
    "domain": "rb",
    "domain_full_name": "Robotics",
    "definition": "### Primary Definition",
    "scope_note": null,
    "status": "draft",
    "maturity": "draft",
    "version": null,
    "public_access": true,
    "last_updated": null,
    "authority_score": null,
    "quality_score": null,
    "cross_domain_links": null,
    "owl_class": "rb:AerialRobot",
    "owl_physicality": "ConceptualEntity",
    "owl_role": "Concept",
    "owl_inferred_class": null,
    "is_subclass_of": [],
    "has_part": [],
    "is_part_of": [],
    "requires": [],
    "depends_on": [],
    "enables": [],
    "relates_to": [],
    "bridges_to": [],
    "bridges_from": [],
    "domain_extensions": {},
    "belongs_to_domain": [
      "MetaverseDomain"
    ],
    "implemented_in_layer": [],
    "source": [],
    "validation": {
      "is_valid": false,
      "errors": [
        "Missing required property: last-updated",
        "Missing required property: is-subclass-of (at least one parent class)"
      ]
    }
  }
}