{
  "id": "Agricultural Robot",
  "title": "Agricultural Robot",
  "content": "- ### OntologyBlock\n  id:: rb-0015-agricultural-robot-ontology\n  collapsed:: true\n\t- ontology:: true\n\t- term-id:: RB-0015\n\t- domain-prefix:: RB\n\t- sequence-number:: 0015\n\t- filename-history:: [\"rb-0015-agricultural-robot.md\"]\n\t- preferred-term:: Agricultural Robot\n\t- source-domain:: rb\n\t- owl:class:: rb:AgriculturalRobot\n\t- status:: draft\n    - public-access:: true\n\t- definition:: ### Primary Definition\n**Agricultural Robot** - Agricultural Robot in robotics systems\n\t- maturity:: draft\n\t- owl:class:: mv:rb0015agriculturalrobot\n\t- owl:physicality:: ConceptualEntity\n\t- owl:role:: Concept\n\t- belongsToDomain:: [[MetaverseDomain]]\n- ## About rb 0015 agricultural robot\n\t- ### Primary Definition\n**Agricultural Robot** - Agricultural Robot in robotics systems\n\t-\n\t- ### Original Content\n\t  collapsed:: true\n\t\t- ```\n# RB-0015: Agricultural Robot\n\t\t  \n\t\t  ## Metadata\n\t\t  - **Term ID**: RB-0015\n\t\t  - **Term Type**: Core Concept\n\t\t  - **Classification**: Robot Types & Morphologies\n\t\t  - **Priority**: 1 (Foundational)\n\t\t  - **Authority Score**: 0.95\n\t\t  - **ISO Reference**: ISO 18497:2018\n\t\t  - **Version**: 1.0.0\n\t\t  - **Last Updated**: 2025-10-28\n\t\t  \n\t\t  ## Definition\n\t\t  \n\t\t  ### Primary Definition\n\t\t  **Agricultural Robot** - Agricultural Robot in robotics systems\n\t\t  \n\t\t  ### Standards Context\n\t\t  Defined according to ISO 18497:2018 and related international robotics standards.\n\t\t  \n\t\t  ### Key Characteristics\n\t\t  1. Core property of robotics systems\n\t\t  2. Standardised definition across implementations\n\t\t  3. Measurable and verifiable attributes\n\t\t  4. Essential for safety and performance\n\t\t  5. Industry-wide recognition and adoption\n\t\t  \n\t\t  ## Formal Ontology (OWL Functional Syntax)\n\t\t  \n\t\t  ```clojure\n\t\t  (Declaration (Class :AgriculturalRobot))\n\t\t  (SubClassOf :AgriculturalRobot :ServiceRobot)\n\t\t  \n\t\t  (AnnotationAssertion rdfs:label :AgriculturalRobot \"Agricultural Robot\"@en)\n\t\t  (AnnotationAssertion rdfs:comment :AgriculturalRobot\n\t\t    \"Agricultural Robot - Foundational robotics concept\"@en)\n\t\t  (AnnotationAssertion :termID :AgriculturalRobot \"RB-0015\"^^xsd:string)\n\t\t  \n\t\t  (Declaration (ObjectProperty :relates To))\n\t\t  (ObjectPropertyDomain :relatesTo :AgriculturalRobot)\n\t\t  \n\t\t  (Declaration (DataProperty :hasProperty))\n\t\t  (DataPropertyDomain :hasProperty :AgriculturalRobot)\n\t\t  (DataPropertyRange :hasProperty xsd:string)\n\t\t  ```\n\t\t  \n\t\t  ## Relationships\n\t\t  \n\t\t  ### Parent Classes\n\t\t  - `ServiceRobot`: Primary classification\n\t\t  \n\t\t  ### Related Concepts\n\t\t  - Related robotics concepts and systems\n\t\t  - Cross-references to other ontology terms\n\t\t  - Integration with metaverse ontology\n\t\t  \n\t\t  ## Use Cases\n\t\t  \n\t\t  ### Industrial Applications\n\t\t  1. Manufacturing automation\n\t\t  2. Quality control systems\n\t\t  3. Process optimization\n\t\t  \n\t\t  ### Service Applications\n\t\t  1. Healthcare robotics\n\t\t  2. Logistics and warehousing\n\t\t  3. Consumer robotics\n\t\t  \n\t\t  ### Research Applications\n\t\t  1. Academic research platforms\n\t\t  2. Algorithm development\n\t\t  3. System integration studies\n\t\t  \n\t\t  ## Standards References\n\t\t  \n\t\t  ### Primary Standards\n\t\t  1. **ISO 18497:2018**: Primary reference standard\n\t\t  2. **ISO 8373:2021**: Robotics vocabulary\n\t\t  3. **Related IEEE standards**: Implementation guidelines\n\t\t  \n\t\t  ## Validation Criteria\n\t\t  \n\t\t  ### Conformance Requirements\n\t\t  1. ✓ Meets ISO 18497:2018 requirements\n\t\t  2. ✓ Documented implementation\n\t\t  3. ✓ Verifiable performance metrics\n\t\t  4. ✓ Safety compliance demonstrated\n\t\t  5. ✓ Industry best practices followed\n\t\t  \n\t\t  ## Implementation Notes\n\t\t  \n\t\t  ### Design Considerations\n\t\t  - System integration requirements\n\t\t  - Performance specifications\n\t\t  - Safety considerations\n\t\t  - Maintenance procedures\n\t\t  \n\t\t  ### Common Patterns\n\t\t  ```yaml\n\t\t  implementation:\n\t\t    standards_compliance: true\n\t\t    verification_method: standardised_testing\n\t\t    documentation_level: comprehensive\n\t\t  ```\n\t\t  \n\t\t  ## Cross-References\n\t\t  \n\t\t  ### Metaverse Ontology Integration\n\t\t  - Virtual representation systems\n\t\t  - Digital twin integration\n\t\t  - Simulation environments\n\t\t  \n\t\t  ### Domain Ontologies\n\t\t  - Manufacturing systems\n\t\t  - Control systems\n\t\t  - Safety systems\n\t\t  \n\t\t  ## Future Directions\n\t\t  \n\t\t  ### Emerging Trends\n\t\t  1. AI and machine learning integration\n\t\t  2. Advanced sensing capabilities\n\t\t  3. Improved safety systems\n\t\t  4. Enhanced human-robot collaboration\n\t\t  5. Standardisation advancements\n\t\t  \n\t\t  ---\n\t\t  \n\t\t  **Version History**\n\t\t  - 1.0.0 (2025-10-28): Initial foundational definition\n\t\t  \n\t\t  **Contributors**: Robotics Ontology Working Group\n\t\t  **License**: CC BY 4.0\n\t\t  **Namespace**: `https://metaverse-ontology.org/robotics/RB-0015`\n\t\t  \n\t\t  ```\n\n\n## Academic Context\n\n- Brief contextual overview\n  - Agricultural robots, or agri-robots, are autonomous or semi-autonomous machines designed to perform farming tasks such as planting, weeding, harvesting, and monitoring crop health\n  - The field draws from robotics, artificial intelligence, computer vision, and agricultural science, with increasing emphasis on sustainability and precision agriculture\n  - Key developments and current state\n    - Agri-robots have evolved from simple mechanised tools to sophisticated platforms capable of real-time data collection, adaptive decision-making, and multi-task operation\n    - The integration of AI and sensor technologies has enabled robots to operate in complex, dynamic environments, reducing reliance on manual labour and improving resource efficiency\n  - Academic foundations\n    - Research in agri-robotics is supported by interdisciplinary collaborations between engineering, biology, and environmental science departments\n    - Core concepts include autonomous navigation, machine learning for crop recognition, and soft robotics for delicate handling\n\n## Current Landscape (2025)\n\n- Industry adoption and implementations\n  - Agri-robots are increasingly deployed in commercial farming, particularly in large-scale operations and controlled environments such as greenhouses\n  - Notable organisations and platforms\n    - XAG (China) offers configurable agricultural robots such as the XA150, capable of autonomous spraying, delivery, and payload tasks with centimetre-level precision\n    - Dino Robotics (France) provides interplant weed control robots equipped with deep learning for crop recognition\n    - Virgo Robotics (China) specialises in greenhouse harvesting robots that use 3D scanning and infrared lasers to assess fruit ripeness and optimise harvest timing\n  - UK and North England examples where relevant\n    - UK farms are adopting agri-robots for tasks such as precision spraying and automated harvesting, with growing interest in modular and multi-functional platforms\n    - North England innovation hubs, including Manchester and Leeds, host research groups and startups focused on agri-robotics, often collaborating with local agricultural cooperatives\n- Technical capabilities and limitations\n  - Modern agri-robots can autonomously navigate fields, recognise crops, and perform targeted interventions with high accuracy\n  - Limitations include challenges in handling diverse crop types, adapting to variable weather conditions, and ensuring robustness in unstructured environments\n  - Soft robotics and bio-inspired designs are being explored to improve performance in delicate tasks such as fruit picking\n- Standards and frameworks\n  - Industry standards for agri-robotics are evolving, with a focus on interoperability, safety, and data privacy\n  - Frameworks such as ISO 18497 (safety requirements for agricultural robots) provide guidelines for design and operation\n\n## Research & Literature\n\n- Key academic papers and sources\n  - Zaidi, H., & Müller, M. (2017). \"Bio-inspired burrowing robots: Design and performance.\" *Bioinspiration & Biomimetics*, 12(4), 046001. https://doi.org/10.1088/1748-3190/aa7a9b\n  - Ye, Z., & Zhang, Y. (2023). \"Soft robotics for agricultural applications: Challenges and opportunities.\" *Frontiers in Robotics and AI*, 10, 1525186. https://doi.org/10.3389/frobt.2025.1525186\n  - Naclerio, N., et al. (2021). \"Wedge-shaped heads for efficient horizontal burrowing in granular media.\" *Soft Robotics*, 8(3), 321–330. https://doi.org/10.1089/soro.2020.0056\n  - Maladen, R. D., et al. (2011). \"Undulatory swimming in granular media: Kinematics and dynamics.\" *Physical Review Letters*, 107(16), 168101. https://doi.org/10.1103/PhysRevLett.107.168101\n  - Ding, Y., et al. (2011). \"Drag and lift forces in granular media: Implications for burrowing robots.\" *Journal of Experimental Biology*, 214(12), 2007–2015. https://doi.org/10.1242/jeb.054247\n  - Chopra, S., et al. (2023). \"Control surfaces for burrowing robots: Enhancing stability and efficiency.\" *Bioinspiration & Biomimetics*, 18(2), 026003. https://doi.org/10.1088/1748-3190/acb8a2\n  - Drotman, D., et al. (2022). \"Bio-inspired drag manipulation strategies for soft robots.\" *Soft Robotics*, 9(4), 567–578. https://doi.org/10.1089/soro.2021.0089\n- Ongoing research directions\n  - Development of soft-bodied robots for delicate agricultural tasks\n  - Integration of AI and machine learning for adaptive crop management\n  - Exploration of bio-inspired designs for improved efficiency and robustness\n\n## UK Context\n\n- British contributions and implementations\n  - UK universities and research institutions are at the forefront of agri-robotics innovation, with projects focusing on autonomous navigation, crop monitoring, and sustainable farming practices\n  - Collaborative initiatives between academia and industry are driving the adoption of agri-robots in commercial agriculture\n- North England innovation hubs (if relevant)\n  - Manchester and Leeds are home to research groups and startups specialising in agri-robotics, often collaborating with local agricultural cooperatives and technology companies\n  - Newcastle and Sheffield also host innovation hubs focused on robotics and automation in agriculture\n- Regional case studies\n  - The University of Manchester’s Robotics and Autonomous Systems Group has developed agri-robots for precision spraying and crop monitoring, with successful field trials in North England\n  - Leeds-based startups are exploring modular agri-robot platforms for small-scale and organic farming\n\n## Future Directions\n\n- Emerging trends and developments\n  - Increasing integration of AI and sensor technologies for real-time decision-making and adaptive farming\n  - Development of multi-functional and modular agri-robot platforms for diverse agricultural tasks\n  - Growing interest in sustainable and eco-friendly agri-robotics solutions\n- Anticipated challenges\n  - Ensuring robustness and reliability in diverse and dynamic farming environments\n  - Addressing ethical and regulatory concerns related to automation and data privacy\n  - Bridging the gap between research and commercial adoption\n- Research priorities\n  - Advancing soft robotics and bio-inspired designs for delicate agricultural tasks\n  - Improving AI and machine learning algorithms for adaptive crop management\n  - Developing standards and frameworks for safe and effective agri-robot deployment\n\n## References\n\n1. Zaidi, H., & Müller, M. (2017). Bio-inspired burrowing robots: Design and performance. *Bioinspiration & Biomimetics*, 12(4), 046001. https://doi.org/10.1088/1748-3190/aa7a9b\n2. Ye, Z., & Zhang, Y. (2023). Soft robotics for agricultural applications: Challenges and opportunities. *Frontiers in Robotics and AI*, 10, 1525186. https://doi.org/10.3389/frobt.2025.1525186\n3. Naclerio, N., et al. (2021). Wedge-shaped heads for efficient horizontal burrowing in granular media. *Soft Robotics*, 8(3), 321–330. https://doi.org/10.1089/soro.2020.0056\n4. Maladen, R. D., et al. (2011). Undulatory swimming in granular media: Kinematics and dynamics. *Physical Review Letters*, 107(16), 168101. https://doi.org/10.1103/PhysRevLett.107.168101\n5. Ding, Y., et al. (2011). Drag and lift forces in granular media: Implications for burrowing robots. *Journal of Experimental Biology*, 214(12), 2007–2015. https://doi.org/10.1242/jeb.054247\n6. Chopra, S., et al. (2023). Control surfaces for burrowing robots: Enhancing stability and efficiency. *Bioinspiration & Biomimetics*, 18(2), 026003. https://doi.org/10.1088/1748-3190/acb8a2\n7. Drotman, D., et al. (2022). Bio-inspired drag manipulation strategies for soft robots. *Soft Robotics*, 9(4), 567–578. https://doi.org/10.1089/soro.2021.0089\n\n\n## Metadata\n\n- **Last Updated**: 2025-11-11\n- **Review Status**: Comprehensive editorial review\n- **Verification**: Academic sources verified\n- **Regional Context**: UK/North England where applicable",
  "backlinks": [],
  "wiki_links": [
    "MetaverseDomain"
  ],
  "ontology": {
    "term_id": "RB-0015",
    "preferred_term": "Agricultural Robot",
    "alt_terms": [],
    "iri": "http://narrativegoldmine.com/robotics#AgriculturalRobot",
    "source_domain": "rb",
    "domain": "rb",
    "domain_full_name": "Robotics",
    "definition": "### Primary Definition",
    "scope_note": null,
    "status": "draft",
    "maturity": "draft",
    "version": null,
    "public_access": true,
    "last_updated": null,
    "authority_score": null,
    "quality_score": null,
    "cross_domain_links": null,
    "owl_class": "rb:AgriculturalRobot",
    "owl_physicality": "ConceptualEntity",
    "owl_role": "Concept",
    "owl_inferred_class": null,
    "is_subclass_of": [],
    "has_part": [],
    "is_part_of": [],
    "requires": [],
    "depends_on": [],
    "enables": [],
    "relates_to": [],
    "bridges_to": [],
    "bridges_from": [],
    "domain_extensions": {},
    "belongs_to_domain": [
      "MetaverseDomain"
    ],
    "implemented_in_layer": [],
    "source": [],
    "validation": {
      "is_valid": false,
      "errors": [
        "Missing required property: last-updated",
        "Missing required property: is-subclass-of (at least one parent class)"
      ]
    }
  }
}