{
  "id": "AI Alignment",
  "title": "AI Alignment",
  "content": "- ### OntologyBlock\n  id:: ai-alignment-ontology\n  collapsed:: true\n\t- ontology:: true\n\t- term-id:: AI-0268\n\t- preferred-term:: AI Alignment\n\t- source-domain:: ai\n\t- status:: draft\n\t- public-access:: true\n\t- definition:: The process of making AI systems' behaviour and goals consistent with human values, preferences, and intentions. AI alignment encompasses technical methods and research aimed at ensuring AI systems act in accordance with human interests, even as they become more capable.\n\t- source:: [[OpenAI]], [[Anthropic]], [[DeepMind]], [[IEEE P7000]]\n\t- maturity:: emerging\n\t- #### Relationships\n\t  id:: ai-alignment-relationships\n\t  collapsed:: true\n\t\t- is-subclass-of:: [[AISafety]]\n\n## AI Alignment\n\nAI Alignment refers to the process of making ai systems' behaviour and goals consistent with human values, preferences, and intentions. ai alignment encompasses technical methods and research aimed at ensuring ai systems act in accordance with human interests, even as they become more capable.\n\n- AI alignment is increasingly critical as AI systems grow more capable and autonomous, particularly with advances in large language models (LLMs) and reinforcement learning.\n  - Industry adoption includes alignment techniques such as reinforcement learning from human feedback (RLHF), synthetic data generation, and red teaming to detect misalignment.\n  - Notable organisations leading alignment research include OpenAI, DeepMind, Anthropic, and academic institutions worldwide.\n  - In the UK, several AI research centres contribute to alignment efforts, with a growing focus on ethical AI deployment.\n- Technical capabilities have improved in robustness and interpretability but challenges remain in fully capturing complex human values and ensuring scalability to future AI systems.\n- Standards and frameworks for AI alignment are emerging, emphasising transparency, auditability, and continual human oversight to maintain alignment over time.\n\n## Technical Details\n\n- **Id**: ai-alignment-ontology\n- **Collapsed**: true\n- **Source Domain**: ai\n- **Status**: draft\n- **Public Access**: true\n\n## Research & Literature\n\n- Key academic papers and sources:\n  - Ji, J., et al. (2025). *AI Alignment: A Comprehensive Survey*. arXiv preprint arXiv:2310.19852. https://doi.org/10.48550/arXiv.2310.19852\n  - Christiano, P., et al. (2017). *Deep reinforcement learning from human preferences*. Advances in Neural Information Processing Systems, 30.\n  - Russell, S. (2019). *Human Compatible: Artificial Intelligence and the Problem of Control*. Viking.\n- Ongoing research directions focus on:\n  - Formalising value alignment and robustness guarantees.\n  - Developing scalable oversight mechanisms.\n  - Improving interpretability and explainability of AI decision-making.\n  - Investigating alignment in multi-agent and emergent AI systems.\n\n## UK Context\n\n- The UK has established itself as a significant contributor to AI alignment research, with institutions such as the Alan Turing Institute and universities in Manchester, Leeds, Newcastle, and Sheffield actively engaged.\n  - Manchesterâ€™s Centre for Digital Trust and Safety explores ethical AI and alignment in real-world applications.\n  - Leeds and Sheffield universities contribute to interpretability and fairness in AI models.\n  - Newcastle hosts initiatives focusing on AI governance and societal impacts.\n- Regional innovation hubs in North England foster collaboration between academia, industry, and government to advance safe and aligned AI technologies.\n- Case studies include NHS pilot projects integrating aligned AI systems for patient diagnosis and care, balancing transparency, privacy, and ethical considerations.\n\n## Future Directions\n\n- Emerging trends include:\n  - Integration of continual learning with alignment to adapt AI behaviour dynamically while preserving safety.\n  - Development of superalignment strategies addressing hypothetical artificial superintelligence risks.\n  - Enhanced human-AI collaboration frameworks to maintain alignment in complex environments.\n- Anticipated challenges:\n  - Operationalising diverse and sometimes conflicting human values across cultures and contexts.\n  - Ensuring alignment mechanisms scale with AI system complexity and autonomy.\n  - Balancing transparency with privacy and security concerns.\n- Research priorities emphasise robust, interpretable, and controllable AI systems with verifiable alignment guarantees, alongside interdisciplinary approaches incorporating social sciences and ethics.\n\n## References\n\n1. Ji, J., et al. (2025). *AI Alignment: A Comprehensive Survey*. arXiv preprint arXiv:2310.19852. https://doi.org/10.48550/arXiv.2310.19852\n2. Christiano, P., Leike, J., Brown, T., et al. (2017). Deep reinforcement learning from human preferences. *Advances in Neural Information Processing Systems*, 30.\n3. Russell, S. (2019). *Human Compatible: Artificial Intelligence and the Problem of Control*. Viking.\n4. AryaXAI. (2025). AI Alignment: Principles, Strategies, and the Path Forward. AryaXAI.\n5. IBM. (2025). What Is AI Alignment? IBM Think.\n6. World Economic Forum. (2024). AI value alignment: Aligning AI with human values.\n7. Witness AI. (2025). AI Alignment: Ensuring AI Systems Reflect Human Values.\n\n## Metadata\n\n- **Last Updated**: 2025-11-11\n- **Review Status**: Comprehensive editorial review\n- **Verification**: Academic sources verified\n- **Regional Context**: UK/North England where applicable",
  "backlinks": [
    "Safety Laser Scanner"
  ],
  "wiki_links": [
    "AISafety",
    "OpenAI",
    "Anthropic",
    "DeepMind",
    "IEEE P7000"
  ],
  "ontology": {
    "term_id": "AI-0268",
    "preferred_term": "AI Alignment",
    "alt_terms": [],
    "iri": null,
    "source_domain": "ai",
    "domain": "ai",
    "domain_full_name": "Artificial Intelligence",
    "definition": "The process of making AI systems' behaviour and goals consistent with human values, preferences, and intentions. AI alignment encompasses technical methods and research aimed at ensuring AI systems act in accordance with human interests, even as they become more capable.",
    "scope_note": null,
    "status": "draft",
    "maturity": "emerging",
    "version": null,
    "public_access": true,
    "last_updated": null,
    "authority_score": null,
    "quality_score": null,
    "cross_domain_links": null,
    "owl_class": null,
    "owl_physicality": null,
    "owl_role": null,
    "owl_inferred_class": null,
    "is_subclass_of": [
      "AISafety"
    ],
    "has_part": [],
    "is_part_of": [],
    "requires": [],
    "depends_on": [],
    "enables": [],
    "relates_to": [],
    "bridges_to": [],
    "bridges_from": [],
    "domain_extensions": {},
    "belongs_to_domain": [],
    "implemented_in_layer": [],
    "source": [
      "OpenAI",
      "Anthropic",
      "DeepMind",
      "IEEE P7000"
    ],
    "validation": {
      "is_valid": false,
      "errors": [
        "Missing required property: last-updated",
        "Missing required property: owl:class",
        "Missing required property: owl:physicality",
        "Missing required property: owl:role"
      ]
    }
  }
}