{
  "id": "AI Governance Maturity Model",
  "title": "AI Governance Maturity Model",
  "content": "- ### OntologyBlock\n  id:: ai-governance-maturity-model-ontology\n  collapsed:: true\n\t- ontology:: true\n\t- term-id:: AI-0396\n\t- preferred-term:: AI Governance Maturity Model\n\t- status:: in\n\t- public-access:: true\n\t- definition:: AI Governance Maturity Model is an assessment framework that defines progressive maturity levels for AI governance capabilities across multiple dimensions, enabling organizations to evaluate current practices, identify gaps, benchmark against peers, and guide continuous improvement toward trustworthy AI deployment. These models characterize maturity through defined levels (typically 1-5) representing progression from ad-hoc reactive practices to optimized proactive governance, with each level specifying capabilities, processes, and artifacts expected at that stage. Maturity dimensions typically include governance structure and leadership (executive commitment, organizational roles, policy frameworks), risk management (identification, assessment, mitigation, monitoring), ethical practices (principles adoption, ethics review processes, fairness auditing), technical practices (documentation standards, testing protocols, monitoring systems), compliance and audit (regulatory alignment, audit procedures, evidence collection), stakeholder engagement (consultation processes, transparency practices, redress mechanisms), and continuous improvement (metrics collection, lessons learned, iterative enhancement). Assessment methodology involves self-assessment questionnaires, evidence review (documentation, process artifacts, system logs), stakeholder interviews, and external validation, producing maturity scores, gap analysis, and improvement roadmaps. Benefits include structured governance development avoiding ad-hoc approaches, prioritization of high-impact improvements, demonstration of due diligence to regulators and stakeholders, and facilitation of organizational learning. Models draw on maturity model methodologies from Capability Maturity Model Integration (CMMI), ISO 21827 Systems Security Engineering Capability Maturity Model, and data governance maturity models, adapted for AI-specific governance challenges. Implementation examples include the Singapore Model AI Governance Framework maturity assessment and organizational maturity models from leading AI governance practitioners.\n\t- source:: [[Singapore Model AI Governance Framework]], [[CMMI Institute]], [[ISO 21827]]\n\t- maturity:: mature\n\t- owl:class:: aigo:AIGovernanceMaturityModel\n\t- owl:physicality:: VirtualEntity\n\t- owl:role:: Process\n\t- owl:inferred-class:: aigo:VirtualProcess\n\t- belongsToDomain:: [[AIEthicsDomain]]\n\t- implementedInLayer:: [[ConceptualLayer]]\n\t- #### Relationships\n\t  id:: ai-governance-maturity-model-relationships\n\t  collapsed:: true\n\t\t- is-subclass-of:: [[AIGovernanceFramework]]\n\n## AI Governance Maturity Model\n\nAI Governance Maturity Model refers to ai governance maturity model is an assessment framework that defines progressive maturity levels for ai governance capabilities across multiple dimensions, enabling organizations to evaluate current practices, identify gaps, benchmark against peers, and guide continuous improvement toward trustworthy ai deployment. these models characterize maturity through defined levels (typically 1-5) representing progression from ad-hoc reactive practices to optimised proactive governance, with each level specifying capabilities, processes, and artefacts expected at that stage. maturity dimensions typically include governance structure and leadership (executive commitment, organizational roles, policy frameworks), risk management (identification, assessment, mitigation, monitoring), ethical practices (principles adoption, ethics review processes, fairness auditing), technical practices (documentation standards, testing protocols, monitoring systems), compliance and audit (regulatory alignment, audit procedures, evidence collection), stakeholder engagement (consultation processes, transparency practices, redress mechanisms), and continuous improvement (metrics collection, lessons learned, iterative enhancement). assessment methodology involves self-assessment questionnaires, evidence review (documentation, process artefacts, system logs), stakeholder interviews, and external validation, producing maturity scores, gap analysis, and improvement roadmaps. benefits include structured governance development avoiding ad-hoc approaches, prioritization of high-impact improvements, demonstration of due diligence to regulators and stakeholders, and facilitation of organizational learning. models draw on maturity model methodologies from capability maturity model integration (cmmi), iso 21827 systems security engineering capability maturity model, and data governance maturity models, adapted for ai-specific governance challenges. implementation examples include the singapore model ai governance framework maturity assessment and organizational maturity models from leading ai governance practitioners.\n\n- Industry adoption and implementations\n\t- AI governance maturity models are widely adopted across public and private sectors, including government agencies, financial institutions, and healthcare providers\n\t- Notable organisations and platforms\n\t\t- CNA’s AI Maturity Model for Government Agencies provides a structured approach for evaluating AI governance across five domains: governance, resourcing, impact, trustworthiness, and security\n\t\t- The AI Governance Maturity Matrix, developed by researchers at Berkeley, offers boards a roadmap across five dimensions: Strategy & Vision, People & Expertise, Processes & Analytics, Ethics & Oversight, and Culture & Collaboration\n\t\t- Athena Solutions’ AI Governance Framework 2025 provides a practical checklist for implementing governance, including leadership buy-in, cross-functional teams, ethical principles, and risk assessment\n\t- UK and North England examples where relevant\n\t\t- Local authorities in Manchester and Leeds have piloted AI governance maturity assessments to guide smart city initiatives and public service automation\n\t\t- Newcastle City Council has integrated AI governance maturity principles into its digital transformation strategy, focusing on transparency and public trust\n\t\t- Sheffield’s Advanced Manufacturing Research Centre (AMRC) uses maturity models to ensure responsible AI deployment in industrial automation\n- Technical capabilities and limitations\n\t- Models enable organisations to benchmark their AI governance practices, identify gaps, and prioritise improvements\n\t- Limitations include the challenge of quantifying qualitative aspects such as organisational culture and ethical oversight\n\t- Some models struggle to keep pace with rapid technological change and emerging regulatory requirements\n- Standards and frameworks\n\t- NIST AI Risk Management Framework provides a flexible foundation for AI governance maturity models\n\t- ISO/IEC 42001 (AI management system) offers international standards for AI governance\n\t- UK-specific guidance from the Centre for Data Ethics and Innovation (CDEI) and the Information Commissioner’s Office (ICO) complements global frameworks\n\n## Technical Details\n\n- **Id**: 0396-ai-governance-maturity-model-about\n- **Collapsed**: true\n- **Domain Prefix**: AI\n- **Sequence Number**: 0396\n- **Filename History**: [\"AI-0396-ai-governance-maturity-model.md\"]\n- **Public Access**: true\n- **Source Domain**: ai\n- **Status**: in-progress\n- **Last Updated**: 2025-10-29\n- **Maturity**: mature\n- **Source**: [[Singapore Model AI Governance Framework]], [[CMMI Institute]], [[ISO 21827]]\n- **Authority Score**: 0.95\n- **Owl:Class**: aigo:AIGovernanceMaturityModel\n- **Owl:Physicality**: VirtualEntity\n- **Owl:Role**: Process\n- **Owl:Inferred Class**: aigo:VirtualProcess\n- **Belongstodomain**: [[AIEthicsDomain]]\n- **Implementedinlayer**: [[ConceptualLayer]]\n\n## Research & Literature\n\n- Key academic papers and sources\n\t- Ångström, R. C., Björn, M., Dahlander, L., Mähring, M., & Wallin, M. W. (2023). Getting AI Implementation Right: Insights from a Global Survey. California Management Review, 66(1), 5–22. https://doi.org/10.1177/00081256231198765\n\t- CNA. (2025). CNA’s Artificial Intelligence (AI) Maturity Model for Government Agencies. https://www.cna.org/reports/2025/05/AI-Maturity-Model-Government-Agencies.pdf\n\t- Athena Solutions. (2025). AI Governance Framework 2025: A Blueprint for Responsible AI. https://athena-solutions.com/ai-governance-framework-2025/\n\t- IEEE-USA Policy Committee. (2025). Maturity Model for AI Governance. https://iapp.org/resources/article/maturity-model-for-ai-governance/\n- Ongoing research directions\n\t- Development of sector-specific maturity models for healthcare, finance, and public services\n\t- Integration of AI governance maturity with broader enterprise risk management frameworks\n\t- Exploration of cultural and organisational factors influencing AI governance effectiveness\n\n## UK Context\n\n- British contributions and implementations\n\t- The UK government has promoted the use of AI governance maturity models through initiatives such as the National AI Strategy and the Centre for Data Ethics and Innovation\n\t- Organisations like NHS Digital and the Financial Conduct Authority have adopted maturity models to guide responsible AI deployment\n- North England innovation hubs (if relevant)\n\t- Manchester’s Digital Health Enterprise Zone uses AI governance maturity assessments to ensure ethical deployment in healthcare AI\n\t- Leeds City Council has established an AI governance working group to support smart city projects\n\t- Newcastle’s Urban Observatory leverages maturity models to guide AI-driven urban analytics\n- Regional case studies\n\t- Sheffield’s AMRC has published case studies on using AI governance maturity models in advanced manufacturing, highlighting the importance of cross-functional collaboration and continuous improvement\n\n## Future Directions\n\n- Emerging trends and developments\n\t- Increasing focus on AI governance maturity in small and medium enterprises (SMEs)\n\t- Development of automated tools for assessing and monitoring AI governance maturity\n\t- Greater integration of AI governance maturity with sustainability and environmental, social, and governance (ESG) reporting\n- Anticipated challenges\n\t- Keeping pace with rapid technological change and evolving regulatory requirements\n\t- Ensuring consistent application of maturity models across diverse sectors and organisational contexts\n\t- Addressing the challenge of measuring qualitative aspects such as organisational culture and ethical oversight\n- Research priorities\n\t- Development of sector-specific maturity models\n\t- Exploration of cultural and organisational factors influencing AI governance effectiveness\n\t- Integration of AI governance maturity with broader enterprise risk management frameworks\n\n## References\n\n1. Ångström, R. C., Björn, M., Dahlander, L., Mähring, M., & Wallin, M. W. (2023). Getting AI Implementation Right: Insights from a Global Survey. California Management Review, 66(1), 5–22. https://doi.org/10.1177/00081256231198765\n2. CNA. (2025). CNA’s Artificial Intelligence (AI) Maturity Model for Government Agencies. https://www.cna.org/reports/2025/05/AI-Maturity-Model-Government-Agencies.pdf\n3. Athena Solutions. (2025). AI Governance Framework 2025: A Blueprint for Responsible AI. https://athena-solutions.com/ai-governance-framework-2025/\n4. IEEE-USA Policy Committee. (2025). Maturity Model for AI Governance. https://iapp.org/resources/article/maturity-model-for-ai-governance/\n5. Centre for Data Ethics and Innovation. (2025). Guidance on AI Governance Maturity Models. https://www.gov.uk/government/organisations/centre-for-data-ethics-and-innovation\n6. Information Commissioner’s Office. (2025). AI Governance and Data Protection. https://ico.org.uk/for-organisations/guide-to-data-protection/guide-to-the-general-data-protection-regulation-gdpr/artificial-intelligence/\n7. NHS Digital. (2025). AI Governance in Healthcare. https://digital.nhs.uk/services/artificial-intelligence\n8. Financial Conduct Authority. (2025). AI Governance in Financial Services. https://www.fca.org.uk/firms/technology-innovation/artificial-intelligence\n9. Manchester Digital Health Enterprise Zone. (2025). AI Governance in Healthcare Case Studies. https://www.manchester.ac.uk/research/digital-health/\n10. Leeds City Council. (2025). AI Governance Working Group. https://www.leeds.gov.uk/\n11. Newcastle Urban Observatory. (2025). AI Governance in Urban Analytics. https://urbanobservatory.ac.uk/\n12. Sheffield AMRC. (2025). AI Governance in Advanced Manufacturing. https://www.amrc.co.uk/\n\n## Metadata\n\n- **Migration Status**: Ontology block enriched on 2025-11-12\n- **Last Updated**: 2025-11-12\n- **Review Status**: Comprehensive editorial review\n- **Verification**: Academic sources verified\n- **Regional Context**: UK/North England where applicable",
  "backlinks": [],
  "wiki_links": [
    "Singapore Model AI Governance Framework",
    "CMMI Institute",
    "AIEthicsDomain",
    "AIGovernanceFramework",
    "ConceptualLayer",
    "ISO 21827"
  ],
  "ontology": {
    "term_id": "AI-0396",
    "preferred_term": "AI Governance Maturity Model",
    "alt_terms": [],
    "iri": "http://narrativegoldmine.com/ai#aigo:AIGovernanceMaturityModel",
    "source_domain": "ai",
    "domain": "ai",
    "domain_full_name": "Artificial Intelligence",
    "definition": "AI Governance Maturity Model is an assessment framework that defines progressive maturity levels for AI governance capabilities across multiple dimensions, enabling organizations to evaluate current practices, identify gaps, benchmark against peers, and guide continuous improvement toward trustworthy AI deployment. These models characterize maturity through defined levels (typically 1-5) representing progression from ad-hoc reactive practices to optimized proactive governance, with each level specifying capabilities, processes, and artifacts expected at that stage. Maturity dimensions typically include governance structure and leadership (executive commitment, organizational roles, policy frameworks), risk management (identification, assessment, mitigation, monitoring), ethical practices (principles adoption, ethics review processes, fairness auditing), technical practices (documentation standards, testing protocols, monitoring systems), compliance and audit (regulatory alignment, audit procedures, evidence collection), stakeholder engagement (consultation processes, transparency practices, redress mechanisms), and continuous improvement (metrics collection, lessons learned, iterative enhancement). Assessment methodology involves self-assessment questionnaires, evidence review (documentation, process artifacts, system logs), stakeholder interviews, and external validation, producing maturity scores, gap analysis, and improvement roadmaps. Benefits include structured governance development avoiding ad-hoc approaches, prioritization of high-impact improvements, demonstration of due diligence to regulators and stakeholders, and facilitation of organizational learning. Models draw on maturity model methodologies from Capability Maturity Model Integration (CMMI), ISO 21827 Systems Security Engineering Capability Maturity Model, and data governance maturity models, adapted for AI-specific governance challenges. Implementation examples include the Singapore Model AI Governance Framework maturity assessment and organizational maturity models from leading AI governance practitioners.",
    "scope_note": null,
    "status": "in",
    "maturity": "mature",
    "version": null,
    "public_access": true,
    "last_updated": "2025-10-29",
    "authority_score": 0.95,
    "quality_score": null,
    "cross_domain_links": null,
    "owl_class": "aigo:AIGovernanceMaturityModel",
    "owl_physicality": "VirtualEntity",
    "owl_role": "Process",
    "owl_inferred_class": "aigo:VirtualProcess",
    "is_subclass_of": [
      "AIGovernanceFramework"
    ],
    "has_part": [],
    "is_part_of": [],
    "requires": [],
    "depends_on": [],
    "enables": [],
    "relates_to": [],
    "bridges_to": [],
    "bridges_from": [],
    "domain_extensions": {},
    "belongs_to_domain": [
      "AIEthicsDomain"
    ],
    "implemented_in_layer": [
      "ConceptualLayer"
    ],
    "source": [
      "Singapore Model AI Governance Framework",
      "CMMI Institute",
      "ISO 21827"
    ],
    "validation": {
      "is_valid": false,
      "errors": [
        "owl:class namespace 'aigo' doesn't match source-domain 'ai'"
      ]
    }
  }
}