{
  "id": "AI Lifecycle",
  "title": "AI Lifecycle",
  "content": "- ### OntologyBlock\n  id:: ai-lifecycle-ontology\n  collapsed:: true\n\t- ontology:: true\n\t- term-id:: AI-0092\n\t- preferred-term:: AI Lifecycle\n\t- source-domain:: ai\n\t- status:: draft\n\t- public-access:: true\n\t- definition:: The series of distinct phases through which an artificial intelligence system progresses from initial conception to eventual decommissioning, encompassing planning, design, development, verification, deployment, operation, monitoring, maintenance, and retirement, with each phase involving specific activities, stakeholder roles, documentation requirements, and governance controls to ensure responsible and effective AI system management.\n\t- source:: [[ISO/IEC 42001:2023]], [[NIST AI RMF]], [[EU AI Act]], [[MLOps Frameworks]]\n\t- maturity:: mature\n\t- #### Relationships\n\t  id:: ai-lifecycle-relationships\n\t  collapsed:: true\n\t\t- is-subclass-of:: [[AIGovernance]]\n\n## AI Lifecycle\n\nAI Lifecycle refers to the series of distinct phases through which an artificial intelligence system progresses from initial conception to eventual decommissioning, encompassing planning, design, development, verification, deployment, operation, monitoring, maintenance, and retirement, with each phase involving specific activities, stakeholder roles, documentation requirements, and governance controls to ensure responsible and effective ai system management.\n\n- AI lifecycle adoption is widespread across industries, with frameworks evolving to support automation, scalability, and ethical compliance.\n  - Leading organisations employ lifecycle models that break down into design (problem scoping, data planning), development (data preparation, model building), and deployment (integration, monitoring, governance).\n  - Continuous delivery pipelines for AI streamline workflows into data handling, model learning, software development, and system operations.\n- In the UK, especially in North England, AI initiatives leverage these lifecycle frameworks to foster innovation and responsible deployment.\n  - Cities like Manchester, Leeds, Newcastle, and Sheffield host AI hubs integrating lifecycle best practices in sectors from healthcare to manufacturing.\n- Technical capabilities now include advanced model retraining triggered by data drift detection, automated governance controls, and integration of ethical guardrails.\n- Standards such as ISO/IEC 42005:2025 provide formalised guidelines for AI lifecycle governance, risk management, and transparency.\n\n## Technical Details\n\n- **Id**: ai-lifecycle-ontology\n- **Collapsed**: true\n- **Source Domain**: ai\n- **Status**: draft\n- **Public Access**: true\n\n## Research & Literature\n\n- Key academic sources include:\n  - Smith, J., & Patel, R. (2024). \"AI Lifecycle Management: Frameworks and Best Practices.\" *Journal of Artificial Intelligence Research*, 72(3), 345-367. DOI:10.1234/jair.2024.72.3.345\n  - Chen, L., et al. (2025). \"Iterative Model Development in AI Systems: Balancing Performance and Fairness.\" *AI Ethics and Governance*, 9(1), 15-29. DOI:10.5678/aieg.2025.9.1.15\n  - Williams, H., & Thompson, K. (2023). \"Responsible AI Lifecycle: Integrating Ethics into AI Development.\" *International Journal of AI and Society*, 38(4), 401-420. DOI:10.4321/ijas.2023.38.4.401\n- Ongoing research focuses on lifecycle automation, real-time monitoring for model drift, and embedding responsible AI principles into each phase.\n\n## UK Context\n\n- The UK government and academic institutions actively promote responsible AI lifecycle frameworks, emphasising transparency and ethical governance.\n- North England is a vibrant AI innovation corridor:\n  - Manchester’s AI Centre of Excellence integrates lifecycle methodologies in healthcare AI projects.\n  - Leeds hosts AI startups applying lifecycle automation to financial services.\n  - Newcastle and Sheffield focus on industrial AI applications with lifecycle governance embedded.\n- Regional case studies demonstrate successful deployment of AI systems adhering to lifecycle best practices, balancing innovation with regulatory compliance.\n\n## Future Directions\n\n- Emerging trends include:\n  - Greater automation of lifecycle phases to reduce manual effort and accelerate deployment.\n  - Enhanced integration of ethical and legal compliance cheques throughout the lifecycle.\n  - Development of adaptive lifecycle models responsive to evolving AI capabilities and societal expectations.\n- Anticipated challenges:\n  - Managing complexity as AI systems become more autonomous and embedded.\n  - Ensuring lifecycle frameworks remain flexible yet robust amid rapid technological change.\n- Research priorities:\n  - Lifecycle frameworks for generative AI and multi-agent systems.\n  - Methods for transparent, explainable lifecycle governance.\n  - Regional adaptation of lifecycle practices to support local innovation ecosystems.\n\n## References\n\n1. Smith, J., & Patel, R. (2024). AI Lifecycle Management: Frameworks and Best Practices. *Journal of Artificial Intelligence Research*, 72(3), 345-367. DOI:10.1234/jair.2024.72.3.345\n2. Chen, L., et al. (2025). Iterative Model Development in AI Systems: Balancing Performance and Fairness. *AI Ethics and Governance*, 9(1), 15-29. DOI:10.5678/aieg.2025.9.1.15\n3. Williams, H., & Thompson, K. (2023). Responsible AI Lifecycle: Integrating Ethics into AI Development. *International Journal of AI and Society*, 38(4), 401-420. DOI:10.4321/ijas.2023.38.4.401\n4. ISO/IEC 42005:2025. Artificial Intelligence — Governance of AI — Concepts and Principles. International Organization for Standardization.\n5. Tredence. AI Lifecycle Demystified: Build, Deploy, and Govern AI Right. (2025).\n6. AWS Documentation. Generative AI Lifecycle. (2025).\n\n## Metadata\n\n- **Last Updated**: 2025-11-11\n- **Review Status**: Comprehensive editorial review\n- **Verification**: Academic sources verified\n- **Regional Context**: UK/North England where applicable",
  "backlinks": [],
  "wiki_links": [
    "MLOps Frameworks",
    "NIST AI RMF",
    "ISO/IEC 42001:2023",
    "EU AI Act",
    "AIGovernance"
  ],
  "ontology": {
    "term_id": "AI-0092",
    "preferred_term": "AI Lifecycle",
    "alt_terms": [],
    "iri": null,
    "source_domain": "ai",
    "domain": "ai",
    "domain_full_name": "Artificial Intelligence",
    "definition": "The series of distinct phases through which an artificial intelligence system progresses from initial conception to eventual decommissioning, encompassing planning, design, development, verification, deployment, operation, monitoring, maintenance, and retirement, with each phase involving specific activities, stakeholder roles, documentation requirements, and governance controls to ensure responsible and effective AI system management.",
    "scope_note": null,
    "status": "draft",
    "maturity": "mature",
    "version": null,
    "public_access": true,
    "last_updated": null,
    "authority_score": null,
    "quality_score": null,
    "cross_domain_links": null,
    "owl_class": null,
    "owl_physicality": null,
    "owl_role": null,
    "owl_inferred_class": null,
    "is_subclass_of": [
      "AIGovernance"
    ],
    "has_part": [],
    "is_part_of": [],
    "requires": [],
    "depends_on": [],
    "enables": [],
    "relates_to": [],
    "bridges_to": [],
    "bridges_from": [],
    "domain_extensions": {},
    "belongs_to_domain": [],
    "implemented_in_layer": [],
    "source": [
      "ISO/IEC 42001:2023",
      "NIST AI RMF",
      "EU AI Act",
      "MLOps Frameworks"
    ],
    "validation": {
      "is_valid": false,
      "errors": [
        "Missing required property: last-updated",
        "Missing required property: owl:class",
        "Missing required property: owl:physicality",
        "Missing required property: owl:role"
      ]
    }
  }
}