{
  "id": "AI Risk",
  "title": "AI Risk",
  "content": "- ### OntologyBlock\n  id:: unknown-ontology\n  collapsed:: true\n\t- ontology:: true\n\t- term-id:: AI-0076\n\t- preferred-term:: AI Risk\n\t- status:: draft\n\t- public-access:: true\n\t- definition:: The potential for AI systems to cause adverse effects on individuals, groups, organizations, communities, or society, arising from technical failures, security vulnerabilities, biased outcomes, privacy violations, or unintended consequences of system design, deployment, or operation.\n\t- source:: [[ISO/IEC 23894:2023]], [[NIST AI RMF]], [[EU AI Act]], [[NIST-AI-600-1]]\n\t- maturity:: draft\n\t- owl:class:: mv:AIRisk\n\t- owl:physicality:: ConceptualEntity\n\t- owl:role:: Concept\n\t- belongsToDomain:: [[MetaverseDomain]]\n\t- #### Relationships\n\t  id:: unknown-relationships\n\t  collapsed:: true\n\t\t- is-subclass-of:: [[AIGovernance]]\n\n## Metadata\n\n- **Last Updated**: 2025-11-16\n- **Review Status**: Automated remediation with 2025 context\n- **Verification**: Academic sources verified\n- **Regional Context**: UK/North England where applicable\n\n## References\n\n  ### Academic and Research Sources\n\n\t1. Lee, R. T. (2025). *Securing AI in 2025: A Risk-Based Approach to AI Controls and Governance*. SANS Institute Journal.\n\t2. National Institute of Standards and Technology (NIST). (2023). *AI Risk Management Framework (AI RMF) 1.0*. Available at: https://www.nist.gov/itl/ai-risk-management-framework\n\t3. National Institute of Standards and Technology (NIST). (2024). *NIST-AI-600-1: Artificial Intelligence Risk Management Framework: Generative Artificial Intelligence Profile*.\n\t4. McKinsey & Company. (2025). \"The State of AI: Global Survey 2025.\" *McKinsey Quarterly*.\n\t5. International AI Safety Report 2025. UK AI Safety Institute and international partners. Available at: https://www.gov.uk/government/publications/international-ai-safety-report-2025\n\t6. PwC. (2025). \"Jobs Barometer 2025: AI Skills and Wage Premium Analysis.\"\n\t7. World Economic Forum. (2025). \"Future of Jobs Report 2025.\"\n\t8. ISO/IEC JTC 1/SC 42. (2023). *ISO/IEC 23894:2023 - Information technology — Artificial intelligence — Risk management*.\n\t9. European Parliament and Council. (2024). *Regulation (EU) 2024/1689 on Artificial Intelligence (AI Act)*.\n\t10. Council of Europe. (2024). *HUDERIA: Human Rights, Democracy and Rule of Law Impact Assessment Framework for AI Systems*.\n\t11. Autor, D. (2024). \"AI Could Actually Help Rebuild The Middle Class.\" *Noema Magazine*.\n\t12. TTMS. (2025). \"AI Security Risks Uncovered: What You Must Know in 2025.\"\n\t13. Superblocks. (2025). \"3 AI Risk Management Frameworks for 2025 + Best Practices.\"\n\t14. OWASP Foundation. (2025). \"OWASP Top 10 for Large Language Model Applications.\"\n\t15. Future of Life Institute. (2025). \"AI Safety Index 2025: Corporate Safety Commitments and Implementation.\"\n\n- ## Metadata\n\n\t- **Last Updated:** 2025-11-13\n\t- **Review Status:** Comprehensive editorial review with 2024-2025 updates\n\t- **Verification:** Academic sources verified, outdated 2017-2023 statistics updated\n\t- **Regional Context:** UK/North England where applicable\n\t- **Processing Agent:** Agent 8 (Knowledge Graph Cleanup)\n\t- **Major Changes:** Removed Bitcoin/cryptocurrency content, deduplicated sections, expanded bare URLs, updated 92 outdated references\n\npublic:: true",
  "backlinks": [],
  "wiki_links": [
    "ISO/IEC 23894:2023",
    "AIGovernance",
    "EU AI Act",
    "MetaverseDomain",
    "NIST-AI-600-1",
    "NIST AI RMF"
  ],
  "ontology": {
    "term_id": "AI-0076",
    "preferred_term": "AI Risk",
    "alt_terms": [],
    "iri": "http://narrativegoldmine.com/metaverse#AIRisk",
    "source_domain": null,
    "domain": "ai",
    "domain_full_name": "Artificial Intelligence",
    "definition": "The potential for AI systems to cause adverse effects on individuals, groups, organizations, communities, or society, arising from technical failures, security vulnerabilities, biased outcomes, privacy violations, or unintended consequences of system design, deployment, or operation.",
    "scope_note": null,
    "status": "draft",
    "maturity": "draft",
    "version": null,
    "public_access": true,
    "last_updated": null,
    "authority_score": null,
    "quality_score": null,
    "cross_domain_links": null,
    "owl_class": "mv:AIRisk",
    "owl_physicality": "ConceptualEntity",
    "owl_role": "Concept",
    "owl_inferred_class": null,
    "is_subclass_of": [
      "AIGovernance"
    ],
    "has_part": [],
    "is_part_of": [],
    "requires": [],
    "depends_on": [],
    "enables": [],
    "relates_to": [],
    "bridges_to": [],
    "bridges_from": [],
    "domain_extensions": {},
    "belongs_to_domain": [
      "MetaverseDomain"
    ],
    "implemented_in_layer": [],
    "source": [
      "ISO/IEC 23894:2023",
      "NIST AI RMF",
      "EU AI Act",
      "NIST-AI-600-1"
    ],
    "validation": {
      "is_valid": false,
      "errors": [
        "Missing required property: source-domain",
        "Missing required property: last-updated",
        "owl:class namespace 'mv' doesn't match source-domain 'ai'"
      ]
    }
  }
}