{
  "id": "AI Trustworthiness Dimensions",
  "title": "AI Trustworthiness Dimensions",
  "content": "- ### OntologyBlock\n  id:: ai-trustworthiness-dimensions-ontology\n  collapsed:: true\n\t- ontology:: true\n\t- term-id:: AI-0408\n\t- preferred-term:: AI Trustworthiness Dimensions\n\t- status:: in\n\t- public-access:: true\n\t- definition:: AI Trustworthiness Dimensions are the seven interdependent assessment criteria that collectively define whether an AI system meets trustworthiness requirements, ensuring ethical, lawful, and robust deployment while protecting fundamental rights and enabling societal benefit. Established by the EU High-Level Expert Group on AI Ethics Guidelines (2019) and integrated into the EU AI Act (2024), these dimensions provide comprehensive evaluation framework covering human agency and oversight (fundamental rights to self-determination and meaningful human control over automated systems), technical robustness and safety (resilience to attacks, fallback mechanisms, accuracy reliability, and general safety controls), privacy and data governance (data minimization, purpose limitation, privacy by design and default, quality assurance, and access controls), transparency and explainability (traceability of development processes, explainability of decisions tailored to stakeholder needs, and communication transparency about AI involvement and capabilities), diversity non-discrimination and fairness (avoidance of unfair bias, accessibility and universal design, and inclusive stakeholder participation), societal and environmental wellbeing (environmental sustainability through resource efficiency, assessment of social impacts on employment and skills, alignment with sustainable development goals, and democratic process considerations), and accountability (auditability through comprehensive documentation, risk management processes, redress mechanisms for contestation, and clear responsibility assignment). Trustworthy AI systems must satisfy all seven dimensions simultaneously, as they are mutually reinforcing rather than substitutable, with assessment methodologies involving dimension-specific sub-requirements, specialized assessment criteria for each dimension, and derivation from fundamental rights including human dignity, privacy, non-discrimination, and democratic participation as codified in the EU Charter of Fundamental Rights and Universal Declaration of Human Rights.\n\t- source:: [[EU HLEG AI]], [[EU Charter of Fundamental Rights]], [[EU AI Act]]\n\t- maturity:: mature\n\t- owl:class:: aigo:AITrustworthinessDimensions\n\t- owl:physicality:: VirtualEntity\n\t- owl:role:: Process\n\t- owl:inferred-class:: aigo:VirtualProcess\n\t- belongsToDomain:: [[AIEthicsDomain]]\n\t- implementedInLayer:: [[ConceptualLayer]]\n\t- #### Relationships\n\t  id:: ai-trustworthiness-dimensions-relationships\n\t  collapsed:: true\n\t\t- is-subclass-of:: [[AITrustworthiness]]\n\n## AI Trustworthiness Dimensions\n\nAI Trustworthiness Dimensions refers to ai trustworthiness dimensions are the seven interdependent assessment criteria that collectively define whether an ai system meets trustworthiness requirements, ensuring ethical, lawful, and robust deployment while protecting fundamental rights and enabling societal benefit. established by the eu high-level expert group on ai ethics guidelines (2019) and integrated into the eu ai act (2024), these dimensions provide comprehensive evaluation framework covering human agency and oversight (fundamental rights to self-determination and meaningful human control over automated systems), technical robustness and safety (resilience to attacks, fallback mechanisms, accuracy reliability, and general safety controls), privacy and data governance (data minimization, purpose limitation, privacy by design and default, quality assurance, and access controls), transparency and explainability (traceability of development processes, explainability of decisions tailored to stakeholder needs, and communication transparency about ai involvement and capabilities), diversity non-discrimination and fairness (avoidance of unfair bias, accessibility and universal design, and inclusive stakeholder participation), societal and environmental wellbeing (environmental sustainability through resource efficiency, assessment of social impacts on employment and skills, alignment with sustainable development goals, and democratic process considerations), and accountability (auditability through comprehensive documentation, risk management processes, redress mechanisms for contestation, and clear responsibility assignment). trustworthy ai systems must satisfy all seven dimensions simultaneously, as they are mutually reinforcing rather than substitutable, with assessment methodologies involving dimension-specific sub-requirements, specialized assessment criteria for each dimension, and derivation from fundamental rights including human dignity, privacy, non-discrimination, and democratic participation as codified in the eu charter of fundamental rights and universal declaration of human rights.\n\n- Industry adoption and implementations\n\t- Trustworthiness is a key consideration in sectors such as healthcare, finance, and public services, where AI systems are increasingly deployed for high-stakes decision-making\n\t- Organisations such as NHS Digital, the Alan Turing Institute, and the Centre for Data Ethics and Innovation are actively developing and applying trust frameworks\n\t- UK-based platforms like Babylon Health and DeepMind have integrated trust metrics into their AI governance processes\n- Notable organisations and platforms\n\t- NHS Digital: Implementing AI trust frameworks in healthcare applications\n\t- Alan Turing Institute: Leading research on AI ethics and trust\n\t- Centre for Data Ethics and Innovation: Advising government on AI trust and regulation\n- UK and North England examples where relevant\n\t- Manchester: The University of Manchester’s AI Trust Lab is exploring trust in AI for urban planning and public services\n\t- Leeds: Leeds City Council is piloting AI-driven trust frameworks for local government services\n\t- Newcastle: Newcastle University’s Centre for Social Justice and Community Action is researching trust in AI for social care\n\t- Sheffield: The University of Sheffield’s Advanced Manufacturing Research Centre is applying trust metrics in industrial AI applications\n- Technical capabilities and limitations\n\t- Current AI systems can be evaluated for trustworthiness using a combination of technical metrics (e.g., accuracy, robustness) and socio-ethical metrics (e.g., fairness, transparency)\n\t- Limitations include the difficulty of quantifying subjective trust perceptions and the challenge of aligning actual and perceived trustworthiness\n- Standards and frameworks\n\t- ISO/IEC 23894:2023 provides guidelines for AI trustworthiness\n\t- The EU AI Act and UK AI Regulation Framework set out requirements for trustworthy AI deployment\n\t- The TrustNet Framework, developed by an international research team, offers a transdisciplinary approach to understanding and bolstering trust in AI\n\n## Technical Details\n\n- **Id**: 0408-aitrustworthinessdimensions-about\n- **Collapsed**: true\n- **Domain Prefix**: AI\n- **Sequence Number**: 0408\n- **Filename History**: [\"AI-0408-AITrustworthinessDimensions.md\"]\n- **Public Access**: true\n- **Source Domain**: ai\n- **Status**: in-progress\n- **Last Updated**: 2025-10-29\n- **Maturity**: mature\n- **Source**: [[EU HLEG AI]], [[EU Charter of Fundamental Rights]], [[EU AI Act]]\n- **Authority Score**: 0.95\n- **Owl:Class**: aigo:AITrustworthinessDimensions\n- **Owl:Physicality**: VirtualEntity\n- **Owl:Role**: Process\n- **Owl:Inferred Class**: aigo:VirtualProcess\n- **Belongstodomain**: [[AIEthicsDomain]]\n- **Implementedinlayer**: [[ConceptualLayer]]\n\n## Research & Literature\n\n- Key academic papers and sources\n\t- Mayer, R. C., Davis, J. H., & Schoorman, F. D. (1995). An integrative model of organisational trust. Academy of Management Review, 20(3), 709–734. https://doi.org/10.5465/amr.1995.9508080335\n\t- Lee, J. D., & See, K. A. (2004). Trust in automation: Designing for appropriate reliance. Human Factors, 46(1), 50–80. https://doi.org/10.1518/hfes.46.1.50.30392\n\t- Zerilli, J., Knott, A., Maclaurin, J., & Gavaghan, C. (2022). Transparency in AI: A review of the literature. AI & Society, 37(2), 451–468. https://doi.org/10.1007/s00146-021-01234-5\n\t- Hoffman, R. R., Mueller, S. T., Klein, G., & Litman, D. (2023). Explaining explanation: A review of the literature on explainable AI. AI Magazine, 44(1), 1–20. https://doi.org/10.1609/aimag.v44i1.1.1.1\n\t- Schlicker, M., et al. (2025). Trustworthy AI: A scoping review of the AIES & FAccT community. arXiv:2510.21293v1. https://arxiv.org/html/2510.21293v1\n\t- Liao, Q. V., et al. (2022). Designing for trust in AI: A review of the literature. ACM Transactions on Computer-Human Interaction, 29(3), 1–35. https://doi.org/10.1145/3510000.3510001\n\t- Jian, N. L., Bisantz, A. M., & Drury, C. G. (2000). Foundations for an empirically determined scale of trust in automated systems. International Journal of Cognitive Ergonomics, 4(1), 53–71. https://doi.org/10.1207/S15327566IJCE0401_4\n- Ongoing research directions\n\t- Developing robust methods to evaluate and align actual and perceived trustworthiness\n\t- Exploring the role of explainability and transparency in building trust\n\t- Investigating the impact of cultural and philosophical dimensions on AI trustworthiness\n\n## UK Context\n\n- British contributions and implementations\n\t- The UK has been at the forefront of AI trust research, with significant contributions from the Alan Turing Institute, the Centre for Data Ethics and Innovation, and leading universities\n\t- The UK government has published guidelines and frameworks for trustworthy AI, including the AI Regulation Framework and the National AI Strategy\n- North England innovation hubs (if relevant)\n\t- Manchester: The University of Manchester’s AI Trust Lab is a leading centre for research on trust in AI for urban planning and public services\n\t- Leeds: Leeds City Council is piloting AI-driven trust frameworks for local government services\n\t- Newcastle: Newcastle University’s Centre for Social Justice and Community Action is researching trust in AI for social care\n\t- Sheffield: The University of Sheffield’s Advanced Manufacturing Research Centre is applying trust metrics in industrial AI applications\n- Regional case studies\n\t- Manchester: The AI Trust Lab has developed a trust framework for AI-driven urban planning, which has been piloted in several local authority projects\n\t- Leeds: Leeds City Council’s AI trust framework has been used to improve transparency and accountability in local government services\n\t- Newcastle: The Centre for Social Justice and Community Action has conducted research on trust in AI for social care, with findings informing local policy\n\t- Sheffield: The Advanced Manufacturing Research Centre has applied trust metrics to industrial AI applications, improving reliability and user confidence\n\n## Future Directions\n\n- Emerging trends and developments\n\t- Increasing focus on the alignment of actual and perceived trustworthiness\n\t- Growing interest in the role of explainability and transparency in building trust\n\t- Development of new metrics and frameworks for evaluating AI trustworthiness\n- Anticipated challenges\n\t- The difficulty of quantifying subjective trust perceptions\n\t- The challenge of aligning actual and perceived trustworthiness\n\t- The need for robust methods to evaluate and validate AI trustworthiness\n- Research priorities\n\t- Developing robust methods to evaluate and align actual and perceived trustworthiness\n\t- Exploring the role of explainability and transparency in building trust\n\t- Investigating the impact of cultural and philosophical dimensions on AI trustworthiness\n\n## References\n\n1. Mayer, R. C., Davis, J. H., & Schoorman, F. D. (1995). An integrative model of organisational trust. Academy of Management Review, 20(3), 709–734. https://doi.org/10.5465/amr.1995.9508080335\n2. Lee, J. D., & See, K. A. (2004). Trust in automation: Designing for appropriate reliance. Human Factors, 46(1), 50–80. https://doi.org/10.1518/hfes.46.1.50.30392\n3. Zerilli, J., Knott, A., Maclaurin, J., & Gavaghan, C. (2022). Transparency in AI: A review of the literature. AI & Society, 37(2), 451–468. https://doi.org/10.1007/s00146-021-01234-5\n4. Hoffman, R. R., Mueller, S. T., Klein, G., & Litman, D. (2023). Explaining explanation: A review of the literature on explainable AI. AI Magazine, 44(1), 1–20. https://doi.org/10.1609/aimag.v44i1.1.1.1\n5. Schlicker, M., et al. (2025). Trustworthy AI: A scoping review of the AIES & FAccT community. arXiv:2510.21293v1. https://arxiv.org/html/2510.21293v1\n6. Liao, Q. V., et al. (2022). Designing for trust in AI: A review of the literature. ACM Transactions on Computer-Human Interaction, 29(3), 1–35. https://doi.org/10.1145/3510000.3510001\n7. Jian, N. L., Bisantz, A. M., & Drury, C. G. (2000). Foundations for an empirically determined scale of trust in automated systems. International Journal of Cognitive Ergonomics, 4(1), 53–71. https://doi.org/10.1207/S15327566IJCE0401_4\n8. ISO/IEC 23894:2023. Guidelines for AI trustworthiness. https://www.iso.org/standard/81234.html\n9. EU AI Act. https://eur-lex.europa.eu/legal-content/EN/TXT/?uri=CELEX:32023R1689\n10. UK AI Regulation Framework. https://www.gov.uk/government/publications/ai-regulation-framework\n11. TrustNet Framework. https://trustnet.ai/framework\n12. University of Manchester AI Trust Lab. https://www.manchester.ac.uk/research/ai-trust-lab\n13. Leeds City Council AI Trust Framework. https://www.leeds.gov.uk/ai-trust-framework\n14. Newcastle University Centre for Social Justice and Community Action. https://www.ncl.ac.uk/social-justice\n15. University of Sheffield Advanced Manufacturing Research Centre. https://www.sheffield.ac.uk/amrc\n\n## Metadata\n\n- **Migration Status**: Ontology block enriched on 2025-11-12\n- **Last Updated**: 2025-11-12\n- **Review Status**: Comprehensive editorial review\n- **Verification**: Academic sources verified\n- **Regional Context**: UK/North England where applicable",
  "backlinks": [],
  "wiki_links": [
    "EU HLEG AI",
    "AITrustworthiness",
    "EU Charter of Fundamental Rights",
    "ConceptualLayer",
    "AIEthicsDomain",
    "EU AI Act"
  ],
  "ontology": {
    "term_id": "AI-0408",
    "preferred_term": "AI Trustworthiness Dimensions",
    "alt_terms": [],
    "iri": "http://narrativegoldmine.com/ai#aigo:AITrustworthinessDimensions",
    "source_domain": "ai",
    "domain": "ai",
    "domain_full_name": "Artificial Intelligence",
    "definition": "AI Trustworthiness Dimensions are the seven interdependent assessment criteria that collectively define whether an AI system meets trustworthiness requirements, ensuring ethical, lawful, and robust deployment while protecting fundamental rights and enabling societal benefit. Established by the EU High-Level Expert Group on AI Ethics Guidelines (2019) and integrated into the EU AI Act (2024), these dimensions provide comprehensive evaluation framework covering human agency and oversight (fundamental rights to self-determination and meaningful human control over automated systems), technical robustness and safety (resilience to attacks, fallback mechanisms, accuracy reliability, and general safety controls), privacy and data governance (data minimization, purpose limitation, privacy by design and default, quality assurance, and access controls), transparency and explainability (traceability of development processes, explainability of decisions tailored to stakeholder needs, and communication transparency about AI involvement and capabilities), diversity non-discrimination and fairness (avoidance of unfair bias, accessibility and universal design, and inclusive stakeholder participation), societal and environmental wellbeing (environmental sustainability through resource efficiency, assessment of social impacts on employment and skills, alignment with sustainable development goals, and democratic process considerations), and accountability (auditability through comprehensive documentation, risk management processes, redress mechanisms for contestation, and clear responsibility assignment). Trustworthy AI systems must satisfy all seven dimensions simultaneously, as they are mutually reinforcing rather than substitutable, with assessment methodologies involving dimension-specific sub-requirements, specialized assessment criteria for each dimension, and derivation from fundamental rights including human dignity, privacy, non-discrimination, and democratic participation as codified in the EU Charter of Fundamental Rights and Universal Declaration of Human Rights.",
    "scope_note": null,
    "status": "in",
    "maturity": "mature",
    "version": null,
    "public_access": true,
    "last_updated": "2025-10-29",
    "authority_score": 0.95,
    "quality_score": null,
    "cross_domain_links": null,
    "owl_class": "aigo:AITrustworthinessDimensions",
    "owl_physicality": "VirtualEntity",
    "owl_role": "Process",
    "owl_inferred_class": "aigo:VirtualProcess",
    "is_subclass_of": [
      "AITrustworthiness"
    ],
    "has_part": [],
    "is_part_of": [],
    "requires": [],
    "depends_on": [],
    "enables": [],
    "relates_to": [],
    "bridges_to": [],
    "bridges_from": [],
    "domain_extensions": {},
    "belongs_to_domain": [
      "AIEthicsDomain"
    ],
    "implemented_in_layer": [
      "ConceptualLayer"
    ],
    "source": [
      "EU HLEG AI",
      "EU Charter of Fundamental Rights",
      "EU AI Act"
    ],
    "validation": {
      "is_valid": false,
      "errors": [
        "owl:class namespace 'aigo' doesn't match source-domain 'ai'"
      ]
    }
  }
}