{
  "id": "AI-0430-privacy-utility-tradeoffs",
  "title": "0430 Privacy Utility Tradeoffs",
  "content": "- ### OntologyBlock\n  id:: 0430-privacy-utility-tradeoffs-ontology\n  collapsed:: true\n\t- ontology:: true\n\t- term-id:: AI-0430\n\t- preferred-term:: 0430 Privacy Utility Tradeoffs\n\t- source-domain:: ai\n\t- status:: in\n\t- public-access:: true\n\n\n\n\n### OWL Classification\n\t- owl:class:: aigo:PrivacyUtilityTradeoffs\n\t- owl:physicality:: VirtualEntity\n\t- owl:role:: Process\n\t- owl:inferred-class:: aigo:VirtualProcess\n\n### Domain & Architecture\n\t- belongsToDomain:: [[AIEthicsDomain]]\n\t- implementedInLayer:: [[ConceptualLayer]]\n\t- maturity:: mature\n\n### Relationships\nid:: 0430-privacy-utility-tradeoffs-relationships\n\n  - #### OWL Axioms\n    id:: 0430-privacy-utility-tradeoffs-owl-axioms\n    collapsed:: true\n    - ```clojure\n      (Declaration (Class :PrivacyUtilityTradeoffs))\n(AnnotationAssertion rdfs:label :PrivacyUtilityTradeoffs \"Privacy Utility Tradeoffs\"@en)\n(SubClassOf :PrivacyUtilityTradeoffs :OptimisationProblem)\n\n;; Core Relationships\n(SubClassOf :PrivacyUtilityTradeoffs\n  (ObjectSomeValuesFrom :balances :PrivacyPreservation))\n(SubClassOf :PrivacyUtilityTradeoffs\n  (ObjectSomeValuesFrom :balances :ModelUtility))\n(SubClassOf :PrivacyUtilityTradeoffs\n  (ObjectSomeValuesFrom :optimises :ParetoFrontier))\n(SubClassOf :PrivacyUtilityTradeoffs\n  (ObjectSomeValuesFrom :quantifies :PrivacyLoss))\n(SubClassOf :PrivacyUtilityTradeoffs\n  (ObjectSomeValuesFrom :quantifies :UtilityDegradation))\n(SubClassOf :PrivacyUtilityTradeoffs\n  (ObjectSomeValuesFrom :navigates :TradeoffSpace))\n(SubClassOf :PrivacyUtilityTradeoffs\n  (ObjectSomeValuesFrom :determines :AcceptableOperatingPoint))\n(SubClassOf :PrivacyUtilityTradeoffs\n  (ObjectSomeValuesFrom :evaluates :Alternatives))\n\n;; Trade-off Dimensions\n(SubClassOf :PrivacyUtilityTradeoffs\n  (ObjectSomeValuesFrom :considers\n    (ObjectUnionOf :Accuracy\n                   :Precision\n                   :Recall\n                   :Latency\n                   :Throughput\n                   :Fairness\n                   :Explainability)))\n\n;; Privacy Metrics\n(SubClassOf :PrivacyUtilityTradeoffs\n  (ObjectSomeValuesFrom :measuresPrivacy\n    (ObjectUnionOf :DifferentialPrivacyBudget\n                   :ReidentificationRisk\n                   :InformationLeakage\n                   :MembershipInferenceRisk)))\n\n;; Utility Metrics\n(SubClassOf :PrivacyUtilityTradeoffs\n  (ObjectSomeValuesFrom :measuresUtility\n    (ObjectUnionOf :ModelAccuracy\n                   :F1Score\n                   :AUC_ROC\n                   :BusinessValue\n                   :UserSatisfaction)))\n\n;; Data Properties\n(SubClassOf :PrivacyUtilityTradeoffs\n  (DataHasValue :privacyBudget\n    (DatatypeRestriction xsd:float (MinInclusive \"0.0\"))))\n(SubClassOf :PrivacyUtilityTradeoffs\n  (DataHasValue :utilityScore\n    (DatatypeRestriction xsd:float (MinInclusive \"0.0\") (MaxInclusive \"1.0\"))))\n(SubClassOf :PrivacyUtilityTradeoffs\n  (DataHasValue :tradeoffRatio\n    (DatatypeRestriction xsd:float (MinInclusive \"0.0\"))))\n(SubClassOf :PrivacyUtilityTradeoffs\n  (DataHasValue :paretoOptimal xsd:boolean))\n\n;; Optimisation Strategies\n(SubClassOf :PrivacyUtilityTradeoffs\n  (ObjectSomeValuesFrom :employs\n    (ObjectUnionOf :MultiObjectiveOptimisation\n                   :ConstrainedOptimisation\n                   :AdaptivePrivacyBudget\n                   :ContextualTradeoff)))\n      ```\n\n### Quality Metrics\n\t- authority-score:: 0.95\n\n- ### OntologyBlock\n  id:: 0430-privacy-utility-tradeoffs-ontology\n  collapsed:: true\n\n  - **Identification**\n    - public-access:: true\n    - ontology:: true\n    - is-subclass-of:: [[ArtificialIntelligenceTechnology]]\n    - term-id:: AI-0430\n    - preferred-term:: 0430 Privacy Utility Tradeoffs\n    - source-domain:: ai-grounded\n    - status:: in-progress\n    - version:: 1.0\n    - last-updated:: 2025-10-29\n\n  - **Definition**\n    - definition:: Privacy-Utility Tradeoffs represent the fundamental tension in privacy-preserving AI between privacy preservation (protecting sensitive information through techniques like differential privacy, anonymization, or encryption) and model utility (maintaining accuracy, precision, recall, and other performance metrics necessary for effective decision-making), characterized by Pareto frontiers of achievable (privacy, utility) pairs where improving privacy typically requires sacrificing utility and vice versa. This tradeoff manifests through multiple mechanisms including noise addition in differential privacy where larger epsilon budgets (weaker privacy) enable more accurate results while smaller epsilon (stronger privacy) introduces more noise degrading utility, generalization in k-anonymity where higher k values (stronger privacy through larger anonymity sets) require more aggressive generalization reducing data granularity and analytical value, encryption overhead in homomorphic encryption where fully homomorphic schemes (strongest privacy enabling arbitrary encrypted computation) incur 10-100x performance penalties versus partially homomorphic schemes with limited operations, and aggregation granularity in federated learning where finer-grained updates provide better model convergence (higher utility) but reveal more information about individual participants (weaker privacy) compared to coarser aggregates. Quantification approaches measure privacy through differential privacy budget tracking cumulative epsilon consumption across queries, re-identification risk estimating probability adversaries can link anonymized records to individuals, information leakage quantifying bits of information disclosed about protected attributes, and membership inference risk measuring ability to determine whether specific individuals participated in training, while measuring utility through model accuracy (classification accuracy, regression R²), task-specific metrics (precision, recall, F1-score for specific applications), business value translating model performance into operational or financial impact, and user satisfaction assessing whether privacy protections produce acceptable user experience. Optimization strategies include multi-objective optimization using Pareto frontiers simultaneously maximizing both objectives identifying non-dominated solutions, constrained optimization treating one objective as constraint (minimum acceptable privacy) while maximizing the other (utility), adaptive privacy budgeting dynamically allocating more privacy budget to queries or model components most critical for utility, and contextual tradeoffs adjusting privacy-utility balance based on data sensitivity (stricter privacy for medical data, relaxed for less sensitive applications) or deployment context (tighter privacy for public deployment, relaxed for controlled research environments). Implementation decisions require determining acceptable operating points on privacy-utility frontier through stakeholder consultation balancing technical capabilities with organizational risk tolerance, regulatory requirements establishing minimum privacy standards (GDPR, HIPAA), ethical considerations assessing impacts on affected populations, and business objectives evaluating whether privacy-preserved models provide sufficient value, with practical experience showing that well-designed privacy-preserving techniques often achieve \"good enough\" utility for many applications (80-95% of unprotected performance) while dramatically reducing privacy risks, though certain high-stakes applications requiring exceptional accuracy may face difficult choices between privacy protection and operational effectiveness.\n    - maturity:: mature\n    - source:: [[Dwork and Roth (2014)]], [[Narayanan and Shmatikov (2008)]], [[NIST Privacy Framework]]\n    - authority-score:: 0.95\n\n  - **Semantic Classification**\n    - owl:class:: aigo:PrivacyUtilityTradeoffs\n    - owl:physicality:: VirtualEntity\n    - owl:role:: Process\n    - owl:inferred-class:: aigo:VirtualProcess\n    - belongsToDomain:: [[AIEthicsDomain]]\n    - implementedInLayer:: [[ConceptualLayer]]\n\n  - #### Relationships\n    id:: 0430-privacy-utility-tradeoffs-relationships\n\n  - #### OWL Axioms\n    id:: 0430-privacy-utility-tradeoffs-owl-axioms\n    collapsed:: true\n    - ```clojure\n      (Declaration (Class :PrivacyUtilityTradeoffs))\n(AnnotationAssertion rdfs:label :PrivacyUtilityTradeoffs \"Privacy Utility Tradeoffs\"@en)\n(SubClassOf :PrivacyUtilityTradeoffs :OptimisationProblem)\n\n;; Core Relationships\n(SubClassOf :PrivacyUtilityTradeoffs\n  (ObjectSomeValuesFrom :balances :PrivacyPreservation))\n(SubClassOf :PrivacyUtilityTradeoffs\n  (ObjectSomeValuesFrom :balances :ModelUtility))\n(SubClassOf :PrivacyUtilityTradeoffs\n  (ObjectSomeValuesFrom :optimises :ParetoFrontier))\n(SubClassOf :PrivacyUtilityTradeoffs\n  (ObjectSomeValuesFrom :quantifies :PrivacyLoss))\n(SubClassOf :PrivacyUtilityTradeoffs\n  (ObjectSomeValuesFrom :quantifies :UtilityDegradation))\n(SubClassOf :PrivacyUtilityTradeoffs\n  (ObjectSomeValuesFrom :navigates :TradeoffSpace))\n(SubClassOf :PrivacyUtilityTradeoffs\n  (ObjectSomeValuesFrom :determines :AcceptableOperatingPoint))\n(SubClassOf :PrivacyUtilityTradeoffs\n  (ObjectSomeValuesFrom :evaluates :Alternatives))\n\n;; Trade-off Dimensions\n(SubClassOf :PrivacyUtilityTradeoffs\n  (ObjectSomeValuesFrom :considers\n    (ObjectUnionOf :Accuracy\n                   :Precision\n                   :Recall\n                   :Latency\n                   :Throughput\n                   :Fairness\n                   :Explainability)))\n\n;; Privacy Metrics\n(SubClassOf :PrivacyUtilityTradeoffs\n  (ObjectSomeValuesFrom :measuresPrivacy\n    (ObjectUnionOf :DifferentialPrivacyBudget\n                   :ReidentificationRisk\n                   :InformationLeakage\n                   :MembershipInferenceRisk)))\n\n;; Utility Metrics\n(SubClassOf :PrivacyUtilityTradeoffs\n  (ObjectSomeValuesFrom :measuresUtility\n    (ObjectUnionOf :ModelAccuracy\n                   :F1Score\n                   :AUC_ROC\n                   :BusinessValue\n                   :UserSatisfaction)))\n\n;; Data Properties\n(SubClassOf :PrivacyUtilityTradeoffs\n  (DataHasValue :privacyBudget\n    (DatatypeRestriction xsd:float (MinInclusive \"0.0\"))))\n(SubClassOf :PrivacyUtilityTradeoffs\n  (DataHasValue :utilityScore\n    (DatatypeRestriction xsd:float (MinInclusive \"0.0\") (MaxInclusive \"1.0\"))))\n(SubClassOf :PrivacyUtilityTradeoffs\n  (DataHasValue :tradeoffRatio\n    (DatatypeRestriction xsd:float (MinInclusive \"0.0\"))))\n(SubClassOf :PrivacyUtilityTradeoffs\n  (DataHasValue :paretoOptimal xsd:boolean))\n\n;; Optimisation Strategies\n(SubClassOf :PrivacyUtilityTradeoffs\n  (ObjectSomeValuesFrom :employs\n    (ObjectUnionOf :MultiObjectiveOptimisation\n                   :ConstrainedOptimisation\n                   :AdaptivePrivacyBudget\n                   :ContextualTradeoff)))\n      ```",
  "backlinks": [],
  "wiki_links": [
    "Dwork and Roth (2014)",
    "ArtificialIntelligenceTechnology",
    "AIEthicsDomain",
    "ConceptualLayer",
    "Narayanan and Shmatikov (2008)",
    "NIST Privacy Framework"
  ],
  "ontology": {
    "term_id": "AI-0430",
    "preferred_term": "0430 Privacy Utility Tradeoffs",
    "alt_terms": [],
    "iri": "http://narrativegoldmine.com/ai#aigo:PrivacyUtilityTradeoffs",
    "source_domain": "ai",
    "domain": "ai",
    "domain_full_name": "Artificial Intelligence",
    "definition": "Privacy-Utility Tradeoffs represent the fundamental tension in privacy-preserving AI between privacy preservation (protecting sensitive information through techniques like differential privacy, anonymization, or encryption) and model utility (maintaining accuracy, precision, recall, and other performance metrics necessary for effective decision-making), characterized by Pareto frontiers of achievable (privacy, utility) pairs where improving privacy typically requires sacrificing utility and vice versa. This tradeoff manifests through multiple mechanisms including noise addition in differential privacy where larger epsilon budgets (weaker privacy) enable more accurate results while smaller epsilon (stronger privacy) introduces more noise degrading utility, generalization in k-anonymity where higher k values (stronger privacy through larger anonymity sets) require more aggressive generalization reducing data granularity and analytical value, encryption overhead in homomorphic encryption where fully homomorphic schemes (strongest privacy enabling arbitrary encrypted computation) incur 10-100x performance penalties versus partially homomorphic schemes with limited operations, and aggregation granularity in federated learning where finer-grained updates provide better model convergence (higher utility) but reveal more information about individual participants (weaker privacy) compared to coarser aggregates. Quantification approaches measure privacy through differential privacy budget tracking cumulative epsilon consumption across queries, re-identification risk estimating probability adversaries can link anonymized records to individuals, information leakage quantifying bits of information disclosed about protected attributes, and membership inference risk measuring ability to determine whether specific individuals participated in training, while measuring utility through model accuracy (classification accuracy, regression R²), task-specific metrics (precision, recall, F1-score for specific applications), business value translating model performance into operational or financial impact, and user satisfaction assessing whether privacy protections produce acceptable user experience. Optimization strategies include multi-objective optimization using Pareto frontiers simultaneously maximizing both objectives identifying non-dominated solutions, constrained optimization treating one objective as constraint (minimum acceptable privacy) while maximizing the other (utility), adaptive privacy budgeting dynamically allocating more privacy budget to queries or model components most critical for utility, and contextual tradeoffs adjusting privacy-utility balance based on data sensitivity (stricter privacy for medical data, relaxed for less sensitive applications) or deployment context (tighter privacy for public deployment, relaxed for controlled research environments). Implementation decisions require determining acceptable operating points on privacy-utility frontier through stakeholder consultation balancing technical capabilities with organizational risk tolerance, regulatory requirements establishing minimum privacy standards (GDPR, HIPAA), ethical considerations assessing impacts on affected populations, and business objectives evaluating whether privacy-preserved models provide sufficient value, with practical experience showing that well-designed privacy-preserving techniques often achieve \"good enough\" utility for many applications (80-95% of unprotected performance) while dramatically reducing privacy risks, though certain high-stakes applications requiring exceptional accuracy may face difficult choices between privacy protection and operational effectiveness.",
    "scope_note": null,
    "status": "in",
    "maturity": "mature",
    "version": "1.0",
    "public_access": true,
    "last_updated": "2025-10-29",
    "authority_score": 0.95,
    "quality_score": null,
    "cross_domain_links": null,
    "owl_class": "aigo:PrivacyUtilityTradeoffs",
    "owl_physicality": "VirtualEntity",
    "owl_role": "Process",
    "owl_inferred_class": "aigo:VirtualProcess",
    "is_subclass_of": [],
    "has_part": [],
    "is_part_of": [],
    "requires": [],
    "depends_on": [],
    "enables": [],
    "relates_to": [],
    "bridges_to": [],
    "bridges_from": [],
    "domain_extensions": {},
    "belongs_to_domain": [
      "AIEthicsDomain",
      "AIEthicsDomain"
    ],
    "implemented_in_layer": [
      "ConceptualLayer",
      "ConceptualLayer"
    ],
    "source": [
      "Dwork and Roth (2014)",
      "Narayanan and Shmatikov (2008)",
      "NIST Privacy Framework"
    ],
    "validation": {
      "is_valid": false,
      "errors": [
        "Missing required property: is-subclass-of (at least one parent class)",
        "owl:class namespace 'aigo' doesn't match source-domain 'ai'"
      ]
    }
  }
}