{
  "id": "AI-0415-IEEE7000SeriesStandards",
  "title": "IEEE 7000 Series Standards",
  "content": "- ### OntologyBlock\n  id:: 0415-ieee7000seriesstandards-ontology\n  collapsed:: true\n\t- ontology:: true\n\t- term-id:: AI-0415\n\t- preferred-term:: IEEE 7000 Series Standards\n\t- status:: in\n\t- public-access:: true\n\t- definition:: IEEE 7000 Series Standards are a comprehensive suite of technical and ethics standards providing process-based guidance for addressing ethical concerns in system design, development, and deployment, with specific focus on autonomous and intelligent systems including AI. This series encompasses multiple complementary standards: IEEE 7000 (core standard for addressing ethical concerns in system design providing systems engineering process for value-sensitive design that identifies stakeholder values and translates them into verifiable requirements), IEEE P7001 (transparency of autonomous systems defining transparency requirements, metrics, and implementation guidance enabling stakeholders to understand system capabilities, limitations, and decision processes), IEEE P7002 (data privacy process establishing privacy-by-design methodologies, privacy impact assessment procedures, and technical safeguards for personal data protection in AI systems), IEEE P7003 (algorithmic bias considerations providing bias assessment methods, fairness testing procedures, and mitigation strategies addressing discriminatory outcomes across protected groups), IEEE P7010 (wellbeing metrics standard for autonomous and intelligent systems establishing impact assessment processes evaluating effects on human wellbeing including physical, mental, social, and emotional dimensions), IEEE P2863 (organizational governance of artificial intelligence providing substantive and procedural governance requirements ensuring organizational structures, policies, and processes support responsible AI development and deployment), and IEEE P2894 (guide for environmental sustainability of AI and ML systems addressing energy efficiency, carbon footprint reduction, and resource optimization throughout AI lifecycle). These standards share common characteristics as process-based rather than prescriptive frameworks applicable throughout system lifecycle from conception through decommissioning, providing standardized processes enabling consistent implementation across organizations and jurisdictions, and complementing regulatory frameworks including EU AI Act, GDPR, and sector-specific regulations. Implementation typically involves integrating IEEE 7000 value-sensitive design methodology as overarching approach, applying domain-specific standards (P7001-P7010) to address particular ethical dimensions, establishing organizational governance per P2863, and documenting compliance evidence demonstrating systematic ethical consideration throughout development, with IEEE 7000 series particularly valued for operational guidance translating abstract ethical principles into concrete engineering practices and assessment procedures.\n\t- source:: [[IEEE 7000]], [[IEEE P7001]], [[IEEE P7003]], [[IEEE P2863]]\n\t- maturity:: mature\n\t- owl:class:: aigo:IEEE7000SeriesStandards\n\t- owl:physicality:: VirtualEntity\n\t- owl:role:: Process\n\t- owl:inferred-class:: aigo:VirtualProcess\n\t- belongsToDomain:: [[AIEthicsDomain]]\n\t- implementedInLayer:: [[ConceptualLayer]]",
  "backlinks": [],
  "wiki_links": [
    "IEEE P7003",
    "IEEE 7000",
    "AIEthicsDomain",
    "IEEE P7001",
    "ConceptualLayer",
    "IEEE P2863"
  ],
  "ontology": {
    "term_id": "AI-0415",
    "preferred_term": "IEEE 7000 Series Standards",
    "alt_terms": [],
    "iri": "http://narrativegoldmine.com/ai#aigo:IEEE7000SeriesStandards",
    "source_domain": null,
    "domain": "ai",
    "domain_full_name": "Artificial Intelligence",
    "definition": "IEEE 7000 Series Standards are a comprehensive suite of technical and ethics standards providing process-based guidance for addressing ethical concerns in system design, development, and deployment, with specific focus on autonomous and intelligent systems including AI. This series encompasses multiple complementary standards: IEEE 7000 (core standard for addressing ethical concerns in system design providing systems engineering process for value-sensitive design that identifies stakeholder values and translates them into verifiable requirements), IEEE P7001 (transparency of autonomous systems defining transparency requirements, metrics, and implementation guidance enabling stakeholders to understand system capabilities, limitations, and decision processes), IEEE P7002 (data privacy process establishing privacy-by-design methodologies, privacy impact assessment procedures, and technical safeguards for personal data protection in AI systems), IEEE P7003 (algorithmic bias considerations providing bias assessment methods, fairness testing procedures, and mitigation strategies addressing discriminatory outcomes across protected groups), IEEE P7010 (wellbeing metrics standard for autonomous and intelligent systems establishing impact assessment processes evaluating effects on human wellbeing including physical, mental, social, and emotional dimensions), IEEE P2863 (organizational governance of artificial intelligence providing substantive and procedural governance requirements ensuring organizational structures, policies, and processes support responsible AI development and deployment), and IEEE P2894 (guide for environmental sustainability of AI and ML systems addressing energy efficiency, carbon footprint reduction, and resource optimization throughout AI lifecycle). These standards share common characteristics as process-based rather than prescriptive frameworks applicable throughout system lifecycle from conception through decommissioning, providing standardized processes enabling consistent implementation across organizations and jurisdictions, and complementing regulatory frameworks including EU AI Act, GDPR, and sector-specific regulations. Implementation typically involves integrating IEEE 7000 value-sensitive design methodology as overarching approach, applying domain-specific standards (P7001-P7010) to address particular ethical dimensions, establishing organizational governance per P2863, and documenting compliance evidence demonstrating systematic ethical consideration throughout development, with IEEE 7000 series particularly valued for operational guidance translating abstract ethical principles into concrete engineering practices and assessment procedures.",
    "scope_note": null,
    "status": "in",
    "maturity": "mature",
    "version": null,
    "public_access": true,
    "last_updated": null,
    "authority_score": null,
    "quality_score": null,
    "cross_domain_links": null,
    "owl_class": "aigo:IEEE7000SeriesStandards",
    "owl_physicality": "VirtualEntity",
    "owl_role": "Process",
    "owl_inferred_class": "aigo:VirtualProcess",
    "is_subclass_of": [],
    "has_part": [],
    "is_part_of": [],
    "requires": [],
    "depends_on": [],
    "enables": [],
    "relates_to": [],
    "bridges_to": [],
    "bridges_from": [],
    "domain_extensions": {},
    "belongs_to_domain": [
      "AIEthicsDomain"
    ],
    "implemented_in_layer": [
      "ConceptualLayer"
    ],
    "source": [
      "IEEE 7000",
      "IEEE P7001",
      "IEEE P7003",
      "IEEE P2863"
    ],
    "validation": {
      "is_valid": false,
      "errors": [
        "Missing required property: source-domain",
        "Missing required property: last-updated",
        "Missing required property: is-subclass-of (at least one parent class)",
        "owl:class namespace 'aigo' doesn't match source-domain 'ai'"
      ]
    }
  }
}