{
  "id": "AI-0423-privacy-preserving-data-mining",
  "title": "0423 Privacy Preserving Data Mining",
  "content": "- ### OntologyBlock\n  id:: 0423-privacy-preserving-data-mining-ontology\n  collapsed:: true\n\t- ontology:: true\n\t- term-id:: AI-0423\n\t- preferred-term:: 0423 Privacy Preserving Data Mining\n\t- source-domain:: ai\n\t- status:: in\n\t- public-access:: true\n\n\n\n\n### OWL Classification\n\t- owl:class:: aigo:PrivacyPreservingDataMining\n\t- owl:physicality:: VirtualEntity\n\t- owl:role:: Process\n\t- owl:inferred-class:: aigo:VirtualProcess\n\n### Domain & Architecture\n\t- belongsToDomain:: [[AIEthicsDomain]]\n\t- implementedInLayer:: [[ConceptualLayer]]\n\t- maturity:: mature\n\n### Relationships\nid:: 0423-privacy-preserving-data-mining-relationships\n\n  - #### OWL Axioms\n    id:: 0423-privacy-preserving-data-mining-owl-axioms\n    collapsed:: true\n    - ```clojure\n      (Declaration (Class :PrivacyPreservingDataMining))\n(SubClassOf :PrivacyPreservingDataMining :PrivacyPreservingTechnique)\n\n;; Core Relationships\n(SubClassOf :PrivacyPreservingDataMining\n  (ObjectSomeValuesFrom :extracts :KnowledgePatterns))\n(SubClassOf :PrivacyPreservingDataMining\n  (ObjectSomeValuesFrom :protects :SensitiveInformation))\n(SubClassOf :PrivacyPreservingDataMining\n  (ObjectSomeValuesFrom :preserves :DataUtility))\n(SubClassOf :PrivacyPreservingDataMining\n  (ObjectSomeValuesFrom :prevents :InformationDisclosure))\n(SubClassOf :PrivacyPreservingDataMining\n  (ObjectSomeValuesFrom :enables :CollaborativeAnalysis))\n(SubClassOf :PrivacyPreservingDataMining\n  (ObjectSomeValuesFrom :maintains :StatisticalAccuracy))\n(SubClassOf :PrivacyPreservingDataMining\n  (ObjectSomeValuesFrom :applies :PrivacyGuarantees))\n(SubClassOf :PrivacyPreservingDataMining\n  (ObjectSomeValuesFrom :supports :DistributedComputation))\n\n;; PPDM Techniques\n(SubClassOf :PrivacyPreservingDataMining\n  (ObjectSomeValuesFrom :employs\n    (ObjectUnionOf :DataPerturbation\n                   :DataAnonymisation\n                   :CryptographicProtocols\n                   :QueryRestriction\n                   :DataDistortion)))\n\n;; Mining Tasks\n(SubClassOf :PrivacyPreservingDataMining\n  (ObjectSomeValuesFrom :performs\n    (ObjectUnionOf :AssociationRuleMining\n                   :ClassificationMining\n                   :ClusteringAnalysis\n                   :OutlierDetection\n                   :SequentialPatternMining)))\n\n;; Privacy Models\n(SubClassOf :PrivacyPreservingDataMining\n  (ObjectSomeValuesFrom :implements\n    (ObjectUnionOf :DifferentialPrivacy\n                   :kAnonymity\n                   :lDiversity\n                   :tCloseness\n                   :SecureMultipartyComputation)))\n\n;; Data Properties\n(SubClassOf :PrivacyPreservingDataMining\n  (DataHasValue :privacyLevel\n    (DatatypeRestriction xsd:float (MinInclusive \"0.0\") (MaxInclusive \"1.0\"))))\n(SubClassOf :PrivacyPreservingDataMining\n  (DataHasValue :accuracyLoss\n    (DatatypeRestriction xsd:float (MinInclusive \"0.0\") (MaxInclusive \"1.0\"))))\n(SubClassOf :PrivacyPreservingDataMining\n  (DataHasValue :miningAlgorithm xsd:string))\n(SubClassOf :PrivacyPreservingDataMining\n  (DataHasValue :informationLeakageRisk\n    (DatatypeRestriction xsd:float (MinInclusive \"0.0\") (MaxInclusive \"1.0\"))))\n\n;; Architectural Patterns\n(SubClassOf :PrivacyPreservingDataMining\n  (ObjectSomeValuesFrom :follows\n    (ObjectUnionOf :CentralisedArchitecture\n                   :DistributedArchitecture\n                   :FederatedArchitecture\n                   :HybridArchitecture)))\n\n;; Regulatory Compliance\n(SubClassOf :PrivacyPreservingDataMining\n  (ObjectSomeValuesFrom :compliesWith\n    (ObjectUnionOf :GDPR_Article6 ;; Lawfulness of processing\n                   :GDPR_Article9 ;; Special categories\n                   :GDPR_Article22 ;; Automated decision-making\n                   :ISO27701\n                   :NISTPrivacyFramework)))\n\n;; Application Domains\n(SubClassOf :PrivacyPreservingDataMining\n  (ObjectSomeValuesFrom :appliesTo\n    (ObjectUnionOf :HealthcareAnalytics\n                   :FinancialForensics\n                   :SocialNetworkAnalysis\n                   :RetailBehaviourAnalysis\n                   :GovernmentStatistics)))\n\n;; Quality Metrics\n(SubClassOf :PrivacyPreservingDataMining\n  (ObjectSomeValuesFrom :measures\n    (ObjectUnionOf :PrivacyMetric\n                   :UtilityMetric\n                   :EfficiencyMetric\n                   :ScalabilityMetric)))\n      ```\n\n### Quality Metrics\n\t- authority-score:: 0.95\n\n- ### OntologyBlock\n  id:: 0423-privacy-preserving-data-mining-ontology\n  collapsed:: true\n\n  - **Identification**\n    - public-access:: true\n    - ontology:: true\n    - term-id:: AI-0423\n    - preferred-term:: 0423 Privacy Preserving Data Mining\n    - source-domain:: ai-grounded\n    - status:: in-progress\n    - version:: 1.0\n    - last-updated:: 2025-10-29\n\n  - **Definition**\n    - definition:: Privacy-Preserving Data Mining is a research field and set of techniques enabling extraction of useful knowledge patterns from datasets while protecting sensitive information and preventing disclosure of individual records, balancing utility of discovered patterns with privacy protection of underlying data. This approach addresses dual objectives of pattern accuracy (ensuring discovered knowledge reflects true underlying patterns without excessive distortion from privacy mechanisms) and privacy protection (preventing adversaries from inferring sensitive individual information from published patterns or intermediate computations). Techniques span data perturbation methods adding noise or modifying values before mining (randomization, data swapping, synthetic data generation), cryptographic protocols enabling secure collaborative mining (secure multi-party computation for distributed pattern discovery, homomorphic encryption for encrypted mining operations), anonymization approaches transforming data before release (k-anonymity, l-diversity, t-closeness for publishing datasets supporting subsequent mining), and query restriction mechanisms limiting information disclosure (differential privacy for query responses, output perturbation for pattern publication). Application domains include healthcare analytics discovering disease patterns while protecting patient privacy, financial forensics detecting fraud patterns without exposing transaction details, social network analysis extracting community structures while preserving user privacy, retail behavior analysis identifying purchase patterns without revealing individual shopping histories, and government statistics enabling policy research without compromising citizen confidentiality. The technique applies across mining tasks including association rule mining discovering itemset patterns with support and confidence privacy constraints, classification learning predictive models on privacy-protected training data, clustering grouping similar records while preventing cluster membership disclosure, and outlier detection identifying anomalies without revealing specific outlier identities. Implementation must navigate inherent tensions including privacy-utility tradeoffs where stronger privacy typically reduces pattern accuracy, computational overhead from cryptographic operations or noise addition, and composability challenges when mining results from multiple analyses could enable inference attacks, with evaluation requiring both privacy metrics (information leakage, re-identification risk) and utility metrics (pattern accuracy, false discovery rate).\n    - maturity:: mature\n    - source:: [[Agrawal and Srikant (2000)]], [[GDPR Article 9]], [[ISO/IEC TR 24027]]\n    - authority-score:: 0.95\n\n  - **Semantic Classification**\n    - owl:class:: aigo:PrivacyPreservingDataMining\n    - owl:physicality:: VirtualEntity\n    - owl:role:: Process\n    - owl:inferred-class:: aigo:VirtualProcess\n    - belongsToDomain:: [[AIEthicsDomain]]\n    - implementedInLayer:: [[ConceptualLayer]]\n\n  - #### Relationships\n    id:: 0423-privacy-preserving-data-mining-relationships\n\n  - #### OWL Axioms\n    id:: 0423-privacy-preserving-data-mining-owl-axioms\n    collapsed:: true\n    - ```clojure\n      (Declaration (Class :PrivacyPreservingDataMining))\n(SubClassOf :PrivacyPreservingDataMining :PrivacyPreservingTechnique)\n\n;; Core Relationships\n(SubClassOf :PrivacyPreservingDataMining\n  (ObjectSomeValuesFrom :extracts :KnowledgePatterns))\n(SubClassOf :PrivacyPreservingDataMining\n  (ObjectSomeValuesFrom :protects :SensitiveInformation))\n(SubClassOf :PrivacyPreservingDataMining\n  (ObjectSomeValuesFrom :preserves :DataUtility))\n(SubClassOf :PrivacyPreservingDataMining\n  (ObjectSomeValuesFrom :prevents :InformationDisclosure))\n(SubClassOf :PrivacyPreservingDataMining\n  (ObjectSomeValuesFrom :enables :CollaborativeAnalysis))\n(SubClassOf :PrivacyPreservingDataMining\n  (ObjectSomeValuesFrom :maintains :StatisticalAccuracy))\n(SubClassOf :PrivacyPreservingDataMining\n  (ObjectSomeValuesFrom :applies :PrivacyGuarantees))\n(SubClassOf :PrivacyPreservingDataMining\n  (ObjectSomeValuesFrom :supports :DistributedComputation))\n\n;; PPDM Techniques\n(SubClassOf :PrivacyPreservingDataMining\n  (ObjectSomeValuesFrom :employs\n    (ObjectUnionOf :DataPerturbation\n                   :DataAnonymisation\n                   :CryptographicProtocols\n                   :QueryRestriction\n                   :DataDistortion)))\n\n;; Mining Tasks\n(SubClassOf :PrivacyPreservingDataMining\n  (ObjectSomeValuesFrom :performs\n    (ObjectUnionOf :AssociationRuleMining\n                   :ClassificationMining\n                   :ClusteringAnalysis\n                   :OutlierDetection\n                   :SequentialPatternMining)))\n\n;; Privacy Models\n(SubClassOf :PrivacyPreservingDataMining\n  (ObjectSomeValuesFrom :implements\n    (ObjectUnionOf :DifferentialPrivacy\n                   :kAnonymity\n                   :lDiversity\n                   :tCloseness\n                   :SecureMultipartyComputation)))\n\n;; Data Properties\n(SubClassOf :PrivacyPreservingDataMining\n  (DataHasValue :privacyLevel\n    (DatatypeRestriction xsd:float (MinInclusive \"0.0\") (MaxInclusive \"1.0\"))))\n(SubClassOf :PrivacyPreservingDataMining\n  (DataHasValue :accuracyLoss\n    (DatatypeRestriction xsd:float (MinInclusive \"0.0\") (MaxInclusive \"1.0\"))))\n(SubClassOf :PrivacyPreservingDataMining\n  (DataHasValue :miningAlgorithm xsd:string))\n(SubClassOf :PrivacyPreservingDataMining\n  (DataHasValue :informationLeakageRisk\n    (DatatypeRestriction xsd:float (MinInclusive \"0.0\") (MaxInclusive \"1.0\"))))\n\n;; Architectural Patterns\n(SubClassOf :PrivacyPreservingDataMining\n  (ObjectSomeValuesFrom :follows\n    (ObjectUnionOf :CentralisedArchitecture\n                   :DistributedArchitecture\n                   :FederatedArchitecture\n                   :HybridArchitecture)))\n\n;; Regulatory Compliance\n(SubClassOf :PrivacyPreservingDataMining\n  (ObjectSomeValuesFrom :compliesWith\n    (ObjectUnionOf :GDPR_Article6 ;; Lawfulness of processing\n                   :GDPR_Article9 ;; Special categories\n                   :GDPR_Article22 ;; Automated decision-making\n                   :ISO27701\n                   :NISTPrivacyFramework)))\n\n;; Application Domains\n(SubClassOf :PrivacyPreservingDataMining\n  (ObjectSomeValuesFrom :appliesTo\n    (ObjectUnionOf :HealthcareAnalytics\n                   :FinancialForensics\n                   :SocialNetworkAnalysis\n                   :RetailBehaviourAnalysis\n                   :GovernmentStatistics)))\n\n;; Quality Metrics\n(SubClassOf :PrivacyPreservingDataMining\n  (ObjectSomeValuesFrom :measures\n    (ObjectUnionOf :PrivacyMetric\n                   :UtilityMetric\n                   :EfficiencyMetric\n                   :ScalabilityMetric)))\n      ```\n\n### Relationships\n- is-subclass-of:: [[MachineLearning]]",
  "backlinks": [],
  "wiki_links": [
    "GDPR Article 9",
    "Agrawal and Srikant (2000)",
    "AIEthicsDomain",
    "MachineLearning",
    "ConceptualLayer",
    "ISO/IEC TR 24027"
  ],
  "ontology": {
    "term_id": "AI-0423",
    "preferred_term": "0423 Privacy Preserving Data Mining",
    "alt_terms": [],
    "iri": "http://narrativegoldmine.com/ai#aigo:PrivacyPreservingDataMining",
    "source_domain": "ai",
    "domain": "ai",
    "domain_full_name": "Artificial Intelligence",
    "definition": "Privacy-Preserving Data Mining is a research field and set of techniques enabling extraction of useful knowledge patterns from datasets while protecting sensitive information and preventing disclosure of individual records, balancing utility of discovered patterns with privacy protection of underlying data. This approach addresses dual objectives of pattern accuracy (ensuring discovered knowledge reflects true underlying patterns without excessive distortion from privacy mechanisms) and privacy protection (preventing adversaries from inferring sensitive individual information from published patterns or intermediate computations). Techniques span data perturbation methods adding noise or modifying values before mining (randomization, data swapping, synthetic data generation), cryptographic protocols enabling secure collaborative mining (secure multi-party computation for distributed pattern discovery, homomorphic encryption for encrypted mining operations), anonymization approaches transforming data before release (k-anonymity, l-diversity, t-closeness for publishing datasets supporting subsequent mining), and query restriction mechanisms limiting information disclosure (differential privacy for query responses, output perturbation for pattern publication). Application domains include healthcare analytics discovering disease patterns while protecting patient privacy, financial forensics detecting fraud patterns without exposing transaction details, social network analysis extracting community structures while preserving user privacy, retail behavior analysis identifying purchase patterns without revealing individual shopping histories, and government statistics enabling policy research without compromising citizen confidentiality. The technique applies across mining tasks including association rule mining discovering itemset patterns with support and confidence privacy constraints, classification learning predictive models on privacy-protected training data, clustering grouping similar records while preventing cluster membership disclosure, and outlier detection identifying anomalies without revealing specific outlier identities. Implementation must navigate inherent tensions including privacy-utility tradeoffs where stronger privacy typically reduces pattern accuracy, computational overhead from cryptographic operations or noise addition, and composability challenges when mining results from multiple analyses could enable inference attacks, with evaluation requiring both privacy metrics (information leakage, re-identification risk) and utility metrics (pattern accuracy, false discovery rate).",
    "scope_note": null,
    "status": "in",
    "maturity": "mature",
    "version": "1.0",
    "public_access": true,
    "last_updated": "2025-10-29",
    "authority_score": 0.95,
    "quality_score": null,
    "cross_domain_links": null,
    "owl_class": "aigo:PrivacyPreservingDataMining",
    "owl_physicality": "VirtualEntity",
    "owl_role": "Process",
    "owl_inferred_class": "aigo:VirtualProcess",
    "is_subclass_of": [],
    "has_part": [],
    "is_part_of": [],
    "requires": [],
    "depends_on": [],
    "enables": [],
    "relates_to": [],
    "bridges_to": [],
    "bridges_from": [],
    "domain_extensions": {},
    "belongs_to_domain": [
      "AIEthicsDomain",
      "AIEthicsDomain"
    ],
    "implemented_in_layer": [
      "ConceptualLayer",
      "ConceptualLayer"
    ],
    "source": [
      "Agrawal and Srikant (2000)",
      "GDPR Article 9",
      "ISO/IEC TR 24027"
    ],
    "validation": {
      "is_valid": false,
      "errors": [
        "Missing required property: is-subclass-of (at least one parent class)",
        "owl:class namespace 'aigo' doesn't match source-domain 'ai'"
      ]
    }
  }
}