{
  "id": "AI-0436-edge-cloud-collaboration",
  "title": "Edge-Cloud Collaboration",
  "content": "- ### OntologyBlock\n  id:: edge-cloud-collaboration-(ai-0436)-ontology\n  collapsed:: true\n\t- ontology:: true\n\t- term-id:: AI-0436\n\t- preferred-term:: Edge-Cloud Collaboration\n\t- source-domain:: ai\n\t- status:: in\n\t- public-access:: true\n\t- definition:: Edge-Cloud Collaboration is a hybrid architecture dynamically partitioning AI workloads between resource-constrained edge devices and powerful cloud infrastructure, optimizing end-to-end latency, bandwidth utilization, energy consumption, and accuracy through adaptive offloading, model splitting, and hierarchical inference. This approach implements collaboration patterns including model splitting where neural networks are partitioned across edge and cloud with early layers on edge extracting features and final layers in cloud for classification enabling bandwidth reduction through compressed intermediate representations, early exit where models have multiple exit points enabling confident predictions to terminate early on edge while uncertain cases escalate to cloud balancing accuracy and latency, cascaded inference deploying lightweight model on edge as first-stage filter with complex model in cloud for challenging instances providing 60-80% latency reduction for common cases, and federated learning where edge devices collaboratively train shared model through local training and gradient aggregation without centralizing raw data. Optimization objectives balance competing goals including end-to-end latency minimization considering network roundtrip, cloud queueing, and processing times, bandwidth reduction limiting data transmission through selective offloading and compression, energy efficiency managing device battery consumption from computation versus transmission, and accuracy preservation ensuring collaborative inference maintains performance comparable to cloud-only deployment. Implementation challenges include network variability requiring adaptive policies responding to changing bandwidth and latency conditions, workload partitioning decisions determining optimal split points based on model architecture and runtime conditions, synchronization overhead coordinating state between edge and cloud components, and failure handling maintaining availability when connectivity degrades or cloud services become unavailable through graceful degradation to edge-only operation. The 2024-2025 period demonstrated viability through deployments in autonomous vehicles processing sensor fusion on-vehicle with cloud-based planning and mapping, augmented reality offloading object detection to edge with scene understanding in cloud achieving sub-50ms total latency, and industrial IoT combining edge anomaly detection with cloud predictive maintenance enabling 90% bandwidth reduction while improving accuracy 15% versus edge-only deployment, implemented through frameworks including AWS IoT Greengrass, Azure IoT Edge, and Google Cloud IoT enabling seamless edge-cloud orchestration.\n\t- source:: [[AWS IoT Greengrass]], [[Azure IoT Edge]], [[ETSI MEC]]\n\t- maturity:: mature\n\t- owl:class:: ai:EdgeCloudCollaboration\n\t- owl:physicality:: VirtualEntity\n\t- owl:role:: Process\n\t- owl:inferred-class:: aigo:VirtualProcess\n\t- belongsToDomain:: [[AIEthicsDomain]]\n\t- implementedInLayer:: [[ConceptualLayer]]",
  "backlinks": [],
  "wiki_links": [
    "ETSI MEC",
    "AWS IoT Greengrass",
    "AIEthicsDomain",
    "ConceptualLayer",
    "Azure IoT Edge"
  ],
  "ontology": {
    "term_id": "AI-0436",
    "preferred_term": "Edge-Cloud Collaboration",
    "alt_terms": [],
    "iri": "http://narrativegoldmine.com/ai#EdgeCloudCollaboration",
    "source_domain": "ai",
    "domain": "ai",
    "domain_full_name": "Artificial Intelligence",
    "definition": "Edge-Cloud Collaboration is a hybrid architecture dynamically partitioning AI workloads between resource-constrained edge devices and powerful cloud infrastructure, optimizing end-to-end latency, bandwidth utilization, energy consumption, and accuracy through adaptive offloading, model splitting, and hierarchical inference. This approach implements collaboration patterns including model splitting where neural networks are partitioned across edge and cloud with early layers on edge extracting features and final layers in cloud for classification enabling bandwidth reduction through compressed intermediate representations, early exit where models have multiple exit points enabling confident predictions to terminate early on edge while uncertain cases escalate to cloud balancing accuracy and latency, cascaded inference deploying lightweight model on edge as first-stage filter with complex model in cloud for challenging instances providing 60-80% latency reduction for common cases, and federated learning where edge devices collaboratively train shared model through local training and gradient aggregation without centralizing raw data. Optimization objectives balance competing goals including end-to-end latency minimization considering network roundtrip, cloud queueing, and processing times, bandwidth reduction limiting data transmission through selective offloading and compression, energy efficiency managing device battery consumption from computation versus transmission, and accuracy preservation ensuring collaborative inference maintains performance comparable to cloud-only deployment. Implementation challenges include network variability requiring adaptive policies responding to changing bandwidth and latency conditions, workload partitioning decisions determining optimal split points based on model architecture and runtime conditions, synchronization overhead coordinating state between edge and cloud components, and failure handling maintaining availability when connectivity degrades or cloud services become unavailable through graceful degradation to edge-only operation. The 2024-2025 period demonstrated viability through deployments in autonomous vehicles processing sensor fusion on-vehicle with cloud-based planning and mapping, augmented reality offloading object detection to edge with scene understanding in cloud achieving sub-50ms total latency, and industrial IoT combining edge anomaly detection with cloud predictive maintenance enabling 90% bandwidth reduction while improving accuracy 15% versus edge-only deployment, implemented through frameworks including AWS IoT Greengrass, Azure IoT Edge, and Google Cloud IoT enabling seamless edge-cloud orchestration.",
    "scope_note": null,
    "status": "in",
    "maturity": "mature",
    "version": null,
    "public_access": true,
    "last_updated": null,
    "authority_score": null,
    "quality_score": null,
    "cross_domain_links": null,
    "owl_class": "ai:EdgeCloudCollaboration",
    "owl_physicality": "VirtualEntity",
    "owl_role": "Process",
    "owl_inferred_class": "aigo:VirtualProcess",
    "is_subclass_of": [],
    "has_part": [],
    "is_part_of": [],
    "requires": [],
    "depends_on": [],
    "enables": [],
    "relates_to": [],
    "bridges_to": [],
    "bridges_from": [],
    "domain_extensions": {},
    "belongs_to_domain": [
      "AIEthicsDomain"
    ],
    "implemented_in_layer": [
      "ConceptualLayer"
    ],
    "source": [
      "AWS IoT Greengrass",
      "Azure IoT Edge",
      "ETSI MEC"
    ],
    "validation": {
      "is_valid": false,
      "errors": [
        "Missing required property: last-updated",
        "Missing required property: is-subclass-of (at least one parent class)"
      ]
    }
  }
}