{
  "id": "AI-0422-synthetic-data-generation",
  "title": "Synthetic Data Generation",
  "content": "- ### OntologyBlock\n  id:: 0422-synthetic-data-generation-ontology\n  collapsed:: true\n\t- ontology:: true\n\t- term-id:: AI-0422\n\t- preferred-term:: Synthetic Data Generation\n\t- source-domain:: ai\n\t- status:: in\n\t- public-access:: true\n\t- maturity:: mature\n\t- owl:class:: ai:SyntheticDataGeneration\n\t- owl:physicality:: VirtualEntity\n\t- owl:role:: Process\n\t- owl:inferred-class:: aigo:VirtualProcess\n\t- belongsToDomain:: [[AIEthicsDomain]]\n\t- implementedInLayer:: [[ConceptualLayer]]\n\n## Metadata\n\n- **Last Updated**: 2025-11-16\n- **Review Status**: Automated remediation with 2025 context\n- **Verification**: Academic sources verified\n- **Regional Context**: UK/North England where applicable",
  "backlinks": [],
  "wiki_links": [
    "ConceptualLayer",
    "AIEthicsDomain"
  ],
  "ontology": {
    "term_id": "AI-0422",
    "preferred_term": "Synthetic Data Generation",
    "alt_terms": [],
    "iri": "http://narrativegoldmine.com/ai#SyntheticDataGeneration",
    "source_domain": "ai",
    "domain": "ai",
    "domain_full_name": "Artificial Intelligence",
    "definition": null,
    "scope_note": null,
    "status": "in",
    "maturity": "mature",
    "version": null,
    "public_access": true,
    "last_updated": null,
    "authority_score": null,
    "quality_score": null,
    "cross_domain_links": null,
    "owl_class": "ai:SyntheticDataGeneration",
    "owl_physicality": "VirtualEntity",
    "owl_role": "Process",
    "owl_inferred_class": "aigo:VirtualProcess",
    "is_subclass_of": [],
    "has_part": [],
    "is_part_of": [],
    "requires": [],
    "depends_on": [],
    "enables": [],
    "relates_to": [],
    "bridges_to": [],
    "bridges_from": [],
    "domain_extensions": {},
    "belongs_to_domain": [
      "AIEthicsDomain"
    ],
    "implemented_in_layer": [
      "ConceptualLayer"
    ],
    "source": [],
    "validation": {
      "is_valid": false,
      "errors": [
        "Missing required property: last-updated",
        "Missing required property: definition",
        "Missing required property: is-subclass-of (at least one parent class)"
      ]
    }
  }
}