{
  "id": "ALBERT",
  "title": "ALBERT",
  "content": "- ### OntologyBlock\n  id:: albert-ontology\n  collapsed:: true\n\t- ontology:: true\n\t- term-id:: AI-0218\n\t- preferred-term:: ALBERT\n\t- source-domain:: metaverse\n\t- status:: draft\n\t- public-access:: true\n\n\n\n\n### OWL Classification\n\t- owl:class:: mv:ALBERT\n\t- owl:physicality:: ConceptualEntity\n\t- owl:role:: Concept\n\n### Domain & Architecture\n\t- belongsToDomain:: [[MetaverseDomain]]\n\t- maturity:: draft\n\n### Relationships\n- is-subclass-of:: [[BERT]]\n\n## Characteristics\n\n- **Parameter Reduction**: Significantly fewer parameters than BERT\n- **Factorised Embeddings**: Separates embedding dimension from hidden dimension\n- **Cross-Layer Sharing**: Shares parameters across layers\n- **Sentence-Order Prediction**: Replaces NSP with more challenging objective\n\n## Academic Foundations\n\n**Primary Source**: Lan et al., \"ALBERT: A Lite BERT for Self-supervised Learning of Language Representations\", arXiv:1909.11942 (2019)\n\n**Efficiency Gains**: 18× fewer parameters than BERT-large whilst achieving better performance on several benchmarks.\n\n## Technical Context\n\nALBERT demonstrates that parameter sharing and factorised embeddings can dramatically reduce model size without sacrificing performance. The sentence-order prediction task proves more effective than BERT's next sentence prediction.\n\n## Ontological Relationships\n\n- **Broader Term**: Pre-trained Language Model\n- **Related Terms**: BERT, RoBERTa, Parameter-Efficient Models\n- **Innovation**: Parameter Sharing, Factorised Embeddings\n\n## Usage Context\n\n\"ALBERT achieves state-of-the-art performance on GLUE, SQuAD, and RACE benchmarks with 18× fewer parameters than BERT-large.\"\n\n## OWL Functional Syntax\n\n```clojure\n(Declaration (Class :ALBERT))\n(AnnotationAssertion rdfs:label :ALBERT \"ALBERT\"@en)\n(AnnotationAssertion rdfs:comment :ALBERT\n  \"A Lite BERT: a parameter-efficient variant of BERT using factorised embedding parameterisation and cross-layer parameter sharing.\"@en)\n(AnnotationAssertion :hasSource :ALBERT\n  \"Lan et al., 'ALBERT: A Lite BERT for Self-supervised Learning', arXiv:1909.11942 (2019)\"@en)\n\n;; Taxonomic relationships\n(SubClassOf :ALBERT :PreTrainedLanguageModel)\n(SubClassOf :ALBERT :TransformerArchitecture)\n(SubClassOf :ALBERT :ParameterEfficientModel)\n\n;; Based on BERT\n(SubClassOf :ALBERT\n  (ObjectSomeValuesFrom :derivedFrom :BERT))\n\n;; Key innovations\n(SubClassOf :ALBERT\n  (ObjectSomeValuesFrom :uses :FactorisedEmbedding))\n(SubClassOf :ALBERT\n  (ObjectSomeValuesFrom :uses :CrossLayerParameterSharing))\n(SubClassOf :ALBERT\n  (ObjectSomeValuesFrom :uses :SentenceOrderPrediction))\n\n;; Capabilities\n(SubClassOf :ALBERT\n  (ObjectSomeValuesFrom :performsTask :LanguageUnderstanding))\n(SubClassOf :ALBERT\n  (ObjectSomeValuesFrom :performsTask :QuestionAnswering))\n\n;; Efficiency properties\n(DataPropertyAssertion :parameterReductionFactor :ALBERT \"18\"^^xsd:integer)\n(DataPropertyAssertion :maintainsPerformance :ALBERT \"true\"^^xsd:boolean)\n(DataPropertyAssertion :isParameterEfficient :ALBERT \"true\"^^xsd:boolean)\n(DataPropertyAssertion :achievesStateOfTheArt :ALBERT \"GLUE, SQuAD, RACE\"^^xsd:string)\n\n;; Related models\n(DisjointClasses :ALBERT :RoBERTa)\n(DisjointClasses :ALBERT :DeBERTa)\n```\n\n## References\n\n- Lan, Z., et al. (2019). \"ALBERT: A Lite BERT for Self-supervised Learning of Language Representations\". arXiv:1909.11942\n\n---\n\n*Ontology Term managed by AI-Grounded Ontology Working Group*\n*UK English Spelling Standards Applied*\n\t- maturity:: draft\n\t- owl:class:: mv:ALBERT\n\t- owl:physicality:: ConceptualEntity\n\t- owl:role:: Concept\n\t- belongsToDomain:: [[MetaverseDomain]]",
  "backlinks": [],
  "wiki_links": [
    "BERT",
    "MetaverseDomain"
  ],
  "ontology": {
    "term_id": "AI-0218",
    "preferred_term": "ALBERT",
    "alt_terms": [],
    "iri": "http://narrativegoldmine.com/metaverse#ALBERT",
    "source_domain": "metaverse",
    "domain": "metaverse",
    "domain_full_name": "",
    "definition": null,
    "scope_note": null,
    "status": "draft",
    "maturity": "draft",
    "version": null,
    "public_access": true,
    "last_updated": null,
    "authority_score": null,
    "quality_score": null,
    "cross_domain_links": null,
    "owl_class": "mv:ALBERT",
    "owl_physicality": "ConceptualEntity",
    "owl_role": "Concept",
    "owl_inferred_class": null,
    "is_subclass_of": [],
    "has_part": [],
    "is_part_of": [],
    "requires": [],
    "depends_on": [],
    "enables": [],
    "relates_to": [],
    "bridges_to": [],
    "bridges_from": [],
    "domain_extensions": {},
    "belongs_to_domain": [
      "MetaverseDomain",
      "MetaverseDomain"
    ],
    "implemented_in_layer": [],
    "source": [],
    "validation": {
      "is_valid": false,
      "errors": [
        "Missing required property: last-updated",
        "Missing required property: definition",
        "Missing required property: is-subclass-of (at least one parent class)",
        "owl:class namespace 'mv' doesn't match source-domain 'metaverse'"
      ]
    }
  }
}