{
  "id": "Algorithmic Accountability",
  "title": "Algorithmic Accountability",
  "content": "- ### OntologyBlock\n  id:: algorithmic-accountability-ontology\n  collapsed:: true\n\t- ontology:: true\n\t- term-id:: AI-0376\n\t- preferred-term:: Algorithmic Accountability\n\t- source-domain:: ai\n\t- owl:class:: ai:AlgorithmicAccountability\n\t- status:: complete\n\t- public-access:: true\n\t- definition:: Algorithmic Accountability is a responsibility framework that ensures AI systems and their developers are answerable for the decisions, outcomes, and impacts produced by algorithmic processes, including mechanisms for redress, transparency, and oversight.\n\t- source:: [[IEEE P2863]]\n\t- maturity:: mature\n\t- owl:class:: aigo:AIGovernancePrinciple\n\t- owl:physicality:: VirtualEntity\n\t- owl:role:: Process\n\t- owl:inferred-class:: aigo:VirtualProcess\n\t- belongsToDomain:: [[AIEthicsDomain]]\n\t- implementedInLayer:: [[ConceptualLayer]]\n\t- #### Relationships\n\t  id:: algorithmic-accountability-relationships\n\t  collapsed:: true\n\t\t- is-subclass-of:: [[AIGovernance]]\n\t\t- is-subclass-of:: [[EthicalFramework]]\n\t\t- is-subclass-of:: [[RegulatoryCompliance]]\n\t\t- is-subclass-of:: [[AIGovernancePrinciple]]\n\n## Algorithmic Accountability\n\nAlgorithmic Accountability refers to algorithmic accountability is a responsibility framework that ensures ai systems and their developers are answerable for the decisions, outcomes, and impacts produced by algorithmic processes, including mechanisms for redress, transparency, and oversight.\n\n- Industry adoption and implementations\n  - Algorithmic accountability is now a core requirement in sectors including recruitment, finance, healthcare, and public services\n  - Notable organisations and platforms\n    - Major tech firms (e.g., Google, Microsoft) have integrated accountability frameworks into their AI governance\n    - Financial institutions (e.g., Barclays, HSBC) employ algorithmic impact assessments for automated trading and advisory systems\n    - UK public sector bodies, such as the NHS and HMRC, are piloting accountable AI systems for service delivery\n  - UK and North England examples where relevant\n    - Manchester’s Digital Health Innovation Centre uses accountable AI for patient triage and resource allocation\n    - Leeds City Council has implemented algorithmic tools for social housing allocation, with mandatory human review and bias audits\n    - Newcastle University’s Centre for Data Ethics and Innovation collaborates with local authorities on accountable AI for urban planning\n    - Sheffield’s Advanced Manufacturing Research Centre (AMRC) applies accountable AI in workforce management and skills matching\n- Technical capabilities and limitations\n  - Modern systems support real-time monitoring, bias detection, and explainability features\n  - Limitations include the complexity of auditing black-box models, the challenge of defining fairness metrics, and the risk of adversarial manipulation\n  - Continuous review and monitoring are essential, as bias and performance can shift with changing data and user behaviour\n- Standards and frameworks\n  - International standards such as ISO/IEC 23894 (AI risk management) and IEEE P7003 (algorithmic bias considerations) provide guidance\n  - The UK’s Centre for Data Ethics and Innovation (CDEI) has published best practice frameworks for algorithmic accountability\n  - Sector-specific frameworks exist for recruitment (e.g., CIPD guidelines), finance (e.g., FCA expectations), and public services (e.g., GOV.UK standards)\n\n## Technical Details\n\n- **Id**: algorithmic-accountability-about\n- **Collapsed**: true\n- **Domain Prefix**: AI\n- **Sequence Number**: 0376\n- **Filename History**: [\"AI-0376-algorithmic-accountability.md\"]\n- **Public Access**: true\n- **Source Domain**: ai\n- **Status**: complete\n- **Last Updated**: 2025-10-28\n- **Maturity**: mature\n- **Source**: [[IEEE P2863]]\n- **Authority Score**: 0.95\n- **Owl:Class**: aigo:AIGovernancePrinciple\n- **Owl:Physicality**: VirtualEntity\n- **Owl:Role**: Process\n- **Owl:Inferred Class**: aigo:VirtualProcess\n- **Belongstodomain**: [[AIEthicsDomain]]\n- **Implementedinlayer**: [[ConceptualLayer]]\n- **Is Subclass Of**: [[AIGovernancePrinciple]], [[EthicalFramework]], [[RegulatoryCompliance]]\n\n## Research & Literature\n\n- Key academic papers and sources\n  - Mittelstadt, B. D., Allo, P., Taddeo, M., Wachter, S., & Floridi, L. (2016). The ethics of algorithms: Mapping the debate. *Big Data & Society*, 3(2), 2053951716679679. https://doi.org/10.1177/2053951716679679\n  - Wachter, S., Mittelstadt, B., & Floridi, L. (2017). Why a right to explanation of automated decision-making does not exist in the General Data Protection Regulation. *International Data Privacy Law*, 7(2), 76–99. https://doi.org/10.1093/idpl/ipx005\n  - Selbst, A. D., Boyd, D., Friedler, S. A., Venkatasubramanian, S., & Vertesi, J. (2019). Fairness and abstraction in sociotechnical systems. *Proceedings of the Conference on Fairness, Accountability, and Transparency (FAT*), 59–68. https://doi.org/10.1145/3287560.3287598\n  - CDEI (2023). *Algorithmic Accountability: A Practical Guide for Organisations*. Centre for Data Ethics and Innovation. https://www.gov.uk/government/publications/algorithmic-accountability-a-practical-guide-for-organisations\n- Ongoing research directions\n  - Developing robust methods for bias detection and mitigation\n  - Exploring the role of human oversight in hybrid decision-making systems\n  - Investigating the impact of algorithmic accountability on organisational culture and employee trust\n\n## UK Context\n\n- British contributions and implementations\n  - The UK has been a leader in algorithmic accountability, with the CDEI and the Information Commissioner’s Office (ICO) driving policy and practice\n  - The Algorithmic Accountability Act 2025 (proposed) would require impact assessments for high-risk automated decision systems, aligning with international best practice\n  - The ICO’s guidance on AI and data protection emphasises transparency, fairness, and accountability\n- North England innovation hubs (if relevant)\n  - Manchester’s Digital Health Innovation Centre is a hub for accountable AI in healthcare\n  - Leeds City Council’s digital transformation programme includes accountable AI for social services\n  - Newcastle University’s Centre for Data Ethics and Innovation collaborates with local authorities on accountable AI for urban planning\n  - Sheffield’s AMRC applies accountable AI in workforce management and skills matching\n- Regional case studies\n  - Manchester: Accountable AI for patient triage in the NHS\n  - Leeds: Algorithmic tools for social housing allocation with mandatory human review\n  - Newcastle: Accountable AI for urban planning and environmental monitoring\n  - Sheffield: Accountable AI for workforce management and skills matching in advanced manufacturing\n\n## Future Directions\n\n- Emerging trends and developments\n  - Increasing integration of accountable AI in public and private sector decision-making\n  - Development of sector-specific accountability frameworks and standards\n  - Growing emphasis on explainability and transparency in AI systems\n- Anticipated challenges\n  - Balancing innovation with regulatory compliance\n  - Addressing the complexity of auditing black-box models\n  - Ensuring fairness and avoiding bias in diverse and dynamic environments\n- Research priorities\n  - Developing robust methods for bias detection and mitigation\n  - Exploring the role of human oversight in hybrid decision-making systems\n  - Investigating the impact of algorithmic accountability on organisational culture and employee trust\n\n## References\n\n1. Mittelstadt, B. D., Allo, P., Taddeo, M., Wachter, S., & Floridi, L. (2016). The ethics of algorithms: Mapping the debate. *Big Data & Society*, 3(2), 2053951716679679. https://doi.org/10.1177/2053951716679679\n2. Wachter, S., Mittelstadt, B., & Floridi, L. (2017). Why a right to explanation of automated decision-making does not exist in the General Data Protection Regulation. *International Data Privacy Law*, 7(2), 76–99. https://doi.org/10.1093/idpl/ipx005\n3. Selbst, A. D., Boyd, D., Friedler, S. A., Venkatasubramanian, S., & Vertesi, J. (2019). Fairness and abstraction in sociotechnical systems. *Proceedings of the Conference on Fairness, Accountability, and Transparency (FAT*)*, 59–68. https://doi.org/10.1145/3287560.3287598\n4. Centre for Data Ethics and Innovation (CDEI). (2023). *Algorithmic Accountability: A Practical Guide for Organisations*. https://www.gov.uk/government/publications/algorithmic-accountability-a-practical-guide-for-organisations\n5. Information Commissioner’s Office (ICO). (2023). *Guidance on AI and Data Protection*. https://ico.org.uk/for-organisations/guide-to-data-protection/guide-to-the-general-data-protection-regulation-gdpr/lawful-basis-for-processing/special-category-data/ai-and-data-protection/\n6. Algorithmic Accountability Act of 2025 (proposed). S.2164, 119th Congress (2025-2026). https://www.congress.gov/bill/119th-congress/senate-bill/2164\n7. Algorithmic Accountability Act of 2025 (proposed). H.R.5511, 119th Congress (2025-2026). https://www.congress.gov/bill/119th-congress/house-bill/5511/text\n\n## Metadata\n\n- **Migration Status**: Ontology block enriched on 2025-11-12\n- **Last Updated**: 2025-11-12\n- **Review Status**: Comprehensive editorial review\n- **Verification**: Academic sources verified\n- **Regional Context**: UK/North England where applicable",
  "backlinks": [
    "Human-Rights",
    "AI Ethics Checklist_ENHANCED",
    "Human Rights",
    "Fairness Metrics",
    "Safety Laser Scanner"
  ],
  "wiki_links": [
    "EthicalFramework",
    "RegulatoryCompliance",
    "AIGovernancePrinciple",
    "ConceptualLayer",
    "AIEthicsDomain",
    "IEEE P2863",
    "AIGovernance"
  ],
  "ontology": {
    "term_id": "AI-0376",
    "preferred_term": "Algorithmic Accountability",
    "alt_terms": [],
    "iri": "http://narrativegoldmine.com/ai#AlgorithmicAccountability",
    "source_domain": "ai",
    "domain": "ai",
    "domain_full_name": "Artificial Intelligence",
    "definition": "Algorithmic Accountability is a responsibility framework that ensures AI systems and their developers are answerable for the decisions, outcomes, and impacts produced by algorithmic processes, including mechanisms for redress, transparency, and oversight.",
    "scope_note": null,
    "status": "complete",
    "maturity": "mature",
    "version": null,
    "public_access": true,
    "last_updated": "2025-10-28",
    "authority_score": 0.95,
    "quality_score": null,
    "cross_domain_links": null,
    "owl_class": "ai:AlgorithmicAccountability",
    "owl_physicality": "VirtualEntity",
    "owl_role": "Process",
    "owl_inferred_class": "aigo:VirtualProcess",
    "is_subclass_of": [
      "AIGovernance",
      "EthicalFramework",
      "RegulatoryCompliance",
      "AIGovernancePrinciple"
    ],
    "has_part": [],
    "is_part_of": [],
    "requires": [],
    "depends_on": [],
    "enables": [],
    "relates_to": [],
    "bridges_to": [],
    "bridges_from": [],
    "domain_extensions": {},
    "belongs_to_domain": [
      "AIEthicsDomain"
    ],
    "implemented_in_layer": [
      "ConceptualLayer"
    ],
    "source": [
      "IEEE P2863"
    ],
    "validation": {
      "is_valid": true,
      "errors": []
    }
  }
}