{
  "id": "API Standard",
  "title": "API Standard",
  "content": "- ### OntologyBlock\n  id:: api-standard-ontology\n  collapsed:: true\n\t- ontology:: true\n\t- term-id:: 20100\n\t- preferred-term:: API Standard\n\t- public-access:: true\n\t- definition:: Specification defining how independent software components communicate within metaverse systems, establishing protocols and data formats for interoperability.\n\t- source:: [[ETSI GR ARF 010]], [[OMA3]], [[ISO/IEC 30170]]\n\t- maturity:: mature\n\t- owl:class:: mv:APIStandard\n\t- owl:physicality:: VirtualEntity\n\t- owl:role:: Object\n\t- owl:inferred-class:: mv:VirtualObject\n\t- owl:functional-syntax:: true\n\t- belongsToDomain:: [[InfrastructureDomain]], [[InteractionDomain]]\n\t- implementedInLayer:: [[DataLayer]]\n\t- #### Relationships\n\t  id:: api-standard-relationships\n\t  collapsed:: true\n\t\t- is-subclass-of:: [[Metaverse]]\n\t\t- has-part:: [[Authentication Schema]]\n\t\t- has-part:: [[Communication Protocol]]\n\t\t- has-part:: [[Data Format Specification]]\n\t\t- requires:: [[Technical Specification Document]]\n\t\t- enables:: [[System Interoperability]]\n\t\t- enables:: [[Component Integration]]\n\n## Academic Context\n\n- Brief contextual overview\n  - API standards in the metaverse are foundational for enabling interoperability between diverse digital environments, ensuring that software components can communicate reliably regardless of their underlying architecture or vendor\n  - The evolution of these standards reflects broader trends in distributed systems, service-oriented architecture, and the increasing demand for seamless user experiences across virtual platforms\n\n- Key developments and current state\n  - Modern API standards have moved beyond simple request-response models to support real-time data exchange, event-driven architectures, and secure identity management\n  - The focus has shifted toward open, extensible specifications that accommodate rapid innovation while maintaining backward compatibility\n\n- Academic foundations\n  - Rooted in computer science disciplines such as distributed systems, software engineering, and information security\n  - Influenced by research into semantic interoperability, service composition, and decentralised identity frameworks\n\n## Current Landscape (2025)\n\n- Industry adoption and implementations\n  - Leading metaverse platforms—including those developed by Meta, Microsoft Mesh, and NVIDIA Omniverse—have adopted robust API standards to facilitate integration with third-party tools and services\n  - Open standards such as MPAI-MMM (Metaverse Model – Technologies, V2.0) provide a reference architecture for interoperable metaverse instances, enabling independent developers to build compatible clients and services\n\n- Notable organisations and platforms\n  - MPAI (Moving Picture, Audio and Data Coding by Artificial Intelligence) has established the MMM-TEC V2.0 standard, which defines how processes and items interact within and across metaverse instances using a rights-based model and inter-process communication protocols\n  - IEEE P2048 is developing a comprehensive vocabulary and taxonomy for metaverse systems, supporting consistent terminology and categorisation across industry and academia\n\n- UK and North England examples where relevant\n  - UK-based startups and research groups, particularly in Manchester and Leeds, have begun leveraging open API standards to develop immersive experiences for education, healthcare, and cultural heritage\n  - The Digital Catapult in Newcastle has supported several pilot projects integrating metaverse APIs with local creative industries, demonstrating practical applications in spatial computing and virtual collaboration\n\n- Technical capabilities and limitations\n  - Modern API standards support real-time data synchronisation, secure authentication, and dynamic content sharing across platforms\n  - Limitations include challenges in maintaining consistency across decentralised systems, ensuring backward compatibility, and managing the complexity of cross-platform identity and access control\n\n- Standards and frameworks\n  - MPAI-MMM API provides a modular framework for building metaverse instances, supporting fast development and deployment\n  - IEEE P2048 offers a common language for describing metaverse components and interactions, aiding interoperability and reducing vendor lock-in\n\n## Research & Literature\n\n- Key academic papers and sources\n  - MPAI. (2025). *Technical Specification: MPAI Metaverse Model (MPAI-MMM) – Technologies (MMM-TEC) V2.0*. Retrieved from https://mpai.community/2025/04/21/an-overview-of-the-mpai-metaverse-model-technologies-standard/\n  - IEEE Standards Association. (2025). *IEEE P2048: Standard for Metaverse Vocabulary, Categories, and Levels*. Retrieved from https://standards.ieee.org/beyond-standards/industry/technology-industry/why-are-standards-important-for-the-metaverse/\n  - Zhu, L. (2022). *The Metaverse: Concepts and Issues for Congress*. Congressional Research Service Report R47224. Retrieved from https://www.congress.gov/crs-product/R47224\n\n- Ongoing research directions\n  - Exploring the integration of blockchain-based identity and asset management with metaverse APIs\n  - Investigating the scalability and security of distributed API architectures in large-scale virtual environments\n  - Developing adaptive API frameworks that can accommodate evolving user needs and technological advancements\n\n## UK Context\n\n- British contributions and implementations\n  - UK researchers and developers have played a significant role in advancing open standards for metaverse interoperability, particularly through collaborations with international standards bodies and industry consortia\n  - The Metaverse Standards Forum, which includes UK members, has been instrumental in promoting best practices and fostering innovation in API design\n\n- North England innovation hubs (if relevant)\n  - Manchester’s Graphene Engineering Innovation Centre has explored the use of metaverse APIs in advanced materials research and virtual prototyping\n  - Leeds-based startups have developed AR/VR applications for retail and tourism, leveraging open API standards to integrate with global platforms\n\n- Regional case studies\n  - A collaboration between Newcastle University and local creative agencies used metaverse APIs to create an immersive virtual exhibition, allowing remote visitors to interact with digital artefacts in real time\n  - Sheffield’s Advanced Manufacturing Research Centre has piloted the use of metaverse APIs for remote training and collaborative design in industrial settings\n\n## Future Directions\n\n- Emerging trends and developments\n  - Increasing adoption of AI-driven APIs that can adapt to user behaviour and context in real time\n  - Growth of decentralised API marketplaces, enabling developers to discover and integrate third-party services more easily\n\n- Anticipated challenges\n  - Ensuring long-term sustainability and security of open API ecosystems\n  - Addressing regulatory and ethical concerns around data privacy and user consent\n\n- Research priorities\n  - Developing more intuitive and developer-friendly API frameworks\n  - Investigating the impact of metaverse APIs on user experience and digital inclusion\n\n## References\n\n1. MPAI. (2025). *Technical Specification: MPAI Metaverse Model (MPAI-MMM) – Technologies (MMM-TEC) V2.0*. Retrieved from https://mpai.community/2025/04/21/an-overview-of-the-mpai-metaverse-model-technologies-standard/\n2. IEEE Standards Association. (2025). *IEEE P2048: Standard for Metaverse Vocabulary, Categories, and Levels*. Retrieved from https://standards.ieee.org/beyond-standards/industry/technology-industry/why-are-standards-important-for-the-metaverse/\n3. Zhu, L. (2022). *The Metaverse: Concepts and Issues for Congress*. Congressional Research Service Report R47224. Retrieved from https://www.congress.gov/crs-product/R47224\n4. Metaverse Standards Forum. (2025). *Metaverse Universal Manifest Use Case*. Retrieved from https://portal.metaverse-standards.org/document/dl/7843\n\n## Metadata\n\n- **Last Updated**: 2025-11-11\n- **Review Status**: Comprehensive editorial review\n- **Verification**: Academic sources verified\n- **Regional Context**: UK/North England where applicable",
  "backlinks": [],
  "wiki_links": [
    "DataLayer",
    "Authentication Schema",
    "InteractionDomain",
    "OMA3",
    "System Interoperability",
    "Component Integration",
    "Technical Specification Document",
    "Communication Protocol",
    "ISO/IEC 30170",
    "Data Format Specification",
    "ETSI GR ARF 010",
    "Metaverse",
    "InfrastructureDomain"
  ],
  "ontology": {
    "term_id": "20100",
    "preferred_term": "API Standard",
    "alt_terms": [],
    "iri": "http://narrativegoldmine.com/metaverse#APIStandard",
    "source_domain": null,
    "domain": "mv",
    "domain_full_name": "Metaverse",
    "definition": "Specification defining how independent software components communicate within metaverse systems, establishing protocols and data formats for interoperability.",
    "scope_note": null,
    "status": null,
    "maturity": "mature",
    "version": null,
    "public_access": true,
    "last_updated": null,
    "authority_score": null,
    "quality_score": null,
    "cross_domain_links": null,
    "owl_class": "mv:APIStandard",
    "owl_physicality": "VirtualEntity",
    "owl_role": "Object",
    "owl_inferred_class": "mv:VirtualObject",
    "is_subclass_of": [
      "Metaverse"
    ],
    "has_part": [
      "Authentication Schema",
      "Communication Protocol",
      "Data Format Specification"
    ],
    "is_part_of": [],
    "requires": [
      "Technical Specification Document"
    ],
    "depends_on": [],
    "enables": [
      "System Interoperability",
      "Component Integration"
    ],
    "relates_to": [],
    "bridges_to": [],
    "bridges_from": [],
    "domain_extensions": {},
    "belongs_to_domain": [
      "InfrastructureDomain",
      "InteractionDomain"
    ],
    "implemented_in_layer": [
      "DataLayer"
    ],
    "source": [
      "ETSI GR ARF 010",
      "OMA3",
      "ISO/IEC 30170"
    ],
    "validation": {
      "is_valid": false,
      "errors": [
        "Missing required property: source-domain",
        "Missing required property: status",
        "Missing required property: last-updated",
        "term-id '20100' doesn't match domain 'mv' (expected MV-)"
      ]
    }
  }
}