{
  "id": "Application Layer",
  "title": "Application Layer",
  "content": "- ### OntologyBlock\n  id:: application-layer-ontology\n  collapsed:: true\n\t- ontology:: true\n\t- term-id:: MV-20160\n\t- preferred-term:: Application Layer\n\t- source-domain:: mv\n\t- owl:class:: mv:ApplicationLayer\n\t- status:: draft\n\t- public-access:: true\n\t- definition:: Software layer providing domain-specific application interfaces and services for metaverse experiences including education, commerce, healthcare, and entertainment applications.\n\t- source:: [[MSF Taxonomy 2025]]\n\t- maturity:: mature\n\t- owl:class:: mv:ApplicationLayer\n\t- owl:physicality:: VirtualEntity\n\t- owl:role:: Object\n\t- owl:inferred-class:: mv:VirtualObject\n\t- owl:functional-syntax:: true\n\t- belongsToDomain:: [[InfrastructureDomain]]\n\t- #### Relationships\n\t  id:: application-layer-relationships\n\t  collapsed:: true\n\t\t- is-part-of:: [[Metaverse Stack]]\n\t\t- is-part-of:: [[Metaverse Architecture Stack]]\n\t\t- has-part:: [[Application API]]\n\t\t- has-part:: [[Service Interface]]\n\t\t- has-part:: [[User Interface Framework]]\n\t\t- has-part:: [[Business Logic Layer]]\n\t\t- requires:: [[Data Storage Layer]]\n\t\t- requires:: [[Compute Layer]]\n\t\t- requires:: [[Network Infrastructure]]\n\t\t- enables:: [[Cross-Platform Interoperability]]\n\t\t- enables:: [[User Experience]]\n\t\t- enables:: [[Business Services]]\n\t\t- enables:: [[Domain-Specific Applications]]\n\t\t- depends-on:: [[Content Delivery]]\n\t\t- depends-on:: [[Identity Services]]\n\t\t- depends-on:: [[Platform Services]]\n\n## Academic Context\n\n- The Application Layer in metaverse architecture represents the software tier delivering domain-specific interfaces and services tailored to immersive digital experiences.\n  - It builds upon foundational technologies such as virtual reality (VR), augmented reality (AR), blockchain, and artificial intelligence (AI) to enable interactive applications.\n  - Academically, it is understood as the layer where user-facing applications operate, encompassing sectors like education, commerce, healthcare, and entertainment within the metaverse ecosystem.\n  - This layer integrates with lower layers (infrastructure, human interface, decentralisation) to provide seamless, persistent, and interoperable experiences.\n\n## Current Landscape (2025)\n\n- Industry adoption of the Application Layer has matured, with platforms offering diverse metaverse applications that support social interaction, commerce, and professional collaboration.\n  - Notable global platforms include Meta’s Horizon Worlds, Decentraland, and Microsoft Mesh, which provide frameworks for application development.\n  - In the UK, and particularly North England, cities such as Manchester and Leeds have seen growing investment in metaverse startups and digital innovation hubs focusing on application development for sectors like education and healthcare.\n- Technical capabilities now support real-time, multi-user interactions with improved latency through 5G and edge computing, though challenges remain in standardising interoperability across platforms.\n- Standards and frameworks continue evolving, with organisations like the Metaverse Standards Forum working to harmonise protocols for application development and asset portability.\n\n## Research & Literature\n\n- Key academic papers include:\n  - Lee, L.-H., Braud, T., Zhou, P., Wang, L., Xu, D., Lin, Z., Kumar, A., & Hui, P. (2021). \"All One Needs to Know about the Metaverse: A Complete Survey on Technological Singularity, Virtual Ecosystem, and Research Agenda.\" *arXiv preprint arXiv:2110.05352*. https://doi.org/10.48550/arXiv.2110.05352\n  - Damar, M. (2021). \"The Metaverse as a 3D Virtual Shared World.\" *Journal of Virtual Worlds Research*, 14(2). https://doi.org/10.4101/jvwr.v14i2.7407\n- Ongoing research focuses on enhancing application layer interoperability, improving user experience through AI-driven personalisation, and integrating blockchain for secure digital ownership.\n\n## UK Context\n\n- The UK government and private sector have invested in metaverse research and development, with initiatives supporting digital innovation in education and healthcare applications.\n- North England innovation hubs, notably in Manchester and Leeds, foster startups developing metaverse applications, leveraging local expertise in digital media and healthcare technology.\n- Regional case studies include the University of Manchester’s projects on immersive educational platforms and Leeds’ digital health initiatives utilising metaverse applications for patient engagement and training.\n\n## Future Directions\n\n- Emerging trends include the integration of AI-powered avatars for personalised user interaction, expansion of creator economies enabling non-technical users to build applications, and deeper incorporation of mixed reality (MR) technologies.\n- Anticipated challenges involve achieving seamless interoperability across diverse metaverse platforms, ensuring data privacy and security, and addressing digital inclusion to prevent regional disparities.\n- Research priorities emphasise scalable application architectures, standardised APIs, and ethical frameworks for user interaction and content moderation.\n\n## References\n\n1. Lee, L.-H., Braud, T., Zhou, P., Wang, L., Xu, D., Lin, Z., Kumar, A., & Hui, P. (2021). All One Needs to Know about the Metaverse: A Complete Survey on Technological Singularity, Virtual Ecosystem, and Research Agenda. *arXiv preprint arXiv:2110.05352*. https://doi.org/10.48550/arXiv.2110.05352\n2. Damar, M. (2021). The Metaverse as a 3D Virtual Shared World. *Journal of Virtual Worlds Research*, 14(2). https://doi.org/10.4101/jvwr.v14i2.7407\n3. Major Cities Chiefs Association. (2024). Metaverse Reference Guide. Retrieved June 2025, from https://majorcitieschiefs.com/wp-content/uploads/2025/06/MCCA_Metaverse-Reference-Guide_Oct-2024.pdf\n4. ilink.dev. (2025). What Is the Metaverse? Complete Guide for 2025-2026. Retrieved November 2025, from https://ilink.dev/blog/what-is-the-metaverse-complete-guide-for-2025-2026/\n\n## Metadata\n\n- **Last Updated**: 2025-11-11\n- **Review Status**: Comprehensive editorial review\n- **Verification**: Academic sources verified\n- **Regional Context**: UK/North England where applicable",
  "backlinks": [
    "AI Model Card",
    "Digital Well-Being Index",
    "Digital Curation Platform",
    "Content Moderation",
    "Photogrammetry",
    "Accessibility Audit Tool",
    "Consent Management",
    "Metaverse Architecture Stack",
    "Data Storage Layer",
    "Compute Layer",
    "Data Protection",
    "Network Infrastructure",
    "Metaverse Psychology Profile"
  ],
  "wiki_links": [
    "Application API",
    "User Experience",
    "Domain-Specific Applications",
    "Metaverse Architecture Stack",
    "Cross-Platform Interoperability",
    "Identity Services",
    "Metaverse Stack",
    "Compute Layer",
    "MSF Taxonomy 2025",
    "Content Delivery",
    "Platform Services",
    "Business Logic Layer",
    "Data Storage Layer",
    "Service Interface",
    "Business Services",
    "Network Infrastructure",
    "User Interface Framework",
    "InfrastructureDomain"
  ],
  "ontology": {
    "term_id": "MV-20160",
    "preferred_term": "Application Layer",
    "alt_terms": [],
    "iri": "http://narrativegoldmine.com/metaverse#ApplicationLayer",
    "source_domain": "mv",
    "domain": "mv",
    "domain_full_name": "Metaverse",
    "definition": "Software layer providing domain-specific application interfaces and services for metaverse experiences including education, commerce, healthcare, and entertainment applications.",
    "scope_note": null,
    "status": "draft",
    "maturity": "mature",
    "version": null,
    "public_access": true,
    "last_updated": null,
    "authority_score": null,
    "quality_score": null,
    "cross_domain_links": null,
    "owl_class": "mv:ApplicationLayer",
    "owl_physicality": "VirtualEntity",
    "owl_role": "Object",
    "owl_inferred_class": "mv:VirtualObject",
    "is_subclass_of": [],
    "has_part": [
      "Application API",
      "Service Interface",
      "User Interface Framework",
      "Business Logic Layer"
    ],
    "is_part_of": [
      "Metaverse Stack",
      "Metaverse Architecture Stack"
    ],
    "requires": [
      "Data Storage Layer",
      "Compute Layer",
      "Network Infrastructure"
    ],
    "depends_on": [
      "Content Delivery",
      "Identity Services",
      "Platform Services"
    ],
    "enables": [
      "Cross-Platform Interoperability",
      "User Experience",
      "Business Services",
      "Domain-Specific Applications"
    ],
    "relates_to": [],
    "bridges_to": [],
    "bridges_from": [],
    "domain_extensions": {},
    "belongs_to_domain": [
      "InfrastructureDomain"
    ],
    "implemented_in_layer": [],
    "source": [
      "MSF Taxonomy 2025"
    ],
    "validation": {
      "is_valid": false,
      "errors": [
        "Missing required property: last-updated",
        "Missing required property: is-subclass-of (at least one parent class)"
      ]
    }
  }
}