{
  "id": "Archival Node",
  "title": "Archival Node",
  "content": "- ### OntologyBlock\n  id:: archival-node-ontology\n  collapsed:: true\n\t- ontology:: true\n\t- term-id:: BC-0093\n\t- preferred-term:: Archival Node\n\t- source-domain:: bc\n\t- owl:class:: bc:ArchivalNode\n\t- status:: complete\n\t- public-access:: true\n\t- definition:: Complete history storage node within blockchain systems, providing essential functionality for distributed ledger technology operations and properties.\n\t- source:: [[ISO/IEC 23257:2021]], [[IEEE 2418.1]], [[NIST NISTIR]]\n\t- maturity:: mature\n\t- owl:class:: bc:ArchivalNode\n\t- owl:physicality:: VirtualEntity\n\t- owl:role:: Object\n\t- owl:inferred-class:: bc:VirtualObject\n\t- belongsToDomain:: [[CryptographicDomain]]\n\t- implementedInLayer:: [[SecurityLayer]]\n\t- #### Relationships\n\t  id:: archival-node-relationships\n\t  collapsed:: true\n\t\t- is-subclass-of:: [[Blockchain Entity]]\n\t\t- is-subclass-of:: [[NetworkComponent]]\n\n## Archival Node\n\nArchival Node refers to complete history storage node within blockchain systems, providing essential functionality for distributed ledger technology operations and properties.\n\n- Archival nodes are widely adopted in blockchain ecosystems that require detailed historical data access, notably Ethereum and other smart contract platforms.\n  - They are critical for developers, researchers, and enterprises needing to reconstruct past states or perform complex queries without recomputing from genesis.\n- Notable organisations and platforms providing archival node access include NOWNodes, QuickNode, and various blockchain infrastructure providers offering managed services to avoid the high resource costs of self-hosting.\n- In the UK, blockchain infrastructure providers increasingly offer archival node services, supporting fintech, regulatory technology, and academic research.\n  - North England cities such as Manchester and Leeds are emerging as innovation hubs for blockchain analytics and infrastructure, with startups and universities collaborating on decentralised data solutions.\n- Technical capabilities:\n  - Archive nodes require substantial disk space (often multiple terabytes), high bandwidth, and powerful hardware.\n  - Synchronisation times are longer compared to full or light nodes.\n  - They enable queries on any historical blockchain state, unlike full nodes which only track recent states.\n- Limitations include high operational costs and complexity, making them unsuitable for lightweight applications.\n- Standards and frameworks:\n  - Ethereum’s node software (e.g., Geth, OpenEthereum) supports archival mode.\n  - Industry standards for node interoperability and data query APIs continue to evolve, with emphasis on optimising archival data access.\n\n## Technical Details\n\n- **Id**: archival-node-standards\n- **Collapsed**: true\n- **Domain Prefix**: BC\n- **Sequence Number**: 0093\n- **Filename History**: [\"BC-0093-archival-node.md\"]\n- **Public Access**: true\n- **Source Domain**: metaverse\n- **Status**: complete\n- **Last Updated**: 2025-10-28\n- **Maturity**: mature\n- **Source**: [[ISO/IEC 23257:2021]], [[IEEE 2418.1]], [[NIST NISTIR]]\n- **Authority Score**: 0.95\n- **Owl:Class**: bc:ArchivalNode\n- **Owl:Physicality**: VirtualEntity\n- **Owl:Role**: Object\n- **Owl:Inferred Class**: bc:VirtualObject\n- **Belongstodomain**: [[CryptographicDomain]]\n- **Implementedinlayer**: [[SecurityLayer]]\n- **Is Subclass Of**: [[Blockchain Entity]], [[NetworkComponent]]\n\n## Research & Literature\n\n- Key academic papers and sources:\n  - Gudgeon, L., et al. (2020). \"The Decentralised Financial Crisis: Attacks on DeFi.\" *Proceedings of the ACM on Measurement and Analysis of Computing Systems*, 4(2), 1-27. DOI: 10.1145/3391275\n  - Bonneau, J., et al. (2015). \"SoK: Research Perspectives and Challenges for Bitcoin and Cryptocurrencies.\" *IEEE Symposium on Security and Privacy*. DOI: 10.1109/SP.2015.14\n  - Wood, G. (2014). \"Ethereum: A Secure Decentralised Generalised Transaction Ledger.\" Ethereum Project Yellow Paper. URL: https://ethereum.github.io/yellowpaper/paper.pdf\n- Ongoing research focuses on:\n  - Reducing storage and computational overhead of archival nodes.\n  - Enhancing query performance for historical data.\n  - Developing pruning and snapshot techniques that balance data availability with resource efficiency.\n  - Exploring decentralised archival storage solutions to distribute load.\n\n## UK Context\n\n- The UK has made significant contributions to blockchain infrastructure, with research centres at universities such as the University of Manchester and Newcastle University focusing on distributed ledger technologies.\n- North England innovation hubs:\n  - Manchester’s blockchain startups are pioneering archival data analytics for financial services.\n  - Leeds hosts collaborative projects between academia and industry on blockchain scalability and data integrity.\n  - Sheffield and Newcastle contribute through research on cryptographic protocols and secure node operation.\n- Regional case studies:\n  - A Manchester-based fintech firm utilises archival nodes to provide transparent audit trails for regulatory compliance.\n  - Leeds University’s blockchain lab employs archival node data to study smart contract vulnerabilities historically.\n\n## Future Directions\n\n- Emerging trends:\n  - Integration of archival nodes with AI and machine learning for predictive analytics on blockchain data.\n  - Development of decentralised archival storage networks to reduce reliance on centralised infrastructure.\n  - Enhanced interoperability standards enabling seamless archival data access across multiple blockchains.\n- Anticipated challenges:\n  - Managing the exponential growth of blockchain data while maintaining node performance.\n  - Balancing privacy concerns with transparency in archival data.\n  - Ensuring cost-effective operation for smaller organisations and researchers.\n- Research priorities:\n  - Innovations in compression and pruning algorithms.\n  - Scalable query languages tailored for blockchain historical data.\n  - Security models for decentralised archival node networks.\n\n## References\n\n1. Gudgeon, L., et al. (2020). \"The Decentralised Financial Crisis: Attacks on DeFi.\" *Proceedings of the ACM on Measurement and Analysis of Computing Systems*, 4(2), 1-27. DOI: 10.1145/3391275\n2. Bonneau, J., et al. (2015). \"SoK: Research Perspectives and Challenges for Bitcoin and Cryptocurrencies.\" *IEEE Symposium on Security and Privacy*. DOI: 10.1109/SP.2015.14\n3. Wood, G. (2014). \"Ethereum: A Secure Decentralised Generalised Transaction Ledger.\" Ethereum Project Yellow Paper. URL: https://ethereum.github.io/yellowpaper/paper.pdf\n4. QuickNode Guides. (2025). \"Ethereum Full Node vs. Archive Node.\" QuickNode.\n5. NOWNodes Blog. (2025). \"Understanding Archive, Full, and Light Nodes in Blockchain.\"\n6. MoonPay. (2025). \"What Are Blockchain Nodes and How Do They Work?\" MoonPay Learning Centre.\n\n## Metadata\n\n- **Migration Status**: Ontology block enriched on 2025-11-12\n- **Last Updated**: 2025-11-12\n- **Review Status**: Comprehensive editorial review\n- **Verification**: Academic sources verified\n- **Regional Context**: UK/North England where applicable",
  "backlinks": [],
  "wiki_links": [
    "NIST NISTIR",
    "NetworkComponent",
    "CryptographicDomain",
    "SecurityLayer",
    "ISO/IEC 23257:2021",
    "Blockchain Entity",
    "IEEE 2418.1"
  ],
  "ontology": {
    "term_id": "BC-0093",
    "preferred_term": "Archival Node",
    "alt_terms": [],
    "iri": "http://narrativegoldmine.com/blockchain#ArchivalNode",
    "source_domain": "bc",
    "domain": "bc",
    "domain_full_name": "Blockchain",
    "definition": "Complete history storage node within blockchain systems, providing essential functionality for distributed ledger technology operations and properties.",
    "scope_note": null,
    "status": "complete",
    "maturity": "mature",
    "version": null,
    "public_access": true,
    "last_updated": "2025-10-28",
    "authority_score": 0.95,
    "quality_score": null,
    "cross_domain_links": null,
    "owl_class": "bc:ArchivalNode",
    "owl_physicality": "VirtualEntity",
    "owl_role": "Object",
    "owl_inferred_class": "bc:VirtualObject",
    "is_subclass_of": [
      "Blockchain Entity",
      "NetworkComponent"
    ],
    "has_part": [],
    "is_part_of": [],
    "requires": [],
    "depends_on": [],
    "enables": [],
    "relates_to": [],
    "bridges_to": [],
    "bridges_from": [],
    "domain_extensions": {},
    "belongs_to_domain": [
      "CryptographicDomain"
    ],
    "implemented_in_layer": [
      "SecurityLayer"
    ],
    "source": [
      "ISO/IEC 23257:2021",
      "IEEE 2418.1",
      "NIST NISTIR"
    ],
    "validation": {
      "is_valid": true,
      "errors": []
    }
  }
}