{
  "id": "Attention Mechanism",
  "title": "Attention Mechanism",
  "content": "- ### OntologyBlock\n  id:: unknown-ontology\n  collapsed:: true\n\t- ontology:: true\n\t- term-id:: AI-0038\n\t- preferred-term:: Attention Mechanism\n\t- source-domain:: ai\n\t- owl:class:: ai:AttentionMechanism\n\t- status:: draft\n\t- public-access:: true\n\t- definition:: Technique that enables models to dynamically focus on the most relevant parts of input data when making predictions.\n\t- maturity:: draft\n\t- owl:physicality:: ConceptualEntity\n\t- owl:role:: Concept\n\t- belongsToDomain:: [[MetaverseDomain]]\n\t- #### Relationships\n\t  id:: unknown-relationships\n\t  collapsed:: true\n\t\t- is-subclass-of:: [[NeuralNetworkComponent]]\n\n## Academic Context\n\n- Attention mechanisms in machine learning are techniques that enable models to dynamically focus on the most relevant parts of input data when making predictions.\n  - They address limitations of traditional sequence models like RNNs and LSTMs, which struggle with long-range dependencies and information retention.\n  - The concept is inspired by human cognitive attention, allowing selective weighting of input elements to improve interpretability and performance.\n- Key developments include the introduction of soft attention (differentiable via softmax), hard attention (non-differentiable, trained with reinforcement learning), self-attention, and multi-head attention.\n  - Self-attention allows each element in a sequence to attend to all others, capturing complex dependencies.\n  - Multi-head attention extends this by attending to multiple representation subspaces simultaneously, enhancing contextual understanding.\n- Attention mechanisms underpin state-of-the-art architectures such as Transformers and models like BERT, revolutionising natural language processing (NLP), computer vision, and speech processing.\n\n## Current Landscape (2025)\n\n- Industry adoption is widespread across AI applications including language translation, text summarisation, image captioning, and speech recognition.\n  - Leading technology companies and platforms integrate attention-based models to improve accuracy and efficiency.\n- In the UK, several AI firms and research institutions employ attention mechanisms in products and services, with notable activity in North England’s tech hubs.\n  - Manchester and Leeds host AI startups leveraging attention for NLP and computer vision applications.\n  - Newcastle and Sheffield contribute through academic research and collaborations with industry.\n- Technical capabilities include improved handling of long sequences, enhanced interpretability by highlighting influential input segments, and adaptability across modalities.\n- Limitations remain in computational cost, especially for very large models, and challenges in fully understanding attention weights as explanations.\n- Standards and frameworks continue evolving, with open-source libraries (e.g., Hugging Face Transformers) providing accessible implementations and fostering community development.\n\n## Research & Literature\n\n- Seminal papers and sources include:\n  - Bahdanau, D., Cho, K., & Bengio, Y. (2015). *Neural Machine Translation by Jointly Learning to Align and Translate*. arXiv preprint arXiv:1409.0473. [https://arxiv.org/abs/1409.0473]\n  - Vaswani, A., et al. (2017). *Attention Is All You Need*. Advances in Neural Information Processing Systems, 30, 5998–6008. [https://arxiv.org/abs/1706.03762]\n  - Devlin, J., et al. (2019). *BERT: Pre-training of Deep Bidirectional Transformers for Language Understanding*. NAACL-HLT. [https://arxiv.org/abs/1810.04805]\n- Ongoing research explores:\n  - Efficient attention mechanisms to reduce computational overhead.\n  - Interpretability and explainability of attention weights.\n  - Extensions beyond NLP to multimodal data and reinforcement learning.\n  - Novel architectures inspired by attention principles.\n\n## UK Context\n\n- The UK has made significant contributions to attention mechanism research, with universities such as the University of Manchester and the University of Leeds publishing influential work.\n- North England’s innovation hubs foster AI startups and collaborations focusing on attention-based models, particularly in NLP and healthcare applications.\n- Regional case studies include:\n  - Manchester-based AI companies developing attention-enhanced chatbots and document analysis tools.\n  - Leeds research groups applying attention mechanisms to medical imaging diagnostics.\n  - Newcastle initiatives integrating attention in speech recognition systems for accessibility technologies.\n\n## Future Directions\n\n- Emerging trends include:\n  - Development of sparse and adaptive attention to improve scalability.\n  - Integration of attention with other AI paradigms, such as graph neural networks and causal inference.\n  - Greater emphasis on ethical AI, ensuring attention models do not propagate biases.\n- Anticipated challenges:\n  - Balancing model complexity with interpretability.\n  - Addressing energy consumption and environmental impact of large attention-based models.\n- Research priorities focus on:\n  - Enhancing robustness and generalisation.\n  - Improving transparency and user trust.\n  - Expanding applications in underexplored domains and languages.\n\n## References\n\n1. Bahdanau, D., Cho, K., & Bengio, Y. (2015). Neural Machine Translation by Jointly Learning to Align and Translate. *arXiv preprint* arXiv:1409.0473. https://arxiv.org/abs/1409.0473\n2. Vaswani, A., Shazeer, N., Parmar, N., Uszkoreit, J., Jones, L., Gomez, A. N., Kaiser, Ł., & Polosukhin, I. (2017). Attention Is All You Need. *Advances in Neural Information Processing Systems*, 30, 5998–6008. https://arxiv.org/abs/1706.03762\n3. Devlin, J., Chang, M.-W., Lee, K., & Toutanova, K. (2019). BERT: Pre-training of Deep Bidirectional Transformers for Language Understanding. *NAACL-HLT*. https://arxiv.org/abs/1810.04805\n4. GeeksforGeeks. (2025). Attention Mechanism in Machine Learning. Last updated 7 November 2025.\n5. GraphApp AI. (2025). Attention Mechanisms in Deep Learning: Beyond Transformers Explained.\n6. IBM. (2025). What is an Attention Mechanism?\n7. Wikipedia contributors. (2025). Attention (machine learning). *Wikipedia*.\n8. DataCamp. (2025). Attention Mechanism in Large Language Models: An Intuitive Explanation.\n\n## Metadata\n\n- **Last Updated**: 2025-11-11\n- **Review Status**: Comprehensive editorial review\n- **Verification**: Academic sources verified\n- **Regional Context**: UK/North England where applicable",
  "backlinks": [
    "Recurrent Neural Network"
  ],
  "wiki_links": [
    "MetaverseDomain",
    "NeuralNetworkComponent"
  ],
  "ontology": {
    "term_id": "AI-0038",
    "preferred_term": "Attention Mechanism",
    "alt_terms": [],
    "iri": "http://narrativegoldmine.com/ai#AttentionMechanism",
    "source_domain": "ai",
    "domain": "ai",
    "domain_full_name": "Artificial Intelligence",
    "definition": "Technique that enables models to dynamically focus on the most relevant parts of input data when making predictions.",
    "scope_note": null,
    "status": "draft",
    "maturity": "draft",
    "version": null,
    "public_access": true,
    "last_updated": null,
    "authority_score": null,
    "quality_score": null,
    "cross_domain_links": null,
    "owl_class": "ai:AttentionMechanism",
    "owl_physicality": "ConceptualEntity",
    "owl_role": "Concept",
    "owl_inferred_class": null,
    "is_subclass_of": [
      "NeuralNetworkComponent"
    ],
    "has_part": [],
    "is_part_of": [],
    "requires": [],
    "depends_on": [],
    "enables": [],
    "relates_to": [],
    "bridges_to": [],
    "bridges_from": [],
    "domain_extensions": {},
    "belongs_to_domain": [
      "MetaverseDomain"
    ],
    "implemented_in_layer": [],
    "source": [],
    "validation": {
      "is_valid": false,
      "errors": [
        "Missing required property: last-updated"
      ]
    }
  }
}