{
  "id": "AUC",
  "title": "AUC",
  "content": "- ### OntologyBlock\n  id:: auc-ontology\n  collapsed:: true\n\t- ontology:: true\n\t- term-id:: AI-0113\n\t- preferred-term:: AUC\n\t- source-domain:: metaverse\n\t- status:: draft\n\t- public-access:: true\n\n\n\n\n### OWL Classification\n\t- owl:class:: mv:AUC\n\t- owl:physicality:: ConceptualEntity\n\t- owl:role:: Concept\n\n### Domain & Architecture\n\t- belongsToDomain:: [[MetaverseDomain]]\n\t- maturity:: draft\n\n### Relationships\nid:: auc-relationships\n\t\t- is-subclass-of:: [[QualityMetric]]\n\n## Mathematical Definition\n\n$$\\text{AUC} = \\int_0^1 \\text{TPR}(t) \\,d(\\text{FPR}(t))$$\n\nWhere TPR (True Positive Rate) and FPR (False Positive Rate) are functions of the classification threshold t.\n\n**Probabilistic Interpretation:**\n$$\\text{AUC} = P(\\text{score}(x^+) > \\text{score}(x^-))$$\n\nWhere x⁺ is a randomly selected positive instance and x⁻ is a randomly selected negative instance.\n\n**Equivalent to Wilcoxon-Mann-Whitney U statistic** normalized to [0,1] range.\n\n## Context and Significance\n\nAUC provides a single number summarising classifier quality across all possible classification thresholds, answering \"How well does this model separate positive and negative classes?\" without requiring threshold selection. This threshold independence makes AUC valuable for model comparison and selection, particularly when deployment thresholds are uncertain or will vary across different use cases.\n\nAn AUC of 0.7 means that 70% of the time, the model assigns a higher score to a randomly selected positive instance than to a randomly selected negative instance. This probabilistic interpretation makes AUC meaningful beyond just the geometric area under a curve.\n\nHowever, AUC has limitations: it treats all errors equally (ignoring asymmetric costs), can be overly optimistic for imbalanced datasets, and provides no information about performance at any specific threshold, which may obscure important trade-offs for practical deployment.\n\n## Key Characteristics\n\n- **Threshold-independent**: Single metric across all thresholds\n- **Probabilistic interpretation**: Measures ranking quality\n- **Range [0.5, 1.0]**: 0.5 = random, 1.0 = perfect (values <0.5 indicate inverted predictions)\n- **Intuitive**: Higher is better, easy to communicate\n- **Model comparison**: Enables comparing classifiers with single number\n- **Imbalance-insensitive** (partially): Less affected by class balance than accuracy, but can still be misleading\n\n## Interpretation Guidelines\n\n**AUC Value Ranges (Informal Guidelines):**\n- **0.90 - 1.00**: Excellent discrimination\n- **0.80 - 0.90**: Good discrimination\n- **0.70 - 0.80**: Acceptable discrimination\n- **0.60 - 0.70**: Poor discrimination\n- **0.50 - 0.60**: Fail (barely better than random)\n- **< 0.50**: Worse than random (predictions inverted)\n\n**Context Matters:** Acceptable AUC varies by:\n- Application difficulty (some problems inherently harder)\n- Class balance (imbalanced data may yield inflated AUC)\n- Business requirements (high-stakes decisions require higher AUC)\n- Alternative model availability (AUC 0.75 good if best achievable is 0.78)\n\n## Relationships\n\n- **Summarises**: ROC Curve in single metric\n- **Component of**: Model Performance assessment\n- **Alternative to**: Precision-Recall AUC (better for imbalanced data)\n- **Equivalent to**: Wilcoxon-Mann-Whitney U statistic (normalised)\n- **Measures**: Classifier's ranking ability\n- **Used in**: Model Evaluation, model comparison, model selection\n- **Threshold-independent**: Unlike precision, recall, F1 at specific threshold\n- **Reported in**: Model Cards, performance dashboards, academic papers\n\n## Examples and Applications\n\n1. **Medical Diagnosis**: Cancer screening model achieves AUC 0.92—means 92% probability the model scores actual cancer patient higher than healthy patient, indicating excellent diagnostic discrimination\n2. **Credit Scoring**: Loan default prediction with AUC 0.78—acceptable performance, though indicates 22% of time model ranks defaulter below non-defaulter, suggesting room for improvement\n3. **Fraud Detection**: Fraud model with AUC 0.88 on balanced test set but 0.65 on production data (highly imbalanced)—reveals AUC can be misleading when data distribution shifts, prompting examination of precision-recall metrics\n4. **Model Comparison**: Comparing three classification algorithms: Model A (AUC 0.85), Model B (AUC 0.82), Model C (AUC 0.87)—Model C selected for deployment based on highest AUC, subject to validation on other metrics\n\n## Calculation and Implementation\n\n**Standard Calculation:**\n```python\nfrom sklearn.metrics import roc_auc_score\n\nauc = roc_auc_score(y_true, y_scores)\nprint(f'AUC: {auc:.3f}')\n```\n\n**With Confidence Intervals:**\n```python\nfrom sklearn.metrics import roc_auc_score\nfrom scipy import stats\nimport numpy as np\n\n# Bootstrap confidence interval\nn_bootstraps = 1000\nrng = np.random.RandomState(42)\nauc_scores = []\n\nfor i in range(n_bootstraps):\n    indices = rng.randint(0, len(y_true), len(y_true))\n    auc_scores.append(roc_auc_score(y_true[indices], y_scores[indices]))\n\nauc_scores = np.array(auc_scores)\nprint(f'AUC: {np.mean(auc_scores):.3f} (95% CI: [{np.percentile(auc_scores, 2.5):.3f}, {np.percentile(auc_scores, 97.5):.3f}])')\n```\n\n**Multi-class AUC:**\n```python\n# One-vs-Rest (OvR) multi-class AUC\nauc_ovr = roc_auc_score(y_true, y_scores, multi_class='ovr', average='macro')\n\n# One-vs-One (OvO) multi-class AUC\nauc_ovo = roc_auc_score(y_true, y_scores, multi_class='ovo', average='macro')\n```\n\n## Implementation Considerations\n\n**Best Practices:**\n- Report AUC with confidence intervals (especially for small datasets)\n- Compare AUC to baseline (e.g., prior probability for imbalanced data)\n- Use Precision-Recall AUC for highly imbalanced datasets\n- Disaggregate AUC across demographic groups for fairness assessment\n- Examine ROC curve, not just AUC, to understand trade-offs\n- Validate AUC on out-of-sample data to avoid overfitting\n- Monitor AUC trends over time to detect model degradation\n\n**When AUC May Be Misleading:**\n- **Highly imbalanced data**: Can be optimistic; use PR-AUC instead\n- **Asymmetric costs**: AUC treats all errors equally; use cost-sensitive metrics\n- **Specific operating point**: AUC says nothing about performance at chosen threshold\n- **Multi-modal score distributions**: AUC may not reflect complex trade-off structures\n\n**Common Pitfalls:**\n- Relying solely on AUC without examining precision, recall, or ROC curve\n- Comparing AUC across datasets with different class balance\n- Not reporting confidence intervals (AUC has sampling variability)\n- Using AUC for multi-class without understanding aggregation method\n- Ignoring that high AUC doesn't guarantee good performance at deployment threshold\n\n## Variants\n\n**PR-AUC (Precision-Recall AUC)**: Area under Precision-Recall curve\n- More appropriate for imbalanced datasets\n- Focuses on positive class performance\n- Range not standardised to [0,1]\n\n**Partial AUC**: Area under specific region of ROC curve\n- Focuses on clinically/operationally relevant FPR range\n- Used when only certain operating points are acceptable\n\n**Multi-class AUC Aggregations:**\n- **Macro-average**: Average of per-class OvR AUCs (treats all classes equally)\n- **Weighted-average**: Class-frequency-weighted average of OvR AUCs\n- **OvO average**: Average of all pairwise class AUCs\n\n## ISO/IEC and Standards Alignment\n\n**ISO/IEC 25059** (Quality Model for AI Systems):\n- AUC as threshold-independent performance metric\n- Discriminative ability quality characteristic\n\n## NIST AI RMF Integration\n\n**MEASURE Function**:\n- MEASURE-2.2: AUC as appropriate threshold-independent metric\n- MEASURE-2.7: AUC assessed across different deployment contexts\n- Supports Valid and Reliable trustworthiness characteristic\n\n## Statistical Considerations\n\n**Sample Size Requirements:**\n- Small samples yield unreliable AUC estimates\n- Confidence intervals essential for sample sizes < 1000\n- Larger positive class sample size needed for reliable estimates\n\n**Hypothesis Testing:**\n- DeLong test: Compare AUCs from two models on same data\n- Permutation test: Test if AUC significantly different from 0.5\n\n**Relationship to Other Statistics:**\n- Equivalent to Wilcoxon-Mann-Whitney U statistic (normalised)\n- Related to Gini coefficient: Gini = 2×AUC - 1\n- Connected to concordance index (C-statistic) in survival analysis\n\n## Related Terms\n\n- [[Model Performance]]: AUC as summary performance metric\n- [[ROC Curve]]: AUC measures area under this curve\n- [[True Positive Rate]]: Component of ROC curve (y-axis)\n- [[False Positive Rate]]: Component of ROC curve (x-axis)\n- [[Precision-Recall Curve]]: Alternative visualization with own AUC\n- [[Model Comparison]]: AUC enables model comparison\n- [[Threshold Selection]]: AUC independent of threshold choice\n- [[Classification]]: AUC specifically for classification tasks\n- [[Ranking Metric]]: AUC measures ranking quality\n\n## References\n\n1. Fawcett, T., *An Introduction to ROC Analysis*, Pattern Recognition Letters (2006)\n2. Hand, D.J., *Measuring Classifier Performance: A Coherent Alternative to the Area Under the ROC Curve*, Machine Learning (2009)\n3. Bradley, A.P., *The Use of the Area Under the ROC Curve in the Evaluation of Machine Learning Algorithms*, Pattern Recognition (1997)\n4. Provost, F. & Fawcett, T., *Robust Classification for Imprecise Environments*, Machine Learning (2001)\n\n## Formal Ontology\n\n<details>\n<summary>OWL Functional Syntax</summary>\n\n```clojure\n;; Class Declaration\n(Declaration (Class :AUC))\n(SubClassOf :AUC :PerformanceMetric)\n(SubClassOf :AUC :ClassificationMetric)\n(SubClassOf :AUC :ThresholdIndependentMetric)\n\n;; Synonyms\n(Declaration (Class :ROCAUC))\n(Declaration (Class :AUROC))\n(Declaration (Class :AreaUnderROCCurve))\n(EquivalentClasses :AUC :ROCAUC :AUROC :AreaUnderROCCurve)\n\n;; Core relationships\n(SubClassOf :AUC\n  (ObjectSomeValuesFrom :measuresPerformanceOf :MachineLearningModel))\n(SubClassOf :AUC\n  (ObjectSomeValuesFrom :summarises :ROCCurve))\n(SubClassOf :AUC\n  (ObjectSomeValuesFrom :measuresDiscriminativeAbility :BinaryClassifier))\n\n;; Curve relationship\n(Declaration (ObjectProperty :areaUnderCurve))\n(SubClassOf :AUC\n  (ObjectSomeValuesFrom :areaUnderCurve :ROCCurve))\n\n;; Metric properties\n(Declaration (DataProperty :hasAUCValue))\n(DataPropertyDomain :hasAUCValue :AUC)\n(DataPropertyRange :hasAUCValue xsd:float)\n(FunctionalDataProperty :hasAUCValue)\n\n;; Value constraints and interpretation\n(SubClassOf :AUC\n  (DataPropertyRestriction\n    :hasAUCValue\n    (MinInclusiveDataRange 0.0^^xsd:float)\n    (MaxInclusiveDataRange 1.0^^xsd:float)))\n\n(Declaration (DataProperty :hasPerformanceLevel))\n(DataPropertyDomain :hasPerformanceLevel :AUC)\n(DataPropertyRange :hasPerformanceLevel xsd:string)\n(AnnotationAssertion rdfs:comment :hasPerformanceLevel\n  \"Performance interpretation: excellent (0.90-1.00), good (0.80-0.90), acceptable (0.70-0.80), poor (0.60-0.70), fail (0.50-0.60)\"@en)\n\n;; Probabilistic interpretation\n(Declaration (Class :RankingMetric))\n(SubClassOf :AUC :RankingMetric)\n(AnnotationAssertion rdfs:comment :AUC\n  \"Probability that the model ranks a randomly chosen positive instance higher than a randomly chosen negative instance\"@en)\n\n;; Statistical equivalence\n(Declaration (Class :WilcoxonMannWhitneyStatistic))\n(Declaration (ObjectProperty :equivalentTo))\n(SubClassOf :AUC\n  (ObjectSomeValuesFrom :equivalentTo :WilcoxonMannWhitneyStatistic))\n\n;; Variants\n(Declaration (Class :PRAUC))\n(Declaration (Class :PartialAUC))\n(SubClassOf :PRAUC :AUC)\n(SubClassOf :PartialAUC :AUC)\n\n(AnnotationAssertion rdfs:comment :PRAUC\n  \"Precision-Recall AUC, more appropriate for imbalanced datasets\"@en)\n\n;; Multi-class extensions\n(Declaration (Class :MultiClassAUC))\n(Declaration (Class :OneVsRestAUC))\n(Declaration (Class :OneVsOneAUC))\n(SubClassOf :MultiClassAUC :AUC)\n(SubClassOf :OneVsRestAUC :MultiClassAUC)\n(SubClassOf :OneVsOneAUC :MultiClassAUC)\n\n;; Threshold independence\n(Declaration (Class :ThresholdIndependentMetric))\n(SubClassOf :AUC :ThresholdIndependentMetric)\n\n;; Annotations\n(AnnotationAssertion rdfs:label :AUC \"AUC\"@en)\n(AnnotationAssertion rdfs:label :AUC \"Area Under the Curve\"@en)\n(AnnotationAssertion rdfs:label :AUC \"ROC-AUC\"@en)\n(AnnotationAssertion rdfs:label :AUC \"AUROC\"@en)\n(AnnotationAssertion rdfs:comment :AUC\n  \"Area Under the Receiver Operating Characteristic Curve, a threshold-independent performance metric representing the probability that the model ranks a randomly chosen positive instance higher than a randomly chosen negative instance.\"@en)\n(AnnotationAssertion dcterms:source :AUC <https://www.iso.org/standard/74438.html>)\n(AnnotationAssertion :termID :AUC \"AI-0113\"^^xsd:string)\n(AnnotationAssertion :mathematicalFormula :AUC\n  \"∫₀¹ TPR(t) d(FPR(t))\"^^xsd:string)\n\n;; ISO/IEC alignment\n(AnnotationAssertion :alignedWith :AUC :ISO25059)\n(AnnotationAssertion :alignedWith :AUC :NISTAIRFM_MEASURE22)\n```\n\n</details>\n\n## See Also\n\n- [[Model Performance]]\n- [[ROC Curve]]\n- [[True Positive Rate]]\n- [[False Positive Rate]]\n- [[Precision-Recall Curve]]\n- [[Model Comparison]]\n- [[Threshold Selection]]\n- [[Classification]]\n- [[Ranking Metric]]\n\t- maturity:: draft\n\t- owl:class:: mv:AUC\n\t- owl:physicality:: ConceptualEntity\n\t- owl:role:: Concept\n\t- belongsToDomain:: [[MetaverseDomain]]\n\t- #### Relationships\n\t  id:: auc-relationships\n\t\t- is-subclass-of:: [[QualityMetric]]",
  "backlinks": [],
  "wiki_links": [
    "QualityMetric",
    "Classification",
    "Ranking Metric",
    "Threshold Selection",
    "Model Comparison",
    "ROC Curve",
    "False Positive Rate",
    "Precision-Recall Curve",
    "MetaverseDomain",
    "Model Performance",
    "True Positive Rate"
  ],
  "ontology": {
    "term_id": "AI-0113",
    "preferred_term": "AUC",
    "alt_terms": [],
    "iri": "http://narrativegoldmine.com/metaverse#AUC",
    "source_domain": "metaverse",
    "domain": "metaverse",
    "domain_full_name": "",
    "definition": null,
    "scope_note": null,
    "status": "draft",
    "maturity": "draft",
    "version": null,
    "public_access": true,
    "last_updated": null,
    "authority_score": null,
    "quality_score": null,
    "cross_domain_links": null,
    "owl_class": "mv:AUC",
    "owl_physicality": "ConceptualEntity",
    "owl_role": "Concept",
    "owl_inferred_class": null,
    "is_subclass_of": [
      "QualityMetric"
    ],
    "has_part": [],
    "is_part_of": [],
    "requires": [],
    "depends_on": [],
    "enables": [],
    "relates_to": [],
    "bridges_to": [],
    "bridges_from": [],
    "domain_extensions": {},
    "belongs_to_domain": [
      "MetaverseDomain",
      "MetaverseDomain"
    ],
    "implemented_in_layer": [],
    "source": [],
    "validation": {
      "is_valid": false,
      "errors": [
        "Missing required property: last-updated",
        "Missing required property: definition",
        "owl:class namespace 'mv' doesn't match source-domain 'metaverse'"
      ]
    }
  }
}