{
  "id": "Autoencoder",
  "title": "Autoencoder",
  "content": "- ### OntologyBlock\n  id:: autoencoder-ontology\n  collapsed:: true\n\t- ontology:: true\n\t- term-id:: AI-0036\n\t- preferred-term:: Autoencoder\n\t- source-domain:: metaverse\n\t- status:: draft\n    - public-access:: true\n\t- definition:: ### Primary Definition\nAn **Autoencoder** is a neural network trained to reconstruct its input by learning a compressed latent representation. It consists of an encoder that maps input to a lower-dimensional space and a decoder that reconstructs the original input from this representation.\n\t- maturity:: draft\n\t- owl:class:: mv:Autoencoder\n\t- owl:physicality:: ConceptualEntity\n\t- owl:role:: Concept\n\t- belongsToDomain:: [[MetaverseDomain]]\n\n### Relationships\n- is-subclass-of:: [[NeuralNetworkArchitecture]]",
  "backlinks": [
    "Variational Autoencoders"
  ],
  "wiki_links": [
    "MetaverseDomain",
    "NeuralNetworkArchitecture"
  ],
  "ontology": {
    "term_id": "AI-0036",
    "preferred_term": "Autoencoder",
    "alt_terms": [],
    "iri": "http://narrativegoldmine.com/metaverse#Autoencoder",
    "source_domain": "metaverse",
    "domain": "metaverse",
    "domain_full_name": "",
    "definition": "### Primary Definition",
    "scope_note": null,
    "status": "draft",
    "maturity": "draft",
    "version": null,
    "public_access": true,
    "last_updated": null,
    "authority_score": null,
    "quality_score": null,
    "cross_domain_links": null,
    "owl_class": "mv:Autoencoder",
    "owl_physicality": "ConceptualEntity",
    "owl_role": "Concept",
    "owl_inferred_class": null,
    "is_subclass_of": [],
    "has_part": [],
    "is_part_of": [],
    "requires": [],
    "depends_on": [],
    "enables": [],
    "relates_to": [],
    "bridges_to": [],
    "bridges_from": [],
    "domain_extensions": {},
    "belongs_to_domain": [
      "MetaverseDomain"
    ],
    "implemented_in_layer": [],
    "source": [],
    "validation": {
      "is_valid": false,
      "errors": [
        "Missing required property: last-updated",
        "Missing required property: is-subclass-of (at least one parent class)",
        "owl:class namespace 'mv' doesn't match source-domain 'metaverse'"
      ]
    }
  }
}