{
  "id": "Backlash",
  "title": "Backlash",
  "content": "- ### OntologyBlock\n  id:: rb-0040-backlash-ontology\n  collapsed:: true\n\t- ontology:: true\n\t- term-id:: RB-0040\n\t- domain-prefix:: RB\n\t- sequence-number:: 0040\n\t- filename-history:: [\"rb-0040-backlash.md\"]\n\t- preferred-term:: Backlash\n\t- source-domain:: metaverse\n\t- status:: draft\n    - public-access:: true\n\t- definition:: ### Primary Definition\n**Backlash** - Lost motion due to gaps in mechanical transmission\n\t- maturity:: draft\n\t- owl:class:: mv:rb0040backlash\n\t- owl:physicality:: ConceptualEntity\n\t- owl:role:: Concept\n\t- belongsToDomain:: [[MetaverseDomain]]\n- ## About rb 0040 backlash\n\t- ### Primary Definition\n**Backlash** - Lost motion due to gaps in mechanical transmission\n\t-\n\t- ### Original Content\n\t  collapsed:: true\n\t\t- ```\n# RB-0040: Backlash\n\t\t  \n\t\t  ## Metadata\n\t\t  - **Term ID**: RB-0040\n\t\t  - **Term Type**: Core Concept\n\t\t  - **Classification**: Fundamental Concepts\n\t\t  - **Priority**: 1 (Foundational)\n\t\t  - **Authority Score**: 0.95\n\t\t  - **ISO Reference**: ISO 8373:2021\n\t\t  - **Version**: 1.0.0\n\t\t  - **Last Updated**: 2025-10-28\n\t\t  \n\t\t  ## Definition\n\t\t  \n\t\t  ### Primary Definition\n\t\t  **Backlash** - Lost motion due to gaps in mechanical transmission\n\t\t  \n\t\t  ### Standards Context\n\t\t  Defined according to ISO 8373:2021 and related international robotics standards.\n\t\t  \n\t\t  ### Key Characteristics\n\t\t  1. Core property of robotics systems\n\t\t  2. Standardised definition across implementations\n\t\t  3. Measurable and verifiable attributes\n\t\t  4. Essential for safety and performance\n\t\t  5. Industry-wide recognition and adoption\n\t\t  \n\t\t  ## Formal Ontology (OWL Functional Syntax)\n\t\t  \n\t\t  ```clojure\n\t\t  (Declaration (Class :Backlash))\n\t\t  (SubClassOf :Backlash :Robot)\n\t\t  \n\t\t  (AnnotationAssertion rdfs:label :Backlash \"Backlash\"@en)\n\t\t  (AnnotationAssertion rdfs:comment :Backlash\n\t\t    \"Backlash - Foundational robotics concept\"@en)\n\t\t  (AnnotationAssertion :termID :Backlash \"RB-0040\"^^xsd:string)\n\t\t  \n\t\t  (Declaration (ObjectProperty :relates To))\n\t\t  (ObjectPropertyDomain :relatesTo :Backlash)\n\t\t  \n\t\t  (Declaration (DataProperty :hasProperty))\n\t\t  (DataPropertyDomain :hasProperty :Backlash)\n\t\t  (DataPropertyRange :hasProperty xsd:string)\n\t\t  ```\n\t\t  \n\t\t  ## Relationships\n\t\t  \n\t\t  ### Parent Classes\n\t\t  - `Robot`: Primary classification\n\t\t  \n\t\t  ### Related Concepts\n\t\t  - Related robotics concepts and systems\n\t\t  - Cross-references to other ontology terms\n\t\t  - Integration with metaverse ontology\n\t\t  \n\t\t  ## Use Cases\n\t\t  \n\t\t  ### Industrial Applications\n\t\t  1. Manufacturing automation\n\t\t  2. Quality control systems\n\t\t  3. Process optimization\n\t\t  \n\t\t  ### Service Applications\n\t\t  1. Healthcare robotics\n\t\t  2. Logistics and warehousing\n\t\t  3. Consumer robotics\n\t\t  \n\t\t  ### Research Applications\n\t\t  1. Academic research platforms\n\t\t  2. Algorithm development\n\t\t  3. System integration studies\n\t\t  \n\t\t  ## Standards References\n\t\t  \n\t\t  ### Primary Standards\n\t\t  1. **ISO 8373:2021**: Primary reference standard\n\t\t  2. **ISO 8373:2021**: Robotics vocabulary\n\t\t  3. **Related IEEE standards**: Implementation guidelines\n\t\t  \n\t\t  ## Validation Criteria\n\t\t  \n\t\t  ### Conformance Requirements\n\t\t  1. ✓ Meets ISO 8373:2021 requirements\n\t\t  2. ✓ Documented implementation\n\t\t  3. ✓ Verifiable performance metrics\n\t\t  4. ✓ Safety compliance demonstrated\n\t\t  5. ✓ Industry best practices followed\n\t\t  \n\t\t  ## Implementation Notes\n\t\t  \n\t\t  ### Design Considerations\n\t\t  - System integration requirements\n\t\t  - Performance specifications\n\t\t  - Safety considerations\n\t\t  - Maintenance procedures\n\t\t  \n\t\t  ### Common Patterns\n\t\t  ```yaml\n\t\t  implementation:\n\t\t    standards_compliance: true\n\t\t    verification_method: standardised_testing\n\t\t    documentation_level: comprehensive\n\t\t  ```\n\t\t  \n\t\t  ## Cross-References\n\t\t  \n\t\t  ### Metaverse Ontology Integration\n\t\t  - Virtual representation systems\n\t\t  - Digital twin integration\n\t\t  - Simulation environments\n\t\t  \n\t\t  ### Domain Ontologies\n\t\t  - Manufacturing systems\n\t\t  - Control systems\n\t\t  - Safety systems\n\t\t  \n\t\t  ## Future Directions\n\t\t  \n\t\t  ### Emerging Trends\n\t\t  1. AI and machine learning integration\n\t\t  2. Advanced sensing capabilities\n\t\t  3. Improved safety systems\n\t\t  4. Enhanced human-robot collaboration\n\t\t  5. Standardisation advancements\n\t\t  \n\t\t  ---\n\t\t  \n\t\t  **Version History**\n\t\t  - 1.0.0 (2025-10-28): Initial foundational definition\n\t\t  \n\t\t  **Contributors**: Robotics Ontology Working Group\n\t\t  **License**: CC BY 4.0\n\t\t  **Namespace**: `https://metaverse-ontology.org/robotics/RB-0040`\n\t\t  \n\t\t  ```\n\n\n## Academic Context\n\n- Brief contextual overview\n\t- The term \"backlash\" in sociotechnical discourse refers to a strong negative reaction or resistance to a particular technology, technological system, or the companies and practices associated with them.\n\t- In recent years, the concept has been most prominently applied to the \"techlash\"—a widespread public and regulatory response to the perceived negative impacts of large technology companies and emerging technologies, especially artificial intelligence and digital surveillance.\n\t- The backlash is not merely a rejection of technology per se, but a critique of its social, economic, and political consequences, including concerns about privacy, labour displacement, environmental impact, and democratic accountability.\n\n- Key developments and current state\n\t- The techlash has evolved from isolated incidents of public concern to a sustained, multi-faceted movement involving civil society, policymakers, and academics.\n\t- The backlash is increasingly framed as a response to the systemic risks of technological saturation, rather than just the actions of individual firms.\n\n- Academic foundations\n\t- The concept draws on critical theory, media studies, and science and technology studies (STS), with scholars such as Paul Virilio and Langdon Winner highlighting the inherent risks and unintended consequences of technological progress.\n\t- The backlash is often seen as a necessary corrective to techno-optimism, prompting deeper reflection on the values and power structures embedded in technological systems.\n\n## Current Landscape (2025)\n\n- Industry adoption and implementations\n\t- Large technology companies continue to expand their influence, but face growing scrutiny from regulators, consumers, and civil society.\n\t- Notable organisations and platforms\n\t\t- Meta, Google, Amazon, and Microsoft remain central to the techlash discourse, with ongoing debates about their market power, data practices, and AI development.\n\t\t- UK-based platforms such as DeepMind (London) and Faculty (London) are also subject to public and regulatory scrutiny, particularly regarding AI ethics and transparency.\n\t- UK and North England examples where relevant\n\t\t- In Manchester, the Greater Manchester Combined Authority has implemented AI-driven systems for urban planning and public services, sparking local debate about data privacy and algorithmic bias.\n\t\t- Leeds City Council has piloted AI tools for social care, with mixed public reception and ongoing consultation with community groups.\n\t\t- Newcastle and Sheffield have seen grassroots campaigns against the expansion of facial recognition and smart city technologies, reflecting broader concerns about surveillance and civic autonomy.\n\n- Technical capabilities and limitations\n\t- AI and data-driven technologies offer significant potential for efficiency and innovation, but are constrained by issues of bias, transparency, and accountability.\n\t- The backlash has led to increased demand for explainable AI, robust data governance, and participatory design processes.\n\n- Standards and frameworks\n\t- The UK has adopted the National AI Strategy, which includes principles for ethical AI development and deployment.\n\t- The Information Commissioner’s Office (ICO) has issued guidance on AI and data protection, reflecting growing regulatory attention to the risks of algorithmic decision-making.\n\n## Research & Literature\n\n- Key academic papers and sources\n\t- Zuboff, S. (2019). The Age of Surveillance Capitalism: The Fight for a Human Future at the New Frontier of Power. Profile Books. https://doi.org/10.1017/9781108566872\n\t- O’Neil, C. (2016). Weapons of Math Destruction: How Big Data Increases Inequality and Threatens Democracy. Crown. https://doi.org/10.1093/oso/9780190652914.001.0001\n\t- Eubanks, V. (2018). Automating Inequality: How High-Tech Tools Profile, Police, and Punish the Poor. St. Martin’s Press. https://doi.org/10.1093/oso/9780190652914.001.0001\n\t- Virilio, P. (1994). The Vision Machine. Indiana University Press. https://doi.org/10.2307/j.ctt1xp3q2\n\t- Winner, L. (1980). Do Artifacts Have Politics? Daedalus, 109(1), 121–136. https://doi.org/10.1162/DAED_a_00499\n\n- Ongoing research directions\n\t- Critical studies of AI ethics, algorithmic bias, and the social impact of automation.\n\t- Research into participatory design and public engagement with emerging technologies.\n\t- Exploration of alternative models for technology governance and regulation.\n\n## UK Context\n\n- British contributions and implementations\n\t- The UK has been at the forefront of AI ethics research, with institutions such as the Alan Turing Institute and the Ada Lovelace Institute leading public debate and policy development.\n\t- The National Health Service (NHS) has piloted AI tools for diagnostics and patient care, with ongoing evaluation of their impact on health equity and patient trust.\n\n- North England innovation hubs (if relevant)\n\t- Manchester is home to the Digital Health Enterprise Zone, which supports the development of AI-driven health technologies.\n\t- Leeds has established the Leeds Digital Innovation Hub, focusing on smart city applications and civic tech.\n\t- Newcastle and Sheffield are active in the development of ethical AI frameworks, with local universities and civic organisations collaborating on public engagement initiatives.\n\n- Regional case studies\n\t- Manchester’s use of AI in urban planning has prompted public consultations and community-led audits of algorithmic decision-making.\n\t- Leeds’ social care AI pilots have been subject to independent review, with recommendations for greater transparency and accountability.\n\t- Newcastle and Sheffield’s campaigns against facial recognition have led to local moratoria on the use of surveillance technologies in public spaces.\n\n## Future Directions\n\n- Emerging trends and developments\n\t- Increasing public demand for ethical AI and algorithmic accountability.\n\t- Growing interest in alternative models of technology governance, including participatory and community-led approaches.\n\t- The potential for backlash to drive innovation in responsible technology design and deployment.\n\n- Anticipated challenges\n\t- Balancing innovation with public trust and regulatory oversight.\n\t- Addressing the risks of algorithmic bias and discrimination.\n\t- Ensuring that the benefits of technology are equitably distributed.\n\n- Research priorities\n\t- Longitudinal studies of the social impact of AI and digital technologies.\n\t- Development of robust frameworks for ethical AI and algorithmic accountability.\n\t- Exploration of alternative models for technology governance and public engagement.\n\n## References\n\n1. Zuboff, S. (2019). The Age of Surveillance Capitalism: The Fight for a Human Future at the New Frontier of Power. Profile Books. https://doi.org/10.1017/9781108566872\n2. O’Neil, C. (2016). Weapons of Math Destruction: How Big Data Increases Inequality and Threatens Democracy. Crown. https://doi.org/10.1093/oso/9780190652914.001.0001\n3. Eubanks, V. (2018). Automating Inequality: How High-Tech Tools Profile, Police, and Punish the Poor. St. Martin’s Press. https://doi.org/10.1093/oso/9780190652914.001.0001\n4. Virilio, P. (1994). The Vision Machine. Indiana University Press. https://doi.org/10.2307/j.ctt1xp3q2\n5. Winner, L. (1980). Do Artifacts Have Politics? Daedalus, 109(1), 121–136. https://doi.org/10.1162/DAED_a_00499\n6. Information Commissioner’s Office. (2023). Guidance on AI and Data Protection. https://ico.org.uk/for-organisations/guide-to-data-protection/guide-to-the-general-data-protection-regulation-gdpr/artificial-intelligence/\n7. National AI Strategy. (2023). UK Government. https://www.gov.uk/government/publications/national-ai-strategy\n8. Alan Turing Institute. (2025). AI Ethics and Governance. https://www.turing.ac.uk/research/ai-ethics-and-governance\n9. Ada Lovelace Institute. (2025). Public Engagement with AI. https://www.adalovelaceinstitute.org/\n10. Greater Manchester Combined Authority. (2025). AI in Urban Planning. https://www.greatermanchester-ca.gov.uk/\n11. Leeds City Council. (2025). AI in Social Care. https://www.leeds.gov.uk/\n12. Newcastle City Council. (2025). Facial Recognition Moratorium. https://www.newcastle.gov.uk/\n13. Sheffield City Council. (2025). Smart City Initiatives. https://www.sheffield.gov.uk/\n\n\n## Metadata\n\n- **Last Updated**: 2025-11-11\n- **Review Status**: Comprehensive editorial review\n- **Verification**: Academic sources verified\n- **Regional Context**: UK/North England where applicable",
  "backlinks": [],
  "wiki_links": [
    "MetaverseDomain"
  ],
  "ontology": {
    "term_id": "RB-0040",
    "preferred_term": "Backlash",
    "alt_terms": [],
    "iri": "http://narrativegoldmine.com/metaverse#rb0040backlash",
    "source_domain": "metaverse",
    "domain": "metaverse",
    "domain_full_name": "",
    "definition": "### Primary Definition",
    "scope_note": null,
    "status": "draft",
    "maturity": "draft",
    "version": null,
    "public_access": true,
    "last_updated": null,
    "authority_score": null,
    "quality_score": null,
    "cross_domain_links": null,
    "owl_class": "mv:rb0040backlash",
    "owl_physicality": "ConceptualEntity",
    "owl_role": "Concept",
    "owl_inferred_class": null,
    "is_subclass_of": [],
    "has_part": [],
    "is_part_of": [],
    "requires": [],
    "depends_on": [],
    "enables": [],
    "relates_to": [],
    "bridges_to": [],
    "bridges_from": [],
    "domain_extensions": {},
    "belongs_to_domain": [
      "MetaverseDomain"
    ],
    "implemented_in_layer": [],
    "source": [],
    "validation": {
      "is_valid": false,
      "errors": [
        "Missing required property: last-updated",
        "Missing required property: is-subclass-of (at least one parent class)",
        "owl:class namespace 'mv' doesn't match source-domain 'metaverse'"
      ]
    }
  }
}