{
  "id": "Backpropagation",
  "title": "Backpropagation",
  "content": "- ### OntologyBlock\n  id:: backpropagation-ontology\n  collapsed:: true\n\t- ontology:: true\n\t- term-id:: AI-0043\n\t- preferred-term:: Backpropagation\n\t- source-domain:: metaverse\n\t- status:: draft\n    - public-access:: true\n\t- definition:: ### Primary Definition\n**Backpropagation** is an algorithm for training neural networks that computes gradients of the loss function with respect to network weights by propagating error signals backward through the network layers. It enables efficient calculation of gradients needed for gradient descent optimisation.\n\t- maturity:: draft\n\t- owl:class:: mv:Backpropagation\n\t- owl:physicality:: ConceptualEntity\n\t- owl:role:: Concept\n\t- is-subclass-of:: [[ArtificialIntelligence]]\n\t- belongsToDomain:: [[MetaverseDomain]]",
  "backlinks": [
    "Deep Learning",
    "Variational Autoencoders",
    "Loss Function"
  ],
  "wiki_links": [
    "MetaverseDomain",
    "ArtificialIntelligence"
  ],
  "ontology": {
    "term_id": "AI-0043",
    "preferred_term": "Backpropagation",
    "alt_terms": [],
    "iri": "http://narrativegoldmine.com/metaverse#Backpropagation",
    "source_domain": "metaverse",
    "domain": "metaverse",
    "domain_full_name": "",
    "definition": "### Primary Definition",
    "scope_note": null,
    "status": "draft",
    "maturity": "draft",
    "version": null,
    "public_access": true,
    "last_updated": null,
    "authority_score": null,
    "quality_score": null,
    "cross_domain_links": null,
    "owl_class": "mv:Backpropagation",
    "owl_physicality": "ConceptualEntity",
    "owl_role": "Concept",
    "owl_inferred_class": null,
    "is_subclass_of": [],
    "has_part": [],
    "is_part_of": [],
    "requires": [],
    "depends_on": [],
    "enables": [],
    "relates_to": [],
    "bridges_to": [],
    "bridges_from": [],
    "domain_extensions": {},
    "belongs_to_domain": [
      "MetaverseDomain"
    ],
    "implemented_in_layer": [],
    "source": [],
    "validation": {
      "is_valid": false,
      "errors": [
        "Missing required property: last-updated",
        "Missing required property: is-subclass-of (at least one parent class)",
        "owl:class namespace 'mv' doesn't match source-domain 'metaverse'"
      ]
    }
  }
}