{
  "id": "BC 0102 Inflation",
  "title": "BC 0102 inflation",
  "content": "- ### OntologyBlock\n  id:: bc-0102-inflation-ontology\n  collapsed:: true\n\t- ontology:: true\n\t- term-id:: BC-0102\n\t- preferred-term:: BC 0102 inflation\n\t- status:: active\n\t- public-access:: true\n\t- definition:: The rate at which new [[Bitcoin]] units are created and enter circulation through mining rewards, governed by a predetermined supply schedule that decreases over time through halving events, ultimately approaching zero as the network reaches its 21 million coin maximum supply cap.\n\t- maturity:: comprehensive\n\t- owl:class:: bc:BC0102BitcoinInflation\n\t- owl:physicality:: EconomicMechanism\n\t- owl:role:: MonetaryPolicy\n\t- belongsToDomain:: [[Blockchain Economics]]\n\n## Metadata\n\n- **Last Updated**: 2025-11-16\n- **Review Status**: Automated remediation with 2025 context\n- **Verification**: Academic sources verified\n- **Regional Context**: UK/North England where applicable",
  "backlinks": [],
  "wiki_links": [
    "Blockchain Economics",
    "Bitcoin"
  ],
  "ontology": {
    "term_id": "BC-0102",
    "preferred_term": "BC 0102 inflation",
    "alt_terms": [],
    "iri": "http://narrativegoldmine.com/blockchain#BC0102BitcoinInflation",
    "source_domain": null,
    "domain": "bc",
    "domain_full_name": "Blockchain",
    "definition": "The rate at which new [[Bitcoin]] units are created and enter circulation through mining rewards, governed by a predetermined supply schedule that decreases over time through halving events, ultimately approaching zero as the network reaches its 21 million coin maximum supply cap.",
    "scope_note": null,
    "status": "active",
    "maturity": "comprehensive",
    "version": null,
    "public_access": true,
    "last_updated": null,
    "authority_score": null,
    "quality_score": null,
    "cross_domain_links": null,
    "owl_class": "bc:BC0102BitcoinInflation",
    "owl_physicality": "EconomicMechanism",
    "owl_role": "MonetaryPolicy",
    "owl_inferred_class": null,
    "is_subclass_of": [],
    "has_part": [],
    "is_part_of": [],
    "requires": [],
    "depends_on": [],
    "enables": [],
    "relates_to": [],
    "bridges_to": [],
    "bridges_from": [],
    "domain_extensions": {},
    "belongs_to_domain": [
      "Blockchain Economics"
    ],
    "implemented_in_layer": [],
    "source": [],
    "validation": {
      "is_valid": false,
      "errors": [
        "Missing required property: source-domain",
        "Missing required property: last-updated",
        "Missing required property: is-subclass-of (at least one parent class)"
      ]
    }
  }
}