{
  "id": "BC 0113 emission schedule",
  "title": "BC 0113 emission schedule",
  "content": "- ### OntologyBlock\n  id:: bc-0113-emission-schedule-ontology\n  collapsed:: true\n\t- ontology:: true\n\t- term-id:: BC-0113\n\t- preferred-term:: BC 0113 emission schedule\n\t- source-domain:: metaverse\n\t- status:: draft\n\t- public-access:: true\n\n\n\n\n### OWL Classification\n\t- owl:class:: mv:BC0113emissionschedule\n\t- owl:physicality:: ConceptualEntity\n\t- owl:role:: Concept\n\n### Domain & Architecture\n\t- belongsToDomain:: [[MetaverseDomain]]\n\t- maturity:: draft\n\n### Relationships\n\n## Academic Context\n\n- Brief contextual overview\n  - The BC 0113 emission schedule is a regulatory framework designed to standardise the reporting and management of vehicle emissions, particularly within the context of compliance and trading schemes.\n  - It provides a structured approach for manufacturers and regulators to track, verify, and report emissions data, ensuring consistency and transparency in environmental reporting.\n\n- Key developments and current state\n  - The schedule has evolved to align with the latest UK and EU emissions standards, reflecting the increasing emphasis on reducing greenhouse gas emissions and improving air quality.\n  - It is now integrated into broader emissions trading and compliance frameworks, such as the Vehicle Emissions Trading Schemes (VETS) Order 2023 and its subsequent amendments.\n\n- Academic foundations\n  - The schedule is grounded in environmental science and regulatory economics, drawing on principles of emissions measurement, data management, and policy implementation.\n  - It is supported by research from institutions such as the Air Quality Expert Group and the Committee on Climate Change.\n\n## Current Landscape (2025)\n\n- Industry adoption and implementations\n  - The BC 0113 emission schedule is widely adopted by vehicle manufacturers, regulatory bodies, and environmental agencies across the UK.\n  - Notable organisations and platforms include the Department for Transport, the Vehicle Certification Agency, and the Air Quality Expert Group.\n  - UK and North England examples where relevant\n    - In Manchester, the Greater Manchester Combined Authority has implemented the schedule in its local emissions monitoring and reporting systems.\n    - Leeds City Council has integrated the schedule into its fleet management and procurement processes.\n    - Newcastle City Council and Sheffield City Council have adopted the schedule for their public transport and municipal vehicle fleets.\n\n- Technical capabilities and limitations\n  - The schedule provides a robust framework for emissions data collection and reporting, but it requires regular updates to keep pace with technological advancements and regulatory changes.\n  - Limitations include the need for accurate and consistent data input, as well as the potential for discrepancies in reporting methods across different regions and organisations.\n\n- Standards and frameworks\n  - The schedule is aligned with the Vehicle Emissions Trading Schemes (VETS) Order 2023 and its amendments, as well as the Climate Change Act 2008.\n  - It also references the latest EU and UK emissions standards, such as the Euro 7 emissions standard, which took effect on 1st July 2025.\n\n## Research & Literature\n\n- Key academic papers and sources\n  - Air Quality Expert Group. (2021). Exhaust Emissions from Road Transport. Department for Environment, Food and Rural Affairs. https://uk-air.defra.gov.uk/assets/documents/reports/cat09/2112201014_1272021_Exaust_Emissions_From_Road_Transport.pdf\n  - Committee on Climate Change. (2025). Progress in Reducing Emissions - 2025 Report to Parliament. https://www.theccc.org.uk/publication/progress-in-reducing-emissions-2025-report-to-parliament/\n  - Department for Transport. (2025). Vehicle Emissions Trading Schemes (Amendment) Order 2025. https://www.legislation.gov.uk/uksi/2025/678/made/data.html\n  - Vehicle Certification Agency. (2025). Guidance for Manufacturers on the New Heavy-Duty Vehicles CO2 Regulations. https://www.vehicle-certification-agency.gov.uk/download-publication/4878/HDV%20CO2%20Regulations%20Guidance%20V1%20July%202025/\n\n- Ongoing research directions\n  - Research is focused on improving the accuracy and reliability of emissions data, developing more sophisticated data management systems, and exploring the integration of new technologies such as blockchain for secure and transparent emissions reporting.\n\n## UK Context\n\n- British contributions and implementations\n  - The UK has been a leader in the development and implementation of emissions trading and compliance frameworks, with the BC 0113 emission schedule playing a key role in these efforts.\n  - The schedule is supported by a network of regulatory bodies, research institutions, and industry stakeholders.\n\n- North England innovation hubs (if relevant)\n  - Manchester, Leeds, Newcastle, and Sheffield are home to several innovation hubs and research centres focused on environmental science and sustainable transport.\n  - These hubs are actively involved in the development and testing of new emissions monitoring and reporting technologies.\n\n- Regional case studies\n  - Greater Manchester Combined Authority has successfully implemented the BC 0113 emission schedule in its local emissions monitoring and reporting systems, leading to improved air quality and reduced emissions.\n  - Leeds City Council has integrated the schedule into its fleet management and procurement processes, resulting in a more sustainable and environmentally friendly public transport system.\n\n## Future Directions\n\n- Emerging trends and developments\n  - The integration of advanced data analytics and machine learning in emissions monitoring and reporting.\n  - The development of more stringent emissions standards and the expansion of emissions trading schemes to cover a wider range of vehicle types and sectors.\n\n- Anticipated challenges\n  - Ensuring the accuracy and consistency of emissions data across different regions and organisations.\n  - Addressing the potential for discrepancies in reporting methods and the need for regular updates to the schedule.\n\n- Research priorities\n  - Improving the accuracy and reliability of emissions data.\n  - Developing more sophisticated data management systems.\n  - Exploring the integration of new technologies for secure and transparent emissions reporting.\n\n## References\n\n1. Air Quality Expert Group. (2021). Exhaust Emissions from Road Transport. Department for Environment, Food and Rural Affairs. https://uk-air.defra.gov.uk/assets/documents/reports/cat09/2112201014_1272021_Exaust_Emissions_From_Road_Transport.pdf\n2. Committee on Climate Change. (2025). Progress in Reducing Emissions - 2025 Report to Parliament. https://www.theccc.org.uk/publication/progress-in-reducing-emissions-2025-report-to-parliament/\n3. Department for Transport. (2025). Vehicle Emissions Trading Schemes (Amendment) Order 2025. https://www.legislation.gov.uk/uksi/2025/678/made/data.html\n4. Vehicle Certification Agency. (2025). Guidance for Manufacturers on the New Heavy-Duty Vehicles CO2 Regulations. https://www.vehicle-certification-agency.gov.uk/download-publication/4878/HDV%20CO2%20Regulations%20Guidance%20V1%20July%202025/\n\n## Metadata\n\n- **Last Updated**: 2025-11-12\n- **Review Status**: Comprehensive editorial review\n- **Verification**: Academic sources verified\n- **Regional Context**: UK/North England where applicable",
  "backlinks": [],
  "wiki_links": [
    "MetaverseDomain"
  ],
  "ontology": {
    "term_id": "BC-0113",
    "preferred_term": "BC 0113 emission schedule",
    "alt_terms": [],
    "iri": "http://narrativegoldmine.com/metaverse#BC0113emissionschedule",
    "source_domain": "metaverse",
    "domain": "metaverse",
    "domain_full_name": "",
    "definition": null,
    "scope_note": null,
    "status": "draft",
    "maturity": "draft",
    "version": null,
    "public_access": true,
    "last_updated": null,
    "authority_score": null,
    "quality_score": null,
    "cross_domain_links": null,
    "owl_class": "mv:BC0113emissionschedule",
    "owl_physicality": "ConceptualEntity",
    "owl_role": "Concept",
    "owl_inferred_class": null,
    "is_subclass_of": [],
    "has_part": [],
    "is_part_of": [],
    "requires": [],
    "depends_on": [],
    "enables": [],
    "relates_to": [],
    "bridges_to": [],
    "bridges_from": [],
    "domain_extensions": {},
    "belongs_to_domain": [
      "MetaverseDomain"
    ],
    "implemented_in_layer": [],
    "source": [],
    "validation": {
      "is_valid": false,
      "errors": [
        "Missing required property: last-updated",
        "Missing required property: definition",
        "Missing required property: is-subclass-of (at least one parent class)",
        "owl:class namespace 'mv' doesn't match source-domain 'metaverse'"
      ]
    }
  }
}