{
  "id": "BC-0493-real-estate-tokenization",
  "title": "Real Estate Tokenization",
  "content": "- ### OntologyBlock\n  id:: bc-0493-real-estate-tokenization-ontology\n  collapsed:: true\n\t- ontology:: true\n\t- term-id:: BC-0493\n\t- preferred-term:: Real Estate Tokenization\n\t- status:: complete\n\t- public-access:: true\n\t- definition:: Blockchain-based systems employing security tokens (ERC-3643, ERC-1400, ERC-20 standards) to represent fractional ownership interests in real estate properties, enabling automated dividend distribution through smart contracts, reducing investment minimums from tens of thousands to £50, and creating 24/7 tradeable markets projected to grow from £2.6-3.5 billion (2024) to £4 trillion (2035) whilst providing regulatory compliance through Regulation D, Regulation A+, and international frameworks.\n\t- maturity:: draft\n\t- owl:class:: bc:RealEstateTokenization\n\t- owl:physicality:: ConceptualEntity\n\t- owl:role:: Concept\n\t- belongsToDomain:: [[BlockchainDomain]]\n\t- #### Relationships\n\t  id:: bc-0493-real-estate-tokenization-relationships\n\t  collapsed:: true\n\t\t- is-subclass-of:: [[Blockchain Application]]\n\n## OWL Formal Semantics\n\n```clojure\nPrefix(:=<http://narrativegoldmine.com/blockchain#>)\nPrefix(owl:=<http://www.w3.org/2002/07/owl#>)\nPrefix(rdf:=<http://www.w3.org/1999/02/22-rdf-syntax-ns#>)\nPrefix(xsd:=<http://www.w3.org/2001/XMLSchema#>)\nPrefix(rdfs:=<http://www.w3.org/2000/01/rdf-schema#>)\nPrefix(dcterms:=<http://purl.org/dc/terms/>)\nPrefix(dt:=<http://narrativegoldmine.com/dt#>)\n\nOntology(<http://narrativegoldmine.com/blockchain/BC-0493>\n  Import(<http://narrativegoldmine.com/dt/properties>)\n\n  ## Class Declaration\n  Declaration(Class(:RealEstateTokenization))\n\n  ## Subclass Relationships\n  SubClassOf(:RealEstateTokenization :BlockchainUseCase)\n  SubClassOf(:RealEstateTokenization :AssetTokenization)\n  SubClassOf(:RealEstateTokenization :SecurityToken)\n  SubClassOf(:RealEstateTokenization :FinancialApplication)\n\n  ## Token Standards\n  SubClassOf(:RealEstateTokenization\n    (ObjectSomeValuesFrom dt:implements :ERC3643))\n  SubClassOf(:RealEstateTokenization\n    (ObjectSomeValuesFrom dt:implements :ERC1400))\n  SubClassOf(:RealEstateTokenization\n    (ObjectSomeValuesFrom dt:implements :ERC20))\n\n  ## Blockchain Platforms\n  SubClassOf(:RealEstateTokenization\n    (ObjectSomeValuesFrom dt:implementedby :Ethereum))\n  SubClassOf(:RealEstateTokenization\n    (ObjectSomeValuesFrom dt:implementedby :Algorand))\n  SubClassOf(:RealEstateTokenization\n    (ObjectSomeValuesFrom dt:implementedby :Hedera))\n  SubClassOf(:RealEstateTokenization\n    (ObjectSomeValuesFrom dt:implementedby :XRPLedger))\n\n  ## Core Technology\n  SubClassOf(:RealEstateTokenization\n    (ObjectSomeValuesFrom dt:uses :SmartContract))\n  SubClassOf(:RealEstateTokenization\n    (ObjectSomeValuesFrom dt:uses :DistributedLedger))\n  SubClassOf(:RealEstateTokenization\n    (ObjectSomeValuesFrom dt:uses :AutomatedDividendDistribution))\n\n  ## Regulatory Compliance\n  SubClassOf(:RealEstateTokenization\n    (ObjectSomeValuesFrom dt:implements :RegulationD))\n  SubClassOf(:RealEstateTokenization\n    (ObjectSomeValuesFrom dt:implements :RegulationAPlus))\n  SubClassOf(:RealEstateTokenization\n    (ObjectSomeValuesFrom dt:implements :KYCAMLVerification))\n\n  ## Core Capabilities\n  SubClassOf(:RealEstateTokenization\n    (ObjectSomeValuesFrom dt:enables :FractionalOwnership))\n  SubClassOf(:RealEstateTokenization\n    (ObjectSomeValuesFrom dt:enables :LiquidityEnhancement))\n  SubClassOf(:RealEstateTokenization\n    (ObjectSomeValuesFrom dt:enables :GlobalAccess))\n  SubClassOf(:RealEstateTokenization\n    (ObjectSomeValuesFrom dt:enables :AutomatedIncomeDistribution))\n\n  ## Requirements\n  SubClassOf(:RealEstateTokenization\n    (ObjectSomeValuesFrom dt:requires :SecuritiesCompliance))\n  SubClassOf(:RealEstateTokenization\n    (ObjectSomeValuesFrom dt:requires :AccreditedInvestorVerification))\n  SubClassOf(:RealEstateTokenization\n    (ObjectSomeValuesFrom dt:requires :LegalStructure))\n\n  ## Related Concepts\n  SubClassOf(:RealEstateTokenization\n    (ObjectSomeValuesFrom dt:relatedto :PropertyRegistry))\n  SubClassOf(:RealEstateTokenization\n    (ObjectSomeValuesFrom dt:relatedto :GovernanceToken))\n\n  ## Annotations\n  AnnotationAssertion(rdfs:label :RealEstateTokenization \"Real Estate Tokenization\"@en)\n  AnnotationAssertion(rdfs:comment :RealEstateTokenization\n    \"Blockchain-based systems employing security tokens (ERC-3643, ERC-1400, ERC-20 standards) to represent fractional ownership interests in real estate properties, enabling automated dividend distribution through smart contracts, reducing investment minimums from tens of thousands to £50, and creating 24/7 tradeable markets projected to grow from £2.6-3.5 billion (2024) to £4 trillion (2035).\"@en)\n  AnnotationAssertion(dcterms:identifier :RealEstateTokenization \"BC-0493\"^^xsd:string)\n  AnnotationAssertion(dt:hasauthorityscore :RealEstateTokenization \"0.87\"^^xsd:decimal)\n  AnnotationAssertion(dt:hasmaturity :RealEstateTokenization \"draft\"@en)\n  AnnotationAssertion(dt:hasstatus :RealEstateTokenization \"complete\"@en)\n)\n```\n\n- ## About Real Estate Tokenization\n  id:: bc-0493-real-estate-tokenization-about\n\n\t- Blockchain-based real estate tokenization transforms the **£637 trillion global real estate market** by converting property ownership into tradeable digital security tokens, reducing investment minimums from tens or hundreds of thousands to as little as **£50** whilst enabling **24/7 global trading** and automated rental income distribution. With the market growing from **£2.6-3.5 billion (2024)** to projected **£4 trillion by 2035** at 27% compound annual growth rate, implementations span RealT's **600+ properties** serving **65,000+ investors** with weekly stablecoin dividends, the St. Regis Aspen Resort's **£18 million** tokenized offering achieving **30% value increase** within 18 months, and Dubai luxury apartments selling out in **under 2 minutes** to buyers from **35 countries**.\n\t-\n\t- The technology employs security token standards including **ERC-3643** (£28 billion in assets tokenized), **ERC-1400** (partition-based compliance), and **ERC-20** (fungible fractional shares) on blockchain platforms including Ethereum, Algorand, Hedera, and XRP Ledger. Smart contracts automate dividend distribution, ownership transfers, and regulatory compliance (KYC/AML verification, accredited investor status, jurisdiction restrictions) whilst legal structures utilise Special Purpose Vehicles (SPVs), tokenized REITs, and emerging direct title deed tokenization synchronised with official property registries.\n\t-\n\t- ### Market Size and Growth Projections\n\n\t\t- **Current Tokenized Value**: The 2024 market reached **£2.6-3.5 billion** with **under £300 billion** in actively tokenized assets representing merely **0.0013%** of the **£9.6 trillion** professionally managed global real estate. Security tokens actively trading total **£128 million**, with tokenized real estate comprising approximately **20%** of total security token market capitalization.\n\n\t\t- **Growth Trajectory**: Projections indicate explosive expansion: **£1,244.18 billion (2025)** in broader asset tokenization markets, **£3-3.2 trillion (2030)** at 49% CAGR, **£19.4 billion (2033)** specifically for tokenized real estate at 21% CAGR, and **£4 trillion (2035)** at 27% CAGR potentially representing **15% of real estate AUM**. The broader Real World Assets (RWA) tokenization market demonstrated **260% growth in 2025** with **200+ active projects** and Total Value Locked (TVL) reaching **£65 billion** (800% jump from 2023).\n\n\t\t- **Adoption Rates**: As of June 2024, **12% of real estate firms globally** had implemented tokenization solutions, **46%** were piloting tokenization projects, and **55% of surveyed investors** plan to allocate funds to tokenized assets within 1-2 years. By 2027, estimates suggest **7-9% of portfolios** will allocate to tokenized assets, with **37% of Asia Pacific asset managers** initiating projects in 2024.\n\n\t- ### Major Named Implementations\n\n\t\t- **RealT (United States)**: Founded 2019, RealT has tokenized **600+ properties** worth over **£83 million** across **970+ units** in seven states (Detroit, Cleveland, Chicago, Toledo, Florida) and two countries, serving **65,000+ registered investors**. The platform distributed **£24 million** in rental income with **6-16% returns** paid weekly in stablecoins. Investment minimums of **£50** enable **88% of users** to invest under £5,000, with properties averaging **254 owners** each. Properties tokenized 2019-2021 generated **238,433 blockchain transactions**, built on Ethereum using ERC-20 tokens.\n\n\t\t- **St. Regis Aspen Resort (Elevated Returns)**: This 179-room luxury hotel in Aspen, Colorado with four food-and-beverage outlets and 29,000 sq ft conference space raised **£18 million** through Aspen Digital token offering (2018) representing **18.9% ownership** of the resort. Tokens sold at **£1 each** with **10,000 token minimum** (£21,000) demonstrated **30% value increase** within 18 months of issuance. Listed on tZERO Alternative Trading System (August 2020), market capitalisation reached **£22.5 million** by March 2021 representing **18% of total tokenized real estate market** at that time. Only accredited investors were permitted.\n\n\t\t- **Dubai Real Estate Tokenization (Prypco Mint)**: Built on XRP Ledger synchronised with official property records, Dubai's platform enables investment minimums of **2,000 dirhams (~£540)**. Two luxury properties sold out within minutes to buyers from **35+ countries**, with the second tokenized apartment selling out in **1 minute 58 seconds** attracting **149 investors** whilst **10,700 investors** joined the waitlist. The **£3 billion MAG Group deal** (May 2025) between MultiBank Group, MAG, and Mavryk tokenizes MAG's luxury real estate portfolio, with projections that tokenized real estate could represent **7% (£16 billion)** of total Dubai property transactions by 2033.\n\n\t\t- **Propy**: Processing **1,000+ real estate transfers** worth over **£1 billion** facilitated and **£4 billion** in digital real estate transactions processed as a licenced title firm, Propy's PropyKeys statistics (2025) show **200,000 digital addresses** created with **80,000 U.S. homes** minted on-chain by true owners. Expected to surpass **£50 billion** in tokenized property value by end of 2025 with **£10 billion** in real estate ready for tokenization. Crypto-native transactions represent **5% of volume**, whilst **12%+ of first-time home buyers** used crypto for down payments. Plans include **£100 million expansion** to acquire U.S. title firms targeting **£1 billion valuation**.\n\n\t\t- **Lofty**: Tokenized **150+ properties** across **40 markets** by mid-2025 generating **£50 million** in tokenized value. Built on Algorand blockchain with **£50 minimum** investment, the platform distributes daily rental yields automatically. Planning DeFi yield farming partnerships for **12-15% APR** returns (2026 projection).\n\n\t\t- **RedSwan CRE**: Managing **£5 billion** in commercial real estate through Token Studio platform on Hedera blockchain, specializing in Class A commercial properties (shopping centres, office buildings, multifamily properties) for accredited investors only.\n\n\t- ### Technical Architecture and Token Standards\n\n\t\t- **ERC-3643 (Official Ethereum Standard)**: The only officially accepted security token standard has tokenized **£28 billion** in assets through modular compliance architecture separating identity/eligibility from token logic. Identity registries and compliance controllers enforce transfer rules, whilst automatic validator systems apply rules related to users and offerings. Compatible with ERC-20 wallets and exchanges, ERC-3643 proves ideal for regulated assets (real estate, securities, private funds) offering more secure, scalable, and flexible implementation than alternatives.\n\n\t\t- **ERC-1400**: Focuses on partitioning token supply into classes with different rules, providing document management systems linking tokens to legal documents. Each partition can have distinct restrictions enabling nuanced control over token batches.\n\n\t\t- **ERC-20**: Standard fungible token used by RealT, AspenCoin, and others for LLC membership interests, enabling fractional ownership and automated distributions with full wallet and exchange compatibility.\n\n\t\t- **Smart Contract Functions**: Dividend distribution automates rental income distribution to token holders (RealT: monthly stablecoin payments; Lofty: daily rental income) using pull-based approaches calculating rewards at user-initiated payouts, eliminating manual processing whilst ensuring timely transparent payments. Ownership transfers automate when conditions are met, updating land registries automatically and adding new blocks to blockchain without human intervention whilst enforcing compliance cheques during transfers. Voting rights and governance embed in smart contracts with compliance integration including KYC/AML verification, transfer restrictions based on jurisdiction and investor status, and real-time regulatory compliance enforcement alongside investor accreditation verification.\n\n\t\t- **Blockchain Platforms**: **Ethereum** dominates implementations (ERC-3643, ERC-1400, ERC-20), **Algorand** powers Lofty, **Hedera** supports RedSwan CRE, and **XRP Ledger** enables Dubai's Prypco Mint.\n\n\t- ### Regulatory Frameworks and Compliance\n\n\t\t- **United States SEC Regulations**: Real estate tokens virtually always qualify as securities under state and federal law, requiring SEC registration or exemption. **Regulation D** provides the most common framework: Rule 506(b) permits unlimited accredited investors plus up to 35 non-accredited without general solicitation, whilst Rule 506(c) requires all investors be accredited but permits general solicitation with verification of accredited status (individuals: £200,000 annual income or £300,000 with spouse; net worth over £1 million excluding primary residence).\n\n\t\t- **Regulation A+ (Mini-IPO)**: **Tier 1** permits up to £20 million in 12 months with non-audited financial statements acceptable but subject to state securities laws (Blue Sky), whilst **Tier 2** permits up to £75 million in 12 months open to non-accredited investors with tokens freely tradable from day one on regulated Alternative Trading Systems, pre-empting state registration requirements whilst requiring audited financials and U.S. or Canadian company issuer status.\n\n\t\t- **International Regulatory Frameworks**: **EU MiCA** explicitly excludes security tokens (real estate falls under MiFID II/MiFIR instead), member states treat property tokens as securities. **Singapore MAS** recognises security tokens under Securities and Futures Act with clear legal frameworks through **Project Guardian** moving from sandbox to full commercialization (2024-2025), requiring Capital Markets Services dealer licences and Recognised Market Operator status for platforms. **Hong Kong SFC** offers security token offerings through sandbox programmes with **Ensemble Sandbox** launched 2024 featuring HSBC and Hashkey Group participation, requiring licenced managers, investor accreditation, and full SFC disclosure compliance. **Dubai/UAE** launched official government-backed Dubai Land Department platform (May 2025) on XRP Ledger synchronised with official property records enabling **£540 minimum** investments with projections of **7% (£16 billion)** of property transactions by 2033.\n\n\t- ### Benefits Over Traditional Real Estate Investment\n\n\t\t- **Fractional Ownership and Reduced Minimums**: Traditional investment requires tens of thousands to millions of dollars, whilst tokenized minimums reach **£50-£1,000** (some platforms as low as £50). RealT demonstrates **88% of users** investing under £5,000, Dubai requires minimum **£540** (2,000 dirhams), enabling investors with £5,000 to own fractions of 10-100 different properties instead of limitation to single investments. Portfolio diversification becomes accessible to retail investors previously restricted to institutional-only high-value properties (luxury hotels, commercial buildings).\n\n\t\t- **Increased Liquidity**: Traditional real estate selling processes take months with high transaction costs (5-10% in fees) requiring finding buyers for entire properties creating illiquid asset classes, whilst tokenized real estate enables instant trading on secondary markets, buying/selling fractional shares without selling entire properties, **25% more liquid** when tradable on decentralised exchanges, 24/7 trading availability, and lower transaction costs. Academic research shows property ownership changes approximately once yearly on average, indicating secondary market liquidity remains developing.\n\n\t\t- **Global Access and 24/7 Markets**: Geographic barriers dissolve as Dubai luxury apartment attracted **149 investors** from **35 countries**, St. Regis Aspen enabled international investor participation, and blockchain enables round-the-clock trading across time zones eliminating complex cross-border legal structures.\n\n\t\t- **Enhanced Transparency and Automated Income**: Blockchain provides immutable ownership records, transparent transaction history, and real-time income distribution tracking. **55% of investors** cite \"enhanced transparency\" and \"lower transaction costs\" as key advantages. Automated distribution includes RealT's **weekly** stablecoin payments and Lofty's **daily** rental income distribution with no manual processing or delays, proportional to token holdings through transparent trustless systems.\n\n\t- ### Legal Structures\n\n\t\t- **Special Purpose Vehicle (SPV) Model**: Most U.S. tokenizations employ LLC structures where property is held by separate legal entities (LLC, trust, limited partnership), entities own title to property, tokens represent shares/membership units in SPVs, and investors own SPV equity (not direct property interest). Clear legal separation provides limited liability for investors, simplified compliance (securities regulation at SPV level), and established legal precedent. Revenue flows from property income through SPV to smart contract distribution to token holders (exemplified by St. Regis Aspen where Aspen Digital entity owns 18.9% of resort).\n\n\t\t- **Direct Ownership Model**: Tokens represent fractional ownership of underlying real estate assets with direct legal rights to property shares including share of rental income, share of appreciation, voting rights on property decisions, and direct claim on property. Challenges include complex legal recognition (many jurisdictions don't recognise blockchain records as legally binding), property law alignment issues, and title registry integration requirements (exemplified by Dubai's Prypco Mint tokenizing title deeds synchronised with official property records).\n\n\t\t- **REIT (Real Estate Investment Trust) Structure**: Digital shares in REIT entities provide token holders same rights as traditional REIT investors with operational revenue distribution and regulatory compliance under REIT laws, offering established regulatory frameworks, tax advantages (REIT pass-through taxation), and institutional familiarity (exemplified by Harbour's The Hub at Columbia tokenized REIT, though ultimately failed).\n\n\t- ### Challenges and Limitations\n\n\t\t- **Legal Recognition Issues**: Many jurisdictions **do not recognise** blockchain-based records as legally binding, complicating enforcement of property rights. Legal statutes in certain locations don't recognise real estate tokens as legitimate proof of ownership, creating uncertainty about token-based ownership alignment with traditional property laws alongside title registry integration challenges and varying recognition across jurisdictions.\n\n\t\t- **Regulatory Complexity**: Legal frameworks remain \"still evolving\" with rules varying widely across countries, creating compliance challenges for issuers and investors. SEC enforcement intensified scrutiny (2023-2024) of non-compliant platforms, particularly those failing AML/KYC compliance, alongside securities classification uncertainty. Multi-jurisdictional compliance demands navigating multiple regulatory regimes (EU: MiFID II for securities; U.S.: SEC registration or exemption; Asia: varying frameworks via MAS, SFC).\n\n\t\t- **Limited Secondary Market Liquidity**: Current state shows property ownership changing approximately **once per year** on average, tokens \"mainly traded within platform of issuance\" with limited investor reach \"inhibiting liquidity benefits.\" Many platforms (RTX21, Finexity, Exporo, FND) have **no secondary market**, RealT buyback limitations (£2,000/week max, 10-day processing), and small total market (only **£128 million** actively traded).\n\n\t\t- **Market Maturity**: Only **0.0013%** of professionally managed global real estate (£9.6 trillion) is tokenized, current market (£3.5 billion) versus traditional market (£637 trillion global) represents limited track record. Investor education challenges include novel concepts for most investors, technical complexity (wallets, blockchain, smart contracts), and trust and adoption challenges.\n\n\t- ### Trading Platforms and Secondary Markets\n\n\t\t- **INX (INX.co)**: First SEC-registered Security Token Offering for U.S. retail investors with **six security tokens** actively trading (INX, SPiCE VC, Blockchain Capital, Protos, Science Blockchain, 22x Fund). Open to accredited investors globally as asset-agnostic platform combining crypto and security tokens through regulated alternative trading system.\n\n\t\t- **Securitize Markets**: Acquired Distributed Technology Markets (DTM), a FINRA-registered ATS and SEC broker-dealer, providing access to private company equity, real estate, and funds through single regulated digital marketplace. Launched secondary market trading (2021) aiming to increase private market liquidity overall.\n\n\t\t- **tZERO**: Alternative Trading System hosting St. Regis Aspen Digital token trading (since August 2020), focusing on digital securities and tokenized assets integrated with SolidBlock for tokenization.\n\n\t\t- **Platform-Specific Trading**: RealT offers primary issuance on platform with secondary trading via **Swapcat** (bid/offer posting) and **Airswap** (decentralised exchange) plus buyback programme (up to **£2,000 per week**, 10-day processing), **25%** more liquidity for DEX-tradable tokens. Market capitalisation grew from **£25 million (December 2020)** to **£32 million (June 2021)** (25% increase in 6 months) to **£128 million (2025)** in active trading.\n\n\t- ### Future Developments\n\n\t\t- **Institutional Adoption Acceleration**: **12% of real estate firms** implementing tokenization and **46% piloting** (June 2024) demonstrates accelerating institutional adoption through major participants including **Goldman Sachs**, **BlackRock**, **BNY Mellon**, and **Citi**. The market projected to reach **15% of real estate AUM by 2030** represents fundamental transformation of property investment accessibility and liquidity.\n\n\t\t- **Regulatory Maturation**: The 2024-2025 **GENIUS Act** provides regulatory clarity, state-level sandbox initiatives allow major institutions (Bank of America, Citi, BlackRock, Coinbase) to explore tokenization, and international harmonisation progresses through Singapore's Project Guardian commercialisation, Hong Kong's Ensemble Sandbox, and Dubai's official government platform launch.\n\n\t\t- **Technology Evolution**: Enhanced security features advance towards quantum-resistant encryption, cross-chain interoperability enables seamless trading across different blockchain platforms, improved scalability solutions (Layer 2, sharding) support higher transaction volumes, and integration with DeFi protocols (Lofty's 12-15% APR yield farming plans) expands investment return opportunities.\n\n\t- #\n\n\n## Metadata\n\n- **Last Updated**: 2025-11-16\n- **Review Status**: Automated remediation with 2025 context\n- **Verification**: Academic sources verified\n- **Regional Context**: UK/North England where applicable\n\n## References and Further Reading\n\t\t- [[BC-0494-property-registry]] - Blockchain land title and property registries\n\t\t- [[BC-0432-consortium-blockchain]] - Multi-organisation blockchain implementations\n\t\t- [[BC-0456-self-sovereign-identity]] - Identity management systems\n\t\t- [[BC-0458-verifiable-credentials]] - Credential verification frameworks\n\t\t- [[BC-0463-governance-token]] - Token governance mechanisms\n\t\t- [[BC-0478-securities-regulation]] - Securities regulatory compliance\n\t\t- [[BC-0488-licencing-requirements]] - Regulatory licencing frameworks",
  "backlinks": [
    "BC-0494-property-registry"
  ],
  "wiki_links": [
    "BC-0458-verifiable-credentials",
    "BC-0463-governance-token",
    "BC-0456-self-sovereign-identity",
    "BC-0478-securities-regulation",
    "BC-0488-licencing-requirements",
    "BlockchainDomain",
    "Blockchain Application",
    "BC-0432-consortium-blockchain",
    "BC-0494-property-registry"
  ],
  "ontology": {
    "term_id": "BC-0493",
    "preferred_term": "Real Estate Tokenization",
    "alt_terms": [],
    "iri": "http://narrativegoldmine.com/blockchain#RealEstateTokenization",
    "source_domain": null,
    "domain": "bc",
    "domain_full_name": "Blockchain",
    "definition": "Blockchain-based systems employing security tokens (ERC-3643, ERC-1400, ERC-20 standards) to represent fractional ownership interests in real estate properties, enabling automated dividend distribution through smart contracts, reducing investment minimums from tens of thousands to £50, and creating 24/7 tradeable markets projected to grow from £2.6-3.5 billion (2024) to £4 trillion (2035) whilst providing regulatory compliance through Regulation D, Regulation A+, and international frameworks.",
    "scope_note": null,
    "status": "complete",
    "maturity": "draft",
    "version": null,
    "public_access": true,
    "last_updated": null,
    "authority_score": null,
    "quality_score": null,
    "cross_domain_links": null,
    "owl_class": "bc:RealEstateTokenization",
    "owl_physicality": "ConceptualEntity",
    "owl_role": "Concept",
    "owl_inferred_class": null,
    "is_subclass_of": [
      "Blockchain Application"
    ],
    "has_part": [],
    "is_part_of": [],
    "requires": [],
    "depends_on": [],
    "enables": [],
    "relates_to": [],
    "bridges_to": [],
    "bridges_from": [],
    "domain_extensions": {},
    "belongs_to_domain": [
      "BlockchainDomain"
    ],
    "implemented_in_layer": [],
    "source": [],
    "validation": {
      "is_valid": false,
      "errors": [
        "Missing required property: source-domain",
        "Missing required property: last-updated"
      ]
    }
  }
}