{
  "id": "BC-0501-esg-reporting",
  "title": "ESG Reporting",
  "content": "- ### OntologyBlock\n  id:: bc-0501-esg-reporting-ontology\n  collapsed:: true\n\t- ontology:: true\n\t- term-id:: BC-0501\n\t- preferred-term:: ESG Reporting\n\t- status:: stub\n\t- public-access:: true\n\t- definition:: A component of the blockchain ecosystem.\n\t- maturity:: draft\n\t- owl:class:: bc:ESGReporting\n\t- owl:physicality:: ConceptualEntity\n\t- owl:role:: Concept\n\t- belongsToDomain:: [[BlockchainDomain]]\n\t- #### Relationships\n\t  id:: bc-0501-esg-reporting-relationships\n\t  collapsed:: true\n\t\t- is-subclass-of:: [[Blockchain Sustainability]]\n\n## OWL Formal Semantics\n\n```clojure\n;; OWL Functional Syntax\n\n(Declaration (Class :ESGReporting))\n\n;; Annotations\n(AnnotationAssertion rdfs:label :ESGReporting \"ESG Reporting\"@en)\n(AnnotationAssertion rdfs:comment :ESGReporting \"A component of the blockchain ecosystem.\"@en)\n\n;; Data Properties\n(AnnotationAssertion dcterms:identifier :ESGReporting \"BC-0501\"^^xsd:string)\n```",
  "backlinks": [],
  "wiki_links": [
    "Blockchain Sustainability",
    "BlockchainDomain"
  ],
  "ontology": {
    "term_id": "BC-0501",
    "preferred_term": "ESG Reporting",
    "alt_terms": [],
    "iri": "http://narrativegoldmine.com/blockchain#ESGReporting",
    "source_domain": null,
    "domain": "bc",
    "domain_full_name": "Blockchain",
    "definition": "A component of the blockchain ecosystem.",
    "scope_note": null,
    "status": "stub",
    "maturity": "draft",
    "version": null,
    "public_access": true,
    "last_updated": null,
    "authority_score": null,
    "quality_score": null,
    "cross_domain_links": null,
    "owl_class": "bc:ESGReporting",
    "owl_physicality": "ConceptualEntity",
    "owl_role": "Concept",
    "owl_inferred_class": null,
    "is_subclass_of": [
      "Blockchain Sustainability"
    ],
    "has_part": [],
    "is_part_of": [],
    "requires": [],
    "depends_on": [],
    "enables": [],
    "relates_to": [],
    "bridges_to": [],
    "bridges_from": [],
    "domain_extensions": {},
    "belongs_to_domain": [
      "BlockchainDomain"
    ],
    "implemented_in_layer": [],
    "source": [],
    "validation": {
      "is_valid": false,
      "errors": [
        "Missing required property: source-domain",
        "Missing required property: last-updated"
      ]
    }
  }
}