{
  "id": "BC-0445-conflict-mineral-tracking",
  "title": "Conflict Mineral Tracking",
  "content": "- ### OntologyBlock\n  id:: bc-0445-conflict-mineral-tracking-ontology\n  collapsed:: true\n\t- ontology:: true\n\t- term-id:: BC-0445\n\t- preferred-term:: Conflict Mineral Tracking\n\t- status:: complete\n\t- public-access:: true\n\t- definition:: Blockchain applications addressing ethical sourcing challenges for 3TG minerals (tin, tantalum, tungsten, gold) used in electronics, ensuring minerals don't finance armed conflict or human rights abuses in DRC and adjoining regions. Over 6,000 companies spend £500 million annually on conflict mineral due diligence under Dodd-Frank Section 1502 and EU Conflict Minerals Regulation, with blockchain implementations by Circulor (Volvo, VW, Tesla), RCS Global Better Sourcing (Apple, Samsung), and Everledger demonstrating 40-60% reductions in due diligence costs through automated verification, immutable custody chains, and cryptographic material fingerprinting that enable 5-15% premium pricing for verified responsible sourcing whilst dramatically reducing human rights abuses.\n\t- maturity:: mature\n\t- owl:class:: bc:ConflictMineralTracking\n\t- owl:physicality:: ConceptualEntity\n\t- owl:role:: Concept\n\t- belongsToDomain:: [[BlockchainDomain]]\n\t- #### Relationships\n\t  id:: bc-0445-conflict-mineral-tracking-relationships\n\t  collapsed:: true\n\t\t- is-subclass-of:: [[Supply Chain Blockchain]]\n\n## OWL Formal Semantics\n\n```clojure\nPrefix(:=<http://narrativegoldmine.com/blockchain#>)\nPrefix(owl:=<http://www.w3.org/2002/07/owl#>)\nPrefix(rdf:=<http://www.w3.org/1999/02/22-rdf-syntax-ns#>)\nPrefix(xsd:=<http://www.w3.org/2001/XMLSchema#>)\nPrefix(rdfs:=<http://www.w3.org/2000/01/rdf-schema#>)\nPrefix(dcterms:=<http://purl.org/dc/terms/>)\nPrefix(dt:=<http://narrativegoldmine.com/dt#>)\n\nOntology(<http://narrativegoldmine.com/blockchain/BC-0445>\n  Import(<http://narrativegoldmine.com/dt/properties>)\n\n  ## Class Declaration\n  Declaration(Class(:ConflictMineralTracking))\n\n  ## Subclass Relationships\n  SubClassOf(:ConflictMineralTracking :BlockchainUseCase)\n  SubClassOf(:ConflictMineralTracking :SupplyChainApplication)\n  SubClassOf(:ConflictMineralTracking :RegulatoryComplianceSolution)\n  SubClassOf(:ConflictMineralTracking :EthicalSourcingVerification)\n\n  ## Core Technology\n  SubClassOf(:ConflictMineralTracking (ObjectSomeValuesFrom dt:uses :HyperledgerFabric))\n  SubClassOf(:ConflictMineralTracking (ObjectSomeValuesFrom dt:uses :Ethereum))\n  SubClassOf(:ConflictMineralTracking (ObjectSomeValuesFrom dt:uses :SmartContracts))\n  SubClassOf(:ConflictMineralTracking (ObjectSomeValuesFrom dt:uses :MaterialFingerprinting))\n  SubClassOf(:ConflictMineralTracking (ObjectSomeValuesFrom dt:uses :GPSTracking))\n\n  ## Standards and Platforms\n  SubClassOf(:ConflictMineralTracking (ObjectSomeValuesFrom dt:implements :OECDDueDiligenceGuidance))\n  SubClassOf(:ConflictMineralTracking (ObjectSomeValuesFrom dt:implements :DoddFrankSection1502))\n  SubClassOf(:ConflictMineralTracking (ObjectSomeValuesFrom dt:implements :EUConflictMineralsRegulation))\n  SubClassOf(:ConflictMineralTracking (ObjectSomeValuesFrom dt:implements :RMAPAuditStandards))\n  SubClassOf(:ConflictMineralTracking (ObjectSomeValuesFrom dt:implementedby :CirculorPlatform))\n  SubClassOf(:ConflictMineralTracking (ObjectSomeValuesFrom dt:implementedby :RCSGlobalBetterSourcing))\n  SubClassOf(:ConflictMineralTracking (ObjectSomeValuesFrom dt:implementedby :EverledgerProvenance))\n\n  ## Core Capabilities\n  SubClassOf(:ConflictMineralTracking (ObjectSomeValuesFrom dt:enables :SourceVerification))\n  SubClassOf(:ConflictMineralTracking (ObjectSomeValuesFrom dt:enables :AutomatedDueDiligence))\n  SubClassOf(:ConflictMineralTracking (ObjectSomeValuesFrom dt:enables :MaterialAuthentication))\n  SubClassOf(:ConflictMineralTracking (ObjectSomeValuesFrom dt:enables :ArtisanalMiningIntegration))\n  SubClassOf(:ConflictMineralTracking (ObjectSomeValuesFrom dt:enables :ChainOfCustodyVerification))\n  SubClassOf(:ConflictMineralTracking (ObjectSomeValuesFrom dt:enables :RegulatoryReporting))\n\n  ## Requirements\n  SubClassOf(:ConflictMineralTracking (ObjectSomeValuesFrom dt:requires :SpectroscopicAnalysis))\n  SubClassOf(:ConflictMineralTracking (ObjectSomeValuesFrom dt:requires :MobileDataCapture))\n  SubClassOf(:ConflictMineralTracking (ObjectSomeValuesFrom dt:requires :SmelterAuditIntegration))\n  SubClassOf(:ConflictMineralTracking (ObjectSomeValuesFrom dt:requires :ArtisanalMinerTraining))\n\n  ## Related Applications\n  SubClassOf(:ConflictMineralTracking (ObjectSomeValuesFrom dt:relatedto :ProvenanceTracking))\n  SubClassOf(:ConflictMineralTracking (ObjectSomeValuesFrom dt:relatedto :SupplyChainManagement))\n  SubClassOf(:ConflictMineralTracking (ObjectSomeValuesFrom dt:relatedto :EnvironmentalSustainability))\n  SubClassOf(:ConflictMineralTracking (ObjectSomeValuesFrom dt:relatedto :ConsortiumBlockchain))\n\n  ## Annotations\n  AnnotationAssertion(rdfs:label :ConflictMineralTracking \"Conflict Mineral Tracking\"@en)\n  AnnotationAssertion(rdfs:comment :ConflictMineralTracking \"Blockchain applications addressing ethical sourcing challenges for 3TG minerals through immutable custody chains, cryptographic material fingerprinting, and automated regulatory compliance.\"@en)\n  AnnotationAssertion(dcterms:identifier :ConflictMineralTracking \"BC-0445\"^^xsd:string)\n  AnnotationAssertion(dt:hasauthorityscore :ConflictMineralTracking \"0.89\"^^xsd:decimal)\n  AnnotationAssertion(dt:hasmaturity :ConflictMineralTracking \"mature\"@en)\n  AnnotationAssertion(dt:hasstatus :ConflictMineralTracking \"complete\"@en)\n)\n```\n\n- ## About Conflict Mineral Tracking\n  id:: conflict-mineral-tracking-about\n\t- Conflict mineral tracking addresses one of the most challenging ethical sourcing problems in global supply chains: ensuring that minerals used in consumer electronics, automotive, aerospace, and industrial manufacturing don't finance armed conflict or human rights abuses in regions including the Democratic Republic of Congo (DRC) and adjoining countries. The \"3TG\" minerals—tin, tantalum, tungsten, and gold—are essential components in modern electronics, with an estimated 80% of consumer electronic devices containing minerals potentially sourced from conflict regions. Traditional conflict mineral due diligence relies on paper-based documentation including supplier declarations, smelter audits, and chain of custody certificates that suffer from fraud, documentation gaps, and the practical impossibility of verifying mineral provenance through supply chains involving dozens of intermediaries spanning artisanal miners, local traders, regional exporters, international smelters, and component manufacturers. [[Blockchain]] technology transforms conflict mineral compliance through immutable supply chain records, cryptographic verification of mineral provenance, and shared visibility that enables stakeholders across complex supply chains to verify responsible sourcing whilst protecting confidential commercial relationships.\n\t-\n\t- Regulatory frameworks including the US Dodd-Frank Act Section 1502 and EU Conflict Minerals Regulation mandate comprehensive due diligence for companies using 3TG minerals, requiring reasonable country of origin inquiries and, when necessary, detailed supply chain audits documenting that minerals aren't financing conflict in DRC or adjoining countries. Compliance costs for affected companies reach £0.8-2 million annually according to SEC estimates, with industry consortia including the Responsible Minerals Initiative reporting that member companies collectively spend over £500 million annually on conflict mineral due diligence. These substantial compliance investments deliver limited assurance due to documentation gaps, with estimates suggesting 15-25% of declared \"conflict-free\" minerals may actually originate from undisclosed conflict sources. Blockchain implementations demonstrate 40-60% reductions in due diligence costs through automated verification replacing manual documentation review, whilst improving source verification accuracy through cryptographic mineral fingerprinting and immutable custody chains that dramatically increase fraud difficulty.\n\t-\n\t- Conflict mineral blockchain deployments must address unique challenges including integration of artisanal and small-scale mining operations with limited technical infrastructure, protection of commercially sensitive supply chain relationships in highly competitive industries, and verification of physical mineral characteristics linking mined materials to blockchain records. Successful implementations including [[Circulor]]'s collaboration with Volvo, Volkswagen, and Tesla for cobalt tracking, [[RCS Global]]'s Better Sourcing programme for tin and tantalum, and [[Everledger]]'s gold provenance platform demonstrate that blockchain can effectively address these challenges through mobile-first data capture for artisanal miners, cryptographic material fingerprinting linking physical minerals to digital records, and privacy-preserving architectures enabling verification without exposing complete supply chain structures. These implementations report that blockchain-verified responsible sourcing enables 5-15% premium pricing in markets including electric vehicle batteries and consumer electronics where ethical sourcing increasingly influences purchasing decisions, creating economic incentives for responsible mining practices whilst reducing human rights abuses and conflict financing.\n\t-\n\t- ### Regulatory Framework and Compliance Requirements\n\t\t- **Dodd-Frank Act Section 1502**: Enacted in 2010 as part of comprehensive financial reform legislation, Section 1502 requires publicly traded companies manufacturing products containing tin, tantalum, tungsten, or gold to conduct reasonable country of origin inquiries (RCOI) determining whether minerals originated in DRC or adjoining countries (Angola, Burundi, Central African Republic, Republic of Congo, Rwanda, South Sudan, Tanzania, Uganda, Zambia). When RCOI cannot exclude DRC/adjoining countries, companies must conduct detailed due diligence following Organisation for Economic Co-operation and Development (OECD) guidance, filing Form SD with the SEC disclosing findings and describing products as \"DRC conflict free,\" \"DRC conflict undeterminable,\" or \"not DRC conflict free.\" Over 6,000 companies file Form SD annually, with compliance costs estimated at £0.8-2 million per company annually, totalling £5-12 billion in aggregate compliance expenditure across the decade since implementation.\n\t\t-\n\t\t- **EU Conflict Minerals Regulation**: Effective January 2021, the EU regulation establishes supply chain due diligence obligations for EU importers of tin, tantalum, tungsten, and gold, applying to both ores and metals. Unlike Dodd-Frank's disclosure approach, the EU regulation mandates substantive due diligence based on OECD guidance, with importers exceeding volume thresholds (0.2 tonnes for gold, 2 tonnes for tantalum, 100 tonnes each for tin and tungsten) required to implement management systems, identify and assess supply chain risks, implement risk mitigation strategies, and undergo independent third-party audits. The regulation affects approximately 600-1,000 direct EU importers plus thousands of downstream manufacturers integrating 3TG minerals into products, with implementation creating opportunities for blockchain-based due diligence systems providing automated compliance evidence.\n\t\t-\n\t\t- **OECD Due Diligence Guidance**: The OECD Due Diligence Guidance for Responsible Supply Chains of Minerals from Conflict-Affected and High-Risk Areas provides the international standard for conflict mineral due diligence, referenced by both Dodd-Frank and EU regulations. The guidance establishes a five-step framework: establish strong company management systems, identify and assess supply chain risks, design and implement risk mitigation strategies, carry out independent third-party audits, and report annually on supply chain due diligence. Blockchain implementations map to OECD framework steps, with smart contracts encoding risk assessment criteria, immutable records satisfying audit requirements, and cryptographic verification enabling risk mitigation through supply chain transparency whilst preserving commercial confidentiality through selective data sharing.\n\t\t-\n\t- ### The 3TG Supply Chain Complexity\n\t\t- **Tin Supply Chains**: Tin, essential for electronic soldering, travels through complex supply chains from artisanal mines in DRC, Indonesia, Myanmar, and Bolivia through local traders, regional exporters, international smelters, and component manufacturers before reaching electronics brands. Indonesia produces approximately 30% of global tin supply, with significant production from artisanal and small-scale miners (ASM) operating with limited oversight. The iTSCi (ITSCI Tin Supply Chain Initiative) programme operated by the International Tin Association implements bag-and-tag systems tracking tin concentrate from mines through export, providing paper-based traceability that blockchain implementations can augment with cryptographic verification and automated data capture reducing manual documentation burden whilst improving accuracy.\n\t\t-\n\t\t- **Tantalum and the Electronics Industry**: Tantalum capacitors are critical components in smartphones, laptops, and virtually all consumer electronics due to their high capacitance in compact sizes. Approximately 35-40% of global tantalum originates from DRC and Rwanda, with artisanal mining representing significant production volumes. Tantalum supply chains involve mineral processing converting tantalum ore (coltan) into tantalum powder and capacitors, with each processing step creating opportunities for co-mingling minerals from different sources. This complexity makes provenance verification particularly challenging, with traditional due diligence relying on smelter audits that verify smelter inputs but provide limited assurance about specific mineral batch provenance. Blockchain batch-level tracking addresses this gap by maintaining provenance through processing steps.\n\t\t-\n\t\t- **Tungsten Applications and Sourcing**: Tungsten's unique properties (hardness, high melting point, density) make it essential for cutting tools, lighting, electronics, and automotive applications. China dominates tungsten production (80% of global supply), with significant production from DRC, Rwanda, and Bolivia. Tungsten supply chains involve chemical processing converting tungsten ore into ammonium paratungstate (APT) and subsequently tungsten carbide for industrial applications. The chemical processing creates technical verification challenges, as processing transforms physical mineral characteristics. Blockchain implementations address this through batch-level tracking where processing facilities record input mineral provenance and output product characteristics, maintaining custody chains through transformation whilst enabling verification that output quantities align with input volumes, detecting co-mingling with unverified materials.\n\t\t-\n\t\t- **Gold's Unique Challenges**: Gold supply chains present distinct challenges due to gold's high value (enabling economically viable smuggling even in small quantities), fungibility (refined gold from different sources is chemically identical), and extensive recycled gold flows (approximately 25-30% of gold supply comes from recycled sources). Artisanal and small-scale gold mining (ASGM) produces 15-20% of global gold supply, with significant ASGM production in conflict-affected regions. Gold due diligence requires both supply chain tracking and material verification, with implementations employing technologies including X-ray fluorescence spectroscopy and laser-induced breakdown spectroscopy creating unique mineral fingerprints that blockchain records, enabling verification that physical gold matches declared provenance.\n\t\t-\n\t- ### Blockchain Implementation Approaches\n\t\t- **Circulor and Electric Vehicle Battery Minerals**: [[Circulor]] developed a blockchain platform for battery mineral tracking initially focused on cobalt (a critical battery mineral with 60% of global supply from DRC, though not technically a 3TG mineral, facing similar conflict concerns). The platform expanded to tantalum, tungsten, and gold tracking for automotive manufacturers including Volvo, Volkswagen, Polestar, and Tesla. Circulor's approach combines QR code bag-and-tag systems at mines, GPS-enabled smartphones capturing geolocation and timestamp data, and material fingerprinting through X-ray fluorescence creating unique chemical signatures. These physical identifiers link to blockchain records built on [[Hyperledger Fabric]] and [[Ethereum]], with smart contracts verifying chain of custody and flagging gaps suggesting potential co-mingling with unverified materials. Volvo reports that blockchain verification reduced cobalt due diligence costs by 40% whilst providing greater assurance than traditional paper-based approaches.\n\t\t-\n\t\t- **RCS Global Better Sourcing Programme**: RCS Global (formerly Responsible Sourcing Network) operates Better Sourcing, a blockchain platform for tin and tantalum tracking from artisanal mines in DRC and Rwanda. The programme partners with mining cooperatives, providing them with mobile applications for production recording, quality testing results, and export documentation. Each mineral bag receives a unique identifier recorded on blockchain, with physical tags containing QR codes and cryptographic seals detecting tampering. Processing facilities scan tags upon receipt, recording custody transfers and processing steps on blockchain. The platform integrates with Responsible Minerals Assurance Process (RMAP) smelter audits, providing auditors with comprehensive blockchain-verified supply chain data reducing audit time by 30-40%. Major electronics manufacturers including Apple and Samsung source blockchain-verified tin and tantalum through Better Sourcing-participating suppliers.\n\t\t-\n\t\t- **Everledger Gold and Diamond Tracking**: [[Everledger]], known for diamond provenance tracking, extended its platform to gold and other precious metals, focusing on artisanal and small-scale mining integration. The implementation combines blockchain provenance records with material fingerprinting, where gold samples undergo spectroscopic analysis creating unique elemental signatures (trace elements including silver, copper, and rare earth elements vary by geological source). These fingerprints commit to blockchain, with subsequent testing at processing facilities and refineries verifying physical gold matches blockchain-registered fingerprints, detecting substitution or co-mingling. The approach addresses gold's fungibility challenge through cryptographic linkage of physical characteristics to digital records. Implementations report 70-85% accuracy in detecting co-mingling with unverified gold through fingerprint mismatches.\n\t\t-\n\t- ### Artisanal Mining Integration Challenges\n\t\t- **Technical Infrastructure Limitations**: Artisanal mining operations, particularly in remote DRC regions, face limited technical infrastructure including unreliable electricity, limited internet connectivity, and low smartphone penetration. Solutions employ offline-first mobile applications that capture data locally and synchronise to blockchain when connectivity is available, often through aggregation points at mining cooperatives or export facilities. Solar-powered charging stations at mining sites enable smartphone operation, with some implementations providing mining cooperatives with smartphones specifically for blockchain data capture. QR codes on mineral bags enable low-bandwidth data recording, with detailed information committed to blockchain whilst bags carry only minimal identifying information. These adaptations demonstrate that blockchain integration is feasible even in challenging infrastructure environments, though implementation costs (£50,000-200,000 per mining cooperative for initial setup) require external funding through development programmes or downstream purchasers motivated by ethical sourcing requirements.\n\t\t-\n\t\t- **Literacy and Training Requirements**: Artisanal miners may have limited literacy and no prior experience with digital technologies, creating training challenges for blockchain implementation. Successful programmes employ visual interfaces minimising text, voice-based data entry enabling verbal recording of production details, and community training where mining cooperative leaders receive comprehensive training and provide ongoing support to members. Initial training typically requires 2-3 days per mining site, with ongoing refresher training and support. Some implementations employ gamification, where miners earning accuracy scores receive recognition or small financial incentives, motivating quality data entry. These human factors considerations prove as critical as technical architecture, with implementations reporting that community engagement and culturally appropriate training determine adoption success more than technology sophistication.\n\t\t-\n\t\t- **Economic Incentives and Premium Pricing**: Artisanal miners participate in blockchain tracking when economic incentives justify additional effort. Responsible sourcing premiums of 5-15% above spot prices for blockchain-verified conflict-free minerals create participation incentives, with mining cooperatives distributing premiums to members. Some implementations provide direct payment mechanisms through blockchain-integrated mobile money, reducing payment delays from the 2-4 weeks typical in traditional supply chains to under 24 hours whilst eliminating intermediary fees that previously captured 10-20% of miner compensation. These economic models align incentives across supply chains, with premiums funded by downstream manufacturers willing to pay for verified responsible sourcing that reduces compliance risks and enhances brand reputation.\n\t\t-\n\t- ### Technology Sector Implementations\n\t\t- **Apple's Responsible Sourcing Programme**: Apple, the world's largest technology company by revenue, implements comprehensive conflict mineral due diligence across supply chains encompassing hundreds of thousands of suppliers. The company participates in blockchain pilots including Better Sourcing for tantalum and collaborations with smelters implementing blockchain tracking. Apple's 2023 supplier list includes 100% of identified tantalum smelters participating in RMAP audits, with blockchain verification augmenting audit programmes through continuous monitoring rather than periodic assessments. Apple reports that blockchain integration reduced due diligence costs by 35% for participating smelters whilst enabling real-time risk identification that periodic audits miss. The company's supply chain scale (over £300 billion annual procurement) makes it particularly influential in driving blockchain adoption among suppliers seeking to maintain Apple relationships.\n\t\t-\n\t\t- **Intel's Responsible Minerals Programme**: Intel pioneered conflict-free processor manufacturing, achieving conflict-free validation for microprocessor production in 2014 and maintaining this status through comprehensive supply chain due diligence. The company participates in blockchain initiatives through the Responsible Minerals Initiative, supporting smelter blockchain implementation that Intel validates through its supplier audit programme. Intel's approach combines blockchain provenance tracking with analytical testing of mineral samples, creating multi-factor verification that blockchain records alone cannot provide given mineral fungibility. The company reports that blockchain integration enabled expansion of conflict-free sourcing to 100% of gold suppliers (previously 85%) through reduced verification costs making previously marginal suppliers economically viable to validate.\n\t\t-\n\t\t- **Tesla and Battery Supply Chain Transparency**: Tesla's massive battery production for electric vehicles creates significant demand for minerals including cobalt, lithium, and nickel, with ESG-conscious investors and customers demanding responsible sourcing verification. The company partnered with [[Circulor]] to implement blockchain tracking for battery minerals, initially focusing on cobalt from DRC and subsequently expanding to other battery materials. Tesla's 2022 Impact Report disclosed that blockchain verification covers approximately 35% of cobalt supply, with plans to reach 100% coverage by 2025. The implementation enables Tesla to provide customers with detailed battery mineral provenance through vehicle identification number (VIN) lookups, creating marketing differentiation around ethical sourcing whilst satisfying regulatory requirements and investor ESG expectations. Tesla reports that blockchain-verified battery production costs increased by only 0.8% whilst brand perception improvements among sustainability-focused consumers drove an estimated 2-3% sales volume increase, providing substantial ROI.\n\t\t-\n\t- ### Material Fingerprinting and Physical Verification\n\t\t- **Spectroscopic Analysis**: Material fingerprinting employs analytical techniques creating unique mineral signatures based on chemical composition and physical characteristics. X-ray fluorescence (XRF) spectroscopy provides rapid, non-destructive elemental analysis identifying trace elements that vary by geological source. For gold, elemental ratios including silver, copper, and rare earth elements create fingerprints that blockchain systems record, enabling subsequent verification that physical gold matches declared provenance. Laser-induced breakdown spectroscopy (LIBS) provides similar capabilities for tin, tantalum, and tungsten, with portable LIBS devices enabling field testing at mining sites. Blockchain platforms integrate fingerprint data through oracles connecting analytical instruments to smart contracts, with cryptographic hashing ensuring fingerprint data integrity.\n\t\t-\n\t\t- **Isotopic Analysis**: Advanced verification employs isotopic ratio analysis, where naturally occurring variations in stable isotope ratios (for example, lead isotopes in gold, oxygen isotopes in tantalum) create geological signatures specific to mining regions. Mass spectrometry determines isotopic ratios with sufficient precision to distinguish between geological provinces, enabling verification that minerals declared from specific regions actually originated there. Isotopic databases maintained by research institutions including the US Geological Survey and mining industry consortia provide reference data for comparison. Whilst more expensive than spectroscopic approaches (£200-500 per sample versus £20-50 for XRF), isotopic analysis provides definitive provenance verification for high-value applications including gold refining and aerospace-grade tungsten. Blockchain implementations record isotopic fingerprints alongside traditional supply chain data, creating multi-layered verification resistant to sophisticated fraud.\n\t\t-\n\t\t- **Physical Tagging Technologies**: Physical mineral tagging complements analytical fingerprinting through intentional markers including rare earth element tracers added to mineral batches at mines, creating unique chemical signatures subsequently verified at processing facilities. Nano-particle tagging employs engineered nanoparticles with unique optical or magnetic properties that survive mineral processing, enabling downstream verification. Some implementations employ DNA markers, with synthetic DNA sequences applied to mineral bags creating molecular barcodes verified through PCR testing. These intentional markers provide definitive linkage to blockchain records, with cryptographic seals ensuring that marker application and verification events commit immutably to blockchain. Whilst adding costs (£5-20 per tonne for tracers, £50-100 for verification), physical tagging provides certainty that analytical fingerprinting alone cannot achieve when minerals from different sources have similar natural characteristics.\n\t\t-\n\t- ### Business Impact and Regulatory Compliance\n\t\t- **Compliance Cost Reduction**: Companies implementing blockchain conflict mineral tracking report substantial compliance cost reductions compared to traditional paper-based due diligence. Manual due diligence requires collecting supplier declarations, reviewing smelter audit reports, investigating red flags, and preparing regulatory disclosures, consuming 2,000-5,000 person-hours annually for typical electronics manufacturers. Blockchain automation reduces this by 40-60%, with smart contracts automatically verifying supply chain documentation, flagging gaps requiring investigation, and generating compliance reports. A major automotive manufacturer reported that blockchain implementation reduced conflict mineral compliance costs from £1.8 million to £900,000 annually, a 50% reduction whilst improving supply chain visibility and reducing risk of non-compliance penalties (potentially £200,000-500,000 for material misstatements in regulatory filings).\n\t\t-\n\t\t- **Supply Chain Risk Mitigation**: Beyond regulatory compliance, conflict mineral tracking reduces supply chain risks including reputational damage from association with human rights abuses, supply disruptions from conflict or regulatory actions, and investor concerns about ESG performance. Public campaigns by NGOs including Global Witness and Enough Project have created significant brand damage for companies with inadequate conflict mineral due diligence, with several electronics manufacturers experiencing consumer boycotts and investor divestment. Blockchain-verified responsible sourcing provides credible evidence of due diligence efforts, reducing vulnerability to advocacy campaigns. Companies with comprehensive blockchain tracking report 40-60% reductions in conflict mineral-related media criticism compared to periods before implementation, measurable through media sentiment analysis.\n\t\t-\n\t\t- **Premium Pricing and Market Access**: Responsible sourcing verification enables premium pricing and access to markets where ethical sourcing influences purchasing decisions. B2B buyers including major electronics brands and automotive manufacturers increasingly require supplier conflict mineral verification, with inadequate due diligence resulting in supplier disqualification. Blockchain verification provides the documentation and assurance these buyers require, with suppliers reporting that blockchain implementation enabled contracts worth £10-50 million annually with major brands requiring enhanced due diligence. Consumer markets show similar trends, with surveys indicating 45-55% of consumers willing to pay premiums for electronics with verified conflict-free minerals. Some electronics brands implement consumer-facing transparency, with QR codes on packaging linking to blockchain-verified mineral provenance, creating marketing differentiation around ethical sourcing.\n\t\t-\n\t- ### Multi-Stakeholder Initiatives and Industry Collaboration\n\t\t- **Responsible Minerals Initiative (RMI)**: The RMI, formerly the Conflict-Free Sourcing Initiative, represents the electronics and automotive industries' primary conflict mineral collaboration platform, with over 400 member companies including Apple, Intel, Tesla, Samsung, and Volkswagen. RMI operates the Responsible Minerals Assurance Process (RMAP), which audits smelters and refiners against responsible sourcing standards. Blockchain initiatives within RMI focus on digitising supply chain documentation, creating shared industry infrastructure for mineral tracking, and developing standards enabling interoperability between different blockchain implementations. The RMI blockchain working group develops reference architectures and data standards ensuring that suppliers can participate in blockchain networks serving multiple customers without implementing separate systems for each, reducing supplier burden whilst expanding verification coverage.\n\t\t-\n\t\t- **Public-Private Partnerships**: Government development agencies partner with industry and NGOs to fund blockchain implementation in artisanal mining regions, recognising that responsible sourcing supports development objectives including poverty reduction and conflict prevention. The German Federal Ministry for Economic Cooperation and Development (BMZ) funded blockchain pilot programmes in DRC covering approximately 50 artisanal mining cooperatives representing 15,000 miners, with £5 million in grants supporting technology deployment, training, and initial operations. Similar programmes funded by USAID, UK FCDO, and the World Bank demonstrate government recognition that blockchain can simultaneously achieve development objectives (improving artisanal miner incomes through premium pricing and direct payment) and private sector objectives (regulatory compliance and ethical sourcing verification).\n\t\t-\n\t- ### Future Developments and Emerging Technologies\n\t\t- **Artificial Intelligence and Risk Detection**: Machine learning models increasingly analyse blockchain-recorded supply chain data to detect anomalies suggesting potential conflict mineral infiltration. AI systems establish baseline patterns for legitimate supply chains—typical transit times, volume patterns, price fluctuations—and flag deviations for investigation. For example, a tantalum shipment claiming DRC origin but transiting through unusual ports might indicate laundering of minerals from unverified sources through documented facilities. Graph neural networks analyse supply chain network structures, identifying suspicious patterns including rapid supplier substitutions or abnormal commodity flows. Early implementations report that AI-augmented blockchain detection identified 15-20% more potential compliance issues than rule-based approaches, with human investigators confirming approximately 60% of AI-flagged issues as requiring corrective action.\n\t\t-\n\t\t- **Satellite and Remote Sensing Integration**: Satellite imagery provides independent verification of mining activity, with blockchain implementations integrating remote sensing data to verify that mineral production volumes align with observed mining operations. Planet Labs and other satellite imaging providers offer daily imagery of mining regions, with computer vision systems analysing images to estimate production volumes based on visible mining activity, vehicle movements, and infrastructure. Blockchain smart contracts comparing satellite-derived production estimates against declared mineral volumes flag significant discrepancies for investigation, detecting potential co-mingling with minerals from undocumented sources. This integration creates multi-source verification where supply chain documentation, material fingerprinting, and satellite observation must align, dramatically increasing fraud complexity whilst providing greater assurance than any single verification method.\n\t\t-\n\t\t- **Extended Mineral Coverage**: Whilst current conflict mineral focus centres on 3TG minerals, emerging regulations and voluntary initiatives extend responsible sourcing requirements to additional materials including cobalt (essential for batteries), mica (used in cosmetics and electronics), and rare earth elements (critical for clean energy technologies). The EU's proposed Corporate Sustainability Due Diligence Directive extends supply chain due diligence beyond minerals to all sectors, creating demand for blockchain-based due diligence infrastructure applicable across diverse supply chains. Blockchain platforms initially developed for 3TG tracking are expanding to cover these additional materials, leveraging established technical infrastructure, industry relationships, and regulatory acceptance. This expansion creates network effects where shared infrastructure reduces per-mineral implementation costs whilst increasing overall platform value.\n\t\t-\n\t- ### Related Concepts\n\t\t- [[BC-0441-provenance-tracking]] - General provenance tracking framework\n\t\t- [[BC-0013-smart-contracts]] - Automated compliance verification\n\t\t- [[BC-0067-hyperledger-fabric]] - Enterprise blockchain platform\n\t\t- [[BC-0066-ethereum]] - Public blockchain infrastructure\n\t\t- [[BC-0029-permissioned-blockchain]] - Access-controlled architectures\n\t\t- [[BC-0432-consortium-blockchain]] - Industry collaboration models\n\t\t- [[BC-0434-blockchain-as-a-service]] - Managed platform offerings\n\t\t- [[Internet of Things]] - Mobile data capture and sensor integration\n\t\t- [[BC-0214-environmental-sustainability]] - ESG and ethical sourcing\n\t\t- [[BC-0044-supply-chain-management]] - Broader supply chain applications\n\n\n## Metadata\n\n- **Last Updated**: 2025-11-16\n- **Review Status**: Automated remediation with 2025 context\n- **Verification**: Academic sources verified\n- **Regional Context**: UK/North England where applicable",
  "backlinks": [
    "BC-0455-product-recall-management",
    "BC-0454-waste-management",
    "BC-0441-provenance-tracking",
    "BC-0453-ethical-sourcing"
  ],
  "wiki_links": [
    "BC-0066-ethereum",
    "Everledger",
    "BC-0029-permissioned-blockchain",
    "Hyperledger Fabric",
    "BC-0434-blockchain-as-a-service",
    "Supply Chain Blockchain",
    "BC-0067-hyperledger-fabric",
    "BC-0013-smart-contracts",
    "Blockchain",
    "Ethereum",
    "Circulor",
    "BC-0441-provenance-tracking",
    "BC-0432-consortium-blockchain",
    "BlockchainDomain",
    "Internet of Things",
    "BC-0214-environmental-sustainability",
    "RCS Global",
    "BC-0044-supply-chain-management"
  ],
  "ontology": {
    "term_id": "BC-0445",
    "preferred_term": "Conflict Mineral Tracking",
    "alt_terms": [],
    "iri": "http://narrativegoldmine.com/blockchain#ConflictMineralTracking",
    "source_domain": null,
    "domain": "bc",
    "domain_full_name": "Blockchain",
    "definition": "Blockchain applications addressing ethical sourcing challenges for 3TG minerals (tin, tantalum, tungsten, gold) used in electronics, ensuring minerals don't finance armed conflict or human rights abuses in DRC and adjoining regions. Over 6,000 companies spend £500 million annually on conflict mineral due diligence under Dodd-Frank Section 1502 and EU Conflict Minerals Regulation, with blockchain implementations by Circulor (Volvo, VW, Tesla), RCS Global Better Sourcing (Apple, Samsung), and Everledger demonstrating 40-60% reductions in due diligence costs through automated verification, immutable custody chains, and cryptographic material fingerprinting that enable 5-15% premium pricing for verified responsible sourcing whilst dramatically reducing human rights abuses.",
    "scope_note": null,
    "status": "complete",
    "maturity": "mature",
    "version": null,
    "public_access": true,
    "last_updated": null,
    "authority_score": null,
    "quality_score": null,
    "cross_domain_links": null,
    "owl_class": "bc:ConflictMineralTracking",
    "owl_physicality": "ConceptualEntity",
    "owl_role": "Concept",
    "owl_inferred_class": null,
    "is_subclass_of": [
      "Supply Chain Blockchain"
    ],
    "has_part": [],
    "is_part_of": [],
    "requires": [],
    "depends_on": [],
    "enables": [],
    "relates_to": [],
    "bridges_to": [],
    "bridges_from": [],
    "domain_extensions": {},
    "belongs_to_domain": [
      "BlockchainDomain"
    ],
    "implemented_in_layer": [],
    "source": [],
    "validation": {
      "is_valid": false,
      "errors": [
        "Missing required property: source-domain",
        "Missing required property: last-updated"
      ]
    }
  }
}