{
  "id": "BC-0020-transaction-confirmation",
  "title": "Transaction Confirmation",
  "content": "- ### OntologyBlock\n  id:: transaction-confirmation-ontology\n  collapsed:: true\n\t- ontology:: true\n\t- term-id:: BC-0020\n\t- preferred-term:: Transaction Confirmation\n\t- source-domain:: bc\n\t- status:: complete\n\t- public-access:: true\n\t- definition:: Inclusion in blockchain within blockchain systems, providing essential functionality for distributed ledger technology operations and properties.\n\t- source:: [[ISO/IEC 23257:2021]], [[IEEE 2418.1]], [[NIST NISTIR]]\n\t- maturity:: mature\n\t- owl:class:: bc:TransactionConfirmation\n\t- owl:physicality:: VirtualEntity\n\t- owl:role:: Object\n\t- owl:inferred-class:: bc:VirtualObject\n\t- belongsToDomain:: [[BlockchainDomain]]\n\t- #### Relationships\n\t  id:: transaction-confirmation-relationships\n\t  collapsed:: true\n\t\t- is-subclass-of:: [[Transaction]]\n\t\t- bridges-to:: [[Distributeddatastructure]]\n\t\t- bridges-to:: [[BlockchainEntity]]",
  "backlinks": [],
  "wiki_links": [
    "BlockchainEntity",
    "NIST NISTIR",
    "BlockchainDomain",
    "IEEE 2418.1",
    "Distributeddatastructure",
    "ISO/IEC 23257:2021",
    "Transaction"
  ],
  "ontology": {
    "term_id": "BC-0020",
    "preferred_term": "Transaction Confirmation",
    "alt_terms": [],
    "iri": "http://narrativegoldmine.com/blockchain#TransactionConfirmation",
    "source_domain": "bc",
    "domain": "bc",
    "domain_full_name": "Blockchain",
    "definition": "Inclusion in blockchain within blockchain systems, providing essential functionality for distributed ledger technology operations and properties.",
    "scope_note": null,
    "status": "complete",
    "maturity": "mature",
    "version": null,
    "public_access": true,
    "last_updated": null,
    "authority_score": null,
    "quality_score": null,
    "cross_domain_links": null,
    "owl_class": "bc:TransactionConfirmation",
    "owl_physicality": "VirtualEntity",
    "owl_role": "Object",
    "owl_inferred_class": "bc:VirtualObject",
    "is_subclass_of": [
      "Transaction"
    ],
    "has_part": [],
    "is_part_of": [],
    "requires": [],
    "depends_on": [],
    "enables": [],
    "relates_to": [],
    "bridges_to": [],
    "bridges_from": [],
    "domain_extensions": {},
    "belongs_to_domain": [
      "BlockchainDomain"
    ],
    "implemented_in_layer": [],
    "source": [
      "ISO/IEC 23257:2021",
      "IEEE 2418.1",
      "NIST NISTIR"
    ],
    "other_relationships": {
      "bridges-to": [
        "Distributeddatastructure",
        "BlockchainEntity"
      ]
    },
    "validation": {
      "is_valid": false,
      "errors": [
        "Missing required property: last-updated"
      ]
    }
  }
}