{
  "id": "BC-0081-network-latency",
  "title": "Network Latency",
  "content": "- ### OntologyBlock\n  id:: network-latency-ontology\n  collapsed:: true\n\t- ontology:: true\n\t- term-id:: BC-0081\n\t- preferred-term:: Network Latency\n\t- source-domain:: bc\n\t- owl:class:: bc:NetworkLatency\n\t- status:: complete\n\t- public-access:: true\n\n\n\n\n### OWL Classification\n\t- owl:class:: bc:NetworkLatency\n\t- owl:physicality:: VirtualEntity\n\t- owl:role:: Object\n\t- owl:inferred-class:: bc:VirtualObject\n\n### Domain & Architecture\n\t- belongsToDomain:: [[CryptographicDomain]]\n\t- maturity:: mature\n\n### Relationships\nid:: relationships\n    - is-subclass-of:: [[Blockchain Network]]\n\n  - #### CrossDomainBridges\n    - bridges-to:: [[BlockchainEntity]] via is-subclass-of\n    - bridges-to:: [[Networkcomponent]] via is-subclass-of\n    - bridges-from:: [[VoiceInteraction]] via depends-on\n\n  -\n\n### Quality Metrics\n\t- authority-score:: 0.95\n\n- ### OntologyBlock\n  id:: network-latency-ontology\n  collapsed:: true\n\n  - **Identification**\n    - public-access:: true\n    - ontology:: true\n    - term-id:: BC-0081\n    - preferred-term:: Network Latency\n    - source-domain:: blockchain\n    - status:: complete\n    - version:: 1.0.0\n    - last-updated:: 2025-10-28\n\n  - **Definition**\n    - definition:: Communication delay within blockchain systems, providing essential functionality for distributed ledger technology operations and properties.\n    - maturity:: mature\n    - source:: [[ISO/IEC 23257:2021]], [[IEEE 2418.1]], [[NIST NISTIR]]\n    - authority-score:: 0.95\n\n  - **Semantic Classification**\n    - owl:class:: bc:NetworkLatency\n    - owl:physicality:: VirtualEntity\n    - owl:role:: Object\n    - owl:inferred-class:: bc:VirtualObject\n    - belongsToDomain:: [[CryptographicDomain]]\n\n  - #### OWL Restrictions\n    \n    \n\n  - #### Relationships\n    id:: relationships\n    - is-subclass-of:: [[Blockchain Network]]\n\n  - #### CrossDomainBridges\n    - bridges-to:: [[BlockchainEntity]] via is-subclass-of\n    - bridges-to:: [[Networkcomponent]] via is-subclass-of\n    - bridges-from:: [[VoiceInteraction]] via depends-on\n\n  -",
  "backlinks": [],
  "wiki_links": [
    "Blockchain Network",
    "BlockchainEntity",
    "ISO/IEC 23257:2021",
    "IEEE 2418.1",
    "CryptographicDomain",
    "Networkcomponent",
    "VoiceInteraction",
    "NIST NISTIR"
  ],
  "ontology": {
    "term_id": "BC-0081",
    "preferred_term": "Network Latency",
    "alt_terms": [],
    "iri": "http://narrativegoldmine.com/blockchain#NetworkLatency",
    "source_domain": "bc",
    "domain": "bc",
    "domain_full_name": "Blockchain",
    "definition": "Communication delay within blockchain systems, providing essential functionality for distributed ledger technology operations and properties.",
    "scope_note": null,
    "status": "complete",
    "maturity": "mature",
    "version": "1.0.0",
    "public_access": true,
    "last_updated": "2025-10-28",
    "authority_score": 0.95,
    "quality_score": null,
    "cross_domain_links": null,
    "owl_class": "bc:NetworkLatency",
    "owl_physicality": "VirtualEntity",
    "owl_role": "Object",
    "owl_inferred_class": "bc:VirtualObject",
    "is_subclass_of": [
      "Blockchain Network"
    ],
    "has_part": [],
    "is_part_of": [],
    "requires": [],
    "depends_on": [],
    "enables": [],
    "relates_to": [],
    "bridges_to": [
      "BlockchainEntity via is",
      "Networkcomponent via is",
      "BlockchainEntity via is",
      "Networkcomponent via is"
    ],
    "bridges_from": [
      "VoiceInteraction via depends",
      "VoiceInteraction via depends"
    ],
    "domain_extensions": {},
    "belongs_to_domain": [
      "CryptographicDomain",
      "CryptographicDomain"
    ],
    "implemented_in_layer": [],
    "source": [
      "ISO/IEC 23257:2021",
      "IEEE 2418.1",
      "NIST NISTIR"
    ],
    "validation": {
      "is_valid": true,
      "errors": []
    }
  }
}