{
  "id": "BC-0468-multi-sig-governance",
  "title": "Multi Sig Governance",
  "content": "- ### OntologyBlock\n  id:: bc-0468-multi-sig-governance-ontology\n  collapsed:: true\n\t- ontology:: true\n\t- term-id:: BC-0468\n\t- preferred-term:: Multi Sig Governance\n\t- status:: stub\n\t- public-access:: true\n\t- definition:: A component of the blockchain ecosystem.\n\t- maturity:: draft\n\t- owl:class:: bc:MultiSigGovernance\n\t- owl:physicality:: ConceptualEntity\n\t- owl:role:: Concept\n\t- belongsToDomain:: [[BlockchainDomain]]\n\t- #### Relationships\n\t  id:: bc-0468-multi-sig-governance-relationships\n\t  collapsed:: true\n\t\t- is-subclass-of:: [[Decentralized Autonomous Organization]]\n\n## OWL Formal Semantics\n\n```clojure\n;; OWL Functional Syntax\n\n(Declaration (Class :MultiSigGovernance))\n\n;; Annotations\n(AnnotationAssertion rdfs:label :MultiSigGovernance \"Multi Sig Governance\"@en)\n(AnnotationAssertion rdfs:comment :MultiSigGovernance \"A component of the blockchain ecosystem.\"@en)\n\n;; Data Properties\n(AnnotationAssertion dcterms:identifier :MultiSigGovernance \"BC-0468\"^^xsd:string)\n```\n\n- ## About Multi-Sig Governance\n  id:: multi-sig-governance-about\n\t-\n\t- Multi-signature (multi-sig) governance represents the most widely deployed security mechanism for managing digital assets and executing high-stakes decisions in blockchain ecosystems. Unlike single-key control where one private key holder has absolute power, multi-sig requires m-of-n signatures from a designated group of keyholders before transactions can be executed. This creates a threshold signature scheme where, for example, any 3 of 5 designated signers must approve before funds can move or critical protocol changes can be implemented. The mechanism borrows from traditional banking's dual control principles whilst leveraging cryptography for enforcement—there is no central authority that can override the signature requirement; the mathematics ensures that insufficient signatures simply cannot execute transactions. Multi-sig has become the de facto security standard for [[BC-0461-decentralized-autonomous-organization]] treasuries, with [[Gnosis Safe]] (now Safe) managing over 50% of all DAO treasury funds, representing tens of billions in total value locked.\n\t-\n\t- The fundamental security advantage lies in eliminating single points of failure. If one key is compromised through phishing, malware, or coercion, the attacker cannot unilaterally drain funds. This has proven invaluable in an ecosystem plagued by key compromise incidents—multi-sig wallets have prevented countless thefts that would have succeeded against single-signature accounts. Major organisations like the Ethereum Foundation, Gitcoin (operating a 9-of-15 multi-sig treasury), ENS DAO, and Uniswap rely on multi-sig for treasury management and emergency protocol controls. The mechanism also serves as a practical governance compromise: more efficient than full token-weighted voting for operational decisions, more decentralised than single-administrator control, and more responsive than time-locked mechanisms for emergency interventions. However, multi-sig governance faces legitimate criticisms around centralisation—concentrating power in small committees (often 3-7 individuals) contradicts blockchain's decentralisation ethos, and the identities of signers may not be publicly known, creating opacity. Key management also presents operational challenges: signers must securely store keys (often using hardware wallets like Ledger or Trezor), remain available for time-sensitive decisions, and avoid collusion whilst maintaining sufficient communication to coordinate. The trade-off between security, efficiency, and decentralisation makes multi-sig an enduring but often temporary governance solution, with many DAOs using it for operational execution whilst reserving strategic decisions for broader token holder voting via [[BC-0462-on-chain-voting]] or [[BC-0469-snapshot-voting]].\n\t-\n\t- ### Mathematical Foundation\n\t  collapsed:: true\n\t\t- Multi-signature schemes rest on threshold cryptography, where a signature is valid only if at least m of n designated public keys sign a transaction. The most common implementation uses Script (Bitcoin) or smart contract verification (Ethereum) rather than cryptographic signature aggregation.\n\t\t-\n\t\t- **Threshold Signature Scheme**: An m-of-n multi-sig has:\n\t\t- - `n` = total number of authorised signers\n\t\t- - `m` = minimum signatures required (threshold)\n\t\t- - Constraint: `1 ≤ m ≤ n`\n\t\t-\n\t\t- **Security Properties**:\n\t\t- - **Completeness**: If m or more honest signers approve, the transaction executes\n\t\t- - **Soundness**: Fewer than m signatures cannot execute the transaction\n\t\t- - **Unforgeability**: Non-signers cannot create valid signatures\n\t\t-\n\t\t- Common configurations by risk tolerance:\n\t\t- - **2-of-3**: Standard for small teams; single point of failure if one key lost, but resistant to single key compromise\n\t\t- - **3-of-5**: Balanced security; can tolerate loss of 2 keys or compromise of 2 keys\n\t\t- - **5-of-9**: High security councils; used by protocol governance for emergency functions\n\t\t- - **m-of-m**: Maximum security but operationally fragile (any single key loss freezes funds)\n\t\t-\n\t\t- **Attack Resistance**: The attacker must compromise m keys. If keys are independently secured:\n\t\t- - **Single key compromise**: No control (unless m=1)\n\t\t- - **m-1 keys compromised**: Still no control\n\t\t- - **m keys compromised**: Full control achieved\n\t\t-\n\t\t- The probability of successful attack assuming independent key compromise probability p:\n\t\t-\n\t\t- `P(attack_success) = Σ(k=m to n) C(n,k) × p^k × (1-p)^(n-k)`\n\t\t-\n\t\t- For example, with p = 0.1 (10% chance any individual key is compromised) in a 3-of-5 scheme:\n\t\t-\n\t\t- `P(attack) = C(5,3)×0.1³×0.9² + C(5,4)×0.1⁴×0.9 + C(5,5)×0.1⁵ ≈ 0.0086` (0.86%)\n\t\t-\n\t\t- Compare to single signature: `P(attack) = 0.1` (10%)\n\t\t-\n\t\t- **Byzantine Fault Tolerance**: Multi-sig provides Byzantine fault tolerance up to n-m failures. With 3-of-5, the system tolerates 2 Byzantine (malicious or offline) signers.\n\t\t-\n\t\t- **Signer Selection Game Theory**: Rational signers may free-ride, assuming others will monitor and sign. This creates coordination failures. Solutions include:\n\t\t- - Rotating signer responsibilities\n\t\t- - Requiring explanations for signature refusals\n\t\t- - Reputation systems tracking signing reliability\n\t\t-\n\t- ### Technical Implementation\n\t  collapsed:: true\n\t\t- Multi-sig implementations vary significantly across blockchains, from native Script support in Bitcoin to smart contract-based solutions in Ethereum and other EVM chains.\n\t\t-\n\t\t- **Bitcoin Native Multi-Sig (P2SH)**:\n\t\t- Bitcoin supports multi-sig through Pay-to-Script-Hash, where the redeem script specifies the m-of-n scheme:\n\t\t- ```\n\t\t- OP_2                  # m = 2 required signatures\n\t\t- <pubkey1>\n\t\t- <pubkey2>\n\t\t- <pubkey3>\n\t\t- OP_3                  # n = 3 total signers\n\t\t- OP_CHECKMULTISIG\n\t\t- ```\n\t\t- To spend, signers provide signatures in the scriptSig. Bitcoin nodes verify that at least 2 of the 3 public keys signed the transaction.\n\t\t-\n\t\t- **Ethereum Smart Contract Multi-Sig (Gnosis Safe)**:\n\t\t- Safe implements multi-sig through a smart contract wallet that validates signatures before executing transactions:\n\t\t-\n\t\t- ```solidity\n\t\t- contract GnosisSafe {\n\t\t-     address[] public owners;\n\t\t-     uint256 public threshold;  // m in m-of-n\n\t\t-     mapping(bytes32 => bool) public approvedHashes;\n\t\t-\n\t\t-     function execTransaction(\n\t\t-         address to,\n\t\t-         uint256 value,\n\t\t-         bytes calldata data,\n\t\t-         bytes calldata signatures\n\t\t-     ) external returns (bool success) {\n\t\t-         bytes32 txHash = keccak256(abi.encode(to, value, data, nonce++));\n\t\t-\n\t\t-         // Verify threshold signatures\n\t\t-         address[] memory signers = extractSigners(txHash, signatures);\n\t\t-         require(signers.length >= threshold, \"Insufficient signatures\");\n\t\t-\n\t\t-         // Verify all signers are owners\n\t\t-         for (uint i = 0; i < signers.length; i++) {\n\t\t-             require(isOwner[signers[i]], \"Invalid signer\");\n\t\t-         }\n\t\t-\n\t\t-         // Execute transaction\n\t\t-         (success, ) = to.call{value: value}(data);\n\t\t-         require(success, \"Transaction failed\");\n\t\t-     }\n\t\t-\n\t\t-     function extractSigners(\n\t\t-         bytes32 txHash,\n\t\t-         bytes memory signatures\n\t\t-     ) internal pure returns (address[] memory) {\n\t\t-         // Split signatures into r,s,v components\n\t\t-         // Recover addresses using ecrecover\n\t\t-         // Return array of signer addresses\n\t\t-     }\n\t\t- }\n\t\t- ```\n\t\t-\n\t\t- **EIP-1271 Contract Signature Validation**:\n\t\t- Safe implements EIP-1271, allowing the contract itself to validate signatures for interactions with DeFi protocols:\n\t\t- ```solidity\n\t\t- function isValidSignature(\n\t\t-     bytes32 hash,\n\t\t-     bytes memory signature\n\t\t- ) external view returns (bytes4 magicValue) {\n\t\t-     if (checkSignatures(hash, signature, threshold)) {\n\t\t-         return 0x1626ba7e;  // EIP-1271 magic value\n\t\t-     }\n\t\t-     return 0xffffffff;\n\t\t- }\n\t\t- ```\n\t\t-\n\t\t- **Hardware Wallet Integration**:\n\t\t- Production multi-sigs integrate with hardware wallets for key security:\n\t\t- - **Ledger**: Secure element stores private keys, requires physical button press to sign\n\t\t- - **Trezor**: Open-source hardware wallet with PIN protection\n\t\t- - **Lattice**: Grid+ hardware wallet supporting multi-chain\n\t\t-\n\t\t- Signers connect hardware wallets to Safe interface, review transaction details on device screen, and approve with physical confirmation. This prevents malware on the host computer from stealing keys or creating unauthorised signatures.\n\t\t-\n\t\t- **Transaction Batching**:\n\t\t- Safe allows batching multiple operations into a single transaction requiring one round of signatures:\n\t\t- ```javascript\n\t\t- const transactions = [\n\t\t-     { to: tokenContract, data: transfer(addr1, 1000) },\n\t\t-     { to: tokenContract, data: transfer(addr2, 2000) },\n\t\t-     { to: governanceContract, data: vote(proposalId, true) }\n\t\t- ];\n\t\t-\n\t\t- const batchedTx = safeSDK.createBatchTransaction(transactions);\n\t\t- await safeSDK.executeBatchTransaction(batchedTx, signatures);\n\t\t- ```\n\t\t-\n\t\t- **Gas Optimisations**:\n\t\t- - **Signature aggregation**: BLS signatures can aggregate m signatures into one, reducing calldata costs\n\t\t- - **Off-chain coordination**: Signers approve transaction hash off-chain via Snapshot or forum, then single party submits with collected signatures\n\t\t- - **Meta-transactions**: Use relayers to pay gas, reimbursing from Safe balance\n\t\t-\n\t\t- **Cross-Chain Multi-Sig**:\n\t\t- Protocols like [[Axelar]] and [[Wormhole]] use multi-sig validators for cross-chain messaging, where signers operate on multiple chains with consistent thresholds.\n\t\t-\n\t- ### Real-World Implementations\n\t  collapsed:: true\n\t\t- **Gnosis Safe / Safe (2018-present)**:\n\t\t- Safe is the dominant multi-sig platform, managing over $40 billion in assets across 15+ chains. As of 2024, over 100,000 Safe instances have been deployed, with roughly 50% of DAO treasuries using Safe for asset custody. The platform processes thousands of transactions daily, ranging from routine payroll to emergency protocol upgrades. Safe's architecture has proven remarkably resilient—no funds have been lost due to smart contract vulnerabilities in the core Safe contracts since launch, though user errors (key loss, wrong transaction parameters) have caused issues. The interface has evolved to support complex workflows: transaction simulation before signing, spending limits for individual owners, role-based modules, and integration with 200+ DeFi protocols via Safe Apps (embedded dApps in the Safe interface).\n\t\t-\n\t\t- **Gitcoin Multi-Sig (2021-present)**:\n\t\t- Gitcoin operates one of the most transparent and well-documented multi-sig treasuries in the ecosystem. Their 9-of-15 Safe holds over $25 million in GTC and stablecoins, funding public goods grants and operational expenses. The 15 signers include Gitcoin core team members, ecosystem contributors, and independent community representatives, with identities publicly known. Operational procedures are formalised: proposals must pass Snapshot votes before execution, multi-sig only validates that executed transactions match approved proposals, signatures required within 7 days of Snapshot conclusion, and all transactions published with explanations on Gitcoin governance forum. In 2022, when a grant proposal passed Snapshot but was later discovered to violate community guidelines, the multi-sig signers refused execution, demonstrating that multi-sig provides a constitutional cheque on token voting. However, this also sparked debate about whether unelected signers should override token holder decisions.\n\t\t-\n\t\t- **ENS DAO Multi-Sig Transition (2021-2022)**:\n\t\t- The Ethereum Name Service operated under a 4-of-7 multi-sig controlled by core team and community members from 2017-2021, managing the .eth registrar and $50+ million in registration fees. In 2021, ENS transitioned to a full DAO with token-based governance, but retained a multi-sig for execution. The new model uses a 3-of-4 multi-sig (\"ENS DAO wallet\") that executes only transactions approved by token voting via Governor contract. This hybrid approach proved valuable in March 2022 when a time-sensitive security upgrade needed deployment—token voting took 48 hours to pass (unusually fast), then multi-sig executed within 6 hours. Pure on-chain execution via Timelock would have added 2-day delay, creating extended vulnerability.\n\t\t-\n\t\t- **Ethereum Foundation (2015-present)**:\n\t\t- The Ethereum Foundation manages ~$1 billion in assets (primarily ETH) across multiple multi-sig wallets with varying thresholds. Their treasury management uses tiered multi-sigs:\n\t\t- - **Cold storage**: 5-of-8 for long-term ETH holdings (>90% of assets)\n\t\t- - **Operational**: 3-of-5 for grant distributions and operating expenses\n\t\t- - **Emergency**: 4-of-6 with specialised signers for crisis response\n\t\t- Signer identities are semi-public (known to regulators, not fully public). In 2021, they executed a $300 million+ sale of ETH through multi-sig-coordinated OTC transactions, demonstrating the mechanism's capability for major financial operations.\n\t\t-\n\t\t- **Optimism Security Council (2023-present)**:\n\t\t- Optimism's Security Council is a 10-member multi-sig with 9-of-10 threshold that can bypass governance delays in emergencies. The council can pause the system, upgrade contracts, or intervene in critical bugs without waiting for token voting. Members include protocol developers, security researchers, and ecosystem contributors. In June 2023, when a potential vulnerability was disclosed, the Security Council coordinated across 7 time zones to gather 9 signatures within 18 hours and deploy a patch, preventing potential $200+ million in exploits. This demonstrated multi-sig's value for emergency response whilst raising centralisation concerns—10 individuals could theoretically steal all bridged assets.\n\t\t-\n\t- ### Advantages and Benefits\n\t  collapsed:: true\n\t\t- **Elimination of Single Points of Failure**: No individual can unilaterally compromise funds or execute malicious transactions. This has prevented countless thefts in an ecosystem where phishing and malware are rampant.\n\t\t-\n\t\t- **Operational Efficiency**: Multi-sig decisions can be made in hours or days, compared to weeks for token voting via [[BC-0462-on-chain-voting]]. For routine operations (payroll, grant disbursements, contract deployments), this efficiency is invaluable.\n\t\t-\n\t\t- **Flexibility and Recoverability**: If a signer loses their key, the remaining n-1 signers can create a new multi-sig and migrate assets, then add a replacement signer. This graceful degradation is impossible with single-key wallets (key loss = permanent fund loss).\n\t\t-\n\t\t- **Emergency Response Capability**: Critical security incidents require rapid response. Multi-sig signers can coordinate urgently to pause systems, upgrade vulnerable contracts, or rescue funds. Token voting or time-locks add delays that attackers can exploit.\n\t\t-\n\t\t- **Trust Minimisation Through Transparency**: Public multi-sig addresses allow anyone to verify that signers are executing only authorised transactions. Platforms like Etherscan show full transaction history, creating accountability.\n\t\t-\n\t\t- **Battle-Tested Security**: Multi-sig contracts, especially Safe, have undergone extensive audits and years of production use. The attack surface is well-understood and far smaller than complex governance mechanisms.\n\t\t-\n\t\t- **Hardware Wallet Integration**: Signers can use hardware wallets, providing strong key security even if their computers are compromised. This combines cryptographic security with physical access requirements.\n\t\t-\n\t\t- **Compatibility with Legal Structures**: Multi-sig maps well to traditional corporate governance. In [[BC-0470-dao-legal-structures]] like Wyoming DAO LLCs, multi-sig signers can be designated as managers with legal authority, creating clear liability and decision-making structures.\n\t\t-\n\t- ### Limitations and Challenges\n\t  collapsed:: true\n\t\t- **Centralisation and Trust Assumptions**: Multi-sig concentrates power in small groups, contradicting blockchain's decentralisation goals. If signers collude, they have absolute control. Even with honest signers, this creates an aristocratic governance model rather than a democratic one.\n\t\t-\n\t\t- **Opacity and Accountability**: Signer identities are often pseudonymous or private, making it difficult to hold individuals accountable. When multi-sig decisions contradict community wishes, there may be no recourse. The Gitcoin example where signers overrode a Snapshot vote illustrates this tension.\n\t\t-\n\t\t- **Operational Complexity**: Coordinating m signatures across potentially global, asynchronous signers creates friction. Time-sensitive decisions may be delayed if signers are unavailable, sleeping, or travelling. Some DAOs have experienced 24-48 hour delays waiting for the final signature.\n\t\t-\n\t\t- **Key Management Burden**: Signers must maintain excellent operational security—securely storing hardware wallets, avoiding phishing, protecting recovery phrases. This expertise isn't universal; key compromise or loss events occur regularly.\n\t\t-\n\t\t- **$5 Wrench Attack Vulnerability**: Physical coercion is a real threat. If attackers can identify and physically threaten m signers, they can extract signatures. This is more feasible than attacking cryptographic primitives. High-value multi-sigs face this risk.\n\t\t-\n\t\t- **Signer Collusion Risk**: m signers could collude to steal funds or execute harmful transactions. Preventing collusion requires careful signer selection, ideally choosing parties with misaligned incentives or geographical/organisational separation. However, assessing collusion risk is difficult.\n\t\t-\n\t\t- **No Recourse for Unauthorised Transactions**: Once m signers approve a transaction, it's final. If they all make a mistake or are tricked by a sophisticated phishing attack, funds are irreversibly lost. There's no admin override or recovery mechanism.\n\t\t-\n\t\t- **Scaling Limitations**: As n grows, coordination difficulty increases non-linearly. Multi-sigs with >15 signers are rare because gathering signatures becomes prohibitive. This caps the level of decentralisation achievable.\n\t\t-\n\t\t- **Legal and Regulatory Ambiguity**: Who is legally liable if a multi-sig executes an illegal transaction? All m signers? Only those who signed? The entity they represent? Case law is undeveloped, creating uncertainty.\n\t\t-\n\t- ### Comparison with Alternatives\n\t  collapsed:: true\n\t\t- **vs. [[BC-0462-on-chain-voting]]**: Token-weighted voting provides broad participation (potentially thousands of voters) but is slow (3-7 day voting periods plus time-locks) and vulnerable to low turnout. Multi-sig is fast (hours to days) and guaranteed execution if m signers agree, but centralised. Many DAOs use hybrid models: token voting for strategic decisions, multi-sig for operational execution. This balances legitimacy with efficiency.\n\t\t-\n\t\t- **vs. [[BC-0469-snapshot-voting]]**: Snapshot enables gasless off-chain voting with flexible strategies, ideal for signalling preferences. However, Snapshot results are not self-executing—someone must execute on-chain. Multi-sigs commonly serve this execution role, validating that on-chain transactions match Snapshot outcomes. Safe has built-in Snapshot integration (SafeSnap module) for this workflow.\n\t\t-\n\t\t- **vs. [[BC-0466-quadratic-voting]]**: Quadratic voting measures preference intensity but requires complex identity verification and discrete voting rounds. Multi-sig has no identity requirements (signers are designated) and operates continuously. However, multi-sig cannot express nuanced preferences—it's binary approve/reject. Some DAOs use quadratic voting for resource allocation decisions, then multi-sig executes the approved allocations.\n\t\t-\n\t\t- **vs. [[BC-0467-conviction-voting]]**: Conviction voting allows continuous funding decisions without quorums, good for treasury management. However, it's gas-intensive and complex. Multi-sig is simpler and cheaper for discrete transactions. A hybrid might use conviction voting to build community consensus, then multi-sig to execute top-conviction proposals on a schedule.\n\t\t-\n\t\t- **vs. Timelock Contracts**: Timelocks enforce mandatory delays (e.g., 48 hours) between proposal and execution, allowing communities to react. Multi-sigs can execute immediately. Many protocols use both: multi-sig must approve, then transaction enters timelock before execution. This combines multi-sig's coordination with timelock's safety buffer.\n\t\t-\n\t\t- **vs. Single Administrator**: Compared to single-key control (e.g., deployer address with admin privileges), multi-sig dramatically improves security and reduces trust assumptions. However, it's operationally heavier. Early-stage projects often start with single admin for speed, then migrate to multi-sig, then eventually to full DAO governance as they mature.\n\t\t-\n\t\t- **Trade-offs Summary**:\n\t\t- - **Speed**: Multi-sig > Timelock > Token voting > Conviction > Quadratic\n\t\t- - **Decentralisation**: Quadratic ≈ Token voting > Conviction > Snapshot > Multi-sig > Single admin\n\t\t- - **Security (vs key compromise)**: Multi-sig > Single admin (vastly superior)\n\t\t- - **Security (vs signer collusion)**: Token voting > Conviction > Quadratic > Multi-sig\n\t\t- - **Operational simplicity**: Single admin > Multi-sig > Timelock > Token voting > Conviction > Quadratic\n\t\t- - **Emergency responsiveness**: Multi-sig > Single admin > Timelock > Token voting > Conviction\n\t\t-\n\t- ### Legal and Regulatory Aspects\n\t  collapsed:: true\n\t\t- **Legal Personality and Liability**: Multi-sig governance raises questions about who is legally responsible for decisions. In traditional corporations, directors owe fiduciary duties and can be held liable. Are multi-sig signers analogous to directors? If the multi-sig executes a transaction that violates securities laws, are all signers liable, or only those who signed? US law has not directly addressed this, but analogies to corporate governance suggest signers acting in governance capacity may incur fiduciary duties to token holders or DAO members.\n\t\t-\n\t\t- **Fiduciary Duties in [[BC-0470-dao-legal-structures]]**: Wyoming's DAO LLC statute allows \"algorithmically managed\" DAOs but also permits member-managed or manager-managed structures. Multi-sig signers designated as managers likely owe fiduciary duties of care and loyalty. This means they must act in the DAO's best interest, avoid conflicts of interest, and exercise reasonable diligence. Violating these duties could create personal liability. Vermont's BBLLC statute has similar implications.\n\t\t-\n\t\t- **Multi-Sig as a Security Control**: For DAOs holding user funds or operating as investment vehicles, regulators may view multi-sig as a required security control. The SEC has emphasised custody and safeguarding of assets in crypto enforcement actions. A DAO using single-key control might face heightened scrutiny compared to one using multi-sig with independent, reputable signers.\n\t\t-\n\t\t- **Sanctions Compliance and OFAC**: Multi-sig signers must ensure they don't facilitate transactions with sanctioned addresses. In 2022, Tornado Cash sanctions created dilemmas for multi-sigs: should they block sanctioned addresses from interacting with contracts they control? Can they be held liable for failing to do so? Some multi-sigs have implemented screening, but this creates centralisation and censorship concerns.\n\t\t-\n\t\t- **Tax Implications**: If a multi-sig controls a treasury generating yield (staking, DeFi), who owes taxes? The DAO as an entity (if legally formed), the multi-sig signers jointly, or individual token holders? In jurisdictions without clear DAO legal status, signers could be deemed a general partnership, making each signer jointly and severally liable for all tax obligations—a frightening prospect.\n\t\t-\n\t\t- **Jurisdictional Challenges**: Multi-sig signers are often distributed globally. If a dispute arises, which jurisdiction's law applies? If 3 signers are in the US, 2 in Europe, and 4 in Asia, and they execute a transaction that violates US law, can US authorities prosecute? The borderless nature of crypto creates novel jurisdictional questions.\n\t\t-\n\t\t- **Contractual Authority**: For DAOs wrapped in legal entities, corporate documents must specify multi-sig signers' authority. Are they authorised to execute any transaction, or only specific categories? Do they need board approval for expenditures above thresholds? Failure to align multi-sig permissions with legal authority can create ultra vires issues where signers exceed their legal authority.\n\t\t-\n\t- ### Best Practices\n\t  collapsed:: true\n\t\t- **Signer Selection Criteria**:\n\t\t- - **Geographic diversity**: Distribute signers across jurisdictions to reduce single-jurisdiction risk\n\t\t- - **Organisational diversity**: Mix core team, investors, community members, and independent experts\n\t\t- - **Skill diversity**: Include technical, legal, financial, and domain-specific expertise\n\t\t- - **Misaligned incentives**: Choose signers unlikely to collude (e.g., competitors, ideologically diverse)\n\t\t- - **Reputation**: Prefer individuals with established track records and reputational stakes\n\t\t- - **Availability**: Ensure signers can respond within required timeframes (document timezone coverage)\n\t\t-\n\t\t- **Threshold Selection**:\n\t\t- - **Small team (3-5 signers)**: Use 2-of-3 or 3-of-5 for balance of security and availability\n\t\t- - **Medium council (7-11 signers)**: Use (n/2)+2 threshold (e.g., 6-of-11, 5-of-9) to require majority plus buffer\n\t\t- - **Large council (>11 signers)**: Use 60-70% thresholds (e.g., 9-of-15, 10-of-15) for resilience\n\t\t- - **Emergency councils**: Consider supermajority (80-90%) for powerful emergency functions\n\t\t-\n\t\t- **Operational Security**:\n\t\t- - **Hardware wallets mandatory**: All signers use Ledger, Trezor, or equivalent—no software wallets\n\t\t- - **Secure communication**: Use encrypted channels (Signal, Wire) for coordination, never public Discord\n\t\t- - **Transaction simulation**: Always simulate transactions on Tenderly or similar before signing\n\t\t- - **Multi-device verification**: Cheque transaction details on hardware wallet screen AND separate device\n\t\t- - **Timelocks for large transactions**: Add 24-48h timelock after multi-sig approval for community review\n\t\t-\n\t\t- **Governance Integration**:\n\t\t- - **Document scope clearly**: Specify which decisions require multi-sig vs token voting vs other mechanisms\n\t\t- - **Snapshot integration**: Use SafeSnap to enforce that multi-sig executes only Snapshot-approved transactions\n\t\t- - **Public transparency**: Publish multi-sig address, explain all transactions in forum/blog posts\n\t\t- - **Regular audits**: Third-party verification that multi-sig only executed authorised transactions\n\t\t-\n\t\t- **Key Management**:\n\t\t- - **Geographic distribution of hardware wallets**: Store devices in different physical locations\n\t\t- - **Secure backup procedures**: Metal seed phrase backups in bank vaults or safety deposit boxes\n\t\t- - **Succession planning**: Document procedures for replacing compromised, lost, or inactive signers\n\t\t- - **Regular signer rotation**: Refresh 1-2 signers annually to prevent stagnation and key compromise\n\t\t-\n\t\t- **Legal Alignment**:\n\t\t- - **Formalise signer roles**: If DAO has legal entity, ensure signers are properly appointed as managers/directors\n\t\t- - **Indemnification agreements**: DAO indemnifies signers for good-faith decisions\n\t\t- - **D&O insurance**: Directors and Officers insurance for legal defence costs\n\t\t- - **Clear operating procedures**: Written policies on signer duties, voting requirements, conflict resolution\n\t\t-\n\t- ### Future Developments\n\t  collapsed:: true\n\t\t- **Threshold Signature Schemes (TSS)**: Cryptographic TSS (like FROST, GG20) enable true threshold signatures where m signers cooperatively generate a single signature indistinguishable from a regular signature. This improves privacy (observers can't see how many signers approved) and efficiency (constant signature size regardless of m/n). Projects like ZenGo and Fireblocks are commercialising TSS for custody.\n\t\t-\n\t\t- **Social Recovery and Progressive Decentralisation**: Safe has proposed \"Social Recovery\" modules where signers can designate trusted contacts (family, friends, colleagues) who can collaboratively recover access if keys are lost. This could evolve into progressive multi-sig where threshold automatically increases as treasury value grows, or decreases during emergencies.\n\t\t-\n\t\t- **AI-Assisted Transaction Review**: As transaction complexity increases, signers struggle to verify correctness. AI tools could analyse transactions, simulate outcomes, cheque against policies, and flag anomalies—enhancing signer due diligence without replacing human judgement.\n\t\t-\n\t\t- **Cross-Chain Multi-Sig Coordination**: Future multi-sigs may control assets across multiple chains with unified signing. Instead of separate multi-sigs per chain, a single signer set could approve cross-chain operations via interoperability protocols like [[Axelar]] or [[LayerZero]], reducing operational overhead.\n\t\t-\n\t\t- **Compliance Modules**: Regulatory pressure may drive development of multi-sig modules that enforce compliance—automatically screening transactions against OFAC lists, requiring additional approvals for large transfers, or generating audit trails for regulators. Safe's module system is well-positioned for this.\n\t\t-\n\t\t- **Hybrid On-Chain/Off-Chain Governance**: Multi-sigs could integrate more tightly with off-chain governance via [[BC-0469-snapshot-voting]]. Imagine automated execution where if a Snapshot vote reaches 60% yes with 10% quorum, multi-sig can execute without individual signer review—reducing coordination overhead whilst maintaining security backstop.\n\t\t-\n\t\t- **Decentralisation Metrics and Reputation**: Tools that measure multi-sig decentralisation (Gini coefficients of signer power, geographic distribution, organisational independence) could emerge, helping communities assess governance quality. Reputation systems tracking signer responsiveness and decision quality could inform signer selection.\n\t\t-\n\t- #\n\n\n## Metadata\n\n- **Last Updated**: 2025-11-16\n- **Review Status**: Automated remediation with 2025 context\n- **Verification**: Academic sources verified\n- **Regional Context**: UK/North England where applicable\n\n## References and Research\n\t  collapsed:: true\n\t\t- **Foundational Technology**:\n\t\t- - Gnosis. (2020). \"Safe (formerly Gnosis Safe): Smart Contract Wallet for Ethereum.\" safe.global\n\t\t- - Maxwell, G. (2013). \"Bitcoin Multi-Signature Wallets.\" Bitcoin Wiki.\n\t\t- - Goldfeder, S., et al. (2018). \"Securing Bitcoin Wallets via Threshold Signatures.\" *IEEE Security & Privacy*.\n\t\t-\n\t\t- **Governance Case Studies**:\n\t\t- - Gitcoin DAO. (2021-2024). \"Multi-Sig Governance Documentation.\" gov.gitcoin.co\n\t\t- - Ethereum Name Service. (2022). \"ENS DAO Multi-Sig Transition Report.\" discuss.ens.domains\n\t\t- - Optimism Collective. (2023). \"Security Council Operations Manual.\" community.optimism.io\n\t\t-\n\t\t- **Security Analysis**:\n\t\t- - ConsenSys Diligence. (2020). \"Gnosis Safe Audit Reports.\" consensys.net/diligence\n\t\t- - Perez, D., & Livshits, B. (2021). \"Smart Contract Vulnerabilities: Vulnerable Does Not Imply Exploited.\" *USENIX Security*.\n\t\t-\n\t\t- **Threshold Cryptography**:\n\t\t- - Gennaro, R., & Goldfeder, S. (2020). \"One Round Threshold ECDSA with Identifiable Abort.\" *IACR Cryptology ePrint Archive*.\n\t\t- - Komlo, C., & Goldberg, I. (2020). \"FROST: Flexible Round-Optimised Schnorr Threshold Signatures.\" *SAC 2020*.\n\t\t-\n\t\t- **Related Mechanisms**:\n\t\t- - [[BC-0461-decentralized-autonomous-organization]] - DAO governance frameworks\n\t\t- - [[BC-0462-on-chain-voting]] - Token-weighted voting mechanisms\n\t\t- - [[BC-0469-snapshot-voting]] - Off-chain voting infrastructure\n\t\t- - [[BC-0470-dao-legal-structures]] - Legal frameworks for DAOs\n\t\t- - [[Gnosis Safe]] - Dominant multi-sig platform\n\t\t- - [[Hardware Security]] - Hardware wallet key management\n\t\t- - [[Threshold Cryptography]] - Mathematical foundations\n\t\t- - [[Byzantine Fault Tolerance]] - Distributed systems theory\n\t\t-\n\t- ### Original Content\n\t  collapsed:: true\n\t\t- ```\n\n\t\t  ```",
  "backlinks": [
    "BC-0467-conviction-voting",
    "BC-0466-quadratic-voting"
  ],
  "wiki_links": [
    "BC-0469-snapshot-voting",
    "BC-0461-decentralized-autonomous-organization",
    "BC-0466-quadratic-voting",
    "Byzantine Fault Tolerance",
    "BlockchainDomain",
    "Gnosis Safe",
    "Wormhole",
    "Axelar",
    "BC-0470-dao-legal-structures",
    "Threshold Cryptography",
    "BC-0467-conviction-voting",
    "Hardware Security",
    "Decentralized Autonomous Organization",
    "LayerZero",
    "BC-0462-on-chain-voting"
  ],
  "ontology": {
    "term_id": "BC-0468",
    "preferred_term": "Multi Sig Governance",
    "alt_terms": [],
    "iri": "http://narrativegoldmine.com/blockchain#MultiSigGovernance",
    "source_domain": null,
    "domain": "bc",
    "domain_full_name": "Blockchain",
    "definition": "A component of the blockchain ecosystem.",
    "scope_note": null,
    "status": "stub",
    "maturity": "draft",
    "version": null,
    "public_access": true,
    "last_updated": null,
    "authority_score": null,
    "quality_score": null,
    "cross_domain_links": null,
    "owl_class": "bc:MultiSigGovernance",
    "owl_physicality": "ConceptualEntity",
    "owl_role": "Concept",
    "owl_inferred_class": null,
    "is_subclass_of": [
      "Decentralized Autonomous Organization"
    ],
    "has_part": [],
    "is_part_of": [],
    "requires": [],
    "depends_on": [],
    "enables": [],
    "relates_to": [],
    "bridges_to": [],
    "bridges_from": [],
    "domain_extensions": {},
    "belongs_to_domain": [
      "BlockchainDomain"
    ],
    "implemented_in_layer": [],
    "source": [],
    "validation": {
      "is_valid": false,
      "errors": [
        "Missing required property: source-domain",
        "Missing required property: last-updated"
      ]
    }
  }
}