{
  "id": "BC-0099-native-token",
  "title": "Native Token",
  "content": "- ### OntologyBlock\n  id:: native-token-ontology\n  collapsed:: true\n\n  - **Identification**\n    - public-access:: true\n    - ontology:: true\n    - term-id:: BC-0099\n    - preferred-term:: Native Token\n    - source-domain:: blockchain\n    - status:: complete\n    - version:: 1.0.0\n    - last-updated:: 2025-10-28\n\n  - **Definition**\n    - definition:: Blockchain-native cryptocurrency within blockchain systems, providing essential functionality for distributed ledger technology operations and properties.\n    - maturity:: mature\n    - source:: [[ISO/IEC 23257:2021]], [[IEEE 2418.1]], [[NIST NISTIR]]\n    - authority-score:: 0.95\n\n  - **Semantic Classification**\n    - owl:class:: bc:NativeToken\n    - owl:physicality:: VirtualEntity\n    - owl:role:: Object\n    - owl:inferred-class:: bc:VirtualObject\n    - belongsToDomain:: [[TokenEconomicsDomain]]\n\n  - #### OWL Restrictions\n    \n    \n\n  - #### Relationships\n    id:: relationships\n    - is-subclass-of:: [[Token]]\n\n  - #### CrossDomainBridges\n    - bridges-to:: [[Economicmechanism]] via is-subclass-of\n    - bridges-to:: [[BlockchainEntity]] via is-subclass-of\n\n  -",
  "backlinks": [],
  "wiki_links": [
    "Economicmechanism",
    "ISO/IEC 23257:2021",
    "BlockchainEntity",
    "TokenEconomicsDomain",
    "IEEE 2418.1",
    "NIST NISTIR",
    "Token"
  ],
  "ontology": {
    "term_id": "BC-0099",
    "preferred_term": "Native Token",
    "alt_terms": [],
    "iri": "http://narrativegoldmine.com/blockchain#NativeToken",
    "source_domain": "blockchain",
    "domain": "blockchain",
    "domain_full_name": "",
    "definition": "Blockchain-native cryptocurrency within blockchain systems, providing essential functionality for distributed ledger technology operations and properties.",
    "scope_note": null,
    "status": "complete",
    "maturity": "mature",
    "version": "1.0.0",
    "public_access": true,
    "last_updated": "2025-10-28",
    "authority_score": 0.95,
    "quality_score": null,
    "cross_domain_links": null,
    "owl_class": "bc:NativeToken",
    "owl_physicality": "VirtualEntity",
    "owl_role": "Object",
    "owl_inferred_class": "bc:VirtualObject",
    "is_subclass_of": [
      "Token"
    ],
    "has_part": [],
    "is_part_of": [],
    "requires": [],
    "depends_on": [],
    "enables": [],
    "relates_to": [],
    "bridges_to": [
      "Economicmechanism via is",
      "BlockchainEntity via is"
    ],
    "bridges_from": [],
    "domain_extensions": {},
    "belongs_to_domain": [
      "TokenEconomicsDomain"
    ],
    "implemented_in_layer": [],
    "source": [
      "ISO/IEC 23257:2021",
      "IEEE 2418.1",
      "NIST NISTIR"
    ],
    "validation": {
      "is_valid": false,
      "errors": [
        "owl:class namespace 'bc' doesn't match source-domain 'blockchain'"
      ]
    }
  }
}