{
  "id": "BC-0474-grant-programs",
  "title": "Grant Programs",
  "content": "- ### OntologyBlock\n  id:: bc-0474-grant-programs-ontology\n  collapsed:: true\n\t- ontology:: true\n\t- term-id:: BC-0474\n\t- preferred-term:: Grant Programs\n\t- status:: stub\n\t- public-access:: true\n\t- definition:: A component of the blockchain ecosystem.\n\t- maturity:: draft\n\t- owl:class:: bc:GrantPrograms\n\t- owl:physicality:: ConceptualEntity\n\t- owl:role:: Concept\n\t- belongsToDomain:: [[BlockchainDomain]]\n\t- #### Relationships\n\t  id:: bc-0474-grant-programs-relationships\n\t  collapsed:: true\n\t\t- is-subclass-of:: [[Decentralized Autonomous Organization]]\n\n## OWL Formal Semantics\n\n```clojure\n;; OWL Functional Syntax\n\n(Declaration (Class :GrantPrograms))\n\n;; Annotations\n(AnnotationAssertion rdfs:label :GrantPrograms \"Grant Programs\"@en)\n(AnnotationAssertion rdfs:comment :GrantPrograms \"A component of the blockchain ecosystem.\"@en)\n\n;; Data Properties\n(AnnotationAssertion dcterms:identifier :GrantPrograms \"BC-0474\"^^xsd:string)\n```\n\n- ## About Grant Programmes\n  id:: grant-programmes-about\n\t- Grant programmes represent crucial mechanisms through which [[DAO|DAOs]] and blockchain protocols allocate resources to ecosystem development, public goods funding, protocol improvements, and community initiatives, transforming governance treasuries from passive holdings into active ecosystem growth engines. As major protocols accumulated substantial treasuries (Uniswap $3.5+ billion, Arbitrum $3+ billion, Optimism $2+ billion, Compound $1+ billion), grant programmes emerged as primary mechanisms for deploying these resources toward protocol development, application ecosystem growth, research advancement, and public goods support. Leading grant programmes demonstrate remarkable scale: [[Uniswap]]'s grants have allocated $74+ million to 200+ projects, [[Compound]]'s multi-year programme committed $42 million to governance and ecosystem development, [[Gitcoin]] Grants distributed over $50 million through innovative quadratic funding mechanisms, [[Optimism]]'s RetroPGF (Retroactive Public Goods Funding) allocated $30+ million across three rounds, [[Aave]] Grants DAO approved $16.28 million in funding, whilst [[Arbitrum]]'s incentive programmes (STIP, LTIPP) distributed over $215 million in ecosystem grants. These programmes vary dramatically in structure: prospective grants funding proposed work versus retroactive funding rewarding completed contributions, centralised committees making allocation decisions versus decentralised quadratic funding reflecting community preferences, milestone-based distributions ensuring deliverables versus upfront funding trusting recipients, and domain-specific programmes focusing particular needs versus general-purpose funding accepting diverse proposals. Grant programmes address multiple objectives simultaneously: bootstrapping application ecosystems on new platforms, funding public goods benefiting entire communities, supporting protocol research and security audits, compensating open-source development, attracting developer talent to ecosystems, and demonstrating protocol commitment to decentralisation and community ownership. However, these programmes face persistent challenges including impact measurement difficulties (how to quantify grant success), allocation efficiency concerns (ensuring funds reach highest-impact projects), fraud and low-quality applications, accountability for fund usage, determining appropriate grant sizes, and avoiding value extraction by mercenary participants. Successful programmes develop sophisticated evaluation frameworks, milestone-based disbursement schedules, retrospective impact assessment, diverse evaluation committees, transparent decision processes, and iterative programme improvements based on outcome data. The emergence of professionalised grant operations—including dedicated grant committees, programme managers, impact evaluators, and grant platforms—demonstrates DAO operational maturity, whilst innovations like quadratic funding, retroactive rewards, and impact certificates explore novel public goods funding mechanisms potentially applicable beyond blockchain ecosystems.\n\t-\n\t- ### Uniswap Grants Programme\n\t\t- **Programme Structure**: [[Uniswap]] launched its grants programme in August 2021 following governance approval of the Uniswap Grants Program v0.1 allocating $750,000 initial funding, subsequently expanded through multiple proposals culminating in the $74 million Uniswap Foundation allocation in 2022. The programme operates through the Uniswap Foundation, a legal entity independent from Uniswap Labs that administers grants, manages application processes, and oversees fund disbursement. The Foundation employs dedicated staff including grant managers, technical evaluators, and operations personnel, professionalising grant administration whilst maintaining accountability to UNI governance.\n\t\t- **Funding Areas**: Uniswap grants target protocol development (improvements to Uniswap core contracts, v4 hook development, integration tools), ecosystem growth (wallets and interfaces, analytics and monitoring, developer tools and SDKs), community initiatives (governance participation tools, educational content, localisation), and research (MEV mitigation, concentrated liquidity optimisation, cross-chain mechanisms). Notable funded projects include Uniswap v3 oracle integrations, governance participation platforms, mobile wallet integrations, and comprehensive educational resources.\n\t\t- **Application and Evaluation**: Grant applications undergo multi-stage evaluation: initial screening for eligibility and alignment, technical review assessing feasibility and team capability, committee deliberation weighing impact potential and resource efficiency, and final approval from grants committee. The Foundation publishes approved grants publicly whilst protecting applicant privacy for rejected proposals. Evaluation criteria emphasise technical capability, clear deliverables, meaningful impact, reasonable budgets, and team track record. Grant sizes range from $10,000 small grants to $500,000+ major initiatives, with typical grants clustering around $50,000-$150,000.\n\t\t- **Impact and Outcomes**: The programme has funded 200+ projects contributing to Uniswap ecosystem expansion. Successful grants include improved governance tooling (Tally enhancements, delegation platforms), protocol integrations (Cowswap, 1inch, Matcha), analytics tools (Uniswap v3 dashboards, liquidity analytics), and educational resources (developer documentation, video tutorials). Impact assessment focuses on adoption metrics (users acquired, volume facilitated, integrations achieved), technical deliverables (code quality, documentation, maintenance), and ecosystem value (building blocks enabling subsequent innovation).\n\t-\n\t- ### Compound Grants Programme\n\t\t- **Multi-Year Commitment**: [[Compound]] approved the Compound Grants Program (CGP) in 2021 with $42.3 million allocation over four years (originally planned as multi-year, later restructured), representing one of DeFi's largest sustained grant commitments. The programme operates through elected Grants Committee members serving defined terms, combining domain expertise with governance accountability. Committee membership includes technical developers, DeFi protocol operators, community leaders, and governance specialists providing diverse evaluation perspectives.\n\t\t- **Grant Categories**: CGP funds developer tools and infrastructure (SDK improvements, testing frameworks, integration libraries), protocol enhancements (security audits, parameter optimisation, cross-chain expansion), community initiatives (governance tooling, education, events), and research (economic modelling, risk analysis, governance experiments). The programme emphasises technical depth, funding sophisticated protocol development over marketing or promotional activities.\n\t\t- **Evaluation Process**: Applications undergo structured review including technical assessment (architecture review, code quality evaluation), team evaluation (relevant experience, completion capability), impact analysis (beneficiary count, strategic value, ecosystem positioning), and budget justification (resource allocation, milestone alignment). The committee maintains public deliberations through forum discussions, creating transparency in decision-making whilst enabling community input before final votes.\n\t\t- **Accountability Mechanisms**: Funded grants face milestone-based disbursement where recipients demonstrate progress before receiving subsequent tranches, regular progress reporting through forum updates and technical documentation, deliverable verification ensuring promised work completion, and retrospective impact assessment evaluating actual versus projected outcomes. Non-performing grants can be terminated with remaining funds reallocated, creating accountability for fund usage.\n\t-\n\t- ### Gitcoin Grants and Quadratic Funding\n\t\t- **Quadratic Funding Mechanism**: [[Gitcoin]] pioneered quadratic funding for public goods where matching funds amplify small contributions more than large ones, theoretically revealing community preferences whilst reducing plutocratic control. The mechanism calculates matching as proportional to the square root of contribution amounts summed and squared: match ∝ (√contrib₁ + √contrib₂ + ... + √contribₙ)². This means a project receiving $1 each from 100 contributors receives more matching than project receiving $100 from one contributor, emphasising breadth of support over total amount.\n\t\t- **Grant Rounds**: Gitcoin conducted 20+ grant rounds from 2019-2024, distributing over $50 million in matched funding to thousands of projects. Rounds organised by category (Ethereum infrastructure, DeFi, NFTs, climate solutions, open-source software, community and education) enable focused evaluation and diverse ecosystem support. Major rounds attracted $1-5 million in matching pools contributed by [[Ethereum Foundation]], protocols ([[Uniswap]], [[Balancer]], [[Yearn]], [[Synthetix]]), and community donors. Round 15 (GR15) distributed $4.9 million across 2,000+ projects, whilst subsequent rounds maintained $2-4 million matching pools.\n\t\t- **Sybil Resistance**: Quadratic funding's vulnerability to Sybil attacks (one person creating multiple identities to gain matching funds) prompted development of sophisticated identity verification: [[Gitcoin Passport]] aggregating identity signals (Proof of Humanity, BrightID, Twitter, Discord, ENS, POAPs) into trust scores, machine learning detecting collusion rings and suspicious contribution patterns, and community flagging enabling ecosystem-wide fraud detection. Despite these measures, Sybil attacks remained persistent challenge with estimated 10-30% of contributions potentially fraudulent in some rounds.\n\t\t- **Gitcoin Grants Protocol (Allo)**: Gitcoin evolved from centralised grants platform to [[Allo Protocol]], decentralised infrastructure enabling any community to run quadratic funding rounds. Allo powers grants programmes for [[Arbitrum]], [[Optimism]], [[Polygon]], [[zkSync]], and dozens more, demonstrating protocol-layer approach to grants infrastructure. The protocol handles contribution processing, matching calculation, payout distribution, and fraud detection whilst enabling customisation of parameters, categories, and policies.\n\t-\n\t- ### Optimism RetroPGF\n\t\t- **Retroactive Model**: [[Optimism]]'s Retroactive Public Goods Funding (RetroPGF) inverts traditional grants by funding completed work rather than proposed projects, implementing the principle \"it's easier to agree on what was useful than what will be useful.\" The model eliminates risk of funding projects that fail delivery whilst creating incentive for contributors to produce public goods expecting potential retroactive rewards. Three rounds conducted through 2024 demonstrated model viability whilst revealing implementation challenges.\n\t\t- **Round 1 (2021)**: RetroPGF 1 allocated $1 million to 58 projects selected by 24 badge holders (Optimism team members and community representatives) voting on public goods that benefited Optimism and Ethereum. Recipients included [[Ethereum]] core developers, EIP authors, community educators, open-source tool builders, and infrastructure providers. The round validated retroactive funding concept whilst highlighting centralisation concerns in badge holder selection.\n\t\t- **Round 2 (2023)**: RetroPGF 2 expanded to $10 million distributed among 195 projects voted on by 69 Citizens (expanded from badge holders). Votes allocated across three categories: Infrastructure, Tooling & Utilities, and Education. Notable recipients included [[EthereumJS]] ($158,000), [[Foundry]] ($142,000), [[WalletConnect]] ($89,000), and dozens of educational initiatives. The round demonstrated scale viability whilst revealing concentration risks (top 10 projects received 25% of funding) and evaluation challenges (assessing diverse contributions comparably).\n\t\t- **Round 3 (2023-2024)**: RetroPGF 3 allocated $30 million across 643 projects voted on by 208 Citizens, representing significant scale expansion. The round introduced improved attestations (contributors creating evidence of impact), impact metrics frameworks (quantitative and qualitative assessment criteria), and refined voting mechanisms. Categories expanded to include OP Stack (core protocol contributions), Collective Governance (governance participation), and Developer Ecosystem (tools and libraries). Individual allocations ranged from $1,000 to $500,000+, with median around $20,000.\n\t\t- **Impact Assessment**: Optimism developed sophisticated impact measurement including usage metrics (users served, value processed, developer adoption), dependency analysis (how many projects build on funded work), counterfactual reasoning (would work exist without funding), and ecosystem multiplier effects. The foundation published detailed analyses showing RetroPGF recipients collectively served tens of millions of users, processed billions in value, and enabled thousands of derivative projects.\n\t-\n\t- ### Aave Grants DAO\n\t\t- **Autonomous Grants Committee**: [[Aave]] established the Aave Grants DAO (AGD) in 2021 as independent entity managing grants funded by Aave ecosystem. Initial funding of $1 million AAVE grew to over $16.28 million in approved grants through 2024. The DAO operates autonomously with elected committee members (8-12 members serving 6-month terms), independent budget authority within approved limits, and accountability to main Aave governance through periodic reporting and budget renewals.\n\t\t- **Grant Focus Areas**: AGD prioritises protocol development (Aave v3 integrations, cross-chain deployments, new market launches), developer experience (SDKs, documentation, testing tools), community growth (educational content, events, ambassadors), security (audits, bug bounties, monitoring tools), and governance improvements (delegation platforms, voting tools, analytics). The programme emphasises technical quality, funding sophisticated development over general ecosystem promotion.\n\t\t- **Notable Grants**: Major funded initiatives include [[Aave]] v3 deployments to new chains ($500,000+ across multiple grants), comprehensive developer documentation ($150,000), security auditing programmes ($300,000+), governance participation tools (Aave Governance v3 interface $75,000), and community ambassador programmes ($50,000 per quarter). The programme funded both specific deliverables (technical integrations, audit reports) and ongoing initiatives (community management, educational content).\n\t\t- **Governance Integration**: AGD maintains unique position as DAO-funded, semi-autonomous organisation accountable to Aave governance. Quarterly budget requests require Aave governance approval, creating periodic accountability whilst enabling operational independence. Published financial reports detail all grant allocations, committee expenses, and programme outcomes, maintaining transparency whilst protecting grant applicant privacy.\n\t-\n\t- ### Arbitrum Incentive Programmes\n\t\t- **Short-Term Incentive Programme (STIP)**: [[Arbitrum]] launched STIP in late 2023 allocating 50 million ARB (approximately $75 million at launch) to protocols building on Arbitrum, incentivising liquidity migration and user acquisition. Applications underwent community voting where ARB holders determined grant allocations across 60+ protocols. Individual allocations ranged from 300,000 ARB ($450,000) to 3.25 million ARB ($4.9 million) for major DeFi protocols. Recipients included [[GMX]], [[Radiant Capital]], [[Vertex Protocol]], [[Camelot]], and dozens more, with incentives distributed to users providing liquidity or trading volume.\n\t\t- **Long-Term Incentive Pilot Programme (LTIPP)**: Following STIP's success, Arbitrum approved LTIPP with 45 million ARB ($65 million) focused on sustainable ecosystem growth rather than short-term incentives. The programme emphasised protocol sustainability, innovative incentive mechanisms beyond simple liquidity mining, cross-protocol collaboration creating network effects, and measurable user retention beyond incentive periods. LTIPP incorporated learnings from STIP's mercenary capital challenges, requiring recipients demonstrate sustainable value creation.\n\t\t- **Gaming Catalyst Programme**: Arbitrum allocated 200 million ARB (approximately $250+ million) to gaming ecosystem development through dedicated grants supporting game development, infrastructure tools, player acquisition, and ecosystem events. This domain-specific programme recognised gaming's unique requirements including longer development cycles, different KPIs versus DeFi, and need for user experience optimisation. The programme combined upfront grants for development with performance-based rewards for user acquisition.\n\t\t- **Impact Analysis**: Early analysis of Arbitrum incentive programmes showed mixed results: total value locked (TVL) increased 50%+ during STIP allocation, daily active addresses grew 30%, but significant portions of liquidity departed after incentive conclusion. Protocols retaining users post-incentives demonstrated genuine product-market fit, whilst others merely attracted mercenary capital. This prompted LTIPP's focus on sustainability metrics beyond pure growth numbers.\n\t-\n\t- ### Polygon Grants and Village\n\t\t- **Polygon Village**: [[Polygon]] established Polygon Village as ecosystem grants programme funding Web3 gaming, NFT projects, DeFi protocols, and infrastructure development. The programme allocated $100+ million across multiple categories with emphasis on user-facing applications driving mainstream adoption. Village operated through quarterly cohorts receiving funding, mentorship, technical support, and ecosystem connections.\n\t\t- **Grant Structures**: Polygon offered diverse grant types including builder grants ($5,000-$50,000 for early development), scale grants ($50,000-$250,000 for growth-stage projects), ecosystem grants ($250,000+ for major initiatives), and investment stakes (equity or token participation for strategic projects). This tiered approach addressed projects at various stages whilst providing growth path from small grants to major funding.\n\t\t- **Success Stories**: Notable Polygon-funded projects include major gaming titles (Decentraland, The Sandbox integrations), DeFi protocols (QuickSwap, Balancer), NFT marketplaces, and infrastructure tools. Some grant recipients achieved $100+ million valuations, demonstrating grants programme's role in ecosystem value creation beyond direct funding amounts.\n\t-\n\t- ### Ethereum Foundation Grants\n\t\t- **Ecosystem Support Programme (ESP)**: The [[Ethereum Foundation]] operates one of crypto's longest-running grants programmes, distributing $100+ million since inception to core protocol development, research, community building, and ecosystem infrastructure. ESP funding ranges from small grants ($5,000-$50,000) supporting individual developers to major allocations ($500,000+) funding protocol research, client development, and security audits.\n\t\t- **Focus Areas**: EF grants emphasise protocol-layer development (consensus clients, execution clients, testing infrastructure), research (cryptography, scalability, privacy), developer experience (tooling, documentation, educational resources), and community building (events, educational initiatives, regional communities). The foundation prioritises public goods and infrastructure over application-layer projects, viewing its role as ecosystem foundation rather than application ecosystem curator.\n\t\t- **Impact**: EF grants funded crucial infrastructure including [[Prysm]], [[Lighthouse]], [[Nimbus]] (consensus clients), [[Geth]], [[Nethermind]] (execution clients), [[Solidity]] compiler improvements, [[Vyper]] language development, [[Web3.py]], [[Ethers.js]] (developer libraries), and countless research papers advancing Ethereum roadmap. This foundational funding enabled ecosystem development worth hundreds of billions in aggregate value.\n\t-\n\t- ### Grant Application Best Practices\n\t\t- **Compelling Proposals**: Successful applications clearly articulate problem being solved, proposed solution's technical approach, expected outcomes with measurable KPIs, team credentials and relevant experience, realistic budget with itemised breakdown, and clear timeline with intermediate milestones. Vague proposals lacking concrete deliverables face high rejection rates regardless of team quality or idea merit.\n\t\t- **Milestone Structuring**: Effective grant proposals structure work into 3-6 milestones with partial fund disbursement after each, demonstrating progress before receiving subsequent tranches. Milestones should represent meaningful deliverables (working prototype, security audit, user testing completion) rather than arbitrary time periods, enabling objective evaluation of grant progress.\n\t\t- **Budget Justification**: Grant committees scrutinise budgets for reasonableness, requiring justification for major expenses, market-rate compensation validation, and explanation for outsourced versus in-house work. Budgets should include appropriate contingency (10-20%) whilst avoiding obvious padding that creates perception of inefficiency or value extraction.\n\t\t- **Impact Framing**: Strongest proposals quantify expected impact: \"serve 10,000 users in first quarter,\" \"reduce transaction costs by 30%,\" \"enable 50 developers to build integrations.\" Measurable outcomes enable retrospective assessment whilst demonstrating applicant's clarity of purpose and success criteria.\n\t-\n\t- ### Success Metrics and KPIs\n\t\t- **Output Metrics**: Grant programmes track deliverable completion rates (percentage of funded projects completing promised deliverables), timeline adherence (on-time versus delayed delivery), budget efficiency (actual versus proposed spending), and technical quality (code quality, documentation, testing coverage). High-performing programmes achieve 70-85% successful completion whilst 10-25% of grants typically fail to deliver.\n\t\t- **Outcome Metrics**: Beyond deliverables, programmes measure user adoption (active users of funded tools/applications), developer usage (integration count for developer tools), protocol impact (value secured, transactions processed), and ecosystem multiplier effects (derivative projects building on funded work). These outcomes often manifest 12-24 months post-grant, requiring patient evaluation.\n\t\t- **Ecosystem Effects**: Sophisticated programmes assess broader ecosystem impact including developer community growth (new developers attracted to ecosystem), public goods provision (open-source tools benefiting multiple projects), ecosystem narrative strengthening (prestigious projects validating platform), and talent signaling (grant receipt indicating protocol backing). These qualitative effects resist precise quantification but provide crucial strategic value.\n\t\t- **Return on Investment**: Some programmes calculate ROI through value created per dollar granted: TVL generated by funded protocols, user acquisition cost compared to alternative marketing, protocol fee generation enabled by grants, and ecosystem valuation growth correlated with grant activity. While attribution challenges complicate ROI calculation, rough estimates help optimise allocation strategies.\n\t-\n\t- ### Common Challenges\n\t\t- **Value Extraction**: Grants programmes attract applicants seeking free capital without commitment to ecosystem success. Mercenary recipients collect grants, deliver minimum viable deliverables, and immediately move to next opportunity. Mitigation strategies include reputation systems tracking applicant history, milestone-based disbursement delaying payment until delivery, claw-back provisions recovering funds for non-delivery, and preference for applicants with demonstrated ecosystem commitment.\n\t\t- **Evaluation Difficulty**: Assessing diverse proposals (compare blockchain explorer grant to community education programme to protocol research) requires domain expertise across technical development, community building, research, and business development. Programmes address this through specialised sub-committees with domain expertise, external expert reviewers for technical proposals, and structured evaluation frameworks weighting standardised criteria.\n\t\t- **Accountability Gaps**: After fund disbursement, ensuring recipients complete promised work and use funds appropriately poses challenges. Solutions include mandatory progress reporting at defined intervals, public commitment to deliverables creating reputational pressure, technical milestone verification before subsequent disbursements, and grant manager oversight reviewing progress.\n\t\t- **Centralization Concerns**: Committee-based grant allocation concentrates power in small groups potentially vulnerable to capture, bias, or conflicts of interest. Gitcoin's quadratic funding, Optimism's Citizens' House voting, and community-voted allocations (Arbitrum STIP) represent experiments in decentralised allocation whilst introducing own challenges around sybil resistance, voter information quality, and populism risks.\n\t-\n\t- ### Innovative Funding Mechanisms\n\t\t- **Impact Certificates**: [[Hypercerts]] and similar protocols create certificates representing expected positive impact, enabling contributors to create and sell impact claims. Retrospective funders purchase certificates representing actual impact, creating market where contributors get upfront capital from speculators who subsequently sell to impact purchasers. This mechanism enables prospective capital formation whilst maintaining retroactive funding's superior information properties.\n\t\t- **Streaming Grants**: [[Superfluid]] and [[Sablier]] enable streaming grants where funds flow continuously per second rather than lump sum or milestone disbursement. Recipients receive steady income whilst funders can cancel streams if dissatisfied, creating real-time accountability mechanism. This model suits ongoing work (community management, documentation maintenance) better than discrete projects.\n\t\t- **Conviction Voting**: [[1Hive]]'s Gardens and similar platforms employ conviction voting where vote weight increases the longer tokens remain allocated to proposal. This mechanism prioritises proposals with sustained community support over momentary popularity, potentially reducing influence of vote brigading whilst creating new strategic voting dynamics.\n\t\t- **Progressive Deliverables**: Some programmes fund same team through escalating grants: initial $10,000 proof-of-concept grant, subsequent $50,000 development grant upon success, then $200,000 scaling grant after user validation. This reduces risk on unproven teams whilst providing clear growth path for successful recipients.\n\t-\n\t- ### Governance Integration\n\t\t- **Allocation Authority**: Grant programmes balance efficiency (quick decisions, expert evaluation) with legitimacy (community governance, decentralised authority). Models include full governance voting on every grant (unwieldy but maximally decentralised), elected committees with delegated authority (balanced approach used by Compound, Aave), independent foundations with governance accountability (Uniswap Foundation), and algorithmic allocation (Gitcoin quadratic funding).\n\t\t- **Budget Approval**: Most programmes require periodic governance approval for budget allocation: quarterly renewals (creating regular accountability points), annual budgets (reducing governance overhead), or one-time allocations (limiting commitment). Approval processes range from simple majority votes to quorum requirements to timelock delays enabling opposition mobilisation.\n\t\t- **Committee Selection**: Elected grant committees face challenges of voter information (knowing candidate qualifications), political dynamics (popularity versus competence), and commitment sustainability (volunteer burnout). Successful programmes combine elections with qualification requirements, term limits preventing entrenchment, and adequate compensation enabling professional participation.\n\t\t- **Reporting Requirements**: Committees maintain legitimacy through transparent reporting including public grant registries listing all approved grants, financial reports detailing fund usage, impact assessments evaluating programme outcomes, and retrospectives documenting lessons learned. This transparency enables governance evaluation of committee performance whilst informing future programme structure.\n\t-\n\t- ### Cross-Programme Coordination\n\t\t- **Grant Stacking**: Projects often receive grants from multiple programmes: an infrastructure project might receive Ethereum Foundation research grant, Optimism ecosystem grant, Gitcoin community funding, and protocol-specific integration grants. This diversified funding reduces dependency on single source whilst creating coordination challenges around deliverable overlap and timeline management.\n\t\t- **Information Sharing**: Grant committees increasingly coordinate to share information about applicants, avoiding duplicate funding, identifying fraudulent applications, and learning from collective experience. Privacy concerns and competitive dynamics limit sharing, but informal coordination networks improve ecosystem-wide grant effectiveness.\n\t\t- **Standards Development**: Emerging standards for grant applications, reporting formats, impact measurement, and evaluation criteria would reduce applicant burden (adapting proposals across programmes) and enable better cross-programme analysis. [[Allo Protocol]] and similar infrastructure layers contribute to standardisation through common technical foundations.\n\t-\n\t- ### Future Developments\n\t\t- **Impact DAOs**: Organisations forming specifically to receive and deploy grants, creating sustained institution around public goods funding. Examples include [[Protocol Guild]] (funding Ethereum core developers), [[Metagov]] (governance research), and domain-specific impact DAOs focusing particular public goods areas.\n\t\t- **Outcomes-Based Funding**: Experiments with payment contingent on achieved outcomes rather than completed deliverables: pay for users acquired, pay for transactions processed, pay for dependent projects created. This aligns incentives toward actual impact whilst introducing measurement challenges and creating risk for grant recipients.\n\t\t- **Perpetual Grants Engines**: Protocols establishing permanent grant programmes funded by protocol revenue rather than treasury allocation. [[Nouns DAO]]'s continuous auction funding daily grants, [[Gitcoin]]'s protocol fees funding matching pools, and protocol revenue sharing with public goods programmes represent movement toward sustainable grant funding.\n\t\t- **AI-Assisted Evaluation**: Emerging tools use AI to screen applications for completeness, compare proposals to similar past grants, identify potential red flags, and synthesize community feedback. These tools augment rather than replace human evaluation whilst potentially reducing committee workload and improving consistency.\n\t-\n\t- #\n\n\n## Metadata\n\n- **Last Updated**: 2025-11-16\n- **Review Status**: Automated remediation with 2025 context\n- **Verification**: Academic sources verified\n- **Regional Context**: UK/North England where applicable\n\n## References and Resources\n\t\t- [[BC-0410-decentralised-autonomous-organisations]]\n\t\t- [[BC-0411-dao-governance-models]]\n\t\t- [[BC-0462-treasury-management]]\n\t\t- [[BC-0469-governance-tokens]]\n\t\t- [[BC-0471-tokenomics-governance]]\n\t\t- [[BC-0472-dao-tooling]]\n\t\t- [[BC-0473-delegate-democracy]]\n\t\t- [[BC-0475-dao-analytics]]\n\t\t- [[Uniswap]]\n\t\t- [[Compound]]\n\t\t- [[Gitcoin]]\n\t\t- [[Optimism]]\n\t\t- [[Aave]]\n\t\t- [[Arbitrum]]\n\t\t- [[Polygon]]\n\t\t- [[Ethereum Foundation]]\n\t-\n\t- ### Original Content\n\t  collapsed:: true\n\t\t- ```\n\n\t\t  ```",
  "backlinks": [],
  "wiki_links": [
    "Nouns DAO",
    "GMX",
    "Nimbus",
    "Nethermind",
    "Arbitrum",
    "Solidity",
    "BC-0473-delegate-democracy",
    "BC-0471-tokenomics-governance",
    "Compound",
    "Optimism",
    "Aave",
    "BlockchainDomain",
    "Balancer",
    "Sablier",
    "Web3.py",
    "BC-0410-decentralised-autonomous-organisations",
    "Vertex Protocol",
    "Polygon",
    "Lighthouse",
    "1Hive",
    "Decentralized Autonomous Organization",
    "Metagov",
    "zkSync",
    "DAO|DAOs",
    "Geth",
    "Gitcoin",
    "EthereumJS",
    "Superfluid",
    "BC-0411-dao-governance-models",
    "Foundry",
    "Camelot",
    "BC-0475-dao-analytics",
    "BC-0472-dao-tooling",
    "Vyper",
    "Radiant Capital",
    "Ethereum Foundation",
    "Protocol Guild",
    "Ethers.js",
    "Hypercerts",
    "Gitcoin Passport",
    "Ethereum",
    "WalletConnect",
    "BC-0469-governance-tokens",
    "Allo Protocol",
    "BC-0462-treasury-management",
    "Yearn",
    "Uniswap",
    "Synthetix",
    "Prysm"
  ],
  "ontology": {
    "term_id": "BC-0474",
    "preferred_term": "Grant Programs",
    "alt_terms": [],
    "iri": "http://narrativegoldmine.com/blockchain#GrantPrograms",
    "source_domain": null,
    "domain": "bc",
    "domain_full_name": "Blockchain",
    "definition": "A component of the blockchain ecosystem.",
    "scope_note": null,
    "status": "stub",
    "maturity": "draft",
    "version": null,
    "public_access": true,
    "last_updated": null,
    "authority_score": null,
    "quality_score": null,
    "cross_domain_links": null,
    "owl_class": "bc:GrantPrograms",
    "owl_physicality": "ConceptualEntity",
    "owl_role": "Concept",
    "owl_inferred_class": null,
    "is_subclass_of": [
      "Decentralized Autonomous Organization"
    ],
    "has_part": [],
    "is_part_of": [],
    "requires": [],
    "depends_on": [],
    "enables": [],
    "relates_to": [],
    "bridges_to": [],
    "bridges_from": [],
    "domain_extensions": {},
    "belongs_to_domain": [
      "BlockchainDomain"
    ],
    "implemented_in_layer": [],
    "source": [],
    "validation": {
      "is_valid": false,
      "errors": [
        "Missing required property: source-domain",
        "Missing required property: last-updated"
      ]
    }
  }
}