{
  "id": "BC-0100-gas",
  "title": "Gas",
  "content": "- ### OntologyBlock\n  id:: gas-ontology\n  collapsed:: true\n\t- ontology:: true\n\t- term-id:: BC-0100\n\t- preferred-term:: Gas\n\t- status:: complete\n\t- public-access:: true\n\t- definition:: Transaction execution cost unit within blockchain systems, providing essential functionality for distributed ledger technology operations and properties.\n\t- source:: [[ISO/IEC 23257:2021]], [[IEEE 2418.1]], [[NIST NISTIR]]\n\t- maturity:: mature\n\t- owl:class:: bc:Gas\n\t- owl:physicality:: VirtualEntity\n\t- owl:role:: Object\n\t- owl:inferred-class:: bc:VirtualObject\n\t- belongsToDomain:: [[TokenEconomicsDomain]]\n\t- #### Relationships\n\t  id:: gas-relationships\n\t  collapsed:: true\n\t\t- is-subclass-of:: [[Transaction Fee]]\n\t\t- bridges-to:: [[Economicmechanism]]\n\t\t- bridges-to:: [[BlockchainEntity]]",
  "backlinks": [],
  "wiki_links": [
    "BlockchainEntity",
    "ISO/IEC 23257:2021",
    "IEEE 2418.1",
    "Economicmechanism",
    "TokenEconomicsDomain",
    "Transaction Fee",
    "NIST NISTIR"
  ],
  "ontology": {
    "term_id": "BC-0100",
    "preferred_term": "Gas",
    "alt_terms": [],
    "iri": "http://narrativegoldmine.com/blockchain#Gas",
    "source_domain": null,
    "domain": "bc",
    "domain_full_name": "Blockchain",
    "definition": "Transaction execution cost unit within blockchain systems, providing essential functionality for distributed ledger technology operations and properties.",
    "scope_note": null,
    "status": "complete",
    "maturity": "mature",
    "version": null,
    "public_access": true,
    "last_updated": null,
    "authority_score": null,
    "quality_score": null,
    "cross_domain_links": null,
    "owl_class": "bc:Gas",
    "owl_physicality": "VirtualEntity",
    "owl_role": "Object",
    "owl_inferred_class": "bc:VirtualObject",
    "is_subclass_of": [
      "Transaction Fee"
    ],
    "has_part": [],
    "is_part_of": [],
    "requires": [],
    "depends_on": [],
    "enables": [],
    "relates_to": [],
    "bridges_to": [],
    "bridges_from": [],
    "domain_extensions": {},
    "belongs_to_domain": [
      "TokenEconomicsDomain"
    ],
    "implemented_in_layer": [],
    "source": [
      "ISO/IEC 23257:2021",
      "IEEE 2418.1",
      "NIST NISTIR"
    ],
    "other_relationships": {
      "bridges-to": [
        "Economicmechanism",
        "BlockchainEntity"
      ]
    },
    "validation": {
      "is_valid": false,
      "errors": [
        "Missing required property: source-domain",
        "Missing required property: last-updated"
      ]
    }
  }
}