{
  "id": "BC-0032-elliptic-curve-cryptography",
  "title": "Elliptic Curve Cryptography",
  "content": "- ### OntologyBlock\n  id:: elliptic-curve-cryptography-ontology\n  collapsed:: true\n\t- ontology:: true\n\t- term-id:: BC-0032\n\t- preferred-term:: Elliptic Curve Cryptography\n\t- status:: complete\n\t- public-access:: true\n\t- definition:: ECC-based public-key system within blockchain systems, providing essential functionality for distributed ledger technology operations and properties.\n\t- source:: [[ISO/IEC 23257:2021]], [[IEEE 2418.1]], [[NIST NISTIR]]\n\t- maturity:: mature\n\t- owl:class:: bc:EllipticCurveCryptography\n\t- owl:physicality:: VirtualEntity\n\t- owl:role:: Object\n\t- owl:inferred-class:: bc:VirtualObject\n\t- belongsToDomain:: [[CryptographicDomain]]\n\t- #### Relationships\n\t  id:: elliptic-curve-cryptography-relationships\n\t  collapsed:: true\n\t\t- is-subclass-of:: [[Public Key Cryptography]]\n\t\t- bridges-to:: [[BlockchainEntity]]\n\t\t- bridges-from:: [[ZeroKnowledgeProofZkp]]",
  "backlinks": [],
  "wiki_links": [
    "NIST NISTIR",
    "CryptographicDomain",
    "ISO/IEC 23257:2021",
    "ZeroKnowledgeProofZkp",
    "Public Key Cryptography",
    "BlockchainEntity",
    "IEEE 2418.1"
  ],
  "ontology": {
    "term_id": "BC-0032",
    "preferred_term": "Elliptic Curve Cryptography",
    "alt_terms": [],
    "iri": "http://narrativegoldmine.com/blockchain#EllipticCurveCryptography",
    "source_domain": null,
    "domain": "bc",
    "domain_full_name": "Blockchain",
    "definition": "ECC-based public-key system within blockchain systems, providing essential functionality for distributed ledger technology operations and properties.",
    "scope_note": null,
    "status": "complete",
    "maturity": "mature",
    "version": null,
    "public_access": true,
    "last_updated": null,
    "authority_score": null,
    "quality_score": null,
    "cross_domain_links": null,
    "owl_class": "bc:EllipticCurveCryptography",
    "owl_physicality": "VirtualEntity",
    "owl_role": "Object",
    "owl_inferred_class": "bc:VirtualObject",
    "is_subclass_of": [
      "Public Key Cryptography"
    ],
    "has_part": [],
    "is_part_of": [],
    "requires": [],
    "depends_on": [],
    "enables": [],
    "relates_to": [],
    "bridges_to": [],
    "bridges_from": [],
    "domain_extensions": {},
    "belongs_to_domain": [
      "CryptographicDomain"
    ],
    "implemented_in_layer": [],
    "source": [
      "ISO/IEC 23257:2021",
      "IEEE 2418.1",
      "NIST NISTIR"
    ],
    "other_relationships": {
      "bridges-to": [
        "BlockchainEntity"
      ],
      "bridges-from": [
        "ZeroKnowledgeProofZkp"
      ]
    },
    "validation": {
      "is_valid": false,
      "errors": [
        "Missing required property: source-domain",
        "Missing required property: last-updated"
      ]
    }
  }
}