{
  "id": "BC-0470-dao-legal-structures",
  "title": "DAO Legal Structures",
  "content": "- ### OntologyBlock\n  id:: bc-0470-dao-legal-structures-ontology\n  collapsed:: true\n\t- ontology:: true\n\t- term-id:: BC-0470\n\t- preferred-term:: DAO Legal Structures\n\t- status:: stub\n\t- public-access:: true\n\t- definition:: A component of the blockchain ecosystem.\n\t- maturity:: draft\n\t- owl:class:: bc:DAOLegalStructures\n\t- owl:physicality:: ConceptualEntity\n\t- owl:role:: Concept\n\t- belongsToDomain:: [[BlockchainDomain]]\n\t- #### Relationships\n\t  id:: bc-0470-dao-legal-structures-relationships\n\t  collapsed:: true\n\t\t- is-subclass-of:: [[Decentralized Autonomous Organization]]\n\n## OWL Formal Semantics\n\n```clojure\n;; OWL Functional Syntax\n\n(Declaration (Class :DAOLegalStructures))\n\n;; Annotations\n(AnnotationAssertion rdfs:label :DAOLegalStructures \"DAO Legal Structures\"@en)\n(AnnotationAssertion rdfs:comment :DAOLegalStructures \"A component of the blockchain ecosystem.\"@en)\n\n;; Data Properties\n(AnnotationAssertion dcterms:identifier :DAOLegalStructures \"BC-0470\"^^xsd:string)\n```",
  "backlinks": [
    "BC-0467-conviction-voting",
    "BC-0466-quadratic-voting",
    "BC-0495-voting-systems",
    "BC-0468-multi-sig-governance"
  ],
  "wiki_links": [
    "BlockchainDomain",
    "Decentralized Autonomous Organization"
  ],
  "ontology": {
    "term_id": "BC-0470",
    "preferred_term": "DAO Legal Structures",
    "alt_terms": [],
    "iri": "http://narrativegoldmine.com/blockchain#DAOLegalStructures",
    "source_domain": null,
    "domain": "bc",
    "domain_full_name": "Blockchain",
    "definition": "A component of the blockchain ecosystem.",
    "scope_note": null,
    "status": "stub",
    "maturity": "draft",
    "version": null,
    "public_access": true,
    "last_updated": null,
    "authority_score": null,
    "quality_score": null,
    "cross_domain_links": null,
    "owl_class": "bc:DAOLegalStructures",
    "owl_physicality": "ConceptualEntity",
    "owl_role": "Concept",
    "owl_inferred_class": null,
    "is_subclass_of": [
      "Decentralized Autonomous Organization"
    ],
    "has_part": [],
    "is_part_of": [],
    "requires": [],
    "depends_on": [],
    "enables": [],
    "relates_to": [],
    "bridges_to": [],
    "bridges_from": [],
    "domain_extensions": {},
    "belongs_to_domain": [
      "BlockchainDomain"
    ],
    "implemented_in_layer": [],
    "source": [],
    "validation": {
      "is_valid": false,
      "errors": [
        "Missing required property: source-domain",
        "Missing required property: last-updated"
      ]
    }
  }
}