{
  "id": "BC-0096-token",
  "title": "Token",
  "content": "- ### OntologyBlock\n  id:: token-ontology\n  collapsed:: true\n\t- ontology:: true\n\t- term-id:: BC-0096\n\t- preferred-term:: Token\n\t- status:: complete\n\t- public-access:: true\n\t- definition:: A token is a digital asset representation on a blockchain that confers specific rights, utility, or value to its holder, implemented as a cryptographically-secured unit that can be owned, transferred, and programmably controlled through smart contracts according to defined rules and protocols.\n\t- source:: [[ISO/IEC 23257:2021]]\n\t- maturity:: mature\n\t- owl:class:: bc:Token\n\t- owl:physicality:: VirtualEntity\n\t- owl:role:: Object\n\t- owl:inferred-class:: bc:VirtualObject\n\t- belongsToDomain:: [[TokenEconomicsDomain]]\n\t- implementedInLayer:: [[EconomicLayer]]\n\t- #### Relationships\n\t  id:: token-relationships\n\t  collapsed:: true\n\t\t- is-subclass-of:: [[Transferable Right]]\n\t\t- is-subclass-of:: [[Digital Asset]]\n\t\t- is-subclass-of:: [[Blockchain Entity]]",
  "backlinks": [],
  "wiki_links": [
    "EconomicLayer",
    "Transferable Right",
    "Blockchain Entity",
    "ISO/IEC 23257:2021",
    "Digital Asset",
    "TokenEconomicsDomain"
  ],
  "ontology": {
    "term_id": "BC-0096",
    "preferred_term": "Token",
    "alt_terms": [],
    "iri": "http://narrativegoldmine.com/blockchain#Token",
    "source_domain": null,
    "domain": "bc",
    "domain_full_name": "Blockchain",
    "definition": "A token is a digital asset representation on a blockchain that confers specific rights, utility, or value to its holder, implemented as a cryptographically-secured unit that can be owned, transferred, and programmably controlled through smart contracts according to defined rules and protocols.",
    "scope_note": null,
    "status": "complete",
    "maturity": "mature",
    "version": null,
    "public_access": true,
    "last_updated": null,
    "authority_score": null,
    "quality_score": null,
    "cross_domain_links": null,
    "owl_class": "bc:Token",
    "owl_physicality": "VirtualEntity",
    "owl_role": "Object",
    "owl_inferred_class": "bc:VirtualObject",
    "is_subclass_of": [
      "Transferable Right",
      "Digital Asset",
      "Blockchain Entity"
    ],
    "has_part": [],
    "is_part_of": [],
    "requires": [],
    "depends_on": [],
    "enables": [],
    "relates_to": [],
    "bridges_to": [],
    "bridges_from": [],
    "domain_extensions": {},
    "belongs_to_domain": [
      "TokenEconomicsDomain"
    ],
    "implemented_in_layer": [
      "EconomicLayer"
    ],
    "source": [
      "ISO/IEC 23257:2021"
    ],
    "validation": {
      "is_valid": false,
      "errors": [
        "Missing required property: source-domain",
        "Missing required property: last-updated"
      ]
    }
  }
}