{
  "id": "BC-0014-block-time",
  "title": "Block Time",
  "content": "- ### OntologyBlock\n  id:: block-time-ontology\n  collapsed:: true\n\t- ontology:: true\n\t- term-id:: BC-0014\n\t- preferred-term:: Block Time\n\t- source-domain:: blockchain\n\t- status:: complete\n\t- public-access:: true\n\n\n\n\n### OWL Classification\n\t- owl:class:: bc:BlockTime\n\t- owl:physicality:: VirtualEntity\n\t- owl:role:: Object\n\t- owl:inferred-class:: bc:VirtualObject\n\n### Domain & Architecture\n\t- belongsToDomain:: [[BlockchainDomain]]\n\t- maturity:: mature\n\n### Relationships\nid:: relationships\n    - is-subclass-of:: [[Block]]\n\n  - #### CrossDomainBridges\n    - bridges-to:: [[Distributeddatastructure]] via is-subclass-of\n\n  -\n\n### Quality Metrics\n\t- authority-score:: 0.95\n\n- ### OntologyBlock\n  id:: block-time-ontology\n  collapsed:: true\n\n  - **Identification**\n    - public-access:: true\n    - ontology:: true\n    - term-id:: BC-0014\n    - preferred-term:: Block Time\n    - source-domain:: blockchain\n    - status:: complete\n    - version:: 1.0.0\n    - last-updated:: 2025-10-28\n\n  - **Definition**\n    - definition:: Average time between blocks within blockchain systems, providing essential functionality for distributed ledger technology operations and properties.\n    - maturity:: mature\n    - source:: [[ISO/IEC 23257:2021]], [[IEEE 2418.1]], [[NIST NISTIR]]\n    - authority-score:: 0.95\n\n  - **Semantic Classification**\n    - owl:class:: bc:BlockTime\n    - owl:physicality:: VirtualEntity\n    - owl:role:: Object\n    - owl:inferred-class:: bc:VirtualObject\n    - belongsToDomain:: [[BlockchainDomain]]\n\n  - #### OWL Restrictions\n    \n    \n\n  - #### Relationships\n    id:: relationships\n    - is-subclass-of:: [[Block]]\n\n  - #### CrossDomainBridges\n    - bridges-to:: [[Distributeddatastructure]] via is-subclass-of\n\n  -",
  "backlinks": [],
  "wiki_links": [
    "Block",
    "NIST NISTIR",
    "BlockchainDomain",
    "IEEE 2418.1",
    "ISO/IEC 23257:2021",
    "Distributeddatastructure"
  ],
  "ontology": {
    "term_id": "BC-0014",
    "preferred_term": "Block Time",
    "alt_terms": [],
    "iri": "http://narrativegoldmine.com/blockchain#BlockTime",
    "source_domain": "blockchain",
    "domain": "blockchain",
    "domain_full_name": "",
    "definition": "Average time between blocks within blockchain systems, providing essential functionality for distributed ledger technology operations and properties.",
    "scope_note": null,
    "status": "complete",
    "maturity": "mature",
    "version": "1.0.0",
    "public_access": true,
    "last_updated": "2025-10-28",
    "authority_score": 0.95,
    "quality_score": null,
    "cross_domain_links": null,
    "owl_class": "bc:BlockTime",
    "owl_physicality": "VirtualEntity",
    "owl_role": "Object",
    "owl_inferred_class": "bc:VirtualObject",
    "is_subclass_of": [
      "Block"
    ],
    "has_part": [],
    "is_part_of": [],
    "requires": [],
    "depends_on": [],
    "enables": [],
    "relates_to": [],
    "bridges_to": [
      "Distributeddatastructure via is",
      "Distributeddatastructure via is"
    ],
    "bridges_from": [],
    "domain_extensions": {},
    "belongs_to_domain": [
      "BlockchainDomain",
      "BlockchainDomain"
    ],
    "implemented_in_layer": [],
    "source": [
      "ISO/IEC 23257:2021",
      "IEEE 2418.1",
      "NIST NISTIR"
    ],
    "validation": {
      "is_valid": false,
      "errors": [
        "owl:class namespace 'bc' doesn't match source-domain 'blockchain'"
      ]
    }
  }
}