{
  "id": "BC-0059-longest-chain-rule",
  "title": "Longest Chain Rule",
  "content": "- ### OntologyBlock\n  id:: longest-chain-rule-ontology\n  collapsed:: true\n\n  - **Identification**\n    - public-access:: true\n    - ontology:: true\n    - term-id:: BC-0059\n    - preferred-term:: Longest Chain Rule\n    - source-domain:: blockchain\n    - status:: complete\n    - version:: 1.0.0\n    - last-updated:: 2025-10-28\n\n  - **Definition**\n    - definition:: Chain selection mechanism within blockchain systems, providing essential functionality for distributed ledger technology operations and properties.\n    - maturity:: mature\n    - source:: [[ISO/IEC 23257:2021]], [[IEEE 2418.1]], [[NIST NISTIR]]\n    - authority-score:: 0.95\n\n  - **Semantic Classification**\n    - owl:class:: bc:LongestChainRule\n    - owl:physicality:: VirtualEntity\n    - owl:role:: Object\n    - owl:inferred-class:: bc:VirtualObject\n    - belongsToDomain:: [[ConsensusDomain]]\n\n  - #### OWL Restrictions\n    \n    \n\n  - #### Relationships\n    id:: relationships\n    - is-subclass-of:: [[Consensus Rule]]\n\n  - #### CrossDomainBridges\n    - bridges-to:: [[BlockchainEntity]] via is-subclass-of\n\n  -",
  "backlinks": [],
  "wiki_links": [
    "Consensus Rule",
    "ConsensusDomain",
    "ISO/IEC 23257:2021",
    "IEEE 2418.1",
    "BlockchainEntity",
    "NIST NISTIR"
  ],
  "ontology": {
    "term_id": "BC-0059",
    "preferred_term": "Longest Chain Rule",
    "alt_terms": [],
    "iri": "http://narrativegoldmine.com/blockchain#LongestChainRule",
    "source_domain": "blockchain",
    "domain": "blockchain",
    "domain_full_name": "",
    "definition": "Chain selection mechanism within blockchain systems, providing essential functionality for distributed ledger technology operations and properties.",
    "scope_note": null,
    "status": "complete",
    "maturity": "mature",
    "version": "1.0.0",
    "public_access": true,
    "last_updated": "2025-10-28",
    "authority_score": 0.95,
    "quality_score": null,
    "cross_domain_links": null,
    "owl_class": "bc:LongestChainRule",
    "owl_physicality": "VirtualEntity",
    "owl_role": "Object",
    "owl_inferred_class": "bc:VirtualObject",
    "is_subclass_of": [
      "Consensus Rule"
    ],
    "has_part": [],
    "is_part_of": [],
    "requires": [],
    "depends_on": [],
    "enables": [],
    "relates_to": [],
    "bridges_to": [
      "BlockchainEntity via is"
    ],
    "bridges_from": [],
    "domain_extensions": {},
    "belongs_to_domain": [
      "ConsensusDomain"
    ],
    "implemented_in_layer": [],
    "source": [
      "ISO/IEC 23257:2021",
      "IEEE 2418.1",
      "NIST NISTIR"
    ],
    "validation": {
      "is_valid": false,
      "errors": [
        "owl:class namespace 'bc' doesn't match source-domain 'blockchain'"
      ]
    }
  }
}