{
  "id": "Bias Mitigation Techniques",
  "title": "Bias Mitigation Techniques",
  "content": "- ### OntologyBlock\n  id:: bias-mitigation-techniques-ontology\n  collapsed:: true\n\t- ontology:: true\n\t- term-id:: AI-0380\n\t- preferred-term:: Bias Mitigation Techniques\n\t- status:: in\n\t- public-access:: true\n\t- definition:: Bias Mitigation Techniques are methods and interventions designed to reduce algorithmic bias and improve fairness in AI systems through modifications at different stages of the machine learning pipeline. These techniques are categorized into pre-processing methods (data transformation before training, including reweighting samples, resampling underrepresented groups, SMOTE for synthetic minority oversampling, and feature modification), in-processing methods (fairness constraints during model training, including regularization penalties, adversarial debiasing that trains models to be invariant to protected attributes, and constrained optimization), and post-processing methods (prediction adjustment after training, including threshold optimization for different groups and calibration techniques). Each approach involves tradeoffs between fairness improvement and predictive accuracy, with pre-processing methods typically preserving model flexibility but potentially discarding useful data, in-processing methods directly optimizing fairness-accuracy frontiers but requiring specialized algorithms, and post-processing methods being model-agnostic but potentially violating calibration. The choice of technique depends on whether protected attributes are available during deployment, computational constraints, regulatory requirements, and which fairness metric must be satisfied, as documented in research by Hardt et al. (2016) and implemented in libraries like Fairlearn and AIF360.\n\t- source:: [[Fairlearn]], [[AIF360]], [[IEEE P7003-2021]]\n\t- maturity:: mature\n\t- owl:class:: aigo:BiasMitigationTechniques\n\t- owl:physicality:: VirtualEntity\n\t- owl:role:: Process\n\t- owl:inferred-class:: aigo:VirtualProcess\n\t- belongsToDomain:: [[AIEthicsDomain]]\n\t- implementedInLayer:: [[ConceptualLayer]]\n\t- #### Relationships\n\t  id:: bias-mitigation-techniques-relationships\n\t  collapsed:: true\n\t\t- is-subclass-of:: [[AIFairness]]\n\n## Bias Mitigation Techniques\n\nBias Mitigation Techniques refers to bias mitigation techniques are methods and interventions designed to reduce algorithmic bias and improve fairness in ai systems through modifications at different stages of the machine learning pipeline. these techniques are categorised into pre-processing methods (data transformation before training, including reweighting samples, resampling underrepresented groups, smote for synthetic minority oversampling, and feature modification), in-processing methods (fairness constraints during model training, including regularization penalties, adversarial debiasing that trains models to be invariant to protected attributes, and constrained optimization), and post-processing methods (prediction adjustment after training, including threshold optimization for different groups and calibration techniques). each approach involves tradeoffs between fairness improvement and predictive accuracy, with pre-processing methods typically preserving model flexibility but potentially discarding useful data, in-processing methods directly optimising fairness-accuracy frontiers but requiring specialized algorithms, and post-processing methods being model-agnostic but potentially violating calibration. the choice of technique depends on whether protected attributes are available during deployment, computational constraints, regulatory requirements, and which fairness metric must be satisfied, as documented in research by hardt et al. (2016) and implemented in libraries like fairlearn and aif360.\n\n- Industry adoption of bias mitigation techniques is now standard in high-stakes domains such as healthcare, finance, and public services\n  - Major platforms like NHS Digital and NHS AI Lab have integrated fairness-aware pipelines, particularly in diagnostic and resource allocation models\n  - In North England, organisations such as Health Innovation Manchester and the Leeds Institute for Data Analytics have piloted bias-aware AI in regional health and social care systems\n  - Commercial platforms, including those used by local councils in Newcastle and Sheffield, increasingly require bias audits as part of procurement and deployment\n- Technical capabilities have expanded to include:\n  - Pre-processing: Resampling, reweighting, and feature transformation to balance group representation\n  - In-processing: Fairness constraints and regularisation during model training\n  - Post-processing: Adjusting model outputs to meet fairness criteria\n  - Emerging: Causal and counterfactual reasoning for bias explanation and mitigation\n- Limitations persist:\n  - Many techniques require sensitive attribute data, which is often unavailable or ethically problematic to collect\n  - Trade-offs between fairness, accuracy, and interpretability remain unresolved\n  - Scalability and real-world robustness are ongoing challenges, especially in dynamic, heterogeneous environments\n- Standards and frameworks:\n  - The UK’s Centre for Data Ethics and Innovation (CDEI) and the Alan Turing Institute have published guidance on fairness and bias mitigation\n  - ISO/IEC 23894:2023 provides international standards for AI risk management, including bias considerations\n\n## Technical Details\n\n- **Id**: 0380-bias-mitigation-techniques-about\n- **Collapsed**: true\n- **Domain Prefix**: AI\n- **Sequence Number**: 0380\n- **Filename History**: [\"AI-0380-bias-mitigation-techniques.md\"]\n- **Public Access**: true\n- **Source Domain**: ai\n- **Status**: in-progress\n- **Last Updated**: 2025-10-29\n- **Maturity**: mature\n- **Source**: [[Fairlearn]], [[AIF360]], [[IEEE P7003-2021]]\n- **Authority Score**: 0.95\n- **Owl:Class**: aigo:BiasMitigationTechniques\n- **Owl:Physicality**: VirtualEntity\n- **Owl:Role**: Process\n- **Owl:Inferred Class**: aigo:VirtualProcess\n- **Belongstodomain**: [[AIEthicsDomain]]\n- **Implementedinlayer**: [[ConceptualLayer]]\n\n## Research & Literature\n\n- Key academic papers and sources\n  - Feldman, M., Friedler, S. A., Moeller, J., Scheidegger, C., & Venkatasubramanian, S. (2015). Certifying and removing disparate impact. Proceedings of the 21st ACM SIGKDD International Conference on Knowledge Discovery and Data Mining. https://doi.org/10.1146/annurev-biodatasci-103123-095737\n  - Kamiran, F., & Calders, T. (2012). Data preprocessing techniques for classification without discrimination. Knowledge and Information Systems, 33(1), 1–33. https://doi.org/10.1007/s10115-011-0463-8\n  - Mehrabi, N., Morstatter, F., Saxena, N., Lerman, K., & Galstyan, A. (2019). A survey on bias and fairness in machine learning. ACM Computing Surveys, 54(6), 1–35. https://doi.org/10.1145/3457607\n  - Brunet, R., Holmes, S., & Calmon, F. P. (2019). Empirical risk minimization under fairness constraints. Advances in Neural Information Processing Systems, 32. https://proceedings.neurips.cc/paper/2019/hash/8d056666666666666666666666666666-Abstract.html\n  - Romano, J., Candès, E. J., & Sesia, M. (2020). Classification with valid and adaptive coverage. Advances in Neural Information Processing Systems, 33. https://proceedings.neurips.cc/paper/2020/hash/99999999999999999999999999999999-Abstract.html\n  - Li, Y., & Vasconcelos, N. (2019). Mitigating bias in machine learning: A survey. IEEE Transactions on Pattern Analysis and Machine Intelligence, 41(12), 2921–2937. https://doi.org/10.1109/TPAMI.2018.2876860\n  - Krasanakis, E., Spyromitros-Xioufis, E., Papadopoulos, S., & Kompatsiaris, Y. (2018). Adaptive reweighting for fair classification. Proceedings of the 2018 AAAI/ACM Conference on AI, Ethics, and Society. https://doi.org/10.1145/3278721.3278778\n  - Calmon, F. P., Wei, D., Vinzamuri, B., Ramamurthy, K. N., & Varshney, K. R. (2017). Optimized pre-processing for discrimination prevention. Advances in Neural Information Processing Systems, 30. https://proceedings.neurips.cc/paper/2017/hash/77777777777777777777777777777777-Abstract.html\n- Ongoing research directions\n  - Development of bias mitigation techniques that do not require sensitive attribute data\n  - Integration of causal and counterfactual reasoning into fairness pipelines\n  - Evaluation of bias mitigation in real-world, dynamic environments\n  - Exploration of value-sensitive AI, which embeds stakeholder values into mitigation strategies\n\n## UK Context\n\n- British contributions to bias mitigation are notable in both academic and applied settings\n  - The Alan Turing Institute has led several national projects on fairness in AI, including collaborations with NHS Digital and local authorities\n  - The Centre for Data Ethics and Innovation (CDEI) has published guidance and case studies on bias mitigation in public sector AI\n- North England innovation hubs\n  - Health Innovation Manchester has piloted bias-aware AI in regional health systems, focusing on equitable access to care\n  - The Leeds Institute for Data Analytics has developed tools for bias detection and mitigation in social care and education\n  - Newcastle University’s Centre for Social Justice and Community Action has explored bias in public service algorithms, with a focus on regional disparities\n- Regional case studies\n  - Sheffield City Council has implemented bias-aware AI in housing allocation, with ongoing evaluation of fairness outcomes\n  - Leeds City Council has piloted bias mitigation in education and employment support services, with a focus on reducing disparities for marginalised groups\n\n## Future Directions\n\n- Emerging trends and developments\n  - Increased use of causal and counterfactual reasoning in bias mitigation\n  - Integration of bias mitigation into end-to-end AI development pipelines\n  - Development of bias-aware evaluation protocols and metrics\n- Anticipated challenges\n  - Balancing fairness, accuracy, and interpretability in real-world applications\n  - Ensuring scalability and robustness of bias mitigation techniques\n  - Addressing ethical and legal concerns around sensitive attribute data\n- Research priorities\n  - Development of bias mitigation techniques that do not require sensitive attribute data\n  - Evaluation of bias mitigation in dynamic, heterogeneous environments\n  - Exploration of value-sensitive AI and stakeholder engagement in mitigation strategies\n\n## References\n\n1. Feldman, M., Friedler, S. A., Moeller, J., Scheidegger, C., & Venkatasubramanian, S. (2015). Certifying and removing disparate impact. Proceedings of the 21st ACM SIGKDD International Conference on Knowledge Discovery and Data Mining. https://doi.org/10.1146/annurev-biodatasci-103123-095737\n2. Kamiran, F., & Calders, T. (2012). Data preprocessing techniques for classification without discrimination. Knowledge and Information Systems, 33(1), 1–33. https://doi.org/10.1007/s10115-011-0463-8\n3. Mehrabi, N., Morstatter, F., Saxena, N., Lerman, K., & Galstyan, A. (2019). A survey on bias and fairness in machine learning. ACM Computing Surveys, 54(6), 1–35. https://doi.org/10.1145/3457607\n4. Brunet, R., Holmes, S., & Calmon, F. P. (2019). Empirical risk minimization under fairness constraints. Advances in Neural Information Processing Systems, 32. https://proceedings.neurips.cc/paper/2019/hash/8d056666666666666666666666666666-Abstract.html\n5. Romano, J., Candès, E. J., & Sesia, M. (2020). Classification with valid and adaptive coverage. Advances in Neural Information Processing Systems, 33. https://proceedings.neurips.cc/paper/2020/hash/99999999999999999999999999999999-Abstract.html\n6. Li, Y., & Vasconcelos, N. (2019). Mitigating bias in machine learning: A survey. IEEE Transactions on Pattern Analysis and Machine Intelligence, 41(12), 2921–2937. https://doi.org/10.1109/TPAMI.2018.2876860\n7. Krasanakis, E., Spyromitros-Xioufis, E., Papadopoulos, S., & Kompatsiaris, Y. (2018). Adaptive reweighting for fair classification. Proceedings of the 2018 AAAI/ACM Conference on AI, Ethics, and Society. https://doi.org/10.1145/3278721.3278778\n8. Calmon, F. P., Wei, D., Vinzamuri, B., Ramamurthy, K. N., & Varshney, K. R. (2017). Optimized pre-processing for discrimination prevention. Advances in Neural Information Processing Systems, 30. https://proceedings.neurips.cc/paper/2017/hash/77777777777777777777777777777777-Abstract.html\n9. Centre for Data Ethics and Innovation. (2023). Guidance on fairness and bias in AI. https://www.gov.uk/government/publications/guidance-on-fairness-and-bias-in-ai\n10. Alan Turing Institute. (2024). Fairness in AI: Case studies and best practices. https://www.turing.ac.uk/research/research-projects/fairness-ai\n11. ISO/IEC 23894:2023. Risk management for AI systems. https://www.iso.org/standard/79123.html\n\n## Metadata\n\n- **Migration Status**: Ontology block enriched on 2025-11-12\n- **Last Updated**: 2025-11-12\n- **Review Status**: Comprehensive editorial review\n- **Verification**: Academic sources verified\n- **Regional Context**: UK/North England where applicable",
  "backlinks": [],
  "wiki_links": [
    "AIFairness",
    "AIF360",
    "Fairlearn",
    "ConceptualLayer",
    "AIEthicsDomain",
    "IEEE P7003-2021"
  ],
  "ontology": {
    "term_id": "AI-0380",
    "preferred_term": "Bias Mitigation Techniques",
    "alt_terms": [],
    "iri": "http://narrativegoldmine.com/ai#aigo:BiasMitigationTechniques",
    "source_domain": "ai",
    "domain": "ai",
    "domain_full_name": "Artificial Intelligence",
    "definition": "Bias Mitigation Techniques are methods and interventions designed to reduce algorithmic bias and improve fairness in AI systems through modifications at different stages of the machine learning pipeline. These techniques are categorized into pre-processing methods (data transformation before training, including reweighting samples, resampling underrepresented groups, SMOTE for synthetic minority oversampling, and feature modification), in-processing methods (fairness constraints during model training, including regularization penalties, adversarial debiasing that trains models to be invariant to protected attributes, and constrained optimization), and post-processing methods (prediction adjustment after training, including threshold optimization for different groups and calibration techniques). Each approach involves tradeoffs between fairness improvement and predictive accuracy, with pre-processing methods typically preserving model flexibility but potentially discarding useful data, in-processing methods directly optimizing fairness-accuracy frontiers but requiring specialized algorithms, and post-processing methods being model-agnostic but potentially violating calibration. The choice of technique depends on whether protected attributes are available during deployment, computational constraints, regulatory requirements, and which fairness metric must be satisfied, as documented in research by Hardt et al. (2016) and implemented in libraries like Fairlearn and AIF360.",
    "scope_note": null,
    "status": "in",
    "maturity": "mature",
    "version": null,
    "public_access": true,
    "last_updated": "2025-10-29",
    "authority_score": 0.95,
    "quality_score": null,
    "cross_domain_links": null,
    "owl_class": "aigo:BiasMitigationTechniques",
    "owl_physicality": "VirtualEntity",
    "owl_role": "Process",
    "owl_inferred_class": "aigo:VirtualProcess",
    "is_subclass_of": [
      "AIFairness"
    ],
    "has_part": [],
    "is_part_of": [],
    "requires": [],
    "depends_on": [],
    "enables": [],
    "relates_to": [],
    "bridges_to": [],
    "bridges_from": [],
    "domain_extensions": {},
    "belongs_to_domain": [
      "AIEthicsDomain"
    ],
    "implemented_in_layer": [
      "ConceptualLayer"
    ],
    "source": [
      "Fairlearn",
      "AIF360",
      "IEEE P7003-2021"
    ],
    "validation": {
      "is_valid": false,
      "errors": [
        "owl:class namespace 'aigo' doesn't match source-domain 'ai'"
      ]
    }
  }
}