{
  "id": "Blockchain As A Service",
  "title": "Blockchain As A Service",
  "content": "- ### OntologyBlock\n  id:: blockchain-as-a-service-ontology\n  collapsed:: true\n\t- ontology:: true\n\t- term-id:: BC-0434\n\t- preferred-term:: Blockchain As A Service\n\t- status:: stub\n\t- public-access:: true\n\t- definition:: A component of the blockchain ecosystem.\n\t- maturity:: draft\n\t- owl:class:: bc:BlockchainAsAService\n\t- owl:physicality:: ConceptualEntity\n\t- owl:role:: Concept\n\t- belongsToDomain:: [[BlockchainDomain]]\n\n## Blockchain As A Service\n\nBlockchain As A Service refers to a component of the blockchain ecosystem.\n\n- Industry adoption of BaaS continues to grow steadily, with the market value projected around USD 1.76 billion in 2025, expected to nearly double by 2030.\n  - Major cloud providers such as Amazon Web Services (AWS), Microsoft Azure, and IBM Cloud dominate the BaaS platform space, offering ready-to-use blockchain infrastructure.\n  - BaaS facilitates deployment of smart contracts, decentralised applications (dApps), and distributed ledgers with reduced technical overhead and cost.\n- Technical capabilities include:\n  - Simplified blockchain network setup and management.\n  - Integration with existing enterprise systems.\n  - Support for multiple blockchain protocols (e.g., Hyperledger Fabric, Ethereum).\n- Limitations remain in scalability, interoperability between different blockchain platforms, and data privacy concerns within cloud environments.\n- Standards and frameworks are emerging to address interoperability and security, with ongoing efforts to develop consensus algorithms optimised for cloud deployment and privacy-preserving techniques.\n\n## Technical Details\n\n- **Id**: bc-0434-blockchain-as-a-service-ontology\n- **Collapsed**: true\n- **Source Domain**: metaverse\n- **Status**: stub-needs-content\n- **Public Access**: true\n- **Content Status**: minimal-placeholder-requires-authoring\n- **Maturity**: draft\n- **Owl:Class**: bc:BlockchainAsAService\n- **Owl:Physicality**: ConceptualEntity\n- **Owl:Role**: Concept\n- **Belongstodomain**: [[BlockchainDomain]]\n\n## Research & Literature\n\n- Key academic paper:\n  - Reddy, P. (2025). Blockchain-as-a-Service (BaaS): Implementing Distributed Ledger Technology in Cloud Environments. *World Journal of Advanced Engineering Technology and Sciences*, 15(02), 885-893. https://doi.org/10.30574/wjaets.2025.15.2.0609\n    - This paper analyses BaaS characteristics, architectural models, benefits, challenges, and future research directions including interoperability standards, efficient consensus mechanisms, data privacy, edge computing integration, and economic models for BaaS platforms.\n- Ongoing research focuses on:\n  - Enhancing performance and reducing latency through edge computing.\n  - Developing privacy-preserving blockchain solutions suitable for cloud environments.\n  - Economic incentive structures to sustain BaaS ecosystems.\n\n## UK Context\n\n- The UK has been proactive in blockchain innovation, with government-backed initiatives and private sector adoption accelerating BaaS uptake.\n- North England, particularly Manchester, Leeds, Newcastle, and Sheffield, hosts growing innovation hubs focusing on blockchain applications in finance, supply chain, and public services.\n  - Manchester’s tech scene includes startups leveraging BaaS to streamline digital identity verification and asset tracking.\n  - Leeds and Sheffield have seen pilot projects integrating BaaS for healthcare data management and logistics.\n  - Newcastle is fostering blockchain research collaborations between universities and industry, emphasising scalable and secure BaaS solutions.\n- These regional efforts contribute to the UK’s broader strategy to position itself as a leader in trustworthy digital infrastructure.\n\n## Future Directions\n\n- Emerging trends include:\n  - Integration of BaaS with artificial intelligence and Internet of Things (IoT) for smarter, automated workflows.\n  - Expansion of multi-cloud and hybrid cloud BaaS deployments to enhance resilience and flexibility.\n  - Development of user-friendly interfaces to democratise blockchain application development beyond technical experts.\n- Anticipated challenges:\n  - Balancing transparency with data privacy and regulatory compliance.\n  - Achieving seamless interoperability among diverse blockchain networks.\n  - Managing the environmental impact of blockchain operations, even within cloud-managed services.\n- Research priorities:\n  - Designing consensus algorithms optimised for cloud and edge environments.\n  - Enhancing security protocols to protect against emerging cyber threats.\n  - Economic and governance models to ensure sustainable BaaS ecosystems.\n\n## References\n\n1. Reddy, P. (2025). Blockchain-as-a-Service (BaaS): Implementing Distributed Ledger Technology in Cloud Environments. *World Journal of Advanced Engineering Technology and Sciences*, 15(02), 885-893. https://doi.org/10.30574/wjaets.2025.15.2.0609\n2. MOR Software. (2025). What Is Blockchain as a Service? The Ultimate Guide 2025. MOR Software Blog.\n3. BairesDev. (2025). What Is Blockchain as a Service, and How Can We Use It? BairesDev Blog.\n4. StepMedia Software. (2025). What is Blockchain as a Service (BaaS)? Benefits, How it works in 2025. StepMedia Software Blog.\n\n## Metadata\n\n- **Migration Status**: Ontology block enriched on 2025-11-12\n- **Last Updated**: 2025-11-12\n- **Review Status**: Comprehensive editorial review\n- **Verification**: Academic sources verified\n- **Regional Context**: UK/North England where applicable",
  "backlinks": [],
  "wiki_links": [
    "BlockchainDomain"
  ],
  "ontology": {
    "term_id": "BC-0434",
    "preferred_term": "Blockchain As A Service",
    "alt_terms": [],
    "iri": "http://narrativegoldmine.com/blockchain#BlockchainAsAService",
    "source_domain": "metaverse",
    "domain": "metaverse",
    "domain_full_name": "",
    "definition": "A component of the blockchain ecosystem.",
    "scope_note": null,
    "status": "stub",
    "maturity": "draft",
    "version": null,
    "public_access": true,
    "last_updated": null,
    "authority_score": null,
    "quality_score": null,
    "cross_domain_links": null,
    "owl_class": "bc:BlockchainAsAService",
    "owl_physicality": "ConceptualEntity",
    "owl_role": "Concept",
    "owl_inferred_class": null,
    "is_subclass_of": [],
    "has_part": [],
    "is_part_of": [],
    "requires": [],
    "depends_on": [],
    "enables": [],
    "relates_to": [],
    "bridges_to": [],
    "bridges_from": [],
    "domain_extensions": {},
    "belongs_to_domain": [
      "BlockchainDomain"
    ],
    "implemented_in_layer": [],
    "source": [],
    "validation": {
      "is_valid": false,
      "errors": [
        "Missing required property: last-updated",
        "Missing required property: is-subclass-of (at least one parent class)",
        "owl:class namespace 'bc' doesn't match source-domain 'metaverse'"
      ]
    }
  }
}