{
  "id": "Carbon Credit Tracking",
  "title": "Carbon Credit Tracking",
  "content": "- ### OntologyBlock\n  id:: carbon-credit-tracking-ontology\n  collapsed:: true\n\t- ontology:: true\n\t- term-id:: BC-0450\n\t- preferred-term:: Carbon Credit Tracking\n\t- status:: stub\n\t- public-access:: true\n\t- definition:: A component of the blockchain ecosystem.\n\t- maturity:: draft\n\t- owl:class:: bc:CarbonCreditTracking\n\t- owl:physicality:: ConceptualEntity\n\t- owl:role:: Concept\n\t- belongsToDomain:: [[BlockchainDomain]]\n\n## Carbon Credit Tracking\n\nCarbon Credit Tracking refers to a component of the blockchain ecosystem.\n\n- Industry adoption and implementations\n\t- Blockchain-based carbon credit platforms are now widely adopted, with major registries and financial institutions integrating distributed ledger technology\n\t- Leading platforms include KlimaDAO, Toucan, Carbonmark, and Verraâ€™s blockchain-enabled registry solutions\n\t- Tokenisation of carbon credits allows for fractional ownership and microtransactions, increasing accessibility for smaller investors and projects\n\t- Smart contracts automate verification and settlement, reducing intermediary costs and enhancing efficiency\n- Notable organisations and platforms\n\t- Kinexys (J.P. Morgan) has developed a blockchain application for tokenising carbon market registries, with testing underway by S&P Global, EcoRegistry, and the International Carbon Registry\n\t- Nasdaq has invested in blockchain solutions to digitise carbon credit registries and streamline pre-issuance processes\n\t- Carbonmark automates purchase and retirement flows, integrates with fintech applications, and supports fractionalised credits\n- UK and North England examples where relevant\n\t- UK-based fintechs and environmental consultancies are increasingly adopting blockchain for carbon credit tracking, particularly in Manchester, Leeds, and Newcastle\n\t- The Northern Powerhouse initiative has supported several pilot projects exploring blockchain for environmental asset management, including carbon credits\n\t- Local authorities in Sheffield have partnered with tech firms to pilot blockchain-based tracking for municipal carbon offsetting schemes\n- Technical capabilities and limitations\n\t- Blockchain provides a tamper-proof ledger for the entire lifecycle of carbon credits, from issuance to retirement\n\t- Integration with IoT sensors, satellites, and AI enables real-time monitoring and automated verification\n\t- Limitations include upfront development costs, transaction fees, and the need for standardisation across platforms\n- Standards and frameworks\n\t- Regulatory bodies are developing standardised smart contract frameworks to harmonise cross-border carbon trading protocols\n\t- The International Carbon Registry and other major registries are adopting blockchain standards to ensure uniformity and trust\n\n## Technical Details\n\n- **Id**: bc-0450-carbon-credit-tracking-ontology\n- **Collapsed**: true\n- **Source Domain**: metaverse\n- **Status**: stub-needs-content\n- **Public Access**: true\n- **Content Status**: minimal-placeholder-requires-authoring\n- **Maturity**: draft\n- **Owl:Class**: bc:CarbonCreditTracking\n- **Owl:Physicality**: ConceptualEntity\n- **Owl:Role**: Concept\n- **Belongstodomain**: [[BlockchainDomain]]\n\n## Research & Literature\n\n- Key academic papers and sources\n\t- Sugumaran, D., Dhanapal, J., & Johnson, R. (2023). Revolutionizing Carbon Credit and Blockchain Solutions for Environmental Asset Management. Grassroots Journals, 8(2), 27-45. https://grassrootsjournals.org/gjnr/nr.08-02-27-sugumaran-dhanapal-johnson.pdf\n\t- Brysa Insights. (2025). How Blockchain Is Revolutionising Carbon Credit Tracking? Brysa. https://brysa.co.uk/insights/blockchain-carbon-credits-tracking\n\t- Fairatmos Insights. (2025). Blockchain Carbon Credits: Innovation or Hype? Fairatmos. https://www.fairatmos.com/blog/blockchain-carbon-credits-innovation-or-hype/\n\t- Intel Market Research. (2025). Blockchain-based Carbon Credit Platform Development Market 2025-2032. Intel Market Research. https://www.intelmarketresearch.com/blockchain-based-carbon-credit-platform-development-2025-2032-529-5100\n\t- Bitdeal. (2025). The Definitive Guide to Carbon Credit Marketplace Development in 2025. Bitdeal. https://www.bitdeal.net/the-definitive-guide-to-carbon-credit-marketplace-development-in-2025\n\t- Carbon Credits. (2025). Are Nature-Based Solutions and Blockchain the Future of Carbon Credits? Carbon Credits. https://carboncredits.com/are-nature-based-solutions-and-blockchain-the-future-of-carbon-credits/\n\t- J.P. Morgan. (2025). Kinexys Launches Carbon Market Blockchain Tokenization. J.P. Morgan. https://carbonmark.com/post/how-blockchain-is-shaping-climate-action-highlights-from-earth-day-2025-panel\n- Ongoing research directions\n\t- Exploring the integration of blockchain with remote sensing technologies for real-time carbon monitoring\n\t- Investigating the potential for decentralised autonomous organisations (DAOs) to govern carbon markets\n\t- Assessing the economic and environmental impacts of tokenised carbon credits\n\n## UK Context\n\n- British contributions and implementations\n\t- The UK has been at the forefront of adopting blockchain for carbon credit tracking, with several fintechs and environmental consultancies leading the way\n\t- The government has supported pilot projects and research initiatives to explore the potential of blockchain in environmental asset management\n- North England innovation hubs (if relevant)\n\t- Manchester, Leeds, and Newcastle have emerged as key innovation hubs for blockchain and environmental technology\n\t- The Northern Powerhouse initiative has funded several projects exploring blockchain for carbon credit tracking and other sustainability applications\n- Regional case studies\n\t- Sheffield City Council has partnered with local tech firms to pilot blockchain-based tracking for municipal carbon offsetting schemes\n\t- Leeds-based fintechs have developed blockchain platforms for carbon credit trading, focusing on transparency and accessibility\n\n## Future Directions\n\n- Emerging trends and developments\n\t- Increased adoption of blockchain for carbon credit tracking in both compliance and voluntary markets\n\t- Development of standardised smart contract frameworks and interoperable platforms\n\t- Integration of blockchain with remote sensing and AI for real-time monitoring and automated verification\n- Anticipated challenges\n\t- Ensuring regulatory alignment and standardisation across platforms\n\t- Addressing upfront development costs and transaction fees\n\t- Overcoming technical and operational barriers to widespread adoption\n- Research priorities\n\t- Exploring the potential for DAOs to govern carbon markets\n\t- Assessing the economic and environmental impacts of tokenised carbon credits\n\t- Investigating the integration of blockchain with remote sensing technologies for real-time carbon monitoring\n\n## References\n\n1. Sugumaran, D., Dhanapal, J., & Johnson, R. (2023). Revolutionizing Carbon Credit and Blockchain Solutions for Environmental Asset Management. Grassroots Journals, 8(2), 27-45. https://grassrootsjournals.org/gjnr/nr.08-02-27-sugumaran-dhanapal-johnson.pdf\n2. Brysa Insights. (2025). How Blockchain Is Revolutionising Carbon Credit Tracking? Brysa. https://brysa.co.uk/insights/blockchain-carbon-credits-tracking\n3. Fairatmos Insights. (2025). Blockchain Carbon Credits: Innovation or Hype? Fairatmos. https://www.fairatmos.com/blog/blockchain-carbon-credits-innovation-or-hype/\n4. Intel Market Research. (2025). Blockchain-based Carbon Credit Platform Development Market 2025-2032. Intel Market Research. https://www.intelmarketresearch.com/blockchain-based-carbon-credit-platform-development-2025-2032-529-5100\n5. Bitdeal. (2025). The Definitive Guide to Carbon Credit Marketplace Development in 2025. Bitdeal. https://www.bitdeal.net/the-definitive-guide-to-carbon-credit-marketplace-development-in-2025\n6. Carbon Credits. (2025). Are Nature-Based Solutions and Blockchain the Future of Carbon Credits? Carbon Credits. https://carboncredits.com/are-nature-based-solutions-and-blockchain-the-future-of-carbon-credits/\n7. J.P. Morgan. (2025). Kinexys Launches Carbon Market Blockchain Tokenization. J.P. Morgan. https://carbonmark.com/post/how-blockchain-is-shaping-climate-action-highlights-from-earth-day-2025-panel\n\n## Metadata\n\n- **Migration Status**: Ontology block enriched on 2025-11-12\n- **Last Updated**: 2025-11-12\n- **Review Status**: Comprehensive editorial review\n- **Verification**: Academic sources verified\n- **Regional Context**: UK/North England where applicable",
  "backlinks": [],
  "wiki_links": [
    "BlockchainDomain"
  ],
  "ontology": {
    "term_id": "BC-0450",
    "preferred_term": "Carbon Credit Tracking",
    "alt_terms": [],
    "iri": "http://narrativegoldmine.com/blockchain#CarbonCreditTracking",
    "source_domain": "metaverse",
    "domain": "metaverse",
    "domain_full_name": "",
    "definition": "A component of the blockchain ecosystem.",
    "scope_note": null,
    "status": "stub",
    "maturity": "draft",
    "version": null,
    "public_access": true,
    "last_updated": null,
    "authority_score": null,
    "quality_score": null,
    "cross_domain_links": null,
    "owl_class": "bc:CarbonCreditTracking",
    "owl_physicality": "ConceptualEntity",
    "owl_role": "Concept",
    "owl_inferred_class": null,
    "is_subclass_of": [],
    "has_part": [],
    "is_part_of": [],
    "requires": [],
    "depends_on": [],
    "enables": [],
    "relates_to": [],
    "bridges_to": [],
    "bridges_from": [],
    "domain_extensions": {},
    "belongs_to_domain": [
      "BlockchainDomain"
    ],
    "implemented_in_layer": [],
    "source": [],
    "validation": {
      "is_valid": false,
      "errors": [
        "Missing required property: last-updated",
        "Missing required property: is-subclass-of (at least one parent class)",
        "owl:class namespace 'bc' doesn't match source-domain 'metaverse'"
      ]
    }
  }
}