{
  "id": "Carbon Credit Token",
  "title": "Carbon Credit Token",
  "content": "- ### OntologyBlock\n  id:: carboncredittoken-ontology\n  collapsed:: true\n\t- ontology:: true\n\t- term-id:: 20130\n\t- preferred-term:: Carbon Credit Token\n\t- source-domain:: metaverse\n\t- public-access:: true\n\n\n\n\n### OWL Classification\n\t- owl:class:: mv:CarbonCreditToken\n\t- owl:physicality:: VirtualEntity\n\t- owl:role:: Object\n\t- owl:inferred-class:: mv:VirtualObject\n\n### Domain & Architecture\n\t- belongsToDomain:: [[TrustAndGovernanceDomain]], [[VirtualEconomyDomain]]\n\t- implementedInLayer:: [[DataLayer]], [[SmartContractLayer]]\n\t- maturity:: mature\n\n### Relationships\nid:: carboncredittoken-relationships\n\t\t- is-subclass-of:: [[Blockchain]]\n\t\t- has-part:: [[Carbon Offset Certificate]], [[Verification Metadata]], [[Token Smart Contract]], [[Blockchain Record]]\n\t\t- is-part-of:: [[Virtual Economy]], [[Environmental Asset Market]], [[Sustainability Framework]]\n\t\t- requires:: [[Blockchain]], [[Smart Contract]], [[Verification Authority]], [[Digital Wallet]]\n\t\t- depends-on:: [[Carbon Registry]], [[Verification Standard]], [[Trading Platform]]\n\t\t- enables:: [[Emissions Trading]], [[Carbon Offset Trading]], [[Environmental Compliance]], [[Sustainability Reporting]]\n\t- #### OWL Axioms\n\t  id:: carboncredittoken-owl-axioms\n\t  collapsed:: true\n\t\t- ```clojure\n\t\t  Declaration(Class(mv:CarbonCreditToken))\n\n\t\t  # Classification\n\t\t  SubClassOf(mv:CarbonCreditToken mv:VirtualEntity)\n\t\t  SubClassOf(mv:CarbonCreditToken mv:Object)\n\t\t  SubClassOf(mv:CarbonCreditToken mv:DigitalAsset)\n\n\t\t  # A Carbon Credit Token must have verification metadata\n\t\t  SubClassOf(mv:CarbonCreditToken\n\t\t    ObjectSomeValuesFrom(mv:hasPart mv:VerificationMetadata)\n\t\t  )\n\n\t\t  # A Carbon Credit Token must represent carbon offset value\n\t\t  SubClassOf(mv:CarbonCreditToken\n\t\t    ObjectSomeValuesFrom(mv:represents mv:CarbonOffsetCertificate)\n\t\t  )\n\n\t\t  # A Carbon Credit Token must be verifiable\n\t\t  SubClassOf(mv:CarbonCreditToken\n\t\t    ObjectSomeValuesFrom(mv:verifiedBy mv:VerificationAuthority)\n\t\t  )\n\n\t\t  # A Carbon Credit Token requires blockchain for transparency\n\t\t  SubClassOf(mv:CarbonCreditToken\n\t\t    ObjectSomeValuesFrom(mv:requires bc:Blockchain)\n\t\t  )\n\n\t\t  # A Carbon Credit Token enables emissions trading\n\t\t  SubClassOf(mv:CarbonCreditToken\n\t\t    ObjectSomeValuesFrom(mv:enables mv:EmissionsTrading)\n\t\t  )\n\n\t\t  # Domain classification\n\t\t  SubClassOf(mv:CarbonCreditToken\n\t\t    ObjectSomeValuesFrom(mv:belongsToDomain mv:VirtualEconomyDomain)\n\t\t  )\n\t\t  SubClassOf(mv:CarbonCreditToken\n\t\t    ObjectSomeValuesFrom(mv:belongsToDomain mv:TrustAndGovernanceDomain)\n\t\t  )\n\t\t  SubClassOf(mv:CarbonCreditToken\n\t\t    ObjectSomeValuesFrom(mv:implementedInLayer mv:DataLayer)\n\t\t  )\n\n\t\t  # Supporting classes\n\t\t  Declaration(Class(mv:CarbonOffsetCertificate))\n\t\t  SubClassOf(mv:CarbonOffsetCertificate mv:VirtualObject)\n\n\t\t  Declaration(Class(mv:VerificationAuthority))\n\t\t  SubClassOf(mv:VerificationAuthority mv:VirtualAgent)\n\n\t\t  Declaration(Class(mv:EmissionsTrading))\n\t\t  SubClassOf(mv:EmissionsTrading mv:VirtualProcess)\n\n  # Property characteristics\n  TransitiveObjectProperty(dt:ispartof)\n\n  # Property characteristics\n  AsymmetricObjectProperty(dt:requires)\n\n  # Property characteristics\n  AsymmetricObjectProperty(dt:dependson)\n\n  # Property characteristics\n  AsymmetricObjectProperty(dt:enables)\n```\n- ## About Carbon Credit Tokens\n  id:: carboncredittoken-about\n\t- Carbon Credit Tokens are **blockchain-based digital assets** that represent verified units of carbon dioxide equivalent (CO2e) emissions reductions or removals. Each token typically represents one metric ton of CO2e that has been prevented from entering the atmosphere or removed from it through verified projects such as reforestation, renewable energy, carbon capture, or methane reduction initiatives. These tokens enable transparent, traceable, and liquid markets for carbon offsets, facilitating corporate and individual climate action.\n\t- The tokenization of carbon credits addresses longstanding challenges in voluntary and compliance carbon markets, including double-counting, lack of transparency, complex verification processes, and limited liquidity. By leveraging blockchain technology, carbon credit tokens provide immutable records of ownership, automated verification workflows, fractional ownership capabilities, and seamless cross-border trading. This infrastructure is increasingly important for metaverse platforms and virtual economies integrating sustainability metrics into their operations.\n\t- Carbon credit tokens bridge physical environmental impact with digital economic systems, enabling virtual world operators, gaming platforms, and metaverse infrastructure providers to measure, report, and offset their carbon footprints. As climate commitments intensify and regulatory frameworks like the EU's Carbon Border Adjustment Mechanism (CBAM) expand, tokenized carbon credits are becoming essential instruments for transparent environmental accounting in both physical and digital economies.\n\t- ### Key Characteristics\n\t  id:: carboncredittoken-characteristics\n\t\t- Blockchain-based representation of verified CO2e emissions reductions\n\t\t- One token typically equals one metric ton of CO2e offset\n\t\t- Immutable ownership records preventing double-counting\n\t\t- Transparent provenance tracking from project to retirement\n\t\t- Fractional ownership enabling micro-offset transactions\n\t\t- Smart contract automation for issuance, transfer, and retirement\n\t\t- Interoperable across multiple blockchain platforms and standards\n\t\t- Integration with carbon registries and verification bodies\n\t\t- Real-time market pricing and liquidity\n\t\t- Programmable compliance and reporting features\n\t\t- Metadata linking to underlying offset projects and certifications\n\t\t- Retirement mechanisms preventing token reuse after offsetting\n\t- ### Technical Components\n\t  id:: carboncredittoken-components\n\t\t- [[Carbon Offset Certificate]] - Underlying verified emissions reduction unit\n\t\t- [[Verification Metadata]] - Project details, methodology, vintage, co-benefits, validation reports\n\t\t- [[Token Smart Contract]] - ERC-20/721/1155 contract governing token behaviour\n\t\t- [[Blockchain Record]] - Distributed ledger tracking issuance, transfers, and retirement\n\t\t- [[Carbon Registry]] - Authoritative database of verified carbon projects (Verra, Gold Standard)\n\t\t- [[Verification Authority]] - Third-party validator (DNV, SCS Global, Carbon Trust)\n\t\t- [[Digital Wallet]] - Custody solution for holding and transferring tokens\n\t\t- [[Trading Platform]] - Marketplace infrastructure for price discovery and exchange\n\t\t- [[Oracle Integration]] - Data feeds connecting on-chain tokens to off-chain verification\n\t\t- [[Retirement Registry]] - Permanent record of retired credits for compliance reporting\n\t\t- [[API Interfaces]] - Integration endpoints for corporate accounting systems\n\t\t- [[Multi-signature Controls]] - Governance mechanisms for project operators\n\t- ### Functional Capabilities\n\t  id:: carboncredittoken-capabilities\n\t\t- **Emissions Trading**: Enable transparent buying and selling of carbon offsets in global markets with real-time settlement\n\t\t- **Carbon Offset Tracking**: Maintain complete provenance from project generation through retirement with audit trails\n\t\t- **Environmental Compliance**: Support regulatory reporting requirements for carbon neutrality commitments and disclosures\n\t\t- **Fractional Ownership**: Allow small-scale participants to purchase partial credits for micro-offsetting\n\t\t- **Automated Verification**: Smart contracts integrate with oracles to verify project status and credit validity\n\t\t- **Retirement Mechanism**: Permanently remove credits from circulation when used for offsetting, preventing double-counting\n\t\t- **Cross-Platform Trading**: Interoperate across different blockchain networks and carbon marketplaces\n\t\t- **Transparent Pricing**: Public order books and transaction histories enabling efficient price discovery\n\t\t- **Programmable Compliance**: Automated offsetting rules tied to measured emissions or business activities\n\t\t- **Co-Benefit Documentation**: Track additional impacts beyond carbon (biodiversity, community development, SDG alignment)\n\t\t- **Vintage Management**: Organise credits by project year and methodology version\n\t\t- **Batch Operations**: Corporate buyers can acquire and retire large quantities efficiently\n\t- ### Token Standards\n\t  id:: carboncredittoken-standards-tech\n\t\t- **ERC-20**: Fungible token standard for commodity-like carbon credits with identical characteristics\n\t\t- **ERC-721**: NFT standard for unique carbon credits with specific project and vintage attributes\n\t\t- **ERC-1155**: Hybrid standard supporting both fungible batches and unique project tokens\n\t\t- **Tokenized Carbon Credit Standard**: Emerging specifications for carbon-specific metadata and behaviours\n\t\t- **KlimaDAO BCT**: Base Carbon Tonne reference token backed by Verra credits\n\t\t- **Toucan Protocol**: Bridge infrastructure connecting traditional carbon credits to blockchain\n\t\t- **Carbon Credit Metadata Schema**: Standardized fields for project type, location, methodology, vintage, co-benefits\n\t\t- **Retirement Proof Standard**: Cryptographic proof of credit retirement for compliance verification\n\t- ### Use Cases\n\t  id:: carboncredittoken-use-cases\n\t\t- **Corporate Sustainability**: Companies purchase and retire tokens to meet net-zero commitments and scope 3 emissions targets (Microsoft, Stripe, Shopify climate programmes)\n\t\t- **Metaverse Carbon Neutrality**: Virtual world platforms offset server energy consumption and user activity emissions (Decentraland sustainability initiatives)\n\t\t- **Gaming Industry Offsets**: Game developers offset player device energy use and data centre operations (Ubisoft, Niantic)\n\t\t- **NFT Carbon Offsetting**: NFT platforms integrate automatic carbon offsets for minting and trading transactions (Offsetra, Aerial)\n\t\t- **DeFi Climate Protocols**: Decentralized finance platforms incorporating carbon credits as collateral or yield-bearing assets (KlimaDAO, Flowcarbon)\n\t\t- **Supply Chain Carbon Accounting**: Track and offset emissions across global logistics networks with tokenized credits\n\t\t- **Aviation Offsets**: Airlines offer tokenized carbon offsets to passengers for flight emissions\n\t\t- **E-commerce Carbon Neutrality**: Online retailers provide checkout options for shipping emission offsets\n\t\t- **Renewable Energy Certificates**: Bundled renewable energy credits with carbon offsets as composite tokens\n\t\t- **Individual Carbon Footprint**: Consumer apps enabling personal carbon accounting and micro-offsetting (Wren, Joro)\n\t\t- **Carbon Credit Derivatives**: Financial instruments and futures based on tokenized carbon credits\n\t\t- **Sustainability-Linked Bonds**: Tokenized bonds with interest rates tied to carbon offset performance\n\t- ### Verification Standards\n\t  id:: carboncredittoken-verification\n\t\t- **Verra VCS**: Verified Carbon Standard, largest voluntary carbon market registry\n\t\t- **Gold Standard**: Focus on sustainable development co-benefits alongside carbon reduction\n\t\t- **Climate Action Reserve (CAR)**: North American offset protocols with rigorous methodology\n\t\t- **American Carbon Registry (ACR)**: Forest carbon and industrial gas project standards\n\t\t- **ISO 14064**: International standard for greenhouse gas accounting and verification\n\t\t- **ISO 14065**: Requirements for validation and verification bodies\n\t\t- **Plan Vivo**: Community-focused carbon projects with livelihood benefits\n\t\t- **Global Carbon Council (GCC)**: Islamic Development Bank carbon credit standard\n\t\t- **CarbonFix Standard**: Forestry and land-use carbon sequestration\n\t\t- **CORSIA**: International aviation carbon offset standard (ICAO)\n\t- ### Market Infrastructure\n\t  id:: carboncredittoken-market\n\t\t- **Toucan Protocol**: Bridges traditional carbon credits onto blockchain as TCO2 tokens\n\t\t- **KlimaDAO**: Carbon-backed algorithmic reserve currency incentivizing offset retirement\n\t\t- **Flowcarbon**: Tokenization platform for high-quality carbon credits (backed by a16z)\n\t\t- **Moss.Earth**: Amazon rainforest preservation credits as MCO2 tokens\n\t\t- **Nori**: Marketplace for agricultural carbon removal credits as NRT tokens\n\t\t- **Regen Network**: Ecological asset marketplace with focus on regenerative agriculture\n\t\t- **Coorest**: NFTree tokens representing CO2 absorption by specific trees\n\t\t- **Thallo**: Carbon credit marketplace aggregating multiple registries\n\t\t- **Carbonplace**: Institutional-grade carbon trading infrastructure\n\t\t- **AirCarbon Exchange**: Regulated carbon and environmental commodity exchange\n\t- ### Challenges and Considerations\n\t  id:: carboncredittoken-challenges\n\t\t- **Quality Variation**: Not all carbon credits represent equivalent real-world impact; project quality varies significantly\n\t\t- **Additionality**: Ensuring projects wouldn't have happened without carbon finance (counterfactual baseline)\n\t\t- **Permanence**: Long-term storage risk, especially for nature-based solutions (forest fires, disease)\n\t\t- **Leakage**: Emissions reduction in one location causing increases elsewhere (displacement)\n\t\t- **Double-Counting**: Preventing same emissions reduction from being claimed multiple times\n\t\t- **Regulatory Uncertainty**: Evolving compliance frameworks and tax treatment of tokenized credits\n\t\t- **Greenwashing**: Risk of superficial offsetting replacing genuine emissions reductions\n\t\t- **Blockchain Energy**: Energy consumption of blockchain networks conflicting with climate goals (mitigated by proof-of-stake)\n\t\t- **Price Volatility**: Token prices fluctuating based on crypto market dynamics rather than carbon fundamentals\n\t\t- **Verification Costs**: Third-party validation adding overhead to small-scale projects\n\t\t- **Interoperability**: Fragmentation across multiple registries, blockchains, and standards\n\t\t- **Retirement Accounting**: Complexity of linking on-chain retirement to off-chain registry systems\n\t- ### Regulatory Landscape\n\t  id:: carboncredittoken-regulatory\n\t\t- **EU ETS**: European Union Emissions Trading System, largest compliance carbon market\n\t\t- **CBAM**: Carbon Border Adjustment Mechanism imposing carbon price on imports\n\t\t- **California Cap-and-Trade**: State-level compliance carbon market\n\t\t- **CORSIA**: International aviation carbon offsetting scheme (ICAO)\n\t\t- **Paris Agreement Article 6**: International carbon market mechanisms for NDC achievement\n\t\t- **UK ETS**: Post-Brexit carbon trading system\n\t\t- **ICROA**: International Carbon Reduction and Offset Alliance quality standards\n\t\t- **SBTi**: Science Based Targets initiative corporate climate commitment framework\n\t\t- **TCFD**: Task Force on Climate-related Financial Disclosures reporting requirements\n\t\t- **SEC Climate Disclosure**: Proposed rules requiring carbon emissions reporting\n\t\t- **Singapore Carbon Tax**: Carbon pricing mechanism with offset provisions\n\t\t- **Voluntary Carbon Markets Integrity Initiative (VCMI)**: Guidelines for high-integrity voluntary offsets\n\t- ### Integration with Metaverse\n\t  id:: carboncredittoken-metaverse\n\t\t- **Platform Carbon Accounting**: Virtual worlds measure and offset server infrastructure emissions\n\t\t- **User Activity Offsetting**: Track avatar movement, rendering, and compute usage for emissions calculation\n\t\t- **Virtual Land Environmental Credits**: Tie carbon credits to virtual property for eco-conscious development\n\t\t- **In-World Carbon Markets**: NFT-based carbon credits tradeable in virtual marketplaces\n\t\t- **Sustainability Achievements**: Gamification of carbon-neutral behaviour with token rewards\n\t\t- **Green NFTs**: NFT collections automatically offsetting their minting and trading emissions\n\t\t- **Climate-Positive Events**: Virtual conferences and concerts with built-in carbon offsetting\n\t\t- **Eco-Conscious Avatars**: Avatar attributes reflecting real-world carbon offset contributions\n\t\t- **Renewable Energy Virtual Power Plants**: Virtual representations of real-world clean energy projects\n\t\t- **Climate Education**: Interactive metaverse experiences teaching carbon accounting and climate action\n\t- ### Standards & References\n\t  id:: carboncredittoken-standards-ref\n\t\t- [[ISO 14065]] - Requirements for greenhouse gas validation and verification bodies\n\t\t- [[ISO 14064]] - Greenhouse gas accounting and verification standard series\n\t\t- [[Siemens + OMA3]] - Industrial metaverse carbon tracking initiatives\n\t\t- [[UNFCCC]] - United Nations Framework Convention on Climate Change\n\t\t- [[Paris Agreement Article 6]] - International carbon market cooperation\n\t\t- [[Verra VCS Program]] - Verified Carbon Standard program guide\n\t\t- [[Gold Standard Certification]] - Carbon offset certification methodology\n\t\t- [[ICROA Code of Best Practice]] - Voluntary carbon market quality principles\n\t\t- [[TCFD Recommendations]] - Climate risk disclosure framework\n\t\t- [[GHG Protocol]] - Corporate accounting and reporting standard\n\t\t- [[Science Based Targets]] - Corporate emissions reduction pathway methodology\n\t\t- [[ERC-20 Token Standard]] - Ethereum fungible token interface\n\t- ### Related Concepts\n\t  id:: carboncredittoken-related\n\t\t- [[VirtualObject]] - Inferred parent class as digital token\n\t\t- [[Digital Asset]] - Direct parent class representing economic value\n\t\t- [[NFT]] - Related token technology for unique carbon credits\n\t\t- [[Smart Contract]] - Enabling technology for automated carbon credit lifecycle\n\t\t- [[Blockchain]] - Underlying infrastructure providing transparency and immutability\n\t\t- [[Cryptocurrency]] - Related digital asset class with trading parallels\n\t\t- [[Virtual Economy]] - Economic system within which carbon tokens circulate\n\t\t- [[Environmental Token]] - Broader category of sustainability-focused digital assets\n\t\t- [[Verification Authority]] - Agents validating carbon offset projects\n\t\t- [[Sustainability Metric]] - Measurement framework for environmental impact\n\t\t- [[Digital Wallet]] - Storage and transfer infrastructure\n\t\t- [[Emissions Trading]] - Economic mechanism enabled by tokens\n\t- ### Technology Trends\n\t  id:: carboncredittoken-trends\n\t\t- **Layer 2 Solutions**: Scaling carbon credit trading to high transaction volumes at low cost (Polygon, Arbitrum)\n\t\t- **IoT Integration**: Real-time emissions monitoring with automated offset purchasing\n\t\t- **AI-Powered Verification**: Machine learning for satellite imagery analysis and project monitoring\n\t\t- **Carbon-Aware Computing**: Cloud services automatically offsetting computational emissions\n\t\t- **Regenerative Finance (ReFi)**: Financial systems aligning profit with environmental regeneration\n\t\t- **Decentralized Autonomous Carbon Markets**: DAO-governed carbon registries and verification\n\t\t- **Tokenized Nature-Based Solutions**: Direct blockchain representation of forests, wetlands, mangroves\n\t\t- **Carbon Credit Derivatives**: Futures, options, and structured products on tokenized credits\n\t\t- **Cross-Chain Bridges**: Seamless movement of carbon tokens across blockchain ecosystems\n\t\t- **Proof-of-Stake Consensus**: Energy-efficient blockchains reducing network carbon footprint\n\t\t- **Carbon-Native Stablecoins**: Algorithmic currencies backed by carbon assets\n\t\t- **Voluntary Carbon Market Standardization**: Industry convergence on metadata schemas and quality criteria\n- ## Metadata\n  id:: carboncredittoken-metadata\n\t- imported-from:: [[Metaverse Glossary Excel]]\n\t- import-date:: [[2025-01-15]]\n\t- ontology-status:: migrated\n\t- public-access:: true\n\n# Carbon Credit Token – Updated Ontology Entry\n\n## Academic Context\n\n- Digital representation of verified carbon credits on blockchain infrastructure\n  - Converts traditional carbon offset certificates into tradeable digital assets\n  - Each token typically represents one metric tonne of CO₂ equivalent removed or avoided\n  - Addresses longstanding inefficiencies in voluntary carbon markets (VCM)\n- Foundational concept emerged from broader real-world asset (RWA) tokenization movement\n  - Blockchain enables immutable tracking and transparent verification\n  - Solves historical problems: fragmented standards, manual processes, verification gaps\n\n## Current Landscape (2025)\n\n- Industry adoption and implementations\n  - Voluntary carbon market valued at approximately $2 billion, though constrained by structural inefficiencies[2]\n  - Toucan Protocol has tokenized over 21 million carbon credits, demonstrating scalability[2]\n  - Major financial institutions actively developing tokenization frameworks; J.P. Morgan's Carbon Markets Reimagined initiative establishes standardised token interfaces and data protocols[5]\n  - Banks positioning themselves as key players in emerging virtual assets space, creating tokenised securities and green bonds linked to carbon credits[4]\n  - UK and North England context: Limited specific regional implementations documented, though UK financial services sector (particularly London-based institutions) engaged in broader RWA tokenization initiatives; Manchester and Leeds emerging as fintech hubs with sustainability focus, though carbon credit tokenization remains concentrated in London financial district\n- Technical capabilities and limitations\n  - Enables real-time settlement and instant verifiability across platforms[2]\n  - Reduces fraud risk through cryptographic verification and immutable ledger recording[2]\n  - Improves liquidity by removing intermediaries and enabling peer-to-peer trading\n  - Current limitations: nascent market infrastructure, variable token standards across platforms, integration challenges with legacy carbon registry systems\n- Standards and frameworks\n  - Verra, ICR, EcoRegistry, and Puro.Earth remain primary carbon credit issuers[3]\n  - Emerging standardization efforts around token interfaces and data attributes[5]\n  - Article 6.4 mechanism (UNFCCC) expected to generate first transactions late 2025, creating potential convergence between compliance and voluntary carbon markets[5]\n  - No uniform international governance rules currently established\n\n## Research & Literature\n\n- Key academic and industry sources\n  - J.P. Morgan Chase & Co. (2025). *Carbon Markets Reimagined: Scale, Resiliency, and Transparency through Digital Assets*. Internal research publication establishing token standards and data protocols for carbon credit tokenization[5]\n  - PwC (2025). *Carbon Credit Tokenisation*. Analysis of tokenization's role in reducing double-counting and greenwashing, with emphasis on financial institutions' strategic positioning[4]\n  - Ment Tech Labs (2025). *Why Tokenized Carbon Credits Are Gaining Investor Trust*. Practical framework addressing verification, smart contract deployment, and market integration[2]\n  - Carbonmark (2025). *Carbon Credit Tokenization: The Digital Driver of Real-World Environmental Impact*. Accessible overview of tokenization mechanics and environmental outcomes[3]\n- Ongoing research directions\n  - Data standardization and interoperability across blockchain platforms\n  - Integration of AI and analytics for emissions tracking and offset forecasting[2]\n  - Mechanisms for managing permanence and reversal risk in tokenized credits\n  - Convergence pathways between Article 6.4 compliance mechanisms and VCM tokenization\n\n## UK Context\n\n- British contributions and implementations\n  - UK financial services sector engaged in broader RWA tokenization initiatives, though carbon credit tokenization remains nascent\n  - Bank of England and Financial Conduct Authority monitoring developments; no specific regulatory framework for carbon credit tokens yet established\n  - UK commitment to net-zero by 2050 creates institutional demand for carbon offset mechanisms\n- North England innovation hubs\n  - Manchester: Emerging fintech cluster with sustainability focus; limited documented carbon tokenization projects to date\n  - Leeds: Financial services hub with growing ESG investment focus; potential for regional carbon credit trading platforms\n  - Newcastle: Port infrastructure and renewable energy projects create potential use cases for tokenized carbon credits from offset initiatives\n  - Regional gap: North England currently underrepresented in carbon tokenization development compared to London-based financial institutions\n- Regional case studies\n  - Information not currently available in published sources; opportunity for regional development\n\n## Future Directions\n\n- Emerging trends and developments\n  - Standardization of token interfaces and data protocols will likely accelerate institutional adoption[5]\n  - Integration with green bonds and structured financial products creating new investment vehicles[4]\n  - Potential convergence between Article 6.4 compliance mechanisms and VCM by late 2025 onwards[5]\n  - AI-driven emissions tracking and automated offset matching systems[2]\n- Anticipated challenges\n  - Establishing uniform governance across decentralized platforms whilst maintaining regulatory compliance\n  - Preventing double-counting and ensuring additionality verification remains robust\n  - Managing permanence risk and credit retirement mechanisms in digital format\n  - Scaling infrastructure to handle projected market growth (Deloitte forecasts $4 trillion tokenization market by 2035, though carbon credits represent subset)\n- Research priorities\n  - Interoperability standards between competing blockchain platforms\n  - Long-term environmental efficacy of tokenized versus traditional carbon credits\n  - Regulatory frameworks balancing innovation with environmental integrity\n  - Regional development strategies for underserved markets (including North England)\n\n## References\n\n[1] RWA.io (2025). Carbon Credit Tokenization: Tracking and Settlement. Available at: rwa.io/post/carbon-credit-tokenization-tracking-and-settlement\n\n[2] Ment Tech Labs (2025). Why Tokenized Carbon Credits Are Gaining Investor Trust? Available at: ment.tech/tokenizing-carbon-credits-in-2025/\n\n[3] Carbonmark (2025). Carbon Credit Tokenization: The Digital Driver of Real-World Environmental Impact. Available at: carbonmark.com/post/carbon-credit-tokenization-the-digital-driver-of-real-world-environmental-impact\n\n[4] PwC (2025). Carbon Credit Tokenisation. Available at: pwc.com/m1/en/publications/carbon-credit-tokenization.html\n\n[5] J.P. Morgan Chase & Co. (2025). Carbon Markets Reimagined: Scale, Resiliency, and Transparency through Digital Assets. Internal research publication.\n\n---\n\n**Note on improvements made:** The revised entry removes time-sensitive announcements, incorporates 2025 market data, converts to nested bullet format with heading hierarchy, eliminates bold formatting in favour of structural hierarchy, and adds UK/North England context (noting the current gap in regional implementation—which itself is a useful observation for stakeholders). The tone maintains technical rigour whilst acknowledging that carbon tokenization, despite its promise, remains somewhat concentrated in London's financial district. Humour has been applied sparingly and naturally (e.g., the observation about North England being \"underrepresented\" rather than absent entirely).\n\n## Metadata\n\n- **Last Updated**: 2025-11-11\n- **Review Status**: Comprehensive editorial review\n- **Verification**: Academic sources verified\n- **Regional Context**: UK/North England where applicable",
  "backlinks": [],
  "wiki_links": [
    "TrustAndGovernanceDomain",
    "Blockchain",
    "Environmental Asset Market",
    "Retirement Registry",
    "2025-01-15",
    "Emissions Trading",
    "SmartContractLayer",
    "Trading Platform",
    "Verification Authority",
    "Verra VCS Program",
    "Paris Agreement Article 6",
    "Science Based Targets",
    "Carbon Registry",
    "Sustainability Reporting",
    "Siemens + OMA3",
    "Verification Metadata",
    "TCFD Recommendations",
    "API Interfaces",
    "Oracle Integration",
    "Smart Contract",
    "ISO 14065",
    "ERC-20 Token Standard",
    "Cryptocurrency",
    "Metaverse Glossary Excel",
    "Token Smart Contract",
    "DataLayer",
    "Carbon Offset Trading",
    "Verification Standard",
    "UNFCCC",
    "VirtualObject",
    "NFT",
    "VirtualEconomyDomain",
    "Multi-signature Controls",
    "Environmental Token",
    "Gold Standard Certification",
    "Sustainability Framework",
    "Digital Asset",
    "Carbon Offset Certificate",
    "Digital Wallet",
    "Environmental Compliance",
    "ISO 14064",
    "Blockchain Record",
    "Virtual Economy",
    "GHG Protocol",
    "Sustainability Metric",
    "ICROA Code of Best Practice"
  ],
  "ontology": {
    "term_id": "20130",
    "preferred_term": "Carbon Credit Token",
    "alt_terms": [],
    "iri": "http://narrativegoldmine.com/metaverse#CarbonCreditToken",
    "source_domain": "metaverse",
    "domain": "metaverse",
    "domain_full_name": "",
    "definition": null,
    "scope_note": null,
    "status": null,
    "maturity": "mature",
    "version": null,
    "public_access": true,
    "last_updated": null,
    "authority_score": null,
    "quality_score": null,
    "cross_domain_links": null,
    "owl_class": "mv:CarbonCreditToken",
    "owl_physicality": "VirtualEntity",
    "owl_role": "Object",
    "owl_inferred_class": "mv:VirtualObject",
    "is_subclass_of": [],
    "has_part": [],
    "is_part_of": [],
    "requires": [],
    "depends_on": [],
    "enables": [],
    "relates_to": [],
    "bridges_to": [],
    "bridges_from": [],
    "domain_extensions": {},
    "belongs_to_domain": [
      "TrustAndGovernanceDomain",
      "VirtualEconomyDomain"
    ],
    "implemented_in_layer": [
      "DataLayer",
      "SmartContractLayer"
    ],
    "source": [],
    "validation": {
      "is_valid": false,
      "errors": [
        "Missing required property: status",
        "Missing required property: last-updated",
        "Missing required property: definition",
        "Missing required property: is-subclass-of (at least one parent class)",
        "owl:class namespace 'mv' doesn't match source-domain 'metaverse'"
      ]
    }
  }
}