{
  "id": "Chain Reorganization",
  "title": "Chain Reorganization",
  "content": "- ### OntologyBlock\n  id:: chain-reorganization-ontology\n  collapsed:: true\n\t- ontology:: true\n\t- term-id:: BC-0015\n\t- preferred-term:: Chain Reorganization\n\t- status:: complete\n\t- public-access:: true\n\t- definition:: Replacement of blockchain segment within blockchain systems, providing essential functionality for distributed ledger technology operations and properties.\n\t- source:: [[ISO/IEC 23257:2021]], [[IEEE 2418.1]], [[NIST NISTIR]]\n\t- maturity:: mature\n\t- owl:class:: bc:ChainReorganization\n\t- owl:physicality:: VirtualEntity\n\t- owl:role:: Object\n\t- owl:inferred-class:: bc:VirtualObject\n\t- belongsToDomain:: [[BlockchainDomain]]\n\t- #### Relationships\n\t  id:: chain-reorganization-relationships\n\t  collapsed:: true\n\t\t- is-subclass-of:: [[Blockchain]]\n\t\t- bridges-to:: [[Distributeddatastructure]]\n\t\t- bridges-to:: [[BlockchainEntity]]\n\n## Chain Reorganization\n\nChain Reorganization refers to replacement of blockchain segment within blockchain systems, providing essential functionality for distributed ledger technology operations and properties.\n\n- Chain reorganizations remain a routine yet critical event in major blockchain networks such as Bitcoin and Ethereum.\n  - They typically occur when two or more blocks are mined at the same height, creating temporary forks resolved by subsequent block discovery.\n  - The process is automatic and usually invisible to end users, though it can cause short-term transaction reversals or delays.\n- Notable platforms implementing chain reorg mechanisms include Bitcoin Core, Ethereum clients, and various Layer-1 blockchains utilising proof-of-work or proof-of-stake consensus.\n- In the UK, blockchain infrastructure providers and financial technology firms integrate chain reorganisation protocols to ensure transaction integrity and network security.\n  - North England cities such as Manchester and Leeds host fintech hubs where blockchain startups develop solutions addressing reorg-related challenges, including transaction finality and security.\n- Technical limitations include the potential for reorg attacks, where malicious actors attempt to rewrite recent transaction history by controlling significant network hash power.\n  - Mitigation strategies involve waiting for multiple block confirmations (commonly six in Bitcoin) before considering transactions final.\n- Standards and frameworks continue to evolve, with organisations like the Enterprise Ethereum Alliance and ISO developing guidelines for blockchain interoperability and security, implicitly covering chain reorganisation processes.\n\n## Technical Details\n\n- **Id**: chain-reorganization-standards\n- **Collapsed**: true\n- **Domain Prefix**: BC\n- **Sequence Number**: 0015\n- **Filename History**: [\"BC-0015-chain-reorganization.md\"]\n- **Public Access**: true\n- **Source Domain**: blockchain\n- **Status**: complete\n- **Last Updated**: 2025-10-28\n- **Maturity**: mature\n- **Source**: [[ISO/IEC 23257:2021]], [[IEEE 2418.1]], [[NIST NISTIR]]\n- **Authority Score**: 0.95\n- **Owl:Class**: bc:ChainReorganization\n- **Owl:Physicality**: VirtualEntity\n- **Owl:Role**: Object\n- **Owl:Inferred Class**: bc:VirtualObject\n- **Belongstodomain**: [[BlockchainDomain]]\n- **Implementedinlayer**: [[ConceptualLayer]]\n- **Is Subclass Of**: [[Blockchain Entity]], [[DistributedDataStructure]]\n\n## Research & Literature\n\n- Key academic papers and sources include:\n  - Nakamoto, S. (2008). *Bitcoin: A Peer-to-Peer Electronic Cash System*. [Original whitepaper introducing the longest chain consensus and implicit reorg mechanism].\n  - Gervais, A., Karame, G. O., Wüst, K., Glykantzis, V., Ritzdorf, H., & Capkun, S. (2016). *On the Security and Performance of Proof of Work Blockchains*. Proceedings of the 2016 ACM SIGSAC Conference on Computer and Communications Security. https://doi.org/10.1145/2976749.2978390\n  - Bonneau, J., Miller, A., Clark, J., Narayanan, A., Kroll, J. A., & Felten, E. W. (2015). *SoK: Research Perspectives and Challenges for Bitcoin and Cryptocurrencies*. IEEE Symposium on Security and Privacy. https://doi.org/10.1109/SP.2015.14\n- Ongoing research focuses on:\n  - Reducing the frequency and impact of chain reorganizations through protocol improvements.\n  - Enhancing transaction finality guarantees in proof-of-stake and hybrid consensus models.\n  - Detecting and mitigating malicious reorg attacks, including 51% attacks, as demonstrated by recent events such as the August 2025 Monero six-block reorganisation.\n  - Exploring Layer-2 solutions and off-chain protocols to minimise on-chain reorg risks.\n\n## UK Context\n\n- The UK has been active in blockchain research and development, with institutions like University College London and the University of Manchester contributing to distributed ledger technology studies.\n- North England innovation hubs in Manchester, Leeds, Newcastle, and Sheffield foster blockchain startups and fintech companies integrating chain reorganisation mechanisms into their platforms.\n  - For example, Manchester’s blockchain incubators support projects focusing on transaction security and consensus resilience.\n- British regulatory bodies, including the Financial Conduct Authority (FCA), monitor blockchain developments to ensure that chain reorganisation risks are managed within financial services.\n- Regional case studies include pilot projects in Leeds utilising blockchain for supply chain transparency, where chain reorganisation ensures data integrity despite network latency or competing data submissions.\n\n## Future Directions\n\n- Emerging trends include:\n  - Development of consensus algorithms that reduce or eliminate chain reorganisations, such as finality gadgets in proof-of-stake protocols.\n  - Increased use of hybrid consensus models combining proof-of-work and proof-of-stake to balance security and efficiency.\n  - Enhanced tooling for real-time detection of reorg attacks and automated response mechanisms.\n- Anticipated challenges:\n  - Scaling blockchain networks while maintaining low reorg rates and high transaction finality.\n  - Addressing the security implications of increasingly sophisticated reorg attacks, especially as demonstrated by recent high-profile incidents.\n  - Balancing decentralisation with performance to prevent centralised control that could facilitate malicious reorganisations.\n- Research priorities:\n  - Formal verification of consensus protocols to guarantee bounded reorg depths.\n  - Cross-chain interoperability standards that handle reorgs gracefully.\n  - User experience improvements to transparently communicate reorg effects without undermining trust.\n\n## References\n\n1. Nakamoto, S. (2008). *Bitcoin: A Peer-to-Peer Electronic Cash System*. https://bitcoin.org/bitcoin.pdf\n2. Gervais, A., Karame, G. O., Wüst, K., Glykantzis, V., Ritzdorf, H., & Capkun, S. (2016). On the Security and Performance of Proof of Work Blockchains. *Proceedings of the 2016 ACM SIGSAC Conference on Computer and Communications Security*. https://doi.org/10.1145/2976749.2978390\n3. Bonneau, J., Miller, A., Clark, J., Narayanan, A., Kroll, J. A., & Felten, E. W. (2015). SoK: Research Perspectives and Challenges for Bitcoin and Cryptocurrencies. *IEEE Symposium on Security and Privacy*. https://doi.org/10.1109/SP.2015.14\n4. Halborn. (2025). *Explained: The Monero 51% Attack (August 2025)*. Halborn Blog.\n5. Enterprise Ethereum Alliance. (2024). *Blockchain Standards and Frameworks*.\n6. Financial Conduct Authority (FCA). (2025). *Regulatory Approach to Distributed Ledger Technology*.\n(And yes, while chain reorganisations might feel like blockchain’s version of musical chairs, they’re essential to keeping the ledger honest — just don’t expect your transaction to win the game until it’s sat comfortably two blocks deep.)\n\n## Metadata\n\n- **Migration Status**: Ontology block enriched on 2025-11-12\n- **Last Updated**: 2025-11-12\n- **Review Status**: Comprehensive editorial review\n- **Verification**: Academic sources verified\n- **Regional Context**: UK/North England where applicable",
  "backlinks": [],
  "wiki_links": [
    "NIST NISTIR",
    "ISO/IEC 23257:2021",
    "BlockchainDomain",
    "ConceptualLayer",
    "BlockchainEntity",
    "Distributeddatastructure",
    "Blockchain",
    "DistributedDataStructure",
    "Blockchain Entity",
    "IEEE 2418.1"
  ],
  "ontology": {
    "term_id": "BC-0015",
    "preferred_term": "Chain Reorganization",
    "alt_terms": [],
    "iri": "http://narrativegoldmine.com/blockchain#ChainReorganization",
    "source_domain": "blockchain",
    "domain": "blockchain",
    "domain_full_name": "",
    "definition": "Replacement of blockchain segment within blockchain systems, providing essential functionality for distributed ledger technology operations and properties.",
    "scope_note": null,
    "status": "complete",
    "maturity": "mature",
    "version": null,
    "public_access": true,
    "last_updated": "2025-10-28",
    "authority_score": 0.95,
    "quality_score": null,
    "cross_domain_links": null,
    "owl_class": "bc:ChainReorganization",
    "owl_physicality": "VirtualEntity",
    "owl_role": "Object",
    "owl_inferred_class": "bc:VirtualObject",
    "is_subclass_of": [
      "Blockchain"
    ],
    "has_part": [],
    "is_part_of": [],
    "requires": [],
    "depends_on": [],
    "enables": [],
    "relates_to": [],
    "bridges_to": [],
    "bridges_from": [],
    "domain_extensions": {},
    "belongs_to_domain": [
      "BlockchainDomain"
    ],
    "implemented_in_layer": [],
    "source": [
      "ISO/IEC 23257:2021",
      "IEEE 2418.1",
      "NIST NISTIR"
    ],
    "other_relationships": {
      "bridges-to": [
        "Distributeddatastructure",
        "BlockchainEntity"
      ]
    },
    "validation": {
      "is_valid": false,
      "errors": [
        "owl:class namespace 'bc' doesn't match source-domain 'blockchain'"
      ]
    }
  }
}