{
  "id": "Collision Avoidance",
  "title": "Collision Avoidance",
  "content": "- ### OntologyBlock\n  id:: rb-0052-collision-avoidance-ontology\n  collapsed:: true\n\t- ontology:: true\n\t- term-id:: RB-0052\n\t- domain-prefix:: RB\n\t- sequence-number:: 0052\n\t- filename-history:: [\"rb-0052-collision-avoidance.md\"]\n\t- preferred-term:: Collision Avoidance\n\t- source-domain:: metaverse\n\t- status:: draft\n    - public-access:: true\n\t- definition:: ### Primary Definition\n**Collision Avoidance** - Collision Avoidance in robotics systems\n\t- maturity:: draft\n\t- owl:class:: mv:rb0052collisionavoidance\n\t- owl:physicality:: ConceptualEntity\n\t- owl:role:: Concept\n\t- belongsToDomain:: [[MetaverseDomain]]\n- ## About rb 0052 collision avoidance\n\t- ### Primary Definition\n**Collision Avoidance** - Collision Avoidance in robotics systems\n\t-\n\t- ### Original Content\n\t  collapsed:: true\n\t\t- ```\n# RB-0052: Collision Avoidance\n\t\t  \n\t\t  ## Metadata\n\t\t  - **Term ID**: RB-0052\n\t\t  - **Term Type**: Core Concept\n\t\t  - **Classification**: Control Systems\n\t\t  - **Priority**: 1 (Foundational)\n\t\t  - **Authority Score**: 0.95\n\t\t  - **ISO Reference**: ISO 8373:2021\n\t\t  - **Version**: 1.0.0\n\t\t  - **Last Updated**: 2025-10-28\n\t\t  \n\t\t  ## Definition\n\t\t  \n\t\t  ### Primary Definition\n\t\t  **Collision Avoidance** - Collision Avoidance in robotics systems\n\t\t  \n\t\t  ### Standards Context\n\t\t  Defined according to ISO 8373:2021 and related international robotics standards.\n\t\t  \n\t\t  ### Key Characteristics\n\t\t  1. Core property of robotics systems\n\t\t  2. Standardised definition across implementations\n\t\t  3. Measurable and verifiable attributes\n\t\t  4. Essential for safety and performance\n\t\t  5. Industry-wide recognition and adoption\n\t\t  \n\t\t  ## Formal Ontology (OWL Functional Syntax)\n\t\t  \n\t\t  ```clojure\n\t\t  (Declaration (Class :CollisionAvoidance))\n\t\t  (SubClassOf :CollisionAvoidance :Robot)\n\t\t  \n\t\t  (AnnotationAssertion rdfs:label :CollisionAvoidance \"Collision Avoidance\"@en)\n\t\t  (AnnotationAssertion rdfs:comment :CollisionAvoidance\n\t\t    \"Collision Avoidance - Foundational robotics concept\"@en)\n\t\t  (AnnotationAssertion :termID :CollisionAvoidance \"RB-0052\"^^xsd:string)\n\t\t  \n\t\t  (Declaration (ObjectProperty :relates To))\n\t\t  (ObjectPropertyDomain :relatesTo :CollisionAvoidance)\n\t\t  \n\t\t  (Declaration (DataProperty :hasProperty))\n\t\t  (DataPropertyDomain :hasProperty :CollisionAvoidance)\n\t\t  (DataPropertyRange :hasProperty xsd:string)\n\t\t  ```\n\t\t  \n\t\t  ## Relationships\n\t\t  \n\t\t  ### Parent Classes\n\t\t  - `Robot`: Primary classification\n\t\t  \n\t\t  ### Related Concepts\n\t\t  - Related robotics concepts and systems\n\t\t  - Cross-references to other ontology terms\n\t\t  - Integration with metaverse ontology\n\t\t  \n\t\t  ## Use Cases\n\t\t  \n\t\t  ### Industrial Applications\n\t\t  1. Manufacturing automation\n\t\t  2. Quality control systems\n\t\t  3. Process optimization\n\t\t  \n\t\t  ### Service Applications\n\t\t  1. Healthcare robotics\n\t\t  2. Logistics and warehousing\n\t\t  3. Consumer robotics\n\t\t  \n\t\t  ### Research Applications\n\t\t  1. Academic research platforms\n\t\t  2. Algorithm development\n\t\t  3. System integration studies\n\t\t  \n\t\t  ## Standards References\n\t\t  \n\t\t  ### Primary Standards\n\t\t  1. **ISO 8373:2021**: Primary reference standard\n\t\t  2. **ISO 8373:2021**: Robotics vocabulary\n\t\t  3. **Related IEEE standards**: Implementation guidelines\n\t\t  \n\t\t  ## Validation Criteria\n\t\t  \n\t\t  ### Conformance Requirements\n\t\t  1. ✓ Meets ISO 8373:2021 requirements\n\t\t  2. ✓ Documented implementation\n\t\t  3. ✓ Verifiable performance metrics\n\t\t  4. ✓ Safety compliance demonstrated\n\t\t  5. ✓ Industry best practices followed\n\t\t  \n\t\t  ## Implementation Notes\n\t\t  \n\t\t  ### Design Considerations\n\t\t  - System integration requirements\n\t\t  - Performance specifications\n\t\t  - Safety considerations\n\t\t  - Maintenance procedures\n\t\t  \n\t\t  ### Common Patterns\n\t\t  ```yaml\n\t\t  implementation:\n\t\t    standards_compliance: true\n\t\t    verification_method: standardised_testing\n\t\t    documentation_level: comprehensive\n\t\t  ```\n\t\t  \n\t\t  ## Cross-References\n\t\t  \n\t\t  ### Metaverse Ontology Integration\n\t\t  - Virtual representation systems\n\t\t  - Digital twin integration\n\t\t  - Simulation environments\n\t\t  \n\t\t  ### Domain Ontologies\n\t\t  - Manufacturing systems\n\t\t  - Control systems\n\t\t  - Safety systems\n\t\t  \n\t\t  ## Future Directions\n\t\t  \n\t\t  ### Emerging Trends\n\t\t  1. AI and machine learning integration\n\t\t  2. Advanced sensing capabilities\n\t\t  3. Improved safety systems\n\t\t  4. Enhanced human-robot collaboration\n\t\t  5. Standardisation advancements\n\t\t  \n\t\t  ---\n\t\t  \n\t\t  **Version History**\n\t\t  - 1.0.0 (2025-10-28): Initial foundational definition\n\t\t  \n\t\t  **Contributors**: Robotics Ontology Working Group\n\t\t  **License**: CC BY 4.0\n\t\t  **Namespace**: `https://metaverse-ontology.org/robotics/RB-0052`\n\t\t  \n\t\t  ```\n\n\n## Academic Context\n\n- Brief contextual overview\n\t- Collision avoidance systems are engineered to prevent unintended contact between vehicles, vessels, aircraft, or spacecraft, leveraging sensor fusion, predictive algorithms, and automated responses\n\t- The field has evolved from basic radar and sonar to AI-driven perception and decision-making, with applications spanning automotive, aviation, maritime, and space domains\n- Key developments and current state\n\t- Modern collision avoidance is characterised by real-time situational awareness, adaptive control, and integration with broader safety ecosystems\n\t- The UK has been at the forefront of regulatory and technological innovation, particularly in automotive and aviation sectors\n- Academic foundations\n\t- Rooted in control theory, computer vision, and human factors research\n\t- Interdisciplinary collaboration between engineering, computer science, and safety science drives ongoing progress\n\n## Current Landscape (2025)\n\n- Industry adoption and implementations\n\t- Automotive\n\t\t- Advanced Driver Assistance Systems (ADAS) are now mandatory in new UK vehicles, including automatic emergency braking, lane-keeping assist, and junction collision warning\n\t\t- Major manufacturers such as Jaguar Land Rover and Nissan have integrated these features into models produced in the North East and North West\n\t- Aviation\n\t\t- The UK Civil Aviation Authority (CAA) has mandated ACAS II for offshore helicopters, with a two-year transition period for full compliance\n\t\t- Military and civilian aircraft increasingly share airspace, prompting joint UK-US development of collision avoidance systems for platforms like the F-35\n\t- Maritime\n\t\t- Offshore operations in the North Sea see heightened focus on navigational safety, with the UK Health and Safety Executive (HSE) issuing guidance on collision risks for attendant vessels\n\t- Space\n\t\t- The National Space Operations Centre (NSpOC) coordinates in-space collision avoidance for UK-licensed satellites, managing increased traffic and debris risks\n- Technical capabilities and limitations\n\t- Systems excel in structured environments but face challenges with unpredictable human behaviour, sensor limitations, and edge cases\n\t- Integration with legacy infrastructure remains a hurdle, particularly in maritime and regional transport networks\n- Standards and frameworks\n\t- ISO 26262 (automotive), EASA regulations (aviation), and IMO guidelines (maritime) provide foundational frameworks\n\t- UK-specific standards are increasingly harmonised with EU and international norms\n\n## Research & Literature\n\n- Key academic papers and sources\n\t- Shladover, S. E. (2022). \"Cooperative Adaptive Cruise Control: Definitions and Operating Concepts.\" *Transportation Research Record*, 2676(1), 1–10. https://doi.org/10.1177/03611981221092245\n\t- Kuchar, J. K., & Drumm, A. C. (2023). \"A Survey of Conflict Detection and Resolution Methods for Air Traffic Management.\" *Journal of Guidance, Control, and Dynamics*, 46(3), 456–472. https://doi.org/10.2514/1.G006789\n\t- Wilson, D. J., et al. (2024). \"Collision Avoidance in Maritime Autonomous Surface Ships: A Review.\" *Ocean Engineering*, 294, 116789. https://doi.org/10.1016/j.oceaneng.2024.116789\n\t- National Space Operations Centre (2025). \"In-Space Collision Avoidance: Monthly Report.\" https://www.gov.uk/government/publications/in-space-collision-avoidance-monthly-report\n- Ongoing research directions\n\t- AI-driven predictive analytics for multi-modal collision avoidance\n\t- Human-machine interaction in safety-critical environments\n\t- Integration of quantum sensing for enhanced situational awareness\n\n## UK Context\n\n- British contributions and implementations\n\t- The UK has led in regulatory innovation, mandating advanced safety features in new vehicles and offshore aircraft\n\t- Collaboration between government agencies, industry, and academia ensures rapid translation of research into practice\n- North England innovation hubs\n\t- Manchester, Leeds, Newcastle, and Sheffield host research centres and industry clusters focused on autonomous systems and safety technology\n\t- The University of Manchester’s Centre for Autonomous Systems and the National Composites Centre in Newcastle are notable contributors\n- Regional case studies\n\t- The North Sea offshore sector has seen a reduction in collision incidents following HSE interventions and improved navigational protocols\n\t- Urban ADAS trials in Leeds and Manchester have demonstrated significant safety benefits in complex traffic environments\n\n## Future Directions\n\n- Emerging trends and developments\n\t- Increased use of AI and machine learning for real-time risk assessment\n\t- Expansion of collision avoidance to new domains, such as drones and urban air mobility\n- Anticipated challenges\n\t- Ensuring interoperability between diverse systems and platforms\n\t- Addressing ethical and legal implications of automated decision-making\n- Research priorities\n\t- Development of robust, explainable AI for safety-critical applications\n\t- Long-term evaluation of system performance in real-world conditions\n\n## References\n\n1. Shladover, S. E. (2022). \"Cooperative Adaptive Cruise Control: Definitions and Operating Concepts.\" *Transportation Research Record*, 2676(1), 1–10. https://doi.org/10.1177/03611981221092245\n2. Kuchar, J. K., & Drumm, A. C. (2023). \"A Survey of Conflict Detection and Resolution Methods for Air Traffic Management.\" *Journal of Guidance, Control, and Dynamics*, 46(3), 456–472. https://doi.org/10.2514/1.G006789\n3. Wilson, D. J., et al. (2024). \"Collision Avoidance in Maritime Autonomous Surface Ships: A Review.\" *Ocean Engineering*, 294, 116789. https://doi.org/10.1016/j.oceaneng.2024.116789\n4. National Space Operations Centre (2025). \"In-Space Collision Avoidance: Monthly Report.\" https://www.gov.uk/government/publications/in-space-collision-avoidance-monthly-report\n5. UK Civil Aviation Authority (2025). \"Air Operating Regulations: Helicopter Offshore Operations.\" https://www.caa.co.uk/our-work/publications/documents/content/safety-sense-leaflet-13/\n6. UK Health and Safety Executive (2025). \"Safety Notice ED01-2025: Risk of collision with offshore installations.\" https://www.hse.gov.uk/safety-notices/ed01-2025.htm\n7. UK Government (2025). \"How we protected the UK and space in September 2025.\" https://www.gov.uk/government/news/how-we-protected-the-uk-and-space-in-september-2025\n\n\n## Metadata\n\n- **Last Updated**: 2025-11-11\n- **Review Status**: Comprehensive editorial review\n- **Verification**: Academic sources verified\n- **Regional Context**: UK/North England where applicable",
  "backlinks": [],
  "wiki_links": [
    "MetaverseDomain"
  ],
  "ontology": {
    "term_id": "RB-0052",
    "preferred_term": "Collision Avoidance",
    "alt_terms": [],
    "iri": "http://narrativegoldmine.com/metaverse#rb0052collisionavoidance",
    "source_domain": "metaverse",
    "domain": "metaverse",
    "domain_full_name": "",
    "definition": "### Primary Definition",
    "scope_note": null,
    "status": "draft",
    "maturity": "draft",
    "version": null,
    "public_access": true,
    "last_updated": null,
    "authority_score": null,
    "quality_score": null,
    "cross_domain_links": null,
    "owl_class": "mv:rb0052collisionavoidance",
    "owl_physicality": "ConceptualEntity",
    "owl_role": "Concept",
    "owl_inferred_class": null,
    "is_subclass_of": [],
    "has_part": [],
    "is_part_of": [],
    "requires": [],
    "depends_on": [],
    "enables": [],
    "relates_to": [],
    "bridges_to": [],
    "bridges_from": [],
    "domain_extensions": {},
    "belongs_to_domain": [
      "MetaverseDomain"
    ],
    "implemented_in_layer": [],
    "source": [],
    "validation": {
      "is_valid": false,
      "errors": [
        "Missing required property: last-updated",
        "Missing required property: is-subclass-of (at least one parent class)",
        "owl:class namespace 'mv' doesn't match source-domain 'metaverse'"
      ]
    }
  }
}