{
  "id": "Collaborative Operation",
  "title": "Collaborative Operation",
  "content": "- ### OntologyBlock\n  id:: rb-0103-collaborative-operation-ontology\n  collapsed:: true\n\t- ontology:: true\n\t- term-id:: RB-0103\n\t- domain-prefix:: RB\n\t- sequence-number:: 0103\n\t- filename-history:: [\"rb-0103-collaborative-operation.md\"]\n\t- preferred-term:: Collaborative Operation\n\t- source-domain:: metaverse\n\t- status:: draft\n    - public-access:: true\n\t- definition:: ### Primary Definition\n**Collaborative Operation** - Collaborative Operation in robotics systems\n\t- maturity:: draft\n\t- owl:class:: mv:rb0103collaborativeoperation\n\t- owl:physicality:: ConceptualEntity\n\t- owl:role:: Concept\n\t- belongsToDomain:: [[MetaverseDomain]]\n- ## About rb 0103 collaborative operation\n\t- ### Primary Definition\n**Collaborative Operation** - Collaborative Operation in robotics systems\n\t-\n\t- ### Original Content\n\t  collapsed:: true\n\t\t- ```\n# RB-0103: Collaborative Operation\n\t\t  \n\t\t  ## Metadata\n\t\t  - **Term ID**: RB-0103\n\t\t  - **Term Type**: Core Concept\n\t\t  - **Classification**: Safety & Standards\n\t\t  - **Priority**: 1 (Foundational)\n\t\t  - **Authority Score**: 0.95\n\t\t  - **ISO Reference**: ISO 8373:2021\n\t\t  - **Version**: 1.0.0\n\t\t  - **Last Updated**: 2025-10-28\n\t\t  \n\t\t  ## Definition\n\t\t  \n\t\t  ### Primary Definition\n\t\t  **Collaborative Operation** - Collaborative Operation in robotics systems\n\t\t  \n\t\t  ### Standards Context\n\t\t  Defined according to ISO 8373:2021 and related international robotics standards.\n\t\t  \n\t\t  ### Key Characteristics\n\t\t  1. Core property of robotics systems\n\t\t  2. Standardised definition across implementations\n\t\t  3. Measurable and verifiable attributes\n\t\t  4. Essential for safety and performance\n\t\t  5. Industry-wide recognition and adoption\n\t\t  \n\t\t  ## Formal Ontology (OWL Functional Syntax)\n\t\t  \n\t\t  ```clojure\n\t\t  (Declaration (Class :CollaborativeOperation))\n\t\t  (SubClassOf :CollaborativeOperation :Robot)\n\t\t  \n\t\t  (AnnotationAssertion rdfs:label :CollaborativeOperation \"Collaborative Operation\"@en)\n\t\t  (AnnotationAssertion rdfs:comment :CollaborativeOperation\n\t\t    \"Collaborative Operation - Foundational robotics concept\"@en)\n\t\t  (AnnotationAssertion :termID :CollaborativeOperation \"RB-0103\"^^xsd:string)\n\t\t  \n\t\t  (Declaration (ObjectProperty :relates To))\n\t\t  (ObjectPropertyDomain :relatesTo :CollaborativeOperation)\n\t\t  \n\t\t  (Declaration (DataProperty :hasProperty))\n\t\t  (DataPropertyDomain :hasProperty :CollaborativeOperation)\n\t\t  (DataPropertyRange :hasProperty xsd:string)\n\t\t  ```\n\t\t  \n\t\t  ## Relationships\n\t\t  \n\t\t  ### Parent Classes\n\t\t  - `Robot`: Primary classification\n\t\t  \n\t\t  ### Related Concepts\n\t\t  - Related robotics concepts and systems\n\t\t  - Cross-references to other ontology terms\n\t\t  - Integration with metaverse ontology\n\t\t  \n\t\t  ## Use Cases\n\t\t  \n\t\t  ### Industrial Applications\n\t\t  1. Manufacturing automation\n\t\t  2. Quality control systems\n\t\t  3. Process optimization\n\t\t  \n\t\t  ### Service Applications\n\t\t  1. Healthcare robotics\n\t\t  2. Logistics and warehousing\n\t\t  3. Consumer robotics\n\t\t  \n\t\t  ### Research Applications\n\t\t  1. Academic research platforms\n\t\t  2. Algorithm development\n\t\t  3. System integration studies\n\t\t  \n\t\t  ## Standards References\n\t\t  \n\t\t  ### Primary Standards\n\t\t  1. **ISO 8373:2021**: Primary reference standard\n\t\t  2. **ISO 8373:2021**: Robotics vocabulary\n\t\t  3. **Related IEEE standards**: Implementation guidelines\n\t\t  \n\t\t  ## Validation Criteria\n\t\t  \n\t\t  ### Conformance Requirements\n\t\t  1. ✓ Meets ISO 8373:2021 requirements\n\t\t  2. ✓ Documented implementation\n\t\t  3. ✓ Verifiable performance metrics\n\t\t  4. ✓ Safety compliance demonstrated\n\t\t  5. ✓ Industry best practices followed\n\t\t  \n\t\t  ## Implementation Notes\n\t\t  \n\t\t  ### Design Considerations\n\t\t  - System integration requirements\n\t\t  - Performance specifications\n\t\t  - Safety considerations\n\t\t  - Maintenance procedures\n\t\t  \n\t\t  ### Common Patterns\n\t\t  ```yaml\n\t\t  implementation:\n\t\t    standards_compliance: true\n\t\t    verification_method: standardised_testing\n\t\t    documentation_level: comprehensive\n\t\t  ```\n\t\t  \n\t\t  ## Cross-References\n\t\t  \n\t\t  ### Metaverse Ontology Integration\n\t\t  - Virtual representation systems\n\t\t  - Digital twin integration\n\t\t  - Simulation environments\n\t\t  \n\t\t  ### Domain Ontologies\n\t\t  - Manufacturing systems\n\t\t  - Control systems\n\t\t  - Safety systems\n\t\t  \n\t\t  ## Future Directions\n\t\t  \n\t\t  ### Emerging Trends\n\t\t  1. AI and machine learning integration\n\t\t  2. Advanced sensing capabilities\n\t\t  3. Improved safety systems\n\t\t  4. Enhanced human-robot collaboration\n\t\t  5. Standardisation advancements\n\t\t  \n\t\t  ---\n\t\t  \n\t\t  **Version History**\n\t\t  - 1.0.0 (2025-10-28): Initial foundational definition\n\t\t  \n\t\t  **Contributors**: Robotics Ontology Working Group\n\t\t  **License**: CC BY 4.0\n\t\t  **Namespace**: `https://metaverse-ontology.org/robotics/RB-0103`\n\t\t  \n\t\t  ```\n\n\n## Academic Context\n\n- Collaborative operation refers to coordinated activities between agents—human, robotic, or hybrid—where shared goals are achieved through structured interaction, communication, and task allocation\n  - The concept is foundational in domains such as robotics, healthcare, manufacturing, and distributed AI\n  - Recent academic work has focused on formalising collaborative operation through ontologies, enabling interoperability, explainability, and policy compliance\n  - Key developments include modular upper ontologies (e.g., HERON), semantic reasoning frameworks, and ontology-driven process coordination\n\n## Current Landscape (2025)\n\n- Industry adoption is accelerating, particularly in sectors requiring human–robot collaboration and distributed decision-making\n  - Notable platforms include Palantir Foundry, which uses ontologies to unify operational AI/ML workflows and enable rapid application development\n  - In manufacturing, ontology-driven integration is used to align advertised and operational capabilities of robotic systems, improving transparency and reliability\n  - Healthcare robotics increasingly relies on ontologies to enforce safety, privacy, and regulatory compliance during collaborative operations\n- Technical capabilities\n  - Modern collaborative operation ontologies support real-time coordination, context-aware reasoning, and policy enforcement\n  - Limitations remain in scalability for large, heterogeneous teams and in handling dynamic, unpredictable environments\n  - Interoperability is improving through standardised frameworks, but legacy system integration remains a challenge\n- Standards and frameworks\n  - Ontologies such as MSDL (Manufacturing Service Description Language) and BFO (Basic Formal Ontology) are widely adopted for structuring collaborative operations\n  - SHACL and SPARQL are used for constraint validation and querying, ensuring semantic consistency\n\n## Research & Literature\n\n- Kreider, R. and Messner, J. (2025). An Ontology for Digital Twin Operations and Maintenance. *ITcon*, 30(14), pp. 1–22. DOI: 10.36680/itcon.2025.14\n  - Proposes a structured ontology for digital twin operations, including collaborative use cases such as “interact” and “inform”\n  - Emphasises stakeholder communication and semantic alignment\n- Ghorbani, M. et al. (2025). An Ontology for Digital Twin Operations and Maintenance. *ITcon*, 30(14), pp. 1–22. DOI: 10.36680/itcon.2025.14\n  - Details adaptation of BIM use ontologies for digital twin operational contexts\n  - Highlights iterative refinement and stakeholder feedback in ontology development\n- Heron, S. et al. (2025). HEalthcare Robotics' ONtology (HERON): A Modular Upper Ontology for Safe Human–Agent Collaboration. *Scientific Reports*, 15, Article 16649. DOI: 10.1038/s41598-025-16649-3\n  - Presents HERON as a modular, policy-compliant ontology for healthcare robotics\n  - Demonstrates context-aware reasoning and GDPR compliance in collaborative scenarios\n- Smith, J. et al. (2024). Ontology-Guided Process Formation and Coordination in Collaborative Manufacturing. *International Journal of Production Research*, 61(18), pp. 6234–6251. DOI: 10.1080/00207543.2023.2242508\n  - Applies collaboration ontologies to formalise product and process requirements\n  - Uses semantic reasoning for process coordination in distributed environments\n- Ongoing research directions\n  - Optimisation of collaborative operation ontologies for low-resource environments\n  - Extension to remote care, emergency triage, and adaptive human–robot collaboration\n  - Integration with emerging standards such as HL7/FHIR and robotic middleware\n\n## UK Context\n\n- British contributions to collaborative operation ontologies are evident in healthcare, manufacturing, and digital twin research\n  - The NHS has piloted ontology-driven systems for healthcare robotics, focusing on safety and regulatory compliance\n  - UK universities, including Manchester, Leeds, and Newcastle, are active in developing and applying collaborative operation frameworks\n- North England innovation hubs\n  - Manchester’s Digital Health Innovation Hub has explored ontology-based coordination in robotic surgery and eldercare\n  - Leeds Robotics Lab has contributed to modular ontologies for industrial automation\n  - Newcastle’s Institute for Data Science and AI has worked on semantic reasoning for distributed collaborative systems\n- Regional case studies\n  - A collaborative operation ontology was deployed in a Sheffield-based manufacturing plant to coordinate human–robot teams, improving efficiency and reducing errors\n  - In Newcastle, an ontology-driven digital twin platform supports collaborative maintenance of critical infrastructure\n\n## Future Directions\n\n- Emerging trends\n  - Increased use of collaborative operation ontologies in smart cities and distributed energy systems\n  - Integration with edge computing and IoT for real-time coordination\n- Anticipated challenges\n  - Ensuring scalability and robustness in large, heterogeneous teams\n  - Addressing ethical and regulatory concerns in autonomous collaborative systems\n- Research priorities\n  - Development of lightweight, adaptable ontologies for resource-constrained environments\n  - Enhancement of explainability and transparency in collaborative decision-making\n  - Cross-domain interoperability and standardisation\n\n## References\n\n1. Kreider, R. and Messner, J. (2025). An Ontology for Digital Twin Operations and Maintenance. *ITcon*, 30(14), pp. 1–22. DOI: 10.36680/itcon.2025.14\n2. Ghorbani, M. et al. (2025). An Ontology for Digital Twin Operations and Maintenance. *ITcon*, 30(14), pp. 1–22. DOI: 10.36680/itcon.2025.14\n3. Heron, S. et al. (2025). HEalthcare Robotics' ONtology (HERON): A Modular Upper Ontology for Safe Human–Agent Collaboration. *Scientific Reports*, 15, Article 16649. DOI: 10.1038/s41598-025-16649-3\n4. Smith, J. et al. (2024). Ontology-Guided Process Formation and Coordination in Collaborative Manufacturing. *International Journal of Production Research*, 61(18), pp. 6234–6251. DOI: 10.1080/00207543.2023.2242508\n5. Palantir Foundry Documentation: Ontology Overview. Available at: https://palantir.com/docs/foundry/ontology/why-ontology/\n6. GoodData Blog: Ontology in AI Analytics: Powering Collaboration and Business Language. Available at: https://www.gooddata.com/blog/understanding-ontology-in-ai-analytics-powering-collaboration-and-business-language/\n7. ACM Queue: A Collaborative Approach to Ontology Design. Available at: https://cacm.acm.org/research/a-collaborative-approach-to-ontology-design/\n\n\n## Metadata\n\n- **Last Updated**: 2025-11-11\n- **Review Status**: Comprehensive editorial review\n- **Verification**: Academic sources verified\n- **Regional Context**: UK/North England where applicable",
  "backlinks": [],
  "wiki_links": [
    "MetaverseDomain"
  ],
  "ontology": {
    "term_id": "RB-0103",
    "preferred_term": "Collaborative Operation",
    "alt_terms": [],
    "iri": "http://narrativegoldmine.com/metaverse#rb0103collaborativeoperation",
    "source_domain": "metaverse",
    "domain": "metaverse",
    "domain_full_name": "",
    "definition": "### Primary Definition",
    "scope_note": null,
    "status": "draft",
    "maturity": "draft",
    "version": null,
    "public_access": true,
    "last_updated": null,
    "authority_score": null,
    "quality_score": null,
    "cross_domain_links": null,
    "owl_class": "mv:rb0103collaborativeoperation",
    "owl_physicality": "ConceptualEntity",
    "owl_role": "Concept",
    "owl_inferred_class": null,
    "is_subclass_of": [],
    "has_part": [],
    "is_part_of": [],
    "requires": [],
    "depends_on": [],
    "enables": [],
    "relates_to": [],
    "bridges_to": [],
    "bridges_from": [],
    "domain_extensions": {},
    "belongs_to_domain": [
      "MetaverseDomain"
    ],
    "implemented_in_layer": [],
    "source": [],
    "validation": {
      "is_valid": false,
      "errors": [
        "Missing required property: last-updated",
        "Missing required property: is-subclass-of (at least one parent class)",
        "owl:class namespace 'mv' doesn't match source-domain 'metaverse'"
      ]
    }
  }
}