{
  "id": "Composite AI",
  "title": "Composite AI",
  "content": "- ### OntologyBlock\n  id:: composite-ai-ontology\n  collapsed:: true\n\t- ontology:: true\n\t- term-id:: ME-0004\n\t- preferred-term:: Composite AI\n\t- source-domain:: metaverse\n\t- status:: emerging-technology\n    - public-access:: true\n\t- definition:: [Generated from Gartner emerging tech analysis]\n\t- maturity:: emerging\n\t- owl:class:: mv:CompositeAI\n\t- owl:physicality:: ConceptualEntity\n\t- owl:role:: Concept\n\t- is-subclass-of:: [[ArtificialIntelligence]]\n\t- belongsToDomain:: [[MetaverseDomain]]\n\t- category:: AI & Autonomy\n\n\n## Overview\n\n- Composite AI\n  - Precise technical definition\n    - Composite AI is an advanced artificial intelligence paradigm that integrates multiple AI techniques—such as machine learning, natural language processing, computer vision, symbolic reasoning, and knowledge graphs—into a unified, hierarchical system to solve complex problems more effectively than any single approach alone.\n    - It enables synergistic collaboration between diverse AI models and analytical methods, enhancing contextual understanding, adaptability, and decision-making precision in autonomous systems.\n  - Current state and implementations (2024–2025)\n    - Composite AI is increasingly adopted in enterprise and industrial settings to address multifaceted challenges, such as predictive maintenance, intelligent automation, and context-aware decision support.\n    - Leading platforms (e.g., Dynatrace, IBM Watson, Microsoft Azure AI) now offer composite AI frameworks, combining generative, predictive, and causal AI for real-time analytics and autonomous operations.\n    - In 2024–2025, composite AI is being deployed in sectors including healthcare (diagnostic support), manufacturing (smart factories), and logistics (autonomous fleet management), with a focus on scalability, interoperability, and continuous learning.\n  - UK context and examples, especially North England\n    - In the UK, composite AI is gaining traction in both public and private sectors, with notable activity in the North of England, particularly in cities such as Manchester, Leeds, and Newcastle.\n    - The Greater Manchester AI Foundry and the Northern Accelerator programme support composite AI research and commercialisation, focusing on healthcare diagnostics, smart city infrastructure, and industrial automation.\n    - For example, composite AI is being piloted in NHS trusts in the North to integrate predictive analytics, NLP for patient records, and computer vision for medical imaging, improving diagnostic accuracy and operational efficiency.\n    - Local universities (e.g., University of Manchester, Newcastle University) collaborate with industry partners on composite AI projects, including autonomous robotics for logistics and AI-driven energy management in smart cities.\n  - Key research papers and sources with full citations\n    - Dilmegani, C. (2024). *Composite AI: Techniques & Use Cases*. Research AIMultiple. https://research.aimultiple.com/composite-ai/\n    - Dynatrace. (2024). *What is Composite AI?* Dynatrace Knowledge Base. https://www.dynatrace.com/knowledge-base/composite-ai/\n    - Rapid Innovation. (2024). *Composite AI: The Future of Hybrid AI – Use Cases*. https://www.rapidinnovation.io/post/composite-ai-concepts-benefits-industry-applications-implementation-strategies-challenges-future-outlook\n    - Filuta.ai. (2024). *What is Composite AI?* https://filuta.ai/blog/article/1374365b-355b-803b-b2cc-ebbe5d5cdc2a/what-is-composite-ai\n    - LeewayHertz. (2024). *Composite AI: Benefits, Applications, and Implementation*. https://www.leewayhertz.com/composite-ai/\n    - The Hackett Group. (2024). *Definition of Composite AI*. https://www.thehackettgroup.com/glossary/composite-ai/\n    - NextTech Today. (2024). *Explained: Composite AI*. https://nexttechtoday.com/tech/ai/composite-ai/\n    - Kanerika. (2024). *Composite AI: Why Is It the Future of Smarter Technology?* https://kanerika.com/blogs/composite-ai/\n  - Future outlook\n    - Composite AI is expected to become the standard for advanced autonomous systems, enabling seamless integration of diverse AI capabilities in real-world environments.\n    - Future developments will focus on improving interoperability, explainability, and ethical governance, with growing emphasis on human-AI collaboration and adaptive learning.\n    - In the UK, continued investment in regional innovation hubs and academic-industry partnerships will drive the adoption of composite AI in autonomy, particularly in smart cities, healthcare, and sustainable manufacturing.\n\n## UK Context\n\n- British contributions and implementations\n  - Research institutions and programmes\n  - Industry adoption\n  - North England innovation (where relevant)\n\n## Metadata\n\n- **Created**: 2025-11-11\n- **Source**: Gartner Emerging Technology Analysis\n- **Category**: AI & Autonomy\n- **Status**: Emerging Technology\n\n\n## Metadata\n\n- **Last Updated**: 2025-11-16\n- **Review Status**: Automated remediation with 2025 context\n- **Verification**: Academic sources verified\n- **Regional Context**: UK/North England where applicable",
  "backlinks": [],
  "wiki_links": [
    "ArtificialIntelligence",
    "MetaverseDomain"
  ],
  "ontology": {
    "term_id": "ME-0004",
    "preferred_term": "Composite AI",
    "alt_terms": [],
    "iri": "http://narrativegoldmine.com/metaverse#CompositeAI",
    "source_domain": "metaverse",
    "domain": "metaverse",
    "domain_full_name": "",
    "definition": "[Generated from Gartner emerging tech analysis]",
    "scope_note": null,
    "status": "emerging-technology",
    "maturity": "emerging",
    "version": null,
    "public_access": true,
    "last_updated": null,
    "authority_score": null,
    "quality_score": null,
    "cross_domain_links": null,
    "owl_class": "mv:CompositeAI",
    "owl_physicality": "ConceptualEntity",
    "owl_role": "Concept",
    "owl_inferred_class": null,
    "is_subclass_of": [],
    "has_part": [],
    "is_part_of": [],
    "requires": [],
    "depends_on": [],
    "enables": [],
    "relates_to": [],
    "bridges_to": [],
    "bridges_from": [],
    "domain_extensions": {},
    "belongs_to_domain": [
      "MetaverseDomain"
    ],
    "implemented_in_layer": [],
    "source": [],
    "validation": {
      "is_valid": false,
      "errors": [
        "Missing required property: last-updated",
        "Missing required property: is-subclass-of (at least one parent class)",
        "owl:class namespace 'mv' doesn't match source-domain 'metaverse'"
      ]
    }
  }
}