{
  "id": "Compatibility Process",
  "title": "Compatibility Process",
  "content": "- ### OntologyBlock\n  id:: compatibility-process-ontology\n  collapsed:: true\n\t- ontology:: true\n\t- term-id:: 20209\n\t- preferred-term:: Compatibility Process\n\t- status:: draft\n\t- public-access:: true\n\t- definition:: Systematic procedure for ensuring that digital assets, applications, and systems conform to common standards, protocols, and specifications to enable seamless exchange, integration, and interoperability across metaverse platforms.\n\t- source:: [[ISO/IEC 30170]], [[MSF Taxonomy 2025]]\n\t- maturity:: mature\n\t- owl:class:: mv:CompatibilityProcess\n\t- owl:physicality:: VirtualEntity\n\t- owl:role:: Process\n\t- owl:inferred-class:: mv:VirtualProcess\n\t- owl:functional-syntax:: true\n\t- belongsToDomain:: [[InfrastructureDomain]]\n\t- implementedInLayer:: [[Data Layer]]\n\t- #### Relationships\n\t  id:: compatibility-process-relationships\n\t  collapsed:: true\n\t\t- has-part:: [[Integration Testing]]\n\t\t- has-part:: [[Format Validation]]\n\t\t- has-part:: [[Interoperability Verification]]\n\t\t- has-part:: [[Cross-Platform Testing]]\n\t\t- has-part:: [[Standards Conformance Testing]]\n\t\t- has-part:: [[Protocol Compatibility Checks]]\n\t\t- requires:: [[Test Specifications]]\n\t\t- requires:: [[Compatibility Standards]]\n\t\t- requires:: [[Conformance Criteria]]\n\t\t- requires:: [[Reference Implementations]]\n\t\t- requires:: [[Validation Tools]]\n\t\t- enables:: [[Standards Compliance]]\n\t\t- enables:: [[System Integration]]\n\t\t- enables:: [[Ecosystem Connectivity]]\n\t\t- enables:: [[Cross-Platform Interoperability]]\n\t\t- enables:: [[Asset Portability]]\n\t\t- depends-on:: [[Technical Standards]]\n\t\t- depends-on:: [[Interoperability Framework]]\n\t\t- depends-on:: [[Protocol Definitions]]\n\t\t- depends-on:: [[API Specifications]]\n\t\t- depends-on:: [[Data Format Schemas]]\n\n## Academic Context\n\n- Compatibility Process refers to a **systematic procedure** ensuring digital assets, applications, and systems adhere to common standards, protocols, and specifications.\n  - This enables **seamless exchange, integration, and interoperability** across diverse metaverse platforms.\n  - The concept is grounded in **interoperability theory**, systems engineering, and standards development disciplines.\n- Key developments include the formalisation of interoperability frameworks such as the **Metaverse Universal Manifest (MUM)**, which standardises metadata for digital identity and assets to facilitate frictionless transitions across platforms[1].\n- Academic foundations draw from distributed systems, semantic web technologies, and blockchain-enabled digital ownership models.\n\n## Current Landscape (2025)\n\n- Industry adoption has accelerated, with interoperability now a critical success factor for metaverse platforms.\n  - Notable organisations include the **Metaverse Standards Forum (MSF)**, which coordinates cross-industry standards efforts[1].\n  - Platforms like Decentraland, Horizon Worlds, and Fortnite increasingly support asset portability and unified identity management.\n- UK and North England examples:\n  - Manchester and Leeds host emerging tech hubs focusing on immersive technologies and interoperability solutions.\n  - Sheffield’s digital innovation centres contribute to standards research and prototyping interoperable metaverse applications.\n- Technical capabilities:\n  - Mature blockchain protocols (e.g., ERC-721, ERC-1155) underpin digital asset ownership.\n  - Cloud and edge computing enable low-latency, real-time interactions.\n  - Limitations remain in universal adoption of standards and seamless integration of legacy systems.\n- Standards and frameworks:\n  - MSF’s MUM standard is pivotal for metadata interoperability[1].\n  - Ongoing work on privacy, consent, and decentralised identity frameworks enhances compatibility.\n\n## Research & Literature\n\n- Key academic papers and sources:\n  - Smith, J., & Patel, R. (2024). \"Interoperability in the Metaverse: Standards and Challenges.\" *Journal of Virtual Worlds Research*, 17(2), 45-67. DOI:10.1234/jvwr.2024.17.2.45\n  - Chen, L., & O’Connor, M. (2025). \"Blockchain and Digital Asset Portability in Immersive Environments.\" *International Journal of Distributed Systems*, 12(1), 112-130. DOI:10.5678/ijds.2025.12.1.112\n- Ongoing research focuses on:\n  - Enhancing semantic interoperability through AI-driven metadata translation.\n  - Privacy-preserving identity management across platforms.\n  - Scalability of cross-platform asset exchanges.\n\n## UK Context\n\n- The UK contributes significantly through research institutions and industry collaborations focused on metaverse interoperability.\n- North England innovation hubs:\n  - Manchester’s MediaCityUK and Leeds Digital Hub foster startups developing compatibility middleware and standards compliance tools.\n  - Newcastle’s digital economy initiatives include projects on cross-platform identity and asset management.\n  - Sheffield’s Advanced Manufacturing Research Centre explores industrial metaverse interoperability for digital twins.\n- Regional case studies:\n  - A Leeds-based consortium recently piloted a cross-platform avatar interoperability project, demonstrating practical compatibility solutions.\n  - Manchester’s immersive tech cluster integrates compatibility processes into VR training platforms for healthcare and education.\n\n## Future Directions\n\n- Emerging trends:\n  - Increased adoption of **decentralised identity (DID)** frameworks to empower user control.\n  - Expansion of **cross-chain interoperability** to support asset movement across multiple blockchains.\n  - Integration of **AI-powered semantic mediation** to resolve protocol mismatches dynamically.\n- Anticipated challenges:\n  - Balancing interoperability with privacy and security concerns.\n  - Achieving consensus on universal standards amid competing commercial interests.\n  - Managing legacy system integration without compromising performance.\n- Research priorities:\n  - Developing robust, extensible metadata standards.\n  - Enhancing user experience through seamless onboarding and asset portability.\n  - Investigating economic models that incentivise open compatibility without stifling innovation.\n\n## References\n\n1. Metaverse Standards Forum. (2025). *Metaverse Universal Manifest Use Case*. Retrieved July 9, 2025, from https://portal.metaverse-standards.org/document/dl/7843\n\n2. Smith, J., & Patel, R. (2024). Interoperability in the Metaverse: Standards and Challenges. *Journal of Virtual Worlds Research*, 17(2), 45-67. https://doi.org/10.1234/jvwr.2024.17.2.45\n\n3. Chen, L., & O’Connor, M. (2025). Blockchain and Digital Asset Portability in Immersive Environments. *International Journal of Distributed Systems*, 12(1), 112-130. https://doi.org/10.5678/ijds.2025.12.1.112\n\n---\n\nA compatibility process without a good standard is like trying to get a Geordie, a Mancunian, and a Yorkshireman to agree on the best pie—possible, but it takes a well-defined recipe and a lot of patience.\n\n## Metadata\n\n- **Last Updated**: 2025-11-11\n- **Review Status**: Comprehensive editorial review\n- **Verification**: Academic sources verified\n- **Regional Context**: UK/North England where applicable",
  "backlinks": [
    "Interoperability Framework"
  ],
  "wiki_links": [
    "InfrastructureDomain",
    "Asset Portability",
    "Technical Standards",
    "Reference Implementations",
    "Format Validation",
    "MSF Taxonomy 2025",
    "Interoperability Verification",
    "API Specifications",
    "Standards Conformance Testing",
    "Cross-Platform Interoperability",
    "Protocol Definitions",
    "Data Format Schemas",
    "Standards Compliance",
    "Ecosystem Connectivity",
    "Test Specifications",
    "Data Layer",
    "Integration Testing",
    "Protocol Compatibility Checks",
    "ISO/IEC 30170",
    "Compatibility Standards",
    "Interoperability Framework",
    "System Integration",
    "Cross-Platform Testing",
    "Conformance Criteria",
    "Validation Tools"
  ],
  "ontology": {
    "term_id": "20209",
    "preferred_term": "Compatibility Process",
    "alt_terms": [],
    "iri": "http://narrativegoldmine.com/metaverse#CompatibilityProcess",
    "source_domain": null,
    "domain": "mv",
    "domain_full_name": "Metaverse",
    "definition": "Systematic procedure for ensuring that digital assets, applications, and systems conform to common standards, protocols, and specifications to enable seamless exchange, integration, and interoperability across metaverse platforms.",
    "scope_note": null,
    "status": "draft",
    "maturity": "mature",
    "version": null,
    "public_access": true,
    "last_updated": null,
    "authority_score": null,
    "quality_score": null,
    "cross_domain_links": null,
    "owl_class": "mv:CompatibilityProcess",
    "owl_physicality": "VirtualEntity",
    "owl_role": "Process",
    "owl_inferred_class": "mv:VirtualProcess",
    "is_subclass_of": [],
    "has_part": [
      "Integration Testing",
      "Format Validation",
      "Interoperability Verification",
      "Cross-Platform Testing",
      "Standards Conformance Testing",
      "Protocol Compatibility Checks"
    ],
    "is_part_of": [],
    "requires": [
      "Test Specifications",
      "Compatibility Standards",
      "Conformance Criteria",
      "Reference Implementations",
      "Validation Tools"
    ],
    "depends_on": [
      "Technical Standards",
      "Interoperability Framework",
      "Protocol Definitions",
      "API Specifications",
      "Data Format Schemas"
    ],
    "enables": [
      "Standards Compliance",
      "System Integration",
      "Ecosystem Connectivity",
      "Cross-Platform Interoperability",
      "Asset Portability"
    ],
    "relates_to": [],
    "bridges_to": [],
    "bridges_from": [],
    "domain_extensions": {},
    "belongs_to_domain": [
      "InfrastructureDomain"
    ],
    "implemented_in_layer": [
      "Data Layer"
    ],
    "source": [
      "ISO/IEC 30170",
      "MSF Taxonomy 2025"
    ],
    "validation": {
      "is_valid": false,
      "errors": [
        "Missing required property: source-domain",
        "Missing required property: last-updated",
        "Missing required property: is-subclass-of (at least one parent class)",
        "term-id '20209' doesn't match domain 'mv' (expected MV-)"
      ]
    }
  }
}