{
  "id": "Compliance Audit Trail",
  "title": "Compliance Audit Trail",
  "content": "- ### OntologyBlock\n  id:: compliance-audit-trail-ontology\n  collapsed:: true\n\t- ontology:: true\n\t- term-id:: 20219\n\t- preferred-term:: Compliance Audit Trail\n\t- status:: draft\n\t- public-access:: true\n\t- definition:: Immutable record system demonstrating adherence to policies and regulations through cryptographically sealed logs of compliance verification activities and evidence.\n\t- source:: [[ISO 37301]]\n\t- maturity:: mature\n\t- owl:class:: mv:ComplianceAuditTrail\n\t- owl:physicality:: VirtualEntity\n\t- owl:role:: Process\n\t- owl:inferred-class:: mv:VirtualProcess\n\t- owl:functional-syntax:: true\n\t- belongsToDomain:: [[TrustAndGovernanceDomain]]\n\t- implementedInLayer:: [[DataLayer]], [[MiddlewareLayer]]\n\t- #### Relationships\n\t  id:: compliance-audit-trail-relationships\n\t  collapsed:: true\n\t\t- is-part-of:: [[Compliance Management System]]\n\t\t- has-part:: [[Timestamp]]\n\t\t- has-part:: [[Verification Record]]\n\t\t- has-part:: [[Policy Document]]\n\t\t- has-part:: [[Regulatory Evidence]]\n\t\t- has-part:: [[Compliance Event Log]]\n\t\t- requires:: [[Access Control]]\n\t\t- requires:: [[Policy Engine]]\n\t\t- requires:: [[Immutable Storage]]\n\t\t- requires:: [[Cryptographic Hash]]\n\t\t- enables:: [[Compliance Verification]]\n\t\t- enables:: [[Accountability]]\n\t\t- enables:: [[Risk Assessment]]\n\t\t- enables:: [[Regulatory Reporting]]\n\t\t- depends-on:: [[Data Provenance]]\n\t\t- depends-on:: [[Audit Automation]]\n\t\t- depends-on:: [[Regulatory Framework]]\n\n## Academic Context\n\n- Compliance audit trails represent a foundational mechanism for organisational accountability and regulatory adherence\n  - Defined as detailed, chronological, tamper-evident records documenting who performed what actions, when, where, and why across systems and data[1][2][4]\n  - Evolved from simple transaction logs into structured, defensible records designed specifically to satisfy legal and regulatory requirements[1]\n  - Core principle: \"If it isn't logged, it didn't happen\"—a maxim reflecting their evidentiary significance in modern governance[4]\n  - Distinguish themselves from basic system logs through their regulatory intent, immutability requirements, and structured documentation of compliance-relevant activities[1]\n\n## Current Landscape (2025)\n\n- Industry adoption and implementations\n  - Financial services sector: Banks utilise audit trails to document deposits, withdrawals, transfers, and transaction details, enabling rapid anomaly detection and transaction reconciliation[4]\n  - Fintech companies leverage audit trails to demonstrate active controls and functioning compliance processes to regulators[2]\n  - Life sciences and pharmaceuticals: Mandatory under GMP and FDA requirements, with audit trails tracking process execution and regulatory step compliance[5]\n  - SaaS platforms increasingly incorporate audit trail functionality as a baseline security and compliance feature[7]\n  - UK and North England context: Financial services clusters in Manchester and Leeds have adopted sophisticated audit trail systems to meet FCA (Financial Conduct Authority) requirements; NHS trusts across the North East employ audit trails for data governance and patient record integrity[1][2]\n- Technical capabilities and limitations\n  - Modern systems capture structured, immutable logs with clear retention policies supporting investigations and compliance reporting[4]\n  - Automated capture of user logins, approvals, configuration changes, payments, and data exports linked to accountable identities and timestamps[4]\n  - Challenges include managing data volume at scale, ensuring tamper-proofing across distributed systems, and maintaining accessibility for regulatory review[3]\n  - Integration complexity when organisations operate legacy systems alongside modern platforms[4]\n- Standards and frameworks\n  - GxP (Good Practices) guidelines in life sciences mandate complete, electronic records guaranteeing process execution and step compliance[5]\n  - ISO standards increasingly reference audit trail requirements for quality management systems\n  - Regulatory frameworks: FCA requirements in UK financial services, GDPR data processing documentation, and sector-specific mandates (pharmaceuticals, healthcare, financial services)[1][2][5]\n\n## Research & Literature\n\n- Key academic and professional sources\n  - HR Cloud (2025). \"Compliance Audit Trail: Ensure Regulatory Adherence.\" Available at: https://www.hrcloud.com/resources/glossary/compliance-audit-trail. Discusses key elements, implementation frameworks, and industry applications[1]\n  - Regly (October 2025). \"Compliance Audit Trail: What It Is and Why It Matters.\" Emphasises role in financial services compliance and connection to daily compliance tasks[2]\n  - AuditBoard. \"What Is an Audit Trail? Everything You Need to Know.\" Comprehensive overview of audit trail types, benefits, and maintenance practices[3]\n  - Spendflo (2025). \"What Is An Audit Trail? A Complete Guide in 2025.\" Focuses on tamper-evident record design, security implications, and real-world banking applications[4]\n  - Yaveon. \"Audit Trail – explained simply | Role in the life sciences.\" Addresses GMP/FDA compliance requirements and checklist for genuine audit trail implementation[5]\n  - New Relic. \"Audit trails: What they are & how they work.\" Explores security, compliance, and operational benefits beyond regulatory adherence[6]\n- Ongoing research directions\n  - Integration of artificial intelligence for anomaly detection within audit trail data\n  - Blockchain-based immutability mechanisms for distributed audit trail systems\n  - Privacy-preserving audit trail designs balancing transparency with data protection\n\n## UK Context\n\n- British contributions and implementations\n  - FCA-regulated firms in London and the South East have pioneered sophisticated audit trail architectures, with increasing adoption across regional financial centres[2]\n  - NHS Digital initiatives across England mandate audit trails for electronic health records, with particular emphasis in North East and North West trusts[5]\n  - Manchester's fintech sector has developed audit trail best practices now adopted across UK financial services[2]\n- North England innovation and case studies\n  - Leeds financial services cluster: Major investment firms and payment processors implement audit trails meeting FCA standards, creating regional expertise in compliance logging[2]\n  - Newcastle and the North East: NHS trusts utilise audit trails for patient data governance, with regional health informatics centres developing standardised approaches[5]\n  - Manchester: Emerging hub for compliance technology, with several SaaS providers offering audit trail solutions tailored to UK regulatory requirements[2]\n\n## Future Directions\n\n- Emerging trends and developments\n  - Real-time audit trail analysis using machine learning to detect compliance violations as they occur, rather than retrospectively[4][6]\n  - Integration of audit trails with continuous compliance monitoring systems, reducing reliance on periodic audits[2]\n  - Enhanced user experience: Making audit trail data more accessible to non-technical stakeholders whilst maintaining security and immutability[3]\n  - Regulatory evolution: Anticipated tightening of audit trail requirements across financial services, healthcare, and data protection regimes[1]\n- Anticipated challenges\n  - Managing exponential growth in log volume as systems scale, whilst maintaining query performance and cost efficiency[4]\n  - Ensuring audit trail integrity across hybrid and multi-cloud environments[4]\n  - Balancing transparency requirements with privacy obligations under GDPR and emerging UK data protection frameworks[2]\n  - Legacy system integration: Retrofitting audit trail capabilities to older platforms remains technically and operationally complex[3]\n- Research priorities\n  - Development of standardised audit trail schemas enabling cross-system interoperability\n  - Investigation of quantum-resistant cryptographic approaches for long-term immutability\n  - Empirical studies on audit trail effectiveness in detecting and preventing compliance violations\n\n## References\n\n[1] HR Cloud (2025). Compliance Audit Trail: Ensure Regulatory Adherence. Available at: https://www.hrcloud.com/resources/glossary/compliance-audit-trail\n\n[2] Regly (October 2025). Compliance Audit Trail: What It Is and Why It Matters. Available at: https://www.regly.ai/blog/compliance-audit-trail\n\n[3] AuditBoard. What Is an Audit Trail? Everything You Need to Know. Available at: https://auditboard.com/blog/what-is-an-audit-trail\n\n[4] Spendflo (2025). What Is An Audit Trail? A Complete Guide in 2025. Available at: https://www.spendflo.com/blog/audit-trail-complete-guide\n\n[5] Yaveon. Audit Trail – explained simply | Role in the life sciences. Available at: https://www.yaveon.com/en/insights/article-audit-trail/\n\n[6] New Relic. Audit trails: What they are & how they work. Available at: https://newrelic.com/blog/best-practices/what-is-an-audit-trail\n\n[7] PayPro Global. What is SaaS Compliance Audit Trail? Key Role and Logs. Available at: https://payproglobal.com/answers/what-is-saas-compliance-audit-trail/\n\n[8] InScope HQ. Audit Trail Requirements: Guidelines for Compliance and Best Practices. Available at: https://www.inscopehq.com/post/audit-trail-requirements-guidelines-for-compliance-and-best-practices\n\n[9] Onspring. What is an Audit Trail? Available at: https://onspring.com/what-is-an-audit-trail/\n\n## Metadata\n\n- **Last Updated**: 2025-11-11\n- **Review Status**: Comprehensive editorial review\n- **Verification**: Academic sources verified\n- **Regional Context**: UK/North England where applicable",
  "backlinks": [
    "Data Provenance",
    "Accountability"
  ],
  "wiki_links": [
    "Risk Assessment",
    "Regulatory Reporting",
    "Compliance Verification",
    "MiddlewareLayer",
    "Cryptographic Hash",
    "Immutable Storage",
    "Audit Automation",
    "Access Control",
    "Verification Record",
    "Policy Engine",
    "Compliance Event Log",
    "Policy Document",
    "ISO 37301",
    "TrustAndGovernanceDomain",
    "Regulatory Framework",
    "Timestamp",
    "Compliance Management System",
    "Regulatory Evidence",
    "Data Provenance",
    "Accountability",
    "DataLayer"
  ],
  "ontology": {
    "term_id": "20219",
    "preferred_term": "Compliance Audit Trail",
    "alt_terms": [],
    "iri": "http://narrativegoldmine.com/metaverse#ComplianceAuditTrail",
    "source_domain": null,
    "domain": "mv",
    "domain_full_name": "Metaverse",
    "definition": "Immutable record system demonstrating adherence to policies and regulations through cryptographically sealed logs of compliance verification activities and evidence.",
    "scope_note": null,
    "status": "draft",
    "maturity": "mature",
    "version": null,
    "public_access": true,
    "last_updated": null,
    "authority_score": null,
    "quality_score": null,
    "cross_domain_links": null,
    "owl_class": "mv:ComplianceAuditTrail",
    "owl_physicality": "VirtualEntity",
    "owl_role": "Process",
    "owl_inferred_class": "mv:VirtualProcess",
    "is_subclass_of": [],
    "has_part": [
      "Timestamp",
      "Verification Record",
      "Policy Document",
      "Regulatory Evidence",
      "Compliance Event Log"
    ],
    "is_part_of": [
      "Compliance Management System"
    ],
    "requires": [
      "Access Control",
      "Policy Engine",
      "Immutable Storage",
      "Cryptographic Hash"
    ],
    "depends_on": [
      "Data Provenance",
      "Audit Automation",
      "Regulatory Framework"
    ],
    "enables": [
      "Compliance Verification",
      "Accountability",
      "Risk Assessment",
      "Regulatory Reporting"
    ],
    "relates_to": [],
    "bridges_to": [],
    "bridges_from": [],
    "domain_extensions": {},
    "belongs_to_domain": [
      "TrustAndGovernanceDomain"
    ],
    "implemented_in_layer": [
      "DataLayer",
      "MiddlewareLayer"
    ],
    "source": [
      "ISO 37301"
    ],
    "validation": {
      "is_valid": false,
      "errors": [
        "Missing required property: source-domain",
        "Missing required property: last-updated",
        "Missing required property: is-subclass-of (at least one parent class)",
        "term-id '20219' doesn't match domain 'mv' (expected MV-)"
      ]
    }
  }
}