{
  "id": "ConsensusAlgorithm",
  "title": "ConsensusAlgorithm",
  "content": "- ### OntologyBlock\n  id:: consensusalgorithm-ontology\n  collapsed:: true\n\t- ontology:: true\n    - is-subclass-of:: [[BlockchainTechnology]]\n\t- term-id:: BC-0002\n\t- preferred-term:: ConsensusAlgorithm\n\t- source-domain:: blockchain\n\t- status:: active\n\t- public-access:: true\n\t- definition:: A protocol used by distributed systems to achieve agreement on a single data value or state among multiple nodes, ensuring network integrity and preventing double-spending.\n\t- maturity:: mature\n\t- owl:class:: bc:ConsensusAlgorithm\n\t- owl:equivalentClass:: mv:ConsensusAlgorithm\n\t- owl:physicality:: ConceptualEntity\n\t- owl:role:: Process\n\t- belongsToDomain:: [[BlockchainDomain]]\n\n## OWL Formal Semantics\n\n```clojure\n;; OWL Functional Syntax\n\n(Declaration (Class :Consensusalgorithm))\n\n;; Annotations\n(AnnotationAssertion rdfs:label :Consensusalgorithm \"ConsensusAlgorithm\"@en)\n(AnnotationAssertion rdfs:comment :Consensusalgorithm \"A component of the metaverse ecosystem.\"@en)\n\n;; Data Properties\n(AnnotationAssertion dcterms:identifier :Consensusalgorithm \"mv-1761742247908\"^^xsd:string)\n```",
  "backlinks": [],
  "wiki_links": [
    "BlockchainDomain",
    "BlockchainTechnology"
  ],
  "ontology": {
    "term_id": "BC-0002",
    "preferred_term": "ConsensusAlgorithm",
    "alt_terms": [],
    "iri": "http://narrativegoldmine.com/blockchain#ConsensusAlgorithm",
    "source_domain": "blockchain",
    "domain": "blockchain",
    "domain_full_name": "",
    "definition": "A protocol used by distributed systems to achieve agreement on a single data value or state among multiple nodes, ensuring network integrity and preventing double-spending.",
    "scope_note": null,
    "status": "active",
    "maturity": "mature",
    "version": null,
    "public_access": true,
    "last_updated": null,
    "authority_score": null,
    "quality_score": null,
    "cross_domain_links": null,
    "owl_class": "bc:ConsensusAlgorithm",
    "owl_physicality": "ConceptualEntity",
    "owl_role": "Process",
    "owl_inferred_class": null,
    "is_subclass_of": [],
    "has_part": [],
    "is_part_of": [],
    "requires": [],
    "depends_on": [],
    "enables": [],
    "relates_to": [],
    "bridges_to": [],
    "bridges_from": [],
    "domain_extensions": {},
    "belongs_to_domain": [
      "BlockchainDomain"
    ],
    "implemented_in_layer": [],
    "source": [],
    "validation": {
      "is_valid": false,
      "errors": [
        "Missing required property: last-updated",
        "Missing required property: is-subclass-of (at least one parent class)",
        "owl:class namespace 'bc' doesn't match source-domain 'blockchain'"
      ]
    }
  }
}