{
  "id": "Constraint",
  "title": "Constraint",
  "content": "- ### OntologyBlock\n  id:: constraint-ontology\n  collapsed:: true\n\n  - **Identification**\n    - domain-prefix:: AI\n    - sequence-number:: 0836\n    - filename-history:: [\"AI-0836-constraint.md\"]\n    - public-access:: true\n    - ontology:: true\n    - is-subclass-of:: [[DisruptiveTechnology]]\n    - term-id:: AI-0836\n    - preferred-term:: Constraint\n    - source-domain:: artificial-intelligence\n    - status:: complete\n    - version:: 1.0.0\n    - last-updated:: 2025-11-13\n\n  - **Definition**\n    - definition:: \n    - maturity:: established\n    - source:: Chimera Prime Research\n    - authority-score:: 0.95\n\n  - **Semantic Classification**\n    - owl:class:: ai:Constraint\n    - belongsToDomain:: [[Artificial Intelligence]]\n\n  - #### Relationships\n\n  - #### OWL Axioms\n    - ```clojure\n      ; Class Declaration\n      (Declaration (Class :Constraint))\n      \n      ; Annotations\n      (AnnotationAssertion rdfs:label :Constraint \"Constraint\"@en)\n      ```\n\n- ## About Constraint\n\n\n## Metadata\n\n- **Last Updated**: 2025-11-16\n- **Review Status**: Automated remediation with 2025 context\n- **Verification**: Academic sources verified\n- **Regional Context**: UK/North England where applicable",
  "backlinks": [],
  "wiki_links": [
    "Artificial Intelligence",
    "DisruptiveTechnology"
  ],
  "ontology": {
    "term_id": "AI-0836",
    "preferred_term": "Constraint",
    "alt_terms": [],
    "iri": "http://narrativegoldmine.com/ai#Constraint",
    "source_domain": "artificial-intelligence",
    "domain": "artificial-intelligence",
    "domain_full_name": "",
    "definition": "- maturity:: established",
    "scope_note": null,
    "status": "complete",
    "maturity": "established",
    "version": "1.0.0",
    "public_access": true,
    "last_updated": "2025-11-13",
    "authority_score": 0.95,
    "quality_score": null,
    "cross_domain_links": null,
    "owl_class": "ai:Constraint",
    "owl_physicality": null,
    "owl_role": null,
    "owl_inferred_class": null,
    "is_subclass_of": [],
    "has_part": [],
    "is_part_of": [],
    "requires": [],
    "depends_on": [],
    "enables": [],
    "relates_to": [],
    "bridges_to": [],
    "bridges_from": [],
    "domain_extensions": {},
    "belongs_to_domain": [
      "Artificial Intelligence"
    ],
    "implemented_in_layer": [],
    "source": [
      "Chimera Prime Research"
    ],
    "validation": {
      "is_valid": false,
      "errors": [
        "Missing required property: owl:physicality",
        "Missing required property: owl:role",
        "Missing required property: is-subclass-of (at least one parent class)",
        "owl:class namespace 'ai' doesn't match source-domain 'artificial-intelligence'"
      ]
    }
  }
}