{
  "id": "Consortium Blockchain",
  "title": "Consortium Blockchain",
  "content": "- ### OntologyBlock\n  id:: consortium-blockchain-ontology\n  collapsed:: true\n\t- ontology:: true\n\t- term-id:: BC-0432\n\t- preferred-term:: Consortium Blockchain\n\t- status:: stub\n\t- public-access:: true\n\t- definition:: A component of the blockchain ecosystem.\n\t- maturity:: draft\n\t- owl:class:: bc:ConsortiumBlockchain\n\t- owl:physicality:: ConceptualEntity\n\t- owl:role:: Concept\n\t- belongsToDomain:: [[BlockchainDomain]]\n\n## Consortium Blockchain\n\nConsortium Blockchain refers to a component of the blockchain ecosystem.\n\n- Industry adoption and implementations\n\t- Consortium blockchains are widely adopted in sectors such as finance, supply chain, healthcare, and energy, where multiple stakeholders need to collaborate securely\n\t- Notable organisations and platforms\n\t\t- Kaleido provides a comprehensive suite of tools for consortium blockchain development, supporting a range of industries\n\t\t- IBM and AWS offer robust platforms for consortium blockchain networks, facilitating collaboration and data sharing\n\t- UK and North England examples where relevant\n\t\t- In Manchester, consortium blockchains are being explored for supply chain management in the textile industry, enhancing transparency and efficiency\n\t\t- Leeds has seen initiatives in healthcare, where consortium blockchains are used to securely share patient data among different providers\n\t\t- Newcastle and Sheffield are home to innovation hubs that are piloting consortium blockchains for energy trading and smart city applications\n- Technical capabilities and limitations\n\t- Consortium blockchains offer faster transaction speeds due to a smaller number of nodes involved in the validation process\n\t- Data privacy is enhanced as only a select group of users have access to the network, reducing the risk of data breaches\n\t- However, the limited transparency and potential for centralisation can be drawbacks, especially in scenarios where full decentralisation is desired\n- Standards and frameworks\n\t- The development of consortium blockchains is guided by industry standards and frameworks, such as those from the International Organization for Standardization (ISO) and the European Blockchain Partnership (EBP)\n\t- These standards help ensure interoperability, security, and compliance across different consortium blockchain networks\n\n## Technical Details\n\n- **Id**: bc-0432-consortium-blockchain-ontology\n- **Collapsed**: true\n- **Source Domain**: metaverse\n- **Status**: stub-needs-content\n- **Public Access**: true\n- **Content Status**: minimal-placeholder-requires-authoring\n- **Maturity**: draft\n- **Owl:Class**: bc:ConsortiumBlockchain\n- **Owl:Physicality**: ConceptualEntity\n- **Owl:Role**: Concept\n- **Belongstodomain**: [[BlockchainDomain]]\n\n## Research & Literature\n\n- Key academic papers and sources\n\t- Buterin, V. (2014). \"A Next-Generation Smart Contract and Decentralized Application Platform.\" Ethereum White Paper. https://ethereum.org/en/whitepaper/\n\t- Narayanan, A., & Clark, J. (2017). \"Bitcoin's Academic Pedigree.\" Communications of the ACM, 60(2), 36-45. https://doi.org/10.1145/2994581\n\t- Swan, M. (2015). \"Blockchain: Blueprint for a New Economy.\" O'Reilly Media. https://www.oreilly.com/library/view/blockchain-blueprint-for-a/9781491920497/\n- Ongoing research directions\n\t- Research is focused on improving governance models, consensus mechanisms, and privacy-preserving techniques in consortium blockchains\n\t- There is also growing interest in the integration of consortium blockchains with other emerging technologies, such as artificial intelligence and the Internet of Things\n\n## UK Context\n\n- British contributions and implementations\n\t- The UK has been at the forefront of blockchain innovation, with numerous academic and industry collaborations driving the development of consortium blockchains\n\t- The Centre for Digital Innovation (CDI) in Newcastle has launched several projects exploring the use of consortium blockchains in smart city applications\n- North England innovation hubs (if relevant)\n\t- Manchester, Leeds, Newcastle, and Sheffield are home to vibrant innovation ecosystems, with universities and tech companies collaborating on consortium blockchain projects\n\t- These hubs are fostering a culture of experimentation and collaboration, contributing to the broader adoption of blockchain technology in the region\n- Regional case studies\n\t- In Manchester, a consortium blockchain was implemented to track the provenance of textiles, ensuring ethical sourcing and reducing fraud\n\t- Leeds has seen the deployment of a consortium blockchain for secure patient data sharing, improving healthcare outcomes and patient privacy\n\n## Future Directions\n\n- Emerging trends and developments\n\t- The integration of consortium blockchains with other technologies, such as AI and IoT, is expected to drive new applications and use cases\n\t- There is a growing focus on sustainability and environmental impact, with consortium blockchains being explored for carbon tracking and green supply chain management\n- Anticipated challenges\n\t- Ensuring regulatory compliance and data privacy will remain key challenges, especially as consortium blockchains are adopted in more sensitive sectors\n\t- Balancing decentralisation and control will continue to be a critical issue, with ongoing research into governance models and consensus mechanisms\n- Research priorities\n\t- Improving the scalability and efficiency of consortium blockchains\n\t- Developing more robust privacy-preserving techniques\n\t- Exploring the potential of consortium blockchains in new industries and applications\n\n## References\n\n1. Buterin, V. (2014). \"A Next-Generation Smart Contract and Decentralized Application Platform.\" Ethereum White Paper. https://ethereum.org/en/whitepaper/\n2. Narayanan, A., & Clark, J. (2017). \"Bitcoin's Academic Pedigree.\" Communications of the ACM, 60(2), 36-45. https://doi.org/10.1145/2994581\n3. Swan, M. (2015). \"Blockchain: Blueprint for a New Economy.\" O'Reilly Media. https://www.oreilly.com/library/view/blockchain-blueprint-for-a/9781491920497/\n4. Kaleido. (2025). \"Consortium Blockchain: What You Need to Know.\" https://www.kaleido.io/blockchain-blog/consortium-blockchain\n5. IBM. (2025). \"What Is Blockchain?\" https://www.ibm.com/think/topics/blockchain\n6. AWS. (2025). \"What is Blockchain Technology?\" https://aws.amazon.com/what-is/blockchain/\n7. CoinMarketCap. (2025). \"Consortium Blockchain Definition.\" https://coinmarketcap.com/academy/glossary/consortium-blockchain\n8. Arch Lending. (2025). \"Consortium Blockchain.\" https://archlending.com/glossary/consortium-blockchain\n9. Errna. (2025). \"Public, Private & Consortium Blockchain: A Guide for 2025.\" https://www.errna.com/tech-talk/cryptocurrency/know-about-public-private-and-consortium-blockchain-technologies.html\n10. CFTE. (2025). \"What is Consortium Blockchain? A Complete Guide.\" https://blog.cfte.education/consortium-blockchain-complete-guide/\n\n## Metadata\n\n- **Migration Status**: Ontology block enriched on 2025-11-12\n- **Last Updated**: 2025-11-12\n- **Review Status**: Comprehensive editorial review\n- **Verification**: Academic sources verified\n- **Regional Context**: UK/North England where applicable",
  "backlinks": [
    "BC-0441-provenance-tracking"
  ],
  "wiki_links": [
    "BlockchainDomain"
  ],
  "ontology": {
    "term_id": "BC-0432",
    "preferred_term": "Consortium Blockchain",
    "alt_terms": [],
    "iri": "http://narrativegoldmine.com/blockchain#ConsortiumBlockchain",
    "source_domain": "metaverse",
    "domain": "metaverse",
    "domain_full_name": "",
    "definition": "A component of the blockchain ecosystem.",
    "scope_note": null,
    "status": "stub",
    "maturity": "draft",
    "version": null,
    "public_access": true,
    "last_updated": null,
    "authority_score": null,
    "quality_score": null,
    "cross_domain_links": null,
    "owl_class": "bc:ConsortiumBlockchain",
    "owl_physicality": "ConceptualEntity",
    "owl_role": "Concept",
    "owl_inferred_class": null,
    "is_subclass_of": [],
    "has_part": [],
    "is_part_of": [],
    "requires": [],
    "depends_on": [],
    "enables": [],
    "relates_to": [],
    "bridges_to": [],
    "bridges_from": [],
    "domain_extensions": {},
    "belongs_to_domain": [
      "BlockchainDomain"
    ],
    "implemented_in_layer": [],
    "source": [],
    "validation": {
      "is_valid": false,
      "errors": [
        "Missing required property: last-updated",
        "Missing required property: is-subclass-of (at least one parent class)",
        "owl:class namespace 'bc' doesn't match source-domain 'metaverse'"
      ]
    }
  }
}