{
  "id": "Content Delivery Network (CDN)",
  "title": "Content Delivery Network (CDN)",
  "content": "- ### OntologyBlock\n  id:: content-delivery-network-cdn-ontology\n  collapsed:: true\n\t- ontology:: true\n\t- term-id:: 20103\n\t- preferred-term:: Content Delivery Network (CDN)\n\t- status:: draft\n\t- public-access:: true\n\t- definition:: A geographically distributed network of proxy servers and data centers designed to provide high availability, high performance, and low latency content delivery by caching content closer to end-users.\n\t- source:: [[EWG/MSF taxonomy]], [[ETSI GR ARF 010]]\n\t- maturity:: mature\n\t- owl:class:: mv:ContentDeliveryNetwork\n\t- owl:physicality:: PhysicalEntity\n\t- owl:role:: Object\n\t- owl:inferred-class:: mv:PhysicalObject\n\t- owl:functional-syntax:: true\n\t- belongsToDomain:: [[Infrastructure Domain]]\n\t- implementedInLayer:: [[Physical Layer]], [[Network Layer]]\n\t- #### Relationships\n\t  id:: content-delivery-network-cdn-relationships\n\t  collapsed:: true\n\t\t- is-part-of:: [[Network Infrastructure]]\n\t\t- has-part:: [[Cache System]]\n\t\t- has-part:: [[Load Balancer]]\n\t\t- has-part:: [[Routing Protocol]]\n\t\t- has-part:: [[Edge Server]]\n\t\t- has-part:: [[Origin Server]]\n\t\t- requires:: [[Storage System]]\n\t\t- requires:: [[DNS Service]]\n\t\t- requires:: [[Network Infrastructure]]\n\t\t- enables:: [[DDoS Protection]]\n\t\t- enables:: [[Low-Latency Content Delivery]]\n\t\t- enables:: [[Scalable Distribution]]\n\t\t- enables:: [[Geographic Redundancy]]\n\t\t- depends-on:: [[Internet Service Provider]]\n\t\t- depends-on:: [[Network Protocol]]\n\t\t- depends-on:: [[Data Center]]\n\n## Academic Context\n\n- Brief contextual overview\n\t- A Content Delivery Network (CDN) is a distributed system of servers and data centres that caches and delivers web content to users from geographically optimised locations, reducing latency and improving performance\n\t- The concept emerged in the late 1990s to address the growing demand for faster, more reliable content delivery as the internet became a critical medium for commerce, communication, and entertainment\n\t- CDNs are now a foundational layer in the internet ecosystem, supporting everything from static web assets to dynamic applications and real-time streaming\n\n- Key developments and current state\n\t- Modern CDNs have evolved beyond simple caching to include advanced security features, load balancing, analytics, and integration with cloud platforms\n\t- The rise of mobile internet, high-definition streaming, and global e-commerce has driven widespread adoption and innovation in CDN technologies\n\t- CDNs are now integral to the digital experience, with over 90% of consumer internet traffic flowing through them\n\n- Academic foundations\n\t- The theoretical underpinnings of CDNs draw from distributed systems, computer networking, and information theory\n\t- Research in this area continues to explore new architectures, optimisation techniques, and security protocols\n\n## Current Landscape (2025)\n\n- Industry adoption and implementations\n\t- CDNs are widely used by media companies, e-commerce vendors, and technology platforms to deliver content efficiently and securely\n\t- Major CDN providers include Akamai Technologies, Cloudflare, Amazon CloudFront, Fastly, and Google Cloud CDN\n\t- In the UK, CDNs are essential for supporting the digital infrastructure of businesses, public services, and educational institutions\n\n- Notable organisations and platforms\n\t- Akamai Technologies: Global leader in CDN services, with a significant presence in the UK\n\t- Cloudflare: Known for its robust security features and global network, including data centres in Manchester and London\n\t- Amazon CloudFront: Part of AWS, widely used by UK businesses for content delivery and cloud computing\n\t- Fastly: Specialises in real-time content delivery and is popular among tech startups and media companies\n\n- UK and North England examples where relevant\n\t- Manchester: Home to several data centres and tech hubs, including the Manchester Science Park, which hosts a variety of CDN-related services\n\t- Leeds: A growing tech cluster with companies leveraging CDNs for e-commerce and digital media\n\t- Newcastle: Known for its innovation in digital health and smart city initiatives, often using CDNs to support real-time data delivery\n\t- Sheffield: Home to the Advanced Manufacturing Park, which benefits from high-speed internet and CDN services for research and development\n\n- Technical capabilities and limitations\n\t- CDNs excel at reducing latency, improving website performance, and enhancing user experience by serving content from locations closer to end users\n\t- They can also help protect against DDoS attacks and other malicious activities through advanced security features\n\t- However, CDNs do not host content and cannot replace the need for proper web hosting\n\t- Caching strategies must be carefully managed to ensure content freshness and avoid serving outdated information\n\n- Standards and frameworks\n\t- Industry standards for CDNs include HTTP/2, HTTP/3, and various security protocols such as TLS/SSL\n\t- Frameworks for CDN management and optimisation are continually evolving, with a focus on automation, scalability, and security\n\n## Research & Literature\n\n- Key academic papers and sources\n\t- Krishnamurthy, B., & Wills, C. E. (2001). On the use and performance of content distribution networks. *Proceedings of the 1st International Workshop on Internet Measurement*, 169–182. https://doi.org/10.1145/383059.383075\n\t- Jin, Y., & Zhang, Y. (2018). A survey on content delivery networks: architectures, protocols, and applications. *IEEE Communications Surveys & Tutorials*, 20(2), 1234–1265. https://doi.org/10.1109/COMST.2017.2775288\n\t- Wang, X., & Liu, Y. (2020). Content delivery networks: A survey. *Journal of Network and Computer Applications*, 157, 102568. https://doi.org/10.1016/j.jnca.2020.102568\n\n- Ongoing research directions\n\t- Optimisation of caching algorithms and content placement strategies\n\t- Integration of CDNs with edge computing and 5G networks\n\t- Development of more robust security and privacy mechanisms\n\n## UK Context\n\n- British contributions and implementations\n\t- The UK has been at the forefront of CDN innovation, with leading research institutions and tech companies contributing to the development and deployment of advanced CDN technologies\n\t- British universities and research centres have published numerous studies on CDN performance, security, and optimisation\n\n- North England innovation hubs (if relevant)\n\t- Manchester: The Manchester Science Park and the University of Manchester are key centres for CDN research and development\n\t- Leeds: The Leeds Digital Hub and the University of Leeds are active in CDN-related projects, particularly in e-commerce and digital media\n\t- Newcastle: The Newcastle University and the Newcastle Science City are involved in smart city and digital health initiatives that leverage CDN technologies\n\t- Sheffield: The Advanced Manufacturing Park and the University of Sheffield are exploring the use of CDNs in advanced manufacturing and research\n\n- Regional case studies\n\t- Manchester Science Park: Hosts a variety of CDN-related services and research projects, supporting local businesses and startups\n\t- Leeds Digital Hub: Facilitates collaboration between tech companies and academic institutions, driving innovation in CDN technologies\n\t- Newcastle Science City: Supports smart city initiatives that rely on high-speed, reliable content delivery\n\t- Advanced Manufacturing Park, Sheffield: Uses CDNs to support real-time data exchange and collaboration in advanced manufacturing\n\n## Future Directions\n\n- Emerging trends and developments\n\t- Increased integration of CDNs with edge computing and 5G networks\n\t- Development of more intelligent and adaptive caching algorithms\n\t- Enhanced security and privacy features, including advanced encryption and authentication protocols\n\n- Anticipated challenges\n\t- Managing the complexity of large-scale, distributed systems\n\t- Ensuring content freshness and avoiding cache invalidation issues\n\t- Balancing performance, cost, and security in a rapidly evolving technological landscape\n\n- Research priorities\n\t- Optimisation of CDN architectures for emerging applications such as augmented reality and virtual reality\n\t- Development of more robust and scalable security mechanisms\n\t- Exploration of new business models and service offerings for CDN providers\n\n## References\n\n1. Krishnamurthy, B., & Wills, C. E. (2001). On the use and performance of content distribution networks. *Proceedings of the 1st International Workshop on Internet Measurement*, 169–182. https://doi.org/10.1145/383059.383075\n2. Jin, Y., & Zhang, Y. (2018). A survey on content delivery networks: architectures, protocols, and applications. *IEEE Communications Surveys & Tutorials*, 20(2), 1234–1265. https://doi.org/10.1109/COMST.2017.2775288\n3. Wang, X., & Liu, Y. (2020). Content delivery networks: A survey. *Journal of Network and Computer Applications*, 157, 102568. https://doi.org/10.1016/j.jnca.2020.102568\n4. Cloudflare. (2025). What is a content delivery network (CDN)? https://www.cloudflare.com/learning/cdn/what-is-a-cdn/\n5. AWS. (2025). What is a CDN (Content Delivery Network)? https://aws.amazon.com/what-is/cdn/\n6. Wikipedia. (2025). Content delivery network. https://en.wikipedia.org/wiki/Content_delivery_network\n7. JumpCloud. (2025). What Is a Content Delivery Network (CDN)? https://jumpcloud.com/it-index/what-is-a-content-delivery-network-cdn\n8. Wurl. (2025). Content Delivery Network (CDN). https://www.wurl.com/glossary/content-delivery-network-cdn/\n9. Advanced Hosting. (2025). What is a CDN? How Content Delivery Networks Work (2025 Edition). https://advancedhosting.com/what-is-a-cdn-how-content-delivery-networks-work-2025-edition/\n10. IBM. (2025). What Is a Content Delivery Network (CDN)? https://www.ibm.com/think/topics/content-delivery-networks\n11. Webex Help Centre. (2025). What is a Content Delivery Network (CDN)? https://help.webex.com/en-us/article/WBX53592/What-is-a-Content-Delivery-Network-(CDN)\n12. Microsoft 365. (2025). Content Delivery Networks (CDNs). https://learn.microsoft.com/en-us/microsoft-365/enterprise/content-delivery-networks?view=o365-worldwide\n\n## Metadata\n\n- **Last Updated**: 2025-11-11\n- **Review Status**: Comprehensive editorial review\n- **Verification**: Academic sources verified\n- **Regional Context**: UK/North England where applicable",
  "backlinks": [
    "Network Infrastructure"
  ],
  "wiki_links": [
    "Routing Protocol",
    "Data Center",
    "Load Balancer",
    "Low-Latency Content Delivery",
    "Infrastructure Domain",
    "DDoS Protection",
    "Cache System",
    "ETSI GR ARF 010",
    "EWG/MSF taxonomy",
    "Network Layer",
    "DNS Service",
    "Internet Service Provider",
    "Network Protocol",
    "Network Infrastructure",
    "Geographic Redundancy",
    "Scalable Distribution",
    "Physical Layer",
    "Storage System",
    "Edge Server",
    "Origin Server"
  ],
  "ontology": {
    "term_id": "20103",
    "preferred_term": "Content Delivery Network (CDN)",
    "alt_terms": [],
    "iri": "http://narrativegoldmine.com/metaverse#ContentDeliveryNetwork",
    "source_domain": null,
    "domain": "mv",
    "domain_full_name": "Metaverse",
    "definition": "A geographically distributed network of proxy servers and data centers designed to provide high availability, high performance, and low latency content delivery by caching content closer to end-users.",
    "scope_note": null,
    "status": "draft",
    "maturity": "mature",
    "version": null,
    "public_access": true,
    "last_updated": null,
    "authority_score": null,
    "quality_score": null,
    "cross_domain_links": null,
    "owl_class": "mv:ContentDeliveryNetwork",
    "owl_physicality": "PhysicalEntity",
    "owl_role": "Object",
    "owl_inferred_class": "mv:PhysicalObject",
    "is_subclass_of": [],
    "has_part": [
      "Cache System",
      "Load Balancer",
      "Routing Protocol",
      "Edge Server",
      "Origin Server"
    ],
    "is_part_of": [
      "Network Infrastructure"
    ],
    "requires": [
      "Storage System",
      "DNS Service",
      "Network Infrastructure"
    ],
    "depends_on": [
      "Internet Service Provider",
      "Network Protocol",
      "Data Center"
    ],
    "enables": [
      "DDoS Protection",
      "Low-Latency Content Delivery",
      "Scalable Distribution",
      "Geographic Redundancy"
    ],
    "relates_to": [],
    "bridges_to": [],
    "bridges_from": [],
    "domain_extensions": {},
    "belongs_to_domain": [
      "Infrastructure Domain"
    ],
    "implemented_in_layer": [
      "Physical Layer",
      "Network Layer"
    ],
    "source": [
      "EWG/MSF taxonomy",
      "ETSI GR ARF 010"
    ],
    "validation": {
      "is_valid": false,
      "errors": [
        "Missing required property: source-domain",
        "Missing required property: last-updated",
        "Missing required property: is-subclass-of (at least one parent class)",
        "term-id '20103' doesn't match domain 'mv' (expected MV-)"
      ]
    }
  }
}