{
  "id": "Context Window",
  "title": "Context Window",
  "content": "- ### OntologyBlock\n  id:: context-window-ontology\n  collapsed:: true\n\t- ontology:: true\n\t- term-id:: AI-0238\n\t- preferred-term:: Context Window\n\t- source-domain:: ai\n\t- owl:class:: ai:ContextWindow\n\t- status:: approved\n\t- public-access:: true\n\t- definition:: The maximum sequence length that a model can process at once, determining how much prior context it can consider during generation or understanding tasks.\n\t- source:: [[Vaswani et al. 2017 Attention is All You Need]], [[Anthropic Context Windows Research 2024]], [[OpenAI GPT-4 Technical Report]]\n\t- maturity:: mature\n\t- #### Relationships\n\t  id:: context-window-relationships\n\t  collapsed:: true\n\t\t- is-subclass-of:: [[ModelProperty]]\n\n## Context Window\n\nContext Window refers to the maximum sequence length that a model can process at once, determining how much prior context it can consider during generation or understanding tasks.\n\n- Industry adoption of large context windows has expanded significantly, with state-of-the-art large language models (LLMs) supporting context windows ranging from several thousand tokens to over a million tokens.\n  - Notable models include GPT-4 Turbo (128k tokens), Anthropic’s Claude 2.1 (200k tokens), and Google DeepMind’s Gemini 1.5 Pro (up to 1 million tokens).\n  - Larger context windows enable models to process entire documents or codebases in one pass, improving reasoning and coherence but at the cost of increased computational resources, latency, and potential noise sensitivity.\n  - Despite advances, challenges such as “lost in the middle” effects—where information in the middle of the context window receives less attention—persist, though newer models show progress in mitigating these issues.\n- UK and North England examples:\n  - AI research hubs in Manchester and Leeds are increasingly involved in developing efficient context window management techniques, focusing on balancing model size, latency, and accuracy for enterprise applications.\n  - Sheffield’s AI innovation centres contribute to applied NLP research, including context window optimisation for domain-specific language models.\n  - Newcastle’s tech sector explores context window applications in time-series analysis and vision AI, extending beyond text to multimodal data.\n- Standards and frameworks for context window usage remain emergent, with ongoing efforts to standardise tokenisation methods and benchmarking protocols for context window performance.\n\n## Technical Details\n\n- **Id**: context-window-ontology\n- **Collapsed**: true\n- **Source Domain**: ai\n- **Status**: draft\n- **Public Access**: true\n\n## Research & Literature\n\n- Key academic papers and sources:\n  - Vaswani, A., Shazeer, N., Parmar, N., et al. (2017). *Attention is All You Need*. Advances in Neural Information Processing Systems, 30. [https://doi.org/10.5555/3295222.3295349]\n  - Dai, Z., Yang, Z., Yang, Y., Carbonell, J., Le, Q. V., & Salakhutdinov, R. (2019). *Transformer-XL: Attentive Language Models Beyond a Fixed-Length Context*. Proceedings of the 57th Annual Meeting of the Association for Computational Linguistics. [https://doi.org/10.18653/v1/P19-1285]\n  - Rae, J. W., Borgeaud, S., Cai, T., et al. (2021). *Scaling Language Models: Methods, Analysis & Insights from Training Gopher*. arXiv preprint arXiv:2112.11446. [https://arxiv.org/abs/2112.11446]\n- Ongoing research directions include:\n  - Efficient context window scaling to reduce computational overhead.\n  - Techniques for dynamic or asymmetric context loading to prioritise relevant information.\n  - Mitigation of context dilution and “lost in the middle” phenomena.\n  - Integration of retrieval-augmented generation (RAG) to extend effective context beyond fixed windows.\n\n## UK Context\n\n- British contributions to context window research are notable in both academia and industry, with universities such as the University of Manchester and University of Leeds leading NLP and AI research.\n  - Manchester’s AI research groups focus on scalable transformer models and context window optimisation for healthcare and legal text analysis.\n  - Leeds hosts interdisciplinary projects combining AI with social sciences, exploring context window impacts on language understanding in diverse dialects, including Northern English vernaculars.\n- North England innovation hubs:\n  - Sheffield’s Advanced Manufacturing Research Centre incorporates AI models with extended context windows for industrial data analysis.\n  - Newcastle’s AI startups apply context window concepts in multimodal AI, including video and sensor data processing.\n- Regional case studies:\n  - A Leeds-based fintech company utilises large context windows in fraud detection models, processing extensive transaction histories in real time.\n  - Manchester’s public sector AI initiatives employ context window-aware chatbots for citizen engagement, improving conversational coherence over extended interactions.\n\n## Future Directions\n\n- Emerging trends:\n  - Continued expansion of context window sizes, potentially reaching tens of millions of tokens, facilitated by hardware advances and algorithmic innovations.\n  - Hybrid models combining fixed context windows with external memory or retrieval systems to overcome inherent size limitations.\n  - Enhanced context window management techniques to dynamically focus on salient information, reducing noise and computational waste.\n- Anticipated challenges:\n  - Balancing context window size with latency and energy consumption, especially for real-time applications.\n  - Addressing model interpretability and ensuring relevant context is prioritised without overwhelming the model.\n  - Developing standardised benchmarks and evaluation metrics for context window effectiveness across diverse tasks.\n- Research priorities:\n  - Investigating asymmetric and hierarchical attention mechanisms.\n  - Exploring context window impacts on fairness and bias in language models.\n  - Integrating multimodal context windows for richer AI understanding across text, vision, and audio.\n\n## References\n\n1. Vaswani, A., Shazeer, N., Parmar, N., Uszkoreit, J., Jones, L., Gomez, A. N., Kaiser, Ł., & Polosukhin, I. (2017). Attention is All You Need. *Advances in Neural Information Processing Systems*, 30, 5998–6008. https://doi.org/10.5555/3295222.3295349\n2. Dai, Z., Yang, Z., Yang, Y., Carbonell, J., Le, Q. V., & Salakhutdinov, R. (2019). Transformer-XL: Attentive Language Models Beyond a Fixed-Length Context. *Proceedings of the 57th Annual Meeting of the Association for Computational Linguistics*, 2978–2988. https://doi.org/10.18653/v1/P19-1285\n3. Rae, J. W., Borgeaud, S., Cai, T., et al. (2021). Scaling Language Models: Methods, Analysis & Insights from Training Gopher. *arXiv preprint arXiv:2112.11446*. https://arxiv.org/abs/2112.11446\n4. IBM. (n.d.). What is a context window? IBM Think. Retrieved 2025, from https://www.ibm.com/think/topics/context-window\n5. Ultralytics. (n.d.). Context Window Explained. Retrieved 2025, from https://www.ultralytics.com/glossary/context-window\n6. Qodo AI. (2025). Understanding Context Window for AI Performance & Use Cases. Retrieved from https://www.qodo.ai/blog/context-windows/\n7. Tech Policy Institute. (2025). From Tokens to Context Windows: Simplifying AI Jargon. Retrieved from https://techpolicyinstitute.org/publications/artificial-intelligence/from-tokens-to-context-windows-simplifying-ai-jargon/\n\n## Metadata\n\n- **Last Updated**: 2025-11-11\n- **Review Status**: Comprehensive editorial review\n- **Verification**: Academic sources verified\n- **Regional Context**: UK/North England where applicable",
  "backlinks": [],
  "wiki_links": [
    "Vaswani et al. 2017 Attention is All You Need",
    "ModelProperty",
    "Anthropic Context Windows Research 2024",
    "OpenAI GPT-4 Technical Report"
  ],
  "ontology": {
    "term_id": "AI-0238",
    "preferred_term": "Context Window",
    "alt_terms": [],
    "iri": "http://narrativegoldmine.com/ai#ContextWindow",
    "source_domain": "ai",
    "domain": "ai",
    "domain_full_name": "Artificial Intelligence",
    "definition": "The maximum sequence length that a model can process at once, determining how much prior context it can consider during generation or understanding tasks.",
    "scope_note": null,
    "status": "approved",
    "maturity": "mature",
    "version": null,
    "public_access": true,
    "last_updated": null,
    "authority_score": null,
    "quality_score": null,
    "cross_domain_links": null,
    "owl_class": "ai:ContextWindow",
    "owl_physicality": null,
    "owl_role": null,
    "owl_inferred_class": null,
    "is_subclass_of": [
      "ModelProperty"
    ],
    "has_part": [],
    "is_part_of": [],
    "requires": [],
    "depends_on": [],
    "enables": [],
    "relates_to": [],
    "bridges_to": [],
    "bridges_from": [],
    "domain_extensions": {},
    "belongs_to_domain": [],
    "implemented_in_layer": [],
    "source": [
      "Vaswani et al. 2017 Attention is All You Need",
      "Anthropic Context Windows Research 2024",
      "OpenAI GPT-4 Technical Report"
    ],
    "validation": {
      "is_valid": false,
      "errors": [
        "Missing required property: last-updated",
        "Missing required property: owl:physicality",
        "Missing required property: owl:role"
      ]
    }
  }
}