{
  "id": "Convolutional Neural Network",
  "title": "Convolutional Neural Network",
  "content": "- ### OntologyBlock\n  id:: convolutional-neural-network-ontology\n  collapsed:: true\n\t- ontology:: true\n\t- term-id:: AI-0032\n\t- preferred-term:: Convolutional Neural Network\n\t- source-domain:: ai\n\t- owl:class:: ai:ConvolutionalNeuralNetwork\n\t- status:: approved\n\t- public-access:: true\n\t- definition:: ### Primary Definition\n\t- source:: [[LeCun et al. 1998 Gradient-Based Learning]], [[Krizhevsky et al. 2012 AlexNet]], [[He et al. 2016 ResNet]], [[IEEE CVPR Proceedings]]\n\t- maturity:: mature\n\t- #### Relationships\n\t  id:: convolutional-neural-network-relationships\n\t  collapsed:: true\n\t\t- is-subclass-of:: [[NeuralNetworkArchitecture]]\n\n## Academic Context\n\n- Convolutional Neural Networks (CNNs) are a class of deep learning models primarily designed to process data with a grid-like topology, such as images, audio spectrograms, and time series.\n  - They learn hierarchical feature representations through layers of convolutional filters (kernels) that detect increasingly complex patterns, from edges and textures to object parts and entire objects.\n  - CNNs are founded on principles of weight sharing and local connectivity, which reduce the number of parameters and improve generalisation compared to fully connected networks.\n  - The architecture typically includes convolutional layers, activation functions (commonly ReLU), pooling layers for dimensionality reduction, and fully connected layers for classification or regression tasks.\n\n## Current Landscape (2025)\n\n- CNNs remain the de facto standard for computer vision tasks such as image classification, object detection, and segmentation, although some applications are increasingly adopting transformer-based architectures.\n  - Industry adoption spans autonomous vehicles, medical imaging, security systems, and multimedia analysis.\n  - Notable platforms supporting CNN development include TensorFlow, PyTorch, and MATLAB.\n- In the UK, and particularly in North England, CNNs are actively researched and applied in innovation hubs and universities.\n  - Manchester, Leeds, Newcastle, and Sheffield host research groups and startups leveraging CNNs for healthcare imaging, industrial automation, and environmental monitoring.\n- Technical capabilities:\n  - CNNs excel at spatial feature extraction and are robust to translation, but can struggle with rotational invariance and require large labelled datasets.\n  - Limitations include high computational costs for very deep networks and vulnerability to adversarial attacks.\n- Standards and frameworks:\n  - Open-source libraries and model zoos provide standardised CNN architectures (e.g., ResNet, EfficientNet) facilitating reproducibility and benchmarking.\n\n## Research & Literature\n\n- Key academic papers:\n  - LeCun, Y., Bottou, L., Bengio, Y., & Haffner, P. (1998). Gradient-based learning applied to document recognition. *Proceedings of the IEEE*, 86(11), 2278-2324. DOI: 10.1109/5.726791\n  - Krizhevsky, A., Sutskever, I., & Hinton, G. E. (2012). ImageNet classification with deep convolutional neural networks. *Communications of the ACM*, 60(6), 84-90. DOI: 10.1145/3065386\n  - He, K., Zhang, X., Ren, S., & Sun, J. (2016). Deep residual learning for image recognition. *Proceedings of the IEEE Conference on Computer Vision and Pattern Recognition (CVPR)*, 770-778. DOI: 10.1109/CVPR.2016.90\n- Ongoing research directions include:\n  - Enhancing CNN efficiency via pruning and quantisation.\n  - Combining CNNs with transformers for improved context understanding.\n  - Developing CNNs resilient to adversarial examples.\n  - Applying CNNs beyond vision, e.g., in natural language processing and genomics.\n\n## UK Context\n\n- The UK has made significant contributions to CNN research and applications, with strong academic groups in institutions such as the University of Manchester and Newcastle University.\n- North England innovation hubs:\n  - Manchesterâ€™s AI and Data Science Institute focuses on healthcare imaging and industrial applications using CNNs.\n  - Leeds hosts startups applying CNNs for environmental monitoring and smart city projects.\n  - Newcastle and Sheffield contribute through interdisciplinary research combining CNNs with robotics and sensor data analysis.\n- Regional case studies:\n  - A Manchester-based project utilises CNNs for early cancer detection in medical images.\n  - Leeds researchers developed CNN models for air quality prediction using satellite imagery.\n\n## Future Directions\n\n- Emerging trends:\n  - Integration of CNNs with transformer architectures to leverage both local feature extraction and global context.\n  - Development of lightweight CNNs for deployment on edge devices and mobile platforms.\n  - Advances in self-supervised and unsupervised learning to reduce reliance on labelled data.\n- Anticipated challenges:\n  - Balancing model complexity with interpretability and explainability.\n  - Addressing ethical concerns around bias and privacy in CNN applications.\n  - Ensuring robustness against adversarial manipulation.\n- Research priorities:\n  - Improving CNN generalisation across diverse domains.\n  - Enhancing energy efficiency and reducing carbon footprint of CNN training.\n  - Expanding CNN applications in UK-specific sectors such as healthcare, manufacturing, and environmental science.\n\n## References\n\n1. LeCun, Y., Bottou, L., Bengio, Y., & Haffner, P. (1998). Gradient-based learning applied to document recognition. *Proceedings of the IEEE*, 86(11), 2278-2324. DOI: 10.1109/5.726791\n2. Krizhevsky, A., Sutskever, I., & Hinton, G. E. (2012). ImageNet classification with deep convolutional neural networks. *Communications of the ACM*, 60(6), 84-90. DOI: 10.1145/3065386\n3. He, K., Zhang, X., Ren, S., & Sun, J. (2016). Deep residual learning for image recognition. *Proceedings of the IEEE Conference on Computer Vision and Pattern Recognition (CVPR)*, 770-778. DOI: 10.1109/CVPR.2016.90\n4. IBM. What are Convolutional Neural Networks? IBM Think. Retrieved 2025.\n5. Wikipedia contributors. Convolutional neural network. Wikipedia. Retrieved 2025.\n6. MATLAB & Simulink. What Is a Convolutional Neural Network? MathWorks. Retrieved 2025.\n7. GeeksforGeeks. Convolutional Neural Network (CNN) in Machine Learning. Updated October 2025.\n\n## Metadata\n\n- **Last Updated**: 2025-11-11\n- **Review Status**: Comprehensive editorial review\n- **Verification**: Academic sources verified\n- **Regional Context**: UK/North England where applicable",
  "backlinks": [
    "Recurrent Neural Network",
    "Super-Resolution"
  ],
  "wiki_links": [
    "NeuralNetworkArchitecture",
    "LeCun et al. 1998 Gradient-Based Learning",
    "IEEE CVPR Proceedings",
    "He et al. 2016 ResNet",
    "Krizhevsky et al. 2012 AlexNet"
  ],
  "ontology": {
    "term_id": "AI-0032",
    "preferred_term": "Convolutional Neural Network",
    "alt_terms": [],
    "iri": "http://narrativegoldmine.com/ai#ConvolutionalNeuralNetwork",
    "source_domain": "ai",
    "domain": "ai",
    "domain_full_name": "Artificial Intelligence",
    "definition": "### Primary Definition",
    "scope_note": null,
    "status": "approved",
    "maturity": "mature",
    "version": null,
    "public_access": true,
    "last_updated": null,
    "authority_score": null,
    "quality_score": null,
    "cross_domain_links": null,
    "owl_class": "ai:ConvolutionalNeuralNetwork",
    "owl_physicality": null,
    "owl_role": null,
    "owl_inferred_class": null,
    "is_subclass_of": [
      "NeuralNetworkArchitecture"
    ],
    "has_part": [],
    "is_part_of": [],
    "requires": [],
    "depends_on": [],
    "enables": [],
    "relates_to": [],
    "bridges_to": [],
    "bridges_from": [],
    "domain_extensions": {},
    "belongs_to_domain": [],
    "implemented_in_layer": [],
    "source": [
      "LeCun et al. 1998 Gradient-Based Learning",
      "Krizhevsky et al. 2012 AlexNet",
      "He et al. 2016 ResNet",
      "IEEE CVPR Proceedings"
    ],
    "validation": {
      "is_valid": false,
      "errors": [
        "Missing required property: last-updated",
        "Missing required property: owl:physicality",
        "Missing required property: owl:role"
      ]
    }
  }
}