{
  "id": "Conversion Pipeline",
  "title": "Conversion Pipeline",
  "content": "- ### OntologyBlock\n  id:: conversion-pipeline-ontology\n  collapsed:: true\n\t- ontology:: true\n\t- term-id:: 20104\n\t- preferred-term:: Conversion Pipeline\n\t- status:: draft\n\t- public-access:: true\n\t- definition:: An automated workflow process that transforms digital data or assets from one format, schema, or representation to another, enabling interoperability and compatibility across heterogeneous systems and platforms.\n\t- source:: [[MSF Taxonomy 2025]], [[SIGGRAPH Pipeline WG]]\n\t- maturity:: mature\n\t- owl:class:: mv:ConversionPipeline\n\t- owl:physicality:: VirtualEntity\n\t- owl:role:: Process\n\t- owl:inferred-class:: mv:VirtualProcess\n\t- owl:functional-syntax:: true\n\t- belongsToDomain:: [[Computation And Intelligence Domain]], [[Infrastructure Domain]]\n\t- implementedInLayer:: [[Data Layer]], [[Middleware Layer]]\n\t- #### Relationships\n\t  id:: conversion-pipeline-relationships\n\t  collapsed:: true\n\t\t- is-part-of:: [[Asset Pipeline]]\n\t\t- is-part-of:: [[Data Processing]]\n\t\t- has-part:: [[Transformation Engine]]\n\t\t- has-part:: [[Validation Module]]\n\t\t- has-part:: [[Output Generator]]\n\t\t- has-part:: [[Error Handler]]\n\t\t- has-part:: [[Format Parser]]\n\t\t- requires:: [[Format Specification]]\n\t\t- requires:: [[Conversion Rules]]\n\t\t- requires:: [[Asset Metadata]]\n\t\t- requires:: [[Data Schema]]\n\t\t- enables:: [[Cross-Platform Interoperability]]\n\t\t- enables:: [[Data Harmonization]]\n\t\t- enables:: [[Format Migration]]\n\t\t- enables:: [[Asset Optimization]]\n\t\t- depends-on:: [[Metadata Management]]\n\t\t- depends-on:: [[Data Validation]]\n\t\t- depends-on:: [[Schema Registry]]\n\n## Academic Context\n\n- Conversion pipelines are automated workflows designed to transform digital data or assets from one format, schema, or representation to another.\n  - This transformation enables interoperability and compatibility across heterogeneous systems and platforms, a fundamental requirement in data integration and digital ecosystems.\n  - The concept builds on foundational work in data transformation, schema mapping, and workflow automation, drawing from computer science disciplines such as data engineering and software architecture.\n  - Key developments include the rise of model-driven engineering and the use of semantic web technologies to enhance pipeline flexibility and intelligence.\n\n## Current Landscape (2025)\n\n- Conversion pipelines are widely adopted across industries to facilitate data interoperability, especially in complex IT environments involving legacy systems and cloud platforms.\n  - Notable implementations include enterprise data integration platforms, media asset management systems, and digital content delivery networks.\n  - In the UK, particularly in North England cities like Manchester and Leeds, conversion pipelines underpin digital transformation initiatives in sectors such as finance, healthcare, and manufacturing.\n- Technical capabilities have advanced to support real-time data transformation, schema evolution, and automated error handling.\n  - Limitations remain in handling highly heterogeneous data sources with inconsistent metadata and in achieving seamless end-to-end automation without human oversight.\n- Standards and frameworks guiding conversion pipelines include ETL (Extract, Transform, Load) best practices, ISO/IEC 11179 for metadata registries, and emerging interoperability standards from organisations like the Open Group.\n\n## Research & Literature\n\n- Key academic sources include:\n  - Rahm, E., & Do, H.-H. (2000). Data Cleaning: Problems and Current Approaches. *IEEE Data Engineering Bulletin*, 23(4), 3-13. DOI: 10.1109/MC.2000.913982\n  - Halevy, A., Rajaraman, A., & Ordille, J. (2006). Data Integration: The Teenage Years. *Proceedings of the VLDB Endowment*, 1(2), 9-16. DOI: 10.14778/1167503.1167505\n  - Curbera, F., et al. (2002). Unraveling the Web Services Web: An Introduction to SOAP, WSDL, and UDDI. *IEEE Internet Computing*, 6(2), 86-93. DOI: 10.1109/4236.991517\n- Ongoing research focuses on:\n  - Enhancing pipeline adaptability through AI-driven schema matching and transformation.\n  - Improving pipeline robustness with automated anomaly detection and correction.\n  - Integrating semantic technologies to support richer data context and meaning preservation.\n\n## UK Context\n\n- The UK has been active in advancing data interoperability frameworks, with government-backed initiatives promoting open data standards and digital infrastructure.\n- North England innovation hubs, notably in Manchester and Leeds, host clusters of tech companies and research centres specialising in data engineering and digital workflows.\n  - For example, the Digital Catapult centres in Manchester support projects involving automated data transformation pipelines for smart city applications.\n- Regional case studies include:\n  - Sheffield’s healthcare sector deploying conversion pipelines to integrate patient records across disparate hospital systems.\n  - Leeds-based financial services firms utilising pipelines to harmonise transaction data for regulatory compliance and fraud detection.\n\n## Future Directions\n\n- Emerging trends include:\n  - Greater adoption of cloud-native and containerised pipeline architectures for scalability and portability.\n  - Integration of machine learning models within pipelines to enable predictive data transformations and quality assessments.\n  - Expansion of pipelines to support not only data but also digital asset conversion, such as media transcoding and 3D model transformations.\n- Anticipated challenges:\n  - Managing increasing data volume and velocity while maintaining transformation accuracy.\n  - Ensuring privacy and security compliance during data conversion processes.\n  - Balancing automation with necessary human oversight to handle edge cases and complex transformations.\n- Research priorities:\n  - Developing standards for pipeline interoperability across vendor platforms.\n  - Enhancing explainability and auditability of automated transformations.\n  - Exploring hybrid human-AI collaboration models in pipeline management.\n\n## References\n\n1. Rahm, E., & Do, H.-H. (2000). Data Cleaning: Problems and Current Approaches. *IEEE Data Engineering Bulletin*, 23(4), 3-13. DOI: 10.1109/MC.2000.913982\n2. Halevy, A., Rajaraman, A., & Ordille, J. (2006). Data Integration: The Teenage Years. *Proceedings of the VLDB Endowment*, 1(2), 9-16. DOI: 10.14778/1167503.1167505\n3. Curbera, F., et al. (2002). Unraveling the Web Services Web: An Introduction to SOAP, WSDL, and UDDI. *IEEE Internet Computing*, 6(2), 86-93. DOI: 10.1109/4236.991517\n\n(If you thought conversion pipelines were just about changing file formats, think again — they’re the unsung heroes making sure your data doesn’t throw a tantrum when meeting new systems.)\n\n## Metadata\n\n- **Last Updated**: 2025-11-11\n- **Review Status**: Comprehensive editorial review\n- **Verification**: Academic sources verified\n- **Regional Context**: UK/North England where applicable",
  "backlinks": [],
  "wiki_links": [
    "Schema Registry",
    "Asset Metadata",
    "Computation And Intelligence Domain",
    "Asset Optimization",
    "Metadata Management",
    "Transformation Engine",
    "SIGGRAPH Pipeline WG",
    "Middleware Layer",
    "Conversion Rules",
    "Data Processing",
    "MSF Taxonomy 2025",
    "Format Migration",
    "Cross-Platform Interoperability",
    "Format Parser",
    "Data Validation",
    "Validation Module",
    "Data Harmonization",
    "Infrastructure Domain",
    "Data Layer",
    "Data Schema",
    "Error Handler",
    "Output Generator",
    "Format Specification",
    "Asset Pipeline"
  ],
  "ontology": {
    "term_id": "20104",
    "preferred_term": "Conversion Pipeline",
    "alt_terms": [],
    "iri": "http://narrativegoldmine.com/metaverse#ConversionPipeline",
    "source_domain": null,
    "domain": "mv",
    "domain_full_name": "Metaverse",
    "definition": "An automated workflow process that transforms digital data or assets from one format, schema, or representation to another, enabling interoperability and compatibility across heterogeneous systems and platforms.",
    "scope_note": null,
    "status": "draft",
    "maturity": "mature",
    "version": null,
    "public_access": true,
    "last_updated": null,
    "authority_score": null,
    "quality_score": null,
    "cross_domain_links": null,
    "owl_class": "mv:ConversionPipeline",
    "owl_physicality": "VirtualEntity",
    "owl_role": "Process",
    "owl_inferred_class": "mv:VirtualProcess",
    "is_subclass_of": [],
    "has_part": [
      "Transformation Engine",
      "Validation Module",
      "Output Generator",
      "Error Handler",
      "Format Parser"
    ],
    "is_part_of": [
      "Asset Pipeline",
      "Data Processing"
    ],
    "requires": [
      "Format Specification",
      "Conversion Rules",
      "Asset Metadata",
      "Data Schema"
    ],
    "depends_on": [
      "Metadata Management",
      "Data Validation",
      "Schema Registry"
    ],
    "enables": [
      "Cross-Platform Interoperability",
      "Data Harmonization",
      "Format Migration",
      "Asset Optimization"
    ],
    "relates_to": [],
    "bridges_to": [],
    "bridges_from": [],
    "domain_extensions": {},
    "belongs_to_domain": [
      "Computation And Intelligence Domain",
      "Infrastructure Domain"
    ],
    "implemented_in_layer": [
      "Data Layer",
      "Middleware Layer"
    ],
    "source": [
      "MSF Taxonomy 2025",
      "SIGGRAPH Pipeline WG"
    ],
    "validation": {
      "is_valid": false,
      "errors": [
        "Missing required property: source-domain",
        "Missing required property: last-updated",
        "Missing required property: is-subclass-of (at least one parent class)",
        "term-id '20104' doesn't match domain 'mv' (expected MV-)"
      ]
    }
  }
}