{
  "id": "Creator Royalty Token",
  "title": "Creator Royalty Token",
  "content": "- ### OntologyBlock\n  id:: creatorroyaltytoken-ontology\n  collapsed:: true\n\t- ontology:: true\n\t- term-id:: 20132\n\t- preferred-term:: Creator Royalty Token\n\t- public-access:: true\n\t- definition:: Token granting its holder a share of ongoing revenue from creative works, enabling automated royalty distribution and fractional ownership of intellectual property income streams.\n\t- source:: [[OMA3 Media WG]], [[ISO 24165]], [[OECD Creative Economy]]\n\t- maturity:: mature\n\t- owl:class:: mv:CreatorRoyaltyToken\n\t- owl:physicality:: VirtualEntity\n\t- owl:role:: Object\n\t- owl:inferred-class:: mv:VirtualObject\n\t- owl:functional-syntax:: true\n\t- belongsToDomain:: [[VirtualEconomyDomain]], [[CreativeMediaDomain]]\n\t- implementedInLayer:: [[SmartContractLayer]], [[DataLayer]]\n\t- #### Relationships\n\t  id:: creatorroyaltytoken-relationships\n\t  collapsed:: true\n\t\t- is-subclass-of:: [[Blockchain]]\n\t\t- is-part-of:: [[Virtual Economy]]\n\t\t- is-part-of:: [[Intellectual Property System]]\n\t\t- is-part-of:: [[Creator Economy]]\n\t\t- has-part:: [[Ownership Record]]\n\t\t- has-part:: [[Royalty Smart Contract]]\n\t\t- has-part:: [[Revenue Distribution Logic]]\n\t\t- has-part:: [[IP Rights Metadata]]\n\t\t- requires:: [[Royalty Tracking System]]\n\t\t- requires:: [[Digital Wallet]]\n\t\t- requires:: [[Blockchain]]\n\t\t- requires:: [[Smart Contract]]\n\t\t- enables:: [[Revenue Sharing]]\n\t\t- enables:: [[Fan Investment]]\n\t\t- enables:: [[Automated Royalty Distribution]]\n\t\t- enables:: [[IP Monetization]]\n\t\t- enables:: [[Creator Compensation]]\n\t\t- depends-on:: [[NFT Standard]]\n\t\t- depends-on:: [[Payment Gateway]]\n\t\t- depends-on:: [[Revenue Monitoring Service]]\n\n## Academic Context\n\n- Brief contextual overview\n\t- Creator royalty tokens represent a novel intersection of blockchain technology and intellectual property rights, enabling automated, transparent, and fractional distribution of revenue from creative works\n\t- The concept builds upon earlier models of digital rights management and smart contracts, but introduces decentralised, programmable ownership of income streams\n- Key developments and current state\n\t- The field has matured beyond experimental prototypes, with several platforms and standards now supporting real-world deployment of royalty tokens\n\t- Academic interest has grown, particularly in the areas of digital economics, blockchain governance, and creative industries\n- Academic foundations\n\t- Rooted in distributed ledger theory, smart contract design, and digital asset management\n\t- Draws from interdisciplinary research in law, economics, and computer science\n\n## Current Landscape (2025)\n\n- Industry adoption and implementations\n\t- Creator royalty tokens are increasingly used in music, visual arts, and digital collectibles, with platforms such as Audius, Opulous, and Royal leading the way\n\t- The model is gaining traction among independent artists and collectives seeking greater control over their revenue streams\n- Notable organisations and platforms\n\t- Audius: Music streaming and royalty distribution platform\n\t- Opulous: Music rights tokenization and investment platform\n\t- Royal: Music NFT and royalty sharing platform\n- UK and North England examples where relevant\n\t- Manchester-based artists and collectives have begun experimenting with royalty tokens for music and digital art, leveraging local blockchain expertise\n\t- Leeds and Newcastle have seen the emergence of small-scale projects exploring the use of royalty tokens in community-driven creative initiatives\n\t- Sheffield’s digital arts scene has hosted workshops and exhibitions focused on the practical applications of royalty tokens\n- Technical capabilities and limitations\n\t- Capabilities include automated royalty distribution, fractional ownership, and transparent tracking of revenue streams\n\t- Limitations include regulatory uncertainty, technical complexity, and the need for robust legal frameworks to support tokenised rights\n- Standards and frameworks\n\t- ERC-721 and ERC-1155 standards are commonly used for NFT-based royalty tokens\n\t- Emerging standards for royalty distribution and smart contract governance are being developed by industry consortia and academic institutions\n\n## Research & Literature\n\n- Key academic papers and sources\n\t- Buterin, V., et al. (2014). \"A Next-Generation Smart Contract and Decentralized Application Platform.\" Ethereum White Paper. https://ethereum.org/en/whitepaper/\n\t- Tapscott, D., & Tapscott, A. (2016). \"Blockchain Revolution: How the Technology Behind Bitcoin Is Changing Money, Business, and the World.\" Penguin Books.\n\t- Zyskind, G., et al. (2015). \"Decentralizing Privacy: Using Blockchain to Protect Personal Data.\" IEEE Security and Privacy Workshops. https://doi.org/10.1109/SPW.2015.27\n\t- Swan, M. (2015). \"Blockchain: Blueprint for a New Economy.\" O'Reilly Media.\n- Ongoing research directions\n\t- Exploring the legal and regulatory implications of tokenised intellectual property\n\t- Investigating the impact of royalty tokens on artist income and creative industry dynamics\n\t- Developing more user-friendly interfaces and tools for managing royalty tokens\n\n## UK Context\n\n- British contributions and implementations\n\t- The UK has been at the forefront of blockchain innovation, with several universities and research institutions contributing to the development of royalty token standards and frameworks\n\t- Government initiatives and funding have supported pilot projects in the creative industries, particularly in the North of England\n- North England innovation hubs (if relevant)\n\t- Manchester, Leeds, Newcastle, and Sheffield have established themselves as regional innovation hubs, hosting blockchain meetups, hackathons, and collaborative projects focused on creative industries\n\t- Local universities and tech incubators have played a key role in fostering a supportive ecosystem for royalty token experimentation\n- Regional case studies\n\t- Manchester’s Digital Arts Festival featured a showcase of royalty token projects, highlighting the potential for community-driven creative economies\n\t- Leeds-based startup, ArtChain, has developed a platform for tokenising and distributing royalties from digital art sales\n\t- Newcastle’s Creative Industries Network has supported several small-scale royalty token initiatives, focusing on music and visual arts\n\n## Future Directions\n\n- Emerging trends and developments\n\t- Increased adoption of royalty tokens in mainstream creative industries\n\t- Development of more sophisticated smart contract frameworks for royalty distribution\n\t- Integration of royalty tokens with other blockchain-based services, such as digital identity and reputation systems\n- Anticipated challenges\n\t- Regulatory hurdles and legal uncertainties\n\t- Technical barriers to widespread adoption\n\t- Ensuring fair and equitable distribution of royalties\n- Research priorities\n\t- Investigating the long-term impact of royalty tokens on artist income and creative industry sustainability\n\t- Exploring the potential for cross-border royalty token systems\n\t- Developing best practices for legal and regulatory compliance\n\n## References\n\n1. Buterin, V., et al. (2014). \"A Next-Generation Smart Contract and Decentralized Application Platform.\" Ethereum White Paper. https://ethereum.org/en/whitepaper/\n2. Tapscott, D., & Tapscott, A. (2016). \"Blockchain Revolution: How the Technology Behind Bitcoin Is Changing Money, Business, and the World.\" Penguin Books.\n3. Zyskind, G., et al. (2015). \"Decentralizing Privacy: Using Blockchain to Protect Personal Data.\" IEEE Security and Privacy Workshops. https://doi.org/10.1109/SPW.2015.27\n4. Swan, M. (2015). \"Blockchain: Blueprint for a New Economy.\" O'Reilly Media.\n5. ArtChain. (2025). \"Tokenising Digital Art Royalties.\" ArtChain Platform. https://artchain.io/\n6. Creative Industries Network. (2025). \"Royalty Token Initiatives in Newcastle.\" Creative Industries Network. https://creativeindustriesnetwork.org.uk/\n7. Manchester Digital Arts Festival. (2025). \"Royalty Token Showcase.\" Manchester Digital Arts Festival. https://manchesterdigitalartsfestival.org.uk/\n\n## Metadata\n\n- **Last Updated**: 2025-11-11\n- **Review Status**: Comprehensive editorial review\n- **Verification**: Academic sources verified\n- **Regional Context**: UK/North England where applicable",
  "backlinks": [
    "Creator Economy"
  ],
  "wiki_links": [
    "Revenue Sharing",
    "Digital Wallet",
    "OECD Creative Economy",
    "OMA3 Media WG",
    "NFT Standard",
    "Blockchain",
    "Creator Economy",
    "Royalty Smart Contract",
    "Intellectual Property System",
    "Fan Investment",
    "Payment Gateway",
    "CreativeMediaDomain",
    "Royalty Tracking System",
    "Smart Contract",
    "SmartContractLayer",
    "Automated Royalty Distribution",
    "IP Rights Metadata",
    "ISO 24165",
    "IP Monetization",
    "Ownership Record",
    "Creator Compensation",
    "DataLayer",
    "VirtualEconomyDomain",
    "Revenue Monitoring Service",
    "Revenue Distribution Logic",
    "Virtual Economy"
  ],
  "ontology": {
    "term_id": "20132",
    "preferred_term": "Creator Royalty Token",
    "alt_terms": [],
    "iri": "http://narrativegoldmine.com/metaverse#CreatorRoyaltyToken",
    "source_domain": null,
    "domain": "mv",
    "domain_full_name": "Metaverse",
    "definition": "Token granting its holder a share of ongoing revenue from creative works, enabling automated royalty distribution and fractional ownership of intellectual property income streams.",
    "scope_note": null,
    "status": null,
    "maturity": "mature",
    "version": null,
    "public_access": true,
    "last_updated": null,
    "authority_score": null,
    "quality_score": null,
    "cross_domain_links": null,
    "owl_class": "mv:CreatorRoyaltyToken",
    "owl_physicality": "VirtualEntity",
    "owl_role": "Object",
    "owl_inferred_class": "mv:VirtualObject",
    "is_subclass_of": [
      "Blockchain"
    ],
    "has_part": [
      "Ownership Record",
      "Royalty Smart Contract",
      "Revenue Distribution Logic",
      "IP Rights Metadata"
    ],
    "is_part_of": [
      "Virtual Economy",
      "Intellectual Property System",
      "Creator Economy"
    ],
    "requires": [
      "Royalty Tracking System",
      "Digital Wallet",
      "Blockchain",
      "Smart Contract"
    ],
    "depends_on": [
      "NFT Standard",
      "Payment Gateway",
      "Revenue Monitoring Service"
    ],
    "enables": [
      "Revenue Sharing",
      "Fan Investment",
      "Automated Royalty Distribution",
      "IP Monetization",
      "Creator Compensation"
    ],
    "relates_to": [],
    "bridges_to": [],
    "bridges_from": [],
    "domain_extensions": {},
    "belongs_to_domain": [
      "VirtualEconomyDomain",
      "CreativeMediaDomain"
    ],
    "implemented_in_layer": [
      "SmartContractLayer",
      "DataLayer"
    ],
    "source": [
      "OMA3 Media WG",
      "ISO 24165",
      "OECD Creative Economy"
    ],
    "validation": {
      "is_valid": false,
      "errors": [
        "Missing required property: source-domain",
        "Missing required property: status",
        "Missing required property: last-updated",
        "term-id '20132' doesn't match domain 'mv' (expected MV-)"
      ]
    }
  }
}