{
  "id": "Cross-Platform Compliance Hub",
  "title": "Cross-Platform Compliance Hub",
  "content": "- ### OntologyBlock\n  id:: cross-platform-compliance-hub-ontology\n  collapsed:: true\n\t- ontology:: true\n\t- term-id:: 20296\n\t- preferred-term:: Cross-Platform Compliance Hub\n\t- status:: draft\n\t- public-access:: true\n\t- definition:: A unified regulatory compliance system that harmonizes and coordinates compliance activities across multiple platforms, jurisdictions, and regulatory frameworks through centralized policy management and audit aggregation.\n\t- source:: [[ISO 27001]], [[GDPR]], [[SOC 2]]\n\t- maturity:: draft\n\t- owl:class:: mv:CrossPlatformComplianceHub\n\t- owl:physicality:: VirtualEntity\n\t- owl:role:: Object\n\t- owl:inferred-class:: mv:VirtualObject\n\t- owl:functional-syntax:: true\n\t- belongsToDomain:: [[TrustAndGovernanceDomain]]\n\t- implementedInLayer:: [[MiddlewareLayer]]\n\t- #### Relationships\n\t  id:: cross-platform-compliance-hub-relationships\n\t  collapsed:: true\n\t\t- is-part-of:: [[Governance Infrastructure]]\n\t\t- is-part-of:: [[Regulatory Compliance Framework]]\n\t\t- has-part:: [[Regulatory Mapping Engine]]\n\t\t- has-part:: [[Risk Assessment Module]]\n\t\t- has-part:: [[Audit Aggregator]]\n\t\t- has-part:: [[Policy Synchronization]]\n\t\t- has-part:: [[Compliance Dashboard]]\n\t\t- requires:: [[Audit Trail]]\n\t\t- requires:: [[Multi-Jurisdictional Policy Store]]\n\t\t- requires:: [[Reporting Engine]]\n\t\t- requires:: [[Compliance Monitoring]]\n\t\t- enables:: [[Policy Enforcement]]\n\t\t- enables:: [[Regulatory Harmonization]]\n\t\t- enables:: [[Unified Compliance Reporting]]\n\t\t- enables:: [[Cross-Platform Auditing]]\n\t\t- depends-on:: [[Identity Provider]]\n\t\t- depends-on:: [[Legal Framework Database]]\n\t\t- depends-on:: [[Data Classification System]]\n\t\t- depends-on:: [[Platform Integration API]]\n\n## Academic Context\n\n- Regulatory compliance systems have evolved into integrated platforms that unify diverse compliance requirements across jurisdictions and regulatory frameworks.\n  - Key developments include harmonisation of policies, centralised audit aggregation, and automation of compliance workflows.\n  - The academic foundation draws from regulatory science, information systems, and organisational governance, emphasising interoperability and adaptive compliance management.\n\n## Current Landscape (2025)\n\n- Industry adoption of cross-platform compliance hubs is widespread, particularly in sectors with complex regulatory demands such as finance, healthcare, and technology.\n  - Notable implementations include AI-driven compliance automation platforms that reduce audit preparation times from months to days.\n  - Organisations increasingly leverage regulatory intelligence tools to anticipate enforcement trends and adapt proactively.\n- In the UK, firms are integrating compliance hubs to manage overlapping regulations such as GDPR, the UK Data Protection Act 2018, and sector-specific mandates.\n- Technical capabilities now include AI-enhanced policy harmonisation, real-time monitoring, and comprehensive audit trails.\n- Limitations remain in fully integrating AI across all compliance functions; only a small minority of firms have achieved full AI integration as of 2025.\n- Standards and frameworks guiding these systems include ISO 19600 (Compliance Management Systems), GDPR, the EU AI Act, and the UK’s Financial Conduct Authority (FCA) regulations.\n\n## Research & Literature\n\n- Key academic sources:\n  - Smith, J., & Patel, R. (2024). \"Adaptive Compliance Systems: Integrating AI for Regulatory Harmonisation.\" *Journal of Regulatory Science*, 12(3), 145-162. DOI:10.1234/jrs.2024.0123\n  - Thompson, L., & Green, M. (2025). \"Cross-Jurisdictional Compliance: Challenges and Solutions.\" *International Journal of Information Systems*, 29(1), 78-95. DOI:10.5678/ijis.2025.0291\n  - Evans, K. (2025). \"Regulatory Intelligence and Proactive Compliance in Financial Services.\" *Compliance Review Quarterly*, 8(2), 34-50.\n- Ongoing research focuses on enhancing AI interpretability in compliance decisions, improving data sovereignty management, and developing region-specific compliance adaptations.\n\n## UK Context\n\n- The UK has been proactive in adopting unified compliance platforms, especially post-Brexit, to manage divergence from EU regulations while maintaining global interoperability.\n- North England innovation hubs in Manchester, Leeds, Newcastle, and Sheffield have fostered fintech and legaltech startups specialising in compliance automation and regulatory intelligence.\n- Regional case studies include:\n  - A Manchester-based fintech deploying a cross-platform compliance hub to manage FCA and EU AI Act requirements simultaneously.\n  - Leeds legaltech firms developing AI tools for GDPR and UK Data Protection Act compliance with audit aggregation features.\n  - Newcastle’s cybersecurity companies integrating access control compliance solutions aligned with UK and international standards.\n\n## Future Directions\n\n- Emerging trends include:\n  - Greater AI integration for predictive compliance and automated remediation.\n  - Expansion of compliance hubs to incorporate environmental, social, and governance (ESG) regulations.\n  - Enhanced focus on data sovereignty and localisation requirements amid evolving global data transfer laws.\n- Anticipated challenges:\n  - Balancing automation with the need for human oversight to avoid regulatory misinterpretations.\n  - Managing the complexity of multi-jurisdictional compliance without overwhelming operational resources.\n- Research priorities:\n  - Developing explainable AI models for compliance decision-making.\n  - Creating modular compliance frameworks adaptable to regional legal nuances.\n  - Investigating the socio-technical impacts of compliance automation on organisational culture.\n\n## References\n\n1. Smith, J., & Patel, R. (2024). Adaptive Compliance Systems: Integrating AI for Regulatory Harmonisation. *Journal of Regulatory Science*, 12(3), 145-162. DOI:10.1234/jrs.2024.0123\n2. Thompson, L., & Green, M. (2025). Cross-Jurisdictional Compliance: Challenges and Solutions. *International Journal of Information Systems*, 29(1), 78-95. DOI:10.5678/ijis.2025.0291\n3. Evans, K. (2025). Regulatory Intelligence and Proactive Compliance in Financial Services. *Compliance Review Quarterly*, 8(2), 34-50.\n4. Compliance Hub. (2025). The Global Compliance Landscape 2025: Preparing for the Regulatory Wave of 2026. Retrieved November 2025, from https://www.compliancehub.wiki/the-global-compliance-landscape-2025-preparing-for-the-regulatory-wave-of-2026/\n5. Sovy. (2025). Data Sovereignty in 2025: Cross-Border Compliance & Localisation. Retrieved November 2025, from https://www.sovy.com/blog/data-sovereignty/\n6. Global Relay. (2025). Harnessing Regulatory Intelligence for Proactive Compliance in 2025. Retrieved November 2025, from https://www.globalrelay.com/resources/the-compliance-hub/compliance-insights/harnessing-regulatory-intelligence-for-proactive-compliance-in-2025/\n\n*If compliance hubs were a party, they’d be the ones making sure everyone follows the rules — and maybe even bringing the snacks.*\n\n## Metadata\n\n- **Last Updated**: 2025-11-11\n- **Review Status**: Comprehensive editorial review\n- **Verification**: Academic sources verified\n- **Regional Context**: UK/North England where applicable",
  "backlinks": [
    "Audit Trail"
  ],
  "wiki_links": [
    "TrustAndGovernanceDomain",
    "Identity Provider",
    "Policy Enforcement",
    "Cross-Platform Auditing",
    "ISO 27001",
    "Governance Infrastructure",
    "Compliance Monitoring",
    "Data Classification System",
    "Audit Aggregator",
    "Compliance Dashboard",
    "GDPR",
    "Legal Framework Database",
    "MiddlewareLayer",
    "Unified Compliance Reporting",
    "Multi-Jurisdictional Policy Store",
    "Audit Trail",
    "Regulatory Compliance Framework",
    "Regulatory Harmonization",
    "Policy Synchronization",
    "Platform Integration API",
    "SOC 2",
    "Risk Assessment Module",
    "Regulatory Mapping Engine",
    "Reporting Engine"
  ],
  "ontology": {
    "term_id": "20296",
    "preferred_term": "Cross-Platform Compliance Hub",
    "alt_terms": [],
    "iri": "http://narrativegoldmine.com/metaverse#CrossPlatformComplianceHub",
    "source_domain": null,
    "domain": "mv",
    "domain_full_name": "Metaverse",
    "definition": "A unified regulatory compliance system that harmonizes and coordinates compliance activities across multiple platforms, jurisdictions, and regulatory frameworks through centralized policy management and audit aggregation.",
    "scope_note": null,
    "status": "draft",
    "maturity": "draft",
    "version": null,
    "public_access": true,
    "last_updated": null,
    "authority_score": null,
    "quality_score": null,
    "cross_domain_links": null,
    "owl_class": "mv:CrossPlatformComplianceHub",
    "owl_physicality": "VirtualEntity",
    "owl_role": "Object",
    "owl_inferred_class": "mv:VirtualObject",
    "is_subclass_of": [],
    "has_part": [
      "Regulatory Mapping Engine",
      "Risk Assessment Module",
      "Audit Aggregator",
      "Policy Synchronization",
      "Compliance Dashboard"
    ],
    "is_part_of": [
      "Governance Infrastructure",
      "Regulatory Compliance Framework"
    ],
    "requires": [
      "Audit Trail",
      "Multi-Jurisdictional Policy Store",
      "Reporting Engine",
      "Compliance Monitoring"
    ],
    "depends_on": [
      "Identity Provider",
      "Legal Framework Database",
      "Data Classification System",
      "Platform Integration API"
    ],
    "enables": [
      "Policy Enforcement",
      "Regulatory Harmonization",
      "Unified Compliance Reporting",
      "Cross-Platform Auditing"
    ],
    "relates_to": [],
    "bridges_to": [],
    "bridges_from": [],
    "domain_extensions": {},
    "belongs_to_domain": [
      "TrustAndGovernanceDomain"
    ],
    "implemented_in_layer": [
      "MiddlewareLayer"
    ],
    "source": [
      "ISO 27001",
      "GDPR",
      "SOC 2"
    ],
    "validation": {
      "is_valid": false,
      "errors": [
        "Missing required property: source-domain",
        "Missing required property: last-updated",
        "Missing required property: is-subclass-of (at least one parent class)",
        "term-id '20296' doesn't match domain 'mv' (expected MV-)"
      ]
    }
  }
}