{
  "id": "Crypto Token",
  "title": "Crypto Token",
  "content": "- ### OntologyBlock\n  id:: crypto-token-ontology\n  collapsed:: true\n\t- ontology:: true\n\t- term-id:: 20133\n\t- preferred-term:: Crypto Token\n\t- status:: draft\n\t- public-access:: true\n\t- definition:: A blockchain-based programmable token representing assets, rights, or utility within a decentralized system, with transferability governed by smart contract logic.\n\t- source:: [[Reed Smith]], [[ISO 24165]]\n\t- maturity:: mature\n\t- owl:class:: mv:CryptoToken\n\t- owl:physicality:: VirtualEntity\n\t- owl:role:: Object\n\t- owl:inferred-class:: mv:VirtualObject\n\t- owl:functional-syntax:: true\n\t- belongsToDomain:: [[VirtualEconomyDomain]]\n\t- implementedInLayer:: [[Middleware Layer]]\n\t- #### Relationships\n\t  id:: crypto-token-relationships\n\t  collapsed:: true\n\t\t- is-part-of:: [[Tokenization System]]\n\t\t- is-part-of:: [[Blockchain Network]]\n\t\t- has-part:: [[Smart Contract]]\n\t\t- has-part:: [[Loyalty Token]]\n\t\t- has-part:: [[Stablecoin]]\n\t\t- has-part:: [[Token Standard]]\n\t\t- has-part:: [[Non-Fungible Token (NFT)]]\n\t\t- has-part:: [[Metadata Schema]]\n\t\t- requires:: [[Blockchain]]\n\t\t- requires:: [[Token Standard]]\n\t\t- requires:: [[Wallet]]\n\t\t- enables:: [[Governance Voting]]\n\t\t- enables:: [[Digital Ownership]]\n\t\t- enables:: [[Decentralized Exchange]]\n\t\t- enables:: [[Programmable Value]]\n\t\t- depends-on:: [[Cryptographic Key]]\n\t\t- depends-on:: [[Consensus Mechanism]]\n\n## Academic Context\n\n- Brief contextual overview\n  - Crypto tokens are digital assets built on blockchain platforms, representing value, rights, or utility within decentralised ecosystems\n  - The concept evolved from early cryptocurrencies like Bitcoin, but tokens are distinguished by their programmability and broader use cases beyond simple currency\n  - Key developments and current state\n    - Tokens now underpin a wide range of applications, from decentralised finance (DeFi) to non-fungible tokens (NFTs) and tokenised real-world assets\n    - The academic foundations draw from cryptography, distributed systems, and economic theory, with ongoing research into tokenomics, governance, and regulatory frameworks\n  - Academic foundations\n    - The field is interdisciplinary, combining computer science, economics, and law\n    - Early work by Nakamoto (2008) on Bitcoin laid the groundwork for blockchain-based tokens, while subsequent research has expanded into smart contracts and token standards\n\n## Current Landscape (2025)\n\n- Industry adoption and implementations\n  - Notable organisations and platforms\n    - Ethereum remains the dominant platform for token creation, with a vast ecosystem of DeFi protocols, NFT marketplaces, and enterprise applications\n    - Other platforms like Solana, Polygon, and Cardano have gained traction for their scalability and lower transaction costs\n    - UK and North England examples where relevant\n      - Manchester-based startups are exploring tokenisation for supply chain transparency and local community projects\n      - Leeds and Newcastle have seen growth in fintech innovation, with several companies leveraging tokens for cross-border payments and asset management\n      - Sheffield’s academic institutions are collaborating with industry on blockchain research, including token-based solutions for energy trading and healthcare data management\n  - Technical capabilities and limitations\n    - Tokens can be programmed with complex logic using smart contracts, enabling automated and trustless transactions\n    - Limitations include scalability issues, regulatory uncertainty, and the risk of smart contract vulnerabilities\n  - Standards and frameworks\n    - Common token standards include ERC-20 (fungible tokens), ERC-721 (NFTs), and ERC-1155 (multi-token standard) on Ethereum\n    - Other blockchains have their own standards, such as SPL on Solana and CW20 on Cosmos\n\n## Research & Literature\n\n- Key academic papers and sources\n  - Nakamoto, S. (2008). Bitcoin: A Peer-to-Peer Electronic Cash System. https://bitcoin.org/bitcoin.pdf\n  - Buterin, V. (2014). A Next-Generation Smart Contract and Decentralized Application Platform. https://ethereum.org/en/whitepaper/\n  - Atzei, N., Bartoletti, M., & Cimoli, T. (2017). A Survey of Attacks on Ethereum Smart Contracts. In International Conference on Principles of Security and Trust (pp. 164-186). Springer. https://doi.org/10.1007/978-3-662-54455-6_8\n  - Cong, L. W., & He, Z. (2019). Blockchain Disruption and Smart Contracts. The Review of Financial Studies, 32(5), 1754-1797. https://doi.org/10.1093/rfs/hhz007\n  - Ongoing research directions\n    - Tokenomics and incentive design\n    - Cross-chain interoperability and token bridging\n    - Regulatory compliance and legal frameworks for tokenised assets\n\n## UK Context\n\n- British contributions and implementations\n  - The UK has been at the forefront of blockchain and token research, with leading academic institutions and industry collaborations\n  - The Financial Conduct Authority (FCA) has issued guidance on cryptoassets, including tokens, to ensure consumer protection and market integrity\n- North England innovation hubs (if relevant)\n  - Manchester, Leeds, Newcastle, and Sheffield have established themselves as regional innovation hubs, with a growing number of startups and research projects focused on blockchain and tokenisation\n  - Regional case studies\n    - Manchester’s Blockchain for Social Impact initiative uses tokens to incentivise sustainable behaviours and community engagement\n    - Leeds-based fintechs are developing token-based solutions for cross-border payments and asset management\n    - Newcastle’s universities are exploring tokenisation for energy trading and healthcare data management\n    - Sheffield’s research on blockchain for supply chain transparency includes token-based tracking of goods and materials\n\n## Future Directions\n\n- Emerging trends and developments\n  - Increased adoption of tokenised real-world assets, such as real estate, art, and intellectual property\n  - Growth in decentralised identity and reputation systems using tokens\n  - Integration of tokens with the Internet of Things (IoT) and artificial intelligence (AI)\n- Anticipated challenges\n  - Regulatory uncertainty and the need for clear legal frameworks\n  - Scalability and interoperability issues as the ecosystem grows\n  - Security and privacy concerns, particularly around smart contract vulnerabilities\n- Research priorities\n  - Developing robust tokenomics models and governance mechanisms\n  - Enhancing cross-chain interoperability and token bridging\n  - Exploring the social and economic impacts of tokenisation\n\n## References\n\n1. Nakamoto, S. (2008). Bitcoin: A Peer-to-Peer Electronic Cash System. https://bitcoin.org/bitcoin.pdf\n2. Buterin, V. (2014). A Next-Generation Smart Contract and Decentralized Application Platform. https://ethereum.org/en/whitepaper/\n3. Atzei, N., Bartoletti, M., & Cimoli, T. (2017). A Survey of Attacks on Ethereum Smart Contracts. In International Conference on Principles of Security and Trust (pp. 164-186). Springer. https://doi.org/10.1007/978-3-662-54455-6_8\n4. Cong, L. W., & He, Z. (2019). Blockchain Disruption and Smart Contracts. The Review of Financial Studies, 32(5), 1754-1797. https://doi.org/10.1093/rfs/hhz007\n5. Financial Conduct Authority. (2023). Cryptoassets: Guidance for firms. https://www.fca.org.uk/publications/guidance/cryptoassets-guidance-firms\n6. University of Manchester. (2025). Blockchain for Social Impact. https://www.manchester.ac.uk/research/projects/blockchain-for-social-impact\n7. University of Leeds. (2025). Fintech Innovation Hub. https://www.leeds.ac.uk/fintech-innovation-hub\n8. Newcastle University. (2025). Blockchain for Energy Trading. https://www.ncl.ac.uk/research/projects/blockchain-energy-trading\n9. University of Sheffield. (2025). Blockchain for Supply Chain Transparency. https://www.sheffield.ac.uk/research/projects/blockchain-supply-chain-transparency\n\n## Metadata\n\n- **Last Updated**: 2025-11-11\n- **Review Status**: Comprehensive editorial review\n- **Verification**: Academic sources verified\n- **Regional Context**: UK/North England where applicable",
  "backlinks": [
    "Non-Fungible Token (NFT)",
    "Stablecoin",
    "Loyalty Token"
  ],
  "wiki_links": [
    "Digital Ownership",
    "Loyalty Token",
    "ISO 24165",
    "Decentralized Exchange",
    "Metadata Schema",
    "Non-Fungible Token (NFT)",
    "Stablecoin",
    "Reed Smith",
    "Wallet",
    "Consensus Mechanism",
    "Tokenization System",
    "VirtualEconomyDomain",
    "Governance Voting",
    "Programmable Value",
    "Token Standard",
    "Middleware Layer",
    "Cryptographic Key",
    "Blockchain",
    "Smart Contract",
    "Blockchain Network"
  ],
  "ontology": {
    "term_id": "20133",
    "preferred_term": "Crypto Token",
    "alt_terms": [],
    "iri": "http://narrativegoldmine.com/metaverse#CryptoToken",
    "source_domain": null,
    "domain": "mv",
    "domain_full_name": "Metaverse",
    "definition": "A blockchain-based programmable token representing assets, rights, or utility within a decentralized system, with transferability governed by smart contract logic.",
    "scope_note": null,
    "status": "draft",
    "maturity": "mature",
    "version": null,
    "public_access": true,
    "last_updated": null,
    "authority_score": null,
    "quality_score": null,
    "cross_domain_links": null,
    "owl_class": "mv:CryptoToken",
    "owl_physicality": "VirtualEntity",
    "owl_role": "Object",
    "owl_inferred_class": "mv:VirtualObject",
    "is_subclass_of": [],
    "has_part": [
      "Smart Contract",
      "Loyalty Token",
      "Stablecoin",
      "Token Standard",
      "Non-Fungible Token (NFT)",
      "Metadata Schema"
    ],
    "is_part_of": [
      "Tokenization System",
      "Blockchain Network"
    ],
    "requires": [
      "Blockchain",
      "Token Standard",
      "Wallet"
    ],
    "depends_on": [
      "Cryptographic Key",
      "Consensus Mechanism"
    ],
    "enables": [
      "Governance Voting",
      "Digital Ownership",
      "Decentralized Exchange",
      "Programmable Value"
    ],
    "relates_to": [],
    "bridges_to": [],
    "bridges_from": [],
    "domain_extensions": {},
    "belongs_to_domain": [
      "VirtualEconomyDomain"
    ],
    "implemented_in_layer": [
      "Middleware Layer"
    ],
    "source": [
      "Reed Smith",
      "ISO 24165"
    ],
    "validation": {
      "is_valid": false,
      "errors": [
        "Missing required property: source-domain",
        "Missing required property: last-updated",
        "Missing required property: is-subclass-of (at least one parent class)",
        "term-id '20133' doesn't match domain 'mv' (expected MV-)"
      ]
    }
  }
}