{
  "id": "Cultural Heritage XR Experience",
  "title": "Cultural Heritage XR Experience",
  "content": "- ### OntologyBlock\n  id:: cultural-heritage-xr-experience-ontology\n  collapsed:: true\n\t- ontology:: true\n\t- term-id:: 20300\n\t- preferred-term:: Cultural Heritage XR Experience\n\t- status:: draft\n\t- public-access:: true\n\t- definition:: An immersive extended reality application designed to preserve, present, and educate users about cultural heritage through interactive 3D reconstructions, AR overlays, and virtual museum experiences.\n\t- source:: [[UNESCO World Heritage Convention]], [[ICOM Museum Definition]]\n\t- maturity:: draft\n\t- owl:class:: mv:CulturalHeritageXRExperience\n\t- owl:physicality:: VirtualEntity\n\t- owl:role:: Object\n\t- owl:inferred-class:: mv:VirtualObject\n\t- owl:functional-syntax:: true\n\t- belongsToDomain:: [[CreativeMediaDomain]], [[VirtualSocietyDomain]]\n\t- implementedInLayer:: [[ApplicationLayer]]\n\t- #### Relationships\n\t  id:: cultural-heritage-xr-experience-relationships\n\t  collapsed:: true\n\t\t- is-part-of:: [[Cultural Heritage Preservation System]]\n\t\t- has-part:: [[Interactive Exhibit]]\n\t\t- has-part:: [[3D Reconstruction]]\n\t\t- has-part:: [[AR Overlay]]\n\t\t- has-part:: [[Cultural Metadata]]\n\t\t- has-part:: [[Educational Narrative]]\n\t\t- requires:: [[XR Runtime Environment]]\n\t\t- requires:: [[Cultural Database]]\n\t\t- requires:: [[Spatial Audio System]]\n\t\t- requires:: [[3D Rendering Engine]]\n\t\t- enables:: [[Heritage Tourism]]\n\t\t- enables:: [[Virtual Museum Tour]]\n\t\t- enables:: [[Cultural Education]]\n\t\t- enables:: [[Archaeological Site Reconstruction]]\n\t\t- depends-on:: [[LiDAR Scanning]]\n\t\t- depends-on:: [[Heritage Documentation]]\n\t\t- depends-on:: [[Photogrammetry]]\n\t\t- depends-on:: [[Museum API]]\n\n## Academic Context\n\n- Extended reality (XR) technologies have fundamentally transformed cultural heritage engagement over the past eighteen months\n  - Integration of immersive technologies now enables audiences to interact with historical artefacts and sites in vivid, intuitive, and interactive ways[4]\n  - The field has matured from experimental installations to systematic frameworks addressing both technological and institutional challenges\n  - Academic discourse increasingly emphasises emotional design and user-centred approaches to heritage preservation[2]\n\n- Foundational shift from one-off custom installations to sustainable, reusable storytelling formats\n  - Recognition that heritage organisations require scalable solutions rather than bespoke technical interventions\n  - Growing emphasis on democratising access to immersive storytelling across the cultural sector[1]\n\n## Current Landscape (2025)\n\n- Industry adoption and implementations\n  - Museums and historical sites now employ XR as part of long-term storytelling strategies rather than novelty experiences\n  - Metadata-driven interactive displays utilise existing artefact information to create dynamic, context-rich narratives[1]\n  - Social XR environments enable simultaneous participation by remote and local visitors, enhancing community-based learning[1]\n  - Virtual production technologies have proven instrumental in exhibition design beyond traditional video applications[3]\n\n- Technical capabilities and limitations\n  - AI-augmented content frameworks now enable digital humans to engage in intelligent, dynamic conversations with visitors—exemplified by recreations of historical figures from Raphael's *School of Athens* using ChatGPT and domain-specific AI models[3]\n  - Persistent challenges include customisation costs, asset availability, and communication gaps between design studios and heritage organisations[1]\n  - Sustainability remains a critical concern; high production costs necessitate reusable templates and integrated workflow tools to justify institutional investment[1]\n\n- Standards and frameworks\n  - Systematic reviews of 177 peer-reviewed papers identify standardised approaches to immersive cultural heritage presentations[4]\n  - Emphasis on ethical, social, and technological risk mitigation alongside technological efficacy[4]\n  - Open-source digital tools increasingly available for heritage professionals, reducing barriers to adoption[5]\n\n## UK Context\n\n- British institutional leadership\n  - The Netherlands Institute for Sound & Vision leads the TransmiXR initiative, though UK heritage organisations increasingly participate in European collaborative frameworks[1]\n  - EUreka3D-XR capacity building events (September 2025) demonstrate growing European coordination, with implications for UK sector adoption[5]\n\n- North England considerations\n  - Regional museums and heritage sites in Manchester, Leeds, Newcastle, and Sheffield remain positioned to benefit from emerging open-source XR tools, though specific institutional implementations are not yet widely documented in academic literature\n  - The shift towards reusable templates and collaborative workflows particularly suits smaller regional institutions with limited bespoke development budgets\n\n## Research & Literature\n\n- Key academic sources\n  - Kim, K. & Park, J.H. (2025). Design of an XR-based AI-augmented Content Framework for Cultural Heritage Exhibition. *International Archives of the Photogrammetry, Remote Sensing and Spatial Information Sciences*, XLVIII-M-9, 699–710. https://doi.org/10.5194/isprs-archives-XLVIII-M-9-2025-699-2025\n  - Systematic review examining 177 papers on immersive technologies in cultural heritage, addressing applications, risks, and future research directions (2025). *Taylor & Francis Online*. https://doi.org/10.1080/10447318.2025.2475996\n  - Emotional design in extended reality for cultural heritage preservation (2025). *Nature*, 40494. https://doi.org/10.1038/s40494-025-01625-x\n  - TransmiXR project documentation on democratising immersive storytelling for cultural heritage organisations, led by Netherlands Institute for Sound & Vision (2025)\n\n- Ongoing research directions\n  - Integration of AI-driven conversational agents with historical accuracy and pedagogical rigour\n  - Scalable asset creation and metadata standardisation across heritage institutions\n  - User experience research on emotional engagement and learning outcomes in immersive environments\n  - Ethical frameworks for digital representation of cultural artefacts and historical narratives\n\n## Future Directions\n\n- Emerging trends and developments\n  - Shift from isolated XR installations towards integrated institutional workflows and collaborative platforms[1]\n  - Increased adoption of AI-augmented content creation, reducing production timelines and costs[3]\n  - Metaverse-based heritage experiences enabling persistent, multi-user engagement with cultural content[3]\n  - Open-source tooling democratising access—though one might observe that \"democratisation\" often means heritage professionals must now learn software engineering, a rather unexpected career pivot\n\n- Anticipated challenges\n  - Balancing technological sophistication with accessibility for diverse visitor demographics\n  - Ensuring digital representations maintain scholarly rigour and cultural sensitivity\n  - Sustaining institutional commitment beyond initial funding cycles\n  - Addressing digital divide concerns, particularly for smaller or under-resourced heritage organisations\n\n- Research priorities\n  - Longitudinal studies on visitor learning outcomes and engagement metrics in XR heritage environments\n  - Development of standardised metadata frameworks enabling asset reusability across institutions\n  - Investigation of social and ethical implications of AI-generated historical personas\n  - Evaluation of cost-benefit analyses for heritage organisations considering XR adoption\n\n## Metadata\n\n- **Last Updated**: 2025-11-11\n- **Review Status**: Comprehensive editorial review\n- **Verification**: Academic sources verified\n- **Regional Context**: UK/North England where applicable",
  "backlinks": [
    "Photogrammetry"
  ],
  "wiki_links": [
    "3D Rendering Engine",
    "Cultural Database",
    "Heritage Tourism",
    "Spatial Audio System",
    "ApplicationLayer",
    "Museum API",
    "ICOM Museum Definition",
    "AR Overlay",
    "XR Runtime Environment",
    "Cultural Education",
    "Cultural Heritage Preservation System",
    "Archaeological Site Reconstruction",
    "CreativeMediaDomain",
    "Heritage Documentation",
    "LiDAR Scanning",
    "3D Reconstruction",
    "VirtualSocietyDomain",
    "Cultural Metadata",
    "Photogrammetry",
    "Educational Narrative",
    "Virtual Museum Tour",
    "Interactive Exhibit",
    "UNESCO World Heritage Convention"
  ],
  "ontology": {
    "term_id": "20300",
    "preferred_term": "Cultural Heritage XR Experience",
    "alt_terms": [],
    "iri": "http://narrativegoldmine.com/metaverse#CulturalHeritageXRExperience",
    "source_domain": null,
    "domain": "mv",
    "domain_full_name": "Metaverse",
    "definition": "An immersive extended reality application designed to preserve, present, and educate users about cultural heritage through interactive 3D reconstructions, AR overlays, and virtual museum experiences.",
    "scope_note": null,
    "status": "draft",
    "maturity": "draft",
    "version": null,
    "public_access": true,
    "last_updated": null,
    "authority_score": null,
    "quality_score": null,
    "cross_domain_links": null,
    "owl_class": "mv:CulturalHeritageXRExperience",
    "owl_physicality": "VirtualEntity",
    "owl_role": "Object",
    "owl_inferred_class": "mv:VirtualObject",
    "is_subclass_of": [],
    "has_part": [
      "Interactive Exhibit",
      "3D Reconstruction",
      "AR Overlay",
      "Cultural Metadata",
      "Educational Narrative"
    ],
    "is_part_of": [
      "Cultural Heritage Preservation System"
    ],
    "requires": [
      "XR Runtime Environment",
      "Cultural Database",
      "Spatial Audio System",
      "3D Rendering Engine"
    ],
    "depends_on": [
      "LiDAR Scanning",
      "Heritage Documentation",
      "Photogrammetry",
      "Museum API"
    ],
    "enables": [
      "Heritage Tourism",
      "Virtual Museum Tour",
      "Cultural Education",
      "Archaeological Site Reconstruction"
    ],
    "relates_to": [],
    "bridges_to": [],
    "bridges_from": [],
    "domain_extensions": {},
    "belongs_to_domain": [
      "CreativeMediaDomain",
      "VirtualSocietyDomain"
    ],
    "implemented_in_layer": [
      "ApplicationLayer"
    ],
    "source": [
      "UNESCO World Heritage Convention",
      "ICOM Museum Definition"
    ],
    "validation": {
      "is_valid": false,
      "errors": [
        "Missing required property: source-domain",
        "Missing required property: last-updated",
        "Missing required property: is-subclass-of (at least one parent class)",
        "term-id '20300' doesn't match domain 'mv' (expected MV-)"
      ]
    }
  }
}