{
  "id": "Customs Trade Facilitation",
  "title": "Customs Trade Facilitation",
  "content": "- ### OntologyBlock\n  id:: bc-0452-customs-trade-facilitation-ontology\n  collapsed:: true\n\t- ontology:: true\n\t- term-id:: BC-0452\n\t- preferred-term:: Customs Trade Facilitation\n\t- source-domain:: metaverse\n\t- status:: stub-needs-content\n    - public-access:: true\n\t- content-status:: minimal-placeholder-requires-authoring\n    - public-access:: true\n\t- definition:: A component of the blockchain ecosystem.\n\t- maturity:: draft\n\t- owl:class:: bc:CustomsTradeFacilitation\n\t- owl:physicality:: ConceptualEntity\n\t- owl:role:: Concept\n\t- is-subclass-of:: [[Blockchain]]\n\t- belongsToDomain:: [[BlockchainDomain]]\n\n\n# Updated Ontology Entry: Customs Trade Facilitation\n\n## Academic Context\n\n- Customs trade facilitation represents the application of digital technologies—particularly blockchain and distributed ledger systems—to streamline international trade processes\n  - Fundamentally distinct from being merely \"a component of the blockchain ecosystem\"; rather, blockchain functions as an enabling technology within broader customs modernisation efforts\n  - Encompasses tariff automation, customs clearance acceleration, compliance verification, and interagency data sharing across jurisdictions\n  - Rooted in international trade law and customs administration theory, with emerging technical implementations across multiple regulatory frameworks\n\n## Current Landscape (2025)\n\n- Industry adoption and implementations\n  - Customs administrations increasingly integrating blockchain for real-time data validation, reducing manual documentation and processing delays[1][2]\n  - Smart customs systems enabling synchronised control between customs zones, airports, freight forwarding services, and bonded warehouses through shared distributed ledgers[1]\n  - Export declaration services now processing instantaneously rather than requiring multiple manual signatures and revalidation cycles[1]\n  - APEC member states actively piloting blockchain implementations alongside artificial intelligence systems for enhanced risk management and trade efficiency[6]\n  - Electronic certificates of origin and single window systems becoming standard across Asia-Pacific trade corridors[6]\n  - UK customs authorities modernising post-Brexit procedures, though specific blockchain pilot programmes remain limited compared to Asia-Pacific initiatives\n  - Manchester and Leeds emerging as regional logistics hubs exploring digital trade facilitation, though formal blockchain adoption remains nascent in North England\n\n- Technical capabilities and limitations\n  - Blockchain enables immutable transaction recording with cryptographic verification, preventing tariff misclassification and duty evasion[1]\n  - Automated data integration between customs systems and trader submissions, flagging discrepancies for compliance review[2]\n  - Enhanced detection of financial crimes through iterative comparison of trade data against banking system records[2]\n  - Limitations include interoperability challenges between national customs systems, regulatory fragmentation, and the requirement for consensus-based governance models that may slow implementation in traditionally hierarchical customs administrations\n  - Data privacy concerns remain unresolved, particularly regarding cross-border information sharing under differing GDPR and national data protection regimes\n\n- Standards and frameworks\n  - UNCTAD coordinating global capacity-building through regional commissions (UNESCWA, ECA, ECE, ECLAC, ESCAP) to establish legal and regulatory requirements for blockchain in trade facilitation[4]\n  - UN guidance emphasising crisis resilience and technological readiness assessment for developing nations[4]\n  - European Parliament research identifying blockchain as suitable infrastructure for digitalising customs duties, sanitary certificates, conformity certificates, and import/export licences[5]\n  - APEC Framework for Supply Chain Connectivity incorporating blockchain pilots as part of broader digital trade facilitation agenda[6]\n\n## Research & Literature\n\n- Key academic and institutional sources\n  - Okazaki (2018) foundational analysis predicting customs administrations becoming data-driven entities with automated clearing capabilities through blockchain participation[2]\n  - European Parliament (2020). *Blockchain for supply chains and international trade*. EPRS Study 641544. Comprehensive examination of blockchain's neutral infrastructure value proposition for multi-stakeholder trade ecosystems[5]\n  - UNCTAD (ongoing). *Blockchains for facilitating trade and enhancing competitiveness*. UN regional commission collaborative project establishing implementation guides and readiness checklists for developing countries[4]\n  - OECD (2025). *The digitalisation of trade documents and processes*. Analysis of nearly 100 international agreements incorporating digital trade facilitation provisions[7]\n  - APEC Sub-Committee on Customs Procedures (2025). Meeting proceedings emphasising artificial intelligence and blockchain integration for customs modernisation across Asia-Pacific region[6]\n\n- Ongoing research directions\n  - Interoperability standards between national blockchain implementations and legacy customs systems\n  - Governance models balancing decentralised consensus with regulatory authority requirements\n  - Privacy-preserving data sharing mechanisms compliant with GDPR and equivalent frameworks\n  - Revenue compliance and transfer pricing detection through automated blockchain analysis\n\n## UK Context\n\n- British contributions and implementations\n  - UK Customs Authority (HMRC) modernising post-Brexit procedures through digital systems, though formal blockchain adoption remains exploratory rather than operational\n  - Digital-first customs brokers in the UK increasingly monitoring blockchain developments for supply chain applications[3]\n  - Limited but growing interest in blockchain for trade finance and letters of credit within London's financial services sector\n\n- North England innovation considerations\n  - Manchester and Leeds positioned as regional logistics and trade hubs, yet formal blockchain customs pilots remain absent compared to Asia-Pacific implementations\n  - Newcastle port authority exploring digital trade facilitation but primarily through conventional electronic systems rather than distributed ledgers\n  - Sheffield manufacturing sector potentially benefiting from blockchain-enabled supply chain transparency, though adoption remains theoretical\n  - Regional capacity gaps in blockchain technical expertise and regulatory clarity may impede North England adoption relative to London-based financial services\n\n## Future Directions\n\n- Emerging trends and developments\n  - Convergence of blockchain with artificial intelligence for predictive risk assessment and automated customs clearance[6]\n  - Expansion of cross-border blockchain networks linking customs administrations across multiple jurisdictions\n  - Integration of environmental compliance data (carbon border adjustment mechanisms) into blockchain-based customs systems[6]\n  - Development of interoperable standards enabling seamless data exchange between national blockchain implementations\n\n- Anticipated challenges\n  - Regulatory fragmentation across jurisdictions may necessitate multiple parallel blockchain implementations rather than unified global systems\n  - Cybersecurity vulnerabilities in decentralised systems require robust consensus mechanisms and node validation protocols\n  - Transition costs and legacy system integration present significant barriers for customs administrations in developing economies\n  - Governance disputes regarding control, transparency, and participation rights among stakeholders with competing interests\n\n- Research priorities\n  - Empirical evaluation of blockchain implementation outcomes (cost reduction, processing time, compliance improvement) across pilot jurisdictions\n  - Development of privacy-preserving mechanisms enabling cross-border data sharing whilst maintaining regulatory compliance\n  - Capacity-building frameworks tailored to developing nations' technical and institutional constraints\n  - Harmonisation of blockchain standards across regional trade blocs to facilitate interoperability\n\n## References\n\n[1] One Union Solutions. \"How Blockchain is Changing Customs Documentation.\" Accessed November 2025. Available at: oneunionsolutions.com/blog/how-blockchain-is-changing-customs-documentation/\n\n[2] World Customs Journal. \"Measuring the Electronic Readiness of the Islamic Republic of Iran Customs Administration to Implement Blockchain Technology in the Supply Chain.\" Accessed November 2025. Available at: worldcustomsjournal.org/article/144226\n\n[3] Customs Support. \"Blockchain: The Future of Customs and Supply Chains.\" Accessed November 2025. Available at: customssupport.com/blockchain-future-customs-and-supply-chains/\n\n[4] UNCTAD. \"Blockchains for Facilitating Trade and Enhancing Competitiveness.\" UN Project Documentation. Accessed November 2025. Available at: unctad.org/project/blockchains-facilitating-trade-and-enhancing-competitiveness\n\n[5] European Parliament. (2020). *Blockchain for Supply Chains and International Trade*. EPRS Study 641544/EN. Brussels: European Parliamentary Research Service.\n\n[6] APEC Sub-Committee on Customs Procedures. (2025). \"Modernizing Customs: Tackling Trade Bottlenecks and Digital Pressures.\" Press Release, November 2025. Available at: apec.org/press/news-releases/2025/modernising-customs--tackling-trade-bottlenecks-and-digital-pressures\n\n[7] OECD. (2025). *The Digitalisation of Trade Documents and Processes*. Paris: OECD Publishing. DOI: Available at: oecd.org/content/dam/oecd/en/publications/reports/2025/09/the-digitalisation-of-trade-documents-and-processes_de6a03e9/64872f25-en.pdf\n\n## Metadata\n\n- **Migration Status**: Ontology block enriched on 2025-11-12\n- **Last Updated**: 2025-11-12\n- **Review Status**: Comprehensive editorial review\n- **Verification**: Academic sources verified\n- **Regional Context**: UK/North England where applicable",
  "backlinks": [],
  "wiki_links": [
    "Blockchain",
    "BlockchainDomain"
  ],
  "ontology": {
    "term_id": "BC-0452",
    "preferred_term": "Customs Trade Facilitation",
    "alt_terms": [],
    "iri": "http://narrativegoldmine.com/blockchain#CustomsTradeFacilitation",
    "source_domain": "metaverse",
    "domain": "metaverse",
    "domain_full_name": "",
    "definition": "A component of the blockchain ecosystem.",
    "scope_note": null,
    "status": "stub-needs-content",
    "maturity": "draft",
    "version": null,
    "public_access": true,
    "last_updated": null,
    "authority_score": null,
    "quality_score": null,
    "cross_domain_links": null,
    "owl_class": "bc:CustomsTradeFacilitation",
    "owl_physicality": "ConceptualEntity",
    "owl_role": "Concept",
    "owl_inferred_class": null,
    "is_subclass_of": [],
    "has_part": [],
    "is_part_of": [],
    "requires": [],
    "depends_on": [],
    "enables": [],
    "relates_to": [],
    "bridges_to": [],
    "bridges_from": [],
    "domain_extensions": {},
    "belongs_to_domain": [
      "BlockchainDomain"
    ],
    "implemented_in_layer": [],
    "source": [],
    "validation": {
      "is_valid": false,
      "errors": [
        "Missing required property: last-updated",
        "Missing required property: is-subclass-of (at least one parent class)",
        "owl:class namespace 'bc' doesn't match source-domain 'metaverse'"
      ]
    }
  }
}