{
  "id": "Data Breach",
  "title": "Data Breach",
  "content": "- ### OntologyBlock\n  id:: databreach-ontology\n  collapsed:: true\n\n  - **Identification**\n    - domain-prefix:: AI\n    - sequence-number:: 0863\n    - filename-history:: [\"AI-0863-databreach.md\"]\n    - public-access:: true\n    - ontology:: true\n    - is-subclass-of:: [[DataResource]]\n    - term-id:: AI-0863\n    - preferred-term:: Data Breach\n    - source-domain:: ai\n    - status:: complete\n    - version:: 1.0.0\n    - last-updated:: 2025-11-13\n\n  - **Definition**\n    - definition:: \n    - maturity:: established\n    - source:: Chimera Prime Research\n    - authority-score:: 0.95\n\n  - **Semantic Classification**\n    - owl:class:: ai:DataBreach\n    - belongsToDomain:: [[Artificial Intelligence]]\n\n  - #### OWL Restrictions\n    \n\n  - #### CrossDomainBridges\n    - bridges-to:: [[Risk]] via is-subclass-of\n\n  -",
  "backlinks": [],
  "wiki_links": [
    "Risk",
    "Artificial Intelligence",
    "DataResource"
  ],
  "ontology": {
    "term_id": "AI-0863",
    "preferred_term": "Data Breach",
    "alt_terms": [],
    "iri": "http://narrativegoldmine.com/ai#DataBreach",
    "source_domain": "ai",
    "domain": "ai",
    "domain_full_name": "Artificial Intelligence",
    "definition": "- maturity:: established",
    "scope_note": null,
    "status": "complete",
    "maturity": "established",
    "version": "1.0.0",
    "public_access": true,
    "last_updated": "2025-11-13",
    "authority_score": 0.95,
    "quality_score": null,
    "cross_domain_links": null,
    "owl_class": "ai:DataBreach",
    "owl_physicality": null,
    "owl_role": null,
    "owl_inferred_class": null,
    "is_subclass_of": [],
    "has_part": [],
    "is_part_of": [],
    "requires": [],
    "depends_on": [],
    "enables": [],
    "relates_to": [],
    "bridges_to": [
      "Risk via is"
    ],
    "bridges_from": [],
    "domain_extensions": {},
    "belongs_to_domain": [
      "Artificial Intelligence"
    ],
    "implemented_in_layer": [],
    "source": [
      "Chimera Prime Research"
    ],
    "validation": {
      "is_valid": false,
      "errors": [
        "Missing required property: owl:physicality",
        "Missing required property: owl:role",
        "Missing required property: is-subclass-of (at least one parent class)"
      ]
    }
  }
}