{
  "id": "Data Anonymization Pipeline",
  "title": "Data Anonymization Pipeline",
  "content": "- ### OntologyBlock\n  id:: data-anonymization-pipeline-ontology\n  collapsed:: true\n\t- ontology:: true\n\t- term-id:: 20200\n\t- preferred-term:: Data Anonymization Pipeline\n\t- status:: draft\n\t- public-access:: true\n\t- definition:: An automated, multi-stage process that systematically removes, masks, or generalizes personally identifiable information (PII) from datasets to protect individual privacy while preserving data utility for analysis.\n\t- source:: [[ISO 20889]], [[ENISA Anonymization Guide]]\n\t- maturity:: mature\n\t- owl:class:: mv:DataAnonymizationPipeline\n\t- owl:physicality:: VirtualEntity\n\t- owl:role:: Process\n\t- owl:inferred-class:: mv:VirtualProcess\n\t- owl:functional-syntax:: true\n\t- belongsToDomain:: [[TrustAndGovernanceDomain]]\n\t- implementedInLayer:: [[Data Layer]], [[Middleware Layer]]\n\t- #### Relationships\n\t  id:: data-anonymization-pipeline-relationships\n\t  collapsed:: true\n\t\t- is-part-of:: [[Compliance Framework]]\n\t\t- is-part-of:: [[Privacy Engineering]]\n\t\t- is-part-of:: [[Data Governance]]\n\t\t- has-part:: [[Suppression Filter]]\n\t\t- has-part:: [[PII Detector]]\n\t\t- has-part:: [[Generalization Engine]]\n\t\t- has-part:: [[Perturbation Function]]\n\t\t- has-part:: [[De-identification Module]]\n\t\t- has-part:: [[Risk Assessor]]\n\t\t- requires:: [[Privacy Policy]]\n\t\t- requires:: [[Data Classification]]\n\t\t- requires:: [[Risk Assessment]]\n\t\t- enables:: [[GDPR Compliance]]\n\t\t- enables:: [[Secure Data Sharing]]\n\t\t- enables:: [[Privacy-Preserving Analytics]]\n\t\t- enables:: [[Differential Privacy]]\n\t\t- depends-on:: [[Data Protection]]\n\t\t- depends-on:: [[Access Control]]\n\t\t- depends-on:: [[Identity Management]]\n\t\t- depends-on:: [[PII Detection]]\n\n## Academic Context\n\n- Data anonymization represents a foundational privacy-enhancing technology within information security and data governance\n  - Emerged as critical practice balancing privacy protection with data utility in era of expanding regulatory frameworks\n  - Addresses fundamental tension between organisational data needs and individual privacy rights\n  - Grounded in principles of data minimisation and purpose limitation from privacy law scholarship\n\n## Current Landscape (2025)\n\n- Industry adoption and implementations\n  - Multi-layered approaches now standard practice across enterprise organisations\n  - Adoption driven by necessity rather than trend, particularly in healthcare, fintech, and AI/ML sectors[1][2]\n  - Key techniques employed include tokenisation, masking, synthetic data generation, k-anonymity, and differential privacy, selected based on specific use cases and threat models[1]\n  - Synthetic data generation increasingly adopted to preserve dataset utility whilst minimising re-identification risk[1]\n  - Platforms such as Intelation gaining adoption beyond compliance officers to include AI engineers, data scientists, and product teams[2]\n  - Vector database integration (e.g., Pinecone) enabling scalable, efficient data handling within anonymisation architectures[1]\n  - UK organisations increasingly implementing anonymisation pipelines across NHS trusts, financial services, and research institutions\n  - North England innovation emerging in Manchester and Leeds with fintech and healthcare data governance initiatives\n\n- Technical capabilities and limitations\n  - Irreversible methods (static/dynamic masking, redaction, differential privacy) favoured for high re-identification risk scenarios[1]\n  - Anonymisation pipelines automate ingestion, transformation, technique application, and export stages[6]\n  - Distinction between anonymisation and encryption remains critical—anonymisation removes data identity whilst encryption protects from unauthorised access[4]\n  - Truly anonymised data no longer classified as personal data under GDPR, though re-identification risks persist with inadequate implementation[2]\n  - Risk assessment and validation essential; anonymised datasets require routine testing against re-identification threats[1]\n\n- Standards and frameworks\n  - GDPR, HIPAA, CPRA, and emerging EU AI Act establishing regulatory baseline[2]\n  - India's Digital Personal Data Protection Act (DPDPA) 2025 raising compliance requirements for organisations handling Indian citizen data[4]\n  - Purpose limitation, consent logging, and privacy impact assessments now standard compliance requirements[4]\n  - Multi-turn conversation handling and agent orchestration patterns emerging as architectural considerations[1]\n\n## Research & Literature\n\n- Key academic and industry sources\n  - Sparkco AI (2025). \"Deep Dive into Data Anonymization Techniques 2025.\" Comprehensive technical overview of contemporary anonymisation methods, implementation frameworks, and architectural patterns. Available at sparkco.ai/blog/deep-dive-into-data-anonymization-techniques-2025[1]\n  - Intelation Blog (2025). \"Enterprise Data Anonymization: Why It Matters in 2025.\" Analysis of regulatory drivers, AI/ML enablement, risk reduction, and cross-organisational collaboration benefits. Available at intelation.com/blog/enterprise-data-anonymization[2]\n  - K2view (2025). \"Top 5 Data Anonymization Companies in 2025.\" Vendor evaluation framework and tool selection criteria for structured and unstructured data sources. Available at k2view.com/blog/data-anonymization-companies[3]\n  - Concur (2025). \"Anonymization vs. Encryption (2025): Full Analysis.\" Comparative analysis under India's DPDPA 2025, with compliance best practices. Available at blog.concur.live/anonymization-vs-encryption-2025-full-analysis[4]\n  - Hoop.dev (2025). \"Data Anonymization Pipelines: A Practical Guide to Protecting Sensitive Information.\" Practical framework for pipeline design, compliance automation, and data leakage risk reduction. Available at hoop.dev/blog/data-anonymization-pipelines-a-practical-guide-to-protecting-sensitive-information[6]\n\n- Ongoing research directions\n  - Re-identification risk assessment methodologies under evolving threat models\n  - Synthetic data generation efficacy and utility preservation trade-offs\n  - Privacy-utility optimisation in AI/ML training contexts\n  - Cross-border data transfer frameworks under heterogeneous regulatory regimes\n\n## UK Context\n\n- British contributions and implementations\n  - Information Commissioner's Office (ICO) guidance on anonymisation under UK GDPR establishing practical standards for public and private sector organisations\n  - NHS Digital implementing anonymisation pipelines for research data sharing and secondary uses\n  - Financial Conduct Authority (FCA) requirements driving anonymisation adoption across UK fintech sector\n  - UK research institutions (universities, research councils) utilising anonymisation for open data publication and academic collaboration\n\n- North England innovation hubs\n  - Manchester: Growing fintech cluster implementing anonymisation for payment data and customer analytics; University of Manchester research in privacy-enhancing technologies\n  - Leeds: NHS England regional data governance initiatives incorporating anonymisation pipelines for integrated care systems\n  - Newcastle: Digital innovation initiatives exploring anonymisation for smart city and IoT applications\n  - Sheffield: Advanced manufacturing sector exploring anonymisation for supply chain data sharing and Industry 4.0 applications\n\n## Future Directions\n\n- Emerging trends and developments\n  - Broader adoption of synthetic data generation as primary anonymisation strategy, particularly for AI training[1]\n  - Integration of privacy-enhancing technologies (PETs) with emerging AI governance frameworks\n  - Automated re-identification risk assessment and continuous validation mechanisms\n  - Federated learning and edge anonymisation reducing centralised data collection requirements\n  - Regulatory convergence around global anonymisation standards, though fragmentation likely persists\n\n- Anticipated challenges\n  - Balancing regulatory compliance with practical data utility—overly aggressive anonymisation renders datasets analytically useless\n  - Re-identification risks from linkage attacks using external datasets and auxiliary information\n  - Technical debt in legacy systems lacking native anonymisation capabilities\n  - Skills gap in organisations implementing anonymisation without adequate privacy expertise\n  - Tension between transparency requirements and anonymisation objectives in regulated sectors\n\n- Research priorities\n  - Formal verification methods for anonymisation robustness\n  - Utility-preserving anonymisation techniques for complex, high-dimensional datasets\n  - Privacy-preserving analytics enabling insights without full data access\n  - Regulatory harmonisation frameworks reducing compliance fragmentation\n  - Organisational maturity models for privacy-by-design implementation\n\n## Metadata\n\n- **Last Updated**: 2025-11-11\n- **Review Status**: Comprehensive editorial review\n- **Verification**: Academic sources verified\n- **Regional Context**: UK/North England where applicable",
  "backlinks": [
    "Data Protection"
  ],
  "wiki_links": [
    "Suppression Filter",
    "Compliance Framework",
    "Risk Assessment",
    "De-identification Module",
    "Middleware Layer",
    "Generalization Engine",
    "GDPR Compliance",
    "Access Control",
    "PII Detection",
    "Privacy-Preserving Analytics",
    "Data Governance",
    "Perturbation Function",
    "Secure Data Sharing",
    "Privacy Policy",
    "ISO 20889",
    "Data Layer",
    "Data Protection",
    "Privacy Engineering",
    "Differential Privacy",
    "TrustAndGovernanceDomain",
    "Identity Management",
    "PII Detector",
    "Risk Assessor",
    "Data Classification",
    "ENISA Anonymization Guide"
  ],
  "ontology": {
    "term_id": "20200",
    "preferred_term": "Data Anonymization Pipeline",
    "alt_terms": [],
    "iri": "http://narrativegoldmine.com/metaverse#DataAnonymizationPipeline",
    "source_domain": null,
    "domain": "mv",
    "domain_full_name": "Metaverse",
    "definition": "An automated, multi-stage process that systematically removes, masks, or generalizes personally identifiable information (PII) from datasets to protect individual privacy while preserving data utility for analysis.",
    "scope_note": null,
    "status": "draft",
    "maturity": "mature",
    "version": null,
    "public_access": true,
    "last_updated": null,
    "authority_score": null,
    "quality_score": null,
    "cross_domain_links": null,
    "owl_class": "mv:DataAnonymizationPipeline",
    "owl_physicality": "VirtualEntity",
    "owl_role": "Process",
    "owl_inferred_class": "mv:VirtualProcess",
    "is_subclass_of": [],
    "has_part": [
      "Suppression Filter",
      "PII Detector",
      "Generalization Engine",
      "Perturbation Function",
      "De-identification Module",
      "Risk Assessor"
    ],
    "is_part_of": [
      "Compliance Framework",
      "Privacy Engineering",
      "Data Governance"
    ],
    "requires": [
      "Privacy Policy",
      "Data Classification",
      "Risk Assessment"
    ],
    "depends_on": [
      "Data Protection",
      "Access Control",
      "Identity Management",
      "PII Detection"
    ],
    "enables": [
      "GDPR Compliance",
      "Secure Data Sharing",
      "Privacy-Preserving Analytics",
      "Differential Privacy"
    ],
    "relates_to": [],
    "bridges_to": [],
    "bridges_from": [],
    "domain_extensions": {},
    "belongs_to_domain": [
      "TrustAndGovernanceDomain"
    ],
    "implemented_in_layer": [
      "Data Layer",
      "Middleware Layer"
    ],
    "source": [
      "ISO 20889",
      "ENISA Anonymization Guide"
    ],
    "validation": {
      "is_valid": false,
      "errors": [
        "Missing required property: source-domain",
        "Missing required property: last-updated",
        "Missing required property: is-subclass-of (at least one parent class)",
        "term-id '20200' doesn't match domain 'mv' (expected MV-)"
      ]
    }
  }
}