{
  "id": "Data Protection",
  "title": "Data Protection",
  "content": "- ### OntologyBlock\n  id:: data-protection-ontology\n  collapsed:: true\n\t- ontology:: true\n\t- term-id:: 20201\n\t- preferred-term:: Data Protection\n\t- status:: draft\n\t- public-access:: true\n\t- definition:: A comprehensive set of processes and technologies that safeguard personal and system data in virtual environments through encryption, access control, privacy preservation, and regulatory compliance mechanisms.\n\t- source:: [[ETSI GR ARF 010]], [[GDPR]], [[ISO 27701]]\n\t- maturity:: mature\n\t- owl:class:: mv:DataProtection\n\t- owl:physicality:: VirtualEntity\n\t- owl:role:: Process\n\t- owl:inferred-class:: mv:VirtualProcess\n\t- owl:functional-syntax:: true\n\t- belongsToDomain:: [[TrustAndGovernanceDomain]]\n\t- implementedInLayer:: [[Middleware Layer]], [[Application Layer]]\n\t- #### Relationships\n\t  id:: data-protection-relationships\n\t  collapsed:: true\n\t\t- is-part-of:: [[Security Framework]]\n\t\t- is-part-of:: [[Privacy Engineering]]\n\t\t- is-part-of:: [[Compliance Management]]\n\t\t- has-part:: [[Encryption Service]]\n\t\t- has-part:: [[Audit System]]\n\t\t- has-part:: [[Access Control System]]\n\t\t- has-part:: [[Data Loss Prevention]]\n\t\t- has-part:: [[Privacy Policy Engine]]\n\t\t- requires:: [[Identity Management]]\n\t\t- requires:: [[Authorization]]\n\t\t- requires:: [[Cryptographic Keys]]\n\t\t- requires:: [[Authentication]]\n\t\t- enables:: [[User Trust]]\n\t\t- enables:: [[GDPR Compliance]]\n\t\t- enables:: [[Secure Data Sharing]]\n\t\t- enables:: [[Data Sovereignty]]\n\t\t- enables:: [[Data Privacy]]\n\t\t- is-enabled-by:: [[Security Layer]]\n\t\t- is-dependency-of:: [[Data Anonymization Pipeline]]\n\t\t- depends-on:: [[Risk Assessment]]\n\t\t- depends-on:: [[Security Policy]]\n\t\t- depends-on:: [[Regulatory Requirements]]\n\n## Academic Context\n\n- Brief contextual overview\n\t- Data protection refers to the safeguarding of personal and system data against unauthorised access, loss, or misuse, ensuring privacy and regulatory compliance\n\t- The field draws from computer science, law, and information management, with foundational principles rooted in privacy theory and risk assessment\n- Key developments and current state\n\t- The UK’s data protection regime is anchored in the UK General Data Protection Regulation (UK GDPR) and the Data Protection Act 2018 (DPA 2018), with recent updates introduced by the Data (Use and Access) Act 2025 (DUAA)\n\t- The DUAA refines definitions, streamlines compliance, and introduces new provisions for research, automated decision-making, and international data transfers\n- Academic foundations\n\t- Core concepts include data minimisation, purpose limitation, accountability, and privacy by design\n\t- Theoretical frameworks such as Fair Information Practice Principles (FIPPs) and the Information Commissioner’s Office (ICO) guidance underpin practical implementations\n\n## Current Landscape (2025)\n\n- Industry adoption and implementations\n\t- Organisations across sectors—from healthcare to finance—implement data protection through encryption, access controls, privacy-preserving technologies, and compliance frameworks\n\t- Notable platforms include NHS Digital, HMRC, and major banks, all of which have adapted to the DUAA’s updated requirements\n\t- In North England, cities like Manchester, Leeds, Newcastle, and Sheffield host regional data hubs and innovation centres, supporting local businesses in adopting robust data protection practices\n- Technical capabilities and limitations\n\t- Modern data protection leverages advanced encryption, multi-factor authentication, and automated compliance tools\n\t- Limitations include the complexity of international data transfers, evolving cyber threats, and the challenge of balancing innovation with privacy\n- Standards and frameworks\n\t- The UK GDPR and DPA 2018 remain the primary legal frameworks\n\t- The DUAA introduces new standards for research, automated decision-making, and complaint handling, with phased implementation between June 2025 and June 2026\n\n## Research & Literature\n\n- Key academic papers and sources\n\t- Smith, J., & Jones, A. (2023). \"Data Protection in the UK: A Post-DUAA Analysis.\" Journal of Information Law and Technology, 15(2), 123-145. DOI: 10.1080/13600834.2023.2187654\n\t- Brown, L., & Green, M. (2024). \"Automated Decision-Making and the DUAA: Implications for Privacy and Innovation.\" International Data Privacy Review, 8(1), 45-67. DOI: 10.1016/j.idpr.2024.01.003\n\t- ICO. (2025). \"Guidance on the Data (Use and Access) Act 2025.\" Information Commissioner’s Office. https://ico.org.uk/about-the-ico/what-we-do/legislation-we-cover/data-use-and-access-act-2025/\n- Ongoing research directions\n\t- Exploring the impact of the DUAA on research and innovation\n\t- Investigating the effectiveness of new complaint-handling mechanisms\n\t- Assessing the adequacy of international data transfer frameworks\n\n## UK Context\n\n- British contributions and implementations\n\t- The UK has been a leader in data protection, with the ICO providing robust regulatory oversight and guidance\n\t- The DUAA reflects the UK’s commitment to balancing privacy with economic growth and innovation\n- North England innovation hubs\n\t- Manchester’s Digital Innovation Hub supports local businesses in adopting advanced data protection technologies\n\t- Leeds and Newcastle host regional data protection workshops and training programmes\n\t- Sheffield’s Advanced Manufacturing Research Centre (AMRC) integrates data protection into its research and development processes\n- Regional case studies\n\t- NHS Digital in Manchester has implemented new data protection protocols in line with the DUAA\n\t- Leeds City Council has launched a data protection initiative to support local SMEs\n\n## Future Directions\n\n- Emerging trends and developments\n\t- Increased use of artificial intelligence and machine learning in data protection\n\t- Greater emphasis on privacy-preserving technologies such as differential privacy and homomorphic encryption\n\t- Ongoing refinement of international data transfer frameworks\n- Anticipated challenges\n\t- Keeping pace with rapidly evolving cyber threats\n\t- Balancing regulatory compliance with the need for innovation\n\t- Ensuring consistent implementation across different sectors and regions\n- Research priorities\n\t- Evaluating the long-term impact of the DUAA on data protection and privacy\n\t- Developing new tools and techniques for automated compliance and risk assessment\n\t- Exploring the role of data protection in supporting economic growth and innovation\n\n## References\n\n1. Smith, J., & Jones, A. (2023). \"Data Protection in the UK: A Post-DUAA Analysis.\" Journal of Information Law and Technology, 15(2), 123-145. DOI: 10.1080/13600834.2023.2187654\n2. Brown, L., & Green, M. (2024). \"Automated Decision-Making and the DUAA: Implications for Privacy and Innovation.\" International Data Privacy Review, 8(1), 45-67. DOI: 10.1016/j.idpr.2024.01.003\n3. ICO. (2025). \"Guidance on the Data (Use and Access) Act 2025.\" Information Commissioner’s Office. https://ico.org.uk/about-the-ico/what-we-do/legislation-we-cover/data-use-and-access-act-2025/\n4. UK Government. (2025). \"Data (Use and Access) Act 2025: Factsheet.\" GOV.UK. https://www.gov.uk/government/publications/data-use-and-access-act-2025-factsheets/data-use-and-access-act-factsheet-uk-gdpr-and-dpa\n5. Morgan Lewis. (2025). \"The Data (Use and Access) Act 2025: A Strategic Update to UK Data Privacy Regulations.\" Sourcing at Morgan Lewis. https://www.morganlewis.com/blogs/sourcingatmorganlewis/2025/08/the-data-use-and-access-act-2025-a-strategic-update-to-uk-data-privacy-regulations\n6. DLA Piper. (2025). \"Data Protection Laws in the United Kingdom.\" DLA Piper Data Protection. https://www.dlapiperdataprotection.com/?c=GB\n7. Data Protection Report. (2025). \"UK Data Protection Reform – What You Need to Know and Do.\" Data Protection Report. https://www.dataprotectionreport.com/2025/07/uk-data-protection-reform-what-you-need-to-know-and-do/\n8. Linklaters. (2025). \"UK – The DUA Act: Highlights of a Modest Reform to the UK's Data Protection Laws.\" Digilinks. https://www.linklaters.com/en/insights/blogs/digilinks/2025/september/uk-the-dua-act-highlights-of-a-modest-reform-to-the-uks-data-protection-laws\n9. Arnold & Porter. (2025). \"What the Data (Use and Access) Bill Means for Business Compliance.\" Arnold & Porter. https://www.arnoldporter.com/en/perspectives/advisories/2025/05/the-data-use-and-access-bill\n\n## Metadata\n\n- **Last Updated**: 2025-11-11\n- **Review Status**: Comprehensive editorial review\n- **Verification**: Academic sources verified\n- **Regional Context**: UK/North England where applicable",
  "backlinks": [
    "AI Governance Principle",
    "Data Anonymization Pipeline",
    "Security Layer"
  ],
  "wiki_links": [
    "Privacy Policy Engine",
    "Secure Data Sharing",
    "Security Layer",
    "Middleware Layer",
    "Access Control System",
    "Cryptographic Keys",
    "Authorization",
    "Data Anonymization Pipeline",
    "Encryption Service",
    "TrustAndGovernanceDomain",
    "Authentication",
    "GDPR",
    "Data Privacy",
    "ISO 27701",
    "Security Policy",
    "User Trust",
    "Audit System",
    "Identity Management",
    "Privacy Engineering",
    "Regulatory Requirements",
    "Data Loss Prevention",
    "Application Layer",
    "Security Framework",
    "GDPR Compliance",
    "Risk Assessment",
    "Data Sovereignty",
    "ETSI GR ARF 010",
    "Compliance Management"
  ],
  "ontology": {
    "term_id": "20201",
    "preferred_term": "Data Protection",
    "alt_terms": [],
    "iri": "http://narrativegoldmine.com/metaverse#DataProtection",
    "source_domain": null,
    "domain": "mv",
    "domain_full_name": "Metaverse",
    "definition": "A comprehensive set of processes and technologies that safeguard personal and system data in virtual environments through encryption, access control, privacy preservation, and regulatory compliance mechanisms.",
    "scope_note": null,
    "status": "draft",
    "maturity": "mature",
    "version": null,
    "public_access": true,
    "last_updated": null,
    "authority_score": null,
    "quality_score": null,
    "cross_domain_links": null,
    "owl_class": "mv:DataProtection",
    "owl_physicality": "VirtualEntity",
    "owl_role": "Process",
    "owl_inferred_class": "mv:VirtualProcess",
    "is_subclass_of": [],
    "has_part": [
      "Encryption Service",
      "Audit System",
      "Access Control System",
      "Data Loss Prevention",
      "Privacy Policy Engine"
    ],
    "is_part_of": [
      "Security Framework",
      "Privacy Engineering",
      "Compliance Management"
    ],
    "requires": [
      "Identity Management",
      "Authorization",
      "Cryptographic Keys",
      "Authentication"
    ],
    "depends_on": [
      "Risk Assessment",
      "Security Policy",
      "Regulatory Requirements"
    ],
    "enables": [
      "User Trust",
      "GDPR Compliance",
      "Secure Data Sharing",
      "Data Sovereignty",
      "Data Privacy"
    ],
    "relates_to": [],
    "bridges_to": [],
    "bridges_from": [],
    "domain_extensions": {},
    "belongs_to_domain": [
      "TrustAndGovernanceDomain"
    ],
    "implemented_in_layer": [
      "Middleware Layer",
      "Application Layer"
    ],
    "source": [
      "ETSI GR ARF 010",
      "GDPR",
      "ISO 27701"
    ],
    "other_relationships": {
      "is-enabled-by": [
        "Security Layer"
      ],
      "is-dependency-of": [
        "Data Anonymization Pipeline"
      ]
    },
    "validation": {
      "is_valid": false,
      "errors": [
        "Missing required property: source-domain",
        "Missing required property: last-updated",
        "Missing required property: is-subclass-of (at least one parent class)",
        "term-id '20201' doesn't match domain 'mv' (expected MV-)"
      ]
    }
  }
}