{
  "id": "DeBERTa",
  "title": "DeBERTa",
  "content": "- ### OntologyBlock\n  id:: deberta-ontology\n  collapsed:: true\n\t- ontology:: true\n\t- term-id:: AI-0220\n\t- preferred-term:: DeBERTa\n\t- source-domain:: metaverse\n\t- status:: draft\n\t- public-access:: true\n\n\n\n\n### OWL Classification\n\t- owl:class:: mv:DeBERTa\n\t- owl:physicality:: ConceptualEntity\n\t- owl:role:: Concept\n\n### Domain & Architecture\n\t- belongsToDomain:: [[MetaverseDomain]]\n\t- maturity:: draft\n\n### Relationships\n- is-subclass-of:: [[BERT]]\n\n## Characteristics\n\n- **Disentangled Attention**: Separate attention matrices for content and position\n- **Enhanced Mask Decoder**: Incorporates absolute positions for prediction\n- **Improved Performance**: Surpasses BERT and RoBERTa on benchmarks\n- **Relative Position Encoding**: More flexible position representation\n\n## Academic Foundations\n\n**Primary Source**: He et al., \"DeBERTa: Decoding-enhanced BERT with Disentangled Attention\", arXiv:2006.03654 (2020)\n\n**Performance**: Surpasses RoBERTa on a majority of NLU tasks and achieves state-of-the-art on SuperGLUE.\n\n## Technical Context\n\nDeBERTa improves upon BERT by using disentangled attention where each word is represented using two vectors (content and position) that are disentangled. An enhanced mask decoder uses absolute positions alongside contextual information for MLM prediction.\n\n## Ontological Relationships\n\n- **Broader Term**: Pre-trained Language Model\n- **Related Terms**: BERT, RoBERTa, Attention Mechanism\n- **Innovation**: Disentangled Attention, Enhanced Mask Decoder\n\n## Usage Context\n\n\"DeBERTa's disentangled attention mechanism separates content and position representations for more effective modelling.\"\n\n## OWL Functional Syntax\n\n```clojure\n(Declaration (Class :DeBERTa))\n(AnnotationAssertion rdfs:label :DeBERTa \"DeBERTa\"@en)\n(AnnotationAssertion rdfs:comment :DeBERTa\n  \"Decoding-enhanced BERT with Disentangled Attention using separate content and position representations.\"@en)\n(AnnotationAssertion :hasSource :DeBERTa\n  \"He et al., 'DeBERTa: Decoding-enhanced BERT with Disentangled Attention', arXiv:2006.03654 (2020)\"@en)\n\n;; Taxonomic relationships\n(SubClassOf :DeBERTa :PreTrainedLanguageModel)\n(SubClassOf :DeBERTa :TransformerArchitecture)\n\n;; Based on BERT\n(SubClassOf :DeBERTa\n  (ObjectSomeValuesFrom :improves :BERT))\n\n;; Key innovations\n(SubClassOf :DeBERTa\n  (ObjectSomeValuesFrom :uses :DisentangledAttention))\n(SubClassOf :DeBERTa\n  (ObjectSomeValuesFrom :uses :EnhancedMaskDecoder))\n(SubClassOf :DeBERTa\n  (ObjectSomeValuesFrom :uses :RelativePositionEncoding))\n\n;; Representations\n(SubClassOf :DeBERTa\n  (ObjectSomeValuesFrom :separates :ContentRepresentation))\n(SubClassOf :DeBERTa\n  (ObjectSomeValuesFrom :separates :PositionRepresentation))\n\n;; Properties\n(DataPropertyAssertion :surpassesBERT :DeBERTa \"true\"^^xsd:boolean)\n(DataPropertyAssertion :surpassesRoBERTa :DeBERTa \"true\"^^xsd:boolean)\n(DataPropertyAssertion :achievesStateOfTheArt :DeBERTa \"SuperGLUE\"^^xsd:string)\n(DataPropertyAssertion :hasDisentangledAttention :DeBERTa \"true\"^^xsd:boolean)\n\n;; Related models\n(DisjointClasses :DeBERTa :ALBERT)\n(DisjointClasses :DeBERTa :ELECTRA)\n```\n\n## References\n\n- He, P., et al. (2020). \"DeBERTa: Decoding-enhanced BERT with Disentangled Attention\". arXiv:2006.03654\n\n---\n\n*Ontology Term managed by AI-Grounded Ontology Working Group*\n*UK English Spelling Standards Applied*\n\t- maturity:: draft\n\t- owl:class:: mv:DeBERTa\n\t- owl:physicality:: ConceptualEntity\n\t- owl:role:: Concept\n\t- belongsToDomain:: [[MetaverseDomain]]",
  "backlinks": [],
  "wiki_links": [
    "MetaverseDomain",
    "BERT"
  ],
  "ontology": {
    "term_id": "AI-0220",
    "preferred_term": "DeBERTa",
    "alt_terms": [],
    "iri": "http://narrativegoldmine.com/metaverse#DeBERTa",
    "source_domain": "metaverse",
    "domain": "metaverse",
    "domain_full_name": "",
    "definition": null,
    "scope_note": null,
    "status": "draft",
    "maturity": "draft",
    "version": null,
    "public_access": true,
    "last_updated": null,
    "authority_score": null,
    "quality_score": null,
    "cross_domain_links": null,
    "owl_class": "mv:DeBERTa",
    "owl_physicality": "ConceptualEntity",
    "owl_role": "Concept",
    "owl_inferred_class": null,
    "is_subclass_of": [],
    "has_part": [],
    "is_part_of": [],
    "requires": [],
    "depends_on": [],
    "enables": [],
    "relates_to": [],
    "bridges_to": [],
    "bridges_from": [],
    "domain_extensions": {},
    "belongs_to_domain": [
      "MetaverseDomain",
      "MetaverseDomain"
    ],
    "implemented_in_layer": [],
    "source": [],
    "validation": {
      "is_valid": false,
      "errors": [
        "Missing required property: last-updated",
        "Missing required property: definition",
        "Missing required property: is-subclass-of (at least one parent class)",
        "owl:class namespace 'mv' doesn't match source-domain 'metaverse'"
      ]
    }
  }
}