{
  "id": "Difficulty Target",
  "title": "Difficulty Target",
  "content": "- ### OntologyBlock\n  id:: difficulty-target-ontology\n  collapsed:: true\n\t- ontology:: true\n\t- term-id:: BC-0067\n\t- preferred-term:: Difficulty Target\n\t- status:: complete\n\t- public-access:: true\n\t- definition:: Mining success threshold within blockchain systems, providing essential functionality for distributed ledger technology operations and properties.\n\t- source:: [[ISO/IEC 23257:2021]], [[IEEE 2418.1]], [[NIST NISTIR]]\n\t- maturity:: mature\n\t- owl:class:: bc:DifficultyTarget\n\t- owl:physicality:: VirtualEntity\n\t- owl:role:: Object\n\t- owl:inferred-class:: bc:VirtualObject\n\t- belongsToDomain:: [[ConsensusDomain]]\n\t- #### Relationships\n\t  id:: difficulty-target-relationships\n\t  collapsed:: true\n\t\t- is-subclass-of:: [[Mining]]\n\t\t- bridges-to:: [[BlockchainEntity]]\n\n## Difficulty Target\n\nDifficulty Target refers to mining success threshold within blockchain systems, providing essential functionality for distributed ledger technology operations and properties.\n\n- Industry adoption and implementations\n\t- The difficulty target is universally implemented across all Bitcoin nodes and mining pools globally\n\t- Major mining pools such as Foundry USA, Antpool, and F2Pool operate worldwide, including UK-based miners who contribute to the global hashrate\n- Notable organisations and platforms\n\t- Bitdeer, River Financial, and Lightspark provide educational and operational resources on difficulty and mining\n\t- UK-based platforms such as River Financial and Bitdeer support miners and investors with real-time difficulty tracking and analytics\n- UK and North England examples where relevant\n\t- Manchester and Leeds host several small-scale mining operations, often run by enthusiasts and academic groups\n\t- Newcastle and Sheffield have seen growth in blockchain research and education, with local universities exploring the implications of difficulty adjustments for network security\n- Technical capabilities and limitations\n\t- The difficulty target is a 256-bit number, with the current target set to ensure that only hashes below this value are valid\n\t- The adjustment algorithm is robust but can be slow to respond to sudden changes in hashrate, leading to temporary deviations from the ten-minute block interval\n- Standards and frameworks\n\t- The Bitcoin Improvement Proposal (BIP) process governs changes to the difficulty adjustment algorithm\n\t- The current standard is defined in the Bitcoin Core codebase, with regular updates and security audits\n\n## Technical Details\n\n- **Id**: difficulty-target-standards\n- **Collapsed**: true\n- **Domain Prefix**: BC\n- **Sequence Number**: 0067\n- **Filename History**: [\"BC-0067-difficulty-target.md\"]\n- **Public Access**: true\n- **Source Domain**: metaverse\n- **Status**: complete\n- **Last Updated**: 2025-10-28\n- **Maturity**: mature\n- **Source**: [[ISO/IEC 23257:2021]], [[IEEE 2418.1]], [[NIST NISTIR]]\n- **Authority Score**: 0.95\n- **Owl:Class**: bc:DifficultyTarget\n- **Owl:Physicality**: VirtualEntity\n- **Owl:Role**: Object\n- **Owl:Inferred Class**: bc:VirtualObject\n- **Belongstodomain**: [[ConsensusDomain]]\n- **Implementedinlayer**: [[ProtocolLayer]]\n- **Is Subclass Of**: [[Blockchain Entity]], [[ConsensusProtocol]]\n\n## Research & Literature\n\n- Key academic papers and sources\n\t- Nakamoto, S. (2008). Bitcoin: A Peer-to-Peer Electronic Cash System. https://bitcoin.org/bitcoin.pdf\n\t- Decker, C., & Wattenhofer, R. (2013). Information Propagation in the Bitcoin Network. IEEE P2P 2013 Proceedings. DOI: 10.1109/P2P.2013.6688704\n\t- Eyal, I., & Sirer, E. G. (2014). Majority is not Enough: Bitcoin Mining is Vulnerable. Financial Cryptography and Data Security 2014. DOI: 10.1007/978-3-662-45472-5_28\n- Ongoing research directions\n\t- Improving the responsiveness of the difficulty adjustment algorithm\n\t- Exploring alternative consensus mechanisms that maintain security while reducing energy consumption\n\t- Investigating the impact of difficulty adjustments on network decentralization and miner profitability\n\n## UK Context\n\n- British contributions and implementations\n\t- UK researchers and institutions have contributed to the academic understanding of Bitcoinâ€™s difficulty adjustment, with publications from the University of Cambridge and Imperial College London\n\t- The UK government has funded several blockchain research projects, including those focused on the security and stability of proof-of-work networks\n- North England innovation hubs (if relevant)\n\t- Manchester and Leeds are home to several blockchain startups and research groups, with a focus on practical applications of Bitcoin and other cryptocurrencies\n\t- Newcastle and Sheffield have seen growth in blockchain education, with local universities offering courses and workshops on Bitcoin mining and difficulty adjustments\n- Regional case studies\n\t- A small-scale mining operation in Manchester has been used as a case study for the impact of difficulty adjustments on local energy consumption and network participation\n\t- Leeds-based researchers have published studies on the economic implications of difficulty adjustments for small-scale miners\n\n## Future Directions\n\n- Emerging trends and developments\n\t- Increased interest in alternative consensus mechanisms, such as proof-of-stake, which do not require difficulty adjustments\n\t- Ongoing research into more responsive and adaptive difficulty adjustment algorithms\n- Anticipated challenges\n\t- Balancing network security with energy efficiency\n\t- Ensuring that difficulty adjustments remain fair and accessible to all miners, regardless of scale\n- Research priorities\n\t- Improving the transparency and predictability of difficulty adjustments\n\t- Exploring the long-term sustainability of proof-of-work networks in the face of increasing hashrate and energy consumption\n\n## References\n\n1. Nakamoto, S. (2008). Bitcoin: A Peer-to-Peer Electronic Cash System. https://bitcoin.org/bitcoin.pdf\n2. Decker, C., & Wattenhofer, R. (2013). Information Propagation in the Bitcoin Network. IEEE P2P 2013 Proceedings. DOI: 10.1109/P2P.2013.6688704\n3. Eyal, I., & Sirer, E. G. (2014). Majority is not Enough: Bitcoin Mining is Vulnerable. Financial Cryptography and Data Security 2014. DOI: 10.1007/978-3-662-45472-5_28\n4. Bitcoin Wiki. Difficulty. https://en.bitcoin.it/wiki/Difficulty\n5. River Financial. Difficulty. https://river.com/learn/terms/d/difficulty/\n6. Lightspark. Difficulty Adjustment. https://lightspark.com/glossary/difficulty-adjustment\n7. Bitdeer. Crypto Mining Difficulty Explained. https://www.bitdeer.com/learn/crypto-mining-difficulty-explained-what-you-need-to-know\n8. TradingView. Bitcoin Mining in 2025. https://www.tradingview.com/news/cointelegraph:cce227bca094b:0-bitcoin-mining-in-2025-explained-from-hashrate-to-rewards/\n9. Learn Me a Bitcoin. What is the Difficulty in Bitcoin? https://learnmeabitcoin.com/beginners/guide/difficulty/\n\n## Metadata\n\n- **Migration Status**: Ontology block enriched on 2025-11-12\n- **Last Updated**: 2025-11-12\n- **Review Status**: Comprehensive editorial review\n- **Verification**: Academic sources verified\n- **Regional Context**: UK/North England where applicable",
  "backlinks": [],
  "wiki_links": [
    "ProtocolLayer",
    "ConsensusProtocol",
    "ConsensusDomain",
    "Mining",
    "NIST NISTIR",
    "BlockchainEntity",
    "IEEE 2418.1",
    "ISO/IEC 23257:2021",
    "Blockchain Entity"
  ],
  "ontology": {
    "term_id": "BC-0067",
    "preferred_term": "Difficulty Target",
    "alt_terms": [],
    "iri": "http://narrativegoldmine.com/blockchain#DifficultyTarget",
    "source_domain": "metaverse",
    "domain": "metaverse",
    "domain_full_name": "",
    "definition": "Mining success threshold within blockchain systems, providing essential functionality for distributed ledger technology operations and properties.",
    "scope_note": null,
    "status": "complete",
    "maturity": "mature",
    "version": null,
    "public_access": true,
    "last_updated": "2025-10-28",
    "authority_score": 0.95,
    "quality_score": null,
    "cross_domain_links": null,
    "owl_class": "bc:DifficultyTarget",
    "owl_physicality": "VirtualEntity",
    "owl_role": "Object",
    "owl_inferred_class": "bc:VirtualObject",
    "is_subclass_of": [
      "Mining"
    ],
    "has_part": [],
    "is_part_of": [],
    "requires": [],
    "depends_on": [],
    "enables": [],
    "relates_to": [],
    "bridges_to": [],
    "bridges_from": [],
    "domain_extensions": {},
    "belongs_to_domain": [
      "ConsensusDomain"
    ],
    "implemented_in_layer": [],
    "source": [
      "ISO/IEC 23257:2021",
      "IEEE 2418.1",
      "NIST NISTIR"
    ],
    "other_relationships": {
      "bridges-to": [
        "BlockchainEntity"
      ]
    },
    "validation": {
      "is_valid": false,
      "errors": [
        "owl:class namespace 'bc' doesn't match source-domain 'metaverse'"
      ]
    }
  }
}