{
  "id": "Difficulty",
  "title": "Difficulty",
  "content": "- ### OntologyBlock\n  id:: difficulty-ontology\n  collapsed:: true\n\n  - **Identification**\n    - domain-prefix:: BC\n    - sequence-number:: 0035\n    - filename-history:: [\"BC-0035-difficulty.md\"]\n    - public-access:: true\n    - ontology:: true\n    - is-subclass-of:: [[BlockchainTechnology]]\n    - term-id:: BC-0035\n    - preferred-term:: Difficulty\n    - source-domain:: blockchain\n    - status:: complete\n    - version:: 2.0.0\n    - last-updated:: 2025-01-14\n\n  - **Definition**\n    - definition:: Mining computational requirement within blockchain systems that adjusts dynamically to maintain consistent block production times, providing essential security and consensus mechanism functionality for distributed ledger technology operations.\n    - maturity:: mature\n    - source:: [[ISO/IEC 23257:2021]], [[IEEE 2418.1]], [[NIST NISTIR 8202]]\n    - authority-score:: 0.95\n\n  - **Semantic Classification**\n    - owl:class:: bc:Difficulty\n    - owl:physicality:: VirtualEntity\n    - owl:role:: Object\n    - owl:inferred-class:: bc:VirtualObject\n    - belongsToDomain:: [[CryptographicDomain]]\n\n  - #### OWL Restrictions\n    \n    \n\n  - #### CrossDomainBridges\n    - bridges-to:: [[BlockchainEntity]] via is-subclass-of\n\n  -",
  "backlinks": [
    "Blockchain Entity",
    "SHA-256"
  ],
  "wiki_links": [
    "ISO/IEC 23257:2021",
    "CryptographicDomain",
    "BlockchainTechnology",
    "IEEE 2418.1",
    "NIST NISTIR 8202",
    "BlockchainEntity"
  ],
  "ontology": {
    "term_id": "BC-0035",
    "preferred_term": "Difficulty",
    "alt_terms": [],
    "iri": "http://narrativegoldmine.com/blockchain#Difficulty",
    "source_domain": "blockchain",
    "domain": "blockchain",
    "domain_full_name": "",
    "definition": "Mining computational requirement within blockchain systems that adjusts dynamically to maintain consistent block production times, providing essential security and consensus mechanism functionality for distributed ledger technology operations.",
    "scope_note": null,
    "status": "complete",
    "maturity": "mature",
    "version": "2.0.0",
    "public_access": true,
    "last_updated": "2025-01-14",
    "authority_score": 0.95,
    "quality_score": null,
    "cross_domain_links": null,
    "owl_class": "bc:Difficulty",
    "owl_physicality": "VirtualEntity",
    "owl_role": "Object",
    "owl_inferred_class": "bc:VirtualObject",
    "is_subclass_of": [],
    "has_part": [],
    "is_part_of": [],
    "requires": [],
    "depends_on": [],
    "enables": [],
    "relates_to": [],
    "bridges_to": [
      "BlockchainEntity via is"
    ],
    "bridges_from": [],
    "domain_extensions": {},
    "belongs_to_domain": [
      "CryptographicDomain"
    ],
    "implemented_in_layer": [],
    "source": [
      "ISO/IEC 23257:2021",
      "IEEE 2418.1",
      "NIST NISTIR 8202"
    ],
    "validation": {
      "is_valid": false,
      "errors": [
        "Missing required property: is-subclass-of (at least one parent class)",
        "owl:class namespace 'bc' doesn't match source-domain 'blockchain'"
      ]
    }
  }
}