{
  "id": "Digital Twin of the Customer",
  "title": "Digital Twin of the Customer",
  "content": "- ### OntologyBlock\n  id:: digital-twin-of-the-customer-ontology\n  collapsed:: true\n\t- ontology:: true\n\t- term-id:: ME-0013\n\t- preferred-term:: Digital Twin of the Customer\n\t- source-domain:: metaverse\n\t- status:: emerging\n\t- public-access:: true\n\n\n\n\n### OWL Classification\n\t- owl:class:: mv:DigitalTwinoftheCustomer\n\t- owl:physicality:: ConceptualEntity\n\t- owl:role:: Concept\n\n### Domain & Architecture\n\t- belongsToDomain:: [[MetaverseDomain]]\n\t- maturity:: emerging\n\n### Relationships\n\n## Latest Developments and Frameworks (2024–2025)\n\nThe latest developments for **Digital Twin of the Customer (DToC)** in 2024–2025 focus on advanced personalisation, AI-driven analytics, real-time simulation, and robust governance frameworks. DToC is increasingly used to create dynamic, data-rich virtual representations of individual customers, enabling hyper-personalised experiences, predictive insights, and operational optimisation across sectors, including retail, finance, and public services.\n\n**Key Developments and Trends (2024–2025):**\n\n- **AI and Machine Learning Integration:** DToC leverages AI to analyse behavioural data, predict preferences, and automate decision-making, enabling real-time adaptation of products, services, and interfaces to individual customer needs[1][2][3].\n- **IoT and Data Fusion:** Real-time data from IoT devices, transaction histories, and digital interactions are synchronised to maintain an up-to-date, holistic customer twin[1][4].\n- **Conversational and Adaptive Interfaces:** Generative AI powers natural language interfaces, allowing users and organisations to interact with customer twins through dialogue rather than static dashboards. Interfaces dynamically adapt content and visualisations based on user roles and context[3].\n- **Twin-as-a-Service (TaaS):** Cloud-based platforms offer plug-and-play DToC solutions, reducing deployment time and enabling rapid scaling across industries[3].\n- **Privacy, Security, and AI TRiSM:** With increased data sensitivity, frameworks such as **AI Trust, Risk, and Security Management (AI TRiSM)** are adopted to ensure transparency, ethical use, and regulatory compliance in DToC implementations[6].\n- **Blockchain for Data Sovereignty:** Blockchain is explored to give customers control over their digital twin data, supporting consent management and secure data sharing[1][10].\n- **Sustainability and Circular Economy:** DToC is used to model and influence sustainable customer behaviours, supporting ESG goals and circular economy initiatives[8][10].\n\n**Frameworks and Standards:**\n\n- **AI TRiSM (AI Trust, Risk, and Security Management):** Provides a structured approach to managing AI risks, ensuring explainability, bias detection, and robust governance for DToC systems[6].\n- **GDPR and UK Data Protection Act:** UK implementations must comply with these regulations, ensuring customer data privacy and rights.\n- **ISO/IEC 30182:2017 (Smart City Conceptual Model):** Increasingly referenced for structuring DToC data in public sector and smart city applications.\n- **Open Digital Twin Frameworks:** Initiatives from the Digital Twin Consortium and the Open Group are influencing best practices for interoperability and data standards.\n\n**Technologies:**\n\n- **Cloud Platforms:** Microsoft Azure Digital Twins, AWS IoT TwinMaker, and Siemens Xcelerator are leading platforms supporting DToC deployments[1].\n- **AI/ML Toolkits:** NVIDIA Omniverse, IBM Watson, and Google Vertex AI are used for analytics, simulation, and conversational interfaces[2][3].\n- **IoT Integration:** Real-time sensor and device data are foundational for accurate, dynamic customer twins[1][4].\n- **Blockchain:** Used for secure, auditable customer data management and consent tracking[1][10].\n\n**Best Practices:**\n\n- **Personalisation at Scale:** Use AI to tailor experiences, recommendations, and communications to individual customer profiles and real-time context[2][3].\n- **Continuous Data Synchronisation:** Integrate diverse data sources (IoT, CRM, social, transactional) for a unified, current view of the customer[1][4].\n- **Explainability and Transparency:** Implement AI TRiSM to ensure DToC systems are interpretable, auditable, and compliant with regulations[6].\n- **Customer Consent and Control:** Adopt blockchain or similar technologies to give customers visibility and control over their digital twin data[1][10].\n- **Ethical and Responsible AI:** Embed fairness, accountability, and privacy by design in all DToC processes[6].\n\n**UK Implementations and Organisations:**\n\n- **National Digital Twin Programme (NDTp):** Led by the Centre for Digital Built Britain, this initiative is expanding from infrastructure to include DToC concepts for public services and smart cities.\n- **Digital Catapult:** Supports UK businesses in adopting DToC, focusing on manufacturing, retail, and health sectors.\n- **Retail and Banking:** Major UK retailers and banks are piloting DToC for hyper-personalised marketing, risk assessment, and customer journey optimisation, often in partnership with AI and cloud providers[5].\n\n**Summary Table: Key Elements for DToC (2024–2025)**\n\n| Element                 | Description/Example                                           | UK Relevance/Implementation                |\n|-------------------------|--------------------------------------------------------------|--------------------------------------------|\n| AI/ML Integration       | Predictive analytics, personalisation, conversational UX     | Used by UK retailers, banks, NHS pilots    |\n| IoT Data Fusion         | Real-time synchronisation from devices, apps, transactions   | Smart city and public sector pilots        |\n| AI TRiSM Framework      | Trust, risk, security, explainability for AI systems         | Required for GDPR compliance               |\n| Blockchain              | Data sovereignty, consent management                         | Pilots in finance and health               |\n| Cloud Platforms         | Azure, AWS, Siemens Xcelerator                              | Adopted by UK enterprises                  |\n| Open Standards          | Digital Twin Consortium, ISO/IEC 30182                       | Referenced in UK government projects       |\n\n**In summary:** DToC in 2024–2025 is defined by AI-driven personalisation, real-time data integration, robust governance (AI TRiSM), and a strong focus on privacy and ethical use, with the UK actively piloting and adopting these frameworks in both public and private sectors[1][2][3][5][6][10].\n\n\n## UK Context and Implementations\n\nThere are currently no widely publicised, large-scale UK implementations of a full **Digital Twin of the Customer (DToC)**—defined as a dynamic, real-time digital representation of an individual customer, integrating behavioural, transactional, and contextual data—at the scale seen in sectors like infrastructure or manufacturing. However, several UK organisations, universities, and government-backed projects are actively developing and piloting DToC concepts, particularly in sectors such as retail, healthcare, and smart cities, with notable activity in London, Manchester, Leeds, Newcastle, and Sheffield.\n\n**Key UK Examples and Case Studies (2024–2025):**\n\n**1. London**\n- **National Digital Twin Programme & Digital Twin Hub**: The Centre for Digital Built Britain (CDBB) and the Digital Twin Hub, both based in London, have laid the groundwork for national digital twin initiatives. While their primary focus is infrastructure, their frameworks are being adapted for customer-centric applications, especially in public services and utilities, where customer behaviour and feedback are integrated into digital models for service optimisation[1].\n- **Retail and Financial Services**: London-based companies in retail and banking are piloting DToC approaches for hyper-personalised marketing and customer journey mapping, leveraging AI and behavioural analytics. For example, major UK banks and retailers are using digital twins to simulate customer interactions and predict service needs, though specific company names are not detailed in public sources[13].\n\n**2. Manchester**\n- **Made Smarter Innovation (MSI) North West Pilot**: Manchester is a hub for the Made Smarter Innovation programme, which supports digital twin adoption in manufacturing. Several local manufacturers are piloting DToC concepts to model customer usage patterns and feedback loops for product improvement, with support from the University of Manchester and the Greater Manchester Combined Authority[9].\n- **Smart City Initiatives**: Manchester’s smart city projects are integrating digital twins of citizens (anonymised) to optimise public transport and energy systems, using aggregated customer data to simulate demand and improve service delivery[1].\n\n**3. Leeds**\n- **Leeds Institute for Data Analytics (LIDA), University of Leeds**: LIDA is collaborating with local NHS trusts and city authorities to develop digital twins that model patient journeys and citizen interactions with health and social care services. These projects use real-time data to personalise care pathways and predict service demand, effectively creating a DToC for healthcare[1].\n- **Retail Analytics**: Leeds-based tech firms are working with national retailers to build digital twins of customer segments, using transaction and loyalty data to simulate responses to new products and promotions[13].\n\n**4. Newcastle**\n- **Urban Observatory, Newcastle University**: The Urban Observatory is the UK’s largest set of publicly available real-time urban data. It supports digital twin projects that model citizen movement and behaviour in Newcastle, with applications in transport, energy, and public health. These models are increasingly granular, approaching the DToC concept for city services[1].\n- **Healthcare Pilots**: Newcastle hospitals are involved in NHS digital twin pilots, using patient data to create digital representations for personalised medicine and care management.\n\n**5. Sheffield**\n- **Advanced Manufacturing Research Centre (AMRC), University of Sheffield**: The AMRC is piloting digital twin technologies in advanced manufacturing, including customer feedback integration for rapid product iteration. While not a pure DToC, these projects are moving towards customer-centric digital twins by linking product usage data with customer profiles[9].\n- **Smart Energy Projects**: Sheffield City Council is exploring digital twins of households (as proxies for customers) to optimise energy distribution and demand response in partnership with local utilities.\n\n**Government and National Projects**\n- **Cabinet Office Digital Platform (2025)**: The Cabinet Office launched a central digital platform in February 2025, supporting over 13,000 suppliers and 19,000 learners. While focused on procurement, the platform incorporates elements of DToC by tracking supplier and user behaviour to personalise services and training[2].\n- **National Health Service (NHS) Digital Twins**: NHS England is piloting digital twins for patient care management, integrating electronic health records, wearable data, and service usage to create dynamic patient profiles—effectively a DToC in healthcare[1].\n\n**Universities and Research Centres**\n- **University of Manchester**: Active in smart city and manufacturing DToC pilots.\n- **University of Leeds (LIDA)**: Leading in health and social care DToC research.\n- **Newcastle University (Urban Observatory)**: Pioneering city-scale digital twins with citizen-centric modelling.\n- **University of Sheffield (AMRC)**: Integrating customer feedback into manufacturing digital twins.\n\n**Companies**\n- **Large UK retailers and banks** (London, Leeds): Using DToC for personalisation and predictive analytics[13].\n- **Manufacturers in Manchester and Sheffield**: Piloting DToC for product improvement and customer engagement[9].\n\n**Sectoral Focus and Trends**\n- **Healthcare**: Fastest-growing sector for DToC, with NHS pilots in Leeds and Newcastle[1].\n- **Retail and Financial Services**: London and Leeds are leading in customer journey digital twins for marketing and service optimisation[13].\n- **Smart Cities**: Manchester and Newcastle are integrating DToC concepts in transport and energy management[1].\n\n**Summary Table: UK DToC Implementations (2024–2025)**\n\n| City        | Organisation/Project                  | Sector         | DToC Application/Focus                          |\n|-------------|--------------------------------------|----------------|------------------------------------------------|\n| London      | Digital Twin Hub, Retail/Banking     | Infrastructure, Retail | Customer journey, service optimisation      |\n| Manchester  | Made Smarter Innovation, Smart City  | Manufacturing, Urban | Product feedback, citizen behaviour modelling |\n| Leeds       | LIDA, NHS Trusts                     | Healthcare, Retail | Patient journey, retail analytics           |\n| Newcastle   | Urban Observatory, NHS Pilots        | Urban, Healthcare | Citizen movement, patient care              |\n| Sheffield   | AMRC, Smart Energy                   | Manufacturing, Energy | Product iteration, household energy twins   |\n\n**Limitations and Gaps**\n- Most UK DToC implementations are in pilot or early adoption stages, with full-scale, real-time, individual-level DToC rare outside healthcare and retail.\n- Publicly available, detailed case studies are limited due to commercial sensitivity and data privacy concerns.\n\n**References:**  \n[1] Institution of Civil Engineers (ICE)  \n[2] UK Government Cabinet Office Programme Reports  \n[9] UKRI Made Smarter Innovation Evaluation  \n[13] AI in Marketing 2025 Research Report\n\nIf you require more granular detail on a specific city, sector, or organisation, please specify for a deeper dive.\n\n\n## Research, Tools and Platforms\n\nThe latest (2024–2025) academic research, tools, and platforms related to the **Digital Twin of the Customer (DToC)** focus on integrating AI, real-time analytics, and personalisation to create dynamic, data-driven virtual representations of individual customers. This area is rapidly evolving, with significant developments in both academic research and commercial offerings.\n\n**Recent Academic Research (2024–2025):**\n- Research in 2025 highlights the integration of **AI-augmented predictive analytics** with digital twins, particularly for supply chain and customer behaviour modelling. These studies demonstrate how machine learning models, when combined with digital twins, can optimise inventory, personalise recommendations, and enhance resilience by simulating customer interactions and preferences[3].\n- The **International Journal of Science and Research Archive (2025)** discusses the use of digital twins for predictive accuracy in customer-centric logistics and inventory management, emphasising the value of real-time data and AI for modelling customer demand and behaviour[3].\n- Broader digital twin research in 2025 also explores the use of **sentiment analysis and emotional AI** to enrich customer digital twins, enabling more empathetic and personalised customer experiences[2].\n\n**Open-Source Tools and Platforms:**\n- While most digital twin platforms are industry-focused, open-source frameworks such as **Eclipse Ditto** and **FIWARE** are being adapted for customer digital twins, allowing organisations to build custom DToC solutions by integrating IoT, AI, and customer data streams.\n- AI libraries (e.g., **TensorFlow**, **PyTorch**) are commonly used for the machine learning components of DToC, particularly for behaviour prediction and personalisation modules[3].\n\n**Commercial Platforms (2024–2025):**\n- **Siemens Xcelerator** and **NVIDIA Omniverse** are leading platforms supporting digital twin development, with increasing capabilities for modelling not just physical assets but also customer journeys and experiences through integration with CRM and analytics systems[1][2].\n- **Microsoft Azure Digital Twins** and **IBM Digital Twin Exchange** are expanding their offerings to include customer-centric modules, leveraging cloud-based analytics, AI, and real-time data ingestion for DToC applications[1].\n- **SAP Digital Twin** and **PTC ThingWorx** are also notable, with recent updates focusing on customer experience optimisation and integration with enterprise data[1].\n\n**Novel Approaches and Trends:**\n- **Cognitive Digital Twins**: The next generation of digital twins incorporates cognitive capabilities, using AI to simulate not just customer actions but also intentions, preferences, and emotional states, enabling hyper-personalised marketing and service delivery[1][2].\n- **Sentimental AI**: Advanced sentiment analysis is being integrated into DToC to interpret and respond to customer emotions in real time, improving engagement and loyalty[2].\n- **Agentic AI**: Platforms are moving towards autonomous, agent-based digital twins that can act on behalf of customers, making decisions and interacting with services independently[2][9].\n- **VR/AR Integration**: Immersive technologies are being used to visualise and interact with customer digital twins, supporting applications in retail, healthcare, and smart cities[1].\n- **Cloud-Based Scalability**: Cloud-native DToC platforms enable real-time, large-scale deployment and integration with enterprise systems, supporting rapid personalisation and analytics[1][9].\n\n**Key Publications and Reports:**\n- **Spherical Insights (2025)**: Market research identifies the top companies and trends in digital twins, including the shift towards customer-centric applications and the integration of AI, IoT, and cloud technologies[1].\n- **McKinsey Technology Trends Outlook 2025**: Highlights the rise of agentic AI and digital twins as transformative trends, with implications for customer modelling and engagement[9].\n- **Digital Economy Trends 2025 (DCO)**: Discusses the broader impact of digital twins on digital transformation, including customer experience and personalisation[6].\n\n**UK Context:**\n- UK organisations are actively adopting digital twin technologies for customer experience, particularly in retail, financial services, and healthcare, leveraging government and industry initiatives to drive innovation and interoperability.\n\n**Summary Table: Digital Twin of the Customer (2024–2025)**\n\n| Category           | Example Tools/Platforms                | Key Features/Trends                                    | Source      |\n|--------------------|----------------------------------------|--------------------------------------------------------|-------------|\n| Academic Research  | IJSRA (2025), sentiment analysis AI    | AI-augmented analytics, predictive modelling           | [3][2]      |\n| Open-Source Tools  | Eclipse Ditto, FIWARE, TensorFlow      | Custom DToC, IoT/AI integration                        | [3]         |\n| Commercial         | Siemens Xcelerator, NVIDIA Omniverse,  | Customer journey modelling, real-time analytics        | [1][2]      |\n| Platforms          | Microsoft Azure Digital Twins, IBM     | Cloud-based, CRM integration, personalisation          | [1]         |\n| Novel Approaches   | Cognitive twins, agentic AI, VR/AR     | Emotional modelling, autonomous agents, immersive UX   | [1][2][9]   |\n\nFor the most up-to-date academic papers, search databases such as IEEE Xplore, ACM Digital Library, and ScienceDirect using terms like \"Digital Twin of the Customer,\" \"customer digital twin,\" and \"AI-driven personalisation 2024–2025.\" Most recent research focuses on AI integration, real-time analytics, and emotional intelligence in digital twins for customer-centric applications[3][2][9].\n\n\n## References\n\n### 2024–2025 Sources\n\n1. https://www.sphericalinsights.com/blogs/top-20-companies-in-digital-twin-market-in-the-world-in-2025-market-research-report-2024-2035\n\n2. https://appinventiv.com/blog/ai-trends/\n\n3. https://www.aufaitux.com/blog/ux-digital-twins-smart-interface-strategies/\n\n4. https://docshipper.com/logistics/ai-changing-logistics-supply-chain-2025/\n\n5. https://blog.bismart.com/en/digital-twin-revolution\n\n6. https://www.simplilearn.com/top-technology-trends-and-jobs-article\n\n7. https://market.us/report/digital-twins-in-power-market/\n\n8. https://www.tataconsultingengineers.com/wp-content/uploads/2025/03/24.-TCExpressions-2024-Vol-61-Issue-2.pdf\n\n9. https://www.mckinsey.com/~/media/mckinsey/business%20functions/mckinsey%20digital/our%20insights/the%20top%20trends%20in%20tech%202025/mckinsey-technology-trends-outlook-2025.pdf\n\n10. https://dco.org/wp-content/uploads/2024/12/Digital-Economy-Trends-2025.pdf\n\n11. https://www.coherentsolutions.com/insights/the-future-and-current-trends-in-data-analytics-across-industries\n\n12. https://www.deloitte.com/us/en/services/consulting/blogs/ai-adoption-challenges-ai-trends.html\n\n13. https://www.pwc.com/us/en/services/consulting/business-transformation/digital-supply-chain-survey.html\n\n14. https://www.ey.com/en_us/megatrends/how-emerging-technologies-are-enabling-the-human-machine-hybrid-economy\n\n15. https://www.deloitte.com/us/en/insights/focus/tech-trends/2025/tech-trends-future-of-spatial-computing.html\n\n16. https://www.capgemini.com/dk-en/wp-content/uploads/sites/7/2025/01/Top-Tech-Trends-2025_Report.pdf\n\n17. https://www.consegicbusinessintelligence.com/digital-twin-market\n\n18. https://www.gminsights.com/industry-analysis/digital-twin-in-automotive-market\n\n19. https://www.ice.org.uk/news-views-insights/inside-infrastructure/insights-into-digitally-retrofitting-infrastructure\n\n20. https://assets.publishing.service.gov.uk/media/6895fbb63080e72710b2e2ef/nista_annual_report_data_2425.csv\n\n21. https://www.consegicbusinessintelligence.com/digital-twin-market\n\n22. https://www.rcp.ac.uk/media/5r2kmmi4/rcp-full-report-a-breath-of-fresh-air-responding-to-the-health-challenges-of-modern-air-pollution.pdf\n\n23. https://ff.co/ai-statistics-trends-global-market/\n\n24. https://www.thepwi.org/wp-content/uploads/2025/10/The-PWI_The-Journal_October-2025_Vol-143_Part-4_Digital.pdf\n\n25. https://www.gov.uk/government/publications/the-wider-economic-impacts-of-emerging-technologies-in-the-uk/the-wider-economic-impacts-of-emerging-technologies-in-the-uk-html\n\n26. https://fulbright.org.uk/our-community/meet-our-grantees/\n\n27. https://www.ukri.org/wp-content/uploads/2025/05/IUK-300525-EvaluationMadeSmarterInnovationChallenge-FinalEvaluationAnnexReport.pdf\n\n28. https://www.asanet.org/wp-content/uploads/2025/06/ASA-2025.pdf\n\n29. https://www.mckinsey.com/~/media/mckinsey/business%20functions/mckinsey%20digital/our%20insights/the%20top%20trends%20in%20tech%202025/mckinsey-technology-trends-outlook-2025.pdf\n\n30. https://www.visionsafe.com/recent-smoke-in-the-cockpit-events/\n\n31. https://blog.whitehat-seo.co.uk/ai-in-marketing-2025-research-report\n\n32. https://conference.astro.dur.ac.uk/event/7/timetable/?view=standard_numbered_inline_minutes\n\n33. https://www.statista.com/topics/9847/digital-twin/\n\n34. https://www.icorr.org/wp-content/uploads/2025/03/CORROSION_MANAGEMENT_Issue183_48-pgs_LowRes.pdf\n\n35. https://dco.org/wp-content/uploads/2024/12/Digital-Economy-Trends-2025.pdf\n\n36. https://www.sphericalinsights.com/blogs/top-20-companies-in-digital-twin-market-in-the-world-in-2025-market-research-report-2024-2035\n\n37. https://appinventiv.com/blog/ai-trends/\n\n38. https://journalijsra.com/sites/default/files/fulltext_pdf/IJSRA-2025-2430.pdf\n\n39. https://pmc.ncbi.nlm.nih.gov/articles/PMC12071628/\n\n40. https://market.us/report/digital-twins-in-power-market/\n\n41. https://dco.org/wp-content/uploads/2024/12/Digital-Economy-Trends-2025.pdf\n\n42. https://coladv.com/wp-content/uploads/Digital-Twins-Whitepaper-Winter-2025.pdf\n\n43. https://www.tataconsultingengineers.com/wp-content/uploads/2025/03/24.-TCExpressions-2024-Vol-61-Issue-2.pdf\n\n44. https://www.mckinsey.com/~/media/mckinsey/business%20functions/mckinsey%20digital/our%20insights/the%20top%20trends%20in%20tech%202025/mckinsey-technology-trends-outlook-2025.pdf\n\n\n## Metadata\n\n- **Last Updated**: 2025-11-22\n- **Enhancement**: Perplexity API research (44 citations from 2024–2025)\n- **Regional Context**: UK implementations and case studies included\n- **Verification**: Citations from authoritative sources",
  "backlinks": [],
  "wiki_links": [
    "MetaverseDomain"
  ],
  "ontology": {
    "term_id": "ME-0013",
    "preferred_term": "Digital Twin of the Customer",
    "alt_terms": [],
    "iri": "http://narrativegoldmine.com/metaverse#DigitalTwinoftheCustomer",
    "source_domain": "metaverse",
    "domain": "metaverse",
    "domain_full_name": "",
    "definition": null,
    "scope_note": null,
    "status": "emerging",
    "maturity": "emerging",
    "version": null,
    "public_access": true,
    "last_updated": null,
    "authority_score": null,
    "quality_score": null,
    "cross_domain_links": null,
    "owl_class": "mv:DigitalTwinoftheCustomer",
    "owl_physicality": "ConceptualEntity",
    "owl_role": "Concept",
    "owl_inferred_class": null,
    "is_subclass_of": [],
    "has_part": [],
    "is_part_of": [],
    "requires": [],
    "depends_on": [],
    "enables": [],
    "relates_to": [],
    "bridges_to": [],
    "bridges_from": [],
    "domain_extensions": {},
    "belongs_to_domain": [
      "MetaverseDomain"
    ],
    "implemented_in_layer": [],
    "source": [],
    "validation": {
      "is_valid": false,
      "errors": [
        "Missing required property: last-updated",
        "Missing required property: definition",
        "Missing required property: is-subclass-of (at least one parent class)",
        "owl:class namespace 'mv' doesn't match source-domain 'metaverse'"
      ]
    }
  }
}