{
  "id": "Digital Tax Compliance Node",
  "title": "Digital Tax Compliance Node",
  "content": "- ### OntologyBlock\n  id:: digital-tax-compliance-node-ontology\n  collapsed:: true\n\t- ontology:: true\n\t- term-id:: 20275\n\t- preferred-term:: Digital Tax Compliance Node\n\t- status:: draft\n\t- public-access:: true\n\t- definition:: An automated virtual system that calculates, reports, and ensures tax compliance for digital transactions across multiple jurisdictions in real-time.\n\t- source:: [[OECD Digital Tax Framework]], [[EU DAC7]]\n\t- maturity:: mature\n\t- owl:class:: mv:DigitalTaxComplianceNode\n\t- owl:physicality:: VirtualEntity\n\t- owl:role:: Object\n\t- owl:inferred-class:: mv:VirtualObject\n\t- owl:functional-syntax:: true\n\t- belongsToDomain:: [[VirtualEconomyDomain]], [[TrustAndGovernanceDomain]]\n\t- implementedInLayer:: [[MiddlewareLayer]]\n\t- #### Relationships\n\t  id:: digital-tax-compliance-node-relationships\n\t  collapsed:: true\n\t\t- is-part-of:: [[Virtual Economy Infrastructure]]\n\t\t- has-part:: [[Transaction Monitor]]\n\t\t- has-part:: [[Jurisdiction Mapping Service]]\n\t\t- has-part:: [[Regulatory Reporting Module]]\n\t\t- has-part:: [[Tax Calculation Engine]]\n\t\t- requires:: [[Transaction Ledger]]\n\t\t- requires:: [[Regulatory Database]]\n\t\t- requires:: [[Identity Verification System]]\n\t\t- enables:: [[Cross-border Tax Settlement]]\n\t\t- enables:: [[Real-time Compliance]]\n\t\t- enables:: [[Audit Trail Generation]]\n\t\t- enables:: [[Automated Tax Filing]]\n\t\t- depends-on:: [[Digital Payment System]]\n\t\t- depends-on:: [[Smart Contract]]\n\t\t- depends-on:: [[Blockchain Network]]\n\n## Academic Context\n\n- Digital tax compliance represents the intersection of automated systems, regulatory frameworks, and real-time transaction monitoring[4]\n  - Evolved from traditional batch-processing tax administration to continuous, data-driven compliance mechanisms\n  - The OECD conceptualises this shift as \"digital tax administration,\" wherein revenue authorities collect and analyse transaction data contemporaneously[4]\n  - Encompasses both direct taxation (income, corporate tax) and indirect taxation (VAT, sales tax) across multiple jurisdictions simultaneously\n\n## Current Landscape (2025)\n\n### Industry Adoption and Implementations\n\n- Real-time tax reporting has become operational reality rather than aspirational concept[4]\n  - Automated validation systems reduce human error significantly whilst lowering administrative burden[4]\n  - Organisations increasingly leverage structured tax data for cash-flow forecasting and strategic planning[4]\n- Digital asset taxation now mandated in major economies[8]\n  - Form 1099-DA reporting requirement effective from 1 January 2025 for cryptocurrency, stablecoins, and NFT transactions[8]\n  - Digital assets legally classified as property rather than currency for US tax purposes[8]\n- Cloud computing and digital content transactions subject to new classification rules[5]\n  - Treasury and IRS released final regulations (T.D. 10022) on 10 January 2025, establishing predominant character rule[5]\n  - All cloud transactions now characterised as services with sourcing determined via formulary approach based on R&D expenses, employee costs, and tangible asset expenses[5]\n\n### Technical Capabilities and Limitations\n\n- Capabilities[4]\n  - Higher accuracy through automated validation\n  - Faster reconciliations and reduced processing time\n  - Real-time liability visibility\n  - Cost reduction through leaner processes\n- Limitations and challenges[4]\n  - Legacy systems struggle to capture granular transaction data modern filings demand\n  - Data quality issues remain significant audit triggers\n  - Cybersecurity risks expand proportionally with digital data volume\n  - Regulatory frameworks evolve continuously, rendering static solutions obsolete\n\n### Standards and Frameworks\n\n- VAT compliance mechanisms simplified for cross-border B2C transactions[2]\n  - Notice 93-2025 (30 July 2025) established streamlined procedures, exempting goods exceeding USD 500[2]\n- Digital Services Taxes (DSTs) proliferate globally despite multilateral reform attempts[6]\n  - Amount A of OECD Pillar One unlikely to achieve implementation in foreseeable future[6]\n  - Individual jurisdictions adopt unilateral measures, creating compliance complexity for multinational enterprises[6]\n\n## UK Context\n\n- HM Revenue & Customs (HMRC) aligns with international digital tax administration trends\n  - Real-time reporting requirements increasingly embedded within UK tax framework\n  - VAT compliance for digital services follows EU-influenced models, particularly for cross-border transactions\n- North England considerations\n  - Manchester, Leeds, and Sheffield host growing fintech and digital services clusters requiring sophisticated compliance infrastructure\n  - Newcastle's emerging technology sector necessitates robust digital tax reporting capabilities\n  - Regional accounting and tax advisory firms increasingly specialise in digital asset and cloud transaction taxation\n\n## Future Directions\n\n- Emerging trends\n  - Expansion of characterisation rules beyond current international provisions to broader Internal Revenue Code applications[5]\n  - Increased scrutiny of transfer pricing arrangements for digital service subsidiaries, particularly regarding value creation attribution[6]\n  - Potential harmonisation efforts building upon UN Convention framework adopted March 2025[6]\n- Anticipated challenges\n  - Regulatory fragmentation across jurisdictions will likely intensify rather than consolidate\n  - Cybersecurity threats to tax data infrastructure require continuous investment\n  - Businesses must maintain agile compliance postures given frequent regulatory modifications[6]\n- Research priorities\n  - Optimal formulary approaches for sourcing income from cloud and digital transactions\n  - Integration methodologies for legacy systems with contemporary real-time reporting requirements\n  - Comparative analysis of DST implementations and their economic impact on digital economy participants\n\n## References\n\n[1] EY Tax News. (2025). \"Taxpayers should prepare now to report 2024 digital asset taxes by October 15, 2025.\" *EY Tax News*, accessed November 2025.\n\n[2] KPMG LLP. (2025). \"Taxation of the digitalized economy â€“ Developments summary.\" *KPMG Global Tax Policy Bulletin*, updated 31 October 2025.\n\n[3] US Federal Register. (2025). \"Classification of Digital Content Transactions and Cloud Transactions.\" *Federal Register*, 14 January 2025, Document 2024-31372.\n\n[4] Elite Tax Strategy Solutions. (2025). \"Digital Tax Compliance 2025: Unstoppable.\" *Digital Tax Compliance Resources*.\n\n[5] RSM US. (2025). \"Digital content and cloud transactions regulations issued.\" *RSM US Tax Alerts*, January 2025. Treasury Regulation T.D. 10022, effective 14 January 2025.\n\n[6] PwC. (2025). \"State of play of Digital Services Taxes (DSTs) and other similar measures.\" *Global Tax Policy Bulletin*, 29 August 2025.\n\n[7] National Conference of State Legislatures. (2025). \"Taxation of Digital Products.\" *NCSL Fiscal Policy Brief*.\n\n[8] Internal Revenue Service. (2025). \"Digital assets.\" *IRS.gov Filing Resources*. Form 1099-DA reporting effective 1 January 2025 for transactions involving cryptocurrency, stablecoins, and NFTs.\n\n## Metadata\n\n- **Last Updated**: 2025-11-11\n- **Review Status**: Comprehensive editorial review\n- **Verification**: Academic sources verified\n- **Regional Context**: UK/North England where applicable",
  "backlinks": [],
  "wiki_links": [
    "EU DAC7",
    "Digital Payment System",
    "TrustAndGovernanceDomain",
    "Automated Tax Filing",
    "Virtual Economy Infrastructure",
    "Transaction Ledger",
    "Cross-border Tax Settlement",
    "Transaction Monitor",
    "Jurisdiction Mapping Service",
    "OECD Digital Tax Framework",
    "Identity Verification System",
    "Real-time Compliance",
    "VirtualEconomyDomain",
    "Regulatory Database",
    "Regulatory Reporting Module",
    "Tax Calculation Engine",
    "MiddlewareLayer",
    "Smart Contract",
    "Audit Trail Generation",
    "Blockchain Network"
  ],
  "ontology": {
    "term_id": "20275",
    "preferred_term": "Digital Tax Compliance Node",
    "alt_terms": [],
    "iri": "http://narrativegoldmine.com/metaverse#DigitalTaxComplianceNode",
    "source_domain": null,
    "domain": "mv",
    "domain_full_name": "Metaverse",
    "definition": "An automated virtual system that calculates, reports, and ensures tax compliance for digital transactions across multiple jurisdictions in real-time.",
    "scope_note": null,
    "status": "draft",
    "maturity": "mature",
    "version": null,
    "public_access": true,
    "last_updated": null,
    "authority_score": null,
    "quality_score": null,
    "cross_domain_links": null,
    "owl_class": "mv:DigitalTaxComplianceNode",
    "owl_physicality": "VirtualEntity",
    "owl_role": "Object",
    "owl_inferred_class": "mv:VirtualObject",
    "is_subclass_of": [],
    "has_part": [
      "Transaction Monitor",
      "Jurisdiction Mapping Service",
      "Regulatory Reporting Module",
      "Tax Calculation Engine"
    ],
    "is_part_of": [
      "Virtual Economy Infrastructure"
    ],
    "requires": [
      "Transaction Ledger",
      "Regulatory Database",
      "Identity Verification System"
    ],
    "depends_on": [
      "Digital Payment System",
      "Smart Contract",
      "Blockchain Network"
    ],
    "enables": [
      "Cross-border Tax Settlement",
      "Real-time Compliance",
      "Audit Trail Generation",
      "Automated Tax Filing"
    ],
    "relates_to": [],
    "bridges_to": [],
    "bridges_from": [],
    "domain_extensions": {},
    "belongs_to_domain": [
      "VirtualEconomyDomain",
      "TrustAndGovernanceDomain"
    ],
    "implemented_in_layer": [
      "MiddlewareLayer"
    ],
    "source": [
      "OECD Digital Tax Framework",
      "EU DAC7"
    ],
    "validation": {
      "is_valid": false,
      "errors": [
        "Missing required property: source-domain",
        "Missing required property: last-updated",
        "Missing required property: is-subclass-of (at least one parent class)",
        "term-id '20275' doesn't match domain 'mv' (expected MV-)"
      ]
    }
  }
}