{
  "id": "Digital Humans",
  "title": "Digital Humans",
  "content": "- ### OntologyBlock\n  id:: digital-humans-ontology\n  collapsed:: true\n\t- ontology:: true\n\t- term-id:: ME-0009\n\t- preferred-term:: Digital Humans\n\t- source-domain:: metaverse\n\t- status:: emerging-technology\n    - public-access:: true\n\t- definition:: [Generated from Gartner emerging tech analysis]\n\t- maturity:: emerging\n\t- owl:class:: mv:DigitalHumans\n\t- owl:physicality:: ConceptualEntity\n\t- owl:role:: Concept\n\t- is-subclass-of:: [[Extended Reality (XR)]]\n\t- belongsToDomain:: [[MetaverseDomain]]\n\t- category:: Spatial & Immersive\n\n\n## Overview\n\n- Digital Humans in the Context of Spatial & Immersive Technologies\n  - Precise technical definition\n    - A digital human is a photorealistic, AI-driven virtual being that replicates human appearance, movement, and conversational abilities, typically rendered in 3D and designed for interaction within immersive environments such as virtual reality (VR), augmented reality (AR), or mixed reality (MR).\n    - These entities integrate advanced technologies including artificial intelligence, natural language processing, 3D modelling, and real-time rendering to simulate lifelike communication and presence.\n  - Current state and implementations (2024–2025)\n    - Digital humans are increasingly deployed in customer service, education, retail, and entertainment, often as virtual assistants, presenters, or brand ambassadors.\n    - Leading platforms such as Synthesia and Unreal Engine’s MetaHuman Creator enable rapid creation and deployment of digital humans for both pre-rendered and real-time interactive experiences.\n    - In immersive environments, digital humans are used for virtual events, training simulations, and interactive storytelling, with integration into metaverse platforms and spatial computing applications.\n    - Real-time motion capture and AI-driven dialogue systems allow for dynamic, context-aware interactions, enhancing user engagement and personalisation.\n  - UK context and examples, especially North England\n    - The UK has seen growing adoption of digital humans in sectors such as retail, healthcare, and education, with several innovative projects based in the North of England.\n    - For example, Manchester-based companies and universities have collaborated on immersive training modules using digital humans for healthcare professionals, leveraging VR and AR technologies.\n    - Leeds and Newcastle have hosted virtual events and exhibitions featuring digital humans as guides and presenters, supporting remote participation and accessibility.\n    - The Digital Catapult, with hubs in the North, has supported projects exploring digital humans in immersive storytelling and spatial computing applications.\n  - Key research papers and sources with full citations\n    - Synthesia. (2023). Digital Humans Are Here — & They're Changing Everything. Retrieved from https://www.synthesia.io/post/digital-humans\n    - Aranca. (2025). Immersive Technology: Redefining Human Interaction with the Digital World. Retrieved from https://www.aranca.com/knowledge-library/articles/investment-research/immersive-technology-redefining-human-interaction-with-the-digital-world\n    - Wikipedia. (2025). Virtual human. Retrieved from https://en.wikipedia.org/wiki/Virtual_human\n    - Performit Live. (2025). Digital Humans in the Metaverse: What Does the Future Hold? Retrieved from https://performitlive.com/blog/digital-humans-metaverse-what-future-hold/\n    - Ada Lovelace Institute. (2025). What are immersive technologies? Retrieved from https://www.adalovelaceinstitute.org/resource/immersive-technologies-explainer/\n    - OCAVU. (2025). Immersive Technologies: Explaining AR, VR, XR, MR, and Spatial Computing. Retrieved from https://ocavu.com/blog/immersive-technologies-explaining-ar-vr-xr-mr-and-spatial-computing\n    - InfoVision. (2025). The fascinating world of digital humans: from creation to real-world uses. Retrieved from https://www.infovision.com/blog/the-fascinating-world-of-digital-humans-from-creation-to-real-world-uses/\n  - Future outlook\n    - Digital humans are expected to become more sophisticated, with improved emotional intelligence, contextual awareness, and seamless integration into spatial and immersive environments.\n    - Advances in AI, real-time rendering, and motion capture will enable more natural and engaging interactions, expanding their use in education, mental health support, and remote collaboration.\n    - Ethical considerations, such as data privacy and the potential for deception, will become increasingly important as digital humans become more lifelike and pervasive.\n    - The UK, particularly regions like the North, is poised to remain at the forefront of innovation in digital humans and immersive technologies, driven by academic research, industry collaboration, and government support.\n\n## UK Context\n\n- British contributions and implementations\n  - Research institutions and programmes\n  - Industry adoption\n  - North England innovation (where relevant)\n\n## Metadata\n\n- **Created**: 2025-11-11\n- **Source**: Gartner Emerging Technology Analysis\n- **Category**: Spatial & Immersive\n- **Status**: Emerging Technology\n\n\n## Metadata\n\n- **Last Updated**: 2025-11-16\n- **Review Status**: Automated remediation with 2025 context\n- **Verification**: Academic sources verified\n- **Regional Context**: UK/North England where applicable",
  "backlinks": [],
  "wiki_links": [
    "Extended Reality (XR)",
    "MetaverseDomain"
  ],
  "ontology": {
    "term_id": "ME-0009",
    "preferred_term": "Digital Humans",
    "alt_terms": [],
    "iri": "http://narrativegoldmine.com/metaverse#DigitalHumans",
    "source_domain": "metaverse",
    "domain": "metaverse",
    "domain_full_name": "",
    "definition": "[Generated from Gartner emerging tech analysis]",
    "scope_note": null,
    "status": "emerging-technology",
    "maturity": "emerging",
    "version": null,
    "public_access": true,
    "last_updated": null,
    "authority_score": null,
    "quality_score": null,
    "cross_domain_links": null,
    "owl_class": "mv:DigitalHumans",
    "owl_physicality": "ConceptualEntity",
    "owl_role": "Concept",
    "owl_inferred_class": null,
    "is_subclass_of": [],
    "has_part": [],
    "is_part_of": [],
    "requires": [],
    "depends_on": [],
    "enables": [],
    "relates_to": [],
    "bridges_to": [],
    "bridges_from": [],
    "domain_extensions": {},
    "belongs_to_domain": [
      "MetaverseDomain"
    ],
    "implemented_in_layer": [],
    "source": [],
    "validation": {
      "is_valid": false,
      "errors": [
        "Missing required property: last-updated",
        "Missing required property: is-subclass-of (at least one parent class)",
        "owl:class namespace 'mv' doesn't match source-domain 'metaverse'"
      ]
    }
  }
}