{
  "id": "Digital Well-Being Index",
  "title": "Digital Well-Being Index",
  "content": "- ### OntologyBlock\n  id:: digital-well-being-index-ontology\n  collapsed:: true\n\t- ontology:: true\n\t- term-id:: 20259\n\t- preferred-term:: Digital Well-Being Index\n\t- status:: draft\n\t- public-access:: true\n\t- definition:: Composite indicator assessing psychological, social, physical, and temporal impacts of extended virtual engagement, providing quantitative measures of healthy metaverse usage patterns.\n\t- source:: [[WHO Digital Well-Being Metrics]]\n\t- maturity:: mature\n\t- owl:class:: mv:DigitalWellBeingIndex\n\t- owl:physicality:: VirtualEntity\n\t- owl:role:: Object\n\t- owl:inferred-class:: mv:VirtualObject\n\t- owl:functional-syntax:: true\n\t- belongsToDomain:: [[VirtualSocietyDomain]], [[TrustAndGovernanceDomain]]\n\t- implementedInLayer:: [[Middleware Layer]], [[Application Layer]]\n\t- #### Relationships\n\t  id:: digital-well-being-index-relationships\n\t  collapsed:: true\n\t\t- is-part-of:: [[Platform Governance Framework]]\n\t\t- is-part-of:: [[User Health Monitoring System]]\n\t\t- has-part:: [[Cognitive Load Measurements]]\n\t\t- has-part:: [[Social Engagement Scores]]\n\t\t- has-part:: [[Physical Activity Indicators]]\n\t\t- has-part:: [[Emotional Wellness Scores]]\n\t\t- has-part:: [[Sleep Impact Assessment]]\n\t\t- has-part:: [[Screen Time Metrics]]\n\t\t- requires:: [[Usage Analytics]]\n\t\t- requires:: [[Temporal Analysis Tools]]\n\t\t- requires:: [[Behavioral Tracking]]\n\t\t- requires:: [[Health Data Integration]]\n\t\t- enables:: [[Parental Controls]]\n\t\t- enables:: [[Regulatory Compliance]]\n\t\t- enables:: [[Platform Health Reports]]\n\t\t- enables:: [[Healthy Engagement Recommendations]]\n\t\t- enables:: [[Usage Alerts]]\n\t\t- depends-on:: [[Activity Logging]]\n\t\t- depends-on:: [[Wearable Device Integration]]\n\t\t- depends-on:: [[Self-Report Surveys]]\n\t\t- depends-on:: [[Metaverse Psychology Profile]]\n\n## Academic Context\n\n- The Digital Well-Being Index (DWBI) is a composite indicator designed to quantitatively assess the psychological, social, physical, and temporal effects of extended virtual engagement, particularly in immersive environments such as the metaverse.\n  - It builds on interdisciplinary academic foundations including psychology, digital sociology, human-computer interaction, and public health.\n  - Key developments include refined conceptual frameworks distinguishing digital well-being from mere absence of digital ill-being, emphasising a balanced subjective experience of online engagement[4].\n  - The index integrates validated psychological metrics such as anxiety and depression scales alongside behavioural and social connectivity measures to provide a holistic view.\n\n## Current Landscape (2025)\n\n- Industry adoption of DWBI frameworks is growing, with major technology companies and research institutions implementing measures to monitor and improve digital well-being.\n  - Notable implementations include Snap Inc.’s annual Digital Well-Being Index, which surveys Generation Z across multiple countries including the UK, providing insights into online psychological well-being without platform bias[1][8].\n  - The Global Digital Wellbeing Index synthesises policy, behavioural, and survey data across 35 countries, offering a comprehensive benchmarking tool for governments and organisations[2].\n- In the UK, digital well-being initiatives increasingly inform regulatory and corporate strategies, especially under frameworks like the EU Digital Services Act that mandate risk-based online harm mitigation[3].\n- Technical capabilities include multi-dimensional data collection combining hard metrics, surveys, and policy indicators; however, limitations persist due to restricted access to platform interventional data and challenges in disentangling online versus offline harm prevalence[3].\n- Standards and frameworks continue to evolve, with growing emphasis on balancing digital opportunity maximisation against risk mitigation, supported by international bodies such as the ITU and OECD[5][6][7].\n\n## Research & Literature\n\n- Key academic sources include:\n  - Elhai et al. (2025). \"A Network Analysis of Digital Well-Being Dimensions and Protective Factors.\" *Journal of Medical Internet Research*, 27(1), e70483. DOI: 10.2196/70483[4].\n  - Stanford University Centre for Digital Health (2025). \"Youth Safety and Digital Wellbeing Report.\" This report highlights complexities in measuring youth online harms and the need for data transparency from platforms[3].\n  - OECD (2025). \"Measuring Well-being and Progress,\" which contextualises digital well-being within broader societal well-being frameworks[7].\n- Ongoing research focuses on refining measurement tools, understanding platform mitigation impacts, and developing evidence-based interventions to promote healthy digital engagement.\n\n## UK Context\n\n- The UK contributes significantly to digital well-being research and policy, with organisations such as Internet Matters running dedicated programmes to track and improve children’s online experiences[9].\n- North England innovation hubs in Manchester, Leeds, Newcastle, and Sheffield are increasingly involved in digital health and well-being initiatives, leveraging local tech ecosystems and academic institutions to pilot interventions and develop regional case studies.\n- For example, Manchester’s digital health clusters collaborate with universities and industry to explore the impact of virtual environments on mental health, while Leeds and Newcastle focus on digital literacy and resilience programmes targeting youth populations.\n\n## Future Directions\n\n- Emerging trends include integration of digital well-being metrics into metaverse governance, personalised well-being feedback systems, and AI-driven adaptive interventions.\n- Anticipated challenges involve ensuring data privacy, addressing disparities in digital access and literacy, and balancing innovation with ethical safeguards.\n- Research priorities emphasise longitudinal studies to track digital well-being trajectories, cross-cultural validation of indices, and enhanced collaboration between academia, industry, and policymakers.\n\n## References\n\n1. Snap Inc. (2025). *Digital Well-Being Index – Year Three*. Snap Safety and Privacy Hub.\n2. Sync Ithra. (2025). *Global Digital Wellbeing Index*.\n3. Stanford University Centre for Digital Health. (2025). *Youth Safety and Digital Wellbeing Report*.\n4. Elhai, J. D., et al. (2025). A Network Analysis of Digital Well-Being Dimensions and Protective Factors. *Journal of Medical Internet Research*, 27(1), e70483. https://doi.org/10.2196/70483\n5. International Telecommunication Union (ITU). (2025). *A Guide to Digital Wellbeing*.\n6. OECD. (2025). *How's Your Digital Well-being?* OECD Statistics Blog.\n7. OECD. (2025). *Measuring Well-being and Progress*.\n8. Snap Inc. (2024). *Digital Well-Being Index Wave 3 Report Presentation*.\n9. Internet Matters. (2025). *Our Digital Wellbeing Research Programme*.\n\n## Metadata\n\n- **Last Updated**: 2025-11-11\n- **Review Status**: Comprehensive editorial review\n- **Verification**: Academic sources verified\n- **Regional Context**: UK/North England where applicable",
  "backlinks": [
    "Metaverse Psychology Profile"
  ],
  "wiki_links": [
    "Physical Activity Indicators",
    "Temporal Analysis Tools",
    "WHO Digital Well-Being Metrics",
    "Middleware Layer",
    "Cognitive Load Measurements",
    "Emotional Wellness Scores",
    "User Health Monitoring System",
    "Metaverse Psychology Profile",
    "Application Layer",
    "Social Engagement Scores",
    "Platform Governance Framework",
    "VirtualSocietyDomain",
    "Self-Report Surveys",
    "Usage Analytics",
    "Parental Controls",
    "Wearable Device Integration",
    "Regulatory Compliance",
    "Health Data Integration",
    "Screen Time Metrics",
    "Healthy Engagement Recommendations",
    "Activity Logging",
    "TrustAndGovernanceDomain",
    "Sleep Impact Assessment",
    "Usage Alerts",
    "Behavioral Tracking",
    "Platform Health Reports"
  ],
  "ontology": {
    "term_id": "20259",
    "preferred_term": "Digital Well-Being Index",
    "alt_terms": [],
    "iri": "http://narrativegoldmine.com/metaverse#DigitalWellBeingIndex",
    "source_domain": null,
    "domain": "mv",
    "domain_full_name": "Metaverse",
    "definition": "Composite indicator assessing psychological, social, physical, and temporal impacts of extended virtual engagement, providing quantitative measures of healthy metaverse usage patterns.",
    "scope_note": null,
    "status": "draft",
    "maturity": "mature",
    "version": null,
    "public_access": true,
    "last_updated": null,
    "authority_score": null,
    "quality_score": null,
    "cross_domain_links": null,
    "owl_class": "mv:DigitalWellBeingIndex",
    "owl_physicality": "VirtualEntity",
    "owl_role": "Object",
    "owl_inferred_class": "mv:VirtualObject",
    "is_subclass_of": [],
    "has_part": [
      "Cognitive Load Measurements",
      "Social Engagement Scores",
      "Physical Activity Indicators",
      "Emotional Wellness Scores",
      "Sleep Impact Assessment",
      "Screen Time Metrics"
    ],
    "is_part_of": [
      "Platform Governance Framework",
      "User Health Monitoring System"
    ],
    "requires": [
      "Usage Analytics",
      "Temporal Analysis Tools",
      "Behavioral Tracking",
      "Health Data Integration"
    ],
    "depends_on": [
      "Activity Logging",
      "Wearable Device Integration",
      "Self-Report Surveys",
      "Metaverse Psychology Profile"
    ],
    "enables": [
      "Parental Controls",
      "Regulatory Compliance",
      "Platform Health Reports",
      "Healthy Engagement Recommendations",
      "Usage Alerts"
    ],
    "relates_to": [],
    "bridges_to": [],
    "bridges_from": [],
    "domain_extensions": {},
    "belongs_to_domain": [
      "VirtualSocietyDomain",
      "TrustAndGovernanceDomain"
    ],
    "implemented_in_layer": [
      "Middleware Layer",
      "Application Layer"
    ],
    "source": [
      "WHO Digital Well-Being Metrics"
    ],
    "validation": {
      "is_valid": false,
      "errors": [
        "Missing required property: source-domain",
        "Missing required property: last-updated",
        "Missing required property: is-subclass-of (at least one parent class)",
        "term-id '20259' doesn't match domain 'mv' (expected MV-)"
      ]
    }
  }
}