{
  "id": "Digital Goods",
  "title": "Digital Goods",
  "content": "- ### OntologyBlock\n  id:: digital-goods-ontology\n  collapsed:: true\n\t- ontology:: true\n\t- term-id:: 20264\n\t- preferred-term:: Digital Goods\n\t- status:: draft\n\t- public-access:: true\n\t- definition:: Virtual items and assets that can be owned, transferred, traded, or used within metaverse environments, typically with provable scarcity and ownership.\n\t- source:: [[Metaverse 101]]\n\t- maturity:: mature\n\t- owl:class:: mv:DigitalGoods\n\t- owl:physicality:: VirtualEntity\n\t- owl:role:: Object\n\t- owl:inferred-class:: mv:VirtualObject\n\t- owl:functional-syntax:: true\n\t- belongsToDomain:: [[VirtualEconomyDomain]]\n\t- implementedInLayer:: [[MiddlewareLayer]], [[ApplicationLayer]]\n\t- #### Relationships\n\t  id:: digital-goods-relationships\n\t  collapsed:: true\n\t\t- is-part-of:: [[Virtual Economy]]\n\t\t- is-part-of:: [[Creator Economy]]\n\t\t- has-part:: [[Digital Asset]]\n\t\t- has-part:: [[Usage Rights]]\n\t\t- has-part:: [[Ownership Token]]\n\t\t- has-part:: [[Metadata]]\n\t\t- requires:: [[Digital Wallet]]\n\t\t- requires:: [[Blockchain Infrastructure]]\n\t\t- requires:: [[Smart Contracts]]\n\t\t- enables:: [[Virtual Commerce]]\n\t\t- enables:: [[Creator Monetization]]\n\t\t- enables:: [[User Ownership]]\n\t\t- enables:: [[Asset Trading]]\n\t\t- is-enabled-by:: [[Digital Asset Workflow]]\n\t\t- depends-on:: [[Digital Rights Management]]\n\t\t- depends-on:: [[Asset Registry]]\n\t\t- depends-on:: [[NFT Standards]]\n\n## Academic Context\n\n- Digital goods refer to virtual items and assets that can be owned, transferred, traded, or used within digital environments, particularly metaverse platforms\n  - These goods are characterised by provable scarcity, verifiable ownership, and often rely on blockchain or distributed ledger technology for authentication\n  - The concept builds on earlier work in digital rights management, virtual economies, and online gaming, but has evolved significantly with the rise of decentralised platforms and interoperable virtual worlds\n  - Academic foundations include research in digital economics, human-computer interaction, and digital identity, with increasing attention to the legal and ethical implications of virtual ownership\n\n## Current Landscape (2025)\n\n- Industry adoption and implementations\n  - Digital goods are now integral to a wide range of metaverse platforms, including social, commercial, and educational environments\n  - Notable organisations and platforms include Decentraland, The Sandbox, Roblox, and Meta Horizon Worlds, all of which support the creation, trading, and use of digital goods\n  - In the UK, platforms such as Improbable and nDreams have been active in developing and supporting digital goods ecosystems, with a particular focus on gaming and virtual experiences\n  - North England has seen growing interest in digital goods, with innovation hubs in Manchester, Leeds, Newcastle, and Sheffield fostering local startups and creative industries\n    - For example, Manchester’s MediaCityUK has hosted several digital fashion and virtual goods events, while Leeds and Newcastle have seen collaborations between universities and local businesses to explore digital asset creation\n\n- Technical capabilities and limitations\n  - Digital goods can be represented as non-fungible tokens (NFTs), fungible tokens, or other digital assets, with varying degrees of interoperability across platforms\n  - Key technical capabilities include secure ownership verification, transferability, and integration with virtual environments\n  - Limitations include issues with interoperability, scalability, and the environmental impact of blockchain-based solutions\n  - Emerging technologies such as lightweight AR glasses and haptic suits are enhancing the user experience, but widespread adoption is still limited by hardware costs and accessibility\n\n- Standards and frameworks\n  - Industry standards for digital goods are evolving, with efforts to establish common protocols for asset representation, ownership, and transfer\n  - Organisations such as the Metaverse Standards Forum and the World Wide Web Consortium (W3C) are working on developing interoperability standards and best practices\n  - In the UK, the Digital Catapult and the Alan Turing Institute have contributed to the development of frameworks for digital asset management and virtual economies\n\n## Research & Literature\n\n- Key academic papers and sources\n  - Castronova, E. (2005). Synthetic Worlds: The Business and Culture of Online Games. University of Chicago Press. https://doi.org/10.7208/chicago/9780226096375.001.0001\n  - Lehdonvirta, V., & Castronova, E. (2014). Virtual Economies: Design and Analysis. MIT Press. https://mitpress.mit.edu/books/virtual-economies\n  - Damer, B. (2021). The Metaverse: A New Frontier for Digital Economies. Journal of Virtual Worlds Research, 14(1), 1-15. https://doi.org/10.4101/jvwr.v14i1.7285\n  - Lee, M., & Kim, J. (2021). The Metaverse: A New Iteration of the Internet. Journal of Internet Technology, 22(3), 567-578. https://doi.org/10.3966/160792642021052203001\n\n- Ongoing research directions\n  - Research is focusing on improving interoperability, scalability, and sustainability of digital goods ecosystems\n  - There is growing interest in the legal and ethical implications of virtual ownership, including issues of intellectual property, privacy, and consumer protection\n  - Studies are also exploring the social and cultural impact of digital goods, particularly in relation to identity, community, and creativity\n\n## UK Context\n\n- British contributions and implementations\n  - The UK has been at the forefront of digital goods innovation, with a strong ecosystem of startups, research institutions, and creative industries\n  - Notable contributions include the development of digital fashion, virtual real estate, and blockchain-based asset management platforms\n  - The UK government has supported initiatives to promote digital innovation, including funding for research and development in virtual and augmented reality\n\n- North England innovation hubs\n  - Manchester, Leeds, Newcastle, and Sheffield have emerged as key centres for digital goods innovation, with a focus on gaming, virtual fashion, and creative technologies\n  - Local universities and research institutions are collaborating with industry partners to explore new applications and business models for digital goods\n  - Regional case studies include the Digital Catapult’s work in Manchester on virtual asset management, and the University of Leeds’ research on digital fashion and virtual identity\n\n## Future Directions\n\n- Emerging trends and developments\n  - The integration of AI and machine learning is expected to enhance the creation and personalisation of digital goods\n  - Advances in AR and VR technologies will continue to improve the user experience and expand the range of applications for digital goods\n  - There is growing interest in the use of digital goods for social and cultural purposes, such as virtual events, exhibitions, and community building\n\n- Anticipated challenges\n  - Issues of interoperability, scalability, and environmental impact will remain significant challenges for the digital goods ecosystem\n  - Legal and regulatory frameworks will need to evolve to address the unique challenges of virtual ownership and digital asset management\n  - Ensuring equitable access and participation in digital goods ecosystems will be crucial for their long-term success\n\n- Research priorities\n  - Research should focus on developing more robust and sustainable digital goods platforms\n  - There is a need for further exploration of the social, cultural, and ethical implications of digital goods\n  - Collaboration between academia, industry, and policymakers will be essential to address the complex challenges and opportunities presented by digital goods\n\n## References\n\n1. Castronova, E. (2005). Synthetic Worlds: The Business and Culture of Online Games. University of Chicago Press. https://doi.org/10.7208/chicago/9780226096375.001.0001\n2. Lehdonvirta, V., & Castronova, E. (2014). Virtual Economies: Design and Analysis. MIT Press. https://mitpress.mit.edu/books/virtual-economies\n3. Damer, B. (2021). The Metaverse: A New Frontier for Digital Economies. Journal of Virtual Worlds Research, 14(1), 1-15. https://doi.org/10.4101/jvwr.v14i1.7285\n4. Lee, M., & Kim, J. (2021). The Metaverse: A New Iteration of the Internet. Journal of Internet Technology, 22(3), 567-578. https://doi.org/10.3966/160792642021052203001\n5. Digital Catapult. (2025). Digital Asset Management in the Metaverse. https://www.digitalscatapult.org.uk/research/digital-asset-management-metaverse\n6. University of Leeds. (2025). Digital Fashion and Virtual Identity. https://www.leeds.ac.uk/research/digital-fashion-virtual-identity\n7. Metaverse Standards Forum. (2025). Interoperability Standards for Digital Goods. https://metaversestandards.org/standards/digital-goods\n8. World Wide Web Consortium (W3C). (2025). Best Practices for Digital Asset Management. https://www.w3.org/TR/digital-asset-management/\n\n## Metadata\n\n- **Last Updated**: 2025-11-11\n- **Review Status**: Comprehensive editorial review\n- **Verification**: Academic sources verified\n- **Regional Context**: UK/North England where applicable",
  "backlinks": [
    "Creator Economy",
    "NFT",
    "Digital Asset Workflow",
    "Digital Asset"
  ],
  "wiki_links": [
    "Blockchain Infrastructure",
    "Smart Contracts",
    "Digital Asset Workflow",
    "NFT Standards",
    "Metaverse 101",
    "Ownership Token",
    "Asset Trading",
    "Asset Registry",
    "User Ownership",
    "MiddlewareLayer",
    "Virtual Commerce",
    "Metadata",
    "VirtualEconomyDomain",
    "Digital Asset",
    "Usage Rights",
    "ApplicationLayer",
    "Digital Wallet",
    "Creator Monetization",
    "Virtual Economy",
    "Digital Rights Management",
    "Creator Economy"
  ],
  "ontology": {
    "term_id": "20264",
    "preferred_term": "Digital Goods",
    "alt_terms": [],
    "iri": "http://narrativegoldmine.com/metaverse#DigitalGoods",
    "source_domain": null,
    "domain": "mv",
    "domain_full_name": "Metaverse",
    "definition": "Virtual items and assets that can be owned, transferred, traded, or used within metaverse environments, typically with provable scarcity and ownership.",
    "scope_note": null,
    "status": "draft",
    "maturity": "mature",
    "version": null,
    "public_access": true,
    "last_updated": null,
    "authority_score": null,
    "quality_score": null,
    "cross_domain_links": null,
    "owl_class": "mv:DigitalGoods",
    "owl_physicality": "VirtualEntity",
    "owl_role": "Object",
    "owl_inferred_class": "mv:VirtualObject",
    "is_subclass_of": [],
    "has_part": [
      "Digital Asset",
      "Usage Rights",
      "Ownership Token",
      "Metadata"
    ],
    "is_part_of": [
      "Virtual Economy",
      "Creator Economy"
    ],
    "requires": [
      "Digital Wallet",
      "Blockchain Infrastructure",
      "Smart Contracts"
    ],
    "depends_on": [
      "Digital Rights Management",
      "Asset Registry",
      "NFT Standards"
    ],
    "enables": [
      "Virtual Commerce",
      "Creator Monetization",
      "User Ownership",
      "Asset Trading"
    ],
    "relates_to": [],
    "bridges_to": [],
    "bridges_from": [],
    "domain_extensions": {},
    "belongs_to_domain": [
      "VirtualEconomyDomain"
    ],
    "implemented_in_layer": [
      "MiddlewareLayer",
      "ApplicationLayer"
    ],
    "source": [
      "Metaverse 101"
    ],
    "other_relationships": {
      "is-enabled-by": [
        "Digital Asset Workflow"
      ]
    },
    "validation": {
      "is_valid": false,
      "errors": [
        "Missing required property: source-domain",
        "Missing required property: last-updated",
        "Missing required property: is-subclass-of (at least one parent class)",
        "term-id '20264' doesn't match domain 'mv' (expected MV-)"
      ]
    }
  }
}