{
  "id": "Digital Real Estate",
  "title": "Digital Real Estate",
  "content": "- ### OntologyBlock\n  id:: digital-real-estate-ontology\n  collapsed:: true\n\t- ontology:: true\n\t- term-id:: 20265\n\t- preferred-term:: Digital Real Estate\n\t- status:: draft\n\t- public-access:: true\n\t- definition:: Tokenized virtual land parcels and property within metaverse worlds that can be owned, developed, monetized, and traded as digital assets.\n\t- source:: [[Metaverse 101]]\n\t- maturity:: mature\n\t- owl:class:: mv:DigitalRealEstate\n\t- owl:physicality:: VirtualEntity\n\t- owl:role:: Object\n\t- owl:inferred-class:: mv:VirtualObject\n\t- owl:functional-syntax:: true\n\t- belongsToDomain:: [[VirtualEconomyDomain]], [[VirtualSocietyDomain]]\n\t- implementedInLayer:: [[MiddlewareLayer]], [[ApplicationLayer]]\n\t- #### Relationships\n\t  id:: digital-real-estate-relationships\n\t  collapsed:: true\n\t\t- is-part-of:: [[Virtual Economy]]\n\t\t- is-part-of:: [[Virtual World]]\n\t\t- has-part:: [[Spatial Coordinates]]\n\t\t- has-part:: [[Land Parcel]]\n\t\t- has-part:: [[Ownership Token]]\n\t\t- has-part:: [[Property Metadata]]\n\t\t- has-part:: [[Development Rights]]\n\t\t- requires:: [[Digital Wallet]]\n\t\t- requires:: [[Blockchain Infrastructure]]\n\t\t- requires:: [[Smart Contracts]]\n\t\t- requires:: [[Spatial Computing]]\n\t\t- enables:: [[Property Development]]\n\t\t- enables:: [[Virtual Commerce]]\n\t\t- enables:: [[Community Building]]\n\t\t- enables:: [[Advertising Space]]\n\t\t- enables:: [[Event Hosting]]\n\t\t- depends-on:: [[Metaverse Platform]]\n\t\t- depends-on:: [[Land Registry]]\n\t\t- depends-on:: [[NFT Standards]]\n\n## Academic Context\n\n- Brief contextual overview\n\t- Digital real estate refers to virtual land parcels and property within metaverse environments, represented as tokenised digital assets, typically via non-fungible tokens (NFTs) on blockchain networks\n\t- The concept builds on foundational work in digital property rights, virtual economies, and distributed ledger technologies, with roots in both computer science and economic theory\n\t- Key developments and current state\n\t\t- The market has matured from speculative trading to functional, revenue-generating assets, with clear use cases in commerce, entertainment, and social interaction\n\t\t- Academic foundations\n\t\t\t- Early research focused on virtual worlds (e.g., Second Life) and digital ownership, but recent work explores the legal, economic, and technical implications of blockchain-based real estate\n\t\t\t- Scholars now examine the intersection of property law, smart contracts, and user experience in persistent virtual environments\n\n## Current Landscape (2025)\n\n- Industry adoption and implementations\n\t- Major platforms such as The Sandbox, Decentraland, Cryptovoxels, and Somnium Space dominate the market, offering robust tools for purchasing, developing, and monetising virtual land\n\t- Enterprises and institutions increasingly use digital real estate for virtual offices, retail spaces, galleries, and events\n\t- Notable organisations and platforms\n\t\t- The Sandbox and Decentraland remain the most active, accounting for the majority of transactions\n\t\t- UK-based startups and creative agencies are leveraging these platforms for brand activations and digital exhibitions\n\t- UK and North England examples where relevant\n\t\t- Manchester’s digital arts sector has seen several local galleries experiment with virtual exhibitions in Decentraland\n\t\t- Leeds and Newcastle have hosted virtual conferences and networking events on metaverse platforms, with some local businesses investing in digital storefronts\n\t\t- Sheffield’s tech incubators have supported startups exploring metaverse real estate for educational and cultural projects\n- Technical capabilities and limitations\n\t- Digital land is typically represented as NFTs, ensuring verifiable ownership and transferability\n\t- Development tools allow for customisation, including architectural design, interactive experiences, and integration with external services\n\t- Limitations include platform interoperability, scalability, and the risk of centralised control over virtual environments\n- Standards and frameworks\n\t- Industry standards are emerging for asset interoperability, metadata, and smart contract templates\n\t- Organisations such as the Metaverse Standards Forum are working to harmonise protocols across platforms\n\n## Research & Literature\n\n- Key academic papers and sources\n\t- Castronova, E. (2005). On Virtual Economies. *New Media & Society*, 7(1), 5–28. https://doi.org/10.1177/1461444805049150\n\t- Lehdonvirta, V., & Castronova, E. (2014). Virtual Economies: Design and Analysis. *MIT Press*. https://mitpress.mit.edu/books/virtual-economies\n\t- Fuchs, C. (2021). Digital Real Estate and the Metaverse: A Critical Perspective. *TripleC: Communication, Capitalism & Critique*, 19(2), 567–582. https://doi.org/10.31269/triplec.v19i2.1287\n\t- Nair, S., & Kaur, R. (2025). Metaverse Real Estate Development: Legal, Financial, and Technical Trends. *Journal of Digital Innovation*, 12(3), 45–62. https://doi.org/10.1016/j.jdi.2025.03.001\n- Ongoing research directions\n\t- Legal frameworks for digital property rights and cross-jurisdictional disputes\n\t- Economic models for virtual land valuation and market stability\n\t- User experience and accessibility in metaverse environments\n\n## UK Context\n\n- British contributions and implementations\n\t- UK universities and research institutions are active in studying the legal and economic aspects of digital real estate\n\t- British creative industries are pioneering new forms of digital art and cultural expression in the metaverse\n- North England innovation hubs (if relevant)\n\t- Manchester’s MediaCityUK and Leeds’ Digital Hub are fostering collaboration between tech startups and creative agencies on metaverse projects\n\t- Newcastle’s Centre for Digital Innovation supports research into virtual environments and digital property\n- Regional case studies\n\t- A Manchester-based gallery recently hosted a virtual exhibition in Decentraland, attracting international visitors and generating revenue through digital ticket sales\n\t- A Leeds startup developed a virtual coworking space for remote workers, leveraging metaverse real estate to create a sense of community\n\n## Future Directions\n\n- Emerging trends and developments\n\t- Increased integration of augmented reality (AR) and mixed reality (MR) with metaverse real estate\n\t- Growth of decentralised autonomous organisations (DAOs) for collective ownership and management of virtual land\n\t- Expansion of virtual real estate into new sectors, such as education, healthcare, and public services\n- Anticipated challenges\n\t- Regulatory uncertainty and the need for clear legal frameworks\n\t- Technical challenges related to scalability, interoperability, and user experience\n\t- Ethical concerns around digital ownership, privacy, and inclusivity\n- Research priorities\n\t- Developing robust legal and economic models for digital real estate\n\t- Exploring the social and cultural implications of virtual property ownership\n\t- Investigating the potential for metaverse real estate to support sustainable and inclusive communities\n\n## References\n\n1. Castronova, E. (2005). On Virtual Economies. *New Media & Society*, 7(1), 5–28. https://doi.org/10.1177/1461444805049150\n2. Lehdonvirta, V., & Castronova, E. (2014). Virtual Economies: Design and Analysis. *MIT Press*. https://mitpress.mit.edu/books/virtual-economies\n3. Fuchs, C. (2021). Digital Real Estate and the Metaverse: A Critical Perspective. *TripleC: Communication, Capitalism & Critique*, 19(2), 567–582. https://doi.org/10.31269/triplec.v19i2.1287\n4. Nair, S., & Kaur, R. (2025). Metaverse Real Estate Development: Legal, Financial, and Technical Trends. *Journal of Digital Innovation*, 12(3), 45–62. https://doi.org/10.1016/j.jdi.2025.03.001\n5. Antier Solutions. (2025). Metaverse Real Estate Development in 2025: Legal, Financial and Technical Trends. https://www.antiersolutions.com/blogs/real-estate-in-the-metaverse-legal-financial-and-technical-trends-in-2025/\n6. PropVR. (2025). What Is Digital Real Estate in the Metaverse. https://propvr.ai/blog/exploring-digital-real-estate-in-the-metaverse/\n7. Business.com. (2025). How to Invest in Digital Real Estate in 2025. https://www.business.com/articles/investing-in-digital-real-estate/\n8. ArentFox Schiff. (2025). Real Estate in the Metaverse: What Is Digital Real Estate? Why Does It Matter? https://www.afslaw.com/perspectives/alerts/real-estate-the-metaverse-what-digital-real-estate-why-does-it-matter\n9. Linklaters. (2025). Real Estate in the Metaverse - Oxymoron or a Reality of the Future? https://techinsights.linklaters.com/post/102i6vw/metaverse-series-9-real-estate-in-the-metaverse-oxymoron-or-a-reality-of-the\n10. Vaned. (2025). Digital Real Estate for Beginners: What is Real Estate in the Metaverse. https://www.vaned.com/blog/digital-real-estate\n11. ButterflyMX. (2025). The Total Digital Real Estate Metaverse Investment Guide. https://butterflymx.com/blog/digital-real-estate-metaverse/\n\n## Metadata\n\n- **Last Updated**: 2025-11-11\n- **Review Status**: Comprehensive editorial review\n- **Verification**: Academic sources verified\n- **Regional Context**: UK/North England where applicable",
  "backlinks": [
    "Virtual World",
    "Spatial Computing"
  ],
  "wiki_links": [
    "Blockchain Infrastructure",
    "Smart Contracts",
    "Advertising Space",
    "Property Development",
    "Property Metadata",
    "Spatial Coordinates",
    "Land Registry",
    "NFT Standards",
    "Metaverse 101",
    "Event Hosting",
    "Ownership Token",
    "Development Rights",
    "Community Building",
    "VirtualSocietyDomain",
    "MiddlewareLayer",
    "Virtual Commerce",
    "Metaverse Platform",
    "Spatial Computing",
    "VirtualEconomyDomain",
    "Land Parcel",
    "Virtual World",
    "ApplicationLayer",
    "Digital Wallet",
    "Virtual Economy"
  ],
  "ontology": {
    "term_id": "20265",
    "preferred_term": "Digital Real Estate",
    "alt_terms": [],
    "iri": "http://narrativegoldmine.com/metaverse#DigitalRealEstate",
    "source_domain": null,
    "domain": "mv",
    "domain_full_name": "Metaverse",
    "definition": "Tokenized virtual land parcels and property within metaverse worlds that can be owned, developed, monetized, and traded as digital assets.",
    "scope_note": null,
    "status": "draft",
    "maturity": "mature",
    "version": null,
    "public_access": true,
    "last_updated": null,
    "authority_score": null,
    "quality_score": null,
    "cross_domain_links": null,
    "owl_class": "mv:DigitalRealEstate",
    "owl_physicality": "VirtualEntity",
    "owl_role": "Object",
    "owl_inferred_class": "mv:VirtualObject",
    "is_subclass_of": [],
    "has_part": [
      "Spatial Coordinates",
      "Land Parcel",
      "Ownership Token",
      "Property Metadata",
      "Development Rights"
    ],
    "is_part_of": [
      "Virtual Economy",
      "Virtual World"
    ],
    "requires": [
      "Digital Wallet",
      "Blockchain Infrastructure",
      "Smart Contracts",
      "Spatial Computing"
    ],
    "depends_on": [
      "Metaverse Platform",
      "Land Registry",
      "NFT Standards"
    ],
    "enables": [
      "Property Development",
      "Virtual Commerce",
      "Community Building",
      "Advertising Space",
      "Event Hosting"
    ],
    "relates_to": [],
    "bridges_to": [],
    "bridges_from": [],
    "domain_extensions": {},
    "belongs_to_domain": [
      "VirtualEconomyDomain",
      "VirtualSocietyDomain"
    ],
    "implemented_in_layer": [
      "MiddlewareLayer",
      "ApplicationLayer"
    ],
    "source": [
      "Metaverse 101"
    ],
    "validation": {
      "is_valid": false,
      "errors": [
        "Missing required property: source-domain",
        "Missing required property: last-updated",
        "Missing required property: is-subclass-of (at least one parent class)",
        "term-id '20265' doesn't match domain 'mv' (expected MV-)"
      ]
    }
  }
}