{
  "id": "DigitalAvatar",
  "title": "DigitalAvatar",
  "content": "- ### OntologyBlock\n  id:: digitalavatar-ontology\n  collapsed:: true\n\t- ontology:: true\n\t- term-id:: MV-0005\n\t- preferred-term:: DigitalAvatar\n\t- source-domain:: metaverse\n\t- status:: active\n\t- public-access:: true\n\t- definition:: A virtual representation of a user in digital environments, ranging from simple 2D icons to sophisticated 3D models that can express emotions and interact with virtual worlds.\n\t- maturity:: mature\n\t- owl:class:: mv:DigitalAvatar\n\t- owl:physicality:: VirtualEntity\n\t- owl:role:: Object\n\t- is-subclass-of:: [[ArtificialIntelligence]]\n\t- belongsToDomain:: [[MetaverseDomain]]\n\t- #### CrossDomainBridges\n\t\t- dt:uses:: [[Computer Vision]]\n\t\t- dt:uses:: [[Machine Learning]]\n\n## OWL Formal Semantics\n\n```clojure\n;; OWL Functional Syntax\n\n(Declaration (Class :Digitalavatar))\n\n;; Annotations\n(AnnotationAssertion rdfs:label :Digitalavatar \"DigitalAvatar\"@en)\n(AnnotationAssertion rdfs:comment :Digitalavatar \"A component of the metaverse ecosystem.\"@en)\n\n;; Data Properties\n(AnnotationAssertion dcterms:identifier :Digitalavatar \"mv-1761742247916\"^^xsd:string)\n```",
  "backlinks": [
    "BC-0009-smart-contract",
    "NFT",
    "Decentralized Identifiers",
    "Large language models"
  ],
  "wiki_links": [
    "MetaverseDomain",
    "ArtificialIntelligence",
    "Machine Learning",
    "Computer Vision"
  ],
  "ontology": {
    "term_id": "MV-0005",
    "preferred_term": "DigitalAvatar",
    "alt_terms": [],
    "iri": "http://narrativegoldmine.com/metaverse#DigitalAvatar",
    "source_domain": "metaverse",
    "domain": "metaverse",
    "domain_full_name": "",
    "definition": "A virtual representation of a user in digital environments, ranging from simple 2D icons to sophisticated 3D models that can express emotions and interact with virtual worlds.",
    "scope_note": null,
    "status": "active",
    "maturity": "mature",
    "version": null,
    "public_access": true,
    "last_updated": null,
    "authority_score": null,
    "quality_score": null,
    "cross_domain_links": null,
    "owl_class": "mv:DigitalAvatar",
    "owl_physicality": "VirtualEntity",
    "owl_role": "Object",
    "owl_inferred_class": null,
    "is_subclass_of": [],
    "has_part": [],
    "is_part_of": [],
    "requires": [],
    "depends_on": [],
    "enables": [],
    "relates_to": [],
    "bridges_to": [],
    "bridges_from": [],
    "domain_extensions": {},
    "belongs_to_domain": [
      "MetaverseDomain"
    ],
    "implemented_in_layer": [],
    "source": [],
    "validation": {
      "is_valid": false,
      "errors": [
        "Missing required property: last-updated",
        "Missing required property: is-subclass-of (at least one parent class)",
        "owl:class namespace 'mv' doesn't match source-domain 'metaverse'"
      ]
    }
  }
}