{
  "id": "Distributed Ledger Technology (DLT)",
  "title": "Distributed Ledger Technology (DLT)",
  "content": "- ### OntologyBlock\n  id:: distributed-ledger-technology-dlt-ontology\n  collapsed:: true\n\t- ontology:: true\n\t- term-id:: 20278\n\t- preferred-term:: Distributed Ledger Technology (DLT)\n\t- status:: draft\n\t- public-access:: true\n\t- definition:: Distributed database infrastructure using cryptographic consensus mechanisms to maintain immutable, tamper-resistant records across decentralized peer-to-peer networks without centralized authority.\n\t- source:: [[ISO 22739]], [[NIST Blockchain Technology Overview]]\n\t- maturity:: mature\n\t- owl:class:: mv:DistributedLedgerTechnology\n\t- owl:physicality:: VirtualEntity\n\t- owl:role:: Object\n\t- owl:inferred-class:: mv:VirtualObject\n\t- owl:functional-syntax:: true\n\t- belongsToDomain:: [[InfrastructureDomain]], [[VirtualEconomyDomain]], [[TrustAndGovernanceDomain]]\n\t- implementedInLayer:: [[InfrastructureLayer]]\n\t- #### Relationships\n\t  id:: distributed-ledger-technology-dlt-relationships\n\t  collapsed:: true\n\t\t- has-part:: [[Consensus Protocol]]\n\t\t- has-part:: [[Block Structure]]\n\t\t- has-part:: [[Transaction Pool]]\n\t\t- has-part:: [[Merkle Tree]]\n\t\t- has-part:: [[Distributed Network]]\n\t\t- has-part:: [[Blockchain]]\n\t\t- has-part:: [[Cryptographic Hash Function]]\n\t\t- requires:: [[Digital Signature]]\n\t\t- requires:: [[Network Protocol]]\n\t\t- requires:: [[Peer-to-Peer Network]]\n\t\t- requires:: [[Byzantine Fault Tolerance]]\n\t\t- requires:: [[Cryptographic Algorithm]]\n\t\t- enables:: [[Immutable Record]]\n\t\t- enables:: [[Decentralized Application]]\n\t\t- enables:: [[Smart Contract]]\n\t\t- enables:: [[Virtual Notary Service]]\n\t\t- enables:: [[Digital Asset]]\n\t\t- enables:: [[Trustless Transaction]]\n\t\t- enables:: [[Cryptocurrency]]\n\t\t- is-required-by:: [[Virtual Notary Service]]\n\t\t- depends-on:: [[Distributed System]]\n\t\t- depends-on:: [[Cryptography]]\n\t\t- depends-on:: [[Data Replication]]\n\t\t- depends-on:: [[Network Infrastructure]]\n\n## Academic Context\n\n- Distributed Ledger Technology represents a paradigm shift in data management architecture\n  - Enables decentralised recording and verification of transactions across multiple nodes without reliance on central authorities[1][2]\n  - Emerged as a distinct technological category following Bitcoin's 2009 launch, demonstrating scalability and security at scale[5]\n  - Broader conceptual framework than blockchain, which constitutes one specific implementation of DLT principles[3]\n  - Historical precedent exists in paper-based and siloed software systems, though DLT eliminates reconciliation inefficiencies inherent in periodic centralised consolidation[5]\n\n- Foundational principles\n  - Each network participant (node) maintains a synchronised copy of the ledger[2]\n  - Consensus mechanisms enable collective validation without trusted intermediaries[2]\n  - Cryptographic security creates immutable, tamper-resistant records[2]\n  - Peer-to-peer architecture removes single points of failure and control[1]\n\n## Current Landscape (2025)\n\n- Technical architecture and capabilities\n  - Records and synchronises data across multiple locations simultaneously[4][5]\n  - Processes and verifies transactions collectively, generating consensus on veracity[5]\n  - Accommodates both static data (registries) and dynamic data (financial transactions)[5]\n  - Supports value transfer across multiple asset classes: currency, securities, and personal information[3]\n  - Eliminates need for central data stores or administration functionality[5]\n\n- Industry adoption and implementations\n  - Financial services sector: bond issuance, trading, settlement, distribution, repo and securities lending transactions[1]\n  - Healthcare and pharmaceutical sectors: early adopters of enterprise DLT applications[5]\n  - Supply chain management: widespread implementation for transparency and traceability[5]\n  - Digital identity systems: emerging applications for decentralised verification[4]\n\n- UK and North England context\n  - Financial services remain primary adoption vector, particularly within London's established fintech ecosystem\n  - Northern innovation hubs (Manchester, Leeds, Sheffield) developing supply chain and digital identity applications, though comprehensive regional case studies remain limited in current literature\n  - UK regulatory framework continues evolving; Financial Conduct Authority maintains oversight of DLT-based financial instruments\n\n- Technical limitations and considerations\n  - Scalability constraints vary by consensus mechanism and network architecture[4]\n  - Energy consumption implications dependent on validation protocols employed\n  - Regulatory uncertainty persists across jurisdictions regarding liability and governance[1]\n  - Interoperability challenges between heterogeneous DLT systems remain unresolved\n\n## Research & Literature\n\n- Foundational sources\n  - Financial Stability Board (2019). *Decentralised financial technologies: Report on financial stability, regulatory and governance implications*. Provides authoritative definitions and regulatory implications[1]\n  - Financial Stability Board (2018). *Crypto-asset markets: Potential channels for future financial stability implications*. Addresses blockchain as specific DLT implementation[1]\n\n- Technical and architectural literature\n  - ICMA (International Capital Market Association). FinTech tracker of DLT-based bond market applications. Ongoing monitoring of financial services implementation[1]\n  - TechTarget SearchCIO. Comprehensive technical definitions and enterprise application frameworks[5]\n\n- Ongoing research directions\n  - Consensus mechanism optimisation for energy efficiency and throughput\n  - Cross-chain interoperability protocols\n  - Regulatory harmonisation across jurisdictions\n  - Privacy-preserving mechanisms within transparent ledger systems\n  - Enterprise scalability solutions\n\n## UK Context\n\n- British financial services leadership\n  - London remains global fintech centre with significant DLT investment and experimentation\n  - Regulatory sandbox approach enables controlled DLT implementation testing\n\n- Northern England developments\n  - Manchester and Leeds emerging as secondary fintech hubs with growing DLT interest\n  - Supply chain applications gaining traction in manufacturing-heavy regions\n  - Digital identity initiatives exploring DLT for decentralised verification systems\n  - Regional universities (Manchester, Leeds, Sheffield) conducting DLT research, though comprehensive documentation of specific projects remains scattered\n\n- Regulatory environment\n  - Financial Conduct Authority maintains oversight of DLT-based financial instruments\n  - HM Treasury engaged in ongoing policy development regarding distributed ledger governance\n  - Bank of England exploring central bank digital currency (CBDC) applications\n\n## Future Directions\n\n- Emerging technical developments\n  - Hybrid architectures combining public and private ledger characteristics\n  - Layer-2 scaling solutions addressing throughput limitations\n  - Zero-knowledge proof implementations enhancing privacy within transparent systems\n  - Quantum-resistant cryptographic protocols under development\n\n- Anticipated challenges\n  - Regulatory fragmentation across jurisdictions creating compliance complexity\n  - Energy consumption concerns driving consensus mechanism evolution\n  - Talent shortage in DLT development and governance expertise\n  - Legacy system integration difficulties within established enterprises\n\n- Research priorities\n  - Standardisation frameworks for interoperability (ISO and industry-specific standards)\n  - Governance models balancing decentralisation with accountability\n  - Environmental impact mitigation strategies\n  - Real-world scalability demonstrations beyond proof-of-concept implementations\n\n---\n\n**Note on methodology:** This revision prioritises technical precision whilst maintaining accessibility. The definition provided remains current as of November 2025; DLT continues evolving as an infrastructure technology rather than experiencing paradigm shifts. UK context reflects available literature, though comprehensive North England case studies remain limitedâ€”an opportunity for future regional research documentation.\n\n## Metadata\n\n- **Last Updated**: 2025-11-11\n- **Review Status**: Comprehensive editorial review\n- **Verification**: Academic sources verified\n- **Regional Context**: UK/North England where applicable",
  "backlinks": [
    "Cryptocurrency",
    "Network Infrastructure",
    "Virtual Notary Service",
    "Digital Asset"
  ],
  "wiki_links": [
    "TrustAndGovernanceDomain",
    "Trustless Transaction",
    "Network Protocol",
    "Consensus Protocol",
    "Data Replication",
    "Merkle Tree",
    "ISO 22739",
    "Cryptographic Hash Function",
    "Distributed System",
    "Cryptographic Algorithm",
    "Byzantine Fault Tolerance",
    "Decentralized Application",
    "Block Structure",
    "Cryptocurrency",
    "Network Infrastructure",
    "Distributed Network",
    "NIST Blockchain Technology Overview",
    "Peer-to-Peer Network",
    "Digital Signature",
    "VirtualEconomyDomain",
    "InfrastructureDomain",
    "Immutable Record",
    "Cryptography",
    "InfrastructureLayer",
    "Virtual Notary Service",
    "Blockchain",
    "Smart Contract",
    "Digital Asset",
    "Transaction Pool"
  ],
  "ontology": {
    "term_id": "20278",
    "preferred_term": "Distributed Ledger Technology (DLT)",
    "alt_terms": [],
    "iri": "http://narrativegoldmine.com/metaverse#DistributedLedgerTechnology",
    "source_domain": null,
    "domain": "mv",
    "domain_full_name": "Metaverse",
    "definition": "Distributed database infrastructure using cryptographic consensus mechanisms to maintain immutable, tamper-resistant records across decentralized peer-to-peer networks without centralized authority.",
    "scope_note": null,
    "status": "draft",
    "maturity": "mature",
    "version": null,
    "public_access": true,
    "last_updated": null,
    "authority_score": null,
    "quality_score": null,
    "cross_domain_links": null,
    "owl_class": "mv:DistributedLedgerTechnology",
    "owl_physicality": "VirtualEntity",
    "owl_role": "Object",
    "owl_inferred_class": "mv:VirtualObject",
    "is_subclass_of": [],
    "has_part": [
      "Consensus Protocol",
      "Block Structure",
      "Transaction Pool",
      "Merkle Tree",
      "Distributed Network",
      "Blockchain",
      "Cryptographic Hash Function"
    ],
    "is_part_of": [],
    "requires": [
      "Digital Signature",
      "Network Protocol",
      "Peer-to-Peer Network",
      "Byzantine Fault Tolerance",
      "Cryptographic Algorithm"
    ],
    "depends_on": [
      "Distributed System",
      "Cryptography",
      "Data Replication",
      "Network Infrastructure"
    ],
    "enables": [
      "Immutable Record",
      "Decentralized Application",
      "Smart Contract",
      "Virtual Notary Service",
      "Digital Asset",
      "Trustless Transaction",
      "Cryptocurrency"
    ],
    "relates_to": [],
    "bridges_to": [],
    "bridges_from": [],
    "domain_extensions": {},
    "belongs_to_domain": [
      "InfrastructureDomain",
      "VirtualEconomyDomain",
      "TrustAndGovernanceDomain"
    ],
    "implemented_in_layer": [
      "InfrastructureLayer"
    ],
    "source": [
      "ISO 22739",
      "NIST Blockchain Technology Overview"
    ],
    "other_relationships": {
      "is-required-by": [
        "Virtual Notary Service"
      ]
    },
    "validation": {
      "is_valid": false,
      "errors": [
        "Missing required property: source-domain",
        "Missing required property: last-updated",
        "Missing required property: is-subclass-of (at least one parent class)",
        "term-id '20278' doesn't match domain 'mv' (expected MV-)"
      ]
    }
  }
}