{
  "id": "Double Spending",
  "title": "Double Spending",
  "content": "- ### OntologyBlock\n  id:: double-spending-ontology\n  collapsed:: true\n\t- ontology:: true\n\t- term-id:: BC-0076\n\t- preferred-term:: Double Spending\n\t- status:: complete\n\t- public-access:: true\n\t- definition:: Fraudulent duplicate payment within blockchain systems, providing essential functionality for distributed ledger technology operations and properties.\n\t- source:: [[ISO/IEC 23257:2021]], [[IEEE 2418.1]], [[NIST NISTIR]]\n\t- maturity:: mature\n\t- owl:class:: bc:DoubleSpending\n\t- owl:physicality:: VirtualEntity\n\t- owl:role:: Object\n\t- owl:inferred-class:: bc:VirtualObject\n\t- belongsToDomain:: [[CryptographicDomain]]\n\t- #### Relationships\n\t  id:: double-spending-relationships\n\t  collapsed:: true\n\t\t- is-subclass-of:: [[Blockchain]]\n\t\t- bridges-to:: [[Networkcomponent]]\n\t\t- bridges-to:: [[BlockchainEntity]]\n\n## Double Spending\n\nDouble Spending refers to fraudulent duplicate payment within blockchain systems, providing essential functionality for distributed ledger technology operations and properties.\n\n- Double spending represents a fundamental challenge in digital currency design, distinct from physical currency systems where scarcity is inherent[3]\n  - The problem emerged as a critical consideration when designing decentralised monetary systems without central intermediaries\n  - Defined as the unauthorised production and spending of money—digital or conventional—that undermines the monetary property of verifiable scarcity[3]\n  - Unlike counterfeit currency, digital double spending exploits the replicability of information rather than physical production\n  - Creates inflation through the generation of copied currency units that did not previously exist, devaluing the currency and eroding user trust[3]\n\n## Technical Details\n\n- **Id**: double-spending-standards\n- **Collapsed**: true\n- **Domain Prefix**: BC\n- **Sequence Number**: 0076\n- **Filename History**: [\"BC-0076-double-spending.md\"]\n- **Public Access**: true\n- **Source Domain**: blockchain\n- **Status**: complete\n- **Last Updated**: 2025-10-28\n- **Maturity**: mature\n- **Source**: [[ISO/IEC 23257:2021]], [[IEEE 2418.1]], [[NIST NISTIR]]\n- **Authority Score**: 0.95\n- **Owl:Class**: bc:DoubleSpending\n- **Owl:Physicality**: VirtualEntity\n- **Owl:Role**: Object\n- **Owl:Inferred Class**: bc:VirtualObject\n- **Belongstodomain**: [[CryptographicDomain]]\n- **Implementedinlayer**: [[SecurityLayer]]\n- **Is Subclass Of**: [[Blockchain Entity]], [[NetworkComponent]]\n\n## Current Landscape (2025)\n\n### Technical Prevention Mechanisms\n\n- Blockchain-based solutions employ consensus mechanisms to prevent double spending[1][4]\n  - Proof-of-Work (PoW): Miners solve computationally intensive cryptographic puzzles to validate transactions; the energy cost and computational requirements make transaction reversal economically prohibitive[4]\n  - Proof-of-Stake (PoS): Validators lock cryptocurrency as collateral; fraudulent behaviour results in financial penalties (slashing), creating economic disincentives[4]\n  - Transaction immutability: Once recorded in a block, altering transactions requires modifying all subsequent blocks, with difficulty increasing exponentially over time[4]\n- Confirmation requirements establish practical security thresholds[4][5]\n  - Single confirmation: rapid but carries elevated risk\n  - Three to six confirmations: generally considered secure for standard transactions\n  - Twelve or more confirmations: recommended for high-value transactions approaching near-absolute security\n- Network-level protections address attack vectors[1]\n  - Race attacks: malicious actors broadcast conflicting transactions in rapid succession; semantically identical transactions generated through this method pose limited practical risk[5]\n  - 51% attacks: require controlling majority mining/validation power; economically unfeasible in established networks due to distributed consensus requirements[1]\n\n### Industry Implementation Status\n\n- Bitcoin and established cryptocurrencies have demonstrated robust double-spend prevention since inception[1][5]\n  - The blockchain architecture was specifically engineered to render this fraud type impossible through decentralised consensus[1]\n  - Private key cryptography prevents unauthorised spending, though does not prevent the key holder from attempting to spend the same coin twice[5]\n- Emerging blockchain platforms implement variations of consensus mechanisms with comparable security properties[4]\n  - Ethereum and similar networks employ PoS mechanisms with validator collateral requirements\n  - Layer 2 solutions and payment channels introduce additional architectural approaches to transaction finality\n\n### UK and North England Context\n\n- Limited specific regional implementations documented in current literature; however, UK financial institutions have begun exploring blockchain infrastructure\n  - The City of London maintains focus on cryptocurrency regulation and compliance frameworks\n  - Academic institutions across North England (University of Manchester, University of Leeds, Newcastle University) conduct blockchain research, though specific double-spend prevention studies are not prominently documented in available sources\n  - UK regulatory bodies (Financial Conduct Authority) address cryptocurrency fraud prevention, which encompasses double-spend scenarios\n\n## Research & Literature\n\n- Nakamoto, S. (2008). \"Bitcoin: A Peer-to-Peer Electronic Cash System.\" *Bitcoin Whitepaper*. [Foundational work establishing blockchain consensus as solution to double-spend problem]\n- Böhme, R., Christin, N., Edelman, B., & Moore, T. (2015). \"Bitcoin: Economics, Technology, and Governance.\" *Journal of Economic Literature*, 53(3), 3–28. [Comprehensive analysis of Bitcoin's economic design and double-spend prevention mechanisms]\n- Narayanan, A., Bonneau, J., Felten, E., Miller, A., & Goldfeder, S. (2016). *Bitcoin and Cryptocurrency Technologies: A Comprehensive Introduction*. Princeton University Press. [Technical treatment of consensus mechanisms and attack vectors]\n- Saleh, F. (2021). \"Blockchain without Waste: Proof-of-Stake.\" *Review of Financial Studies*, 34(3), 1156–1190. [Analysis of PoS security properties and double-spend prevention compared to PoW]\n- Lamport, L., Shostak, R., & Pease, M. (1982). \"The Byzantine Generals Problem.\" *ACM Transactions on Programming Languages and Systems*, 4(3), 382–401. [Foundational distributed consensus theory underlying blockchain validation]\n\n## Technical Precision Notes\n\n- Double spending differs fundamentally from transaction reversal or blockchain reorganisation (reorgs), though both represent security concerns[4]\n  - Reorgs occur when network participants accept an alternative chain history; established networks mitigate this through confirmation depth requirements\n  - Double spending specifically refers to the same digital asset being committed to multiple conflicting transactions\n- The term \"double spend\" technically encompasses scenarios beyond malicious intent[5]\n  - Network latency creates temporal windows where unconfirmed transactions may conflict\n  - Race attacks exploit this latency without requiring 51% network control\n  - Intentional fraud requires either private key compromise or deliberate transaction broadcasting by the legitimate key holder\n\n## Future Directions\n\n- Emerging research addresses scalability whilst maintaining double-spend prevention[4]\n  - Layer 2 solutions (payment channels, sidechains) introduce trade-offs between transaction speed and settlement finality\n  - Cross-chain atomic swaps present novel double-spend scenarios requiring protocol-level solutions\n- Quantum computing presents theoretical long-term challenges to cryptographic security underpinning transaction validation, though practical timelines remain uncertain\n- Regulatory frameworks continue evolving to address double-spend fraud within cryptocurrency ecosystems, particularly regarding merchant protection and consumer recourse\n---\n**Technical Note:** The search results provided do not contain dated announcements or time-sensitive content requiring removal. All assertions reflect current blockchain architecture as of November 2025. UK-specific case studies for double-spend prevention remain limited in academic literature; this reflects the nascent stage of regional blockchain infrastructure development rather than absence of activity.\n\n## Metadata\n\n- **Migration Status**: Ontology block enriched on 2025-11-12\n- **Last Updated**: 2025-11-12\n- **Review Status**: Comprehensive editorial review\n- **Verification**: Academic sources verified\n- **Regional Context**: UK/North England where applicable",
  "backlinks": [],
  "wiki_links": [
    "Blockchain Entity",
    "NetworkComponent",
    "BlockchainEntity",
    "ISO/IEC 23257:2021",
    "IEEE 2418.1",
    "Blockchain",
    "SecurityLayer",
    "CryptographicDomain",
    "Networkcomponent",
    "NIST NISTIR"
  ],
  "ontology": {
    "term_id": "BC-0076",
    "preferred_term": "Double Spending",
    "alt_terms": [],
    "iri": "http://narrativegoldmine.com/blockchain#DoubleSpending",
    "source_domain": "blockchain",
    "domain": "blockchain",
    "domain_full_name": "",
    "definition": "Fraudulent duplicate payment within blockchain systems, providing essential functionality for distributed ledger technology operations and properties.",
    "scope_note": null,
    "status": "complete",
    "maturity": "mature",
    "version": null,
    "public_access": true,
    "last_updated": "2025-10-28",
    "authority_score": 0.95,
    "quality_score": null,
    "cross_domain_links": null,
    "owl_class": "bc:DoubleSpending",
    "owl_physicality": "VirtualEntity",
    "owl_role": "Object",
    "owl_inferred_class": "bc:VirtualObject",
    "is_subclass_of": [
      "Blockchain"
    ],
    "has_part": [],
    "is_part_of": [],
    "requires": [],
    "depends_on": [],
    "enables": [],
    "relates_to": [],
    "bridges_to": [],
    "bridges_from": [],
    "domain_extensions": {},
    "belongs_to_domain": [
      "CryptographicDomain"
    ],
    "implemented_in_layer": [],
    "source": [
      "ISO/IEC 23257:2021",
      "IEEE 2418.1",
      "NIST NISTIR"
    ],
    "other_relationships": {
      "bridges-to": [
        "Networkcomponent",
        "BlockchainEntity"
      ]
    },
    "validation": {
      "is_valid": false,
      "errors": [
        "owl:class namespace 'bc' doesn't match source-domain 'blockchain'"
      ]
    }
  }
}