{
  "id": "Dropout",
  "title": "Dropout",
  "content": "- ### OntologyBlock\n  id:: dropout-ontology\n  collapsed:: true\n\t- ontology:: true\n\t- term-id:: AI-0057\n\t- preferred-term:: Dropout\n\t- source-domain:: metaverse\n\t- status:: draft\n    - public-access:: true\n\t- definition:: ### Primary Definition\n**Dropout** is a regularisation technique that randomly deactivates (drops) a fraction of neurons during each training iteration, preventing co-adaptation and reducing overfitting. Dropout rate (typically 0.2-0.5) controls the fraction of neurons dropped.\n\t- maturity:: draft\n\t- owl:class:: mv:Dropout\n\t- owl:physicality:: ConceptualEntity\n\t- owl:role:: Concept\n\t- is-subclass-of:: [[ArtificialIntelligence]]\n\t- belongsToDomain:: [[MetaverseDomain]]",
  "backlinks": [],
  "wiki_links": [
    "ArtificialIntelligence",
    "MetaverseDomain"
  ],
  "ontology": {
    "term_id": "AI-0057",
    "preferred_term": "Dropout",
    "alt_terms": [],
    "iri": "http://narrativegoldmine.com/metaverse#Dropout",
    "source_domain": "metaverse",
    "domain": "metaverse",
    "domain_full_name": "",
    "definition": "### Primary Definition",
    "scope_note": null,
    "status": "draft",
    "maturity": "draft",
    "version": null,
    "public_access": true,
    "last_updated": null,
    "authority_score": null,
    "quality_score": null,
    "cross_domain_links": null,
    "owl_class": "mv:Dropout",
    "owl_physicality": "ConceptualEntity",
    "owl_role": "Concept",
    "owl_inferred_class": null,
    "is_subclass_of": [],
    "has_part": [],
    "is_part_of": [],
    "requires": [],
    "depends_on": [],
    "enables": [],
    "relates_to": [],
    "bridges_to": [],
    "bridges_from": [],
    "domain_extensions": {},
    "belongs_to_domain": [
      "MetaverseDomain"
    ],
    "implemented_in_layer": [],
    "source": [],
    "validation": {
      "is_valid": false,
      "errors": [
        "Missing required property: last-updated",
        "Missing required property: is-subclass-of (at least one parent class)",
        "owl:class namespace 'mv' doesn't match source-domain 'metaverse'"
      ]
    }
  }
}