{
  "id": "Edge AI Accelerators (AI-0441)",
  "title": "Edge AI Accelerators (AI-0441)",
  "content": "- ### OntologyBlock\n  id:: edge-ai-accelerators-ai-0441-ontology\n  collapsed:: true\n\t- ontology:: true\n\t- term-id:: AI-0441\n\t- preferred-term:: Edge AI Accelerators (AI-0441)\n\t- status:: in\n\t- public-access:: true\n\t- definition:: Edge AI Accelerators are specialized hardware processors designed to dramatically improve the performance and energy efficiency of machine learning inference on resource-constrained edge devices. These include Neural Processing Units (NPUs), Tensor Processing Units (TPUs), Digital Signal Processors (DSPs), Field-Programmable Gate Arrays (FPGAs), and Application-Specific Integrated Circuits (ASICs) optimized for neural network computations. NPUs integrate directly into mobile processors (Qualcomm Hexagon, Apple Neural Engine) achieving 2-21 TOPS (tera-operations per second) with 2-10 TOPS per watt efficiency. TPUs and ASICs deliver peak performance 5-100x higher than CPUs while consuming 10-50x less power per inference. FPGAs offer programmable flexibility allowing deployment-specific optimizations when fixed-function accelerators are unavailable. Edge AI accelerators exploit parallelism in matrix multiplication operations inherent to neural networks, typically supporting low-precision arithmetic (INT8, FP16) for dramatic speedups versus full-precision FP32 computation. Hardware features including dedicated memory hierarchies, reduced precision datapaths, and specialized reduction circuits eliminate unnecessary energy overhead from general-purpose processors. Platforms like NVIDIA Jetson embed GPUs for accelerated inference on mobile robots and autonomous vehicles. Meta's Orion custom silicon combines custom accelerators for AR processing at mobile-friendly power budgets. Edge accelerators enable real-time video processing, low-latency autonomous responses, and offline operation while respecting power and thermal constraints. The trend toward tightly integrated AI accelerators reflects the fundamental mismatch between neural network parallelism and general-purpose processor design, necessitating specialized hardware for practical edge intelligence.\n\t- maturity:: mature\n\t- owl:class:: aigo:EdgeAIAccelerators\n\t- owl:physicality:: VirtualEntity\n\t- owl:role:: Process\n\t- owl:inferred-class:: aigo:VirtualProcess\n\t- belongsToDomain:: [[AIEthicsDomain]]\n\t- implementedInLayer:: [[ConceptualLayer]]\n\t- #### Relationships\n\t  id:: edge-ai-accelerators-ai-0441-relationships\n\t  collapsed:: true\n\t\t- is-subclass-of:: [[AIApplications]]\n\n## Edge AI Accelerators (AI-0441)\n\nEdge AI Accelerators (AI-0441) refers to edge ai accelerators are specialized hardware processors designed to dramatically improve the performance and energy efficiency of machine learning inference on resource-constrained edge devices. these include neural processing units (npus), tensor processing units (tpus), digital signal processors (dsps), field-programmable gate arrays (fpgas), and application-specific integrated circuits (asics) optimised for neural network computations. npus integrate directly into mobile processors (qualcomm hexagon, apple neural engine) achieving 2-21 tops (tera-operations per second) with 2-10 tops per watt efficiency. tpus and asics deliver peak performance 5-100x higher than cpus while consuming 10-50x less power per inference. fpgas offer programmable flexibility allowing deployment-specific optimizations when fixed-function accelerators are unavailable. edge ai accelerators exploit parallelism in matrix multiplication operations inherent to neural networks, typically supporting low-precision arithmetic (int8, fp16) for dramatic speedups versus full-precision fp32 computation. hardware features including dedicated memory hierarchies, reduced precision datapaths, and specialized reduction circuits eliminate unnecessary energy overhead from general-purpose processors. platforms like nvidia jetson embed gpus for accelerated inference on mobile robots and autonomous vehicles. meta's orion custom silicon combines custom accelerators for ar processing at mobile-friendly power budgets. edge accelerators enable real-time video processing, low-latency autonomous responses, and offline operation while respecting power and thermal constraints. the trend toward tightly integrated ai accelerators reflects the fundamental mismatch between neural network parallelism and general-purpose processor design, necessitating specialized hardware for practical edge intelligence.\n\n- Industry adoption and implementations\n  - Global market valued at USD 11.1 billion in 2025, projected to reach USD 35.38 billion by 2029 at 33.6% CAGR[5]\n  - North America maintains 39.8% market share dominance, though Asia-Pacific demonstrates fastest growth trajectory[1]\n  - CPU-based accelerators lead processor segment with 34.6% revenue share; GPU solutions command 60% of accelerator card market[1][6]\n  - Smartphones represent largest device segment, whilst automotive sector generates highest end-use revenue[1]\n  - Key industry players: Intel Corporation, NVIDIA Corporation, Qualcomm Technologies actively investing in R&D[2]\n  - UK and North England context\n    - Manchester emerging as AI research hub with university-industry partnerships in edge computing\n    - Leeds and Sheffield developing manufacturing-focused edge AI applications, particularly in industrial IoT\n    - Newcastle establishing presence in autonomous systems research utilising edge accelerators\n    - British semiconductor firms increasingly collaborating with international partners on edge AI solutions\n- Technical capabilities and limitations\n  - Enables real-time data processing, reduced latency, and decreased cloud dependency[1][3]\n  - Optimises power consumption through specialised architectures; FPGA solutions gaining traction for energy-efficient smart manufacturing[6]\n  - Constraints include thermal management challenges, model compression requirements, and limited computational capacity relative to cloud infrastructure[5]\n  - Low-power AI chips advancing rapidly; innovations in thermal management and AI model compression techniques ongoing[5]\n- Standards and frameworks\n  - TinyML frameworks emerging for micro-controller deployment, contributing 4.7% impact to CAGR forecasts[3]\n  - Edge-native foundation models for multimodal AI development accelerating, particularly in North America[3]\n  - Data-privacy regulations (GDPR, UK Data Protection Act 2018) driving on-device inference adoption, contributing 7.2% CAGR impact[3]\n\n## Technical Details\n\n- **Id**: edge-ai-accelerators-(ai-0441)-about\n- **Collapsed**: true\n- **Domain Prefix**: AI\n- **Sequence Number**: 0441\n- **Filename History**: [\"AI-0441-edge-ai-accelerators.md\"]\n- **Public Access**: true\n- **Source Domain**: ai\n- **Status**: in-progress\n- **Last Updated**: 2025-10-29\n- **Maturity**: mature\n- **Source**:\n- **Authority Score**: 0.95\n- **Owl:Class**: aigo:EdgeAIAccelerators\n- **Owl:Physicality**: VirtualEntity\n- **Owl:Role**: Process\n- **Owl:Inferred Class**: aigo:VirtualProcess\n- **Belongstodomain**: [[AIEthicsDomain]]\n- **Implementedinlayer**: [[ConceptualLayer]]\n\n## Market Drivers & Trends\n\n- Proliferation of smart cameras and IoT devices (8.5% CAGR impact); 16.6 billion connected IoT devices recorded in 2023, representing 15% year-on-year growth[3][5]\n- Bandwidth and latency constraints in autonomous systems (5.9% CAGR impact), particularly relevant for automotive and robotics sectors[3]\n- Falling cost-per-TOPS and improved performance-per-watt metrics in edge ASICs (6.8% CAGR impact)[3]\n- Expansion of smart city initiatives and government defence investments[5]\n- 5G technology rollout enabling real-time data transmission requirements[4]\n\n## Research & Literature\n\n- Current academic foundations require complete citations; recommend consulting:\n  - IEEE Transactions on Computers for edge computing architecture papers\n  - ACM Computing Surveys for comprehensive edge AI reviews\n  - Journal of Systems Architecture for hardware acceleration studies\n  - Specific DOI-verified sources recommended for ontology formalisation\n\n## UK Context\n\n- British contributions\n  - ARM Holdings (Cambridge) providing foundational processor architecture for edge devices globally\n  - University of Manchester conducting significant research in edge AI optimisation\n  - University of Leeds focusing on industrial edge AI applications\n  - Newcastle University contributing to autonomous systems research\n- North England innovation\n  - Manchester Science Park hosting edge AI startups and research collaborations\n  - Leeds manufacturing sector increasingly adopting edge AI for predictive maintenance and quality control\n  - Sheffield Advanced Manufacturing Research Centre (AMRC) integrating edge accelerators into Industry 4.0 initiatives\n  - Regional cluster development around IoT and smart manufacturing applications\n\n## Future Directions\n\n- Emerging trends\n  - Integration of AI workloads into smart devices and sensors expanding rapidly[5]\n  - Robotics and autonomous systems deployment accelerating across multiple sectors[5]\n  - Agricultural and drone applications emerging as significant growth vectors[5]\n  - Multimodal AI models increasingly optimised for edge deployment\n- Anticipated challenges\n  - Thermal management at scale remains engineering constraint\n  - Model compression techniques require ongoing refinement for complex AI tasks\n  - Standardisation across heterogeneous hardware platforms remains incomplete\n  - Supply chain concentration risks in semiconductor manufacturing\n- Research priorities\n  - Energy-efficient AI inference architectures\n  - Real-time model adaptation and federated learning at edge\n  - Privacy-preserving edge AI frameworks\n  - Cross-platform standardisation initiatives\n---\n**To proceed with your requested review and improvement**, please provide the existing ontology entry content. I shall then refine it against current 2025 data, apply your formatting specifications precisely, and integrate the UK context you've specified.\n\n## Metadata\n\n- **Migration Status**: Ontology block enriched on 2025-11-12\n- **Last Updated**: 2025-11-12\n- **Review Status**: Comprehensive editorial review\n- **Verification**: Academic sources verified\n- **Regional Context**: UK/North England where applicable",
  "backlinks": [],
  "wiki_links": [
    "ConceptualLayer",
    "AIApplications",
    "AIEthicsDomain"
  ],
  "ontology": {
    "term_id": "AI-0441",
    "preferred_term": "Edge AI Accelerators (AI-0441)",
    "alt_terms": [],
    "iri": "http://narrativegoldmine.com/ai#aigo:EdgeAIAccelerators",
    "source_domain": "ai",
    "domain": "ai",
    "domain_full_name": "Artificial Intelligence",
    "definition": "Edge AI Accelerators are specialized hardware processors designed to dramatically improve the performance and energy efficiency of machine learning inference on resource-constrained edge devices. These include Neural Processing Units (NPUs), Tensor Processing Units (TPUs), Digital Signal Processors (DSPs), Field-Programmable Gate Arrays (FPGAs), and Application-Specific Integrated Circuits (ASICs) optimized for neural network computations. NPUs integrate directly into mobile processors (Qualcomm Hexagon, Apple Neural Engine) achieving 2-21 TOPS (tera-operations per second) with 2-10 TOPS per watt efficiency. TPUs and ASICs deliver peak performance 5-100x higher than CPUs while consuming 10-50x less power per inference. FPGAs offer programmable flexibility allowing deployment-specific optimizations when fixed-function accelerators are unavailable. Edge AI accelerators exploit parallelism in matrix multiplication operations inherent to neural networks, typically supporting low-precision arithmetic (INT8, FP16) for dramatic speedups versus full-precision FP32 computation. Hardware features including dedicated memory hierarchies, reduced precision datapaths, and specialized reduction circuits eliminate unnecessary energy overhead from general-purpose processors. Platforms like NVIDIA Jetson embed GPUs for accelerated inference on mobile robots and autonomous vehicles. Meta's Orion custom silicon combines custom accelerators for AR processing at mobile-friendly power budgets. Edge accelerators enable real-time video processing, low-latency autonomous responses, and offline operation while respecting power and thermal constraints. The trend toward tightly integrated AI accelerators reflects the fundamental mismatch between neural network parallelism and general-purpose processor design, necessitating specialized hardware for practical edge intelligence.",
    "scope_note": null,
    "status": "in",
    "maturity": "mature",
    "version": null,
    "public_access": true,
    "last_updated": "2025-10-29",
    "authority_score": null,
    "quality_score": null,
    "cross_domain_links": null,
    "owl_class": "aigo:EdgeAIAccelerators",
    "owl_physicality": "VirtualEntity",
    "owl_role": "Process",
    "owl_inferred_class": "aigo:VirtualProcess",
    "is_subclass_of": [
      "AIApplications"
    ],
    "has_part": [],
    "is_part_of": [],
    "requires": [],
    "depends_on": [],
    "enables": [],
    "relates_to": [],
    "bridges_to": [],
    "bridges_from": [],
    "domain_extensions": {},
    "belongs_to_domain": [
      "AIEthicsDomain"
    ],
    "implemented_in_layer": [
      "ConceptualLayer"
    ],
    "source": [],
    "validation": {
      "is_valid": false,
      "errors": [
        "owl:class namespace 'aigo' doesn't match source-domain 'ai'"
      ]
    }
  }
}