{
  "id": "Edge AI System (AI-0431)",
  "title": "Edge AI System (AI-0431)",
  "content": "- ### OntologyBlock\n  id:: edge-ai-system-ai-0431-ontology\n  collapsed:: true\n\t- ontology:: true\n\t- term-id:: AI-0431\n\t- preferred-term:: Edge AI System (AI-0431)\n\t- status:: in\n\t- public-access:: true\n\t- definition:: An Edge AI System is a distributed computing architecture that deploys machine learning models directly onto edge devices and sensors at the network periphery, enabling local inference without requiring continuous cloud connectivity. These systems process data in real-time at the source, reducing latency to milliseconds while minimizing bandwidth consumption and cloud dependency. Edge AI Systems optimize for resource-constrained environments with limited memory (typically 128KB-512MB), power budgets (10-100mW), and computational capacity compared to data centers. They incorporate model compression techniques including quantization, pruning, and knowledge distillation to fit neural networks into embedded hardware. Core characteristics include deterministic latency guarantees, offline-capable operation, privacy preservation through local processing, and direct sensor-to-actuator decision loops. Edge AI Systems span diverse deployment scenarios: industrial IoT monitoring for predictive maintenance, autonomous vehicle perception pipelines, smart home voice processing, medical wearables, drone navigation, and surveillance analytics. The architecture balances accuracy against resource constraints through adaptive model selection, hierarchical processing, and strategic cloud-edge collaboration for complex inference tasks. Standards like IEEE P2956 and IEC 63296 provide architectural frameworks. Edge AI Systems represent the convergence of embedded systems, machine learning, and real-time computing, enabling intelligent autonomous operations across distributed networks with minimal human intervention.\n\t- maturity:: mature\n\t- owl:class:: aigo:EdgeAISystem\n\t- owl:physicality:: VirtualEntity\n\t- owl:role:: Process\n\t- owl:inferred-class:: aigo:VirtualProcess\n\t- belongsToDomain:: [[AIEthicsDomain]]\n\t- implementedInLayer:: [[ConceptualLayer]]\n\t- #### Relationships\n\t  id:: edge-ai-system-ai-0431-relationships\n\t  collapsed:: true\n\t\t- is-subclass-of:: [[AIApplications]]\n\n## Edge AI System (AI-0431)\n\nEdge AI System (AI-0431) refers to an edge ai system is a distributed computing architecture that deploys machine learning models directly onto edge devices and sensors at the network periphery, enabling local inference without requiring continuous cloud connectivity. these systems process data in real-time at the source, reducing latency to milliseconds while minimising bandwidth consumption and cloud dependency. edge ai systems optimise for resource-constrained environments with limited memory (typically 128kb-512mb), power budgets (10-100mw), and computational capacity compared to data centres. they incorporate model compression techniques including quantization, pruning, and knowledge distillation to fit neural networks into embedded hardware. core characteristics include deterministic latency guarantees, offline-capable operation, privacy preservation through local processing, and direct sensor-to-actuator decision loops. edge ai systems span diverse deployment scenarios: industrial iot monitoring for predictive maintenance, autonomous vehicle perception pipelines, smart home voice processing, medical wearables, drone navigation, and surveillance analytics. the architecture balances accuracy against resource constraints through adaptive model selection, hierarchical processing, and strategic cloud-edge collaboration for complex inference tasks. standards like ieee p2956 and iec 63296 provide architectural frameworks. edge ai systems represent the convergence of embedded systems, machine learning, and real-time computing, enabling intelligent autonomous operations across distributed networks with minimal human intervention.\n\n- Industry adoption of Edge AI has accelerated significantly, with estimates suggesting that by 2025, approximately 75% of data generated by IoT devices is processed at the edge rather than in the cloud.\n  - Notable implementations span sectors such as manufacturing (Industry 4.0), smart cities, energy grids, healthcare, and autonomous vehicles.\n  - Leading organisations and platforms include Advantech, Nutanix, and Arm, which provide hardware and software solutions tailored for edge AI deployment.\n- In the UK, especially in North England cities like Manchester, Leeds, Newcastle, and Sheffield, Edge AI is increasingly embedded in smart infrastructure projects, advanced manufacturing, and energy management systems.\n  - For example, smart traffic monitoring and energy grid resilience initiatives leverage Edge AI to enable real-time responsiveness and reduce network strain.\n- Technical capabilities now include real-time inference on-device, advanced preprocessing to reduce data volume, and hybrid cloud-edge architectures for model updates and continuous learning.\n  - Limitations remain in computational power constraints on edge devices and the need for optimised, lightweight AI models.\n- Standards and frameworks are evolving to address interoperability, security, and privacy concerns, with growing emphasis on UK and EU regulatory compliance.\n\n## Technical Details\n\n- **Id**: edge-ai-system-(ai-0431)-about\n- **Collapsed**: true\n- **Domain Prefix**: AI\n- **Sequence Number**: 0431\n- **Filename History**: [\"AI-0431-edge-ai-system.md\"]\n- **Public Access**: true\n- **Source Domain**: ai\n- **Status**: in-progress\n- **Last Updated**: 2025-10-29\n- **Maturity**: mature\n- **Source**:\n- **Authority Score**: 0.95\n- **Owl:Class**: aigo:EdgeAISystem\n- **Owl:Physicality**: VirtualEntity\n- **Owl:Role**: Process\n- **Owl:Inferred Class**: aigo:VirtualProcess\n- **Belongstodomain**: [[AIEthicsDomain]]\n- **Implementedinlayer**: [[ConceptualLayer]]\n\n## Research & Literature\n\n- Key academic sources include:\n  - Shi, W., Cao, J., Zhang, Q., Li, Y., & Xu, L. (2016). Edge Computing: Vision and Challenges. *IEEE Internet of Things Journal*, 3(5), 637-646. https://doi.org/10.1109/JIOT.2016.2579198\n  - Satyanarayanan, M. (2017). The Emergence of Edge Computing. *Computer*, 50(1), 30-39. https://doi.org/10.1109/MC.2017.9\n  - Zhang, K., Mao, Y., Leng, S., Maharjan, S., & Zhang, Y. (2019). Mobile Edge Computing and Networking for Green and Low-Latency Internet of Things. *IEEE Communications Magazine*, 56(5), 39-45. https://doi.org/10.1109/MCOM.2018.1800133\n- Ongoing research focuses on:\n  - Developing ultra-efficient AI models for constrained edge hardware.\n  - Enhancing security and privacy-preserving techniques for edge AI.\n  - Hybrid cloud-edge learning frameworks enabling continuous model adaptation.\n  - Application-specific optimisations in sectors like energy, healthcare, and transport.\n\n## UK Context\n\n- The UK has made significant strides in Edge AI research and deployment, supported by government initiatives and industry partnerships.\n  - The Alan Turing Institute and UK Research and Innovation (UKRI) fund projects exploring edge AI applications in smart cities and healthcare.\n- North England serves as a vibrant innovation hub, with cities such as Manchester and Leeds hosting clusters of AI startups and research centres focusing on edge computing.\n  - Sheffield’s advanced manufacturing sector integrates Edge AI to optimise production lines and predictive maintenance.\n  - Newcastle’s energy sector leverages edge AI for grid management and renewable integration.\n- Regional case studies include smart traffic systems in Manchester utilising edge AI for real-time vehicle and pedestrian detection, reducing congestion and improving safety.\n\n## Future Directions\n\n- Emerging trends include:\n  - The rise of federated learning at the edge to enhance privacy and reduce data movement.\n  - Integration of 5G and beyond networks to improve edge AI connectivity and responsiveness.\n  - Expansion of edge AI into new domains such as augmented reality and personalised healthcare.\n- Anticipated challenges:\n  - Balancing computational demands with energy efficiency on edge devices.\n  - Ensuring robust security against increasingly sophisticated cyber threats.\n  - Navigating regulatory frameworks that vary across regions, including the UK and EU.\n- Research priorities:\n  - Designing adaptable AI models that can operate reliably across heterogeneous edge environments.\n  - Developing standardised protocols for edge AI deployment and interoperability.\n  - Investigating socio-technical impacts, including ethical considerations and workforce implications.\n\n## References\n\n1. Shi, W., Cao, J., Zhang, Q., Li, Y., & Xu, L. (2016). Edge Computing: Vision and Challenges. *IEEE Internet of Things Journal*, 3(5), 637-646. https://doi.org/10.1109/JIOT.2016.2579198\n2. Satyanarayanan, M. (2017). The Emergence of Edge Computing. *Computer*, 50(1), 30-39. https://doi.org/10.1109/MC.2017.9\n3. Zhang, K., Mao, Y., Leng, S., Maharjan, S., & Zhang, Y. (2019). Mobile Edge Computing and Networking for Green and Low-Latency Internet of Things. *IEEE Communications Magazine*, 56(5), 39-45. https://doi.org/10.1109/MCOM.2018.1800133\n4. Advantech. (2025). AI at the Edge Explained: Benefits, Uses & More. Retrieved November 2025, from Advantech website.\n5. Nutanix. (2025). Edge AI: Definitions, Advantages, Use Cases. Retrieved November 2025, from Nutanix website.\n6. World Economic Forum. (2025). Why edge AI is now crucial for powering the global grid. Retrieved November 2025.\n7. Fabrity. (2025). Edge AI technology: driving Industry 4.0 in 2025. Retrieved November 2025.\n\n## Metadata\n\n- **Migration Status**: Ontology block enriched on 2025-11-12\n- **Last Updated**: 2025-11-12\n- **Review Status**: Comprehensive editorial review\n- **Verification**: Academic sources verified\n- **Regional Context**: UK/North England where applicable",
  "backlinks": [],
  "wiki_links": [
    "ConceptualLayer",
    "AIApplications",
    "AIEthicsDomain"
  ],
  "ontology": {
    "term_id": "AI-0431",
    "preferred_term": "Edge AI System (AI-0431)",
    "alt_terms": [],
    "iri": "http://narrativegoldmine.com/ai#aigo:EdgeAISystem",
    "source_domain": "ai",
    "domain": "ai",
    "domain_full_name": "Artificial Intelligence",
    "definition": "An Edge AI System is a distributed computing architecture that deploys machine learning models directly onto edge devices and sensors at the network periphery, enabling local inference without requiring continuous cloud connectivity. These systems process data in real-time at the source, reducing latency to milliseconds while minimizing bandwidth consumption and cloud dependency. Edge AI Systems optimize for resource-constrained environments with limited memory (typically 128KB-512MB), power budgets (10-100mW), and computational capacity compared to data centers. They incorporate model compression techniques including quantization, pruning, and knowledge distillation to fit neural networks into embedded hardware. Core characteristics include deterministic latency guarantees, offline-capable operation, privacy preservation through local processing, and direct sensor-to-actuator decision loops. Edge AI Systems span diverse deployment scenarios: industrial IoT monitoring for predictive maintenance, autonomous vehicle perception pipelines, smart home voice processing, medical wearables, drone navigation, and surveillance analytics. The architecture balances accuracy against resource constraints through adaptive model selection, hierarchical processing, and strategic cloud-edge collaboration for complex inference tasks. Standards like IEEE P2956 and IEC 63296 provide architectural frameworks. Edge AI Systems represent the convergence of embedded systems, machine learning, and real-time computing, enabling intelligent autonomous operations across distributed networks with minimal human intervention.",
    "scope_note": null,
    "status": "in",
    "maturity": "mature",
    "version": null,
    "public_access": true,
    "last_updated": "2025-10-29",
    "authority_score": null,
    "quality_score": null,
    "cross_domain_links": null,
    "owl_class": "aigo:EdgeAISystem",
    "owl_physicality": "VirtualEntity",
    "owl_role": "Process",
    "owl_inferred_class": "aigo:VirtualProcess",
    "is_subclass_of": [
      "AIApplications"
    ],
    "has_part": [],
    "is_part_of": [],
    "requires": [],
    "depends_on": [],
    "enables": [],
    "relates_to": [],
    "bridges_to": [],
    "bridges_from": [],
    "domain_extensions": {},
    "belongs_to_domain": [
      "AIEthicsDomain"
    ],
    "implemented_in_layer": [
      "ConceptualLayer"
    ],
    "source": [],
    "validation": {
      "is_valid": false,
      "errors": [
        "owl:class namespace 'aigo' doesn't match source-domain 'ai'"
      ]
    }
  }
}