{
  "id": "Encoder-Decoder Architecture",
  "title": "Encoder-Decoder Architecture",
  "content": "- ### OntologyBlock\n  id:: encoder-decoder-architecture-ontology\n  collapsed:: true\n\t- ontology:: true\n\t- term-id:: AI-0207\n\t- preferred-term:: Encoder-Decoder Architecture\n\t- status:: approved\n\t- public-access:: true\n\t- definition:: A neural network structure consisting of an encoder that processes the input sequence and a decoder that generates the output sequence, commonly used in sequence-to-sequence tasks.\n\t- source:: [[Sutskever et al. 2014 Sequence to Sequence Learning]], [[Vaswani et al. 2017 Attention is All You Need]], [[Raffel et al. 2020 T5]], [[Lewis et al. 2020 BART]]\n\t- maturity:: mature\n\t- #### Relationships\n\t  id:: encoder-decoder-architecture-relationships\n\t  collapsed:: true\n\t\t- is-subclass-of:: [[ModelArchitecture]]\n\n## Encoder Decoder Architecture\n\nEncoder Decoder Architecture refers to a neural network structure consisting of an encoder that processes the input sequence and a decoder that generates the output sequence, commonly used in sequence-to-sequence tasks.\n\n- Foundational neural network paradigm for sequence-to-sequence tasks\n  - Emerged as transformative approach for handling variable-length input and output sequences\n  - Enables complex mappings between sequential data domains (translation, summarisation, speech recognition)\n  - Architecture separates concerns elegantly: encoding (compression) and decoding (generation)\n- Core innovation: context vector as compressed numerical representation\n  - Captures essential information from input whilst discarding redundancy\n  - Allows model to process sequences of arbitrary length\n  - Particularly effective when combined with attention mechanisms\n\n## Technical Details\n\n- **Id**: encoder-decoder-architecture-ontology\n- **Collapsed**: true\n- **Source Domain**: ai\n- **Status**: draft\n- **Public Access**: true\n\n## Current Landscape (2025)\n\n- Industry adoption and implementations\n  - Powers major translation services (Google Translate and similar platforms)[2]\n  - Enables conversational AI and human-like chatbot systems[2]\n  - Fundamental to modern large language model architectures\n  - Widely deployed across commercial NLP applications\n- Technical capabilities and limitations\n  - Handles variable-length sequences effectively through encoder-decoder separation[1]\n  - Learns complex mappings via recurrent neural networks (RNNs, LSTMs, GRUs) or Transformer variants[1][3]\n  - Self-attention layers enable contextual understanding of relationships between input elements[3]\n  - Encoder-decoder attention mechanism allows decoder to focus on relevant input portions during generation[4]\n  - Causally masked self-attention in decoder prevents information leakage from future tokens[4]\n- Standards and frameworks\n  - Transformer architecture represents current state-of-the-art implementation[4][5]\n  - Multi-head attention mechanisms standardised across implementations\n  - Embedding layers (token and positional) now standard practice[5]\n  - Cross-attention mechanisms enable sophisticated encoder-decoder interaction\n\n## Research & Literature\n\n- Key academic papers and sources\n  - Transformer architecture foundations: attention-based encoder-decoder design with multi-head mechanisms[4]\n  - Encoder-decoder models for NLP: comprehensive treatment of architecture components and training methodologies[1][3]\n  - Recent developments: TreeGPT explores attention-free encoder-decoder variants using pure TreeFFN design[7]\n- Training and optimisation approaches\n  - Teacher forcing: providing ground truth output tokens during training to stabilise learning[1]\n  - Backpropagation through time: weight updates based on temporal gradient propagation[1]\n  - Loss functions: cross-entropy and mean squared error for sequence prediction tasks[1]\n  - Regularisation: dropout and L1/L2 techniques improve generalisation[1]\n  - Optimisation algorithms: Adam and SGD widely employed[1]\n\n## Technical Architecture Details\n\n- Encoder component\n  - Processes input sequence to extract essential information\n  - Produces context vector (compressed representation) from final hidden state[2]\n  - For text: RNNs, LSTMs, GRUs capture sequential dependencies[2]\n  - For images: CNNs progressively reduce spatial dimensions whilst increasing feature channels[2]\n  - Self-attention layer enables focus on contextually important input portions[3]\n  - Feed-forward neural network captures complex patterns and relationships[3]\n- Decoder component\n  - Receives context vector and generates output sequence step-by-step\n  - For text: predicts words based on previous outputs whilst maintaining fluency[2]\n  - For images: reconstructs or generates through upsampling and transpose convolutional layers[2]\n  - Self-attention layer focuses on generated output portions[3]\n  - Encoder-decoder attention layer (cross-attention) focuses on relevant input data[3][4]\n  - Feed-forward network processes information for final output generation[3]\n  - Causally masked self-attention prevents attending to future tokens[4]\n  - Autoregressive generation: samples tokens according to probability distribution, iteratively producing output[4]\n\n## UK Context\n\n- British academic contributions\n  - Significant research contributions from UK universities in transformer and attention mechanism development\n  - Active research communities in NLP and deep learning across Russell Group institutions\n- North England innovation\n  - Manchester and Leeds host substantial AI research programmes\n  - Growing technology sector engagement with encoder-decoder applications in commercial NLP\n  - Sheffield and Newcastle contribute to broader machine learning research ecosystem\n- Industrial applications\n  - UK technology companies increasingly adopt encoder-decoder architectures for translation and summarisation services\n  - Financial services sector utilises these models for document processing and analysis\n\n## Future Directions\n\n- Emerging trends and developments\n  - Attention-free alternatives gaining traction (TreeGPT and similar architectures)[7]\n  - Hybrid approaches combining traditional encoder-decoder with novel neural designs\n  - Efficiency improvements for deployment on resource-constrained devices\n  - Multimodal extensions handling diverse input types (text, image, audio simultaneously)\n- Anticipated challenges\n  - Computational cost of training large-scale models remains significant\n  - Context vector bottleneck in traditional architectures (though attention mechanisms mitigate this)\n  - Interpretability of attention mechanisms still requires substantial research\n  - Generalisation to out-of-distribution sequences remains problematic\n- Research priorities\n  - More efficient attention mechanisms reducing computational complexity\n  - Better handling of extremely long sequences\n  - Improved cross-lingual and cross-modal transfer learning\n  - Robustness to adversarial inputs and distribution shifts\n---\n**Note on improvements made:** The original definition, whilst accurate, understated the architectural sophistication. The revised entry reflects 2025 understanding of encoder-decoder systems, emphasising attention mechanisms and modern Transformer implementations rather than earlier RNN-centric approaches. UK context has been integrated where relevant, though the encoder-decoder architecture remains fundamentally international in its development and deployment. The somewhat amusing reality is that despite decades of neural network research, the basic encoder-decoder principle—compress then expand—remains elegantly simple, even as implementations have grown considerably more sophisticated.\n\n## Metadata\n\n- **Last Updated**: 2025-11-11\n- **Review Status**: Comprehensive editorial review\n- **Verification**: Academic sources verified\n- **Regional Context**: UK/North England where applicable",
  "backlinks": [
    "Recurrent Neural Network"
  ],
  "wiki_links": [
    "ModelArchitecture",
    "Lewis et al. 2020 BART",
    "Sutskever et al. 2014 Sequence to Sequence Learning",
    "Vaswani et al. 2017 Attention is All You Need",
    "Raffel et al. 2020 T5"
  ],
  "ontology": {
    "term_id": "AI-0207",
    "preferred_term": "Encoder-Decoder Architecture",
    "alt_terms": [],
    "iri": null,
    "source_domain": "ai",
    "domain": "ai",
    "domain_full_name": "Artificial Intelligence",
    "definition": "A neural network structure consisting of an encoder that processes the input sequence and a decoder that generates the output sequence, commonly used in sequence-to-sequence tasks.",
    "scope_note": null,
    "status": "approved",
    "maturity": "mature",
    "version": null,
    "public_access": true,
    "last_updated": null,
    "authority_score": null,
    "quality_score": null,
    "cross_domain_links": null,
    "owl_class": null,
    "owl_physicality": null,
    "owl_role": null,
    "owl_inferred_class": null,
    "is_subclass_of": [
      "ModelArchitecture"
    ],
    "has_part": [],
    "is_part_of": [],
    "requires": [],
    "depends_on": [],
    "enables": [],
    "relates_to": [],
    "bridges_to": [],
    "bridges_from": [],
    "domain_extensions": {},
    "belongs_to_domain": [],
    "implemented_in_layer": [],
    "source": [
      "Sutskever et al. 2014 Sequence to Sequence Learning",
      "Vaswani et al. 2017 Attention is All You Need",
      "Raffel et al. 2020 T5",
      "Lewis et al. 2020 BART"
    ],
    "validation": {
      "is_valid": false,
      "errors": [
        "Missing required property: last-updated",
        "Missing required property: owl:class",
        "Missing required property: owl:physicality",
        "Missing required property: owl:role"
      ]
    }
  }
}