{
  "id": "Environmental Sustainability Label",
  "title": "Environmental Sustainability Label",
  "content": "- ### OntologyBlock\n  id:: environmental-sustainability-label-ontology\n  collapsed:: true\n\t- ontology:: true\n\t- term-id:: 20225\n\t- preferred-term:: Environmental Sustainability Label\n\t- status:: draft\n\t- public-access:: true\n\t- definition:: Certification process and label indicating compliance with environmental sustainability standards for digital infrastructure, energy consumption, and carbon footprint in metaverse operations.\n\t- source:: [[ISO 14021]]\n\t- maturity:: mature\n\t- owl:class:: mv:EnvironmentalSustainabilityLabel\n\t- owl:physicality:: VirtualEntity\n\t- owl:role:: Process\n\t- owl:inferred-class:: mv:VirtualProcess\n\t- owl:functional-syntax:: true\n\t- belongsToDomain:: [[TrustAndGovernanceDomain]]\n\t- implementedInLayer:: [[Middleware Layer]]\n\t- #### Relationships\n\t  id:: environmental-sustainability-label-relationships\n\t  collapsed:: true\n\t\t- is-part-of:: [[Sustainability Compliance System]]\n\t\t- is-part-of:: [[Governance Framework]]\n\t\t- has-part:: [[Compliance Verification]]\n\t\t- has-part:: [[Energy Consumption Audit]]\n\t\t- has-part:: [[Certification Issuance]]\n\t\t- has-part:: [[Carbon Footprint Assessment]]\n\t\t- requires:: [[Infrastructure Metrics]]\n\t\t- requires:: [[Third-Party Auditor]]\n\t\t- requires:: [[Energy Monitoring System]]\n\t\t- requires:: [[Carbon Accounting]]\n\t\t- enables:: [[Carbon Neutrality Verification]]\n\t\t- enables:: [[Green Infrastructure Certification]]\n\t\t- enables:: [[User Trust Building]]\n\t\t- enables:: [[Sustainability Reporting]]\n\t\t- depends-on:: [[Environmental Standards]]\n\t\t- depends-on:: [[Measurement Protocols]]\n\n## Academic Context\n\n- Environmental sustainability labels serve as certification mechanisms indicating compliance with established environmental standards, particularly for digital infrastructure, energy consumption, and carbon footprint management within metaverse operations.\n  - These labels are grounded in sustainability science, environmental management systems, and digital technology governance.\n  - The academic foundation includes studies on eco-label effectiveness, consumer behaviour in digital contexts, and lifecycle assessment of digital infrastructures.\n\n## Current Landscape (2025)\n\n- Industry adoption of environmental sustainability labels in the metaverse is growing, driven by increasing regulatory pressure and consumer demand for transparency.\n  - Notable organisations such as Meta and blockchain platforms like Tezos and EOSIO have integrated sustainability criteria into their operations and certification processes.\n  - NFT marketplaces like Abris.io and KodaDot exemplify sustainable practices by leveraging carbon-negative or low-carbon blockchains.\n- In the UK, and specifically North England, digital innovation hubs in Manchester and Leeds are exploring sustainable metaverse applications, focusing on energy-efficient data centres and green digital services.\n- Technical capabilities include:\n  - Use of energy-efficient Proof of Stake (PoS) blockchains to reduce carbon footprints.\n  - Implementation of carbon labelling for virtual goods and services to inform consumer choices.\n- Limitations remain in standardising metrics across platforms and ensuring verifiable, transparent reporting.\n- Established standards and frameworks include:\n  - Science-based targets aligned with net-zero goals (e.g., Meta’s 2030 net zero commitment).\n  - Emerging meta-sustainability labels that aim to unify diverse sustainability claims under a common, comprehensible certification.\n\n## Research & Literature\n\n- Key academic contributions:\n  - Torma, G., & Thøgersen, J. (2023). *Can a meta sustainability label facilitate more sustainable consumer choices?* Business Strategy and the Environment. DOI: 10.1002/bse.3488\n    - This study evaluates the efficacy of meta-sustainability labels in reducing consumer confusion and enhancing sustainable purchasing decisions.\n  - Lifecycle assessments and carbon accounting methodologies for digital infrastructures are increasingly refined to support label accuracy.\n- Ongoing research focuses on:\n  - Harmonising sustainability criteria across digital platforms.\n  - Behavioural impacts of sustainability labels in virtual environments.\n  - Integration of circular economy principles into digital asset lifecycles.\n\n## UK Context\n\n- The UK government and private sector have prioritised green digital transformation, with initiatives supporting sustainable data centres and low-carbon digital services.\n- North England innovation hubs:\n  - Manchester’s Digital Green Innovation Centre promotes sustainable digital infrastructure.\n  - Leeds hosts research clusters focusing on energy-efficient computing and sustainable blockchain technologies.\n  - Newcastle and Sheffield contribute through academic research and pilot projects in sustainable virtual environments.\n- Regional case studies include collaborative projects between universities and industry to develop eco-certification standards tailored for UK digital ecosystems.\n\n## Future Directions\n\n- Emerging trends:\n  - Development of unified meta-sustainability labels integrating multiple environmental criteria for the metaverse.\n  - Increased use of AI and blockchain for real-time sustainability monitoring and reporting.\n- Anticipated challenges:\n  - Balancing transparency with privacy and proprietary concerns.\n  - Overcoming fragmentation in sustainability standards across jurisdictions and platforms.\n- Research priorities:\n  - Enhancing label credibility through third-party verification.\n  - Exploring user engagement strategies to maximise the behavioural impact of sustainability labels.\n  - Investigating the socio-economic implications of sustainability certifications in digital economies.\n\n## References\n\n1. Torma, G., & Thøgersen, J. (2023). Can a meta sustainability label facilitate more sustainable consumer choices? *Business Strategy and the Environment*. https://doi.org/10.1002/bse.3488\n2. Meta Platforms, Inc. (2025). *Meta 2025 Sustainability Report*. Meta.\n3. VML. (2025). Sustainability in the metaverse. VML Insights.\n4. Hyperspace MV. (2025). Sustainable and eco-friendly metaverse events.\n5. AntiEr Solutions. (2024). How metaverse sustainability is shaping the business landscape.\n\n*If sustainability labels were a fashion statement in the metaverse, they’d be the little black dress — timeless, essential, and surprisingly good at reducing your carbon footprint.*\n\n## Metadata\n\n- **Last Updated**: 2025-11-11\n- **Review Status**: Comprehensive editorial review\n- **Verification**: Academic sources verified\n- **Regional Context**: UK/North England where applicable",
  "backlinks": [],
  "wiki_links": [
    "Third-Party Auditor",
    "User Trust Building",
    "Carbon Accounting",
    "Certification Issuance",
    "Middleware Layer",
    "Carbon Neutrality Verification",
    "Measurement Protocols",
    "TrustAndGovernanceDomain",
    "Energy Monitoring System",
    "Infrastructure Metrics",
    "Green Infrastructure Certification",
    "Environmental Standards",
    "Compliance Verification",
    "ISO 14021",
    "Sustainability Compliance System",
    "Energy Consumption Audit",
    "Carbon Footprint Assessment",
    "Sustainability Reporting",
    "Governance Framework"
  ],
  "ontology": {
    "term_id": "20225",
    "preferred_term": "Environmental Sustainability Label",
    "alt_terms": [],
    "iri": "http://narrativegoldmine.com/metaverse#EnvironmentalSustainabilityLabel",
    "source_domain": null,
    "domain": "mv",
    "domain_full_name": "Metaverse",
    "definition": "Certification process and label indicating compliance with environmental sustainability standards for digital infrastructure, energy consumption, and carbon footprint in metaverse operations.",
    "scope_note": null,
    "status": "draft",
    "maturity": "mature",
    "version": null,
    "public_access": true,
    "last_updated": null,
    "authority_score": null,
    "quality_score": null,
    "cross_domain_links": null,
    "owl_class": "mv:EnvironmentalSustainabilityLabel",
    "owl_physicality": "VirtualEntity",
    "owl_role": "Process",
    "owl_inferred_class": "mv:VirtualProcess",
    "is_subclass_of": [],
    "has_part": [
      "Compliance Verification",
      "Energy Consumption Audit",
      "Certification Issuance",
      "Carbon Footprint Assessment"
    ],
    "is_part_of": [
      "Sustainability Compliance System",
      "Governance Framework"
    ],
    "requires": [
      "Infrastructure Metrics",
      "Third-Party Auditor",
      "Energy Monitoring System",
      "Carbon Accounting"
    ],
    "depends_on": [
      "Environmental Standards",
      "Measurement Protocols"
    ],
    "enables": [
      "Carbon Neutrality Verification",
      "Green Infrastructure Certification",
      "User Trust Building",
      "Sustainability Reporting"
    ],
    "relates_to": [],
    "bridges_to": [],
    "bridges_from": [],
    "domain_extensions": {},
    "belongs_to_domain": [
      "TrustAndGovernanceDomain"
    ],
    "implemented_in_layer": [
      "Middleware Layer"
    ],
    "source": [
      "ISO 14021"
    ],
    "validation": {
      "is_valid": false,
      "errors": [
        "Missing required property: source-domain",
        "Missing required property: last-updated",
        "Missing required property: is-subclass-of (at least one parent class)",
        "term-id '20225' doesn't match domain 'mv' (expected MV-)"
      ]
    }
  }
}