{
  "id": "ERC721",
  "title": "ERC721",
  "content": "- ### OntologyBlock\n  id:: erc721-ontology\n  collapsed:: true\n\t- ontology:: true\n    - is-subclass-of:: [[BlockchainTechnology]]\n\t- term-id:: BC-0104\n\t- preferred-term:: ERC721\n\t- source-domain:: blockchain\n\t- status:: active\n\t- public-access:: true\n\t- definition:: The Ethereum token standard for creating non-fungible tokens (NFTs) where each token has unique identifiers and metadata, enabling verifiable digital ownership of distinct assets.\n\t- maturity:: mature\n\t- owl:class:: bc:ERC721\n\t- owl:equivalentClass:: mv:ERC721\n\t- owl:physicality:: ConceptualEntity\n\t- owl:role:: Standard\n\t- belongsToDomain:: [[BlockchainDomain]]",
  "backlinks": [],
  "wiki_links": [
    "BlockchainTechnology",
    "BlockchainDomain"
  ],
  "ontology": {
    "term_id": "BC-0104",
    "preferred_term": "ERC721",
    "alt_terms": [],
    "iri": "http://narrativegoldmine.com/blockchain#ERC721",
    "source_domain": "blockchain",
    "domain": "blockchain",
    "domain_full_name": "",
    "definition": "The Ethereum token standard for creating non-fungible tokens (NFTs) where each token has unique identifiers and metadata, enabling verifiable digital ownership of distinct assets.",
    "scope_note": null,
    "status": "active",
    "maturity": "mature",
    "version": null,
    "public_access": true,
    "last_updated": null,
    "authority_score": null,
    "quality_score": null,
    "cross_domain_links": null,
    "owl_class": "bc:ERC721",
    "owl_physicality": "ConceptualEntity",
    "owl_role": "Standard",
    "owl_inferred_class": null,
    "is_subclass_of": [],
    "has_part": [],
    "is_part_of": [],
    "requires": [],
    "depends_on": [],
    "enables": [],
    "relates_to": [],
    "bridges_to": [],
    "bridges_from": [],
    "domain_extensions": {},
    "belongs_to_domain": [
      "BlockchainDomain"
    ],
    "implemented_in_layer": [],
    "source": [],
    "validation": {
      "is_valid": false,
      "errors": [
        "Missing required property: last-updated",
        "Missing required property: is-subclass-of (at least one parent class)",
        "owl:class namespace 'bc' doesn't match source-domain 'blockchain'"
      ]
    }
  }
}