{
  "id": "ETSI_Domain_Governance_&_Ethics",
  "title": "ETSI Domain: Governance & Ethics",
  "content": "- ### OntologyBlock\n  id:: etsi-domain-governance-ethics-ontology\n  collapsed:: true\n\t- ontology:: true\n\t- term-id:: 20349\n\t- source-domain:: metaverse\n\t- status:: draft\n    - public-access:: true\n\t- preferred-term:: ETSI Domain: Governance & Ethics\n\t- definition:: Crossover domain for ETSI metaverse categorization addressing ethical governance frameworks, responsible decision-making processes, and value-aligned organizational structures.\n\t- maturity:: mature\n\t- source:: [[ETSI GR MEC 032]]\n\t- owl:class:: mv:ETSIDomain_Governance_Ethics\n\t- owl:physicality:: VirtualEntity\n\t- owl:role:: Object\n\t- owl:inferred-class:: mv:VirtualObject\n\t- owl:functional-syntax:: true\n\t- belongsToDomain:: [[InfrastructureDomain]]\n\t- implementedInLayer:: [[ApplicationLayer]]\n\t- #### Relationships\n\t  id:: etsi-domain-governance-ethics-relationships\n\t\t- is-subclass-of:: [[Metaverse]]\n\t\t- is-part-of:: [[ETSI Metaverse Domain Taxonomy]]\n\t\t- has-part:: [[Ethics Committee]], [[Governance Board]], [[Value Framework]], [[Stakeholder Engagement]]\n\t\t- requires:: [[Governance]], [[Ethics & Law]]\n\t\t- enables:: [[Ethical Decision-Making]], [[Stakeholder Accountability]], [[Value Alignment]]\n\t\t- depends-on:: [[Ethical Principles]], [[Governance Models]]\n\t- #### OWL Axioms\n\t  id:: etsi-domain-governance-ethics-owl-axioms\n\t  collapsed:: true\n\t\t- ```clojure\n\t\t  Declaration(Class(mv:ETSIDomain_Governance_Ethics))\n\n\t\t  # Classification along two primary dimensions\n\t\t  SubClassOf(mv:ETSIDomain_Governance_Ethics mv:VirtualEntity)\n\t\t  SubClassOf(mv:ETSIDomain_Governance_Ethics mv:Object)\n\n\t\t  # Domain classification\n\t\t  SubClassOf(mv:ETSIDomain_Governance_Ethics\n\t\t    ObjectSomeValuesFrom(mv:belongsToDomain mv:InfrastructureDomain)\n\t\t  )\n\n\t\t  # Layer classification\n\t\t  SubClassOf(mv:ETSIDomain_Governance_Ethics\n\t\t    ObjectSomeValuesFrom(mv:implementedInLayer mv:ApplicationLayer)\n\t\t  )\n\n\t\t  # Crossover domain dependencies\n\t\t  SubClassOf(mv:ETSIDomain_Governance_Ethics\n\t\t    ObjectSomeValuesFrom(mv:requires mv:ETSIDomain_Governance)\n\t\t  )\n\t\t  SubClassOf(mv:ETSIDomain_Governance_Ethics\n\t\t    ObjectSomeValuesFrom(mv:requires mv:ETSIDomain_EthicsLaw)\n\t\t  )\n\n\t\t  # Ethical decision-making enablement\n\t\t  SubClassOf(mv:ETSIDomain_Governance_Ethics\n\t\t    ObjectSomeValuesFrom(mv:enables mv:EthicalDecisionMaking)\n\t\t  )\n\n  # Property characteristics\n  TransitiveObjectProperty(dt:ispartof)\n\n  # Property characteristics\n  AsymmetricObjectProperty(dt:requires)\n\n  # Property characteristics\n  AsymmetricObjectProperty(dt:enables)\n\n  # Property characteristics\n  AsymmetricObjectProperty(dt:dependson)\n```",
  "backlinks": [],
  "wiki_links": [
    "Governance",
    "Ethics Committee",
    "ApplicationLayer",
    "ETSI Metaverse Domain Taxonomy",
    "Stakeholder Accountability",
    "Ethical Decision-Making",
    "Value Framework",
    "Stakeholder Engagement",
    "Value Alignment",
    "Metaverse",
    "Governance Board",
    "ETSI GR MEC 032",
    "Ethics & Law",
    "InfrastructureDomain",
    "Ethical Principles",
    "Governance Models"
  ],
  "ontology": {
    "term_id": "20349",
    "preferred_term": "ETSI Domain: Governance & Ethics",
    "alt_terms": [],
    "iri": "http://narrativegoldmine.com/metaverse#ETSIDomain_Governance_Ethics",
    "source_domain": "metaverse",
    "domain": "metaverse",
    "domain_full_name": "",
    "definition": "Crossover domain for ETSI metaverse categorization addressing ethical governance frameworks, responsible decision-making processes, and value-aligned organizational structures.",
    "scope_note": null,
    "status": "draft",
    "maturity": "mature",
    "version": null,
    "public_access": true,
    "last_updated": null,
    "authority_score": null,
    "quality_score": null,
    "cross_domain_links": null,
    "owl_class": "mv:ETSIDomain_Governance_Ethics",
    "owl_physicality": "VirtualEntity",
    "owl_role": "Object",
    "owl_inferred_class": "mv:VirtualObject",
    "is_subclass_of": [
      "Metaverse"
    ],
    "has_part": [
      "Ethics Committee",
      "Governance Board",
      "Value Framework",
      "Stakeholder Engagement"
    ],
    "is_part_of": [
      "ETSI Metaverse Domain Taxonomy"
    ],
    "requires": [
      "Governance",
      "Ethics & Law"
    ],
    "depends_on": [
      "Ethical Principles",
      "Governance Models"
    ],
    "enables": [
      "Ethical Decision-Making",
      "Stakeholder Accountability",
      "Value Alignment"
    ],
    "relates_to": [],
    "bridges_to": [],
    "bridges_from": [],
    "domain_extensions": {},
    "belongs_to_domain": [
      "InfrastructureDomain"
    ],
    "implemented_in_layer": [
      "ApplicationLayer"
    ],
    "source": [
      "ETSI GR MEC 032"
    ],
    "validation": {
      "is_valid": false,
      "errors": [
        "Missing required property: last-updated",
        "owl:class namespace 'mv' doesn't match source-domain 'metaverse'"
      ]
    }
  }
}