{
  "id": "ETSI_Domain_Application___Creative",
  "title": "ETSI Domain Application + Creative",
  "content": "- ### OntologyBlock\n  id:: etsi-domain-application-creative-ontology\n  collapsed:: true\n\t- ontology:: true\n\t- term-id:: 20335\n\t- source-domain:: metaverse\n\t- status:: draft\n    - public-access:: true\n\t- preferred-term:: ETSI Domain Application + Creative\n\t- definition:: Cross-domain marker for metaverse application components focused on creative industries including digital art, music production, animation, film, design tools, and creative collaboration platforms.\n\t- maturity:: mature\n\t- source:: [[ETSI GS MEC]]\n\t- owl:class:: mv:ETSIDomainApplicationCreative\n\t- owl:physicality:: VirtualEntity\n\t- owl:role:: Object\n\t- owl:inferred-class:: mv:VirtualObject\n\t- owl:functional-syntax:: true\n\t- belongsToDomain:: [[InfrastructureDomain]], [[CreativeMediaDomain]]\n\t- implementedInLayer:: [[ApplicationLayer]]\n\t- #### Relationships\n\t  id:: etsi-domain-application-creative-relationships\n\t\t- is-subclass-of:: [[Metaverse]]\n\t\t- is-part-of:: [[ETSI Domain Taxonomy]]\n\t\t- depends-on:: [[InfrastructureDomain]], [[CreativeMediaDomain]]\n\t\t- enables:: [[Creative Application Classification]], [[Collaboration Tool Categorization]]\n\t\t- categorizes:: [[Digital Art Application]], [[Music Production Tool]], [[Animation Software]], [[Design Platform]]\n\t- #### OWL Axioms\n\t  id:: etsi-domain-application-creative-owl-axioms\n\t  collapsed:: true\n\t\t- ```clojure\n\t\t  Declaration(Class(mv:ETSIDomainApplicationCreative))\n\n\t\t  # Classification along two primary dimensions\n\t\t  SubClassOf(mv:ETSIDomainApplicationCreative mv:VirtualEntity)\n\t\t  SubClassOf(mv:ETSIDomainApplicationCreative mv:Object)\n\n\t\t  # Cross-domain marker classification\n\t\t  SubClassOf(mv:ETSIDomainApplicationCreative mv:DomainMarker)\n\t\t  SubClassOf(mv:ETSIDomainApplicationCreative mv:CrossDomainMarker)\n\n\t\t  # Multiple domain classification\n\t\t  SubClassOf(mv:ETSIDomainApplicationCreative\n\t\t    ObjectSomeValuesFrom(mv:belongsToDomain mv:InfrastructureDomain)\n\t\t  )\n\t\t  SubClassOf(mv:ETSIDomainApplicationCreative\n\t\t    ObjectSomeValuesFrom(mv:belongsToDomain mv:CreativeMediaDomain)\n\t\t  )\n\n\t\t  # Layer classification\n\t\t  SubClassOf(mv:ETSIDomainApplicationCreative\n\t\t    ObjectSomeValuesFrom(mv:implementedInLayer mv:ApplicationLayer)\n\t\t  )\n\n  # Property characteristics\n  TransitiveObjectProperty(dt:ispartof)\n\n  # Property characteristics\n  AsymmetricObjectProperty(dt:dependson)\n\n  # Property characteristics\n  AsymmetricObjectProperty(dt:enables)\n```",
  "backlinks": [],
  "wiki_links": [
    "ETSI GS MEC",
    "CreativeMediaDomain",
    "Metaverse",
    "Collaboration Tool Categorization",
    "Design Platform",
    "ETSI Domain Taxonomy",
    "Music Production Tool",
    "InfrastructureDomain",
    "ApplicationLayer",
    "Animation Software",
    "Digital Art Application",
    "Creative Application Classification"
  ],
  "ontology": {
    "term_id": "20335",
    "preferred_term": "ETSI Domain Application + Creative",
    "alt_terms": [],
    "iri": "http://narrativegoldmine.com/metaverse#ETSIDomainApplicationCreative",
    "source_domain": "metaverse",
    "domain": "metaverse",
    "domain_full_name": "",
    "definition": "Cross-domain marker for metaverse application components focused on creative industries including digital art, music production, animation, film, design tools, and creative collaboration platforms.",
    "scope_note": null,
    "status": "draft",
    "maturity": "mature",
    "version": null,
    "public_access": true,
    "last_updated": null,
    "authority_score": null,
    "quality_score": null,
    "cross_domain_links": null,
    "owl_class": "mv:ETSIDomainApplicationCreative",
    "owl_physicality": "VirtualEntity",
    "owl_role": "Object",
    "owl_inferred_class": "mv:VirtualObject",
    "is_subclass_of": [
      "Metaverse"
    ],
    "has_part": [],
    "is_part_of": [
      "ETSI Domain Taxonomy"
    ],
    "requires": [],
    "depends_on": [
      "InfrastructureDomain",
      "CreativeMediaDomain"
    ],
    "enables": [
      "Creative Application Classification",
      "Collaboration Tool Categorization"
    ],
    "relates_to": [],
    "bridges_to": [],
    "bridges_from": [],
    "domain_extensions": {},
    "belongs_to_domain": [
      "InfrastructureDomain",
      "CreativeMediaDomain"
    ],
    "implemented_in_layer": [
      "ApplicationLayer"
    ],
    "source": [
      "ETSI GS MEC"
    ],
    "other_relationships": {
      "categorizes": [
        "Digital Art Application",
        "Music Production Tool",
        "Animation Software",
        "Design Platform"
      ]
    },
    "validation": {
      "is_valid": false,
      "errors": [
        "Missing required property: last-updated",
        "owl:class namespace 'mv' doesn't match source-domain 'metaverse'"
      ]
    }
  }
}