{
  "id": "ETSI_Domain_Application___Industry",
  "title": "ETSI Domain Application + Industry",
  "content": "- ### OntologyBlock\n  id:: etsi-domain-application-industry-ontology\n  collapsed:: true\n\t- ontology:: true\n\t- term-id:: 20338\n\t- source-domain:: metaverse\n\t- status:: draft\n    - public-access:: true\n\t- preferred-term:: ETSI Domain Application + Industry\n\t- definition:: Cross-domain marker for metaverse application components focused on industrial applications including manufacturing simulations, industrial digital twins, predictive maintenance, remote operations, and industrial training systems.\n\t- maturity:: mature\n\t- source:: [[ETSI GS MEC]]\n\t- owl:class:: mv:ETSIDomainApplicationIndustry\n\t- owl:physicality:: VirtualEntity\n\t- owl:role:: Object\n\t- owl:inferred-class:: mv:VirtualObject\n\t- owl:functional-syntax:: true\n\t- belongsToDomain:: [[InfrastructureDomain]], [[VirtualEconomyDomain]]\n\t- implementedInLayer:: [[ApplicationLayer]]\n\t- #### Relationships\n\t  id:: etsi-domain-application-industry-relationships\n\t\t- is-subclass-of:: [[ArtificialIntelligence]]\n\t\t- is-part-of:: [[ETSI Domain Taxonomy]]\n\t\t- depends-on:: [[InfrastructureDomain]], [[VirtualEconomyDomain]]\n\t\t- enables:: [[Industrial Application Classification]], [[Manufacturing Platform Categorization]]\n\t\t- categorizes:: [[Industrial Digital Twin]], [[Manufacturing Simulation]], [[Predictive Maintenance]], [[Remote Operations]]\n\t- #### OWL Axioms\n\t  id:: etsi-domain-application-industry-owl-axioms\n\t  collapsed:: true\n\t\t- ```clojure\n\t\t  Declaration(Class(mv:ETSIDomainApplicationIndustry))\n\n\t\t  # Classification along two primary dimensions\n\t\t  SubClassOf(mv:ETSIDomainApplicationIndustry mv:VirtualEntity)\n\t\t  SubClassOf(mv:ETSIDomainApplicationIndustry mv:Object)\n\n\t\t  # Cross-domain marker classification\n\t\t  SubClassOf(mv:ETSIDomainApplicationIndustry mv:DomainMarker)\n\t\t  SubClassOf(mv:ETSIDomainApplicationIndustry mv:CrossDomainMarker)\n\n\t\t  # Multiple domain classification\n\t\t  SubClassOf(mv:ETSIDomainApplicationIndustry\n\t\t    ObjectSomeValuesFrom(mv:belongsToDomain mv:InfrastructureDomain)\n\t\t  )\n\t\t  SubClassOf(mv:ETSIDomainApplicationIndustry\n\t\t    ObjectSomeValuesFrom(mv:belongsToDomain mv:VirtualEconomyDomain)\n\t\t  )\n\n\t\t  # Layer classification\n\t\t  SubClassOf(mv:ETSIDomainApplicationIndustry\n\t\t    ObjectSomeValuesFrom(mv:implementedInLayer mv:ApplicationLayer)\n\t\t  )\n\n  # Property characteristics\n  TransitiveObjectProperty(dt:ispartof)\n\n  # Property characteristics\n  AsymmetricObjectProperty(dt:dependson)\n\n  # Property characteristics\n  AsymmetricObjectProperty(dt:enables)\n```",
  "backlinks": [],
  "wiki_links": [
    "ETSI GS MEC",
    "VirtualEconomyDomain",
    "Manufacturing Platform Categorization",
    "Remote Operations",
    "ApplicationLayer",
    "Industrial Digital Twin",
    "Industrial Application Classification",
    "Predictive Maintenance",
    "Manufacturing Simulation",
    "ETSI Domain Taxonomy",
    "InfrastructureDomain",
    "ArtificialIntelligence"
  ],
  "ontology": {
    "term_id": "20338",
    "preferred_term": "ETSI Domain Application + Industry",
    "alt_terms": [],
    "iri": "http://narrativegoldmine.com/metaverse#ETSIDomainApplicationIndustry",
    "source_domain": "metaverse",
    "domain": "metaverse",
    "domain_full_name": "",
    "definition": "Cross-domain marker for metaverse application components focused on industrial applications including manufacturing simulations, industrial digital twins, predictive maintenance, remote operations, and industrial training systems.",
    "scope_note": null,
    "status": "draft",
    "maturity": "mature",
    "version": null,
    "public_access": true,
    "last_updated": null,
    "authority_score": null,
    "quality_score": null,
    "cross_domain_links": null,
    "owl_class": "mv:ETSIDomainApplicationIndustry",
    "owl_physicality": "VirtualEntity",
    "owl_role": "Object",
    "owl_inferred_class": "mv:VirtualObject",
    "is_subclass_of": [
      "ArtificialIntelligence"
    ],
    "has_part": [],
    "is_part_of": [
      "ETSI Domain Taxonomy"
    ],
    "requires": [],
    "depends_on": [
      "InfrastructureDomain",
      "VirtualEconomyDomain"
    ],
    "enables": [
      "Industrial Application Classification",
      "Manufacturing Platform Categorization"
    ],
    "relates_to": [],
    "bridges_to": [],
    "bridges_from": [],
    "domain_extensions": {},
    "belongs_to_domain": [
      "InfrastructureDomain",
      "VirtualEconomyDomain"
    ],
    "implemented_in_layer": [
      "ApplicationLayer"
    ],
    "source": [
      "ETSI GS MEC"
    ],
    "other_relationships": {
      "categorizes": [
        "Industrial Digital Twin",
        "Manufacturing Simulation",
        "Predictive Maintenance",
        "Remote Operations"
      ]
    },
    "validation": {
      "is_valid": false,
      "errors": [
        "Missing required property: last-updated",
        "owl:class namespace 'mv' doesn't match source-domain 'metaverse'"
      ]
    }
  }
}