{
  "id": "ETSI_Domain_Governance___Ethics",
  "title": "ETSI_Domain_Governance___Ethics",
  "content": "- ### OntologyBlock\n  id:: etsi_domain_governance___ethics-ontology\n  collapsed:: true\n\t- ontology:: true\n\t- term-id:: MV-0015\n\t- preferred-term:: ETSI_Domain_Governance___Ethics\n\t- status:: draft\n\t- public-access:: true\n\t- definition:: A component of the metaverse ecosystem.\n\t- maturity:: draft\n\t- owl:class:: mv:ETSI_Domain_Governance___Ethics\n\t- owl:physicality:: ConceptualEntity\n\t- owl:role:: Concept\n\t- belongsToDomain:: [[MetaverseDomain]]\n\n## OWL Formal Semantics\n\n```clojure\n;; OWL Functional Syntax\n\n(Declaration (Class :Etsidomaingovernanceethics))\n\n;; Annotations\n(AnnotationAssertion rdfs:label :Etsidomaingovernanceethics \"ETSI_Domain_Governance___Ethics\"@en)\n(AnnotationAssertion rdfs:comment :Etsidomaingovernanceethics \"A component of the metaverse ecosystem.\"@en)\n\n;; Data Properties\n(AnnotationAssertion dcterms:identifier :Etsidomaingovernanceethics \"mv-1761742247920\"^^xsd:string)\n```",
  "backlinks": [],
  "wiki_links": [
    "MetaverseDomain"
  ],
  "ontology": {
    "term_id": "MV-0015",
    "preferred_term": "ETSI_Domain_Governance___Ethics",
    "alt_terms": [],
    "iri": "http://narrativegoldmine.com/metaverse#ETSI_Domain_Governance___Ethics",
    "source_domain": null,
    "domain": "mv",
    "domain_full_name": "Metaverse",
    "definition": "A component of the metaverse ecosystem.",
    "scope_note": null,
    "status": "draft",
    "maturity": "draft",
    "version": null,
    "public_access": true,
    "last_updated": null,
    "authority_score": null,
    "quality_score": null,
    "cross_domain_links": null,
    "owl_class": "mv:ETSI_Domain_Governance___Ethics",
    "owl_physicality": "ConceptualEntity",
    "owl_role": "Concept",
    "owl_inferred_class": null,
    "is_subclass_of": [],
    "has_part": [],
    "is_part_of": [],
    "requires": [],
    "depends_on": [],
    "enables": [],
    "relates_to": [],
    "bridges_to": [],
    "bridges_from": [],
    "domain_extensions": {},
    "belongs_to_domain": [
      "MetaverseDomain"
    ],
    "implemented_in_layer": [],
    "source": [],
    "validation": {
      "is_valid": false,
      "errors": [
        "Missing required property: source-domain",
        "Missing required property: last-updated",
        "Missing required property: is-subclass-of (at least one parent class)"
      ]
    }
  }
}