{
  "id": "ETSI_Domain_Application___Health",
  "title": "ETSI Domain Application + Health",
  "content": "- ### OntologyBlock\n  id:: etsi-domain-application-health-ontology\n  collapsed:: true\n\t- ontology:: true\n\t- term-id:: 20337\n\t- source-domain:: metaverse\n\t- status:: draft\n    - public-access:: true\n\t- preferred-term:: ETSI Domain Application + Health\n\t- definition:: Cross-domain marker for metaverse application components focused on healthcare and wellness including telemedicine platforms, medical training simulations, therapeutic VR applications, and health monitoring systems.\n\t- maturity:: mature\n\t- source:: [[ETSI GS MEC]]\n\t- owl:class:: mv:ETSIDomainApplicationHealth\n\t- owl:physicality:: VirtualEntity\n\t- owl:role:: Object\n\t- owl:inferred-class:: mv:VirtualObject\n\t- owl:functional-syntax:: true\n\t- belongsToDomain:: [[InfrastructureDomain]], [[VirtualSocietyDomain]]\n\t- implementedInLayer:: [[ApplicationLayer]]\n\t- #### Relationships\n\t  id:: etsi-domain-application-health-relationships\n\t\t- is-subclass-of:: [[Metaverse]]\n\t\t- is-part-of:: [[ETSI Domain Taxonomy]]\n\t\t- depends-on:: [[InfrastructureDomain]], [[VirtualSocietyDomain]]\n\t\t- enables:: [[Healthcare Application Classification]], [[Medical Platform Categorization]]\n\t\t- categorizes:: [[Telemedicine Platform]], [[Medical Simulation]], [[Therapeutic VR]], [[Health Monitoring]]\n\t- #### OWL Axioms\n\t  id:: etsi-domain-application-health-owl-axioms\n\t  collapsed:: true\n\t\t- ```clojure\n\t\t  Declaration(Class(mv:ETSIDomainApplicationHealth))\n\n\t\t  # Classification along two primary dimensions\n\t\t  SubClassOf(mv:ETSIDomainApplicationHealth mv:VirtualEntity)\n\t\t  SubClassOf(mv:ETSIDomainApplicationHealth mv:Object)\n\n\t\t  # Cross-domain marker classification\n\t\t  SubClassOf(mv:ETSIDomainApplicationHealth mv:DomainMarker)\n\t\t  SubClassOf(mv:ETSIDomainApplicationHealth mv:CrossDomainMarker)\n\n\t\t  # Multiple domain classification\n\t\t  SubClassOf(mv:ETSIDomainApplicationHealth\n\t\t    ObjectSomeValuesFrom(mv:belongsToDomain mv:InfrastructureDomain)\n\t\t  )\n\t\t  SubClassOf(mv:ETSIDomainApplicationHealth\n\t\t    ObjectSomeValuesFrom(mv:belongsToDomain mv:VirtualSocietyDomain)\n\t\t  )\n\n\t\t  # Layer classification\n\t\t  SubClassOf(mv:ETSIDomainApplicationHealth\n\t\t    ObjectSomeValuesFrom(mv:implementedInLayer mv:ApplicationLayer)\n\t\t  )\n\n  # Property characteristics\n  TransitiveObjectProperty(dt:ispartof)\n\n  # Property characteristics\n  AsymmetricObjectProperty(dt:dependson)\n\n  # Property characteristics\n  AsymmetricObjectProperty(dt:enables)\n```",
  "backlinks": [],
  "wiki_links": [
    "Therapeutic VR",
    "Telemedicine Platform",
    "ETSI GS MEC",
    "Healthcare Application Classification",
    "Medical Platform Categorization",
    "Metaverse",
    "ApplicationLayer",
    "Medical Simulation",
    "VirtualSocietyDomain",
    "ETSI Domain Taxonomy",
    "InfrastructureDomain",
    "Health Monitoring"
  ],
  "ontology": {
    "term_id": "20337",
    "preferred_term": "ETSI Domain Application + Health",
    "alt_terms": [],
    "iri": "http://narrativegoldmine.com/metaverse#ETSIDomainApplicationHealth",
    "source_domain": "metaverse",
    "domain": "metaverse",
    "domain_full_name": "",
    "definition": "Cross-domain marker for metaverse application components focused on healthcare and wellness including telemedicine platforms, medical training simulations, therapeutic VR applications, and health monitoring systems.",
    "scope_note": null,
    "status": "draft",
    "maturity": "mature",
    "version": null,
    "public_access": true,
    "last_updated": null,
    "authority_score": null,
    "quality_score": null,
    "cross_domain_links": null,
    "owl_class": "mv:ETSIDomainApplicationHealth",
    "owl_physicality": "VirtualEntity",
    "owl_role": "Object",
    "owl_inferred_class": "mv:VirtualObject",
    "is_subclass_of": [
      "Metaverse"
    ],
    "has_part": [],
    "is_part_of": [
      "ETSI Domain Taxonomy"
    ],
    "requires": [],
    "depends_on": [
      "InfrastructureDomain",
      "VirtualSocietyDomain"
    ],
    "enables": [
      "Healthcare Application Classification",
      "Medical Platform Categorization"
    ],
    "relates_to": [],
    "bridges_to": [],
    "bridges_from": [],
    "domain_extensions": {},
    "belongs_to_domain": [
      "InfrastructureDomain",
      "VirtualSocietyDomain"
    ],
    "implemented_in_layer": [
      "ApplicationLayer"
    ],
    "source": [
      "ETSI GS MEC"
    ],
    "other_relationships": {
      "categorizes": [
        "Telemedicine Platform",
        "Medical Simulation",
        "Therapeutic VR",
        "Health Monitoring"
      ]
    },
    "validation": {
      "is_valid": false,
      "errors": [
        "Missing required property: last-updated",
        "owl:class namespace 'mv' doesn't match source-domain 'metaverse'"
      ]
    }
  }
}