{
  "id": "ETSI_Domain_Data",
  "title": "ETSI Domain Data",
  "content": "- ### OntologyBlock\n  id:: etsi-domain-data-ontology\n  collapsed:: true\n\t- ontology:: true\n\t- term-id:: 20374\n\t- source-domain:: metaverse\n\t- status:: draft\n    - public-access:: true\n\t- preferred-term:: ETSI Domain Data\n\t- definition:: Domain categorization for data management, storage, analytics, AI/ML systems, and intelligence capabilities processing information in metaverse environments.\n\t- maturity:: mature\n\t- source:: [[ETSI GR MEC 032]], [[ISO 23257]]\n\t- owl:class:: mv:ETSIDomainData\n\t- owl:physicality:: VirtualEntity\n\t- owl:role:: Object\n\t- owl:inferred-class:: mv:VirtualObject\n\t- owl:functional-syntax:: true\n\t- belongsToDomain:: [[ComputationAndIntelligenceDomain]]\n\t- implementedInLayer:: [[ApplicationLayer]]\n\t- #### Relationships\n\t  id:: etsi-domain-data-relationships\n\t\t- is-subclass-of:: [[ArtificialIntelligence]]\n\t\t- is-part-of:: [[ETSI Metaverse Domain Model]]\n\t\t- has-part:: [[Data Storage]], [[Data Analytics]], [[Machine Learning]], [[AI Systems]]\n\t\t- enables:: [[Data Processing]], [[Intelligence]], [[Predictive Analytics]]\n\t- #### OWL Axioms\n\t  id:: etsi-domain-data-owl-axioms\n\t  collapsed:: true\n\t\t- ```clojure\n\t\t  Declaration(Class(mv:ETSIDomainData))\n\n\t\t  SubClassOf(mv:ETSIDomainData mv:VirtualEntity)\n\t\t  SubClassOf(mv:ETSIDomainData mv:Object)\n\n\t\t  SubClassOf(mv:ETSIDomainData\n\t\t    ObjectSomeValuesFrom(mv:belongsToDomain mv:ComputationAndIntelligenceDomain)\n\t\t  )\n\n\t\t  SubClassOf(mv:ETSIDomainData\n\t\t    ObjectSomeValuesFrom(mv:implementedInLayer mv:ApplicationLayer)\n\t\t  )\n\n\t\t  SubClassOf(mv:ETSIDomainData\n\t\t    ObjectSomeValuesFrom(mv:hasPart mv:DataStorage)\n\t\t  )\n\n\t\t  SubClassOf(mv:ETSIDomainData\n\t\t    ObjectSomeValuesFrom(mv:hasPart ai:MachineLearning)\n\t\t  )\n\n\t\t  SubClassOf(mv:ETSIDomainData\n\t\t    ObjectSomeValuesFrom(mv:enablesCapability mv:DataProcessing)\n\t\t  )\n\n\t\t  SubClassOf(mv:ETSIDomainData\n\t\t    ObjectSomeValuesFrom(mv:enablesCapability mv:Intelligence)\n\t\t  )\n\n  # Property characteristics\n  TransitiveObjectProperty(dt:ispartof)\n\n  # Property characteristics\n  AsymmetricObjectProperty(dt:enables)\n```",
  "backlinks": [],
  "wiki_links": [
    "Data Processing",
    "Intelligence",
    "Machine Learning",
    "ComputationAndIntelligenceDomain",
    "Data Storage",
    "Data Analytics",
    "ArtificialIntelligence",
    "Predictive Analytics",
    "AI Systems",
    "ISO 23257",
    "ApplicationLayer",
    "ETSI Metaverse Domain Model",
    "ETSI GR MEC 032"
  ],
  "ontology": {
    "term_id": "20374",
    "preferred_term": "ETSI Domain Data",
    "alt_terms": [],
    "iri": "http://narrativegoldmine.com/metaverse#ETSIDomainData",
    "source_domain": "metaverse",
    "domain": "metaverse",
    "domain_full_name": "",
    "definition": "Domain categorization for data management, storage, analytics, AI/ML systems, and intelligence capabilities processing information in metaverse environments.",
    "scope_note": null,
    "status": "draft",
    "maturity": "mature",
    "version": null,
    "public_access": true,
    "last_updated": null,
    "authority_score": null,
    "quality_score": null,
    "cross_domain_links": null,
    "owl_class": "mv:ETSIDomainData",
    "owl_physicality": "VirtualEntity",
    "owl_role": "Object",
    "owl_inferred_class": "mv:VirtualObject",
    "is_subclass_of": [
      "ArtificialIntelligence"
    ],
    "has_part": [
      "Data Storage",
      "Data Analytics",
      "Machine Learning",
      "AI Systems"
    ],
    "is_part_of": [
      "ETSI Metaverse Domain Model"
    ],
    "requires": [],
    "depends_on": [],
    "enables": [
      "Data Processing",
      "Intelligence",
      "Predictive Analytics"
    ],
    "relates_to": [],
    "bridges_to": [],
    "bridges_from": [],
    "domain_extensions": {},
    "belongs_to_domain": [
      "ComputationAndIntelligenceDomain"
    ],
    "implemented_in_layer": [
      "ApplicationLayer"
    ],
    "source": [
      "ETSI GR MEC 032",
      "ISO 23257"
    ],
    "validation": {
      "is_valid": false,
      "errors": [
        "Missing required property: last-updated",
        "owl:class namespace 'mv' doesn't match source-domain 'metaverse'"
      ]
    }
  }
}