{
  "id": "ETSI_Domain_Application___Tourism",
  "title": "ETSI Domain Application + Tourism",
  "content": "- ### OntologyBlock\n  id:: etsi-domain-application-tourism-ontology\n  collapsed:: true\n\t- ontology:: true\n\t- term-id:: 20339\n\t- source-domain:: metaverse\n\t- status:: draft\n    - public-access:: true\n\t- preferred-term:: ETSI Domain Application + Tourism\n\t- definition:: Cross-domain marker for metaverse application components focused on tourism and hospitality including virtual tours, destination previews, cultural heritage experiences, and travel planning platforms in immersive environments.\n\t- maturity:: mature\n\t- source:: [[ETSI GS MEC]]\n\t- owl:class:: mv:ETSIDomainApplicationTourism\n\t- owl:physicality:: VirtualEntity\n\t- owl:role:: Object\n\t- owl:inferred-class:: mv:VirtualObject\n\t- owl:functional-syntax:: true\n\t- belongsToDomain:: [[InfrastructureDomain]], [[VirtualSocietyDomain]]\n\t- implementedInLayer:: [[ApplicationLayer]]\n\t- #### Relationships\n\t  id:: etsi-domain-application-tourism-relationships\n\t\t- is-subclass-of:: [[Extended Reality (XR)]]\n\t\t- is-part-of:: [[ETSI Domain Taxonomy]]\n\t\t- depends-on:: [[InfrastructureDomain]], [[VirtualSocietyDomain]]\n\t\t- enables:: [[Tourism Application Classification]], [[Cultural Experience Categorization]]\n\t\t- categorizes:: [[Virtual Tour]], [[Destination Preview]], [[Cultural Heritage Experience]], [[Travel Planning Platform]]\n\t- #### OWL Axioms\n\t  id:: etsi-domain-application-tourism-owl-axioms\n\t  collapsed:: true\n\t\t- ```clojure\n\t\t  Declaration(Class(mv:ETSIDomainApplicationTourism))\n\n\t\t  # Classification along two primary dimensions\n\t\t  SubClassOf(mv:ETSIDomainApplicationTourism mv:VirtualEntity)\n\t\t  SubClassOf(mv:ETSIDomainApplicationTourism mv:Object)\n\n\t\t  # Cross-domain marker classification\n\t\t  SubClassOf(mv:ETSIDomainApplicationTourism mv:DomainMarker)\n\t\t  SubClassOf(mv:ETSIDomainApplicationTourism mv:CrossDomainMarker)\n\n\t\t  # Multiple domain classification\n\t\t  SubClassOf(mv:ETSIDomainApplicationTourism\n\t\t    ObjectSomeValuesFrom(mv:belongsToDomain mv:InfrastructureDomain)\n\t\t  )\n\t\t  SubClassOf(mv:ETSIDomainApplicationTourism\n\t\t    ObjectSomeValuesFrom(mv:belongsToDomain mv:VirtualSocietyDomain)\n\t\t  )\n\n\t\t  # Layer classification\n\t\t  SubClassOf(mv:ETSIDomainApplicationTourism\n\t\t    ObjectSomeValuesFrom(mv:implementedInLayer mv:ApplicationLayer)\n\t\t  )\n\n  # Property characteristics\n  TransitiveObjectProperty(dt:ispartof)\n\n  # Property characteristics\n  AsymmetricObjectProperty(dt:dependson)\n\n  # Property characteristics\n  AsymmetricObjectProperty(dt:enables)\n```",
  "backlinks": [],
  "wiki_links": [
    "Virtual Tour",
    "ETSI GS MEC",
    "Extended Reality (XR)",
    "Travel Planning Platform",
    "ApplicationLayer",
    "Cultural Experience Categorization",
    "Destination Preview",
    "Cultural Heritage Experience",
    "VirtualSocietyDomain",
    "ETSI Domain Taxonomy",
    "InfrastructureDomain",
    "Tourism Application Classification"
  ],
  "ontology": {
    "term_id": "20339",
    "preferred_term": "ETSI Domain Application + Tourism",
    "alt_terms": [],
    "iri": "http://narrativegoldmine.com/metaverse#ETSIDomainApplicationTourism",
    "source_domain": "metaverse",
    "domain": "metaverse",
    "domain_full_name": "",
    "definition": "Cross-domain marker for metaverse application components focused on tourism and hospitality including virtual tours, destination previews, cultural heritage experiences, and travel planning platforms in immersive environments.",
    "scope_note": null,
    "status": "draft",
    "maturity": "mature",
    "version": null,
    "public_access": true,
    "last_updated": null,
    "authority_score": null,
    "quality_score": null,
    "cross_domain_links": null,
    "owl_class": "mv:ETSIDomainApplicationTourism",
    "owl_physicality": "VirtualEntity",
    "owl_role": "Object",
    "owl_inferred_class": "mv:VirtualObject",
    "is_subclass_of": [
      "Extended Reality (XR)"
    ],
    "has_part": [],
    "is_part_of": [
      "ETSI Domain Taxonomy"
    ],
    "requires": [],
    "depends_on": [
      "InfrastructureDomain",
      "VirtualSocietyDomain"
    ],
    "enables": [
      "Tourism Application Classification",
      "Cultural Experience Categorization"
    ],
    "relates_to": [],
    "bridges_to": [],
    "bridges_from": [],
    "domain_extensions": {},
    "belongs_to_domain": [
      "InfrastructureDomain",
      "VirtualSocietyDomain"
    ],
    "implemented_in_layer": [
      "ApplicationLayer"
    ],
    "source": [
      "ETSI GS MEC"
    ],
    "other_relationships": {
      "categorizes": [
        "Virtual Tour",
        "Destination Preview",
        "Cultural Heritage Experience",
        "Travel Planning Platform"
      ]
    },
    "validation": {
      "is_valid": false,
      "errors": [
        "Missing required property: last-updated",
        "owl:class namespace 'mv' doesn't match source-domain 'metaverse'"
      ]
    }
  }
}