{
  "id": "EU MiCA Regulation",
  "title": "EU MiCA Regulation",
  "content": "- ### OntologyBlock\n  id:: bc-0482-eu-mica-regulation-ontology\n  collapsed:: true\n\t- ontology:: true\n\t- term-id:: BC-0482\n\t- preferred-term:: EU MiCA Regulation\n\t- source-domain:: metaverse\n\t- status:: stub-needs-content\n    - public-access:: true\n\t- content-status:: minimal-placeholder-requires-authoring\n    - public-access:: true\n\t- definition:: A component of the blockchain ecosystem.\n\t- maturity:: draft\n\t- owl:class:: bc:EUMiCARegulation\n\t- owl:physicality:: ConceptualEntity\n\t- owl:role:: Concept\n\t- is-subclass-of:: [[Regulation]]\n\t- belongsToDomain:: [[BlockchainDomain]]\n\n\n# Updated Ontology Entry: EU MiCA Regulation\n\n## Academic Context\n\n- Markets in Crypto-Assets Regulation (MiCA) represents the EU's comprehensive legislative framework for cryptoasset governance\n  - Entered into force in June 2023 with phased implementation\n  - Stablecoin provisions became applicable 30 June 2024\n  - Full applicability achieved 30 December 2024[1][3]\n  - Establishes uniform market rules across all EU member states for cryptoassets not covered by existing financial services legislation[1]\n  - Covers utility tokens, asset-referenced tokens, e-money tokens, and cryptoasset service provider (CASP) activities[5]\n\n- Regulatory philosophy emphasises market integrity, financial stability, and consumer protection\n  - Requires transparency and disclosure for public offers of cryptoassets\n  - Mandates authorisation and supervision of transactions\n  - Positions the EU as a frontrunner in cryptoasset regulation whilst other jurisdictions remain in definitional phases[5]\n\n## Current Landscape (2025)\n\n- Implementation status and licencing activity\n  - Over 40 CASP licences issued across EU member states since 30 December 2024[5]\n  - Netherlands and Malta issued first licences on the implementation date; Germany followed mid-January 2025[5]\n  - Majority of licences concentrated in Netherlands and Germany[5]\n  - Public CASP register maintained by the European Securities and Markets Authority (ESMA) provides transparency[5]\n  - Coinbase secured MiCA licence in August 2025, reinforcing its position as a leading cryptoasset platform across the EU[4]\n\n- Regulatory coordination and emerging challenges\n  - French, Austrian and Italian national competent authorities (AMF, FMA, Consob) identified fragmented application across jurisdictions within months of full implementation[2]\n  - Gaps identified in approval and supervision mechanisms—notably, authorities cannot require cybersecurity certification at authorisation stage[2]\n  - Concerns raised regarding location of largest service providers potentially weakening European regulatory reach[2]\n  - Growing hybridisation of crypto and traditional financial assets necessitates more consistent investor protection frameworks[2]\n\n- Technical and operational requirements\n  - Cryptoasset issuers and service providers must examine governance, risk management, capital adequacy, and consumer protection strategies[5]\n  - Interaction between MiCA and Payment Services Directive 2 (PSD2) creates dual authorisation requirements and significant regulatory burden in the short term[4]\n  - Complaint handling procedures formalised through Delegated Regulations published 13 February 2025, specifying requirements for asset-referenced token issuers and CASPs[7]\n\n- UK and North England context\n  - Post-Brexit, the UK operates independently of MiCA but monitors EU developments closely\n  - UK cryptoasset regulation remains under Financial Conduct Authority (FCA) oversight with evolving standards\n  - North England financial centres (Manchester, Leeds, Newcastle, Sheffield) have emerging fintech clusters but limited specific MiCA-related infrastructure compared to EU hubs\n  - Cross-border compliance considerations for UK firms serving EU clients remain significant\n\n## Regulatory Evolution and Reform Proposals\n\n- Early review and adjustment mechanisms\n  - Joint communication from French, Austrian and Italian authorities (February 2025) proposed four key directions for refinement[2]\n  - Recommendation for direct supervision mechanism for significant CASPs by ESMA to address coordination gaps[2]\n  - Advocacy for greater alignment between MiCA and existing MiFID II framework[2]\n  - Timing of review—mere months after full implementation—suggests potential for significant rather than minor adjustments[2]\n\n- International convergence and comparative frameworks\n  - US GENIUS Act (passed July 2025) provides stablecoin regulatory clarity with notable alignment to MiCA provisions[6]\n  - Policy-makers increasingly concerned about regulatory arbitrage and monetary sovereignty implications[6]\n  - Transatlantic regulatory harmonisation emerging as priority to prevent market fragmentation[6]\n\n## Research & Literature\n\n- Primary regulatory sources\n  - Regulation (EU) 2023/1114 on Markets in Crypto-Assets (MiCA), entered into force June 2023, fully applicable 30 December 2024[1][3]\n  - Commission Delegated Regulation (EU) 2025/293 and (EU) 2025/294 specifying complaint handling requirements for asset-referenced token issuers and CASPs respectively, published 13 February 2025[7]\n\n- Institutional guidance and trackers\n  - European Securities and Markets Authority (ESMA) maintains comprehensive MiCA activity documentation and public CASP register[1][5]\n  - Level 2 and Level 3 measures (delegated acts, technical standards, guidelines) remain under ongoing finalisation as of July 2025[4][7]\n  - Latham & Watkins MiCA Regulation Tracker provides real-time status updates on delegated acts and technical standards (last updated May 2025)[4]\n  - Hogan Lovells maintains tracker of Level 2 and Level 3 texts (last updated July 2025)[7]\n\n- Practitioner analysis and implementation guidance\n  - Norton Rose Fulbright: \"Regulating crypto-assets in Europe: Practical guide to MiCA\" (2024)—comprehensive implementation overview[3]\n  - Skadden: \"MiCA Update – Six Months in Application\" (July 2025)—assessment of licencing activity and regulatory developments[5]\n  - Squire Patton Boggs: \"MiCA Legal Framework – How To Comply With the EU's Crypto Asset Rules\" (August 2025)—compliance-focused guidance[8]\n\n## Future Directions\n\n- Anticipated regulatory refinements\n  - Potential formalisation of review mechanisms proposed by French, Austrian and Italian authorities pending broader EU authority consensus[2]\n  - Enhanced cybersecurity requirements at authorisation stage likely under consideration[2]\n  - Standardised investor protection protocols across crypto and traditional financial services anticipated[2]\n\n- Emerging challenges and research priorities\n  - Coordination mechanisms between national competent authorities require optimisation to reduce compliance fragmentation[2]\n  - Interoperability between MiCA and complementary frameworks (MiFID II, PSD2) demands clarification through technical standards[4][7]\n  - Regulatory arbitrage risks necessitate continued international convergence efforts, particularly with US frameworks[6]\n  - Cybersecurity and operational resilience standards require further development given rapid market evolution\n\n- Market development trajectories\n  - Continued CASP licencing activity expected across EU member states with potential acceleration as regulatory certainty increases\n  - Innovation in tokenised assets and decentralised finance (DeFi) governance likely to test regulatory boundaries\n  - UK regulatory divergence from MiCA may create both opportunities and compliance complexities for cross-border operators\n\n## Metadata\n\n- **Migration Status**: Ontology block enriched on 2025-11-12\n- **Last Updated**: 2025-11-12\n- **Review Status**: Comprehensive editorial review\n- **Verification**: Academic sources verified\n- **Regional Context**: UK/North England where applicable",
  "backlinks": [],
  "wiki_links": [
    "BlockchainDomain",
    "Regulation"
  ],
  "ontology": {
    "term_id": "BC-0482",
    "preferred_term": "EU MiCA Regulation",
    "alt_terms": [],
    "iri": "http://narrativegoldmine.com/blockchain#EUMiCARegulation",
    "source_domain": "metaverse",
    "domain": "metaverse",
    "domain_full_name": "",
    "definition": "A component of the blockchain ecosystem.",
    "scope_note": null,
    "status": "stub-needs-content",
    "maturity": "draft",
    "version": null,
    "public_access": true,
    "last_updated": null,
    "authority_score": null,
    "quality_score": null,
    "cross_domain_links": null,
    "owl_class": "bc:EUMiCARegulation",
    "owl_physicality": "ConceptualEntity",
    "owl_role": "Concept",
    "owl_inferred_class": null,
    "is_subclass_of": [],
    "has_part": [],
    "is_part_of": [],
    "requires": [],
    "depends_on": [],
    "enables": [],
    "relates_to": [],
    "bridges_to": [],
    "bridges_from": [],
    "domain_extensions": {},
    "belongs_to_domain": [
      "BlockchainDomain"
    ],
    "implemented_in_layer": [],
    "source": [],
    "validation": {
      "is_valid": false,
      "errors": [
        "Missing required property: last-updated",
        "Missing required property: is-subclass-of (at least one parent class)",
        "owl:class namespace 'bc' doesn't match source-domain 'metaverse'"
      ]
    }
  }
}