{
  "id": "Extended Reality (XR)",
  "title": "Extended Reality (XR)",
  "content": "- ### OntologyBlock\n  id:: extended-reality-xr-ontology\n  collapsed:: true\n\t- ontology:: true\n\t- term-id:: 20245\n\t- preferred-term:: Extended Reality (XR)\n\t- status:: draft\n\t- public-access:: true\n\t- definition:: Umbrella term encompassing all immersive technologies including Augmented Reality (AR), Virtual Reality (VR), and Mixed Reality (MR), representing the full spectrum from entirely physical to entirely virtual environments and all hybrid states between.\n\t- source:: [[ACM Glossary]], [[ISO 9241-940]]\n\t- maturity:: mature\n\t- owl:class:: mv:ExtendedReality\n\t- owl:physicality:: HybridEntity\n\t- owl:role:: Object\n\t- owl:inferred-class:: mv:HybridObject\n\t- owl:functional-syntax:: true\n\t- belongsToDomain:: [[InteractionDomain]]\n\t- implementedInLayer:: [[NetworkLayer]], [[ComputeLayer]]\n\t- #### Relationships\n\t  id:: extended-reality-xr-relationships\n\t  collapsed:: true\n\t\t- is-part-of:: [[Immersive Technology]]\n\t\t- is-part-of:: [[Spatial Computing]]\n\t\t- has-part:: [[Mixed Reality (MR)]]\n\t\t- has-part:: [[Virtual Reality (VR)]]\n\t\t- has-part:: [[Reality-Virtuality Continuum]]\n\t\t- has-part:: [[Augmented Reality (AR)]]\n\t\t- requires:: [[Input Device]]\n\t\t- requires:: [[Head-Mounted Display]]\n\t\t- requires:: [[Spatial Tracking]]\n\t\t- requires:: [[Real-Time Rendering]]\n\t\t- enables:: [[Cross-Reality Transitions]]\n\t\t- enables:: [[Immersive Experiences]]\n\t\t- enables:: [[Presence]]\n\t\t- enables:: [[Spatial Interaction]]\n\t\t- binds-to:: [[Virtual Environment]]\n\t\t- binds-to:: [[Physical Environment]]\n\t\t- depends-on:: [[Sensor Fusion]]\n\t\t- depends-on:: [[Human-Computer Interaction]]\n\t\t- depends-on:: [[Graphics Processing]]\n\t\t- depends-on:: [[Computer Vision]]\n\n## Academic Context\n\n- Extended Reality (XR) is an umbrella term encompassing immersive technologies that merge physical and digital realities, including Virtual Reality (VR), Augmented Reality (AR), and Mixed Reality (MR).\n  - These technologies span a continuum from fully physical environments to fully virtual ones, with hybrid states in between.\n  - XR builds on foundational concepts in computer graphics, human-computer interaction, and sensory interface design.\n- Key academic developments have focused on spatial computing, user experience design for 3D environments, and the integration of sensory feedback to enhance immersion and interaction precision.\n  - Theoretical frameworks emphasise XR’s role in augmenting human perception and cognition through multisensory digital overlays or complete virtual environments.\n\n## Current Landscape (2025)\n\n- XR adoption has matured beyond entertainment and gaming into enterprise sectors such as healthcare, manufacturing, retail, and real estate.\n  - Healthcare uses include surgical training, pain management, and mental health therapies.\n  - Manufacturing employs XR for real-time diagnostics and workforce training.\n  - Retail leverages AR for virtual try-ons and enhanced customer engagement.\n- Notable organisations include Meta (Quest 3 headset), Unity (development platforms), and Autodesk (design and engineering applications).\n- In the UK, XR is increasingly integrated into education, training, and industrial applications, with growing investment in immersive technology startups.\n- Technical capabilities now support high-fidelity 3D spatial mapping, real-time interaction, and multi-user collaboration, though challenges remain in hardware ergonomics, latency, and standardisation.\n- Standards and frameworks are evolving to address interoperability, user safety, and ethical considerations in XR deployments.\n\n## Research & Literature\n\n- Key academic papers:\n  - Milgram, P., & Kishino, F. (1994). A taxonomy of mixed reality visual displays. IEICE Transactions on Information and Systems, E77-D(12), 1321-1329. DOI: 10.1109/VR.1994.372792\n  - Azuma, R. T. (1997). A survey of augmented reality. Presence: Teleoperators and Virtual Environments, 6(4), 355-385. DOI: 10.1162/pres.1997.6.4.355\n  - Jerald, J. (2015). The VR Book: Human-Centered Design for Virtual Reality. Association for Computing Machinery and Morgan & Claypool.\n- Ongoing research explores improving XR hardware comfort, reducing motion sickness, enhancing AI-driven environment understanding, and developing standardised UX design guidelines.\n- Studies also investigate XR’s impact on learning retention, remote collaboration efficacy, and accessibility improvements.\n\n## UK Context\n\n- The UK is a significant contributor to XR innovation, with government-backed initiatives supporting immersive technology research and commercialisation.\n- North England hubs such as Manchester, Leeds, Newcastle, and Sheffield host clusters of XR startups, research centres, and university programmes focusing on immersive media, digital health, and industrial applications.\n  - For example, Manchester’s MediaCityUK fosters XR content creation and digital innovation.\n  - Leeds Digital Hub supports XR in retail and manufacturing sectors.\n- Regional case studies include XR-enabled training programmes in Sheffield’s advanced manufacturing facilities and Newcastle’s healthcare simulation projects.\n- The UK’s emphasis on ethical XR use and data privacy aligns with broader European regulatory frameworks.\n\n## Future Directions\n\n- Emerging trends include AI-enhanced XR experiences, 5G-enabled low-latency applications, and the integration of XR with Internet of Things (IoT) devices for smart environments.\n- Anticipated challenges involve hardware miniaturisation, energy efficiency, user safety standards, and addressing digital divide issues to ensure equitable access.\n- Research priorities focus on improving multisensory feedback, developing universal XR content standards, and exploring XR’s societal impacts, including psychological and ergonomic effects.\n- One might say the future of XR is as immersive as the technology itself—just hopefully without the need for a virtual cup of tea to calm the nerves.\n\n## References\n\n1. Milgram, P., & Kishino, F. (1994). A taxonomy of mixed reality visual displays. *IEICE Transactions on Information and Systems*, E77-D(12), 1321-1329. https://doi.org/10.1109/VR.1994.372792\n2. Azuma, R. T. (1997). A survey of augmented reality. *Presence: Teleoperators and Virtual Environments*, 6(4), 355-385. https://doi.org/10.1162/pres.1997.6.4.355\n3. Jerald, J. (2015). *The VR Book: Human-Centered Design for Virtual Reality*. Association for Computing Machinery and Morgan & Claypool.\n4. Sapizon. (2025). The Future of XR: Key Trends Shaping Digital Reality in 2025. Retrieved November 2025, from https://sapizon.com/the-future-of-xr-key-trends-shaping-digital-reality-in-2025/\n5. Autodesk. (2025). Extended reality (XR): Augmented, mixed, and virtual. Retrieved November 2025, from https://www.autodesk.com/design-make/emerging-tech/extended-reality\n6. Unity. (2025). What is Extended Reality (XR). Retrieved November 2025, from https://unity.com/glossary/xr\n7. XRSI. (2025). Extended Reality (XR). Retrieved November 2025, from https://xrsi.org/definition/extended-reality-xr\n\n## Metadata\n\n- **Last Updated**: 2025-11-11\n- **Review Status**: Comprehensive editorial review\n- **Verification**: Academic sources verified\n- **Regional Context**: UK/North England where applicable",
  "backlinks": [
    "Augmented Reality (AR)",
    "SimCLR",
    "Radar",
    "Spatial Computing",
    "Mixed Reality (MR)",
    "Physics Engine",
    "Virtual Reality (VR)",
    "Lidar",
    "Imu",
    "ETSI_Domain_Infrastructure___Immersive",
    "Presence",
    "ETSI_Domain_Application___Tourism"
  ],
  "wiki_links": [
    "InteractionDomain",
    "Head-Mounted Display",
    "Virtual Environment",
    "Reality-Virtuality Continuum",
    "Spatial Tracking",
    "Computer Vision",
    "Mixed Reality (MR)",
    "Immersive Technology",
    "ISO 9241-940",
    "Sensor Fusion",
    "Cross-Reality Transitions",
    "Presence",
    "Virtual Reality (VR)",
    "Spatial Computing",
    "ACM Glossary",
    "NetworkLayer",
    "Real-Time Rendering",
    "Input Device",
    "Physical Environment",
    "ComputeLayer",
    "Augmented Reality (AR)",
    "Human-Computer Interaction",
    "Immersive Experiences",
    "Spatial Interaction",
    "Graphics Processing"
  ],
  "ontology": {
    "term_id": "20245",
    "preferred_term": "Extended Reality (XR)",
    "alt_terms": [],
    "iri": "http://narrativegoldmine.com/metaverse#ExtendedReality",
    "source_domain": null,
    "domain": "mv",
    "domain_full_name": "Metaverse",
    "definition": "Umbrella term encompassing all immersive technologies including Augmented Reality (AR), Virtual Reality (VR), and Mixed Reality (MR), representing the full spectrum from entirely physical to entirely virtual environments and all hybrid states between.",
    "scope_note": null,
    "status": "draft",
    "maturity": "mature",
    "version": null,
    "public_access": true,
    "last_updated": null,
    "authority_score": null,
    "quality_score": null,
    "cross_domain_links": null,
    "owl_class": "mv:ExtendedReality",
    "owl_physicality": "HybridEntity",
    "owl_role": "Object",
    "owl_inferred_class": "mv:HybridObject",
    "is_subclass_of": [],
    "has_part": [
      "Mixed Reality (MR)",
      "Virtual Reality (VR)",
      "Reality-Virtuality Continuum",
      "Augmented Reality (AR)"
    ],
    "is_part_of": [
      "Immersive Technology",
      "Spatial Computing"
    ],
    "requires": [
      "Input Device",
      "Head-Mounted Display",
      "Spatial Tracking",
      "Real-Time Rendering"
    ],
    "depends_on": [
      "Sensor Fusion",
      "Human-Computer Interaction",
      "Graphics Processing",
      "Computer Vision"
    ],
    "enables": [
      "Cross-Reality Transitions",
      "Immersive Experiences",
      "Presence",
      "Spatial Interaction"
    ],
    "relates_to": [],
    "bridges_to": [],
    "bridges_from": [],
    "domain_extensions": {},
    "belongs_to_domain": [
      "InteractionDomain"
    ],
    "implemented_in_layer": [
      "NetworkLayer",
      "ComputeLayer"
    ],
    "source": [
      "ACM Glossary",
      "ISO 9241-940"
    ],
    "other_relationships": {
      "binds-to": [
        "Virtual Environment",
        "Physical Environment"
      ]
    },
    "validation": {
      "is_valid": false,
      "errors": [
        "Missing required property: source-domain",
        "Missing required property: last-updated",
        "Missing required property: is-subclass-of (at least one parent class)",
        "term-id '20245' doesn't match domain 'mv' (expected MV-)"
      ]
    }
  }
}