{
  "id": "Fairness Auditing Tools",
  "title": "Fairness Auditing Tools",
  "content": "- ### OntologyBlock\n  id:: 0386-fairness-auditing-tools-ontology\n  collapsed:: true\n\n  - **Identification**\n\n    - domain-prefix:: AI\n\n    - sequence-number:: 0386\n\n    - filename-history:: [\"AI-0386-fairness-auditing-tools.md\"]\n    - public-access:: true\n    - ontology:: true\n    - term-id:: AI-0386\n    - preferred-term:: Fairness Auditing Tools\n    - source-domain:: ai-grounded\n    - status:: complete\n    - version:: 1.0\n    - last-updated:: 2025-10-29\n\n  - **Definition**\n    - definition:: Fairness Auditing Tools are software libraries, platforms, and frameworks designed to detect, measure, and mitigate algorithmic bias in AI systems through automated analysis, visualization, and intervention capabilities. Leading open-source tools include Fairlearn (Microsoft, MIT license) providing fairness metrics and mitigation algorithms for Python with scikit-learn integration, AIF360 (IBM, Apache-2.0 license) offering comprehensive bias detection and mitigation across the ML pipeline with 70+ fairness metrics, What-If Tool (Google, Apache-2.0) providing interactive visual interfaces for TensorFlow model exploration and counterfactual analysis, Aequitas (University of Chicago, MIT license) focusing on fairness auditing for criminal justice and policy applications, and FairTest (Columbia University, MIT license) enabling statistical fairness testing with association discovery. These tools implement fairness metrics including demographic parity, equalized odds, and predictive parity, provide visualizations such as fairness dashboards, confusion matrices disaggregated by group, and disparity charts, and support mitigation techniques including reweighting, threshold optimization, and adversarial debiasing. Adoption best practices include multi-tool validation to cross-verify findings, integration into CI/CD pipelines for continuous fairness monitoring, documentation of fairness decisions and tradeoffs, and stakeholder engagement in selecting appropriate fairness metrics. These tools operationalize fairness requirements from standards including IEEE P7003-2021, ISO/IEC TR 24027:2021, and the EU AI Act Article 10 on data governance and bias mitigation.\n    - maturity:: mature\n    - source:: [[Fairlearn]], [[AIF360]], [[IEEE P7003-2021]], [[ISO/IEC TR 24027]]\n    - authority-score:: 0.95\n\n  - **Semantic Classification**\n    - owl:class:: aigo:FairnessAuditingTools\n    - owl:physicality:: VirtualEntity\n    - owl:role:: Process\n    - owl:inferred-class:: aigo:VirtualProcess\n    - belongsToDomain:: [[AIEthicsDomain]]\n    - implementedInLayer:: [[ConceptualLayer]]\n\n  - #### Relationships\n    id:: 0386-fairness-auditing-tools-relationships\n\n  - #### OWL Axioms\n    id:: 0386-fairness-auditing-tools-owl-axioms\n    collapsed:: true\n    - ```clojure\n      (Declaration (Class :FairnessAuditingTool))\n(SubClassOf :FairnessAuditingTool :SoftwareTool)\n(SubClassOf :FairnessAuditingTool :EthicalAIInfrastructure)\n\n(AnnotationAssertion rdfs:label :FairnessAuditingTool\n  \"Fairness Auditing Tool\"@en)\n(AnnotationAssertion rdfs:comment :FairnessAuditingTool\n  \"Software libraries and platforms for detecting, measuring, and mitigating algorithmic bias, including Fairlearn, AIF360, What-If Tool, Aequitas, and FairTest.\"@en)\n\n;; Object Properties\n(Declaration (ObjectProperty :implements))\n(ObjectPropertyDomain :implements :FairnessAuditingTool)\n(ObjectPropertyRange :implements :FairnessMetric)\n\n(Declaration (ObjectProperty :providesVisualization))\n(ObjectPropertyDomain :providesVisualization :FairnessAuditingTool)\n(ObjectPropertyRange :providesVisualization :VisualizationType)\n\n(Declaration (ObjectProperty :supportsMitigation))\n(ObjectPropertyDomain :supportsMitigation :FairnessAuditingTool)\n(ObjectPropertyRange :supportsMitigation :BiasMitigationTechnique)\n\n;; Data Properties\n(Declaration (DataProperty :hasLicense))\n(DataPropertyDomain :hasLicense :FairnessAuditingTool)\n(DataPropertyRange :hasLicense xsd:string)\n\n(Declaration (DataProperty :supportsProgrammingLanguage))\n(DataPropertyDomain :supportsProgrammingLanguage :FairnessAuditingTool)\n(DataPropertyRange :supportsProgrammingLanguage xsd:string)\n\n(Declaration (DataProperty :hasRepositoryURL))\n(DataPropertyDomain :hasRepositoryURL :FairnessAuditingTool)\n(DataPropertyRange :hasRepositoryURL xsd:anyURI)\n\n;; Tool Subclasses\n(Declaration (Class :Fairlearn))\n(SubClassOf :Fairlearn :FairnessAuditingTool)\n(DataPropertyAssertion :hasLicense :Fairlearn \"MIT\"^^xsd:string)\n(DataPropertyAssertion :supportsProgrammingLanguage :Fairlearn \"Python\"^^xsd:string)\n(DataPropertyAssertion :hasRepositoryURL :Fairlearn\n  \"https://github.com/fairlearn/fairlearn\"^^xsd:anyURI)\n\n(Declaration (Class :AIF360))\n(SubClassOf :AIF360 :FairnessAuditingTool)\n(DataPropertyAssertion :hasLicense :AIF360 \"Apache-2.0\"^^xsd:string)\n(DataPropertyAssertion :supportsProgrammingLanguage :AIF360 \"Python\"^^xsd:string)\n\n(Declaration (Class :WhatIfTool))\n(SubClassOf :WhatIfTool :FairnessAuditingTool)\n(DataPropertyAssertion :hasLicense :WhatIfTool \"Apache-2.0\"^^xsd:string)\n(AnnotationAssertion rdfs:comment :WhatIfTool\n  \"Interactive visual interface for TensorFlow models\"@en)\n\n(Declaration (Class :Aequitas))\n(SubClassOf :Aequitas :FairnessAuditingTool)\n(DataPropertyAssertion :hasLicense :Aequitas \"MIT\"^^xsd:string)\n\n(Declaration (Class :FairTest))\n(SubClassOf :FairTest :FairnessAuditingTool)\n(DataPropertyAssertion :hasLicense :FairTest \"MIT\"^^xsd:string)\n      ```\n\n- ## About 0386 Fairness Auditing Tools\n  id:: 0386-fairness-auditing-tools-about\n\n  - \n  -\n    - ### Use Cases\n    - **Education**: Teaching fairness concepts interactively\n    - **Model Exploration**: Understanding model behavior\n    - **Debugging**: Identifying systematic errors\n    -\n  - ### Best Practices\n  - ### 1. Multi-Tool Validation\n    Use multiple tools to cross-validate findings:\n    - Fairlearn for quick checks\n    - AIF360 for comprehensive analysis\n    - Aequitas for compliance verification\n\n\t- ## Consumer AI Adoption\n\t\t- An estimated 1.7 to 1.8 billion people globally use AI tools.\n\t\t- 61% of Americans have used AI.\n\t\t- Nearly one in five Americans use AI every day.\n\t\t- AI usage is prevalent across all generations, with millennials leading in daily use at 24%.\n\n- # Agentic Tool Use\n\n\t- ### Audio Enhancement\n\t\t- AI-powered tools can be used to improve the quality of audio recordings by removing background noise, reducing echo, and balancing audio levels.\n\n\t- ### [Adobe Podcast](https://podcast.adobe.com/)\n\t\t- A suite of AI-powered tools for recording and editing podcasts.\n\n\t- ## AI Tools and Extensions\n\n\t\t- ## Finding all the tools.\n\t\t\t- https://github.com/comfyanonymous/ComfyUI\n\t\t\t- {{renderer :linkpreview,https://github.com/comfyanonymous/ComfyUI}}\n\t\t\t- https://huggingface.co/\n\t\t\t- {{renderer :linkpreview,https://huggingface.co/}}\n\t\t\t- https://civitai.com/\n\t\t\t- {{renderer :linkpreview,https://civitai.com/}}\n\t\t\t- https://www.comfyworkflows.com\n\t\t\t- {{renderer :linkpreview,https://www.comfyworkflows.com}}\n\n- # Selected Consumer Tools\n\t- Search\n\t\t- [Perplexity](https://www.perplexity.ai/)\n\t\t- Deep research.\n\t\t-\n\n\t\t- ##### Webaverse\n\t\t\t- [Webaverse](https://webaverse.com/) are an open collective using opensource tools to create interoperable metaverses.\n\n\t- ### Salesforce\n\t\t- Slack. Don't discount Salesforce. Again, if you use slack, stick with this for now. **All** of the tools are coming to **all** of the platforms.\n\n\t- ## Consumer AI Adoption\n\t\t- An estimated 1.7 to 1.8 billion people globally use AI tools.\n\t\t- 61% of Americans have used AI.\n\t\t- Nearly one in five Americans use AI every day.\n\t\t- AI usage is prevalent across all generations, with millennials leading in daily use at 24%.\n\n- # Agentic Tool Use\n\n\t- ### Audio Enhancement\n\t\t- AI-powered tools can be used to improve the quality of audio recordings by removing background noise, reducing echo, and balancing audio levels.\n\n\t- ### [Adobe Podcast](https://podcast.adobe.com/)\n\t\t- A suite of AI-powered tools for recording and editing podcasts.\n\n\t- ## AI Tools and Extensions\n\n\t\t- ## Finding all the tools.\n\t\t\t- https://github.com/comfyanonymous/ComfyUI\n\t\t\t- {{renderer :linkpreview,https://github.com/comfyanonymous/ComfyUI}}\n\t\t\t- https://huggingface.co/\n\t\t\t- {{renderer :linkpreview,https://huggingface.co/}}\n\t\t\t- https://civitai.com/\n\t\t\t- {{renderer :linkpreview,https://civitai.com/}}\n\t\t\t- https://www.comfyworkflows.com\n\t\t\t- {{renderer :linkpreview,https://www.comfyworkflows.com}}\n\n- # Selected Consumer Tools\n\t- Search\n\t\t- [Perplexity](https://www.perplexity.ai/)\n\t\t- Deep research.\n\t\t-\n\n\t\t- ##### Webaverse\n\t\t\t- [Webaverse](https://webaverse.com/) are an open collective using opensource tools to create interoperable metaverses.\n\n\t- ### Salesforce\n\t\t- Slack. Don't discount Salesforce. Again, if you use slack, stick with this for now. **All** of the tools are coming to **all** of the platforms.\n\n\t- ## AI Tools and Extensions\n\n\t\t- ## Finding all the tools.\n\t\t\t- {{renderer :linkpreview,https://www.comfyworkflows.com}}\n\n\t\t- ##### Webaverse\n\t\t\t- [Webaverse](https://webaverse.com/) are an open collective using opensource tools to create interoperable metaverses.\n\n\t- ### Salesforce\n\t\t- Slack. Don't discount Salesforce. Again, if you use slack, stick with this for now. **All** of the tools are coming to **all** of the platforms.\n\n\t\t- ## Finding all the tools.\n\t\t\t- {{renderer :linkpreview,https://www.comfyworkflows.com}}\n\n\t\t\t- ### Developer-Oriented Tools\n\t\t- **For Roleplay:** SillyTavern excels in flexibility with multiple backends.\n\n\t\t- ## Finding all the tools.\n\t\t\t- {{renderer :linkpreview,https://www.comfyworkflows.com}}\n\n\t\t\t- ### Developer-Oriented Tools\n\t\t- **For Roleplay:** SillyTavern excels in flexibility with multiple backends.\n\n\t\t\t- ### Developer-Oriented Tools\n\t\t- **For Roleplay:** SillyTavern excels in flexibility with multiple backends.\n\n- ## Tools and Platforms\n\n- ## Tools and Platforms\n\n- ## Tools and Platforms\n\n- ## Tools and Platforms\n\n- ## Tools and Platforms\n\n- ## Tools and Platforms\n\n- ## Tools and Platforms\n\n\n\n## Academic Context\n\n- Fairness auditing tools are systematic frameworks and software solutions designed to detect, measure, and mitigate bias in artificial intelligence (AI) systems.\n  - These tools are grounded in interdisciplinary research spanning computer science, ethics, law, and social sciences, reflecting the complex nature of fairness in AI.\n  - Key academic foundations include fairness metrics such as demographic parity, equal opportunity, and disparate impact, which quantify bias and guide mitigation strategies.\n  - The academic discourse emphasises that fairness is not merely a technical problem but a socio-technical challenge requiring transparency, accountability, and stakeholder engagement.\n\n## Current Landscape (2025)\n\n- Fairness auditing tools have become integral to AI development pipelines across industries, particularly in high-stakes domains like healthcare, finance, recruitment, and law enforcement.\n  - Leading platforms include IBM AI Fairness 360, Microsoft Fairlearn, Google’s What-If Tool, and Amazon SageMaker Clarify, each offering capabilities for data auditing, model analysis, and bias mitigation.\n  - Organisations increasingly adopt ethics-driven auditing approaches that combine quantitative metrics with qualitative assessments to ensure compliance with ethical standards such as fairness, accountability, transparency, and privacy (FAT-P).\n- Technical capabilities now extend beyond bias detection to include explainability, robustness testing, and continuous monitoring, although challenges remain in addressing intersectional biases and context-specific fairness.\n- Standards and frameworks guiding fairness audits have matured, with regulatory bodies and industry consortia promoting trustworthy AI principles and compliance mechanisms to foster ethical AI deployment.\n\n## Research & Literature\n\n- Key academic contributions include:\n  - Barocas, S., Hardt, M., & Narayanan, A. (2019). *Fairness and Machine Learning: Limitations and Opportunities*. Available online. This foundational text explores fairness definitions and algorithmic trade-offs.\n  - Mehrabi, N., Morstatter, F., Saxena, N., Lerman, K., & Galstyan, A. (2021). \"A Survey on Bias and Fairness in Machine Learning.\" *ACM Computing Surveys*, 54(6), 1-35. DOI: 10.1145/3457607.\n  - Friedler, S. A., Scheidegger, C., & Venkatasubramanian, S. (2021). \"The (Im)possibility of Fairness: Different Value Systems Require Different Mechanisms for Fair Decision Making.\" *Communications of the ACM*, 64(4), 136-143. DOI: 10.1145/3433949.\n- Ongoing research focuses on developing context-aware fairness metrics, improving audit transparency, and integrating human-in-the-loop approaches to balance technical and ethical considerations.\n\n## UK Context\n\n- The UK has been a proactive player in ethical AI, with government initiatives and research centres promoting fairness auditing tools.\n  - Notable contributions include the Alan Turing Institute’s work on AI ethics and fairness, which collaborates with industry and academia to develop practical auditing methodologies.\n- In North England, innovation hubs in Manchester, Leeds, Newcastle, and Sheffield are fostering AI ethics research and deploying fairness auditing in sectors such as healthcare and public services.\n  - For example, Manchester’s AI research community actively explores bias mitigation in healthcare diagnostics, while Leeds focuses on fair AI in social policy applications.\n- Regional case studies demonstrate the integration of fairness audits in public sector AI deployments, highlighting the importance of local context and stakeholder engagement.\n\n## Future Directions\n\n- Emerging trends include:\n  - The integration of fairness auditing tools with generative AI systems, addressing new challenges posed by large language models and synthetic data.\n  - Development of dynamic, real-time auditing frameworks capable of adapting to evolving AI behaviours and data distributions.\n  - Greater emphasis on intersectional fairness and the inclusion of diverse stakeholder perspectives in audit processes.\n- Anticipated challenges involve balancing transparency with intellectual property concerns, managing audit complexity, and ensuring fairness across global and culturally diverse contexts.\n- Research priorities focus on enhancing audit explainability, automating bias detection without sacrificing nuance, and embedding fairness as a continuous lifecycle process rather than a one-off check.\n\n## References\n\n1. Barocas, S., Hardt, M., & Narayanan, A. (2019). *Fairness and Machine Learning: Limitations and Opportunities*. Available at: https://fairmlbook.org  \n2. Mehrabi, N., Morstatter, F., Saxena, N., Lerman, K., & Galstyan, A. (2021). \"A Survey on Bias and Fairness in Machine Learning.\" *ACM Computing Surveys*, 54(6), 1-35. DOI: 10.1145/3457607  \n3. Friedler, S. A., Scheidegger, C., & Venkatasubramanian, S. (2021). \"The (Im)possibility of Fairness: Different Value Systems Require Different Mechanisms for Fair Decision Making.\" *Communications of the ACM*, 64(4), 136-143. DOI: 10.1145/3433949  \n4. The Alan Turing Institute. (2025). *AI Ethics and Fairness Research*. Available at: https://www.turing.ac.uk/research/research-programmes/ai-ethics-and-fairness  \n5. Aud-AI Consortium. (2025). \"AI Bias and Fairness Audits: Ensuring Ethical and Transparent Artificial Intelligence.\" Available at: https://aud-ai.eu/ai-bias-and-fairness-audits-ensuring-ethical-and-transparent-artificial-intelligence/\n\n\n## Metadata\n\n\n- **Migration Status**: Ontology block enriched on 2025-11-12\n- **Last Updated**: 2025-11-12\n- **Review Status**: Comprehensive editorial review\n- **Verification**: Academic sources verified\n- **Regional Context**: UK/North England where applicable",
  "backlinks": [
    "Fairness Metrics"
  ],
  "wiki_links": [
    "ISO/IEC TR 24027",
    "AIF360",
    "Fairlearn",
    "ConceptualLayer",
    "AIEthicsDomain",
    "IEEE P7003-2021"
  ],
  "ontology": {
    "term_id": "AI-0386",
    "preferred_term": "Fairness Auditing Tools",
    "alt_terms": [],
    "iri": null,
    "source_domain": "ai-grounded",
    "domain": "ai-grounded",
    "domain_full_name": "",
    "definition": "Fairness Auditing Tools are software libraries, platforms, and frameworks designed to detect, measure, and mitigate algorithmic bias in AI systems through automated analysis, visualization, and intervention capabilities. Leading open-source tools include Fairlearn (Microsoft, MIT license) providing fairness metrics and mitigation algorithms for Python with scikit-learn integration, AIF360 (IBM, Apache-2.0 license) offering comprehensive bias detection and mitigation across the ML pipeline with 70+ fairness metrics, What-If Tool (Google, Apache-2.0) providing interactive visual interfaces for TensorFlow model exploration and counterfactual analysis, Aequitas (University of Chicago, MIT license) focusing on fairness auditing for criminal justice and policy applications, and FairTest (Columbia University, MIT license) enabling statistical fairness testing with association discovery. These tools implement fairness metrics including demographic parity, equalized odds, and predictive parity, provide visualizations such as fairness dashboards, confusion matrices disaggregated by group, and disparity charts, and support mitigation techniques including reweighting, threshold optimization, and adversarial debiasing. Adoption best practices include multi-tool validation to cross-verify findings, integration into CI/CD pipelines for continuous fairness monitoring, documentation of fairness decisions and tradeoffs, and stakeholder engagement in selecting appropriate fairness metrics. These tools operationalize fairness requirements from standards including IEEE P7003-2021, ISO/IEC TR 24027:2021, and the EU AI Act Article 10 on data governance and bias mitigation.",
    "scope_note": null,
    "status": "complete",
    "maturity": "mature",
    "version": "1.0",
    "public_access": true,
    "last_updated": "2025-10-29",
    "authority_score": 0.95,
    "quality_score": null,
    "cross_domain_links": null,
    "owl_class": "aigo:FairnessAuditingTools",
    "owl_physicality": "VirtualEntity",
    "owl_role": "Process",
    "owl_inferred_class": "aigo:VirtualProcess",
    "is_subclass_of": [],
    "has_part": [],
    "is_part_of": [],
    "requires": [],
    "depends_on": [],
    "enables": [],
    "relates_to": [],
    "bridges_to": [],
    "bridges_from": [],
    "domain_extensions": {},
    "belongs_to_domain": [
      "AIEthicsDomain"
    ],
    "implemented_in_layer": [
      "ConceptualLayer"
    ],
    "source": [
      "Fairlearn",
      "AIF360",
      "IEEE P7003-2021",
      "ISO/IEC TR 24027"
    ],
    "validation": {
      "is_valid": false,
      "errors": [
        "Missing required property: is-subclass-of (at least one parent class)",
        "owl:class namespace 'aigo' doesn't match source-domain 'ai-grounded'"
      ]
    }
  }
}