{
  "id": "Federated Edge Learning (AI-0437)",
  "title": "Federated Edge Learning (AI-0437)",
  "content": "- ### OntologyBlock\n  id:: federated-edge-learning-ai-0437-ontology\n  collapsed:: true\n\t- ontology:: true\n\t- term-id:: AI-0437\n\t- preferred-term:: Federated Edge Learning (AI-0437)\n\t- status:: in\n\t- public-access:: true\n\t- definition:: Federated Edge Learning combines distributed machine learning with edge computing, enabling collaborative model training across decentralized edge devices while keeping training data locally on-device. This paradigm addresses privacy concerns by transmitting only model updates (gradients) rather than raw sensitive data to aggregation servers. Participants train local models on their devices using private datasets, then securely aggregate updates into a global model that improves collectively. Federated Edge Learning maintains data sovereignty, allowing healthcare systems, financial institutions, and autonomous fleets to benefit from collaborative intelligence without compromising individual privacy. The architecture comprises edge clients performing local training with limited computational resources, aggregation servers coordinating model updates, and secure aggregation protocols ensuring gradient confidentiality. Communication efficiency is critical; techniques like gradient compression, selective client participation, and quantization reduce network overhead by 10x or more. The approach supports differential privacy mechanisms, adding calibrated noise to gradients for formal privacy guarantees. Federated Edge Learning handles statistical heterogeneity where edge devices have non-identical data distributions, requiring robust aggregation algorithms. Applications include keyboard prediction on mobile devices, vehicular perception across connected cars, and enterprise analytics on sensitive data. Standards like IEEE P3652.1 specify federated learning baselines. This paradigm fundamentally shifts ML from centralized cloud processing to privacy-preserving distributed intelligence at network edges.\n\t- maturity:: mature\n\t- owl:class:: aigo:FederatedEdgeLearning\n\t- owl:physicality:: VirtualEntity\n\t- owl:role:: Process\n\t- owl:inferred-class:: aigo:VirtualProcess\n\t- belongsToDomain:: [[AIEthicsDomain]]\n\t- implementedInLayer:: [[ConceptualLayer]]\n\t- #### Relationships\n\t  id:: federated-edge-learning-ai-0437-relationships\n\t  collapsed:: true\n\t\t- is-subclass-of:: [[AIApplications]]\n\n## Federated Edge Learning (AI-0437)\n\nFederated Edge Learning (AI-0437) refers to federated edge learning combines distributed machine learning with edge computing, enabling collaborative model training across decentralized edge devices while keeping training data locally on-device. this paradigm addresses privacy concerns by transmitting only model updates (gradients) rather than raw sensitive data to aggregation servers. participants train local models on their devices using private datasets, then securely aggregate updates into a global model that improves collectively. federated edge learning maintains data sovereignty, allowing healthcare systems, financial institutions, and autonomous fleets to benefit from collaborative intelligence without compromising individual privacy. the architecture comprises edge clients performing local training with limited computational resources, aggregation servers coordinating model updates, and secure aggregation protocols ensuring gradient confidentiality. communication efficiency is critical; techniques like gradient compression, selective client participation, and quantization reduce network overhead by 10x or more. the approach supports differential privacy mechanisms, adding calibrated noise to gradients for formal privacy guarantees. federated edge learning handles statistical heterogeneity where edge devices have non-identical data distributions, requiring robust aggregation algorithms. applications include keyboard prediction on mobile devices, vehicular perception across connected cars, and enterprise analytics on sensitive data. standards like ieee p3652.1 specify federated learning baselines. this paradigm fundamentally shifts ml from centralised cloud processing to privacy-preserving distributed intelligence at network edges.\n\n- Industry adoption and implementations\n\t- FEL is increasingly adopted in sectors requiring real-time analytics and data privacy, such as healthcare, manufacturing, and smart transportation\n\t- Notable organisations and platforms\n\t\t- Google’s Federated Learning of Cohorts (FLoC) and related privacy-preserving initiatives\n\t\t- Microsoft’s Azure Edge AI and Federated Learning Toolkit\n\t\t- UK-based startups and research consortia, including those affiliated with the Alan Turing Institute and the UKRI Centre for Doctoral Training in AI for Medical Diagnosis and Care\n- UK and North England examples where relevant\n\t- The University of Manchester’s Smart Cities Research Centre utilises FEL for urban traffic management and environmental monitoring\n\t- Leeds City Council collaborates with local universities on FEL-driven smart city projects, focusing on energy efficiency and public safety\n\t- Newcastle University’s Urban Observatory employs FEL for real-time data analysis from distributed sensors across the city\n\t- Sheffield’s Advanced Manufacturing Research Centre (AMRC) explores FEL for predictive maintenance in industrial settings\n- Technical capabilities and limitations\n\t- Capabilities\n\t\t- Enables collaborative learning without centralising sensitive data\n\t\t- Reduces communication overhead and latency compared to cloud-based approaches\n\t\t- Supports adaptive and resilient models in dynamic environments\n\t- Limitations\n\t\t- Resource constraints on edge devices can limit model complexity and training speed\n\t\t- Heterogeneous device capabilities and network conditions pose challenges for consistent performance\n\t\t- Security and privacy risks remain, particularly in adversarial settings\n- Standards and frameworks\n\t- Open-source frameworks such as TensorFlow Federated and PySyft facilitate FEL development\n\t- Industry standards and best practices are emerging, driven by consortia like the Open Compute Project and the Edge Computing Consortium\n\n## Technical Details\n\n- **Id**: federated-edge-learning-(ai-0437)-about\n- **Collapsed**: true\n- **Domain Prefix**: AI\n- **Sequence Number**: 0437\n- **Filename History**: [\"AI-0437-federated-edge-learning.md\"]\n- **Public Access**: true\n- **Source Domain**: ai\n- **Status**: in-progress\n- **Last Updated**: 2025-10-29\n- **Maturity**: mature\n- **Source**:\n- **Authority Score**: 0.95\n- **Owl:Class**: aigo:FederatedEdgeLearning\n- **Owl:Physicality**: VirtualEntity\n- **Owl:Role**: Process\n- **Owl:Inferred Class**: aigo:VirtualProcess\n- **Belongstodomain**: [[AIEthicsDomain]]\n- **Implementedinlayer**: [[ConceptualLayer]]\n\n## Research & Literature\n\n- Key academic papers and sources\n\t- Karim, M. H. (2025). A Federated Learning Solution For Secure And Scalable Edge Computing In Distributed Environments. Master of Science Thesis, University of North Dakota. https://commons.und.edu/theses/7123\n\t- Li, Y., et al. (2025). Deep federated learning: a systematic review of methods. Frontiers in Computer Science, 7, 1617597. https://doi.org/10.3389/fcomp.2025.1617597\n\t- Zhang, Y., et al. (2025). Adaptive resource aware and privacy preserving federated edge learning. Scientific Reports, 15, 23398. https://doi.org/10.1038/s41598-025-23398-w\n\t- Wang, J., et al. (2025). Federated Learning and Edge AI for the Next Decade. Scientific Research Publishing. https://www.scirp.org/journal/paperinformation?paperid=140719\n- Ongoing research directions\n\t- Integration of FEL with generative AI models for synthetic data generation\n\t- Development of quantum-enhanced FEL algorithms for improved computational efficiency\n\t- Exploration of blockchain-based secure aggregation for tamper-proof model updates\n\t- Investigation of resource-aware scheduling and adaptive aggregation strategies for heterogeneous edge environments\n\n## UK Context\n\n- British contributions and implementations\n\t- The UK has been at the forefront of FEL research, with significant contributions from institutions such as the University of Cambridge, Imperial College London, and the University of Edinburgh\n\t- The Alan Turing Institute leads several FEL-focused projects, including those related to healthcare and smart cities\n- North England innovation hubs (if relevant)\n\t- Manchester, Leeds, Newcastle, and Sheffield host vibrant research communities and innovation hubs focused on FEL and related technologies\n\t- These cities benefit from strong collaborations between academia, industry, and local government, fostering a dynamic ecosystem for FEL development and deployment\n- Regional case studies\n\t- Manchester’s Smart Cities Research Centre has implemented FEL for urban traffic management, reducing congestion and improving public safety\n\t- Leeds City Council’s smart city initiatives leverage FEL for energy efficiency and environmental monitoring\n\t- Newcastle’s Urban Observatory uses FEL for real-time data analysis from distributed sensors, enhancing urban planning and emergency response\n\t- Sheffield’s AMRC applies FEL for predictive maintenance in manufacturing, optimising production processes and reducing downtime\n\n## Future Directions\n\n- Emerging trends and developments\n\t- Increased integration of FEL with generative AI and quantum computing\n\t- Expansion of FEL applications to new domains, such as autonomous vehicles and smart agriculture\n\t- Development of more robust and scalable FEL frameworks to support large-scale deployments\n- Anticipated challenges\n\t- Ensuring data privacy and security in increasingly complex and interconnected systems\n\t- Addressing resource constraints and heterogeneity in edge environments\n\t- Standardising FEL protocols and best practices across different industries and regions\n- Research priorities\n\t- Advancing adaptive and resource-aware FEL algorithms\n\t- Exploring the potential of blockchain and quantum technologies in FEL\n\t- Investigating the social and ethical implications of FEL, particularly in sensitive domains like healthcare and public safety\n\n## References\n\n1. Karim, M. H. (2025). A Federated Learning Solution For Secure And Scalable Edge Computing In Distributed Environments. Master of Science Thesis, University of North Dakota. https://commons.und.edu/theses/7123\n2. Li, Y., et al. (2025). Deep federated learning: a systematic review of methods. Frontiers in Computer Science, 7, 1617597. https://doi.org/10.3389/fcomp.2025.1617597\n3. Zhang, Y., et al. (2025). Adaptive resource aware and privacy preserving federated edge learning. Scientific Reports, 15, 23398. https://doi.org/10.1038/s41598-025-23398-w\n4. Wang, J., et al. (2025). Federated Learning and Edge AI for the Next Decade. Scientific Research Publishing. https://www.scirp.org/journal/paperinformation?paperid=140719\n\n## Metadata\n\n- **Migration Status**: Ontology block enriched on 2025-11-12\n- **Last Updated**: 2025-11-12\n- **Review Status**: Comprehensive editorial review\n- **Verification**: Academic sources verified\n- **Regional Context**: UK/North England where applicable",
  "backlinks": [],
  "wiki_links": [
    "AIApplications",
    "ConceptualLayer",
    "AIEthicsDomain"
  ],
  "ontology": {
    "term_id": "AI-0437",
    "preferred_term": "Federated Edge Learning (AI-0437)",
    "alt_terms": [],
    "iri": "http://narrativegoldmine.com/ai#aigo:FederatedEdgeLearning",
    "source_domain": "ai",
    "domain": "ai",
    "domain_full_name": "Artificial Intelligence",
    "definition": "Federated Edge Learning combines distributed machine learning with edge computing, enabling collaborative model training across decentralized edge devices while keeping training data locally on-device. This paradigm addresses privacy concerns by transmitting only model updates (gradients) rather than raw sensitive data to aggregation servers. Participants train local models on their devices using private datasets, then securely aggregate updates into a global model that improves collectively. Federated Edge Learning maintains data sovereignty, allowing healthcare systems, financial institutions, and autonomous fleets to benefit from collaborative intelligence without compromising individual privacy. The architecture comprises edge clients performing local training with limited computational resources, aggregation servers coordinating model updates, and secure aggregation protocols ensuring gradient confidentiality. Communication efficiency is critical; techniques like gradient compression, selective client participation, and quantization reduce network overhead by 10x or more. The approach supports differential privacy mechanisms, adding calibrated noise to gradients for formal privacy guarantees. Federated Edge Learning handles statistical heterogeneity where edge devices have non-identical data distributions, requiring robust aggregation algorithms. Applications include keyboard prediction on mobile devices, vehicular perception across connected cars, and enterprise analytics on sensitive data. Standards like IEEE P3652.1 specify federated learning baselines. This paradigm fundamentally shifts ML from centralized cloud processing to privacy-preserving distributed intelligence at network edges.",
    "scope_note": null,
    "status": "in",
    "maturity": "mature",
    "version": null,
    "public_access": true,
    "last_updated": "2025-10-29",
    "authority_score": null,
    "quality_score": null,
    "cross_domain_links": null,
    "owl_class": "aigo:FederatedEdgeLearning",
    "owl_physicality": "VirtualEntity",
    "owl_role": "Process",
    "owl_inferred_class": "aigo:VirtualProcess",
    "is_subclass_of": [
      "AIApplications"
    ],
    "has_part": [],
    "is_part_of": [],
    "requires": [],
    "depends_on": [],
    "enables": [],
    "relates_to": [],
    "bridges_to": [],
    "bridges_from": [],
    "domain_extensions": {},
    "belongs_to_domain": [
      "AIEthicsDomain"
    ],
    "implemented_in_layer": [
      "ConceptualLayer"
    ],
    "source": [],
    "validation": {
      "is_valid": false,
      "errors": [
        "owl:class namespace 'aigo' doesn't match source-domain 'ai'"
      ]
    }
  }
}