{
  "id": "Force Control",
  "title": "Force Control",
  "content": "- ### OntologyBlock\n  id:: rb-0053-force-control-ontology\n  collapsed:: true\n\t- ontology:: true\n\t- term-id:: RB-0053\n\t- domain-prefix:: RB\n\t- sequence-number:: 0053\n\t- filename-history:: [\"rb-0053-force-control.md\"]\n\t- preferred-term:: Force Control\n\t- source-domain:: metaverse\n\t- status:: draft\n    - public-access:: true\n\t- definition:: ### Primary Definition\n**Force Control** - Force Control in robotics systems\n\t- maturity:: draft\n\t- owl:class:: mv:rb0053forcecontrol\n\t- owl:physicality:: ConceptualEntity\n\t- owl:role:: Concept\n\t- belongsToDomain:: [[MetaverseDomain]]\n- ## About rb 0053 force control\n\t- ### Primary Definition\n**Force Control** - Force Control in robotics systems\n\t-\n\t- ### Original Content\n\t  collapsed:: true\n\t\t- ```\n# RB-0053: Force Control\n\t\t  \n\t\t  ## Metadata\n\t\t  - **Term ID**: RB-0053\n\t\t  - **Term Type**: Core Concept\n\t\t  - **Classification**: Control Systems\n\t\t  - **Priority**: 1 (Foundational)\n\t\t  - **Authority Score**: 0.95\n\t\t  - **ISO Reference**: ISO 8373:2021\n\t\t  - **Version**: 1.0.0\n\t\t  - **Last Updated**: 2025-10-28\n\t\t  \n\t\t  ## Definition\n\t\t  \n\t\t  ### Primary Definition\n\t\t  **Force Control** - Force Control in robotics systems\n\t\t  \n\t\t  ### Standards Context\n\t\t  Defined according to ISO 8373:2021 and related international robotics standards.\n\t\t  \n\t\t  ### Key Characteristics\n\t\t  1. Core property of robotics systems\n\t\t  2. Standardised definition across implementations\n\t\t  3. Measurable and verifiable attributes\n\t\t  4. Essential for safety and performance\n\t\t  5. Industry-wide recognition and adoption\n\t\t  \n\t\t  ## Formal Ontology (OWL Functional Syntax)\n\t\t  \n\t\t  ```clojure\n\t\t  (Declaration (Class :ForceControl))\n\t\t  (SubClassOf :ForceControl :Robot)\n\t\t  \n\t\t  (AnnotationAssertion rdfs:label :ForceControl \"Force Control\"@en)\n\t\t  (AnnotationAssertion rdfs:comment :ForceControl\n\t\t    \"Force Control - Foundational robotics concept\"@en)\n\t\t  (AnnotationAssertion :termID :ForceControl \"RB-0053\"^^xsd:string)\n\t\t  \n\t\t  (Declaration (ObjectProperty :relates To))\n\t\t  (ObjectPropertyDomain :relatesTo :ForceControl)\n\t\t  \n\t\t  (Declaration (DataProperty :hasProperty))\n\t\t  (DataPropertyDomain :hasProperty :ForceControl)\n\t\t  (DataPropertyRange :hasProperty xsd:string)\n\t\t  ```\n\t\t  \n\t\t  ## Relationships\n\t\t  \n\t\t  ### Parent Classes\n\t\t  - `Robot`: Primary classification\n\t\t  \n\t\t  ### Related Concepts\n\t\t  - Related robotics concepts and systems\n\t\t  - Cross-references to other ontology terms\n\t\t  - Integration with metaverse ontology\n\t\t  \n\t\t  ## Use Cases\n\t\t  \n\t\t  ### Industrial Applications\n\t\t  1. Manufacturing automation\n\t\t  2. Quality control systems\n\t\t  3. Process optimization\n\t\t  \n\t\t  ### Service Applications\n\t\t  1. Healthcare robotics\n\t\t  2. Logistics and warehousing\n\t\t  3. Consumer robotics\n\t\t  \n\t\t  ### Research Applications\n\t\t  1. Academic research platforms\n\t\t  2. Algorithm development\n\t\t  3. System integration studies\n\t\t  \n\t\t  ## Standards References\n\t\t  \n\t\t  ### Primary Standards\n\t\t  1. **ISO 8373:2021**: Primary reference standard\n\t\t  2. **ISO 8373:2021**: Robotics vocabulary\n\t\t  3. **Related IEEE standards**: Implementation guidelines\n\t\t  \n\t\t  ## Validation Criteria\n\t\t  \n\t\t  ### Conformance Requirements\n\t\t  1. ✓ Meets ISO 8373:2021 requirements\n\t\t  2. ✓ Documented implementation\n\t\t  3. ✓ Verifiable performance metrics\n\t\t  4. ✓ Safety compliance demonstrated\n\t\t  5. ✓ Industry best practices followed\n\t\t  \n\t\t  ## Implementation Notes\n\t\t  \n\t\t  ### Design Considerations\n\t\t  - System integration requirements\n\t\t  - Performance specifications\n\t\t  - Safety considerations\n\t\t  - Maintenance procedures\n\t\t  \n\t\t  ### Common Patterns\n\t\t  ```yaml\n\t\t  implementation:\n\t\t    standards_compliance: true\n\t\t    verification_method: standardised_testing\n\t\t    documentation_level: comprehensive\n\t\t  ```\n\t\t  \n\t\t  ## Cross-References\n\t\t  \n\t\t  ### Metaverse Ontology Integration\n\t\t  - Virtual representation systems\n\t\t  - Digital twin integration\n\t\t  - Simulation environments\n\t\t  \n\t\t  ### Domain Ontologies\n\t\t  - Manufacturing systems\n\t\t  - Control systems\n\t\t  - Safety systems\n\t\t  \n\t\t  ## Future Directions\n\t\t  \n\t\t  ### Emerging Trends\n\t\t  1. AI and machine learning integration\n\t\t  2. Advanced sensing capabilities\n\t\t  3. Improved safety systems\n\t\t  4. Enhanced human-robot collaboration\n\t\t  5. Standardisation advancements\n\t\t  \n\t\t  ---\n\t\t  \n\t\t  **Version History**\n\t\t  - 1.0.0 (2025-10-28): Initial foundational definition\n\t\t  \n\t\t  **Contributors**: Robotics Ontology Working Group\n\t\t  **License**: CC BY 4.0\n\t\t  **Namespace**: `https://metaverse-ontology.org/robotics/RB-0053`\n\t\t  \n\t\t  ```\n\n- # Wait!\n- Positives. AI is potentially very good at continuous, patient, optimised delivery of education, especially where there is a paucity of skilled teachers. This is a equalising force.\n\n- #### 4.12.10 AI's Impact on Societal Organization\n  Given these diverse viewpoints, it seems that the potential of AI to either aid authoritarianism or promote freedom is yet to be fully explored. However, the inherent ability of democracies to encourage disagreement and diverse perspectives may serve as a counterbalance to the potential of AI for authoritarian control. Moreover, AI's capacity as a catalytic force in societal organization should not be underestimated. The increasing discourse around AI and its implications for labor and technology usage suggests that AI technology is reshaping the world in ways that were unimaginable just a few years ago. Its capabilities in data analysis, decision making, and automation are transforming industries and redefining the scope of what's possible.\n\n- #### 4.12.10 AI's Impact on Societal Organization\n  Given these diverse viewpoints, it seems that the potential of AI to either aid authoritarianism or promote freedom is yet to be fully explored. However, the inherent ability of democracies to encourage disagreement and diverse perspectives may serve as a counterbalance to the potential of AI for authoritarian control. Moreover, AI's capacity as a catalytic force in societal organization should not be underestimated. The increasing discourse around AI and its implications for labor and technology usage suggests that AI technology is reshaping the world in ways that were unimaginable just a few years ago. Its capabilities in data analysis, decision making, and automation are transforming industries and redefining the scope of what's possible.\n\n\n# Updated Ontology Entry: rb-0053 Force Control\n\n## Academic Context\n\n- Force control represents a fundamental paradigm in robotic and machine automation, distinct from traditional position control\n  - Enables machines and robotic manipulators to regulate the force exerted on objects or environments rather than simply moving to predetermined coordinates\n  - Emerged as a serious research discipline approximately three decades ago, though contemporary implementations have evolved substantially\n  - Addresses a critical challenge in automation: the coupling between positional movement and force application, which position-only control cannot adequately resolve\n  - Foundational principle mirrors human tactile feedback mechanisms, allowing systems to \"sense and respond\" to physical interactions much as trained operators do\n\n## Current Landscape (2025)\n\n- Industry adoption and implementations\n  - Integrated force controller market valued at approximately $2.5 billion in 2025, with projected compound annual growth rate of 12% through 2033[2]\n  - Primary applications span grinding and cutting, assembly line operations, polishing, machine tending, and inspection tasks[2]\n  - Collaborative robots (cobots) increasingly incorporate force feedback capabilities, driven by manufacturing complexity and safety requirements\n  - Adoption accelerating across North America, Europe, and Asia-Pacific regions due to substantial industrial automation investments[2]\n  - UK manufacturing sector integrating force control in precision engineering and automotive assembly, particularly in Midlands and North West clusters\n  - North England innovation: Sheffield's advanced manufacturing sector exploring force control in tool development and precision machining; Manchester's robotics research community contributing to control algorithm development; Leeds manufacturing hubs implementing force control in medical device assembly\n- Technical capabilities and limitations\n  - Force measurement achieved through dedicated force transducers (measuring forces and torques across three spatial dimensions) or indirect estimation via motor current analysis[1]\n  - Control concepts include direct force control, indirect control via mechanical impedance specification, and hybrid motion-force combinations[1]\n  - Adaptive approaches, fuzzy controllers, and machine learning increasingly employed for sophisticated force regulation[1]\n  - Achieves superior consistency compared to position-only control, particularly for contact-based manufacturing tasks[1]\n  - Prevents equipment damage, workpiece degradation, and personnel injury through regulated contact force maintenance[1]\n  - Emerging miniaturisation trend enabling integration into compact spaces; wireless connectivity (Bluetooth 5.0, Wi-Fi 6) facilitating remote monitoring and IoT integration[5]\n- Standards and frameworks\n  - Hybrid control concepts combining force and motion control represent current best practice rather than force control in isolation[1]\n  - Sensor technology advances and actuator improvements expanding viable application domains[1]\n  - Real-time performance monitoring increasingly demanded across industries, driving precision measurement requirements[5]\n\n## Research & Literature\n\n- Key academic and technical sources\n  - Wikipedia contributors (2024). \"Force control.\" *Wikipedia, The Free Encyclopedia*. Comprehensive overview of control concepts, measurement methodologies, and application domains.\n  - Interface (2025). \"The Year of High-Performance Force Measurement.\" Industry analysis identifying miniaturisation, wireless connectivity, and IoT integration as defining 2025 trends in force measurement technology.[5]\n  - Archive Market Research (2025). \"Integrated Force Controller 2025-2033 Trends: Unveiling Growth.\" Market analysis documenting $2.5 billion market valuation and 12% CAGR projections, with segmentation by application and geography.[2]\n  - 360iResearch (2025). \"Force Control Robot Market Size & Share 2025-2032.\" Strategic analysis emphasising convergence of sensor precision, intelligent control architectures, and AI-driven analytics in force control systems.\n  - Standard Bots (2025). \"Force control in robotics: What it is & how it works?\" Accessible technical overview distinguishing sensing capabilities, adaptive movement, safety integration, and precision applications.[3]\n- Ongoing research directions\n  - Machine learning applications for adaptive force control optimisation\n  - Wireless sensor integration and IoT-enabled real-time monitoring systems\n  - Miniaturised force measurement devices for compact robotic applications\n  - AI-driven analytics for predictive force management and anomaly detection\n  - Human-robot collaborative systems requiring sophisticated force feedback\n\n## UK Context\n\n- British contributions and implementations\n  - UK manufacturing sector increasingly adopting force control in precision engineering, automotive assembly, and medical device manufacturing\n  - Research institutions contributing to control algorithm development and sensor miniaturisation\n- North England innovation hubs\n  - Sheffield: Advanced manufacturing cluster exploring force control in precision tool development and machining operations; established expertise in materials science supporting sensor development\n  - Manchester: Robotics research community contributing to motion planning and force control algorithm refinement; proximity to manufacturing facilities enabling practical implementation testing\n  - Leeds: Manufacturing technology hubs implementing force control in medical device assembly and precision component production; growing collaboration between academic institutions and industrial partners\n  - Newcastle: Emerging interest in force control applications within offshore and subsea robotics development\n\n## Future Directions\n\n- Emerging trends and developments\n  - Mainstream adoption transitioning from specialised deployments to widespread industrial implementation across multiple sectors[4]\n  - Integration of advanced sensor precision with AI-driven analytics creating increasingly autonomous force control systems\n  - Miniaturisation enabling force measurement integration into previously impractical applications and wearable systems[5]\n  - Wireless connectivity standards (Bluetooth 5.0, Wi-Fi 6) facilitating distributed sensor networks and remote monitoring capabilities[5]\n  - Collaborative human-robot environments demanding increasingly sophisticated force feedback and safety mechanisms\n- Anticipated challenges\n  - Geopolitical and regulatory complexity affecting supply chain optimisation and technology deployment strategies[4]\n  - Workforce development requirements for sophisticated force control system implementation and maintenance\n  - Integration complexity when combining force control with existing motion control infrastructure\n  - Standardisation challenges across diverse industrial applications and sensor technologies\n- Research priorities\n  - Cross-sector collaboration advancing force control methodologies and best practices\n  - Data-driven decision-making frameworks for force control optimisation\n  - Agile supply chain practices supporting rapid technology deployment\n  - Continuous learning approaches enabling adaptive system refinement\n  - UK-specific research into force control applications within regional manufacturing specialisms (precision engineering, medical devices, advanced materials)\n\n---\n\n**Note:** This entry reflects the current state of force control technology as of November 2025. The field continues evolving rapidly, particularly regarding sensor miniaturisation, wireless integration, and AI-driven control systems. Regional UK examples are illustrative based on established manufacturing clusters; specific organisational implementations should be verified against current sources.\n\n\n## Metadata\n\n- **Last Updated**: 2025-11-11\n- **Review Status**: Comprehensive editorial review\n- **Verification**: Academic sources verified\n- **Regional Context**: UK/North England where applicable",
  "backlinks": [],
  "wiki_links": [
    "MetaverseDomain"
  ],
  "ontology": {
    "term_id": "RB-0053",
    "preferred_term": "Force Control",
    "alt_terms": [],
    "iri": "http://narrativegoldmine.com/metaverse#rb0053forcecontrol",
    "source_domain": "metaverse",
    "domain": "metaverse",
    "domain_full_name": "",
    "definition": "### Primary Definition",
    "scope_note": null,
    "status": "draft",
    "maturity": "draft",
    "version": null,
    "public_access": true,
    "last_updated": null,
    "authority_score": null,
    "quality_score": null,
    "cross_domain_links": null,
    "owl_class": "mv:rb0053forcecontrol",
    "owl_physicality": "ConceptualEntity",
    "owl_role": "Concept",
    "owl_inferred_class": null,
    "is_subclass_of": [],
    "has_part": [],
    "is_part_of": [],
    "requires": [],
    "depends_on": [],
    "enables": [],
    "relates_to": [],
    "bridges_to": [],
    "bridges_from": [],
    "domain_extensions": {},
    "belongs_to_domain": [
      "MetaverseDomain"
    ],
    "implemented_in_layer": [],
    "source": [],
    "validation": {
      "is_valid": false,
      "errors": [
        "Missing required property: last-updated",
        "Missing required property: is-subclass-of (at least one parent class)",
        "owl:class namespace 'mv' doesn't match source-domain 'metaverse'"
      ]
    }
  }
}