{
  "id": "Forward Kinematics",
  "title": "Forward Kinematics",
  "content": "- ### OntologyBlock\n  id:: rb-0028-forward-kinematics-ontology\n  collapsed:: true\n\t- ontology:: true\n\t- term-id:: RB-0028\n\t- domain-prefix:: RB\n\t- sequence-number:: 0028\n\t- filename-history:: [\"rb-0028-forward-kinematics.md\"]\n\t- preferred-term:: Forward Kinematics\n\t- source-domain:: metaverse\n\t- status:: draft\n    - public-access:: true\n\t- definition:: ### Primary Definition\n**Forward Kinematics** - Computing end-effector pose from joint angles\n\t- maturity:: draft\n\t- owl:class:: mv:rb0028forwardkinematics\n\t- owl:physicality:: ConceptualEntity\n\t- owl:role:: Concept\n\t- belongsToDomain:: [[MetaverseDomain]]\n- ## About rb 0028 forward kinematics\n\t- ### Primary Definition\n**Forward Kinematics** - Computing end-effector pose from joint angles\n\t-\n\t- ### Original Content\n\t  collapsed:: true\n\t\t- ```\n# RB-0028: Forward Kinematics\n\t\t  \n\t\t  ## Metadata\n\t\t  - **Term ID**: RB-0028\n\t\t  - **Term Type**: Core Concept\n\t\t  - **Classification**: Fundamental Concepts\n\t\t  - **Priority**: 1 (Foundational)\n\t\t  - **Authority Score**: 0.95\n\t\t  - **ISO Reference**: ISO 8373:2021\n\t\t  - **Version**: 1.0.0\n\t\t  - **Last Updated**: 2025-10-28\n\t\t  \n\t\t  ## Definition\n\t\t  \n\t\t  ### Primary Definition\n\t\t  **Forward Kinematics** - Computing end-effector pose from joint angles\n\t\t  \n\t\t  ### Standards Context\n\t\t  Defined according to ISO 8373:2021 and related international robotics standards.\n\t\t  \n\t\t  ### Key Characteristics\n\t\t  1. Core property of robotics systems\n\t\t  2. Standardised definition across implementations\n\t\t  3. Measurable and verifiable attributes\n\t\t  4. Essential for safety and performance\n\t\t  5. Industry-wide recognition and adoption\n\t\t  \n\t\t  ## Formal Ontology (OWL Functional Syntax)\n\t\t  \n\t\t  ```clojure\n\t\t  (Declaration (Class :ForwardKinematics))\n\t\t  (SubClassOf :ForwardKinematics :Robot)\n\t\t  \n\t\t  (AnnotationAssertion rdfs:label :ForwardKinematics \"Forward Kinematics\"@en)\n\t\t  (AnnotationAssertion rdfs:comment :ForwardKinematics\n\t\t    \"Forward Kinematics - Foundational robotics concept\"@en)\n\t\t  (AnnotationAssertion :termID :ForwardKinematics \"RB-0028\"^^xsd:string)\n\t\t  \n\t\t  (Declaration (ObjectProperty :relates To))\n\t\t  (ObjectPropertyDomain :relatesTo :ForwardKinematics)\n\t\t  \n\t\t  (Declaration (DataProperty :hasProperty))\n\t\t  (DataPropertyDomain :hasProperty :ForwardKinematics)\n\t\t  (DataPropertyRange :hasProperty xsd:string)\n\t\t  ```\n\t\t  \n\t\t  ## Relationships\n\t\t  \n\t\t  ### Parent Classes\n\t\t  - `Robot`: Primary classification\n\t\t  \n\t\t  ### Related Concepts\n\t\t  - Related robotics concepts and systems\n\t\t  - Cross-references to other ontology terms\n\t\t  - Integration with metaverse ontology\n\t\t  \n\t\t  ## Use Cases\n\t\t  \n\t\t  ### Industrial Applications\n\t\t  1. Manufacturing automation\n\t\t  2. Quality control systems\n\t\t  3. Process optimization\n\t\t  \n\t\t  ### Service Applications\n\t\t  1. Healthcare robotics\n\t\t  2. Logistics and warehousing\n\t\t  3. Consumer robotics\n\t\t  \n\t\t  ### Research Applications\n\t\t  1. Academic research platforms\n\t\t  2. Algorithm development\n\t\t  3. System integration studies\n\t\t  \n\t\t  ## Standards References\n\t\t  \n\t\t  ### Primary Standards\n\t\t  1. **ISO 8373:2021**: Primary reference standard\n\t\t  2. **ISO 8373:2021**: Robotics vocabulary\n\t\t  3. **Related IEEE standards**: Implementation guidelines\n\t\t  \n\t\t  ## Validation Criteria\n\t\t  \n\t\t  ### Conformance Requirements\n\t\t  1. ✓ Meets ISO 8373:2021 requirements\n\t\t  2. ✓ Documented implementation\n\t\t  3. ✓ Verifiable performance metrics\n\t\t  4. ✓ Safety compliance demonstrated\n\t\t  5. ✓ Industry best practices followed\n\t\t  \n\t\t  ## Implementation Notes\n\t\t  \n\t\t  ### Design Considerations\n\t\t  - System integration requirements\n\t\t  - Performance specifications\n\t\t  - Safety considerations\n\t\t  - Maintenance procedures\n\t\t  \n\t\t  ### Common Patterns\n\t\t  ```yaml\n\t\t  implementation:\n\t\t    standards_compliance: true\n\t\t    verification_method: standardised_testing\n\t\t    documentation_level: comprehensive\n\t\t  ```\n\t\t  \n\t\t  ## Cross-References\n\t\t  \n\t\t  ### Metaverse Ontology Integration\n\t\t  - Virtual representation systems\n\t\t  - Digital twin integration\n\t\t  - Simulation environments\n\t\t  \n\t\t  ### Domain Ontologies\n\t\t  - Manufacturing systems\n\t\t  - Control systems\n\t\t  - Safety systems\n\t\t  \n\t\t  ## Future Directions\n\t\t  \n\t\t  ### Emerging Trends\n\t\t  1. AI and machine learning integration\n\t\t  2. Advanced sensing capabilities\n\t\t  3. Improved safety systems\n\t\t  4. Enhanced human-robot collaboration\n\t\t  5. Standardisation advancements\n\t\t  \n\t\t  ---\n\t\t  \n\t\t  **Version History**\n\t\t  - 1.0.0 (2025-10-28): Initial foundational definition\n\t\t  \n\t\t  **Contributors**: Robotics Ontology Working Group\n\t\t  **License**: CC BY 4.0\n\t\t  **Namespace**: `https://metaverse-ontology.org/robotics/RB-0028`\n\t\t  \n\t\t  ```\n\n\n## Academic Context\n\n- Forward kinematics (FK) is the mathematical process of determining the position and orientation of a robot's end-effector based on known joint parameters and link dimensions.\n  - It relies on kinematic equations that model the robot as a series of rigid transformations alternating between joint movements and link lengths.\n  - The foundational theory dates back to classical robotics and mechanical system kinematics, formalised in works such as Russell, Shen, and Sodhi (2018).\n- FK is fundamental in robotics, computer animation, and simulation, providing the basis for calculating tool paths and spatial positioning without considering forces or dynamics.\n\n## Current Landscape (2025)\n\n- FK is widely adopted in industrial robotics, virtual reality, and simulation platforms to compute end-effector poses from joint inputs.\n  - Notable implementations include robotic arms in manufacturing, Stewart platforms in motion simulators, and VR headset tracking systems.\n- In the UK, robotics firms and research institutions integrate FK algorithms into automation and digital twin technologies.\n  - North England hubs such as Manchester and Leeds are active in robotics research, focusing on precision manufacturing and autonomous systems.\n- Technical capabilities:\n  - FK algorithms efficiently compute forward transformations using Denavit-Hartenberg parameters or equivalent matrix representations.\n  - Limitations arise in complex, redundant manipulators where FK is straightforward but inverse kinematics (IK) is more challenging.\n- Standards and frameworks:\n  - FK computations adhere to established robotics standards such as ISO 8373 and are implemented in software libraries like ROS (Robot Operating System).\n\n## Research & Literature\n\n- Key academic references:\n  - Russell, K., Shen, Q., & Sodhi, R. S. (2018). *Kinematics and Dynamics of Mechanical Systems Implementation in MATLAB® and Simmechanics®*. Taylor & Francis.  \n  - Craig, J. J. (2005). *Introduction to Robotics: Mechanics and Control*. Pearson.  \n  - Siciliano, B., Sciavicco, L., Villani, L., & Oriolo, G. (2010). *Robotics: Modelling, Planning and Control*. Springer.  \n- Ongoing research explores:\n  - Enhancements in FK for soft robotics and continuum manipulators.\n  - Integration of FK with machine learning for adaptive control.\n  - Real-time FK computation optimisations for high-DOF systems.\n\n## UK Context\n\n- The UK contributes significantly to robotics kinematics research, with universities such as the University of Manchester and University of Leeds leading in robotic manipulation and control.\n- North England innovation hubs:\n  - Manchester’s Robotics and Autonomous Systems group focuses on industrial automation incorporating FK algorithms.\n  - Leeds hosts research on human-robot interaction where FK underpins motion prediction.\n  - Newcastle and Sheffield contribute through collaborative projects in manufacturing robotics and digital twins.\n- Regional case studies include FK-based robotic arms deployed in automotive assembly lines around Sheffield and VR training simulators developed in Newcastle.\n\n## Future Directions\n\n- Emerging trends:\n  - FK integration with AI for predictive and adaptive robotic control.\n  - Expansion of FK models to accommodate flexible and soft robotic structures.\n  - Enhanced simulation fidelity in VR and digital twins using FK.\n- Anticipated challenges:\n  - Managing computational complexity in high-degree-of-freedom systems.\n  - Bridging FK with dynamic and force-based models for comprehensive robot control.\n- Research priorities:\n  - Developing standardised FK frameworks for emerging robot architectures.\n  - Improving FK accuracy in uncertain or noisy sensor environments.\n  - Leveraging UK regional expertise to foster industry-academia collaboration.\n\n## References\n\n1. Russell, K., Shen, Q., & Sodhi, R. S. (2018). *Kinematics and Dynamics of Mechanical Systems Implementation in MATLAB® and Simmechanics®*. Taylor & Francis.  \n2. Craig, J. J. (2005). *Introduction to Robotics: Mechanics and Control*. Pearson Education.  \n3. Siciliano, B., Sciavicco, L., Villani, L., & Oriolo, G. (2010). *Robotics: Modelling, Planning and Control*. Springer.  \n4. Wikipedia contributors. (2025). Forward kinematics. In *Wikipedia, The Free Encyclopedia*. Retrieved November 11, 2025, from https://en.wikipedia.org/wiki/Forward_kinematics  \n5. Iris Dynamics. (2025). Forward and Inverse Kinematics: Explained. Retrieved November 11, 2025, from https://irisdynamics.com/articles/forward-and-inverse-kinematics  \n\n*If robots had a sense of humour, they'd probably say FK is just their way of knowing where their hands are — a bit like us trying to find our glasses while wearing them.*\n\n\n## Metadata\n\n- **Last Updated**: 2025-11-11\n- **Review Status**: Comprehensive editorial review\n- **Verification**: Academic sources verified\n- **Regional Context**: UK/North England where applicable",
  "backlinks": [],
  "wiki_links": [
    "MetaverseDomain"
  ],
  "ontology": {
    "term_id": "RB-0028",
    "preferred_term": "Forward Kinematics",
    "alt_terms": [],
    "iri": "http://narrativegoldmine.com/metaverse#rb0028forwardkinematics",
    "source_domain": "metaverse",
    "domain": "metaverse",
    "domain_full_name": "",
    "definition": "### Primary Definition",
    "scope_note": null,
    "status": "draft",
    "maturity": "draft",
    "version": null,
    "public_access": true,
    "last_updated": null,
    "authority_score": null,
    "quality_score": null,
    "cross_domain_links": null,
    "owl_class": "mv:rb0028forwardkinematics",
    "owl_physicality": "ConceptualEntity",
    "owl_role": "Concept",
    "owl_inferred_class": null,
    "is_subclass_of": [],
    "has_part": [],
    "is_part_of": [],
    "requires": [],
    "depends_on": [],
    "enables": [],
    "relates_to": [],
    "bridges_to": [],
    "bridges_from": [],
    "domain_extensions": {},
    "belongs_to_domain": [
      "MetaverseDomain"
    ],
    "implemented_in_layer": [],
    "source": [],
    "validation": {
      "is_valid": false,
      "errors": [
        "Missing required property: last-updated",
        "Missing required property: is-subclass-of (at least one parent class)",
        "owl:class namespace 'mv' doesn't match source-domain 'metaverse'"
      ]
    }
  }
}