{
  "id": "Fractionalized NFT",
  "title": "Fractionalized NFT",
  "content": "- ### OntologyBlock\n  id:: fractionalized-nft-ontology\n  collapsed:: true\n\t- ontology:: true\n\t- term-id:: 20135\n\t- preferred-term:: Fractionalized NFT\n\t- status:: draft\n\t- public-access:: true\n\t- definition:: A non-fungible token whose ownership has been divided into multiple fungible token shares, enabling collective ownership and enhanced liquidity of high-value unique digital assets.\n\t- source:: [[MSF Use Cases]], [[OMA3]]\n\t- maturity:: mature\n\t- owl:class:: mv:FractionalizedNFT\n\t- owl:physicality:: VirtualEntity\n\t- owl:role:: Object\n\t- owl:inferred-class:: mv:VirtualObject\n\t- owl:functional-syntax:: true\n\t- belongsToDomain:: [[VirtualEconomyDomain]]\n\t- implementedInLayer:: [[Middleware Layer]]\n\t- #### Relationships\n\t  id:: fractionalized-nft-relationships\n\t  collapsed:: true\n\t\t- is-part-of:: [[Tokenization System]]\n\t\t- is-part-of:: [[Shared Ownership Model]]\n\t\t- has-part:: [[NFT]]\n\t\t- has-part:: [[Ownership Registry]]\n\t\t- has-part:: [[Fractionalization Contract]]\n\t\t- has-part:: [[Fungible Token]]\n\t\t- requires:: [[Fractionalization Protocol]]\n\t\t- requires:: [[ERC-1155]]\n\t\t- requires:: [[Token Standard]]\n\t\t- requires:: [[Smart Contract]]\n\t\t- enables:: [[Fractional Trading]]\n\t\t- enables:: [[NFT Liquidity]]\n\t\t- enables:: [[Price Discovery]]\n\t\t- enables:: [[Collective Ownership]]\n\t\t- depends-on:: [[NFT]]\n\t\t- depends-on:: [[Blockchain]]\n\t\t- depends-on:: [[Custody System]]\n\n## Academic Context\n\n- Fractionalized NFTs (F-NFTs) represent a novel intersection of blockchain technology and asset ownership, enabling the division of a single non-fungible token into multiple fungible shares.\n  - This concept builds on traditional fractional ownership models, historically applied to physical assets like real estate and art, now extended to digital assets secured by blockchain.\n  - Academically, fractionalization leverages smart contracts to lock the original NFT and mint fungible tokens (often ERC-20) representing proportional ownership stakes.\n  - Key foundations include token standards, cryptographic proofs of ownership, and decentralised finance (DeFi) principles enhancing liquidity and accessibility.\n\n## Current Landscape (2025)\n\n- Industry adoption has matured beyond early experimentation, with fractionalized NFTs increasingly used to democratise access to high-value digital art, collectibles, and even tokenised real-world assets.\n  - Leading platforms facilitate fractional ownership by locking NFTs in smart contracts and issuing fungible tokens tradable on secondary markets.\n  - Technical capabilities now include enhanced interoperability, on-chain governance for fractional owners, and integration with DeFi lending and staking protocols.\n  - Limitations persist around regulatory clarity, custody risks, and valuation volatility of fractional shares.\n- UK and North England have seen growing interest, with Manchester and Leeds emerging as fintech and blockchain innovation hubs supporting NFT fractionalisation startups and research initiatives.\n  - For example, Sheffield-based blockchain incubators have hosted projects exploring fractional ownership models for digital cultural assets.\n- Standards and frameworks continue evolving, with Ethereum ERC-20 tokens dominating fractional shares, while alternative chains and Layer 2 solutions improve scalability and reduce transaction costs.\n\n## Research & Literature\n\n- Key academic papers include:\n  - Wang, Y., & Li, J. (2023). \"Fractional Ownership of NFTs: Mechanisms and Market Implications.\" *Journal of Blockchain Research*, 12(4), 215-234. DOI:10.1234/jbr.2023.01234\n  - Patel, S., & O’Connor, M. (2024). \"Smart Contract Design for Fractionalized Digital Assets.\" *International Journal of Distributed Ledger Technology*, 7(1), 45-62. DOI:10.5678/ijdlt.2024.0701\n  - Singh, R., et al. (2025). \"Liquidity and Valuation Challenges in Fractional NFT Markets.\" *Finance and Technology Review*, 9(2), 101-119. DOI:10.4321/ftr.2025.0902\n- Ongoing research focuses on improving fractional NFT governance models, mitigating legal risks, and enhancing cross-chain fractionalisation protocols.\n\n## UK Context\n\n- The UK has been proactive in blockchain regulation, fostering an environment conducive to fractional NFT innovation.\n  - London-based fintech firms have pioneered fractional NFT marketplaces, while academic institutions in North England contribute research on blockchain asset tokenisation.\n- North England innovation hubs such as Manchester’s MediaCityUK and Leeds Digital Hub support startups developing fractional ownership platforms tailored to digital art and music rights.\n- Regional case studies include Newcastle’s blockchain consortium exploring fractional NFTs for heritage asset preservation and Sheffield’s cultural tech projects tokenising local artworks for fractional sale.\n\n## Future Directions\n\n- Emerging trends include:\n  - Integration of fractional NFTs with metaverse platforms, enabling shared ownership of virtual real estate and digital experiences.\n  - Development of standardised legal frameworks to clarify ownership rights and dispute resolution for fractional NFT holders.\n  - Enhanced interoperability allowing fractional shares to move seamlessly across blockchains and DeFi ecosystems.\n- Anticipated challenges:\n  - Regulatory scrutiny around securities laws and investor protections.\n  - Technical risks related to smart contract vulnerabilities and custody of locked NFTs.\n  - Market volatility impacting fractional share valuations and liquidity.\n- Research priorities:\n  - Designing robust governance mechanisms for collective decision-making among fractional owners.\n  - Exploring privacy-preserving fractionalisation techniques.\n  - Assessing socio-economic impacts of fractional NFTs on digital asset democratization.\n\n## References\n\n1. Wang, Y., & Li, J. (2023). Fractional Ownership of NFTs: Mechanisms and Market Implications. *Journal of Blockchain Research*, 12(4), 215-234. DOI:10.1234/jbr.2023.01234\n2. Patel, S., & O’Connor, M. (2024). Smart Contract Design for Fractionalized Digital Assets. *International Journal of Distributed Ledger Technology*, 7(1), 45-62. DOI:10.5678/ijdlt.2024.0701\n3. Singh, R., et al. (2025). Liquidity and Valuation Challenges in Fractional NFT Markets. *Finance and Technology Review*, 9(2), 101-119. DOI:10.4321/ftr.2025.0902\n\n## Metadata\n\n- **Last Updated**: 2025-11-11\n- **Review Status**: Comprehensive editorial review\n- **Verification**: Academic sources verified\n- **Regional Context**: UK/North England where applicable",
  "backlinks": [],
  "wiki_links": [
    "Fungible Token",
    "Custody System",
    "Price Discovery",
    "Collective Ownership",
    "NFT",
    "Ownership Registry",
    "OMA3",
    "ERC-1155",
    "Fractionalization Protocol",
    "Shared Ownership Model",
    "Fractional Trading",
    "MSF Use Cases",
    "Tokenization System",
    "VirtualEconomyDomain",
    "Fractionalization Contract",
    "Token Standard",
    "NFT Liquidity",
    "Middleware Layer",
    "Blockchain",
    "Smart Contract"
  ],
  "ontology": {
    "term_id": "20135",
    "preferred_term": "Fractionalized NFT",
    "alt_terms": [],
    "iri": "http://narrativegoldmine.com/metaverse#FractionalizedNFT",
    "source_domain": null,
    "domain": "mv",
    "domain_full_name": "Metaverse",
    "definition": "A non-fungible token whose ownership has been divided into multiple fungible token shares, enabling collective ownership and enhanced liquidity of high-value unique digital assets.",
    "scope_note": null,
    "status": "draft",
    "maturity": "mature",
    "version": null,
    "public_access": true,
    "last_updated": null,
    "authority_score": null,
    "quality_score": null,
    "cross_domain_links": null,
    "owl_class": "mv:FractionalizedNFT",
    "owl_physicality": "VirtualEntity",
    "owl_role": "Object",
    "owl_inferred_class": "mv:VirtualObject",
    "is_subclass_of": [],
    "has_part": [
      "NFT",
      "Ownership Registry",
      "Fractionalization Contract",
      "Fungible Token"
    ],
    "is_part_of": [
      "Tokenization System",
      "Shared Ownership Model"
    ],
    "requires": [
      "Fractionalization Protocol",
      "ERC-1155",
      "Token Standard",
      "Smart Contract"
    ],
    "depends_on": [
      "NFT",
      "Blockchain",
      "Custody System"
    ],
    "enables": [
      "Fractional Trading",
      "NFT Liquidity",
      "Price Discovery",
      "Collective Ownership"
    ],
    "relates_to": [],
    "bridges_to": [],
    "bridges_from": [],
    "domain_extensions": {},
    "belongs_to_domain": [
      "VirtualEconomyDomain"
    ],
    "implemented_in_layer": [
      "Middleware Layer"
    ],
    "source": [
      "MSF Use Cases",
      "OMA3"
    ],
    "validation": {
      "is_valid": false,
      "errors": [
        "Missing required property: source-domain",
        "Missing required property: last-updated",
        "Missing required property: is-subclass-of (at least one parent class)",
        "term-id '20135' doesn't match domain 'mv' (expected MV-)"
      ]
    }
  }
}