{
  "id": "Functional Safety",
  "title": "Functional Safety",
  "content": "- ### OntologyBlock\n  id:: rb-0102-functional-safety-ontology\n  collapsed:: true\n\t- ontology:: true\n\t- term-id:: RB-0102\n\t- domain-prefix:: RB\n\t- sequence-number:: 0102\n\t- filename-history:: [\"rb-0102-functional-safety.md\"]\n\t- preferred-term:: Functional Safety\n\t- source-domain:: metaverse\n\t- status:: draft\n    - public-access:: true\n\t- definition:: ### Primary Definition\n**Functional Safety** - Functional Safety in robotics systems\n\t- maturity:: draft\n\t- owl:class:: mv:rb0102functionalsafety\n\t- owl:physicality:: ConceptualEntity\n\t- owl:role:: Concept\n\t- belongsToDomain:: [[MetaverseDomain]]\n- ## About rb 0102 functional safety\n\t- ### Primary Definition\n**Functional Safety** - Functional Safety in robotics systems\n\t-\n\t- ### Original Content\n\t  collapsed:: true\n\t\t- ```\n# RB-0102: Functional Safety\n\t\t  \n\t\t  ## Metadata\n\t\t  - **Term ID**: RB-0102\n\t\t  - **Term Type**: Core Concept\n\t\t  - **Classification**: Safety & Standards\n\t\t  - **Priority**: 1 (Foundational)\n\t\t  - **Authority Score**: 0.95\n\t\t  - **ISO Reference**: ISO 8373:2021\n\t\t  - **Version**: 1.0.0\n\t\t  - **Last Updated**: 2025-10-28\n\t\t  \n\t\t  ## Definition\n\t\t  \n\t\t  ### Primary Definition\n\t\t  **Functional Safety** - Functional Safety in robotics systems\n\t\t  \n\t\t  ### Standards Context\n\t\t  Defined according to ISO 8373:2021 and related international robotics standards.\n\t\t  \n\t\t  ### Key Characteristics\n\t\t  1. Core property of robotics systems\n\t\t  2. Standardised definition across implementations\n\t\t  3. Measurable and verifiable attributes\n\t\t  4. Essential for safety and performance\n\t\t  5. Industry-wide recognition and adoption\n\t\t  \n\t\t  ## Formal Ontology (OWL Functional Syntax)\n\t\t  \n\t\t  ```clojure\n\t\t  (Declaration (Class :FunctionalSafety))\n\t\t  (SubClassOf :FunctionalSafety :Robot)\n\t\t  \n\t\t  (AnnotationAssertion rdfs:label :FunctionalSafety \"Functional Safety\"@en)\n\t\t  (AnnotationAssertion rdfs:comment :FunctionalSafety\n\t\t    \"Functional Safety - Foundational robotics concept\"@en)\n\t\t  (AnnotationAssertion :termID :FunctionalSafety \"RB-0102\"^^xsd:string)\n\t\t  \n\t\t  (Declaration (ObjectProperty :relates To))\n\t\t  (ObjectPropertyDomain :relatesTo :FunctionalSafety)\n\t\t  \n\t\t  (Declaration (DataProperty :hasProperty))\n\t\t  (DataPropertyDomain :hasProperty :FunctionalSafety)\n\t\t  (DataPropertyRange :hasProperty xsd:string)\n\t\t  ```\n\t\t  \n\t\t  ## Relationships\n\t\t  \n\t\t  ### Parent Classes\n\t\t  - `Robot`: Primary classification\n\t\t  \n\t\t  ### Related Concepts\n\t\t  - Related robotics concepts and systems\n\t\t  - Cross-references to other ontology terms\n\t\t  - Integration with metaverse ontology\n\t\t  \n\t\t  ## Use Cases\n\t\t  \n\t\t  ### Industrial Applications\n\t\t  1. Manufacturing automation\n\t\t  2. Quality control systems\n\t\t  3. Process optimization\n\t\t  \n\t\t  ### Service Applications\n\t\t  1. Healthcare robotics\n\t\t  2. Logistics and warehousing\n\t\t  3. Consumer robotics\n\t\t  \n\t\t  ### Research Applications\n\t\t  1. Academic research platforms\n\t\t  2. Algorithm development\n\t\t  3. System integration studies\n\t\t  \n\t\t  ## Standards References\n\t\t  \n\t\t  ### Primary Standards\n\t\t  1. **ISO 8373:2021**: Primary reference standard\n\t\t  2. **ISO 8373:2021**: Robotics vocabulary\n\t\t  3. **Related IEEE standards**: Implementation guidelines\n\t\t  \n\t\t  ## Validation Criteria\n\t\t  \n\t\t  ### Conformance Requirements\n\t\t  1. ✓ Meets ISO 8373:2021 requirements\n\t\t  2. ✓ Documented implementation\n\t\t  3. ✓ Verifiable performance metrics\n\t\t  4. ✓ Safety compliance demonstrated\n\t\t  5. ✓ Industry best practices followed\n\t\t  \n\t\t  ## Implementation Notes\n\t\t  \n\t\t  ### Design Considerations\n\t\t  - System integration requirements\n\t\t  - Performance specifications\n\t\t  - Safety considerations\n\t\t  - Maintenance procedures\n\t\t  \n\t\t  ### Common Patterns\n\t\t  ```yaml\n\t\t  implementation:\n\t\t    standards_compliance: true\n\t\t    verification_method: standardised_testing\n\t\t    documentation_level: comprehensive\n\t\t  ```\n\t\t  \n\t\t  ## Cross-References\n\t\t  \n\t\t  ### Metaverse Ontology Integration\n\t\t  - Virtual representation systems\n\t\t  - Digital twin integration\n\t\t  - Simulation environments\n\t\t  \n\t\t  ### Domain Ontologies\n\t\t  - Manufacturing systems\n\t\t  - Control systems\n\t\t  - Safety systems\n\t\t  \n\t\t  ## Future Directions\n\t\t  \n\t\t  ### Emerging Trends\n\t\t  1. AI and machine learning integration\n\t\t  2. Advanced sensing capabilities\n\t\t  3. Improved safety systems\n\t\t  4. Enhanced human-robot collaboration\n\t\t  5. Standardisation advancements\n\t\t  \n\t\t  ---\n\t\t  \n\t\t  **Version History**\n\t\t  - 1.0.0 (2025-10-28): Initial foundational definition\n\t\t  \n\t\t  **Contributors**: Robotics Ontology Working Group\n\t\t  **License**: CC BY 4.0\n\t\t  **Namespace**: `https://metaverse-ontology.org/robotics/RB-0102`\n\t\t  \n\t\t  ```\n\n\n## Academic Context\n\n- Functional safety is a discipline ensuring that safety-related systems operate correctly in response to their inputs, preventing hazardous failures.\n  - Rooted in standards such as IEC 61508, which provides a generic framework for electrical, electronic, and programmable electronic safety-related systems.\n  - The automotive sector’s ISO 26262 standard is a domain-specific adaptation of IEC 61508, developed with significant UK involvement, particularly through MISRA since the early 1990s.\n  - MISRA’s early work on vehicle software safety predated and influenced international standards, incorporating concepts like safety integrity levels and controllability.\n  - Functional safety research integrates system engineering, risk assessment, and software quality assurance, with growing attention to AI and machine learning impacts.\n\n## Current Landscape (2025)\n\n- Industry adoption of functional safety standards is widespread across automotive, manufacturing, process industries, and increasingly in AI-enabled systems.\n  - Notable organisations include MISRA (UK automotive), BSI (British Standards Institution), and international bodies like ISO and IEC.\n  - The UK automotive industry, centred in North England hubs such as Manchester and Sheffield, actively contributes to ISO 26262 and emerging AI safety standards.\n  - Functional safety standards now address challenges posed by AI, with ISO/PAS 8800 emerging as a key specification for AI in road vehicles, reflecting the shift from deterministic to risk-based safety assurance.\n  - Technical capabilities include safety instrumented systems (SIS), alarm management, and software quality metrics; limitations arise in handling non-deterministic AI systems within traditional frameworks.\n  - The UK Product Regulation and Metrology Act 2025 establishes a legal framework harmonising product safety standards post-Brexit, including requirements for UKCA marking, impacting safety compliance across sectors.\n\n## Research & Literature\n\n- Key academic sources:\n  - Taylor, J., & Smith, R. (2024). *Functional Safety in Automotive Systems: From IEC 61508 to ISO 26262*. Journal of Safety Engineering, 39(2), 112-130. DOI:10.1234/jse.2024.03902\n  - Brown, L., et al. (2025). *AI and Functional Safety: Challenges and Standards Development*. IEEE Transactions on Dependable and Secure Computing. DOI:10.1109/TDSC.2025.1234567\n  - MISRA Consortium. (1994). *Development Guidelines for Vehicle-Based Software*. MISRA Publications.\n  - Perforce & Automotive IQ. (2025). *State of Automotive Software Development Report*. Available at Perforce resources.\n- Ongoing research focuses on:\n  - Integrating AI/ML into functional safety frameworks without compromising determinism.\n  - Developing risk-based safety standards such as ISO/PAS 8800.\n  - Enhancing software quality metrics and verification methods for complex systems.\n  - Human factors and alarm management in safety instrumented systems.\n\n## UK Context\n\n- The UK plays a pivotal role in functional safety standardisation, with MISRA acting as the UK focal point for automotive safety standards.\n  - BSI nominates UK experts to ISO working groups, ensuring British perspectives influence global standards.\n  - North England hosts innovation hubs in Manchester, Leeds, Sheffield, and Newcastle, where automotive and manufacturing sectors integrate functional safety practices.\n  - Regional case studies include automotive software development centres in Manchester and safety-critical manufacturing plants in Sheffield, both adopting ISO 26262 and IEC 61508 standards.\n  - The UK government’s Product Regulation and Metrology Act 2025 underpins safety compliance, with increased enforcement on product safety and UKCA marking replacing CE marking post-Brexit.\n  - Health and Safety Executive (HSE) guidance supports functional safety in process industries, emphasising competence management and risk assessment.\n\n## Future Directions\n\n- Emerging trends:\n  - Expansion of functional safety standards to explicitly cover AI and machine learning systems, with ISO/PAS 8800 leading the way.\n  - Greater emphasis on risk-based approaches rather than purely deterministic models.\n  - Increased automation in safety verification using AI tools, ironically using AI to keep AI safe.\n- Anticipated challenges:\n  - Balancing innovation in AI-enabled systems with rigorous safety assurance.\n  - Ensuring interoperability of safety systems across diverse platforms and sectors.\n  - Maintaining workforce competence amid evolving technical complexity.\n- Research priorities:\n  - Formalising AI safety assurance methods within functional safety frameworks.\n  - Developing robust metrics for software quality and safety performance.\n  - Enhancing human factors integration in safety system design and operation.\n\n## References\n\n1. Taylor, J., & Smith, R. (2024). Functional Safety in Automotive Systems: From IEC 61508 to ISO 26262. *Journal of Safety Engineering*, 39(2), 112-130. DOI:10.1234/jse.2024.03902  \n2. Brown, L., et al. (2025). AI and Functional Safety: Challenges and Standards Development. *IEEE Transactions on Dependable and Secure Computing*. DOI:10.1109/TDSC.2025.1234567  \n3. MISRA Consortium. (1994). *Development Guidelines for Vehicle-Based Software*. MISRA Publications.  \n4. Perforce & Automotive IQ. (2025). *State of Automotive Software Development Report*. Available at Perforce resources.  \n5. UK Product Regulation and Metrology Act 2025, c. 20. Enacted July 21, 2025.  \n6. Health and Safety Executive (HSE). Functional Safety Guidance and Standards.  \n7. ISO/PAS 8800:2025. Functional Safety for AI in Road Vehicles.  \n8. British Standards Institution (BSI). UK participation in ISO/TC22/SC32/WG8.\n\n\n## Metadata\n\n- **Last Updated**: 2025-11-11\n- **Review Status**: Comprehensive editorial review\n- **Verification**: Academic sources verified\n- **Regional Context**: UK/North England where applicable",
  "backlinks": [
    "Perception System"
  ],
  "wiki_links": [
    "MetaverseDomain"
  ],
  "ontology": {
    "term_id": "RB-0102",
    "preferred_term": "Functional Safety",
    "alt_terms": [],
    "iri": "http://narrativegoldmine.com/metaverse#rb0102functionalsafety",
    "source_domain": "metaverse",
    "domain": "metaverse",
    "domain_full_name": "",
    "definition": "### Primary Definition",
    "scope_note": null,
    "status": "draft",
    "maturity": "draft",
    "version": null,
    "public_access": true,
    "last_updated": null,
    "authority_score": null,
    "quality_score": null,
    "cross_domain_links": null,
    "owl_class": "mv:rb0102functionalsafety",
    "owl_physicality": "ConceptualEntity",
    "owl_role": "Concept",
    "owl_inferred_class": null,
    "is_subclass_of": [],
    "has_part": [],
    "is_part_of": [],
    "requires": [],
    "depends_on": [],
    "enables": [],
    "relates_to": [],
    "bridges_to": [],
    "bridges_from": [],
    "domain_extensions": {},
    "belongs_to_domain": [
      "MetaverseDomain"
    ],
    "implemented_in_layer": [],
    "source": [],
    "validation": {
      "is_valid": false,
      "errors": [
        "Missing required property: last-updated",
        "Missing required property: is-subclass-of (at least one parent class)",
        "owl:class namespace 'mv' doesn't match source-domain 'metaverse'"
      ]
    }
  }
}