{
  "id": "Gas Limit",
  "title": "Gas Limit",
  "content": "- ### OntologyBlock\n  id:: gas-limit-ontology\n  collapsed:: true\n\t- ontology:: true\n\t- term-id:: BC-0107\n\t- preferred-term:: Gas Limit\n\t- status:: complete\n\t- public-access:: true\n\t- definition:: The maximum amount of computational work (measured in gas units) that a user is willing to allocate for transaction execution on Ethereum and EVM-compatible blockchains.\n\t- source:: Chimera Prime Research, Ethereum Documentation\n\t- maturity:: mature\n\t- owl:class:: bc:GasLimit\n\t- owl:physicality:: ConceptualEntity\n\t- owl:role:: Concept\n\t- belongsToDomain:: [[Blockchain]]\n\t- #### Relationships\n\t  id:: gas-limit-relationships\n\t  collapsed:: true\n\t\t- is-subclass-of:: [[Transaction Parameter]]\n\t\t- is-subclass-of:: [[Resource Control]]\n\t\t- related-to:: [[Transaction Fee]]\n\t\t- related-to:: [[Gas Price]]\n\t\t- related-to:: [[Base Fee]]\n\n## Metadata\n\n- **Last Updated**: 2025-11-16\n- **Review Status**: Automated remediation with 2025 context\n- **Verification**: Academic sources verified\n- **Regional Context**: UK/North England where applicable",
  "backlinks": [],
  "wiki_links": [
    "Gas Price",
    "Base Fee",
    "Resource Control",
    "Transaction Parameter",
    "Transaction Fee",
    "Blockchain"
  ],
  "ontology": {
    "term_id": "BC-0107",
    "preferred_term": "Gas Limit",
    "alt_terms": [],
    "iri": "http://narrativegoldmine.com/blockchain#GasLimit",
    "source_domain": null,
    "domain": "bc",
    "domain_full_name": "Blockchain",
    "definition": "The maximum amount of computational work (measured in gas units) that a user is willing to allocate for transaction execution on Ethereum and EVM-compatible blockchains.",
    "scope_note": null,
    "status": "complete",
    "maturity": "mature",
    "version": null,
    "public_access": true,
    "last_updated": null,
    "authority_score": null,
    "quality_score": null,
    "cross_domain_links": null,
    "owl_class": "bc:GasLimit",
    "owl_physicality": "ConceptualEntity",
    "owl_role": "Concept",
    "owl_inferred_class": null,
    "is_subclass_of": [
      "Transaction Parameter",
      "Resource Control"
    ],
    "has_part": [],
    "is_part_of": [],
    "requires": [],
    "depends_on": [],
    "enables": [],
    "relates_to": [],
    "bridges_to": [],
    "bridges_from": [],
    "domain_extensions": {},
    "belongs_to_domain": [
      "Blockchain"
    ],
    "implemented_in_layer": [],
    "source": [
      "Chimera Prime Research, Ethereum Documentation"
    ],
    "other_relationships": {
      "related-to": [
        "Transaction Fee",
        "Gas Price",
        "Base Fee"
      ]
    },
    "validation": {
      "is_valid": false,
      "errors": [
        "Missing required property: source-domain",
        "Missing required property: last-updated"
      ]
    }
  }
}