{
  "id": "Gossip Protocol",
  "title": "Gossip Protocol",
  "content": "- ### OntologyBlock\n  id:: gossip-protocol-ontology\n  collapsed:: true\n\t- ontology:: true\n\t- term-id:: BC-0088\n\t- preferred-term:: Gossip Protocol\n\t- status:: complete\n\t- public-access:: true\n\t- definition:: Information propagation method within blockchain systems, providing essential functionality for distributed ledger technology operations and properties.\n\t- source:: [[ISO/IEC 23257:2021]], [[IEEE 2418.1]], [[NIST NISTIR]]\n\t- maturity:: mature\n\t- owl:class:: bc:GossipProtocol\n\t- owl:physicality:: VirtualEntity\n\t- owl:role:: Object\n\t- owl:inferred-class:: bc:VirtualObject\n\t- belongsToDomain:: [[CryptographicDomain]]\n\t- #### Relationships\n\t  id:: gossip-protocol-relationships\n\t  collapsed:: true\n\t\t- is-subclass-of:: [[Blockchain Network]]\n\t\t- bridges-to:: [[Networkcomponent]]\n\t\t- bridges-to:: [[BlockchainEntity]]\n\n## Gossip Protocol\n\nGossip Protocol refers to decentralized peer-to-peer information dissemination method within blockchain systems, providing essential functionality for distributed ledger technology operations through probabilistic message propagation across network nodes.\n\nGossip protocols, also termed epidemic protocols, enable scalable and fault-tolerant data propagation in distributed systems without centralized coordination. In blockchain networks, nodes share transactions, blocks, and state updates by randomly selecting peers and exchanging information, ensuring eventual consistency across the network. Bitcoin employs gossiping for transaction and block propagation, whilst Ethereum uses eth/64+ wire protocols incorporating gossip mechanisms. The probabilistic nature allows networks to achieve logarithmic message complexity relative to network size, making gossip particularly suitable for large-scale decentralized systems.\n\nIndustry adoption spans major blockchain platforms including Bitcoin, Ethereum, and permissioned networks like Hyperledger Fabric which implements gossip data dissemination protocols for ledger synchronization. Ethereum 2.0's Beacon Chain utilizes gossipsubâ€”a libp2p pubsub protocol optimizing message routing through topic-based mesh networks. Solana employs Turbine, a block propagation protocol inspired by gossip principles, achieving sub-second block times through optimized data sharding and forwarding.\n\nTechnical capabilities include resilience to node failures (Byzantine fault tolerance), partition tolerance, and natural load balancing through randomized peer selection. Limitations involve potential message redundancy consuming bandwidth, variable propagation delays affecting consensus latency, and vulnerability to eclipse attacks where malicious nodes isolate victims. Gossip protocols must balance fanout (peer count per gossip round), message frequency, and TTL (time-to-live) to optimize throughput whilst minimizing overhead.\n\nUK blockchain research, including work at Imperial College London and University of Edinburgh, contributes to gossip protocol optimization for permissioned enterprise deployments. North England innovation hubs in Manchester and Leeds explore gossip-based supply chain transparency systems, leveraging gossip protocols for real-time inventory tracking across distributed stakeholders.\n\nStandards include libp2p specifications (used by Ethereum and IPFS), W3C Decentralized Identifiers incorporating gossip-based synchronization, and Bitcoin Improvement Proposals governing peer discovery and message relay rules.\n\n## Technical Details\n\n- **Id**: gossip-protocol-standards\n- **Collapsed**: true\n- **Domain Prefix**: BC\n- **Sequence Number**: 0088\n- **Filename History**: [\"BC-0088-gossip-protocol.md\"]\n- **Public Access**: true\n- **Source Domain**: blockchain\n- **Status**: complete\n- **Last Updated**: 2025-10-28\n- **Maturity**: mature\n- **Source**: [[ISO/IEC 23257:2021]], [[IEEE 2418.1]], [[NIST NISTIR]]\n- **Authority Score**: 0.95\n- **Owl:Class**: bc:GossipProtocol\n- **Owl:Physicality**: VirtualEntity\n- **Owl:Role**: Object\n- **Owl:Inferred Class**: bc:VirtualObject\n- **Belongstodomain**: [[CryptographicDomain]]\n- **Implementedinlayer**: [[SecurityLayer]]\n- **Is Subclass Of**: [[Blockchain Entity]], [[NetworkComponent]]",
  "backlinks": [],
  "wiki_links": [
    "Blockchain Entity",
    "NetworkComponent",
    "Blockchain Network",
    "BlockchainEntity",
    "ISO/IEC 23257:2021",
    "IEEE 2418.1",
    "SecurityLayer",
    "CryptographicDomain",
    "Networkcomponent",
    "NIST NISTIR"
  ],
  "ontology": {
    "term_id": "BC-0088",
    "preferred_term": "Gossip Protocol",
    "alt_terms": [],
    "iri": "http://narrativegoldmine.com/blockchain#GossipProtocol",
    "source_domain": "blockchain",
    "domain": "blockchain",
    "domain_full_name": "",
    "definition": "Information propagation method within blockchain systems, providing essential functionality for distributed ledger technology operations and properties.",
    "scope_note": null,
    "status": "complete",
    "maturity": "mature",
    "version": null,
    "public_access": true,
    "last_updated": "2025-10-28",
    "authority_score": 0.95,
    "quality_score": null,
    "cross_domain_links": null,
    "owl_class": "bc:GossipProtocol",
    "owl_physicality": "VirtualEntity",
    "owl_role": "Object",
    "owl_inferred_class": "bc:VirtualObject",
    "is_subclass_of": [
      "Blockchain Network"
    ],
    "has_part": [],
    "is_part_of": [],
    "requires": [],
    "depends_on": [],
    "enables": [],
    "relates_to": [],
    "bridges_to": [],
    "bridges_from": [],
    "domain_extensions": {},
    "belongs_to_domain": [
      "CryptographicDomain"
    ],
    "implemented_in_layer": [],
    "source": [
      "ISO/IEC 23257:2021",
      "IEEE 2418.1",
      "NIST NISTIR"
    ],
    "other_relationships": {
      "bridges-to": [
        "Networkcomponent",
        "BlockchainEntity"
      ]
    },
    "validation": {
      "is_valid": false,
      "errors": [
        "owl:class namespace 'bc' doesn't match source-domain 'blockchain'"
      ]
    }
  }
}