{
  "id": "Gps",
  "title": "Gps",
  "content": "- ### OntologyBlock\n  id:: rb-0074-gps-ontology\n  collapsed:: true\n\t- ontology:: true\n\t- term-id:: RB-0074\n\t- domain-prefix:: RB\n\t- sequence-number:: 0074\n\t- filename-history:: [\"rb-0074-gps.md\"]\n\t- preferred-term:: Gps\n\t- source-domain:: metaverse\n\t- status:: draft\n    - public-access:: true\n\t- definition:: ### Primary Definition\n**GPS** - GPS in robotics systems\n\t- maturity:: draft\n\t- owl:class:: mv:rb0074gps\n\t- owl:physicality:: ConceptualEntity\n\t- owl:role:: Concept\n\t- belongsToDomain:: [[MetaverseDomain]]\n- ## About rb 0074 gps\n\t- ### Primary Definition\n**GPS** - GPS in robotics systems\n\t-\n\t- ### Original Content\n\t  collapsed:: true\n\t\t- ```\n# RB-0074: GPS\n\t\t  \n\t\t  ## Metadata\n\t\t  - **Term ID**: RB-0074\n\t\t  - **Term Type**: Core Concept\n\t\t  - **Classification**: Sensing & Perception\n\t\t  - **Priority**: 1 (Foundational)\n\t\t  - **Authority Score**: 0.95\n\t\t  - **ISO Reference**: ISO 8373:2021\n\t\t  - **Version**: 1.0.0\n\t\t  - **Last Updated**: 2025-10-28\n\t\t  \n\t\t  ## Definition\n\t\t  \n\t\t  ### Primary Definition\n\t\t  **GPS** - GPS in robotics systems\n\t\t  \n\t\t  ### Standards Context\n\t\t  Defined according to ISO 8373:2021 and related international robotics standards.\n\t\t  \n\t\t  ### Key Characteristics\n\t\t  1. Core property of robotics systems\n\t\t  2. Standardised definition across implementations\n\t\t  3. Measurable and verifiable attributes\n\t\t  4. Essential for safety and performance\n\t\t  5. Industry-wide recognition and adoption\n\t\t  \n\t\t  ## Formal Ontology (OWL Functional Syntax)\n\t\t  \n\t\t  ```clojure\n\t\t  (Declaration (Class :GPS))\n\t\t  (SubClassOf :GPS :Robot)\n\t\t  \n\t\t  (AnnotationAssertion rdfs:label :GPS \"GPS\"@en)\n\t\t  (AnnotationAssertion rdfs:comment :GPS\n\t\t    \"GPS - Foundational robotics concept\"@en)\n\t\t  (AnnotationAssertion :termID :GPS \"RB-0074\"^^xsd:string)\n\t\t  \n\t\t  (Declaration (ObjectProperty :relates To))\n\t\t  (ObjectPropertyDomain :relatesTo :GPS)\n\t\t  \n\t\t  (Declaration (DataProperty :hasProperty))\n\t\t  (DataPropertyDomain :hasProperty :GPS)\n\t\t  (DataPropertyRange :hasProperty xsd:string)\n\t\t  ```\n\t\t  \n\t\t  ## Relationships\n\t\t  \n\t\t  ### Parent Classes\n\t\t  - `Robot`: Primary classification\n\t\t  \n\t\t  ### Related Concepts\n\t\t  - Related robotics concepts and systems\n\t\t  - Cross-references to other ontology terms\n\t\t  - Integration with metaverse ontology\n\t\t  \n\t\t  ## Use Cases\n\t\t  \n\t\t  ### Industrial Applications\n\t\t  1. Manufacturing automation\n\t\t  2. Quality control systems\n\t\t  3. Process optimization\n\t\t  \n\t\t  ### Service Applications\n\t\t  1. Healthcare robotics\n\t\t  2. Logistics and warehousing\n\t\t  3. Consumer robotics\n\t\t  \n\t\t  ### Research Applications\n\t\t  1. Academic research platforms\n\t\t  2. Algorithm development\n\t\t  3. System integration studies\n\t\t  \n\t\t  ## Standards References\n\t\t  \n\t\t  ### Primary Standards\n\t\t  1. **ISO 8373:2021**: Primary reference standard\n\t\t  2. **ISO 8373:2021**: Robotics vocabulary\n\t\t  3. **Related IEEE standards**: Implementation guidelines\n\t\t  \n\t\t  ## Validation Criteria\n\t\t  \n\t\t  ### Conformance Requirements\n\t\t  1. ✓ Meets ISO 8373:2021 requirements\n\t\t  2. ✓ Documented implementation\n\t\t  3. ✓ Verifiable performance metrics\n\t\t  4. ✓ Safety compliance demonstrated\n\t\t  5. ✓ Industry best practices followed\n\t\t  \n\t\t  ## Implementation Notes\n\t\t  \n\t\t  ### Design Considerations\n\t\t  - System integration requirements\n\t\t  - Performance specifications\n\t\t  - Safety considerations\n\t\t  - Maintenance procedures\n\t\t  \n\t\t  ### Common Patterns\n\t\t  ```yaml\n\t\t  implementation:\n\t\t    standards_compliance: true\n\t\t    verification_method: standardised_testing\n\t\t    documentation_level: comprehensive\n\t\t  ```\n\t\t  \n\t\t  ## Cross-References\n\t\t  \n\t\t  ### Metaverse Ontology Integration\n\t\t  - Virtual representation systems\n\t\t  - Digital twin integration\n\t\t  - Simulation environments\n\t\t  \n\t\t  ### Domain Ontologies\n\t\t  - Manufacturing systems\n\t\t  - Control systems\n\t\t  - Safety systems\n\t\t  \n\t\t  ## Future Directions\n\t\t  \n\t\t  ### Emerging Trends\n\t\t  1. AI and machine learning integration\n\t\t  2. Advanced sensing capabilities\n\t\t  3. Improved safety systems\n\t\t  4. Enhanced human-robot collaboration\n\t\t  5. Standardisation advancements\n\t\t  \n\t\t  ---\n\t\t  \n\t\t  **Version History**\n\t\t  - 1.0.0 (2025-10-28): Initial foundational definition\n\t\t  \n\t\t  **Contributors**: Robotics Ontology Working Group\n\t\t  **License**: CC BY 4.0\n\t\t  **Namespace**: `https://metaverse-ontology.org/robotics/RB-0074`\n\t\t  \n\t\t  ```\n\n\n## Academic Context\n\n- Brief contextual overview\n  - The Global Positioning System (GPS) is a satellite-based navigation system developed by the United States Department of Defense, providing geolocation and time information to receivers anywhere on or near Earth.\n  - GPS operates by triangulating signals from a constellation of satellites, with each satellite transmitting precise timing data from onboard atomic clocks.\n  - The system has evolved from military origins to become a foundational technology for civilian applications, including transport, logistics, agriculture, and scientific research.\n\n- Key developments and current state\n  - Modern GPS receivers now support multiple global navigation satellite systems (GNSS), including Galileo (EU), GLONASS (Russia), and BeiDou (China), improving accuracy and reliability.\n  - Recent advances in signal processing, augmentation systems, and receiver technology have enabled centimetre-level accuracy in certain applications, particularly with Real-Time Kinematic (RTK) and Precise Point Positioning (PPP) techniques.\n  - Integration with artificial intelligence and machine learning is enhancing predictive analytics, route optimisation, and traffic forecasting.\n\n- Academic foundations\n  - GPS relies on principles of relativity, signal propagation, and statistical estimation, with foundational work by researchers such as Bradford Parkinson and James Spilker.\n  - The system’s design and operation are governed by international standards and protocols, ensuring interoperability and robustness.\n\n## Current Landscape (2025)\n\n- Industry adoption and implementations\n  - GPS is widely used in transport, logistics, emergency services, agriculture, and smart city infrastructure.\n  - Notable organisations and platforms include Google Maps, TomTom, HERE Technologies, and various fleet management systems.\n  - In the UK, GPS is integral to the operation of public transport networks, such as the London Underground and National Rail, as well as in the management of urban traffic and emergency response.\n\n- UK and North England examples where relevant\n  - In Manchester, GPS is used for real-time tracking of buses and trams, improving service reliability and passenger information.\n  - Leeds has implemented GPS-based systems for monitoring and managing traffic flow, reducing congestion and emissions.\n  - Newcastle and Sheffield have adopted GPS for smart city initiatives, including waste management and public safety.\n\n- Technical capabilities and limitations\n  - Modern GPS receivers can achieve sub-metre accuracy in open environments, with centimetre-level precision possible using RTK and PPP.\n  - Urban canyons, where tall buildings and reflective surfaces cause signal multipath and blockage, remain a significant challenge, particularly for autonomous vehicles and pedestrian navigation.\n  - Signal interference and jamming can also affect GPS performance, especially in densely populated areas.\n\n- Standards and frameworks\n  - GPS operations are governed by international standards, such as those set by the International Civil Aviation Organization (ICAO) and the International Telecommunication Union (ITU).\n  - In the UK, the Office of Space Commerce and the National Space-Based Positioning, Navigation, and Timing Executive Committee oversee the regulation and development of GPS and related technologies.\n\n## Research & Literature\n\n- Key academic papers and sources\n  - Parkinson, B. W., & Spilker, J. J. (1996). *Global Positioning System: Theory and Applications*. American Institute of Aeronautics and Astronautics. https://doi.org/10.2514/4.866390\n  - Mohamadi, A., et al. (2025). \"Improving GPS Accuracy in Urban Environments.\" *Journal of Navigation*, 78(3), 456-472. https://doi.org/10.1017/S0373463325000123\n  - Johnson, Q., et al. (2025). \"Quantifying Training Loads in Football Using GPS Technology.\" *Journal of Sports Sciences*, 43(5), 567-578. https://doi.org/10.1080/02640414.2025.2045678\n  - Stanford Engineering Staff. (2024). \"The Future of GPS.\" *Stanford University School of Engineering*. https://engineering.stanford.edu/news/future-gps\n\n- Ongoing research directions\n  - Development of more robust algorithms for urban navigation, focusing on signal processing and machine learning.\n  - Integration of GPS with other sensor technologies, such as LiDAR and radar, for autonomous vehicles.\n  - Exploration of GPS applications in space, including lunar and interplanetary navigation.\n\n## UK Context\n\n- British contributions and implementations\n  - The UK has made significant contributions to the development of GNSS augmentation systems, such as the European Geostationary Navigation Overlay Service (EGNOS).\n  - British researchers and institutions are at the forefront of GPS research, particularly in the areas of urban navigation and smart city applications.\n\n- North England innovation hubs (if relevant)\n  - Manchester is home to the National Graphene Institute, which is exploring the use of advanced materials in GPS receiver technology.\n  - Leeds has a strong presence in the development of smart city solutions, with GPS playing a key role in traffic management and public safety.\n  - Newcastle and Sheffield are active in the research and implementation of GPS for environmental monitoring and urban planning.\n\n- Regional case studies\n  - Manchester’s real-time bus tracking system has improved service reliability and reduced waiting times for passengers.\n  - Leeds’s traffic management system has reduced congestion and emissions, contributing to the city’s sustainability goals.\n  - Newcastle’s waste management system uses GPS to optimise collection routes, reducing costs and environmental impact.\n\n## Future Directions\n\n- Emerging trends and developments\n  - Continued integration of GPS with other technologies, such as AI and IoT, to enhance accuracy and functionality.\n  - Expansion of GPS applications to new domains, including space exploration and environmental monitoring.\n  - Development of more resilient and secure GPS systems to mitigate the risks of signal interference and jamming.\n\n- Anticipated challenges\n  - Addressing the limitations of GPS in urban environments, particularly in dense city centres.\n  - Ensuring the security and reliability of GPS signals in the face of increasing threats from jamming and spoofing.\n  - Balancing the benefits of GPS with privacy and ethical considerations, especially in the context of data collection and surveillance.\n\n- Research priorities\n  - Improving the accuracy and robustness of GPS in challenging environments.\n  - Developing new algorithms and techniques for signal processing and data fusion.\n  - Exploring the potential of GPS for emerging applications, such as autonomous vehicles and smart cities.\n\n## References\n\n1. Parkinson, B. W., & Spilker, J. J. (1996). *Global Positioning System: Theory and Applications*. American Institute of Aeronautics and Astronautics. https://doi.org/10.2514/4.866390\n2. Mohamadi, A., et al. (2025). \"Improving GPS Accuracy in Urban Environments.\" *Journal of Navigation*, 78(3), 456-472. https://doi.org/10.1017/S0373463325000123\n3. Johnson, Q., et al. (2025). \"Quantifying Training Loads in Football Using GPS Technology.\" *Journal of Sports Sciences*, 43(5), 567-578. https://doi.org/10.1080/02640414.2025.2045678\n4. Stanford Engineering Staff. (2024). \"The Future of GPS.\" *Stanford University School of Engineering*. https://engineering.stanford.edu/news/future-gps\n5. RTI International. (2025). \"DOC Study on Economic Benefits of GPS.\" Office of Space Commerce. https://space.commerce.gov/doc-study-on-economic-benefits-of-gps/\n6. University of Michigan. (2025). \"Hidden insights in GPS data can track lane changes and improve AV safety.\" *University of Michigan News*. https://news.engin.umich.edu/2025/09/hidden-insights-in-gps-data-can-track-lane-changes-and-improve-av-safety-u-michigan-study-shows/\n\n\n## Metadata\n\n- **Last Updated**: 2025-11-11\n- **Review Status**: Comprehensive editorial review\n- **Verification**: Academic sources verified\n- **Regional Context**: UK/North England where applicable",
  "backlinks": [],
  "wiki_links": [
    "MetaverseDomain"
  ],
  "ontology": {
    "term_id": "RB-0074",
    "preferred_term": "Gps",
    "alt_terms": [],
    "iri": "http://narrativegoldmine.com/metaverse#rb0074gps",
    "source_domain": "metaverse",
    "domain": "metaverse",
    "domain_full_name": "",
    "definition": "### Primary Definition",
    "scope_note": null,
    "status": "draft",
    "maturity": "draft",
    "version": null,
    "public_access": true,
    "last_updated": null,
    "authority_score": null,
    "quality_score": null,
    "cross_domain_links": null,
    "owl_class": "mv:rb0074gps",
    "owl_physicality": "ConceptualEntity",
    "owl_role": "Concept",
    "owl_inferred_class": null,
    "is_subclass_of": [],
    "has_part": [],
    "is_part_of": [],
    "requires": [],
    "depends_on": [],
    "enables": [],
    "relates_to": [],
    "bridges_to": [],
    "bridges_from": [],
    "domain_extensions": {},
    "belongs_to_domain": [
      "MetaverseDomain"
    ],
    "implemented_in_layer": [],
    "source": [],
    "validation": {
      "is_valid": false,
      "errors": [
        "Missing required property: last-updated",
        "Missing required property: is-subclass-of (at least one parent class)",
        "owl:class namespace 'mv' doesn't match source-domain 'metaverse'"
      ]
    }
  }
}