{
  "id": "GPT-2",
  "title": "GPT 2",
  "content": "- ### OntologyBlock\n  id:: gpt-2-ontology\n  collapsed:: true\n\t- ontology:: true\n\t- term-id:: AI-0213\n\t- preferred-term:: GPT 2\n\t- source-domain:: metaverse\n\t- status:: draft\n\t- public-access:: true\n\n\n\n\n### OWL Classification\n\t- owl:class:: mv:GPT2\n\t- owl:physicality:: ConceptualEntity\n\t- owl:role:: Concept\n\n### Domain & Architecture\n\t- belongsToDomain:: [[MetaverseDomain]]\n\t- maturity:: draft\n\n### Relationships\n- is-subclass-of:: [[GPT]]\n\n## Characteristics\n\n- **Scale Increase**: 10Ã— larger than original GPT\n- **Zero-Shot Learning**: Performs tasks without fine-tuning\n- **Multitask Capability**: Single model handles diverse tasks\n- **Internet-Scale Training**: Trained on WebText dataset\n\n## Academic Foundations\n\n**Primary Source**: Radford et al., \"Language Models are Unsupervised Multitask Learners\" (2019)\n\n**Key Finding**: Language models begin to learn tasks without explicit supervision when trained on millions of webpages, demonstrating emergent multitask capabilities.\n\n## Technical Context\n\nGPT-2 demonstrated that sufficiently large language models trained on diverse internet text can perform many tasks in a zero-shot setting without task-specific fine-tuning, a precursor to the few-shot learning capabilities in GPT-3.\n\n## Ontological Relationships\n\n- **Broader Term**: Pre-trained Language Model\n- **Related Terms**: GPT, GPT-3, Zero-Shot Learning, Autoregressive Language Model\n- **Architecture Evolution**: Successor to GPT, predecessor to GPT-3\n\n## Usage Context\n\n\"GPT-2 demonstrates that language models begin to learn tasks without explicit supervision when trained on millions of webpages.\"\n\n## OWL Functional Syntax\n\n```clojure\n(Declaration (Class :GPT2))\n(AnnotationAssertion rdfs:label :GPT2 \"GPT-2\"@en)\n(AnnotationAssertion rdfs:comment :GPT2\n  \"A 1.5 billion parameter transformer language model demonstrating unsupervised multitask learning capabilities.\"@en)\n(AnnotationAssertion :hasSource :GPT2\n  \"Radford et al., 'Language Models are Unsupervised Multitask Learners' (2019)\"@en)\n\n;; Taxonomic relationships\n(SubClassOf :GPT2 :PreTrainedLanguageModel)\n(SubClassOf :GPT2 :AutoregressiveLanguageModel)\n(SubClassOf :GPT2 :TransformerArchitecture)\n\n;; Evolution\n(SubClassOf :GPT2\n  (ObjectSomeValuesFrom :successorOf :GPT))\n(SubClassOf :GPT3\n  (ObjectSomeValuesFrom :successorOf :GPT2))\n\n;; Training\n(SubClassOf :GPT2\n  (ObjectSomeValuesFrom :trainedOn :WebText))\n\n;; Capabilities\n(SubClassOf :GPT2\n  (ObjectSomeValuesFrom :demonstrates :ZeroShotLearning))\n(SubClassOf :GPT2\n  (ObjectSomeValuesFrom :demonstrates :UnsupervisedMultitaskLearning))\n\n;; Properties\n(DataPropertyAssertion :parameterCount :GPT2 \"1500000000\"^^xsd:integer)\n(DataPropertyAssertion :trainingDataSize :GPT2 \"40GB\"^^xsd:string)\n(DataPropertyAssertion :contextLength :GPT2 \"1024\"^^xsd:integer)\n(DataPropertyAssertion :scaleIncrease :GPT2 \"10x vs GPT\"^^xsd:string)\n(DataPropertyAssertion :requiresFineTuning :GPT2 \"false\"^^xsd:boolean)\n\n;; Related models\n(DisjointClasses :GPT2 :BERT)\n(DisjointClasses :GPT2 :T5)\n```\n\n## References\n\n- Radford, A., et al. (2019). \"Language Models are Unsupervised Multitask Learners\". OpenAI\n\n---\n\n*Ontology Term managed by AI-Grounded Ontology Working Group*\n*UK English Spelling Standards Applied*\n\t- maturity:: draft\n\t- owl:class:: mv:GPT2\n\t- owl:physicality:: ConceptualEntity\n\t- owl:role:: Concept\n\t- belongsToDomain:: [[MetaverseDomain]]",
  "backlinks": [],
  "wiki_links": [
    "GPT",
    "MetaverseDomain"
  ],
  "ontology": {
    "term_id": "AI-0213",
    "preferred_term": "GPT 2",
    "alt_terms": [],
    "iri": "http://narrativegoldmine.com/metaverse#GPT2",
    "source_domain": "metaverse",
    "domain": "metaverse",
    "domain_full_name": "",
    "definition": null,
    "scope_note": null,
    "status": "draft",
    "maturity": "draft",
    "version": null,
    "public_access": true,
    "last_updated": null,
    "authority_score": null,
    "quality_score": null,
    "cross_domain_links": null,
    "owl_class": "mv:GPT2",
    "owl_physicality": "ConceptualEntity",
    "owl_role": "Concept",
    "owl_inferred_class": null,
    "is_subclass_of": [],
    "has_part": [],
    "is_part_of": [],
    "requires": [],
    "depends_on": [],
    "enables": [],
    "relates_to": [],
    "bridges_to": [],
    "bridges_from": [],
    "domain_extensions": {},
    "belongs_to_domain": [
      "MetaverseDomain",
      "MetaverseDomain"
    ],
    "implemented_in_layer": [],
    "source": [],
    "validation": {
      "is_valid": false,
      "errors": [
        "Missing required property: last-updated",
        "Missing required property: definition",
        "Missing required property: is-subclass-of (at least one parent class)",
        "owl:class namespace 'mv' doesn't match source-domain 'metaverse'"
      ]
    }
  }
}