{
  "id": "Hash Function",
  "title": "Hash Function",
  "content": "- ### OntologyBlock\n  id:: hash-function-ontology\n  collapsed:: true\n\n  - **Identification**\n\n    - domain-prefix:: BC\n\n    - sequence-number:: 0027\n\n    - filename-history:: [\"BC-0027-hash-function.md\"]\n    - public-access:: true\n    - ontology:: true\n    - is-subclass-of:: [[BlockchainTechnology]]\n    - term-id:: BC-0027\n    - preferred-term:: Hash Function\n    - source-domain:: blockchain\n    - status:: complete\n    - version:: 1.0.0\n    - last-updated:: 2025-10-28\n\n  - **Definition**\n    - definition:: One-way data transformation within blockchain systems, providing essential functionality for distributed ledger technology operations and properties.\n    - maturity:: mature\n    - source:: [[ISO/IEC 23257:2021]], [[IEEE 2418.1]], [[NIST NISTIR]]\n    - authority-score:: 1.0\n\n  - **Semantic Classification**\n    - owl:class:: bc:HashFunction\n    - owl:physicality:: VirtualEntity\n    - owl:role:: Object\n    - owl:inferred-class:: bc:VirtualObject\n    - belongsToDomain:: [[CryptographicDomain]]\n\n  - #### OWL Restrictions\n    \n    \n\n  - #### CrossDomainBridges\n    - bridges-to:: [[BlockchainEntity]] via is-subclass-of\n\n  -",
  "backlinks": [
    "BC-0043-blake2",
    "BC-0029-merkle-tree",
    "BC-0048-collision-resistance",
    "BC-0042-keccak-256",
    "BC-0046-hash-collision",
    "SHA-256",
    "BC-0047-preimage-resistance",
    "BC-0028-sha-256"
  ],
  "wiki_links": [
    "ISO/IEC 23257:2021",
    "BlockchainTechnology",
    "BlockchainEntity",
    "IEEE 2418.1",
    "NIST NISTIR",
    "CryptographicDomain"
  ],
  "ontology": {
    "term_id": "BC-0027",
    "preferred_term": "Hash Function",
    "alt_terms": [],
    "iri": "http://narrativegoldmine.com/blockchain#HashFunction",
    "source_domain": "blockchain",
    "domain": "blockchain",
    "domain_full_name": "",
    "definition": "One-way data transformation within blockchain systems, providing essential functionality for distributed ledger technology operations and properties.",
    "scope_note": null,
    "status": "complete",
    "maturity": "mature",
    "version": "1.0.0",
    "public_access": true,
    "last_updated": "2025-10-28",
    "authority_score": 1.0,
    "quality_score": null,
    "cross_domain_links": null,
    "owl_class": "bc:HashFunction",
    "owl_physicality": "VirtualEntity",
    "owl_role": "Object",
    "owl_inferred_class": "bc:VirtualObject",
    "is_subclass_of": [],
    "has_part": [],
    "is_part_of": [],
    "requires": [],
    "depends_on": [],
    "enables": [],
    "relates_to": [],
    "bridges_to": [
      "BlockchainEntity via is"
    ],
    "bridges_from": [],
    "domain_extensions": {},
    "belongs_to_domain": [
      "CryptographicDomain"
    ],
    "implemented_in_layer": [],
    "source": [
      "ISO/IEC 23257:2021",
      "IEEE 2418.1",
      "NIST NISTIR"
    ],
    "validation": {
      "is_valid": false,
      "errors": [
        "Missing required property: is-subclass-of (at least one parent class)",
        "owl:class namespace 'bc' doesn't match source-domain 'blockchain'"
      ]
    }
  }
}