{
  "id": "Health Metaverse Application",
  "title": "Health Metaverse Application",
  "content": "- ### OntologyBlock\n  id:: health-metaverse-application-ontology\n  collapsed:: true\n\t- ontology:: true\n\t- term-id:: 20311\n\t- preferred-term:: Health Metaverse Application\n\t- status:: draft\n\t- public-access:: true\n\t- definition:: A specialized virtual platform integrating healthcare delivery, medical training, therapeutic interventions, and patient engagement through immersive environments that comply with health data regulations and clinical standards.\n\t- source:: [[HL7 FHIR]], [[DICOM]], [[FDA Digital Health]], [[OpenXR Healthcare]]\n\t- maturity:: mature\n\t- owl:class:: mv:HealthMetaverseApplication\n\t- owl:physicality:: VirtualEntity\n\t- owl:role:: Object\n\t- owl:inferred-class:: mv:VirtualObject\n\t- owl:functional-syntax:: true\n\t- belongsToDomain:: [[VirtualSocietyDomain]], [[ComputationAndIntelligenceDomain]]\n\t- implementedInLayer:: [[ApplicationLayer]]\n\t- #### Relationships\n\t  id:: health-metaverse-application-relationships\n\t  collapsed:: true\n\t\t- is-part-of:: [[Metaverse Application Platform]]\n\t\t- has-part:: [[Therapy Environment]]\n\t\t- has-part:: [[Virtual Clinic]]\n\t\t- has-part:: [[Diagnostic Interface]]\n\t\t- has-part:: [[Patient Portal]]\n\t\t- has-part:: [[Medical Simulation]]\n\t\t- has-part:: [[Health Record System]]\n\t\t- requires:: [[End-to-End Encryption]]\n\t\t- requires:: [[Identity Management]]\n\t\t- requires:: [[Biometric Sensor Integration]]\n\t\t- requires:: [[Haptic Feedback System]]\n\t\t- enables:: [[Mental Health Therapy]]\n\t\t- enables:: [[Telemedicine]]\n\t\t- enables:: [[Surgical Training]]\n\t\t- enables:: [[Rehabilitation Program]]\n\t\t- enables:: [[Medical Education]]\n\t\t- depends-on:: [[Clinical AI]]\n\t\t- depends-on:: [[XR Device]]\n\t\t- depends-on:: [[Network Infrastructure]]\n\t\t- depends-on:: [[3D Medical Imaging]]\n\n## Academic Context\n\n- The health metaverse represents a convergence of immersive technologies—virtual reality (VR), augmented reality (AR), artificial intelligence (AI), blockchain, and digital twins—creating integrated virtual environments for healthcare delivery, education, and therapy.\n  - These technologies enable simulated clinical scenarios, remote consultations, and personalised patient engagement, grounded in rigorous academic research on digital health and extended reality applications.\n  - Foundational studies highlight the metaverse’s role in enhancing surgical precision, mental health interventions, and collaborative healthcare communication, establishing a robust interdisciplinary academic framework[1][4].\n\n## Current Landscape (2025)\n\n- Industry adoption is accelerating, with the global metaverse healthcare market valued at approximately USD 18.9 billion in 2025 and projected to exceed USD 100 billion by 2030, driven by a compound annual growth rate (CAGR) near 36%[3].\n  - Leading platforms integrate XR technologies for medical training, virtual clinics, rehabilitation, and personalised medicine, reflecting a shift towards immersive, patient-centred care[1][2].\n  - Notable implementations include digital therapeutics for mental health (e.g., gameChange by University of Oxford), VR-based social skills training for neurodiverse populations (Floreo), and virtual treatment rooms by XRHealth[2].\n- Technical capabilities now support realistic anatomical simulations, AI-driven health analytics, and secure data sharing compliant with health data regulations, though challenges remain in interoperability and equitable access.\n- Standards and frameworks are evolving to address data privacy, clinical validation, and ethical considerations, with increasing emphasis on regulatory compliance and patient safety in virtual environments[1][4].\n\n## Research & Literature\n\n- Key academic contributions include:\n  - Lee et al. (2024), \"The application of metaverse in healthcare,\" *Frontiers in Public Health*, highlighting immersive virtual healthcare experiences and collaborative platforms[1].\n  - Kim et al. (2025), \"Analyzing metaverse-based digital therapies, their effectiveness and potential risks,\" *Scientific Reports*, evaluating digital therapeutics for PTSD, anxiety, and ADHD with clinical validation[6].\n  - Nguyen et al. (2024), \"How the Metaverse Is Shaping the Future of Healthcare,\" *NIH*, discussing integration of AI, blockchain, and digital twins in healthcare communication and training[4].\n- Ongoing research focuses on improving long-term efficacy of metaverse therapies, addressing privacy and accessibility, and refining AI-personalised healthcare delivery models[6].\n\n## UK Context\n\n- The UK is an active contributor to metaverse healthcare innovation, with institutions like the University of Oxford pioneering VR-based mental health treatments and digital therapeutics[2].\n- North England hosts emerging innovation hubs in Manchester, Leeds, Newcastle, and Sheffield, fostering collaborations between NHS trusts, universities, and tech startups to develop immersive training and virtual care solutions.\n  - For example, Manchester’s digital health clusters are exploring XR applications for surgical training and patient rehabilitation, while Leeds is advancing telemedicine platforms integrated with metaverse environments.\n- Regional case studies demonstrate improved patient engagement and training outcomes, though infrastructure and digital literacy disparities remain challenges to widespread adoption.\n\n## Future Directions\n\n- Emerging trends include:\n  - Expansion of AI-powered personalised medicine within metaverse platforms, enabling dynamic, data-driven patient care.\n  - Integration of quantum computing and Internet of Medical Things (IoMT) to enhance real-time data processing and device interoperability.\n  - Development of standardised regulatory frameworks to ensure safety, privacy, and ethical use of metaverse healthcare applications.\n- Anticipated challenges involve balancing technological innovation with equitable access, addressing digital divide issues, and ensuring robust clinical validation.\n- Research priorities focus on longitudinal studies of therapeutic effectiveness, scalable deployment models, and ethical governance of immersive healthcare environments.\n\n## References\n\n1. Lee, J., Park, S., & Kim, H. (2024). The application of metaverse in healthcare. *Frontiers in Public Health*, 12, 1420367. https://doi.org/10.3389/fpubh.2024.1420367\n2. PwC. (2024). The Future of Healthcare in the Metaverse. PwC Industry Report.\n3. NextMSC. (2025). Metaverse in Healthcare Market Analysis 2025-2030.\n4. Nguyen, T., et al. (2024). How the Metaverse Is Shaping the Future of Healthcare. *NIH*. PMC12003935.\n5. World Health Expo Insights Staff. (2023). The potential of metaverse in disrupting healthcare. *World Health Expo*.\n6. Kim, Y., Lee, S., & Choi, J. (2025). Analyzing metaverse-based digital therapies, their effectiveness and potential risks. *Scientific Reports*, 15, 9164. https://doi.org/10.1038/s41598-025-00916-4\n\n*If the metaverse can help surgeons rehearse complex procedures virtually, perhaps it can also help patients rehearse their excuses for missing appointments—though we’d advise sticking to the virtual clinic rather than the virtual fibbing.*\n\n## Metadata\n\n- **Last Updated**: 2025-11-11\n- **Review Status**: Comprehensive editorial review\n- **Verification**: Academic sources verified\n- **Regional Context**: UK/North England where applicable",
  "backlinks": [
    "Network Infrastructure"
  ],
  "wiki_links": [
    "Medical Simulation",
    "Health Record System",
    "Metaverse Application Platform",
    "Clinical AI",
    "FDA Digital Health",
    "Telemedicine",
    "VirtualSocietyDomain",
    "XR Device",
    "Therapy Environment",
    "Medical Education",
    "Diagnostic Interface",
    "End-to-End Encryption",
    "Network Infrastructure",
    "Biometric Sensor Integration",
    "DICOM",
    "Patient Portal",
    "3D Medical Imaging",
    "Haptic Feedback System",
    "Mental Health Therapy",
    "Surgical Training",
    "OpenXR Healthcare",
    "Rehabilitation Program",
    "Identity Management",
    "HL7 FHIR",
    "ComputationAndIntelligenceDomain",
    "ApplicationLayer",
    "Virtual Clinic"
  ],
  "ontology": {
    "term_id": "20311",
    "preferred_term": "Health Metaverse Application",
    "alt_terms": [],
    "iri": "http://narrativegoldmine.com/metaverse#HealthMetaverseApplication",
    "source_domain": null,
    "domain": "mv",
    "domain_full_name": "Metaverse",
    "definition": "A specialized virtual platform integrating healthcare delivery, medical training, therapeutic interventions, and patient engagement through immersive environments that comply with health data regulations and clinical standards.",
    "scope_note": null,
    "status": "draft",
    "maturity": "mature",
    "version": null,
    "public_access": true,
    "last_updated": null,
    "authority_score": null,
    "quality_score": null,
    "cross_domain_links": null,
    "owl_class": "mv:HealthMetaverseApplication",
    "owl_physicality": "VirtualEntity",
    "owl_role": "Object",
    "owl_inferred_class": "mv:VirtualObject",
    "is_subclass_of": [],
    "has_part": [
      "Therapy Environment",
      "Virtual Clinic",
      "Diagnostic Interface",
      "Patient Portal",
      "Medical Simulation",
      "Health Record System"
    ],
    "is_part_of": [
      "Metaverse Application Platform"
    ],
    "requires": [
      "End-to-End Encryption",
      "Identity Management",
      "Biometric Sensor Integration",
      "Haptic Feedback System"
    ],
    "depends_on": [
      "Clinical AI",
      "XR Device",
      "Network Infrastructure",
      "3D Medical Imaging"
    ],
    "enables": [
      "Mental Health Therapy",
      "Telemedicine",
      "Surgical Training",
      "Rehabilitation Program",
      "Medical Education"
    ],
    "relates_to": [],
    "bridges_to": [],
    "bridges_from": [],
    "domain_extensions": {},
    "belongs_to_domain": [
      "VirtualSocietyDomain",
      "ComputationAndIntelligenceDomain"
    ],
    "implemented_in_layer": [
      "ApplicationLayer"
    ],
    "source": [
      "HL7 FHIR",
      "DICOM",
      "FDA Digital Health",
      "OpenXR Healthcare"
    ],
    "validation": {
      "is_valid": false,
      "errors": [
        "Missing required property: source-domain",
        "Missing required property: last-updated",
        "Missing required property: is-subclass-of (at least one parent class)",
        "term-id '20311' doesn't match domain 'mv' (expected MV-)"
      ]
    }
  }
}