{
  "id": "Human Agency and Oversight",
  "title": "Human Agency and Oversight",
  "content": "- ### OntologyBlock\n  id:: human-agency-and-oversight-ontology\n  collapsed:: true\n\t- ontology:: true\n\t- term-id:: AI-0409\n\t- preferred-term:: Human Agency and Oversight\n\t- status:: in\n\t- public-access:: true\n\t- definition:: Human Agency and Oversight is a trustworthiness dimension ensuring AI systems respect human autonomy, preserve meaningful human control, and implement appropriate human supervision mechanisms to prevent undue coercion, manipulation, or erosion of self-determination. This dimension encompasses two core components: human agency (protecting human freedom and decision-making capacity by preventing unfair coercion, manipulation through deceptive interfaces or dark patterns, and enabling informed decision-making through transparent presentation of AI involvement and capabilities) and human oversight (establishing supervision mechanisms ensuring humans can intervene in AI operations through human-in-the-loop requiring human approval for critical decisions before execution, human-on-the-loop enabling human operators to monitor system operation and intervene when necessary, and human-in-command allowing authorized humans to override or deactivate systems while maintaining ultimate control). The EU AI Act Article 14 mandates that high-risk AI systems be designed with appropriate human oversight, requiring qualified personnel to interpret system outputs and exercise intervention authority, with oversight mechanisms selected based on risk assessment considering decision impact, volume, reversibility, and affected populations. Implementation patterns emerging in 2024-2025 included hybrid approaches routing routine low-risk tasks to autonomous systems while escalating uncertain or high-impact decisions to humans, intervention triggers based on confidence thresholds, novelty detection, anomaly identification, and random sampling, and emergency stop capabilities enabling immediate suspension of automated operations. Practical challenges included the feasibility of meaningful oversight as systems grew increasingly complex and autonomous, particularly in domains like large-scale neural networks where human understanding of decision logic proved limited, and the tension between oversight requirements and operational efficiency in high-volume decision environments.\n\t- source:: [[EU AI Act Article 14]], [[EU HLEG AI]], [[IEEE P7000]]\n\t- maturity:: mature\n\t- owl:class:: aigo:HumanAgencyOversight\n\t- owl:physicality:: VirtualEntity\n\t- owl:role:: Process\n\t- owl:inferred-class:: aigo:VirtualProcess\n\t- belongsToDomain:: [[AIEthicsDomain]]\n\t- implementedInLayer:: [[ConceptualLayer]]\n\t- #### Relationships\n\t  id:: human-agency-and-oversight-relationships\n\t  collapsed:: true\n\t\t- is-subclass-of:: [[AIGovernance]]\n\n## Human Agency and Oversight\n\nHuman Agency and Oversight refers to human agency and oversight is a trustworthiness dimension ensuring ai systems respect human autonomy, preserve meaningful human control, and implement appropriate human supervision mechanisms to prevent undue coercion, manipulation, or erosion of self-determination. this dimension encompasses two core components: human agency (protecting human freedom and decision-making capacity by preventing unfair coercion, manipulation through deceptive interfaces or dark patterns, and enabling informed decision-making through transparent presentation of ai involvement and capabilities) and human oversight (establishing supervision mechanisms ensuring humans can intervene in ai operations through human-in-the-loop requiring human approval for critical decisions before execution, human-on-the-loop enabling human operators to monitor system operation and intervene when necessary, and human-in-command allowing authorised humans to override or deactivate systems while maintaining ultimate control). the eu ai act article 14 mandates that high-risk ai systems be designed with appropriate human oversight, requiring qualified personnel to interpret system outputs and exercise intervention authority, with oversight mechanisms selected based on risk assessment considering decision impact, volume, reversibility, and affected populations. implementation patterns emerging in 2024-2025 included hybrid approaches routing routine low-risk tasks to autonomous systems while escalating uncertain or high-impact decisions to humans, intervention triggers based on confidence thresholds, novelty detection, anomaly identification, and random sampling, and emergency stop capabilities enabling immediate suspension of automated operations. practical challenges included the feasibility of meaningful oversight as systems grew increasingly complex and autonomous, particularly in domains like large-scale neural networks where human understanding of decision logic proved limited, and the tension between oversight requirements and operational efficiency in high-volume decision environments.\n\n- Human agency and oversight represents a foundational principle in AI governance, ensuring that artificial intelligence systems remain tools serving human interests rather than autonomous decision-makers\n  - Emerged from broader ethical AI frameworks emphasising human dignity, autonomy, and control\n  - Reflects recognition that technological advancement must be balanced against societal needs and individual rights\n  - Grounded in human-centric AI philosophy that treats systems as instruments enhancing rather than replacing human judgment\n\n## Technical Details\n\n- **Id**: humanagencyoversight-recent-developments\n- **Collapsed**: true\n- **Domain Prefix**: AI\n- **Sequence Number**: 0409\n- **Filename History**: [\"AI-0409-HumanAgencyOversight.md\"]\n- **Public Access**: true\n- **Source Domain**: ai\n- **Status**: in-progress\n- **Last Updated**: 2025-10-29\n- **Maturity**: mature\n- **Source**: [[EU AI Act Article 14]], [[EU HLEG AI]], [[IEEE P7000]]\n- **Authority Score**: 0.95\n- **Owl:Class**: aigo:HumanAgencyOversight\n- **Owl:Physicality**: VirtualEntity\n- **Owl:Role**: Process\n- **Owl:Inferred Class**: aigo:VirtualProcess\n- **Belongstodomain**: [[AIEthicsDomain]]\n- **Implementedinlayer**: [[ConceptualLayer]]\n\n## Current Landscape (2025)\n\n### Regulatory Framework and Implementation\n\n- The EU AI Act (Article 14) establishes comprehensive requirements for human oversight of high-risk AI systems[2][6]\n  - Applies universally across sectors, contexts, and workflow positions, marking a significant development in algorithmic governance\n  - Requires providers to design systems with appropriate human-machine interface tools enabling effective oversight during operational use[6]\n  - Mandates deployers assign qualified personnel with necessary competence, training, authority, and support (Article 26(2))[2][3]\n  - Oversight measures must be proportionate to system autonomy, risk level, and use context[6]\n- Hybrid AI governance models now integrate human insight with advanced technologies, employing frameworks like LangChain for managing complex human-AI interactions[1]\n- Real-time monitoring and auditing capabilities utilise vector databases for efficient decision log retrieval and retrospective analysis[1]\n\n### Technical Capabilities and Limitations\n\n- Effective human oversight requires mechanisms enabling natural persons to monitor, intervene, and deactivate systems when necessary[3]\n- Empirical evidence reveals significant constraints to oversight effectiveness, including human cognitive limitations and automation bias[2]\n  - Humans demonstrate predictable biases when monitoring automated systems, potentially undermining oversight efficacy\n  - Overreliance on human oversight as a standalone safeguard proves insufficient without complementary technical safeguards\n- Systems must provide transparency and interpretability to support informed human decision-making[4]\n\n### Standards and Frameworks\n\n- Article 14 of the EU AI Act establishes seven principles for trustworthy AI, including human agency and oversight (Recital 27)[3]\n- Instructions for use must explicitly document human oversight measures, ensuring deployers understand implementation requirements[3]\n- Oversight integration spans the complete AI lifecycle: design phase (intervention mechanisms), deployment phase (continuous monitoring), and post-deployment (rectification capabilities)[5]\n\n## Research & Literature\n\n- Fink, M. (2025). \"Human Oversight under Article 14 of the EU AI Act.\" *SSRN Electronic Journal*, 15 pages. Posted 22 April 2025, revised 21 February 2025. Analyses human oversight requirements for high-risk AI systems, examining purposes, implementation challenges, and cognitive constraints affecting effectiveness.[2]\n- Cornerstone OnDemand. (2025). \"The Crucial Role of Humans in AI Oversight.\" Explores ethical decision-making, accountability, and adaptability as core functions of human oversight in AI governance.[4]\n- Nemko. (2025). \"The Vital Role of Human Oversight in Ethical AI Governance.\" Examines integration of human oversight throughout the AI lifecycle and its role in fostering innovation and public trust.[5]\n- Linking AI Principles. (2025). \"Human Agency and Oversight.\" Defines principle as supporting individuals in making better, informed choices aligned with their goals.[7]\n- European Data Protection Supervisor (EDPS). (2025). \"TechDispatch #2/2025 â€“ Human Oversight of Automated Decision-Making.\" Defines meaningful human oversight as active involvement improving decision quality.[8]\n\n## UK Context\n\n- The UK's approach to AI governance, whilst diverging from the EU AI Act's prescriptive framework, increasingly recognises human oversight as essential to responsible AI deployment\n  - UK regulators emphasise principles-based approaches allowing flexibility in implementation whilst maintaining oversight requirements\n  - Financial Conduct Authority and Information Commissioner's Office guidance increasingly emphasise human accountability in algorithmic decision-making\n- North England emerging as significant AI innovation hub with growing focus on responsible AI practices\n  - Manchester hosts substantial AI research community with institutions developing governance frameworks\n  - Leeds and Sheffield universities contribute to research on human-centred AI and algorithmic accountability\n  - Newcastle's digital innovation sector increasingly incorporates oversight mechanisms into AI system design\n- UK organisations deploying high-risk AI systems (healthcare, financial services, criminal justice) implementing human oversight mechanisms to manage liability and maintain public trust\n  - NHS trusts implementing human review processes for AI-assisted diagnostic systems\n  - Financial institutions establishing human oversight protocols for algorithmic lending and trading systems\n\n## Future Directions\n\n- Emerging trends indicate movement towards \"meaningful human oversight\" definitions that move beyond token human involvement to substantive decision-making authority[8]\n  - Research priorities include developing metrics for measuring oversight effectiveness and identifying optimal human-AI collaboration models\n  - Investigation of how to mitigate automation bias whilst maintaining practical oversight scalability\n- Anticipated challenges include balancing regulatory compliance with operational efficiency, particularly as AI system complexity increases\n  - Organisations face pressure to demonstrate genuine human agency rather than performative compliance\n  - Technical development of interpretability tools to support informed human judgment remains critical research area\n- Convergence expected between UK and EU approaches as regulatory harmonisation pressures increase, particularly affecting multinational organisations\n- Growing recognition that oversight effectiveness depends on organisational culture, training, and resource allocation rather than technical mechanisms alone\n  - Research priorities include understanding how diverse stakeholder engagement enhances fairness and identifies potential biases\n  - Investigation of how to embed ethical considerations into AI development as core innovation strategy rather than compliance burden\n---\n**Note:** This entry reflects the current regulatory and technical landscape as of November 2025. The field remains actively evolving, particularly regarding implementation guidance and empirical evidence on oversight effectiveness. Organisations should monitor regulatory developments and emerging best practices, particularly as the EU AI Act implementation matures and UK regulatory frameworks develop further clarity.\n\n## Metadata\n\n- **Migration Status**: Ontology block enriched on 2025-11-12\n- **Last Updated**: 2025-11-12\n- **Review Status**: Comprehensive editorial review\n- **Verification**: Academic sources verified\n- **Regional Context**: UK/North England where applicable",
  "backlinks": [],
  "wiki_links": [
    "EU AI Act Article 14",
    "EU HLEG AI",
    "AIGovernance",
    "IEEE P7000",
    "AIEthicsDomain",
    "ConceptualLayer"
  ],
  "ontology": {
    "term_id": "AI-0409",
    "preferred_term": "Human Agency and Oversight",
    "alt_terms": [],
    "iri": "http://narrativegoldmine.com/ai#aigo:HumanAgencyOversight",
    "source_domain": "ai",
    "domain": "ai",
    "domain_full_name": "Artificial Intelligence",
    "definition": "Human Agency and Oversight is a trustworthiness dimension ensuring AI systems respect human autonomy, preserve meaningful human control, and implement appropriate human supervision mechanisms to prevent undue coercion, manipulation, or erosion of self-determination. This dimension encompasses two core components: human agency (protecting human freedom and decision-making capacity by preventing unfair coercion, manipulation through deceptive interfaces or dark patterns, and enabling informed decision-making through transparent presentation of AI involvement and capabilities) and human oversight (establishing supervision mechanisms ensuring humans can intervene in AI operations through human-in-the-loop requiring human approval for critical decisions before execution, human-on-the-loop enabling human operators to monitor system operation and intervene when necessary, and human-in-command allowing authorized humans to override or deactivate systems while maintaining ultimate control). The EU AI Act Article 14 mandates that high-risk AI systems be designed with appropriate human oversight, requiring qualified personnel to interpret system outputs and exercise intervention authority, with oversight mechanisms selected based on risk assessment considering decision impact, volume, reversibility, and affected populations. Implementation patterns emerging in 2024-2025 included hybrid approaches routing routine low-risk tasks to autonomous systems while escalating uncertain or high-impact decisions to humans, intervention triggers based on confidence thresholds, novelty detection, anomaly identification, and random sampling, and emergency stop capabilities enabling immediate suspension of automated operations. Practical challenges included the feasibility of meaningful oversight as systems grew increasingly complex and autonomous, particularly in domains like large-scale neural networks where human understanding of decision logic proved limited, and the tension between oversight requirements and operational efficiency in high-volume decision environments.",
    "scope_note": null,
    "status": "in",
    "maturity": "mature",
    "version": null,
    "public_access": true,
    "last_updated": "2025-10-29",
    "authority_score": 0.95,
    "quality_score": null,
    "cross_domain_links": null,
    "owl_class": "aigo:HumanAgencyOversight",
    "owl_physicality": "VirtualEntity",
    "owl_role": "Process",
    "owl_inferred_class": "aigo:VirtualProcess",
    "is_subclass_of": [
      "AIGovernance"
    ],
    "has_part": [],
    "is_part_of": [],
    "requires": [],
    "depends_on": [],
    "enables": [],
    "relates_to": [],
    "bridges_to": [],
    "bridges_from": [],
    "domain_extensions": {},
    "belongs_to_domain": [
      "AIEthicsDomain"
    ],
    "implemented_in_layer": [
      "ConceptualLayer"
    ],
    "source": [
      "EU AI Act Article 14",
      "EU HLEG AI",
      "IEEE P7000"
    ],
    "validation": {
      "is_valid": false,
      "errors": [
        "owl:class namespace 'aigo' doesn't match source-domain 'ai'"
      ]
    }
  }
}