{
  "id": "HumanRobotInteraction",
  "title": "HumanRobotInteraction",
  "content": "- ### OntologyBlock\n  id:: humanrobotinteraction-ontology\n  collapsed:: true\n\t- ontology:: true\n\t- term-id:: MV-0041\n\t- preferred-term:: HumanRobotInteraction\n\t- status:: draft\n\t- public-access:: true\n\t- definition:: A component of the metaverse ecosystem.\n\t- maturity:: draft\n\t- owl:class:: rb:HumanRobotInteraction\n\t- owl:physicality:: ConceptualEntity\n\t- owl:role:: Concept\n\t- belongsToDomain:: [[RoboticsDomain]]\n\t- #### CrossDomainBridges\n\t  id:: humanrobotinteraction-bridges\n\t  collapsed:: true\n\t\t- dt:uses:: [[Machine Learning]]\n\t\t- dt:uses:: [[Large language models]]\n\t\t- dt:uses:: [[Computer Vision]]\n\n## OWL Formal Semantics\n\n```clojure\n;; OWL Functional Syntax\n\n(Declaration (Class :Humanrobotinteraction))\n\n;; Annotations\n(AnnotationAssertion rdfs:label :Humanrobotinteraction \"HumanRobotInteraction\"@en)\n(AnnotationAssertion rdfs:comment :Humanrobotinteraction \"A component of the metaverse ecosystem.\"@en)\n\n;; Data Properties\n(AnnotationAssertion dcterms:identifier :Humanrobotinteraction \"mv-1761742247935\"^^xsd:string)\n```\n\n- ## About HumanRobotInteraction\n\t- A component of the metaverse ecosystem.\n\t-\n\t- ### Original Content\n\t  collapsed:: true\n\t\t- ```\n- # Ontology Block\n\t\t    collapsed:: true\n\t\t    - **Class:** HumanRobotInteraction\n\t\t    - **IRI:** http://narrativegoldmine.com/robotics#HumanRobotInteraction\n\t\t    - **SubClassOf:** InteractionParadigm\n\t\t    - **Source Domain:** robotics\n\t\t    - **Source File:** robotics-ontology-unified.ttl\n\t\t    - **Integration Date:** 2025-10-28\n\t\t    - **TRL:** 6\n\t\t    - **Quality Score:** 0.89\n\t\t    - ```turtle\n\t\t      rb:HumanRobotInteraction rdf:type owl:Class ;\n\t\t          rdfs:label \"Human-Robot Interaction\"@en ;\n\t\t          rdfs:comment \"Study and design of interfaces and interaction modalities between humans and robots for safe, effective, and natural collaboration.\"@en ;\n\t\t          rdfs:subClassOf rb:InteractionParadigm ;\n\t\t          meta:sourceOntology \"rb:\" ;\n\t\t          meta:technologyDomain \"robotics\" ;\n\t\t          meta:disruptiveTechCategory \"autonomous-robotic-systems\" ;\n\t\t          meta:technologyReadinessLevel \"6\"^^xsd:integer ;\n\t\t          meta:qualityScore \"0.89\"^^xsd:float .\n\t\t      ```\n\t\t\n\t\t  - ## Description\n\t\t    - Facilitates natural interaction between humans and robots\n\t\t    - Includes voice, gesture, touch, and visual interfaces\n\t\t    - Ensures safety in shared workspaces\n\t\t    - Enables intuitive robot programming and control\n\t\t    - Supports collaborative task execution\n\t\t\n\t\t  - ## Properties\n\t\t    - Object properties\n\t\t      - [[usesModality]] - Interaction modalities (voice, gesture, etc.)\n\t\t      - [[ensuresSafety]] - Safety mechanisms and protocols\n\t\t      - [[enablesCollaboration]] - Collaborative task types\n\t\t      - [[providesInterface]] - User interface types\n\t\t    - Data properties\n\t\t      - safetyRating - Safety certification level\n\t\t      - intuitiveness Score - Ease of interaction\n\t\t      - responseTime - System response latency\n\t\t      - userSatisfaction - User satisfaction metric\n\t\t\n\t\t  - ## Cross-Domain Relationships\n\t\t    - [[dt:enhancedBy]] → [[NaturalLanguageProcessing]] - Voice commands\n\t\t    - [[dt:uses]] → [[GestureRecognition]] - Gesture-based control\n\t\t    - [[dt:trainedVia]] → [[MachineLearning]] - Learning user preferences\n\t\t    - [[dt:presentedIn]] → [[VirtualReality]] - VR-based robot control\n\t\t    - [[dt:securedBy]] → [[Authentication]] - User authentication\n\t\t\n\t\t  - ## Related Concepts\n\t\t    - [[CollaborativeRobot]]\n\t\t    - [[SafetyProtocol]]\n\t\t    - [[IntuitiveInterface]]\n\t\t    - [[SharedWorkspace]]\n\t\t    - [[TeachPendant]]\n\t\t\n\t\t  - ## Use Cases\n\t\t    - Collaborative manufacturing\n\t\t    - Service robots in public spaces\n\t\t    - Assistive robotics\n\t\t    - Telepresence robots\n\t\t    - Educational robots\n\t\t\n\t\t  ```\n\n\n## Metadata\n\n- **Last Updated**: 2025-11-16\n- **Review Status**: Automated remediation with 2025 context\n- **Verification**: Academic sources verified\n- **Regional Context**: UK/North England where applicable",
  "backlinks": [
    "TELE-200-robotic-telepresence",
    "robotics-core-concepts",
    "TELE-CONV-002-robotics-telepresence-bridge"
  ],
  "wiki_links": [
    "IntuitiveInterface",
    "dt:enhancedBy",
    "CollaborativeRobot",
    "Authentication",
    "Machine Learning",
    "dt:securedBy",
    "providesInterface",
    "dt:trainedVia",
    "SafetyProtocol",
    "Large language models",
    "SharedWorkspace",
    "TeachPendant",
    "Computer Vision",
    "enablesCollaboration",
    "GestureRecognition",
    "dt:presentedIn",
    "NaturalLanguageProcessing",
    "VirtualReality",
    "dt:uses",
    "MachineLearning",
    "usesModality",
    "ensuresSafety",
    "RoboticsDomain"
  ],
  "ontology": {
    "term_id": "MV-0041",
    "preferred_term": "HumanRobotInteraction",
    "alt_terms": [],
    "iri": "http://narrativegoldmine.com/robotics#HumanRobotInteraction",
    "source_domain": null,
    "domain": "mv",
    "domain_full_name": "Metaverse",
    "definition": "A component of the metaverse ecosystem.",
    "scope_note": null,
    "status": "draft",
    "maturity": "draft",
    "version": null,
    "public_access": true,
    "last_updated": null,
    "authority_score": null,
    "quality_score": null,
    "cross_domain_links": null,
    "owl_class": "rb:HumanRobotInteraction",
    "owl_physicality": "ConceptualEntity",
    "owl_role": "Concept",
    "owl_inferred_class": null,
    "is_subclass_of": [],
    "has_part": [],
    "is_part_of": [],
    "requires": [],
    "depends_on": [],
    "enables": [],
    "relates_to": [],
    "bridges_to": [],
    "bridges_from": [],
    "domain_extensions": {},
    "belongs_to_domain": [
      "RoboticsDomain"
    ],
    "implemented_in_layer": [],
    "source": [],
    "validation": {
      "is_valid": false,
      "errors": [
        "Missing required property: source-domain",
        "Missing required property: last-updated",
        "Missing required property: is-subclass-of (at least one parent class)",
        "owl:class namespace 'rb' doesn't match source-domain 'mv'"
      ]
    }
  }
}