{
  "id": "Identity Federation",
  "title": "Identity Federation",
  "content": "- ### OntologyBlock\n  id:: identity-federation-ontology\n  collapsed:: true\n\t- ontology:: true\n\t- term-id:: 20284\n\t- preferred-term:: Identity Federation\n\t- status:: draft\n\t- public-access:: true\n\t- definition:: A distributed authentication workflow that enables cross-domain identity linking through trust relationships, allowing users to access resources across multiple organizations using a single set of credentials.\n\t- source:: [[OASIS SAML]], [[OpenID Foundation]], [[NIST SP 800-63C]]\n\t- maturity:: mature\n\t- owl:class:: mv:IdentityFederation\n\t- owl:physicality:: VirtualEntity\n\t- owl:role:: Process\n\t- owl:inferred-class:: mv:VirtualProcess\n\t- owl:functional-syntax:: true\n\t- belongsToDomain:: [[TrustAndGovernanceDomain]]\n\t- implementedInLayer:: [[MiddlewareLayer]]\n\t- #### Relationships\n\t  id:: identity-federation-relationships\n\t  collapsed:: true\n\t\t- is-part-of:: [[Distributed Authentication Architecture]]\n\t\t- is-part-of:: [[Identity Management System]]\n\t\t- has-part:: [[Trust Establishment]]\n\t\t- has-part:: [[Attribute Exchange]]\n\t\t- has-part:: [[Session Propagation]]\n\t\t- has-part:: [[Credential Mapping]]\n\t\t- has-part:: [[Token Translation]]\n\t\t- has-part:: [[Policy Negotiation]]\n\t\t- requires:: [[Federation Protocol]]\n\t\t- requires:: [[Trust Framework]]\n\t\t- requires:: [[Metadata Exchange]]\n\t\t- requires:: [[Identity Provider (IdP)]]\n\t\t- enables:: [[Multi-Organization Access]]\n\t\t- enables:: [[B2B Collaboration]]\n\t\t- enables:: [[Decentralized Identity]]\n\t\t- enables:: [[Cross-Domain SSO]]\n\t\t- is-required-by:: [[Multiverse]]\n\t\t- is-enabled-by:: [[Identity Provider (IdP)]]\n\t\t- depends-on:: [[Federation Agreement]]\n\t\t- depends-on:: [[Attribute Schema]]\n\t\t- depends-on:: [[Security Token]]\n\t\t- depends-on:: [[PKI Infrastructure]]\n\n## Academic Context\n\n- Identity federation refers to a distributed authentication process enabling users to access resources across multiple organisations using a single set of credentials, based on trust relationships between domains.\n  - This concept is foundational in digital identity management, particularly in complex ecosystems like the metaverse where cross-platform interoperability is essential.\n  - Academic foundations include federated identity protocols such as SAML (Security Assertion Markup Language), OpenID Connect, and frameworks outlined by NIST SP 800-63C, which provide guidelines for digital identity proofing and federation.\n  - Recent scholarship emphasises the multidimensional nature of identity in virtual environments, highlighting principles such as equivalence to real-world identity behaviours and the dynamic evolution of identity through interactions in digital spaces[2][4].\n\n## Current Landscape (2025)\n\n- Identity federation is widely adopted in industry to enable seamless single sign-on (SSO) and cross-domain access, critical for both enterprise and emerging metaverse platforms.\n  - Major standards bodies such as OASIS (SAML), OpenID Foundation, and NIST continue to update protocols to address security, privacy, and interoperability challenges.\n  - In the metaverse context, identity federation supports user confidence and trust by enabling consistent identity representation across diverse virtual environments[1][3].\n  - Technical capabilities now include trust establishment, credential mapping, attribute exchange, policy negotiation, token translation, and session propagation as integral parts of the federation workflow.\n  - Limitations remain around privacy management, legal boundaries, and identity fragmentation, especially given the decentralised and multi-stakeholder nature of metaverse ecosystems[2][5].\n  - UK organisations, including those in North England, are increasingly involved in developing middleware solutions and trust frameworks that support identity federation in digital and virtual environments.\n\n## Research & Literature\n\n- Key academic sources include:\n  - \"Metaverse Identity: Core Principles and Critical Challenges\" (arXiv, 2024) which articulates guiding principles and challenges such as interoperability and privacy management[2].\n  - \"Framing Metaverse Identity: A Multidimensional Framework\" (Telecommunications Policy, 2025) proposing a comprehensive model for understanding identity in virtual spaces[4].\n  - World Economic Forumâ€™s report \"Metaverse Identity: Defining the Self in a Blended Reality\" (2024) emphasises inclusivity, accessibility, and security in identity frameworks[3].\n- Ongoing research focuses on:\n  - Developing standards for decentralised identity systems that maintain user control and privacy.\n  - Addressing ethical considerations and governance in identity data usage.\n  - Enhancing interoperability between federated identity providers and metaverse platforms[6][7].\n\n## UK Context\n\n- The UK has contributed to identity federation standards and implementations, with active participation in international bodies and local innovation hubs.\n  - North England hosts technology clusters focusing on cybersecurity and digital identity middleware, supporting federated identity solutions for both public and private sectors.\n  - Regional case studies include collaborative projects between universities and industry partners developing trust frameworks for cross-organisational access in virtual environments.\n  - UK policy discussions increasingly address digital identity governance, balancing innovation with privacy and security concerns in line with GDPR and emerging UK data protection regulations.\n\n## Future Directions\n\n- Emerging trends include:\n  - Greater integration of decentralised identifiers (DIDs) and verifiable credentials to enhance user sovereignty over identity data.\n  - Expansion of identity federation into new domains such as digital twins, avatars, and synthetic identities within the metaverse.\n  - Increased focus on ethical frameworks and digital rights management to prevent identity misuse and fragmentation.\n- Anticipated challenges:\n  - Balancing seamless user experience with robust security and privacy safeguards.\n  - Navigating legal and regulatory complexities across jurisdictions, including the UK.\n  - Ensuring inclusivity and accessibility in identity federation systems to avoid replicating real-world inequalities.\n- Research priorities:\n  - Developing adaptive, human-centred identity frameworks that accommodate evolving digital behaviours.\n  - Enhancing interoperability standards to support diverse federation protocols and metadata exchange.\n  - Investigating the socio-technical impacts of identity federation on trust and governance in virtual ecosystems.\n\n## References\n\n1. ITU-T Focus Group on Metaverse. (2024). A framework for confidence in the metaverse. ITU.\n2. Zhang, Y., et al. (2024). Metaverse Identity: Core Principles and Critical Challenges. arXiv. https://doi.org/10.48550/arXiv.2406.08029\n3. World Economic Forum. (2024). Metaverse Identity: Defining the Self in a Blended Reality. https://www3.weforum.org/docs/WEF_Metaverse_Identity_Defining_the_Self_in_a_Blended_Reality_2024.pdf\n4. Li, H., & Wang, J. (2025). Framing metaverse identity: A multidimensional framework for digital identity. Telecommunications Policy, 49(1), 102906. https://doi.org/10.1016/j.telpol.2025.102906\n5. Identity Management Institute. (2025). Managing Identity in Metaverse Virtual Worlds. https://identitymanagementinstitute.org/managing-identity-in-metaverse-virtual-worlds/\n6. Metaverse Standards Forum. (2025). Metaverse Universal Manifest Use Case. https://portal.metaverse-standards.org/document/dl/7843\n7. IEEE Standards Association. (2025). IEEE Standards for the Metaverse. https://standards.ieee.org/initiatives/metaverse-standards/\n\n## Metadata\n\n- Last Updated: 2025-11-11\n- Review Status: Comprehensive editorial review\n- Verification: Academic sources verified\n- Regional Context: UK/North England where applicable",
  "backlinks": [
    "Identity Provider (IdP)",
    "Multiverse"
  ],
  "wiki_links": [
    "OpenID Foundation",
    "Session Propagation",
    "MiddlewareLayer",
    "Multiverse",
    "Identity Provider (IdP)",
    "PKI Infrastructure",
    "Credential Mapping",
    "B2B Collaboration",
    "Metadata Exchange",
    "Attribute Exchange",
    "Token Translation",
    "Trust Framework",
    "NIST SP 800-63C",
    "Federation Protocol",
    "Cross-Domain SSO",
    "Multi-Organization Access",
    "Decentralized Identity",
    "Attribute Schema",
    "Security Token",
    "TrustAndGovernanceDomain",
    "Identity Management System",
    "Federation Agreement",
    "Distributed Authentication Architecture",
    "OASIS SAML",
    "Policy Negotiation",
    "Trust Establishment"
  ],
  "ontology": {
    "term_id": "20284",
    "preferred_term": "Identity Federation",
    "alt_terms": [],
    "iri": "http://narrativegoldmine.com/metaverse#IdentityFederation",
    "source_domain": null,
    "domain": "mv",
    "domain_full_name": "Metaverse",
    "definition": "A distributed authentication workflow that enables cross-domain identity linking through trust relationships, allowing users to access resources across multiple organizations using a single set of credentials.",
    "scope_note": null,
    "status": "draft",
    "maturity": "mature",
    "version": null,
    "public_access": true,
    "last_updated": null,
    "authority_score": null,
    "quality_score": null,
    "cross_domain_links": null,
    "owl_class": "mv:IdentityFederation",
    "owl_physicality": "VirtualEntity",
    "owl_role": "Process",
    "owl_inferred_class": "mv:VirtualProcess",
    "is_subclass_of": [],
    "has_part": [
      "Trust Establishment",
      "Attribute Exchange",
      "Session Propagation",
      "Credential Mapping",
      "Token Translation",
      "Policy Negotiation"
    ],
    "is_part_of": [
      "Distributed Authentication Architecture",
      "Identity Management System"
    ],
    "requires": [
      "Federation Protocol",
      "Trust Framework",
      "Metadata Exchange",
      "Identity Provider (IdP)"
    ],
    "depends_on": [
      "Federation Agreement",
      "Attribute Schema",
      "Security Token",
      "PKI Infrastructure"
    ],
    "enables": [
      "Multi-Organization Access",
      "B2B Collaboration",
      "Decentralized Identity",
      "Cross-Domain SSO"
    ],
    "relates_to": [],
    "bridges_to": [],
    "bridges_from": [],
    "domain_extensions": {},
    "belongs_to_domain": [
      "TrustAndGovernanceDomain"
    ],
    "implemented_in_layer": [
      "MiddlewareLayer"
    ],
    "source": [
      "OASIS SAML",
      "OpenID Foundation",
      "NIST SP 800-63C"
    ],
    "other_relationships": {
      "is-required-by": [
        "Multiverse"
      ],
      "is-enabled-by": [
        "Identity Provider (IdP)"
      ]
    },
    "validation": {
      "is_valid": false,
      "errors": [
        "Missing required property: source-domain",
        "Missing required property: last-updated",
        "Missing required property: is-subclass-of (at least one parent class)",
        "term-id '20284' doesn't match domain 'mv' (expected MV-)"
      ]
    }
  }
}