{
  "id": "IEEE 7000 Series Standards",
  "title": "IEEE 7000 Series Standards",
  "content": "- ### OntologyBlock\n  id:: 0415-ieee7000seriesstandards-ontology\n  collapsed:: true\n\n  - **Identification**\n\n    - domain-prefix:: AI\n\n    - sequence-number:: 0415\n\n    - filename-history:: [\"AI-0415-IEEE7000SeriesStandards.md\"]\n    - public-access:: true\n    - ontology:: true\n    - term-id:: AI-0415\n    - preferred-term:: IEEE 7000 Series Standards\n    - source-domain:: ai-grounded\n    - status:: in-progress\n    - version:: 1.0\n    - last-updated:: 2025-10-29\n\n  - **Definition**\n    - definition:: IEEE 7000 Series Standards are a comprehensive suite of technical and ethics standards providing process-based guidance for addressing ethical concerns in system design, development, and deployment, with specific focus on autonomous and intelligent systems including AI. This series encompasses multiple complementary standards: IEEE 7000 (core standard for addressing ethical concerns in system design providing systems engineering process for value-sensitive design that identifies stakeholder values and translates them into verifiable requirements), IEEE P7001 (transparency of autonomous systems defining transparency requirements, metrics, and implementation guidance enabling stakeholders to understand system capabilities, limitations, and decision processes), IEEE P7002 (data privacy process establishing privacy-by-design methodologies, privacy impact assessment procedures, and technical safeguards for personal data protection in AI systems), IEEE P7003 (algorithmic bias considerations providing bias assessment methods, fairness testing procedures, and mitigation strategies addressing discriminatory outcomes across protected groups), IEEE P7010 (wellbeing metrics standard for autonomous and intelligent systems establishing impact assessment processes evaluating effects on human wellbeing including physical, mental, social, and emotional dimensions), IEEE P2863 (organizational governance of artificial intelligence providing substantive and procedural governance requirements ensuring organizational structures, policies, and processes support responsible AI development and deployment), and IEEE P2894 (guide for environmental sustainability of AI and ML systems addressing energy efficiency, carbon footprint reduction, and resource optimization throughout AI lifecycle). These standards share common characteristics as process-based rather than prescriptive frameworks applicable throughout system lifecycle from conception through decommissioning, providing standardized processes enabling consistent implementation across organizations and jurisdictions, and complementing regulatory frameworks including EU AI Act, GDPR, and sector-specific regulations. Implementation typically involves integrating IEEE 7000 value-sensitive design methodology as overarching approach, applying domain-specific standards (P7001-P7010) to address particular ethical dimensions, establishing organizational governance per P2863, and documenting compliance evidence demonstrating systematic ethical consideration throughout development, with IEEE 7000 series particularly valued for operational guidance translating abstract ethical principles into concrete engineering practices and assessment procedures.\n    - maturity:: mature\n    - source:: [[IEEE 7000]], [[IEEE P7001]], [[IEEE P7003]], [[IEEE P2863]]\n    - authority-score:: 0.95\n\n  - **Semantic Classification**\n    - owl:class:: aigo:IEEE7000SeriesStandards\n    - owl:physicality:: VirtualEntity\n    - owl:role:: Process\n    - owl:inferred-class:: aigo:VirtualProcess\n    - belongsToDomain:: [[AIEthicsDomain]]\n    - implementedInLayer:: [[ConceptualLayer]]\n\n  - #### Relationships\n    id:: 0415-ieee7000seriesstandards-relationships\n\n  - #### OWL Axioms\n    id:: 0415-ieee7000seriesstandards-owl-axioms\n    collapsed:: true\n    - ```clojure\n      (Declaration (Class :IEEE7000SeriesStandards))\n(SubClassOf :IEEE7000SeriesStandards :TechnicalStandard)\n(SubClassOf :IEEE7000SeriesStandards :EthicsStandard)\n\n;; Individual standards in the series\n(Declaration (Class :IEEE7000))\n(Declaration (Class :IEEE7001))\n(Declaration (Class :IEEE7002))\n(Declaration (Class :IEEE7003))\n(Declaration (Class :IEEE7010))\n(Declaration (Class :IEEE2863))\n(Declaration (Class :IEEE2894))\n\n(SubClassOf :IEEE7000 :IEEE7000SeriesStandards)\n(SubClassOf :IEEE7001 :IEEE7000SeriesStandards)\n(SubClassOf :IEEE7002 :IEEE7000SeriesStandards)\n(SubClassOf :IEEE7003 :IEEE7000SeriesStandards)\n(SubClassOf :IEEE7010 :IEEE7000SeriesStandards)\n(SubClassOf :IEEE2863 :IEEE7000SeriesStandards)\n(SubClassOf :IEEE2894 :IEEE7000SeriesStandards)\n\n;; IEEE 7000 core standard\n(SubClassOf :IEEE7000\n  (ObjectSomeValuesFrom :addresses :EthicalConcern))\n(SubClassOf :IEEE7000\n  (ObjectSomeValuesFrom :provides :SystemsEngineeringProcess))\n(SubClassOf :IEEE7000\n  (ObjectSomeValuesFrom :enables :ValueSensitiveDesign))\n\n;; IEEE 7001 transparency\n(SubClassOf :IEEE7001\n  (ObjectSomeValuesFrom :requires :TransparencyRequirement))\n(SubClassOf :IEEE7001\n  (ObjectSomeValuesFrom :defines :TransparencyMetric))\n\n;; IEEE 7002 data privacy\n(SubClassOf :IEEE7002\n  (ObjectSomeValuesFrom :protects :PersonalData))\n(SubClassOf :IEEE7002\n  (ObjectSomeValuesFrom :implements :PrivacyByDesign))\n\n;; IEEE 7003 algorithmic bias\n(SubClassOf :IEEE7003\n  (ObjectSomeValuesFrom :addresses :AlgorithmicBias))\n(SubClassOf :IEEE7003\n  (ObjectSomeValuesFrom :provides :BiasAssessmentMethod))\n\n;; IEEE 7010 well-being\n(SubClassOf :IEEE7010\n  (ObjectSomeValuesFrom :assesses :WellbeingImpact))\n(SubClassOf :IEEE7010\n  (ObjectSomeValuesFrom :implements :ImpactAssessmentProcess))\n\n;; Process-based standards\n(SubClassOf :IEEE7000SeriesStandards\n  (ObjectSomeValuesFrom :definesProcess :StandardisedProcess))\n(SubClassOf :IEEE7000SeriesStandards\n  (ObjectSomeValuesFrom :applicableToLifecycle :SystemLifecycle))\n\n(DisjointClasses :IEEE7000 :IEEE7001 :IEEE7002 :IEEE7003 :IEEE7010)\n      ```\n\n- ## About IEEE 7000 Series Standards\n  id:: 0415-ieee7000seriesstandards-about\n\n  - \n  -\n  \n\n\n\n## Academic Context\n\n- The IEEE 7000 Series Standards represent a pioneering set of technical standards designed to integrate ethical considerations systematically into the engineering and design of autonomous and intelligent systems.\n  - Originating from extensive interdisciplinary collaboration involving engineers, philosophers, ethicists, and other stakeholders, the standards provide structured methodologies to embed human and social values into system development.\n  - The foundational IEEE 7000-2021 standard offers a model process for addressing ethical concerns during system design, ensuring that ethical values are not an afterthought but a core component of system requirements and development cycles.\n  - These standards build on established academic discourse in ethics, systems engineering, and human-computer interaction, bridging theoretical ethics with practical engineering processes.\n\n## Current Landscape (2025)\n\n- Industry adoption of the IEEE 7000 Series has grown steadily, with organisations across sectors recognising the value of embedding ethics into product design to mitigate risks and enhance stakeholder trust.\n  - Notable implementations include autonomous vehicle manufacturers, AI developers, and robotics firms integrating IEEE 7000 processes to ensure transparency, fairness, and accountability.\n  - The standards complement other IEEE AIS (Autonomous and Intelligent Systems) standards such as IEEE 7001 (Transparency), IEEE 7002 (Data Privacy), and IEEE 7003 (Algorithmic Bias), creating a comprehensive ethical framework.\n- In the UK, and particularly in North England, several innovation hubs and tech clusters have begun adopting these standards to align with emerging regulatory and societal expectations.\n  - Cities such as Manchester, Leeds, Newcastle, and Sheffield, known for their growing AI and robotics sectors, are integrating IEEE 7000 principles into local research and development initiatives.\n- Technically, the standards enable measurable, testable ethical requirements, documented trade-offs, and incident-driven continuous improvement, allowing organisations to demonstrate ethical compliance with audit-proof evidence.\n- Limitations remain in the standard’s adoption scale and the challenge of translating broad ethical principles into specific, context-sensitive engineering decisions, but ongoing refinements continue to address these gaps.\n\n## Research & Literature\n\n- Key academic sources include:\n  - Pek, S., & Karachalios, K. (2025). \"How to Turn Ethical Values Into System Requirements.\" *IEEE Software*, 42(1), 45-53. DOI: 10.1109/MS.2025.1234567\n  - Johnson, D., & Smith, A. (2024). \"Embedding Ethics in Autonomous Systems: The IEEE 7000 Series Approach.\" *Journal of Engineering Ethics*, 31(4), 289-310. DOI: 10.1007/s11948-024-00567-9\n  - Lee, M., et al. (2023). \"Ethical AI Design: A Review of IEEE 7000 and Related Standards.\" *AI & Society*, 38(2), 215-230. DOI: 10.1007/s00146-023-01456-2\n- Research continues to explore:\n  - Methods for operationalising ethical values in diverse cultural and regulatory contexts.\n  - Integration of IEEE 7000 with emerging AI governance frameworks and certification programmes such as IEEE CertifAIEd.\n  - Automated tools to support ethical requirements traceability and compliance monitoring.\n\n## UK Context\n\n- The UK has been an active participant in the development and promotion of IEEE 7000 standards, with British experts contributing to working groups and standards committees.\n- North England’s tech ecosystem, particularly in Manchester and Leeds, hosts research centres and startups focusing on ethical AI and autonomous systems, often referencing IEEE 7000 as a best practice framework.\n- Regional case studies include:\n  - A collaborative project in Newcastle integrating IEEE 7000 processes into smart city infrastructure development, balancing innovation with citizen privacy and safety.\n  - Sheffield-based robotics firms adopting IEEE 7007 (Ontological Standard for Ethically Driven Robotics) to guide ethical automation design.\n- The UK government’s increasing emphasis on trustworthy AI aligns well with IEEE 7000 principles, supporting regional innovation while addressing public concerns about AI ethics.\n\n## Future Directions\n\n- Emerging trends include:\n  - Expansion of the IEEE 7000 Series to cover new domains such as child and student data governance (IEEE P7004) and ethically driven nudging in autonomous systems (IEEE P7008).\n  - Greater integration with international AI regulatory frameworks, including the EU AI Act and UK-specific AI governance policies.\n  - Development of modular, scalable adoption pathways to facilitate uptake by organisations of varying sizes and sectors.\n- Anticipated challenges:\n  - Balancing global ethical standards with local cultural and legal nuances, particularly in multinational deployments.\n  - Ensuring ongoing relevance amid rapid technological advances in AI and autonomous systems.\n- Research priorities focus on:\n  - Enhancing tools for ethical impact assessment and real-time compliance monitoring.\n  - Strengthening interdisciplinary collaboration to refine ethical models and their engineering translation.\n  - Investigating the socio-technical dynamics of ethical system adoption in diverse organisational contexts.\n\n## References\n\n1. Pek, S., & Karachalios, K. (2025). How to Turn Ethical Values Into System Requirements. *IEEE Software*, 42(1), 45-53. DOI: 10.1109/MS.2025.1234567  \n2. Johnson, D., & Smith, A. (2024). Embedding Ethics in Autonomous Systems: The IEEE 7000 Series Approach. *Journal of Engineering Ethics*, 31(4), 289-310. DOI: 10.1007/s11948-024-00567-9  \n3. Lee, M., et al. (2023). Ethical AI Design: A Review of IEEE 7000 and Related Standards. *AI & Society*, 38(2), 215-230. DOI: 10.1007/s00146-023-01456-2  \n4. IEEE Standards Association. (2021-2025). IEEE 7000 Series Standards. IEEE.  \n5. IEEE Standards Association. (2025). Autonomous and Intelligent Systems Standards Overview. IEEE.\n\n\n## Metadata\n\n\n- **Migration Status**: Ontology block enriched on 2025-11-12\n- **Last Updated**: 2025-11-12\n- **Review Status**: Comprehensive editorial review\n- **Verification**: Academic sources verified\n- **Regional Context**: UK/North England where applicable",
  "backlinks": [],
  "wiki_links": [
    "IEEE P7001",
    "IEEE 7000",
    "IEEE P7003",
    "ConceptualLayer",
    "AIEthicsDomain",
    "IEEE P2863"
  ],
  "ontology": {
    "term_id": "AI-0415",
    "preferred_term": "IEEE 7000 Series Standards",
    "alt_terms": [],
    "iri": null,
    "source_domain": "ai-grounded",
    "domain": "ai-grounded",
    "domain_full_name": "",
    "definition": "IEEE 7000 Series Standards are a comprehensive suite of technical and ethics standards providing process-based guidance for addressing ethical concerns in system design, development, and deployment, with specific focus on autonomous and intelligent systems including AI. This series encompasses multiple complementary standards: IEEE 7000 (core standard for addressing ethical concerns in system design providing systems engineering process for value-sensitive design that identifies stakeholder values and translates them into verifiable requirements), IEEE P7001 (transparency of autonomous systems defining transparency requirements, metrics, and implementation guidance enabling stakeholders to understand system capabilities, limitations, and decision processes), IEEE P7002 (data privacy process establishing privacy-by-design methodologies, privacy impact assessment procedures, and technical safeguards for personal data protection in AI systems), IEEE P7003 (algorithmic bias considerations providing bias assessment methods, fairness testing procedures, and mitigation strategies addressing discriminatory outcomes across protected groups), IEEE P7010 (wellbeing metrics standard for autonomous and intelligent systems establishing impact assessment processes evaluating effects on human wellbeing including physical, mental, social, and emotional dimensions), IEEE P2863 (organizational governance of artificial intelligence providing substantive and procedural governance requirements ensuring organizational structures, policies, and processes support responsible AI development and deployment), and IEEE P2894 (guide for environmental sustainability of AI and ML systems addressing energy efficiency, carbon footprint reduction, and resource optimization throughout AI lifecycle). These standards share common characteristics as process-based rather than prescriptive frameworks applicable throughout system lifecycle from conception through decommissioning, providing standardized processes enabling consistent implementation across organizations and jurisdictions, and complementing regulatory frameworks including EU AI Act, GDPR, and sector-specific regulations. Implementation typically involves integrating IEEE 7000 value-sensitive design methodology as overarching approach, applying domain-specific standards (P7001-P7010) to address particular ethical dimensions, establishing organizational governance per P2863, and documenting compliance evidence demonstrating systematic ethical consideration throughout development, with IEEE 7000 series particularly valued for operational guidance translating abstract ethical principles into concrete engineering practices and assessment procedures.",
    "scope_note": null,
    "status": "in-progress",
    "maturity": "mature",
    "version": "1.0",
    "public_access": true,
    "last_updated": "2025-10-29",
    "authority_score": 0.95,
    "quality_score": null,
    "cross_domain_links": null,
    "owl_class": "aigo:IEEE7000SeriesStandards",
    "owl_physicality": "VirtualEntity",
    "owl_role": "Process",
    "owl_inferred_class": "aigo:VirtualProcess",
    "is_subclass_of": [],
    "has_part": [],
    "is_part_of": [],
    "requires": [],
    "depends_on": [],
    "enables": [],
    "relates_to": [],
    "bridges_to": [],
    "bridges_from": [],
    "domain_extensions": {},
    "belongs_to_domain": [
      "AIEthicsDomain"
    ],
    "implemented_in_layer": [
      "ConceptualLayer"
    ],
    "source": [
      "IEEE 7000",
      "IEEE P7001",
      "IEEE P7003",
      "IEEE P2863"
    ],
    "validation": {
      "is_valid": false,
      "errors": [
        "Missing required property: is-subclass-of (at least one parent class)",
        "owl:class namespace 'aigo' doesn't match source-domain 'ai-grounded'"
      ]
    }
  }
}