{
  "id": "Infrastructure Layer",
  "title": "Infrastructure Layer",
  "content": "- ### OntologyBlock\n  id:: infrastructure-layer-ontology\n  collapsed:: true\n\t- ontology:: true\n\t- term-id:: 20169\n\t- preferred-term:: Infrastructure Layer\n\t- status:: draft\n\t- public-access:: true\n\t- definition:: Foundational base layer providing computing, storage, and network capabilities that enable metaverse applications and services to operate at scale.\n\t- source:: [[MSF Taxonomy 2025]]\n\t- maturity:: mature\n\t- owl:class:: mv:InfrastructureLayer\n\t- owl:physicality:: VirtualEntity\n\t- owl:role:: Object\n\t- owl:inferred-class:: mv:VirtualObject\n\t- owl:functional-syntax:: true\n\t- belongsToDomain:: [[InfrastructureDomain]]\n\t- implementedInLayer:: [[Physical Layer]]\n\t- #### Relationships\n\t  id:: infrastructure-layer-relationships\n\t  collapsed:: true\n\t\t- is-part-of:: [[InfrastructureDomain]]\n\t\t- has-part:: [[Edge Computing]]\n\t\t- has-part:: [[Cloud Computing]]\n\t\t- has-part:: [[Spatial Computing Layer]]\n\t\t- has-part:: [[Data Centers]]\n\t\t- has-part:: [[CDN]]\n\t\t- has-part:: [[Storage Layer]]\n\t\t- has-part:: [[5G Network]]\n\t\t- has-part:: [[Hardware Abstraction Layer (HAL)]]\n\t\t- requires:: [[Power Systems]]\n\t\t- requires:: [[Physical Hardware]]\n\t\t- requires:: [[Network Infrastructure]]\n\t\t- enables:: [[Low Latency]]\n\t\t- enables:: [[Scalability]]\n\t\t- enables:: [[High Availability]]\n\t\t- enables:: [[Distributed Computing]]\n\n## Academic Context\n\n- The Infrastructure Layer represents the foundational technological substrate enabling metaverse functionality and scalability[1][2]\n  - Comprises interconnected systems spanning computing, storage, networking, and security domains\n  - Conceptualised within Jon Radoff's seven-layer metaverse framework as the base upon which all higher-order capabilities depend[2]\n  - Distinguished from application layers by its focus on enabling technologies rather than user-facing experiences\n\n- Core architectural principle: abstraction of complexity\n  - Physical hardware and network topology hidden from end-users through standardised APIs and service interfaces\n  - Enables seamless content delivery across heterogeneous devices and geographic locations[1]\n\n## Current Landscape (2025)\n\n- Computing and processing infrastructure\n  - Data centres and server farms optimised for high-performance computing, consuming 20-45 kW per rack versus 5-10 kW for traditional computing[6]\n  - GPU acceleration critical for rendering, AI model inference, and real-time spatial computation[2][3]\n  - Edge computing increasingly distributed to consumer devices, reducing latency and centralised processing bottlenecks[2]\n  - Cloud platforms (AWS, Google Cloud Platform) providing elastic autoscaling for variable user loads[4]\n\n- Network connectivity\n  - 5G networks dramatically improving bandwidth and reducing latency for responsive real-time interactions[2]\n  - 6G infrastructure in development phases, anticipated to further enhance connectivity capabilities[3]\n  - Content Delivery Networks (CDNs) and load balancers distributing content geographically for optimised user experience[4]\n  - InterPlanetary File System (IPFS) enabling decentralised content hosting without centralised server dependency[2]\n\n- Storage and data management\n  - Distributed storage systems supporting persistent digital twins—digital replicas of physical objects and locations fed by real-world data[5]\n  - Blockchain-based storage for immutable asset ownership records and transaction histories[5]\n  - Redundant power systems and failover mechanisms ensuring service continuity[6]\n\n- Security and authentication infrastructure\n  - Encryption protocols protecting user data and privacy across distributed systems[1]\n  - Access control mechanisms and cybersecurity protocols establishing trusted environments[1]\n  - Smart contract auditing and regulatory alignment for blockchain-based asset management[4]\n\n- Energy infrastructure challenges\n  - Advanced cooling systems consuming 30-40% of data centre energy budgets[6]\n  - Projected carbon footprint of 77-125 million metric tonnes CO₂ annually by 2030 if powered by fossil fuels[6]\n  - Renewable energy integration emerging as critical sustainability requirement for scalable deployment[6]\n\n- Standards and frameworks\n  - Service-oriented architecture patterns using Kubernetes and Docker containerisation[4]\n  - ERC-721/ERC-1155 standards for non-fungible token implementation[4]\n  - ERC-20 token standards for in-platform economies and governance mechanisms[4]\n\n## Research & Literature\n\n- Foundational frameworks\n  - Radoff, J. (2021). The Metaverse Value-Chain. *Convergence*. Establishes the seven-layer taxonomy widely adopted across industry and academia[2]\n  - IEEE Metaverse Reality publications documenting infrastructure component integration and persistent digital twin concepts[5]\n\n- Technical infrastructure studies\n  - Emerging research on edge computing distribution and latency optimisation for immersive experiences\n  - Studies examining blockchain scalability constraints for high-concurrency metaverse transactions\n  - Research into AI-driven infrastructure optimisation and predictive resource allocation\n\n- Energy and sustainability research\n  - 8M Solar (2025). Analysis of renewable energy requirements for metaverse infrastructure sustainability[6]\n  - Ongoing research into carbon-neutral data centre operations and grid integration challenges\n\n## UK Context\n\n- British technology contributions\n  - UK-based cloud infrastructure providers and CDN operators supporting metaverse platforms\n  - Research institutions (Imperial College London, University of Manchester) investigating distributed computing architectures and edge computing optimisation\n\n- North England innovation considerations\n  - Manchester's emerging position in digital infrastructure research, particularly around edge computing and distributed systems\n  - Potential for regional data centre development supporting latency-sensitive metaverse applications\n  - Limited but growing involvement in blockchain infrastructure standardisation efforts\n\n- Regulatory environment\n  - UK regulatory framework increasingly addressing data sovereignty and cybersecurity requirements for metaverse infrastructure\n  - Financial Conduct Authority guidance on smart contract compliance and token-based economies\n\n## Future Directions\n\n- Emerging technological trajectories\n  - Neural interfaces and biosensors advancing human-computer interaction beyond current VR/AR headsets[2]\n  - Microelectromechanical systems (MEMS) enabling contact lens-based computing and sensing[3]\n  - 6G networks anticipated to provide unprecedented bandwidth and ultra-low latency capabilities\n\n- Anticipated infrastructure challenges\n  - Scalability bottlenecks as concurrent user populations approach millions\n  - Energy consumption sustainability requiring renewable energy integration at scale[6]\n  - Interoperability standards development across competing metaverse platforms and proprietary systems\n  - Latency reduction requirements for photorealistic real-time rendering and haptic feedback\n\n- Research priorities\n  - Decentralised infrastructure models reducing dependency on centralised data centre operators\n  - AI-driven infrastructure optimisation and predictive resource allocation\n  - Quantum computing applications for cryptographic security and complex spatial computations\n  - Sustainable infrastructure design minimising environmental impact whilst maintaining performance\n\n## Metadata\n\n- Last Updated: 2025-11-11\n- Review Status: Comprehensive editorial review completed\n- Verification: Current academic and industry sources verified as of November 2025\n- Regional Context: UK and North England context integrated where substantively relevant\n- Format: Logseq nested bullet structure with academic precision and cordial tone",
  "backlinks": [
    "Spatial Computing Layer",
    "Hardware Abstraction Layer (HAL)",
    "Network Infrastructure",
    "Storage Layer"
  ],
  "wiki_links": [
    "Low Latency",
    "InfrastructureDomain",
    "Physical Layer",
    "5G Network",
    "Network Infrastructure",
    "Power Systems",
    "Edge Computing",
    "MSF Taxonomy 2025",
    "Scalability",
    "Storage Layer",
    "Hardware Abstraction Layer (HAL)",
    "Physical Hardware",
    "CDN",
    "High Availability",
    "Cloud Computing",
    "Distributed Computing",
    "Data Centers",
    "Spatial Computing Layer"
  ],
  "ontology": {
    "term_id": "20169",
    "preferred_term": "Infrastructure Layer",
    "alt_terms": [],
    "iri": "http://narrativegoldmine.com/metaverse#InfrastructureLayer",
    "source_domain": null,
    "domain": "mv",
    "domain_full_name": "Metaverse",
    "definition": "Foundational base layer providing computing, storage, and network capabilities that enable metaverse applications and services to operate at scale.",
    "scope_note": null,
    "status": "draft",
    "maturity": "mature",
    "version": null,
    "public_access": true,
    "last_updated": null,
    "authority_score": null,
    "quality_score": null,
    "cross_domain_links": null,
    "owl_class": "mv:InfrastructureLayer",
    "owl_physicality": "VirtualEntity",
    "owl_role": "Object",
    "owl_inferred_class": "mv:VirtualObject",
    "is_subclass_of": [],
    "has_part": [
      "Edge Computing",
      "Cloud Computing",
      "Spatial Computing Layer",
      "Data Centers",
      "CDN",
      "Storage Layer",
      "5G Network",
      "Hardware Abstraction Layer (HAL)"
    ],
    "is_part_of": [
      "InfrastructureDomain"
    ],
    "requires": [
      "Power Systems",
      "Physical Hardware",
      "Network Infrastructure"
    ],
    "depends_on": [],
    "enables": [
      "Low Latency",
      "Scalability",
      "High Availability",
      "Distributed Computing"
    ],
    "relates_to": [],
    "bridges_to": [],
    "bridges_from": [],
    "domain_extensions": {},
    "belongs_to_domain": [
      "InfrastructureDomain"
    ],
    "implemented_in_layer": [
      "Physical Layer"
    ],
    "source": [
      "MSF Taxonomy 2025"
    ],
    "validation": {
      "is_valid": false,
      "errors": [
        "Missing required property: source-domain",
        "Missing required property: last-updated",
        "Missing required property: is-subclass-of (at least one parent class)",
        "term-id '20169' doesn't match domain 'mv' (expected MV-)"
      ]
    }
  }
}