{
  "id": "Interoperability Framework",
  "title": "Interoperability Framework",
  "content": "- ### OntologyBlock\n  id:: interoperability-framework-ontology\n  collapsed:: true\n\t- ontology:: true\n\t- term-id:: 20184\n\t- preferred-term:: Interoperability Framework\n\t- status:: draft\n\t- public-access:: true\n\t- definition:: Coordinated set of standards and specifications enabling interaction between heterogeneous systems in metaverse environments.\n\t- source:: [[ETSI GR ARF 010]], [[MSF]]\n\t- maturity:: mature\n\t- owl:class:: mv:InteroperabilityFramework\n\t- owl:physicality:: VirtualEntity\n\t- owl:role:: Object\n\t- owl:inferred-class:: mv:VirtualObject\n\t- owl:functional-syntax:: true\n\t- belongsToDomain:: [[InfrastructureDomain]]\n\t- implementedInLayer:: [[DataLayer]]\n\t- #### Relationships\n\t  id:: interoperability-framework-relationships\n\t  collapsed:: true\n\t\t- is-part-of:: [[Metaverse Architecture]]\n\t\t- has-part:: [[Technical Standards]]\n\t\t- has-part:: [[Protocol Definitions]]\n\t\t- has-part:: [[Data Integration Interface]]\n\t\t- has-part:: [[Metadata Standard]]\n\t\t- has-part:: [[API Specifications]]\n\t\t- has-part:: [[Universal Manifest]]\n\t\t- has-part:: [[Data Formats]]\n\t\t- requires:: [[Standardization Bodies]]\n\t\t- requires:: [[Technical Documentation]]\n\t\t- enables:: [[System Interoperability]]\n\t\t- enables:: [[Cross-Platform Integration]]\n\t\t- enables:: [[Scalable Architecture]]\n\t\t- is-dependency-of:: [[Compatibility Process]]\n\n## Academic Context\n\n- Metaverse interoperability represents a fundamental architectural requirement rather than an optional enhancement\n  - Defined as the capability of disparate virtual environments, systems, and platforms to function together seamlessly\n  - Encompasses the portability of digital assets, user identities, and experiences across multiple metaverse ecosystems\n  - Distinguishes between isolated virtual worlds and a genuinely interconnected digital infrastructure\n  - Conceptually analogous to the open web's standardised protocols, though substantially more complex given the immersive, real-time nature of metaverse interactions\n\n## Current Landscape (2025)\n\n- Industry adoption and standardisation efforts\n  - The Metaverse Standards Forum operates as an independent non-profit consortium, fostering interoperability standards across multiple technical domains\n  - Active working groups address critical layers: 3D asset interoperability (USD and glTF formats), avatar and character portability, digital asset management, privacy and cybersecurity, and network requirements\n  - Exploratory groups investigating decentralised Web3 services and XR device interoperability indicate emerging technical frontiers\n  - Blockchain-based standards (ERC-721, ERC-1155) provide foundational frameworks for digital ownership recognition across platforms, though broader adoption remains nascent\n\n- Technical capabilities and current limitations\n  - Identity layer: Decentralised Identifiers (DIDs) and blockchain-based authentication enable persistent digital identities, yet full cross-platform recognition remains incomplete\n  - Digital assets: NFT standards facilitate ownership transfer, but usage rights, visual consistency, and functional compatibility across heterogeneous environments present ongoing challenges\n  - Communication protocols: WebRTC and similar open standards support voice and text interactions, though real-time avatar synchronisation and gesture recognition across platforms remain technically demanding\n  - 3D content portability: glTF and USD formats advance consistency, but rendering variations and platform-specific optimisations create practical friction\n  - Economic systems: Cross-chain bridges and compatible digital currencies are developing, though transaction latency and regulatory fragmentation complicate seamless commerce\n  - Governance: Interoperable moderation, access control, and content rights frameworks remain in early developmental stages—a notable gap given safety and fairness imperatives\n\n- Standards and frameworks\n  - ITU-T Recommendation Y.4812 (March 2025) addresses identity interoperability for IoT devices across metaverse platforms, specifying technical features for identity transfer and authentication across heterogeneous systems\n  - European Commission's Digital Markets Act signals regulatory intent to mandate interoperability, establishing precedent for anticipatory governance in digital infrastructure\n  - The Metaverse Standards Register catalogues emerging technical specifications, though comprehensive standardisation remains incomplete\n\n## UK Context\n\n- British institutional engagement\n  - The Metaverse Standards Forum includes participation from UK-based technology organisations and research institutions, though specific regional contributions remain underreported in current literature\n  - UK regulatory frameworks, particularly the Online Safety Bill and emerging digital infrastructure standards, intersect with metaverse interoperability requirements, though explicit policy guidance remains limited\n\n- North England innovation considerations\n  - Manchester, Leeds, and Newcastle host significant digital technology clusters and research centres with potential relevance to metaverse development, though dedicated interoperability research initiatives are not prominently documented in current sources\n  - The region's established strengths in gaming, digital media, and software development position it favourably for future metaverse infrastructure contributions, should strategic investment materialise\n\n## Future Directions\n\n- Emerging technical priorities\n  - Real-time synchronisation of avatars and environmental states across heterogeneous platforms remains a critical unsolved challenge\n  - Interoperable governance frameworks must evolve to balance user safety, content moderation, and platform autonomy—a tension unlikely to resolve without regulatory clarity\n  - Privacy-preserving identity systems that enable cross-platform functionality whilst protecting user data represent a significant research frontier\n\n- Anticipated challenges\n  - Regulatory fragmentation: Different jurisdictions may impose conflicting interoperability requirements, creating compliance complexity\n  - Commercial incentives: Platform operators may resist standardisation that diminishes competitive differentiation or user lock-in\n  - Technical debt: Legacy systems and proprietary architectures complicate retrofit interoperability\n  - The balance between frictionless user experience and robust safeguards remains philosophically and technically contested\n\n- Research priorities\n  - Decentralised identity systems that function reliably at scale\n  - Standardised protocols for real-time synchronisation across geographically distributed systems\n  - Governance models that distribute authority without compromising security or user protection\n  - Economic mechanisms that enable fair value exchange across interoperable platforms\n\n## References\n\n- Metaverse Standards Forum. (2025). *Building an Open Metaverse: Interoperability Standards and Working Groups*. Retrieved from metaverse-standards.org\n\n- International Telecommunication Union. (2025). *Recommendation ITU-T Y.4812 (03/2025): Identity Interoperability for IoT Devices Across Metaverse Platforms*. ITU-T.\n\n- World Economic Forum. (2024). *Metaverse Interoperability is Essential. How Will Regulation Play a Part?* Centre for AI Excellence, Connected Future Initiative. Retrieved August 2024.\n\n- GamesPad. (2025). *What Is Metaverse Interoperability?* Retrieved from gamespad.io\n\n- Webisoft. (2025). *Metaverse Interoperability and the Future of the Metaverse*. Retrieved from webisoft.com\n\n- United States Congress Research Service. (2024). *The Metaverse: Concepts and Issues for Congress* (Report R47224).\n\n## Metadata\n\n- **Last Updated**: 2025-11-11\n- **Review Status**: Comprehensive editorial review\n- **Verification**: Academic sources verified\n- **Regional Context**: UK/North England where applicable",
  "backlinks": [
    "Data Integration Interface",
    "Universal Manifest",
    "Compatibility Process",
    "Metadata Standard"
  ],
  "wiki_links": [
    "Standardization Bodies",
    "InfrastructureDomain",
    "DataLayer",
    "Data Formats",
    "Protocol Definitions",
    "Technical Standards",
    "Metadata Standard",
    "Universal Manifest",
    "Technical Documentation",
    "System Interoperability",
    "MSF",
    "Scalable Architecture",
    "Cross-Platform Integration",
    "ETSI GR ARF 010",
    "Compatibility Process",
    "Data Integration Interface",
    "Metaverse Architecture",
    "API Specifications"
  ],
  "ontology": {
    "term_id": "20184",
    "preferred_term": "Interoperability Framework",
    "alt_terms": [],
    "iri": "http://narrativegoldmine.com/metaverse#InteroperabilityFramework",
    "source_domain": null,
    "domain": "mv",
    "domain_full_name": "Metaverse",
    "definition": "Coordinated set of standards and specifications enabling interaction between heterogeneous systems in metaverse environments.",
    "scope_note": null,
    "status": "draft",
    "maturity": "mature",
    "version": null,
    "public_access": true,
    "last_updated": null,
    "authority_score": null,
    "quality_score": null,
    "cross_domain_links": null,
    "owl_class": "mv:InteroperabilityFramework",
    "owl_physicality": "VirtualEntity",
    "owl_role": "Object",
    "owl_inferred_class": "mv:VirtualObject",
    "is_subclass_of": [],
    "has_part": [
      "Technical Standards",
      "Protocol Definitions",
      "Data Integration Interface",
      "Metadata Standard",
      "API Specifications",
      "Universal Manifest",
      "Data Formats"
    ],
    "is_part_of": [
      "Metaverse Architecture"
    ],
    "requires": [
      "Standardization Bodies",
      "Technical Documentation"
    ],
    "depends_on": [],
    "enables": [
      "System Interoperability",
      "Cross-Platform Integration",
      "Scalable Architecture"
    ],
    "relates_to": [],
    "bridges_to": [],
    "bridges_from": [],
    "domain_extensions": {},
    "belongs_to_domain": [
      "InfrastructureDomain"
    ],
    "implemented_in_layer": [
      "DataLayer"
    ],
    "source": [
      "ETSI GR ARF 010",
      "MSF"
    ],
    "other_relationships": {
      "is-dependency-of": [
        "Compatibility Process"
      ]
    },
    "validation": {
      "is_valid": false,
      "errors": [
        "Missing required property: source-domain",
        "Missing required property: last-updated",
        "Missing required property: is-subclass-of (at least one parent class)",
        "term-id '20184' doesn't match domain 'mv' (expected MV-)"
      ]
    }
  }
}