{
  "id": "IoT AI Integration (AI-0438)",
  "title": "IoT AI Integration (AI-0438)",
  "content": "- ### OntologyBlock\n  id:: iot-ai-integration-ai-0438-ontology\n  collapsed:: true\n\t- ontology:: true\n\t- term-id:: AI-0438\n\t- preferred-term:: IoT AI Integration (AI-0438)\n\t- status:: in\n\t- public-access:: true\n\t- definition:: IoT AI Integration synergizes Internet of Things sensor networks with embedded machine learning, enabling intelligent autonomous decision-making directly on IoT devices without requiring centralized cloud processing. IoT devices continuously generate multi-modal sensor data from accelerometers, temperature sensors, light sensors, and microphones; AI models analyze this streaming data locally for anomaly detection, pattern recognition, and real-time control actions. The integration addresses IoT challenges including network latency, bandwidth limitations, power constraints, and privacy concerns by moving inference onto resource-constrained edge devices. IoT sensors typically operate with extreme power budgets (milliwatts), making efficient inference critical for battery-powered deployments. AI models deployed on IoT devices employ quantization and pruning to fit within 128KB-1MB memory constraints while maintaining sufficient accuracy for task-specific applications. Communication protocols like MQTT, CoAP, and LoRaWAN support integration with backend systems while minimizing network traffic through selective event-driven transmission. IoT AI systems handle diverse use cases: smart building occupancy detection, agricultural soil monitoring, predictive maintenance in manufacturing, environmental monitoring, and personal health tracking. The architecture enables edge intelligence that reduces latency from seconds to milliseconds, enables offline operation during connectivity loss, and preserves privacy by processing sensitive data locally. Standards like IEEE 2413-2019 and ETSI TS 103645 guide secure IoT AI deployments. This integration transforms IoT from passive data collection to active intelligent edge systems.\n\t- maturity:: mature\n\t- owl:class:: aigo:IoTAIIntegration\n\t- owl:physicality:: VirtualEntity\n\t- owl:role:: Process\n\t- owl:inferred-class:: aigo:VirtualProcess\n\t- belongsToDomain:: [[AIEthicsDomain]]\n\t- implementedInLayer:: [[ConceptualLayer]]\n\n## IoT AI Integration (AI-0438)\n\nIoT AI Integration (AI-0438) refers to iot ai integration synergizes internet of things sensor networks with embedded machine learning, enabling intelligent autonomous decision-making directly on iot devices without requiring centralized cloud processing. iot devices continuously generate multi-modal sensor data from accelerometers, temperature sensors, light sensors, and microphones; ai models analyze this streaming data locally for anomaly detection, pattern recognition, and real-time control actions. the integration addresses iot challenges including network latency, bandwidth limitations, power constraints, and privacy concerns by moving inference onto resource-constrained edge devices. iot sensors typically operate with extreme power budgets (milliwatts), making efficient inference critical for battery-powered deployments. ai models deployed on iot devices employ quantization and pruning to fit within 128kb-1mb memory constraints while maintaining sufficient accuracy for task-specific applications. communication protocols like mqtt, coap, and lorawan support integration with backend systems while minimizing network traffic through selective event-driven transmission. iot ai systems handle diverse use cases: smart building occupancy detection, agricultural soil monitoring, predictive maintenance in manufacturing, environmental monitoring, and personal health tracking. the architecture enables edge intelligence that reduces latency from seconds to milliseconds, enables offline operation during connectivity loss, and preserves privacy by processing sensitive data locally. standards like ieee 2413-2019 and etsi ts 103645 guide secure iot ai deployments. this integration transforms iot from passive data collection to active intelligent edge systems.\n\n- The convergence of Artificial Intelligence and Internet of Things represents one of the most significant technological developments of the 2020s[1][2]\n  - Artificial Intelligence of Things (AIoT) denotes the systematic integration of AI technologies into IoT systems and devices, enabling sophisticated environmental interaction[1]\n  - This interdisciplinary field moves machine learning capabilities closer to data sources, fundamentally altering how distributed networks process and respond to information[1]\n  - The theoretical foundation rests on decades of IoT research combined with recent advances in machine learning and edge computing paradigms\n\n## Technical Details\n\n- **Id**: iot-ai-integration-(ai-0438)-about\n- **Collapsed**: true\n- **Domain Prefix**: AI\n- **Sequence Number**: 0438\n- **Filename History**: [\"AI-0438-iot-ai-integration.md\"]\n- **Public Access**: true\n- **Source Domain**: ai\n- **Status**: in-progress\n- **Last Updated**: 2025-10-29\n- **Maturity**: mature\n- **Source**:\n- **Authority Score**: 0.95\n- **Owl:Class**: aigo:IoTAIIntegration\n- **Owl:Physicality**: VirtualEntity\n- **Owl:Role**: Process\n- **Owl:Inferred Class**: aigo:VirtualProcess\n- **Belongstodomain**: [[AIEthicsDomain]]\n- **Implementedinlayer**: [[ConceptualLayer]]\n\n## Current Landscape (2025)\n\n- Industry adoption and implementations\n  - The enterprise IoT market is forecasted to grow at 14% compound annual growth rate through 2030, with AI integration serving as a primary growth driver[4]\n  - Approximately 75 billion connected devices are anticipated by end of 2025, representing exponential expansion from previous years[3]\n  - Key application domains include manufacturing (Industry 4.0 and emerging Industry 5.0 frameworks), healthcare, energy management, and smart infrastructure[2][4][5]\n  - Real-time decision-making capabilities now enable autonomous systems, smart traffic management, and industrial automation at scale[2]\n  - Predictive maintenance applications reduce downtime and operational costs across manufacturing, power generation, and aerospace sectors[2]\n  - Notable implementations include Google's AI-optimised data centre cooling systems, demonstrating measurable efficiency gains[3]\n  - UK and North England context: whilst specific regional implementations remain limited in available literature, the North of England's manufacturing heritage positions cities such as Manchester, Leeds, and Sheffield as potential innovation hubs for Industry 4.0 and AIoT deployment, particularly given existing industrial automation clusters\n- Technical capabilities and limitations\n  - AI-driven IoT systems excel at processing vast datasets, filtering noise, and extracting actionable insights for decision-making[2]\n  - Deep learning approaches demonstrate superior efficiency in handling large-scale IoT data generation compared to traditional machine learning[3]\n  - Automated feature extraction from raw data enables complex pattern recognition previously requiring manual intervention[3]\n  - Edge computing deployment allows inference operations to occur proximate to data sources, reducing latency and bandwidth requirements[4]\n  - Current limitations include resource constraints on IoT devices, necessitating tailored machine learning algorithms for embedded systems[3]\n  - Security remains a critical consideration, though AI strengthens threat detection and real-time breach prevention[2]\n- Standards and frameworks\n  - IEEE AIoT Conference (2025) establishes emerging standards for AIoT research and development[1]\n  - Industry 4.0 frameworks increasingly incorporate AI and IoT integration for self-optimising manufacturing processes[2][5]\n  - Industry 5.0 represents the next evolutionary stage, emphasising human-centric and sustainable operations through AI-IoT synergy[5]\n  - Cloud and edge computing architectures form the technological backbone, with software-defined solutions gaining prominence over traditional hardware-centric approaches[4]\n\n## Research & Literature\n\n- Key academic papers and sources\n  - IEEE AIoT 2025 Conference proceedings (forthcoming) – focuses on integration of AI technologies into IoT systems and devices; selected papers recommended for fast-track publication in IEEE Journal of Biomedical and Health Informatics (Impact Factor: 6.8) and Digital Communications and Networks (Impact Factor: 7.5)[1]\n  - Alabiech et al. (2025) – \"A Survey: The Uses of Artificial Intelligence of Things (AIoT)\" – International Journal of Computer Applications, Volume 187, No. 45, September 2025; comprehensive examination of machine learning and deep learning security applications in IoT systems[3]\n  - Emerald Group Publishing (2025) – \"From Industry 4.0 to 5.0: Leveraging AI and IoT for Sustainable and Human-Centric Operations\" – investigates transition frameworks and integration methodologies[5]\n  - IoT Analytics (2025) – \"State of Enterprise IoT: Market Recovery, AI Integration, Regulations\" – Spring 2025 report providing market forecasts and adoption trends through 2030[4]\n- Ongoing research directions\n  - Security and privacy enhancement through AI-driven threat detection in heterogeneous IoT environments[3]\n  - Resource-constrained algorithm development for embedded IoT devices[3]\n  - Deep linking protocols enabling autonomous device interaction without human intervention[3]\n  - Sustainability optimisation across energy, utilities, and smart infrastructure sectors[4]\n  - Human-centric design principles in Industry 5.0 implementations[5]\n\n## UK Context\n\n- British contributions and implementations\n  - UK academic institutions actively participate in IEEE AIoT research initiatives, though specific institutional leads remain undocumented in current literature\n  - The UK's digital infrastructure strategy increasingly emphasises AI-IoT convergence for smart city development and industrial modernisation\n- North England innovation potential\n  - Manchester's established technology sector and university research capabilities position it as a potential AIoT innovation centre, particularly for manufacturing applications\n  - Leeds and Sheffield's historical manufacturing expertise aligns with Industry 4.0 and 5.0 deployment opportunities\n  - Newcastle's emerging technology clusters could benefit from AIoT applications in energy management and smart infrastructure\n  - Specific case studies and regional implementations require further investigation, as current academic literature does not yet document North England-specific AIoT deployments at scale\n\n## Future Directions\n\n- Emerging trends and developments\n  - Hardware market recovery anticipated in 2025, particularly for controllers and gateways supporting edge computing (projected 4.5% CAGR through 2030)[4]\n  - Structural shift from hardware-centric to software-defined IoT solutions, with AI as a central transformation pillar[4]\n  - Increased edge inference deployment, moving computational workloads closer to data sources[4]\n  - Expansion of personalised applications in smart homes and healthcare through AI-IoT integration[2]\n- Anticipated challenges\n  - Supply chain uncertainties and tariff-related pressures may impact 2025 market expectations[4]\n  - Balancing security and privacy with real-time processing requirements remains technically demanding[2][3]\n  - Standardisation across heterogeneous IoT ecosystems continues to present integration obstacles\n  - Resource constraints on embedded devices necessitate ongoing algorithmic innovation\n- Research priorities\n  - Development of lightweight machine learning models suitable for resource-constrained IoT devices[3]\n  - Comprehensive security frameworks addressing emerging threat vectors in distributed AIoT systems[3]\n  - Human-centric design methodologies for Industry 5.0 implementations[5]\n  - Sustainability metrics and optimisation strategies for large-scale AIoT deployments[4][5]\n  - Regional innovation ecosystem development, particularly in UK manufacturing centres\n\n## References\n\n1. IEEE AIoT 2025 Conference. (2025). \"Artificial Intelligence of Things Conference.\" Available at: https://www.ieee-aiot.org/2025/\n2. SmartDev. (2025). \"AI and IoT in 2025: How Smart Integration Transforms Industries.\" Retrieved from https://smartdev.com/the-convergence-of-ai-and-iot-in-2025/\n3. Alabiech et al. (2025). \"A Survey: The Uses of Artificial Intelligence of Things (AIoT).\" *International Journal of Computer Applications*, 187(45), September 2025.\n4. IoT Analytics. (2025). \"State of Enterprise IoT: Market Recovery, AI Integration, Regulations.\" Spring 2025 Report. Retrieved from https://iot-analytics.com/state-of-enterprise-iot/\n5. Emerald Group Publishing. (2025). \"From Industry 4.0 to 5.0: Leveraging AI and IoT for Sustainable and Human-Centric Operations.\" *International Journal of Industrial Engineering and Operations Management*, 5(2), April 2025. https://doi.org/10.1108/IJIEOM-04-2025-0070\n\n## Metadata\n\n- **Migration Status**: Ontology block enriched on 2025-11-12\n- **Last Updated**: 2025-11-12\n- **Review Status**: Comprehensive editorial review\n- **Verification**: Academic sources verified\n- **Regional Context**: UK/North England where applicable",
  "backlinks": [],
  "wiki_links": [
    "ConceptualLayer",
    "AIEthicsDomain"
  ],
  "ontology": {
    "term_id": "AI-0438",
    "preferred_term": "IoT AI Integration (AI-0438)",
    "alt_terms": [],
    "iri": "http://narrativegoldmine.com/ai#aigo:IoTAIIntegration",
    "source_domain": "ai",
    "domain": "ai",
    "domain_full_name": "Artificial Intelligence",
    "definition": "IoT AI Integration synergizes Internet of Things sensor networks with embedded machine learning, enabling intelligent autonomous decision-making directly on IoT devices without requiring centralized cloud processing. IoT devices continuously generate multi-modal sensor data from accelerometers, temperature sensors, light sensors, and microphones; AI models analyze this streaming data locally for anomaly detection, pattern recognition, and real-time control actions. The integration addresses IoT challenges including network latency, bandwidth limitations, power constraints, and privacy concerns by moving inference onto resource-constrained edge devices. IoT sensors typically operate with extreme power budgets (milliwatts), making efficient inference critical for battery-powered deployments. AI models deployed on IoT devices employ quantization and pruning to fit within 128KB-1MB memory constraints while maintaining sufficient accuracy for task-specific applications. Communication protocols like MQTT, CoAP, and LoRaWAN support integration with backend systems while minimizing network traffic through selective event-driven transmission. IoT AI systems handle diverse use cases: smart building occupancy detection, agricultural soil monitoring, predictive maintenance in manufacturing, environmental monitoring, and personal health tracking. The architecture enables edge intelligence that reduces latency from seconds to milliseconds, enables offline operation during connectivity loss, and preserves privacy by processing sensitive data locally. Standards like IEEE 2413-2019 and ETSI TS 103645 guide secure IoT AI deployments. This integration transforms IoT from passive data collection to active intelligent edge systems.",
    "scope_note": null,
    "status": "in",
    "maturity": "mature",
    "version": null,
    "public_access": true,
    "last_updated": "2025-10-29",
    "authority_score": null,
    "quality_score": null,
    "cross_domain_links": null,
    "owl_class": "aigo:IoTAIIntegration",
    "owl_physicality": "VirtualEntity",
    "owl_role": "Process",
    "owl_inferred_class": "aigo:VirtualProcess",
    "is_subclass_of": [],
    "has_part": [],
    "is_part_of": [],
    "requires": [],
    "depends_on": [],
    "enables": [],
    "relates_to": [],
    "bridges_to": [],
    "bridges_from": [],
    "domain_extensions": {},
    "belongs_to_domain": [
      "AIEthicsDomain"
    ],
    "implemented_in_layer": [
      "ConceptualLayer"
    ],
    "source": [],
    "validation": {
      "is_valid": false,
      "errors": [
        "Missing required property: is-subclass-of (at least one parent class)",
        "owl:class namespace 'aigo' doesn't match source-domain 'ai'"
      ]
    }
  }
}