{
  "id": "Keccak-256",
  "title": "Keccak-256",
  "content": "- ### OntologyBlock\n  id:: keccak-256-ontology\n  collapsed:: true\n\t- ontology:: true\n\t- term-id:: BC-0042\n\t- preferred-term:: Keccak-256\n\t- status:: complete\n\t- public-access:: true\n\t- definition:: SHA-3 hash function variant within blockchain systems, providing essential functionality for distributed ledger technology operations and properties.\n\t- source:: [[ISO/IEC 23257:2021]], [[IEEE 2418.1]], [[NIST NISTIR]]\n\t- maturity:: mature\n\t- owl:class:: bc:Keccak-256\n\t- owl:physicality:: VirtualEntity\n\t- owl:role:: Object\n\t- owl:inferred-class:: bc:VirtualObject\n\t- belongsToDomain:: [[CryptographicDomain]]",
  "backlinks": [
    "SHA-256"
  ],
  "wiki_links": [
    "CryptographicDomain",
    "ISO/IEC 23257:2021",
    "IEEE 2418.1",
    "NIST NISTIR"
  ],
  "ontology": {
    "term_id": "BC-0042",
    "preferred_term": "Keccak-256",
    "alt_terms": [],
    "iri": "http://narrativegoldmine.com/blockchain#Keccak-256",
    "source_domain": null,
    "domain": "bc",
    "domain_full_name": "Blockchain",
    "definition": "SHA-3 hash function variant within blockchain systems, providing essential functionality for distributed ledger technology operations and properties.",
    "scope_note": null,
    "status": "complete",
    "maturity": "mature",
    "version": null,
    "public_access": true,
    "last_updated": null,
    "authority_score": null,
    "quality_score": null,
    "cross_domain_links": null,
    "owl_class": "bc:Keccak-256",
    "owl_physicality": "VirtualEntity",
    "owl_role": "Object",
    "owl_inferred_class": "bc:VirtualObject",
    "is_subclass_of": [],
    "has_part": [],
    "is_part_of": [],
    "requires": [],
    "depends_on": [],
    "enables": [],
    "relates_to": [],
    "bridges_to": [],
    "bridges_from": [],
    "domain_extensions": {},
    "belongs_to_domain": [
      "CryptographicDomain"
    ],
    "implemented_in_layer": [],
    "source": [
      "ISO/IEC 23257:2021",
      "IEEE 2418.1",
      "NIST NISTIR"
    ],
    "validation": {
      "is_valid": false,
      "errors": [
        "Missing required property: source-domain",
        "Missing required property: last-updated",
        "Missing required property: is-subclass-of (at least one parent class)"
      ]
    }
  }
}