{
  "id": "Leeds Digital Hub",
  "title": "Leeds Digital Hub",
  "content": "- ### OntologyBlock\n  id:: leeds-digital-hub-ontology\n  collapsed:: true\n\t- ontology:: true\n\t- term-id:: UK-002\n\t- preferred-term:: Leeds Digital Hub\n\t- status:: active\n\t- public-access:: true\n\t- definition:: Leeds' digital technology sector focusing on health technology innovation, financial services technology, and digital creative industries.\n\t- maturity:: established\n\t- owl:class:: uk:LeedsDigitalHub\n\t- owl:physicality:: ConceptualEntity\n\t- owl:role:: RegionalEcosystem\n\t- belongsToDomain:: [[UKTechEcosystem]]\n\n## Leeds Digital Hub\n\nLeeds Digital Hub refers to leeds' digital technology sector focusing on health technology innovation, financial services technology, and digital creative industries.\n\n\n## Technical Details\n\n- **Id**: leeds-digital-hub-ontology\n- **Collapsed**: true\n- **Source Domain**: uk-regions\n- **Status**: active\n- **Public Access**: true\n- **Maturity**: established\n- **Region**: West Yorkshire\n- **Focus Areas**: HealthTech, FinTech, Digital Industries\n- **Owl:Class**: uk:UK-002-LeedsDigitalHub\n- **Owl:Physicality**: ConceptualEntity\n- **Owl:Role**: RegionalEcosystem\n- **Belongstodomain**: [[UKTechEcosystem]]\n\n## Overview\n\n**History and Development**\nThe Leeds Digital Hub was established in 2014 as a catalyst for digital innovation in the city.[5] It has evolved into a central component of Leeds' broader strategy to position itself as a technology and innovation powerhouse. The hub operates within the context of the Leeds City Region's digital economy, which has seen significant growth and investment over the past decade.\n**Current State and Infrastructure**\nThe Leeds Digital Hub functions as a collaborative space within the city centre, offering office accommodation, mentoring, training facilities, and event spaces designed to foster innovation and entrepreneurship.[10] The hub is part of a broader ecosystem that includes complementary facilities such as Futurelabs, Duke Studios, Leeds Hackspace, Prime Studios, and the Nexus innovation hub.[5] These interconnected spaces create a comprehensive support network for digital businesses and startups.\n**Key Organisations and Institutions**\nThe hub operates within a rich institutional landscape. The University of Leeds plays a crucial role as a world-class academic institution driving research and talent development.[4] Leeds Teaching Hospitals NHS Trust contributes significant expertise in healthcare innovation, whilst the Leeds Academic Health Partnership coordinates collaborative efforts across the region. Additionally, the Medicines and Healthcare products Regulatory Agency (MHRA) has established a digital hub in Wellington Place, Leeds city centre, further strengthening the city's regulatory and innovation infrastructure.[2][4]\n\n## Technology Focus\n\n**Primary Technology Sectors**\nLeeds' technology ecosystem spans multiple sectors, with particular strength in healthcare innovation, digital industries, and creative technologies.[5] The city has positioned itself as a \"healthcare innovation powerhouse,\" with particular emphasis on digital health and life sciences.[2][4] The West Yorkshire Healthtech and Digital Technology Investment Zone, valued at £160-£180 million, underscores this strategic focus.[1][3]\n**Notable Companies and Startups**\nThe region hosts a diverse range of technology companies across various sectors. In creative, media, and gaming, notable firms include Rockstar, Sky Betting & Gaming, William Hill, True North, and Daisybeck Studios.[5] Hardware and software development is represented by companies such as Infinity Works, Proactis, CSC, Smoothwall, and Tracsis.[5] Corporate technology services are provided by major organisations including Asda-Walmart, TomTom, Marks & Spencer, Yorkshire Water, and KPMG.[5]\nA particularly notable success story is DigiBete, a Leeds-based company transforming care for children with diabetes across the UK and worldwide.[4]\n**Research Institutions and Universities**\nThe University of Leeds serves as a cornerstone institution, providing research capabilities, talent development, and innovation partnerships.[4] The institution contributes significantly to the city's positioning as a healthcare innovation centre through its academic programmes and research initiatives.\n**Innovation Programmes**\nThe Leeds Innovation Pop Up community demonstrates strong early interest in emerging opportunities, with over 50 members already engaged in discussions about new innovation spaces.[3] Support packages are being designed to be bespoke and tailored to individual innovator needs, with the aim of enabling rapid deployment and collaboration.[3]\n\n## Economic Impact\n\n**Employment and Growth**\nThe Leeds Innovation Village project alone is projected to deliver 4,000 new jobs and generate an economic boost of up to £13 billion for the region.[1][9] This transformational development represents a significant catalyst for regional economic growth and employment creation.\n**Investment and Funding**\nGovernment investment has been substantial, with the West Yorkshire Healthtech and Digital Technology Investment Zone receiving £160-£180 million in funding.[1][3] The MHRA's establishment of a digital hub in Leeds represents additional government commitment to the region's innovation infrastructure.[2] However, regional leaders have noted the importance of developing diverse funding streams beyond central government support, which can be unpredictable.[6]\n**Regional Contribution**\nChannel 4's relocation of its headquarters to Leeds in 2021 created a significant domino effect, attracting additional innovative companies and startups to the city.[6] This demonstrates how anchor institutions can catalyse broader economic development and reinforce the city's position as a technology hub.\n\n## Notable Projects\n\n**Healthtech Innovation Hub**\nThe transformation of Leeds Teaching Hospitals' Old Medical School into a Healthtech Innovation Hub represents a flagship project combining heritage preservation with modern innovation infrastructure.[1][3] The building, which first opened in 1894, will be repurposed to include state-of-the-art co-working spaces, offices, laboratories, event spaces, and meeting rooms whilst retaining its historic features, including the original library and lecture theatre.[3] Completion is anticipated in 2027.[3]\n**Leeds Innovation Village**\nThis broader development on the site of Leeds General Infirmary encompasses the Healthtech Innovation Hub as its first phase and represents a transformational health and life science-led development in Leeds city centre.[1] The project is positioned as a pivotal component of the city's Innovation Arc, enabling innovation that creates a healthier, greener, and more inclusive future.[1]\n**MHRA Digital Hub**\nThe Medicines and Healthcare products Regulatory Agency's new digital hub, located at Wellington Place in Leeds city centre, strengthens regulatory capabilities and enables closer collaboration with digital health networks, NHS organisations, and leading academic institutions nationwide.[2][4]\n\n## Future Development\n\n**Growth Plans and Strategies**\nLeeds has established itself as a centre for digital and creative industries with significant opportunity for cluster development.[5] The city's strategy emphasises building on existing strengths in healthcare innovation, digital health, and life sciences whilst attracting skilled talent and local investment.[2]\n**Infrastructure Investments**\nMajor infrastructure projects underway include the construction of Leeds Teaching Hospitals' new state-of-the-art digital hospital on the Leeds General Infirmary site, which serves as a catalyst for the broader Innovation Village development.[1] The redevelopment of the Old Medical School into a modern innovation hub represents a significant investment in physical infrastructure designed to support emerging healthtech companies and innovators.[3]\n**Policy Support**\nGovernment support is evident through the Places for Growth strategy, which aims to expand the regional footprint of public bodies and ensure opportunities and expertise are more evenly distributed across the UK.[2] Health Secretary Wes Streeting has articulated a clear vision of Yorkshire leading a global technology revolution in healthcare, with Leeds positioned at the centre of this transformation.[2][4] This policy commitment provides a framework for sustained investment and development in the region's innovation ecosystem.\n\n## Related Hubs\n\n- [[North England Innovation Corridor]]\n- [[Northern Powerhouse]]\n- [[UK Tech Ecosystem]]\n\n\n## Metadata\n\n- **Last Updated**: 2025-11-16\n- **Review Status**: Automated remediation with 2025 context\n- **Verification**: Academic sources verified\n- **Regional Context**: UK/North England where applicable\n\n## References\n\n1. [https://www.leedsth.nhs.uk/news/government-funding-gives-massive-boost-to-regions-flagship-new-healthtech-innovation-hub/](https://www.leedsth.nhs.uk/news/government-funding-gives-massive-boost-to-regions-flagship-new-healthtech-innovation-hub/)\n2. [https://www.gov.uk/government/news/mhra-launches-new-digital-hub-in-leeds-to-drive-innovation-and-regional-growth](https://www.gov.uk/government/news/mhra-launches-new-digital-hub-in-leeds-to-drive-innovation-and-regional-growth)\n3. [https://healthinnovationleeds.com/latest/spotlight/health-innovators-eye-fast-track-growth-as-leeds-transforms-historic-medical-school/](https://healthinnovationleeds.com/latest/spotlight/health-innovators-eye-fast-track-growth-as-leeds-transforms-historic-medical-school/)\n4. [https://www.leeds.ac.uk/working-region/news/article/5791/hi-tech-healthcare-in-leeds](https://www.leeds.ac.uk/working-region/news/article/5791/hi-tech-healthcare-in-leeds)\n5. [https://www.westyorks-ca.gov.uk/media/1955/digital-fact-sheets-2018.pdf](https://www.westyorks-ca.gov.uk/media/1955/digital-fact-sheets-2018.pdf)\n6. [https://www.centreforcities.org/blog/what-needs-to-happen-to-boost-growth-in-west-yorkshire/](https://www.centreforcities.org/blog/what-needs-to-happen-to-boost-growth-in-west-yorkshire/)\n7. [https://www.healthinnovationyh.org.uk/wp-content/uploads/2024/04/Innovation-Hub-Brochure.pdf](https://www.healthinnovationyh.org.uk/wp-content/uploads/2024/04/Innovation-Hub-Brochure.pdf)\n8. [https://leedsdigital.org](https://leedsdigital.org)\n9. [https://www.thebusinessdesk.com/yorkshire/news/2121504-government-funding-backs-flagship-healthtech-innovation-hub](https://www.thebusinessdesk.com/yorkshire/news/2121504-government-funding-backs-flagship-healthtech-innovation-hub)\n10. [https://www.prolificnorth.co.uk/news/leeds-digital-hub-searches-tech-start-ups-support-yorkshire-post/](https://www.prolificnorth.co.uk/news/leeds-digital-hub-searches-tech-start-ups-support-yorkshire-post/)\n\n## Metadata\n\n- **Created**: 2025-11-11\n- **Region**: West Yorkshire, North England\n- **Category**: Regional Technology Ecosystem\n- **Status**: Active",
  "backlinks": [],
  "wiki_links": [
    "North England Innovation Corridor",
    "Northern Powerhouse",
    "UKTechEcosystem",
    "UK Tech Ecosystem"
  ],
  "ontology": {
    "term_id": "UK-002",
    "preferred_term": "Leeds Digital Hub",
    "alt_terms": [],
    "iri": null,
    "source_domain": "uk-regions",
    "domain": "uk-regions",
    "domain_full_name": "",
    "definition": "Leeds' digital technology sector focusing on health technology innovation, financial services technology, and digital creative industries.",
    "scope_note": null,
    "status": "active",
    "maturity": "established",
    "version": null,
    "public_access": true,
    "last_updated": null,
    "authority_score": null,
    "quality_score": null,
    "cross_domain_links": null,
    "owl_class": "uk:LeedsDigitalHub",
    "owl_physicality": "ConceptualEntity",
    "owl_role": "RegionalEcosystem",
    "owl_inferred_class": null,
    "is_subclass_of": [],
    "has_part": [],
    "is_part_of": [],
    "requires": [],
    "depends_on": [],
    "enables": [],
    "relates_to": [],
    "bridges_to": [],
    "bridges_from": [],
    "domain_extensions": {},
    "belongs_to_domain": [
      "UKTechEcosystem"
    ],
    "implemented_in_layer": [],
    "source": [],
    "validation": {
      "is_valid": false,
      "errors": [
        "Missing required property: last-updated",
        "Missing required property: is-subclass-of (at least one parent class)",
        "owl:class namespace 'uk' doesn't match source-domain 'uk-regions'"
      ]
    }
  }
}