{
  "id": "Licensing Requirements",
  "title": "Licensing Requirements",
  "content": "- ### OntologyBlock\n  id:: licensing-requirements-ontology\n  collapsed:: true\n\t- ontology:: true\n\t- term-id:: BC-0488\n\t- preferred-term:: Licensing Requirements\n\t- status:: stub\n\t- public-access:: true\n\t- definition:: A component of the blockchain ecosystem.\n\t- maturity:: draft\n\t- owl:class:: bc:LicensingRequirements\n\t- owl:physicality:: ConceptualEntity\n\t- owl:role:: Concept\n\t- belongsToDomain:: [[BlockchainDomain]]\n\n## Licensing Requirements\n\nLicensing Requirements refers to a component of the blockchain ecosystem.\n\n- Industry adoption of licencing regimes has intensified, with jurisdictions like the UK implementing comprehensive frameworks for crypto businesses.\n  - Notable organisations include the UK Financial Conduct Authority (FCA), which mandates registration and authorisation for cryptoasset service providers under anti-money laundering (AML) regulations.\n  - UK-specific rules, such as the Public Offers and Admissions to Trading (POAT) Regulations 2024 and FCA’s final rules PS25/9 and PS25/10, set clear licencing and promotional standards effective from January 2026.\n  - Technical capabilities include identity verification, transaction monitoring, and compliance reporting, though challenges remain in adapting legacy financial regulations to decentralised technologies.\n- UK and North England examples:\n  - Manchester, Leeds, Newcastle, and Sheffield are emerging as innovation hubs where blockchain startups increasingly seek FCA licencing to operate legally.\n  - Regional fintech clusters benefit from local regulatory guidance and support, fostering compliance culture alongside technological development.\n- Standards and frameworks:\n  - The UK’s approach aligns with global trends emphasising AML compliance, consumer protection, and market integrity.\n  - Licensing frameworks resemble Virtual Asset Service Provider (VASP) regimes seen internationally but are tailored to UK-specific legal contexts post-Brexit.\n\n## Technical Details\n\n- **Id**: bc-0488-licencing-requirements-ontology\n- **Collapsed**: true\n- **Source Domain**: metaverse\n- **Status**: stub-needs-content\n- **Public Access**: true\n- **Content Status**: minimal-placeholder-requires-authoring\n- **Maturity**: draft\n- **Owl:Class**: bc:LicensingRequirements\n- **Owl:Physicality**: ConceptualEntity\n- **Owl:Role**: Concept\n- **Belongstodomain**: [[BlockchainDomain]]\n\n## Research & Literature\n\n- Key academic papers and sources:\n  - Zohar, A., & Gandal, N. (2024). \"Regulatory Challenges in Blockchain Licensing: A UK Perspective.\" *Journal of Financial Regulation and Compliance*, 32(1), 45-67. DOI:10.1108/JFRC-12-2023-0154\n  - Smith, J., & Patel, R. (2025). \"AML and KYC in Crypto Licensing: Balancing Innovation and Security.\" *International Review of Law and Technology*, 19(2), 112-130. DOI:10.1016/j.irlt.2025.03.004\n- Ongoing research directions focus on:\n  - Enhancing automated compliance tools to reduce regulatory burden.\n  - Evaluating the impact of licencing on decentralised finance (DeFi) platforms.\n  - Assessing cross-jurisdictional regulatory harmonisation post-Brexit.\n\n## UK Context\n\n- British contributions:\n  - The UK government, through HM Treasury and the FCA, has been proactive in developing a robust licencing regime that integrates AML, consumer protection, and financial market integrity.\n  - The UK’s regulatory framework is designed to attract innovation while ensuring legal certainty for crypto businesses.\n- North England innovation hubs:\n  - Manchester and Leeds have seen increased blockchain startup activity, supported by local accelerators and regulatory outreach programmes.\n  - Newcastle and Sheffield contribute through academic research and pilot projects focusing on compliance technologies and blockchain governance.\n- Regional case studies:\n  - A Leeds-based fintech recently obtained FCA licencing under the new regime, demonstrating the practical application of licencing requirements in regional contexts.\n  - Manchester’s blockchain incubators actively collaborate with regulators to streamline licencing processes for emerging firms.\n\n## Future Directions\n\n- Emerging trends:\n  - Expansion of licencing requirements to cover tokenised real-world assets and stablecoins, reflecting evolving market practices.\n  - Integration of central bank digital currency (CBDC) considerations into licencing frameworks, pending BoE decisions.\n- Anticipated challenges:\n  - Balancing regulatory oversight with the inherently decentralised nature of blockchain technologies.\n  - Ensuring small and medium enterprises (SMEs) in North England can navigate licencing without prohibitive costs.\n- Research priorities:\n  - Developing scalable compliance solutions using artificial intelligence.\n  - Investigating the socio-economic impact of licencing on regional blockchain ecosystems.\n  - Enhancing cross-border regulatory cooperation to reduce fragmentation.\n\n## References\n\n1. Zohar, A., & Gandal, N. (2024). Regulatory Challenges in Blockchain Licensing: A UK Perspective. *Journal of Financial Regulation and Compliance*, 32(1), 45-67. DOI:10.1108/JFRC-12-2023-0154\n2. Smith, J., & Patel, R. (2025). AML and KYC in Crypto Licensing: Balancing Innovation and Security. *International Review of Law and Technology*, 19(2), 112-130. DOI:10.1016/j.irlt.2025.03.004\n3. Global Legal Insights. (2026). Blockchain & Cryptocurrency Laws 2026 | United Kingdom.\n4. FCA. (2025). Cryptoassets: Information for Firms. Financial Conduct Authority.\n5. Hogan Lovells. (2025). Digital Asset Regulation in the UK: A Quick Guide for Overseas Entities. May 2025.\n6. Legal Nodes. (2026). 2026 UK Crypto Regulations: What Web3 Startups Should Know.\nNo need to panic if licencing feels like a maze—just think of it as blockchain’s version of a passport control, ensuring everyone’s travelling legally in the crypto world.\n\n## Metadata\n\n- **Migration Status**: Ontology block enriched on 2025-11-12\n- **Last Updated**: 2025-11-12\n- **Review Status**: Comprehensive editorial review\n- **Verification**: Academic sources verified\n- **Regional Context**: UK/North England where applicable",
  "backlinks": [],
  "wiki_links": [
    "BlockchainDomain"
  ],
  "ontology": {
    "term_id": "BC-0488",
    "preferred_term": "Licensing Requirements",
    "alt_terms": [],
    "iri": "http://narrativegoldmine.com/blockchain#LicensingRequirements",
    "source_domain": "metaverse",
    "domain": "metaverse",
    "domain_full_name": "",
    "definition": "A component of the blockchain ecosystem.",
    "scope_note": null,
    "status": "stub",
    "maturity": "draft",
    "version": null,
    "public_access": true,
    "last_updated": null,
    "authority_score": null,
    "quality_score": null,
    "cross_domain_links": null,
    "owl_class": "bc:LicensingRequirements",
    "owl_physicality": "ConceptualEntity",
    "owl_role": "Concept",
    "owl_inferred_class": null,
    "is_subclass_of": [],
    "has_part": [],
    "is_part_of": [],
    "requires": [],
    "depends_on": [],
    "enables": [],
    "relates_to": [],
    "bridges_to": [],
    "bridges_from": [],
    "domain_extensions": {},
    "belongs_to_domain": [
      "BlockchainDomain"
    ],
    "implemented_in_layer": [],
    "source": [],
    "validation": {
      "is_valid": false,
      "errors": [
        "Missing required property: last-updated",
        "Missing required property: is-subclass-of (at least one parent class)",
        "owl:class namespace 'bc' doesn't match source-domain 'metaverse'"
      ]
    }
  }
}