{
  "id": "Longest Chain Rule",
  "title": "Longest Chain Rule",
  "content": "- ### OntologyBlock\n  id:: longest-chain-rule-ontology\n  collapsed:: true\n\t- ontology:: true\n\t- term-id:: BC-0059\n\t- preferred-term:: Longest Chain Rule\n\t- status:: complete\n\t- public-access:: true\n\t- definition:: Chain selection mechanism within blockchain systems, providing essential functionality for distributed ledger technology operations and properties.\n\t- source:: [[ISO/IEC 23257:2021]], [[IEEE 2418.1]], [[NIST NISTIR]]\n\t- maturity:: mature\n\t- owl:class:: bc:LongestChainRule\n\t- owl:physicality:: VirtualEntity\n\t- owl:role:: Object\n\t- owl:inferred-class:: bc:VirtualObject\n\t- belongsToDomain:: [[ConsensusDomain]]\n\t- implementedInLayer:: [[ProtocolLayer]]\n\t- #### Relationships\n\t  id:: longest-chain-rule-relationships\n\t  collapsed:: true\n\t\t- is-subclass-of:: [[Blockchain Entity]]\n\t\t- is-subclass-of:: [[ConsensusProtocol]]\n\n## Longest Chain Rule\n\nLongest Chain Rule refers to chain selection mechanism within blockchain systems, providing essential functionality for distributed ledger technology operations and properties.\n\n- The longest chain rule remains the backbone of Proof-of-Work blockchains such as Bitcoin, underpinning their security and decentralisation.\n  - Industry adoption is widespread in cryptocurrencies and increasingly in blockchain-based applications requiring strong immutability guarantees.\n  - Notable platforms include Bitcoin, Litecoin, and other PoW-based networks that rely on this rule to maintain consensus.\n- In the UK, blockchain initiatives in financial services and supply chain management continue to explore hybrid consensus models, but the longest chain rule’s principles influence security assumptions.\n  - North England hubs such as Manchester and Leeds host blockchain startups and research groups focusing on distributed ledger technologies, often collaborating with universities and industry.\n- Technical limitations include high energy consumption inherent in Proof-of-Work and vulnerability to 51% attacks if a single entity controls majority hash power.\n- Standards and frameworks continue to evolve, with efforts to improve efficiency and security, including proposals for hybrid consensus and alternative proof systems that retain longest chain concepts.\n\n## Technical Details\n\n- **Id**: longest-chain-rule-standards\n- **Collapsed**: true\n- **Domain Prefix**: BC\n- **Sequence Number**: 0059\n- **Filename History**: [\"BC-0059-longest-chain-rule.md\"]\n- **Public Access**: true\n- **Source Domain**: blockchain\n- **Status**: complete\n- **Last Updated**: 2025-10-28\n- **Maturity**: mature\n- **Source**: [[ISO/IEC 23257:2021]], [[IEEE 2418.1]], [[NIST NISTIR]]\n- **Authority Score**: 0.95\n- **Owl:Class**: bc:LongestChainRule\n- **Owl:Physicality**: VirtualEntity\n- **Owl:Role**: Object\n- **Owl:Inferred Class**: bc:VirtualObject\n- **Belongstodomain**: [[ConsensusDomain]]\n- **Implementedinlayer**: [[ProtocolLayer]]\n- **Is Subclass Of**: [[Blockchain Entity]], [[ConsensusProtocol]]\n\n## Research & Literature\n\n- Key academic papers:\n  - Nakamoto, S. (2008). *Bitcoin: A Peer-to-Peer Electronic Cash System*. [Original whitepaper introducing the longest chain rule as part of Bitcoin’s consensus mechanism].\n  - Garay, J., Kiayias, A., & Leonardos, N. (2015). *The Bitcoin Backbone Protocol: Analysis and Applications*. Advances in Cryptology – EUROCRYPT 2015. DOI: 10.1007/978-3-662-46803-6_8\n  - Pass, R., Seeman, L., & Shelat, A. (2017). *Analysis of the Blockchain Protocol in Asynchronous Networks*. Advances in Cryptology – CRYPTO 2017. DOI: 10.1007/978-3-319-63688-7_22\n- Ongoing research explores reducing energy consumption while preserving security guarantees, including efficient proof systems and longest-chain protocol variants (e.g., Chia’s approach splitting chain into trunk and foliage to mitigate grinding attacks).\n\n## UK Context\n\n- The UK has contributed to blockchain research and development, with institutions such as University of Manchester and Newcastle University conducting advanced studies on blockchain consensus and security.\n- North England innovation hubs, including Leeds and Sheffield, foster startups applying blockchain to logistics, finance, and public services, often leveraging longest chain principles for data integrity.\n- Regional case studies include pilot projects in supply chain transparency and digital identity verification, where longest chain consensus ensures tamper-evident records.\n\n## Future Directions\n\n- Emerging trends focus on integrating longest chain concepts with more energy-efficient consensus mechanisms, such as Proof-of-Stake hybrids and novel proof systems.\n- Anticipated challenges include scaling longest chain protocols to support higher throughput without compromising security or decentralisation.\n- Research priorities involve formal verification of longest chain variants, resistance to new attack vectors, and adapting the rule to permissioned and consortium blockchains.\n- A subtle reminder: while the longest chain rule is robust, it’s not a race to the bottom—miners must keep their energy bills in cheque lest the blockchain becomes a very expensive paperweight.\n\n## References\n\n1. Nakamoto, S. (2008). *Bitcoin: A Peer-to-Peer Electronic Cash System*. Available at: https://bitcoin.org/bitcoin.pdf\n2. Garay, J., Kiayias, A., & Leonardos, N. (2015). The Bitcoin Backbone Protocol: Analysis and Applications. *Advances in Cryptology – EUROCRYPT 2015*, Lecture Notes in Computer Science, vol 9057. DOI: 10.1007/978-3-662-46803-6_8\n3. Pass, R., Seeman, L., & Shelat, A. (2017). Analysis of the Blockchain Protocol in Asynchronous Networks. *Advances in Cryptology – CRYPTO 2017*, Lecture Notes in Computer Science, vol 10401. DOI: 10.1007/978-3-319-63688-7_22\n4. Chia Network. (2024). *Longest-Chain Protocols from Efficient Proof Systems*. Chia Docs. Available at: https://docs.chia.net/chia-blockchain/green-paper/longest-chain-protocols/\n\n## Metadata\n\n- **Migration Status**: Ontology block enriched on 2025-11-12\n- **Last Updated**: 2025-11-12\n- **Review Status**: Comprehensive editorial review\n- **Verification**: Academic sources verified\n- **Regional Context**: UK/North England where applicable",
  "backlinks": [],
  "wiki_links": [
    "ProtocolLayer",
    "ConsensusProtocol",
    "ConsensusDomain",
    "NIST NISTIR",
    "IEEE 2418.1",
    "ISO/IEC 23257:2021",
    "Blockchain Entity"
  ],
  "ontology": {
    "term_id": "BC-0059",
    "preferred_term": "Longest Chain Rule",
    "alt_terms": [],
    "iri": "http://narrativegoldmine.com/blockchain#LongestChainRule",
    "source_domain": "blockchain",
    "domain": "blockchain",
    "domain_full_name": "",
    "definition": "Chain selection mechanism within blockchain systems, providing essential functionality for distributed ledger technology operations and properties.",
    "scope_note": null,
    "status": "complete",
    "maturity": "mature",
    "version": null,
    "public_access": true,
    "last_updated": "2025-10-28",
    "authority_score": 0.95,
    "quality_score": null,
    "cross_domain_links": null,
    "owl_class": "bc:LongestChainRule",
    "owl_physicality": "VirtualEntity",
    "owl_role": "Object",
    "owl_inferred_class": "bc:VirtualObject",
    "is_subclass_of": [
      "Blockchain Entity",
      "ConsensusProtocol"
    ],
    "has_part": [],
    "is_part_of": [],
    "requires": [],
    "depends_on": [],
    "enables": [],
    "relates_to": [],
    "bridges_to": [],
    "bridges_from": [],
    "domain_extensions": {},
    "belongs_to_domain": [
      "ConsensusDomain"
    ],
    "implemented_in_layer": [
      "ProtocolLayer"
    ],
    "source": [
      "ISO/IEC 23257:2021",
      "IEEE 2418.1",
      "NIST NISTIR"
    ],
    "validation": {
      "is_valid": false,
      "errors": [
        "owl:class namespace 'bc' doesn't match source-domain 'blockchain'"
      ]
    }
  }
}