{
  "id": "Manipulator",
  "title": "Manipulator",
  "content": "- ### OntologyBlock\n  id:: manipulator-ontology\n  collapsed:: true\n\n  - **Identification**\n\n    - domain-prefix:: RB\n\n    - sequence-number:: 0003\n\n    - filename-history:: [\"RB-0003-manipulator.md\"]\n    - public-access:: true\n    - ontology:: true\n    - is-subclass-of:: [[RoboticsTechnology]]\n    - term-id:: RB-0003\n    - preferred-term:: Manipulator\n    - source-domain:: robotics\n    - status:: complete\n    - version:: 1.0.0\n    - last-updated:: 2025-10-28\n\n  - **Definition**\n    - definition:: A manipulator is a robot consisting of a series of segments, typically moving in a serial or parallel kinematic chain, with an end-effector for performing tasks.\n    - maturity:: mature\n    - source:: [[ISO 8373:2021]]\n    - authority-score:: 0.99\n\n  - **Semantic Classification**\n    - owl:class:: rb:Manipulator\n    - owl:physicality:: PhysicalEntity\n    - owl:role:: Object\n    - belongsToDomain:: [[Robotics]]\n    - owl:disjointWith:: [[LanguageModel]]\n\n  - #### OWL Restrictions\n    - hasKinematicChain some KinematicStructure\n    - is-part-of some RobotRb0001\n    - definesWorkspace some WorkspaceVolume\n    - hasEndEffector some EndEffector\n\n  - #### CrossDomainBridges\n    - bridges-to:: [[WorkspaceVolume]] via definesWorkspace\n    - bridges-to:: [[KinematicStructure]] via hasKinematicChain\n\n  -",
  "backlinks": [],
  "wiki_links": [
    "KinematicStructure",
    "ISO 8373:2021",
    "Robotics",
    "LanguageModel",
    "RoboticsTechnology",
    "WorkspaceVolume"
  ],
  "ontology": {
    "term_id": "RB-0003",
    "preferred_term": "Manipulator",
    "alt_terms": [],
    "iri": "http://narrativegoldmine.com/robotics#Manipulator",
    "source_domain": "robotics",
    "domain": "robotics",
    "domain_full_name": "",
    "definition": "A manipulator is a robot consisting of a series of segments, typically moving in a serial or parallel kinematic chain, with an end-effector for performing tasks.",
    "scope_note": null,
    "status": "complete",
    "maturity": "mature",
    "version": "1.0.0",
    "public_access": true,
    "last_updated": "2025-10-28",
    "authority_score": 0.99,
    "quality_score": null,
    "cross_domain_links": null,
    "owl_class": "rb:Manipulator",
    "owl_physicality": "PhysicalEntity",
    "owl_role": "Object",
    "owl_inferred_class": null,
    "is_subclass_of": [],
    "has_part": [],
    "is_part_of": [],
    "requires": [],
    "depends_on": [],
    "enables": [],
    "relates_to": [],
    "bridges_to": [
      "WorkspaceVolume via definesWorkspace",
      "KinematicStructure via hasKinematicChain"
    ],
    "bridges_from": [],
    "domain_extensions": {},
    "belongs_to_domain": [
      "Robotics"
    ],
    "implemented_in_layer": [],
    "source": [
      "ISO 8373:2021"
    ],
    "validation": {
      "is_valid": false,
      "errors": [
        "Missing required property: is-subclass-of (at least one parent class)",
        "owl:class namespace 'rb' doesn't match source-domain 'robotics'"
      ]
    }
  }
}