{
  "id": "mBERT",
  "title": "mBERT",
  "content": "- ### OntologyBlock\n  id:: mbert-ontology\n  collapsed:: true\n\t- ontology:: true\n\t- term-id:: AI-0225\n\t- preferred-term:: mBERT\n\t- source-domain:: metaverse\n\t- status:: draft\n\t- public-access:: true\n\n\n\n\n### OWL Classification\n\t- owl:class:: mv:mBERT\n\t- owl:physicality:: ConceptualEntity\n\t- owl:role:: Concept\n\n### Domain & Architecture\n\t- belongsToDomain:: [[MetaverseDomain]]\n\t- maturity:: draft\n\n### Relationships\n- is-subclass-of:: [[BERT]]\n\n## OWL Formal Semantics\n\n```clojure\n;; OWL Functional Syntax\n\n(Declaration (Class :Mbert))\n\n;; Annotations\n(AnnotationAssertion rdfs:label :Mbert \"mBERT\"@en)\n(AnnotationAssertion rdfs:comment :Mbert \"Multilingual BERT: a variant of BERT pre-trained on Wikipedia in 104 languages, enabling cross-lingual transfer and multilingual understanding without language-specific modifications.\"@en)\n\n;; Data Properties\n(AnnotationAssertion dcterms:identifier :Mbert \"AI-0225\"^^xsd:string)\n(DataPropertyAssertion :isAITechnology :Mbert \"true\"^^xsd:boolean)\n```\n\n## Characteristics\n\n- **Multilingual Coverage**: Supports 104 languages\n- **Shared Vocabulary**: Single vocabulary across all languages\n- **Cross-Lingual Transfer**: Transfers knowledge between languages\n- **Same Architecture**: Identical to monolingual BERT\n\n## Academic Foundations\n\n**Primary Source**: Devlin et al., \"BERT: Pre-training of Deep Bidirectional Transformers for Language Understanding\", arXiv:1810.04805 (2018)\n\n**Cross-Lingual Ability**: Demonstrates zero-shot cross-lingual transfer on various NLU tasks despite being trained without explicit cross-lingual objectives.\n\n## Technical Context\n\nmBERT is trained on concatenated Wikipedia dumps from 104 languages using the same masked language modelling objective as monolingual BERT. Surprisingly, it learns to align representations across languages, enabling zero-shot cross-lingual transfer.\n\n## Ontological Relationships\n\n- **Broader Term**: Pre-trained Language Model, Multilingual Model\n- **Related Terms**: BERT, mT5, XLM-RoBERTa\n- **Base Architecture**: BERT with multilingual training data\n\n## Usage Context\n\n\"mBERT enables zero-shot cross-lingual transfer across 104 languages without language-specific training objectives.\"\n\n## References\n\n- Devlin, J., et al. (2018). \"BERT: Pre-training of Deep Bidirectional Transformers for Language Understanding\". arXiv:1810.04805\n\n---\n\n*Ontology Term managed by AI-Grounded Ontology Working Group*\n*UK English Spelling Standards Applied*\n\t- maturity:: draft\n\t- owl:class:: mv:mBERT\n\t- owl:physicality:: ConceptualEntity\n\t- owl:role:: Concept\n\t- belongsToDomain:: [[MetaverseDomain]]",
  "backlinks": [],
  "wiki_links": [
    "MetaverseDomain",
    "BERT"
  ],
  "ontology": {
    "term_id": "AI-0225",
    "preferred_term": "mBERT",
    "alt_terms": [],
    "iri": "http://narrativegoldmine.com/metaverse#mBERT",
    "source_domain": "metaverse",
    "domain": "metaverse",
    "domain_full_name": "",
    "definition": null,
    "scope_note": null,
    "status": "draft",
    "maturity": "draft",
    "version": null,
    "public_access": true,
    "last_updated": null,
    "authority_score": null,
    "quality_score": null,
    "cross_domain_links": null,
    "owl_class": "mv:mBERT",
    "owl_physicality": "ConceptualEntity",
    "owl_role": "Concept",
    "owl_inferred_class": null,
    "is_subclass_of": [],
    "has_part": [],
    "is_part_of": [],
    "requires": [],
    "depends_on": [],
    "enables": [],
    "relates_to": [],
    "bridges_to": [],
    "bridges_from": [],
    "domain_extensions": {},
    "belongs_to_domain": [
      "MetaverseDomain",
      "MetaverseDomain"
    ],
    "implemented_in_layer": [],
    "source": [],
    "validation": {
      "is_valid": false,
      "errors": [
        "Missing required property: last-updated",
        "Missing required property: definition",
        "Missing required property: is-subclass-of (at least one parent class)",
        "owl:class namespace 'mv' doesn't match source-domain 'metaverse'"
      ]
    }
  }
}