{
  "id": "Medical Imaging AI",
  "title": "Medical Imaging AI",
  "content": "- ### OntologyBlock\n  id:: medical-imaging-ai-ontology\n  collapsed:: true\n\t- ontology:: true\n\t- term-id:: AI-0338\n\t- preferred-term:: Medical Imaging AI\n\t- source-domain:: ai\n\t- owl:class:: ai:MedicalImagingAI\n\t- status:: draft\n\t- public-access:: true\n\t- definition:: Medical Imaging AI encompasses artificial intelligence systems designed to analyse, interpret, and enhance medical images including radiological scans, pathology slides, and other diagnostic imaging modalities. These systems employ deep learning architectures, particularly convolutional neural networks, to perform tasks such as lesion detection, disease classification, segmentation of anatomical structures, and quantitative image analysis whilst adhering to clinical validation standards and regulatory requirements.\n\t- #### Relationships\n\t  id:: medical-imaging-ai-relationships\n\t  collapsed:: true\n\t\t- is-subclass-of:: [[MedicalAI]]\n\n## Medical Imaging AI\n\nMedical Imaging AI refers to medical imaging ai encompasses artificial intelligence systems designed to analyse, interpret, and enhance medical images including radiological scans, pathology slides, and other diagnostic imaging modalities. these systems employ deep learning architectures, particularly convolutional neural networks, to perform tasks such as lesion detection, disease classification, segmentation of anatomical structures, and quantitative image analysis whilst adhering to clinical validation standards and regulatory requirements.\n\n- Medical Imaging AI has seen widespread adoption in clinical workflows, research, and healthcare IT systems globally, with increasing integration into diagnostic radiology and pathology.\n  - Leading organisations include academic medical centres, technology companies, and NHS trusts deploying AI tools for image analysis, workflow optimisation, and decision support.\n  - In the UK, NHS Digital and NHSX have supported AI initiatives, with North England hosting innovation hubs such as the Northern Health Science Alliance that foster AI-driven medical imaging research and deployment.\n- Technical capabilities have matured to include multi-modal imaging analysis, integration with electronic health records, and real-time image enhancement.\n  - Limitations remain around generalisability across diverse populations, regulatory compliance, and explainability of AI decisions.\n- Standards and frameworks such as SNOMED CT, HL7 FHIR, and ISO/IEC standards underpin data interoperability and clinical validation.\n  - Ontology-driven approaches enhance semantic integration across heterogeneous datasets, addressing challenges of fragmented data and inconsistent terminologies[2][6].\n\n## Technical Details\n\n- **Id**: medical-imaging-ai-ontology\n- **Collapsed**: true\n- **Source Domain**: ai\n- **Status**: draft\n- **Public Access**: true\n\n## Research & Literature\n\n- Key academic contributions include:\n  - Ambalavanan et al. (2025) discuss ontology-driven semantic integration for AI in healthcare, highlighting challenges like scalability and ethical concerns, and proposing adaptive ontology models and governance frameworks (DOI: 10.3389/fdgth.2025.1668385)[2].\n  - Rubin et al. (2014) describe the Radiology Gamuts Ontology as a formal knowledge model supporting differential diagnosis in radiology, facilitating semantic web integration (DOI: 10.1148/rg.341135036)[5].\n  - Recent studies emphasise ontology-based architectures for patient safety and AI explainability, advocating standards-driven development to improve clinical outcomes[6].\n- Ongoing research focuses on:\n  - Enhancing multi-modal data fusion using ontologies.\n  - Developing scalable, maintainable ontology frameworks.\n  - Addressing ethical issues such as bias and data privacy in AI models.\n\n## UK Context\n\n- The UK has contributed significantly to Medical Imaging AI through NHS-led initiatives and academic research.\n  - The Northern Health Science Alliance and centres like the University of Manchester and Newcastle University are notable for AI and medical imaging research collaborations.\n  - NHS trusts in North England have piloted AI tools for radiology workflow optimisation and diagnostic support, integrating ontology-based systems to improve semantic interoperability.\n- Regional case studies include AI-assisted lung cancer screening and pathology slide analysis projects utilising ontology frameworks to standardise data and enhance diagnostic accuracy.\n\n## Future Directions\n\n- Emerging trends include:\n  - Integration of generative AI models with ontology-based knowledge representation to improve diagnostic reasoning.\n  - Expansion of AI applications beyond radiology to pathology, cardiology, and multi-omics imaging.\n  - Development of adaptive, self-evolving ontologies to keep pace with medical knowledge growth.\n- Anticipated challenges:\n  - Ensuring regulatory compliance and clinical validation in diverse healthcare settings.\n  - Managing ethical concerns around AI transparency, bias, and patient data security.\n  - Achieving seamless interoperability across international standards and healthcare systems.\n- Research priorities:\n  - Robust ontology management techniques leveraging AI assistance.\n  - Enhanced semantic integration to support personalised medicine.\n  - Collaborative frameworks involving clinicians, AI developers, and regulatory bodies.\n\n## References\n\n1. Ambalavanan, S., et al. (2025). Ontologies as the semantic bridge between artificial intelligence and healthcare integration. *Frontiers in Digital Health*. DOI: 10.3389/fdgth.2025.1668385\n2. Rubin, D.L., et al. (2014). Radiology Gamuts Ontology: Differential Diagnosis for the Semantic Web. *Radiographics*, 34(1), 135-136. DOI: 10.1148/rg.341135036\n3. Additional references on ontology applications in medical imaging AI and standards integration as cited in the text.\n\n## Metadata\n\n- Last Updated: 2025-11-11\n- Review Status: Comprehensive editorial review\n- Verification: Academic sources verified\n- Regional Context: UK/North England where applicable",
  "backlinks": [],
  "wiki_links": [
    "MedicalAI"
  ],
  "ontology": {
    "term_id": "AI-0338",
    "preferred_term": "Medical Imaging AI",
    "alt_terms": [],
    "iri": "http://narrativegoldmine.com/ai#MedicalImagingAI",
    "source_domain": "ai",
    "domain": "ai",
    "domain_full_name": "Artificial Intelligence",
    "definition": "Medical Imaging AI encompasses artificial intelligence systems designed to analyse, interpret, and enhance medical images including radiological scans, pathology slides, and other diagnostic imaging modalities. These systems employ deep learning architectures, particularly convolutional neural networks, to perform tasks such as lesion detection, disease classification, segmentation of anatomical structures, and quantitative image analysis whilst adhering to clinical validation standards and regulatory requirements.",
    "scope_note": null,
    "status": "draft",
    "maturity": null,
    "version": null,
    "public_access": true,
    "last_updated": null,
    "authority_score": null,
    "quality_score": null,
    "cross_domain_links": null,
    "owl_class": "ai:MedicalImagingAI",
    "owl_physicality": null,
    "owl_role": null,
    "owl_inferred_class": null,
    "is_subclass_of": [
      "MedicalAI"
    ],
    "has_part": [],
    "is_part_of": [],
    "requires": [],
    "depends_on": [],
    "enables": [],
    "relates_to": [],
    "bridges_to": [],
    "bridges_from": [],
    "domain_extensions": {},
    "belongs_to_domain": [],
    "implemented_in_layer": [],
    "source": [],
    "validation": {
      "is_valid": false,
      "errors": [
        "Missing required property: last-updated",
        "Missing required property: owl:physicality",
        "Missing required property: owl:role"
      ]
    }
  }
}