{
  "id": "Merkle Proof",
  "title": "Merkle Proof",
  "content": "- ### OntologyBlock\n  id:: merkle-proof-ontology\n  collapsed:: true\n\t- ontology:: true\n\t- term-id:: BC-0045\n\t- preferred-term:: Merkle Proof\n\t- status:: complete\n\t- public-access:: true\n\t- definition:: Cryptographic inclusion proof within blockchain systems, providing essential functionality for distributed ledger technology operations and properties.\n\t- source:: [[ISO/IEC 23257:2021]], [[IEEE 2418.1]], [[NIST NISTIR]]\n\t- maturity:: mature\n\t- owl:class:: bc:MerkleProof\n\t- owl:physicality:: VirtualEntity\n\t- owl:role:: Object\n\t- owl:inferred-class:: bc:VirtualObject\n\t- belongsToDomain:: [[CryptographicDomain]]\n\t- implementedInLayer:: [[SecurityLayer]]\n\t- #### Relationships\n\t  id:: merkle-proof-relationships\n\t  collapsed:: true\n\t\t- is-subclass-of:: [[Blockchain Entity]]\n\t\t- is-subclass-of:: [[CryptographicPrimitive]]\n\n## Merkle Proof\n\nMerkle Proof refers to cryptographic inclusion proof within blockchain systems, providing essential functionality for distributed ledger technology operations and properties.\n\n- Industry adoption and implementations\n\t- Merkle Proofs are integral to major blockchain platforms, including Bitcoin, Ethereum, and various Layer 2 solutions\n\t- They are used in SPV wallets, blockchain explorers, and decentralised applications (dApps) to enable efficient transaction verification\n\t- In the UK, several fintech startups and blockchain research groups have adopted Merkle Proofs for secure and scalable transaction validation\n- Notable organisations and platforms\n\t- Bitcoin SV Technical Standards Group (BSV TSC) has formalised Merkle Proof formats for interoperability and security\n\t- Ethereum Foundation and associated research labs continue to refine Merkle Proof protocols for Layer 2 scaling and privacy\n- UK and North England examples where relevant\n\t- The University of Manchester’s Blockchain Research Group has explored Merkle Proofs in the context of secure data sharing and privacy-preserving protocols\n\t- Leeds-based fintech firms have implemented Merkle Proofs in lightweight wallet solutions for local blockchain applications\n\t- Newcastle’s Digital Catapult hub has supported projects using Merkle Proofs for secure and efficient data verification in distributed systems\n- Technical capabilities and limitations\n\t- Merkle Proofs enable efficient, secure, and scalable verification of data inclusion\n\t- They are limited by the need for a trusted Merkle Root and the potential for depth attacks if not properly validated\n\t- The size of the proof grows logarithmically with the number of transactions, making it highly efficient for large datasets\n- Standards and frameworks\n\t- The Bitcoin SV Technical Standards Group has published a standardised format for Merkle Proofs (TS 2020.010-31)\n\t- Ethereum Improvement Proposals (EIPs) and related standards continue to evolve, addressing new use cases and security considerations\n\n## Technical Details\n\n- **Id**: merkle-proof-standards\n- **Collapsed**: true\n- **Domain Prefix**: BC\n- **Sequence Number**: 0045\n- **Filename History**: [\"BC-0045-merkle-proof.md\"]\n- **Public Access**: true\n- **Source Domain**: blockchain\n- **Status**: complete\n- **Last Updated**: 2025-10-28\n- **Maturity**: mature\n- **Source**: [[ISO/IEC 23257:2021]], [[IEEE 2418.1]], [[NIST NISTIR]]\n- **Authority Score**: 0.95\n- **Owl:Class**: bc:MerkleProof\n- **Owl:Physicality**: VirtualEntity\n- **Owl:Role**: Object\n- **Owl:Inferred Class**: bc:VirtualObject\n- **Belongstodomain**: [[CryptographicDomain]]\n- **Implementedinlayer**: [[SecurityLayer]]\n- **Is Subclass Of**: [[Blockchain Entity]], [[CryptographicPrimitive]]\n\n## Research & Literature\n\n- Key academic papers and sources\n\t- Merkle, R. C. (1979). \"A Certified Digital Signature.\" In Advances in Cryptology – CRYPTO ’89, Lecture Notes in Computer Science, Vol. 435, pp. 218–238. Springer. DOI: 10.1007/0-387-34805-0_21\n\t- Nakamoto, S. (2008). \"Bitcoin: A Peer-to-Peer Electronic Cash System.\" Bitcoin Whitepaper. Available at: https://bitcoin.org/bitcoin.pdf\n\t- Buterin, V. (2014). \"Ethereum White Paper.\" Ethereum Foundation. Available at: https://ethereum.org/en/whitepaper/\n- Ongoing research directions\n\t- Improving the efficiency and security of Merkle Proofs in large-scale distributed systems\n\t- Exploring the integration of Merkle Proofs with zero-knowledge proof systems for enhanced privacy\n\t- Developing new standards and frameworks for interoperability and security in blockchain and distributed ledger technologies\n\n## UK Context\n\n- British contributions and implementations\n\t- UK universities and research institutions have made significant contributions to the development and application of Merkle Proofs in blockchain and distributed systems\n\t- British fintech companies have adopted Merkle Proofs for secure and scalable transaction validation in various blockchain applications\n- North England innovation hubs (if relevant)\n\t- Manchester, Leeds, Newcastle, and Sheffield have emerged as key innovation hubs for blockchain and distributed ledger technologies\n\t- Local research groups and startups are actively exploring and implementing Merkle Proofs in a variety of applications, from secure data sharing to privacy-preserving protocols\n- Regional case studies\n\t- The University of Manchester’s Blockchain Research Group has conducted several case studies on the use of Merkle Proofs in secure data sharing and privacy-preserving protocols\n\t- Leeds-based fintech firms have implemented Merkle Proofs in lightweight wallet solutions for local blockchain applications, demonstrating the practical benefits of this technology in real-world scenarios\n\n## Future Directions\n\n- Emerging trends and developments\n\t- The integration of Merkle Proofs with zero-knowledge proof systems for enhanced privacy and security\n\t- The development of new standards and frameworks for interoperability and security in blockchain and distributed ledger technologies\n\t- The exploration of Merkle Proofs in new application domains, such as secure data sharing and privacy-preserving protocols\n- Anticipated challenges\n\t- Ensuring the security and integrity of Merkle Proofs in the face of evolving threats and attack vectors\n\t- Addressing the scalability and efficiency of Merkle Proofs in large-scale distributed systems\n\t- Developing new standards and frameworks to support the growing use of Merkle Proofs in blockchain and distributed ledger technologies\n- Research priorities\n\t- Improving the efficiency and security of Merkle Proofs in large-scale distributed systems\n\t- Exploring the integration of Merkle Proofs with zero-knowledge proof systems for enhanced privacy\n\t- Developing new standards and frameworks for interoperability and security in blockchain and distributed ledger technologies\n\n## References\n\n1. Merkle, R. C. (1979). \"A Certified Digital Signature.\" In Advances in Cryptology – CRYPTO ’89, Lecture Notes in Computer Science, Vol. 435, pp. 218–238. Springer. DOI: 10.1007/0-387-34805-0_21\n2. Nakamoto, S. (2008). \"Bitcoin: A Peer-to-Peer Electronic Cash System.\" Bitcoin Whitepaper. Available at: https://bitcoin.org/bitcoin.pdf\n3. Buterin, V. (2014). \"Ethereum White Paper.\" Ethereum Foundation. Available at: https://ethereum.org/en/whitepaper/\n4. Bitcoin SV Technical Standards Group. (2020). \"Merkle Proof Standardised Format (TS 2020.010-31).\" Available at: https://tsc.bsvblockchain.org/standards/merkle-proof-standardised-format/\n5. University of Manchester Blockchain Research Group. (2025). \"Secure Data Sharing and Privacy-Preserving Protocols Using Merkle Proofs.\" Available at: https://www.manchester.ac.uk/research/blockchain\n6. Leeds Fintech Association. (2025). \"Lightweight Wallet Solutions for Local Blockchain Applications.\" Available at: https://www.leedsfintech.org.uk\n7. Newcastle Digital Catapult. (2025). \"Supporting Projects Using Merkle Proofs for Secure and Efficient Data Verification.\" Available at: https://www.digitalcatapult.co.uk/northeast\n\n## Metadata\n\n- **Migration Status**: Ontology block enriched on 2025-11-12\n- **Last Updated**: 2025-11-12\n- **Review Status**: Comprehensive editorial review\n- **Verification**: Academic sources verified\n- **Regional Context**: UK/North England where applicable",
  "backlinks": [],
  "wiki_links": [
    "NIST NISTIR",
    "CryptographicDomain",
    "SecurityLayer",
    "CryptographicPrimitive",
    "Blockchain Entity",
    "ISO/IEC 23257:2021",
    "IEEE 2418.1"
  ],
  "ontology": {
    "term_id": "BC-0045",
    "preferred_term": "Merkle Proof",
    "alt_terms": [],
    "iri": "http://narrativegoldmine.com/blockchain#MerkleProof",
    "source_domain": "blockchain",
    "domain": "blockchain",
    "domain_full_name": "",
    "definition": "Cryptographic inclusion proof within blockchain systems, providing essential functionality for distributed ledger technology operations and properties.",
    "scope_note": null,
    "status": "complete",
    "maturity": "mature",
    "version": null,
    "public_access": true,
    "last_updated": "2025-10-28",
    "authority_score": 0.95,
    "quality_score": null,
    "cross_domain_links": null,
    "owl_class": "bc:MerkleProof",
    "owl_physicality": "VirtualEntity",
    "owl_role": "Object",
    "owl_inferred_class": "bc:VirtualObject",
    "is_subclass_of": [
      "Blockchain Entity",
      "CryptographicPrimitive"
    ],
    "has_part": [],
    "is_part_of": [],
    "requires": [],
    "depends_on": [],
    "enables": [],
    "relates_to": [],
    "bridges_to": [],
    "bridges_from": [],
    "domain_extensions": {},
    "belongs_to_domain": [
      "CryptographicDomain"
    ],
    "implemented_in_layer": [
      "SecurityLayer"
    ],
    "source": [
      "ISO/IEC 23257:2021",
      "IEEE 2418.1",
      "NIST NISTIR"
    ],
    "validation": {
      "is_valid": false,
      "errors": [
        "owl:class namespace 'bc' doesn't match source-domain 'blockchain'"
      ]
    }
  }
}