{
  "id": "Merkle Tree",
  "title": "Merkle Tree",
  "content": "- ### OntologyBlock\n  id:: merkle-tree-ontology\n  collapsed:: true\n\t- ontology:: true\n\t- term-id:: BC-0029\n\t- preferred-term:: Merkle Tree\n\t- status:: complete\n\t- public-access:: true\n\t- definition:: Hierarchical hash data structure within blockchain systems, providing essential functionality for distributed ledger technology operations and properties.\n\t- source:: [[ISO/IEC 23257:2021]], [[IEEE 2418.1]], [[NIST NISTIR]]\n\t- maturity:: mature\n\t- owl:class:: bc:MerkleTree\n\t- owl:physicality:: VirtualEntity\n\t- owl:role:: Object\n\t- owl:inferred-class:: bc:VirtualObject\n\t- belongsToDomain:: [[CryptographicDomain]]\n\t- implementedInLayer:: [[SecurityLayer]]\n\t- #### Relationships\n\t  id:: merkle-tree-relationships\n\t  collapsed:: true\n\t\t- is-subclass-of:: [[Blockchain Entity]]\n\t\t- is-subclass-of:: [[CryptographicPrimitive]]\n\n## Merkle Tree\n\nMerkle Tree refers to hierarchical hash data structure within blockchain systems, providing essential functionality for distributed ledger technology operations and properties.\n\n- Merkle trees remain integral to blockchain systems such as Bitcoin and Ethereum.\n  - Bitcoin uses Merkle trees to summarise transactions within blocks, enabling Simplified Payment Verification (SPV) for lightweight clients.\n  - Ethereum employs a variant called the Merkle Patricia Trie for state and transaction commitments.\n- Industry adoption extends beyond cryptocurrencies to banking, supply chain, and distributed ledger technologies.\n  - Applications include tamper-proof audit trails, proof-of-reserves, and efficient interbank settlements.\n- Notable organisations utilising Merkle trees include major blockchain platforms and financial institutions exploring cryptographic proofs for transparency.\n- In the UK, blockchain startups and fintech firms in London and Manchester incorporate Merkle tree structures for secure data verification.\n- Technical capabilities:\n  - Merkle proofs allow verification with logarithmic complexity relative to dataset size.\n  - Limitations include computational overhead for very large datasets and challenges in dynamic data updates.\n- Standards and frameworks continue to evolve, with ongoing work on interoperability and optimisation within Web3 protocols.\n\n## Technical Details\n\n- **Id**: merkle-tree-standards\n- **Collapsed**: true\n- **Domain Prefix**: BC\n- **Sequence Number**: 0029\n- **Filename History**: [\"BC-0029-merkle-tree.md\"]\n- **Public Access**: true\n- **Source Domain**: metaverse\n- **Status**: complete\n- **Last Updated**: 2025-10-28\n- **Maturity**: mature\n- **Source**: [[ISO/IEC 23257:2021]], [[IEEE 2418.1]], [[NIST NISTIR]]\n- **Authority Score**: 0.95\n- **Owl:Class**: bc:MerkleTree\n- **Owl:Physicality**: VirtualEntity\n- **Owl:Role**: Object\n- **Owl:Inferred Class**: bc:VirtualObject\n- **Belongstodomain**: [[CryptographicDomain]]\n- **Implementedinlayer**: [[SecurityLayer]]\n- **Is Subclass Of**: [[Blockchain Entity]], [[CryptographicPrimitive]]\n\n## Research & Literature\n\n- Key academic papers and sources:\n  - Merkle, R.C. (1987). \"A Digital Signature Based on a Conventional Encryption Function.\" *Advances in Cryptology — CRYPTO '87*, Lecture Notes in Computer Science, vol 293. Springer. DOI: 10.1007/3-540-48184-2_32\n  - Crosby, S.A., & Wallach, D.S. (2009). \"Efficient Data Structures for Tamper-Evident Logging.\" *USENIX Security Symposium*. URL: https://www.usenix.org/legacy/event/sec09/tech/full_papers/crosby.pdf\n  - Bonneau, J., et al. (2015). \"SoK: Research Perspectives and Challenges for Bitcoin and Cryptocurrencies.\" *IEEE Symposium on Security and Privacy*. DOI: 10.1109/SP.2015.14\n- Ongoing research focuses on:\n  - Enhancing Merkle tree variants (e.g., Sparse Merkle Trees) for scalability and privacy.\n  - Integration with zero-knowledge proofs to improve confidentiality.\n  - Optimising Merkle tree computations for resource-constrained environments.\n\n## UK Context\n\n- The UK has a vibrant blockchain and cryptography research community, with universities such as the University of Manchester and University of Leeds contributing to cryptographic protocol development.\n- North England innovation hubs, including Manchester’s Digital Innovation Hub and Leeds’ Blockchain Lab, support startups and research projects leveraging Merkle trees for secure data verification.\n- Regional case studies:\n  - Sheffield-based fintech firms have piloted Merkle tree-based proof-of-reserves systems to enhance transparency without compromising client confidentiality.\n  - Newcastle’s blockchain initiatives explore Merkle tree applications in supply chain provenance and public sector data integrity.\n- British contributions often focus on practical implementations and regulatory-compliant cryptographic solutions, balancing security with usability.\n\n## Future Directions\n\n- Emerging trends:\n  - Wider adoption of Merkle tree variants in Web3, DeFi, and cross-chain interoperability.\n  - Integration with advanced cryptographic techniques such as zk-SNARKs and homomorphic encryption.\n- Anticipated challenges:\n  - Managing computational costs as datasets grow exponentially.\n  - Ensuring privacy while maintaining verifiability in public ledgers.\n  - Standardising Merkle tree implementations across diverse platforms.\n- Research priorities include:\n  - Developing lightweight Merkle tree constructions for IoT and edge computing.\n  - Enhancing dynamic update capabilities without full recomputation.\n  - Exploring Merkle tree applications beyond blockchain, such as secure machine learning data provenance.\n\n## References\n\n1. Merkle, R.C. (1987). \"A Digital Signature Based on a Conventional Encryption Function.\" *Advances in Cryptology — CRYPTO '87*, Lecture Notes in Computer Science, vol 293. Springer. DOI: 10.1007/3-540-48184-2_32\n2. Crosby, S.A., & Wallach, D.S. (2009). \"Efficient Data Structures for Tamper-Evident Logging.\" *USENIX Security Symposium*. Available at: https://www.usenix.org/legacy/event/sec09/tech/full_papers/crosby.pdf\n3. Bonneau, J., Miller, A., Clark, J., Narayanan, A., Kroll, J.A., & Felten, E.W. (2015). \"SoK: Research Perspectives and Challenges for Bitcoin and Cryptocurrencies.\" *IEEE Symposium on Security and Privacy*. DOI: 10.1109/SP.2015.14\n4. Nakamoto, S. (2008). \"Bitcoin: A Peer-to-Peer Electronic Cash System.\" Available at: https://bitcoin.org/bitcoin.pdf\n5. Wood, G. (2014). \"Ethereum: A Secure Decentralised Generalised Transaction Ledger.\" Ethereum Project Yellow Paper. Available at: https://ethereum.github.io/yellowpaper/paper.pdf\n*If Merkle trees were a family, they’d be the reliable relatives who always keep the family secrets safe — and never forget a thing.*\n\n## Metadata\n\n- **Migration Status**: Ontology block enriched on 2025-11-12\n- **Last Updated**: 2025-11-12\n- **Review Status**: Comprehensive editorial review\n- **Verification**: Academic sources verified\n- **Regional Context**: UK/North England where applicable",
  "backlinks": [
    "BC-0044-merkle-root",
    "Distributed Ledger Technology (DLT)",
    "BC-0045-merkle-proof",
    "SHA-256"
  ],
  "wiki_links": [
    "NIST NISTIR",
    "CryptographicDomain",
    "SecurityLayer",
    "CryptographicPrimitive",
    "Blockchain Entity",
    "ISO/IEC 23257:2021",
    "IEEE 2418.1"
  ],
  "ontology": {
    "term_id": "BC-0029",
    "preferred_term": "Merkle Tree",
    "alt_terms": [],
    "iri": "http://narrativegoldmine.com/blockchain#MerkleTree",
    "source_domain": "metaverse",
    "domain": "metaverse",
    "domain_full_name": "",
    "definition": "Hierarchical hash data structure within blockchain systems, providing essential functionality for distributed ledger technology operations and properties.",
    "scope_note": null,
    "status": "complete",
    "maturity": "mature",
    "version": null,
    "public_access": true,
    "last_updated": "2025-10-28",
    "authority_score": 0.95,
    "quality_score": null,
    "cross_domain_links": null,
    "owl_class": "bc:MerkleTree",
    "owl_physicality": "VirtualEntity",
    "owl_role": "Object",
    "owl_inferred_class": "bc:VirtualObject",
    "is_subclass_of": [
      "Blockchain Entity",
      "CryptographicPrimitive"
    ],
    "has_part": [],
    "is_part_of": [],
    "requires": [],
    "depends_on": [],
    "enables": [],
    "relates_to": [],
    "bridges_to": [],
    "bridges_from": [],
    "domain_extensions": {},
    "belongs_to_domain": [
      "CryptographicDomain"
    ],
    "implemented_in_layer": [
      "SecurityLayer"
    ],
    "source": [
      "ISO/IEC 23257:2021",
      "IEEE 2418.1",
      "NIST NISTIR"
    ],
    "validation": {
      "is_valid": false,
      "errors": [
        "owl:class namespace 'bc' doesn't match source-domain 'metaverse'"
      ]
    }
  }
}