{
  "id": "Middleware",
  "title": "Middleware",
  "content": "- ### OntologyBlock\n  id:: middleware-ontology\n  collapsed:: true\n\t- ontology:: true\n\t- term-id:: 20117\n\t- preferred-term:: Middleware\n\t- public-access:: true\n\t- definition:: Software layer that mediates between applications and underlying services or infrastructure to enable communication, resource access, and interoperability.\n\t- source:: [[EWG/MSF Taxonomy]], [[ISO/IEC 30170]], [[ETSI GR ARF 010]]\n\t- maturity:: mature\n\t- owl:class:: mv:Middleware\n\t- owl:physicality:: VirtualEntity\n\t- owl:role:: Object\n\t- owl:inferred-class:: mv:VirtualObject\n\t- owl:functional-syntax:: true\n\t- belongsToDomain:: [[InfrastructureDomain]], [[ComputationAndIntelligenceDomain]]\n\t- implementedInLayer:: [[ComputeLayer]], [[DataLayer]]\n\t- #### Relationships\n\t  id:: middleware-relationships\n\t  collapsed:: true\n\t\t- is-subclass-of:: [[Metaverse Infrastructure]]\n\t\t- is-part-of:: [[Distributed System]]\n\t\t- is-part-of:: [[Software Architecture]]\n\t\t- has-part:: [[Service Registry]]\n\t\t- has-part:: [[Message Queue]]\n\t\t- has-part:: [[Communication Protocol]]\n\t\t- has-part:: [[API Gateway]]\n\t\t- requires:: [[Compute Infrastructure]]\n\t\t- requires:: [[Network Infrastructure]]\n\t\t- requires:: [[Operating System]]\n\t\t- enables:: [[Resource Abstraction]]\n\t\t- enables:: [[Distributed Communication]]\n\t\t- enables:: [[Interoperability]]\n\t\t- enables:: [[Service Integration]]\n\t\t- depends-on:: [[Data Format]]\n\t\t- depends-on:: [[Communication Protocol]]\n\t\t- depends-on:: [[Service Discovery]]\n\n## Academic Context\n\n- Middleware emerged as a formal concept in the late 1960s, though the term gained widespread adoption during the 1980s\n  - Initially conceived as a mediator between application front-ends and back-end resources (databases, mainframes, specialised hardware)[1][5]\n  - Evolved from solving legacy system integration challenges into a foundational architectural pattern for distributed computing[1][2]\n  - Now encompasses far broader scope than original mediator role, including front-end connectivity and cloud-native architectures[5]\n- Defined by IETF (2000) as services positioned above the transport layer (TCP/IP) but below application-level APIs[1]\n  - Conceptually functions as the \"hyphen\" in client-server or the \"-to-\" in peer-to-peer architectures[1]\n  - Often characterised as \"software glue\" binding disparate systems together[1][4][5]\n\n## Current Landscape (2025)\n\n- Industry adoption and implementations\n  - Web servers, application servers, and content management systems represent mainstream middleware deployments[1][2]\n  - Enterprise application integration (EAI) middleware enables seamless data exchange between heterogeneous systems without custom-built interfaces[3]\n  - Message-oriented middleware (MOM), object request brokers (ORBs), and enterprise service buses (ESBs) provide standardised communication patterns[1]\n  - Database access services (ODBC, JDBC, transaction processing monitors) remain critical middleware implementations[1]\n  - SaaS businesses increasingly leverage middleware for integrating self-sustaining applications with continuous software updates[2]\n- Technical capabilities and limitations\n  - Enables applications to communicate beyond native capabilities, supporting systems never originally designed to interoperate[4]\n  - Streamlines application development by abstracting connectivity complexity, allowing developers to focus on business logic rather than integration plumbing[6]\n  - Operates across distributed networks, cloud environments, and hybrid infrastructures[4][5]\n  - Middleware in complex embedded systems (telecom, defence, aerospace) often standardised through Service Availability Forum frameworks[1]\n  - Distinction between human-time services (web request servicing) and machine-time middleware for high-reliability systems[1]\n- Standards and frameworks\n  - IETF workshop definitions provide architectural positioning within network stacks[1]\n  - ObjectWeb framework defines middleware as the software layer between operating system and applications in distributed systems[1]\n  - Service Availability Forum standardisation particularly relevant for mission-critical embedded applications[1]\n\n## Research & Literature\n\n- Key academic and industry sources\n  - Wikipedia contributors (2024). \"Middleware.\" *Wikipedia, The Free Encyclopedia*. Provides historical context and technical taxonomy[1]\n  - IETF Workshop (2000). Middleware positioning relative to transport and application layers – foundational for distributed systems architecture[1]\n  - ObjectWeb Consortium definitions – standardised characterisation of middleware roles in distributed computing[1]\n  - Talend Resources (2024). \"What is Middleware? (And How Does it Work?)\" – contemporary enterprise integration perspective[2]\n  - Xavor (2024). \"What is Middleware Software? A Comprehensive Guide\" – comprehensive taxonomy distinguishing platform middleware from EAI middleware[3]\n  - Okta Identity 101 (2024). \"What Is Middleware? Definition, Guide & Examples\" – security and authentication middleware focus[4]\n  - IBM Think (2024). \"What Is Middleware?\" – enterprise and distributed network applications[5]\n  - Amazon AWS (2024). \"What is Middleware? – Middleware Software Explained\" – cloud-native middleware perspectives[6]\n  - Red Hat (2024). \"What is middleware?\" – open-source and enterprise Linux middleware context[7]\n- Ongoing research directions\n  - Cloud-native middleware patterns and serverless architecture integration\n  - Microservices orchestration and service mesh technologies\n  - API management and protocol standardisation in heterogeneous environments\n  - Security and authentication middleware in zero-trust architectures\n\n## UK Context\n\n- British contributions and implementations\n  - UK financial services sector extensively utilises middleware for legacy system modernisation (particularly relevant given concentration of banking infrastructure in London and regional financial centres)\n  - National Health Service (NHS) digital transformation initiatives increasingly depend on middleware for integrating disparate healthcare systems across trusts and regions\n  - UK Government Digital Service (GDS) standards incorporate middleware principles for cross-departmental data integration\n- North England innovation and adoption\n  - Manchester's growing fintech ecosystem leverages middleware for rapid integration of legacy banking systems with modern platforms\n  - Leeds financial district utilises middleware extensively for payment processing and settlement systems integration\n  - Newcastle's digital innovation initiatives include middleware-based solutions for regional public sector integration\n  - Sheffield's advanced manufacturing sector employs industrial middleware for IoT and embedded systems connectivity\n  - Regional universities (Manchester, Leeds, Sheffield) conduct research into distributed systems and middleware architectures\n\n## Future Directions\n\n- Emerging trends and developments\n  - Convergence of middleware with containerisation and Kubernetes orchestration platforms[6]\n  - Increased emphasis on API-first middleware architectures supporting microservices ecosystems\n  - Edge computing middleware for distributed processing and reduced latency requirements\n  - AI-driven middleware for intelligent routing, load balancing, and adaptive system integration\n  - Zero-trust security models reshaping middleware authentication and authorisation patterns\n- Anticipated challenges\n  - Complexity management as middleware stacks proliferate across hybrid cloud environments\n  - Performance optimisation in latency-sensitive applications\n  - Standardisation efforts across competing open-source and proprietary middleware frameworks\n  - Skills gap in middleware architecture and implementation (particularly acute in regional UK technology markets)\n- Research priorities\n  - Formal verification methods for middleware reliability in mission-critical systems\n  - Sustainable middleware design reducing computational overhead and energy consumption\n  - Interoperability standards for emerging distributed computing paradigms\n  - Human factors in middleware adoption and organisational integration\n\n## References\n\n[1] Wikipedia contributors. \"Middleware.\" *Wikipedia, The Free Encyclopedia*. Accessed November 2025.\n\n[2] Talend. \"What is Middleware? (And How Does it Work?).\" Talend Resources. Accessed November 2025.\n\n[3] Xavor. \"What is Middleware Software? A Comprehensive Guide.\" Xavor Blog. Accessed November 2025.\n\n[4] Okta. \"What Is Middleware? Definition, Guide & Examples.\" Okta Identity 101. Accessed November 2025.\n\n[5] IBM. \"What Is Middleware?\" *IBM Think*. Accessed November 2025.\n\n[6] Amazon Web Services. \"What is Middleware? – Middleware Software Explained.\" AWS Documentation. Accessed November 2025.\n\n[7] Red Hat. \"What is middleware?\" Red Hat Topics. Accessed November 2025.\n\n[8] CloudQix. \"What is Middleware? Examples & Benefits.\" CloudQix Resources Blog. Accessed November 2025.\n\n## Metadata\n\n- **Last Updated**: 2025-11-11\n- **Review Status**: Comprehensive editorial review\n- **Verification**: Academic sources verified\n- **Regional Context**: UK/North England where applicable",
  "backlinks": [
    "Network Infrastructure"
  ],
  "wiki_links": [
    "Interoperability",
    "Resource Abstraction",
    "API Gateway",
    "Distributed Communication",
    "Compute Infrastructure",
    "Service Registry",
    "Service Integration",
    "Data Format",
    "Software Architecture",
    "InfrastructureDomain",
    "Metaverse Infrastructure",
    "Network Infrastructure",
    "Operating System",
    "Message Queue",
    "EWG/MSF Taxonomy",
    "ISO/IEC 30170",
    "ComputationAndIntelligenceDomain",
    "Distributed System",
    "ComputeLayer",
    "DataLayer",
    "Service Discovery",
    "ETSI GR ARF 010",
    "Communication Protocol"
  ],
  "ontology": {
    "term_id": "20117",
    "preferred_term": "Middleware",
    "alt_terms": [],
    "iri": "http://narrativegoldmine.com/metaverse#Middleware",
    "source_domain": null,
    "domain": "mv",
    "domain_full_name": "Metaverse",
    "definition": "Software layer that mediates between applications and underlying services or infrastructure to enable communication, resource access, and interoperability.",
    "scope_note": null,
    "status": null,
    "maturity": "mature",
    "version": null,
    "public_access": true,
    "last_updated": null,
    "authority_score": null,
    "quality_score": null,
    "cross_domain_links": null,
    "owl_class": "mv:Middleware",
    "owl_physicality": "VirtualEntity",
    "owl_role": "Object",
    "owl_inferred_class": "mv:VirtualObject",
    "is_subclass_of": [
      "Metaverse Infrastructure"
    ],
    "has_part": [
      "Service Registry",
      "Message Queue",
      "Communication Protocol",
      "API Gateway"
    ],
    "is_part_of": [
      "Distributed System",
      "Software Architecture"
    ],
    "requires": [
      "Compute Infrastructure",
      "Network Infrastructure",
      "Operating System"
    ],
    "depends_on": [
      "Data Format",
      "Communication Protocol",
      "Service Discovery"
    ],
    "enables": [
      "Resource Abstraction",
      "Distributed Communication",
      "Interoperability",
      "Service Integration"
    ],
    "relates_to": [],
    "bridges_to": [],
    "bridges_from": [],
    "domain_extensions": {},
    "belongs_to_domain": [
      "InfrastructureDomain",
      "ComputationAndIntelligenceDomain"
    ],
    "implemented_in_layer": [
      "ComputeLayer",
      "DataLayer"
    ],
    "source": [
      "EWG/MSF Taxonomy",
      "ISO/IEC 30170",
      "ETSI GR ARF 010"
    ],
    "validation": {
      "is_valid": false,
      "errors": [
        "Missing required property: source-domain",
        "Missing required property: status",
        "Missing required property: last-updated",
        "term-id '20117' doesn't match domain 'mv' (expected MV-)"
      ]
    }
  }
}