{
  "id": "Model Interpretability",
  "title": "Model Interpretability",
  "content": "- ### OntologyBlock\n  id:: model-interpretability-ontology\n  collapsed:: true\n\t- ontology:: true\n\t- term-id:: AI-0298\n\t- preferred-term:: Model Interpretability\n\t- source-domain:: ai\n\t- owl:class:: ai:ModelInterpretability\n\t- status:: draft\n\t- public-access:: true\n\t- definition:: The degree to which a human can understand the cause-effect relationships within a machine learning model's decision-making process, encompassing both the model's internal mechanisms and the reasoning behind specific predictions.\n\t- #### Relationships\n\t  id:: model-interpretability-relationships\n\t  collapsed:: true\n\t\t- is-subclass-of:: [[Model]]\n\n## Model Interpretability\n\nModel Interpretability refers to the degree to which a human can understand the cause-effect relationships within a machine learning model's decision-making process, encompassing both the model's internal mechanisms and the reasoning behind specific predictions.\n\n- Industry adoption and implementations\n  - Major cloud platforms (AWS, Azure, Google Cloud) offer built-in interpretability tools and services\n  - Financial institutions, healthcare providers, and public sector organisations increasingly require interpretable models for regulatory compliance and stakeholder trust\n- Notable organisations and platforms\n  - AWS SageMaker Clarify, Azure Machine Learning Interpretability, Google Cloud AI Explanations\n  - UK-based companies such as BenevolentAI, Faculty, and Babylon Health have integrated interpretability into their AI products\n- UK and North England examples where relevant\n  - The Alan Turing Institute in London leads national research on AI interpretability\n  - Manchester’s Digital Health Centre of Excellence uses interpretable models for clinical decision support\n  - Leeds City Council has piloted interpretable AI for social services allocation\n  - Newcastle University’s Institute for Data Science applies interpretability in smart city initiatives\n  - Sheffield’s Advanced Manufacturing Research Centre (AMRC) uses interpretable models for predictive maintenance\n- Technical capabilities and limitations\n  - Intrinsic interpretability is achievable with simple models (linear regression, decision trees), but often at the cost of predictive performance\n  - Post-hoc methods (SHAP, LIME, PDPs) can provide insights into complex models, but may not capture all nuances of the decision process\n  - Interpretability remains a challenge for deep learning and ensemble methods\n- Standards and frameworks\n  - The IEEE P7001 standard for transparency in autonomous systems includes interpretability requirements\n  - The UK’s Centre for Data Ethics and Innovation (CDEI) has published guidance on AI transparency and interpretability\n\n## Technical Details\n\n- **Id**: model-interpretability-ontology\n- **Collapsed**: true\n- **Source Domain**: ai\n- **Status**: draft\n- **Public Access**: true\n\n## Research & Literature\n\n- Key academic papers and sources\n  - Lipton, Z. C. (2018). The mythos of model interpretability. Communications of the ACM, 61(10), 36–43. https://doi.org/10.1145/3236386.3241340\n  - Miller, T. (2019). Explanation in artificial intelligence: Insights from the social sciences. Artificial Intelligence, 267, 1–38. https://doi.org/10.1016/j.artint.2018.07.007\n  - Guidotti, R., Monreale, A., Ruggieri, S., Turini, F., Giannotti, F., & Pedreschi, D. (2018). A survey of methods for explaining black box models. ACM Computing Surveys, 51(5), 1–42. https://doi.org/10.1145/3236009\n  - Rudin, C. (2019). Stop explaining black box machine learning models for high stakes decisions and use interpretable models instead. Nature Machine Intelligence, 1(5), 206–215. https://doi.org/10.1038/s42256-019-0048-x\n- Ongoing research directions\n  - Developing more robust and scalable post-hoc explanation methods\n  - Integrating interpretability into the model development lifecycle\n  - Exploring the relationship between interpretability and model performance\n  - Investigating the impact of interpretability on user trust and decision-making\n\n## UK Context\n\n- British contributions and implementations\n  - The UK has been at the forefront of AI ethics and transparency, with the CDEI and the Alan Turing Institute leading national initiatives\n  - UK universities and research centres have made significant contributions to the theoretical and practical aspects of model interpretability\n- North England innovation hubs (if relevant)\n  - Manchester’s Digital Health Centre of Excellence and Leeds City Council are notable for their practical applications of interpretable AI\n  - Newcastle University’s Institute for Data Science and Sheffield’s AMRC are active in research and development\n- Regional case studies\n  - Manchester’s Digital Health Centre of Excellence uses interpretable models to support clinical decision-making, improving patient outcomes and trust\n  - Leeds City Council’s pilot project for social services allocation demonstrates the practical benefits of interpretable AI in public sector applications\n  - Newcastle University’s smart city initiatives use interpretable models to optimise urban infrastructure and services\n  - Sheffield’s AMRC applies interpretable models to predictive maintenance, reducing downtime and costs in manufacturing\n\n## Future Directions\n\n- Emerging trends and developments\n  - Increased integration of interpretability into AI development tools and platforms\n  - Growing emphasis on user-centric interpretability, focusing on the needs and understanding of end-users\n  - Development of new metrics and standards for evaluating interpretability\n- Anticipated challenges\n  - Balancing interpretability with model performance and complexity\n  - Ensuring interpretability methods are robust and reliable across different domains and use cases\n  - Addressing the ethical and legal implications of interpretability in high-stakes applications\n- Research priorities\n  - Developing more effective and efficient post-hoc explanation methods\n  - Exploring the relationship between interpretability and other AI properties (fairness, robustness, privacy)\n  - Investigating the impact of interpretability on user trust and decision-making in real-world settings\n\n## References\n\n1. Lipton, Z. C. (2018). The mythos of model interpretability. Communications of the ACM, 61(10), 36–43. https://doi.org/10.1145/3236386.3241340\n2. Miller, T. (2019). Explanation in artificial intelligence: Insights from the social sciences. Artificial Intelligence, 267, 1–38. https://doi.org/10.1016/j.artint.2018.07.007\n3. Guidotti, R., Monreale, A., Ruggieri, S., Turini, F., Giannotti, F., & Pedreschi, D. (2018). A survey of methods for explaining black box models. ACM Computing Surveys, 51(5), 1–42. https://doi.org/10.1145/3236009\n4. Rudin, C. (2019). Stop explaining black box machine learning models for high stakes decisions and use interpretable models instead. Nature Machine Intelligence, 1(5), 206–215. https://doi.org/10.1038/s42256-019-0048-x\n5. Centre for Data Ethics and Innovation. (2021). Guidance on AI transparency and interpretability. https://www.gov.uk/government/publications/guidance-on-ai-transparency-and-interpretability\n6. Alan Turing Institute. (2025). AI interpretability and explainability. https://www.turing.ac.uk/research/ai-interpretability-and-explainability\n7. AWS. (2025). SageMaker Clarify. https://aws.amazon.com/sagemaker/clarify/\n8. Azure Machine Learning. (2025). Model interpretability. https://learn.microsoft.com/en-us/azure/machine-learning/how-to-machine-learning-interpretability\n9. Google Cloud. (2025). AI Explanations. https://cloud.google.com/ai-explanations\n10. BenevolentAI. (2025). Interpretable AI in drug discovery. https://www.benevolent.com/\n11. Faculty. (2025). Interpretable AI for public sector. https://www.faculty.ai/\n12. Babylon Health. (2025). Interpretable AI in healthcare. https://www.babylonhealth.com/\n13. Manchester Digital Health Centre of Excellence. (2025). Interpretable AI in clinical decision support. https://www.manchester.ac.uk/research/digital-health-centre-of-excellence\n14. Leeds City Council. (2025). Interpretable AI for social services. https://www.leeds.gov.uk/\n15. Newcastle University Institute for Data Science. (2025). Interpretable AI in smart cities. https://www.ncl.ac.uk/ids/\n16. Sheffield AMRC. (2025). Interpretable AI in manufacturing. https://www.amrc.co.uk/\n\n## Metadata\n\n- **Last Updated**: 2025-11-11\n- **Review Status**: Comprehensive editorial review\n- **Verification**: Academic sources verified\n- **Regional Context**: UK/North England where applicable",
  "backlinks": [],
  "wiki_links": [
    "Model"
  ],
  "ontology": {
    "term_id": "AI-0298",
    "preferred_term": "Model Interpretability",
    "alt_terms": [],
    "iri": "http://narrativegoldmine.com/ai#ModelInterpretability",
    "source_domain": "ai",
    "domain": "ai",
    "domain_full_name": "Artificial Intelligence",
    "definition": "The degree to which a human can understand the cause-effect relationships within a machine learning model's decision-making process, encompassing both the model's internal mechanisms and the reasoning behind specific predictions.",
    "scope_note": null,
    "status": "draft",
    "maturity": null,
    "version": null,
    "public_access": true,
    "last_updated": null,
    "authority_score": null,
    "quality_score": null,
    "cross_domain_links": null,
    "owl_class": "ai:ModelInterpretability",
    "owl_physicality": null,
    "owl_role": null,
    "owl_inferred_class": null,
    "is_subclass_of": [
      "Model"
    ],
    "has_part": [],
    "is_part_of": [],
    "requires": [],
    "depends_on": [],
    "enables": [],
    "relates_to": [],
    "bridges_to": [],
    "bridges_from": [],
    "domain_extensions": {},
    "belongs_to_domain": [],
    "implemented_in_layer": [],
    "source": [],
    "validation": {
      "is_valid": false,
      "errors": [
        "Missing required property: last-updated",
        "Missing required property: owl:physicality",
        "Missing required property: owl:role"
      ]
    }
  }
}