{
  "id": "mT5",
  "title": "mT5",
  "content": "- ### OntologyBlock\n  id:: mt5-ontology\n  collapsed:: true\n\t- ontology:: true\n\t- term-id:: AI-0224\n\t- preferred-term:: mT5\n\t- source-domain:: metaverse\n\t- status:: draft\n\t- public-access:: true\n\n\n\n\n### OWL Classification\n\t- owl:class:: mv:mT5\n\t- owl:physicality:: ConceptualEntity\n\t- owl:role:: Concept\n\n### Domain & Architecture\n\t- belongsToDomain:: [[MetaverseDomain]]\n\t- maturity:: draft\n\n### Relationships\n\n## OWL Formal Semantics\n\n```clojure\n;; OWL Functional Syntax\n\n(Declaration (Class :Mt5))\n\n;; Annotations\n(AnnotationAssertion rdfs:label :Mt5 \"mT5\"@en)\n(AnnotationAssertion rdfs:comment :Mt5 \"Multilingual T5: a massively multilingual variant of T5 pre-trained on the mC4 corpus covering 101 languages, using the same text-to-text framework as T5.\"@en)\n\n;; Data Properties\n(AnnotationAssertion dcterms:identifier :Mt5 \"AI-0224\"^^xsd:string)\n(DataPropertyAssertion :isAITechnology :Mt5 \"true\"^^xsd:boolean)\n```\n\n## Characteristics\n\n- **Multilingual Coverage**: Supports 101 languages\n- **Text-to-Text Framework**: Same unified approach as T5\n- **mC4 Corpus**: Multilingual Common Crawl dataset\n- **Cross-Lingual Transfer**: Enables zero-shot cross-lingual performance\n\n## Academic Foundations\n\n**Primary Source**: Xue et al., \"mT5: A Massively Multilingual Pre-trained Text-to-Text Transformer\", arXiv:2010.11934 (2020)\n\n**Dataset**: Introduces mC4 (multilingual C4) covering 101 languages.\n\n## Technical Context\n\nmT5 extends T5's text-to-text framework to multilingual settings, demonstrating that the same pre-training approach works effectively across diverse languages. It shows strong cross-lingual transfer, enabling zero-shot performance on languages with limited training data.\n\n## Ontological Relationships\n\n- **Broader Term**: Pre-trained Language Model, Multilingual Model\n- **Related Terms**: T5, mBERT, XLM-R\n- **Base Architecture**: T5 with multilingual training\n\n## Usage Context\n\n\"mT5 enables cross-lingual transfer across 101 languages using T5's unified text-to-text framework.\"\n\n## References\n\n- Xue, L., et al. (2020). \"mT5: A Massively Multilingual Pre-trained Text-to-Text Transformer\". arXiv:2010.11934\n\n---\n\n*Ontology Term managed by AI-Grounded Ontology Working Group*\n*UK English Spelling Standards Applied*\n\t- maturity:: draft\n\t- owl:class:: mv:mT5\n\t- owl:physicality:: ConceptualEntity\n\t- owl:role:: Concept\n\t- is-subclass-of:: [[ArtificialIntelligence]]\n\t- belongsToDomain:: [[MetaverseDomain]]",
  "backlinks": [],
  "wiki_links": [
    "ArtificialIntelligence",
    "MetaverseDomain"
  ],
  "ontology": {
    "term_id": "AI-0224",
    "preferred_term": "mT5",
    "alt_terms": [],
    "iri": "http://narrativegoldmine.com/metaverse#mT5",
    "source_domain": "metaverse",
    "domain": "metaverse",
    "domain_full_name": "",
    "definition": null,
    "scope_note": null,
    "status": "draft",
    "maturity": "draft",
    "version": null,
    "public_access": true,
    "last_updated": null,
    "authority_score": null,
    "quality_score": null,
    "cross_domain_links": null,
    "owl_class": "mv:mT5",
    "owl_physicality": "ConceptualEntity",
    "owl_role": "Concept",
    "owl_inferred_class": null,
    "is_subclass_of": [],
    "has_part": [],
    "is_part_of": [],
    "requires": [],
    "depends_on": [],
    "enables": [],
    "relates_to": [],
    "bridges_to": [],
    "bridges_from": [],
    "domain_extensions": {},
    "belongs_to_domain": [
      "MetaverseDomain",
      "MetaverseDomain"
    ],
    "implemented_in_layer": [],
    "source": [],
    "validation": {
      "is_valid": false,
      "errors": [
        "Missing required property: last-updated",
        "Missing required property: definition",
        "Missing required property: is-subclass-of (at least one parent class)",
        "owl:class namespace 'mv' doesn't match source-domain 'metaverse'"
      ]
    }
  }
}