{
  "id": "Multiverse",
  "title": "Multiverse",
  "content": "- ### OntologyBlock\n  id:: multiverse-ontology\n  collapsed:: true\n\t- ontology:: true\n\t- term-id:: 20316\n\t- source-domain:: metaverse\n\t- status:: draft\n    - public-access:: true\n\t- preferred-term:: Multiverse\n\t- definition:: A network of interconnected but distinct metaverses and virtual worlds that enable cross-platform identity, asset portability, and interoperability while maintaining individual world sovereignty and distinct governance models.\n\t- maturity:: draft\n\t- source:: [[OMA3]], [[Metaverse Standards Forum]]\n\t- owl:class:: mv:Multiverse\n\t- owl:physicality:: VirtualEntity\n\t- owl:role:: Object\n\t- owl:inferred-class:: mv:VirtualObject\n\t- owl:functional-syntax:: true\n\t- belongsToDomain:: [[InfrastructureDomain]], [[VirtualSocietyDomain]]\n\t- implementedInLayer:: [[ApplicationLayer]]\n\t- #### Relationships\n\t  id:: multiverse-relationships\n\t\t- is-subclass-of:: [[Metaverse Infrastructure]]\n\t\t- has-part:: [[Metaverse]], [[Interoperability Protocol]], [[Federated Identity]], [[Cross-Chain Bridge]], [[Portal System]], [[Multi-World Governance]], [[Asset Translation Layer]], [[Universal Inventory]]\n\t\t- is-part-of:: [[Spatial Web]]\n\t\t- requires:: [[Identity Federation]], [[Protocol Translation]], [[Asset Bridging]], [[Distributed Governance]], [[Standard Format Support]], [[Cross-Platform Authentication]]\n\t\t- depends-on:: [[Blockchain]], [[Decentralized Identifier]], [[Verifiable Credential]], [[Smart Contract]], [[Interoperability Standard]]\n\t\t- enables:: [[Cross-World Travel]], [[Asset Portability]], [[Multi-Platform Gaming]], [[Federated Social Networks]], [[Cross-Metaverse Commerce]], [[Universal Avatar]]\n\t- #### OWL Axioms\n\t  id:: multiverse-owl-axioms\n\t  collapsed:: true\n\t\t- ```clojure\n\t\t  Declaration(Class(mv:Multiverse))\n\n\t\t  # Classification along two primary dimensions\n\t\t  SubClassOf(mv:Multiverse mv:VirtualEntity)\n\t\t  SubClassOf(mv:Multiverse mv:Object)\n\n\t\t  # Multiverse consists of multiple metaverses\n\t\t  SubClassOf(mv:Multiverse\n\t\t    ObjectMinCardinality(2 mv:hasPart mv:Metaverse)\n\t\t  )\n\n\t\t  # Core interoperability infrastructure\n\t\t  SubClassOf(mv:Multiverse\n\t\t    ObjectSomeValuesFrom(mv:hasPart mv:InteroperabilityProtocol)\n\t\t  )\n\t\t  SubClassOf(mv:Multiverse\n\t\t    ObjectSomeValuesFrom(mv:hasPart mv:FederatedIdentity)\n\t\t  )\n\t\t  SubClassOf(mv:Multiverse\n\t\t    ObjectSomeValuesFrom(mv:hasPart mv:CrossChainBridge)\n\t\t  )\n\n\t\t  # Navigation and connectivity systems\n\t\t  SubClassOf(mv:Multiverse\n\t\t    ObjectSomeValuesFrom(mv:hasPart mv:PortalSystem)\n\t\t  )\n\t\t  SubClassOf(mv:Multiverse\n\t\t    ObjectSomeValuesFrom(mv:hasPart mv:AssetTranslationLayer)\n\t\t  )\n\t\t  SubClassOf(mv:Multiverse\n\t\t    ObjectSomeValuesFrom(mv:hasPart mv:UniversalInventory)\n\t\t  )\n\n\t\t  # Governance and coordination\n\t\t  SubClassOf(mv:Multiverse\n\t\t    ObjectSomeValuesFrom(mv:hasPart mv:MultiWorldGovernance)\n\t\t  )\n\n\t\t  # Technical requirements for cross-world functionality\n\t\t  SubClassOf(mv:Multiverse\n\t\t    ObjectSomeValuesFrom(mv:requires mv:IdentityFederation)\n\t\t  )\n\t\t  SubClassOf(mv:Multiverse\n\t\t    ObjectSomeValuesFrom(mv:requires mv:ProtocolTranslation)\n\t\t  )\n\t\t  SubClassOf(mv:Multiverse\n\t\t    ObjectSomeValuesFrom(mv:requires mv:AssetBridging)\n\t\t  )\n\t\t  SubClassOf(mv:Multiverse\n\t\t    ObjectSomeValuesFrom(mv:requires mv:DistributedGovernance)\n\t\t  )\n\t\t  SubClassOf(mv:Multiverse\n\t\t    ObjectSomeValuesFrom(mv:requires mv:StandardFormatSupport)\n\t\t  )\n\n\t\t  # Domain classifications\n\t\t  SubClassOf(mv:Multiverse\n\t\t    ObjectSomeValuesFrom(mv:belongsToDomain mv:InfrastructureDomain)\n\t\t  )\n\t\t  SubClassOf(mv:Multiverse\n\t\t    ObjectSomeValuesFrom(mv:belongsToDomain mv:VirtualSocietyDomain)\n\t\t  )\n\n\t\t  # Layer classification\n\t\t  SubClassOf(mv:Multiverse\n\t\t    ObjectSomeValuesFrom(mv:implementedInLayer mv:ApplicationLayer)\n\t\t  )\n\n  # Property characteristics\n  TransitiveObjectProperty(dt:ispartof)\n\n  # Property characteristics\n  AsymmetricObjectProperty(dt:requires)\n\n  # Property characteristics\n  AsymmetricObjectProperty(dt:dependson)\n\n  # Property characteristics\n  AsymmetricObjectProperty(dt:enables)\n```",
  "backlinks": [
    "Metaverse"
  ],
  "wiki_links": [
    "Asset Portability",
    "Cross-Metaverse Commerce",
    "Metaverse",
    "Metaverse Infrastructure",
    "Federated Identity",
    "Identity Federation",
    "Universal Inventory",
    "Blockchain",
    "Federated Social Networks",
    "Decentralized Identifier",
    "Distributed Governance",
    "Interoperability Standard",
    "Interoperability Protocol",
    "Spatial Web",
    "Universal Avatar",
    "Cross-Chain Bridge",
    "OMA3",
    "InfrastructureDomain",
    "Asset Bridging",
    "VirtualSocietyDomain",
    "Asset Translation Layer",
    "Cross-World Travel",
    "ApplicationLayer",
    "Cross-Platform Authentication",
    "Metaverse Standards Forum",
    "Standard Format Support",
    "Smart Contract",
    "Multi-World Governance",
    "Protocol Translation",
    "Verifiable Credential",
    "Multi-Platform Gaming",
    "Portal System"
  ],
  "ontology": {
    "term_id": "20316",
    "preferred_term": "Multiverse",
    "alt_terms": [],
    "iri": "http://narrativegoldmine.com/metaverse#Multiverse",
    "source_domain": "metaverse",
    "domain": "metaverse",
    "domain_full_name": "",
    "definition": "A network of interconnected but distinct metaverses and virtual worlds that enable cross-platform identity, asset portability, and interoperability while maintaining individual world sovereignty and distinct governance models.",
    "scope_note": null,
    "status": "draft",
    "maturity": "draft",
    "version": null,
    "public_access": true,
    "last_updated": null,
    "authority_score": null,
    "quality_score": null,
    "cross_domain_links": null,
    "owl_class": "mv:Multiverse",
    "owl_physicality": "VirtualEntity",
    "owl_role": "Object",
    "owl_inferred_class": "mv:VirtualObject",
    "is_subclass_of": [
      "Metaverse Infrastructure"
    ],
    "has_part": [
      "Metaverse",
      "Interoperability Protocol",
      "Federated Identity",
      "Cross-Chain Bridge",
      "Portal System",
      "Multi-World Governance",
      "Asset Translation Layer",
      "Universal Inventory"
    ],
    "is_part_of": [
      "Spatial Web"
    ],
    "requires": [
      "Identity Federation",
      "Protocol Translation",
      "Asset Bridging",
      "Distributed Governance",
      "Standard Format Support",
      "Cross-Platform Authentication"
    ],
    "depends_on": [
      "Blockchain",
      "Decentralized Identifier",
      "Verifiable Credential",
      "Smart Contract",
      "Interoperability Standard"
    ],
    "enables": [
      "Cross-World Travel",
      "Asset Portability",
      "Multi-Platform Gaming",
      "Federated Social Networks",
      "Cross-Metaverse Commerce",
      "Universal Avatar"
    ],
    "relates_to": [],
    "bridges_to": [],
    "bridges_from": [],
    "domain_extensions": {},
    "belongs_to_domain": [
      "InfrastructureDomain",
      "VirtualSocietyDomain"
    ],
    "implemented_in_layer": [
      "ApplicationLayer"
    ],
    "source": [
      "OMA3",
      "Metaverse Standards Forum"
    ],
    "validation": {
      "is_valid": false,
      "errors": [
        "Missing required property: last-updated",
        "owl:class namespace 'mv' doesn't match source-domain 'metaverse'"
      ]
    }
  }
}