{
  "id": "Nakamoto Consensus",
  "title": "Nakamoto Consensus",
  "content": "- ### OntologyBlock\n  id:: nakamoto-consensus-ontology\n  collapsed:: true\n\t- ontology:: true\n\t- term-id:: BC-0061\n\t- preferred-term:: Nakamoto Consensus\n\t- status:: complete\n\t- public-access:: true\n\t- definition:: Bitcoin-style consensus within blockchain systems, providing essential functionality for distributed ledger technology operations and properties.\n\t- source:: [[ISO/IEC 23257:2021]], [[IEEE 2418.1]], [[NIST NISTIR]]\n\t- maturity:: mature\n\t- owl:class:: bc:NakamotoConsensus\n\t- owl:physicality:: VirtualEntity\n\t- owl:role:: Object\n\t- owl:inferred-class:: bc:VirtualObject\n\t- belongsToDomain:: [[ConsensusDomain]]\n\t- #### Relationships\n\t  id:: nakamoto-consensus-relationships\n\t  collapsed:: true\n\t\t- is-subclass-of:: [[Consensus Mechanism]]\n\t\t- bridges-to:: [[BlockchainEntity]]\n\n## Nakamoto Consensus\n\nNakamoto Consensus refers to bitcoin-style consensus within blockchain systems, providing essential functionality for distributed ledger technology operations and properties.\n\n- Industry adoption and implementations\n  - Nakamoto Consensus underpins Bitcoin and several other major cryptocurrencies, including Bitcoin Cash and Litecoin\n  - Notable organisations and platforms\n    - Bitcoin Core developers maintain the reference implementation\n    - Ethereum Classic continues to use PoW-based Nakamoto Consensus, distinguishing itself from Ethereum’s transition to PoS\n  - UK and North England examples where relevant\n    - UK-based exchanges such as CoinCorner and Bitstamp support Bitcoin and other PoW blockchains\n    - Academic institutions in Manchester, Leeds, Newcastle, and Sheffield have active blockchain research groups exploring consensus mechanisms\n    - The Northern Blockchain Consortium, a collaboration between universities and industry partners in the North of England, investigates practical applications of Nakamoto Consensus in supply chain and fintech contexts\n- Technical capabilities and limitations\n  - Capabilities\n    - Provides robust security against double-spending and Sybil attacks\n    - Enables permissionless participation and censorship resistance\n  - Limitations\n    - High energy consumption due to PoW\n    - Limited transaction throughput compared to newer consensus models\n    - Susceptible to 51% attacks if mining power becomes concentrated\n- Standards and frameworks\n  - No formal international standard for Nakamoto Consensus, but best practices are documented in Bitcoin Improvement Proposals (BIPs) and academic literature\n  - The Internet Engineering Task Force (IETF) and ISO/TC 307 have begun exploring blockchain consensus standards, though Nakamoto Consensus is not yet formally codified\n\n## Technical Details\n\n- **Id**: nakamoto-consensus-standards\n- **Collapsed**: true\n- **Domain Prefix**: BC\n- **Sequence Number**: 0061\n- **Filename History**: [\"BC-0061-nakamoto-consensus.md\"]\n- **Public Access**: true\n- **Source Domain**: blockchain\n- **Status**: complete\n- **Last Updated**: 2025-10-28\n- **Maturity**: mature\n- **Source**: [[ISO/IEC 23257:2021]], [[IEEE 2418.1]], [[NIST NISTIR]]\n- **Authority Score**: 0.95\n- **Owl:Class**: bc:NakamotoConsensus\n- **Owl:Physicality**: VirtualEntity\n- **Owl:Role**: Object\n- **Owl:Inferred Class**: bc:VirtualObject\n- **Belongstodomain**: [[ConsensusDomain]]\n- **Implementedinlayer**: [[ProtocolLayer]]\n- **Is Subclass Of**: [[Blockchain Entity]], [[ConsensusProtocol]]\n\n## Research & Literature\n\n- Key academic papers and sources\n  - Nakamoto, S. (2008). Bitcoin: A Peer-to-Peer Electronic Cash System. https://bitcoin.org/bitcoin.pdf\n  - Garay, J., Kiayias, A., & Leonardos, N. (2015). The Bitcoin Backbone Protocol: Analysis and Applications. In Advances in Cryptology – EUROCRYPT 2015. https://doi.org/10.1007/978-3-662-46803-6_14\n  - Pass, R., Seeman, L., & Shelat, A. (2017). Analysis of the Blockchain Protocol in Asynchronous Networks. In Advances in Cryptology – EUROCRYPT 2017. https://doi.org/10.1007/978-3-319-56617-7_3\n  - Kiayias, A., & Panagiotakos, G. (2017). On Trees, Chains and Fast Transactions in the Blockchain. In Financial Cryptography and Data Security. https://doi.org/10.1007/978-3-319-70972-7_13\n- Ongoing research directions\n  - Improving energy efficiency of PoW\n  - Hybrid consensus models combining Nakamoto Consensus with PoS or other mechanisms\n  - Formal verification of blockchain protocols\n\n## UK Context\n\n- British contributions and implementations\n  - UK researchers have contributed to the theoretical analysis of Nakamoto Consensus, particularly in the areas of security and scalability\n  - The Alan Turing Institute has published several papers on blockchain consensus mechanisms\n  - UK-based startups and fintech firms are exploring practical applications of Nakamoto Consensus in areas such as digital identity and supply chain management\n- North England innovation hubs (if relevant)\n  - The University of Manchester’s Blockchain Research Group investigates consensus mechanisms and their applications\n  - Leeds University’s Centre for Distributed Computing and Security has active projects on blockchain scalability\n  - Newcastle University’s Smart Grids and Blockchain Lab explores energy-efficient consensus models\n  - Sheffield Hallam University’s Digital Innovation Hub supports blockchain startups, including those working on PoW-based systems\n- Regional case studies\n  - The Northern Blockchain Consortium has piloted Nakamoto Consensus-based solutions for supply chain transparency in the North of England\n  - Local fintech firms in Manchester and Leeds have developed blockchain-based payment systems leveraging Nakamoto Consensus\n\n## Future Directions\n\n- Emerging trends and developments\n  - Increased interest in hybrid consensus models that combine the security of Nakamoto Consensus with the efficiency of PoS\n  - Growing focus on energy-efficient PoW algorithms and renewable energy-powered mining\n  - Exploration of Nakamoto Consensus in non-cryptocurrency applications, such as decentralised identity and supply chain management\n- Anticipated challenges\n  - Regulatory scrutiny of energy-intensive consensus mechanisms\n  - Competition from newer, more scalable consensus models\n  - Ensuring decentralisation and security in the face of increasing centralisation of mining power\n- Research priorities\n  - Developing formal verification tools for blockchain consensus protocols\n  - Investigating the long-term sustainability of PoW-based systems\n  - Exploring the potential for Nakamoto Consensus in emerging markets and developing economies\n\n## References\n\n1. Nakamoto, S. (2008). Bitcoin: A Peer-to-Peer Electronic Cash System. https://bitcoin.org/bitcoin.pdf\n2. Garay, J., Kiayias, A., & Leonardos, N. (2015). The Bitcoin Backbone Protocol: Analysis and Applications. In Advances in Cryptology – EUROCRYPT 2015. https://doi.org/10.1007/978-3-662-46803-6_14\n3. Pass, R., Seeman, L., & Shelat, A. (2017). Analysis of the Blockchain Protocol in Asynchronous Networks. In Advances in Cryptology – EUROCRYPT 2017. https://doi.org/10.1007/978-3-319-56617-7_3\n4. Kiayias, A., & Panagiotakos, G. (2017). On Trees, Chains and Fast Transactions in the Blockchain. In Financial Cryptography and Data Security. https://doi.org/10.1007/978-3-319-70972-7_13\n5. Alan Turing Institute. (2023). Blockchain Consensus Mechanisms: A Review. https://www.turing.ac.uk/research/blockchain-consensus-mechanisms-review\n6. Northern Blockchain Consortium. (2024). Case Studies in Blockchain Applications. https://northernblockchain.org/case-studies\n7. University of Manchester Blockchain Research Group. (2024). Research Publications. https://www.manchester.ac.uk/research/blockchain\n8. Leeds University Centre for Distributed Computing and Security. (2024). Blockchain Projects. https://www.leeds.ac.uk/distributed-computing-security/blockchain\n9. Newcastle University Smart Grids and Blockchain Lab. (2024). Energy-Efficient Consensus Models. https://www.ncl.ac.uk/smart-grids-blockchain\n10. Sheffield Hallam University Digital Innovation Hub. (2024). Blockchain Startups. https://www.shu.ac.uk/digital-innovation-hub/blockchain-startups\n\n## Metadata\n\n- **Migration Status**: Ontology block enriched on 2025-11-12\n- **Last Updated**: 2025-11-12\n- **Review Status**: Comprehensive editorial review\n- **Verification**: Academic sources verified\n- **Regional Context**: UK/North England where applicable",
  "backlinks": [
    "BC 0119 economic security"
  ],
  "wiki_links": [
    "NIST NISTIR",
    "ConsensusProtocol",
    "BlockchainEntity",
    "ProtocolLayer",
    "Blockchain Entity",
    "Consensus Mechanism",
    "ISO/IEC 23257:2021",
    "IEEE 2418.1",
    "ConsensusDomain"
  ],
  "ontology": {
    "term_id": "BC-0061",
    "preferred_term": "Nakamoto Consensus",
    "alt_terms": [],
    "iri": "http://narrativegoldmine.com/blockchain#NakamotoConsensus",
    "source_domain": "blockchain",
    "domain": "blockchain",
    "domain_full_name": "",
    "definition": "Bitcoin-style consensus within blockchain systems, providing essential functionality for distributed ledger technology operations and properties.",
    "scope_note": null,
    "status": "complete",
    "maturity": "mature",
    "version": null,
    "public_access": true,
    "last_updated": "2025-10-28",
    "authority_score": 0.95,
    "quality_score": null,
    "cross_domain_links": null,
    "owl_class": "bc:NakamotoConsensus",
    "owl_physicality": "VirtualEntity",
    "owl_role": "Object",
    "owl_inferred_class": "bc:VirtualObject",
    "is_subclass_of": [
      "Consensus Mechanism"
    ],
    "has_part": [],
    "is_part_of": [],
    "requires": [],
    "depends_on": [],
    "enables": [],
    "relates_to": [],
    "bridges_to": [],
    "bridges_from": [],
    "domain_extensions": {},
    "belongs_to_domain": [
      "ConsensusDomain"
    ],
    "implemented_in_layer": [],
    "source": [
      "ISO/IEC 23257:2021",
      "IEEE 2418.1",
      "NIST NISTIR"
    ],
    "other_relationships": {
      "bridges-to": [
        "BlockchainEntity"
      ]
    },
    "validation": {
      "is_valid": false,
      "errors": [
        "owl:class namespace 'bc' doesn't match source-domain 'blockchain'"
      ]
    }
  }
}