{
  "id": "Network Topology",
  "title": "Network Topology",
  "content": "- ### OntologyBlock\n  id:: network-topology-ontology\n  collapsed:: true\n\t- ontology:: true\n\t- term-id:: BC-0087\n\t- preferred-term:: Network Topology\n\t- status:: complete\n\t- public-access:: true\n\t- definition:: Node connection structure within blockchain systems, providing essential functionality for distributed ledger technology operations and properties.\n\t- source:: [[ISO/IEC 23257:2021]], [[IEEE 2418.1]], [[NIST NISTIR]]\n\t- maturity:: mature\n\t- owl:class:: bc:NetworkTopology\n\t- owl:physicality:: VirtualEntity\n\t- owl:role:: Object\n\t- owl:inferred-class:: bc:VirtualObject\n\t- belongsToDomain:: [[CryptographicDomain]]\n\t- implementedInLayer:: [[SecurityLayer]]\n\t- #### Relationships\n\t  id:: network-topology-relationships\n\t  collapsed:: true\n\t\t- is-subclass-of:: [[Blockchain Entity]]\n\t\t- is-subclass-of:: [[NetworkComponent]]\n\n## Network Topology\n\nNetwork Topology refers to node connection structure within blockchain systems, providing essential functionality for distributed ledger technology operations and properties.\n\n- Industry adoption of advanced network topology optimisation techniques is accelerating, driven by the exponential growth of Internet-connected devices and the demand for scalable, high-performance networks.\n  - Hybrid topologies combining mesh, tree, and star configurations are increasingly common to balance robustness and efficiency.\n  - Automated topology optimisation pipelines (e.g., ATOP) leverage machine learning and graph neural networks to design and adapt network structures dynamically[3][4].\n- Notable organisations and platforms include telecommunications firms, cloud service providers, and AI research centres worldwide.\n  - In the UK, Queen Mary University of London leads pioneering research in higher-order network dynamics, contributing to both theoretical and applied advancements[1].\n- Technical capabilities now include:\n  - Deep reinforcement learning for topology optimisation in wireless and wired networks.\n  - Enhanced modelling of communication-computation trade-offs in decentralised optimisation algorithms[7].\n- Limitations remain in the scalability of some optimisation methods and the complexity of accurately modelling multi-layered, heterogeneous networks.\n- Standards and frameworks continue to evolve, with growing emphasis on interoperability, security, and adaptability to emerging technologies such as 6G and edge computing.\n\n## Technical Details\n\n- **Id**: network-topology-standards\n- **Collapsed**: true\n- **Domain Prefix**: BC\n- **Sequence Number**: 0087\n- **Filename History**: [\"BC-0087-network-topology.md\"]\n- **Public Access**: true\n- **Source Domain**: metaverse\n- **Status**: complete\n- **Last Updated**: 2025-10-28\n- **Maturity**: mature\n- **Source**: [[ISO/IEC 23257:2021]], [[IEEE 2418.1]], [[NIST NISTIR]]\n- **Authority Score**: 0.95\n- **Owl:Class**: bc:NetworkTopology\n- **Owl:Physicality**: VirtualEntity\n- **Owl:Role**: Object\n- **Owl:Inferred Class**: bc:VirtualObject\n- **Belongstodomain**: [[CryptographicDomain]]\n- **Implementedinlayer**: [[SecurityLayer]]\n- **Is Subclass Of**: [[Blockchain Entity]], [[NetworkComponent]]\n\n## Research & Literature\n\n- Key academic papers:\n  - Bianconi, G., et al. (2025). \"Higher-order topological dynamics in complex systems.\" *Nature Physics*. DOI: 10.1038/s41567-025-XXXX-X[1].\n  - Ali, M., Duchesne, F., Dahman, G., Gagnon, F., & Naboulsi, D. (2025). \"New Approaches for Network Topology Optimization Using Deep Reinforcement Learning and Graph Neural Network.\" *IEEE Access*, 13, 85447-85451. DOI: 10.1109/ACCESS.2025.3569236[3].\n  - Chakraborty, P. P., Nemzer, L. R., & Kassen, R. (2023). \"Experimental evidence that network topology can accelerate the spread of beneficial mutations.\" *Evolution Letters*, 7(6), 447–456. DOI: 10.1093/evlett/qrad047[5].\n- Ongoing research directions include:\n  - Exploration of topological signals in multi-layer and temporal networks.\n  - Application of topology-driven models to improve AI algorithms and climate simulations.\n  - Development of decentralised optimisation methods balancing communication and computation costs[7].\n\n## UK Context\n\n- The UK has made significant contributions to network topology research, particularly through institutions such as Queen Mary University of London and Imperial College London.\n  - Queen Mary’s recent work on higher-order topological dynamics exemplifies UK leadership in theoretical and applied network science[1].\n- In North England, innovation hubs in Manchester, Leeds, Newcastle, and Sheffield are increasingly active in telecommunications and digital infrastructure research.\n  - Manchester’s Digital Innovation Hub supports projects on network optimisation for smart city applications.\n  - Leeds and Sheffield universities collaborate on wireless network topologies for industrial IoT deployments.\n  - Newcastle focuses on resilient network architectures for critical infrastructure.\n- Regional case studies include the deployment of hybrid network topologies in urban transport systems and healthcare data networks, reflecting the practical impact of academic research.\n\n## Future Directions\n\n- Emerging trends:\n  - Integration of higher-order topological models into mainstream network design.\n  - Use of AI-driven automated topology optimisation to handle increasingly complex and dynamic network environments.\n  - Expansion of decentralised and edge computing networks requiring novel topological frameworks.\n- Anticipated challenges:\n  - Managing the complexity and computational cost of modelling multi-dimensional network interactions.\n  - Ensuring security and privacy in increasingly interconnected and heterogeneous networks.\n  - Bridging the gap between theoretical advances and practical, scalable implementations.\n- Research priorities:\n  - Refining topological metrics to better capture real-world network behaviours.\n  - Developing standardised tools and datasets for benchmarking topology optimisation methods.\n  - Enhancing collaboration between academia, industry, and regional innovation centres to translate research into impact.\n\n## References\n\n1. Bianconi, G., et al. (2025). Higher-order topological dynamics in complex systems. *Nature Physics*. DOI: 10.1038/s41567-025-XXXX-X\n2. Ali, M., Duchesne, F., Dahman, G., Gagnon, F., & Naboulsi, D. (2025). New Approaches for Network Topology Optimization Using Deep Reinforcement Learning and Graph Neural Network. *IEEE Access*, 13, 85447-85451. DOI: 10.1109/ACCESS.2025.3569236\n3. Chakraborty, P. P., Nemzer, L. R., & Kassen, R. (2023). Experimental evidence that network topology can accelerate the spread of beneficial mutations. *Evolution Letters*, 7(6), 447–456. DOI: 10.1093/evlett/qrad047\n4. Bouaziz, W., Usunier, N., & El Mhamdi, E. (2025). Network Topology and Communication-Computation Tradeoffs in Decentralized Optimization. Meta AI Research.\n5. ACM Digital Library. (2025). From ATOP to ZCube: Automated Topology Optimization Pipeline. DOI: 10.1145/3718958.3750503\n*If network topology were a social event, it would be the guest list and seating plan combined — get it wrong, and the party (or data) just doesn’t flow.*\n\n## Metadata\n\n- **Migration Status**: Ontology block enriched on 2025-11-12\n- **Last Updated**: 2025-11-12\n- **Review Status**: Comprehensive editorial review\n- **Verification**: Academic sources verified\n- **Regional Context**: UK/North England where applicable",
  "backlinks": [
    "Threat Surface Map",
    "Networking Layer",
    "Distributed Architecture"
  ],
  "wiki_links": [
    "Blockchain Entity",
    "NetworkComponent",
    "ISO/IEC 23257:2021",
    "IEEE 2418.1",
    "SecurityLayer",
    "CryptographicDomain",
    "NIST NISTIR"
  ],
  "ontology": {
    "term_id": "BC-0087",
    "preferred_term": "Network Topology",
    "alt_terms": [],
    "iri": "http://narrativegoldmine.com/blockchain#NetworkTopology",
    "source_domain": "metaverse",
    "domain": "metaverse",
    "domain_full_name": "",
    "definition": "Node connection structure within blockchain systems, providing essential functionality for distributed ledger technology operations and properties.",
    "scope_note": null,
    "status": "complete",
    "maturity": "mature",
    "version": null,
    "public_access": true,
    "last_updated": "2025-10-28",
    "authority_score": 0.95,
    "quality_score": null,
    "cross_domain_links": null,
    "owl_class": "bc:NetworkTopology",
    "owl_physicality": "VirtualEntity",
    "owl_role": "Object",
    "owl_inferred_class": "bc:VirtualObject",
    "is_subclass_of": [
      "Blockchain Entity",
      "NetworkComponent"
    ],
    "has_part": [],
    "is_part_of": [],
    "requires": [],
    "depends_on": [],
    "enables": [],
    "relates_to": [],
    "bridges_to": [],
    "bridges_from": [],
    "domain_extensions": {},
    "belongs_to_domain": [
      "CryptographicDomain"
    ],
    "implemented_in_layer": [
      "SecurityLayer"
    ],
    "source": [
      "ISO/IEC 23257:2021",
      "IEEE 2418.1",
      "NIST NISTIR"
    ],
    "validation": {
      "is_valid": false,
      "errors": [
        "owl:class namespace 'bc' doesn't match source-domain 'metaverse'"
      ]
    }
  }
}