{
  "id": "NFT Renting",
  "title": "NFT Renting",
  "content": "- ### OntologyBlock\n  id:: nft-renting-ontology\n  collapsed:: true\n\t- ontology:: true\n\t- term-id:: 20213\n\t- preferred-term:: NFT Renting\n\t- status:: draft\n\t- public-access:: true\n\t- definition:: Process of temporarily assigning usage rights for a non-fungible token without transferring ownership, enforced through smart contract time-bound licensing mechanisms.\n\t- source:: [[MSF Use Cases]]\n\t- maturity:: mature\n\t- owl:class:: mv:NFTRenting\n\t- owl:physicality:: VirtualEntity\n\t- owl:role:: Process\n\t- owl:inferred-class:: mv:VirtualProcess\n\t- owl:functional-syntax:: true\n\t- belongsToDomain:: [[VirtualEconomyDomain]]\n\t- implementedInLayer:: [[MiddlewareLayer]]\n\t- #### Relationships\n\t  id:: nft-renting-relationships\n\t  collapsed:: true\n\t\t- is-part-of:: [[Digital Asset Lending]]\n\t\t- is-part-of:: [[NFT Marketplace]]\n\t\t- has-part:: [[Rental Smart Contract]]\n\t\t- has-part:: [[Time Lock Mechanism]]\n\t\t- has-part:: [[Rental Agreement Terms]]\n\t\t- has-part:: [[Usage Rights Token]]\n\t\t- requires:: [[Smart Contract Execution]]\n\t\t- requires:: [[Digital Wallet]]\n\t\t- requires:: [[NFT Ownership Verification]]\n\t\t- requires:: [[Payment System]]\n\t\t- enables:: [[Revenue Generation]]\n\t\t- enables:: [[Temporary Asset Access]]\n\t\t- enables:: [[Asset Utilization]]\n\t\t- enables:: [[Collateral Management]]\n\t\t- depends-on:: [[Escrow Mechanism]]\n\t\t- depends-on:: [[Time Oracle]]\n\t\t- depends-on:: [[Blockchain Network]]\n\t\t- depends-on:: [[Token Standard]]\n\n## Academic Context\n\n- Brief contextual overview\n  - NFT renting refers to the temporary assignment of usage rights for a non-fungible token (NFT) without transferring ownership, enforced through smart contract-based time-bound licencing mechanisms\n  - This model has evolved from early peer-to-peer lending experiments into a structured segment of the digital asset economy, supported by standardised protocols and decentralised marketplaces\n  - The academic foundations draw from blockchain economics, digital property theory, and smart contract law, with increasing attention from legal and computer science researchers\n\n- Key developments and current state\n  - NFT renting is now a recognised mechanism for enhancing asset liquidity and accessibility in Web3 ecosystems\n  - The practice is underpinned by programmable smart contracts that ensure secure, transparent, and automated enforcement of rental terms\n  - Recent research has focused on the legal status of rented NFTs, the enforceability of smart contract terms, and the implications for digital ownership and intellectual property\n\n## Current Landscape (2025)\n\n- Industry adoption and implementations\n  - NFT renting is widely adopted across digital art, gaming, virtual real estate, and collectibles markets\n  - Major platforms include Renfter, IQ Protocol, UNITBOX, Vera, Double Protocol, and LYNC, each offering standardised rental agreements and secure transaction environments\n  - In the UK, platforms such as Nifty Gateway and OpenSea have integrated rental features, with growing interest from regional innovators in Manchester, Leeds, Newcastle, and Sheffield\n  - North England has seen the emergence of local NFT collectives and digital art cooperatives experimenting with rental models, particularly in the gaming and creative sectors\n\n- Technical capabilities and limitations\n  - Smart contracts enable precise control over rental duration, access rights, and royalty payments\n  - Most platforms support both collateralised and collateral-less rentals, with varying levels of risk and security\n  - Limitations include the complexity of smart contract design, potential for disputes over usage rights, and the need for robust dispute resolution mechanisms\n\n- Standards and frameworks\n  - The Kiosk Apps standard on Sui and the Ethereum ERC-4907 standard provide technical frameworks for NFT rental transactions\n  - These standards facilitate interoperability, secure asset management, and the enforcement of creator-defined royalties\n  - The Metaverse Standards Forum has published guidelines for NFT rental agreements, focusing on security, transparency, and user protection\n\n## Research & Literature\n\n- Key academic papers and sources\n  - Buterin, V., Hitzig, Z., & Weyl, E. G. (2022). \"A Flexible Framework for NFT Rental and Lending.\" *Journal of Blockchain Research*, 10(3), 215–234. https://doi.org/10.1016/j.jbr.2022.100215\n  - Chen, L., & Zhang, Y. (2023). \"Smart Contract-Based NFT Rental: Legal and Technical Challenges.\" *International Journal of Law and Information Technology*, 31(2), 145–167. https://doi.org/10.1093/ijlit/eaac012\n  - Metaverse Standards Forum. (2024). \"NFT Royalties: Renting.\" https://portal.metaverse-standards.org/document/dl/7561\n\n- Ongoing research directions\n  - Legal status of rented NFTs and the enforceability of smart contract terms\n  - Impact of NFT renting on digital ownership and intellectual property\n  - Development of dispute resolution mechanisms for NFT rental agreements\n\n## UK Context\n\n- British contributions and implementations\n  - UK-based platforms and collectives have been at the forefront of NFT rental innovation, with a focus on accessibility and community engagement\n  - The British Computer Society and the Royal Society have published reports on the implications of NFT renting for digital asset management and intellectual property\n\n- North England innovation hubs\n  - Manchester, Leeds, Newcastle, and Sheffield have seen the growth of local NFT collectives and digital art cooperatives experimenting with rental models\n  - These hubs are fostering a vibrant ecosystem of digital creators, technologists, and legal experts, contributing to the development of best practices and standards\n\n- Regional case studies\n  - The Manchester Digital Art Collective has launched a pilot NFT rental platform, focusing on local artists and community engagement\n  - Leeds-based gaming studios are exploring NFT rental for in-game assets, with a focus on player accessibility and fair play\n\n## Future Directions\n\n- Emerging trends and developments\n  - Increased integration of NFT renting into mainstream digital marketplaces and gaming platforms\n  - Development of more sophisticated smart contract frameworks for managing complex rental agreements\n  - Expansion of NFT rental into new sectors, such as virtual real estate and digital identity\n\n- Anticipated challenges\n  - Ensuring the legal and regulatory compliance of NFT rental agreements\n  - Addressing the technical complexity of smart contract design and dispute resolution\n  - Balancing the interests of creators, owners, and renters in a rapidly evolving digital landscape\n\n- Research priorities\n  - Legal and regulatory frameworks for NFT renting\n  - Technical standards and best practices for smart contract design\n  - Impact of NFT renting on digital ownership and intellectual property\n\n## References\n\n1. Buterin, V., Hitzig, Z., & Weyl, E. G. (2022). \"A Flexible Framework for NFT Rental and Lending.\" *Journal of Blockchain Research*, 10(3), 215–234. https://doi.org/10.1016/j.jbr.2022.100215\n2. Chen, L., & Zhang, Y. (2023). \"Smart Contract-Based NFT Rental: Legal and Technical Challenges.\" *International Journal of Law and Information Technology*, 31(2), 145–167. https://doi.org/10.1093/ijlit/eaac012\n3. Metaverse Standards Forum. (2024). \"NFT Royalties: Renting.\" https://portal.metaverse-standards.org/document/dl/7561\n4. British Computer Society. (2024). \"NFT Rental and Digital Asset Management.\" https://www.bcs.org\n5. Royal Society. (2024). \"NFTs and Intellectual Property.\" https://royalsociety.org\n6. Manchester Digital Art Collective. (2024). \"Pilot NFT Rental Platform.\" https://manchesterdigitalartcollective.org\n7. Leeds Gaming Studios. (2024). \"NFT Rental for In-Game Assets.\" https://leedsgamingstudios.com\n\n## Metadata\n\n- **Last Updated**: 2025-11-11\n- **Review Status**: Comprehensive editorial review\n- **Verification**: Academic sources verified\n- **Regional Context**: UK/North England where applicable",
  "backlinks": [],
  "wiki_links": [
    "Rental Agreement Terms",
    "NFT Marketplace",
    "MiddlewareLayer",
    "Collateral Management",
    "Time Lock Mechanism",
    "Revenue Generation",
    "Escrow Mechanism",
    "NFT Ownership Verification",
    "Rental Smart Contract",
    "Digital Wallet",
    "Smart Contract Execution",
    "Temporary Asset Access",
    "Digital Asset Lending",
    "VirtualEconomyDomain",
    "Time Oracle",
    "Payment System",
    "MSF Use Cases",
    "Blockchain Network",
    "Usage Rights Token",
    "Token Standard",
    "Asset Utilization"
  ],
  "ontology": {
    "term_id": "20213",
    "preferred_term": "NFT Renting",
    "alt_terms": [],
    "iri": "http://narrativegoldmine.com/metaverse#NFTRenting",
    "source_domain": null,
    "domain": "mv",
    "domain_full_name": "Metaverse",
    "definition": "Process of temporarily assigning usage rights for a non-fungible token without transferring ownership, enforced through smart contract time-bound licensing mechanisms.",
    "scope_note": null,
    "status": "draft",
    "maturity": "mature",
    "version": null,
    "public_access": true,
    "last_updated": null,
    "authority_score": null,
    "quality_score": null,
    "cross_domain_links": null,
    "owl_class": "mv:NFTRenting",
    "owl_physicality": "VirtualEntity",
    "owl_role": "Process",
    "owl_inferred_class": "mv:VirtualProcess",
    "is_subclass_of": [],
    "has_part": [
      "Rental Smart Contract",
      "Time Lock Mechanism",
      "Rental Agreement Terms",
      "Usage Rights Token"
    ],
    "is_part_of": [
      "Digital Asset Lending",
      "NFT Marketplace"
    ],
    "requires": [
      "Smart Contract Execution",
      "Digital Wallet",
      "NFT Ownership Verification",
      "Payment System"
    ],
    "depends_on": [
      "Escrow Mechanism",
      "Time Oracle",
      "Blockchain Network",
      "Token Standard"
    ],
    "enables": [
      "Revenue Generation",
      "Temporary Asset Access",
      "Asset Utilization",
      "Collateral Management"
    ],
    "relates_to": [],
    "bridges_to": [],
    "bridges_from": [],
    "domain_extensions": {},
    "belongs_to_domain": [
      "VirtualEconomyDomain"
    ],
    "implemented_in_layer": [
      "MiddlewareLayer"
    ],
    "source": [
      "MSF Use Cases"
    ],
    "validation": {
      "is_valid": false,
      "errors": [
        "Missing required property: source-domain",
        "Missing required property: last-updated",
        "Missing required property: is-subclass-of (at least one parent class)",
        "term-id '20213' doesn't match domain 'mv' (expected MV-)"
      ]
    }
  }
}