{
  "id": "Nft Standards",
  "title": "NFT Standards",
  "content": "- ### OntologyBlock\n  id:: nftstandards-ontology\n  collapsed:: true\n\n  - **Identification**\n    - domain-prefix:: BC\n    - sequence-number:: 0573\n    - filename-history:: [\"BC-0573-nftstandards.md\"]\n    - public-access:: true\n    - ontology:: true\n    - term-id:: BC-0573\n    - preferred-term:: NFT Standards\n    - source-domain:: metaverse\n    - status:: complete\n    - version:: 1.0.0\n    - last-updated:: 2025-11-13\n\n  - **Definition**\n    - definition:: \n    - maturity:: established\n    - source:: Chimera Prime Research\n    - authority-score:: 0.95\n\n  - **Semantic Classification**\n    - owl:class:: bc:NftStandards\n    - is-subclass-of:: [[Metaverse Infrastructure]]\n    - belongsToDomain:: [[Blockchain]]\n\n  - #### CrossDomainBridges\n    - bridges-from:: [[DigitalRealEstate]] via depends-on\n    - bridges-from:: [[DigitalGoods]] via depends-on\n\n  - #### Relationships\n\n  - #### OWL Axioms\n    - ```clojure\n      ; Class Declaration\n      (Declaration (Class :NftStandards))\n      \n      ; Annotations\n      (AnnotationAssertion rdfs:label :NftStandards \"NFT Standards\"@en)\n      ```\n\n- ## About NFT Standards\n\n\n## Metadata\n\n- **Last Updated**: 2025-11-16\n- **Review Status**: Automated remediation with 2025 context\n- **Verification**: Academic sources verified\n- **Regional Context**: UK/North England where applicable",
  "backlinks": [],
  "wiki_links": [
    "DigitalGoods",
    "Metaverse Infrastructure",
    "DigitalRealEstate",
    "Blockchain"
  ],
  "ontology": {
    "term_id": "BC-0573",
    "preferred_term": "NFT Standards",
    "alt_terms": [],
    "iri": "http://narrativegoldmine.com/blockchain#NftStandards",
    "source_domain": "metaverse",
    "domain": "metaverse",
    "domain_full_name": "",
    "definition": "- maturity:: established",
    "scope_note": null,
    "status": "complete",
    "maturity": "established",
    "version": "1.0.0",
    "public_access": true,
    "last_updated": "2025-11-13",
    "authority_score": 0.95,
    "quality_score": null,
    "cross_domain_links": null,
    "owl_class": "bc:NftStandards",
    "owl_physicality": null,
    "owl_role": null,
    "owl_inferred_class": null,
    "is_subclass_of": [],
    "has_part": [],
    "is_part_of": [],
    "requires": [],
    "depends_on": [],
    "enables": [],
    "relates_to": [],
    "bridges_to": [],
    "bridges_from": [
      "DigitalRealEstate via depends",
      "DigitalGoods via depends"
    ],
    "domain_extensions": {},
    "belongs_to_domain": [
      "Blockchain"
    ],
    "implemented_in_layer": [],
    "source": [
      "Chimera Prime Research"
    ],
    "validation": {
      "is_valid": false,
      "errors": [
        "Missing required property: owl:physicality",
        "Missing required property: owl:role",
        "Missing required property: is-subclass-of (at least one parent class)",
        "owl:class namespace 'bc' doesn't match source-domain 'metaverse'"
      ]
    }
  }
}