{
  "id": "Non Genesis Block",
  "title": "Non Genesis Block",
  "content": "- ### OntologyBlock\n  id:: nongenesisblock-ontology\n  collapsed:: true\n\n  - **Identification**\n    - domain-prefix:: BC\n    - sequence-number:: 0568\n    - filename-history:: [\"BC-0568-nongenesisblock.md\"]\n    - public-access:: true\n    - ontology:: true\n    - term-id:: BC-0568\n    - preferred-term:: Non Genesis Block\n    - source-domain:: metaverse\n    - status:: complete\n    - version:: 1.0.0\n    - last-updated:: 2025-11-13\n\n  - **Definition**\n    - definition:: \n    - maturity:: established\n    - source:: Chimera Prime Research\n    - authority-score:: 0.95\n\n  - **Semantic Classification**\n    - owl:class:: bc:NonGenesisBlock\n    - is-subclass-of:: [[Blockchain]]\n    - belongsToDomain:: [[Blockchain]]\n\n  - #### OWL Restrictions\n    \n\n  -",
  "backlinks": [],
  "wiki_links": [
    "Blockchain"
  ],
  "ontology": {
    "term_id": "BC-0568",
    "preferred_term": "Non Genesis Block",
    "alt_terms": [],
    "iri": "http://narrativegoldmine.com/blockchain#NonGenesisBlock",
    "source_domain": "metaverse",
    "domain": "metaverse",
    "domain_full_name": "",
    "definition": "- maturity:: established",
    "scope_note": null,
    "status": "complete",
    "maturity": "established",
    "version": "1.0.0",
    "public_access": true,
    "last_updated": "2025-11-13",
    "authority_score": 0.95,
    "quality_score": null,
    "cross_domain_links": null,
    "owl_class": "bc:NonGenesisBlock",
    "owl_physicality": null,
    "owl_role": null,
    "owl_inferred_class": null,
    "is_subclass_of": [],
    "has_part": [],
    "is_part_of": [],
    "requires": [],
    "depends_on": [],
    "enables": [],
    "relates_to": [],
    "bridges_to": [],
    "bridges_from": [],
    "domain_extensions": {},
    "belongs_to_domain": [
      "Blockchain"
    ],
    "implemented_in_layer": [],
    "source": [
      "Chimera Prime Research"
    ],
    "validation": {
      "is_valid": false,
      "errors": [
        "Missing required property: owl:physicality",
        "Missing required property: owl:role",
        "Missing required property: is-subclass-of (at least one parent class)",
        "owl:class namespace 'bc' doesn't match source-domain 'metaverse'"
      ]
    }
  }
}