{
  "id": "Ontology in LLM Operations",
  "title": "Ontology in LLM Operations",
  "content": "- ### OntologyBlock\n  id:: ontology-llm-operations-ontology\n  collapsed:: true\n\n  - **Identification**\n    - domain-prefix:: AI\n    - sequence-number:: 0878\n    - filename-history:: [\"AI-0878-ontology-llm-operations.md\"]\n    - public-access:: true\n    - ontology:: true\n    - is-subclass-of:: [[ArtificialIntelligenceTechnology]]\n    - term-id:: AI-0878\n    - preferred-term:: Ontology in LLM Operations\n    - source-domain:: ai\n    - status:: complete\n    - version:: 1.0.0\n    - last-updated:: 2025-11-13\n\n  - **Definition**\n    - definition:: The application of formal knowledge representation systems (OWL 2, SHACL, SPARQL) to provide schema-grounded layers that make retrieval, reasoning, outputs, and monitoring in large language model pipelines more deterministic, auditable, and controllable than text-only or pure vector-based approaches.\n    - maturity:: emerging\n    - source:: Industry analysis and W3C standards integration\n    - authority-score:: 0.88\n\n  - **Semantic Classification**\n    - owl:class:: ai:OntologyInLLMOperations\n    - belongsToDomain:: [[Artificial Intelligence]]\n\n  - #### OWL Restrictions\n    - supports some AiGovernance\n    - related-to some KnowledgeGraph\n    \n    - enables some ExplainableAi\n    - related-to some RetrievalAugmentedGenerationRag\n    - related-to some LargeLanguageModel\n\n  - #### CrossDomainBridges\n    - bridges-to:: [[LargeLanguageModel]] via related-to\n    - bridges-to:: [[RetrievalAugmentedGenerationRag]] via related-to\n    - bridges-to:: [[KnowledgeRepresentation]] via is-subclass-of\n    - bridges-to:: [[KnowledgeGraph]] via related-to\n\n  -",
  "backlinks": [],
  "wiki_links": [
    "RetrievalAugmentedGenerationRag",
    "KnowledgeRepresentation",
    "LargeLanguageModel",
    "ArtificialIntelligenceTechnology",
    "Artificial Intelligence",
    "KnowledgeGraph"
  ],
  "ontology": {
    "term_id": "AI-0878",
    "preferred_term": "Ontology in LLM Operations",
    "alt_terms": [],
    "iri": "http://narrativegoldmine.com/ai#OntologyInLLMOperations",
    "source_domain": "ai",
    "domain": "ai",
    "domain_full_name": "Artificial Intelligence",
    "definition": "The application of formal knowledge representation systems (OWL 2, SHACL, SPARQL) to provide schema-grounded layers that make retrieval, reasoning, outputs, and monitoring in large language model pipelines more deterministic, auditable, and controllable than text-only or pure vector-based approaches.",
    "scope_note": null,
    "status": "complete",
    "maturity": "emerging",
    "version": "1.0.0",
    "public_access": true,
    "last_updated": "2025-11-13",
    "authority_score": 0.88,
    "quality_score": null,
    "cross_domain_links": null,
    "owl_class": "ai:OntologyInLLMOperations",
    "owl_physicality": null,
    "owl_role": null,
    "owl_inferred_class": null,
    "is_subclass_of": [],
    "has_part": [],
    "is_part_of": [],
    "requires": [],
    "depends_on": [],
    "enables": [],
    "relates_to": [],
    "bridges_to": [
      "LargeLanguageModel via related",
      "RetrievalAugmentedGenerationRag via related",
      "KnowledgeRepresentation via is",
      "KnowledgeGraph via related"
    ],
    "bridges_from": [],
    "domain_extensions": {},
    "belongs_to_domain": [
      "Artificial Intelligence"
    ],
    "implemented_in_layer": [],
    "source": [
      "Industry analysis and W3C standards integration"
    ],
    "validation": {
      "is_valid": false,
      "errors": [
        "Missing required property: owl:physicality",
        "Missing required property: owl:role",
        "Missing required property: is-subclass-of (at least one parent class)"
      ]
    }
  }
}