{
  "id": "Optimal Control",
  "title": "Optimal Control",
  "content": "- ### OntologyBlock\n  id:: rb-0060-optimal-control-ontology\n  collapsed:: true\n\t- ontology:: true\n\t- term-id:: RB-0060\n\t- domain-prefix:: RB\n\t- sequence-number:: 0060\n\t- filename-history:: [\"rb-0060-optimal-control.md\"]\n\t- preferred-term:: Optimal Control\n\t- source-domain:: metaverse\n\t- status:: draft\n    - public-access:: true\n\t- definition:: ### Primary Definition\n**Optimal Control** - Optimal Control in robotics systems\n\t- maturity:: draft\n\t- owl:class:: mv:rb0060optimalcontrol\n\t- owl:physicality:: ConceptualEntity\n\t- owl:role:: Concept\n\t- belongsToDomain:: [[MetaverseDomain]]\n- ## About rb 0060 optimal control\n\t- ### Primary Definition\n**Optimal Control** - Optimal Control in robotics systems\n\t-\n\t- ### Original Content\n\t  collapsed:: true\n\t\t- ```\n# RB-0060: Optimal Control\n\t\t  \n\t\t  ## Metadata\n\t\t  - **Term ID**: RB-0060\n\t\t  - **Term Type**: Core Concept\n\t\t  - **Classification**: Control Systems\n\t\t  - **Priority**: 1 (Foundational)\n\t\t  - **Authority Score**: 0.95\n\t\t  - **ISO Reference**: ISO 8373:2021\n\t\t  - **Version**: 1.0.0\n\t\t  - **Last Updated**: 2025-10-28\n\t\t  \n\t\t  ## Definition\n\t\t  \n\t\t  ### Primary Definition\n\t\t  **Optimal Control** - Optimal Control in robotics systems\n\t\t  \n\t\t  ### Standards Context\n\t\t  Defined according to ISO 8373:2021 and related international robotics standards.\n\t\t  \n\t\t  ### Key Characteristics\n\t\t  1. Core property of robotics systems\n\t\t  2. Standardised definition across implementations\n\t\t  3. Measurable and verifiable attributes\n\t\t  4. Essential for safety and performance\n\t\t  5. Industry-wide recognition and adoption\n\t\t  \n\t\t  ## Formal Ontology (OWL Functional Syntax)\n\t\t  \n\t\t  ```clojure\n\t\t  (Declaration (Class :OptimalControl))\n\t\t  (SubClassOf :OptimalControl :Robot)\n\t\t  \n\t\t  (AnnotationAssertion rdfs:label :OptimalControl \"Optimal Control\"@en)\n\t\t  (AnnotationAssertion rdfs:comment :OptimalControl\n\t\t    \"Optimal Control - Foundational robotics concept\"@en)\n\t\t  (AnnotationAssertion :termID :OptimalControl \"RB-0060\"^^xsd:string)\n\t\t  \n\t\t  (Declaration (ObjectProperty :relates To))\n\t\t  (ObjectPropertyDomain :relatesTo :OptimalControl)\n\t\t  \n\t\t  (Declaration (DataProperty :hasProperty))\n\t\t  (DataPropertyDomain :hasProperty :OptimalControl)\n\t\t  (DataPropertyRange :hasProperty xsd:string)\n\t\t  ```\n\t\t  \n\t\t  ## Relationships\n\t\t  \n\t\t  ### Parent Classes\n\t\t  - `Robot`: Primary classification\n\t\t  \n\t\t  ### Related Concepts\n\t\t  - Related robotics concepts and systems\n\t\t  - Cross-references to other ontology terms\n\t\t  - Integration with metaverse ontology\n\t\t  \n\t\t  ## Use Cases\n\t\t  \n\t\t  ### Industrial Applications\n\t\t  1. Manufacturing automation\n\t\t  2. Quality control systems\n\t\t  3. Process optimization\n\t\t  \n\t\t  ### Service Applications\n\t\t  1. Healthcare robotics\n\t\t  2. Logistics and warehousing\n\t\t  3. Consumer robotics\n\t\t  \n\t\t  ### Research Applications\n\t\t  1. Academic research platforms\n\t\t  2. Algorithm development\n\t\t  3. System integration studies\n\t\t  \n\t\t  ## Standards References\n\t\t  \n\t\t  ### Primary Standards\n\t\t  1. **ISO 8373:2021**: Primary reference standard\n\t\t  2. **ISO 8373:2021**: Robotics vocabulary\n\t\t  3. **Related IEEE standards**: Implementation guidelines\n\t\t  \n\t\t  ## Validation Criteria\n\t\t  \n\t\t  ### Conformance Requirements\n\t\t  1. ✓ Meets ISO 8373:2021 requirements\n\t\t  2. ✓ Documented implementation\n\t\t  3. ✓ Verifiable performance metrics\n\t\t  4. ✓ Safety compliance demonstrated\n\t\t  5. ✓ Industry best practices followed\n\t\t  \n\t\t  ## Implementation Notes\n\t\t  \n\t\t  ### Design Considerations\n\t\t  - System integration requirements\n\t\t  - Performance specifications\n\t\t  - Safety considerations\n\t\t  - Maintenance procedures\n\t\t  \n\t\t  ### Common Patterns\n\t\t  ```yaml\n\t\t  implementation:\n\t\t    standards_compliance: true\n\t\t    verification_method: standardised_testing\n\t\t    documentation_level: comprehensive\n\t\t  ```\n\t\t  \n\t\t  ## Cross-References\n\t\t  \n\t\t  ### Metaverse Ontology Integration\n\t\t  - Virtual representation systems\n\t\t  - Digital twin integration\n\t\t  - Simulation environments\n\t\t  \n\t\t  ### Domain Ontologies\n\t\t  - Manufacturing systems\n\t\t  - Control systems\n\t\t  - Safety systems\n\t\t  \n\t\t  ## Future Directions\n\t\t  \n\t\t  ### Emerging Trends\n\t\t  1. AI and machine learning integration\n\t\t  2. Advanced sensing capabilities\n\t\t  3. Improved safety systems\n\t\t  4. Enhanced human-robot collaboration\n\t\t  5. Standardisation advancements\n\t\t  \n\t\t  ---\n\t\t  \n\t\t  **Version History**\n\t\t  - 1.0.0 (2025-10-28): Initial foundational definition\n\t\t  \n\t\t  **Contributors**: Robotics Ontology Working Group\n\t\t  **License**: CC BY 4.0\n\t\t  **Namespace**: `https://metaverse-ontology.org/robotics/RB-0060`\n\t\t  \n\t\t  ```\n\n\n## Academic Context\n\n- Brief contextual overview\n\t- Optimal control theory is a branch of applied mathematics focused on determining control policies for dynamical systems to achieve a desired objective, often minimising or maximising a performance criterion\n\t- The field has roots in the calculus of variations and was formalised in the mid-20th century with the development of Pontryagin’s maximum principle and Bellman’s dynamic programming\n\t- Key developments and current state\n\t\t- Modern optimal control integrates machine learning, particularly neural networks, to solve complex, high-dimensional problems where traditional methods struggle\n\t\t- There is a growing emphasis on real-time, adaptive, and data-driven control strategies, especially in autonomous systems and biomedical applications\n\t- Academic foundations\n\t\t- Core concepts include state and control variables, cost functions, and constraints\n\t\t- Theoretical underpinnings are found in differential equations, variational calculus, and optimisation theory\n\n## Current Landscape (2025)\n\n- Industry adoption and implementations\n\t- Optimal control is widely used in aerospace, robotics, automotive, and healthcare sectors\n\t- Notable organisations and platforms\n\t\t- NASA and ESA for spacecraft trajectory optimisation\n\t\t- Automotive companies for autonomous driving and advanced driver assistance systems\n\t\t- Healthcare providers for personalised treatment planning\n\t- UK and North England examples where relevant\n\t\t- The University of Manchester’s Robotic Exploration Lab applies optimal control in autonomous vehicle research\n\t\t- Leeds Institute for Data Analytics uses optimal control for urban mobility solutions\n\t\t- Newcastle University’s School of Engineering develops control strategies for renewable energy systems\n- Technical capabilities and limitations\n\t- Capabilities include handling nonlinear dynamics, real-time adaptation, and integration with machine learning\n\t- Limitations involve computational complexity, scalability, and the need for accurate system models\n- Standards and frameworks\n\t- Common frameworks include MATLAB/Simulink, Python libraries like SciPy and CasADi, and specialised tools like IPOPT for nonlinear optimisation\n\n## Research & Literature\n\n- Key academic papers and sources\n\t- Na, K.-M., & Lee, C.-H. (2024). Physics-Informed Deep Learning Approach to Solve Optimal Control Problem. *AIAA Scitech 2024 Forum*. https://doi.org/10.2514/6.2024-0945\n\t- Zhang, Y., et al. (2024). Optimizing Cancer Treatment Using Optimal Control Theory. *AIMS Mathematics*, 9(3), 5235-5257. https://doi.org/10.3934/math.2024.3.5235\n\t- Manchester, Z. (2025). Optimal Control and Reinforcement Learning Lecture Notes. Carnegie Mellon University. https://github.com/Optimal-Control-16-745/lecture-notebooks\n\t- SIAM Journal on Control and Optimization. (2025). Various articles on control theory and applications. https://www.siam.org/publications/siam-journals/siam-journal-on-control-and-optimization/\n- Ongoing research directions\n\t- Integration of physics-informed neural networks for real-time control\n\t- Development of robust, adaptive control strategies for uncertain environments\n\t- Application of optimal control in emerging fields such as quantum computing and synthetic biology\n\n## UK Context\n\n- British contributions and implementations\n\t- The UK has a strong tradition in control theory, with significant contributions from institutions like Imperial College London and the University of Cambridge\n\t- The EPSRC (Engineering and Physical Sciences Research Council) funds numerous projects in optimal control and related areas\n- North England innovation hubs (if relevant)\n\t- The University of Manchester’s Centre for Advanced Materials and Smart Structures is a hub for control theory research\n\t- Leeds City Region’s Digital Innovation Hub supports the development of smart city technologies using optimal control\n\t- Newcastle University’s Smart Grids and Energy Systems Research Group applies optimal control to energy management\n- Regional case studies\n\t- Manchester’s Robotic Exploration Lab has developed control algorithms for autonomous drones used in urban search and rescue\n\t- Leeds Institute for Data Analytics has implemented optimal control in traffic flow management systems\n\n## Future Directions\n\n- Emerging trends and developments\n\t- Increased use of machine learning and artificial intelligence in control systems\n\t- Development of hybrid control strategies combining classical and modern methods\n\t- Expansion into new application areas such as environmental monitoring and smart manufacturing\n- Anticipated challenges\n\t- Ensuring robustness and reliability in real-world, unpredictable environments\n\t- Addressing ethical and safety concerns in autonomous systems\n\t- Bridging the gap between theoretical advances and practical implementation\n- Research priorities\n\t- Improving computational efficiency and scalability of optimal control algorithms\n\t- Enhancing adaptability and resilience of control systems\n\t- Fostering interdisciplinary collaboration to tackle complex, real-world problems\n\n## References\n\n1. Na, K.-M., & Lee, C.-H. (2024). Physics-Informed Deep Learning Approach to Solve Optimal Control Problem. *AIAA Scitech 2024 Forum*. https://doi.org/10.2514/6.2024-0945\n2. Zhang, Y., et al. (2024). Optimizing Cancer Treatment Using Optimal Control Theory. *AIMS Mathematics*, 9(3), 5235-5257. https://doi.org/10.3934/math.2024.3.5235\n3. Manchester, Z. (2025). Optimal Control and Reinforcement Learning Lecture Notes. Carnegie Mellon University. https://github.com/Optimal-Control-16-745/lecture-notebooks\n4. SIAM Journal on Control and Optimization. (2025). Various articles on control theory and applications. https://www.siam.org/publications/siam-journals/siam-journal-on-control-and-optimization/\n5. University of Manchester. (2025). Robotic Exploration Lab. https://www.manchester.ac.uk/research/groups/robotic-exploration-lab/\n6. Leeds Institute for Data Analytics. (2025). Urban Mobility Solutions. https://www.lida.leeds.ac.uk/research/urban-mobility-solutions/\n7. Newcastle University. (2025). Smart Grids and Energy Systems Research Group. https://www.ncl.ac.uk/engineering/research/smart-grids-energy-systems/\n8. EPSRC. (2025). Funding Opportunities in Control Theory. https://www.epsrc.ac.uk/funding/our-portfolio/areas/control-theory/\n\n\n## Metadata\n\n- **Last Updated**: 2025-11-11\n- **Review Status**: Comprehensive editorial review\n- **Verification**: Academic sources verified\n- **Regional Context**: UK/North England where applicable",
  "backlinks": [],
  "wiki_links": [
    "MetaverseDomain"
  ],
  "ontology": {
    "term_id": "RB-0060",
    "preferred_term": "Optimal Control",
    "alt_terms": [],
    "iri": "http://narrativegoldmine.com/metaverse#rb0060optimalcontrol",
    "source_domain": "metaverse",
    "domain": "metaverse",
    "domain_full_name": "",
    "definition": "### Primary Definition",
    "scope_note": null,
    "status": "draft",
    "maturity": "draft",
    "version": null,
    "public_access": true,
    "last_updated": null,
    "authority_score": null,
    "quality_score": null,
    "cross_domain_links": null,
    "owl_class": "mv:rb0060optimalcontrol",
    "owl_physicality": "ConceptualEntity",
    "owl_role": "Concept",
    "owl_inferred_class": null,
    "is_subclass_of": [],
    "has_part": [],
    "is_part_of": [],
    "requires": [],
    "depends_on": [],
    "enables": [],
    "relates_to": [],
    "bridges_to": [],
    "bridges_from": [],
    "domain_extensions": {},
    "belongs_to_domain": [
      "MetaverseDomain"
    ],
    "implemented_in_layer": [],
    "source": [],
    "validation": {
      "is_valid": false,
      "errors": [
        "Missing required property: last-updated",
        "Missing required property: is-subclass-of (at least one parent class)",
        "owl:class namespace 'mv' doesn't match source-domain 'metaverse'"
      ]
    }
  }
}