{
  "id": "Permissionless Network",
  "title": "Permissionless Network",
  "content": "- ### OntologyBlock\n  id:: permissionless-network-ontology\n  collapsed:: true\n\t- ontology:: true\n\t- term-id:: BC-0090\n\t- preferred-term:: Permissionless Network\n\t- status:: complete\n\t- public-access:: true\n\t- definition:: Open access blockchain within blockchain systems, providing essential functionality for distributed ledger technology operations and properties.\n\t- source:: [[ISO/IEC 23257:2021]], [[IEEE 2418.1]], [[NIST NISTIR]]\n\t- maturity:: mature\n\t- owl:class:: bc:PermissionlessNetwork\n\t- owl:physicality:: VirtualEntity\n\t- owl:role:: Object\n\t- owl:inferred-class:: bc:VirtualObject\n\t- belongsToDomain:: [[CryptographicDomain]]\n\t- #### Relationships\n\t  id:: permissionless-network-relationships\n\t  collapsed:: true\n\t\t- is-subclass-of:: [[Blockchain Network]]\n\t\t- bridges-to:: [[Networkcomponent]]\n\t\t- bridges-to:: [[BlockchainEntity]]\n\n## Permissionless Network\n\nPermissionless Network refers to open access blockchain within blockchain systems, providing essential functionality for distributed ledger technology operations and properties.\n\n- Industry adoption and implementations\n\t- Notable organisations and platforms\n\t\t- Bitcoin and Ethereum continue to dominate as the most widely used permissionless blockchains\n\t\t- Layer-2 solutions (e.g., Optimism, Arbitrum) have matured, improving scalability and reducing transaction costs\n\t\t- DeFi and NFT platforms built on permissionless networks are now mainstream, with significant user bases and institutional interest\n\t- UK and North England examples where relevant\n\t\t- UK-based fintechs and Web3 startups increasingly leverage permissionless networks for transparent, trustless services\n\t\t- In North England, cities like Manchester and Leeds host growing blockchain communities, with local universities and incubators supporting research and development\n\t\t- For example, the University of Manchester’s Distributed Systems Group explores permissionless architectures for supply chain and identity management\n\t- Technical capabilities and limitations\n\t\t- Permissionless networks offer high transparency and censorship resistance, but face challenges in scalability, energy efficiency, and regulatory compliance\n\t\t- Advances in consensus algorithms and Layer-2 solutions have mitigated some limitations, but trade-offs remain\n\t- Standards and frameworks\n\t\t- Industry standards (e.g., ERC-20, ERC-721) and open-source frameworks (e.g., Ethereum, Polkadot) facilitate interoperability and innovation\n\t\t- Regulatory frameworks in the UK are evolving, with the Financial Conduct Authority (FCA) providing guidance on crypto assets and decentralised finance\n\n## Technical Details\n\n- **Id**: permissionless-network-standards\n- **Collapsed**: true\n- **Domain Prefix**: BC\n- **Sequence Number**: 0090\n- **Filename History**: [\"BC-0090-permissionless-network.md\"]\n- **Public Access**: true\n- **Source Domain**: metaverse\n- **Status**: complete\n- **Last Updated**: 2025-10-28\n- **Maturity**: mature\n- **Source**: [[ISO/IEC 23257:2021]], [[IEEE 2418.1]], [[NIST NISTIR]]\n- **Authority Score**: 0.95\n- **Owl:Class**: bc:PermissionlessNetwork\n- **Owl:Physicality**: VirtualEntity\n- **Owl:Role**: Object\n- **Owl:Inferred Class**: bc:VirtualObject\n- **Belongstodomain**: [[CryptographicDomain]]\n- **Implementedinlayer**: [[SecurityLayer]]\n- **Is Subclass Of**: [[Blockchain Entity]], [[NetworkComponent]]\n\n## Research & Literature\n\n- Key academic papers and sources\n\t- Nakamoto, S. (2008). Bitcoin: A Peer-to-Peer Electronic Cash System. https://bitcoin.org/bitcoin.pdf\n\t- Buterin, V. (2014). A Next-Generation Smart Contract and Decentralized Application Platform. Ethereum White Paper. https://ethereum.org/en/whitepaper/\n\t- Seira, A., Allen, J., Watsky, C., & Alley, R. (2024). Governance of Permissionless Blockchain Networks. FEDS Notes. https://doi.org/10.17016/2380-7172.3443\n\t- Wood, G. (2014). Ethereum: A Secure Decentralised Generalised Transaction Ledger. Ethereum Yellow Paper. https://ethereum.github.io/yellowpaper/paper.pdf\n- Ongoing research directions\n\t- Scalability and energy efficiency of consensus algorithms\n\t- Decentralised governance and stakeholder participation\n\t- Regulatory compliance and privacy-preserving technologies\n\n## UK Context\n\n- British contributions and implementations\n\t- UK researchers and institutions have made significant contributions to blockchain and distributed systems, with a focus on permissionless architectures\n\t- The FCA and Bank of England are actively engaged in regulatory and policy discussions around crypto assets and decentralised finance\n- North England innovation hubs (if relevant)\n\t- Manchester, Leeds, Newcastle, and Sheffield are home to vibrant tech and academic communities exploring blockchain and Web3\n\t- Local universities and incubators support startups and research projects in permissionless networks, fostering regional innovation\n- Regional case studies\n\t- The University of Manchester’s Distributed Systems Group collaborates with industry on permissionless blockchain applications for supply chain and identity management\n\t- Leeds-based fintechs are experimenting with DeFi protocols built on permissionless networks, aiming to enhance financial inclusion and transparency\n\n## Future Directions\n\n- Emerging trends and developments\n\t- Continued evolution of Layer-2 solutions and cross-chain interoperability\n\t- Growing interest in privacy-preserving technologies and regulatory compliance\n\t- Expansion of permissionless networks into new sectors, such as healthcare and public services\n- Anticipated challenges\n\t- Balancing decentralisation with regulatory requirements\n\t- Addressing scalability and energy efficiency concerns\n\t- Ensuring robust security and resilience against attacks\n- Research priorities\n\t- Scalability and energy efficiency of consensus algorithms\n\t- Decentralised governance and stakeholder participation\n\t- Regulatory compliance and privacy-preserving technologies\n\n## References\n\n1. Nakamoto, S. (2008). Bitcoin: A Peer-to-Peer Electronic Cash System. https://bitcoin.org/bitcoin.pdf\n2. Buterin, V. (2014). A Next-Generation Smart Contract and Decentralized Application Platform. Ethereum White Paper. https://ethereum.org/en/whitepaper/\n3. Seira, A., Allen, J., Watsky, C., & Alley, R. (2024). Governance of Permissionless Blockchain Networks. FEDS Notes. https://doi.org/10.17016/2380-7172.3443\n4. Wood, G. (2014). Ethereum: A Secure Decentralised Generalised Transaction Ledger. Ethereum Yellow Paper. https://ethereum.github.io/yellowpaper/paper.pdf\n5. Financial Conduct Authority (FCA). (2025). Cryptoassets: Regulatory Guidance. https://www.fca.org.uk/firms/cryptoassets\n6. Bank of England. (2025). Central Bank Digital Currency: Progress and Prospects. https://www.bankofengland.co.uk/central-bank-digital-currency\n7. University of Manchester. (2025). Distributed Systems Group. https://www.manchester.ac.uk/research/groups/distributed-systems-group\n8. Leeds Fintech Hub. (2025). DeFi and Blockchain Innovation. https://www.leedsfintechhub.co.uk/defi-blockchain-innovation\n\n## Metadata\n\n- **Migration Status**: Ontology block enriched on 2025-11-12\n- **Last Updated**: 2025-11-12\n- **Review Status**: Comprehensive editorial review\n- **Verification**: Academic sources verified\n- **Regional Context**: UK/North England where applicable",
  "backlinks": [],
  "wiki_links": [
    "NIST NISTIR",
    "Blockchain Network",
    "BlockchainEntity",
    "CryptographicDomain",
    "SecurityLayer",
    "NetworkComponent",
    "Blockchain Entity",
    "ISO/IEC 23257:2021",
    "Networkcomponent",
    "IEEE 2418.1"
  ],
  "ontology": {
    "term_id": "BC-0090",
    "preferred_term": "Permissionless Network",
    "alt_terms": [],
    "iri": "http://narrativegoldmine.com/blockchain#PermissionlessNetwork",
    "source_domain": "metaverse",
    "domain": "metaverse",
    "domain_full_name": "",
    "definition": "Open access blockchain within blockchain systems, providing essential functionality for distributed ledger technology operations and properties.",
    "scope_note": null,
    "status": "complete",
    "maturity": "mature",
    "version": null,
    "public_access": true,
    "last_updated": "2025-10-28",
    "authority_score": 0.95,
    "quality_score": null,
    "cross_domain_links": null,
    "owl_class": "bc:PermissionlessNetwork",
    "owl_physicality": "VirtualEntity",
    "owl_role": "Object",
    "owl_inferred_class": "bc:VirtualObject",
    "is_subclass_of": [
      "Blockchain Network"
    ],
    "has_part": [],
    "is_part_of": [],
    "requires": [],
    "depends_on": [],
    "enables": [],
    "relates_to": [],
    "bridges_to": [],
    "bridges_from": [],
    "domain_extensions": {},
    "belongs_to_domain": [
      "CryptographicDomain"
    ],
    "implemented_in_layer": [],
    "source": [
      "ISO/IEC 23257:2021",
      "IEEE 2418.1",
      "NIST NISTIR"
    ],
    "other_relationships": {
      "bridges-to": [
        "Networkcomponent",
        "BlockchainEntity"
      ]
    },
    "validation": {
      "is_valid": false,
      "errors": [
        "owl:class namespace 'bc' doesn't match source-domain 'metaverse'"
      ]
    }
  }
}