{
  "id": "Physics Engine",
  "title": "Physics Engine",
  "content": "- ### OntologyBlock\n  id:: physics-engine-ontology\n  collapsed:: true\n\t- ontology:: true\n\t- term-id:: 20118\n\t- preferred-term:: Physics Engine\n\t- public-access:: true\n\t- definition:: Software component that simulates physical interactions, constraints, and dynamics in real-time for virtual environments.\n\t- source:: [[EWG/MSF Taxonomy]], [[SIGGRAPH Pipeline WG]], [[ISO/IEC 23090-3]]\n\t- maturity:: mature\n\t- owl:class:: mv:PhysicsEngine\n\t- owl:physicality:: VirtualEntity\n\t- owl:role:: Object\n\t- owl:inferred-class:: mv:VirtualObject\n\t- owl:functional-syntax:: true\n\t- belongsToDomain:: [[CreativeMediaDomain]], [[InfrastructureDomain]]\n\t- implementedInLayer:: [[ComputeLayer]]\n\t- #### Relationships\n\t  id:: physics-engine-relationships\n\t  collapsed:: true\n\t\t- is-subclass-of:: [[Extended Reality (XR)]]\n\t\t- is-part-of:: [[Compute Layer]]\n\t\t- is-part-of:: [[Virtual World]]\n\t\t- is-part-of:: [[Simulation Environment]]\n\t\t- is-part-of:: [[Game Engine]]\n\t\t- has-part:: [[Constraint Solver]]\n\t\t- has-part:: [[Particle System]]\n\t\t- has-part:: [[Collision Detection System]]\n\t\t- has-part:: [[Rigid Body Dynamics]]\n\t\t- requires:: [[Graphics API]]\n\t\t- requires:: [[Math Library]]\n\t\t- requires:: [[Compute Infrastructure]]\n\t\t- enables:: [[Physical Simulation]]\n\t\t- enables:: [[Realistic Interaction]]\n\t\t- enables:: [[Collision Response]]\n\t\t- enables:: [[Kinematic Animation]]\n\t\t- is-dependency-of:: [[Mixed Reality (MR)]]\n\t\t- is-dependency-of:: [[Virtual Performance Space]]\n\t\t- is-required-by:: [[Physics-Based Animation]]\n\t\t- depends-on:: [[3D Engine]]\n\t\t- depends-on:: [[Animation System]]\n\t\t- depends-on:: [[Rendering Pipeline]]\n\t- #### CrossDomainBridges\n\t  id:: physics-engine-bridges\n\t  collapsed:: true\n\t\t- dt:uses:: [[Machine Learning]]\n\t\t- dt:enables:: [[VirtualWorld]]\n\t\t- dt:enables:: [[Digital Twin]]\n\n## Academic Context\n\n- Physics engines represent a foundational computational paradigm for simulating Newtonian mechanics in virtual environments\n  - Emerged from computational physics research and real-time graphics development in the 1990s\n  - Now integral to game development, robotics simulation, and virtual reality applications\n  - Mathematical foundations rooted in classical mechanics, collision detection algorithms, and numerical integration methods\n\n## Current Landscape (2025)\n\n- Industry adoption and implementations\n  - Commercial engines: Havok (widely deployed in legacy systems), PhysX, Bullet Physics\n  - Open-source alternatives gaining traction: Bullet, ODE (Open Dynamics Engine), Rapier\n  - Game development platforms: Unreal Engine, Unity, Godot all feature integrated physics systems\n  - Robotics simulation: MuJoCo remains standard for research; NVIDIA's Newton (open-source, GPU-accelerated) represents recent advancement in robotics-focused physics simulation\n  - Virtual environments: Second Life continues using Havok engine; newer platforms exploring modular physics abstraction layers\n  - UK and North England context\n    - Unreal Engine development community active across Manchester and Leeds tech hubs\n    - Game development studios in Sheffield and Newcastle increasingly adopting physics-based gameplay mechanics\n    - University research groups (particularly in computer science departments across North England) contributing to physics simulation optimisation\n\n- Technical capabilities and limitations\n  - Core capabilities: gravity simulation, collision detection and response, rigid body dynamics, constraint solving, friction and elasticity modelling\n  - Particle systems and fluid dynamics increasingly integrated (though computationally expensive)\n  - Real-time performance remains primary constraint; trade-offs between accuracy and computational efficiency unavoidable\n  - Determinism challenges in networked environments complicate multiplayer implementations\n  - GPU acceleration (NVIDIA Warp, DirectX compute) now standard for performance-critical applications\n\n- Standards and frameworks\n  - No universal standard; engine selection typically dictated by project requirements\n  - Physics Abstraction Layer (PAL) concept enables theoretical engine interchangeability, though rarely implemented in practice\n  - OpenUSD gaining adoption for standardised physics asset representation\n\n## Research & Literature\n\n- Key academic papers and sources\n  - Millington, I. (2007). *Game Physics Engine Development: How to Build a Robust Commercial-Grade Physics Engine for Your Game*. CRC Press. [Foundational text on real-time physics implementation]\n  - Erleben, K., Sporring, J., Henriksen, K., & Dohlmann, H. (2005). Physics-Based Animation. Charles River Media. [Comprehensive treatment of animation physics]\n  - Baraff, D. (2001). Physically Based Modelling: Principles and Practice. *SIGGRAPH Course Notes*. [Seminal work on constraint-based dynamics]\n  - Recent developments: GPU-accelerated physics simulation papers from NVIDIA Research and DeepMind robotics division (2024-2025) exploring differentiable physics for machine learning applications\n\n- Ongoing research directions\n  - Differentiable physics engines enabling gradient-based optimisation for robotics and design applications\n  - Physics-informed neural networks (PINNs) for hybrid simulation approaches\n  - Real-time cloth and fluid simulation improvements\n  - Deterministic physics for competitive multiplayer gaming\n\n## UK Context\n\n- British contributions and implementations\n  - Havok (originally Irish, now part of Microsoft ecosystem) widely adopted across UK game studios\n  - University of Manchester and University of Leeds maintain active research groups in computational physics and game technology\n  - UK game development industry (particularly in Brighton, Manchester, and Guildford) relies heavily on physics engines for AAA and indie titles\n\n- North England innovation hubs\n  - Sheffield: Home to established game development community; physics-based mechanics increasingly central to local studio output\n  - Leeds: Growing tech sector with game development studios integrating advanced physics for VR applications\n  - Manchester: Emerging hub for graphics and simulation research; university partnerships exploring robotics simulation\n  - Newcastle: Digital media sector expanding; physics simulation relevant to emerging XR applications\n\n- Regional case studies\n  - North England universities collaborating on physics simulation optimisation for resource-constrained environments\n  - Local game studios adopting open-source physics engines to reduce licencing costs\n\n## Future Directions\n\n- Emerging trends and developments\n  - Shift towards open-source, modular physics solutions reducing vendor lock-in\n  - GPU-accelerated physics becoming standard rather than optional\n  - Integration with machine learning pipelines for physics-informed AI training\n  - Increased focus on deterministic physics for competitive gaming and financial simulations\n  - Physics engines expanding beyond entertainment into architectural visualisation, industrial simulation, and autonomous systems\n\n- Anticipated challenges\n  - Balancing simulation accuracy with real-time performance constraints remains persistent\n  - Standardisation efforts progressing slowly; fragmentation across platforms continues\n  - Licensing complexity for commercial applications (particularly relevant for studios seeking open-source alternatives)\n  - Skill gap: developers increasingly need physics literacy alongside programming expertise\n\n- Research priorities\n  - Efficient contact handling in complex, many-body scenarios\n  - Stable constraint solving for soft-body and cloth simulation\n  - Physics simulation reproducibility across hardware platforms\n  - Integration frameworks enabling seamless physics engine substitution\n\n---\n\n**Note on current status:** The definition provided remains accurate as of November 2025. Physics engines continue functioning as real-time simulators of physical interactions; no fundamental paradigm shifts have occurred since 2024. The field is consolidating around GPU acceleration and open-source solutions rather than experiencing revolutionary changeâ€”rather like watching a well-tuned engine run smoothly, which is precisely what one hopes for in production systems.\n\n## Metadata\n\n- **Last Updated**: 2025-11-11\n- **Review Status**: Comprehensive editorial review\n- **Verification**: Academic sources verified\n- **Regional Context**: UK/North England where applicable",
  "backlinks": [
    "Game Engine",
    "Virtual World",
    "Virtual Performance Space",
    "Mixed Reality (MR)",
    "Compute Layer",
    "VirtualWorld",
    "Physics-Based Animation"
  ],
  "wiki_links": [
    "EWG/MSF Taxonomy",
    "Collision Detection System",
    "Machine Learning",
    "Mixed Reality (MR)",
    "ISO/IEC 23090-3",
    "VirtualWorld",
    "Game Engine",
    "Physical Simulation",
    "Simulation Environment",
    "InfrastructureDomain",
    "Extended Reality (XR)",
    "Compute Layer",
    "Animation System",
    "CreativeMediaDomain",
    "Kinematic Animation",
    "Virtual Performance Space",
    "Rendering Pipeline",
    "Digital Twin",
    "Compute Infrastructure",
    "Particle System",
    "3D Engine",
    "ComputeLayer",
    "Virtual World",
    "Graphics API",
    "Realistic Interaction",
    "Rigid Body Dynamics",
    "Physics-Based Animation",
    "Constraint Solver",
    "Collision Response",
    "SIGGRAPH Pipeline WG",
    "Math Library"
  ],
  "ontology": {
    "term_id": "20118",
    "preferred_term": "Physics Engine",
    "alt_terms": [],
    "iri": "http://narrativegoldmine.com/metaverse#PhysicsEngine",
    "source_domain": null,
    "domain": "mv",
    "domain_full_name": "Metaverse",
    "definition": "Software component that simulates physical interactions, constraints, and dynamics in real-time for virtual environments.",
    "scope_note": null,
    "status": null,
    "maturity": "mature",
    "version": null,
    "public_access": true,
    "last_updated": null,
    "authority_score": null,
    "quality_score": null,
    "cross_domain_links": null,
    "owl_class": "mv:PhysicsEngine",
    "owl_physicality": "VirtualEntity",
    "owl_role": "Object",
    "owl_inferred_class": "mv:VirtualObject",
    "is_subclass_of": [
      "Extended Reality (XR)"
    ],
    "has_part": [
      "Constraint Solver",
      "Particle System",
      "Collision Detection System",
      "Rigid Body Dynamics"
    ],
    "is_part_of": [
      "Compute Layer",
      "Virtual World",
      "Simulation Environment",
      "Game Engine"
    ],
    "requires": [
      "Graphics API",
      "Math Library",
      "Compute Infrastructure"
    ],
    "depends_on": [
      "3D Engine",
      "Animation System",
      "Rendering Pipeline"
    ],
    "enables": [
      "Physical Simulation",
      "Realistic Interaction",
      "Collision Response",
      "Kinematic Animation"
    ],
    "relates_to": [],
    "bridges_to": [],
    "bridges_from": [],
    "domain_extensions": {},
    "belongs_to_domain": [
      "CreativeMediaDomain",
      "InfrastructureDomain"
    ],
    "implemented_in_layer": [
      "ComputeLayer"
    ],
    "source": [
      "EWG/MSF Taxonomy",
      "SIGGRAPH Pipeline WG",
      "ISO/IEC 23090-3"
    ],
    "other_relationships": {
      "is-dependency-of": [
        "Mixed Reality (MR)",
        "Virtual Performance Space"
      ],
      "is-required-by": [
        "Physics-Based Animation"
      ]
    },
    "validation": {
      "is_valid": false,
      "errors": [
        "Missing required property: source-domain",
        "Missing required property: status",
        "Missing required property: last-updated",
        "term-id '20118' doesn't match domain 'mv' (expected MV-)"
      ]
    }
  }
}