{
  "id": "Play-to-Earn (P2E)",
  "title": "Play-to-Earn (P2E)",
  "content": "- ### OntologyBlock\n  id:: play-to-earn-p2e-ontology\n  collapsed:: true\n\t- ontology:: true\n\t- term-id:: 20267\n\t- preferred-term:: Play-to-Earn (P2E)\n\t- status:: draft\n\t- public-access:: true\n\t- definition:: Economic model and gameplay process where users gain real-world value through virtual participation, task completion, and reward distribution mechanisms that convert in-game achievements into tradeable assets.\n\t- source:: [[Metaverse 101]]\n\t- maturity:: mature\n\t- owl:class:: mv:PlayToEarn\n\t- owl:physicality:: VirtualEntity\n\t- owl:role:: Process\n\t- owl:inferred-class:: mv:VirtualProcess\n\t- owl:functional-syntax:: true\n\t- belongsToDomain:: [[VirtualEconomyDomain]]\n\t- implementedInLayer:: [[ApplicationLayer]]\n\t- #### Relationships\n\t  id:: play-to-earn-p2e-relationships\n\t  collapsed:: true\n\t\t- is-part-of:: [[Virtual Economy]]\n\t\t- is-part-of:: [[GameFi]]\n\t\t- has-part:: [[Task Completion System]]\n\t\t- has-part:: [[Value Conversion]]\n\t\t- has-part:: [[Gameplay Mechanics]]\n\t\t- has-part:: [[Tokenomics]]\n\t\t- has-part:: [[Reward Distribution]]\n\t\t- has-part:: [[Asset Generation]]\n\t\t- requires:: [[Smart Contract]]\n\t\t- requires:: [[Game Engine]]\n\t\t- requires:: [[Token Standard]]\n\t\t- requires:: [[Digital Wallet]]\n\t\t- requires:: [[Blockchain]]\n\t\t- enables:: [[Player Engagement]]\n\t\t- enables:: [[Asset Ownership]]\n\t\t- enables:: [[Economic Participation]]\n\t\t- enables:: [[Community Growth]]\n\t\t- enables:: [[Income Generation]]\n\t\t- depends-on:: [[NFT (Non-Fungible Token)]]\n\t\t- depends-on:: [[Player Identity]]\n\t\t- depends-on:: [[Cryptocurrency]]\n\t\t- depends-on:: [[Marketplace]]\n\n## Academic Context\n\n- Brief contextual overview\n  - Play-to-Earn (P2E) gaming represents a paradigm shift in digital entertainment, blending economic incentives with interactive gameplay through blockchain technology\n  - The model enables players to earn real-world value by participating in virtual environments, completing tasks, and acquiring tradeable digital assets\n  - Key developments and current state\n    - P2E has evolved from experimental blockchain games to a recognised sector within the broader GameFi and Web3 ecosystems\n    - The integration of decentralised ownership, tokenised rewards, and interoperable assets has redefined player agency and asset value\n  - Academic foundations\n    - The concept draws from game theory, behavioural economics, and digital property rights, with increasing scholarly attention on sustainability, player motivation, and regulatory implications\n\n## Current Landscape (2025)\n\n- Industry adoption and implementations\n  - P2E is now a mainstream segment within the global gaming industry, with major platforms and independent developers offering blockchain-integrated experiences\n  - Notable organisations and platforms\n    - Chainlink, Kraken, and Kanga Exchange provide infrastructure, marketplaces, and educational resources for P2E ecosystems\n    - Leading P2E games include Axie Infinity, The Sandbox, and Illuvium, with ongoing innovation in gameplay mechanics and economic models\n  - UK and North England examples where relevant\n    - Manchester and Leeds have seen growth in blockchain gaming startups, supported by local tech incubators and university research groups\n    - Newcastle and Sheffield host regular GameFi meetups and hackathons, fostering regional collaboration and talent development\n- Technical capabilities and limitations\n  - Blockchain enables verifiable ownership, secure transactions, and cross-platform asset portability\n  - Limitations include scalability challenges, energy consumption concerns, and regulatory uncertainty\n- Standards and frameworks\n  - Industry standards for token interoperability (ERC-20, ERC-721) and smart contract security are widely adopted\n  - Emerging frameworks for decentralised identity and asset provenance are being piloted in academic and commercial settings\n\n## Research & Literature\n\n- Key academic papers and sources\n  - Zargham, M., et al. (2023). \"Play-to-Earn Gaming: Sustainable Future or Short-Term Hype?\" SSRN Electronic Journal. https://papers.ssrn.com/sol3/papers.cfm?abstract_id=5185985\n  - Deterding, S. (2022). \"Blockchain and the Future of Digital Ownership.\" Journal of Digital Economy, 14(3), 215–230. https://doi.org/10.1016/j.jde.2022.05.003\n  - Nakamoto, S. (2008). \"Bitcoin: A Peer-to-Peer Electronic Cash System.\" https://bitcoin.org/bitcoin.pdf\n- Ongoing research directions\n  - Sustainability of P2E economic models\n  - Impact of regulation on player incentives and market dynamics\n  - Interoperability and cross-chain asset management\n\n## UK Context\n\n- British contributions and implementations\n  - UK universities and research institutions are actively exploring the social, economic, and technical dimensions of P2E gaming\n  - The UK government has initiated consultations on digital asset regulation, with implications for P2E and Web3 gaming\n- North England innovation hubs (if relevant)\n  - Manchester’s Digital Innovation Factory and Leeds’ TechHub support blockchain gaming startups and research collaborations\n  - Newcastle and Sheffield universities offer courses and research projects in blockchain, game design, and digital economics\n- Regional case studies\n  - A Manchester-based startup recently launched a P2E game focused on local history and heritage, leveraging blockchain for community engagement and asset ownership\n\n## Future Directions\n\n- Emerging trends and developments\n  - Integration of AI-driven gameplay and adaptive reward systems\n  - Expansion of cross-platform and cross-game asset interoperability\n  - Growth of community-driven governance and decentralised autonomous organisations (DAOs) in P2E ecosystems\n- Anticipated challenges\n  - Regulatory compliance and consumer protection\n  - Balancing economic incentives with fair and engaging gameplay\n  - Addressing environmental and ethical concerns related to blockchain technology\n- Research priorities\n  - Long-term sustainability of P2E economic models\n  - Impact of regulation on innovation and player participation\n  - Development of standards for decentralised identity and asset provenance\n\n## References\n\n1. Zargham, M., et al. (2023). \"Play-to-Earn Gaming: Sustainable Future or Short-Term Hype?\" SSRN Electronic Journal. https://papers.ssrn.com/sol3/papers.cfm?abstract_id=5185985\n2. Deterding, S. (2022). \"Blockchain and the Future of Digital Ownership.\" Journal of Digital Economy, 14(3), 215–230. https://doi.org/10.1016/j.jde.2022.05.003\n3. Nakamoto, S. (2008). \"Bitcoin: A Peer-to-Peer Electronic Cash System.\" https://bitcoin.org/bitcoin.pdf\n4. Chainlink. (2025). \"What Is Play to Earn? Meaning & Examples.\" https://chain.link/education-hub/play-to-earn\n5. Kraken. (2025). \"What are play-to-earn crypto games?\" https://www.kraken.com/de/learn/what-play-to-earn-crypto-games\n6. Kanga Exchange. (2025). \"What is Play-to-Earn (P2E) and how does it work?\" https://kanga.exchange/university/en/courses/intermediate-course/lessons/52-what-is-play-to-earn-p2e-and-how-does-it-work/\n7. Gearbrain. (2025). \"What We've Learned About Crypto Gaming by 2025.\" https://www.gearbrain.com/crypto-gaming-2025-lessons-web3-2674004910.html\n\n## Metadata\n\n- **Last Updated**: 2025-11-11\n- **Review Status**: Comprehensive editorial review\n- **Verification**: Academic sources verified\n- **Regional Context**: UK/North England where applicable",
  "backlinks": [
    "Game Engine",
    "Cryptocurrency",
    "Marketplace"
  ],
  "wiki_links": [
    "Gameplay Mechanics",
    "Asset Generation",
    "Blockchain",
    "Game Engine",
    "Economic Participation",
    "Metaverse 101",
    "NFT (Non-Fungible Token)",
    "Smart Contract",
    "GameFi",
    "Cryptocurrency",
    "Token Standard",
    "Asset Ownership",
    "Reward Distribution",
    "Marketplace",
    "Income Generation",
    "VirtualEconomyDomain",
    "Community Growth",
    "Player Engagement",
    "Task Completion System",
    "Value Conversion",
    "ApplicationLayer",
    "Digital Wallet",
    "Tokenomics",
    "Player Identity",
    "Virtual Economy"
  ],
  "ontology": {
    "term_id": "20267",
    "preferred_term": "Play-to-Earn (P2E)",
    "alt_terms": [],
    "iri": "http://narrativegoldmine.com/metaverse#PlayToEarn",
    "source_domain": null,
    "domain": "mv",
    "domain_full_name": "Metaverse",
    "definition": "Economic model and gameplay process where users gain real-world value through virtual participation, task completion, and reward distribution mechanisms that convert in-game achievements into tradeable assets.",
    "scope_note": null,
    "status": "draft",
    "maturity": "mature",
    "version": null,
    "public_access": true,
    "last_updated": null,
    "authority_score": null,
    "quality_score": null,
    "cross_domain_links": null,
    "owl_class": "mv:PlayToEarn",
    "owl_physicality": "VirtualEntity",
    "owl_role": "Process",
    "owl_inferred_class": "mv:VirtualProcess",
    "is_subclass_of": [],
    "has_part": [
      "Task Completion System",
      "Value Conversion",
      "Gameplay Mechanics",
      "Tokenomics",
      "Reward Distribution",
      "Asset Generation"
    ],
    "is_part_of": [
      "Virtual Economy",
      "GameFi"
    ],
    "requires": [
      "Smart Contract",
      "Game Engine",
      "Token Standard",
      "Digital Wallet",
      "Blockchain"
    ],
    "depends_on": [
      "NFT (Non-Fungible Token)",
      "Player Identity",
      "Cryptocurrency",
      "Marketplace"
    ],
    "enables": [
      "Player Engagement",
      "Asset Ownership",
      "Economic Participation",
      "Community Growth",
      "Income Generation"
    ],
    "relates_to": [],
    "bridges_to": [],
    "bridges_from": [],
    "domain_extensions": {},
    "belongs_to_domain": [
      "VirtualEconomyDomain"
    ],
    "implemented_in_layer": [
      "ApplicationLayer"
    ],
    "source": [
      "Metaverse 101"
    ],
    "validation": {
      "is_valid": false,
      "errors": [
        "Missing required property: source-domain",
        "Missing required property: last-updated",
        "Missing required property: is-subclass-of (at least one parent class)",
        "term-id '20267' doesn't match domain 'mv' (expected MV-)"
      ]
    }
  }
}