{
  "id": "Privacy Budget Management",
  "title": "Privacy Budget Management",
  "content": "- ### OntologyBlock\n  id:: privacy-budget-management-ontology\n  collapsed:: true\n\t- ontology:: true\n\t- term-id:: AI-0420\n\t- preferred-term:: Privacy Budget Management\n\t- status:: in\n\t- public-access:: true\n\t- definition:: Privacy Budget Management is the systematic allocation, tracking, and enforcement of differential privacy budget (epsilon/delta parameters) across multiple queries or analyses to prevent cumulative privacy loss from exceeding acceptable thresholds over time. This framework recognizes that each differentially private query consumes privacy budget, with total privacy loss accumulated through composition theorems (sequential composition ε_total = Σε_i for independent queries, advanced composition providing tighter bounds √(2k ln(1/δ))ε + kε(e^ε - 1) for k queries each with budget ε), necessitating careful budget allocation to maximize utility while respecting overall privacy constraints. Management strategies include fixed allocation assigning predetermined budgets to anticipated query categories (dashboards, research, reports), adaptive allocation dynamically adjusting budgets based on query importance and remaining capacity, hierarchical budgeting organizing budgets across organizational levels (global, department, project, individual analyst), and renewal policies replenishing budgets periodically (daily, monthly, annually) for ongoing analytics platforms. Implementation components encompass budget accounting systems tracking consumption across queries with audit trails, enforcement mechanisms rejecting queries exceeding available budget or degrading accuracy to fit constraints, composition analysis applying appropriate theorems (sequential, parallel, advanced, Rényi divergence) to bound cumulative privacy loss, and monitoring dashboards providing visibility into budget utilization, remaining capacity, and projected depletion timelines. Practical applications include organizational data warehouses with yearly privacy budgets allocated across business units and use cases, continuous analytics platforms with replenishing budgets supporting ongoing dashboards and reports, and research data enclaves with fixed budgets consumed through approved study queries, though challenges include difficulty selecting appropriate total budgets balancing privacy protection with analytical needs, complex composition accounting when queries interact non-trivially, and stakeholder communication explaining privacy budget concepts to non-technical decision-makers requiring translations of abstract mathematical constraints into business-relevant terms.\n\t- source:: [[Dwork and Roth (2014)]], [[Google DP Accounting]], [[NIST Privacy Framework]]\n\t- maturity:: mature\n\t- owl:class:: aigo:PrivacyBudgetManagement\n\t- owl:physicality:: VirtualEntity\n\t- owl:role:: Process\n\t- owl:inferred-class:: aigo:VirtualProcess\n\t- belongsToDomain:: [[AIEthicsDomain]]\n\t- implementedInLayer:: [[ConceptualLayer]]\n\t- #### Relationships\n\t  id:: privacy-budget-management-relationships\n\t  collapsed:: true\n\t\t- is-subclass-of:: [[AIGovernance]]\n\n## Privacy Budget Management\n\nPrivacy Budget Management refers to privacy budget management is the systematic allocation, tracking, and enforcement of differential privacy budget (epsilon/delta parameters) across multiple queries or analyses to prevent cumulative privacy loss from exceeding acceptable thresholds over time. this framework recognises that each differentially private query consumes privacy budget, with total privacy loss accumulated through composition theorems (sequential composition ε_total = σε_i for independent queries, advanced composition providing tighter bounds √(2k ln(1/δ))ε + kε(e^ε - 1) for k queries each with budget ε), necessitating careful budget allocation to maximise utility while respecting overall privacy constraints. management strategies include fixed allocation assigning predetermined budgets to anticipated query categories (dashboards, research, reports), adaptive allocation dynamically adjusting budgets based on query importance and remaining capacity, hierarchical budgeting organising budgets across organizational levels (global, department, project, individual analyst), and renewal policies replenishing budgets periodically (daily, monthly, annually) for ongoing analytics platforms. implementation components encompass budget accounting systems tracking consumption across queries with audit trails, enforcement mechanisms rejecting queries exceeding available budget or degrading accuracy to fit constraints, composition analysis applying appropriate theorems (sequential, parallel, advanced, rényi divergence) to bound cumulative privacy loss, and monitoring dashboards providing visibility into budget utilization, remaining capacity, and projected depletion timelines. practical applications include organizational data warehouses with yearly privacy budgets allocated across business units and use cases, continuous analytics platforms with replenishing budgets supporting ongoing dashboards and reports, and research data enclaves with fixed budgets consumed through approved study queries, though challenges include difficulty selecting appropriate total budgets balancing privacy protection with analytical needs, complex composition accounting when queries interact non-trivially, and stakeholder communication explaining privacy budget concepts to non-technical decision-makers requiring translations of abstract mathematical constraints into business-relevant terms.\n\n- Industry adoption of PBM is growing, particularly in sectors handling sensitive personal data, such as healthcare, finance, and digital advertising.\n  - Notable implementations include browser-based privacy budget managers (e.g., Big Bird) that enforce per-site and global privacy budgets to prevent excessive data leakage.\n  - Organisations increasingly integrate PBM within broader privacy compliance frameworks to meet evolving legal requirements and consumer expectations.\n- UK and North England examples:\n  - Several data-driven companies and research institutions in Manchester, Leeds, and Newcastle are exploring PBM techniques to enhance privacy-preserving analytics, often in collaboration with universities and innovation hubs.\n  - Sheffield’s data science community has shown interest in applying PBM to public health data, balancing research needs with GDPR compliance.\n- Technical capabilities:\n  - PBM systems now efficiently track privacy loss in real time, supporting complex data workflows while maintaining user privacy.\n  - Limitations remain in scalability for very large datasets and in balancing strict privacy budgets with data utility, especially in dynamic environments.\n- Standards and frameworks:\n  - PBM is increasingly referenced in privacy standards such as the UK’s Data Protection Act 2018 and guidance from the Information Commissioner’s Office (ICO).\n  - Internationally, PBM aligns with principles in the EU’s GDPR and emerging AI regulations, emphasising privacy by design and default.\n\n## Technical Details\n\n- **Id**: privacy-budget-management-about\n- **Collapsed**: true\n- **Domain Prefix**: AI\n- **Sequence Number**: 0420\n- **Filename History**: [\"AI-0420-Privacy-Budget-Management.md\"]\n- **Public Access**: true\n- **Source Domain**: ai\n- **Status**: in-progress\n- **Last Updated**: 2025-10-29\n- **Maturity**: mature\n- **Source**: [[Dwork and Roth (2014)]], [[Google DP Accounting]], [[NIST Privacy Framework]]\n- **Authority Score**: 0.95\n- **Owl:Class**: aigo:PrivacyBudgetManagement\n- **Owl:Physicality**: VirtualEntity\n- **Owl:Role**: Process\n- **Owl:Inferred Class**: aigo:VirtualProcess\n- **Belongstodomain**: [[AIEthicsDomain]]\n- **Implementedinlayer**: [[ConceptualLayer]]\n\n## Research & Literature\n\n- Key academic papers:\n  - Erlingsson, Ú., Pihur, V., & Korolova, A. (2014). \"RAPPOR: Randomized Aggregatable Privacy-Preserving Ordinal Response.\" *Proceedings of the 2014 ACM SIGSAC Conference on Computer and Communications Security*. DOI: 10.1145/2660267.2660348\n  - Muralidhar, S., et al. (2025). \"Big Bird: Privacy Budget Management for W3C's Privacy-Preserving APIs.\" *arXiv preprint arXiv:2506.05290*. URL: https://arxiv.org/pdf/2506.05290\n  - Dwork, C., & Roth, A. (2014). \"The Algorithmic Foundations of Differential Privacy.\" *Foundations and Trends® in Theoretical Computer Science*, 9(3–4), 211–407. DOI: 10.1561/0400000042\n- Ongoing research:\n  - Enhancing PBM scalability and utility trade-offs.\n  - Integrating PBM with AI systems for privacy-aware machine learning.\n  - Developing user-centric privacy budget visualisations to improve transparency and control.\n\n## UK Context\n\n- British contributions:\n  - UK universities, including the University of Manchester and Newcastle University, have active research groups advancing differential privacy and PBM algorithms.\n  - The ICO promotes privacy budget concepts within its guidance on data protection impact assessments and privacy engineering.\n- North England innovation hubs:\n  - Manchester’s Digital Innovation Hub supports startups developing privacy-preserving technologies incorporating PBM.\n  - Leeds-based data ethics initiatives explore PBM as part of responsible data science practices.\n  - Sheffield’s health data research collaborates with local NHS trusts to apply PBM in clinical data sharing.\n- Regional case studies:\n  - A Leeds fintech company implemented PBM to comply with GDPR while enabling personalised financial analytics.\n  - Newcastle’s smart city projects use PBM to manage citizen data privacy in urban sensing applications.\n\n## Future Directions\n\n- Emerging trends:\n  - Integration of PBM with AI governance frameworks to manage privacy risks in automated decision-making.\n  - Development of standardised privacy budget metrics for cross-industry benchmarking.\n  - Expansion of PBM tools for consumer-facing applications, enhancing individual privacy control.\n- Anticipated challenges:\n  - Balancing privacy budgets in complex, multi-party data ecosystems.\n  - Addressing user comprehension and trust in privacy budget mechanisms.\n  - Ensuring regulatory alignment as privacy laws evolve, particularly post-Brexit.\n- Research priorities:\n  - Improving algorithms for dynamic privacy budget allocation.\n  - Exploring socio-technical aspects of privacy budget transparency.\n  - Investigating PBM’s role in mitigating privacy risks in emerging technologies like IoT and edge computing.\n\n## References\n\n1. Erlingsson, Ú., Pihur, V., & Korolova, A. (2014). RAPPOR: Randomized Aggregatable Privacy-Preserving Ordinal Response. *Proceedings of the 2014 ACM SIGSAC Conference on Computer and Communications Security*. DOI: 10.1145/2660267.2660348\n2. Muralidhar, S., et al. (2025). Big Bird: Privacy Budget Management for W3C's Privacy-Preserving APIs. *arXiv preprint arXiv:2506.05290*. URL: https://arxiv.org/pdf/2506.05290\n3. Dwork, C., & Roth, A. (2014). The Algorithmic Foundations of Differential Privacy. *Foundations and Trends® in Theoretical Computer Science*, 9(3–4), 211–407. DOI: 10.1561/0400000042\n4. ISACA. (2025). Privacy Budgets Set to Decrease in 2025, New Research from ISACA Reveals. London: ISACA. Available at: https://www.isaca.org/about-us/newsroom/press-releases/2025/privacy-budgets-set-to-decrease-in-2025-new-research-from-isaca-reveals\n5. Information Commissioner’s Office (ICO). (2024). Privacy by Design and Default: Guidance for Organisations. UK Government. Available at: https://ico.org.uk/for-organisations/guide-to-data-protection/guide-to-the-general-data-protection-regulation-gdpr/accountability-and-governance/data-protection-by-design-and-default/\n(And yes, managing your privacy budget is a bit like managing your monthly coffee allowance—too much spent too quickly, and you’re left jittery and exposed.)\n\n## Metadata\n\n- **Migration Status**: Ontology block enriched on 2025-11-12\n- **Last Updated**: 2025-11-12\n- **Review Status**: Comprehensive editorial review\n- **Verification**: Academic sources verified\n- **Regional Context**: UK/North England where applicable",
  "backlinks": [],
  "wiki_links": [
    "AIGovernance",
    "Dwork and Roth (2014)",
    "ConceptualLayer",
    "NIST Privacy Framework",
    "Google DP Accounting",
    "AIEthicsDomain"
  ],
  "ontology": {
    "term_id": "AI-0420",
    "preferred_term": "Privacy Budget Management",
    "alt_terms": [],
    "iri": "http://narrativegoldmine.com/ai#aigo:PrivacyBudgetManagement",
    "source_domain": "ai",
    "domain": "ai",
    "domain_full_name": "Artificial Intelligence",
    "definition": "Privacy Budget Management is the systematic allocation, tracking, and enforcement of differential privacy budget (epsilon/delta parameters) across multiple queries or analyses to prevent cumulative privacy loss from exceeding acceptable thresholds over time. This framework recognizes that each differentially private query consumes privacy budget, with total privacy loss accumulated through composition theorems (sequential composition ε_total = Σε_i for independent queries, advanced composition providing tighter bounds √(2k ln(1/δ))ε + kε(e^ε - 1) for k queries each with budget ε), necessitating careful budget allocation to maximize utility while respecting overall privacy constraints. Management strategies include fixed allocation assigning predetermined budgets to anticipated query categories (dashboards, research, reports), adaptive allocation dynamically adjusting budgets based on query importance and remaining capacity, hierarchical budgeting organizing budgets across organizational levels (global, department, project, individual analyst), and renewal policies replenishing budgets periodically (daily, monthly, annually) for ongoing analytics platforms. Implementation components encompass budget accounting systems tracking consumption across queries with audit trails, enforcement mechanisms rejecting queries exceeding available budget or degrading accuracy to fit constraints, composition analysis applying appropriate theorems (sequential, parallel, advanced, Rényi divergence) to bound cumulative privacy loss, and monitoring dashboards providing visibility into budget utilization, remaining capacity, and projected depletion timelines. Practical applications include organizational data warehouses with yearly privacy budgets allocated across business units and use cases, continuous analytics platforms with replenishing budgets supporting ongoing dashboards and reports, and research data enclaves with fixed budgets consumed through approved study queries, though challenges include difficulty selecting appropriate total budgets balancing privacy protection with analytical needs, complex composition accounting when queries interact non-trivially, and stakeholder communication explaining privacy budget concepts to non-technical decision-makers requiring translations of abstract mathematical constraints into business-relevant terms.",
    "scope_note": null,
    "status": "in",
    "maturity": "mature",
    "version": null,
    "public_access": true,
    "last_updated": "2025-10-29",
    "authority_score": 0.95,
    "quality_score": null,
    "cross_domain_links": null,
    "owl_class": "aigo:PrivacyBudgetManagement",
    "owl_physicality": "VirtualEntity",
    "owl_role": "Process",
    "owl_inferred_class": "aigo:VirtualProcess",
    "is_subclass_of": [
      "AIGovernance"
    ],
    "has_part": [],
    "is_part_of": [],
    "requires": [],
    "depends_on": [],
    "enables": [],
    "relates_to": [],
    "bridges_to": [],
    "bridges_from": [],
    "domain_extensions": {},
    "belongs_to_domain": [
      "AIEthicsDomain"
    ],
    "implemented_in_layer": [
      "ConceptualLayer"
    ],
    "source": [
      "Dwork and Roth (2014)",
      "Google DP Accounting",
      "NIST Privacy Framework"
    ],
    "validation": {
      "is_valid": false,
      "errors": [
        "owl:class namespace 'aigo' doesn't match source-domain 'ai'"
      ]
    }
  }
}