{
  "id": "Privacy Impact Assessment (PIA)",
  "title": "Privacy Impact Assessment (PIA)",
  "content": "- ### OntologyBlock\n  id:: privacy-impact-assessment-pia-ontology\n  collapsed:: true\n\t- ontology:: true\n\t- term-id:: 20227\n\t- preferred-term:: Privacy Impact Assessment (PIA)\n\t- status:: draft\n\t- public-access:: true\n\t- definition:: Systematic evaluation process that identifies and assesses privacy risks arising from the processing of personal data in metaverse systems, ensuring compliance with data protection regulations and ethical standards.\n\t- source:: [[ISO 29134]]\n\t- maturity:: mature\n\t- owl:class:: mv:PrivacyImpactAssessment\n\t- owl:physicality:: VirtualEntity\n\t- owl:role:: Process\n\t- owl:inferred-class:: mv:VirtualProcess\n\t- owl:functional-syntax:: true\n\t- belongsToDomain:: [[TrustAndGovernanceDomain]]\n\t- implementedInLayer:: [[MiddlewareLayer]]\n\t- #### Relationships\n\t  id:: privacy-impact-assessment-pia-relationships\n\t  collapsed:: true\n\t\t- is-subclass-of:: [[AIGovernance]]\n\t\t- is-part-of:: [[Data Protection Management System]]\n\t\t- is-part-of:: [[Privacy Governance Framework]]\n\t\t- has-part:: [[Impact Analysis Framework]]\n\t\t- has-part:: [[Stakeholder Consultation Engine]]\n\t\t- has-part:: [[Risk Identification Module]]\n\t\t- has-part:: [[Compliance Verification System]]\n\t\t- has-part:: [[Mitigation Strategy Generator]]\n\t\t- requires:: [[Privacy Requirements]]\n\t\t- requires:: [[Data Flow Mapping]]\n\t\t- requires:: [[Risk Assessment Methodology]]\n\t\t- requires:: [[Regulatory Compliance Database]]\n\t\t- enables:: [[User Trust]]\n\t\t- enables:: [[Privacy By Design]]\n\t\t- enables:: [[Risk Mitigation]]\n\t\t- enables:: [[GDPR Compliance]]\n\t\t- enables:: [[Transparent Data Processing]]\n\t\t- depends-on:: [[Personal Data Inventory]]\n\t\t- depends-on:: [[Legal Framework]]\n\t\t- depends-on:: [[Organizational Privacy Policy]]\n\n## Academic Context\n\n- Privacy Impact Assessment (PIA) is a **systematic process** designed to evaluate how personal data is collected, used, shared, and maintained within information systems, with the goal of identifying and mitigating privacy risks.\n  - Rooted in data protection principles and privacy-by-design frameworks, PIAs ensure compliance with legal, regulatory, and ethical standards.\n  - The academic foundation draws from information privacy theory, risk management, and legal studies, emphasising accountability and transparency in data processing.\n  - Key developments include integration of PIAs into broader privacy governance and risk assessment methodologies, especially in complex digital environments such as metaverse systems.\n\n## Current Landscape (2025)\n\n- PIAs are widely adopted across industries to manage privacy risks associated with personal data processing, particularly in emerging technologies like metaverse platforms.\n  - Organisations implement PIAs as part of compliance with data protection laws such as the UK GDPR and the Data Protection Act 2018.\n  - Notable platforms and institutions in the UK, including those in North England, increasingly embed PIAs in project lifecycles to address privacy in digital innovation.\n- Technical capabilities have advanced with automated tools supporting PIA processes, yet challenges remain in fully capturing dynamic privacy risks in evolving systems.\n- Established standards and frameworks guide PIA implementation, including the UK Information Commissioner's Office (ICO) PIA guidance, ISO/IEC 29134:2017 on Privacy Impact Assessment, and the European Data Protection Board recommendations.\n\n## Research & Literature\n\n- Key academic sources include:\n  - Cavoukian, A. (2010). *Privacy by Design: The 7 Foundational Principles*. Information and Privacy Commissioner of Ontario.\n  - Wright, D., & De Hert, P. (2012). *Privacy Impact Assessment*. Springer.\n  - Kuner, C., et al. (2020). *The GDPR: Understanding the General Data Protection Regulation*. Oxford University Press.\n- Ongoing research explores:\n  - Enhancing PIA methodologies for AI and metaverse environments.\n  - Quantitative risk assessment models within PIAs.\n  - Integration of ethical considerations alongside legal compliance.\n- DOIs and URLs are available via academic databases for these works.\n\n## UK Context\n\n- The UK Information Commissioner’s Office (ICO) provides authoritative guidance on PIAs, emphasising their role in GDPR compliance and accountability.\n- North England innovation hubs such as Manchester’s Digital Innovation District, Leeds’ Digital Hub, and Newcastle’s Science Central actively incorporate PIAs in digital projects, particularly those involving personal data in immersive technologies.\n- Regional case studies highlight successful PIA applications in public sector digital transformation and private sector metaverse initiatives, demonstrating practical privacy risk management.\n\n## Future Directions\n\n- Emerging trends include:\n  - Expansion of PIAs to cover complex data ecosystems, including cross-border data flows and AI-driven decision-making.\n  - Greater automation and integration of PIAs into agile development cycles.\n- Anticipated challenges:\n  - Balancing comprehensive privacy risk assessment with rapid innovation demands.\n  - Addressing privacy risks in decentralised and immersive metaverse platforms.\n- Research priorities focus on:\n  - Developing standardised metrics for privacy risk quantification.\n  - Enhancing stakeholder engagement in PIA processes.\n  - Embedding ethical frameworks alongside technical assessments.\n\n## References\n\n1. Cavoukian, A. (2010). *Privacy by Design: The 7 Foundational Principles*. Information and Privacy Commissioner of Ontario.\n2. Wright, D., & De Hert, P. (2012). *Privacy Impact Assessment*. Springer.\n3. Kuner, C., et al. (2020). *The GDPR: Understanding the General Data Protection Regulation*. Oxford University Press.\n4. Information Commissioner’s Office (2023). *Conducting privacy impact assessments code of practice*. ICO.\n5. ISO/IEC 29134:2017. *Information technology — Security techniques — Guidelines for privacy impact assessment*. International Organization for Standardization.\n\n## Metadata\n\n- **Last Updated**: 2025-11-11\n- **Review Status**: Comprehensive editorial review\n- **Verification**: Academic sources verified\n- **Regional Context**: UK/North England where applicable",
  "backlinks": [],
  "wiki_links": [
    "Data Flow Mapping",
    "AIGovernance",
    "Regulatory Compliance Database",
    "Organizational Privacy Policy",
    "Legal Framework",
    "Risk Identification Module",
    "Risk Assessment Methodology",
    "Personal Data Inventory",
    "Mitigation Strategy Generator",
    "TrustAndGovernanceDomain",
    "Privacy Requirements",
    "Stakeholder Consultation Engine",
    "MiddlewareLayer",
    "Privacy By Design",
    "ISO 29134",
    "User Trust",
    "Transparent Data Processing",
    "Data Protection Management System",
    "Privacy Governance Framework",
    "Risk Mitigation",
    "Impact Analysis Framework",
    "GDPR Compliance",
    "Compliance Verification System"
  ],
  "ontology": {
    "term_id": "20227",
    "preferred_term": "Privacy Impact Assessment (PIA)",
    "alt_terms": [],
    "iri": "http://narrativegoldmine.com/metaverse#PrivacyImpactAssessment",
    "source_domain": null,
    "domain": "mv",
    "domain_full_name": "Metaverse",
    "definition": "Systematic evaluation process that identifies and assesses privacy risks arising from the processing of personal data in metaverse systems, ensuring compliance with data protection regulations and ethical standards.",
    "scope_note": null,
    "status": "draft",
    "maturity": "mature",
    "version": null,
    "public_access": true,
    "last_updated": null,
    "authority_score": null,
    "quality_score": null,
    "cross_domain_links": null,
    "owl_class": "mv:PrivacyImpactAssessment",
    "owl_physicality": "VirtualEntity",
    "owl_role": "Process",
    "owl_inferred_class": "mv:VirtualProcess",
    "is_subclass_of": [
      "AIGovernance"
    ],
    "has_part": [
      "Impact Analysis Framework",
      "Stakeholder Consultation Engine",
      "Risk Identification Module",
      "Compliance Verification System",
      "Mitigation Strategy Generator"
    ],
    "is_part_of": [
      "Data Protection Management System",
      "Privacy Governance Framework"
    ],
    "requires": [
      "Privacy Requirements",
      "Data Flow Mapping",
      "Risk Assessment Methodology",
      "Regulatory Compliance Database"
    ],
    "depends_on": [
      "Personal Data Inventory",
      "Legal Framework",
      "Organizational Privacy Policy"
    ],
    "enables": [
      "User Trust",
      "Privacy By Design",
      "Risk Mitigation",
      "GDPR Compliance",
      "Transparent Data Processing"
    ],
    "relates_to": [],
    "bridges_to": [],
    "bridges_from": [],
    "domain_extensions": {},
    "belongs_to_domain": [
      "TrustAndGovernanceDomain"
    ],
    "implemented_in_layer": [
      "MiddlewareLayer"
    ],
    "source": [
      "ISO 29134"
    ],
    "validation": {
      "is_valid": false,
      "errors": [
        "Missing required property: source-domain",
        "Missing required property: last-updated",
        "term-id '20227' doesn't match domain 'mv' (expected MV-)"
      ]
    }
  }
}