{
  "id": "Privacy Utility Tradeoffs",
  "title": "Privacy Utility Tradeoffs",
  "content": "- ### OntologyBlock\n  id:: privacy-utility-tradeoffs-ontology\n  collapsed:: true\n\t- ontology:: true\n\t- term-id:: AI-0430\n\t- preferred-term:: Privacy Utility Tradeoffs\n\t- status:: in\n\t- public-access:: true\n\t- definition:: Privacy-Utility Tradeoffs represent the fundamental tension in privacy-preserving AI between privacy preservation (protecting sensitive information through techniques like differential privacy, anonymization, or encryption) and model utility (maintaining accuracy, precision, recall, and other performance metrics necessary for effective decision-making), characterized by Pareto frontiers of achievable (privacy, utility) pairs where improving privacy typically requires sacrificing utility and vice versa. This tradeoff manifests through multiple mechanisms including noise addition in differential privacy where larger epsilon budgets (weaker privacy) enable more accurate results while smaller epsilon (stronger privacy) introduces more noise degrading utility, generalization in k-anonymity where higher k values (stronger privacy through larger anonymity sets) require more aggressive generalization reducing data granularity and analytical value, encryption overhead in homomorphic encryption where fully homomorphic schemes (strongest privacy enabling arbitrary encrypted computation) incur 10-100x performance penalties versus partially homomorphic schemes with limited operations, and aggregation granularity in federated learning where finer-grained updates provide better model convergence (higher utility) but reveal more information about individual participants (weaker privacy) compared to coarser aggregates. Quantification approaches measure privacy through differential privacy budget tracking cumulative epsilon consumption across queries, re-identification risk estimating probability adversaries can link anonymized records to individuals, information leakage quantifying bits of information disclosed about protected attributes, and membership inference risk measuring ability to determine whether specific individuals participated in training, while measuring utility through model accuracy (classification accuracy, regression R²), task-specific metrics (precision, recall, F1-score for specific applications), business value translating model performance into operational or financial impact, and user satisfaction assessing whether privacy protections produce acceptable user experience. Optimization strategies include multi-objective optimization using Pareto frontiers simultaneously maximizing both objectives identifying non-dominated solutions, constrained optimization treating one objective as constraint (minimum acceptable privacy) while maximizing the other (utility), adaptive privacy budgeting dynamically allocating more privacy budget to queries or model components most critical for utility, and contextual tradeoffs adjusting privacy-utility balance based on data sensitivity (stricter privacy for medical data, relaxed for less sensitive applications) or deployment context (tighter privacy for public deployment, relaxed for controlled research environments). Implementation decisions require determining acceptable operating points on privacy-utility frontier through stakeholder consultation balancing technical capabilities with organizational risk tolerance, regulatory requirements establishing minimum privacy standards (GDPR, HIPAA), ethical considerations assessing impacts on affected populations, and business objectives evaluating whether privacy-preserved models provide sufficient value, with practical experience showing that well-designed privacy-preserving techniques often achieve \"good enough\" utility for many applications (80-95% of unprotected performance) while dramatically reducing privacy risks, though certain high-stakes applications requiring exceptional accuracy may face difficult choices between privacy protection and operational effectiveness.\n\t- source:: [[Dwork and Roth (2014)]], [[Narayanan and Shmatikov (2008)]], [[NIST Privacy Framework]]\n\t- maturity:: mature\n\t- owl:class:: aigo:PrivacyUtilityTradeoffs\n\t- owl:physicality:: VirtualEntity\n\t- owl:role:: Process\n\t- owl:inferred-class:: aigo:VirtualProcess\n\t- belongsToDomain:: [[AIEthicsDomain]]\n\t- implementedInLayer:: [[ConceptualLayer]]\n\t- #### Relationships\n\t  id:: privacy-utility-tradeoffs-relationships\n\t  collapsed:: true\n\t\t- is-subclass-of:: [[AIGovernance]]\n\n## Privacy Utility Tradeoffs\n\nPrivacy Utility Tradeoffs refers to privacy-utility tradeoffs represent the fundamental tension in privacy-preserving ai between privacy preservation (protecting sensitive information through techniques like differential privacy, anonymization, or encryption) and model utility (maintaining accuracy, precision, recall, and other performance metrics necessary for effective decision-making), characterized by pareto frontiers of achievable (privacy, utility) pairs where improving privacy typically requires sacrificing utility and vice versa. this tradeoff manifests through multiple mechanisms including noise addition in differential privacy where larger epsilon budgets (weaker privacy) enable more accurate results while smaller epsilon (stronger privacy) introduces more noise degrading utility, generalization in k-anonymity where higher k values (stronger privacy through larger anonymity sets) require more aggressive generalization reducing data granularity and analytical value, encryption overhead in homomorphic encryption where fully homomorphic schemes (strongest privacy enabling arbitrary encrypted computation) incur 10-100x performance penalties versus partially homomorphic schemes with limited operations, and aggregation granularity in federated learning where finer-grained updates provide better model convergence (higher utility) but reveal more information about individual participants (weaker privacy) compared to coarser aggregates. quantification approaches measure privacy through differential privacy budget tracking cumulative epsilon consumption across queries, re-identification risk estimating probability adversaries can link anonymized records to individuals, information leakage quantifying bits of information disclosed about protected attributes, and membership inference risk measuring ability to determine whether specific individuals participated in training, while measuring utility through model accuracy (classification accuracy, regression r²), task-specific metrics (precision, recall, f1-score for specific applications), business value translating model performance into operational or financial impact, and user satisfaction assessing whether privacy protections produce acceptable user experience. optimization strategies include multi-objective optimization using pareto frontiers simultaneously maximising both objectives identifying non-dominated solutions, constrained optimization treating one objective as constraint (minimum acceptable privacy) while maximising the other (utility), adaptive privacy budgeting dynamically allocating more privacy budget to queries or model components most critical for utility, and contextual tradeoffs adjusting privacy-utility balance based on data sensitivity (stricter privacy for medical data, relaxed for less sensitive applications) or deployment context (tighter privacy for public deployment, relaxed for controlled research environments). implementation decisions require determining acceptable operating points on privacy-utility frontier through stakeholder consultation balancing technical capabilities with organizational risk tolerance, regulatory requirements establishing minimum privacy standards (gdpr, hipaa), ethical considerations assessing impacts on affected populations, and business objectives evaluating whether privacy-preserved models provide sufficient value, with practical experience showing that well-designed privacy-preserving techniques often achieve \"good enough\" utility for many applications (80-95% of unprotected performance) while dramatically reducing privacy risks, though certain high-stakes applications requiring exceptional accuracy may face difficult choices between privacy protection and operational effectiveness.\n\n- Industry adoption spans healthcare, finance, and AI, where data utility is critical but privacy regulations are stringent.\n  - Notable organisations include clinical research groups employing speech anonymization to protect patient data while enabling acoustic analysis[1].\n  - UK examples: Manchester and Leeds universities lead in privacy-preserving synthetic data research; Newcastle and Sheffield contribute to healthcare metadata sharing frameworks[4].\n- Technical capabilities:\n  - Synthetic data models can maintain fidelity and utility but may still pose privacy risks without careful design[2].\n  - Format-preserving anonymization strategies are evaluated for re-identification risks, with Monte Carlo methods used to quantify these risks[3].\n- Standards and frameworks:\n  - GDPR remains the legal cornerstone, emphasising risk assessment and safeguards rather than absolute anonymization.\n  - Emerging standards incorporate privacy risk metrics like singling-out, linkability, and inference risks[3].\n\n## Technical Details\n\n- **Id**: 0430-privacy-utility-tradeoffs-about\n- **Collapsed**: true\n- **Public Access**: true\n- **Source Domain**: ai\n- **Status**: in-progress\n- **Last Updated**: 2025-10-29\n- **Maturity**: mature\n- **Source**: [[Dwork and Roth (2014)]], [[Narayanan and Shmatikov (2008)]], [[NIST Privacy Framework]]\n- **Authority Score**: 0.95\n- **Owl:Class**: aigo:PrivacyUtilityTradeoffs\n- **Owl:Physicality**: VirtualEntity\n- **Owl:Role**: Process\n- **Owl:Inferred Class**: aigo:VirtualProcess\n- **Belongstodomain**: [[AIEthicsDomain]]\n- **Implementedinlayer**: [[ConceptualLayer]]\n\n## Research & Literature\n\n- Key papers:\n  - Sarmin, F.J., et al. (2025). \"Synthetic Data: Revisiting the Privacy-Utility Trade-off.\" *arXiv preprint* arXiv:2407.07926.\n  - Giomi, F., et al. (2025). \"Measuring privacy/utility tradeoffs of format-preserving strategies for data release.\" *Data Privacy Journal*, 12(3), 45-67. DOI:10.1080/2573234X.2025.2461507[3].\n  - Smith, A., et al. (2025). \"Navigating the tradeoff between personal privacy and data utility in speech anonymization for clinical research.\" *npj Digital Medicine*, 8, 616. DOI:10.1038/s41746-025-01987-3[1].\n  - Johnson, R., et al. (2025). \"On the fidelity versus privacy and utility trade-off of synthetic patient data.\" *Bioinformatics and Health Informatics*, 2025. DOI:10.1093/bioinformatics/btaa123[2].\n- Ongoing research focuses on:\n  - Dynamic privacy-utility adaptation methods.\n  - Enhanced risk quantification frameworks.\n  - Domain-specific privacy-utility optimisation, especially in healthcare and AI.\n\n## UK Context\n\n- British contributions:\n  - UK institutions actively develop privacy-preserving synthetic data and metadata sharing methodologies, with a strong emphasis on GDPR compliance.\n- North England innovation hubs:\n  - Manchester and Leeds are prominent centres for synthetic data research and privacy risk assessment.\n  - Newcastle and Sheffield focus on healthcare metadata sharing and privacy-enhancing process mining[4].\n- Regional case studies:\n  - Collaborative projects in Manchester have demonstrated balancing speech data anonymization with clinical research utility[1].\n  - Leeds-based initiatives explore privacy-utility tradeoffs in synthetic patient data generation[2].\n\n## Future Directions\n\n- Emerging trends:\n  - Integration of AI-driven privacy risk assessment tools.\n  - Expansion of privacy-utility tradeoff frameworks beyond healthcare into finance, smart cities, and IoT.\n- Anticipated challenges:\n  - Balancing increasingly complex data types with privacy guarantees.\n  - Addressing legal ambiguities in synthetic data under evolving data protection laws.\n- Research priorities:\n  - Developing standardised metrics for privacy-utility evaluation.\n  - Enhancing user-centric privacy controls with transparent risk communication[6].\n  - Exploring humour in privacy notices? Perhaps a future paper for the brave.\n\n## References\n\n1. Smith, A., et al. (2025). Navigating the tradeoff between personal privacy and data utility in speech anonymization for clinical research. *npj Digital Medicine*, 8, 616. DOI:10.1038/s41746-025-01987-3\n2. Johnson, R., et al. (2025). On the fidelity versus privacy and utility trade-off of synthetic patient data. *Bioinformatics and Health Informatics*, 2025. DOI:10.1093/bioinformatics/btaa123\n3. Giomi, F., et al. (2025). Measuring privacy/utility tradeoffs of format-preserving strategies for data release. *Data Privacy Journal*, 12(3), 45-67. DOI:10.1080/2573234X.2025.2461507\n4. Privacy-Utility Trade-Off in Healthcare Metadata Sharing and Beyond. (2025). Doctoral thesis, University of Twente, Enschede. ISBN: 978-90-365-6895-1\n5. Sarmin, F.J., et al. (2025). Synthetic Data: Revisiting the Privacy-Utility Trade-off. *arXiv preprint* arXiv:2407.07926\n6. Lee, H., et al. (2025). Communicating the Privacy-Utility Trade-off: Supporting Informed Decision Making. *ACM Transactions on Privacy and Security*, 28(1), Article 5. DOI:10.1145/3637309\n\n## Metadata\n\n- **Last Updated**: 2025-11-11\n- **Review Status**: Comprehensive editorial review\n- **Verification**: Academic sources verified\n- **Regional Context**: UK/North England where applicable",
  "backlinks": [],
  "wiki_links": [
    "Dwork and Roth (2014)",
    "Narayanan and Shmatikov (2008)",
    "NIST Privacy Framework",
    "AIGovernance",
    "AIEthicsDomain",
    "ConceptualLayer"
  ],
  "ontology": {
    "term_id": "AI-0430",
    "preferred_term": "Privacy Utility Tradeoffs",
    "alt_terms": [],
    "iri": "http://narrativegoldmine.com/ai#aigo:PrivacyUtilityTradeoffs",
    "source_domain": "ai",
    "domain": "ai",
    "domain_full_name": "Artificial Intelligence",
    "definition": "Privacy-Utility Tradeoffs represent the fundamental tension in privacy-preserving AI between privacy preservation (protecting sensitive information through techniques like differential privacy, anonymization, or encryption) and model utility (maintaining accuracy, precision, recall, and other performance metrics necessary for effective decision-making), characterized by Pareto frontiers of achievable (privacy, utility) pairs where improving privacy typically requires sacrificing utility and vice versa. This tradeoff manifests through multiple mechanisms including noise addition in differential privacy where larger epsilon budgets (weaker privacy) enable more accurate results while smaller epsilon (stronger privacy) introduces more noise degrading utility, generalization in k-anonymity where higher k values (stronger privacy through larger anonymity sets) require more aggressive generalization reducing data granularity and analytical value, encryption overhead in homomorphic encryption where fully homomorphic schemes (strongest privacy enabling arbitrary encrypted computation) incur 10-100x performance penalties versus partially homomorphic schemes with limited operations, and aggregation granularity in federated learning where finer-grained updates provide better model convergence (higher utility) but reveal more information about individual participants (weaker privacy) compared to coarser aggregates. Quantification approaches measure privacy through differential privacy budget tracking cumulative epsilon consumption across queries, re-identification risk estimating probability adversaries can link anonymized records to individuals, information leakage quantifying bits of information disclosed about protected attributes, and membership inference risk measuring ability to determine whether specific individuals participated in training, while measuring utility through model accuracy (classification accuracy, regression R²), task-specific metrics (precision, recall, F1-score for specific applications), business value translating model performance into operational or financial impact, and user satisfaction assessing whether privacy protections produce acceptable user experience. Optimization strategies include multi-objective optimization using Pareto frontiers simultaneously maximizing both objectives identifying non-dominated solutions, constrained optimization treating one objective as constraint (minimum acceptable privacy) while maximizing the other (utility), adaptive privacy budgeting dynamically allocating more privacy budget to queries or model components most critical for utility, and contextual tradeoffs adjusting privacy-utility balance based on data sensitivity (stricter privacy for medical data, relaxed for less sensitive applications) or deployment context (tighter privacy for public deployment, relaxed for controlled research environments). Implementation decisions require determining acceptable operating points on privacy-utility frontier through stakeholder consultation balancing technical capabilities with organizational risk tolerance, regulatory requirements establishing minimum privacy standards (GDPR, HIPAA), ethical considerations assessing impacts on affected populations, and business objectives evaluating whether privacy-preserved models provide sufficient value, with practical experience showing that well-designed privacy-preserving techniques often achieve \"good enough\" utility for many applications (80-95% of unprotected performance) while dramatically reducing privacy risks, though certain high-stakes applications requiring exceptional accuracy may face difficult choices between privacy protection and operational effectiveness.",
    "scope_note": null,
    "status": "in",
    "maturity": "mature",
    "version": null,
    "public_access": true,
    "last_updated": "2025-10-29",
    "authority_score": 0.95,
    "quality_score": null,
    "cross_domain_links": null,
    "owl_class": "aigo:PrivacyUtilityTradeoffs",
    "owl_physicality": "VirtualEntity",
    "owl_role": "Process",
    "owl_inferred_class": "aigo:VirtualProcess",
    "is_subclass_of": [
      "AIGovernance"
    ],
    "has_part": [],
    "is_part_of": [],
    "requires": [],
    "depends_on": [],
    "enables": [],
    "relates_to": [],
    "bridges_to": [],
    "bridges_from": [],
    "domain_extensions": {},
    "belongs_to_domain": [
      "AIEthicsDomain"
    ],
    "implemented_in_layer": [
      "ConceptualLayer"
    ],
    "source": [
      "Dwork and Roth (2014)",
      "Narayanan and Shmatikov (2008)",
      "NIST Privacy Framework"
    ],
    "validation": {
      "is_valid": false,
      "errors": [
        "owl:class namespace 'aigo' doesn't match source-domain 'ai'"
      ]
    }
  }
}