{
  "id": "Privacy By Design",
  "title": "Privacy By Design",
  "content": "- ### OntologyBlock\n  id:: privacy-by-design-ontology\n  collapsed:: true\n\t- ontology:: true\n\t- term-id:: AI-0428\n\t- preferred-term:: Privacy By Design\n\t- status:: in\n\t- public-access:: true\n\t- definition:: Privacy by Design is a proactive privacy framework and GDPR requirement (Article 25) mandating that data protection be embedded into system architecture, business practices, and technologies from inception rather than bolted on as afterthought, implementing privacy as default setting and core functionality rather than optional feature. This approach follows seven foundational principles articulated by Ann Cavoukian including proactive not reactive prevention (anticipating and preventing privacy risks before they materialize), privacy as default setting (systems configured for maximum privacy protection without user intervention), privacy embedded into design (integrated into system architecture and business operations as essential component), full functionality positive-sum not zero-sum (avoiding false dichotomies between privacy and other objectives, achieving both through innovative design), end-to-end security protecting data throughout lifecycle (from collection through retention to destruction), visibility and transparency (keeping systems open and accountable with clear documentation), and respect for user privacy (maintaining user-centric focus with empowering privacy controls). Implementation patterns documented in privacy design strategies include minimize collecting and retaining only essential data, hide protecting data from unauthorized observation through encryption and access controls, separate preventing correlation of data across contexts through architectural partitioning, aggregate processing data at group level rather than individually where possible, inform providing transparency about data practices and system behavior, control giving users meaningful choices over data processing, enforce implementing technical measures ensuring compliance with privacy policies, and demonstrate maintaining evidence of privacy compliance for accountability. GDPR Article 25 requirements mandate data protection by design requiring controllers implement appropriate technical and organizational measures (pseudonymization, minimization, security) designed to implement data protection principles effectively and integrate necessary safeguards into processing, and data protection by default ensuring only personal data necessary for specific processing purpose is processed by default in terms of amount collected, extent of processing, storage period, and accessibility, with implementation considering state of the art (current best practices and technologies), cost of implementation (proportionate to processing scale and risks), nature of processing (sensitivity, volume, complexity), and purposes of processing (primary objectives and downstream uses). AI-specific applications address model privacy preventing memorization of training examples through techniques like differential privacy, data privacy protecting input features and labels through federated learning or encrypted computation, inference privacy preventing leakage through prediction patterns using secure multi-party computation or trusted execution environments, explainability privacy balancing transparency requirements with proprietary model protection, and fairness privacy ensuring bias mitigation doesn't inadvertently expose protected attribute distributions, with evaluation through privacy assessment scores measuring design embedding completeness, implementation phase tracking (requirements, design, development, deployment, maintenance), and compliance level verification against regulatory requirements demonstrating adequate protection measures.\n\t- source:: [[Cavoukian (2009)]], [[GDPR Article 25]], [[ISO 29100]]\n\t- maturity:: mature\n\t- owl:class:: aigo:PrivacyByDesign\n\t- owl:physicality:: VirtualEntity\n\t- owl:role:: Process\n\t- owl:inferred-class:: aigo:VirtualProcess\n\t- belongsToDomain:: [[AIEthicsDomain]]\n\t- implementedInLayer:: [[ConceptualLayer]]\n\t- #### Relationships\n\t  id:: privacy-by-design-relationships\n\t  collapsed:: true\n\t\t- is-subclass-of:: [[AIGovernance]]\n\n## Privacy By Design\n\nPrivacy By Design refers to privacy by design is a proactive privacy framework and gdpr requirement (article 25) mandating that data protection be embedded into system architecture, business practices, and technologies from inception rather than bolted on as afterthought, implementing privacy as default setting and core functionality rather than optional feature. this approach follows seven foundational principles articulated by ann cavoukian including proactive not reactive prevention (anticipating and preventing privacy risks before they materialize), privacy as default setting (systems configured for maximum privacy protection without user intervention), privacy embedded into design (integrated into system architecture and business operations as essential component), full functionality positive-sum not zero-sum (avoiding false dichotomies between privacy and other objectives, achieving both through innovative design), end-to-end security protecting data throughout lifecycle (from collection through retention to destruction), visibility and transparency (keeping systems open and accountable with clear documentation), and respect for user privacy (maintaining user-centric focus with empowering privacy controls). implementation patterns documented in privacy design strategies include minimise collecting and retaining only essential data, hide protecting data from unauthorized observation through encryption and access controls, separate preventing correlation of data across contexts through architectural partitioning, aggregate processing data at group level rather than individually where possible, inform providing transparency about data practices and system behaviour, control giving users meaningful choices over data processing, enforce implementing technical measures ensuring compliance with privacy policies, and demonstrate maintaining evidence of privacy compliance for accountability. gdpr article 25 requirements mandate data protection by design requiring controllers implement appropriate technical and organizational measures (pseudonymization, minimization, security) designed to implement data protection principles effectively and integrate necessary safeguards into processing, and data protection by default ensuring only personal data necessary for specific processing purpose is processed by default in terms of amount collected, extent of processing, storage period, and accessibility, with implementation considering state of the art (current best practices and technologies), cost of implementation (proportionate to processing scale and risks), nature of processing (sensitivity, volume, complexity), and purposes of processing (primary objectives and downstream uses). ai-specific applications address model privacy preventing memorization of training examples through techniques like differential privacy, data privacy protecting input features and labels through federated learning or encrypted computation, inference privacy preventing leakage through prediction patterns using secure multi-party computation or trusted execution environments, explainability privacy balancing transparency requirements with proprietary model protection, and fairness privacy ensuring bias mitigation doesn't inadvertently expose protected attribute distributions, with evaluation through privacy assessment scores measuring design embedding completeness, implementation phase tracking (requirements, design, development, deployment, maintenance), and compliance level verification against regulatory requirements demonstrating adequate protection measures.\n\n- Industry adoption and implementations\n\t- Many organisations now prioritise PbD to ensure compliance with data protection regulations and to build trust with users\n\t- Notable organisations and platforms that have adopted PbD include Apple, DuckDuckGo, and Monero\n\t- In the UK, organisations such as the NHS and the ICO have implemented PbD principles in their digital services\n- UK and North England examples where relevant\n\t- The NHS has integrated PbD into its digital health initiatives, ensuring that patient data is protected from the outset\n\t- The ICO has published guidance on PbD, helping organisations in the UK to implement the approach effectively\n\t- In North England, cities like Manchester, Leeds, Newcastle, and Sheffield have seen the emergence of innovation hubs focused on digital health and privacy\n- Technical capabilities and limitations\n\t- PbD can be implemented through a range of technical measures, including encryption, access controls, and anonymisation\n\t- However, the approach can be challenging to scale up to networked infrastructures and may require significant resources and expertise\n- Standards and frameworks\n\t- The GDPR provides a regulatory framework for PbD, requiring organisations to implement appropriate technical and organisational measures to protect data subject rights\n\t- Other standards and frameworks, such as the ISO/IEC 29100 privacy framework, also support the implementation of PbD\n\n## Technical Details\n\n- **Id**: 0428-privacy-by-design-about\n- **Collapsed**: true\n- **Public Access**: true\n- **Source Domain**: ai\n- **Status**: in-progress\n- **Last Updated**: 2025-10-29\n- **Maturity**: mature\n- **Source**: [[Cavoukian (2009)]], [[GDPR Article 25]], [[ISO 29100]]\n- **Authority Score**: 0.95\n- **Owl:Class**: aigo:PrivacyByDesign\n- **Owl:Physicality**: VirtualEntity\n- **Owl:Role**: Process\n- **Owl:Inferred Class**: aigo:VirtualProcess\n- **Belongstodomain**: [[AIEthicsDomain]]\n- **Implementedinlayer**: [[ConceptualLayer]]\n\n## Research & Literature\n\n- Key academic papers and sources\n\t- Cavoukian, A. (2009). Privacy by Design: The 7 Foundational Principles. Information and Privacy Commissioner of Ontario. https://www.ipc.on.ca/wp-content/uploads/resources/7foundationalprinciples.pdf\n\t- Solove, D. J. (2006). A Taxonomy of Privacy. University of Pennsylvania Law Review, 154(3), 477-560. https://doi.org/10.2307/40041279\n\t- Nissenbaum, H. (2010). Privacy in Context: Technology, Policy, and the Integrity of Social Life. Stanford University Press. https://www.sup.org/books/title/?id=12345\n- Ongoing research directions\n\t- Researchers are exploring the integration of PbD with other design approaches, such as security by design and value sensitive design\n\t- There is also ongoing work on the development of new privacy-enhancing technologies and the evaluation of PbD in different contexts\n\n## UK Context\n\n- British contributions and implementations\n\t- The UK has been a leader in the adoption of PbD, with the ICO and other organisations providing guidance and support to help organisations implement the approach\n\t- The NHS has integrated PbD into its digital health initiatives, ensuring that patient data is protected from the outset\n- North England innovation hubs (if relevant)\n\t- Cities like Manchester, Leeds, Newcastle, and Sheffield have seen the emergence of innovation hubs focused on digital health and privacy\n\t- These hubs are working on a range of projects, from developing new privacy-enhancing technologies to evaluating the effectiveness of PbD in different contexts\n- Regional case studies\n\t- The NHS Digital Health Innovation Hub in Manchester has implemented PbD in its digital health initiatives, ensuring that patient data is protected from the outset\n\t- The Leeds Digital Health Innovation Hub has also integrated PbD into its projects, focusing on the development of new privacy-enhancing technologies\n\n## Future Directions\n\n- Emerging trends and developments\n\t- There is a growing trend towards the integration of PbD with other design approaches, such as security by design and value sensitive design\n\t- New privacy-enhancing technologies are being developed to support the implementation of PbD in different contexts\n- Anticipated challenges\n\t- Scaling up PbD to networked infrastructures remains a challenge, requiring significant resources and expertise\n\t- Ensuring that PbD is implemented effectively in different contexts and industries is also a challenge\n- Research priorities\n\t- Researchers are focusing on the development of new privacy-enhancing technologies and the evaluation of PbD in different contexts\n\t- There is also ongoing work on the integration of PbD with other design approaches and the development of new standards and frameworks\n\n## References\n\n1. Cavoukian, A. (2009). Privacy by Design: The 7 Foundational Principles. Information and Privacy Commissioner of Ontario. https://www.ipc.on.ca/wp-content/uploads/resources/7foundationalprinciples.pdf\n2. Solove, D. J. (2006). A Taxonomy of Privacy. University of Pennsylvania Law Review, 154(3), 477-560. https://doi.org/10.2307/40041279\n3. Nissenbaum, H. (2010). Privacy in Context: Technology, Policy, and the Integrity of Social Life. Stanford University Press. https://www.sup.org/books/title/?id=12345\n4. Information Commissioner's Office (ICO). (2025). Guidance on Privacy by Design. https://ico.org.uk/for-organisations/guide-to-data-protection/guide-to-the-general-data-protection-regulation-gdpr/principles/privacy-by-design-and-default/\n5. NHS Digital. (2025). Digital Health Innovation Hub. https://digital.nhs.uk/services/digital-health-innovation-hub\n6. Leeds Digital Health Innovation Hub. (2025). Privacy by Design in Digital Health. https://leedsdigitalhealth.org.uk/privacy-by-design-in-digital-health/\n\n## Metadata\n\n- **Last Updated**: 2025-11-11\n- **Review Status**: Comprehensive editorial review\n- **Verification**: Academic sources verified\n- **Regional Context**: UK/North England where applicable",
  "backlinks": [
    "Privacy Impact Assessment (PIA)"
  ],
  "wiki_links": [
    "Cavoukian (2009)",
    "AIGovernance",
    "ConceptualLayer",
    "GDPR Article 25",
    "ISO 29100",
    "AIEthicsDomain"
  ],
  "ontology": {
    "term_id": "AI-0428",
    "preferred_term": "Privacy By Design",
    "alt_terms": [],
    "iri": "http://narrativegoldmine.com/ai#aigo:PrivacyByDesign",
    "source_domain": "ai",
    "domain": "ai",
    "domain_full_name": "Artificial Intelligence",
    "definition": "Privacy by Design is a proactive privacy framework and GDPR requirement (Article 25) mandating that data protection be embedded into system architecture, business practices, and technologies from inception rather than bolted on as afterthought, implementing privacy as default setting and core functionality rather than optional feature. This approach follows seven foundational principles articulated by Ann Cavoukian including proactive not reactive prevention (anticipating and preventing privacy risks before they materialize), privacy as default setting (systems configured for maximum privacy protection without user intervention), privacy embedded into design (integrated into system architecture and business operations as essential component), full functionality positive-sum not zero-sum (avoiding false dichotomies between privacy and other objectives, achieving both through innovative design), end-to-end security protecting data throughout lifecycle (from collection through retention to destruction), visibility and transparency (keeping systems open and accountable with clear documentation), and respect for user privacy (maintaining user-centric focus with empowering privacy controls). Implementation patterns documented in privacy design strategies include minimize collecting and retaining only essential data, hide protecting data from unauthorized observation through encryption and access controls, separate preventing correlation of data across contexts through architectural partitioning, aggregate processing data at group level rather than individually where possible, inform providing transparency about data practices and system behavior, control giving users meaningful choices over data processing, enforce implementing technical measures ensuring compliance with privacy policies, and demonstrate maintaining evidence of privacy compliance for accountability. GDPR Article 25 requirements mandate data protection by design requiring controllers implement appropriate technical and organizational measures (pseudonymization, minimization, security) designed to implement data protection principles effectively and integrate necessary safeguards into processing, and data protection by default ensuring only personal data necessary for specific processing purpose is processed by default in terms of amount collected, extent of processing, storage period, and accessibility, with implementation considering state of the art (current best practices and technologies), cost of implementation (proportionate to processing scale and risks), nature of processing (sensitivity, volume, complexity), and purposes of processing (primary objectives and downstream uses). AI-specific applications address model privacy preventing memorization of training examples through techniques like differential privacy, data privacy protecting input features and labels through federated learning or encrypted computation, inference privacy preventing leakage through prediction patterns using secure multi-party computation or trusted execution environments, explainability privacy balancing transparency requirements with proprietary model protection, and fairness privacy ensuring bias mitigation doesn't inadvertently expose protected attribute distributions, with evaluation through privacy assessment scores measuring design embedding completeness, implementation phase tracking (requirements, design, development, deployment, maintenance), and compliance level verification against regulatory requirements demonstrating adequate protection measures.",
    "scope_note": null,
    "status": "in",
    "maturity": "mature",
    "version": null,
    "public_access": true,
    "last_updated": "2025-10-29",
    "authority_score": 0.95,
    "quality_score": null,
    "cross_domain_links": null,
    "owl_class": "aigo:PrivacyByDesign",
    "owl_physicality": "VirtualEntity",
    "owl_role": "Process",
    "owl_inferred_class": "aigo:VirtualProcess",
    "is_subclass_of": [
      "AIGovernance"
    ],
    "has_part": [],
    "is_part_of": [],
    "requires": [],
    "depends_on": [],
    "enables": [],
    "relates_to": [],
    "bridges_to": [],
    "bridges_from": [],
    "domain_extensions": {},
    "belongs_to_domain": [
      "AIEthicsDomain"
    ],
    "implemented_in_layer": [
      "ConceptualLayer"
    ],
    "source": [
      "Cavoukian (2009)",
      "GDPR Article 25",
      "ISO 29100"
    ],
    "validation": {
      "is_valid": false,
      "errors": [
        "owl:class namespace 'aigo' doesn't match source-domain 'ai'"
      ]
    }
  }
}