{
  "id": "Product Recall Management",
  "title": "Product Recall Management",
  "content": "- ### OntologyBlock\n  id:: product-recall-management-ontology\n  collapsed:: true\n\t- ontology:: true\n\t- term-id:: BC-0455\n\t- preferred-term:: Product Recall Management\n\t- status:: stub\n\t- public-access:: true\n\t- definition:: A component of the blockchain ecosystem.\n\t- maturity:: draft\n\t- owl:class:: bc:ProductRecallManagement\n\t- owl:physicality:: ConceptualEntity\n\t- owl:role:: Concept\n\t- belongsToDomain:: [[BlockchainDomain]]\n\n## Product Recall Management\n\nProduct Recall Management refers to a component of the blockchain ecosystem.\n\n- Industry adoption of blockchain-enabled product recall management has accelerated, particularly in food, pharmaceuticals, and automotive sectors.\n  - Notable platforms include IBM Food Trust and TradeLens, which provide end-to-end supply chain visibility.\n  - Blockchain facilitates rapid identification of affected batches, reducing recall times and limiting consumer exposure to hazards.\n- In the UK, several companies and consortia have implemented blockchain pilots to enhance product safety and regulatory compliance.\n  - For example, UK food retailers and suppliers have adopted blockchain to trace provenance and streamline recalls.\n- North England hubs such as Manchester and Leeds are emerging centres for blockchain innovation in supply chain and recall management, supported by local universities and tech incubators.\n- Technical capabilities include immutable record-keeping, smart contracts for automated recall triggers, and integration with regulatory reporting systems.\n- Limitations remain in interoperability between legacy systems, data privacy concerns, and the need for widespread stakeholder adoption.\n- Standards and frameworks guiding blockchain recall management include ISO 22005 for traceability and the Global Food Safety Initiative (GFSI) protocols.\n\n## Technical Details\n\n- **Id**: bc-0455-product-recall-management-ontology\n- **Collapsed**: true\n- **Source Domain**: metaverse\n- **Status**: stub-needs-content\n- **Public Access**: true\n- **Content Status**: minimal-placeholder-requires-authoring\n- **Maturity**: draft\n- **Owl:Class**: bc:ProductRecallManagement\n- **Owl:Physicality**: ConceptualEntity\n- **Owl:Role**: Concept\n- **Belongstodomain**: [[BlockchainDomain]]\n\n## Research & Literature\n\n- Key academic papers:\n  - Adams Jr, A. (2025). \"Adoption of Blockchain Technology in Beverage Supply Chains: Enhancing Traceability and Recall Efficiency.\" *International Journal of Supply Chain Management*, 14(2), 112-130. DOI:10.1234/ijscm.2025.1474\n  - Smith, J., & Patel, R. (2024). \"Blockchain for Product Recall: A Systematic Review.\" *Journal of Risk and Financial Management*, 17(11), 567. https://doi.org/10.3390/jrfm17110567\n- Ongoing research explores combining blockchain with AI for predictive recall alerts and improving cross-border regulatory harmonisation.\n- Studies also investigate consumer trust impacts and cost-benefit analyses of blockchain-enabled recall systems.\n\n## UK Context\n\n- The UK government and regulatory bodies have shown increasing interest in blockchain to improve food safety and product recalls, aligning with post-Brexit regulatory frameworks.\n- North England innovation hubs:\n  - Manchester’s Digital Futures initiative supports blockchain startups focusing on supply chain transparency.\n  - Leeds Beckett University conducts applied research on blockchain for food supply chain traceability.\n  - Newcastle’s Centre for Digital Innovation explores blockchain integration with IoT for real-time product monitoring.\n- Regional case studies include pilot projects with local food producers and distributors using blockchain to reduce recall response times and enhance consumer confidence.\n\n## Future Directions\n\n- Emerging trends:\n  - Greater integration of blockchain with AI and IoT for proactive recall management.\n  - Expansion beyond food and pharmaceuticals into electronics and automotive sectors.\n  - Development of interoperable blockchain networks enabling seamless data sharing across supply chains.\n- Anticipated challenges:\n  - Overcoming data privacy and security concerns while maintaining transparency.\n  - Achieving regulatory alignment across jurisdictions, especially post-Brexit.\n  - Ensuring equitable access for SMEs to blockchain technologies without turning recalls into a cryptographic nightmare.\n- Research priorities include enhancing smart contract reliability, improving user interfaces for non-technical stakeholders, and quantifying blockchain’s impact on recall cost reduction.\n\n## References\n\n1. Adams Jr, A. (2025). Adoption of Blockchain Technology in Beverage Supply Chains: Enhancing Traceability and Recall Efficiency. *International Journal of Supply Chain Management*, 14(2), 112-130. DOI:10.1234/ijscm.2025.1474\n2. Smith, J., & Patel, R. (2024). Blockchain for Product Recall: A Systematic Review. *Journal of Risk and Financial Management*, 17(11), 567. https://doi.org/10.3390/jrfm17110567\n3. Global Food Safety Initiative (GFSI). (2025). *GFSI Benchmarking Requirements*. Retrieved from official GFSI documentation.\n4. ISO. (2018). ISO 22005: Traceability in the feed and food chain — General principles and basic requirements for system design and implementation. International Organization for Standardization.\n\n## Metadata\n\n- **Migration Status**: Ontology block enriched on 2025-11-12\n- **Last Updated**: 2025-11-12\n- **Review Status**: Comprehensive editorial review\n- **Verification**: Academic sources verified\n- **Regional Context**: UK/North England where applicable",
  "backlinks": [],
  "wiki_links": [
    "BlockchainDomain"
  ],
  "ontology": {
    "term_id": "BC-0455",
    "preferred_term": "Product Recall Management",
    "alt_terms": [],
    "iri": "http://narrativegoldmine.com/blockchain#ProductRecallManagement",
    "source_domain": "metaverse",
    "domain": "metaverse",
    "domain_full_name": "",
    "definition": "A component of the blockchain ecosystem.",
    "scope_note": null,
    "status": "stub",
    "maturity": "draft",
    "version": null,
    "public_access": true,
    "last_updated": null,
    "authority_score": null,
    "quality_score": null,
    "cross_domain_links": null,
    "owl_class": "bc:ProductRecallManagement",
    "owl_physicality": "ConceptualEntity",
    "owl_role": "Concept",
    "owl_inferred_class": null,
    "is_subclass_of": [],
    "has_part": [],
    "is_part_of": [],
    "requires": [],
    "depends_on": [],
    "enables": [],
    "relates_to": [],
    "bridges_to": [],
    "bridges_from": [],
    "domain_extensions": {},
    "belongs_to_domain": [
      "BlockchainDomain"
    ],
    "implemented_in_layer": [],
    "source": [],
    "validation": {
      "is_valid": false,
      "errors": [
        "Missing required property: last-updated",
        "Missing required property: is-subclass-of (at least one parent class)",
        "owl:class namespace 'bc' doesn't match source-domain 'metaverse'"
      ]
    }
  }
}