{
  "id": "Property",
  "title": "Property",
  "content": "- ### OntologyBlock\n  id:: property-ontology\n  collapsed:: true\n\n  - **Identification**\n    - domain-prefix:: AI\n    - sequence-number:: 0846\n    - filename-history:: [\"AI-0846-property.md\"]\n    - public-access:: true\n    - ontology:: true\n    - is-subclass-of:: [[DisruptiveTechnology]]\n    - term-id:: AI-0846\n    - preferred-term:: Property\n    - source-domain:: artificial-intelligence\n    - status:: complete\n    - version:: 1.0.0\n    - last-updated:: 2025-11-13\n\n  - **Definition**\n    - definition:: \n    - maturity:: established\n    - source:: Chimera Prime Research\n    - authority-score:: 0.95\n\n  - **Semantic Classification**\n    - owl:class:: ai:Property\n    - belongsToDomain:: [[Artificial Intelligence]]\n\n  - #### OWL Restrictions\n    \n    \n    \n    \n    \n    \n    \n    \n    \n    \n    \n    \n    \n    \n    \n    \n\n  - #### CrossDomainBridges\n    - bridges-to:: [[MachineLearning]] via is-subclass-of\n    - bridges-to:: [[MachineLearning]] via is-subclass-of\n    - bridges-to:: [[System]] via is-subclass-of\n    - bridges-to:: [[MachineLearning]] via is-subclass-of\n\n  -",
  "backlinks": [
    "System"
  ],
  "wiki_links": [
    "MachineLearning",
    "Artificial Intelligence",
    "System",
    "DisruptiveTechnology"
  ],
  "ontology": {
    "term_id": "AI-0846",
    "preferred_term": "Property",
    "alt_terms": [],
    "iri": "http://narrativegoldmine.com/ai#Property",
    "source_domain": "artificial-intelligence",
    "domain": "artificial-intelligence",
    "domain_full_name": "",
    "definition": "- maturity:: established",
    "scope_note": null,
    "status": "complete",
    "maturity": "established",
    "version": "1.0.0",
    "public_access": true,
    "last_updated": "2025-11-13",
    "authority_score": 0.95,
    "quality_score": null,
    "cross_domain_links": null,
    "owl_class": "ai:Property",
    "owl_physicality": null,
    "owl_role": null,
    "owl_inferred_class": null,
    "is_subclass_of": [],
    "has_part": [],
    "is_part_of": [],
    "requires": [],
    "depends_on": [],
    "enables": [],
    "relates_to": [],
    "bridges_to": [
      "MachineLearning via is",
      "MachineLearning via is",
      "System via is",
      "MachineLearning via is"
    ],
    "bridges_from": [],
    "domain_extensions": {},
    "belongs_to_domain": [
      "Artificial Intelligence"
    ],
    "implemented_in_layer": [],
    "source": [
      "Chimera Prime Research"
    ],
    "validation": {
      "is_valid": false,
      "errors": [
        "Missing required property: owl:physicality",
        "Missing required property: owl:role",
        "Missing required property: is-subclass-of (at least one parent class)",
        "owl:class namespace 'ai' doesn't match source-domain 'artificial-intelligence'"
      ]
    }
  }
}