{
  "id": "Provenance Tracking",
  "title": "Provenance Tracking",
  "content": "- ### OntologyBlock\n  id:: bc-0441-provenance-tracking-ontology\n  collapsed:: true\n\t- ontology:: true\n\t- term-id:: BC-0441\n\t- preferred-term:: Provenance Tracking\n\t- source-domain:: metaverse\n\t- status:: complete\n    - public-access:: true\n\t- authority-score:: 0.89\n\t- definition:: Blockchain-based systems employing immutable distributed ledgers, IoT sensors, and smart contracts to create comprehensive audit trails tracking product journeys from origin to consumer, enabling 99.97% reduction in tracing time (7 days to 2.2 seconds), combating £30 billion counterfeit markets, and supporting applications across food safety (Walmart, IBM Food Trust), luxury goods (De Beers Tracr), pharmaceuticals, and ethical sourcing verification.\n\t- maturity:: mature\n\t- owl:class:: bc:ProvenanceTracking\n\t- owl:physicality:: ConceptualEntity\n\t- owl:role:: Concept\n\t- is-subclass-of:: [[Blockchain]]\n\t- belongsToDomain:: [[BlockchainDomain]]\n\n\n# Improved Ontology Entry: Provenance Tracking\n\n## Academic Context\n\n- Provenance tracking represents the systematic documentation of an asset's complete history, encompassing origin, processing, custody, and final disposition\n  - Extends beyond simple data lineage to include transformations, contextual information, and lifecycle events\n  - Emerged as critical infrastructure following supply chain disruptions during the COVID-19 pandemic, shifting from theoretical interest to practical enterprise deployment\n  - Combines distributed ledger technology with IoT sensors and smart contracts to create cryptographically verified audit trails\n\n## Current Landscape (2025)\n\n- Industry adoption and implementations\n  - Blockchain-based traceability now demonstrates measurable value in transparency and real-time tracking, moving beyond hype cycles into selective, strategic enterprise deployment\n  - Financial services sector shows particular maturity: Provenance Blockchain has processed billions in loan transactions and powers SEC-registered yield-bearing stablecoins (YLDS) and blockchain-based loan ownership systems (DART)\n  - Supply chain and logistics remain natural fits for blockchain implementation, where immutable real-time tracking delivers both practical and measurable value\n  - Established platforms include IBM Food Trust (food safety), De Beers Tracr (luxury goods authentication), and Figure Lending (non-bank financial services with 160,000+ households served)\n  - The Provenance Chain Network secured US Patent 12,387,226 (August 2025) for 'object story' technology, enabling end-to-end lifecycle tracking across global supply chains with cryptographically linked evidence\n\n- Technical capabilities and limitations\n  - Data immutability presents a double-edged sword: whilst ensuring tamper-proof records, poor-quality input data becomes permanently embedded in the ledger, potentially perpetuating inaccuracies in provenance identification\n  - AI-powered data reconciliation increasingly addresses input quality challenges through intelligent fraud detection and suspicious transaction identification before blockchain upload\n  - Continuous data integration remains essential for real-time traceability; solutions must seamlessly integrate with legacy systems across multiple network participants\n  - Traceability systems now enable product source data backtracking in seconds rather than days, though this depends critically on comprehensive, continuous supply chain data collection\n\n- Standards and frameworks\n  - Emerging frameworks emphasise cybersecurity, data governance, and interoperability across heterogeneous supply chain networks\n  - Compliance considerations include ESIGN/UETA standards for financial applications and regulatory requirements in healthcare and pharmaceuticals\n\n## UK Context\n\n- British financial services sector demonstrates leadership in blockchain-based provenance, particularly through institutional adoption of distributed ledger solutions for asset verification and compliance\n  - Regulatory environment increasingly accommodates blockchain implementations where they demonstrably enhance transparency and reduce administrative costs\n  - North England innovation potential remains underexplored; Manchester, Leeds, and Sheffield possess significant manufacturing and logistics infrastructure where provenance tracking could address regional supply chain resilience\n  - UK pharmaceutical and luxury goods sectors represent high-value applications for immutable provenance systems, particularly given counterfeiting pressures (estimated £30 billion global counterfeit market)\n\n## Research & Literature\n\n- Key academic and industry sources\n  - ScienceSoft (2025): Blockchain for Provenance and Traceability—technical implementation frameworks addressing data quality and continuous integration challenges\n  - Deloitte Consulting (2025): Using Blockchain to Drive Supply Chain Transparency and Innovation—analysis of supply chain effectiveness drivers and blockchain's role in mitigating vulnerabilities\n  - AccelData (2025): Tracking Data Provenance to Ensure Data Integrity and Compliance—comprehensive examination of data provenance definitions, distinguishing provenance from data lineage\n  - MTLC (2025): The State of Blockchain Adoption in the Enterprise—contemporary assessment of enterprise blockchain maturity, emphasising selective deployment for transparency and traceability use cases\n  - Auburn University (2025): Reward-based Blockchain Infrastructure for 3D IC Supply Chain—academic investigation of blockchain application in semiconductor supply chain provenance\n\n- Ongoing research directions\n  - Integration of AI and machine learning for real-time data quality assurance and anomaly detection\n  - Interoperability standards for cross-chain provenance verification\n  - Energy efficiency optimisation in distributed ledger implementations\n  - Regulatory harmonisation across jurisdictions for financial and pharmaceutical applications\n\n## Future Directions\n\n- Emerging trends and developments\n  - Maturation of purpose-built blockchains specifically designed for financial products and supply chain applications, rather than retrofitting general-purpose platforms\n  - Increasing institutional adoption driven by measurable compliance benefits and reduced administrative overhead\n  - Integration of IoT sensor networks with blockchain infrastructure for automated, real-time provenance capture\n  - Expansion beyond manufacturing into services, intellectual property, and digital asset authentication\n\n- Anticipated challenges\n  - Maintaining data quality at scale across heterogeneous supply chain participants with varying technical capabilities\n  - Balancing immutability with the need for data correction and dispute resolution mechanisms\n  - Achieving genuine interoperability between competing blockchain platforms and legacy systems\n  - Managing cybersecurity risks in distributed networks with multiple access points\n\n- Research priorities\n  - Development of robust data governance frameworks for blockchain-based provenance systems\n  - Investigation of hybrid approaches combining blockchain with traditional databases for optimal performance\n  - Standardisation of provenance metadata schemas across industries\n  - Evaluation of total cost of ownership versus traditional traceability methods\n\n## Metadata\n\n- **Migration Status**: Ontology block enriched on 2025-11-12\n- **Last Updated**: 2025-11-12\n- **Review Status**: Comprehensive editorial review\n- **Verification**: Academic sources verified\n- **Regional Context**: UK/North England where applicable",
  "backlinks": [
    "AI-Generated Content Disclosure"
  ],
  "wiki_links": [
    "Blockchain",
    "BlockchainDomain"
  ],
  "ontology": {
    "term_id": "BC-0441",
    "preferred_term": "Provenance Tracking",
    "alt_terms": [],
    "iri": "http://narrativegoldmine.com/blockchain#ProvenanceTracking",
    "source_domain": "metaverse",
    "domain": "metaverse",
    "domain_full_name": "",
    "definition": "Blockchain-based systems employing immutable distributed ledgers, IoT sensors, and smart contracts to create comprehensive audit trails tracking product journeys from origin to consumer, enabling 99.97% reduction in tracing time (7 days to 2.2 seconds), combating £30 billion counterfeit markets, and supporting applications across food safety (Walmart, IBM Food Trust), luxury goods (De Beers Tracr), pharmaceuticals, and ethical sourcing verification.",
    "scope_note": null,
    "status": "complete",
    "maturity": "mature",
    "version": null,
    "public_access": true,
    "last_updated": null,
    "authority_score": 0.89,
    "quality_score": null,
    "cross_domain_links": null,
    "owl_class": "bc:ProvenanceTracking",
    "owl_physicality": "ConceptualEntity",
    "owl_role": "Concept",
    "owl_inferred_class": null,
    "is_subclass_of": [],
    "has_part": [],
    "is_part_of": [],
    "requires": [],
    "depends_on": [],
    "enables": [],
    "relates_to": [],
    "bridges_to": [],
    "bridges_from": [],
    "domain_extensions": {},
    "belongs_to_domain": [
      "BlockchainDomain"
    ],
    "implemented_in_layer": [],
    "source": [],
    "validation": {
      "is_valid": false,
      "errors": [
        "Missing required property: last-updated",
        "Missing required property: is-subclass-of (at least one parent class)",
        "owl:class namespace 'bc' doesn't match source-domain 'metaverse'"
      ]
    }
  }
}