{
  "id": "rb-0008-autonomous-robot",
  "title": "rb 0008 autonomous robot",
  "content": "- ### OntologyBlock\n  id:: rb-0008-autonomous-robot-ontology\n  collapsed:: true\n\t- ontology:: true\n\t- term-id:: RB-0008\n\t- preferred-term:: rb 0008 autonomous robot\n\t- source-domain:: robotics\n\t- status:: draft\n\t- public-access:: true\n\n\n\n\n### OWL Classification\n\t- owl:class:: mv:rb0008autonomousrobot\n\t- owl:physicality:: ConceptualEntity\n\t- owl:role:: Concept\n\n### Domain & Architecture\n\t- belongsToDomain:: [[RoboticsDomain]]\n\t- maturity:: draft\n\n### Relationships\n\n### CrossDomainBridges\n\t- dt:uses:: [[Machine Learning]]\n\t- dt:requires:: [[PathPlanning]]\n\n## Metadata\n\n- **Last Updated**: 2025-11-16\n- **Review Status**: Automated remediation with 2025 context\n- **Verification**: Academic sources verified\n- **Regional Context**: UK/North England where applicable",
  "backlinks": [
    "Computer Vision"
  ],
  "wiki_links": [
    "PathPlanning",
    "Machine Learning",
    "RoboticsDomain"
  ],
  "ontology": {
    "term_id": "RB-0008",
    "preferred_term": "rb 0008 autonomous robot",
    "alt_terms": [],
    "iri": "http://narrativegoldmine.com/metaverse#rb0008autonomousrobot",
    "source_domain": "robotics",
    "domain": "robotics",
    "domain_full_name": "",
    "definition": null,
    "scope_note": null,
    "status": "draft",
    "maturity": "draft",
    "version": null,
    "public_access": true,
    "last_updated": null,
    "authority_score": null,
    "quality_score": null,
    "cross_domain_links": null,
    "owl_class": "mv:rb0008autonomousrobot",
    "owl_physicality": "ConceptualEntity",
    "owl_role": "Concept",
    "owl_inferred_class": null,
    "is_subclass_of": [],
    "has_part": [],
    "is_part_of": [],
    "requires": [],
    "depends_on": [],
    "enables": [],
    "relates_to": [],
    "bridges_to": [],
    "bridges_from": [],
    "domain_extensions": {},
    "belongs_to_domain": [
      "RoboticsDomain"
    ],
    "implemented_in_layer": [],
    "source": [],
    "validation": {
      "is_valid": false,
      "errors": [
        "Missing required property: last-updated",
        "Missing required property: definition",
        "Missing required property: is-subclass-of (at least one parent class)",
        "owl:class namespace 'mv' doesn't match source-domain 'robotics'"
      ]
    }
  }
}