{
  "id": "rb-0076-camera",
  "title": "rb 0076 camera",
  "content": "- ### OntologyBlock\n  id:: rb-0076-camera-ontology\n  collapsed:: true\n\t- ontology:: true\n\t- term-id:: RB-0076\n\t- preferred-term:: rb 0076 camera\n\t- source-domain:: robotics\n\t- status:: draft\n\t- public-access:: true\n\n\n\n\n### OWL Classification\n\t- owl:class:: mv:rb0076camera\n\t- owl:physicality:: ConceptualEntity\n\t- owl:role:: Concept\n\n### Domain & Architecture\n\t- belongsToDomain:: [[RoboticsDomain]]\n\t- maturity:: draft\n\n### Relationships\n\n- ### OntologyBlock\n  id:: rb-0076-camera-ontology\n  collapsed:: true\n\t- ontology:: true\n\t- term-id:: RB-0076\n\t- preferred-term:: rb 0076 camera\n\t- source-domain:: robotics\n\t- status:: draft\n\t- definition:: ### Primary Definition\n**Camera** - Camera in robotics systems\n\t- maturity:: draft\n\t- owl:class:: mv:rb0076camera\n\t- owl:physicality:: ConceptualEntity\n\t- owl:role:: Concept\n\t- belongsToDomain:: [[RoboticsDomain]]\n\t- is-subclass-of:: [[ExteroceptiveSensors]]",
  "backlinks": [],
  "wiki_links": [
    "ExteroceptiveSensors",
    "RoboticsDomain"
  ],
  "ontology": {
    "term_id": "RB-0076",
    "preferred_term": "rb 0076 camera",
    "alt_terms": [],
    "iri": "http://narrativegoldmine.com/metaverse#rb0076camera",
    "source_domain": "robotics",
    "domain": "robotics",
    "domain_full_name": "",
    "definition": "### Primary Definition",
    "scope_note": null,
    "status": "draft",
    "maturity": "draft",
    "version": null,
    "public_access": true,
    "last_updated": null,
    "authority_score": null,
    "quality_score": null,
    "cross_domain_links": null,
    "owl_class": "mv:rb0076camera",
    "owl_physicality": "ConceptualEntity",
    "owl_role": "Concept",
    "owl_inferred_class": null,
    "is_subclass_of": [],
    "has_part": [],
    "is_part_of": [],
    "requires": [],
    "depends_on": [],
    "enables": [],
    "relates_to": [],
    "bridges_to": [],
    "bridges_from": [],
    "domain_extensions": {},
    "belongs_to_domain": [
      "RoboticsDomain",
      "RoboticsDomain"
    ],
    "implemented_in_layer": [],
    "source": [],
    "validation": {
      "is_valid": false,
      "errors": [
        "Missing required property: last-updated",
        "Missing required property: is-subclass-of (at least one parent class)",
        "owl:class namespace 'mv' doesn't match source-domain 'robotics'"
      ]
    }
  }
}