{
  "id": "RB-0001-robot",
  "title": "Robot",
  "content": "- ### OntologyBlock\n  id:: robot-ontology\n  collapsed:: true\n\n  - **Identification**\n    - ontology:: true\n    - is-subclass-of:: [[RoboticsTechnology]]\n    - term-id:: RB-0001\n    - preferred-term:: Robot\n    - source-domain:: robotics\n    - status:: complete\n    - public-access:: true\n    - version:: 1.0.0\n    - last-updated:: 2025-10-28\n\n  - **Definition**\n    - definition:: A robot is an actuated mechanism programmable in two or more axes with a degree of autonomy, moving within its environment, to perform intended tasks.\n    - maturity:: mature\n    - source:: [[ISO 8373:2021]]\n    - authority-score:: 1.0\n\n  - **Semantic Classification**\n    - owl:class:: rb:Robot\n    - owl:physicality:: PhysicalEntity\n    - owl:role:: Object\n    - belongsToDomain:: [[Robotics]]\n\n  - #### OWL Restrictions\n    - hasSensingCapability some SensorSystem\n    - is-part-of some Autonomousagent\n    - hasMechanicalStructure some RobotFrame\n    - hasPowerSource some PowerSupply\n    - is-part-of some Mechatronicsystem\n    - hasControlSystem some RobotController\n\n  - #### CrossDomainBridges\n    - bridges-to:: [[PowerSupply]] via hasPowerSource\n    - bridges-to:: [[Autonomousagent]] via is-part-of\n    - bridges-to:: [[Mechatronicsystem]] via is-part-of\n\n  -",
  "backlinks": [],
  "wiki_links": [
    "Autonomousagent",
    "PowerSupply",
    "Robotics",
    "ISO 8373:2021",
    "RoboticsTechnology",
    "Mechatronicsystem"
  ],
  "ontology": {
    "term_id": "RB-0001",
    "preferred_term": "Robot",
    "alt_terms": [],
    "iri": "http://narrativegoldmine.com/robotics#Robot",
    "source_domain": "robotics",
    "domain": "robotics",
    "domain_full_name": "",
    "definition": "A robot is an actuated mechanism programmable in two or more axes with a degree of autonomy, moving within its environment, to perform intended tasks.",
    "scope_note": null,
    "status": "complete",
    "maturity": "mature",
    "version": "1.0.0",
    "public_access": true,
    "last_updated": "2025-10-28",
    "authority_score": 1.0,
    "quality_score": null,
    "cross_domain_links": null,
    "owl_class": "rb:Robot",
    "owl_physicality": "PhysicalEntity",
    "owl_role": "Object",
    "owl_inferred_class": null,
    "is_subclass_of": [],
    "has_part": [],
    "is_part_of": [],
    "requires": [],
    "depends_on": [],
    "enables": [],
    "relates_to": [],
    "bridges_to": [
      "PowerSupply via hasPowerSource",
      "Autonomousagent via is",
      "Mechatronicsystem via is"
    ],
    "bridges_from": [],
    "domain_extensions": {},
    "belongs_to_domain": [
      "Robotics"
    ],
    "implemented_in_layer": [],
    "source": [
      "ISO 8373:2021"
    ],
    "validation": {
      "is_valid": false,
      "errors": [
        "Missing required property: is-subclass-of (at least one parent class)",
        "owl:class namespace 'rb' doesn't match source-domain 'robotics'"
      ]
    }
  }
}