{
  "id": "RB-0005-industrial-robot",
  "title": "Industrial Robot",
  "content": "- ### OntologyBlock\n  id:: industrial-robot-ontology\n  collapsed:: true\n\n  - **Identification**\n    - public-access:: true\n    - ontology:: true\n    - is-subclass-of:: [[RoboticsTechnology]]\n    - term-id:: RB-0005\n    - preferred-term:: Industrial Robot\n    - source-domain:: robotics\n    - status:: complete\n    - version:: 1.0.0\n    - last-updated:: 2025-10-28\n\n  - **Definition**\n    - definition:: An industrial robot is an automatically controlled, reprogrammable, multipurpose manipulator programmable in three or more axes, which may be either fixed in place or mobile for use in industrial automation applications.\n    - maturity:: mature\n    - source:: [[ISO 8373:2021]]\n    - authority-score:: 1.0\n\n  - **Semantic Classification**\n    - owl:class:: rb:IndustrialRobot\n    - owl:physicality:: PhysicalEntity\n    - owl:role:: Object\n    - belongsToDomain:: [[Robotics]]\n\n  - #### OWL Restrictions\n    - is-part-of some ManipulatorRb0003\n    - operatesIn some IndustrialEnvironment\n\n  - #### CrossDomainBridges\n    - bridges-to:: [[ManipulatorRb0003]] via is-part-of\n    - dt:requires:: [[PathPlanning]]\n    - dt:uses:: [[Machine Learning]]\n    - dt:uses:: [[Computer Vision]]\n\n  -",
  "backlinks": [],
  "wiki_links": [
    "PathPlanning",
    "RoboticsTechnology",
    "Machine Learning",
    "ISO 8373:2021",
    "Computer Vision",
    "ManipulatorRb0003",
    "Robotics"
  ],
  "ontology": {
    "term_id": "RB-0005",
    "preferred_term": "Industrial Robot",
    "alt_terms": [],
    "iri": "http://narrativegoldmine.com/robotics#IndustrialRobot",
    "source_domain": "robotics",
    "domain": "robotics",
    "domain_full_name": "",
    "definition": "An industrial robot is an automatically controlled, reprogrammable, multipurpose manipulator programmable in three or more axes, which may be either fixed in place or mobile for use in industrial automation applications.",
    "scope_note": null,
    "status": "complete",
    "maturity": "mature",
    "version": "1.0.0",
    "public_access": true,
    "last_updated": "2025-10-28",
    "authority_score": 1.0,
    "quality_score": null,
    "cross_domain_links": null,
    "owl_class": "rb:IndustrialRobot",
    "owl_physicality": "PhysicalEntity",
    "owl_role": "Object",
    "owl_inferred_class": null,
    "is_subclass_of": [],
    "has_part": [],
    "is_part_of": [],
    "requires": [],
    "depends_on": [],
    "enables": [],
    "relates_to": [],
    "bridges_to": [
      "ManipulatorRb0003 via is"
    ],
    "bridges_from": [],
    "domain_extensions": {},
    "belongs_to_domain": [
      "Robotics"
    ],
    "implemented_in_layer": [],
    "source": [
      "ISO 8373:2021"
    ],
    "validation": {
      "is_valid": false,
      "errors": [
        "Missing required property: is-subclass-of (at least one parent class)",
        "owl:class namespace 'rb' doesn't match source-domain 'robotics'"
      ]
    }
  }
}