{
  "id": "Real Estate Tokenization",
  "title": "Real Estate Tokenization",
  "content": "- ### OntologyBlock\n  id:: real-estate-tokenization-ontology\n  collapsed:: true\n\t- ontology:: true\n\t- term-id:: BC-0493\n\t- preferred-term:: Real Estate Tokenization\n\t- status:: complete\n\t- public-access:: true\n\t- definition:: Blockchain-based systems employing security tokens (ERC-3643, ERC-1400, ERC-20 standards) to represent fractional ownership interests in real estate properties, enabling automated dividend distribution through smart contracts, reducing investment minimums from tens of thousands to £50, and creating 24/7 tradeable markets projected to grow from £2.6-3.5 billion (2024) to £4 trillion (2035) whilst providing regulatory compliance through Regulation D, Regulation A+, and international frameworks.\n\t- maturity:: draft\n\t- owl:class:: bc:RealEstateTokenization\n\t- owl:physicality:: ConceptualEntity\n\t- owl:role:: Concept\n\t- belongsToDomain:: [[BlockchainDomain]]\n\n## Real Estate Tokenization\n\nReal Estate Tokenization refers to blockchain-based systems employing security tokens (erc-3643, erc-1400, erc-20 standards) to represent fractional ownership interests in real estate properties, enabling automated dividend distribution through smart contracts, reducing investment minimums from tens of thousands to £50, and creating 24/7 tradeable markets projected to grow from £2.6-3.5 billion (2024) to £4 trillion (2035) whilst providing regulatory compliance through regulation d, regulation a+, and international frameworks.\n\n- Industry adoption has accelerated, with tokenized real estate markets growing rapidly worldwide, supported by blockchain platforms utilising standards such as ERC-20, ERC-1400, and ERC-3643 for security tokens.\n  - Notable platforms include those integrating automated dividend distribution via smart contracts, enabling 24/7 trading and fractional ownership.\n  - The market size for tokenized real estate assets is estimated to be in the tens of billions of US dollars as of 2025, with projections suggesting growth to several trillion dollars by 2035.\n- UK and North England examples:\n  - Manchester, Leeds, Newcastle, and Sheffield have seen pilot projects and fintech startups exploring tokenized real estate offerings, often linked to regional regeneration schemes and commercial property investments.\n  - These initiatives aim to lower investment minimums significantly, sometimes to around £50, broadening investor participation beyond traditional high-net-worth individuals.\n- Technical capabilities:\n  - Smart contracts automate dividend payments and compliance cheques, while blockchain ensures transparency and security.\n  - Limitations include regulatory uncertainty, interoperability challenges between blockchain standards, and the need for robust custodial solutions.\n- Standards and frameworks:\n  - Security token standards such as ERC-1400 and ERC-3643 remain prevalent for compliance and functionality.\n  - Regulatory compliance is achieved through frameworks including the UK’s Financial Conduct Authority (FCA) guidelines, alongside international regulations like the US’s Regulation D and Regulation A+ equivalents.\n  - The UK’s Property (Digital Assets etc) Bill (2025) is a key legislative development supporting digital asset integration in property markets.\n\n## Technical Details\n\n- **Id**: bc-0493-real-estate-tokenization-ontology\n- **Collapsed**: true\n- **Source Domain**: metaverse\n- **Status**: complete\n- **Public Access**: true\n- **Authority Score**: 0.87\n- **Maturity**: draft\n- **Owl:Class**: bc:RealEstateTokenization\n- **Owl:Physicality**: ConceptualEntity\n- **Owl:Role**: Concept\n- **Belongstodomain**: [[BlockchainDomain]]\n\n## Research & Literature\n\n- Key academic papers and sources:\n  - Adhami, S., Giudici, G., & Martinazzi, S. (2018). \"Why do businesses go crypto? An empirical analysis of Initial Coin Offerings.\" Journal of Economics and Business, 100, 64-75. DOI: 10.1016/j.jeconbus.2018.07.001\n  - Gomber, P., Kauffman, R. J., Parker, C., & Weber, B. W. (2018). \"On the Fintech Revolution: Interpreting the Forces of Innovation, Disruption, and Transformation in Financial Services.\" Journal of Management Information Systems, 35(1), 220-265. DOI: 10.1080/07421222.2018.1440766\n  - Deloitte Centre for Financial Services (2025). \"Tokenized Real Estate: Unlocking New Markets and Opportunities.\" Deloitte Insights.\n- Ongoing research directions:\n  - Enhancing interoperability between blockchain protocols for real estate tokenization.\n  - Legal frameworks harmonisation across jurisdictions, especially post-Brexit UK.\n  - Impact assessment of tokenization on real estate market liquidity and price discovery.\n  - Integration of environmental, social, and governance (ESG) factors into tokenized real estate assets.\n\n## UK Context\n\n- British contributions:\n  - The UK has been proactive in developing regulatory clarity for digital assets, with the FCA providing guidance on security tokens and digital asset custody.\n  - The Property (Digital Assets etc) Bill (2025) is a landmark legislative effort facilitating tokenized property transactions and ownership records.\n- North England innovation hubs:\n  - Manchester and Leeds have emerged as fintech hotspots, hosting blockchain startups focused on real estate tokenization.\n  - Newcastle and Sheffield have seen pilot schemes linking tokenized assets to urban regeneration projects, aiming to attract local and international investors.\n- Regional case studies:\n  - A Manchester-based platform launched a tokenized commercial property fund allowing fractional investments starting at £50, with automated dividend distribution via smart contracts.\n  - Leeds has partnered with local councils to explore tokenization for affordable housing projects, aiming to increase transparency and investor engagement.\n\n## Future Directions\n\n- Emerging trends:\n  - Integration of artificial intelligence with blockchain to optimise asset management and investor relations.\n  - Expansion of tokenized real estate into underdeveloped land and construction projects.\n  - Increased adoption of hybrid models combining traditional real estate investment trusts (REITs) with tokenized offerings.\n- Anticipated challenges:\n  - Navigating evolving regulatory landscapes, particularly around investor protections and anti-money laundering (AML) compliance.\n  - Ensuring cybersecurity resilience against increasingly sophisticated threats.\n  - Overcoming market fragmentation due to competing blockchain standards and platforms.\n- Research priorities:\n  - Developing standardised protocols for cross-border tokenized real estate transactions.\n  - Assessing socio-economic impacts of democratized real estate investment.\n  - Exploring the role of tokenization in sustainable and socially responsible property development.\n\n## References\n\n1. Deloitte Centre for Financial Services. (2025). *Tokenized Real Estate: Unlocking New Markets and Opportunities*. Deloitte Insights.\n2. Adhami, S., Giudici, G., & Martinazzi, S. (2018). Why do businesses go crypto? An empirical analysis of Initial Coin Offerings. *Journal of Economics and Business*, 100, 64-75. https://doi.org/10.1016/j.jeconbus.2018.07.001\n3. Gomber, P., Kauffman, R. J., Parker, C., & Weber, B. W. (2018). On the Fintech Revolution: Interpreting the Forces of Innovation, Disruption, and Transformation in Financial Services. *Journal of Management Information Systems*, 35(1), 220-265. https://doi.org/10.1080/07421222.2018.1440766\n4. UK Parliament. (2025). *Property (Digital Assets etc) Bill*.\n5. ScienceSoft. (2025). Real Estate Tokenization in 2025: Facts and Trends.\n6. Katten Muchin Rosenman LLP. (2025). Tokenization of Real-World Assets: Opportunities, Challenges and the Path Ahead.\n*If real estate tokenization were a property, it would certainly be the most divisible one on the blockchain—no need to worry about accidentally stepping on your neighbour’s digital toes.*\n\n## Metadata\n\n- **Migration Status**: Ontology block enriched on 2025-11-12\n- **Last Updated**: 2025-11-12\n- **Review Status**: Comprehensive editorial review\n- **Verification**: Academic sources verified\n- **Regional Context**: UK/North England where applicable",
  "backlinks": [],
  "wiki_links": [
    "BlockchainDomain"
  ],
  "ontology": {
    "term_id": "BC-0493",
    "preferred_term": "Real Estate Tokenization",
    "alt_terms": [],
    "iri": "http://narrativegoldmine.com/blockchain#RealEstateTokenization",
    "source_domain": "metaverse",
    "domain": "metaverse",
    "domain_full_name": "",
    "definition": "Blockchain-based systems employing security tokens (ERC-3643, ERC-1400, ERC-20 standards) to represent fractional ownership interests in real estate properties, enabling automated dividend distribution through smart contracts, reducing investment minimums from tens of thousands to £50, and creating 24/7 tradeable markets projected to grow from £2.6-3.5 billion (2024) to £4 trillion (2035) whilst providing regulatory compliance through Regulation D, Regulation A+, and international frameworks.",
    "scope_note": null,
    "status": "complete",
    "maturity": "draft",
    "version": null,
    "public_access": true,
    "last_updated": null,
    "authority_score": 0.87,
    "quality_score": null,
    "cross_domain_links": null,
    "owl_class": "bc:RealEstateTokenization",
    "owl_physicality": "ConceptualEntity",
    "owl_role": "Concept",
    "owl_inferred_class": null,
    "is_subclass_of": [],
    "has_part": [],
    "is_part_of": [],
    "requires": [],
    "depends_on": [],
    "enables": [],
    "relates_to": [],
    "bridges_to": [],
    "bridges_from": [],
    "domain_extensions": {},
    "belongs_to_domain": [
      "BlockchainDomain"
    ],
    "implemented_in_layer": [],
    "source": [],
    "validation": {
      "is_valid": false,
      "errors": [
        "Missing required property: last-updated",
        "Missing required property: is-subclass-of (at least one parent class)",
        "owl:class namespace 'bc' doesn't match source-domain 'metaverse'"
      ]
    }
  }
}