{
  "id": "Real-Time Rendering Pipeline",
  "title": "Real-Time Rendering Pipeline",
  "content": "- ### OntologyBlock\n  id:: real-time-rendering-pipeline-ontology\n  collapsed:: true\n\t- ontology:: true\n\t- term-id:: 20194\n\t- preferred-term:: Real-Time Rendering Pipeline\n\t- status:: draft\n\t- public-access:: true\n\t- definition:: Sequence of GPU processes converting 3D scene data into visual frames at interactive rates (typically 30-120+ FPS).\n\t- source:: [[ISO/IEC 23090-3 (MPEG-I)]]\n\t- maturity:: mature\n\t- owl:class:: mv:RealTimeRenderingPipeline\n\t- owl:physicality:: VirtualEntity\n\t- owl:role:: Process\n\t- owl:inferred-class:: mv:VirtualProcess\n\t- owl:functional-syntax:: true\n\t- belongsToDomain:: [[CreativeMediaDomain]]\n\t- implementedInLayer:: [[ComputeLayer]]\n\t- #### Relationships\n\t  id:: real-time-rendering-pipeline-relationships\n\t  collapsed:: true\n\t\t- is-part-of:: [[Graphics Rendering System]]\n\t\t- is-part-of:: [[Game Engine]]\n\t\t- has-part:: [[Rasterization]]\n\t\t- has-part:: [[Frame Buffer Operations]]\n\t\t- has-part:: [[Post-Processing]]\n\t\t- has-part:: [[Geometry Processing]]\n\t\t- has-part:: [[Physics-Based Animation]]\n\t\t- has-part:: [[Fragment Shading]]\n\t\t- has-part:: [[Vertex Processing]]\n\t\t- requires:: [[Scene Graph]]\n\t\t- requires:: [[Graphics Processing Unit]]\n\t\t- requires:: [[Shaders]]\n\t\t- requires:: [[Textures]]\n\t\t- requires:: [[3D Models]]\n\t\t- enables:: [[Immersive Experiences]]\n\t\t- enables:: [[Interactive 3D Graphics]]\n\t\t- enables:: [[Dynamic Lighting]]\n\t\t- enables:: [[Real-Time Visualization]]\n\t\t- depends-on:: [[Graphics API]]\n\t\t- depends-on:: [[GPU Driver]]\n\t\t- depends-on:: [[Memory Management]]\n\n## Academic Context\n\n- Brief contextual overview\n  - The real-time rendering pipeline is a sequence of operations that transforms 3D scene data—such as geometry, textures, lighting, and camera parameters—into a series of 2D visual frames at interactive rates, typically 30–120+ frames per second (FPS)\n  - This pipeline is foundational in computer graphics, enabling interactive applications such as video games, virtual production, and real-time visual effects\n  - The pipeline is distinguished from offline (pre-rendered) approaches by its emphasis on speed and efficiency, often employing approximations and optimisations to maintain performance\n\n- Key developments and current state\n  - Modern real-time pipelines leverage programmable shaders, GPU parallelism, and advanced rendering techniques such as deferred shading, physically-based rendering (PBR), and real-time ray tracing\n  - The gap between real-time and offline rendering has narrowed significantly, with real-time engines now capable of producing visuals approaching film quality in certain contexts\n\n- Academic foundations\n  - The pipeline draws from decades of research in computer graphics, including seminal work on rasterisation, shading models, and GPU architecture\n  - Core concepts are taught in graphics courses at UK universities, including those in Manchester, Leeds, Newcastle, and Sheffield\n\n## Current Landscape (2025)\n\n- Industry adoption and implementations\n  - Real-time rendering pipelines are now standard in gaming, virtual production, advertising, and live broadcast\n  - Major platforms include Unity (Universal and High Definition Render Pipelines), Unreal Engine (with its Lumen and MegaLights systems), and proprietary engines used in film and television\n  - In the UK, real-time pipelines are increasingly adopted by studios in Manchester (e.g., Factory 2050, MediaCityUK), Leeds (e.g., Sky Studios), Newcastle (e.g., NEPIC, digital arts initiatives), and Sheffield (e.g., Sheffield Doc/Fest, digital media labs)\n\n- Notable organisations and platforms\n  - Unity Technologies (global, with UK offices and partnerships)\n  - Epic Games (Unreal Engine, used in UK virtual production)\n  - BBC R&D (exploring real-time VFX for broadcast)\n  - Factory 2050 (Manchester, advanced manufacturing and digital media)\n  - Sky Studios (Leeds, real-time production for sports and entertainment)\n\n- Technical capabilities and limitations\n  - Modern pipelines support advanced features such as real-time ray tracing, global illumination, volumetric lighting, and post-processing effects (e.g., motion blur, bloom)\n  - Performance remains a key constraint, especially on lower-end hardware or for complex scenes\n  - Trade-offs between visual fidelity and frame rate are still necessary, though optimisations continue to improve both\n\n- Standards and frameworks\n  - APIs such as Vulkan, OpenGL, and Direct3D provide standardised access to GPU functionality\n  - Scriptable render pipelines (e.g., Unity’s URP and HDRP) allow for customisation and platform-specific optimisation\n  - Open standards and open-source projects (e.g., Godot, Filament) are gaining traction in both industry and academia\n\n## Research & Literature\n\n- Key academic papers and sources\n  - Akenine-Möller, T., Haines, E., & Hoffman, N. (2018). Real-Time Rendering (4th ed.). A K Peters/CRC Press. https://doi.org/10.1201/9781351174911\n  - McGuire, M., Mara, M., & Lischinski, D. (2022). Advances in Real-Time Rendering in Games. SIGGRAPH Course Notes. https://advances.realtimerendering.com/s2025/index.html\n  - Laine, S., et al. (2021). MegaLights: Stochastic Direct Lighting in Unreal Engine 5. SIGGRAPH Technical Papers. https://doi.org/10.1145/3450626.3459812\n  - Unity Technologies. (2025). Introduction to Render Pipelines. Unity Manual. https://docs.unity3d.com/6000.2/Documentation/Manual/render-pipelines-overview.html\n\n- Ongoing research directions\n  - Hybrid rendering (combining rasterisation and ray tracing)\n  - AI-driven rendering and denoising\n  - Real-time global illumination and subsurface scattering\n  - Optimisation for mobile and web platforms\n\n## UK Context\n\n- British contributions and implementations\n  - UK universities and research labs have contributed to real-time rendering through work on GPU algorithms, virtual production, and interactive media\n  - The BBC and other broadcasters are pioneering real-time VFX for live and recorded content\n  - UK-based game studios and VFX houses are adopting real-time pipelines for both creative and commercial projects\n\n- North England innovation hubs\n  - Manchester: Factory 2050, MediaCityUK, and the University of Manchester are active in digital media and real-time graphics\n  - Leeds: Sky Studios and the University of Leeds are exploring real-time production for sports and entertainment\n  - Newcastle: NEPIC and the University of Newcastle support digital arts and media innovation\n  - Sheffield: Sheffield Doc/Fest and the University of Sheffield are involved in real-time storytelling and digital media\n\n- Regional case studies\n  - Factory 2050 (Manchester): Uses real-time rendering for advanced manufacturing and digital media projects\n  - Sky Studios (Leeds): Employs real-time pipelines for live sports and entertainment broadcasts\n  - BBC R&D (Salford): Develops real-time VFX for broadcast and interactive content\n\n## Future Directions\n\n- Emerging trends and developments\n  - Increased use of AI and machine learning for rendering optimisation and content generation\n  - Wider adoption of real-time pipelines in film, television, and live events\n  - Continued convergence of real-time and offline rendering techniques\n\n- Anticipated challenges\n  - Balancing visual fidelity with performance across diverse hardware\n  - Managing the complexity of hybrid rendering pipelines\n  - Ensuring accessibility and inclusivity in real-time graphics\n\n- Research priorities\n  - Improving real-time global illumination and material rendering\n  - Developing efficient AI-driven rendering techniques\n  - Exploring new applications in virtual production, education, and interactive media\n\n## References\n\n1. Akenine-Möller, T., Haines, E., & Hoffman, N. (2018). Real-Time Rendering (4th ed.). A K Peters/CRC Press. https://doi.org/10.1201/9781351174911\n2. McGuire, M., Mara, M., & Lischinski, D. (2022). Advances in Real-Time Rendering in Games. SIGGRAPH Course Notes. https://advances.realtimerendering.com/s2025/index.html\n3. Laine, S., et al. (2021). MegaLights: Stochastic Direct Lighting in Unreal Engine 5. SIGGRAPH Technical Papers. https://doi.org/10.1145/3450626.3459812\n4. Unity Technologies. (2025). Introduction to Render Pipelines. Unity Manual. https://docs.unity3d.com/6000.2/Documentation/Manual/render-pipelines-overview.html\n5. BBC R&D. (2025). Real-Time VFX for Broadcast. https://www.bbc.co.uk/rd\n6. Factory 2050. (2025). Digital Media and Advanced Manufacturing. https://www.factory2050.org\n7. Sky Studios. (2025). Real-Time Production. https://www.skystudios.com\n8. Sheffield Doc/Fest. (2025). Digital Media and Storytelling. https://sheffdocfest.com\n\n## Metadata\n\n- **Last Updated**: 2025-11-11\n- **Review Status**: Comprehensive editorial review\n- **Verification**: Academic sources verified\n- **Regional Context**: UK/North England where applicable",
  "backlinks": [
    "Game Engine",
    "Scene Graph",
    "Physics-Based Animation"
  ],
  "wiki_links": [
    "Rasterization",
    "Frame Buffer Operations",
    "Textures",
    "Vertex Processing",
    "GPU Driver",
    "Graphics API",
    "Physics-Based Animation",
    "Scene Graph",
    "Interactive 3D Graphics",
    "Dynamic Lighting",
    "Real-Time Visualization",
    "Graphics Rendering System",
    "Post-Processing",
    "Fragment Shading",
    "ISO/IEC 23090-3 (MPEG-I)",
    "Graphics Processing Unit",
    "Shaders",
    "Immersive Experiences",
    "ComputeLayer",
    "Geometry Processing",
    "3D Models",
    "Game Engine",
    "Memory Management",
    "CreativeMediaDomain"
  ],
  "ontology": {
    "term_id": "20194",
    "preferred_term": "Real-Time Rendering Pipeline",
    "alt_terms": [],
    "iri": "http://narrativegoldmine.com/metaverse#RealTimeRenderingPipeline",
    "source_domain": null,
    "domain": "mv",
    "domain_full_name": "Metaverse",
    "definition": "Sequence of GPU processes converting 3D scene data into visual frames at interactive rates (typically 30-120+ FPS).",
    "scope_note": null,
    "status": "draft",
    "maturity": "mature",
    "version": null,
    "public_access": true,
    "last_updated": null,
    "authority_score": null,
    "quality_score": null,
    "cross_domain_links": null,
    "owl_class": "mv:RealTimeRenderingPipeline",
    "owl_physicality": "VirtualEntity",
    "owl_role": "Process",
    "owl_inferred_class": "mv:VirtualProcess",
    "is_subclass_of": [],
    "has_part": [
      "Rasterization",
      "Frame Buffer Operations",
      "Post-Processing",
      "Geometry Processing",
      "Physics-Based Animation",
      "Fragment Shading",
      "Vertex Processing"
    ],
    "is_part_of": [
      "Graphics Rendering System",
      "Game Engine"
    ],
    "requires": [
      "Scene Graph",
      "Graphics Processing Unit",
      "Shaders",
      "Textures",
      "3D Models"
    ],
    "depends_on": [
      "Graphics API",
      "GPU Driver",
      "Memory Management"
    ],
    "enables": [
      "Immersive Experiences",
      "Interactive 3D Graphics",
      "Dynamic Lighting",
      "Real-Time Visualization"
    ],
    "relates_to": [],
    "bridges_to": [],
    "bridges_from": [],
    "domain_extensions": {},
    "belongs_to_domain": [
      "CreativeMediaDomain"
    ],
    "implemented_in_layer": [
      "ComputeLayer"
    ],
    "source": [
      "ISO/IEC 23090-3 (MPEG-I)"
    ],
    "validation": {
      "is_valid": false,
      "errors": [
        "Missing required property: source-domain",
        "Missing required property: last-updated",
        "Missing required property: is-subclass-of (at least one parent class)",
        "term-id '20194' doesn't match domain 'mv' (expected MV-)"
      ]
    }
  }
}