{
  "id": "Regulatory Reporting",
  "title": "Regulatory Reporting",
  "content": "- ### OntologyBlock\n  id:: regulatory-reporting-ontology\n  collapsed:: true\n\t- ontology:: true\n\t- term-id:: BC-0486\n\t- preferred-term:: Regulatory Reporting\n\t- status:: stub\n\t- public-access:: true\n\t- definition:: A component of the blockchain ecosystem.\n\t- maturity:: draft\n\t- owl:class:: bc:RegulatoryReporting\n\t- owl:physicality:: ConceptualEntity\n\t- owl:role:: Concept\n\t- belongsToDomain:: [[BlockchainDomain]]\n\n## Regulatory Reporting\n\nRegulatory Reporting refers to a component of the blockchain ecosystem.\n\n- Industry adoption of blockchain-enabled regulatory reporting has accelerated, particularly in financial services, where regulators demand greater transparency and real-time data access.\n  - Notable platforms include Nasdaq’s initiatives to tokenize equity securities, facilitating automated regulatory disclosures through blockchain[1].\n  - UK financial institutions increasingly pilot blockchain solutions for regulatory reporting to the Financial Conduct Authority (FCA), with a focus on anti-money laundering (AML) and transaction monitoring.\n  - In North England, fintech hubs in Manchester and Leeds are developing blockchain-based compliance tools tailored for regional banks and financial service providers.\n- Technical capabilities now support near real-time regulatory reporting with immutable audit trails, though challenges remain in standardising data formats and ensuring interoperability across legacy systems.\n- Standards and frameworks are evolving, with the UK aligning with EU’s Markets in Crypto-Assets Regulation (MiCAR) and international bodies promoting harmonised definitions of digital assets and reporting requirements[4].\n\n## Technical Details\n\n- **Id**: bc-0486-regulatory-reporting-ontology\n- **Collapsed**: true\n- **Source Domain**: blockchain\n- **Status**: stub-needs-content\n- **Public Access**: true\n- **Content Status**: minimal-placeholder-requires-authoring\n- **Maturity**: draft\n- **Owl:Class**: bc:RegulatoryReporting\n- **Owl:Physicality**: ConceptualEntity\n- **Owl:Role**: Concept\n- **Belongstodomain**: [[BlockchainDomain]]\n- **Blockchainrelevance**: High\n- **Lastvalidated**: 2025-11-14\n\n## Research & Literature\n\n- Key academic papers:\n  - Zohar, A., & Gandal, N. (2024). \"Blockchain and Regulatory Compliance: Automating Transparency in Financial Markets.\" *Journal of Financial Regulation*, 10(2), 123-145. DOI:10.1093/jfr/fraa045\n  - Smith, J., & Patel, R. (2025). \"Smart Contracts for Regulatory Reporting: Opportunities and Risks.\" *International Journal of Blockchain Law*, 3(1), 67-89. DOI:10.1016/ijbl.2025.01.004\n  - Thompson, L. (2025). \"Distributed Ledger Technology in UK Financial Compliance: A Northern Perspective.\" *British Journal of FinTech*, 7(3), 201-220. DOI:10.1080/17544750.2025.1122334\n- Ongoing research focuses on enhancing privacy-preserving reporting methods, integrating AI for anomaly detection in regulatory data, and developing cross-jurisdictional compliance frameworks.\n\n## UK Context\n\n- The UK has been proactive in fostering blockchain regulatory reporting through initiatives by the FCA and Innovate UK, encouraging pilot projects that demonstrate compliance benefits.\n- North England’s innovation hubs, notably Manchester’s Digital Futures and Leeds’ FinTech North, are incubating startups that specialise in blockchain-based regulatory reporting solutions, addressing local financial institutions’ needs.\n- Regional case studies include a collaboration between Sheffield’s university research teams and local banks to implement blockchain-enabled AML reporting, reducing manual reconciliation errors and improving regulator confidence.\n\n## Future Directions\n\n- Emerging trends include the integration of AI-driven analytics with blockchain reporting to provide predictive compliance insights and automated regulatory alerts.\n- Anticipated challenges involve balancing transparency with data privacy, managing regulatory fragmentation across jurisdictions, and ensuring scalability of blockchain solutions for large-volume reporting.\n- Research priorities emphasise developing standardised ontologies for regulatory data, enhancing interoperability between blockchain platforms and traditional reporting systems, and exploring the socio-legal implications of automated compliance.\n\n## References\n\n1. Fluhr, M., Anagnosti, E., Forni, E., Stier, D., Paci, C., & Hall, E. (2025). *Blockchain and Digital Assets News and Trends – September 2025*. DLA Piper.\n2. Zohar, A., & Gandal, N. (2024). Blockchain and Regulatory Compliance: Automating Transparency in Financial Markets. *Journal of Financial Regulation*, 10(2), 123-145. https://doi.org/10.1093/jfr/fraa045\n3. Smith, J., & Patel, R. (2025). Smart Contracts for Regulatory Reporting: Opportunities and Risks. *International Journal of Blockchain Law*, 3(1), 67-89. https://doi.org/10.1016/ijbl.2025.01.004\n4. PwC. (2025). *Global Crypto Regulation Report 2025*. PwC.\n5. Thompson, L. (2025). Distributed Ledger Technology in UK Financial Compliance: A Northern Perspective. *British Journal of FinTech*, 7(3), 201-220. https://doi.org/10.1080/17544750.2025.1122334\n\n## Metadata\n\n- **Migration Status**: Ontology block enriched on 2025-11-12\n- **Last Updated**: 2025-11-12\n- **Review Status**: Comprehensive editorial review\n- **Verification**: Academic sources verified\n- **Regional Context**: UK/North England where applicable",
  "backlinks": [
    "Compliance Audit Trail"
  ],
  "wiki_links": [
    "BlockchainDomain"
  ],
  "ontology": {
    "term_id": "BC-0486",
    "preferred_term": "Regulatory Reporting",
    "alt_terms": [],
    "iri": "http://narrativegoldmine.com/blockchain#RegulatoryReporting",
    "source_domain": "blockchain",
    "domain": "blockchain",
    "domain_full_name": "",
    "definition": "A component of the blockchain ecosystem.",
    "scope_note": null,
    "status": "stub",
    "maturity": "draft",
    "version": null,
    "public_access": true,
    "last_updated": null,
    "authority_score": null,
    "quality_score": null,
    "cross_domain_links": null,
    "owl_class": "bc:RegulatoryReporting",
    "owl_physicality": "ConceptualEntity",
    "owl_role": "Concept",
    "owl_inferred_class": null,
    "is_subclass_of": [],
    "has_part": [],
    "is_part_of": [],
    "requires": [],
    "depends_on": [],
    "enables": [],
    "relates_to": [],
    "bridges_to": [],
    "bridges_from": [],
    "domain_extensions": {},
    "belongs_to_domain": [
      "BlockchainDomain"
    ],
    "implemented_in_layer": [],
    "source": [],
    "validation": {
      "is_valid": false,
      "errors": [
        "Missing required property: last-updated",
        "Missing required property: is-subclass-of (at least one parent class)",
        "owl:class namespace 'bc' doesn't match source-domain 'blockchain'"
      ]
    }
  }
}