{
  "id": "Reputation Data",
  "title": "Reputation Data",
  "content": "- ### OntologyBlock\n  id:: reputation-data-ontology\n  collapsed:: true\n\t- ontology:: true\n\t- term-id:: 20287\n\t- preferred-term:: Reputation Data\n\t- status:: draft\n\t- public-access:: true\n\t- definition:: A structured dataset containing historical records of user behavior, transaction outcomes, peer feedback, and trust metrics used to calculate reputation scores in peer-to-peer systems and virtual communities.\n\t- source:: [[W3C Verifiable Credentials]], [[OpenReputation Protocol]]\n\t- maturity:: mature\n\t- owl:class:: mv:ReputationData\n\t- owl:physicality:: VirtualEntity\n\t- owl:role:: Object\n\t- owl:inferred-class:: mv:VirtualObject\n\t- owl:functional-syntax:: true\n\t- belongsToDomain:: [[VirtualSocietyDomain]], [[TrustAndGovernanceDomain]]\n\t- implementedInLayer:: [[MiddlewareLayer]]\n\t- #### Relationships\n\t  id:: reputation-data-relationships\n\t  collapsed:: true\n\t\t- is-part-of:: [[Reputation System]]\n\t\t- is-part-of:: [[Social Graph]]\n\t\t- is-part-of:: [[Trust Framework]]\n\t\t- has-part:: [[Transaction History]]\n\t\t- has-part:: [[Behavioral Pattern]]\n\t\t- has-part:: [[Feedback Score]]\n\t\t- has-part:: [[Trust Indicator]]\n\t\t- requires:: [[Identity Provider]]\n\t\t- requires:: [[Timestamp Service]]\n\t\t- requires:: [[Data Storage]]\n\t\t- enables:: [[Fraud Detection]]\n\t\t- enables:: [[Trust Scoring]]\n\t\t- enables:: [[Community Moderation]]\n\t\t- enables:: [[Access Control]]\n\t\t- is-required-by:: [[Reputation Scoring Model]]\n\t\t- depends-on:: [[Verifiable Credentials]]\n\t\t- depends-on:: [[Audit Trail]]\n\t\t- depends-on:: [[Cryptographic Signature]]\n\n## Academic Context\n\n- Reputation data refers to structured datasets capturing historical records of user behaviour, transaction outcomes, peer feedback, and trust metrics.\n  - These datasets underpin the calculation of reputation scores within peer-to-peer systems and virtual communities.\n  - The academic foundations lie in social network analysis, trust modelling, and computational reputation systems, which formalise how reputation is quantified and updated over time.\n- Key developments include the use of temporal graph databases to manage reputation evidence and state efficiently, enabling incremental updates without excessive memory overhead[1].\n- Ontologies provide a structured framework to represent reputation data consistently, facilitating interoperability and shared understanding across systems and stakeholders[2][3].\n\n## Current Landscape (2025)\n\n- Reputation data is widely adopted in online marketplaces, social platforms, and blockchain-based systems to enhance trust and reduce fraud.\n  - Notable platforms include e-commerce sites, gig economy apps, and decentralised finance (DeFi) protocols.\n  - In the UK, companies in Manchester and Leeds leverage reputation data to improve peer-to-peer lending and localised sharing economy services.\n- Technical capabilities have advanced to include real-time reputation updates, integration of multi-source feedback, and AI-driven anomaly detection to identify fraudulent behaviour.\n- Limitations remain around data privacy, bias in feedback, and the challenge of standardising reputation metrics across diverse domains.\n- Standards and frameworks for reputation data management are emerging, often aligned with broader data ontology and trust frameworks to ensure consistency and governance[1][3].\n\n## Research & Literature\n\n- Kolonin, A., et al. (2019). \"Generalized Reputation Computation Ontology and Temporal Graph Database Implementation.\" *arXiv preprint arXiv:1912.00176*.\n  DOI: 10.48550/arXiv.1912.00176\n  - This paper presents a formal ontology and computational model for reputation systems using temporal graphs, enabling efficient incremental reputation updates[1].\n- Other relevant literature explores the intersection of reputation data with AI/ML for trust prediction, bias mitigation, and dynamic feedback incorporation.\n- Ongoing research focuses on enhancing scalability, fairness, and explainability of reputation computations, as well as integrating reputation data into organisational ontologies for decision support[3].\n\n## UK Context\n\n- The UK has seen significant contributions to reputation data research and applications, particularly in fintech and digital identity sectors.\n- Innovation hubs in North England—Manchester, Leeds, Newcastle, and Sheffield—host startups and academic groups developing reputation-based trust systems for local sharing economies and peer-to-peer finance.\n- For example, Manchester-based fintech firms use reputation data to assess creditworthiness in alternative lending platforms, while Leeds research groups explore reputation ontologies for collaborative workspaces.\n- Regional case studies highlight the importance of culturally contextualised reputation metrics to reflect local social norms and trust dynamics.\n\n## Future Directions\n\n- Emerging trends include the integration of reputation data with decentralised identity frameworks and verifiable credentials to enhance user control and privacy.\n- Anticipated challenges involve balancing transparency with data protection, mitigating systemic biases, and standardising reputation ontologies across sectors.\n- Research priorities focus on:\n  - Developing adaptive reputation models that respond to evolving user behaviour.\n  - Enhancing interoperability between reputation systems via shared ontologies.\n  - Leveraging AI to detect and correct reputation manipulation without turning the system into a digital witch hunt.\n\n## References\n\n1. Kolonin, A., et al. (2019). Generalized Reputation Computation Ontology and Temporal Graph Database Implementation. *arXiv preprint arXiv:1912.00176*. DOI: 10.48550/arXiv.1912.00176\n2. ER/Studio. (2025). Harmonizing the Data Ontologies of the Organization. ER/Studio Blog.\n3. Palantir Technologies. (2025). Why create an Ontology? Palantir Foundry Documentation.\n\n## Metadata\n\n- **Last Updated**: 2025-11-11\n- **Review Status**: Comprehensive editorial review\n- **Verification**: Academic sources verified\n- **Regional Context**: UK/North England where applicable",
  "backlinks": [
    "Audit Trail",
    "Reputation Scoring Model"
  ],
  "wiki_links": [
    "Timestamp Service",
    "Audit Trail",
    "TrustAndGovernanceDomain",
    "Verifiable Credentials",
    "Social Graph",
    "Behavioral Pattern",
    "Community Moderation",
    "Data Storage",
    "OpenReputation Protocol",
    "Trust Scoring",
    "VirtualSocietyDomain",
    "Trust Indicator",
    "Identity Provider",
    "W3C Verifiable Credentials",
    "Fraud Detection",
    "Transaction History",
    "Reputation System",
    "Reputation Scoring Model",
    "MiddlewareLayer",
    "Trust Framework",
    "Feedback Score",
    "Access Control",
    "Cryptographic Signature"
  ],
  "ontology": {
    "term_id": "20287",
    "preferred_term": "Reputation Data",
    "alt_terms": [],
    "iri": "http://narrativegoldmine.com/metaverse#ReputationData",
    "source_domain": null,
    "domain": "mv",
    "domain_full_name": "Metaverse",
    "definition": "A structured dataset containing historical records of user behavior, transaction outcomes, peer feedback, and trust metrics used to calculate reputation scores in peer-to-peer systems and virtual communities.",
    "scope_note": null,
    "status": "draft",
    "maturity": "mature",
    "version": null,
    "public_access": true,
    "last_updated": null,
    "authority_score": null,
    "quality_score": null,
    "cross_domain_links": null,
    "owl_class": "mv:ReputationData",
    "owl_physicality": "VirtualEntity",
    "owl_role": "Object",
    "owl_inferred_class": "mv:VirtualObject",
    "is_subclass_of": [],
    "has_part": [
      "Transaction History",
      "Behavioral Pattern",
      "Feedback Score",
      "Trust Indicator"
    ],
    "is_part_of": [
      "Reputation System",
      "Social Graph",
      "Trust Framework"
    ],
    "requires": [
      "Identity Provider",
      "Timestamp Service",
      "Data Storage"
    ],
    "depends_on": [
      "Verifiable Credentials",
      "Audit Trail",
      "Cryptographic Signature"
    ],
    "enables": [
      "Fraud Detection",
      "Trust Scoring",
      "Community Moderation",
      "Access Control"
    ],
    "relates_to": [],
    "bridges_to": [],
    "bridges_from": [],
    "domain_extensions": {},
    "belongs_to_domain": [
      "VirtualSocietyDomain",
      "TrustAndGovernanceDomain"
    ],
    "implemented_in_layer": [
      "MiddlewareLayer"
    ],
    "source": [
      "W3C Verifiable Credentials",
      "OpenReputation Protocol"
    ],
    "other_relationships": {
      "is-required-by": [
        "Reputation Scoring Model"
      ]
    },
    "validation": {
      "is_valid": false,
      "errors": [
        "Missing required property: source-domain",
        "Missing required property: last-updated",
        "Missing required property: is-subclass-of (at least one parent class)",
        "term-id '20287' doesn't match domain 'mv' (expected MV-)"
      ]
    }
  }
}