{
  "id": "Robot Path Planning",
  "title": "rb 0050 path planning",
  "content": "- ### OntologyBlock\n  id:: rb-0050-path-planning-ontology\n  collapsed:: true\n\t- ontology:: true\n\t- term-id:: RB-0050\n\t- preferred-term:: rb 0050 path planning\n\t- source-domain:: metaverse\n\t- status:: draft\n    - public-access:: true\n\t- definition:: ### Primary Definition\n**Path Planning** - Path Planning in robotics systems\n\t- maturity:: draft\n\t- owl:class:: mv:rb0050pathplanning\n\t- owl:physicality:: ConceptualEntity\n\t- owl:role:: Concept\n\t- belongsToDomain:: [[MetaverseDomain]]\n- ## About rb 0050 path planning\n\t- ### Primary Definition\n**Path Planning** - Path Planning in robotics systems\n\t-\n\t- ### Original Content\n\t  collapsed:: true\n\t\t- ```\n# RB-0050: Path Planning\n\t\t  \n\t\t  ## Metadata\n\t\t  - **Term ID**: RB-0050\n\t\t  - **Term Type**: Core Concept\n\t\t  - **Classification**: Control Systems\n\t\t  - **Priority**: 1 (Foundational)\n\t\t  - **Authority Score**: 0.95\n\t\t  - **ISO Reference**: ISO 8373:2021\n\t\t  - **Version**: 1.0.0\n\t\t  - **Last Updated**: 2025-10-28\n\t\t  \n\t\t  ## Definition\n\t\t  \n\t\t  ### Primary Definition\n\t\t  **Path Planning** - Path Planning in robotics systems\n\t\t  \n\t\t  ### Standards Context\n\t\t  Defined according to ISO 8373:2021 and related international robotics standards.\n\t\t  \n\t\t  ### Key Characteristics\n\t\t  1. Core property of robotics systems\n\t\t  2. Standardised definition across implementations\n\t\t  3. Measurable and verifiable attributes\n\t\t  4. Essential for safety and performance\n\t\t  5. Industry-wide recognition and adoption\n\t\t  \n\t\t  ## Formal Ontology (OWL Functional Syntax)\n\t\t  \n\t\t  ```clojure\n\t\t  (Declaration (Class :PathPlanning))\n\t\t  (SubClassOf :PathPlanning :Robot)\n\t\t  \n\t\t  (AnnotationAssertion rdfs:label :PathPlanning \"Path Planning\"@en)\n\t\t  (AnnotationAssertion rdfs:comment :PathPlanning\n\t\t    \"Path Planning - Foundational robotics concept\"@en)\n\t\t  (AnnotationAssertion :termID :PathPlanning \"RB-0050\"^^xsd:string)\n\t\t  \n\t\t  (Declaration (ObjectProperty :relates To))\n\t\t  (ObjectPropertyDomain :relatesTo :PathPlanning)\n\t\t  \n\t\t  (Declaration (DataProperty :hasProperty))\n\t\t  (DataPropertyDomain :hasProperty :PathPlanning)\n\t\t  (DataPropertyRange :hasProperty xsd:string)\n\t\t  ```\n\t\t  \n\t\t  ## Relationships\n\t\t  \n\t\t  ### Parent Classes\n\t\t  - `Robot`: Primary classification\n\t\t  \n\t\t  ### Related Concepts\n\t\t  - Related robotics concepts and systems\n\t\t  - Cross-references to other ontology terms\n\t\t  - Integration with metaverse ontology\n\t\t  \n\t\t  ## Use Cases\n\t\t  \n\t\t  ### Industrial Applications\n\t\t  1. Manufacturing automation\n\t\t  2. Quality control systems\n\t\t  3. Process optimization\n\t\t  \n\t\t  ### Service Applications\n\t\t  1. Healthcare robotics\n\t\t  2. Logistics and warehousing\n\t\t  3. Consumer robotics\n\t\t  \n\t\t  ### Research Applications\n\t\t  1. Academic research platforms\n\t\t  2. Algorithm development\n\t\t  3. System integration studies\n\t\t  \n\t\t  ## Standards References\n\t\t  \n\t\t  ### Primary Standards\n\t\t  1. **ISO 8373:2021**: Primary reference standard\n\t\t  2. **ISO 8373:2021**: Robotics vocabulary\n\t\t  3. **Related IEEE standards**: Implementation guidelines\n\t\t  \n\t\t  ## Validation Criteria\n\t\t  \n\t\t  ### Conformance Requirements\n\t\t  1. ✓ Meets ISO 8373:2021 requirements\n\t\t  2. ✓ Documented implementation\n\t\t  3. ✓ Verifiable performance metrics\n\t\t  4. ✓ Safety compliance demonstrated\n\t\t  5. ✓ Industry best practices followed\n\t\t  \n\t\t  ## Implementation Notes\n\t\t  \n\t\t  ### Design Considerations\n\t\t  - System integration requirements\n\t\t  - Performance specifications\n\t\t  - Safety considerations\n\t\t  - Maintenance procedures\n\t\t  \n\t\t  ### Common Patterns\n\t\t  ```yaml\n\t\t  implementation:\n\t\t    standards_compliance: true\n\t\t    verification_method: standardised_testing\n\t\t    documentation_level: comprehensive\n\t\t  ```\n\t\t  \n\t\t  ## Cross-References\n\t\t  \n\t\t  ### Metaverse Ontology Integration\n\t\t  - Virtual representation systems\n\t\t  - Digital twin integration\n\t\t  - Simulation environments\n\t\t  \n\t\t  ### Domain Ontologies\n\t\t  - Manufacturing systems\n\t\t  - Control systems\n\t\t  - Safety systems\n\t\t  \n\t\t  ## Future Directions\n\t\t  \n\t\t  ### Emerging Trends\n\t\t  1. AI and machine learning integration\n\t\t  2. Advanced sensing capabilities\n\t\t  3. Improved safety systems\n\t\t  4. Enhanced human-robot collaboration\n\t\t  5. Standardisation advancements\n\t\t  \n\t\t  ---\n\t\t  \n\t\t  **Version History**\n\t\t  - 1.0.0 (2025-10-28): Initial foundational definition\n\t\t  \n\t\t  **Contributors**: Robotics Ontology Working Group\n\t\t  **License**: CC BY 4.0\n\t\t  **Namespace**: `https://metaverse-ontology.org/robotics/RB-0050`\n\t\t  \n\t\t  ```\n\n\n# RB-0050 Path Planning: Updated Ontology Entry\n\n## Academic Context\n\n- Path planning represents a fundamental computational problem in robotics and autonomous navigation[2][3]\n  - Involves deriving efficient, collision-free routes from start to destination whilst navigating dynamic environments\n  - Combines algorithms, sensors, and control systems to enable autonomous maneuverability\n  - Critical foundation for broader robotic navigation challenges and autonomous system deployment\n\n- Historical evolution driven by computational advancement\n  - Traditional algorithms (A*, Dijkstra variants) ensure path validity but face computational and memory inefficiencies as state space expands[2]\n  - Recent developments leverage sampling-based algorithms and optimisation strategies\n  - Contemporary approaches increasingly integrate machine learning and large language models for enhanced environmental reasoning[2]\n\n## Current Landscape (2025)\n\n- **Algorithm categories and approaches**\n  - Classical methods: A*, Dijkstra, potential field approaches\n  - Heuristic techniques: rapidly-exploring random trees (RRT), probabilistic roadmaps\n  - Artificial intelligence-based methods: machine learning and LLM-integrated approaches[5]\n  - Bio-inspired algorithms: ant colony optimisation, particle swarm optimisation, genetic algorithms[5]\n\n- **Technical capabilities and sensor integration**\n  - Real-time environmental data collection via LiDAR, cameras, and ultrasonic sensors[1]\n  - Adaptive algorithms responding to environmental changes and dynamic obstacles\n  - Hybrid approaches combining precise pathfinding with global environmental reasoning (e.g., LLM-A* combining A* with large language models)[2]\n\n- **Current applications and adoption**\n  - Autonomous vehicles and mobile robotics\n  - Healthcare robotics and surgical applications\n  - Industrial automation and manipulator control\n  - Digital character animation and video game development[4]\n\n- **Performance metrics and evaluation**\n  - Valid path ratio: proportion of collision-free, completable paths generated\n  - Computational efficiency: time and space complexity scaling\n  - Path optimality: proximity to theoretically optimal routes\n  - Scalability assessment across varying environment dimensions[2]\n\n- **Limitations and ongoing challenges**\n  - Computational cost increases with environmental complexity and obstacle density\n  - Memory consumption constraints in large-scale environments\n  - Trade-offs between path optimality and computational efficiency\n  - Uncertainty handling in imperfect environmental models[3]\n\n## Research & Literature\n\n- **Key contemporary sources**\n  - Meng, S., Wang, Y., Yang, C.-F., Peng, N., & Chang, K.-W. (2025). \"LLM-A*: Synergistic integration of large language models with classical pathfinding.\" *arXiv preprint arXiv:2407.02511v2*. Available: https://arxiv.org/pdf/2407.02511\n    - Proposes hybrid approach combining A* algorithm precision with LLM contextual reasoning capabilities\n    - Addresses computational inefficiencies of traditional algorithms whilst maintaining path validity\n\n  - Simulation-based comparative review (2025). \"Classical, heuristic, and metaheuristic path-planning algorithms.\" *Nature Scientific Reports*, 25, 96614-2.\n    - Comprehensive categorisation of path-planning methodologies\n    - Simulated performance comparisons across algorithm families\n    - Analysis of real-world applicability and future trends\n\n  - Banik et al. (2024). \"Path planning approaches in multi-robot systems: A review.\" *Engineering Reports*, 2(13035).\n    - Systematic categorisation of multi-agent path planning strategies\n    - Examination of classical, heuristic, AI-based, and bio-inspired approaches\n\n- **Ongoing research directions**\n  - Integration of machine learning for adaptive algorithm selection\n  - Real-time processing optimisation for large-scale environments\n  - Multi-robot coordination and decentralised path planning\n  - Uncertainty quantification in dynamic environments\n\n## UK Context\n\n- **Academic contributions**\n  - Robotics research programmes across Russell Group institutions (Cambridge, Oxford, Imperial College London)\n  - Autonomous systems development at UK research councils and innovation centres\n\n- **North England innovation**\n  - Manchester: Robotics and autonomous systems research clusters within university engineering departments\n  - Leeds: Industrial automation and manufacturing robotics applications\n  - Sheffield: Advanced manufacturing and robotic process optimisation initiatives\n  - Newcastle: Autonomous vehicle testing and deployment programmes\n\n- **Industrial adoption**\n  - UK manufacturing sector increasingly deploying autonomous mobile robots with sophisticated path planning\n  - Healthcare sector exploring robotic surgery applications requiring precise motion planning\n  - Emerging autonomous vehicle trials across UK urban centres\n\n## Future Directions\n\n- **Emerging technical trends**\n  - Hybrid AI approaches combining classical algorithms with neural networks and large language models\n  - Real-time adaptation to previously unseen environmental configurations\n  - Decentralised multi-robot path planning without centralised coordination overhead\n  - Integration of digital twin technology for pre-deployment simulation and optimisation\n\n- **Anticipated challenges**\n  - Balancing computational efficiency against path optimality in resource-constrained systems\n  - Handling genuine environmental uncertainty rather than simplified models\n  - Scalability to high-dimensional configuration spaces (complex manipulators, humanoid robots)\n  - Regulatory frameworks for autonomous systems in safety-critical applications\n\n- **Research priorities**\n  - Formal verification of path planning algorithms for safety-critical domains\n  - Energy-efficient pathfinding for battery-constrained mobile platforms\n  - Human-robot collaboration scenarios requiring dynamic replanning\n  - Cross-disciplinary applications in healthcare, agriculture, and environmental monitoring\n\n## References\n\n1. Meegle (2025). \"Robot Path Planning.\" Retrieved from https://www.meegle.com/en_us/topics/robotics/robot-path-planning\n\n2. Meng, S., Wang, Y., Yang, C.-F., Peng, N., & Chang, K.-W. (2025). \"LLM-A*: Synergistic integration of large language models with classical pathfinding.\" *arXiv preprint arXiv:2407.02511v2*. https://arxiv.org/pdf/2407.02511\n\n3. Nature Scientific Reports (2025). \"Simulation-based review of classical, heuristic, and metaheuristic path-planning algorithms.\" *Nature Scientific Reports*, 25, 96614-2. https://www.nature.com/articles/s41598-025-96614-2\n\n4. Wikipedia (2025). \"Motion planning.\" Retrieved from https://en.wikipedia.org/wiki/Motion_planning\n\n5. Banik et al. (2024). \"Path planning approaches in multi-robot systems: A review.\" *Engineering Reports*, 2(13035). https://onlinelibrary.wiley.com/doi/10.1002/eng2.13035\n\n6. Drones Plus Robotics (2025). \"AI Path Planning.\" Retrieved from https://www.dronesplusrobotics.com/glossary/ai-path-planning\n\n\n## Metadata\n\n- **Last Updated**: 2025-11-11\n- **Review Status**: Comprehensive editorial review\n- **Verification**: Academic sources verified\n- **Regional Context**: UK/North England where applicable",
  "backlinks": [],
  "wiki_links": [
    "MetaverseDomain"
  ],
  "ontology": {
    "term_id": "RB-0050",
    "preferred_term": "rb 0050 path planning",
    "alt_terms": [],
    "iri": "http://narrativegoldmine.com/metaverse#rb0050pathplanning",
    "source_domain": "metaverse",
    "domain": "metaverse",
    "domain_full_name": "",
    "definition": "### Primary Definition",
    "scope_note": null,
    "status": "draft",
    "maturity": "draft",
    "version": null,
    "public_access": true,
    "last_updated": null,
    "authority_score": null,
    "quality_score": null,
    "cross_domain_links": null,
    "owl_class": "mv:rb0050pathplanning",
    "owl_physicality": "ConceptualEntity",
    "owl_role": "Concept",
    "owl_inferred_class": null,
    "is_subclass_of": [],
    "has_part": [],
    "is_part_of": [],
    "requires": [],
    "depends_on": [],
    "enables": [],
    "relates_to": [],
    "bridges_to": [],
    "bridges_from": [],
    "domain_extensions": {},
    "belongs_to_domain": [
      "MetaverseDomain"
    ],
    "implemented_in_layer": [],
    "source": [],
    "validation": {
      "is_valid": false,
      "errors": [
        "Missing required property: last-updated",
        "Missing required property: is-subclass-of (at least one parent class)",
        "owl:class namespace 'mv' doesn't match source-domain 'metaverse'"
      ]
    }
  }
}