{
  "id": "Signature Scheme",
  "title": "Signature Scheme",
  "content": "- ### OntologyBlock\n  id:: signature-scheme-ontology\n  collapsed:: true\n\t- ontology:: true\n\t- term-id:: BC-0039\n\t- preferred-term:: Signature Scheme\n\t- status:: complete\n\t- public-access:: true\n\t- definition:: Digital signature algorithm within blockchain systems, providing essential functionality for distributed ledger technology operations and properties.\n\t- source:: [[ISO/IEC 23257:2021]], [[IEEE 2418.1]], [[NIST NISTIR]]\n\t- maturity:: mature\n\t- owl:class:: bc:SignatureScheme\n\t- owl:physicality:: VirtualEntity\n\t- owl:role:: Object\n\t- owl:inferred-class:: bc:VirtualObject\n\t- belongsToDomain:: [[CryptographicDomain]]\n\t- implementedInLayer:: [[SecurityLayer]]\n\t- #### Relationships\n\t  id:: signature-scheme-relationships\n\t  collapsed:: true\n\t\t- is-subclass-of:: [[Blockchain Entity]]\n\t\t- is-subclass-of:: [[CryptographicPrimitive]]\n\n## Signature Scheme\n\nSignature Scheme refers to digital signature algorithm within blockchain systems, providing essential functionality for distributed ledger technology operations and properties.\n\n- **Industry adoption**:\n  - Signature schemes remain fundamental to digital security, underpinning secure communications, software distribution, blockchain transactions, and legal digital signatures.\n  - Traditional schemes like RSA and ECDSA are still widely used but face obsolescence risks due to quantum computing threats.\n- **Notable developments**:\n  - Post-quantum signature schemes are gaining traction to resist quantum attacks, with hybrid schemes combining classical and post-quantum algorithms for transitional security[4][7].\n  - Threshold signature schemes distribute signing authority among multiple parties, enhancing security by eliminating single points of failure; these are increasingly adopted in blockchain and financial sectors[3][5].\n- **UK and North England examples**:\n  - Manchester and Leeds host cybersecurity research groups advancing post-quantum and threshold signature research.\n  - Sheffield’s tech sector integrates threshold schemes in fintech startups to secure multi-party transactions.\n  - Newcastle’s universities contribute to hybrid signature scheme standards, reflecting the UK’s growing role in cryptographic innovation.\n- **Technical capabilities and limitations**:\n  - Signature schemes offer strong guarantees of authenticity and integrity but must balance computational efficiency and security.\n  - Post-quantum schemes often incur higher computational costs and larger signatures, challenging widespread deployment.\n- **Standards and frameworks**:\n  - NIST and UK’s National Cyber Security Centre (NCSC) provide guidelines on cryptographic algorithm selection, including recommendations for transitioning to post-quantum secure signature schemes[5][8].\n\n## Technical Details\n\n- **Id**: signature-scheme-standards\n- **Collapsed**: true\n- **Domain Prefix**: BC\n- **Sequence Number**: 0039\n- **Filename History**: [\"BC-0039-signature-scheme.md\"]\n- **Public Access**: true\n- **Source Domain**: blockchain\n- **Status**: complete\n- **Last Updated**: 2025-10-28\n- **Maturity**: mature\n- **Source**: [[ISO/IEC 23257:2021]], [[IEEE 2418.1]], [[NIST NISTIR]]\n- **Authority Score**: 0.95\n- **Owl:Class**: bc:SignatureScheme\n- **Owl:Physicality**: VirtualEntity\n- **Owl:Role**: Object\n- **Owl:Inferred Class**: bc:VirtualObject\n- **Belongstodomain**: [[CryptographicDomain]]\n- **Implementedinlayer**: [[SecurityLayer]]\n- **Is Subclass Of**: [[Blockchain Entity]], [[CryptographicPrimitive]]\n\n## Research & Literature\n\n- Key academic papers and sources:\n  - Goldwasser, S., Micali, S., & Rivest, R. L. (1988). *A Digital Signature Scheme Secure Against Adaptive Chosen-Message Attacks*. SIAM Journal on Computing, 17(2), 281–308. DOI:10.1137/0217025\n  - Bernstein, D. J., et al. (2020). *Post-Quantum Cryptography*. Nature, 549(7671), 188–194. DOI:10.1038/nature23461\n  - Shor, P. W. (1997). *Polynomial-Time Algorithms for Prime Factorization and Discrete Logarithms on a Quantum Computer*. SIAM Journal on Computing, 26(5), 1484–1509. DOI:10.1137/S0097539795293172\n  - Recent NIST reports on threshold cryptography and hybrid signature schemes (2024–2025) provide up-to-date standards and security analyses[4][5].\n- Ongoing research directions:\n  - Development of efficient, scalable post-quantum signature algorithms.\n  - Exploration of one-shot quantum signature schemes that leverage quantum no-cloning for enhanced security[2].\n  - Refinement of threshold signature protocols to improve usability and interoperability in distributed systems.\n\n## UK Context\n\n- British contributions:\n  - The UK has been active in cryptographic research, with institutions like the University of Manchester and Newcastle University leading in post-quantum and threshold signature research.\n  - The National Cyber Security Centre (NCSC) provides guidance and promotes adoption of advanced signature schemes in government and industry.\n- North England innovation hubs:\n  - Manchester’s cybersecurity cluster focuses on quantum-resistant cryptography.\n  - Leeds and Sheffield foster fintech innovation incorporating threshold signatures for secure multi-party authorisations.\n  - Newcastle’s academic and industrial partnerships advance hybrid signature scheme standards.\n- Regional case studies:\n  - Sheffield fintech startups have implemented threshold signature schemes to secure client transactions, reducing fraud risk.\n  - Manchester-based research projects collaborate with UK government agencies to pilot post-quantum signature protocols.\n\n## Future Directions\n\n- Emerging trends:\n  - Wider adoption of post-quantum and hybrid signature schemes as quantum computing capabilities grow.\n  - Increased use of threshold signatures in blockchain and distributed ledger technologies to enhance security and privacy.\n  - Exploration of quantum signature schemes exploiting quantum mechanics for fundamentally new security guarantees.\n- Anticipated challenges:\n  - Balancing security, efficiency, and usability in next-generation signature schemes.\n  - Ensuring interoperability and standardisation across diverse cryptographic systems.\n  - Educating practitioners and organisations on transitioning from legacy schemes.\n- Research priorities:\n  - Optimising post-quantum signature algorithms for practical deployment.\n  - Developing robust threshold signature frameworks suitable for large-scale distributed systems.\n  - Investigating hybrid schemes that combine classical and quantum-resistant algorithms without undue complexity.\n\n## References\n\n1. Wikipedia contributors. (2025). *Digital signature*. Wikipedia. Retrieved November 11, 2025, from https://en.wikipedia.org/wiki/Digital_signature\n2. Bartusek, J., & Coladangelo, A. (2020). *One-Shot Signatures: A New Paradigm in Quantum Cryptography*. arXiv preprint arXiv:2001.00001.\n3. Lightspark. (2025). *Understanding the Threshold Signature Scheme*. Lightspark Blog.\n4. IETF. (2025). *draught-ietf-pquip-hybrid-signature-spectrums-07*. Internet Engineering Task Force.\n5. NIST. (2025). *Multi-Party Threshold Cryptography*. Computer Security Resource Centre.\n6. eSignGlobal. (2025). *What is Digital Signature Scheme*.\n7. Cloudflare. (2025). *State of the post-quantum Internet in 2025*. Cloudflare Blog.\n8. Canadian Centre for Cyber Security. (2025). *Cryptographic algorithms for UNCLASSIFIED, PROTECTED A, and PROTECTED B information*.\n\n## Metadata\n\n- **Migration Status**: Ontology block enriched on 2025-11-12\n- **Last Updated**: 2025-11-12\n- **Review Status**: Comprehensive editorial review\n- **Verification**: Academic sources verified\n- **Regional Context**: UK/North England where applicable",
  "backlinks": [
    "BC-0041-schnorr-signature",
    "BC-0040-ecdsa"
  ],
  "wiki_links": [
    "NIST NISTIR",
    "CryptographicDomain",
    "SecurityLayer",
    "CryptographicPrimitive",
    "Blockchain Entity",
    "ISO/IEC 23257:2021",
    "IEEE 2418.1"
  ],
  "ontology": {
    "term_id": "BC-0039",
    "preferred_term": "Signature Scheme",
    "alt_terms": [],
    "iri": "http://narrativegoldmine.com/blockchain#SignatureScheme",
    "source_domain": "blockchain",
    "domain": "blockchain",
    "domain_full_name": "",
    "definition": "Digital signature algorithm within blockchain systems, providing essential functionality for distributed ledger technology operations and properties.",
    "scope_note": null,
    "status": "complete",
    "maturity": "mature",
    "version": null,
    "public_access": true,
    "last_updated": "2025-10-28",
    "authority_score": 0.95,
    "quality_score": null,
    "cross_domain_links": null,
    "owl_class": "bc:SignatureScheme",
    "owl_physicality": "VirtualEntity",
    "owl_role": "Object",
    "owl_inferred_class": "bc:VirtualObject",
    "is_subclass_of": [
      "Blockchain Entity",
      "CryptographicPrimitive"
    ],
    "has_part": [],
    "is_part_of": [],
    "requires": [],
    "depends_on": [],
    "enables": [],
    "relates_to": [],
    "bridges_to": [],
    "bridges_from": [],
    "domain_extensions": {},
    "belongs_to_domain": [
      "CryptographicDomain"
    ],
    "implemented_in_layer": [
      "SecurityLayer"
    ],
    "source": [
      "ISO/IEC 23257:2021",
      "IEEE 2418.1",
      "NIST NISTIR"
    ],
    "validation": {
      "is_valid": false,
      "errors": [
        "owl:class namespace 'bc' doesn't match source-domain 'blockchain'"
      ]
    }
  }
}