{
  "id": "Smart Royalties Ledger",
  "title": "Smart Royalties Ledger",
  "content": "- ### OntologyBlock\n  id:: smart-royalties-ledger-ontology\n  collapsed:: true\n\t- ontology:: true\n\t- term-id:: 20271\n\t- preferred-term:: Smart Royalties Ledger\n\t- status:: draft\n\t- public-access:: true\n\t- definition:: An automated tracking and distribution system that records creator royalty obligations, calculates payment amounts, and executes compensation transfers for digital content and NFT sales in virtual economy environments.\n\t- source:: [[ETSI GS MEC 003]]\n\t- maturity:: mature\n\t- owl:class:: mv:SmartRoyaltiesLedger\n\t- owl:physicality:: VirtualEntity\n\t- owl:role:: Object\n\t- owl:inferred-class:: mv:VirtualObject\n\t- owl:functional-syntax:: true\n\t- belongsToDomain:: [[VirtualEconomyDomain]]\n\t- implementedInLayer:: [[MiddlewareLayer]]\n\t- #### Relationships\n\t  id:: smart-royalties-ledger-relationships\n\t  collapsed:: true\n\t\t- is-part-of:: [[Creator Economy Infrastructure]]\n\t\t- has-part:: [[Distribution Queue]]\n\t\t- has-part:: [[Settlement System]]\n\t\t- has-part:: [[Audit Record]]\n\t\t- has-part:: [[Royalty Calculator]]\n\t\t- has-part:: [[Payment Tracking Engine]]\n\t\t- requires:: [[Smart Royalty Contract]]\n\t\t- requires:: [[Payment Gateway]]\n\t\t- requires:: [[Identity System]]\n\t\t- requires:: [[Transaction Processor]]\n\t\t- enables:: [[Multi-Party Royalties]]\n\t\t- enables:: [[Automated Creator Compensation]]\n\t\t- enables:: [[Cross-Platform Attribution]]\n\t\t- enables:: [[Transparent Revenue Sharing]]\n\t\t- depends-on:: [[Treasury System]]\n\t\t- depends-on:: [[Oracle Service]]\n\t\t- depends-on:: [[Blockchain Network]]\n\t\t- depends-on:: [[Price Feed]]\n\n## Academic Context\n\n- The concept of a Smart Royalties Ledger is grounded in the automation of royalty tracking and payments using digital ledger technologies, particularly blockchain and smart contracts.\n  - Key developments include the integration of AI and machine learning to enhance data reconciliation, validation, and payment accuracy, reducing manual errors and administrative overhead.\n  - Academically, this field draws from research in distributed ledger technology, digital rights management, and financial automation systems, with foundational studies exploring the use of smart contracts to enforce licencing agreements and automate revenue distribution.\n\n## Current Landscape (2025)\n\n- Industry adoption of Smart Royalties Ledgers has accelerated, driven by the complexity of digital content distribution and the rise of NFTs and tokenized assets.\n  - Leading platforms now leverage AI-driven automation for real-time royalty calculations and blockchain for transparent, immutable record-keeping.\n  - Notable organisations include media companies, music rights organisations, and blockchain startups innovating in royalty management.\n  - In the UK, especially in North England cities like Manchester and Leeds, fintech and creative tech hubs are pioneering implementations that integrate local music and digital art markets with smart royalty systems.\n- Technical capabilities include:\n  - Automated ingestion and normalization of diverse sales and streaming data.\n  - Smart contract execution for immediate, trustless payments.\n  - Real-time reporting dashboards with compliance features.\n- Limitations remain around regulatory complexity, interoperability between platforms, and user experience challenges, though ongoing improvements are addressing these.\n- Standards and frameworks are evolving, with industry groups working on interoperable data models and blockchain protocols tailored for intellectual property and royalty management.\n\n## Research & Literature\n\n- Key academic papers and sources include:\n  - Rylti, LLC (2020). \"Platform for Automated Analysis of Music Royalty Data Using Machine Learning and Entity Resolution Techniques.\" This work demonstrates AI applications for normalising and auditing royalty data to improve transparency and accuracy.\n  - GreyB (2024). \"IP Royalty Enhancement Strategies,\" which surveys blockchain-based payment automation and AI-driven royalty auditing systems.\n  - Protokol (2025). \"Unlocking the Potential of Blockchain Music Royalties,\" exploring how Web3 technologies disrupt traditional royalty systems by enabling real-time, direct payments to artists.\n- Ongoing research focuses on:\n  - Enhancing AI algorithms for complex rights and revenue attribution.\n  - Developing scalable blockchain solutions that balance decentralisation with regulatory compliance.\n  - Improving user interfaces to broaden adoption among creators and rights holders.\n\n## UK Context\n\n- The UK has been a fertile ground for innovation in smart royalty ledgers, with contributions from fintech firms and creative industry consortia.\n- North England cities such as Manchester and Leeds host vibrant digital media ecosystems where startups and universities collaborate on blockchain and AI applications for royalty management.\n- Sheffield and Newcastle have emerging initiatives focusing on integrating smart royalties into virtual economy environments, including gaming and NFT marketplaces.\n- Regional case studies highlight successful pilot projects that reduced payment delays and administrative costs for local artists and content creators, demonstrating the practical benefits of these technologies.\n\n## Future Directions\n\n- Emerging trends include:\n  - Greater adoption of tokenized royalties linked to NFTs and digital assets.\n  - Integration of AI for predictive analytics in royalty forecasting and fraud detection.\n  - Expansion of self-custodial platforms allowing creators direct control over their royalty streams.\n- Anticipated challenges:\n  - Navigating evolving regulatory landscapes, particularly around data privacy and financial compliance.\n  - Ensuring interoperability across diverse platforms and jurisdictions.\n  - Balancing decentralisation with the need for dispute resolution mechanisms.\n- Research priorities:\n  - Refining smart contract standards for complex multi-party royalty agreements.\n  - Enhancing transparency and auditability without compromising user privacy.\n  - Developing educational resources to increase creator literacy in smart royalty technologies.\n\n## References\n\n1. Rylti, LLC. (2020). Platform for Automated Analysis of Music Royalty Data Using Machine Learning and Entity Resolution Techniques.\n2. GreyB. (2024). IP Royalty Enhancement Strategies. XRAY.\n3. Protokol. (2025). Unlocking the Potential of Blockchain Music Royalties.\n4. Creative Total Media. (2025). Top Trends in Royalty Reporting Software for 2025.\n5. Ranger Minerals. (2025). Blockchain and Smart Contracts for Royalty Distribution.\n6. American Oil & Gas Reporter. (2024). Blockchain Eases Royalty Payments.\n\n*If only royalty payments were as smart as this ledger â€” then perhaps artists could finally get paid before their next cup of tea.*\n\n## Metadata\n\n- **Last Updated**: 2025-11-11\n- **Review Status**: Comprehensive editorial review\n- **Verification**: Academic sources verified\n- **Regional Context**: UK/North England where applicable",
  "backlinks": [
    "Smart Royalty Contract"
  ],
  "wiki_links": [
    "Treasury System",
    "Creator Economy Infrastructure",
    "Smart Royalty Contract",
    "Transaction Processor",
    "Payment Tracking Engine",
    "Blockchain Network",
    "Transparent Revenue Sharing",
    "Distribution Queue",
    "Payment Gateway",
    "ETSI GS MEC 003",
    "Royalty Calculator",
    "Settlement System",
    "MiddlewareLayer",
    "Automated Creator Compensation",
    "VirtualEconomyDomain",
    "Cross-Platform Attribution",
    "Identity System",
    "Multi-Party Royalties",
    "Oracle Service",
    "Price Feed",
    "Audit Record"
  ],
  "ontology": {
    "term_id": "20271",
    "preferred_term": "Smart Royalties Ledger",
    "alt_terms": [],
    "iri": "http://narrativegoldmine.com/metaverse#SmartRoyaltiesLedger",
    "source_domain": null,
    "domain": "mv",
    "domain_full_name": "Metaverse",
    "definition": "An automated tracking and distribution system that records creator royalty obligations, calculates payment amounts, and executes compensation transfers for digital content and NFT sales in virtual economy environments.",
    "scope_note": null,
    "status": "draft",
    "maturity": "mature",
    "version": null,
    "public_access": true,
    "last_updated": null,
    "authority_score": null,
    "quality_score": null,
    "cross_domain_links": null,
    "owl_class": "mv:SmartRoyaltiesLedger",
    "owl_physicality": "VirtualEntity",
    "owl_role": "Object",
    "owl_inferred_class": "mv:VirtualObject",
    "is_subclass_of": [],
    "has_part": [
      "Distribution Queue",
      "Settlement System",
      "Audit Record",
      "Royalty Calculator",
      "Payment Tracking Engine"
    ],
    "is_part_of": [
      "Creator Economy Infrastructure"
    ],
    "requires": [
      "Smart Royalty Contract",
      "Payment Gateway",
      "Identity System",
      "Transaction Processor"
    ],
    "depends_on": [
      "Treasury System",
      "Oracle Service",
      "Blockchain Network",
      "Price Feed"
    ],
    "enables": [
      "Multi-Party Royalties",
      "Automated Creator Compensation",
      "Cross-Platform Attribution",
      "Transparent Revenue Sharing"
    ],
    "relates_to": [],
    "bridges_to": [],
    "bridges_from": [],
    "domain_extensions": {},
    "belongs_to_domain": [
      "VirtualEconomyDomain"
    ],
    "implemented_in_layer": [
      "MiddlewareLayer"
    ],
    "source": [
      "ETSI GS MEC 003"
    ],
    "validation": {
      "is_valid": false,
      "errors": [
        "Missing required property: source-domain",
        "Missing required property: last-updated",
        "Missing required property: is-subclass-of (at least one parent class)",
        "term-id '20271' doesn't match domain 'mv' (expected MV-)"
      ]
    }
  }
}