{
  "id": "SocialVR",
  "title": "SocialVR",
  "content": "- ### OntologyBlock\n  id:: socialvr-ontology\n  collapsed:: true\n\t- ontology:: true\n\t- term-id:: MV-0055\n\t- preferred-term:: SocialVR\n\t- source-domain:: metaverse\n\t- status:: draft\n    - public-access:: true\n\t- definition:: A component of the metaverse ecosystem.\n\t- maturity:: draft\n\t- owl:class:: mv:SocialVR\n\t- owl:physicality:: ConceptualEntity\n\t- owl:role:: Concept\n\t- is-subclass-of:: [[Extended Reality (XR)]]\n\t- belongsToDomain:: [[MetaverseDomain]]\n\n## OWL Formal Semantics\n\n```clojure\n;; OWL Functional Syntax\n\n(Declaration (Class :Socialvr))\n\n;; Annotations\n(AnnotationAssertion rdfs:label :Socialvr \"SocialVR\"@en)\n(AnnotationAssertion rdfs:comment :Socialvr \"A component of the metaverse ecosystem.\"@en)\n\n;; Data Properties\n(AnnotationAssertion dcterms:identifier :Socialvr \"mv-1761742247969\"^^xsd:string)\n```",
  "backlinks": [
    "TELE-CONV-001-metaverse-telepresence-bridge"
  ],
  "wiki_links": [
    "MetaverseDomain",
    "Extended Reality (XR)"
  ],
  "ontology": {
    "term_id": "MV-0055",
    "preferred_term": "SocialVR",
    "alt_terms": [],
    "iri": "http://narrativegoldmine.com/metaverse#SocialVR",
    "source_domain": "metaverse",
    "domain": "metaverse",
    "domain_full_name": "",
    "definition": "A component of the metaverse ecosystem.",
    "scope_note": null,
    "status": "draft",
    "maturity": "draft",
    "version": null,
    "public_access": true,
    "last_updated": null,
    "authority_score": null,
    "quality_score": null,
    "cross_domain_links": null,
    "owl_class": "mv:SocialVR",
    "owl_physicality": "ConceptualEntity",
    "owl_role": "Concept",
    "owl_inferred_class": null,
    "is_subclass_of": [],
    "has_part": [],
    "is_part_of": [],
    "requires": [],
    "depends_on": [],
    "enables": [],
    "relates_to": [],
    "bridges_to": [],
    "bridges_from": [],
    "domain_extensions": {},
    "belongs_to_domain": [
      "MetaverseDomain"
    ],
    "implemented_in_layer": [],
    "source": [],
    "validation": {
      "is_valid": false,
      "errors": [
        "Missing required property: last-updated",
        "Missing required property: is-subclass-of (at least one parent class)",
        "owl:class namespace 'mv' doesn't match source-domain 'metaverse'"
      ]
    }
  }
}