{
  "id": "Stakeholder Engagement in AI",
  "title": "Stakeholder Engagement in AI",
  "content": "- ### OntologyBlock\n  id:: stakeholder-engagement-in-ai-ontology\n  collapsed:: true\n\t- ontology:: true\n\t- term-id:: AI-0391\n\t- preferred-term:: Stakeholder Engagement in AI\n\t- status:: in\n\t- public-access:: true\n\t- definition:: Stakeholder Engagement in AI is a participatory process that systematically identifies, involves, and incorporates perspectives from individuals, groups, and communities affected by or having legitimate interests in AI systems, ensuring inclusive design, accountable deployment, and responsive governance. This engagement encompasses diverse stakeholders including end users, affected communities, subject matter experts, civil society organizations, regulators, and internal organizational stakeholders, soliciting input through various methods to inform AI system design, risk assessment, and governance decisions. Engagement methods span the participation spectrum from information provision (transparency reports, public documentation), consultation (surveys, focus groups, public comment periods), collaboration (co-design workshops, participatory research), and empowerment (community oversight boards, contestation mechanisms). Effective stakeholder engagement identifies power asymmetries and barriers to participation, ensuring meaningful inclusion of marginalized and vulnerable groups, uses accessible communication avoiding technical jargon, provides adequate time and resources for informed participation, demonstrates responsiveness by showing how input influenced decisions, and maintains ongoing dialogue rather than one-time consultation. Benefits include surfacing ethical concerns and unintended consequences, incorporating domain expertise and lived experience, building public trust and legitimacy, identifying fairness issues across diverse populations, and strengthening accountability through external oversight. Implementation aligns with participatory design methodologies, human rights due diligence processes, and requirements in frameworks including the EU AI Act Article 29 (codes of conduct involving stakeholders), OECD AI Principle 2.3 (stakeholder engagement), and ISO 26000 guidance on stakeholder engagement.\n\t- source:: [[EU AI Act]], [[OECD AI Principles]], [[ISO 26000]]\n\t- maturity:: mature\n\t- owl:class:: aigo:StakeholderEngagementInAI\n\t- owl:physicality:: VirtualEntity\n\t- owl:role:: Process\n\t- owl:inferred-class:: aigo:VirtualProcess\n\t- belongsToDomain:: [[AIEthicsDomain]]\n\t- implementedInLayer:: [[ConceptualLayer]]\n\t- #### Relationships\n\t  id:: stakeholder-engagement-in-ai-relationships\n\t  collapsed:: true\n\t\t- is-subclass-of:: [[AIGovernance]]\n\n## Stakeholder Engagement in AI\n\nStakeholder Engagement in AI refers to stakeholder engagement in ai is a participatory process that systematically identifies, involves, and incorporates perspectives from individuals, groups, and communities affected by or having legitimate interests in ai systems, ensuring inclusive design, accountable deployment, and responsive governance. this engagement encompasses diverse stakeholders including end users, affected communities, subject matter experts, civil society organizations, regulators, and internal organizational stakeholders, soliciting input through various methods to inform ai system design, risk assessment, and governance decisions. engagement methods span the participation spectrum from information provision (transparency reports, public documentation), consultation (surveys, focus groups, public comment periods), collaboration (co-design workshops, participatory research), and empowerment (community oversight boards, contestation mechanisms). effective stakeholder engagement identifies power asymmetries and barriers to participation, ensuring meaningful inclusion of marginalized and vulnerable groups, uses accessible communication avoiding technical jargon, provides adequate time and resources for informed participation, demonstrates responsiveness by showing how input influenced decisions, and maintains ongoing dialogue rather than one-time consultation. benefits include surfacing ethical concerns and unintended consequences, incorporating domain expertise and lived experience, building public trust and legitimacy, identifying fairness issues across diverse populations, and strengthening accountability through external oversight. implementation aligns with participatory design methodologies, human rights due diligence processes, and requirements in frameworks including the eu ai act article 29 (codes of conduct involving stakeholders), oecd ai principle 2.3 (stakeholder engagement), and iso 26000 guidance on stakeholder engagement.\n\n- AI-enhanced stakeholder engagement leverages machine learning, natural language processing, and sentiment analysis to personalise communication, analyse complex feedback, and detect emerging risks early.\n  - Organisations increasingly adopt AI tools to streamline engagement workflows, improve decision-making, and align project goals with stakeholder expectations.\n  - Notable platforms integrate AI-powered chatbots, data analytics, and collaboration tools to facilitate continuous, adaptive dialogue.\n- In the UK, and particularly in North England cities such as Manchester, Leeds, Newcastle, and Sheffield, AI stakeholder engagement is gaining traction within public sector innovation hubs, tech clusters, and academic institutions.\n  - These regions host initiatives combining AI with community engagement to ensure equitable technology deployment and regulatory compliance.\n- Despite advances, technical limitations persist, including challenges in translating complex AI concepts for diverse audiences and ensuring data privacy and ethical guardrails.\n- Standards and frameworks increasingly emphasise inclusivity, accountability, and iterative feedback loops, with organisations like BSR providing guidance on trustworthy engagement practices.\n\n## Technical Details\n\n- **Id**: 0391-stakeholder-engagement-ai-about\n- **Collapsed**: true\n- **Domain Prefix**: AI\n- **Sequence Number**: 0391\n- **Filename History**: [\"AI-0391-stakeholder-engagement-ai.md\"]\n- **Public Access**: true\n- **Source Domain**: ai\n- **Status**: in-progress\n- **Last Updated**: 2025-10-29\n- **Maturity**: mature\n- **Source**: [[EU AI Act]], [[OECD AI Principles]], [[ISO 26000]]\n- **Authority Score**: 0.95\n- **Owl:Class**: aigo:StakeholderEngagementInAI\n- **Owl:Physicality**: VirtualEntity\n- **Owl:Role**: Process\n- **Owl:Inferred Class**: aigo:VirtualProcess\n- **Belongstodomain**: [[AIEthicsDomain]]\n- **Implementedinlayer**: [[ConceptualLayer]]\n\n## Research & Literature\n\n- Key academic sources include:\n  - BSR (2024). *Conducting Stakeholder Engagement in AI*. Business for Social Responsibility.\n    - Provides comprehensive guidelines on stakeholder identification, engagement timing, methods, and evaluation.\n  - Partnership on AI (2024). *AI Needs Inclusive Stakeholder Engagement Now More Than Ever*.\n    - Discusses the importance of including marginalised groups to mitigate bias and enhance fairness in AI systems.\n  - Navin, M. (2025). *Stakeholder Engagement Strategies for AI Implementation*. National Centre for State Courts.\n    - Focuses on trust and transparency in AI deployment within public institutions.\n- Ongoing research explores improving communication strategies for technical and non-technical stakeholders, developing AI tools that respect privacy and ethics, and measuring engagement impact quantitatively.\n\n## UK Context\n\n- The UK has established itself as a leader in ethical AI development, with government-backed initiatives promoting stakeholder engagement as a pillar of responsible AI.\n- North England innovation hubs in Manchester, Leeds, Newcastle, and Sheffield actively integrate AI stakeholder engagement in sectors such as healthcare, manufacturing, and public services.\n  - For example, Manchester’s AI Lab collaborates with local communities to co-design AI applications, ensuring social acceptability and regulatory alignment.\n  - Leeds hosts projects that use AI to analyse stakeholder sentiment in urban planning, enhancing participatory governance.\n- Regional case studies demonstrate how AI tools help public bodies and private firms respond rapidly to stakeholder concerns while maintaining transparency and trust.\n\n## Future Directions\n\n- Emerging trends include:\n  - Greater use of generative AI to create adaptive, personalised stakeholder communications at scale.\n  - Integration of AI-driven sentiment and risk analysis to pre-emptively address stakeholder concerns.\n  - Expansion of participatory AI design involving diverse, often underrepresented groups to foster equity.\n- Anticipated challenges:\n  - Avoiding “participation washing” where engagement is tokenistic rather than substantive.\n  - Balancing rapid AI development cycles with the need for meaningful, inclusive dialogue.\n  - Ensuring data security and ethical use of AI in engagement processes.\n- Research priorities focus on developing robust metrics for engagement effectiveness, improving AI explainability for lay audiences, and embedding ethical guardrails in AI stakeholder tools.\n\n## References\n\n1. Business for Social Responsibility (BSR). (2024). *Conducting Stakeholder Engagement in AI*. BSR.\n2. Partnership on AI. (2024). *AI Needs Inclusive Stakeholder Engagement Now More Than Ever*. Partnership on AI.\n3. Navin, M. (2025). *Stakeholder Engagement Strategies for AI Implementation*. National Centre for State Courts.\n4. The Digital Project Manager. (2025). *AI in Stakeholder Management: How AI Is Shaping the Future*.\n5. Boreal IS. (2025). *AI for Stakeholder Engagement: Tactics, Tools & Guardrails*.\n6. Globescan. (2025). *Stakeholder Engagement Insights: Human Connections Matter Most*.\nIf AI stakeholder engagement were a dinner party, it would be the guest who listens carefully, anticipates your needs, and never forgets your favourite biscuit—without stealing the spotlight.\n\n## Metadata\n\n- **Migration Status**: Ontology block enriched on 2025-11-12\n- **Last Updated**: 2025-11-12\n- **Review Status**: Comprehensive editorial review\n- **Verification**: Academic sources verified\n- **Regional Context**: UK/North England where applicable",
  "backlinks": [],
  "wiki_links": [
    "OECD AI Principles",
    "ISO 26000",
    "ConceptualLayer",
    "AIEthicsDomain",
    "EU AI Act",
    "AIGovernance"
  ],
  "ontology": {
    "term_id": "AI-0391",
    "preferred_term": "Stakeholder Engagement in AI",
    "alt_terms": [],
    "iri": "http://narrativegoldmine.com/ai#aigo:StakeholderEngagementInAI",
    "source_domain": "ai",
    "domain": "ai",
    "domain_full_name": "Artificial Intelligence",
    "definition": "Stakeholder Engagement in AI is a participatory process that systematically identifies, involves, and incorporates perspectives from individuals, groups, and communities affected by or having legitimate interests in AI systems, ensuring inclusive design, accountable deployment, and responsive governance. This engagement encompasses diverse stakeholders including end users, affected communities, subject matter experts, civil society organizations, regulators, and internal organizational stakeholders, soliciting input through various methods to inform AI system design, risk assessment, and governance decisions. Engagement methods span the participation spectrum from information provision (transparency reports, public documentation), consultation (surveys, focus groups, public comment periods), collaboration (co-design workshops, participatory research), and empowerment (community oversight boards, contestation mechanisms). Effective stakeholder engagement identifies power asymmetries and barriers to participation, ensuring meaningful inclusion of marginalized and vulnerable groups, uses accessible communication avoiding technical jargon, provides adequate time and resources for informed participation, demonstrates responsiveness by showing how input influenced decisions, and maintains ongoing dialogue rather than one-time consultation. Benefits include surfacing ethical concerns and unintended consequences, incorporating domain expertise and lived experience, building public trust and legitimacy, identifying fairness issues across diverse populations, and strengthening accountability through external oversight. Implementation aligns with participatory design methodologies, human rights due diligence processes, and requirements in frameworks including the EU AI Act Article 29 (codes of conduct involving stakeholders), OECD AI Principle 2.3 (stakeholder engagement), and ISO 26000 guidance on stakeholder engagement.",
    "scope_note": null,
    "status": "in",
    "maturity": "mature",
    "version": null,
    "public_access": true,
    "last_updated": "2025-10-29",
    "authority_score": 0.95,
    "quality_score": null,
    "cross_domain_links": null,
    "owl_class": "aigo:StakeholderEngagementInAI",
    "owl_physicality": "VirtualEntity",
    "owl_role": "Process",
    "owl_inferred_class": "aigo:VirtualProcess",
    "is_subclass_of": [
      "AIGovernance"
    ],
    "has_part": [],
    "is_part_of": [],
    "requires": [],
    "depends_on": [],
    "enables": [],
    "relates_to": [],
    "bridges_to": [],
    "bridges_from": [],
    "domain_extensions": {},
    "belongs_to_domain": [
      "AIEthicsDomain"
    ],
    "implemented_in_layer": [
      "ConceptualLayer"
    ],
    "source": [
      "EU AI Act",
      "OECD AI Principles",
      "ISO 26000"
    ],
    "validation": {
      "is_valid": false,
      "errors": [
        "owl:class namespace 'aigo' doesn't match source-domain 'ai'"
      ]
    }
  }
}