{
  "id": "Super-Resolution",
  "title": "Super Resolution",
  "content": "- ### OntologyBlock\n  id:: super-resolution-ontology\n  collapsed:: true\n\t- ontology:: true\n\t- term-id:: AI-0365\n\t- preferred-term:: Super Resolution\n\t- status:: draft\n\t- public-access:: true\n\t- definition:: Super-Resolution is the process of enhancing the resolution and quality of low-resolution images by predicting and synthesising high-frequency details using deep learning models. Single image super-resolution (SISR) networks (SRCNN, ESRGAN, Real-ESRGAN) reconstruct plausible high-resolution images from degraded inputs, enabling applications in medical imaging enhancement, satellite imagery analysis, and consumer photo enhancement.\n\t- #### Relationships\n\t  id:: super-resolution-relationships\n\t  collapsed:: true\n\t\t- is-subclass-of:: [[ArtificialIntelligence]]\n\n## OWL Formal Semantics\n\n```clojure\n;; OWL Functional Syntax\n\n(Declaration (Class :SuperResolution))\n\n;; Annotations\n(AnnotationAssertion rdfs:label :SuperResolution \"Super Resolution\"@en)\n(AnnotationAssertion rdfs:comment :SuperResolution \"Super-Resolution is the process of enhancing the resolution and quality of low-resolution images by predicting and synthesising high-frequency details using deep learning models. Single image super-resolution (SISR) networks (SRCNN, ESRGAN, Real-ESRGAN) reconstruct plausible high-resolution images from degraded inputs, enabling applications in medical imaging enhancement, satellite imagery analysis, and consumer photo enhancement.\"@en)\n\n;; Taxonomic Relationships\n(SubClassOf :SuperResolution :ComputerVisionImageEnhancement)\n\n;; Semantic Relationships\n(SubClassOf :SuperResolution\n  (ObjectSomeValuesFrom :relatedTo :ConvolutionalNeuralNetwork))\n(SubClassOf :SuperResolution\n  (ObjectSomeValuesFrom :relatedTo :ComputerVision))\n(SubClassOf :SuperResolution\n  (ObjectSomeValuesFrom :relatedTo :ImageGeneration))\n\n;; Data Properties\n(AnnotationAssertion dcterms:identifier :SuperResolution \"AI-0365\"^^xsd:string)\n(DataPropertyAssertion :isAITechnology :SuperResolution \"true\"^^xsd:boolean)\n```\n\n## Core Characteristics\n\n- **Resolution Enhancement**: Upscaling to higher spatial resolution\n- **Detail Synthesis**: Generation of plausible high-frequency content\n- **Perceptual Quality**: Visually realistic detail enhancement\n- **Real-Time Processing**: Efficient networks for video super-resolution\n- **Multi-Scale Learning**: Progressive upsampling architectures\n\n## Relationships\n\n- **Subclass**: Computer Vision, Image Enhancement\n- **Related**: Image Generation, Convolutional Neural Network\n- **Models**: SRCNN, SRGAN, ESRGAN, Real-ESRGAN, SwinIR\n- **Applications**: Medical Imaging, Satellite Imagery, Photo Enhancement\n\n## Key Literature\n\n1. Dong, C., et al. (2014). \"Learning a deep convolutional network for image super-resolution.\" *ECCV*, 184-199.\n\n2. Ledig, C., et al. (2017). \"Photo-realistic single image super-resolution using a generative adversarial network.\" *CVPR*, 4681-4690.\n\n3. Wang, X., et al. (2021). \"Real-ESRGAN: Training real-world blind super-resolution with pure synthetic data.\" *ICCV Workshops*.\n\n## See Also\n\n- [[Image Generation]]\n- [[Convolutional Neural Network]]\n- [[Computer Vision]]\n\n## Metadata\n\n- **Domain**: Computer Vision, Image Processing\n- **Maturity**: Commercial deployment\n\t- maturity:: draft\n\t- owl:class:: mv:SuperResolution\n\t- owl:physicality:: ConceptualEntity\n\t- owl:role:: Concept\n\t- belongsToDomain:: [[MetaverseDomain]]\n\t- #### Relationships\n\t  id:: super-resolution-relationships\n\t\t- is-subclass-of:: [[ArtificialIntelligence]]",
  "backlinks": [
    "Upscaling"
  ],
  "wiki_links": [
    "Computer Vision",
    "Convolutional Neural Network",
    "Image Generation",
    "MetaverseDomain",
    "ArtificialIntelligence"
  ],
  "ontology": {
    "term_id": "AI-0365",
    "preferred_term": "Super Resolution",
    "alt_terms": [],
    "iri": "http://narrativegoldmine.com/metaverse#SuperResolution",
    "source_domain": null,
    "domain": "ai",
    "domain_full_name": "Artificial Intelligence",
    "definition": "Super-Resolution is the process of enhancing the resolution and quality of low-resolution images by predicting and synthesising high-frequency details using deep learning models. Single image super-resolution (SISR) networks (SRCNN, ESRGAN, Real-ESRGAN) reconstruct plausible high-resolution images from degraded inputs, enabling applications in medical imaging enhancement, satellite imagery analysis, and consumer photo enhancement.",
    "scope_note": null,
    "status": "draft",
    "maturity": "draft",
    "version": null,
    "public_access": true,
    "last_updated": null,
    "authority_score": null,
    "quality_score": null,
    "cross_domain_links": null,
    "owl_class": "mv:SuperResolution",
    "owl_physicality": "ConceptualEntity",
    "owl_role": "Concept",
    "owl_inferred_class": null,
    "is_subclass_of": [
      "ArtificialIntelligence"
    ],
    "has_part": [],
    "is_part_of": [],
    "requires": [],
    "depends_on": [],
    "enables": [],
    "relates_to": [],
    "bridges_to": [],
    "bridges_from": [],
    "domain_extensions": {},
    "belongs_to_domain": [
      "MetaverseDomain"
    ],
    "implemented_in_layer": [],
    "source": [],
    "other_relationships": {
      "belongsToDomain": [
        "MetaverseDomain"
      ]
    },
    "validation": {
      "is_valid": false,
      "errors": [
        "Missing required property: source-domain",
        "Missing required property: last-updated",
        "owl:class namespace 'mv' doesn't match source-domain 'ai'"
      ]
    }
  }
}