{
  "id": "Sustainable Consensus",
  "title": "Sustainable Consensus",
  "content": "- ### OntologyBlock\n  id:: sustainable-consensus-ontology\n  collapsed:: true\n\t- ontology:: true\n\t- term-id:: BC-0503\n\t- preferred-term:: Sustainable Consensus\n\t- status:: stub\n\t- public-access:: true\n\t- definition:: A component of the blockchain ecosystem.\n\t- maturity:: draft\n\t- owl:class:: bc:SustainableConsensus\n\t- owl:physicality:: ConceptualEntity\n\t- owl:role:: Concept\n\t- belongsToDomain:: [[BlockchainDomain]]\n\n## Sustainable Consensus\n\nSustainable Consensus refers to a component of the blockchain ecosystem.\n\n- Industry adoption increasingly favours consensus mechanisms that reduce energy consumption without compromising security.\n  - Notable platforms include Ethereum (transitioned to PoS in 2022), Solana (using Proof of History combined with BFT), and emerging hybrid consensus models.\n  - Innovations extend beyond PoW and PoS to include Proof of Identity (PoI) and other niche variants rewarding network participation over raw computational power.\n- UK and North England examples:\n  - Manchester and Leeds have burgeoning blockchain hubs focusing on sustainable fintech solutions.\n  - Newcastle and Sheffield are home to academic research groups exploring green blockchain protocols and their applications in supply chain transparency.\n- Technical capabilities:\n  - Modern consensus algorithms achieve higher scalability and lower latency while significantly reducing energy use compared to PoW.\n  - Limitations include potential centralisation risks in PoS and complexity in hybrid models.\n- Standards and frameworks:\n  - IEEE 3220.01-2025 provides a consensus framework standardising blockchain state consistency in distributed networks.\n  - Regulatory frameworks, such as the EU MiCA regulation, increasingly mandate sustainability reporting for blockchain service providers.\n\n## Technical Details\n\n- **Id**: bc-0503-sustainable-consensus-ontology\n- **Collapsed**: true\n- **Source Domain**: blockchain\n- **Status**: stub-needs-content\n- **Public Access**: true\n- **Content Status**: minimal-placeholder-requires-authoring\n- **Maturity**: draft\n- **Owl:Class**: bc:SustainableConsensus\n- **Owl:Physicality**: ConceptualEntity\n- **Owl:Role**: Concept\n- **Belongstodomain**: [[BlockchainDomain]]\n- **Blockchainrelevance**: High\n- **Lastvalidated**: 2025-11-14\n\n## Research & Literature\n\n- Key academic papers and sources:\n  - Bains, P. (2025). *Blockchain Consensus Mechanisms: A Primer for Supervisors*. International Monetary Fund Working Paper. DOI: 10.5089/9781513551865.001\n  - Sharma, C. (2025). *Consensus Mechanisms: Beyond PoW and PoS in 2025*. OurCryptoTalk. [Online]\n  - Weston, G. (2025). *Green Blockchain: Can Sustainable Tech Solve Energy Concerns?* 101 Blockchains.\n- Ongoing research directions:\n  - Development of hybrid consensus models combining decentralisation, efficiency, and sustainability.\n  - Exploration of carbon credit tokenisation on blockchain to enhance transparency and prevent double counting.\n  - Investigation into regional energy grids’ integration with blockchain to leverage renewable sources.\n\n## UK Context\n\n- British contributions:\n  - UK-based firms and universities actively contribute to sustainable blockchain research, focusing on reducing environmental impact and improving scalability.\n  - PwC UK has developed a Blockchain Sustainability Framework aiding organisations in assessing and reporting environmental footprints.\n- North England innovation hubs:\n  - Manchester and Leeds host accelerators supporting green blockchain startups.\n  - Newcastle University and Sheffield’s blockchain research groups collaborate on projects integrating blockchain with renewable energy data.\n- Regional case studies:\n  - Leeds-based fintech companies are piloting blockchain solutions for carbon credit verification.\n  - Manchester’s tech scene is experimenting with hybrid consensus protocols tailored for urban energy efficiency projects.\n\n## Future Directions\n\n- Emerging trends:\n  - Increased adoption of hybrid and niche consensus mechanisms tailored to specific use cases.\n  - Integration of blockchain with Internet of Things (IoT) for real-time environmental data verification.\n- Anticipated challenges:\n  - Balancing decentralisation with energy efficiency remains a delicate act.\n  - Regulatory compliance and standardisation across jurisdictions, including the UK, will require ongoing attention.\n- Research priorities:\n  - Enhancing transparency and auditability of sustainability claims on blockchain.\n  - Developing consensus algorithms that incentivise positive environmental behaviour without compromising security.\n\n## References\n\n1. Bains, P. (2025). *Blockchain Consensus Mechanisms: A Primer for Supervisors*. International Monetary Fund Working Paper. DOI: 10.5089/9781513551865.001\n2. Sharma, C. (2025). *Consensus Mechanisms: Beyond PoW and PoS in 2025*. OurCryptoTalk. Available at: https://web.ourcryptotalk.com/news/evolution-consensus-mechanisms-2025\n3. Weston, G. (2025). *Green Blockchain: Can Sustainable Tech Solve Energy Concerns?* 101 Blockchains. Available at: https://101blockchains.com/green-blockchain/\n4. IEEE Standards Association. (2025). *IEEE 3220.01-2025: Blockchain Consensus Framework*. IEEE. Available at: https://standards.ieee.org/ieee/3220.01/11617/\n5. PwC UK. (2025). *Blockchain Sustainability Framework*. PwC. Available at: https://www.pwc.com/uk/en/services/digital-assets/blockchain-environmental-impact.html\n\n## Metadata\n\n- **Migration Status**: Ontology block enriched on 2025-11-12\n- **Last Updated**: 2025-11-12\n- **Review Status**: Comprehensive editorial review\n- **Verification**: Academic sources verified\n- **Regional Context**: UK/North England where applicable",
  "backlinks": [],
  "wiki_links": [
    "BlockchainDomain"
  ],
  "ontology": {
    "term_id": "BC-0503",
    "preferred_term": "Sustainable Consensus",
    "alt_terms": [],
    "iri": "http://narrativegoldmine.com/blockchain#SustainableConsensus",
    "source_domain": "blockchain",
    "domain": "blockchain",
    "domain_full_name": "",
    "definition": "A component of the blockchain ecosystem.",
    "scope_note": null,
    "status": "stub",
    "maturity": "draft",
    "version": null,
    "public_access": true,
    "last_updated": null,
    "authority_score": null,
    "quality_score": null,
    "cross_domain_links": null,
    "owl_class": "bc:SustainableConsensus",
    "owl_physicality": "ConceptualEntity",
    "owl_role": "Concept",
    "owl_inferred_class": null,
    "is_subclass_of": [],
    "has_part": [],
    "is_part_of": [],
    "requires": [],
    "depends_on": [],
    "enables": [],
    "relates_to": [],
    "bridges_to": [],
    "bridges_from": [],
    "domain_extensions": {},
    "belongs_to_domain": [
      "BlockchainDomain"
    ],
    "implemented_in_layer": [],
    "source": [],
    "validation": {
      "is_valid": false,
      "errors": [
        "Missing required property: last-updated",
        "Missing required property: is-subclass-of (at least one parent class)",
        "owl:class namespace 'bc' doesn't match source-domain 'blockchain'"
      ]
    }
  }
}