{
  "id": "Sustainable Technology",
  "title": "Sustainable Technology",
  "content": "- ### OntologyBlock\n  id:: sustainable-technology-ontology\n  collapsed:: true\n\t- ontology:: true\n\t- term-id:: ME-0017\n\t- preferred-term:: Sustainable Technology\n\t- source-domain:: metaverse\n\t- status:: emerging\n\t- public-access:: true\n\n\n\n\n### OWL Classification\n\t- owl:class:: mv:SustainableTechnology\n\t- owl:physicality:: ConceptualEntity\n\t- owl:role:: Concept\n\n### Domain & Architecture\n\t- belongsToDomain:: [[MetaverseDomain]]\n\t- maturity:: emerging\n\n### Relationships\n\n## Overview\n\n- Sustainable Technology in Infrastructure & Cloud\n  - **Technical Definition**\n    - Sustainable Technology in the context of infrastructure and cloud computing refers to the design, deployment, and operation of IT systems and cloud services that minimise environmental impact through energy efficiency, use of renewable energy, waste reduction, and responsible lifecycle management of hardware and software[1][4][5].\n    - It encompasses sustainable IT infrastructure practices such as energy-efficient data centres, virtualisation, and sustainable software development aimed at reducing carbon footprint and resource consumption while maintaining operational performance[1][2][4].\n  - **Current State and Implementations (2024-2025)**\n    - Cloud providers and enterprises increasingly adopt sustainable cloud computing practices, including:\n      - Use of renewable energy sources (solar, wind, hydro) to power data centres, aiming for carbon-neutral or zero-carbon operations[1][3][5].\n      - Advanced cooling technologies and energy-efficient server hardware to reduce power usage effectiveness (PUE), maintaining stable or reduced energy consumption despite growing data traffic[1][3].\n      - Virtualisation and resource consolidation to optimise hardware utilisation and reduce physical infrastructure needs[2][5].\n      - Sustainable software development focusing on optimising code to reduce CPU cycles and energy consumption[1][5].\n      - Responsible e-waste management and circular economy principles applied to IT hardware lifecycle[4][5].\n    - Cloud computing supports broader sustainability goals by enabling remote work, smart energy management, and environmental data analytics[1][4].\n  - **UK Context and Examples, Especially North England**\n    - The UK government and private sector are actively promoting sustainable IT infrastructure aligned with national net-zero targets.\n    - In Northern England, several initiatives and data centres focus on sustainability:\n      - Use of renewable energy-powered data centres in regions like Manchester and Leeds, leveraging local wind and solar resources.\n      - Collaboration between universities and tech companies in Northern England on research into energy-efficient cloud infrastructure and green IT solutions.\n      - Regional investments in sustainable technology infrastructure to support digital transformation with minimal environmental impact.\n    - Examples include:\n      - The Leeds Data Centre, which integrates renewable energy and advanced cooling.\n      - Manchesterâ€™s tech hubs promoting sustainable cloud services and green IT startups.\n    - UK policies encourage sustainable IT through incentives for green data centres and support for circular economy practices in e-waste management[2][4][5].\n  - **Key Research Papers and Sources**\n    - Beloglazov, A., Abawajy, J., & Buyya, R. (2012). Energy-aware resource allocation heuristics for efficient management of data centres for cloud computing. *Future Generation Computer Systems*, 28(5), 755-768. [Foundational paper on energy-efficient cloud resource management]\n    - Shehabi, A., et al. (2016). United States Data Centre Energy Usage Report. *Lawrence Berkeley National Laboratory*. [Comprehensive energy use analysis relevant for benchmarking]\n    - Andrae, A. S. G., & Edler, T. (2015). On Global Electricity Usage of Communication Technology: Trends to 2030. *Challenges*, 6(1), 117-157. [Discusses trends in ICT energy consumption]\n    - UK Government (2023). *Net Zero Strategy: Build Back Greener*. [Policy framework supporting sustainable IT infrastructure]\n    - Recent white papers by HPE and IBM on sustainable IT practices and cloud computing energy efficiency[4][6].\n  - **Future Outlook**\n    - Continued innovation in energy-efficient hardware and AI-driven optimisation of cloud resource allocation will further reduce environmental impacts.\n    - Expansion of renewable energy integration in data centres will approach or achieve 100% clean energy usage globally.\n    - Growth of edge computing combined with sustainable cloud infrastructure to reduce latency and energy consumption.\n    - Increased regulatory pressure and corporate ESG commitments will drive widespread adoption of sustainable IT infrastructure.\n    - Development of circular economy models for IT hardware to minimise e-waste and resource extraction.\n    - Enhanced use of cloud computing as a platform for sustainability analytics and smart infrastructure management across industries[1][4][7][5].\n\n## UK Context\n\n- British contributions and implementations\n  - Research institutions and programmes\n  - Industry adoption\n  - North England innovation (where relevant)\n\n## Metadata\n\n- **Created**: 2025-11-11\n- **Source**: Gartner Emerging Technology Analysis\n- **Category**: Infrastructure & Cloud\n- **Status**: Emerging Technology\n\n\n## Metadata\n\n- **Last Updated**: 2025-11-16\n- **Review Status**: Automated remediation with 2025 context\n- **Verification**: Academic sources verified\n- **Regional Context**: UK/North England where applicable",
  "backlinks": [],
  "wiki_links": [
    "MetaverseDomain"
  ],
  "ontology": {
    "term_id": "ME-0017",
    "preferred_term": "Sustainable Technology",
    "alt_terms": [],
    "iri": "http://narrativegoldmine.com/metaverse#SustainableTechnology",
    "source_domain": "metaverse",
    "domain": "metaverse",
    "domain_full_name": "",
    "definition": null,
    "scope_note": null,
    "status": "emerging",
    "maturity": "emerging",
    "version": null,
    "public_access": true,
    "last_updated": null,
    "authority_score": null,
    "quality_score": null,
    "cross_domain_links": null,
    "owl_class": "mv:SustainableTechnology",
    "owl_physicality": "ConceptualEntity",
    "owl_role": "Concept",
    "owl_inferred_class": null,
    "is_subclass_of": [],
    "has_part": [],
    "is_part_of": [],
    "requires": [],
    "depends_on": [],
    "enables": [],
    "relates_to": [],
    "bridges_to": [],
    "bridges_from": [],
    "domain_extensions": {},
    "belongs_to_domain": [
      "MetaverseDomain"
    ],
    "implemented_in_layer": [],
    "source": [],
    "validation": {
      "is_valid": false,
      "errors": [
        "Missing required property: last-updated",
        "Missing required property: definition",
        "Missing required property: is-subclass-of (at least one parent class)",
        "owl:class namespace 'mv' doesn't match source-domain 'metaverse'"
      ]
    }
  }
}