{
  "id": "SwarmRobotics",
  "title": "SwarmRobotics",
  "content": "- ### OntologyBlock\n  id:: swarmrobotics-ontology\n  collapsed:: true\n\t- ontology:: true\n\t- term-id:: RB-0107\n\t- preferred-term:: SwarmRobotics\n\t- status:: active\n\t- public-access:: true\n\t- definition:: A field studying the coordination and collective behavior of multiple simple robots through local rules and interactions, inspired by biological swarm systems like ant colonies and bee swarms.\n\t- maturity:: mature\n\t- owl:class:: rb:SwarmRobotics\n\t- owl:physicality:: ConceptualEntity\n\t- owl:role:: Discipline\n\t- owl:equivalentClass:: rb:SwarmRobotics\n\t- belongsToDomain:: [[RoboticsDomain]]\n\t- #### CrossDomainBridges\n\t  id:: swarmrobotics-bridges\n\t  collapsed:: true\n\t\t- dt:uses:: [[ConsensusMechanism]]\n\t\t- dt:uses:: [[Machine Learning]]\n\n## OWL Formal Semantics\n\n```clojure\n;; OWL Functional Syntax\n\n(Declaration (Class :Swarmrobotics))\n\n;; Annotations\n(AnnotationAssertion rdfs:label :Swarmrobotics \"SwarmRobotics\"@en)\n(AnnotationAssertion rdfs:comment :Swarmrobotics \"A component of the metaverse ecosystem.\"@en)\n\n;; Data Properties\n(AnnotationAssertion dcterms:identifier :Swarmrobotics \"mv-1761742247974\"^^xsd:string)\n```",
  "backlinks": [
    "robotics-core-concepts"
  ],
  "wiki_links": [
    "ConsensusMechanism",
    "Machine Learning",
    "RoboticsDomain"
  ],
  "ontology": {
    "term_id": "RB-0107",
    "preferred_term": "SwarmRobotics",
    "alt_terms": [],
    "iri": "http://narrativegoldmine.com/robotics#SwarmRobotics",
    "source_domain": null,
    "domain": "rb",
    "domain_full_name": "Robotics",
    "definition": "A field studying the coordination and collective behavior of multiple simple robots through local rules and interactions, inspired by biological swarm systems like ant colonies and bee swarms.",
    "scope_note": null,
    "status": "active",
    "maturity": "mature",
    "version": null,
    "public_access": true,
    "last_updated": null,
    "authority_score": null,
    "quality_score": null,
    "cross_domain_links": null,
    "owl_class": "rb:SwarmRobotics",
    "owl_physicality": "ConceptualEntity",
    "owl_role": "Discipline",
    "owl_inferred_class": null,
    "is_subclass_of": [],
    "has_part": [],
    "is_part_of": [],
    "requires": [],
    "depends_on": [],
    "enables": [],
    "relates_to": [],
    "bridges_to": [],
    "bridges_from": [],
    "domain_extensions": {},
    "belongs_to_domain": [
      "RoboticsDomain"
    ],
    "implemented_in_layer": [],
    "source": [],
    "validation": {
      "is_valid": false,
      "errors": [
        "Missing required property: source-domain",
        "Missing required property: last-updated",
        "Missing required property: is-subclass-of (at least one parent class)"
      ]
    }
  }
}