{
  "id": "Synthetic Data Generator",
  "title": "Synthetic Data Generator",
  "content": "- ### OntologyBlock\n  id:: synthetic-data-generator-ontology\n  collapsed:: true\n\t- ontology:: true\n\t- term-id:: 20205\n\t- preferred-term:: Synthetic Data Generator\n\t- status:: draft\n\t- public-access:: true\n\t- definition:: AI-powered system that produces artificial datasets preserving statistical properties and structural characteristics of original data while protecting privacy and enabling testing scenarios.\n\t- source:: [[ISO/IEC 5259]], [[OECD AI]], [[IEEE P2048-9]]\n\t- maturity:: mature\n\t- owl:class:: mv:SyntheticDataGenerator\n\t- owl:physicality:: VirtualEntity\n\t- owl:role:: Process\n\t- owl:inferred-class:: mv:VirtualProcess\n\t- owl:functional-syntax:: true\n\t- belongsToDomain:: [[ComputationAndIntelligenceDomain]], [[InfrastructureDomain]]\n\t- implementedInLayer:: [[DataLayer]], [[AILayer]]\n\t- #### Relationships\n\t  id:: synthetic-data-generator-relationships\n\t  collapsed:: true\n\t\t- is-part-of:: [[AI Pipeline]]\n\t\t- is-part-of:: [[Data Management Platform]]\n\t\t- has-part:: [[Generative Model]]\n\t\t- has-part:: [[Data Simulator]]\n\t\t- has-part:: [[Privacy Validator]]\n\t\t- has-part:: [[Statistical Analyzer]]\n\t\t- requires:: [[Privacy Metrics]]\n\t\t- requires:: [[Training Data]]\n\t\t- requires:: [[Statistical Models]]\n\t\t- requires:: [[Machine Learning Framework]]\n\t\t- enables:: [[Model Training]]\n\t\t- enables:: [[Data Augmentation]]\n\t\t- enables:: [[Privacy-Preserving Data Sharing]]\n\t\t- enables:: [[Testing Dataset Creation]]\n\t\t- depends-on:: [[Generative Adversarial Network]]\n\t\t- depends-on:: [[Differential Privacy]]\n\n## Academic Context\n\n- Synthetic data generation represents a fundamental shift in how organisations approach machine learning development and data governance\n  - Emerged from statistical modelling traditions but has evolved dramatically with advances in generative AI\n  - Now recognised as essential infrastructure rather than experimental technique\n  - Addresses the classical tension between data utility and privacy protection\n\n- Core principle: artificially generated information that mimics statistical properties and patterns of real-world data without containing identifiable elements[1][2]\n  - Maintains relational integrity and structural characteristics of source datasets\n  - Enables rigorous testing and model development without exposing sensitive information\n  - Particularly valuable in regulated sectors where data access remains constrained\n\n## Current Landscape (2025)\n\n- Industry adoption has accelerated substantially, moving from niche application to mainstream deployment\n  - Gartner forecasts synthetic data will surpass real-world datasets for AI training by 2030[5]\n  - Major technology firms (Nvidia, Databricks) have built scalable synthetic data pipelines for production systems[5]\n  - Cost-effectiveness compared to traditional data collection has become a primary driver of adoption\n\n- Primary generation techniques now in widespread use\n  - Generative Adversarial Networks (GANs): two competing neural networks where a generator creates synthetic samples whilst a discriminator assesses authenticity, iteratively improving output quality[3][4]\n  - Statistical and machine learning models: regression models, Gaussian mixtures, and probabilistic frameworks that capture underlying data distributions[4]\n  - Rule-based generation: predefined business rules ensuring data relationships remain intact, particularly valuable in financial and healthcare contexts[4]\n  - Generative AI models: GPTs, VAEs, and diffusion models enabling high-fidelity synthetic data at scale[2]\n  - Entity cloning: extracting and masking single business entities, then generating variants with unique identifiers[1]\n  - Data masking: replacing personally identifiable information with fictitious yet structurally consistent values[1]\n\n- Technical capabilities and current limitations\n  - Can generate diverse data types: visual data (images, videos), structured tabular data, and natural language text[2]\n  - Particularly effective for rare scenarios, edge cases, and conditions difficult or dangerous to collect naturally\n  - Quality remains dependent on source data characteristics and model sophistication\n  - Potential for mode collapse in GANs and statistical bias propagation requires careful validation\n\n- Regulatory and privacy drivers\n  - GDPR, CCPA, and HIPAA compliance pressures have accelerated adoption across European and North American organisations[2]\n  - Provides privacy-compliant training datasets without exposing real personal or confidential information\n  - Enables responsible AI development in regulated sectors\n\n- UK and North England context\n  - Manchester and Leeds emerging as regional AI development hubs with growing synthetic data applications in financial services and healthcare\n  - NHS trusts increasingly exploring synthetic patient records for research whilst maintaining GDPR compliance\n  - Sheffield and Newcastle universities conducting research into synthetic data validation and quality assurance\n\n## Research & Literature\n\n- Key academic and industry sources\n  - K2view (2024). \"What is Synthetic Data Generation? A Practical Guide.\" Comprehensive technical overview of generation techniques and applications.\n  - Humans in the Loop (2025). \"Why Synthetic Data Is Taking Over in 2025: Solving AI's Data Crisis.\" Analysis of adoption drivers and enterprise-scale deployment.\n  - Netguru (2025). \"Synthetic Data: Revolutionising Modern AI Development in 2025.\" Technical examination of GAN architectures and recent advances in generation quality.\n  - Daffodil Software (2025). \"Everything You Should Know About Synthetic Data in 2025.\" Practical guide to rule-based, statistical, and adversarial generation methods.\n  - CleverX (2025). \"Synthetic Data Generation in 2025: Scale ML Training Smartly.\" Industry analysis with focus on cost-effectiveness and scalability for machine learning.\n  - MIT News (2025). \"3 Questions: The Pros and Cons of Synthetic Data in AI.\" Academic perspective on benefits and limitations.\n  - NIST Cybersecurity Resource Centre. \"Synthetic Data Generation.\" Formal definition: \"A process in which seed data are used to create artificial data that have some of the statistical characteristics of the seed data.\"[7]\n  - IBM (2025). \"What Is Synthetic Data?\" Overview of statistical and AI-driven generation methods.\n\n- Ongoing research directions\n  - Validation frameworks for assessing synthetic data fidelity and utility\n  - Bias detection and mitigation in generated datasets\n  - Domain-specific generation techniques for healthcare, finance, and autonomous systems\n  - Integration with federated learning and privacy-preserving machine learning\n\n## UK Context\n\n- British contributions to synthetic data development\n  - Academic institutions (particularly Russell Group universities) conducting foundational research into generation quality and privacy guarantees\n  - NHS Digital exploring synthetic patient records for research access without compromising patient confidentiality\n  - Financial Conduct Authority (FCA) encouraging regulated firms to adopt synthetic data for testing and compliance scenarios\n\n- North England innovation activity\n  - Manchester: financial services sector increasingly adopting synthetic data for algorithmic testing and model validation\n  - Leeds: healthcare and life sciences organisations implementing synthetic patient records for research\n  - Newcastle: emerging research into synthetic data applications in autonomous systems and robotics\n  - Sheffield: university research into statistical validation methods for synthetic datasets\n\n- Regional case studies\n  - Manchester-based fintech firms using synthetic transaction data to accelerate model development whilst maintaining regulatory compliance\n  - NHS trusts in Yorkshire exploring synthetic patient records to enable research access without GDPR complications (rather elegant solution to a genuinely thorny problem)\n\n## Future Directions\n\n- Emerging trends and developments\n  - Simulation-driven training becoming essential for robotics and physical AI systems, particularly for autonomous vehicles[5]\n  - Integration with agentic AI systems requiring diverse datasets at scale across multiple domains[9]\n  - Advancement in progressive GAN architectures and style-based generation improving diversity and realism\n  - Copula models and advanced statistical techniques capturing complex correlations within production datasets\n\n- Anticipated challenges\n  - Ensuring synthetic data remains representative as source data distributions shift\n  - Detecting and preventing synthetic data bias propagation into production models\n  - Establishing industry standards for synthetic data quality and validation\n  - Balancing computational costs of generation against traditional data acquisition expenses\n\n- Research priorities\n  - Developing robust validation frameworks for assessing synthetic data utility across domains\n  - Creating domain-specific generation techniques for highly regulated sectors\n  - Establishing best practices for synthetic data governance and lineage tracking\n  - Investigating synthetic data effectiveness for rare event prediction and anomaly detection\n\n---\n\n**Note on definition refinement:** The original definition remains substantially accurate. Consider expanding to: \"AI-powered system that generates artificial datasets through statistical modelling, machine learning, or generative techniques, preserving statistical properties and structural relationships whilst eliminating personally identifiable information, enabling privacy-compliant testing, model development, and training at scale.\"\n\n## Metadata\n\n- **Last Updated**: 2025-11-11\n- **Review Status**: Comprehensive editorial review\n- **Verification**: Academic sources verified\n- **Regional Context**: UK/North England where applicable",
  "backlinks": [],
  "wiki_links": [
    "InfrastructureDomain",
    "Testing Dataset Creation",
    "AI Pipeline",
    "Generative Model",
    "Machine Learning Framework",
    "AILayer",
    "Data Management Platform",
    "Statistical Analyzer",
    "OECD AI",
    "ISO/IEC 5259",
    "Data Augmentation",
    "Privacy Validator",
    "Training Data",
    "IEEE P2048-9",
    "Data Simulator",
    "Generative Adversarial Network",
    "Model Training",
    "Privacy-Preserving Data Sharing",
    "Differential Privacy",
    "Privacy Metrics",
    "ComputationAndIntelligenceDomain",
    "Statistical Models",
    "DataLayer"
  ],
  "ontology": {
    "term_id": "20205",
    "preferred_term": "Synthetic Data Generator",
    "alt_terms": [],
    "iri": "http://narrativegoldmine.com/metaverse#SyntheticDataGenerator",
    "source_domain": null,
    "domain": "mv",
    "domain_full_name": "Metaverse",
    "definition": "AI-powered system that produces artificial datasets preserving statistical properties and structural characteristics of original data while protecting privacy and enabling testing scenarios.",
    "scope_note": null,
    "status": "draft",
    "maturity": "mature",
    "version": null,
    "public_access": true,
    "last_updated": null,
    "authority_score": null,
    "quality_score": null,
    "cross_domain_links": null,
    "owl_class": "mv:SyntheticDataGenerator",
    "owl_physicality": "VirtualEntity",
    "owl_role": "Process",
    "owl_inferred_class": "mv:VirtualProcess",
    "is_subclass_of": [],
    "has_part": [
      "Generative Model",
      "Data Simulator",
      "Privacy Validator",
      "Statistical Analyzer"
    ],
    "is_part_of": [
      "AI Pipeline",
      "Data Management Platform"
    ],
    "requires": [
      "Privacy Metrics",
      "Training Data",
      "Statistical Models",
      "Machine Learning Framework"
    ],
    "depends_on": [
      "Generative Adversarial Network",
      "Differential Privacy"
    ],
    "enables": [
      "Model Training",
      "Data Augmentation",
      "Privacy-Preserving Data Sharing",
      "Testing Dataset Creation"
    ],
    "relates_to": [],
    "bridges_to": [],
    "bridges_from": [],
    "domain_extensions": {},
    "belongs_to_domain": [
      "ComputationAndIntelligenceDomain",
      "InfrastructureDomain"
    ],
    "implemented_in_layer": [
      "DataLayer",
      "AILayer"
    ],
    "source": [
      "ISO/IEC 5259",
      "OECD AI",
      "IEEE P2048-9"
    ],
    "validation": {
      "is_valid": false,
      "errors": [
        "Missing required property: source-domain",
        "Missing required property: last-updated",
        "Missing required property: is-subclass-of (at least one parent class)",
        "term-id '20205' doesn't match domain 'mv' (expected MV-)"
      ]
    }
  }
}