{
  "id": "T5",
  "title": "T5",
  "content": "- ### OntologyBlock\n  id:: t5-ontology\n  collapsed:: true\n\t- ontology:: true\n\t- term-id:: AI-0216\n\t- preferred-term:: T5\n\t- source-domain:: metaverse\n\t- status:: draft\n\t- public-access:: true\n\n\n\n\n### OWL Classification\n\t- owl:class:: mv:T5\n\t- owl:physicality:: ConceptualEntity\n\t- owl:role:: Concept\n\n### Domain & Architecture\n\t- belongsToDomain:: [[MetaverseDomain]]\n\t- maturity:: draft\n\n### Relationships\n\n## Characteristics\n\n- **Unified Framework**: All tasks framed as text-to-text\n- **Encoder-Decoder Architecture**: Full transformer with both components\n- **Span Corruption**: Pre-training objective masking spans of text\n- **Flexible Task Formulation**: Single model for all NLP tasks\n\n## Academic Foundations\n\n**Primary Source**: Raffel et al., \"Exploring the Limits of Transfer Learning with a Unified Text-to-Text Transformer\", arXiv:1910.10683 (2019)\n\n**C4 Dataset**: Introduced Colossal Clean Crawled Corpus for pre-training.\n\n## Technical Context\n\nT5 explores transfer learning techniques systematically, comparing various pre-training objectives, architectures, and datasets. The text-to-text framework allows the same model, loss function, and hyperparameters to be used across all tasks.\n\n## Ontological Relationships\n\n- **Broader Term**: Pre-trained Language Model\n- **Related Terms**: BERT, GPT, Encoder-Decoder Architecture\n- **Variants**: mT5 (multilingual), ByT5 (byte-level)\n\n## Usage Context\n\n\"T5's text-to-text framework enables a single model to handle translation, summarisation, classification, and question answering with the same architecture.\"\n\n## OWL Functional Syntax\n\n```clojure\n(Declaration (Class :T5))\n(AnnotationAssertion rdfs:label :T5 \"T5\"@en)\n(AnnotationAssertion :fullName :T5 \"Text-to-Text Transfer Transformer\"@en)\n(AnnotationAssertion rdfs:comment :T5\n  \"Unified framework converting all NLP tasks to text-to-text format using encoder-decoder architecture.\"@en)\n(AnnotationAssertion :hasSource :T5\n  \"Raffel et al., 'Exploring the Limits of Transfer Learning', arXiv:1910.10683 (2019)\"@en)\n\n;; Taxonomic relationships\n(SubClassOf :T5 :PreTrainedLanguageModel)\n(SubClassOf :T5 :EncoderDecoderArchitecture)\n(SubClassOf :T5 :TransformerArchitecture)\n\n;; Architectural characteristics\n(SubClassOf :T5\n  (ObjectSomeValuesFrom :hasComponent :Encoder))\n(SubClassOf :T5\n  (ObjectSomeValuesFrom :hasComponent :Decoder))\n(DataPropertyAssertion :usesFullEncoderDecoder :T5 \"true\"^^xsd:boolean)\n\n;; Unified framework\n(Declaration (Class :TextToTextFramework))\n(SubClassOf :T5\n  (ObjectSomeValuesFrom :implements :TextToTextFramework))\n\n(AnnotationAssertion rdfs:comment :TextToTextFramework\n  \"Converts all tasks to text-to-text format: input text â†’ output text\"@en)\n\n;; Pre-training objective\n(Declaration (Class :SpanCorruption))\n(SubClassOf :T5\n  (ObjectSomeValuesFrom :trainedWith :SpanCorruption))\n\n(AnnotationAssertion rdfs:comment :SpanCorruption\n  \"Pre-training objective masking contiguous spans of text\"@en)\n\n;; Training data\n(Declaration (Class :C4Dataset))\n(SubClassOf :T5\n  (ObjectSomeValuesFrom :trainedOn :C4Dataset))\n\n(AnnotationAssertion :fullName :C4Dataset \"Colossal Clean Crawled Corpus\"@en)\n\n;; Task versatility\n(DataPropertyAssertion :handlesAllNLPTasks :T5 \"true\"^^xsd:boolean)\n(DataPropertyAssertion :usesSameArchitecture :T5 \"true\"^^xsd:boolean)\n(DataPropertyAssertion :usesSameLossFunction :T5 \"true\"^^xsd:boolean)\n(DataPropertyAssertion :usesSameHyperparameters :T5 \"true\"^^xsd:boolean)\n\n;; Supported tasks (via text-to-text)\n(AnnotationAssertion :supportsTask :T5 \"Translation\"@en)\n(AnnotationAssertion :supportsTask :T5 \"Summarisation\"@en)\n(AnnotationAssertion :supportsTask :T5 \"Classification\"@en)\n(AnnotationAssertion :supportsTask :T5 \"Question Answering\"@en)\n\n;; Model variants\n(Declaration (Class :T5Small))\n(Declaration (Class :T5Base))\n(Declaration (Class :T5Large))\n(Declaration (Class :T5_3B))\n(Declaration (Class :T5_11B))\n\n(SubClassOf :T5Small :T5)\n(SubClassOf :T5Base :T5)\n(SubClassOf :T5Large :T5)\n(SubClassOf :T5_3B :T5)\n(SubClassOf :T5_11B :T5)\n\n(DataPropertyAssertion :hasParameterCount :T5Small \"60M\"^^xsd:string)\n(DataPropertyAssertion :hasParameterCount :T5Base \"220M\"^^xsd:string)\n(DataPropertyAssertion :hasParameterCount :T5Large \"770M\"^^xsd:string)\n(DataPropertyAssertion :hasParameterCount :T5_3B \"3B\"^^xsd:string)\n(DataPropertyAssertion :hasParameterCount :T5_11B \"11B\"^^xsd:string)\n\n;; Multilingual and specialized variants\n(SubClassOf :mT5 :T5)\n(SubClassOf :ByT5 :T5)\n\n(AnnotationAssertion :fullName :mT5 \"Multilingual T5\"@en)\n(AnnotationAssertion :fullName :ByT5 \"Byte-level T5\"@en)\n```\n\n## References\n\n- Raffel, C., et al. (2019). \"Exploring the Limits of Transfer Learning with a Unified Text-to-Text Transformer\". arXiv:1910.10683\n\n---\n\n*Ontology Term managed by AI-Grounded Ontology Working Group*\n*UK English Spelling Standards Applied*\n\t- maturity:: draft\n\t- owl:class:: mv:T5\n\t- owl:physicality:: ConceptualEntity\n\t- owl:role:: Concept\n\t- is-subclass-of:: [[ArtificialIntelligence]]\n\t- belongsToDomain:: [[MetaverseDomain]]",
  "backlinks": [],
  "wiki_links": [
    "MetaverseDomain",
    "ArtificialIntelligence"
  ],
  "ontology": {
    "term_id": "AI-0216",
    "preferred_term": "T5",
    "alt_terms": [],
    "iri": "http://narrativegoldmine.com/metaverse#T5",
    "source_domain": "metaverse",
    "domain": "metaverse",
    "domain_full_name": "",
    "definition": null,
    "scope_note": null,
    "status": "draft",
    "maturity": "draft",
    "version": null,
    "public_access": true,
    "last_updated": null,
    "authority_score": null,
    "quality_score": null,
    "cross_domain_links": null,
    "owl_class": "mv:T5",
    "owl_physicality": "ConceptualEntity",
    "owl_role": "Concept",
    "owl_inferred_class": null,
    "is_subclass_of": [],
    "has_part": [],
    "is_part_of": [],
    "requires": [],
    "depends_on": [],
    "enables": [],
    "relates_to": [],
    "bridges_to": [],
    "bridges_from": [],
    "domain_extensions": {},
    "belongs_to_domain": [
      "MetaverseDomain",
      "MetaverseDomain"
    ],
    "implemented_in_layer": [],
    "source": [],
    "validation": {
      "is_valid": false,
      "errors": [
        "Missing required property: last-updated",
        "Missing required property: definition",
        "Missing required property: is-subclass-of (at least one parent class)",
        "owl:class namespace 'mv' doesn't match source-domain 'metaverse'"
      ]
    }
  }
}