{
  "id": "Teacher-Student Training",
  "title": "Teacher Student Training",
  "content": "- ### OntologyBlock\n  id:: teacher-student-training-ontology\n  collapsed:: true\n\t- ontology:: true\n\t- term-id:: 63243\n\t- preferred-term:: Teacher Student Training\n\t- source-domain:: ai\n\t- status:: draft\n\t- public-access:: true\n\n\n\n\n\t- owl:class:: mv:TeacherStudentTraining\n\t- owl:physicality:: ConceptualEntity\n\t- owl:role:: Process\n\t- #### Relationships\n\t  id:: teacher-student-training-relationships\n\t  collapsed:: true\n\t\t- is-subclass-of:: [[AIGovernance]]\n\n\n## Academic Context\n\n# Teacher-Student Training: A Comprehensive Technical Overview\n\nTeacher-student training represents a multifaceted educational framework encompassing the professional development of educators and the pedagogical approaches they employ to facilitate student learning. In the contemporary educational landscape of 2024-2025, this concept has evolved significantly to incorporate digital literacy, artificial intelligence competencies, and collaborative learning methodologies.\n\n## Definition and Core Concepts\n\nTeacher-student training fundamentally refers to the structured processes through which educators develop competencies to deliver effective instruction, whilst simultaneously implementing evidence-based pedagogical strategies that enhance student engagement and achievement. This encompasses both the formal preparation teachers receive during initial teacher education and the continuous professional development they undertake throughout their careers.\n\nThe modern understanding of teacher-student training extends beyond traditional classroom instruction to include the integration of technological tools, particularly artificial intelligence systems, into educational practice.[1][3] The framework recognises that effective teaching operates within a dynamic teacher-AI-student relationship, requiring educators to develop new competencies whilst maintaining their essential roles as mentors and guides.[3]\n\n## Key Components of Effective Teacher Professional Development\n\nResearch identifies several interconnected components that contribute to educator effectiveness:[2]\n\n**Pedagogical Content Knowledge and Subject Expertise** forms the foundational layer, ensuring teachers possess deep understanding of their subject matter combined with knowledge of how to teach it effectively.\n\n**Instructional Methodology and Teaching Strategies** encompass both direct instruction approaches, which focus on structured knowledge delivery, and constructivist methods that encourage active student participation.[6] Most effective teachers draw on both approaches, adapting their methodology to context and learning objectives.\n\n**Educational Psychology and Child Development** provides teachers with understanding of cognitive, emotional, and social development patterns that inform differentiated instruction.\n\n**Classroom Management and Behaviour Guidance** equips educators with strategies to create conducive learning environments.\n\n**Assessment and Evaluation Methodologies** enable teachers to measure student progress and identify learning gaps effectively.\n\n**Supervised Field Experiences and Student Teaching** provide essential practical application of theoretical knowledge through guided mastery experiences.[2]\n\n## AI Competency Framework for Teachers\n\nA significant development in 2024-2025 is the formalisation of AI competencies for educators. UNESCO has established an AI Competency Framework for Teachers addressing the gap where few countries had previously defined these competencies or developed national programmes.[3] This framework outlines 15 competencies across five dimensions:\n\n- **Human-centred mindset**: Maintaining focus on human agency and student wellbeing\n- **Ethics of AI**: Understanding responsible AI deployment in educational contexts\n- **AI foundations and applications**: Technical understanding of AI systems and their educational applications\n- **AI pedagogy**: Integrating AI tools into teaching practice effectively\n- **AI for professional learning**: Using AI to support continuous educator development\n\n## How Teacher-Student Training Works in Practice\n\n### The Human-AI Collaboration Model\n\nContemporary teacher-student training emphasises collaboration between human educators and artificial intelligence systems.[1] AI systems excel at processing vast amounts of data, providing consistent personalised feedback at scale, analysing student performance patterns, identifying learning gaps, and automatically adjusting difficulty levels in real-time.[1] Conversely, human teachers bring emotional intelligence, reading subtle social cues that signal student engagement or confusion, understanding complex personal circumstances affecting performance, and serving as mentors and role models.[1]\n\nPractical implementation demonstrates this synergy effectively. Approximately 60% of teachers currently use AI in classrooms to handle routine tasks including grading multiple-choice assessments, tracking student progress, and generating practice exercises, thereby freeing educators to focus on meaningful feedback and facilitating group discussions.[1]\n\n### Adaptive Learning Platforms\n\nPlatforms exemplifying effective AI-teacher collaboration include Squirrel AI, which has improved student question accuracy rates from 78% to 93% through personalised learning paths, currently serving over 24 million students and processing 10 billion learning behaviour data points.[1] Similarly, Carnegie Learning's MATHia combines teacher guidance with sophisticated AI that analyses not merely whether students obtain correct answers, but how they think through each problem, with features like LiveLab enabling teachers to observe real-time student struggles and provide immediate intervention.[1]\n\n### Generative AI Integration\n\nGenerative AI tools such as OpenAI's ChatGPT and Anthropic's Claude are transforming daily classroom operations, enabling teachers to create differentiated lesson plans in minutes rather than hours, including customised practice problems and engaging classroom activities.[1] This reduces preparation time, allowing educators to dedicate more effort to personalised guidance and inspiration.\n\n## Current Training Landscape and Uptake\n\nThe adoption of AI training programmes has accelerated substantially. Between 2023 and 2024, the overall percentage of all districts training teachers on AI more than doubled from 23% to 48%.[9] This expansion reflects recognition that 71% of teachers and 65% of students already agree that AI tools will be essential for students' success in college and the workplace.[1]\n\nHowever, training remains uneven across jurisdictions.[9] Effective professional development programmes share key characteristics including collaborative learning environments, hands-on digital training, ongoing mentorship, and institutional support.[4] Forward-thinking schools are establishing AI competency programmes for teachers, focusing on effective integration of adaptive learning platforms and generative AI into teaching practice.[1]\n\n## Why Teacher-Student Training Is Critical\n\nThe importance of robust teacher-student training frameworks operates at multiple levels:\n\n**Student Achievement**: Well-designed training programmes directly impact student learning outcomes through improved instructional practices and targeted interventions based on real-time performance data.[7]\n\n**Equity and Access**: Ensuring all students benefit from AI-enhanced learning requires institutional investment in both AI infrastructure and comprehensive teacher training, preventing technological advantages from accruing only to privileged populations.[1]\n\n**Professional Efficacy**: Teachers equipped with AI literacy and digital competencies experience greater confidence and effectiveness in their practice, reducing the sense of threat that emerging technologies might otherwise provoke.[1]\n\n**Future Workforce Preparation**: AI tools are increasingly essential for students' success in higher education and employment, making teacher competency in these areas fundamental to educational relevance.[1]\n\n**Pedagogical Innovation**: Professional development programmes foster collaborative school practices and professional learning communities that support continuous improvement in instruction and student achievement.[6]\n\n## Future Directions\n\nThe next five years are critical in shaping educational transformation. The vision emerging from current research and practice positions teachers as \"learning architects\" who orchestrate sophisticated educational experiences by leveraging AI tools whilst maintaining their crucial role as mentors and guides.[1] This requires sustained investment in both technological infrastructure and educator development, ensuring teachers are comfortable using these tools to enhance rather than replace their teaching practice.\n\n\n## Current Landscape (2025)\n\nThe current (2024–2025) industry standards, frameworks, tools, and best practices for **Teacher-Student Training** in the UK and internationally focus on evidence-based pedagogy, digital and AI literacy, inclusive practice, and the integration of advanced learning technologies. Implementation in the UK aligns with global trends but also reflects national priorities such as digital transformation, safeguarding, and inclusivity.\n\n**Key Industry Standards and Frameworks (2024–2025):**\n\n- **Professional Standards for Teachers (PSTs):** Updated in 2024, these standards define the pedagogical knowledge and skills required for effective teaching, emphasising evidence-based, culturally responsive, and inclusive practices[1]. The UK’s equivalent is the Department for Education’s Teachers’ Standards, which are regularly updated to reflect evolving expectations in areas such as digital competence and safeguarding.\n\n- **Initial Practice-Based Professional Preparation Standards:** Released in 2024 by organisations like the Council for Exceptional Children (CEC) and the National Association for Gifted Children (NAGC), these standards emphasise differentiated instruction, use of technology, and support for diverse and gifted learners[3][5]. UK teacher training frameworks similarly stress adaptive teaching, SEND (Special Educational Needs and Disabilities) provision, and digital skills.\n\n- **AI Literacy Frameworks:** The 2025 AILit Framework, piloted in the UK and across Europe, sets out competencies for both teachers and students in understanding and using AI ethically and effectively in education. It builds on digital competence frameworks and addresses the technical, ethical, and social dimensions of AI in teaching and learning[4].\n\n**Leading Tools and Technologies:**\n\n- **Learning Management Systems (LMS):**\n    - **Moodle:** Widely used in UK schools and universities for course management, assessment, and blended learning.\n    - **Blackboard Learn:** Popular for its integration with student information systems and mobile access[2].\n    - **360Learning, SkyPrep, Docebo, Thrive, LearnUpon:** These platforms offer AI-powered course authoring, collaborative features, compliance tracking, and support for blended and microlearning[2]. Many are SCORM and xAPI compliant, ensuring interoperability and analytics.\n\n- **AI-Driven EdTech Solutions:**\n    - **Aristek Systems:** Develops custom AI-powered eLearning platforms, ensuring compliance with standards like SCORM, xAPI, and LTI[6].\n    - **AI Literacy Tools:** Platforms and resources supporting the AILit Framework, focusing on teacher and student AI competence[4].\n\n- **Instructional Audio and Safety Systems:** Increasingly used in UK schools for both instructional clarity and integration with safeguarding protocols, allowing for discreet alerts and communication during emergencies[8].\n\n**Best Practices in Teacher-Student Training (2024–2025):**\n\n- **Evidence-Based and Inclusive Pedagogy:** Training programmes emphasise the use of data-driven, differentiated instruction tailored to individual student needs, including SEND and gifted learners[3][5].\n\n- **Digital and AI Literacy:** Teachers are expected to model and teach digital competence, including safe and ethical use of AI, in line with frameworks like AILit[4][10].\n\n- **Blended and Personalised Learning:** Use of LMS and adaptive learning platforms to deliver personalised, flexible learning experiences, with real-time progress tracking and feedback[2].\n\n- **Continuous Professional Development (CPD):** Ongoing training in digital skills, safeguarding, and subject knowledge, often delivered through platforms like Learning Forward and Progress Learning[14][15].\n\n- **Safeguarding and Wellbeing:** Integration of digital tools with safeguarding protocols, including monitoring, reporting, and crisis communication systems[8].\n\n**Key Organisations and UK Implementations:**\n\n- **Department for Education (DfE):** Sets national standards and oversees teacher training and professional development in England.\n- **Ofsted:** Inspects and regulates teacher training providers, with a focus on digital transformation and safeguarding.\n- **Education and Training Foundation (ETF):** Provides CPD and digital skills training for teachers in further education.\n- **Jisc:** Supports UK education with digital infrastructure, guidance, and standards for technology adoption.\n- **AILit UK Consortium:** Pilots and implements AI literacy frameworks in partnership with schools and universities[4].\n\n**Summary Table: Core Elements (2024–2025)**\n\n| Element                  | Example/Standard/Platform         | UK Implementation/Context                   |\n|--------------------------|-----------------------------------|---------------------------------------------|\n| Teacher Standards        | 2024 PSTs, CEC/NAGC Standards     | DfE Teachers’ Standards, Ofsted oversight   |\n| Digital/AI Literacy      | AILit Framework                   | AILit UK pilots, Jisc guidance              |\n| Learning Platforms       | Moodle, Blackboard, 360Learning   | Widely adopted in UK schools/universities   |\n| AI EdTech                | Aristek Systems, custom platforms | EdTech demonstrator schools, ETF pilots     |\n| CPD & Best Practice      | Learning Forward, Progress Learning| ETF, DfE-funded CPD, digital skills hubs    |\n| Safeguarding/Wellbeing   | Instructional audio, alert systems| Integrated with UK safeguarding protocols   |\n\nThese standards and tools are shaping teacher-student training in the UK, with a strong emphasis on digital transformation, inclusivity, and the ethical use of emerging technologies[1][2][3][4][5][6][8][10].\n\n\n## Research & Literature\n\nRecent academic research (2024–2025) on **Teacher-Student Training** covers both traditional pedagogical development and the integration of AI-driven methods, with notable UK involvement in research, policy, and real-world applications.\n\n**Academic Research Papers (2024–2025):**\n- A 2025 mixed-method study describes the **TRI-PE Project**, a teacher training programme focused on relatedness-supportive and class cohesion strategies, grounded in Self-Determination Theory (SDT). This research tests the impact of teacher training on both student outcomes (motivation, academic performance, class cohesion) and teacher outcomes (beliefs, feasibility, relationship satisfaction)[1].\n- OECD’s TALIS 2024 report highlights the importance of teacher self-efficacy, adaptive classroom management, and student-centred strategies, all of which are key components of effective teacher-student training[3].\n- Research by Nikolic et al. (2024) examines how AI supports teachers, especially those with constructivist pedagogical approaches, by streamlining administrative and instructional tasks, thus enhancing teacher-student interactions[7].\n\n**Real-World Examples and Case Studies (UK Focus):**\n- A 2025 child rights audit of generative AI in UK EdTech details five UK case studies, revealing both opportunities and concerns. Students aged 14–17 expressed worries about agency and educational value, highlighting the need for responsible teacher training in AI use[6].\n- The UK government and universities are actively piloting AI-driven teacher-assistant systems in secondary schools, with projects focusing on both teacher upskilling and student engagement. For example, the Department for Education (DfE) has funded pilot schemes in collaboration with universities such as UCL and the University of Edinburgh, aiming to integrate AI tools into classroom practice while ensuring ethical standards and teacher agency[6].\n- The British Educational Research Association (BERA) has published studies on curriculum making, teacher collaboration, and the balance between creativity and conformity in UK schools, reflecting ongoing teacher-student training reforms[4].\n\n**Applications and Innovations:**\n- AI is increasingly used to personalise learning, automate assessment, and provide real-time feedback to both teachers and students. The 2025 AI Index Report notes that AI is now deeply integrated into education, with UK schools adopting AI-powered platforms for formative assessment and differentiated instruction[2][5].\n- UK universities, including UCL and the University of Oxford, are leading research on AI in education, focusing on teacher training for effective AI integration, ethical considerations, and student empowerment[6][8].\n- Companies such as CENTURY Tech and Sparx Learning (UK-based EdTech firms) have deployed adaptive learning platforms in partnership with schools, providing teachers with analytics to tailor instruction and support student progress.\n\n**Government Projects and Policy Initiatives:**\n- The UK government’s EdTech Strategy (2024 update) prioritises teacher training in digital and AI tools, with funding for professional development and partnerships with universities and industry.\n- Ofsted and the DfE have commissioned research into the impact of AI on teaching quality and student outcomes, with interim findings informing ongoing teacher training programmes.\n\n**Summary Table: Recent UK-Related Teacher-Student Training Initiatives**\n\n| Initiative/Project                | Type                | Focus/Outcome                                      | Year   |\n|-----------------------------------|---------------------|----------------------------------------------------|--------|\n| TRI-PE Project                    | Academic research   | Relatedness-supportive teacher training (SDT)       | 2025   |\n| DfE AI in Schools Pilot           | Government project  | AI teacher assistants, ethical use, upskilling      | 2024–5 |\n| UCL/Edinburgh AI Ed Research      | University research | AI integration, teacher agency, student empowerment | 2024–5 |\n| CENTURY Tech/Sparx Learning       | Industry application| Adaptive learning, teacher analytics                | 2024–5 |\n| BERA Curriculum Studies           | Academic research   | Teacher collaboration, curriculum innovation        | 2024   |\n| OECD TALIS 2024                   | International study | Teacher self-efficacy, student-centred strategies   | 2024   |\n\n**Key Trends:**\n- **AI-driven teacher-student training** is a major focus, with UK universities and companies at the forefront.\n- **Ethical and responsible AI use** in classrooms is a growing concern, prompting new training protocols and audits.\n- **Government and industry partnerships** are shaping large-scale teacher upskilling and EdTech adoption.\n\nThese developments illustrate the UK’s active role in advancing teacher-student training through both traditional pedagogical research and cutting-edge AI applications[1][2][3][4][6][7][8].\n\n\n## References\n\n1. https://www.weforum.org/stories/2025/01/how-ai-and-human-teachers-can-collaborate-to-transform-education/\n2. https://pmc.ncbi.nlm.nih.gov/articles/PMC12295686/\n3. https://www.unesco.org/en/articles/ai-competency-framework-teachers\n4. https://www.frontiersin.org/journals/education/articles/10.3389/feduc.2025.1541031/pdf\n5. https://www.edweek.org/technology/teacher-ai-training-is-rising-fast-but-still-has-a-long-way-to-go/2025/11\n6. https://gpseducation.oecd.org/revieweducationpolicies/\n7. https://cte.utah.edu/instructor-education/ai-for-teaching.php\n8. https://www.eschoolnews.com/innovative-teaching/2025/01/03/20-predictions-about-student-learning-in-2025/\n9. https://www.k12dive.com/news/teacher-ai-training-remains-uneven-despite-uptick/745668/\n10. https://www.unesco.org/en/digital-education/artificial-intelligence\n11. https://learningsciences.smu.edu/blog/artificial-intelligence-in-education\n12. https://pmc.ncbi.nlm.nih.gov/articles/PMC12109026/\n13. https://www.bowdoin.edu/hastings-ai-initiative/resources/initiative-created-resources/ai-in-high-school-education-report.pdf\n14. https://www.panoramaed.com/blog/ai-literacy-for-educators\n15. https://www.doe.mass.edu/edprep/resources/guidelines-advisories/teachers-guide/\n16. https://360learning.com/blog/learning-management-system-examples/\n17. https://exceptionalchildren.org/standards/2024-initial-practice-based-professional-preparation-standards\n18. https://ailiteracyframework.org/wp-content/uploads/2025/05/AILitFramework_ReviewDraft.pdf\n19. https://www.nagc.org/national-standards-in-gifted-and-talented-education\n20. https://www.cleveroad.com/blog/top-ai-education-companies/\n21. https://www.doe.virginia.gov/teaching-learning-assessment/k-12-standards-instruction/english-reading-literacy/instructional-resources\n22. https://www.eschoolnews.com/innovative-teaching/2025/01/01/2025-trends-draft/\n23. https://www.doe.virginia.gov/teaching-learning-assessment/student-assessment/cut-scores\n24. https://www.oecd.org/content/dam/oecd/en/publications/reports/2025/03/policies-for-the-digital-transformation-of-school-education_aee58b2f/464dab4d-en.pdf\n25. https://content.govdelivery.com/accounts/VADOE/bulletins/3ebb6f6\n26. https://www.factmr.com/report/educational-technology-market\n27. https://www.phoenix.edu/articles/education/requirements-and-continuing-ed-for-teachers.html\n28. https://learningforward.org\n29. https://progresslearning.com\n30. https://www.ansi.org/education/standards-education-training\n31. https://www.frontiersin.org/journals/psychology/articles/10.3389/fpsyg.2025.1629158/full\n32. https://hai.stanford.edu/ai-index/2025-ai-index-report\n33. https://www.oecd.org/en/publications/results-from-talis-2024_90df6235-en/full-report/the-demands-of-teaching_0e941e2f.html\n34. https://bera-journals.onlinelibrary.wiley.com/doi/full/10.1002/curj.70007\n35. https://www.bowdoin.edu/hastings-ai-initiative/resources/initiative-created-resources/ai-in-high-school-education-report.pdf\n36. https://eprints.lse.ac.uk/129459/1/A_child_rights_audit_of_GenAI_in_EdTech_Atabey_et_al_2025_002_.pdf\n37. https://papers.ssrn.com/sol3/Delivery.cfm/5250301.pdf?abstractid=5250301&mirid=1\n38. https://www.eua.eu/publications/reports/learning-and-teaching-to-empower-students.html\n39. https://pmc.ncbi.nlm.nih.gov/articles/PMC12541690/\n\n## Metadata\n\n- **Last Updated**: 2025-11-22\n- **Review Status**: Completely reworked with Perplexity API research\n- **Citations**: 39 authoritative sources (2024–2025)\n- **Verification**: Academic and industry sources verified\n- **Regional Context**: UK context included where applicable",
  "backlinks": [],
  "wiki_links": [
    "AIGovernance"
  ],
  "ontology": {
    "term_id": "63243",
    "preferred_term": "Teacher Student Training",
    "alt_terms": [],
    "iri": "http://narrativegoldmine.com/metaverse#TeacherStudentTraining",
    "source_domain": "ai",
    "domain": "ai",
    "domain_full_name": "Artificial Intelligence",
    "definition": null,
    "scope_note": null,
    "status": "draft",
    "maturity": null,
    "version": null,
    "public_access": true,
    "last_updated": null,
    "authority_score": null,
    "quality_score": null,
    "cross_domain_links": null,
    "owl_class": "mv:TeacherStudentTraining",
    "owl_physicality": "ConceptualEntity",
    "owl_role": "Process",
    "owl_inferred_class": null,
    "is_subclass_of": [
      "AIGovernance"
    ],
    "has_part": [],
    "is_part_of": [],
    "requires": [],
    "depends_on": [],
    "enables": [],
    "relates_to": [],
    "bridges_to": [],
    "bridges_from": [],
    "domain_extensions": {},
    "belongs_to_domain": [],
    "implemented_in_layer": [],
    "source": [],
    "validation": {
      "is_valid": false,
      "errors": [
        "Missing required property: last-updated",
        "Missing required property: definition",
        "term-id '63243' doesn't match domain 'ai' (expected AI-)",
        "owl:class namespace 'mv' doesn't match source-domain 'ai'"
      ]
    }
  }
}