{
  "id": "Teleoperated Robot",
  "title": "Teleoperated Robot",
  "content": "- ### OntologyBlock\n  id:: rb-0009-teleoperated-robot-ontology\n  collapsed:: true\n\t- ontology:: true\n    - is-subclass-of:: [[RoboticsTechnology]]\n\t- term-id:: RB-0009\n\t- domain-prefix:: RB\n\t- sequence-number:: 0009\n\t- filename-history:: [\"rb-0009-teleoperated-robot.md\"]\n\t- preferred-term:: Teleoperated Robot\n\t- source-domain:: robotics\n\t- status:: draft\n    - public-access:: true\n\t- definition:: ### Primary Definition\n**Teleoperated Robot** - Teleoperated Robot in robotics systems\n\t- maturity:: draft\n\t- owl:class:: mv:rb0009teleoperatedrobot\n\t- owl:physicality:: ConceptualEntity\n\t- owl:role:: Concept\n\t- belongsToDomain:: [[MetaverseDomain]]\n- ## About rb 0009 teleoperated robot\n\t- ### Primary Definition\n**Teleoperated Robot** - Teleoperated Robot in robotics systems\n\t-\n\t- ### Original Content\n\t  collapsed:: true\n\t\t- ```\n# RB-0009: Teleoperated Robot\n\t\t  \n\t\t  ## Metadata\n\t\t  - **Term ID**: RB-0009\n\t\t  - **Term Type**: Core Concept\n\t\t  - **Classification**: Robot Types & Morphologies\n\t\t  - **Priority**: 1 (Foundational)\n\t\t  - **Authority Score**: 0.95\n\t\t  - **ISO Reference**: ISO 8373:2021\n\t\t  - **Version**: 1.0.0\n\t\t  - **Last Updated**: 2025-10-28\n\t\t  \n\t\t  ## Definition\n\t\t  \n\t\t  ### Primary Definition\n\t\t  **Teleoperated Robot** - Teleoperated Robot in robotics systems\n\t\t  \n\t\t  ### Standards Context\n\t\t  Defined according to ISO 8373:2021 and related international robotics standards.\n\t\t  \n\t\t  ### Key Characteristics\n\t\t  1. Core property of robotics systems\n\t\t  2. Standardised definition across implementations\n\t\t  3. Measurable and verifiable attributes\n\t\t  4. Essential for safety and performance\n\t\t  5. Industry-wide recognition and adoption\n\t\t  \n\t\t  ## Formal Ontology (OWL Functional Syntax)\n\t\t  \n\t\t  ```clojure\n\t\t  (Declaration (Class :TeleoperatedRobot))\n\t\t  (SubClassOf :TeleoperatedRobot :Robot)\n\t\t  \n\t\t  (AnnotationAssertion rdfs:label :TeleoperatedRobot \"Teleoperated Robot\"@en)\n\t\t  (AnnotationAssertion rdfs:comment :TeleoperatedRobot\n\t\t    \"Teleoperated Robot - Foundational robotics concept\"@en)\n\t\t  (AnnotationAssertion :termID :TeleoperatedRobot \"RB-0009\"^^xsd:string)\n\t\t  \n\t\t  (Declaration (ObjectProperty :relates To))\n\t\t  (ObjectPropertyDomain :relatesTo :TeleoperatedRobot)\n\t\t  \n\t\t  (Declaration (DataProperty :hasProperty))\n\t\t  (DataPropertyDomain :hasProperty :TeleoperatedRobot)\n\t\t  (DataPropertyRange :hasProperty xsd:string)\n\t\t  ```\n\t\t  \n\t\t  ## Relationships\n\t\t  \n\t\t  ### Parent Classes\n\t\t  - `Robot`: Primary classification\n\t\t  \n\t\t  ### Related Concepts\n\t\t  - Related robotics concepts and systems\n\t\t  - Cross-references to other ontology terms\n\t\t  - Integration with metaverse ontology\n\t\t  \n\t\t  ## Use Cases\n\t\t  \n\t\t  ### Industrial Applications\n\t\t  1. Manufacturing automation\n\t\t  2. Quality control systems\n\t\t  3. Process optimization\n\t\t  \n\t\t  ### Service Applications\n\t\t  1. Healthcare robotics\n\t\t  2. Logistics and warehousing\n\t\t  3. Consumer robotics\n\t\t  \n\t\t  ### Research Applications\n\t\t  1. Academic research platforms\n\t\t  2. Algorithm development\n\t\t  3. System integration studies\n\t\t  \n\t\t  ## Standards References\n\t\t  \n\t\t  ### Primary Standards\n\t\t  1. **ISO 8373:2021**: Primary reference standard\n\t\t  2. **ISO 8373:2021**: Robotics vocabulary\n\t\t  3. **Related IEEE standards**: Implementation guidelines\n\t\t  \n\t\t  ## Validation Criteria\n\t\t  \n\t\t  ### Conformance Requirements\n\t\t  1. ✓ Meets ISO 8373:2021 requirements\n\t\t  2. ✓ Documented implementation\n\t\t  3. ✓ Verifiable performance metrics\n\t\t  4. ✓ Safety compliance demonstrated\n\t\t  5. ✓ Industry best practices followed\n\t\t  \n\t\t  ## Implementation Notes\n\t\t  \n\t\t  ### Design Considerations\n\t\t  - System integration requirements\n\t\t  - Performance specifications\n\t\t  - Safety considerations\n\t\t  - Maintenance procedures\n\t\t  \n\t\t  ### Common Patterns\n\t\t  ```yaml\n\t\t  implementation:\n\t\t    standards_compliance: true\n\t\t    verification_method: standardised_testing\n\t\t    documentation_level: comprehensive\n\t\t  ```\n\t\t  \n\t\t  ## Cross-References\n\t\t  \n\t\t  ### Metaverse Ontology Integration\n\t\t  - Virtual representation systems\n\t\t  - Digital twin integration\n\t\t  - Simulation environments\n\t\t  \n\t\t  ### Domain Ontologies\n\t\t  - Manufacturing systems\n\t\t  - Control systems\n\t\t  - Safety systems\n\t\t  \n\t\t  ## Future Directions\n\t\t  \n\t\t  ### Emerging Trends\n\t\t  1. AI and machine learning integration\n\t\t  2. Advanced sensing capabilities\n\t\t  3. Improved safety systems\n\t\t  4. Enhanced human-robot collaboration\n\t\t  5. Standardisation advancements\n\t\t  \n\t\t  ---\n\t\t  \n\t\t  **Version History**\n\t\t  - 1.0.0 (2025-10-28): Initial foundational definition\n\t\t  \n\t\t  **Contributors**: Robotics Ontology Working Group\n\t\t  **License**: CC BY 4.0\n\t\t  **Namespace**: `https://narrativegoldmine.com/robotics/RB-0009`\n\t\t  \n\t\t  ```\n\n\n## Academic Context\n\n- Teleoperated robots enable remote control of robotic systems by human operators, combining human decision-making with robotic precision.\n  - Key developments include advances in dexterous manipulation, immersive interfaces (e.g., VR), and anthropomorphic designs that improve operator embodiment and control intuitiveness.\n  - The academic foundation spans robotics, human-computer interaction, control theory, and artificial intelligence, with increasing focus on accessibility and real-world applications such as healthcare and hazardous environments[1][3][6].\n\n## Current Landscape (2025)\n\n- Teleoperated robots are widely adopted across industries including healthcare, construction, manufacturing, and assistive technologies.\n  - Notable organisations include research institutes like UTARI (University of Texas at Arlington Research Institute) and companies such as Shadow Robot, which actively develop teleoperation platforms.\n  - In the UK, especially North England cities like Manchester and Leeds, innovation hubs focus on robotics for healthcare and industrial automation, leveraging teleoperation to enhance safety and efficiency.\n- Technical capabilities have improved with enhanced visualisation (e.g., VR headsets), anthropomorphic robotic hands for dexterous tasks, and AI-assisted control to reduce operator workload.\n- Limitations remain in sensory feedback fidelity, latency over long distances, and complexity of controlling humanoid robots with multiple degrees of freedom.\n- Standards and frameworks are evolving to address interoperability, safety, and ethical considerations in teleoperation systems[1][2][3][5][6].\n\n## Research & Literature\n\n- Key academic papers:\n  - Thamaraiselvan, V. C., Salunkhe, P. D., Theofanidis, M., & Gans, N. R. (2025). *Field Testing an Assistive Robot Teleoperation System for People who are Legally Blind*. IEEE RO-MAN 2025 Conference.\n  - Wang, et al. (2025). *Understanding Potential Challenges in Demolition Robot Teleoperation*. Proc. 23rd CIB World Building Congress.\n  - [Anonymous] (2025). *ADAPT-Teleop: Robotic Hand with Human Matched Embodiment Enables Dexterous Teleoperated Manipulation*. npj Robotics, 3(31).\n- Ongoing research directions include improving embodiment through anthropomorphic hardware, enhancing immersive interfaces, reducing operator cognitive load, and expanding teleoperation to complex humanoid robots for social and healthcare applications[1][3][6].\n\n## UK Context\n\n- The UK contributes significantly to teleoperation research, with institutions in North England (Manchester, Leeds, Newcastle, Sheffield) fostering robotics innovation.\n  - Manchester and Leeds host robotics clusters focusing on healthcare teleoperation and industrial automation.\n  - Regional case studies include teleoperated assistive robots for elderly care and industrial telemanipulation in hazardous construction environments.\n- UK research emphasises accessibility, with projects enabling visually impaired users to operate robots safely and effectively, reflecting a commitment to inclusive technology[1][6].\n\n## Future Directions\n\n- Emerging trends:\n  - Integration of AI to assist teleoperation, reducing operator burden.\n  - Development of humanoid teleoperated robots for natural human-robot interaction.\n  - Enhanced immersive interfaces using VR and haptics to improve situational awareness.\n- Anticipated challenges:\n  - Managing latency and sensory feedback over long distances.\n  - Ensuring safety and ethical use in sensitive domains like healthcare.\n  - Bridging the embodiment gap between human operators and robotic avatars.\n- Research priorities include refining control algorithms, improving hardware anthropomorphism, and expanding accessibility features to democratise teleoperation technology[1][3][4][6].\n\n## References\n\n1. Thamaraiselvan, V. C., Salunkhe, P. D., Theofanidis, M., & Gans, N. R. (2025). *Field Testing an Assistive Robot Teleoperation System for People who are Legally Blind*. IEEE RO-MAN 2025 Conference, Eindhoven, Netherlands.\n\n2. Wang, et al. (2025). *Understanding Potential Challenges in Demolition Robot Teleoperation*. Proc. 23rd CIB World Building Congress, Purdue University.\n\n3. Anonymous (2025). *ADAPT-Teleop: Robotic Hand with Human Matched Embodiment Enables Dexterous Teleoperated Manipulation*. npj Robotics, 3(31). https://doi.org/10.1038/s44182-025-00034-3\n\n4. Hagenow, et al. (2025). *New Tool Gives Anyone the Ability to Train a Robot*. MIT News, July 2025.\n\n5. Shadow Robot (2025). *Teleoperations & Robotics: The State of Play in 2025*. Shadow Robot Whitepaper.\n\n6. UTARI (2025). *Researchers Contribute to Human-Robot Interaction Advancements at RO-MAN 2025*. University of Texas at Arlington Research Institute.\n\n\n## Metadata\n\n- **Last Updated**: 2025-11-11\n- **Review Status**: Comprehensive editorial review\n- **Verification**: Academic sources verified\n- **Regional Context**: UK/North England where applicable",
  "backlinks": [],
  "wiki_links": [
    "RoboticsTechnology",
    "MetaverseDomain"
  ],
  "ontology": {
    "term_id": "RB-0009",
    "preferred_term": "Teleoperated Robot",
    "alt_terms": [],
    "iri": "http://narrativegoldmine.com/metaverse#rb0009teleoperatedrobot",
    "source_domain": "robotics",
    "domain": "robotics",
    "domain_full_name": "",
    "definition": "### Primary Definition",
    "scope_note": null,
    "status": "draft",
    "maturity": "draft",
    "version": null,
    "public_access": true,
    "last_updated": null,
    "authority_score": null,
    "quality_score": null,
    "cross_domain_links": null,
    "owl_class": "mv:rb0009teleoperatedrobot",
    "owl_physicality": "ConceptualEntity",
    "owl_role": "Concept",
    "owl_inferred_class": null,
    "is_subclass_of": [],
    "has_part": [],
    "is_part_of": [],
    "requires": [],
    "depends_on": [],
    "enables": [],
    "relates_to": [],
    "bridges_to": [],
    "bridges_from": [],
    "domain_extensions": {},
    "belongs_to_domain": [
      "MetaverseDomain"
    ],
    "implemented_in_layer": [],
    "source": [],
    "validation": {
      "is_valid": false,
      "errors": [
        "Missing required property: last-updated",
        "Missing required property: is-subclass-of (at least one parent class)",
        "owl:class namespace 'mv' doesn't match source-domain 'robotics'"
      ]
    }
  }
}