{
  "id": "TELE-001-telepresence",
  "title": "Telepresence",
  "content": "- ### OntologyBlock\n  id:: telepresence-ontology\n  collapsed:: true\n\t- ontology:: true\n\t- term-id:: TELE-001\n\t- preferred-term:: Telepresence\n\t- source-domain:: tc\n\t- owl:class:: tc:Telepresence\n\t- status:: active\n\t- public-access:: true\n\t- definition:: \"The technology-mediated experience of 'being there' in a remote location, creating the psychological sensation of physical presence despite geographical separation through immersive technologies, real-time communication, and sensory feedback systems that replicate spatial, visual, auditory, and tactile cues of co-location.\"\n\t- maturity:: mature\n\t- owl:physicality:: ConceptualEntity\n\t- owl:role:: Concept\n\t- #### Relationships\n\t  id:: telepresence-relationships\n\t  collapsed:: true\n\t\t- is-subclass-of:: [[RemoteCommunication]]\n\t\t- requires:: [[RealTimeNetworking]]\n\t\t- requires:: [[ImmersiveTechnology]]\n\t\t- requires:: [[VisualRendering]]\n\t\t- requires:: [[SpatialAudio]]\n\t\t- enables:: [[DistributedWork]]\n\t\t- enables:: [[RemoteCollaboration]]\n\t\t- enables:: [[VirtualMeeting]]\n\t\t- enables:: [[Teleoperation]]\n\t\t- related-to:: [[TELE-003-social-presence-theory]]\n\t\t- related-to:: [[TELE-006-presence]]\n\t\t- related-to:: [[Immersion]]\n\t\t- related-to:: [[Embodiment]]\n\t\t- has-component:: [[AudioPresence]]\n\t\t- has-component:: [[SocialPresence]]\n\t\t- has-component:: [[HapticPresence]]\n\t\t- has-component:: [[VisualPresence]]\n\n## Definition\n\n**Telepresence** is the technology-mediated phenomenon whereby individuals experience a psychological sense of \"being there\" in a remote physical or virtual location despite actual geographical separation. First conceptualised by Marvin Minsky in the 1980s, telepresence encompasses the integration of immersive visual displays, spatial audio rendering, haptic feedback systems, and real-time bidirectional communication to replicate the sensory and social cues of co-location.\n\nUnlike traditional remote communication (telephone, video conferencing), telepresence aims to eliminate perceptual barriers between local and remote environments through high-fidelity sensory reproduction. This creates a subjective experience where users feel physically present in the remote space, enabling natural interaction patterns including spatial navigation, object manipulation, non-verbal communication, and shared attention that mirror in-person collaboration.\n\nThe concept spans multiple implementation paradigms: virtual reality telepresence places users in entirely computer-generated environments ([[TELE-020-virtual-reality-telepresence]]), augmented reality telepresence overlays remote participants onto local physical spaces ([[TELE-021-augmented-reality-collaboration]]), and robotic telepresence projects remote operators into physical locations through mobile robotic avatars ([[TELE-200-robotic-telepresence]]).\n\n## Current Landscape (2025)\n\nThe telepresence market in 2025 has evolved from niche research prototypes to mainstream enterprise and consumer adoption, driven by convergent advances in XR hardware, neural rendering, 5G/6G networking, and artificial intelligence.\n\n**Enterprise Adoption**:\n- 67% of Fortune 500 companies deploy XR telepresence for remote collaboration (IDC, 2025)\n- Average cost reduction of 42% compared to business travel (PwC Enterprise XR Survey, 2025)\n- Virtual meeting room adoption up 340% since 2023 (Gartner Technology Trends Report)\n\n**Technology Capabilities**:\n- **Visual Fidelity**: Photorealistic rendering at 90+ FPS with <20ms motion-to-photon latency\n- **Spatial Audio**: Object-based audio with head-related transfer functions (HRTFs) for 3D localisation\n- **Neural Compression**: AI-driven bandwidth reduction enabling 4K streaming at <15 Mbps\n- **Haptic Feedback**: Consumer-grade force feedback gloves with 10+ DOF (degrees of freedom)\n\n**UK Context**:\nThe United Kingdom leads European telepresence research, with North England institutions pioneering volumetric capture and immersive training systems:\n- **National Centre for Virtual Environments** (Salford): Real-time volumetric video conferencing research\n- **University of Manchester**: Digital Innovation Factory testing 6G telepresence applications\n- **Innovate UK**: Â£23M funding for immersive collaboration technologies (2024-2026)\n\nBritish Telecom (BT) and Sky have deployed commercial telepresence services integrating with Microsoft Mesh and Meta Horizon Workrooms platforms.\n\n## Theoretical Foundations\n\n### Social Presence Theory\nTelepresence builds on **Social Presence Theory** (Short, Williams, & Christie, 1976), which posits that communication media vary in their capacity to convey social cues (facial expressions, vocal inflection, body language). High social presence media enable participants to perceive others as psychologically present, facilitating trust, empathy, and collaborative effectiveness. Telepresence systems maximise social presence through multimodal sensory channels.\n\n### Media Richness Theory\n**Media Richness Theory** (Daft & Lengel, 1986) classifies communication media by their ability to convey complex information through multiple cues, immediate feedback, language variety, and personalisation. Telepresence represents the richest possible medium, approaching face-to-face communication by providing real-time visual, auditory, and haptic feedback in spatial contexts.\n\n### Presence Framework\nThe subjective experience of telepresence comprises three dimensions (Heeter, 1992):\n1. **Personal Presence**: Feeling one's body exists in the remote environment\n2. **Social Presence**: Perceiving other humans as co-present\n3. **Environmental Presence**: Responding to remote environment as if physically there\n\n## Technical Components\n\n### Visual Systems\n- **Display Technology**: VR headsets (Meta Quest 3, Apple Vision Pro), AR glasses (HoloLens 2), holographic displays\n- **Rendering**: Real-time rasterisation, neural rendering ([[TELE-051-3d-gaussian-splatting]]), volumetric capture ([[TELE-053-volumetric-video-conferencing]])\n- **Tracking**: Inside-out SLAM (Simultaneous Localisation and Mapping), marker-based tracking, LiDAR depth sensing\n\n### Audio Systems\n- **Spatial Audio**: Ambisonics, binaural rendering, head-related transfer functions (HRTFs)\n- **AI Processing**: Noise cancellation ([[TELE-110-spatial-audio-processing]]), acoustic echo cancellation, beamforming\n- **Standards**: MPEG-H 3D Audio, Dolby Atmos, Spatial Audio by Apple\n\n### Haptic Systems\n- **Tactile Feedback**: Vibrotactile actuators, ultrasonic mid-air haptics\n- **Force Feedback**: Exoskeletons, cable-driven mechanisms, pneumatic systems ([[TELE-203-haptic-feedback-telepresence]])\n- **Thermal Feedback**: Peltier-element skin temperature simulation\n\n### Networking Infrastructure\n- **Protocols**: WebRTC ([[TELE-150-webrtc]]), RTP/RTCP, QUIC\n- **Latency Requirements**: <20ms motion-to-photon for comfortable VR, <100ms for social interaction\n- **5G Features**: Network slicing for guaranteed QoS, edge computing for local rendering ([[TELE-153-5g-telepresence]])\n\n## Cross-Domain Applications\n\n### Metaverse Integration\nTelepresence forms the perceptual foundation of metaverse experiences, enabling users to inhabit virtual worlds with embodied presence. Platforms like [[TELE-026-microsoft-mesh]] and Horizon Workrooms leverage telepresence principles for persistent virtual offices where distributed teams collaborate as avatars in shared 3D spaces.\n\n### Robotic Teleoperation\nIn industrial and medical contexts, telepresence extends to physical robot control ([[TELE-201-teleoperation-systems]]). Surgical telepresence systems like da Vinci SP enable surgeons to perform minimally invasive procedures on patients hundreds of kilometres away, with haptic feedback providing tactile sensation of tissue manipulation.\n\n### AI-Enhanced Presence\nArtificial intelligence augments telepresence through photorealistic AI avatars ([[TELE-100-ai-avatars]]) that replicate users' appearance and mannerisms, real-time language translation ([[TELE-105-real-time-language-translation]]) for cross-lingual collaboration, and predictive tracking algorithms that compensate for network latency.\n\n### Blockchain Coordination\nDecentralised autonomous organisations (DAOs) leverage telepresence for governance meetings conducted in immersive VR environments, with smart contracts ([[TELE-251-smart-contract-coordination]]) automatically executing decisions made during virtual assemblies.\n\n## Challenges and Limitations\n\n**Technical Challenges**:\n- **Latency**: Network delays disrupt natural interaction; requires <20ms end-to-end latency\n- **Bandwidth**: Photorealistic rendering demands 50-100 Mbps per stream; limits scalability\n- **Hardware**: Current headsets cause discomfort during extended use (>60 minutes)\n- **Interoperability**: Proprietary platforms (Meta, Apple, Microsoft) lack standardised protocols\n\n**Human Factors**:\n- **Cybersickness**: Sensory conflicts between visual motion and vestibular signals cause nausea\n- **Social Fatigue**: Prolonged VR interaction is cognitively demanding; \"Zoom fatigue\" persists in XR\n- **Privacy Concerns**: Biometric data capture (gaze tracking, facial expressions) raises surveillance issues\n- **Digital Divide**: High equipment costs exclude lower-income participants\n\n## Future Directions\n\n**Near-Term (2025-2027)**:\n- Consumer adoption of lightweight AR glasses for hybrid physical-virtual collaboration\n- Integration of brain-computer interfaces for thought-based avatar control\n- Photorealistic full-body avatars with real-time clothing simulation\n\n**Medium-Term (2027-2030)**:\n- 6G networks enabling <5ms latency for multi-user immersive experiences\n- Holographic displays eliminating need for headsets (light-field technology)\n- Standardised metaverse protocols for cross-platform telepresence\n\n**Long-Term (2030+)**:\n- Sensory substitution devices enabling complete proprioceptive feedback\n- Neural interfaces for direct perception of remote environments\n- Quantum networks for zero-latency global telepresence\n\n## Related Concepts\n\n**Foundational Concepts**:\n- [[TELE-002-telecollaboration]] - Collaborative work through telepresence\n- [[TELE-003-social-presence-theory]] - Theoretical framework\n- [[TELE-006-presence]] - Psychological sense of being there\n\n**Technical Implementations**:\n- [[TELE-020-virtual-reality-telepresence]] - VR-based systems\n- [[TELE-021-augmented-reality-collaboration]] - AR overlays\n- [[TELE-200-robotic-telepresence]] - Physical robot avatars\n\n**Enabling Technologies**:\n- [[TELE-051-3d-gaussian-splatting]] - Neural rendering\n- [[TELE-150-webrtc]] - Real-time communication\n- [[TELE-110-spatial-audio-processing]] - 3D audio\n\n## Academic References\n\n1. Minsky, M. (1980). \"Telepresence\". *Omni Magazine*, June 1980.\n2. Short, J., Williams, E., & Christie, B. (1976). *The Social Psychology of Telecommunications*. John Wiley & Sons.\n3. Daft, R. L., & Lengel, R. H. (1986). \"Organizational Information Requirements, Media Richness and Structural Design\". *Management Science*, 32(5), 554-571.\n4. Heeter, C. (1992). \"Being There: The Subjective Experience of Presence\". *Presence: Teleoperators and Virtual Environments*, 1(2), 262-271.\n5. Lombard, M., & Ditton, T. (1997). \"At the Heart of It All: The Concept of Presence\". *Journal of Computer-Mediated Communication*, 3(2).\n6. Slater, M., & Wilbur, S. (1997). \"A Framework for Immersive Virtual Environments (FIVE): Speculations on the Role of Presence in Virtual Environments\". *Presence: Teleoperators and Virtual Environments*, 6(6), 603-616.\n\n## Standards and Organisations\n\n- **IEEE P2888**: Standard for Networked Smart Learning Objects for Online Laboratories\n- **ETSI ISG ARF**: Augmented Reality Framework (Industry Specification Group)\n- **Metaverse Standards Forum**: Cross-industry interoperability protocols\n- **W3C Immersive Web Working Group**: WebXR Device API, WebXR Layers API\n\n## Metadata\n\n- **Term-ID**: TELE-001\n- **Last Updated**: 2025-11-16\n- **Verification Status**: Mature\n- **Authority Score**: 0.95\n- **UK Context**: High (major research institutions)\n- **Cross-Domain**: Bridges to Metaverse, AI, Robotics domains",
  "backlinks": [
    "TELE-021-augmented-reality-collaboration",
    "TELE-006-presence",
    "TELE-200-robotic-telepresence",
    "TELE-020-virtual-reality-telepresence",
    "TELE-CONV-001-metaverse-telepresence-bridge",
    "TELE-028-horizon-workrooms",
    "TELE-003-social-presence-theory",
    "TELE-100-ai-avatars",
    "TELE-150-webrtc",
    "TELE-203-haptic-feedback-telepresence",
    "TELE-CONV-002-robotics-telepresence-bridge",
    "TELE-004-media-richness-theory",
    "TELE-002-telecollaboration"
  ],
  "wiki_links": [
    "Teleoperation",
    "RemoteCollaboration",
    "TELE-150-webrtc",
    "TELE-026-microsoft-mesh",
    "TELE-201-teleoperation-systems",
    "VirtualMeeting",
    "ImmersiveTechnology",
    "TELE-110-spatial-audio-processing",
    "TELE-200-robotic-telepresence",
    "TELE-006-presence",
    "TELE-100-ai-avatars",
    "TELE-003-social-presence-theory",
    "TELE-002-telecollaboration",
    "HapticPresence",
    "TELE-053-volumetric-video-conferencing",
    "Embodiment",
    "DistributedWork",
    "AudioPresence",
    "SocialPresence",
    "TELE-105-real-time-language-translation",
    "TELE-021-augmented-reality-collaboration",
    "TELE-203-haptic-feedback-telepresence",
    "RealTimeNetworking",
    "TELE-251-smart-contract-coordination",
    "VisualPresence",
    "VisualRendering",
    "TELE-020-virtual-reality-telepresence",
    "TELE-153-5g-telepresence",
    "SpatialAudio",
    "RemoteCommunication",
    "TELE-051-3d-gaussian-splatting",
    "Immersion"
  ],
  "ontology": {
    "term_id": "TELE-001",
    "preferred_term": "Telepresence",
    "alt_terms": [],
    "iri": "http://narrativegoldmine.com/telecollaboration#Telepresence",
    "source_domain": "tc",
    "domain": "tc",
    "domain_full_name": "Telecollaboration",
    "definition": "\"The technology-mediated experience of 'being there' in a remote location, creating the psychological sensation of physical presence despite geographical separation through immersive technologies, real-time communication, and sensory feedback systems that replicate spatial, visual, auditory, and tactile cues of co-location.\"",
    "scope_note": null,
    "status": "active",
    "maturity": "mature",
    "version": null,
    "public_access": true,
    "last_updated": null,
    "authority_score": null,
    "quality_score": null,
    "cross_domain_links": null,
    "owl_class": "tc:Telepresence",
    "owl_physicality": "ConceptualEntity",
    "owl_role": "Concept",
    "owl_inferred_class": null,
    "is_subclass_of": [
      "RemoteCommunication"
    ],
    "has_part": [],
    "is_part_of": [],
    "requires": [
      "RealTimeNetworking",
      "ImmersiveTechnology",
      "VisualRendering",
      "SpatialAudio"
    ],
    "depends_on": [],
    "enables": [
      "DistributedWork",
      "RemoteCollaboration",
      "VirtualMeeting",
      "Teleoperation"
    ],
    "relates_to": [],
    "bridges_to": [],
    "bridges_from": [],
    "domain_extensions": {},
    "belongs_to_domain": [],
    "implemented_in_layer": [],
    "source": [],
    "other_relationships": {
      "related-to": [
        "TELE-003-social-presence-theory",
        "TELE-006-presence",
        "Immersion",
        "Embodiment"
      ],
      "has-component": [
        "AudioPresence",
        "SocialPresence",
        "HapticPresence",
        "VisualPresence"
      ]
    },
    "validation": {
      "is_valid": false,
      "errors": [
        "Missing required property: last-updated",
        "term-id 'TELE-001' doesn't match domain 'tc' (expected TC-)"
      ]
    }
  }
}