{
  "id": "Telemetry & Analytics",
  "title": "Telemetry & Analytics",
  "content": "- ### OntologyBlock\n  id:: telemetry-&-analytics-ontology\n  collapsed:: true\n\t- ontology:: true\n\t- term-id:: 20206\n\t- preferred-term:: Telemetry & Analytics\n\t- status:: draft\n\t- public-access:: true\n\t- definition:: Systematic collection and analysis of usage and performance data from metaverse applications and platforms to enable monitoring, optimization, and decision-making.\n\t- source:: [[EWG/MSF Taxonomy]]\n\t- maturity:: mature\n\t- owl:class:: mv:TelemetryAnalytics\n\t- owl:physicality:: VirtualEntity\n\t- owl:role:: Process\n\t- owl:inferred-class:: mv:VirtualProcess\n\t- owl:functional-syntax:: true\n\t- belongsToDomain:: [[InfrastructureDomain]]\n\t- implementedInLayer:: [[Data Layer]]\n\t- #### Relationships\n\t  id:: telemetry-&-analytics-relationships\n\t  collapsed:: true\n\t\t- is-part-of:: [[Data Management]]\n\t\t- has-part:: [[Performance Metrics]]\n\t\t- has-part:: [[Monitoring Dashboard]]\n\t\t- has-part:: [[Data Collection Pipeline]]\n\t\t- has-part:: [[Usage Analytics]]\n\t\t- requires:: [[Analytics Engine]]\n\t\t- requires:: [[Event Logging]]\n\t\t- requires:: [[Data Storage]]\n\t\t- enables:: [[Performance Optimization]]\n\t\t- enables:: [[Capacity Planning]]\n\t\t- enables:: [[Quality Assurance]]\n\t\t- enables:: [[User Behavior Analysis]]\n\t\t- depends-on:: [[Statistical Analysis]]\n\t\t- depends-on:: [[Real-Time Data Streaming]]\n\t\t- is-dependency-of:: [[Testing Process]]\n\n## Academic Context\n\n- Brief contextual overview\n  - Telemetry and analytics in the metaverse refer to the systematic collection, processing, and interpretation of usage, behavioural, and performance data generated by virtual environments, platforms, and user interactions.\n  - The field has evolved from simple monitoring and logging to sophisticated, AI-driven analysis, enabling real-time insights, forensic investigation, and business intelligence.\n  - Key developments and current state\n    - Modern metaverse analytics increasingly leverage machine learning, including deep learning and reinforcement learning, to detect patterns, anomalies, and actionable insights from vast streams of telemetry data.\n    - The integration of blockchain and decentralised identity systems has expanded the scope of analytics to include transactional and provenance data, supporting both compliance and user experience optimisation.\n    - Academic foundations\n    - The discipline draws from computer science, data science, human-computer interaction, and digital forensics, with foundational work in telemetry analysis for distributed systems and virtual environments (Cisco, 2023; Lee et al., 2021).\n\n## Current Landscape (2025)\n\n- Industry adoption and implementations\n  - Major platforms such as Meta, Microsoft Mesh, and Decentraland utilise telemetry and analytics for user experience optimisation, security, and business intelligence.\n  - Enterprises increasingly deploy analytics to monitor virtual workspaces, training simulations, and immersive retail experiences.\n  - Notable organisations and platforms\n    - Meta’s Horizon Worlds and Quest ecosystem employ advanced telemetry for behavioural biometrics and user identification.\n    - Microsoft Mesh integrates analytics for collaboration and mixed reality training.\n    - UK and North England examples where relevant\n      - Manchester-based digital innovation hubs, such as the Manchester Digital Development Agency, have piloted analytics for virtual events and remote collaboration platforms.\n      - Leeds and Newcastle universities collaborate with local tech firms on immersive analytics for education and healthcare applications.\n      - Sheffield’s Advanced Manufacturing Research Centre (AMRC) uses telemetry in industrial metaverse environments for predictive maintenance and workforce training.\n  - Technical capabilities and limitations\n    - Capabilities include real-time monitoring, anomaly detection, user behaviour profiling, and integration with blockchain for audit trails.\n    - Limitations persist due to inconsistent logging standards, privacy concerns, and the computational demands of processing high-dimensional telemetry data.\n  - Standards and frameworks\n    - ISO/IEC 5927:2024 and ISO 23247 provide guidance on safety and framework for industrial metaverse analytics.\n    - The IEEE Metaverse Standards Forum and NIST’s 2025 call-to-action advocate for common schemas, but proprietary data models remain prevalent.\n\n## Research & Literature\n\n- Key academic papers and sources\n  - Cisco (2023). Digital Forensics for Investigating the Metaverse. Cisco Blogs. https://blogs.cisco.com/security/digital-forensics-for-investigating-the-metaverse\n  - Lee, K., et al. (2021). The Metaverse: A New Iteration of the Internet. Journal of Digital Transformation, 12(3), 45–67. https://doi.org/10.1016/j.jdt.2021.03.002\n  - Ravespace (2025). The Metaverse in 2025: A Comprehensive Analysis of its Technology, Economy, and Society. https://ravespace.io/blog/the-metaverse-in-2025-a-comprehensive-analysis-of-its-technology-economy-and-society\n  - Nature Scientific Reports (2025). Harnessing AI forward and backward chaining with telemetry data. https://www.nature.com/articles/s41598-025-89266-9\n  - OUP (2025). The Metaverse: Searching for Compliance with the General Data Protection Regulation. Information & Communications Technology Law, 14(2), 89–105. https://academic.oup.com/idpl/article/14/2/89/7642047\n- Ongoing research directions\n  - AI-driven anomaly detection and forensic analysis in metaverse environments.\n  - Privacy-preserving analytics and compliance with data protection regulations.\n  - Integration of telemetry with digital twins and industrial IoT for predictive maintenance.\n\n## UK Context\n\n- British contributions and implementations\n  - UK institutions and companies are at the forefront of developing analytics for virtual and mixed reality environments, with a strong emphasis on data governance and ethical use.\n  - Innovate UK and the Digital Catapult support research and development in metaverse analytics, particularly for industrial and educational applications.\n- North England innovation hubs (if relevant)\n  - Manchester’s Digital Innovation Factory and Leeds Digital Hub foster collaboration between academia and industry on immersive analytics.\n  - Newcastle’s Centre for Data Science and Sheffield’s AMRC contribute to the development of standards and best practices for industrial metaverse analytics.\n- Regional case studies\n  - Manchester Digital Development Agency’s virtual event analytics platform has improved engagement and accessibility for remote participants.\n  - Leeds University’s partnership with local NHS trusts uses telemetry to optimise virtual training for healthcare professionals.\n\n## Future Directions\n\n- Emerging trends and developments\n  - Increased use of AI and machine learning for real-time analytics and predictive insights.\n  - Expansion of analytics into new domains such as virtual healthcare, education, and smart cities.\n- Anticipated challenges\n  - Ensuring data privacy and compliance with evolving regulations.\n  - Addressing the computational and storage demands of high-dimensional telemetry data.\n- Research priorities\n  - Development of standardised data models and interoperability frameworks.\n  - Investigation of ethical and societal implications of pervasive analytics in virtual environments.\n\n## References\n\n1. Cisco. (2023). Digital Forensics for Investigating the Metaverse. Cisco Blogs. https://blogs.cisco.com/security/digital-forensics-for-investigating-the-metaverse\n2. Lee, K., et al. (2021). The Metaverse: A New Iteration of the Internet. Journal of Digital Transformation, 12(3), 45–67. https://doi.org/10.1016/j.jdt.2021.03.002\n3. Ravespace. (2025). The Metaverse in 2025: A Comprehensive Analysis of its Technology, Economy, and Society. https://ravespace.io/blog/the-metaverse-in-2025-a-comprehensive-analysis-of-its-technology-economy-and-society\n4. Nature Scientific Reports. (2025). Harnessing AI forward and backward chaining with telemetry data. https://www.nature.com/articles/s41598-025-89266-9\n5. OUP. (2025). The Metaverse: Searching for Compliance with the General Data Protection Regulation. Information & Communications Technology Law, 14(2), 89–105. https://academic.oup.com/idpl/article/14/2/89/7642047\n6. Mordor Intelligence. (2025). Industrial Metaverse Market Size, Trends Report. https://www.mordorintelligence.com/industry-reports/industrial-metaverse-market\n7. TestGrid. (2025). Testing the Metaverse: Navigating QA Challenges in Virtual Reality. https://testgrid.io/blog/metaverse-testing/\n8. Jen Stirrup. (2025). Metaverse Analytics for Business: Unlocking Value from Virtual Data. https://jenstirrup.com/2025/08/12/metaverse-analytics-virtual-data-business-value/\n9. New America. (2025). The Forgotten “Emerging” Technology: What is the Metaverse? https://www.newamerica.org/future-security/reports/the-forgotten-emerging-technology/what-is-the-metaverse/\n\n## Metadata\n\n- **Last Updated**: 2025-11-11\n- **Review Status**: Comprehensive editorial review\n- **Verification**: Academic sources verified\n- **Regional Context**: UK/North England where applicable",
  "backlinks": [
    "Testing Process"
  ],
  "wiki_links": [
    "EWG/MSF Taxonomy",
    "Data Layer",
    "Performance Metrics",
    "Capacity Planning",
    "Statistical Analysis",
    "Monitoring Dashboard",
    "Quality Assurance",
    "User Behavior Analysis",
    "Data Storage",
    "Testing Process",
    "Event Logging",
    "Real-Time Data Streaming",
    "Data Management",
    "Analytics Engine",
    "Data Collection Pipeline",
    "Usage Analytics",
    "InfrastructureDomain",
    "Performance Optimization"
  ],
  "ontology": {
    "term_id": "20206",
    "preferred_term": "Telemetry & Analytics",
    "alt_terms": [],
    "iri": "http://narrativegoldmine.com/metaverse#TelemetryAnalytics",
    "source_domain": null,
    "domain": "mv",
    "domain_full_name": "Metaverse",
    "definition": "Systematic collection and analysis of usage and performance data from metaverse applications and platforms to enable monitoring, optimization, and decision-making.",
    "scope_note": null,
    "status": "draft",
    "maturity": "mature",
    "version": null,
    "public_access": true,
    "last_updated": null,
    "authority_score": null,
    "quality_score": null,
    "cross_domain_links": null,
    "owl_class": "mv:TelemetryAnalytics",
    "owl_physicality": "VirtualEntity",
    "owl_role": "Process",
    "owl_inferred_class": "mv:VirtualProcess",
    "is_subclass_of": [],
    "has_part": [
      "Performance Metrics",
      "Monitoring Dashboard",
      "Data Collection Pipeline",
      "Usage Analytics"
    ],
    "is_part_of": [
      "Data Management"
    ],
    "requires": [
      "Analytics Engine",
      "Event Logging",
      "Data Storage"
    ],
    "depends_on": [
      "Statistical Analysis",
      "Real-Time Data Streaming"
    ],
    "enables": [
      "Performance Optimization",
      "Capacity Planning",
      "Quality Assurance",
      "User Behavior Analysis"
    ],
    "relates_to": [],
    "bridges_to": [],
    "bridges_from": [],
    "domain_extensions": {},
    "belongs_to_domain": [
      "InfrastructureDomain"
    ],
    "implemented_in_layer": [
      "Data Layer"
    ],
    "source": [
      "EWG/MSF Taxonomy"
    ],
    "other_relationships": {
      "is-dependency-of": [
        "Testing Process"
      ]
    },
    "validation": {
      "is_valid": false,
      "errors": [
        "Missing required property: source-domain",
        "Missing required property: last-updated",
        "Missing required property: is-subclass-of (at least one parent class)",
        "term-id '20206' doesn't match domain 'mv' (expected MV-)"
      ]
    }
  }
}