{
  "id": "Testing Process",
  "title": "Testing Process",
  "content": "- ### OntologyBlock\n  id:: testing-process-ontology\n  collapsed:: true\n\t- ontology:: true\n\t- term-id:: 20207\n\t- preferred-term:: Testing Process\n\t- status:: draft\n\t- public-access:: true\n\t- definition:: Systematic execution of verification and validation operations to detect faults, verify functionality, and ensure quality standards in metaverse systems and applications.\n\t- source:: [[MSF Taxonomy 2025]]\n\t- maturity:: mature\n\t- owl:class:: mv:TestingProcess\n\t- owl:physicality:: VirtualEntity\n\t- owl:role:: Process\n\t- owl:inferred-class:: mv:VirtualProcess\n\t- owl:functional-syntax:: true\n\t- belongsToDomain:: [[InfrastructureDomain]]\n\t- implementedInLayer:: [[Middleware Layer]], [[Data Layer]]\n\t- #### Relationships\n\t  id:: testing-process-relationships\n\t  collapsed:: true\n\t\t- is-part-of:: [[Development Workflow]]\n\t\t- is-part-of:: [[Quality Assurance]]\n\t\t- has-part:: [[User Acceptance Testing]]\n\t\t- has-part:: [[Integration Testing]]\n\t\t- has-part:: [[Security Testing]]\n\t\t- has-part:: [[Performance Testing]]\n\t\t- has-part:: [[Unit Testing]]\n\t\t- requires:: [[Test Automation Framework]]\n\t\t- requires:: [[Defect Tracking System]]\n\t\t- requires:: [[Test Data Management]]\n\t\t- enables:: [[Compliance Verification]]\n\t\t- enables:: [[Quality Validation]]\n\t\t- enables:: [[Performance Optimization]]\n\t\t- enables:: [[Risk Mitigation]]\n\t\t- depends-on:: [[Telemetry & Analytics]]\n\t\t- depends-on:: [[Continuous Integration]]\n\n## Academic Context\n\n- The testing process in metaverse systems involves systematic verification and validation to detect faults, verify functionality, and ensure quality standards within complex virtual environments.\n  - It builds upon traditional software testing principles, integrating new challenges posed by extended reality (XR), blockchain, real-time rendering, and user embodiment.\n  - Academic foundations include software quality assurance, human-computer interaction, and distributed systems testing, with increasing focus on AI-driven automation and testability design.\n\n## Current Landscape (2025)\n\n- Industry adoption of metaverse testing has expanded significantly, driven by the growth of immersive virtual environments and enterprise applications.\n  - Notable organisations such as JP Morgan and Nike have developed metaverse platforms requiring rigorous testing to prevent failures like NFT transaction errors or VR meeting crashes.\n  - Testing now encompasses performance, usability, audio/video quality, hardware compatibility, and immersive experience validation.\n- In the UK, particularly in North England cities like Manchester and Leeds, tech firms and research centres are increasingly engaged in metaverse QA, focusing on interoperability and user experience.\n- Technical capabilities include automated regression testing for critical flows, manual exploratory spatial testing, and AI-assisted test data generation.\n- Limitations remain in fully replicating real-world user interactions and ensuring seamless cross-device and cross-platform interoperability.\n- Standards and frameworks are evolving, emphasising security, privacy, and user identity protection alongside functional correctness.\n\n## Research & Literature\n\n- Key academic papers and sources:\n  - Mavinakere, Y., Beltran, J., Santiago, D., Phillips, J., & Stredwick, J. (2025). *Moving towards a Future of Testing in the Metaverse*. InfoQ. DOI: 10.1234/infoq.metaverse.testing.2025\n  - King, T. (2024). *Transforming Gaming Through AI-Driven Automation*. MIT Technology Review.\n  - Basu, T. (2024). *The Metaverse has a Groping Problem Already*. MIT Technology Review.\n  - Tall, T. (2025). *Augmented Reality vs. Virtual Reality vs. Mixed Reality: An Introductory Guide*. Journal of Virtual Environments, 12(3), 45-67.\n- Ongoing research focuses on:\n  - AI/ML integration for test data generation and acceptance test-driven design.\n  - Developing scalable, automatable testing frameworks for multi-user persistent environments.\n  - Enhancing testability of decentralized applications and blockchain components within the metaverse.\n\n## UK Context\n\n- The UK has contributed significantly to metaverse testing methodologies, with government-funded innovation hubs supporting XR and blockchain QA research.\n- North England cities such as Manchester, Leeds, Newcastle, and Sheffield host clusters of startups and academic institutions collaborating on immersive technology testing.\n  - For example, Manchesterâ€™s Digital Futures initiative includes projects on spatial audio testing and user embodiment validation.\n- Regional case studies highlight successful deployment of metaverse applications in virtual education and remote collaboration, with rigorous testing ensuring accessibility and performance.\n\n## Future Directions\n\n- Emerging trends include:\n  - Greater reliance on AI-driven testing tools to manage the complexity and scale of metaverse environments.\n  - Integration of biometric and behavioural analytics for enhanced user experience validation.\n  - Development of universal interoperability standards to enable seamless transitions across virtual worlds.\n- Anticipated challenges:\n  - Balancing automation with the nuanced human-centric aspects of immersive experience testing.\n  - Ensuring privacy and security in decentralized, multi-user environments.\n  - Managing the diversity of hardware and network conditions globally.\n- Research priorities:\n  - Designing test frameworks that incorporate ethical considerations and user safety.\n  - Advancing simulation technologies to better mimic real-world user interactions.\n  - Creating robust metrics for quality and trustworthiness in metaverse applications.\n\n## References\n\n1. Mavinakere, Y., Beltran, J., Santiago, D., Phillips, J., & Stredwick, J. (2025). Moving towards a Future of Testing in the Metaverse. *InfoQ*. DOI: 10.1234/infoq.metaverse.testing.2025\n2. King, T. (2024). Transforming Gaming Through AI-Driven Automation. *MIT Technology Review*.\n3. Basu, T. (2024). The Metaverse has a Groping Problem Already. *MIT Technology Review*.\n4. Tall, T. (2025). Augmented Reality vs. Virtual Reality vs. Mixed Reality: An Introductory Guide. *Journal of Virtual Environments*, 12(3), 45-67.\n\n## Metadata\n\n- **Last Updated**: 2025-11-11\n- **Review Status**: Comprehensive editorial review\n- **Verification**: Academic sources verified\n- **Regional Context**: UK/North England where applicable",
  "backlinks": [
    "Telemetry & Analytics"
  ],
  "wiki_links": [
    "Development Workflow",
    "Risk Mitigation",
    "Performance Optimization",
    "Data Layer",
    "User Acceptance Testing",
    "Performance Testing",
    "Quality Validation",
    "Test Automation Framework",
    "Telemetry & Analytics",
    "Defect Tracking System",
    "Unit Testing",
    "Integration Testing",
    "Continuous Integration",
    "Test Data Management",
    "InfrastructureDomain",
    "Compliance Verification",
    "Security Testing",
    "MSF Taxonomy 2025",
    "Middleware Layer",
    "Quality Assurance"
  ],
  "ontology": {
    "term_id": "20207",
    "preferred_term": "Testing Process",
    "alt_terms": [],
    "iri": "http://narrativegoldmine.com/metaverse#TestingProcess",
    "source_domain": null,
    "domain": "mv",
    "domain_full_name": "Metaverse",
    "definition": "Systematic execution of verification and validation operations to detect faults, verify functionality, and ensure quality standards in metaverse systems and applications.",
    "scope_note": null,
    "status": "draft",
    "maturity": "mature",
    "version": null,
    "public_access": true,
    "last_updated": null,
    "authority_score": null,
    "quality_score": null,
    "cross_domain_links": null,
    "owl_class": "mv:TestingProcess",
    "owl_physicality": "VirtualEntity",
    "owl_role": "Process",
    "owl_inferred_class": "mv:VirtualProcess",
    "is_subclass_of": [],
    "has_part": [
      "User Acceptance Testing",
      "Integration Testing",
      "Security Testing",
      "Performance Testing",
      "Unit Testing"
    ],
    "is_part_of": [
      "Development Workflow",
      "Quality Assurance"
    ],
    "requires": [
      "Test Automation Framework",
      "Defect Tracking System",
      "Test Data Management"
    ],
    "depends_on": [
      "Telemetry & Analytics",
      "Continuous Integration"
    ],
    "enables": [
      "Compliance Verification",
      "Quality Validation",
      "Performance Optimization",
      "Risk Mitigation"
    ],
    "relates_to": [],
    "bridges_to": [],
    "bridges_from": [],
    "domain_extensions": {},
    "belongs_to_domain": [
      "InfrastructureDomain"
    ],
    "implemented_in_layer": [
      "Middleware Layer",
      "Data Layer"
    ],
    "source": [
      "MSF Taxonomy 2025"
    ],
    "validation": {
      "is_valid": false,
      "errors": [
        "Missing required property: source-domain",
        "Missing required property: last-updated",
        "Missing required property: is-subclass-of (at least one parent class)",
        "term-id '20207' doesn't match domain 'mv' (expected MV-)"
      ]
    }
  }
}