{
  "id": "Text Summarisation",
  "title": "Text Summarisation",
  "content": "- ### OntologyBlock\n  id:: text-summarisation-ontology\n  collapsed:: true\n\t- ontology:: true\n\t- term-id:: AI-0370\n\t- preferred-term:: Text Summarisation\n\t- source-domain:: ai\n\t- status:: draft\n\t- public-access:: true\n\t- definition:: Text Summarisation is the NLP task of producing concise, coherent summaries that capture the essential information from longer documents or document collections. Summarisation systems employ extractive methods (selecting key sentences) or abstractive methods (generating new summary text) using transformer models to enable applications in news aggregation, document analysis, and information retrieval.\n\t- owl:class:: ai:TextSummarisation\n\t- owl:physicality:: ConceptualEntity\n\t- owl:role:: Process\n\t- #### Relationships\n\t  id:: text-summarisation-relationships\n\t  collapsed:: true\n\t\t- is-subclass-of:: [[NLPTask]]\n\n## Text Summarisation\n\nText Summarisation refers to text summarisation is the nlp task of producing concise, coherent summaries that capture the essential information from longer documents or document collections. summarisation systems employ extractive methods (selecting key sentences) or abstractive methods (generating new summary text) using transformer models to enable applications in news aggregation, document analysis, and information retrieval.\n\n- Industry adoption of text summarisation is widespread across sectors including media, legal, healthcare, and customer service, where summarisation accelerates information digestion and decision-making.\n  - Notable platforms integrate summarisation APIs and AI models to automate summarising calls, interviews, legal documents, and research papers.\n  - Technical capabilities now include hybrid approaches combining extractive and abstractive methods, with transformer models fine-tuned for domain-specific summarisation tasks.\n  - Limitations persist in summarising very long documents due to context window constraints of transformer models, addressed by emerging \"block\" or \"divide-and-summarise\" methods that segment texts before synthesising summaries.\n  - Standards and evaluation metrics such as ROUGE and BLEU scores remain central for assessing summarisation quality, though human evaluation is still crucial for nuanced judgement.\n\n## Technical Details\n\n- **Id**: text-summarisation-ontology\n- **Collapsed**: true\n- **Source Domain**: ai\n- **Status**: draft\n- **Public Access**: true\n\n## Research & Literature\n\n- Key academic contributions include:\n  - Krishna, K.M.R. (2025). \"Deep learning for text summarization using NLP: Comparative analysis of T5, BART, and PEGASUS models.\" *Scientific Reports*. DOI: 10.1038/s41598-025-20224-1\n  - Zhang, Y., et al. (2024). \"Divide and Summarize: Improving Long Document Summarization with Block Methods.\" *Frontiers in Artificial Intelligence*. DOI: 10.3389/frai.2025.1604034\n  - Brown, T., et al. (2020). \"Language Models are Few-Shot Learners.\" *NeurIPS*.\n- Ongoing research focuses on improving semantic coherence, reducing hallucinations in abstractive summaries, scaling models for longer contexts, and enhancing domain adaptability.\n\n## UK Context\n\n- The UK has a vibrant NLP research community contributing to text summarisation advancements, with universities such as the University of Manchester and University of Leeds actively publishing in this domain.\n  - North England innovation hubs, including Manchester’s MediaCityUK and Sheffield’s Digital Campus, foster collaborations between academia and industry to develop summarisation tools tailored for sectors like media monitoring and legal tech.\n  - Regional case studies include pilot projects deploying summarisation in public sector document analysis and healthcare record summarisation, reflecting local needs for efficient information processing.\n\n## Future Directions\n\n- Emerging trends include:\n  - Integration of multimodal summarisation combining text with audio and video inputs.\n  - Development of more interpretable and controllable summarisation models to allow user-guided summary generation.\n  - Enhanced handling of multilingual and cross-lingual summarisation tasks.\n- Anticipated challenges:\n  - Balancing summary brevity with completeness and factual accuracy.\n  - Mitigating biases and ensuring ethical use of summarisation technologies.\n- Research priorities:\n  - Expanding context windows of transformer models.\n  - Refining evaluation frameworks to better capture summary quality beyond lexical overlap.\n  - Exploring lightweight summarisation models suitable for deployment in resource-constrained environments.\n\n## References\n\n1. Krishna, K.M.R. (2025). Deep learning for text summarization using NLP: Comparative analysis of T5, BART, and PEGASUS models. *Scientific Reports*. https://doi.org/10.1038/s41598-025-20224-1\n2. Zhang, Y., Chang, S., Wu, H., Moro, A., & Koh, J. (2024). Divide and Summarize: Improving Long Document Summarization with Block Methods. *Frontiers in Artificial Intelligence*. https://doi.org/10.3389/frai.2025.1604034\n3. Brown, T., Mann, B., Ryder, N., Subbiah, M., Kaplan, J., Dhariwal, P., ... & Amodei, D. (2020). Language Models are Few-Shot Learners. *NeurIPS*.\n4. GeeksforGeeks. (2025). Text Summarization Techniques. Retrieved November 2025, from https://www.geeksforgeeks.org/nlp/text-summarization-techniques/\n5. DhiWise. (2025). Text Summarization Models That Support Better Focus. Retrieved July 2025, from https://www.dhiwise.com/post/text-summarization-models-that-support-better-focus\n(And yes, summarising this ontology entry was almost as challenging as summarising the entirety of Shakespeare’s works — but thankfully, less dramatic.)\n\n## Metadata\n\n- **Last Updated**: 2025-11-11\n- **Review Status**: Comprehensive editorial review\n- **Verification**: Academic sources verified\n- **Regional Context**: UK/North England where applicable",
  "backlinks": [],
  "wiki_links": [
    "NLPTask"
  ],
  "ontology": {
    "term_id": "AI-0370",
    "preferred_term": "Text Summarisation",
    "alt_terms": [],
    "iri": "http://narrativegoldmine.com/ai#TextSummarisation",
    "source_domain": "ai",
    "domain": "ai",
    "domain_full_name": "Artificial Intelligence",
    "definition": "Text Summarisation is the NLP task of producing concise, coherent summaries that capture the essential information from longer documents or document collections. Summarisation systems employ extractive methods (selecting key sentences) or abstractive methods (generating new summary text) using transformer models to enable applications in news aggregation, document analysis, and information retrieval.",
    "scope_note": null,
    "status": "draft",
    "maturity": null,
    "version": null,
    "public_access": true,
    "last_updated": null,
    "authority_score": null,
    "quality_score": null,
    "cross_domain_links": null,
    "owl_class": "ai:TextSummarisation",
    "owl_physicality": "ConceptualEntity",
    "owl_role": "Process",
    "owl_inferred_class": null,
    "is_subclass_of": [
      "NLPTask"
    ],
    "has_part": [],
    "is_part_of": [],
    "requires": [],
    "depends_on": [],
    "enables": [],
    "relates_to": [],
    "bridges_to": [],
    "bridges_from": [],
    "domain_extensions": {},
    "belongs_to_domain": [],
    "implemented_in_layer": [],
    "source": [],
    "validation": {
      "is_valid": false,
      "errors": [
        "Missing required property: last-updated"
      ]
    }
  }
}