{
  "id": "Tokenisation",
  "title": "Tokenisation",
  "content": "- ### OntologyBlock\n  id:: tokenisation-ontology\n  collapsed:: true\n\t- ontology:: true\n\t- term-id:: AI-0231\n\t- preferred-term:: Tokenisation\n\t- source-domain:: metaverse\n\t- status:: draft\n\t- public-access:: true\n\n\n\n\n### OWL Classification\n\t- owl:class:: mv:Tokenisation\n\t- owl:physicality:: ConceptualEntity\n\t- owl:role:: Concept\n\n### Domain & Architecture\n\t- belongsToDomain:: [[MetaverseDomain]]\n\t- maturity:: draft\n\n### Relationships\n\n## OWL Formal Semantics\n\n```clojure\n;; OWL Functional Syntax\n\n(Declaration (Class :Tokenisation))\n\n;; Annotations\n(AnnotationAssertion rdfs:label :Tokenisation \"Tokenisation\"@en)\n(AnnotationAssertion rdfs:comment :Tokenisation \"The process of breaking text into discrete units (tokens) that can be processed by neural networks, ranging from characters to subwords to whole words.\"@en)\n\n;; Data Properties\n(AnnotationAssertion dcterms:identifier :Tokenisation \"AI-0231\"^^xsd:string)\n(DataPropertyAssertion :isAITechnology :Tokenisation \"true\"^^xsd:boolean)\n```\n\n## Characteristics\n\n- **Text Segmentation**: Breaks continuous text into processable units\n- **Vocabulary Construction**: Creates finite set of tokens\n- **Multiple Granularities**: Character, subword, or word-level\n- **Language Dependency**: Different strategies for different languages\n\n## Academic Foundations\n\n**Primary Source**: Multiple sources; comprehensive comparison in arXiv:2411.17669 (2024)\n\n**Impact**: Significantly affects model performance, vocabulary size, and ability to handle rare words and out-of-vocabulary terms.\n\n## Technical Context\n\nTokenisation is a fundamental preprocessing step that significantly impacts model performance and vocabulary size. Modern approaches use subword tokenisation (BPE, WordPiece, SentencePiece) to balance vocabulary size with the ability to represent rare words.\n\n## Ontological Relationships\n\n- **Broader Term**: Natural Language Processing Technique\n- **Related Terms**: Subword Tokenisation, Byte-Pair Encoding, WordPiece, Vocabulary\n- **Narrower Terms**: Character Tokenisation, Word Tokenisation, Subword Tokenisation\n\n## Usage Context\n\n\"Tokenisation is a fundamental preprocessing step that significantly impacts model performance and vocabulary size.\"\n\n## References\n\n- Mielke et al. (2021). \"Between words and characters: A Brief History of Open-Vocabulary Modelling and Tokenization in NLP\". arXiv:2112.10508\n- Comparison study: arXiv:2411.17669 (2024)\n\n---\n\n*Ontology Term managed by AI-Grounded Ontology Working Group*\n*UK English Spelling Standards Applied*\n\t- maturity:: draft\n\t- owl:class:: mv:Tokenisation\n\t- owl:physicality:: ConceptualEntity\n\t- owl:role:: Concept\n\t- is-subclass-of:: [[ArtificialIntelligence]]\n\t- belongsToDomain:: [[MetaverseDomain]]",
  "backlinks": [],
  "wiki_links": [
    "MetaverseDomain",
    "ArtificialIntelligence"
  ],
  "ontology": {
    "term_id": "AI-0231",
    "preferred_term": "Tokenisation",
    "alt_terms": [],
    "iri": "http://narrativegoldmine.com/metaverse#Tokenisation",
    "source_domain": "metaverse",
    "domain": "metaverse",
    "domain_full_name": "",
    "definition": null,
    "scope_note": null,
    "status": "draft",
    "maturity": "draft",
    "version": null,
    "public_access": true,
    "last_updated": null,
    "authority_score": null,
    "quality_score": null,
    "cross_domain_links": null,
    "owl_class": "mv:Tokenisation",
    "owl_physicality": "ConceptualEntity",
    "owl_role": "Concept",
    "owl_inferred_class": null,
    "is_subclass_of": [],
    "has_part": [],
    "is_part_of": [],
    "requires": [],
    "depends_on": [],
    "enables": [],
    "relates_to": [],
    "bridges_to": [],
    "bridges_from": [],
    "domain_extensions": {},
    "belongs_to_domain": [
      "MetaverseDomain",
      "MetaverseDomain"
    ],
    "implemented_in_layer": [],
    "source": [],
    "validation": {
      "is_valid": false,
      "errors": [
        "Missing required property: last-updated",
        "Missing required property: definition",
        "Missing required property: is-subclass-of (at least one parent class)",
        "owl:class namespace 'mv' doesn't match source-domain 'metaverse'"
      ]
    }
  }
}