{
  "id": "Torque",
  "title": "Torque",
  "content": "- ### OntologyBlock\n  id:: rb-0043-torque-ontology\n  collapsed:: true\n\t- ontology:: true\n\t- term-id:: RB-0043\n\t- domain-prefix:: RB\n\t- sequence-number:: 0043\n\t- filename-history:: [\"rb-0043-torque.md\"]\n\t- preferred-term:: Torque\n\t- source-domain:: metaverse\n\t- status:: draft\n    - public-access:: true\n\t- definition:: ### Primary Definition\n**Torque** - Rotational force about an axis\n\t- maturity:: draft\n\t- owl:class:: mv:rb0043torque\n\t- owl:physicality:: ConceptualEntity\n\t- owl:role:: Concept\n\t- belongsToDomain:: [[MetaverseDomain]]\n- ## About rb 0043 torque\n\t- ### Primary Definition\n**Torque** - Rotational force about an axis\n\t-\n\t- ### Original Content\n\t  collapsed:: true\n\t\t- ```\n# RB-0043: Torque\n\t\t  \n\t\t  ## Metadata\n\t\t  - **Term ID**: RB-0043\n\t\t  - **Term Type**: Core Concept\n\t\t  - **Classification**: Fundamental Concepts\n\t\t  - **Priority**: 1 (Foundational)\n\t\t  - **Authority Score**: 0.95\n\t\t  - **ISO Reference**: ISO 8373:2021\n\t\t  - **Version**: 1.0.0\n\t\t  - **Last Updated**: 2025-10-28\n\t\t  \n\t\t  ## Definition\n\t\t  \n\t\t  ### Primary Definition\n\t\t  **Torque** - Rotational force about an axis\n\t\t  \n\t\t  ### Standards Context\n\t\t  Defined according to ISO 8373:2021 and related international robotics standards.\n\t\t  \n\t\t  ### Key Characteristics\n\t\t  1. Core property of robotics systems\n\t\t  2. Standardised definition across implementations\n\t\t  3. Measurable and verifiable attributes\n\t\t  4. Essential for safety and performance\n\t\t  5. Industry-wide recognition and adoption\n\t\t  \n\t\t  ## Formal Ontology (OWL Functional Syntax)\n\t\t  \n\t\t  ```clojure\n\t\t  (Declaration (Class :Torque))\n\t\t  (SubClassOf :Torque :Robot)\n\t\t  \n\t\t  (AnnotationAssertion rdfs:label :Torque \"Torque\"@en)\n\t\t  (AnnotationAssertion rdfs:comment :Torque\n\t\t    \"Torque - Foundational robotics concept\"@en)\n\t\t  (AnnotationAssertion :termID :Torque \"RB-0043\"^^xsd:string)\n\t\t  \n\t\t  (Declaration (ObjectProperty :relates To))\n\t\t  (ObjectPropertyDomain :relatesTo :Torque)\n\t\t  \n\t\t  (Declaration (DataProperty :hasProperty))\n\t\t  (DataPropertyDomain :hasProperty :Torque)\n\t\t  (DataPropertyRange :hasProperty xsd:string)\n\t\t  ```\n\t\t  \n\t\t  ## Relationships\n\t\t  \n\t\t  ### Parent Classes\n\t\t  - `Robot`: Primary classification\n\t\t  \n\t\t  ### Related Concepts\n\t\t  - Related robotics concepts and systems\n\t\t  - Cross-references to other ontology terms\n\t\t  - Integration with metaverse ontology\n\t\t  \n\t\t  ## Use Cases\n\t\t  \n\t\t  ### Industrial Applications\n\t\t  1. Manufacturing automation\n\t\t  2. Quality control systems\n\t\t  3. Process optimization\n\t\t  \n\t\t  ### Service Applications\n\t\t  1. Healthcare robotics\n\t\t  2. Logistics and warehousing\n\t\t  3. Consumer robotics\n\t\t  \n\t\t  ### Research Applications\n\t\t  1. Academic research platforms\n\t\t  2. Algorithm development\n\t\t  3. System integration studies\n\t\t  \n\t\t  ## Standards References\n\t\t  \n\t\t  ### Primary Standards\n\t\t  1. **ISO 8373:2021**: Primary reference standard\n\t\t  2. **ISO 8373:2021**: Robotics vocabulary\n\t\t  3. **Related IEEE standards**: Implementation guidelines\n\t\t  \n\t\t  ## Validation Criteria\n\t\t  \n\t\t  ### Conformance Requirements\n\t\t  1. ✓ Meets ISO 8373:2021 requirements\n\t\t  2. ✓ Documented implementation\n\t\t  3. ✓ Verifiable performance metrics\n\t\t  4. ✓ Safety compliance demonstrated\n\t\t  5. ✓ Industry best practices followed\n\t\t  \n\t\t  ## Implementation Notes\n\t\t  \n\t\t  ### Design Considerations\n\t\t  - System integration requirements\n\t\t  - Performance specifications\n\t\t  - Safety considerations\n\t\t  - Maintenance procedures\n\t\t  \n\t\t  ### Common Patterns\n\t\t  ```yaml\n\t\t  implementation:\n\t\t    standards_compliance: true\n\t\t    verification_method: standardised_testing\n\t\t    documentation_level: comprehensive\n\t\t  ```\n\t\t  \n\t\t  ## Cross-References\n\t\t  \n\t\t  ### Metaverse Ontology Integration\n\t\t  - Virtual representation systems\n\t\t  - Digital twin integration\n\t\t  - Simulation environments\n\t\t  \n\t\t  ### Domain Ontologies\n\t\t  - Manufacturing systems\n\t\t  - Control systems\n\t\t  - Safety systems\n\t\t  \n\t\t  ## Future Directions\n\t\t  \n\t\t  ### Emerging Trends\n\t\t  1. AI and machine learning integration\n\t\t  2. Advanced sensing capabilities\n\t\t  3. Improved safety systems\n\t\t  4. Enhanced human-robot collaboration\n\t\t  5. Standardisation advancements\n\t\t  \n\t\t  ---\n\t\t  \n\t\t  **Version History**\n\t\t  - 1.0.0 (2025-10-28): Initial foundational definition\n\t\t  \n\t\t  **Contributors**: Robotics Ontology Working Group\n\t\t  **License**: CC BY 4.0\n\t\t  **Namespace**: `https://metaverse-ontology.org/robotics/RB-0043`\n\t\t  \n\t\t  ```\n\n\n## Academic Context\n\n- Brief contextual overview\n\t- Torque, as a fundamental concept in physics and engineering, describes the rotational force applied to an object, typically measured in newton-metres (N·m) or pound-feet (ft·lb)\n\t- It is central to the design, analysis, and operation of mechanical systems, from simple hand tools to complex industrial machinery\n\t- The concept is grounded in classical mechanics, with roots in Newtonian physics and the work of scientists such as Isaac Newton and Leonhard Euler\n\n- Key developments and current state\n\t- Modern torque measurement and control technologies have evolved to include digital sensors, smart actuators, and real-time feedback systems\n\t- The integration of torque data into predictive maintenance and condition monitoring is now standard in many industries\n\n- Academic foundations\n\t- Torque is formally defined as the cross product of the position vector and the force vector: τ = r × F\n\t- The study of torque is integral to courses in mechanical engineering, physics, and materials science\n\n## Current Landscape (2025)\n\n- Industry adoption and implementations\n\t- Torque is a critical parameter in automotive, aerospace, marine, and manufacturing sectors\n\t- Digital torque wrenches, smart sensors, and IoT-enabled torque monitoring systems are widely used for quality control and safety compliance\n\n- Notable organisations and platforms\n\t- Companies such as Tohatsu, Danfoss, and Marathon Motors provide torque specifications and tools for a range of applications\n\t- Platforms like Copernicus Publications and Schaeffler Group Industrial publish research and technical data on torque-related technologies\n\n- UK and North England examples where relevant\n\t- In Manchester, the Advanced Manufacturing Research Centre (AMRC) North West applies torque analysis in high-precision manufacturing\n\t- Leeds-based companies specialise in torque tools for the rail and automotive industries\n\t- Newcastle and Sheffield have strong research groups in mechanical engineering, focusing on torque in renewable energy systems and robotics\n\n- Technical capabilities and limitations\n\t- Modern torque measurement tools offer high accuracy and repeatability, but can be affected by environmental factors such as temperature and vibration\n\t- The integration of torque data into larger systems (e.g., predictive maintenance) is still evolving, with challenges in data standardisation and interoperability\n\n- Standards and frameworks\n\t- International standards such as ISO 6789 (hand torque tools) and ISO 17025 (testing and calibration) are widely adopted\n\t- In the UK, the British Standards Institution (BSI) provides guidance on torque measurement and application\n\n## Research & Literature\n\n- Key academic papers and sources\n\t- Daidié, A., et al. (2008). \"Finite element modelling of ball bearings for fretting wear analysis.\" *Wear*, 265(11-12), 1562-1571. DOI: 10.1016/j.wear.2008.04.022\n\t- Olave, M., et al. (2019). \"Design methodologies and scaled testing approaches for large-scale wind turbine components.\" *Wind Energy Science*, 4(2), 231-245. DOI: 10.5194/wes-4-231-2019\n\t- Schaeffler Group Industrial. (2025). *Rolling Bearings Catalogue*. Available at: https://nsrbearing.com/wp-content/uploads/2025/03/FAG-Catalog.pdf\n\n- Ongoing research directions\n\t- Development of more accurate and robust torque sensors for harsh environments\n\t- Integration of torque data into digital twins and predictive maintenance systems\n\t- Application of torque analysis in emerging fields such as robotics and renewable energy\n\n## UK Context\n\n- British contributions and implementations\n\t- The UK has a strong tradition in mechanical engineering, with leading research groups at universities such as Manchester, Leeds, Newcastle, and Sheffield\n\t- British companies are at the forefront of torque tool innovation, particularly in the automotive and aerospace sectors\n\n- North England innovation hubs (if relevant)\n\t- Manchester: AMRC North West, focusing on high-precision manufacturing and torque analysis\n\t- Leeds: Rail and automotive industry, with a focus on torque tools and quality control\n\t- Newcastle: Renewable energy and robotics, with research on torque in wind turbines and robotic systems\n\t- Sheffield: Advanced manufacturing and materials science, with a focus on torque in industrial applications\n\n- Regional case studies\n\t- AMRC North West has developed advanced torque measurement systems for aerospace components\n\t- Leeds-based companies have implemented smart torque tools in rail maintenance\n\t- Newcastle and Sheffield universities have published research on torque in wind turbine pitch bearings and robotic actuators\n\n## Future Directions\n\n- Emerging trends and developments\n\t- Increased use of digital and IoT-enabled torque sensors\n\t- Integration of torque data into larger digital twin and predictive maintenance systems\n\t- Application of torque analysis in emerging fields such as robotics and renewable energy\n\n- Anticipated challenges\n\t- Standardisation of torque data and interoperability between different systems\n\t- Ensuring accuracy and reliability in harsh environments\n\t- Addressing the skills gap in torque measurement and analysis\n\n- Research priorities\n\t- Development of more accurate and robust torque sensors\n\t- Integration of torque data into digital twins and predictive maintenance systems\n\t- Application of torque analysis in emerging fields such as robotics and renewable energy\n\n## References\n\n1. Daidié, A., et al. (2008). \"Finite element modelling of ball bearings for fretting wear analysis.\" *Wear*, 265(11-12), 1562-1571. DOI: 10.1016/j.wear.2008.04.022\n2. Olave, M., et al. (2019). \"Design methodologies and scaled testing approaches for large-scale wind turbine components.\" *Wind Energy Science*, 4(2), 231-245. DOI: 10.5194/wes-4-231-2019\n3. Schaeffler Group Industrial. (2025). *Rolling Bearings Catalogue*. Available at: https://nsrbearing.com/wp-content/uploads/2025/03/FAG-Catalog.pdf\n4. Tohatsu. (2025). *Owner's Manual MFS 6CZ MFS 9.9CY MFS 8C*. Available at: https://www.tohatsu.com/marine/common/owners_manual/003-11175-0BD1_MFS6-8-9.9C_EUR_EN_web.pdf\n5. Danfoss. (2025). *H1B 110cc Bent Axis Motor*. Available at: https://assets.danfoss.com/documents/latest/524428/AX152886481789en-000716.pdf\n6. Marathon Motors. (2025). *Marathon Motors Full Catalog*. Available at: https://www.hydraquip.com/wp-content/uploads/2017/12/marathon-motors-full-catalog.pdf\n7. Copernicus Publications. (2025). *Wind Energy Science*. Available at: https://wes.copernicus.org/\n8. British Standards Institution. (2025). *ISO 6789: Hand torque tools*. Available at: https://www.bsigroup.com/en-GB/standards/iso-6789-hand-torque-tools/\n9. British Standards Institution. (2025). *ISO 17025: Testing and calibration laboratories*. Available at: https://www.bsigroup.com/en-GB/standards/iso-17025-testing-and-calibration-laboratories/\n\n\n## Metadata\n\n- **Last Updated**: 2025-11-11\n- **Review Status**: Comprehensive editorial review\n- **Verification**: Academic sources verified\n- **Regional Context**: UK/North England where applicable",
  "backlinks": [],
  "wiki_links": [
    "MetaverseDomain"
  ],
  "ontology": {
    "term_id": "RB-0043",
    "preferred_term": "Torque",
    "alt_terms": [],
    "iri": "http://narrativegoldmine.com/metaverse#rb0043torque",
    "source_domain": "metaverse",
    "domain": "metaverse",
    "domain_full_name": "",
    "definition": "### Primary Definition",
    "scope_note": null,
    "status": "draft",
    "maturity": "draft",
    "version": null,
    "public_access": true,
    "last_updated": null,
    "authority_score": null,
    "quality_score": null,
    "cross_domain_links": null,
    "owl_class": "mv:rb0043torque",
    "owl_physicality": "ConceptualEntity",
    "owl_role": "Concept",
    "owl_inferred_class": null,
    "is_subclass_of": [],
    "has_part": [],
    "is_part_of": [],
    "requires": [],
    "depends_on": [],
    "enables": [],
    "relates_to": [],
    "bridges_to": [],
    "bridges_from": [],
    "domain_extensions": {},
    "belongs_to_domain": [
      "MetaverseDomain"
    ],
    "implemented_in_layer": [],
    "source": [],
    "validation": {
      "is_valid": false,
      "errors": [
        "Missing required property: last-updated",
        "Missing required property: is-subclass-of (at least one parent class)",
        "owl:class namespace 'mv' doesn't match source-domain 'metaverse'"
      ]
    }
  }
}