{
  "id": "Training",
  "title": "Training",
  "content": "- ### OntologyBlock\n\t- ontology:: true\n\t- term-id:: AI-0041\n\t- preferred-term:: Training\n\t- source-domain:: metaverse\n\t- status:: draft\n    - public-access:: true\n\t- definition:: ### Primary Definition\n**Training** is the process of using a training dataset to cause a model to be created or updated. Training involves iterative adjustment of model parameters to minimise error or maximise performance on the training task.\n\t- maturity:: draft\n\t- owl:class:: mv:Training\n\t- owl:physicality:: ConceptualEntity\n\t- owl:role:: Concept\n\t- belongsToDomain:: [[MetaverseDomain]]\n\n### Relationships\n- is-subclass-of:: [[MachineLearning]]",
  "backlinks": [
    "Loss Function"
  ],
  "wiki_links": [
    "MetaverseDomain",
    "MachineLearning"
  ],
  "ontology": {
    "term_id": "AI-0041",
    "preferred_term": "Training",
    "alt_terms": [],
    "iri": "http://narrativegoldmine.com/metaverse#Training",
    "source_domain": "metaverse",
    "domain": "metaverse",
    "domain_full_name": "",
    "definition": "### Primary Definition",
    "scope_note": null,
    "status": "draft",
    "maturity": "draft",
    "version": null,
    "public_access": true,
    "last_updated": null,
    "authority_score": null,
    "quality_score": null,
    "cross_domain_links": null,
    "owl_class": "mv:Training",
    "owl_physicality": "ConceptualEntity",
    "owl_role": "Concept",
    "owl_inferred_class": null,
    "is_subclass_of": [],
    "has_part": [],
    "is_part_of": [],
    "requires": [],
    "depends_on": [],
    "enables": [],
    "relates_to": [],
    "bridges_to": [],
    "bridges_from": [],
    "domain_extensions": {},
    "belongs_to_domain": [
      "MetaverseDomain"
    ],
    "implemented_in_layer": [],
    "source": [],
    "validation": {
      "is_valid": false,
      "errors": [
        "Missing required property: last-updated",
        "Missing required property: is-subclass-of (at least one parent class)",
        "owl:class namespace 'mv' doesn't match source-domain 'metaverse'"
      ]
    }
  }
}