{
  "id": "Transaction Confirmation",
  "title": "Transaction Confirmation",
  "content": "- ### OntologyBlock\n  id:: transaction-confirmation-ontology\n  collapsed:: true\n\n  - **Identification**\n\n    - domain-prefix:: BC\n\n    - sequence-number:: 0020\n\n    - filename-history:: [\"BC-0020-transaction-confirmation.md\"]\n    - public-access:: true\n    - ontology:: true\n    - is-subclass-of:: [[BlockchainTechnology]]\n    - term-id:: BC-0020\n    - preferred-term:: Transaction Confirmation\n    - source-domain:: blockchain\n    - status:: complete\n    - version:: 1.1.0\n    - last-updated:: 2025-11-15\n    - quality-score:: 0.92\n    - completeness:: 0.94\n    - technical-depth:: 0.91\n    - citation-quality:: 0.90\n\n  - **Definition**\n    - definition:: Inclusion in blockchain within blockchain systems, providing essential functionality for distributed ledger technology operations and properties.\n    - maturity:: mature\n    - source:: [[ISO/IEC 23257:2021]], [[IEEE 2418.1]], [[NIST NISTIR]]\n    - authority-score:: 0.95\n\n  - **Semantic Classification**\n    - owl:class:: bc:TransactionConfirmation\n    - owl:physicality:: VirtualEntity\n    - owl:role:: Object\n    - owl:inferred-class:: bc:VirtualObject\n    - belongsToDomain:: [[BlockchainDomain]]\n\n  - #### OWL Restrictions\n    \n    \n\n  - #### CrossDomainBridges\n    - bridges-to:: [[BlockchainEntity]] via is-subclass-of\n    - bridges-to:: [[Distributeddatastructure]] via is-subclass-of\n\n  -",
  "backlinks": [],
  "wiki_links": [
    "BlockchainDomain",
    "ISO/IEC 23257:2021",
    "Distributeddatastructure",
    "IEEE 2418.1",
    "BlockchainEntity",
    "NIST NISTIR",
    "BlockchainTechnology"
  ],
  "ontology": {
    "term_id": "BC-0020",
    "preferred_term": "Transaction Confirmation",
    "alt_terms": [],
    "iri": "http://narrativegoldmine.com/blockchain#TransactionConfirmation",
    "source_domain": "blockchain",
    "domain": "blockchain",
    "domain_full_name": "",
    "definition": "Inclusion in blockchain within blockchain systems, providing essential functionality for distributed ledger technology operations and properties.",
    "scope_note": null,
    "status": "complete",
    "maturity": "mature",
    "version": "1.1.0",
    "public_access": true,
    "last_updated": "2025-11-15",
    "authority_score": 0.95,
    "quality_score": 0.92,
    "cross_domain_links": null,
    "owl_class": "bc:TransactionConfirmation",
    "owl_physicality": "VirtualEntity",
    "owl_role": "Object",
    "owl_inferred_class": "bc:VirtualObject",
    "is_subclass_of": [],
    "has_part": [],
    "is_part_of": [],
    "requires": [],
    "depends_on": [],
    "enables": [],
    "relates_to": [],
    "bridges_to": [
      "BlockchainEntity via is",
      "Distributeddatastructure via is"
    ],
    "bridges_from": [],
    "domain_extensions": {},
    "belongs_to_domain": [
      "BlockchainDomain"
    ],
    "implemented_in_layer": [],
    "source": [
      "ISO/IEC 23257:2021",
      "IEEE 2418.1",
      "NIST NISTIR"
    ],
    "validation": {
      "is_valid": false,
      "errors": [
        "Missing required property: is-subclass-of (at least one parent class)",
        "owl:class namespace 'bc' doesn't match source-domain 'blockchain'"
      ]
    }
  }
}