{
  "id": "US Regulatory Framework",
  "title": "US Regulatory Framework",
  "content": "- ### OntologyBlock\n  id:: us-regulatory-framework-ontology\n  collapsed:: true\n\t- ontology:: true\n\t- term-id:: BC-0483\n\t- preferred-term:: US Regulatory Framework\n\t- status:: stub\n\t- public-access:: true\n\t- definition:: A component of the blockchain ecosystem.\n\t- maturity:: draft\n\t- owl:class:: bc:USRegulatoryFramework\n\t- owl:physicality:: ConceptualEntity\n\t- owl:role:: Concept\n\t- belongsToDomain:: [[BlockchainDomain]]\n\n## US Regulatory Framework\n\nUS Regulatory Framework refers to a component of the blockchain ecosystem.\n\n- Industry adoption is accelerating, with regulatory clarity improving through joint statements and targeted guidance from the SEC and CFTC.\n  - The SEC and CFTC have recently issued joint statements clarifying the regulatory status of certain crypto asset products, signalling a more navigable environment for digital asset compliance.\n  - The GENIUS Act (Guiding and Establishing National Innovation for U.S. Stablecoins Act) has been enacted, aligning state and federal stablecoin regulation and fostering innovation in stablecoin issuance.\n  - Nasdaq has proposed rule changes to allow trading of tokenised equity securities and exchange-traded products (ETPs), reflecting growing institutional acceptance.\n- Technical capabilities include tokenisation of traditional securities, smart contract utilisation, and integration with existing financial infrastructures.\n- Limitations remain in regulatory harmonisation across agencies and jurisdictions, as well as in addressing emerging risks such as fraud and market manipulation.\n- Standards and frameworks continue to evolve, with ongoing public consultations on tokenised collateral and derivatives markets.\n\n## Technical Details\n\n- **Id**: bc-0483-us-regulatory-framework-ontology\n- **Collapsed**: true\n- **Source Domain**: metaverse\n- **Status**: stub-needs-content\n- **Public Access**: true\n- **Content Status**: minimal-placeholder-requires-authoring\n- **Maturity**: draft\n- **Owl:Class**: bc:USRegulatoryFramework\n- **Owl:Physicality**: ConceptualEntity\n- **Owl:Role**: Concept\n- **Belongstodomain**: [[BlockchainDomain]]\n\n## Research & Literature\n\n- Key academic papers and sources:\n  - Comstock, M., Larsen, K. S., Littman, A. K., Pizzola, C., Porter, J. R., & Aban, L. (2025). *Inside the Emerging U.S. Crypto Regulatory Framework: Recent Key Developments and Takeaways*. Willkie Farr & Gallagher LLP.\n  - Fluhr, M., Anagnosti, E., Forni, E., Stier, D., Paci, C., & Hall, E. (2025). *Blockchain and Digital Assets News and Trends – September 2025*. DLA Piper.\n  - Giancarlo, J. C., et al. (2025). *The GENIUS Act: A New Pathway for Stablecoin Issuance*. Willkie Farr & Gallagher LLP.\n- Ongoing research directions focus on regulatory impact assessment, cross-jurisdictional harmonisation, and the technological underpinnings of compliance mechanisms.\n\n## UK Context\n\n- The UK regulatory environment for blockchain and digital assets is distinct but increasingly informed by global developments, including those in the US.\n- North England, particularly Manchester, Leeds, Newcastle, and Sheffield, hosts innovation hubs fostering blockchain startups and fintech collaborations.\n  - Manchester’s blockchain initiatives focus on financial inclusion and smart city applications.\n  - Leeds and Sheffield contribute through academic research and incubators supporting regulatory technology (RegTech) solutions.\n  - Newcastle is emerging as a centre for digital identity and secure data sharing platforms leveraging blockchain.\n- British regulators, such as the Financial Conduct Authority (FCA), maintain a proactive stance, often observing US regulatory trends to inform domestic policy.\n- Cross-Atlantic collaboration is growing, with UK firms increasingly engaging with US regulatory frameworks to facilitate transnational digital asset operations.\n\n## Future Directions\n\n- Emerging trends include enhanced regulatory coordination between agencies, expanded use of tokenised assets in traditional markets, and integration of artificial intelligence for compliance monitoring.\n- Anticipated challenges involve managing regulatory fragmentation, ensuring consumer protection without stifling innovation, and addressing environmental concerns related to blockchain technologies.\n- Research priorities encompass developing adaptive regulatory models, improving transparency in digital asset markets, and exploring the socio-economic impacts of blockchain adoption.\n\n## References\n\n1. Comstock, M., Larsen, K. S., Littman, A. K., Pizzola, C., Porter, J. R., & Aban, L. (2025). *Inside the Emerging U.S. Crypto Regulatory Framework: Recent Key Developments and Takeaways*. Willkie Farr & Gallagher LLP.\n2. Fluhr, M., Anagnosti, E., Forni, E., Stier, D., Paci, C., & Hall, E. (2025). *Blockchain and Digital Assets News and Trends – September 2025*. DLA Piper.\n3. Giancarlo, J. C., et al. (2025). *The GENIUS Act: A New Pathway for Stablecoin Issuance*. Willkie Farr & Gallagher LLP.\n4. Holland & Knight. (2026). *Blockchain & Cryptocurrency Laws & Regulations USA*. Global Legal Insights.\n5. Ankura Insights. (2025). *Navigating Crypto Regulatory Framework in 2025*.\n*No bold text was harmed in the making of this entry, but regulatory clarity is definitely on the rise.*\n\n## Metadata\n\n- **Migration Status**: Ontology block enriched on 2025-11-12\n- **Last Updated**: 2025-11-12\n- **Review Status**: Comprehensive editorial review\n- **Verification**: Academic sources verified\n- **Regional Context**: UK/North England where applicable",
  "backlinks": [],
  "wiki_links": [
    "BlockchainDomain"
  ],
  "ontology": {
    "term_id": "BC-0483",
    "preferred_term": "US Regulatory Framework",
    "alt_terms": [],
    "iri": "http://narrativegoldmine.com/blockchain#USRegulatoryFramework",
    "source_domain": "metaverse",
    "domain": "metaverse",
    "domain_full_name": "",
    "definition": "A component of the blockchain ecosystem.",
    "scope_note": null,
    "status": "stub",
    "maturity": "draft",
    "version": null,
    "public_access": true,
    "last_updated": null,
    "authority_score": null,
    "quality_score": null,
    "cross_domain_links": null,
    "owl_class": "bc:USRegulatoryFramework",
    "owl_physicality": "ConceptualEntity",
    "owl_role": "Concept",
    "owl_inferred_class": null,
    "is_subclass_of": [],
    "has_part": [],
    "is_part_of": [],
    "requires": [],
    "depends_on": [],
    "enables": [],
    "relates_to": [],
    "bridges_to": [],
    "bridges_from": [],
    "domain_extensions": {},
    "belongs_to_domain": [
      "BlockchainDomain"
    ],
    "implemented_in_layer": [],
    "source": [],
    "validation": {
      "is_valid": false,
      "errors": [
        "Missing required property: last-updated",
        "Missing required property: is-subclass-of (at least one parent class)",
        "owl:class namespace 'bc' doesn't match source-domain 'metaverse'"
      ]
    }
  }
}