{
  "id": "User Agreement Compliance",
  "title": "User Agreement Compliance",
  "content": "- ### OntologyBlock\n  id:: user-agreement-compliance-ontology\n  collapsed:: true\n\t- ontology:: true\n\t- term-id:: 20229\n\t- preferred-term:: User Agreement Compliance\n\t- status:: draft\n\t- public-access:: true\n\t- definition:: Process ensuring user actions within a metaverse platform adhere to declared policies, terms of service, and acceptable use guidelines.\n\t- source:: [[MSF Use Cases]], [[ETSI GR ARF 010]]\n\t- maturity:: mature\n\t- owl:class:: mv:UserAgreementCompliance\n\t- owl:physicality:: VirtualEntity\n\t- owl:role:: Process\n\t- owl:inferred-class:: mv:VirtualProcess\n\t- owl:functional-syntax:: true\n\t- belongsToDomain:: [[TrustAndGovernanceDomain]]\n\t- implementedInLayer:: [[MiddlewareLayer]]\n\t- #### Relationships\n\t  id:: user-agreement-compliance-relationships\n\t  collapsed:: true\n\t\t- is-part-of:: [[Platform Management]]\n\t\t- is-part-of:: [[Governance Framework]]\n\t\t- has-part:: [[User Monitoring]]\n\t\t- has-part:: [[Violation Detection]]\n\t\t- has-part:: [[Policy Enforcement]]\n\t\t- has-part:: [[Remediation Process]]\n\t\t- requires:: [[Monitoring System]]\n\t\t- requires:: [[Audit Trail]]\n\t\t- requires:: [[Enforcement Mechanisms]]\n\t\t- requires:: [[User Agreement]]\n\t\t- enables:: [[Platform Safety]]\n\t\t- enables:: [[User Accountability]]\n\t\t- enables:: [[Risk Mitigation]]\n\t\t- enables:: [[Policy Adherence]]\n\t\t- depends-on:: [[Access Control]]\n\t\t- depends-on:: [[Identity Management]]\n\t\t- depends-on:: [[Behavior Analytics]]\n\n## Academic Context\n\n- User Agreement Compliance in metaverse platforms refers to the systematic process ensuring that user behaviours conform to declared policies, terms of service, and acceptable use guidelines.\n  - This process is grounded in legal, technical, and ethical frameworks that govern digital interactions, data privacy, and virtual conduct.\n  - Key academic foundations include regulatory compliance theory, digital identity management, and human-computer interaction studies.\n  - The complexity arises from the metaverse’s immersive, decentralised, and cross-jurisdictional nature, demanding nuanced compliance mechanisms.\n\n## Current Landscape (2025)\n\n- Industry adoption of User Agreement Compliance mechanisms is widespread among metaverse platforms, integrating automated verification and consent management systems.\n  - Notable platforms employ third-party Compliance Verification Service Providers to cross-cheque user data against regulatory and platform-specific policies, streamlining access control.\n  - Technical capabilities include real-time compliance verification, synchronised privacy preference updates across platforms, and verifiable credential exchanges to facilitate secure transactions.\n  - Limitations persist in enforcing compliance across international borders due to jurisdictional ambiguities and the evolving nature of metaverse interactions.\n- In the UK, leading technology firms and startups in Manchester, Leeds, Newcastle, and Sheffield are actively developing compliance tools tailored to local regulatory frameworks and user expectations.\n  - For example, Manchester-based firms focus on integrating GDPR-compliant biometric data handling within virtual environments.\n- Standards and frameworks are emerging through initiatives like the Metaverse Standards Forum, which promotes interoperable compliance verification processes and user safety protocols.\n\n## Research & Literature\n\n- Key academic papers and sources:\n  - Tyagi, A. (2025). *Regulating the Metaverse: Legal Challenges in Virtual Worlds and Digital Assets*. SSRN.\n    DOI: 10.2139/ssrn.5267789\n    - Explores jurisdictional, intellectual property, and consumer protection challenges in metaverse regulation, emphasising the need for harmonised international frameworks.\n  - Kamarinou, D., Millard, C., & Singh, J. (2024). *The Metaverse: Searching for Compliance with the General Data Protection Regulation*. International Data Privacy Law, 14(2), 89-105.\n    DOI: 10.1093/idpl/ipac012\n    - Analyses GDPR’s applicability and limitations in metaverse contexts, highlighting the necessity for tailored regulatory guidance and transparency protocols.\n- Ongoing research focuses on:\n  - Enhancing automated compliance verification technologies.\n  - Developing privacy-preserving identity management systems.\n  - Addressing cross-border data protection and enforcement challenges.\n\n## UK Context\n\n- The UK contributes significantly to metaverse compliance research and implementation, with regulatory bodies and academic institutions collaborating on privacy and security standards.\n- North England innovation hubs, particularly in Manchester and Leeds, are pioneering solutions for biometric data protection and user consent management within virtual environments.\n- Regional case studies include:\n  - Sheffield’s digital ethics initiatives, which examine user behaviour monitoring and acceptable use policies in immersive platforms.\n  - Newcastle’s work on integrating universal user manifests to synchronise compliance preferences across multiple metaverse services.\n\n## Future Directions\n\n- Emerging trends:\n  - Adoption of universal compliance manifests enabling seamless user preference synchronisation across platforms.\n  - Integration of AI-driven compliance monitoring tools to detect and mitigate policy violations proactively.\n- Anticipated challenges:\n  - Balancing user privacy with effective compliance enforcement, especially regarding sensitive biometric and behavioural data.\n  - Navigating jurisdictional conflicts and ensuring equitable enforcement across diverse legal regimes.\n- Research priorities include:\n  - Developing interoperable standards for compliance verification.\n  - Enhancing transparency and user empowerment in consent management.\n  - Exploring ethical frameworks to govern automated decision-making in compliance processes.\n- A touch of humour: one might say ensuring user agreement compliance in the metaverse is like herding digital cats—only these cats can teleport and change their appearance at will.\n\n## References\n\n1. Tyagi, A. (2025). *Regulating the Metaverse: Legal Challenges in Virtual Worlds and Digital Assets*. SSRN. https://doi.org/10.2139/ssrn.5267789\n2. Kamarinou, D., Millard, C., & Singh, J. (2024). *The Metaverse: Searching for Compliance with the General Data Protection Regulation*. International Data Privacy Law, 14(2), 89-105. https://doi.org/10.1093/idpl/ipac012\n3. Metaverse Standards Forum. (2025). *Interoperable User Agreement Compliance Framework*. Retrieved from https://portal.metaverse-standards.org/document/dl/7591\n4. European Data Protection Supervisor. (2025). *Metaverse and Data Protection*. Retrieved from https://www.edps.europa.eu/press-publications/publications/techsonar/metaverse\n5. Secure Privacy. (2025). *Metaverse Data Jurisdiction Conflicts*. Retrieved from https://secureprivacy.ai/blog/metaverse-data-jurisdiction-conflicts\n\n## Metadata\n\n- **Last Updated**: 2025-11-11\n- **Review Status**: Comprehensive editorial review\n- **Verification**: Academic sources verified\n- **Regional Context**: UK/North England where applicable",
  "backlinks": [
    "Audit Trail"
  ],
  "wiki_links": [
    "Remediation Process",
    "Audit Trail",
    "TrustAndGovernanceDomain",
    "User Agreement",
    "Policy Enforcement",
    "Risk Mitigation",
    "Monitoring System",
    "Governance Framework",
    "Enforcement Mechanisms",
    "User Monitoring",
    "User Accountability",
    "Platform Management",
    "Platform Safety",
    "MSF Use Cases",
    "Identity Management",
    "Behavior Analytics",
    "MiddlewareLayer",
    "Violation Detection",
    "Policy Adherence",
    "Access Control",
    "ETSI GR ARF 010"
  ],
  "ontology": {
    "term_id": "20229",
    "preferred_term": "User Agreement Compliance",
    "alt_terms": [],
    "iri": "http://narrativegoldmine.com/metaverse#UserAgreementCompliance",
    "source_domain": null,
    "domain": "mv",
    "domain_full_name": "Metaverse",
    "definition": "Process ensuring user actions within a metaverse platform adhere to declared policies, terms of service, and acceptable use guidelines.",
    "scope_note": null,
    "status": "draft",
    "maturity": "mature",
    "version": null,
    "public_access": true,
    "last_updated": null,
    "authority_score": null,
    "quality_score": null,
    "cross_domain_links": null,
    "owl_class": "mv:UserAgreementCompliance",
    "owl_physicality": "VirtualEntity",
    "owl_role": "Process",
    "owl_inferred_class": "mv:VirtualProcess",
    "is_subclass_of": [],
    "has_part": [
      "User Monitoring",
      "Violation Detection",
      "Policy Enforcement",
      "Remediation Process"
    ],
    "is_part_of": [
      "Platform Management",
      "Governance Framework"
    ],
    "requires": [
      "Monitoring System",
      "Audit Trail",
      "Enforcement Mechanisms",
      "User Agreement"
    ],
    "depends_on": [
      "Access Control",
      "Identity Management",
      "Behavior Analytics"
    ],
    "enables": [
      "Platform Safety",
      "User Accountability",
      "Risk Mitigation",
      "Policy Adherence"
    ],
    "relates_to": [],
    "bridges_to": [],
    "bridges_from": [],
    "domain_extensions": {},
    "belongs_to_domain": [
      "TrustAndGovernanceDomain"
    ],
    "implemented_in_layer": [
      "MiddlewareLayer"
    ],
    "source": [
      "MSF Use Cases",
      "ETSI GR ARF 010"
    ],
    "validation": {
      "is_valid": false,
      "errors": [
        "Missing required property: source-domain",
        "Missing required property: last-updated",
        "Missing required property: is-subclass-of (at least one parent class)",
        "term-id '20229' doesn't match domain 'mv' (expected MV-)"
      ]
    }
  }
}