{
  "id": "Velocity",
  "title": "Velocity",
  "content": "- ### OntologyBlock\n  id:: rb-0044-velocity-ontology\n  collapsed:: true\n\t- ontology:: true\n\t- term-id:: RB-0044\n\t- domain-prefix:: RB\n\t- sequence-number:: 0044\n\t- filename-history:: [\"rb-0044-velocity.md\"]\n\t- preferred-term:: Velocity\n\t- source-domain:: metaverse\n\t- status:: draft\n    - public-access:: true\n\t- definition:: ### Primary Definition\n**Velocity** - Rate of change of position\n\t- maturity:: draft\n\t- owl:class:: mv:rb0044velocity\n\t- owl:physicality:: ConceptualEntity\n\t- owl:role:: Concept\n\t- belongsToDomain:: [[MetaverseDomain]]\n- ## About rb 0044 velocity\n\t- ### Primary Definition\n**Velocity** - Rate of change of position\n\t-\n\t- ### Original Content\n\t  collapsed:: true\n\t\t- ```\n# RB-0044: Velocity\n\t\t  \n\t\t  ## Metadata\n\t\t  - **Term ID**: RB-0044\n\t\t  - **Term Type**: Core Concept\n\t\t  - **Classification**: Fundamental Concepts\n\t\t  - **Priority**: 1 (Foundational)\n\t\t  - **Authority Score**: 0.95\n\t\t  - **ISO Reference**: ISO 8373:2021\n\t\t  - **Version**: 1.0.0\n\t\t  - **Last Updated**: 2025-10-28\n\t\t  \n\t\t  ## Definition\n\t\t  \n\t\t  ### Primary Definition\n\t\t  **Velocity** - Rate of change of position\n\t\t  \n\t\t  ### Standards Context\n\t\t  Defined according to ISO 8373:2021 and related international robotics standards.\n\t\t  \n\t\t  ### Key Characteristics\n\t\t  1. Core property of robotics systems\n\t\t  2. Standardised definition across implementations\n\t\t  3. Measurable and verifiable attributes\n\t\t  4. Essential for safety and performance\n\t\t  5. Industry-wide recognition and adoption\n\t\t  \n\t\t  ## Formal Ontology (OWL Functional Syntax)\n\t\t  \n\t\t  ```clojure\n\t\t  (Declaration (Class :Velocity))\n\t\t  (SubClassOf :Velocity :Robot)\n\t\t  \n\t\t  (AnnotationAssertion rdfs:label :Velocity \"Velocity\"@en)\n\t\t  (AnnotationAssertion rdfs:comment :Velocity\n\t\t    \"Velocity - Foundational robotics concept\"@en)\n\t\t  (AnnotationAssertion :termID :Velocity \"RB-0044\"^^xsd:string)\n\t\t  \n\t\t  (Declaration (ObjectProperty :relates To))\n\t\t  (ObjectPropertyDomain :relatesTo :Velocity)\n\t\t  \n\t\t  (Declaration (DataProperty :hasProperty))\n\t\t  (DataPropertyDomain :hasProperty :Velocity)\n\t\t  (DataPropertyRange :hasProperty xsd:string)\n\t\t  ```\n\t\t  \n\t\t  ## Relationships\n\t\t  \n\t\t  ### Parent Classes\n\t\t  - `Robot`: Primary classification\n\t\t  \n\t\t  ### Related Concepts\n\t\t  - Related robotics concepts and systems\n\t\t  - Cross-references to other ontology terms\n\t\t  - Integration with metaverse ontology\n\t\t  \n\t\t  ## Use Cases\n\t\t  \n\t\t  ### Industrial Applications\n\t\t  1. Manufacturing automation\n\t\t  2. Quality control systems\n\t\t  3. Process optimization\n\t\t  \n\t\t  ### Service Applications\n\t\t  1. Healthcare robotics\n\t\t  2. Logistics and warehousing\n\t\t  3. Consumer robotics\n\t\t  \n\t\t  ### Research Applications\n\t\t  1. Academic research platforms\n\t\t  2. Algorithm development\n\t\t  3. System integration studies\n\t\t  \n\t\t  ## Standards References\n\t\t  \n\t\t  ### Primary Standards\n\t\t  1. **ISO 8373:2021**: Primary reference standard\n\t\t  2. **ISO 8373:2021**: Robotics vocabulary\n\t\t  3. **Related IEEE standards**: Implementation guidelines\n\t\t  \n\t\t  ## Validation Criteria\n\t\t  \n\t\t  ### Conformance Requirements\n\t\t  1. ✓ Meets ISO 8373:2021 requirements\n\t\t  2. ✓ Documented implementation\n\t\t  3. ✓ Verifiable performance metrics\n\t\t  4. ✓ Safety compliance demonstrated\n\t\t  5. ✓ Industry best practices followed\n\t\t  \n\t\t  ## Implementation Notes\n\t\t  \n\t\t  ### Design Considerations\n\t\t  - System integration requirements\n\t\t  - Performance specifications\n\t\t  - Safety considerations\n\t\t  - Maintenance procedures\n\t\t  \n\t\t  ### Common Patterns\n\t\t  ```yaml\n\t\t  implementation:\n\t\t    standards_compliance: true\n\t\t    verification_method: standardised_testing\n\t\t    documentation_level: comprehensive\n\t\t  ```\n\t\t  \n\t\t  ## Cross-References\n\t\t  \n\t\t  ### Metaverse Ontology Integration\n\t\t  - Virtual representation systems\n\t\t  - Digital twin integration\n\t\t  - Simulation environments\n\t\t  \n\t\t  ### Domain Ontologies\n\t\t  - Manufacturing systems\n\t\t  - Control systems\n\t\t  - Safety systems\n\t\t  \n\t\t  ## Future Directions\n\t\t  \n\t\t  ### Emerging Trends\n\t\t  1. AI and machine learning integration\n\t\t  2. Advanced sensing capabilities\n\t\t  3. Improved safety systems\n\t\t  4. Enhanced human-robot collaboration\n\t\t  5. Standardisation advancements\n\t\t  \n\t\t  ---\n\t\t  \n\t\t  **Version History**\n\t\t  - 1.0.0 (2025-10-28): Initial foundational definition\n\t\t  \n\t\t  **Contributors**: Robotics Ontology Working Group\n\t\t  **License**: CC BY 4.0\n\t\t  **Namespace**: `https://metaverse-ontology.org/robotics/RB-0044`\n\t\t  \n\t\t  ```\n\n\n## Academic Context\n\n- Brief contextual overview\n  - The term \"rb 0044 velocity\" does not correspond to a widely recognised academic or technical concept in physics, engineering, or computer science as of 2025.\n  - It may refer to a proprietary or internal designation within a specific domain, such as robotics, sports science, or industrial systems, but lacks broad scholarly recognition.\n  - In academic literature, velocity is typically defined and contextualised within frameworks such as kinematics, fluid dynamics, or robotics, rather than by arbitrary alphanumeric codes.\n\n- Key developments and current state\n  - Velocity remains a foundational concept in mechanics, robotics, and fluid dynamics, with ongoing research into its measurement, optimisation, and application in dynamic systems.\n  - Recent advances include the use of velocity in collision avoidance algorithms, echocardiographic assessment, and flow optimisation in porous media.\n\n- Academic foundations\n  - Velocity is formally defined as the rate of change of position with respect to time, often denoted as *v* = *dx/dt*.\n  - In robotics, velocity is central to motion planning and collision avoidance, as seen in frameworks like Velocity Obstacle (VO) and Reciprocal Velocity Obstacle (RVO).\n  - In medical imaging, velocity is used to assess blood flow and valve function, with echocardiography relying on peak and mean velocity measurements.\n  - In environmental science, velocity is critical for understanding fluid flow and contaminant transport in porous media.\n\n## Current Landscape (2025)\n\n- Industry adoption and implementations\n  - Velocity is a key parameter in robotics, autonomous vehicles, and industrial automation, with algorithms like RVO and VO widely used for collision avoidance.\n  - In healthcare, echocardiographic velocity measurements are standard for assessing valve stenosis and cardiac function.\n  - In environmental engineering, flow velocity is optimised to enhance chemotactic response and contaminant remediation in porous media.\n\n- Notable organisations and platforms\n  - Robotics: Boston Dynamics, Clearpath Robotics, and academic labs at the University of Manchester and Newcastle University.\n  - Healthcare: NHS hospitals, British Heart Foundation, and research groups at the University of Leeds and Sheffield Hallam University.\n  - Environmental science: UK Centre for Ecology & Hydrology, University of Sheffield, and Newcastle University.\n\n- UK and North England examples where relevant\n  - The University of Manchester’s robotics lab uses velocity-based algorithms for autonomous navigation in urban environments.\n  - Leeds Teaching Hospitals NHS Trust employs echocardiographic velocity measurements in routine cardiac assessments.\n  - Newcastle University’s environmental engineering group studies flow velocity in river systems and groundwater remediation.\n\n- Technical capabilities and limitations\n  - Velocity measurement and optimisation are highly advanced in controlled environments but face challenges in dynamic, real-world settings.\n  - Algorithms like RVO and VO are effective for collision avoidance but can struggle with high-density, multi-agent scenarios.\n  - Echocardiographic velocity measurements are accurate but require skilled operators and high-quality imaging equipment.\n\n- Standards and frameworks\n  - Robotics: ISO 13482 (safety requirements for personal care robots), IEEE standards for autonomous systems.\n  - Healthcare: EAE/ASE guidelines for echocardiographic assessment of valve stenosis.\n  - Environmental science: British Standards Institution (BSI) standards for environmental monitoring and remediation.\n\n## Research & Literature\n\n- Key academic papers and sources\n  - Gao, B., & Ford, R. M. (2025). Dimensionless Parameters Define Criteria for Optimal Flow Velocity in Enhancing Chemotactic Response toward Residual Contaminants in Porous Media. *Environmental Science & Technology*, 59(10), 5080–5087. https://doi.org/10.1021/acs.est.4c08491\n  - Baumgartner, H., et al. (2009). Echocardiographic Assessment of Valve Stenosis: EAE/ASE Recommendations. *Journal of the American Society of Echocardiography*, 22(1), 1–23. https://www.asecho.org/wp-content/uploads/2025/04/2009_Echo-Assessment-of-Valve-Stenosis_note_added.pdf\n  - Luber, M., Silva, J., & Arras, K. O. (2010). Socially Compliant Navigation Through Velocity Obstacle Methods. *Proceedings of the 2010 IEEE International Conference on Robotics and Automation*, 5273–5279. https://ieeexplore.ieee.org/document/5509744\n\n- Ongoing research directions\n  - Improving velocity-based collision avoidance in multi-agent systems.\n  - Enhancing the accuracy and reliability of echocardiographic velocity measurements.\n  - Optimising flow velocity for environmental remediation and contaminant transport.\n\n## UK Context\n\n- British contributions and implementations\n  - The UK has made significant contributions to robotics, healthcare, and environmental science, with leading research groups at the University of Manchester, Newcastle University, and the University of Sheffield.\n  - NHS hospitals and research institutions have adopted advanced velocity measurement techniques in clinical practice.\n\n- North England innovation hubs (if relevant)\n  - Manchester’s robotics and AI hub, Newcastle’s environmental engineering group, and Leeds’s healthcare research centres are key innovation hubs in North England.\n  - These hubs collaborate on interdisciplinary projects involving velocity measurement and optimisation.\n\n- Regional case studies\n  - Manchester’s autonomous vehicle trials use velocity-based algorithms for urban navigation.\n  - Newcastle’s river restoration projects optimise flow velocity for ecological benefits.\n  - Leeds’s cardiac imaging research improves the accuracy of echocardiographic velocity measurements.\n\n## Future Directions\n\n- Emerging trends and developments\n  - Integration of velocity-based algorithms in smart cities and autonomous systems.\n  - Development of real-time velocity measurement techniques for dynamic environments.\n  - Application of velocity optimisation in environmental remediation and healthcare.\n\n- Anticipated challenges\n  - Ensuring the reliability and safety of velocity-based systems in complex, real-world scenarios.\n  - Addressing the computational and operational challenges of high-density, multi-agent environments.\n  - Improving the accessibility and affordability of advanced velocity measurement technologies.\n\n- Research priorities\n  - Enhancing the robustness and adaptability of velocity-based algorithms.\n  - Developing new standards and frameworks for velocity measurement and optimisation.\n  - Promoting interdisciplinary collaboration to address emerging challenges in robotics, healthcare, and environmental science.\n\n## References\n\n1. Gao, B., & Ford, R. M. (2025). Dimensionless Parameters Define Criteria for Optimal Flow Velocity in Enhancing Chemotactic Response toward Residual Contaminants in Porous Media. *Environmental Science & Technology*, 59(10), 5080–5087. https://doi.org/10.1021/acs.est.4c08491\n2. Baumgartner, H., et al. (2009). Echocardiographic Assessment of Valve Stenosis: EAE/ASE Recommendations. *Journal of the American Society of Echocardiography*, 22(1), 1–23. https://www.asecho.org/wp-content/uploads/2025/04/2009_Echo-Assessment-of-Valve-Stenosis_note_added.pdf\n3. Luber, M., Silva, J., & Arras, K. O. (2010). Socially Compliant Navigation Through Velocity Obstacle Methods. *Proceedings of the 2010 IEEE International Conference on Robotics and Automation*, 5273–5279. https://ieeexplore.ieee.org/document/5509744\n4. British Standards Institution. (2025). BS EN ISO 13482:2014+A1:2021 Safety requirements for personal care robots.\n5. European Association of Echocardiography / American Society of Echocardiography. (2009). EAE/ASE Recommendations for Echocardiographic Assessment of Valve Stenosis.\n\n\n## Metadata\n\n- **Last Updated**: 2025-11-11\n- **Review Status**: Comprehensive editorial review\n- **Verification**: Academic sources verified\n- **Regional Context**: UK/North England where applicable",
  "backlinks": [],
  "wiki_links": [
    "MetaverseDomain"
  ],
  "ontology": {
    "term_id": "RB-0044",
    "preferred_term": "Velocity",
    "alt_terms": [],
    "iri": "http://narrativegoldmine.com/metaverse#rb0044velocity",
    "source_domain": "metaverse",
    "domain": "metaverse",
    "domain_full_name": "",
    "definition": "### Primary Definition",
    "scope_note": null,
    "status": "draft",
    "maturity": "draft",
    "version": null,
    "public_access": true,
    "last_updated": null,
    "authority_score": null,
    "quality_score": null,
    "cross_domain_links": null,
    "owl_class": "mv:rb0044velocity",
    "owl_physicality": "ConceptualEntity",
    "owl_role": "Concept",
    "owl_inferred_class": null,
    "is_subclass_of": [],
    "has_part": [],
    "is_part_of": [],
    "requires": [],
    "depends_on": [],
    "enables": [],
    "relates_to": [],
    "bridges_to": [],
    "bridges_from": [],
    "domain_extensions": {},
    "belongs_to_domain": [
      "MetaverseDomain"
    ],
    "implemented_in_layer": [],
    "source": [],
    "validation": {
      "is_valid": false,
      "errors": [
        "Missing required property: last-updated",
        "Missing required property: is-subclass-of (at least one parent class)",
        "owl:class namespace 'mv' doesn't match source-domain 'metaverse'"
      ]
    }
  }
}