{
  "id": "Virtual Production Volume",
  "title": "Virtual Production Volume",
  "content": "- ### OntologyBlock\n  id:: virtual-production-volume-ontology\n  collapsed:: true\n\t- ontology:: true\n\t- term-id:: 20158\n\t- preferred-term:: Virtual Production Volume\n\t- status:: draft\n\t- public-access:: true\n\t- definition:: Large-scale physical LED wall or projection stage environment that merges live-action footage with real-time rendered 3D backgrounds, including LED panels, tracking systems, camera infrastructure, and stage hardware.\n\t- source:: [[SMPTE ST 2117]]\n\t- maturity:: mature\n\t- owl:class:: mv:VirtualProductionVolume\n\t- owl:physicality:: PhysicalEntity\n\t- owl:role:: Object\n\t- owl:inferred-class:: mv:PhysicalObject\n\t- owl:functional-syntax:: true\n\t- belongsToDomain:: [[CreativeMediaDomain]]\n\t- implementedInLayer:: [[ApplicationLayer]]\n\t- #### Relationships\n\t  id:: virtual-production-volume-relationships\n\t  collapsed:: true\n\t\t- is-part-of:: [[Film Production Studio]]\n\t\t- is-part-of:: [[Virtual Production Pipeline]]\n\t\t- has-part:: [[Display Processor]]\n\t\t- has-part:: [[Lighting Rig]]\n\t\t- has-part:: [[LED Wall]]\n\t\t- has-part:: [[Camera Tracking System]]\n\t\t- has-part:: [[Rendering Cluster]]\n\t\t- has-part:: [[Physical Stage]]\n\t\t- requires:: [[Color Management System]]\n\t\t- requires:: [[Network Infrastructure]]\n\t\t- requires:: [[Camera Tracking]]\n\t\t- requires:: [[Real-time Rendering Engine]]\n\t\t- enables:: [[In-Camera VFX]]\n\t\t- enables:: [[Interactive Filmmaking]]\n\t\t- enables:: [[Real-time Background Rendering]]\n\t\t- enables:: [[Virtual Location]]\n\t\t- depends-on:: [[ISO/IEC 23090-3]]\n\t\t- depends-on:: [[SMPTE ST 2117]]\n\n## Academic Context\n\n- Definition and foundational concepts\n  - On-set virtual production (OSVP) represents a paradigm shift from traditional green-screen compositing workflows[3]\n  - The Volume functions as an integrated ecosystem combining LED panels, real-time rendering engines, camera tracking systems, and computational infrastructure[1]\n  - Terminology varies across industry: OSVP, In-Camera Visual Effects (ICVFX), immersive virtual production (IVP), and simply \"The Volume\" are used interchangeably[3]\n- Key technical distinction from predecessor technologies\n  - Unlike virtual studio technology, OSVP captures virtual environments directly in-camera rather than compositing them in post-production[3]\n  - Objects on set receive interactive lighting from LED screens, creating realistic illumination effects that would otherwise require extensive post-production correction[3]\n  - Natural optical phenomena—lens distortion, depth of field, bokeh, and lens flare—are captured natively, approximating location shooting more authentically than green-screen alternatives[3]\n\n## Current Landscape (2025)\n\n- Industry adoption and technical maturity\n  - Virtual production platforms now represent integrated software and hardware ecosystems enabling real-time blending of virtual elements with live-action footage[2]\n  - Game engines, particularly Unreal Engine (versions 5.3 through 5.5), provide real-time rendering with substantially improved performance and artist-friendly toolsets[5]\n  - Hardware and software improvements have made the technology increasingly accessible; graphics card costs have decreased whilst computational power has increased exponentially[5]\n  - The misconception that volumes deliver tenfold cost savings has been corrected; producers now recognise their genuine strengths in vehicle process shots, rapid environment creation, and dynamic set repositioning[5]\n- Core technical capabilities\n  - LED volumes display high-resolution, computer-generated backgrounds rendered in real-time, responding dynamically to camera movements and lighting changes[2]\n  - Camera tracking systems (such as Stype and Mosys) capture low-latency positional data, enabling parallax depth cues to render correctly as the camera moves through the virtual scene[3]\n  - Virtual Art Departments (VAD) construct digital environments using game engines with real-world scale and precision, working in harmony with traditional art departments to ensure seamless integration of physical and virtual elements[1]\n- Notable implementations and organisations\n  - Disney's *The Mandalorian* established widespread industry recognition, demonstrating how exotic and alien locations could be created within soundstages using Unreal Engine and LED walls[2]\n  - Amazon Studios has formalised OSVP terminology and workflows through their production portal, standardising best practices across their content[1]\n  - Netflix and other major streaming platforms have integrated virtual production into standard production pipelines[7]\n- UK and North England context\n  - Information regarding specific North England implementations (Manchester, Leeds, Newcastle, Sheffield) is not currently available in established technical literature\n  - UK production facilities have adopted virtual production infrastructure, though comprehensive regional case studies remain limited in publicly available sources\n  - The technology is increasingly relevant to UK independent producers seeking to reduce location-dependent costs and scheduling constraints\n\n- Standards and frameworks\n  - Industry organisations including SMPTE, the Academy of Motion Picture Arts and Sciences, and the American Society of Cinematographers have initiated formal support for OSVP development[3]\n  - Standardisation efforts remain ongoing, particularly regarding LED specifications, camera tracking protocols, and real-time rendering benchmarks\n\n## Technical Architecture\n\n- Hardware components\n  - LED panel arrays with integrated processors, typically housed within soundstages[1]\n  - Camera tracking systems providing sub-millimetre positional accuracy[3]\n  - Computational clusters running real-time rendering engines[1]\n  - Traditional lighting and grip equipment adapted for LED volume environments[5]\n- Software infrastructure\n  - Real-time game engines (Unreal Engine 5.x) as the primary rendering backbone[2][5]\n  - Previsualisation and technical visualisation tools for planning and optimisation[6]\n  - Motion capture systems for character performance integration[6]\n  - Virtual Art Department software for environment construction and asset management[1]\n- Workflow integration\n  - Previsualisation and technical visualisation enable directors to plan camera angles, movements, and set layouts before principal photography[6]\n  - Real-time visualisation allows cast and crew to interact with environments during filming, improving performance authenticity and creative decision-making[2]\n  - Hybrid workflows seamlessly combine live-action and digital elements without traditional post-production compositing[6]\n\n## Research & Literature\n\n- Key technical references\n  - On-set virtual production represents an application of extended reality technologies, formally documented in entertainment technology literature[3]\n  - Real-time rendering advancements, particularly Nanite technology in Unreal Engine 5.3+, have substantially reduced environment creation timelines[5]\n  - Camera tracking and motion capture integration enables accurate parallax rendering, a critical technical requirement for photorealistic results[3]\n- Ongoing research directions\n  - Optimisation of LED panel specifications for various cinematographic requirements\n  - Integration of AI-assisted environment generation to accelerate virtual art department workflows\n  - Standardisation of OSVP protocols across equipment manufacturers and software platforms\n  - Cost-benefit analysis across different production types and scales\n\n## Future Directions\n\n- Emerging technological trends\n  - Continued reduction in computational costs and increased accessibility for mid-tier productions[5]\n  - Enhanced real-time graphics quality approaching photorealistic standards[5]\n  - Integration of AI tools for rapid environment generation and asset creation\n  - Expansion of LED volume capabilities beyond traditional soundstage constraints\n- Anticipated challenges\n  - Standardisation across fragmented hardware and software ecosystems remains incomplete\n  - Training and workforce development lag behind technological advancement\n  - Initial capital investment remains substantial despite declining costs\n  - Balancing creative flexibility with technical constraints of real-time rendering\n- Industry evolution\n  - Virtual production is transitioning from novelty to standard practice across major studios\n  - Smaller independent productions increasingly adopt the technology as costs decrease\n  - Hybrid workflows combining OSVP with traditional techniques are becoming the norm rather than exception\n\n---\n\n**Note on methodology:** This entry reflects current technical understanding as of November 2025. Specific North England case studies and UK-specific implementations remain underrepresented in publicly available technical literature; this represents an opportunity for regional documentation and research contribution.\n\n## Metadata\n\n- **Last Updated**: 2025-11-11\n- **Review Status**: Comprehensive editorial review\n- **Verification**: Academic sources verified\n- **Regional Context**: UK/North England where applicable",
  "backlinks": [
    "Network Infrastructure"
  ],
  "wiki_links": [
    "Color Management System",
    "SMPTE ST 2117",
    "Virtual Production Pipeline",
    "Camera Tracking",
    "Rendering Cluster",
    "Camera Tracking System",
    "In-Camera VFX",
    "Real-time Rendering Engine",
    "ApplicationLayer",
    "ISO/IEC 23090-3",
    "Network Infrastructure",
    "Display Processor",
    "Virtual Location",
    "Film Production Studio",
    "Lighting Rig",
    "Real-time Background Rendering",
    "Physical Stage",
    "Interactive Filmmaking",
    "LED Wall",
    "CreativeMediaDomain"
  ],
  "ontology": {
    "term_id": "20158",
    "preferred_term": "Virtual Production Volume",
    "alt_terms": [],
    "iri": "http://narrativegoldmine.com/metaverse#VirtualProductionVolume",
    "source_domain": null,
    "domain": "mv",
    "domain_full_name": "Metaverse",
    "definition": "Large-scale physical LED wall or projection stage environment that merges live-action footage with real-time rendered 3D backgrounds, including LED panels, tracking systems, camera infrastructure, and stage hardware.",
    "scope_note": null,
    "status": "draft",
    "maturity": "mature",
    "version": null,
    "public_access": true,
    "last_updated": null,
    "authority_score": null,
    "quality_score": null,
    "cross_domain_links": null,
    "owl_class": "mv:VirtualProductionVolume",
    "owl_physicality": "PhysicalEntity",
    "owl_role": "Object",
    "owl_inferred_class": "mv:PhysicalObject",
    "is_subclass_of": [],
    "has_part": [
      "Display Processor",
      "Lighting Rig",
      "LED Wall",
      "Camera Tracking System",
      "Rendering Cluster",
      "Physical Stage"
    ],
    "is_part_of": [
      "Film Production Studio",
      "Virtual Production Pipeline"
    ],
    "requires": [
      "Color Management System",
      "Network Infrastructure",
      "Camera Tracking",
      "Real-time Rendering Engine"
    ],
    "depends_on": [
      "ISO/IEC 23090-3",
      "SMPTE ST 2117"
    ],
    "enables": [
      "In-Camera VFX",
      "Interactive Filmmaking",
      "Real-time Background Rendering",
      "Virtual Location"
    ],
    "relates_to": [],
    "bridges_to": [],
    "bridges_from": [],
    "domain_extensions": {},
    "belongs_to_domain": [
      "CreativeMediaDomain"
    ],
    "implemented_in_layer": [
      "ApplicationLayer"
    ],
    "source": [
      "SMPTE ST 2117"
    ],
    "validation": {
      "is_valid": false,
      "errors": [
        "Missing required property: source-domain",
        "Missing required property: last-updated",
        "Missing required property: is-subclass-of (at least one parent class)",
        "term-id '20158' doesn't match domain 'mv' (expected MV-)"
      ]
    }
  }
}