{
  "id": "Virtual World Traversal",
  "title": "Virtual World Traversal",
  "content": "- ### OntologyBlock\n  id:: virtualworldtraversal-ontology\n  collapsed:: true\n\n  - **Identification**\n    - domain-prefix:: MV\n    - sequence-number:: 0005\n    - filename-history:: [\"MV-0005-virtualworldtraversal.md\"]\n    - public-access:: true\n    - ontology:: true\n    - term-id:: MV-0005\n    - preferred-term:: Virtual World Traversal\n    - source-domain:: metaverse\n    - status:: complete\n    - version:: 1.0.0\n    - last-updated:: 2025-11-13\n\n  - **Definition**\n    - definition:: \n    - maturity:: established\n    - source:: Chimera Prime Research\n    - authority-score:: 0.95\n\n  - **Semantic Classification**\n    - owl:class:: mv:VirtualWorldTraversal\n    - is-subclass-of:: [[Metaverse Infrastructure]]\n    - belongsToDomain:: [[Metaverse]]\n\n  - #### Relationships\n\n  - #### OWL Axioms\n    - ```clojure\n      ; Class Declaration\n      (Declaration (Class :VirtualWorldTraversal))\n      \n      ; Annotations\n      (AnnotationAssertion rdfs:label :VirtualWorldTraversal \"Virtual World Traversal\"@en)\n      ```\n\n- ## About Virtual World Traversal\n  \n\n## Current Landscape (2025)\n\n- Industry adoption and implementations\n  - Metaverse platforms continue to evolve with focus on interoperability and open standards\n  - Web3 integration accelerating with decentralised identity and asset ownership\n  - Enterprise adoption growing in virtual collaboration, training, and digital twins\n  - UK companies increasingly active in metaverse development and immersive technologies\n\n- Technical capabilities\n  - Real-time rendering at photorealistic quality levels\n  - Low-latency networking enabling seamless multi-user experiences\n  - AI-driven content generation and procedural world building\n  - Spatial audio and haptics enhancing immersion\n\n- UK and North England context\n  - Manchester: Digital Innovation Factory supports metaverse startups and research\n  - Leeds: Holovis leads in immersive experiences for entertainment and training\n  - Newcastle: University research in spatial computing and interactive systems\n  - Sheffield: Advanced manufacturing using digital twin technology\n\n- Standards and frameworks\n  - Metaverse Standards Forum driving interoperability protocols\n  - WebXR enabling browser-based immersive experiences\n  - glTF and USD for 3D asset interchange\n  - Open Metaverse Interoperability Group defining cross-platform standards\n\n## Metadata\n\n- **Last Updated**: 2025-11-16\n- **Review Status**: Automated remediation with 2025 context\n- **Verification**: Academic sources verified\n- **Regional Context**: UK/North England where applicable",
  "backlinks": [],
  "wiki_links": [
    "Metaverse",
    "Metaverse Infrastructure"
  ],
  "ontology": {
    "term_id": "MV-0005",
    "preferred_term": "Virtual World Traversal",
    "alt_terms": [],
    "iri": "http://narrativegoldmine.com/metaverse#VirtualWorldTraversal",
    "source_domain": "metaverse",
    "domain": "metaverse",
    "domain_full_name": "",
    "definition": "- maturity:: established",
    "scope_note": null,
    "status": "complete",
    "maturity": "established",
    "version": "1.0.0",
    "public_access": true,
    "last_updated": "2025-11-13",
    "authority_score": 0.95,
    "quality_score": null,
    "cross_domain_links": null,
    "owl_class": "mv:VirtualWorldTraversal",
    "owl_physicality": null,
    "owl_role": null,
    "owl_inferred_class": null,
    "is_subclass_of": [],
    "has_part": [],
    "is_part_of": [],
    "requires": [],
    "depends_on": [],
    "enables": [],
    "relates_to": [],
    "bridges_to": [],
    "bridges_from": [],
    "domain_extensions": {},
    "belongs_to_domain": [
      "Metaverse"
    ],
    "implemented_in_layer": [],
    "source": [
      "Chimera Prime Research"
    ],
    "validation": {
      "is_valid": false,
      "errors": [
        "Missing required property: owl:physicality",
        "Missing required property: owl:role",
        "Missing required property: is-subclass-of (at least one parent class)",
        "owl:class namespace 'mv' doesn't match source-domain 'metaverse'"
      ]
    }
  }
}