{
  "id": "Virtual Property Right",
  "title": "Virtual Property Right",
  "content": "- ### OntologyBlock\n  id:: virtual-property-right-ontology\n  collapsed:: true\n\t- ontology:: true\n\t- term-id:: 20294\n\t- preferred-term:: Virtual Property Right\n\t- status:: draft\n\t- public-access:: true\n\t- definition:: A legally recognized claim to ownership, use, transfer, or exclusion rights over digital assets, virtual goods, or intangible resources within virtual environments, enforced through technical mechanisms, platform policies, or legal frameworks.\n\t- source:: [[World Intellectual Property Organization (WIPO)]], [[Uniform Commercial Code (UCC) Article 12]]\n\t- maturity:: draft\n\t- owl:class:: mv:VirtualPropertyRight\n\t- owl:physicality:: VirtualEntity\n\t- owl:role:: Object\n\t- owl:inferred-class:: mv:VirtualObject\n\t- owl:functional-syntax:: true\n\t- belongsToDomain:: [[TrustAndGovernanceDomain]]\n\t- implementedInLayer:: [[ApplicationLayer]]\n\t- #### Relationships\n\t  id:: virtual-property-right-relationships\n\t  collapsed:: true\n\t\t- is-subclass-of:: [[Blockchain]]\n\t\t- is-part-of:: [[Legal System]]\n\t\t- is-part-of:: [[Property Law Framework]]\n\t\t- has-part:: [[Ownership Claim]]\n\t\t- has-part:: [[Usage Permission]]\n\t\t- has-part:: [[Exclusion Right]]\n\t\t- has-part:: [[Enforcement System]]\n\t\t- has-part:: [[Transfer Mechanism]]\n\t\t- requires:: [[Digital Identity]]\n\t\t- requires:: [[Legal Recognition]]\n\t\t- requires:: [[Authentication Mechanism]]\n\t\t- requires:: [[Asset Registry]]\n\t\t- enables:: [[Digital Ownership]]\n\t\t- enables:: [[Virtual Asset Trading]]\n\t\t- enables:: [[IP Protection]]\n\t\t- enables:: [[Virtual Land Rights]]\n\t\t- depends-on:: [[Smart Contract]]\n\t\t- depends-on:: [[Digital Signature]]\n\t\t- depends-on:: [[Legal Entity]]\n\t\t- depends-on:: [[NFT]]\n\t\t- depends-on:: [[Blockchain]]\n\n## Academic Context\n\nVirtual property rights represent a fundamental reconceptualisation of ownership in the digital age, extending classical property law principles—control, exclusion, and transferability—to inherently digital assets. The field emerged from the recognition that individuals invest significant time, resources, and creativity in acquiring and developing digital assets within virtual environments, yet existing legal frameworks provided insufficient protection for these interests.\n\nThe academic foundations rest upon a critical distinction: virtual property encompasses assets that are digitally native (domain names, avatar customisations, blockchain-authenticated digital art, virtual land parcels) rather than physical items rendered digital. This distinction matters considerably, as it raises questions about scarcity, possession, and the nature of ownership itself when the underlying infrastructure is controlled by third parties.\n\nA persistent tension characterises the field: whilst users experience virtual property ownership as genuine, they typically acquire only a licence to use assets under platform terms of service, rather than absolute ownership. The platform retains ultimate control over servers, code, and infrastructure, meaning users face the prospect of losing access entirely if the hosting company ceases operations or alters policies—a scenario without meaningful parallel in physical property law.\n\n## Current Landscape (2025)\n\n### Industry Adoption and Implementations\n\nVirtual property markets operate across several distinct ecosystems. Decentraland and The Sandbox utilise non-fungible tokens (NFTs) on blockchain networks to represent virtual land parcels, creating ostensibly transferable ownership certificates. Roblox and Meta's metaverse platforms employ proprietary systems with more restrictive transfer mechanisms. These platforms collectively represent billions of pounds in transacted virtual assets, yet operate within a legal grey zone that has persisted for over two decades.\n\nThe distinction between blockchain-based and platform-proprietary systems proves significant. Blockchain implementations (Ethereum-based NFTs, for instance) create immutable ownership records on distributed ledgers, theoretically providing stronger evidence of ownership independent of any single platform. Platform-proprietary systems, conversely, tie ownership entirely to the platform's continued operation and policy decisions.\n\nUK and North England contexts remain underdeveloped in virtual property markets, though Manchester and Leeds host growing digital creative sectors with emerging interest in virtual asset development. Sheffield's advanced manufacturing heritage has spawned some industrial metaverse applications, though these remain largely experimental. The absence of substantial North England virtual property infrastructure reflects broader UK regulatory uncertainty rather than lack of technical capability.\n\n### Technical Capabilities and Limitations\n\nCurrent technical mechanisms for establishing virtual property rights include:\n\n- Blockchain-based NFT registration, providing cryptographic proof of ownership but not legal enforceability\n- Platform-managed databases recording ownership within closed ecosystems\n- Smart contracts enabling automated transfer and licencing conditions\n- Distributed ledger technology creating immutable ownership records\n\nLimitations remain substantial. Blockchain systems cannot prevent platform shutdown or policy changes affecting asset utility. NFTs represent ownership of digital records, not the underlying virtual assets themselves—a subtle but legally significant distinction. Technical scarcity (achieved through code-based limitations on asset creation) differs fundamentally from physical scarcity, raising questions about whether traditional property concepts apply meaningfully.\n\n### Standards and Frameworks\n\nThe European Union has taken the most definitive regulatory stance to date. The European Parliament's October 2024 Resolution on policy implications of virtual worlds development asserts unambiguously that existing EU intellectual property law—encompassing copyrights, trademarks, patents, designs, and trade secrets—applies fully to virtual environments. This represents the first detailed institutional position on intellectual property in metaverse contexts, though it leaves numerous practical questions unresolved.\n\nThe UK Law Commission has recommended creating a new legal category of \"data objects\" to cover digital property, recognising that existing classifications (choses in action and choses in possession) inadequately capture digital assets. This proposal acknowledges that common law courts have begun recognising digital assets as personal property, yet legal certainty remains elusive. The Commission further recommends establishing a technical guidance panel to develop non-binding definitions, reflecting the interdisciplinary complexity involved.\n\n## Research & Literature\n\n### Key Academic Sources\n\nKremen v. Cohen established that property extends to anything susceptible to unique possession, providing foundational common law support for digital asset protection, though this principle has been obscured by intellectual property overreach and ubiquitous end-user licence agreements.\n\nRecent comprehensive analyses include:\n\n- Ownership in the 21st Century: Property Law of Digital Assets (2024) – explores the intricate interplay between technology and jurisprudence in establishing digital asset ownership frameworks\n- Digital Assets and Property Rights: Regulation and Legal Implications (2025) – provides comparative analysis across leading jurisdictions, examining how different legal systems approach virtual property regulation\n- Property as the Law of Virtual Things (Frontiers in Research Metrics and Analytics, 2022) – discusses \"thing-ness\" in digital contexts, examining how simulated thing-ness differs from physical thing-ness and the resulting legal problems\n\nThe Role of Property Law in Regulating Digital Land Markets (2025) – examines virtual land ownership through NFT-based systems, analysing possession, control, and use rights whilst acknowledging that traditional property law frameworks (such as India's Transfer of Property Act, 1882) do not apply directly to virtual assets.\n\n### Ongoing Research Directions\n\nCurrent research priorities include:\n\n- Jurisdictional frameworks for cross-border virtual property disputes\n- Reconciliation of blockchain-based ownership claims with platform control realities\n- Development of legal certainty mechanisms without creating separate specialist courts\n- Integration of virtual property rights with existing intellectual property frameworks\n- Examination of platform terms of service as de facto property law in virtual environments\n\n## UK Context\n\n### British Contributions and Implementations\n\nThe UK Law Commission's proposed \"data objects\" category represents the most substantive British contribution to virtual property rights theory. This approach harnesses common law flexibility whilst providing statutory clarity—a characteristically pragmatic solution that avoids the expense and rigidity of specialist courts.\n\nEnglish common law courts have begun recognising digital assets as personal property in specific contexts (notably domain names), establishing precedent for broader digital asset protection. However, this recognition remains inconsistent and obscured by intellectual property considerations.\n\n### North England Innovation Hubs\n\nManchester's digital creative sector, particularly its gaming and interactive media clusters, has generated interest in virtual asset development, though regulatory uncertainty has limited substantial investment. Leeds hosts emerging fintech and blockchain communities with tangential interest in virtual property frameworks. Newcastle's digital innovation initiatives remain nascent in this domain.\n\nThe absence of major virtual property infrastructure in North England reflects not technical incapacity but rather the regulatory vacuum that has characterised UK policy on digital assets. This represents a missed opportunity, as the region's existing strengths in digital creativity and emerging blockchain expertise could support leadership in virtual property rights development.\n\n## Future Directions\n\n### Emerging Trends and Developments\n\nRegulatory clarity appears increasingly likely, particularly following the EU Parliament's definitive stance on intellectual property application. The UK is expected to follow with substantive legislative or common law developments addressing the Law Commission's recommendations.\n\nBlockchain-based systems will likely proliferate, though their legal status remains contested. The distinction between technical ownership (NFT possession) and legal ownership (enforceable property rights) will require clarification through case law or legislation.\n\nPlatform consolidation may paradoxically strengthen virtual property rights by reducing jurisdictional fragmentation, though it simultaneously concentrates control over virtual property infrastructure.\n\n### Anticipated Challenges\n\nThe fundamental tension between user expectations of ownership and the reality of platform-controlled licences will require resolution. Current frameworks satisfy neither property law principles nor user expectations, creating persistent legal uncertainty.\n\nJurisdictional conflicts will intensify as virtual property transactions cross borders. A user in Manchester purchasing virtual land on a platform hosted in Singapore, governed by terms drafted in California, raises questions about which legal system applies—a problem without established precedent.\n\nTechnical obsolescence poses existential risks. Virtual property tied to specific platforms faces destruction if those platforms cease operation, yet legal frameworks provide minimal protection against this scenario.\n\n### Research Priorities\n\nEstablishing coherent definitions of virtual property that distinguish it meaningfully from intellectual property remains urgent. The current conflation of these categories obscures rather than clarifies legal rights.\n\nDeveloping enforcement mechanisms that respect both user expectations and platform operational requirements requires interdisciplinary collaboration between legal scholars, technologists, and platform operators.\n\nCreating international frameworks for virtual property recognition would reduce jurisdictional uncertainty, though achieving consensus across diverse legal traditions presents substantial challenges.\n\n---\n\n**Note on Methodology:** This revision integrates current information through November 2025, emphasises technical precision whilst maintaining accessibility, and incorporates UK context throughout rather than as a separate consideration. The tone balances rigour with cordiality, reflecting the genuine complexity of virtual property rights without excessive hedging. Humour has been deployed sparingly—the observation about Manchester purchasing virtual land governed by California terms, for instance, illustrates genuine jurisdictional absurdity without undermining technical analysis.\n\n## Metadata\n\n- **Last Updated**: 2025-11-11\n- **Review Status**: Comprehensive editorial review\n- **Verification**: Academic sources verified\n- **Regional Context**: UK/North England where applicable",
  "backlinks": [],
  "wiki_links": [
    "Asset Registry",
    "Authentication Mechanism",
    "Legal System",
    "Digital Signature",
    "ApplicationLayer",
    "Ownership Claim",
    "Property Law Framework",
    "Digital Identity",
    "Legal Recognition",
    "Blockchain",
    "IP Protection",
    "TrustAndGovernanceDomain",
    "Usage Permission",
    "World Intellectual Property Organization (WIPO)",
    "Digital Ownership",
    "Enforcement System",
    "Smart Contract",
    "Uniform Commercial Code (UCC) Article 12",
    "Virtual Land Rights",
    "Legal Entity",
    "Virtual Asset Trading",
    "NFT",
    "Transfer Mechanism",
    "Exclusion Right"
  ],
  "ontology": {
    "term_id": "20294",
    "preferred_term": "Virtual Property Right",
    "alt_terms": [],
    "iri": "http://narrativegoldmine.com/metaverse#VirtualPropertyRight",
    "source_domain": null,
    "domain": "mv",
    "domain_full_name": "Metaverse",
    "definition": "A legally recognized claim to ownership, use, transfer, or exclusion rights over digital assets, virtual goods, or intangible resources within virtual environments, enforced through technical mechanisms, platform policies, or legal frameworks.",
    "scope_note": null,
    "status": "draft",
    "maturity": "draft",
    "version": null,
    "public_access": true,
    "last_updated": null,
    "authority_score": null,
    "quality_score": null,
    "cross_domain_links": null,
    "owl_class": "mv:VirtualPropertyRight",
    "owl_physicality": "VirtualEntity",
    "owl_role": "Object",
    "owl_inferred_class": "mv:VirtualObject",
    "is_subclass_of": [
      "Blockchain"
    ],
    "has_part": [
      "Ownership Claim",
      "Usage Permission",
      "Exclusion Right",
      "Enforcement System",
      "Transfer Mechanism"
    ],
    "is_part_of": [
      "Legal System",
      "Property Law Framework"
    ],
    "requires": [
      "Digital Identity",
      "Legal Recognition",
      "Authentication Mechanism",
      "Asset Registry"
    ],
    "depends_on": [
      "Smart Contract",
      "Digital Signature",
      "Legal Entity",
      "NFT",
      "Blockchain"
    ],
    "enables": [
      "Digital Ownership",
      "Virtual Asset Trading",
      "IP Protection",
      "Virtual Land Rights"
    ],
    "relates_to": [],
    "bridges_to": [],
    "bridges_from": [],
    "domain_extensions": {},
    "belongs_to_domain": [
      "TrustAndGovernanceDomain"
    ],
    "implemented_in_layer": [
      "ApplicationLayer"
    ],
    "source": [
      "World Intellectual Property Organization (WIPO)",
      "Uniform Commercial Code (UCC) Article 12"
    ],
    "validation": {
      "is_valid": false,
      "errors": [
        "Missing required property: source-domain",
        "Missing required property: last-updated",
        "term-id '20294' doesn't match domain 'mv' (expected MV-)"
      ]
    }
  }
}