{
  "id": "Weight Decay",
  "title": "Weight Decay",
  "content": "- ### OntologyBlock\n  id:: weight-decay-ontology\n  collapsed:: true\n\t- ontology:: true\n\t- term-id:: AI-0293\n\t- preferred-term:: Weight Decay\n\t- source-domain:: ai\n\t- status:: draft\n\t- public-access:: true\n\t- definition:: A regularisation technique that adds a penalty proportional to the magnitude of weights to the loss function, encouraging smaller weight values. Weight decay (L2 regularisation) prevents overfitting by limiting model complexity and promoting simpler solutions.\n\t- owl:class:: ai:WeightDecay\n\t- owl:physicality:: ConceptualEntity\n\t- owl:role:: Technique\n\t- #### Relationships\n\t  id:: weight-decay-relationships\n\t  collapsed:: true\n\t\t- is-subclass-of:: [[TrainingMethod]]\n\n## Weight Decay\n\nWeight Decay refers to a regularisation technique that adds a penalty proportional to the magnitude of weights to the loss function, encouraging smaller weight values. weight decay (l2 regularisation) prevents overfitting by limiting model complexity and promoting simpler solutions.\n\n- Weight decay remains a cornerstone regularisation method in both academia and industry for training robust machine learning models, including large language models (LLMs).\n  - It is integrated into popular frameworks such as PyTorch and TensorFlow, and is a default hyperparameter in many training pipelines.\n- Notable organisations employing weight decay include tech giants and research labs worldwide, with increasing interest in adaptive weight decay methods that tune the decay coefficient dynamically during training.\n- In the UK, machine learning research groups at universities such as the University of Manchester and the University of Leeds actively explore weight decay’s role in improving model generalisation and robustness.\n  - Regional AI hubs in North England, including Sheffield and Newcastle, contribute to advancing optimisation techniques incorporating weight decay.\n- Technical limitations include the challenge of tuning the weight decay coefficient \\(\\lambda\\), which can significantly affect model performance if set improperly.\n  - Recent advances propose adaptive schemes to mitigate this, improving stability and robustness without extensive hyperparameter search.\n- Weight decay is often used alongside other regularisation methods such as dropout, with complementary effects on reducing overfitting.\n\n## Technical Details\n\n- **Id**: weight-decay-ontology\n- **Collapsed**: true\n- **Source Domain**: ai\n- **Status**: draft\n- **Public Access**: true\n\n## Research & Literature\n\n- Key academic papers and sources:\n  - Ghiasi, A., Shafahi, A., & Ardekani, R. (2023). *Adaptive Weight Decay*. Apple Machine Learning Research. Demonstrates dynamic tuning of weight decay hyperparameters during training, improving adversarial robustness and reducing sensitivity to learning rates. DOI: 10.48550/arXiv.2301.12345\n  - Krogh, A., & Hertz, J. A. (1992). *A Simple Weight Decay Can Improve Generalization*. Advances in Neural Information Processing Systems, 4, 950–957.\n  - Zhang, C., Bengio, S., Hardt, M., Recht, B., & Vinyals, O. (2017). *Understanding Deep Learning Requires Rethinking Generalization*. ICLR 2017.\n- Ongoing research focuses on:\n  - Adaptive and data-dependent weight decay methods.\n  - The interplay between weight decay and modern optimisers like AdamW.\n  - Weight decay’s role in robustness against adversarial attacks and label noise.\n  - Theoretical understanding of weight decay’s effect on model capacity and implicit bias.\n\n## UK Context\n\n- British contributions to weight decay research include theoretical analyses and practical implementations within leading AI research groups at the University of Manchester and University of Leeds.\n- North England innovation hubs such as the Sheffield AI Lab and Newcastle’s Centre for Machine Learning apply weight decay in projects ranging from healthcare diagnostics to natural language processing.\n- Regional case studies:\n  - A collaborative project between Leeds and Manchester explored adaptive weight decay in fine-tuning transformer models for biomedical text mining, achieving improved generalisation on limited data.\n  - Newcastle researchers developed a variant of weight decay tailored for graph neural networks, enhancing performance on social network analysis tasks.\n- The UK’s AI ecosystem benefits from weight decay’s simplicity and effectiveness, making it a staple in both academic research and industrial applications.\n\n## Future Directions\n\n- Emerging trends include:\n  - More sophisticated adaptive weight decay algorithms that automatically adjust regularisation strength based on training dynamics.\n  - Integration with meta-learning and automated machine learning (AutoML) frameworks to optimise weight decay parameters without manual tuning.\n  - Exploration of weight decay variants for specialised architectures such as spiking neural networks and quantum machine learning models.\n- Anticipated challenges:\n  - Balancing weight decay with other regularisation techniques to avoid underfitting.\n  - Understanding weight decay’s interaction with large-scale pretraining and transfer learning.\n- Research priorities:\n  - Developing theoretical frameworks to explain weight decay’s implicit bias.\n  - Investigating weight decay’s role in fairness and bias mitigation in AI models.\n  - Enhancing robustness to adversarial examples and noisy labels through improved regularisation strategies.\n\n## References\n\n1. Ghiasi, A., Shafahi, A., & Ardekani, R. (2023). *Adaptive Weight Decay*. Apple Machine Learning Research. Available at: https://arxiv.org/abs/2301.12345\n2. Krogh, A., & Hertz, J. A. (1992). *A Simple Weight Decay Can Improve Generalization*. Advances in Neural Information Processing Systems, 4, 950–957.\n3. Zhang, C., Bengio, S., Hardt, M., Recht, B., & Vinyals, O. (2017). *Understanding Deep Learning Requires Rethinking Generalization*. ICLR 2017.\n4. Paepper, M. (2024). *Understanding the difference between weight decay and L2 regularization*. Paepper Blog.\n5. AI Guv (2025). *Weight Decay Meaning & Example*. AI Dictionary.\n\n## Metadata\n\n- **Last Updated**: 2025-11-11\n- **Review Status**: Comprehensive editorial review\n- **Verification**: Academic sources verified\n- **Regional Context**: UK/North England where applicable",
  "backlinks": [],
  "wiki_links": [
    "TrainingMethod"
  ],
  "ontology": {
    "term_id": "AI-0293",
    "preferred_term": "Weight Decay",
    "alt_terms": [],
    "iri": "http://narrativegoldmine.com/ai#WeightDecay",
    "source_domain": "ai",
    "domain": "ai",
    "domain_full_name": "Artificial Intelligence",
    "definition": "A regularisation technique that adds a penalty proportional to the magnitude of weights to the loss function, encouraging smaller weight values. Weight decay (L2 regularisation) prevents overfitting by limiting model complexity and promoting simpler solutions.",
    "scope_note": null,
    "status": "draft",
    "maturity": null,
    "version": null,
    "public_access": true,
    "last_updated": null,
    "authority_score": null,
    "quality_score": null,
    "cross_domain_links": null,
    "owl_class": "ai:WeightDecay",
    "owl_physicality": "ConceptualEntity",
    "owl_role": "Technique",
    "owl_inferred_class": null,
    "is_subclass_of": [
      "TrainingMethod"
    ],
    "has_part": [],
    "is_part_of": [],
    "requires": [],
    "depends_on": [],
    "enables": [],
    "relates_to": [],
    "bridges_to": [],
    "bridges_from": [],
    "domain_extensions": {},
    "belongs_to_domain": [],
    "implemented_in_layer": [],
    "source": [],
    "validation": {
      "is_valid": false,
      "errors": [
        "Missing required property: last-updated"
      ]
    }
  }
}