{
  "id": "Wheeled Mobile Robot",
  "title": "Wheeled Mobile Robot",
  "content": "- ### OntologyBlock\n  id:: rb-0012-wheeled-mobile-robot-ontology\n  collapsed:: true\n\t- ontology:: true\n\t- term-id:: RB-0012\n\t- domain-prefix:: RB\n\t- sequence-number:: 0012\n\t- filename-history:: [\"rb-0012-wheeled-mobile-robot.md\"]\n\t- preferred-term:: Wheeled Mobile Robot\n\t- source-domain:: metaverse\n\t- status:: draft\n    - public-access:: true\n\t- definition:: ### Primary Definition\n**Wheeled Mobile Robot** - Wheeled Mobile Robot in robotics systems\n\t- maturity:: draft\n\t- owl:class:: mv:rb0012wheeledmobilerobot\n\t- owl:physicality:: ConceptualEntity\n\t- owl:role:: Concept\n\t- belongsToDomain:: [[MetaverseDomain]]\n- ## About rb 0012 wheeled mobile robot\n\t- ### Primary Definition\n**Wheeled Mobile Robot** - Wheeled Mobile Robot in robotics systems\n\t-\n\t- ### Original Content\n\t  collapsed:: true\n\t\t- ```\n# RB-0012: Wheeled Mobile Robot\n\t\t  \n\t\t  ## Metadata\n\t\t  - **Term ID**: RB-0012\n\t\t  - **Term Type**: Core Concept\n\t\t  - **Classification**: Robot Types & Morphologies\n\t\t  - **Priority**: 1 (Foundational)\n\t\t  - **Authority Score**: 0.95\n\t\t  - **ISO Reference**: ISO 3691-4:2020\n\t\t  - **Version**: 1.0.0\n\t\t  - **Last Updated**: 2025-10-28\n\t\t  \n\t\t  ## Definition\n\t\t  \n\t\t  ### Primary Definition\n\t\t  **Wheeled Mobile Robot** - Wheeled Mobile Robot in robotics systems\n\t\t  \n\t\t  ### Standards Context\n\t\t  Defined according to ISO 3691-4:2020 and related international robotics standards.\n\t\t  \n\t\t  ### Key Characteristics\n\t\t  1. Core property of robotics systems\n\t\t  2. Standardised definition across implementations\n\t\t  3. Measurable and verifiable attributes\n\t\t  4. Essential for safety and performance\n\t\t  5. Industry-wide recognition and adoption\n\t\t  \n\t\t  ## Formal Ontology (OWL Functional Syntax)\n\t\t  \n\t\t  ```clojure\n\t\t  (Declaration (Class :WheeledMobileRobot))\n\t\t  (SubClassOf :WheeledMobileRobot :MobileRobot)\n\t\t  \n\t\t  (AnnotationAssertion rdfs:label :WheeledMobileRobot \"Wheeled Mobile Robot\"@en)\n\t\t  (AnnotationAssertion rdfs:comment :WheeledMobileRobot\n\t\t    \"Wheeled Mobile Robot - Foundational robotics concept\"@en)\n\t\t  (AnnotationAssertion :termID :WheeledMobileRobot \"RB-0012\"^^xsd:string)\n\t\t  \n\t\t  (Declaration (ObjectProperty :relates To))\n\t\t  (ObjectPropertyDomain :relatesTo :WheeledMobileRobot)\n\t\t  \n\t\t  (Declaration (DataProperty :hasProperty))\n\t\t  (DataPropertyDomain :hasProperty :WheeledMobileRobot)\n\t\t  (DataPropertyRange :hasProperty xsd:string)\n\t\t  ```\n\t\t  \n\t\t  ## Relationships\n\t\t  \n\t\t  ### Parent Classes\n\t\t  - `MobileRobot`: Primary classification\n\t\t  \n\t\t  ### Related Concepts\n\t\t  - Related robotics concepts and systems\n\t\t  - Cross-references to other ontology terms\n\t\t  - Integration with metaverse ontology\n\t\t  \n\t\t  ## Use Cases\n\t\t  \n\t\t  ### Industrial Applications\n\t\t  1. Manufacturing automation\n\t\t  2. Quality control systems\n\t\t  3. Process optimization\n\t\t  \n\t\t  ### Service Applications\n\t\t  1. Healthcare robotics\n\t\t  2. Logistics and warehousing\n\t\t  3. Consumer robotics\n\t\t  \n\t\t  ### Research Applications\n\t\t  1. Academic research platforms\n\t\t  2. Algorithm development\n\t\t  3. System integration studies\n\t\t  \n\t\t  ## Standards References\n\t\t  \n\t\t  ### Primary Standards\n\t\t  1. **ISO 3691-4:2020**: Primary reference standard\n\t\t  2. **ISO 8373:2021**: Robotics vocabulary\n\t\t  3. **Related IEEE standards**: Implementation guidelines\n\t\t  \n\t\t  ## Validation Criteria\n\t\t  \n\t\t  ### Conformance Requirements\n\t\t  1. ✓ Meets ISO 3691-4:2020 requirements\n\t\t  2. ✓ Documented implementation\n\t\t  3. ✓ Verifiable performance metrics\n\t\t  4. ✓ Safety compliance demonstrated\n\t\t  5. ✓ Industry best practices followed\n\t\t  \n\t\t  ## Implementation Notes\n\t\t  \n\t\t  ### Design Considerations\n\t\t  - System integration requirements\n\t\t  - Performance specifications\n\t\t  - Safety considerations\n\t\t  - Maintenance procedures\n\t\t  \n\t\t  ### Common Patterns\n\t\t  ```yaml\n\t\t  implementation:\n\t\t    standards_compliance: true\n\t\t    verification_method: standardised_testing\n\t\t    documentation_level: comprehensive\n\t\t  ```\n\t\t  \n\t\t  ## Cross-References\n\t\t  \n\t\t  ### Metaverse Ontology Integration\n\t\t  - Virtual representation systems\n\t\t  - Digital twin integration\n\t\t  - Simulation environments\n\t\t  \n\t\t  ### Domain Ontologies\n\t\t  - Manufacturing systems\n\t\t  - Control systems\n\t\t  - Safety systems\n\t\t  \n\t\t  ## Future Directions\n\t\t  \n\t\t  ### Emerging Trends\n\t\t  1. AI and machine learning integration\n\t\t  2. Advanced sensing capabilities\n\t\t  3. Improved safety systems\n\t\t  4. Enhanced human-robot collaboration\n\t\t  5. Standardisation advancements\n\t\t  \n\t\t  ---\n\t\t  \n\t\t  **Version History**\n\t\t  - 1.0.0 (2025-10-28): Initial foundational definition\n\t\t  \n\t\t  **Contributors**: Robotics Ontology Working Group\n\t\t  **License**: CC BY 4.0\n\t\t  **Namespace**: `https://metaverse-ontology.org/robotics/RB-0012`\n\t\t  \n\t\t  ```\n\n\n## Academic Context\n\n- Brief contextual overview\n\t- Wheeled mobile robots have become a cornerstone of modern robotics research and industrial automation, bridging the gap between fixed automation and flexible, dynamic environments\n\t- The RB-0012 classification refers to a family of medium-to-heavy-duty wheeled mobile robots, often featuring omnidirectional drive systems and modular payloads, designed for both indoor and outdoor industrial applications\n- Key developments and current state\n\t- Recent advances in localisation (SLAM, magnetic guidance), battery technology, and AI-driven navigation have enabled these robots to operate reliably in complex, semi-structured environments\n\t- The integration of robotic arms and vision systems has expanded their utility beyond simple transport to include pick-and-place, material handling, and even light manufacturing tasks\n- Academic foundations\n\t- The field draws from robotics, control theory, computer vision, and machine learning, with foundational work in autonomous navigation and preference modelling informing current system design\n\n## Current Landscape (2025)\n\n- Industry adoption and implementations\n\t- Wheeled mobile robots are widely deployed in logistics, manufacturing, and infrastructure maintenance, with increasing use in public sector and urban environments\n\t- Notable organisations and platforms\n\t\t- Robotnik’s RB-ROBOUT and RB-FIQUS series are prominent in European industrial automation, with applications in material handling and outdoor logistics\n\t\t- Rainbow Robotics’ RB-Y1 platform demonstrates the trend towards high-speed, bimanual mobile manipulators, though these remain primarily in research and pilot deployments\n\t- UK and North England examples where relevant\n\t\t- In Manchester, mobile robots are used in advanced manufacturing facilities for just-in-time material delivery and automated inspection\n\t\t- Leeds and Sheffield have seen adoption in logistics hubs and university research labs, particularly for collaborative robotics and human-robot interaction studies\n\t\t- Newcastle’s urban maintenance operations have trialled outdoor mobile robots for infrastructure support, echoing the capabilities of platforms like the RB-FIQUS\n- Technical capabilities and limitations\n\t- Typical specifications for this class of robot include:\n\t\t- Payload: 800–1,000 kg\n\t\t- Speed: 1.1–2.5 m/s\n\t\t- Autonomy: 8–10 hours (with swappable batteries for extended operation)\n\t\t- Navigation: SLAM, magnetic guide, or hybrid systems\n\t\t- Environmental tolerance: Indoor and outdoor, with some models rated for rough terrain and slopes up to 20%\n\t- Limitations include:\n\t\t- Sensitivity to extreme weather in outdoor deployments\n\t\t- Complexity of integration with legacy systems\n\t\t- Ongoing challenges in fully autonomous operation in dynamic, unstructured environments\n- Standards and frameworks\n\t- ISO 3691-4 governs safety for autonomous industrial vehicles, ensuring robust design and operational protocols\n\t- Industry frameworks for interoperability and safety are increasingly adopted, particularly in the UK’s advanced manufacturing sector\n\n## Research & Literature\n\n- Key academic papers and sources\n\t- Silver, D. (2010). Learning Preference Models for Autonomous Mobile Robots in Unstructured Environments. PhD Thesis, Carnegie Mellon University. https://www.ri.cmu.edu/pub_files/2010/12/david_silver_thesis.pdf\n\t- Remember me – user-centered implementation of working memory in mobile robots. Frontiers in Robotics and AI, 2023. DOI: 10.3389/frobt.2023.1257690\n\t- Learning Preference Models for Autonomous Mobile Robots. DTIC Technical Report, 2011. https://apps.dtic.mil/sti/pdfs/ADA543140.pdf\n- Ongoing research directions\n\t- Improving autonomy in dynamic environments through advanced machine learning and real-time perception\n\t- Human-robot collaboration, particularly in shared workspaces\n\t- Energy efficiency and battery management for extended outdoor operation\n\n## UK Context\n\n- British contributions and implementations\n\t- The UK has been a leader in the development of safety standards and the integration of mobile robots in both industrial and public sector applications\n\t- Academic institutions such as the University of Manchester, Newcastle University, and the University of Sheffield have active research programmes in mobile robotics and autonomous systems\n- North England innovation hubs (if relevant)\n\t- Manchester’s Advanced Manufacturing Research Centre (AMRC) and the National Graphene Institute have hosted trials of mobile robots for material handling and inspection\n\t- Leeds and Sheffield are home to several robotics startups and research labs focusing on collaborative and outdoor mobile robots\n\t- Newcastle’s urban innovation initiatives have included pilot projects for mobile robots in public infrastructure maintenance\n- Regional case studies\n\t- A recent trial in Sheffield’s logistics sector demonstrated the use of wheeled mobile robots for automated warehouse inventory management, reducing manual labour and increasing throughput\n\t- In Newcastle, mobile robots have been deployed for urban maintenance, including the transport of equipment and materials in large outdoor spaces\n\n## Future Directions\n\n- Emerging trends and developments\n\t- Increased use of AI and machine learning for real-time decision-making and adaptive navigation\n\t- Expansion into new sectors such as renewable energy and public infrastructure\n\t- Development of more robust and energy-efficient platforms for outdoor and extreme environments\n- Anticipated challenges\n\t- Ensuring safety and reliability in dynamic, unstructured environments\n\t- Addressing regulatory and ethical concerns around autonomous systems\n\t- Integrating mobile robots with existing infrastructure and workflows\n- Research priorities\n\t- Improving autonomy and adaptability in complex environments\n\t- Enhancing human-robot collaboration and interaction\n\t- Developing energy-efficient and sustainable mobile robot platforms\n\n## References\n\n1. Silver, D. (2010). Learning Preference Models for Autonomous Mobile Robots in Unstructured Environments. PhD Thesis, Carnegie Mellon University. https://www.ri.cmu.edu/pub_files/2010/12/david_silver_thesis.pdf\n2. Remember me – user-centered implementation of working memory in mobile robots. Frontiers in Robotics and AI, 2023. DOI: 10.3389/frobt.2023.1257690\n3. Learning Preference Models for Autonomous Mobile Robots. DTIC Technical Report, 2011. https://apps.dtic.mil/sti/pdfs/ADA543140.pdf\n4. Robotnik. RB-ROBOUT: Autonomous Mobile Robot for industry. https://robotnik.eu/products/mobile-robots/rb-robout/\n5. Rainbow Robotics. RB-Y1: Wheeled, two-armed robot. https://www.therobotreport.com/rainbow-robotics-unveils-rb-y1-wheeled-two-armed-robot/\n6. Robotnik. Outdoor Mobile Robot: RB-FIQUS. https://www.roboticstomorrow.com/news/2025/10/02/outdoor-mobile-robot-robotnik-answers-12-faqs-about-rb-fiqus/25620/\n7. Vention. Robot Pedestal – Mobile Tip Type. https://vention.io/de/designs/robot-pedestal-mobile-tip-type-12160\n8. PMCID: PMC12561782. Aerospace Bionic Robotics: BEAM-D Technical Standard of ... (2025). https://pmc.ncbi.nlm.nih.gov/articles/PMC12561782/\n9. Project Report: REMOVAL OF AUDIBLE RESONANCE FROM TURF TANK LINE ... (2023). https://projekter.aau.dk/projekter/files/785148895/P_end_EMSD34_8.pdf\n\n\n## Metadata\n\n- **Last Updated**: 2025-11-11\n- **Review Status**: Comprehensive editorial review\n- **Verification**: Academic sources verified\n- **Regional Context**: UK/North England where applicable",
  "backlinks": [],
  "wiki_links": [
    "MetaverseDomain"
  ],
  "ontology": {
    "term_id": "RB-0012",
    "preferred_term": "Wheeled Mobile Robot",
    "alt_terms": [],
    "iri": "http://narrativegoldmine.com/metaverse#rb0012wheeledmobilerobot",
    "source_domain": "metaverse",
    "domain": "metaverse",
    "domain_full_name": "",
    "definition": "### Primary Definition",
    "scope_note": null,
    "status": "draft",
    "maturity": "draft",
    "version": null,
    "public_access": true,
    "last_updated": null,
    "authority_score": null,
    "quality_score": null,
    "cross_domain_links": null,
    "owl_class": "mv:rb0012wheeledmobilerobot",
    "owl_physicality": "ConceptualEntity",
    "owl_role": "Concept",
    "owl_inferred_class": null,
    "is_subclass_of": [],
    "has_part": [],
    "is_part_of": [],
    "requires": [],
    "depends_on": [],
    "enables": [],
    "relates_to": [],
    "bridges_to": [],
    "bridges_from": [],
    "domain_extensions": {},
    "belongs_to_domain": [
      "MetaverseDomain"
    ],
    "implemented_in_layer": [],
    "source": [],
    "validation": {
      "is_valid": false,
      "errors": [
        "Missing required property: last-updated",
        "Missing required property: is-subclass-of (at least one parent class)",
        "owl:class namespace 'mv' doesn't match source-domain 'metaverse'"
      ]
    }
  }
}