{
  "id": "XLNet",
  "title": "XLNet",
  "content": "- ### OntologyBlock\n  id:: xlnet-ontology\n  collapsed:: true\n\t- ontology:: true\n\t- term-id:: AI-0221\n\t- preferred-term:: XLNet\n\t- source-domain:: metaverse\n\t- status:: draft\n\t- public-access:: true\n\n\n\n\n### OWL Classification\n\t- owl:class:: mv:XLNet\n\t- owl:physicality:: ConceptualEntity\n\t- owl:role:: Concept\n\n### Domain & Architecture\n\t- belongsToDomain:: [[MetaverseDomain]]\n\t- maturity:: draft\n\n### Relationships\n\n## OWL Formal Semantics\n\n```clojure\n;; OWL Functional Syntax\n\n(Declaration (Class :Xlnet))\n\n;; Annotations\n(AnnotationAssertion rdfs:label :Xlnet \"XLNet\"@en)\n(AnnotationAssertion rdfs:comment :Xlnet \"A generalised autoregressive pre-training method that learns bidirectional contexts by maximising expected likelihood over all permutations of the factorisation order, overcoming limitations of BERT's masked language modelling.\"@en)\n\n;; Data Properties\n(AnnotationAssertion dcterms:identifier :Xlnet \"AI-0221\"^^xsd:string)\n(DataPropertyAssertion :isAITechnology :Xlnet \"true\"^^xsd:boolean)\n```\n\n## Characteristics\n\n- **Permutation Language Modelling**: Trains on all factorisation orders\n- **Bidirectional Context**: Captures dependencies in both directions\n- **Autoregressive**: Avoids independence assumption of masked tokens\n- **Transformer-XL Integration**: Incorporates segment recurrence mechanism\n\n## Academic Foundations\n\n**Primary Source**: Yang et al., \"XLNet: Generalized Autoregressive Pretraining for Language Understanding\", arXiv:1906.08237 (2019)\n\n**Performance**: Outperforms BERT on 20 tasks including question answering, natural language inference, sentiment analysis, and document ranking.\n\n## Technical Context\n\nXLNet addresses BERT's limitations by using permutation language modelling, which trains the model to predict tokens in all possible orders. This enables learning bidirectional context whilst maintaining an autoregressive formulation that doesn't assume independence amongst masked positions.\n\n## Ontological Relationships\n\n- **Broader Term**: Pre-trained Language Model\n- **Related Terms**: BERT, Transformer-XL, Permutation Language Modelling\n- **Innovation**: Permutation Language Modelling\n\n## Usage Context\n\n\"XLNet's permutation language modelling enables bidirectional context learning without BERT's masked token independence assumption.\"\n\n## References\n\n- Yang, Z., et al. (2019). \"XLNet: Generalized Autoregressive Pretraining for Language Understanding\". arXiv:1906.08237\n\n---\n\n*Ontology Term managed by AI-Grounded Ontology Working Group*\n*UK English Spelling Standards Applied*\n\t- maturity:: draft\n\t- owl:class:: mv:XLNet\n\t- owl:physicality:: ConceptualEntity\n\t- owl:role:: Concept\n\t- is-subclass-of:: [[ArtificialIntelligence]]\n\t- belongsToDomain:: [[MetaverseDomain]]",
  "backlinks": [],
  "wiki_links": [
    "ArtificialIntelligence",
    "MetaverseDomain"
  ],
  "ontology": {
    "term_id": "AI-0221",
    "preferred_term": "XLNet",
    "alt_terms": [],
    "iri": "http://narrativegoldmine.com/metaverse#XLNet",
    "source_domain": "metaverse",
    "domain": "metaverse",
    "domain_full_name": "",
    "definition": null,
    "scope_note": null,
    "status": "draft",
    "maturity": "draft",
    "version": null,
    "public_access": true,
    "last_updated": null,
    "authority_score": null,
    "quality_score": null,
    "cross_domain_links": null,
    "owl_class": "mv:XLNet",
    "owl_physicality": "ConceptualEntity",
    "owl_role": "Concept",
    "owl_inferred_class": null,
    "is_subclass_of": [],
    "has_part": [],
    "is_part_of": [],
    "requires": [],
    "depends_on": [],
    "enables": [],
    "relates_to": [],
    "bridges_to": [],
    "bridges_from": [],
    "domain_extensions": {},
    "belongs_to_domain": [
      "MetaverseDomain",
      "MetaverseDomain"
    ],
    "implemented_in_layer": [],
    "source": [],
    "validation": {
      "is_valid": false,
      "errors": [
        "Missing required property: last-updated",
        "Missing required property: definition",
        "Missing required property: is-subclass-of (at least one parent class)",
        "owl:class namespace 'mv' doesn't match source-domain 'metaverse'"
      ]
    }
  }
}