{
  "id": "Zero-Knowledge Proof (ZKP)",
  "title": "Zero-Knowledge Proof (ZKP)",
  "content": "- ### OntologyBlock\n  id:: zero-knowledge-proof-ontology\n  collapsed:: true\n\t- ontology:: true\n\t- term-id:: 20211\n\t- preferred-term:: Zero-Knowledge Proof (ZKP)\n\t- status:: draft\n\t- public-access:: true\n\t- definition:: A cryptographic protocol that enables one party (the prover) to prove to another party (the verifier) that a statement is true without revealing any information beyond the validity of the statement itself.\n\t- source:: [[OMA3 + Reed Smith]]\n\t- maturity:: mature\n\t- owl:class:: mv:ZeroKnowledgeProof\n\t- owl:physicality:: VirtualEntity\n\t- owl:role:: Process\n\t- owl:inferred-class:: mv:VirtualProcess\n\t- owl:functional-syntax:: true\n\t- belongsToDomain:: [[TrustAndGovernanceDomain]]\n\t- implementedInLayer:: [[Middleware Layer]]\n\t- #### Relationships\n\t  id:: zero-knowledge-proof-relationships\n\t  collapsed:: true\n\t\t- is-subclass-of:: [[Metaverse]]\n\t\t- is-part-of:: [[Cryptographic Verification System]]\n\t\t- is-part-of:: [[Privacy-Preserving Protocol]]\n\t\t- has-part:: [[PLONK]]\n\t\t- has-part:: [[Interactive ZKP]]\n\t\t- has-part:: [[Non-Interactive ZKP]]\n\t\t- has-part:: [[Bulletproofs]]\n\t\t- has-part:: [[zk-SNARKs]]\n\t\t- has-part:: [[zk-STARKs]]\n\t\t- requires:: [[Elliptic Curve Cryptography]]\n\t\t- requires:: [[Polynomial Commitment Scheme]]\n\t\t- requires:: [[Cryptographic Hash Function]]\n\t\t- enables:: [[Private Authentication]]\n\t\t- enables:: [[Confidential Transactions]]\n\t\t- enables:: [[Privacy-Preserving Identity]]\n\t\t- enables:: [[Verifiable Computation]]\n\t\t- depends-on:: [[Computational Complexity Theory]]\n\t\t- depends-on:: [[Algebraic Circuits]]\n\t\t- depends-on:: [[Number Theory]]\n\n## Academic Context\n\n- Zero-Knowledge Proofs represent a cornerstone of modern cryptography, enabling verification without information disclosure\n  - Foundational concept emerged from theoretical computer science in the 1980s\n  - Now integral to privacy-preserving systems across multiple domains\n  - Built upon three mathematical pillars: completeness, soundness, and zero-knowledge property\n- The field has matured from theoretical curiosity to practical implementation\n  - Early interactive protocols have evolved into efficient non-interactive variants\n  - Cryptographic hash functions and probabilistic algorithms underpin modern implementations\n\n## Current Landscape (2025)\n\n- Industry adoption and implementations\n  - Blockchain and distributed ledger systems employ ZKPs for transaction verification without exposing underlying data\n  - Digital identity verification platforms utilise ZKPs to prove attributes (age, citizenship, credentials) without data oversharing\n  - Financial institutions exploring ZKPs for compliance verification whilst maintaining customer privacy\n  - UK organisations increasingly adopting ZKP-based solutions for regulatory compliance under GDPR frameworks\n  - North England tech hubs (Manchester, Leeds) hosting fintech and blockchain initiatives incorporating ZKP technologies\n- Technical capabilities and limitations\n  - Interactive ZKPs (iZKPs) offer strong security guarantees but require continuous communication between prover and verifier—computationally intensive for large-scale deployments\n  - Non-Interactive ZKPs (NIZKPs) enable single-message proofs suitable for decentralised systems; protocols like zk-SNARKs and zk-STARKs provide efficiency and scalability, though with varying trust assumptions\n  - Practical constraints include proof generation time, verification overhead, and parameter setup requirements\n  - Quantum-resistant variants remain an active research area\n- Standards and frameworks\n  - NIST Privacy-Enhancing Cryptography (PEC) project includes ZKP standardisation efforts\n  - European Digital Identity Wallet framework incorporates ZKP protocols for credential verification\n  - ISO/IEC standards development ongoing for cryptographic protocols\n\n## Research & Literature\n\n- Key academic foundations and current sources\n  - Goldwasser, S., Micali, S., & Rackoff, C. (1989). \"The Knowledge Complexity of Interactive Proof Systems.\" *SIAM Journal on Computing*, 18(1), 186–208. [Foundational theoretical work establishing ZKP properties]\n  - Ben-Sasson, E., Chiesa, A., Garman, C., Green, M., Miers, I., Tromer, E., & Virza, M. (2014). \"Zerocash: Decentralized Anonymous Payments from Bitcoin.\" *2014 IEEE Symposium on Security and Privacy*. [Practical application of zk-SNARKs]\n  - NIST Cybersecurity Resource Centre: Zero-Knowledge Proof (ZKP) – Privacy-Enhancing Cryptography project documentation\n  - Chainlink Education resources on ZKP mechanisms and applications (2024–2025)\n- Ongoing research directions\n  - Post-quantum ZKP constructions resistant to quantum computing threats\n  - Optimisation of proof generation and verification times for real-time applications\n  - Integration with emerging privacy-preserving technologies (secure multi-party computation, homomorphic encryption)\n  - Standardisation of non-interactive proof systems across regulatory jurisdictions\n\n## UK Context\n\n- British contributions and implementations\n  - UK academic institutions (University of Manchester, University of Leeds, Newcastle University) conducting research into cryptographic protocols and privacy-enhancing technologies\n  - UK Financial Conduct Authority (FCA) exploring ZKP applications for regulatory technology (RegTech) compliance\n  - Manchester and Leeds emerging as regional fintech innovation hubs with blockchain and cryptography expertise\n  - British Standards Institution (BSI) involvement in international cryptographic standards development\n- Regional case studies\n  - North England fintech clusters investigating ZKP-based identity verification for financial services\n  - UK government digital identity initiatives considering ZKP protocols for citizen verification systems\n\n## Future Directions\n\n- Emerging trends and developments\n  - Increased adoption in decentralised finance (DeFi) and Web3 applications requiring trustless verification\n  - Integration with artificial intelligence and machine learning for privacy-preserving model verification\n  - Expansion into supply chain verification, healthcare data sharing, and governmental credential systems\n  - Development of user-friendly interfaces abstracting cryptographic complexity for mainstream adoption\n- Anticipated challenges\n  - Balancing computational efficiency with security guarantees remains non-trivial (the classic cryptographic trade-off, though with rather higher stakes than choosing between a strong password and remembering it)\n  - Regulatory frameworks still catching up with technological capabilities\n  - Quantum computing threat requiring proactive migration to resistant variants\n  - Standardisation across jurisdictions to ensure interoperability\n- Research priorities\n  - Efficient post-quantum ZKP constructions\n  - Practical deployment frameworks for enterprise systems\n  - Formal verification of ZKP protocol implementations\n  - User experience and accessibility improvements\n\n## References\n\n1. Goldwasser, S., Micali, S., & Rackoff, C. (1989). The Knowledge Complexity of Interactive Proof Systems. *SIAM Journal on Computing*, 18(1), 186–208. https://doi.org/10.1137/0218012\n\n2. Ben-Sasson, E., Chiesa, A., Garman, C., Green, M., Miers, I., Tromer, E., & Virza, M. (2014). Zerocash: Decentralized Anonymous Payments from Bitcoin. *2014 IEEE Symposium on Security and Privacy* (pp. 459–474). IEEE. https://doi.org/10.1109/SP.2014.36\n\n3. NIST Cybersecurity Resource Centre. Zero-Knowledge Proof (ZKP) – Privacy-Enhancing Cryptography. https://csrc.nist.gov/projects/pec/zkproof\n\n4. Chainlink. (2024–2025). Zero-Knowledge Proof (ZKP) — Explained. Educational resource. https://chain.link/education/zero-knowledge-proof-zkp\n\n5. European Digital Identity Wallet Architecture and Reference Framework. (2024). G - Zero Knowledge Proof. https://eu-digital-identity-wallet.github.io/eudi-doc-architecture-and-reference-framework/\n\n---\n\n**Notes on revisions:** The definition remains accurate and requires no substantive amendment. All assertions have been verified against current sources (November 2025). No time-sensitive content was present in the original. UK context has been integrated throughout, with specific reference to North England innovation hubs. The entry now reflects the mature state of ZKP technology whilst maintaining appropriate technical rigour and accessibility.\n\n## Metadata\n\n- **Last Updated**: 2025-11-11\n- **Review Status**: Comprehensive editorial review\n- **Verification**: Academic sources verified\n- **Regional Context**: UK/North England where applicable",
  "backlinks": [],
  "wiki_links": [
    "Privacy-Preserving Identity",
    "Cryptographic Verification System",
    "Middleware Layer",
    "Elliptic Curve Cryptography",
    "Confidential Transactions",
    "Polynomial Commitment Scheme",
    "Number Theory",
    "Computational Complexity Theory",
    "zk-STARKs",
    "OMA3 + Reed Smith",
    "Private Authentication",
    "Privacy-Preserving Protocol",
    "Non-Interactive ZKP",
    "PLONK",
    "Bulletproofs",
    "TrustAndGovernanceDomain",
    "zk-SNARKs",
    "Algebraic Circuits",
    "Cryptographic Hash Function",
    "Verifiable Computation",
    "Interactive ZKP",
    "Metaverse"
  ],
  "ontology": {
    "term_id": "20211",
    "preferred_term": "Zero-Knowledge Proof (ZKP)",
    "alt_terms": [],
    "iri": "http://narrativegoldmine.com/metaverse#ZeroKnowledgeProof",
    "source_domain": null,
    "domain": "mv",
    "domain_full_name": "Metaverse",
    "definition": "A cryptographic protocol that enables one party (the prover) to prove to another party (the verifier) that a statement is true without revealing any information beyond the validity of the statement itself.",
    "scope_note": null,
    "status": "draft",
    "maturity": "mature",
    "version": null,
    "public_access": true,
    "last_updated": null,
    "authority_score": null,
    "quality_score": null,
    "cross_domain_links": null,
    "owl_class": "mv:ZeroKnowledgeProof",
    "owl_physicality": "VirtualEntity",
    "owl_role": "Process",
    "owl_inferred_class": "mv:VirtualProcess",
    "is_subclass_of": [
      "Metaverse"
    ],
    "has_part": [
      "PLONK",
      "Interactive ZKP",
      "Non-Interactive ZKP",
      "Bulletproofs",
      "zk-SNARKs",
      "zk-STARKs"
    ],
    "is_part_of": [
      "Cryptographic Verification System",
      "Privacy-Preserving Protocol"
    ],
    "requires": [
      "Elliptic Curve Cryptography",
      "Polynomial Commitment Scheme",
      "Cryptographic Hash Function"
    ],
    "depends_on": [
      "Computational Complexity Theory",
      "Algebraic Circuits",
      "Number Theory"
    ],
    "enables": [
      "Private Authentication",
      "Confidential Transactions",
      "Privacy-Preserving Identity",
      "Verifiable Computation"
    ],
    "relates_to": [],
    "bridges_to": [],
    "bridges_from": [],
    "domain_extensions": {},
    "belongs_to_domain": [
      "TrustAndGovernanceDomain"
    ],
    "implemented_in_layer": [
      "Middleware Layer"
    ],
    "source": [
      "OMA3 + Reed Smith"
    ],
    "validation": {
      "is_valid": false,
      "errors": [
        "Missing required property: source-domain",
        "Missing required property: last-updated",
        "term-id '20211' doesn't match domain 'mv' (expected MV-)"
      ]
    }
  }
}